{
  "type": "Feature",
  "properties": {
    "iso:country":"US",
    "sg:address":"1200 E High St",
    "sg:city":"Pottstown",
    "sg:classifiers":[
        {
            "category":"Banks & Credit Unions",
            "subcategory":"Bank",
            "type":"Services"
        }
    ],
    "sg:phone":"+1 610 323 4495",
    "sg:postcode":"19464",
    "sg:province":"PA",
    "sg:tags":[
        "loan",
        "real estate"
    ],
    "wof:name":"Aegis Mortgage Corp",
    "wof:placetype":"venue"
},
  "geometry": {"coordinates":[-75.62329099999999,40.243688],"type":"Point"}
}