{
  "type": "Feature",
  "properties": {
    "addr:full":"1880 John F Kennedy Blvd Philadelphia PA 19103",
    "addr:housenumber":"1880",
    "addr:postcode":"19103",
    "addr:street":"John F Kennedy Blvd",
    "iso:country":"US",
    "sg:address":"1880 John F Kennedy Blvd",
    "sg:city":"Philadelphia",
    "sg:classifiers":[
        {
            "category":"Professional",
            "subcategory":"Accounting & Tax Preparation",
            "type":"Services"
        }
    ],
    "sg:phone":"+1 215 665 8560",
    "sg:postcode":"19103",
    "sg:province":"PA",
    "sg:tags":[
        "return",
        "filing"
    ],
    "wof:name":"John S Frost PC",
    "wof:placetype":"venue"
},
  "geometry": {"coordinates":[-75.17039,39.954155],"type":"Point"}
}