{
  "type": "Feature",
  "properties": {
    "addr:full":"141 Stimely Rd Lewistown PA 17044",
    "addr:housenumber":"141",
    "addr:postcode":"17044",
    "addr:street":"Stimely Rd",
    "iso:country":"US",
    "sg:address":"141 Stimely Rd",
    "sg:city":"Lewistown",
    "sg:classifiers":[
        {
            "category":"Utilities",
            "subcategory":"Refuse",
            "type":"Services"
        }
    ],
    "sg:phone":"+1 717 242 8777",
    "sg:postcode":"17044",
    "sg:province":"PA",
    "sg:tags":[
        "garbage",
        "collection"
    ],
    "wof:name":"S & S Trash Svc",
    "wof:placetype":"venue"
},
  "geometry": {"coordinates":[-77.52410399999999,40.630777],"type":"Point"}
}