{
  "type": "Feature",
  "properties": {
    "iso:country":"US",
    "sg:address":"214 Harrison Ave",
    "sg:city":"Somerset",
    "sg:classifiers":[
        {
            "category":"Organizations",
            "subcategory":"Non-profit Organization",
            "type":"Services"
        }
    ],
    "sg:phone":"+1 814 443 2433",
    "sg:postcode":"15501",
    "sg:province":"PA",
    "sg:website":"www.laurelarts.org",
    "wof:name":"Laurel Arts",
    "wof:placetype":"venue"
},
  "geometry": {"coordinates":[-79.092178,40.006778],"type":"Point"}
}