{
  "type": "Feature",
  "properties": {
    "iso:country":"US",
    "sg:address":"504 E Main St",
    "sg:city":"Everett",
    "sg:classifiers":[
        {
            "category":"Restaurant",
            "type":"Food & Drink"
        }
    ],
    "sg:phone":"+1 814 652 2314",
    "sg:postcode":"15537",
    "sg:province":"PA",
    "wof:name":"Kelly's Scenic View",
    "wof:placetype":"venue"
},
  "geometry": {"coordinates":[-78.362611,40.011655],"type":"Point"}
}