{
  "type": "Feature",
  "properties": {
    "addr:full":"162 S Pool Forge Rd Narvon PA 17555",
    "addr:housenumber":"162",
    "addr:postcode":"17555",
    "addr:street":"S Pool Forge Rd",
    "iso:country":"US",
    "sg:address":"162 S Pool Forge Rd",
    "sg:city":"Narvon",
    "sg:classifiers":[
        {
            "category":"Freight",
            "type":"Transportation"
        }
    ],
    "sg:phone":"+1   ",
    "sg:postcode":"17555",
    "sg:province":"PA",
    "sg:tags":[
        "operator",
        "trucking"
    ],
    "wof:name":"James J Ferrell Jr",
    "wof:placetype":"venue"
},
  "geometry": {"coordinates":[-75.976517,40.127024],"type":"Point"}
}