{
  "type": "Feature",
  "properties": {
    "iso:country":"US",
    "sg:address":"81 Meadow Hill Dr",
    "sg:city":"York",
    "sg:classifiers":[
        {
            "category":"Professional",
            "type":"Services"
        }
    ],
    "sg:phone":"+1 717 757 2232",
    "sg:postcode":"17402",
    "sg:province":"PA",
    "sg:tags":[
        "establishment"
    ],
    "wof:name":"Pall Corp",
    "wof:placetype":"venue"
},
  "geometry": {"coordinates":[-76.655143,39.957252],"type":"Point"}
}