{
  "type": "Feature",
  "properties": {
    "addr:full":"623 N 3rd St Bellwood PA 16617",
    "addr:housenumber":"623",
    "addr:postcode":"16617",
    "addr:street":"N 3Rd St",
    "iso:country":"US",
    "sg:address":"623 N 3rd St",
    "sg:city":"Bellwood",
    "sg:classifiers":[
        {
            "category":"Banks & Credit Unions",
            "subcategory":"Investment Brokerage",
            "type":"Services"
        }
    ],
    "sg:phone":"+1   ",
    "sg:postcode":"16617",
    "sg:province":"PA",
    "sg:tags":[
        "security"
    ],
    "wof:name":"Up Your Assets Investment",
    "wof:placetype":"venue"
},
  "geometry": {"coordinates":[-78.33475799999999,40.604097],"type":"Point"}
}