{
  "type": "Feature",
  "properties": {
    "addr:full":"3809 Birney Ave Moosic PA 18507",
    "addr:housenumber":"3809",
    "addr:postcode":"18507",
    "addr:street":"Birney Ave",
    "iso:country":"US",
    "sg:address":"3809 Birney Ave",
    "sg:city":"Moosic",
    "sg:classifiers":[
        {
            "category":"Building & Trades",
            "subcategory":"Construction",
            "type":"Services"
        }
    ],
    "sg:phone":"+1 570 341 6830",
    "sg:postcode":"18507",
    "sg:province":"PA",
    "sg:tags":[
        "home",
        "builder"
    ],
    "wof:name":"In Home Personal Care Svc Inc",
    "wof:placetype":"venue"
},
  "geometry": {"coordinates":[-75.70890900000001,41.370859],"type":"Point"}
}