{
  "type": "Feature",
  "properties": {
    "addr:full":"17 Cricket Ave Ardmore PA 19003",
    "addr:housenumber":"17",
    "addr:postcode":"19003",
    "addr:street":"Cricket Ave",
    "iso:country":"US",
    "sg:address":"17 Cricket Ave",
    "sg:city":"Ardmore",
    "sg:classifiers":[
        {
            "category":"Restaurant",
            "type":"Food & Drink"
        }
    ],
    "sg:phone":"+1 610 642 9280",
    "sg:postcode":"19003",
    "sg:province":"PA",
    "wof:name":"Mc Closkey's Bar",
    "wof:placetype":"venue"
},
  "geometry": {"coordinates":[-75.29107999999999,40.007626],"type":"Point"}
}