{
  "type": "Feature",
  "properties": {
    "iso:country":"US",
    "sg:address":"2 E Main St",
    "sg:city":"Everett",
    "sg:classifiers":[
        {
            "category":"Personal",
            "subcategory":"Beauty Salon",
            "type":"Services"
        }
    ],
    "sg:phone":"+1 814 652 2922",
    "sg:postcode":"15537",
    "sg:province":"PA",
    "wof:name":"Sagittarius Hair Design",
    "wof:placetype":"venue"
},
  "geometry": {"coordinates":[-78.37254,40.011509],"type":"Point"}
}