{
  "type": "Feature",
  "properties": {
    "iso:country":"US",
    "sg:address":"129 Marlin Dr W",
    "sg:city":"Pittsburgh",
    "sg:classifiers":[
        {
            "category":"Wholesale",
            "subcategory":"Durable Goods & Equipment",
            "type":"Manufacturing & Wholesale Goods"
        },
        {
            "category":"Wholesale",
            "subcategory":"Electrical",
            "type":"Manufacturing & Wholesale Goods"
        }
    ],
    "sg:phone":"+1 412 531 0227",
    "sg:postcode":"15216",
    "sg:province":"PA",
    "sg:tags":[
        "manufacturer",
        "wiring",
        "representative",
        "apparatus",
        "supply"
    ],
    "wof:name":"Paul Zvonar Associates Inc",
    "wof:placetype":"venue"
},
  "geometry": {"coordinates":[-80.052868,40.388571],"type":"Point"}
}