{
  "type": "Feature",
  "properties": {
    "iso:country":"US",
    "sg:address":"3723 Easton Nazareth Hwy",
    "sg:city":"Easton",
    "sg:classifiers":[
        {
            "category":"Retail",
            "subcategory":"Event Space",
            "type":"Services"
        }
    ],
    "sg:phone":"+1 610 250 5090",
    "sg:postcode":"18045",
    "sg:province":"PA",
    "sg:tags":[
        "facility",
        "hall",
        "reception",
        "banquet"
    ],
    "wof:name":"Lotus Conference Center",
    "wof:placetype":"venue"
},
  "geometry": {"coordinates":[-75.28211899999999,40.71193],"type":"Point"}
}