{
  "type": "Feature",
  "properties": {
    "addr:full":"965 Baltimore Pike Springfield PA 19064",
    "addr:housenumber":"965",
    "addr:postcode":"19064",
    "addr:street":"Baltimore Pike Springfield",
    "iso:country":"US",
    "sg:address":"965 Baltimore Pike",
    "sg:city":"Springfield",
    "sg:classifiers":[
        {
            "category":"Shopping",
            "subcategory":"Clothing, Apparel, & Fashions",
            "type":"Retail Goods"
        }
    ],
    "sg:phone":"+1   ",
    "sg:postcode":"19064",
    "sg:province":"PA",
    "sg:tags":[
        "shop",
        "bridal",
        "dress"
    ],
    "wof:name":"Davids Bridal",
    "wof:placetype":"venue"
},
  "geometry": {"coordinates":[-75.341847,39.914433],"type":"Point"}
}