{
  "type": "Feature",
  "properties": {
    "addr:full":"1028 Morgan Hwy Clarks Summit PA 18411",
    "addr:housenumber":"1028",
    "addr:postcode":"18411",
    "addr:street":"Morgan Hwy",
    "iso:country":"US",
    "sg:address":"1028 Morgan Hwy",
    "sg:city":"Clarks Summit",
    "sg:classifiers":[
        {
            "category":"Insurance",
            "subcategory":"Insurance Agent",
            "type":"Services"
        }
    ],
    "sg:phone":"+1 570 587 5161",
    "sg:postcode":"18411",
    "sg:province":"PA",
    "wof:name":"Met Life",
    "wof:placetype":"venue"
},
  "geometry": {"coordinates":[-75.716939,41.485079],"type":"Point"}
}