{
  "type": "Feature",
  "properties": {
    "iso:country":"US",
    "sg:address":"202 Hillside Ave",
    "sg:city":"Norristown",
    "sg:classifiers":[
        {
            "category":"Building & Trades",
            "subcategory":"Construction",
            "type":"Services"
        }
    ],
    "sg:phone":"+1 610 539 6191",
    "sg:postcode":"19403",
    "sg:province":"PA",
    "sg:tags":[
        "roofing",
        "industrial",
        "contractors-commercial",
        "contractor"
    ],
    "wof:name":"Frank Degrazio",
    "wof:placetype":"venue"
},
  "geometry": {"coordinates":[-75.40007900000001,40.150496],"type":"Point"}
}