{
  "type": "Feature",
  "properties": {
    "iso:country":"US",
    "sg:address":"4 Ppg Pl",
    "sg:city":"Pittsburgh",
    "sg:classifiers":[
        {
            "category":"Sports & Exercise",
            "subcategory":"Ice Rink",
            "type":"Entertainment"
        }
    ],
    "sg:phone":"+1 412 394 3641",
    "sg:postcode":"15222",
    "sg:province":"PA",
    "sg:tags":[
        "skating"
    ],
    "sg:website":"www.ppgplace.com",
    "wof:name":"Ppg Place-the Rink",
    "wof:placetype":"venue"
},
  "geometry": {"coordinates":[-80.00467999999999,40.44244],"type":"Point"}
}