{
  "type": "Feature",
  "properties": {
    "iso:country":"US",
    "sg:address":"2619 Riverside Dr",
    "sg:city":"Williamsport",
    "sg:classifiers":[
        {
            "category":"Building & Trades",
            "subcategory":"Construction",
            "type":"Services"
        }
    ],
    "sg:phone":"+1   ",
    "sg:postcode":"17702",
    "sg:province":"PA",
    "sg:tags":[
        "house"
    ],
    "wof:name":"Cascheras Home Improvement",
    "wof:placetype":"venue"
},
  "geometry": {"coordinates":[-77.033131,41.226971],"type":"Point"}
}