{
  "type": "Feature",
  "properties": {
    "iso:country":"US",
    "sg:address":"265 Hahnstown Rd",
    "sg:city":"Ephrata",
    "sg:classifiers":[
        {
            "category":"Freight",
            "type":"Transportation"
        },
        {
            "category":"Home & Garden",
            "subcategory":"Garden Supply",
            "type":"Retail Goods"
        }
    ],
    "sg:phone":"+1 717 738 1312",
    "sg:postcode":"17522",
    "sg:province":"PA",
    "sg:tags":[
        "mulch",
        "local",
        "company",
        "trucking"
    ],
    "wof:name":"Quality Mulch Products LLC",
    "wof:placetype":"venue"
},
  "geometry": {"coordinates":[-76.123746,40.171282],"type":"Point"}
}