{
  "type": "Feature",
  "properties": {
    "addr:full":"3190 Glenwood Park Ave Erie PA 16508",
    "addr:housenumber":"3190",
    "addr:postcode":"16508",
    "addr:street":"Glenwood Park Ave",
    "iso:country":"US",
    "sg:address":"3190 Glenwood Park Ave",
    "sg:city":"Erie",
    "sg:classifiers":[
        {
            "category":"Health Services",
            "subcategory":"Doctor",
            "type":"Services"
        }
    ],
    "sg:phone":"+1 814 459 2726",
    "sg:postcode":"16508",
    "sg:province":"PA",
    "sg:tags":[
        "physician",
        "surgeon",
        "medical"
    ],
    "wof:name":"Dieteman David F MD Inc",
    "wof:placetype":"venue"
},
  "geometry": {"coordinates":[-80.07569100000001,42.103428],"type":"Point"}
}