{
  "type": "Feature",
  "properties": {
    "addr:full":"1801 S 15th St Philadelphia PA 19145",
    "addr:housenumber":"1801",
    "addr:postcode":"19145",
    "addr:street":"S 15Th St",
    "iso:country":"US",
    "sg:address":"1801 S 15th St",
    "sg:city":"Philadelphia",
    "sg:classifiers":[
        {
            "category":"Social Services",
            "type":"Services"
        }
    ],
    "sg:phone":"+1 215 338 6709",
    "sg:postcode":"19145",
    "sg:province":"PA",
    "sg:tags":[
        "self",
        "group",
        "help"
    ],
    "wof:name":"Gamblers Anonymous",
    "wof:placetype":"venue"
},
  "geometry": {"coordinates":[-75.170846,39.927034],"type":"Point"}
}