{
  "type": "Feature",
  "properties": {
    "iso:country":"US",
    "sg:address":"9120 Carlisle Pike",
    "sg:city":"York Springs",
    "sg:phone":"+1   ",
    "sg:postcode":"17372",
    "sg:province":"PA",
    "sg:tags":[
        "farm",
        "corn",
        "soybean"
    ],
    "wof:name":"Herman Leer",
    "wof:placetype":"venue"
},
  "geometry": {"coordinates":[-77.123334,40.017408],"type":"Point"}
}