{
  "type": "Feature",
  "properties": {
    "iso:country":"US",
    "sg:address":"155 Wilson Ave",
    "sg:city":"Washington",
    "sg:classifiers":[
        {
            "category":"Health Services",
            "subcategory":"Doctor",
            "type":"Services"
        }
    ],
    "sg:phone":"+1   ",
    "sg:postcode":"15301",
    "sg:province":"PA",
    "sg:tags":[
        "medical"
    ],
    "wof:name":"Platto Michael J MD",
    "wof:placetype":"venue"
},
  "geometry": {"coordinates":[-80.24847200000001,40.182127],"type":"Point"}
}