{
  "type": "Feature",
  "properties": {
    "iso:country":"US",
    "sg:address":"531 Decatur Ave",
    "sg:city":"Pittsburgh",
    "sg:classifiers":[
        {
            "category":"Recreation",
            "type":"Entertainment"
        }
    ],
    "sg:phone":"+1 412 401 7853",
    "sg:postcode":"15221",
    "sg:province":"PA",
    "sg:tags":[
        "aquarium"
    ],
    "wof:name":"Fishy Things",
    "wof:placetype":"venue"
},
  "geometry": {"coordinates":[-79.845016,40.420747],"type":"Point"}
}