{
  "type": "Feature",
  "properties": {
    "iso:country":"US",
    "sg:address":"1291 Southampton Rd",
    "sg:city":"Philadelphia",
    "sg:classifiers":[
        {
            "category":"Retail",
            "subcategory":"Auto Repair",
            "type":"Services"
        }
    ],
    "sg:phone":"+1   ",
    "sg:postcode":"19116",
    "sg:province":"PA",
    "sg:tags":[
        "automotive"
    ],
    "wof:name":"Docs Towing",
    "wof:placetype":"venue"
},
  "geometry": {"coordinates":[-74.99714299999999,40.121346],"type":"Point"}
}