{
  "type": "Feature",
  "properties": {
    "iso:country":"US",
    "sg:address":"3429 Dawson St",
    "sg:city":"Pittsburgh",
    "sg:classifiers":[
        {
            "category":"Real Estate",
            "subcategory":"Real Estate Agent",
            "type":"Services"
        }
    ],
    "sg:phone":"+1 412 688 9062",
    "sg:postcode":"15213",
    "sg:province":"PA",
    "wof:name":"Prudential Realty Co",
    "wof:placetype":"venue"
},
  "geometry": {"coordinates":[-79.952868,40.436088],"type":"Point"}
}