{
  "type": "Feature",
  "properties": {
    "addr:full":"19136 Grange Center Rd Saegertown PA 16433",
    "addr:housenumber":"19136",
    "addr:postcode":"16433",
    "addr:street":"Grange Center Rd",
    "iso:country":"US",
    "sg:address":"19136 Grange Center Rd",
    "sg:city":"Saegertown",
    "sg:classifiers":[
        {
            "category":"Building & Trades",
            "subcategory":"Construction",
            "type":"Services"
        }
    ],
    "sg:phone":"+1   ",
    "sg:postcode":"16433",
    "sg:province":"PA",
    "sg:tags":[
        "carpentry"
    ],
    "wof:name":"Seth Baker Construction",
    "wof:placetype":"venue"
},
  "geometry": {"coordinates":[-80.171149,41.748584],"type":"Point"}
}