{
  "type": "Feature",
  "properties": {
    "iso:country":"US",
    "sg:address":"712 Cooper Ave",
    "sg:city":"Johnstown",
    "sg:classifiers":[
        {
            "category":"Government",
            "subcategory":"Office",
            "type":"Public Place"
        }
    ],
    "sg:phone":"+1 814 539 5230",
    "sg:postcode":"15906",
    "sg:province":"PA",
    "sg:tags":[
        "village"
    ],
    "wof:name":"West Taylor Twp Municipal Bldg",
    "wof:placetype":"venue"
},
  "geometry": {"coordinates":[-78.93452499999999,40.367749],"type":"Point"}
}