{
  "type": "Feature",
  "properties": {
    "iso:country":"US",
    "sg:address":"1117 Walnut St",
    "sg:city":"Philadelphia",
    "sg:classifiers":[
        {
            "category":"Shopping",
            "subcategory":"Clothing, Apparel, & Fashions",
            "type":"Retail Goods"
        }
    ],
    "sg:phone":"+1 215 592 7870",
    "sg:postcode":"19107",
    "sg:province":"PA",
    "sg:tags":[
        "shop",
        "bridal"
    ],
    "sg:website":"www.phillybride.com",
    "wof:name":"Bridals By Danielle",
    "wof:placetype":"venue"
},
  "geometry": {"coordinates":[-75.159538,39.948823],"type":"Point"}
}