{
  "type": "Feature",
  "properties": {
    "iso:country":"US",
    "sg:address":"429 S Canal St",
    "sg:city":"Walnutport",
    "sg:classifiers":[
        {
            "category":"Building & Trades",
            "subcategory":"Construction",
            "type":"Services"
        }
    ],
    "sg:phone":"+1 610 760 9906",
    "sg:postcode":"18088",
    "sg:province":"PA",
    "sg:tags":[
        "housing"
    ],
    "wof:name":"Construction With Concern",
    "wof:placetype":"venue"
},
  "geometry": {"coordinates":[-75.59899799999999,40.750305],"type":"Point"}
}