{
  "type": "Feature",
  "properties": {
    "iso:country":"US",
    "sg:address":"5006 E Trindle Rd",
    "sg:city":"Mechanicsburg",
    "sg:classifiers":[
        {
            "category":"Professional",
            "subcategory":"Accounting & Tax Preparation",
            "type":"Services"
        }
    ],
    "sg:phone":"+1 717 761 1222",
    "sg:postcode":"17050",
    "sg:province":"PA",
    "sg:tags":[
        "public",
        "accountants-certified"
    ],
    "wof:name":"Abram C Bert Cpa",
    "wof:placetype":"venue"
},
  "geometry": {"coordinates":[-76.970189,40.225846],"type":"Point"}
}