{
  "type": "Feature",
  "properties": {
    "iso:country":"US",
    "sg:address":"307 Foster Hill Rd",
    "sg:city":"Milford",
    "sg:classifiers":[
        {
            "category":"Professional",
            "subcategory":"Business Services",
            "type":"Services"
        }
    ],
    "sg:phone":"+1   ",
    "sg:postcode":"18337",
    "sg:province":"PA",
    "sg:tags":[
        "design",
        "clothing",
        "mfg"
    ],
    "wof:name":"Gordon De Vries Studio",
    "wof:placetype":"venue"
},
  "geometry": {"coordinates":[-74.80972800000001,41.350698],"type":"Point"}
}