{
  "type": "Feature",
  "properties": {
    "iso:country":"US",
    "sg:address":"1442 N Sunset Beach Rd",
    "sg:city":"Taylorstown",
    "sg:classifiers":[
        {
            "category":"Mining & Drilling",
            "type":"Manufacturing & Wholesale Goods"
        }
    ],
    "sg:phone":"+1 724 948 3388",
    "sg:postcode":"15323",
    "sg:province":"PA",
    "sg:tags":[
        "oil",
        "gas",
        "producer"
    ],
    "wof:name":"Pennzoil Exploration & Prdctn",
    "wof:placetype":"venue"
},
  "geometry": {"coordinates":[-80.372933,40.14726],"type":"Point"}
}