{
  "type": "Feature",
  "properties": {
    "iso:country":"US",
    "sg:address":"26 E Union St",
    "sg:city":"Kingston",
    "sg:classifiers":[
        {
            "category":"Shopping",
            "subcategory":"Musical Instruments",
            "type":"Retail Goods"
        }
    ],
    "sg:phone":"+1 570 287 1503",
    "sg:postcode":"18704",
    "sg:province":"PA",
    "wof:name":"String Shop",
    "wof:placetype":"venue"
},
  "geometry": {"coordinates":[-75.88490400000001,41.270604],"type":"Point"}
}