{
  "type": "Feature",
  "properties": {
    "iso:country":"US",
    "sg:address":"18 S George St",
    "sg:city":"York",
    "sg:classifiers":[
        {
            "category":"Professional",
            "subcategory":"Engineering",
            "type":"Services"
        }
    ],
    "sg:phone":"+1 717 848 2590",
    "sg:postcode":"17401",
    "sg:province":"PA",
    "sg:tags":[
        "engineer"
    ],
    "wof:name":"H Wilden & Assoc Inc",
    "wof:placetype":"venue"
},
  "geometry": {"coordinates":[-76.727716,39.962466],"type":"Point"}
}