{
  "type": "Feature",
  "properties": {
    "addr:full":"1716 Poplar Ave Braddock PA 15104",
    "addr:housenumber":"1716",
    "addr:postcode":"15104",
    "addr:street":"Poplar Ave",
    "iso:country":"US",
    "sg:address":"1716 Poplar Ave",
    "sg:city":"Braddock",
    "sg:classifiers":[
        {
            "category":"Retail",
            "subcategory":"Auto Repair",
            "type":"Services"
        }
    ],
    "sg:phone":"+1   ",
    "sg:postcode":"15104",
    "sg:province":"PA",
    "sg:tags":[
        "general"
    ],
    "wof:name":"Larrys Auto Service",
    "wof:placetype":"venue"
},
  "geometry": {"coordinates":[-79.839961,40.402129],"type":"Point"}
}