{
  "type": "Feature",
  "properties": {
    "iso:country":"US",
    "sg:address":"703 Stevenson Blvd",
    "sg:city":"New Kensington",
    "sg:classifiers":[
        {
            "category":"Education",
            "subcategory":"School",
            "type":"Public Place"
        }
    ],
    "sg:phone":"+1 724 337 4536",
    "sg:postcode":"15068",
    "sg:province":"PA",
    "wof:name":"Valley High School",
    "wof:placetype":"venue"
},
  "geometry": {"coordinates":[-79.75450499999999,40.56513],"type":"Point"}
}