{
  "type": "Feature",
  "properties": {
    "iso:country":"US",
    "sg:address":"57 W Lancaster Ave",
    "sg:city":"Paoli",
    "sg:classifiers":[
        {
            "category":"Shopping",
            "subcategory":"Used Merchandise",
            "type":"Retail Goods"
        }
    ],
    "sg:phone":"+1 610 722 5900",
    "sg:postcode":"19301",
    "sg:province":"PA",
    "sg:tags":[
        "antique"
    ],
    "wof:name":"Oliver Fleury",
    "wof:placetype":"venue"
},
  "geometry": {"coordinates":[-75.48451799999999,40.041991],"type":"Point"}
}