{
  "type": "Feature",
  "properties": {
    "iso:country":"US",
    "sg:address":"5244 Rising Sun Ave",
    "sg:city":"Philadelphia",
    "sg:classifiers":[
        {
            "category":"Travel",
            "subcategory":"Travel Agent",
            "type":"Entertainment"
        }
    ],
    "sg:phone":"+1 215 329 5521",
    "sg:postcode":"19120",
    "sg:province":"PA",
    "sg:tags":[
        "agency"
    ],
    "wof:name":"One Stop Travel",
    "wof:placetype":"venue"
},
  "geometry": {"coordinates":[-75.118977,40.02963],"type":"Point"}
}