{
  "type": "Feature",
  "properties": {
    "iso:country":"US",
    "sg:address":"18 Palmer Dr",
    "sg:city":"Camp Hill",
    "sg:classifiers":[
        {
            "category":"Building & Trades",
            "subcategory":"Construction",
            "type":"Services"
        }
    ],
    "sg:phone":"+1 717 975 9872",
    "sg:postcode":"17011",
    "sg:province":"PA",
    "sg:tags":[
        "street",
        "paving",
        "highway",
        "contractor"
    ],
    "wof:name":"Mark's Paving",
    "wof:placetype":"venue"
},
  "geometry": {"coordinates":[-76.948644,40.208648],"type":"Point"}
}