{
  "type": "Feature",
  "properties": {
    "iso:country":"US",
    "sg:address":"355 Manor Dr",
    "sg:city":"Nazareth",
    "sg:classifiers":[
        {
            "category":"Shopping",
            "type":"Retail Goods"
        },
        {
            "category":"Manufacturing",
            "subcategory":"Paper Products",
            "type":"Manufacturing & Wholesale Goods"
        }
    ],
    "sg:phone":"+1 610 759 3237",
    "sg:postcode":"18064",
    "sg:province":"PA",
    "sg:tags":[
        "packaging",
        "materials-wholesale",
        "material",
        "manufacturer"
    ],
    "wof:name":"Blue Mountain Packaging",
    "wof:placetype":"venue"
},
  "geometry": {"coordinates":[-75.342348,40.699703],"type":"Point"}
}