{
  "type": "Feature",
  "properties": {
    "iso:country":"US",
    "sg:address":"2411 Bellwood Dr",
    "sg:city":"Pittsburgh",
    "sg:classifiers":[
        {
            "category":"Professional",
            "subcategory":"Management & Consulting",
            "type":"Services"
        }
    ],
    "sg:phone":"+1 412 366 9994",
    "sg:postcode":"15237",
    "sg:province":"PA",
    "sg:tags":[
        "consultant",
        "educational"
    ],
    "wof:name":"Educational Achievement Ctr",
    "wof:placetype":"venue"
},
  "geometry": {"coordinates":[-80.080448,40.585099],"type":"Point"}
}