{
  "type": "Feature",
  "properties": {
    "iso:country":"US",
    "sg:address":"10 Old William Penn Hwy",
    "sg:city":"Blairsville",
    "sg:classifiers":[
        {
            "category":"Personal",
            "subcategory":"Beauty Salon",
            "type":"Services"
        }
    ],
    "sg:phone":"+1 724 459 3483",
    "sg:postcode":"15717",
    "sg:province":"PA",
    "wof:name":"Tammy Rose Beauty Salon & Tan",
    "wof:placetype":"venue"
},
  "geometry": {"coordinates":[-79.24752100000001,40.434168],"type":"Point"}
}