{
  "type": "Feature",
  "properties": {
    "iso:country":"US",
    "sg:address":"790 Edison Furlong Rd",
    "sg:city":"Furlong",
    "sg:classifiers":[
        {
            "category":"Ice Cream",
            "type":"Food & Drink"
        }
    ],
    "sg:menulink":"http://www.allmenus.com/pa/doylestown/234834-ritas-ice-custard-happiness/menu/",
    "sg:phone":"+1 215 794 8388",
    "sg:postcode":"18925",
    "sg:province":"PA",
    "sg:tags":[
        "american"
    ],
    "wof:name":"Rita's Ice Custard Happiness",
    "wof:placetype":"venue"
},
  "geometry": {"coordinates":[-75.084638,40.295439],"type":"Point"}
}