{
  "type": "Feature",
  "properties": {
    "iso:country":"US",
    "sg:address":"439 7th Ave",
    "sg:city":"Pittsburgh",
    "sg:classifiers":[
        {
            "category":"Restaurant",
            "type":"Food & Drink"
        }
    ],
    "sg:phone":"+1 412 471 0511",
    "sg:postcode":"15219",
    "sg:province":"PA",
    "wof:name":"Tower Diner",
    "wof:placetype":"venue"
},
  "geometry": {"coordinates":[-79.995001,40.442263],"type":"Point"}
}