{
  "type": "Feature",
  "properties": {
    "iso:country":"US",
    "sg:address":"1158 York Rd",
    "sg:city":"Warminster",
    "sg:classifiers":[
        {
            "category":"Professional",
            "subcategory":"Lawyer & Legal Services",
            "type":"Services"
        }
    ],
    "sg:phone":"+1 215 672 1951",
    "sg:postcode":"18974",
    "sg:province":"PA",
    "wof:name":"Joseph V Cardona",
    "wof:placetype":"venue"
},
  "geometry": {"coordinates":[-75.097078,40.223578],"type":"Point"}
}