{
  "type": "Feature",
  "properties": {
    "addr:full":"3351 Industrial Blvd Bethel Park PA 15102",
    "addr:housenumber":"3351",
    "addr:postcode":"15102",
    "addr:street":"Industrial Blvd",
    "iso:country":"US",
    "sg:address":"3351 Industrial Blvd",
    "sg:city":"Bethel Park",
    "sg:classifiers":[
        {
            "category":"Retail",
            "subcategory":"Repair Shop",
            "type":"Services"
        }
    ],
    "sg:phone":"+1 412 831 3180",
    "sg:postcode":"15102",
    "sg:province":"PA",
    "sg:tags":[
        "welding"
    ],
    "wof:name":"South Park Welding",
    "wof:placetype":"venue"
},
  "geometry": {"coordinates":[-80.04535799999999,40.324227],"type":"Point"}
}