{
  "type": "Feature",
  "properties": {
    "addr:full":"4609 Liberty Ave Pittsburgh PA 15224",
    "addr:housenumber":"4609",
    "addr:postcode":"15224",
    "addr:street":"Liberty Ave",
    "iso:country":"US",
    "sg:address":"4609 Liberty Ave",
    "sg:city":"Pittsburgh",
    "sg:classifiers":[
        {
            "category":"Personal",
            "subcategory":"Beauty Salon",
            "type":"Services"
        }
    ],
    "sg:phone":"+1   ",
    "sg:postcode":"15224",
    "sg:province":"PA",
    "sg:tags":[
        "shop"
    ],
    "wof:name":"Holiday Hair",
    "wof:placetype":"venue"
},
  "geometry": {"coordinates":[-79.950536,40.46255],"type":"Point"}
}