{
  "type": "Feature",
  "properties": {
    "addr:full":"25 E Ridge St Lansford PA 18232",
    "addr:housenumber":"25",
    "addr:postcode":"18232",
    "addr:street":"E Ridge St",
    "iso:country":"US",
    "sg:address":"25 E Ridge St",
    "sg:city":"Lansford",
    "sg:classifiers":[
        {
            "category":"Insurance",
            "subcategory":"Insurance Agent",
            "type":"Services"
        }
    ],
    "sg:phone":"+1 570 645 3127",
    "sg:postcode":"18232",
    "sg:province":"PA",
    "sg:tags":[
        "agency"
    ],
    "wof:name":"Lewis Insurance Inc",
    "wof:placetype":"venue"
},
  "geometry": {"coordinates":[-75.88317600000001,40.832475],"type":"Point"}
}