{
  "type": "Feature",
  "properties": {
    "addr:full":"201 S 2nd St Wrightsville PA 17368",
    "addr:housenumber":"201",
    "addr:postcode":"17368",
    "addr:street":"S 2Nd St",
    "iso:country":"US",
    "sg:address":"201 S 2nd St",
    "sg:city":"Wrightsville",
    "sg:classifiers":[
        {
            "category":"Organizations",
            "subcategory":"Religious Organization",
            "type":"Services"
        }
    ],
    "sg:phone":"+1 717 252 9700",
    "sg:postcode":"17368",
    "sg:province":"PA",
    "sg:tags":[
        "church"
    ],
    "wof:name":"Heritage International",
    "wof:placetype":"venue"
},
  "geometry": {"coordinates":[-76.529309,40.024797],"type":"Point"}
}