{
  "type": "Feature",
  "properties": {
    "iso:country":"US",
    "sg:address":"3600 S Darien St",
    "sg:city":"Philadelphia",
    "sg:classifiers":[
        {
            "category":"Building & Trades",
            "subcategory":"Construction",
            "type":"Services"
        }
    ],
    "sg:phone":"+1 215 218 1000",
    "sg:postcode":"19148",
    "sg:province":"PA",
    "sg:tags":[
        "contractor"
    ],
    "wof:name":"Turner Construction Co",
    "wof:placetype":"venue"
},
  "geometry": {"coordinates":[-75.158997,39.920898],"type":"Point"}
}