{
  "type": "Feature",
  "properties": {
    "addr:full":"320 E North Ave Pittsburgh PA 15212",
    "addr:housenumber":"320",
    "addr:postcode":"15212",
    "addr:street":"E North Ave",
    "iso:country":"US",
    "sg:address":"320 E North Ave",
    "sg:city":"Pittsburgh",
    "sg:classifiers":[
        {
            "category":"Health Services",
            "subcategory":"Doctor",
            "type":"Services"
        }
    ],
    "sg:phone":"+1 412 359 3038",
    "sg:postcode":"15212",
    "sg:province":"PA",
    "sg:tags":[
        "physician",
        "surgeon"
    ],
    "sg:website":"www.wpahs.org",
    "wof:name":"Pulmonary Lab",
    "wof:placetype":"venue"
},
  "geometry": {"coordinates":[-80.003742,40.456076],"type":"Point"}
}