{
  "type": "Feature",
  "properties": {
    "addr:full":"510 S Orange St Media PA 19063",
    "addr:housenumber":"510",
    "addr:postcode":"19063",
    "addr:street":"S Orange St",
    "iso:country":"US",
    "sg:address":"510 S Orange St",
    "sg:city":"Media",
    "sg:classifiers":[
        {
            "category":"Wholesale",
            "subcategory":"Durable Goods & Equipment",
            "type":"Manufacturing & Wholesale Goods"
        }
    ],
    "sg:phone":"+1 610 565 2406",
    "sg:postcode":"19063",
    "sg:province":"PA",
    "sg:tags":[
        "environmental",
        "ecological",
        "prod"
    ],
    "wof:name":"Environmental Marine Equipment",
    "wof:placetype":"venue"
},
  "geometry": {"coordinates":[-75.39464,39.913144],"type":"Point"}
}