{
  "type": "Feature",
  "properties": {
    "addr:full":"901 N Fallon St Philadelphia PA 19131",
    "addr:housenumber":"901",
    "addr:postcode":"19131",
    "addr:street":"N Fallon St",
    "iso:country":"US",
    "sg:address":"901 N Fallon St",
    "sg:city":"Philadelphia",
    "sg:classifiers":[
        {
            "category":"Personal",
            "subcategory":"Barber",
            "type":"Services"
        }
    ],
    "sg:phone":"+1 215 477 4414",
    "sg:postcode":"19131",
    "sg:province":"PA",
    "wof:name":"Semaj International",
    "wof:placetype":"venue"
},
  "geometry": {"coordinates":[-75.21779600000001,39.969002],"type":"Point"}
}