{
  "type": "Feature",
  "properties": {
    "iso:country":"US",
    "sg:address":"1648 W Main St",
    "sg:city":"Ephrata",
    "sg:classifiers":[
        {
            "category":"Wholesale",
            "subcategory":"Poultry",
            "type":"Manufacturing & Wholesale Goods"
        },
        {
            "category":"Farming",
            "subcategory":"Livestock Farm",
            "type":"Manufacturing & Wholesale Goods"
        }
    ],
    "sg:phone":"+1 717 733 7434",
    "sg:postcode":"17522",
    "sg:province":"PA",
    "sg:tags":[
        "buyer",
        "auction",
        "market"
    ],
    "wof:name":"Irwin W Martin",
    "wof:placetype":"venue"
},
  "geometry": {"coordinates":[-76.204264,40.199255],"type":"Point"}
}