{
  "type": "Feature",
  "properties": {
    "addr:full":"850 Jennings St Bethlehem PA 18017",
    "addr:housenumber":"850",
    "addr:postcode":"18017",
    "addr:street":"Jennings St",
    "iso:country":"US",
    "sg:address":"850 Jennings St",
    "sg:city":"Bethlehem",
    "sg:classifiers":[
        {
            "category":"Building & Trades",
            "subcategory":"Construction",
            "type":"Services"
        }
    ],
    "sg:phone":"+1   ",
    "sg:postcode":"18017",
    "sg:province":"PA",
    "sg:tags":[
        "painting",
        "contractor"
    ],
    "wof:name":"Zarnas Inc",
    "wof:placetype":"venue"
},
  "geometry": {"coordinates":[-75.357114,40.624177],"type":"Point"}
}