{
  "type": "Feature",
  "properties": {
    "addr:full":"315 Meetinghouse Rd Horsham PA 19044",
    "addr:housenumber":"315",
    "addr:postcode":"19044",
    "addr:street":"Meetinghouse Rd",
    "iso:country":"US",
    "sg:address":"315 Meetinghouse Rd",
    "sg:city":"Horsham",
    "sg:classifiers":[
        {
            "category":"Government",
            "subcategory":"Fire Station",
            "type":"Public Place"
        }
    ],
    "sg:phone":"+1 215 672 6212",
    "sg:postcode":"19044",
    "sg:province":"PA",
    "sg:tags":[
        "department"
    ],
    "wof:name":"Horsham Fire Co",
    "wof:placetype":"venue"
},
  "geometry": {"coordinates":[-75.130207,40.1838],"type":"Point"}
}