{
  "type": "Feature",
  "properties": {
    "iso:country":"US",
    "sg:address":"1105 Rochester Rd",
    "sg:city":"Pittsburgh",
    "sg:classifiers":[
        {
            "category":"Professional",
            "subcategory":"Engineering",
            "type":"Services"
        }
    ],
    "sg:phone":"+1 412 367 0313",
    "sg:postcode":"15237",
    "sg:province":"PA",
    "sg:tags":[
        "engineer"
    ],
    "wof:name":"Indriss Inc",
    "wof:placetype":"venue"
},
  "geometry": {"coordinates":[-80.056782,40.550849],"type":"Point"}
}