{
  "type": "Feature",
  "properties": {
    "iso:country":"US",
    "sg:address":"800 Spruce St",
    "sg:city":"Philadelphia",
    "sg:classifiers":[
        {
            "category":"Health Services",
            "subcategory":"Doctor",
            "type":"Services"
        }
    ],
    "sg:phone":"+1 215 829 7550",
    "sg:postcode":"19107",
    "sg:province":"PA",
    "wof:name":"Jamieson Dara G MD",
    "wof:placetype":"venue"
},
  "geometry": {"coordinates":[-75.154701,39.945801],"type":"Point"}
}