{
  "type": "Feature",
  "properties": {
    "iso:country":"US",
    "sg:address":"1024 Trenton Rd",
    "sg:city":"Levittown",
    "sg:classifiers":[
        {
            "category":"Autos & Motor Vehicles",
            "subcategory":"Auto Supplies",
            "type":"Retail Goods"
        }
    ],
    "sg:phone":"+1 215 295 3222",
    "sg:postcode":"19054",
    "sg:province":"PA",
    "sg:tags":[
        "body",
        "automotive",
        "repair"
    ],
    "wof:name":"Jaguar Specialists Inc",
    "wof:placetype":"venue"
},
  "geometry": {"coordinates":[-74.826643,40.188536],"type":"Point"}
}