{
  "type": "Feature",
  "properties": {
    "iso:country":"US",
    "sg:address":"646 Baldwin St",
    "sg:city":"Bridgeville",
    "sg:classifiers":[
        {
            "category":"Organizations",
            "subcategory":"Religious Organization",
            "type":"Services"
        }
    ],
    "sg:phone":"+1   ",
    "sg:postcode":"15017",
    "sg:province":"PA",
    "wof:name":"Corporation of President of Th",
    "wof:placetype":"venue"
},
  "geometry": {"coordinates":[-80.106618,40.357613],"type":"Point"}
}