{
  "type": "Feature",
  "properties": {
    "addr:full":"672 Miller Ave Clairton PA 15025",
    "addr:housenumber":"672",
    "addr:postcode":"15025",
    "addr:street":"Miller Ave",
    "iso:country":"US",
    "sg:address":"672 Miller Ave",
    "sg:city":"Clairton",
    "sg:classifiers":[
        {
            "category":"Retail",
            "subcategory":"Auto Repair",
            "type":"Services"
        }
    ],
    "sg:phone":"+1 412 233 5076",
    "sg:postcode":"15025",
    "sg:province":"PA",
    "wof:name":"Webb's Automotive Service",
    "wof:placetype":"venue"
},
  "geometry": {"coordinates":[-79.8843,40.290401],"type":"Point"}
}