{
  "type": "Feature",
  "properties": {
    "addr:full":"1315 Main St Bentleyville PA 15314",
    "addr:housenumber":"1315",
    "addr:postcode":"15314",
    "addr:street":"Main St",
    "iso:country":"US",
    "sg:address":"1315 Main St",
    "sg:city":"Bentleyville",
    "sg:classifiers":[
        {
            "category":"Shopping",
            "subcategory":"Crafts & Fabrics",
            "type":"Retail Goods"
        }
    ],
    "sg:phone":"+1 724 239 5152",
    "sg:postcode":"15314",
    "sg:province":"PA",
    "sg:tags":[
        "sewing"
    ],
    "wof:name":"Fabric Fair",
    "wof:placetype":"venue"
},
  "geometry": {"coordinates":[-79.99733500000001,40.127104],"type":"Point"}
}