{
  "type": "Feature",
  "properties": {
    "iso:country":"US",
    "sg:address":"142 Cliff Ave",
    "sg:city":"Lancaster",
    "sg:classifiers":[
        {
            "category":"Manufacturing",
            "subcategory":"Soap",
            "type":"Manufacturing & Wholesale Goods"
        }
    ],
    "sg:phone":"+1   ",
    "sg:postcode":"17602",
    "sg:province":"PA",
    "sg:tags":[
        "detergent",
        "mfg"
    ],
    "wof:name":"Gretchen Maser",
    "wof:placetype":"venue"
},
  "geometry": {"coordinates":[-76.29923599999999,40.006673],"type":"Point"}
}