{
  "type": "Feature",
  "properties": {
    "iso:country":"US",
    "sg:address":"8135 Devon St",
    "sg:city":"Philadelphia",
    "sg:classifiers":[
        {
            "category":"Wholesale",
            "subcategory":"Durable Goods & Equipment",
            "type":"Manufacturing & Wholesale Goods"
        }
    ],
    "sg:phone":"+1 215 248 4151",
    "sg:postcode":"19118",
    "sg:province":"PA",
    "sg:tags":[
        "merchandise-wholesale",
        "store",
        "variety"
    ],
    "wof:name":"Pcg Wholesale",
    "wof:placetype":"venue"
},
  "geometry": {"coordinates":[-75.20080400000001,40.073146],"type":"Point"}
}