{
  "type": "Feature",
  "properties": {
    "iso:country":"US",
    "sg:address":"2562 Riddle Run Rd",
    "sg:city":"Tarentum",
    "sg:classifiers":[
        {
            "category":"Autos & Motor Vehicles",
            "subcategory":"Auto Supplies",
            "type":"Retail Goods"
        }
    ],
    "sg:phone":"+1   ",
    "sg:postcode":"15084",
    "sg:province":"PA",
    "wof:name":"Smooth Line Inc",
    "wof:placetype":"venue"
},
  "geometry": {"coordinates":[-79.784633,40.564278],"type":"Point"}
}