{
  "type": "Feature",
  "properties": {
    "addr:full":"4844 Main St Walnutport PA 18088",
    "addr:housenumber":"4844",
    "addr:postcode":"18088",
    "addr:street":"Main St",
    "iso:country":"US",
    "sg:address":"4844 Main St",
    "sg:city":"Walnutport",
    "sg:classifiers":[
        {
            "category":"Professional",
            "subcategory":"Art Services",
            "type":"Services"
        }
    ],
    "sg:phone":"+1 610 760 1776",
    "sg:postcode":"18088",
    "sg:province":"PA",
    "sg:tags":[
        "graphic",
        "designer"
    ],
    "wof:name":"Omnigrafix",
    "wof:placetype":"venue"
},
  "geometry": {"coordinates":[-75.58772500000001,40.760186],"type":"Point"}
}