{
  "type": "Feature",
  "properties": {
    "addr:full":"7141 Germantown Ave Philadelphia PA 19119",
    "addr:housenumber":"7141",
    "addr:postcode":"19119",
    "addr:street":"Germantown Ave",
    "iso:country":"US",
    "sg:address":"7141 Germantown Ave",
    "sg:city":"Philadelphia",
    "sg:classifiers":[
        {
            "category":"Cinema",
            "subcategory":"Movie Rental",
            "type":"Entertainment"
        }
    ],
    "sg:phone":"+1 215 247 1235",
    "sg:postcode":"19119",
    "sg:province":"PA",
    "sg:tags":[
        "leasing",
        "video",
        "disc",
        "tape"
    ],
    "wof:name":"Video Library Of Mt Airy",
    "wof:placetype":"venue"
},
  "geometry": {"coordinates":[-75.190055,40.059098],"type":"Point"}
}