{
  "type": "Feature",
  "properties": {
    "iso:country":"US",
    "sg:address":"1776 Louisa Ln",
    "sg:city":"Mechanicsburg",
    "sg:classifiers":[
        {
            "category":"Real Estate",
            "subcategory":"Real Estate Operator",
            "type":"Services"
        }
    ],
    "sg:phone":"+1 717 635 2413",
    "sg:postcode":"17050",
    "sg:province":"PA",
    "sg:tags":[
        "apartment"
    ],
    "wof:name":"Pmi Brambles Apts",
    "wof:placetype":"venue"
},
  "geometry": {"coordinates":[-76.976539,40.240812],"type":"Point"}
}