{
  "type": "Feature",
  "properties": {
    "addr:full":"1115 Ridge Rd Burgettstown PA 15021",
    "addr:housenumber":"1115",
    "addr:postcode":"15021",
    "addr:street":"Ridge Rd",
    "iso:country":"US",
    "sg:address":"1115 Ridge Rd",
    "sg:city":"Burgettstown",
    "sg:classifiers":[
        {
            "category":"Restaurant",
            "type":"Food & Drink"
        }
    ],
    "sg:phone":"+1   ",
    "sg:postcode":"15021",
    "sg:province":"PA",
    "sg:tags":[
        "eating"
    ],
    "wof:name":"Lounders Family Restaurant",
    "wof:placetype":"venue"
},
  "geometry": {"coordinates":[-80.348423,40.334677],"type":"Point"}
}