{
  "type": "Feature",
  "properties": {
    "iso:country":"US",
    "sg:address":"1009 S 11th St",
    "sg:city":"Philadelphia",
    "sg:classifiers":[
        {
            "category":"Manufacturing",
            "subcategory":"Printing",
            "type":"Manufacturing & Wholesale Goods"
        }
    ],
    "sg:phone":"+1 215 463 4883",
    "sg:postcode":"19147",
    "sg:province":"PA",
    "sg:tags":[
        "scanning",
        "printer",
        "supply",
        "lithographic",
        "commercial",
        "equipment",
        "plotting"
    ],
    "wof:name":"Farr Well Printing",
    "wof:placetype":"venue"
},
  "geometry": {"coordinates":[-75.161278,39.937962],"type":"Point"}
}