{
  "type": "Feature",
  "properties": {
    "iso:country":"US",
    "sg:address":"106 Crestview Ave",
    "sg:city":"New Holland",
    "sg:classifiers":[
        {
            "category":"Real Estate",
            "subcategory":"Real Estate Agent",
            "type":"Services"
        }
    ],
    "sg:phone":"+1   ",
    "sg:postcode":"17557",
    "sg:province":"PA",
    "wof:name":"Troop Appraisal Services",
    "wof:placetype":"venue"
},
  "geometry": {"coordinates":[-76.06127499999999,40.115102],"type":"Point"}
}