{
  "type": "Feature",
  "properties": {
    "iso:country":"US",
    "sg:address":"435 N Webster Ave",
    "sg:city":"Scranton",
    "sg:classifiers":[
        {
            "category":"Professional",
            "type":"Services"
        }
    ],
    "sg:phone":"+1   ",
    "sg:postcode":"18510",
    "sg:province":"PA",
    "wof:name":"Zabawa",
    "wof:placetype":"venue"
},
  "geometry": {"coordinates":[-75.65222300000001,41.406087],"type":"Point"}
}