{
  "type": "Feature",
  "properties": {
    "addr:full":"6180 Harshman Rd Chambersburg PA 17201",
    "addr:housenumber":"6180",
    "addr:postcode":"17201",
    "addr:street":"Harshman Rd",
    "iso:country":"US",
    "sg:address":"6180 Harshman Rd",
    "sg:city":"Chambersburg",
    "sg:classifiers":[
        {
            "category":"Farming",
            "subcategory":"Dairy Farm",
            "type":"Manufacturing & Wholesale Goods"
        }
    ],
    "sg:phone":"+1   ",
    "sg:postcode":"17201",
    "sg:province":"PA",
    "wof:name":"Slouthour Trefford",
    "wof:placetype":"venue"
},
  "geometry": {"coordinates":[-77.69995,39.852469],"type":"Point"}
}