{
  "type": "Feature",
  "properties": {
    "iso:country":"US",
    "sg:address":"4359 Woodbury Pike",
    "sg:city":"Woodbury",
    "sg:classifiers":[
        {
            "category":"Organizations",
            "subcategory":"Religious Organization",
            "type":"Services"
        }
    ],
    "sg:phone":"+1 814 793 2288",
    "sg:postcode":"16695",
    "sg:province":"PA",
    "sg:tags":[
        "church"
    ],
    "wof:name":"Woodbury Church-The Brethren",
    "wof:placetype":"venue"
},
  "geometry": {"coordinates":[-78.36342999999999,40.241365],"type":"Point"}
}