{
  "type": "Feature",
  "properties": {
    "iso:country":"US",
    "sg:address":"5562 Sell Rd",
    "sg:city":"Schnecksville",
    "sg:classifiers":[
        {
            "category":"Building & Trades",
            "subcategory":"Plumbing",
            "type":"Services"
        }
    ],
    "sg:phone":"+1 610 760 8724",
    "sg:postcode":"18078",
    "sg:province":"PA",
    "sg:tags":[
        "contractor"
    ],
    "wof:name":"All American Heating & Cooling",
    "wof:placetype":"venue"
},
  "geometry": {"coordinates":[-75.66633899999999,40.671315],"type":"Point"}
}