{
  "type": "Feature",
  "properties": {
    "addr:full":"1525 Dillon Rd Ambler PA 19002",
    "addr:housenumber":"1525",
    "addr:postcode":"19002",
    "addr:street":"Dillon Rd",
    "iso:country":"US",
    "sg:address":"1525 Dillon Rd",
    "sg:city":"Ambler",
    "sg:classifiers":[
        {
            "category":"Real Estate",
            "subcategory":"Architect",
            "type":"Services"
        }
    ],
    "sg:phone":"+1 215 643 1311",
    "sg:postcode":"19002",
    "sg:province":"PA",
    "sg:tags":[
        "home",
        "planning",
        "design",
        "architectural"
    ],
    "wof:name":"Glen Maple Home Accents",
    "wof:placetype":"venue"
},
  "geometry": {"coordinates":[-75.179563,40.159087],"type":"Point"}
}