{
  "type": "Feature",
  "properties": {
    "addr:full":"310 Mitchell Hill Rd Butler PA 16002",
    "addr:housenumber":"310",
    "addr:postcode":"16002",
    "addr:street":"Mitchell Hill Rd",
    "iso:country":"US",
    "sg:address":"310 Mitchell Hill Rd",
    "sg:city":"Butler",
    "sg:classifiers":[
        {
            "category":"Building & Trades",
            "subcategory":"Construction",
            "type":"Services"
        }
    ],
    "sg:phone":"+1 724 282 6913",
    "sg:postcode":"16002",
    "sg:province":"PA",
    "sg:tags":[
        "paving",
        "contractor"
    ],
    "wof:name":"Wiest Asphalt Products & Paving Inc",
    "wof:placetype":"venue"
},
  "geometry": {"coordinates":[-79.871917,40.863251],"type":"Point"}
}