{
  "type": "Feature",
  "properties": {
    "addr:full":"513 Gladiola Dr Clarks Summit PA 18411",
    "addr:housenumber":"513",
    "addr:postcode":"18411",
    "addr:street":"Gladiola Dr",
    "iso:country":"US",
    "sg:address":"513 Gladiola Dr",
    "sg:city":"Clarks Summit",
    "sg:classifiers":[
        {
            "category":"Building & Trades",
            "subcategory":"Construction",
            "type":"Services"
        }
    ],
    "sg:phone":"+1 570 586 6986",
    "sg:postcode":"18411",
    "sg:province":"PA",
    "sg:tags":[
        "contractor",
        "general"
    ],
    "wof:name":"A To Z Contractors Builders",
    "wof:placetype":"venue"
},
  "geometry": {"coordinates":[-75.698042,41.482112],"type":"Point"}
}