{
  "type": "Feature",
  "properties": {
    "addr:full":"700 Pattison Ave Philadelphia PA 19148",
    "addr:housenumber":"700",
    "addr:postcode":"19148",
    "addr:street":"Pattison Ave",
    "iso:country":"US",
    "sg:address":"700 Pattison Ave",
    "sg:city":"Philadelphia",
    "sg:classifiers":[
        {
            "category":"Food & Beverages",
            "subcategory":"Groceries & Convenience Stores",
            "type":"Retail Goods"
        }
    ],
    "sg:phone":"+1 215 465 3055",
    "sg:postcode":"19148",
    "sg:province":"PA",
    "wof:name":"Lee's Wholesale & Distributors",
    "wof:placetype":"venue"
},
  "geometry": {"coordinates":[-75.1623,39.9039],"type":"Point"}
}