{
  "type": "Feature",
  "properties": {
    "iso:country":"US",
    "sg:address":"137 E Main St",
    "sg:city":"Lock Haven",
    "sg:classifiers":[
        {
            "category":"Food & Beverages",
            "subcategory":"Liquor & Beverages",
            "type":"Retail Goods"
        }
    ],
    "sg:phone":"+1 570 893 2950",
    "sg:postcode":"17745",
    "sg:province":"PA",
    "wof:name":"Lock Haven Liquor Store",
    "wof:placetype":"venue"
},
  "geometry": {"coordinates":[-77.44535399999999,41.137182],"type":"Point"}
}