{
  "type": "Feature",
  "properties": {
    "iso:country":"US",
    "sg:address":"1900 Barclay Hill Rd",
    "sg:city":"Beaver",
    "sg:classifiers":[
        {
            "category":"Communications",
            "subcategory":"Television Station",
            "type":"Services"
        }
    ],
    "sg:phone":"+1 724 643 4998",
    "sg:postcode":"15009",
    "sg:province":"PA",
    "sg:tags":[
        "satellite",
        "cable"
    ],
    "wof:name":"Precision Fiber And Cable",
    "wof:placetype":"venue"
},
  "geometry": {"coordinates":[-80.379059,40.667931],"type":"Point"}
}