{
  "type": "Feature",
  "properties": {
    "iso:country":"US",
    "sg:address":"17th & Chew Sts",
    "sg:city":"Allentown",
    "sg:classifiers":[
        {
            "category":"Health Services",
            "subcategory":"Doctor",
            "type":"Services"
        }
    ],
    "sg:phone":"+1 610 402 1600",
    "sg:postcode":"18101",
    "sg:province":"PA",
    "sg:tags":[
        "obstetrician",
        "gynecologist"
    ],
    "sg:website":"www.lvpg.org",
    "wof:name":"Center For Women's Medicine",
    "wof:placetype":"venue"
},
  "geometry": {"coordinates":[-75.494227,40.600785],"type":"Point"}
}