{
  "type": "Feature",
  "properties": {
    "iso:country":"US",
    "sg:address":"3910 W Lincoln Hwy",
    "sg:city":"Downingtown",
    "sg:classifiers":[
        {
            "category":"Autos & Motor Vehicles",
            "subcategory":"Auto Supplies",
            "type":"Retail Goods"
        },
        {
            "category":"Retail",
            "subcategory":"Auto Repair",
            "type":"Services"
        }
    ],
    "sg:phone":"+1 610 269 5700",
    "sg:postcode":"19335",
    "sg:province":"PA",
    "sg:tags":[
        "exhaust",
        "tire",
        "system",
        "brake",
        "muffler"
    ],
    "sg:website":"http://www.mrtire.com",
    "wof:name":"Mr. Tire Auto Service Centers",
    "wof:placetype":"venue"
},
  "geometry": {"coordinates":[-75.72687999999999,39.998787],"type":"Point"}
}