{
  "type": "Feature",
  "properties": {
    "addr:full":"2730 W 12th St Erie PA 16505",
    "addr:housenumber":"2730",
    "addr:postcode":"16505",
    "addr:street":"W 12Th St",
    "iso:country":"US",
    "sg:address":"2730 W 12th St",
    "sg:city":"Erie",
    "sg:classifiers":[
        {
            "category":"Autos & Motor Vehicles",
            "subcategory":"Auto Supplies",
            "type":"Retail Goods"
        }
    ],
    "sg:phone":"+1 814 835 1323",
    "sg:postcode":"16505",
    "sg:province":"PA",
    "sg:tags":[
        "sound",
        "automotive",
        "equipment",
        "accessory"
    ],
    "wof:name":"Empire Car Audio & Racing",
    "wof:placetype":"venue"
},
  "geometry": {"coordinates":[-80.14206,42.101261],"type":"Point"}
}