{
  "type": "Feature",
  "properties": {
    "addr:full":"7404 Boyertown Pike Earlville PA 19519",
    "addr:housenumber":"7404",
    "addr:postcode":"19519",
    "addr:street":"Boyertown Pike",
    "iso:country":"US",
    "sg:address":"7404 Boyertown Pike",
    "sg:city":"Earlville",
    "sg:classifiers":[
        {
            "category":"Government",
            "subcategory":"Post Office",
            "type":"Public Place"
        }
    ],
    "sg:phone":"+1 610 689 9219",
    "sg:postcode":"19519",
    "sg:province":"PA",
    "wof:name":"US Post Office",
    "wof:placetype":"venue"
},
  "geometry": {"coordinates":[-75.729603,40.317374],"type":"Point"}
}