{
  "type": "Feature",
  "properties": {
    "iso:country":"US",
    "sg:address":"627 Washington Ave",
    "sg:city":"Charleroi",
    "sg:classifiers":[
        {
            "category":"Building & Trades",
            "subcategory":"Cleaning & Sanitation",
            "type":"Services"
        }
    ],
    "sg:phone":"+1 724 483 4797",
    "sg:postcode":"15022",
    "sg:province":"PA",
    "sg:tags":[
        "maintenance"
    ],
    "wof:name":"Advanced Building Maintenance",
    "wof:placetype":"venue"
},
  "geometry": {"coordinates":[-79.901082,40.139312],"type":"Point"}
}