{
  "type": "Feature",
  "properties": {
    "iso:country":"US",
    "sg:address":"3400 Birchwood Rd",
    "sg:city":"East Stroudsburg",
    "sg:classifiers":[
        {
            "category":"Real Estate",
            "subcategory":"Real Estate Operator",
            "type":"Services"
        }
    ],
    "sg:phone":"+1   ",
    "sg:postcode":"18301",
    "sg:province":"PA",
    "sg:tags":[
        "building",
        "nonresidential"
    ],
    "wof:name":"Birchwood Resorts",
    "wof:placetype":"venue"
},
  "geometry": {"coordinates":[-75.256016,41.063806],"type":"Point"}
}