{
  "type": "Feature",
  "properties": {
    "iso:country":"US",
    "sg:address":"31 N Hanover St.",
    "sg:city":"Carlisle",
    "sg:classifiers":[
        {
            "category":"Restaurant",
            "type":"Food & Drink"
        }
    ],
    "sg:phone":"+1 717 218 2006",
    "sg:postcode":"17013",
    "sg:province":"PA",
    "sg:tags":[
        "thai"
    ],
    "wof:name":"Lily Cafe Express",
    "wof:placetype":"venue"
},
  "geometry": {"coordinates":[-77.188892,40.202799],"type":"Point"}
}