{
  "type": "Feature",
  "properties": {
    "iso:country":"US",
    "sg:address":"7 W Main St",
    "sg:city":"Norristown",
    "sg:classifiers":[
        {
            "category":"Restaurant",
            "type":"Food & Drink"
        }
    ],
    "sg:phone":"+1 610 272 1919",
    "sg:postcode":"19401",
    "sg:province":"PA",
    "sg:tags":[
        "shop",
        "coffee"
    ],
    "wof:name":"Banks Cafe Inc",
    "wof:placetype":"venue"
},
  "geometry": {"coordinates":[-75.34561600000001,40.114985],"type":"Point"}
}