{
  "type": "Feature",
  "properties": {
    "iso:country":"US",
    "sg:address":"28 Crawford Ave",
    "sg:city":"Simpson",
    "sg:classifiers":[
        {
            "category":"Manufacturing",
            "subcategory":"Glass & Minerals",
            "type":"Manufacturing & Wholesale Goods"
        }
    ],
    "sg:phone":"+1 570 282 5850",
    "sg:postcode":"18407",
    "sg:province":"PA",
    "sg:tags":[
        "ready"
    ],
    "wof:name":"Carbondale Concrete Co",
    "wof:placetype":"venue"
},
  "geometry": {"coordinates":[-75.48664599999999,41.587142],"type":"Point"}
}