{
  "type": "Feature",
  "properties": {
    "iso:country":"US",
    "sg:address":"916 S 6th St",
    "sg:city":"Allentown",
    "sg:classifiers":[
        {
            "category":"Health Services",
            "subcategory":"Hospital",
            "type":"Services"
        }
    ],
    "sg:phone":"+1 484 274 6331",
    "sg:postcode":"18103",
    "sg:province":"PA",
    "wof:name":"Good Shepard Hospital",
    "wof:placetype":"venue"
},
  "geometry": {"coordinates":[-75.4652,40.592066],"type":"Point"}
}