{
  "type": "Feature",
  "properties": {
    "iso:country":"US",
    "sg:address":"424 Old Philly Pike",
    "sg:city":"Kempton",
    "sg:classifiers":[
        {
            "category":"Building & Trades",
            "subcategory":"Equipment Rental",
            "type":"Services"
        }
    ],
    "sg:phone":"+1 610 756 6144",
    "sg:postcode":"19529",
    "sg:province":"PA",
    "sg:tags":[
        "yard",
        "leasing",
        "store"
    ],
    "wof:name":"Muth Rentals",
    "wof:placetype":"venue"
},
  "geometry": {"coordinates":[-75.855217,40.634899],"type":"Point"}
}