{
  "type": "Feature",
  "properties": {
    "addr:full":"1001 Lincoln Hwy Exton PA 19320",
    "addr:housenumber":"1001",
    "addr:postcode":"19320",
    "addr:street":"Lincoln Hwy",
    "iso:country":"US",
    "sg:address":"1001 Lincoln Hwy",
    "sg:city":"Exton",
    "sg:classifiers":[
        {
            "category":"Education",
            "subcategory":"School",
            "type":"Public Place"
        }
    ],
    "sg:phone":"+1 610 363 7500",
    "sg:postcode":"19320",
    "sg:province":"PA",
    "sg:website":"www.gocfs.net",
    "wof:name":"CFS The School At Church Frm",
    "wof:placetype":"venue"
},
  "geometry": {"coordinates":[-75.85125600000001,39.984314],"type":"Point"}
}