{
  "type": "Feature",
  "properties": {
    "iso:country":"US",
    "sg:address":"680 Log Tavern Rd",
    "sg:city":"Milford",
    "sg:classifiers":[
        {
            "category":"Government",
            "subcategory":"Fire Station",
            "type":"Public Place"
        },
        {
            "category":"Government",
            "subcategory":"Office",
            "type":"Public Place"
        }
    ],
    "sg:phone":"+1 570 686 3696",
    "sg:postcode":"18337",
    "sg:province":"PA",
    "sg:tags":[
        "department",
        "township",
        "protection",
        "government-city",
        "village"
    ],
    "wof:name":"Dingman Volunteer Fire Department",
    "wof:placetype":"venue"
},
  "geometry": {"coordinates":[-74.95826,41.2994],"type":"Point"}
}