{
  "type": "Feature",
  "properties": {
    "iso:country":"US",
    "sg:address":"1433 Sandy Lake Rd",
    "sg:city":"Grove City",
    "sg:classifiers":[
        {
            "category":"Farming",
            "subcategory":"Farm",
            "type":"Manufacturing & Wholesale Goods"
        }
    ],
    "sg:phone":"+1   ",
    "sg:postcode":"16127",
    "sg:province":"PA",
    "sg:tags":[
        "crop",
        "general"
    ],
    "wof:name":"David McDowell",
    "wof:placetype":"venue"
},
  "geometry": {"coordinates":[-80.07605599999999,41.224204],"type":"Point"}
}