{
  "type": "Feature",
  "properties": {
    "addr:full":"338 Pennsylvania Ave Rochester PA 15074",
    "addr:housenumber":"338",
    "addr:postcode":"15074",
    "addr:street":"Pennsylvania Ave",
    "iso:country":"US",
    "sg:address":"338 Pennsylvania Ave",
    "sg:city":"Rochester",
    "sg:classifiers":[
        {
            "category":"Recreation",
            "type":"Entertainment"
        }
    ],
    "sg:phone":"+1   ",
    "sg:postcode":"15074",
    "sg:province":"PA",
    "wof:name":"Rochester Turners Gymnastics",
    "wof:placetype":"venue"
},
  "geometry": {"coordinates":[-80.279966,40.704721],"type":"Point"}
}