{
  "type": "Feature",
  "properties": {
    "iso:country":"US",
    "sg:address":"171 7th Ave",
    "sg:city":"Valencia",
    "sg:classifiers":[
        {
            "category":"Manufacturing",
            "subcategory":"Petroleum Products",
            "type":"Manufacturing & Wholesale Goods"
        }
    ],
    "sg:phone":"+1 724 625 1505",
    "sg:postcode":"16059",
    "sg:province":"PA",
    "sg:tags":[
        "asphalt"
    ],
    "wof:name":"Russell Standard Corp",
    "wof:placetype":"venue"
},
  "geometry": {"coordinates":[-79.998537,40.68176],"type":"Point"}
}