{
  "type": "Feature",
  "properties": {
    "iso:country":"US",
    "sg:address":"1223 E Chocolate Ave",
    "sg:city":"Hershey",
    "sg:phone":"+1 717 520 0882",
    "sg:postcode":"17033",
    "sg:province":"PA",
    "sg:website":"http://www.ensmingerbuilder.com/aboutus/",
    "wof:name":"Ensminger Builder Inc.",
    "wof:placetype":"venue"
},
  "geometry": {"coordinates":[-76.622311,40.296189],"type":"Point"}
}