{
  "type": "Feature",
  "properties": {
    "addr:full":"82 S 69th St Upper Darby PA 19082",
    "addr:housenumber":"82",
    "addr:postcode":"19082",
    "addr:street":"S 69Th St",
    "iso:country":"US",
    "sg:address":"82 S 69th St",
    "sg:city":"Upper Darby",
    "sg:classifiers":[
        {
            "category":"Shopping",
            "subcategory":"Clothing, Apparel, & Fashions",
            "type":"Retail Goods"
        }
    ],
    "sg:phone":"+1 610 352 6425",
    "sg:postcode":"19082",
    "sg:province":"PA",
    "sg:tags":[
        "children's",
        "clothing"
    ],
    "sg:website":"www.childrensplace.com",
    "wof:name":"Children's Place",
    "wof:placetype":"venue"
},
  "geometry": {"coordinates":[-75.25859800000001,39.959301],"type":"Point"}
}