{
  "type": "Feature",
  "properties": {
    "iso:country":"US",
    "sg:address":"909 N 45th St",
    "sg:city":"Philadelphia",
    "sg:classifiers":[
        {
            "category":"Professional",
            "subcategory":"Employment Agencies",
            "type":"Services"
        }
    ],
    "sg:phone":"+1 215 473 6390",
    "sg:postcode":"19104",
    "sg:province":"PA",
    "sg:tags":[
        "modeling",
        "help",
        "supply"
    ],
    "wof:name":"New Style Modeling Agency",
    "wof:placetype":"venue"
},
  "geometry": {"coordinates":[-75.21253299999999,39.969755],"type":"Point"}
}