{
  "type": "Feature",
  "properties": {
    "iso:country":"US",
    "sg:address":"425 Reading Ave",
    "sg:city":"West Reading",
    "sg:classifiers":[
        {
            "category":"Health Services",
            "subcategory":"Nursing And Care Facility",
            "type":"Services"
        }
    ],
    "sg:phone":"+1 610 373 5166",
    "sg:postcode":"19611",
    "sg:province":"PA",
    "sg:tags":[
        "home",
        "convalescent"
    ],
    "wof:name":"Manor Care Health Svc",
    "wof:placetype":"venue"
},
  "geometry": {"coordinates":[-75.94618199999999,40.336632],"type":"Point"}
}