{
  "type": "Feature",
  "properties": {
    "addr:full":"438 W Mount Airy Ave Philadelphia PA 19119",
    "addr:housenumber":"438",
    "addr:postcode":"19119",
    "addr:street":"W Mount Airy Ave",
    "iso:country":"US",
    "sg:address":"438 W Mount Airy Ave",
    "sg:city":"Philadelphia",
    "sg:classifiers":[
        {
            "category":"Organizations",
            "subcategory":"Professional Association",
            "type":"Services"
        }
    ],
    "sg:phone":"+1 215 242 4233",
    "sg:postcode":"19119",
    "sg:province":"PA",
    "wof:name":"Margaret Burke",
    "wof:placetype":"venue"
},
  "geometry": {"coordinates":[-75.19792099999999,40.053466],"type":"Point"}
}