{
  "type": "Feature",
  "properties": {
    "iso:country":"US",
    "sg:address":"10306 Mountain Rd",
    "sg:city":"Orrstown",
    "sg:classifiers":[
        {
            "category":"Building & Trades",
            "subcategory":"Construction",
            "type":"Services"
        }
    ],
    "sg:phone":"+1 717 530 9325",
    "sg:postcode":"17244",
    "sg:province":"PA",
    "sg:tags":[
        "hanging",
        "contractor"
    ],
    "wof:name":"Don Yohe Painting",
    "wof:placetype":"venue"
},
  "geometry": {"coordinates":[-77.709084,40.060517],"type":"Point"}
}