{
  "type": "Feature",
  "properties": {
    "iso:country":"US",
    "sg:address":"70 E Beau St",
    "sg:city":"Washington",
    "sg:classifiers":[
        {
            "category":"Professional",
            "subcategory":"Lawyer & Legal Services",
            "type":"Services"
        }
    ],
    "sg:phone":"+1 724 222 4520",
    "sg:postcode":"15301",
    "sg:province":"PA",
    "sg:tags":[
        "attorney",
        "practice"
    ],
    "wof:name":"Roberts Susan T",
    "wof:placetype":"venue"
},
  "geometry": {"coordinates":[-80.243656,40.171158],"type":"Point"}
}