{
  "type": "Feature",
  "properties": {
    "iso:country":"US",
    "sg:address":"1199 Cherrington Ln",
    "sg:city":"Harrisburg",
    "sg:classifiers":[
        {
            "category":"Building & Trades",
            "subcategory":"Plumbing",
            "type":"Services"
        }
    ],
    "sg:phone":"+1 717 541 0687",
    "sg:postcode":"17111",
    "sg:province":"PA",
    "sg:tags":[
        "conditioning",
        "air",
        "system",
        "contractor"
    ],
    "wof:name":"George W Wilson Inc",
    "wof:placetype":"venue"
},
  "geometry": {"coordinates":[-76.75425199999999,40.301183],"type":"Point"}
}