{
  "type": "Feature",
  "properties": {
    "iso:country":"US",
    "sg:address":"1040 Saint Davids Rd",
    "sg:city":"Williamsport",
    "sg:classifiers":[
        {
            "category":"Recreation",
            "subcategory":"Gun Range",
            "type":"Entertainment"
        }
    ],
    "sg:phone":"+1 570 322 6371",
    "sg:postcode":"17701",
    "sg:province":"PA",
    "sg:tags":[
        "pistol",
        "rifle"
    ],
    "wof:name":"Laurel Lodge Hunting Club Inc",
    "wof:placetype":"venue"
},
  "geometry": {"coordinates":[-76.95538999999999,41.25209],"type":"Point"}
}