{
  "type": "Feature",
  "properties": {
    "iso:country":"US",
    "sg:address":"516 E Woods Dr",
    "sg:city":"Lititz",
    "sg:classifiers":[
        {
            "category":"Professional",
            "subcategory":"Business Services",
            "type":"Services"
        }
    ],
    "sg:phone":"+1 717 917 7223",
    "sg:postcode":"17543",
    "sg:province":"PA",
    "sg:tags":[
        "organizing",
        "services-household"
    ],
    "wof:name":"Penn Cinema Management Company",
    "wof:placetype":"venue"
},
  "geometry": {"coordinates":[-76.270531,40.133781],"type":"Point"}
}