{
  "type": "Feature",
  "properties": {
    "iso:country":"US",
    "sg:address":"39 N 3rd St",
    "sg:city":"Chambersburg",
    "sg:classifiers":[
        {
            "category":"Building & Trades",
            "subcategory":"Landscaping Services",
            "type":"Services"
        }
    ],
    "sg:phone":"+1 717 263 2932",
    "sg:postcode":"17201",
    "sg:province":"PA",
    "sg:tags":[
        "snow",
        "removal"
    ],
    "wof:name":"Shank, Doug, Lester, Daniel, David",
    "wof:placetype":"venue"
},
  "geometry": {"coordinates":[-77.656937,39.937759],"type":"Point"}
}