{
  "type": "Feature",
  "properties": {
    "iso:country":"US",
    "sg:address":"2632 Nazareth Rd",
    "sg:city":"Easton",
    "sg:classifiers":[
        {
            "category":"Health Services",
            "subcategory":"Doctor",
            "type":"Services"
        }
    ],
    "sg:phone":"+1 610 253 5257",
    "sg:postcode":"18045",
    "sg:province":"PA",
    "sg:tags":[
        "physician",
        "surgeon"
    ],
    "wof:name":"B K Mehta Md",
    "wof:placetype":"venue"
},
  "geometry": {"coordinates":[-75.25617800000001,40.689774],"type":"Point"}
}