{
  "type": "Feature",
  "properties": {
    "addr:full":"1030 Walnut St Sunbury PA 17801",
    "addr:housenumber":"1030",
    "addr:postcode":"17801",
    "addr:street":"Walnut St",
    "iso:country":"US",
    "sg:address":"1030 Walnut St",
    "sg:city":"Sunbury",
    "sg:classifiers":[
        {
            "category":"Building & Trades",
            "subcategory":"Electrical",
            "type":"Services"
        }
    ],
    "sg:phone":"+1 570 286 9598",
    "sg:postcode":"17801",
    "sg:province":"PA",
    "sg:tags":[
        "electric",
        "contractor"
    ],
    "wof:name":"K & N Electric Inc",
    "wof:placetype":"venue"
},
  "geometry": {"coordinates":[-76.78733200000001,40.855218],"type":"Point"}
}