{
  "type": "Feature",
  "properties": {
    "iso:country":"US",
    "sg:address":"2955 Brodhead Rd",
    "sg:city":"Aliquippa",
    "sg:classifiers":[
        {
            "category":"Home & Garden",
            "subcategory":"Household Appliances",
            "type":"Retail Goods"
        }
    ],
    "sg:phone":"+1   ",
    "sg:postcode":"15001",
    "sg:province":"PA",
    "wof:name":"Campisi L P & Son Plbg Contr",
    "wof:placetype":"venue"
},
  "geometry": {"coordinates":[-80.25734799999999,40.580237],"type":"Point"}
}