{
  "type": "Feature",
  "properties": {
    "addr:full":"508 Grant Way Kennett Square PA 19348",
    "addr:housenumber":"508",
    "addr:postcode":"19348",
    "addr:street":"Grant Way",
    "iso:country":"US",
    "sg:address":"508 Grant Way",
    "sg:city":"Kennett Square",
    "sg:classifiers":[
        {
            "category":"Building & Trades",
            "subcategory":"Construction",
            "type":"Services"
        }
    ],
    "sg:phone":"+1 610 444 9711",
    "sg:postcode":"19348",
    "sg:province":"PA",
    "sg:tags":[
        "excavating",
        "contractor"
    ],
    "wof:name":"D & P Excavating",
    "wof:placetype":"venue"
},
  "geometry": {"coordinates":[-75.71614099999999,39.840766],"type":"Point"}
}