{
  "type": "Feature",
  "properties": {
    "iso:country":"US",
    "sg:address":"19 Fort Couch Rd",
    "sg:city":"Pittsburgh",
    "sg:classifiers":[
        {
            "category":"Shopping",
            "subcategory":"Clothing, Apparel, & Fashions",
            "type":"Retail Goods"
        }
    ],
    "sg:phone":"+1   ",
    "sg:postcode":"15241",
    "sg:province":"PA",
    "wof:name":"Christopher & Banks Inc",
    "wof:placetype":"venue"
},
  "geometry": {"coordinates":[-80.051238,40.335465],"type":"Point"}
}