{
  "type": "Feature",
  "properties": {
    "iso:country":"US",
    "sg:address":"12944 Springboro Rd",
    "sg:city":"Conneautville",
    "sg:classifiers":[
        {
            "category":"Farming",
            "subcategory":"Livestock Farm",
            "type":"Manufacturing & Wholesale Goods"
        }
    ],
    "sg:phone":"+1   ",
    "sg:postcode":"16406",
    "sg:province":"PA",
    "sg:tags":[
        "equine"
    ],
    "wof:name":"Edward Bowen",
    "wof:placetype":"venue"
},
  "geometry": {"coordinates":[-80.273404,41.791383],"type":"Point"}
}