{
  "type": "Feature",
  "properties": {
    "iso:country":"US",
    "sg:address":"1378 River Rd",
    "sg:city":"Drumore",
    "sg:classifiers":[
        {
            "category":"Shopping",
            "type":"Retail Goods"
        }
    ],
    "sg:phone":"+1   ",
    "sg:postcode":"17518",
    "sg:province":"PA",
    "sg:tags":[
        "merchandise"
    ],
    "wof:name":"Math-U-See Inc",
    "wof:placetype":"venue"
},
  "geometry": {"coordinates":[-76.238409,39.822808],"type":"Point"}
}