{
  "type": "Feature",
  "properties": {
    "iso:country":"US",
    "sg:address":"Murrysville & Washin",
    "sg:city":"Mars",
    "sg:classifiers":[
        {
            "category":"Health Services",
            "subcategory":"Optometrist",
            "type":"Services"
        }
    ],
    "sg:phone":"+1 724 772 3388",
    "sg:postcode":"16046",
    "sg:province":"PA",
    "sg:tags":[
        "ophthalmologist"
    ],
    "wof:name":"Pediatric Ophthalmology & Strabismus Inc",
    "wof:placetype":"venue"
},
  "geometry": {"coordinates":[-80.041496,40.681702],"type":"Point"}
}