{
  "type": "Feature",
  "properties": {
    "iso:country":"US",
    "sg:address":"1525 Locust St",
    "sg:city":"Philadelphia",
    "sg:classifiers":[
        {
            "category":"Real Estate",
            "subcategory":"Architect",
            "type":"Services"
        }
    ],
    "sg:phone":"+1 215 772 0204",
    "sg:postcode":"19102",
    "sg:province":"PA",
    "wof:name":"Terry Crockette",
    "wof:placetype":"venue"
},
  "geometry": {"coordinates":[-75.167024,39.948643],"type":"Point"}
}