{
  "type": "Feature",
  "properties": {
    "iso:country":"US",
    "sg:address":"2733 Elm Ct",
    "sg:city":"Allentown",
    "sg:classifiers":[
        {
            "category":"Personal",
            "subcategory":"Beauty Salon",
            "type":"Services"
        }
    ],
    "sg:phone":"+1 610 433 3739",
    "sg:postcode":"18104",
    "sg:province":"PA",
    "wof:name":"Staying On Top",
    "wof:placetype":"venue"
},
  "geometry": {"coordinates":[-75.511515,40.586744],"type":"Point"}
}