{
  "type": "Feature",
  "properties": {
    "iso:country":"US",
    "sg:address":"199 Thomas Rd",
    "sg:city":"Bloomsburg",
    "sg:classifiers":[
        {
            "category":"Shopping",
            "subcategory":"Gifts & Souvenirs",
            "type":"Retail Goods"
        }
    ],
    "sg:phone":"+1 570 387 1012",
    "sg:postcode":"17815",
    "sg:province":"PA",
    "wof:name":"Creek Side Pottery Outlet",
    "wof:placetype":"venue"
},
  "geometry": {"coordinates":[-76.483048,41.039969],"type":"Point"}
}