{
  "type": "Feature",
  "properties": {
    "iso:country":"US",
    "sg:address":"912 Diamond Park",
    "sg:city":"Meadville",
    "sg:classifiers":[
        {
            "category":"Social Services",
            "type":"Services"
        }
    ],
    "sg:phone":"+1 814 724 8589",
    "sg:postcode":"16335",
    "sg:province":"PA",
    "sg:tags":[
        "organization",
        "welfare"
    ],
    "wof:name":"Big Brothers & Big Sisters",
    "wof:placetype":"venue"
},
  "geometry": {"coordinates":[-80.150555,41.638248],"type":"Point"}
}