{
  "type": "Feature",
  "properties": {
    "iso:country":"US",
    "sg:address":"1129 Avalon Pkwy",
    "sg:city":"Williamsport",
    "sg:classifiers":[
        {
            "category":"Health Services",
            "subcategory":"Doctor",
            "type":"Services"
        }
    ],
    "sg:phone":"+1 570 320 7318",
    "sg:postcode":"17701",
    "sg:province":"PA",
    "sg:tags":[
        "physician",
        "surgeon"
    ],
    "wof:name":"John Bailey MD",
    "wof:placetype":"venue"
},
  "geometry": {"coordinates":[-76.999313,41.269944],"type":"Point"}
}