{
  "type": "Feature",
  "properties": {
    "iso:country":"US",
    "sg:address":"5356A Baltimore Pike",
    "sg:city":"Littlestown",
    "sg:classifiers":[
        {
            "category":"Insurance",
            "subcategory":"Hazard Insurance",
            "type":"Services"
        },
        {
            "category":"Insurance",
            "subcategory":"Insurance Agent",
            "type":"Services"
        },
        {
            "category":"Insurance",
            "subcategory":"Life Insurance",
            "type":"Services"
        },
        {
            "category":"Insurance",
            "subcategory":"Title Insurance",
            "type":"Services"
        }
    ],
    "sg:phone":"+1 717 359 7380",
    "sg:postcode":"17340",
    "sg:province":"PA",
    "sg:tags":[
        "auto",
        "homeowner"
    ],
    "sg:website":"http://www.nationwide.com/agent/Littlestown-PENNSYLVANIA-insurance-agent/john-adamik/office.html",
    "wof:name":"Adamik Insurance Agy Inc - Nationwide Insurance",
    "wof:placetype":"venue"
},
  "geometry": {"coordinates":[-77.095338,39.752149],"type":"Point"}
}