{
  "type": "Feature",
  "properties": {
    "addr:full":"896 Grim Rd Kutztown PA 19530",
    "addr:housenumber":"896",
    "addr:postcode":"19530",
    "addr:street":"Grim Rd",
    "iso:country":"US",
    "sg:address":"896 Grim Rd",
    "sg:city":"Kutztown",
    "sg:classifiers":[
        {
            "category":"Building & Trades",
            "subcategory":"Construction",
            "type":"Services"
        }
    ],
    "sg:phone":"+1   ",
    "sg:postcode":"19530",
    "sg:province":"PA",
    "sg:tags":[
        "house"
    ],
    "wof:name":"Warren H Ziegler",
    "wof:placetype":"venue"
},
  "geometry": {"coordinates":[-75.704663,40.545214],"type":"Point"}
}