{
  "type": "Feature",
  "properties": {
    "addr:full":"1700 S Broad St Philadelphia PA 19145",
    "addr:housenumber":"1700",
    "addr:postcode":"19145",
    "addr:street":"S Broad St",
    "iso:country":"US",
    "sg:address":"1700 S Broad St",
    "sg:city":"Philadelphia",
    "sg:classifiers":[
        {
            "category":"Shopping",
            "subcategory":"News",
            "type":"Retail Goods"
        }
    ],
    "sg:phone":"+1   ",
    "sg:postcode":"19145",
    "sg:province":"PA",
    "wof:name":"Pierantozzi Theresa",
    "wof:placetype":"venue"
},
  "geometry": {"coordinates":[-75.168819,39.928658],"type":"Point"}
}