{
  "type": "Feature",
  "properties": {
    "iso:country":"US",
    "sg:address":"18 Allegheny Sq",
    "sg:city":"Glassport",
    "sg:classifiers":[
        {
            "category":"Freight",
            "type":"Transportation"
        }
    ],
    "sg:phone":"+1 412 675 1000",
    "sg:postcode":"15045",
    "sg:province":"PA",
    "sg:tags":[
        "wooden",
        "box",
        "mfg"
    ],
    "wof:name":"Export Boxing & Crating Inc",
    "wof:placetype":"venue"
},
  "geometry": {"coordinates":[-79.892365,40.320886],"type":"Point"}
}