{
  "type": "Feature",
  "properties": {
    "addr:full":"4500 Westminster Ave Philadelphia PA 19131",
    "addr:housenumber":"4500",
    "addr:postcode":"19131",
    "addr:street":"Westminster Ave",
    "iso:country":"US",
    "sg:address":"4500 Westminster Ave",
    "sg:city":"Philadelphia",
    "sg:classifiers":[
        {
            "category":"Organizations",
            "subcategory":"Religious Organization",
            "type":"Services"
        }
    ],
    "sg:phone":"+1 215 883 1500",
    "sg:postcode":"19131",
    "sg:province":"PA",
    "sg:tags":[
        "church"
    ],
    "wof:name":"Peoples Deliverance Church",
    "wof:placetype":"venue"
},
  "geometry": {"coordinates":[-75.21384399999999,39.969288],"type":"Point"}
}