{
  "type": "Feature",
  "properties": {
    "addr:full":"375 Berry Rd Washington PA 15301",
    "addr:housenumber":"375",
    "addr:postcode":"15301",
    "addr:street":"Berry Rd",
    "iso:country":"US",
    "sg:address":"375 Berry Rd",
    "sg:city":"Washington",
    "sg:classifiers":[
        {
            "category":"Recreation",
            "type":"Entertainment"
        }
    ],
    "sg:phone":"+1   ",
    "sg:postcode":"15301",
    "sg:province":"PA",
    "sg:tags":[
        "range",
        "golf",
        "driving"
    ],
    "wof:name":"Tower Driving Range",
    "wof:placetype":"venue"
},
  "geometry": {"coordinates":[-80.22808499999999,40.189493],"type":"Point"}
}