{
  "type": "Feature",
  "properties": {
    "addr:full":"106 Weymouth Cir Lansdale PA 19446",
    "addr:housenumber":"106",
    "addr:postcode":"19446",
    "addr:street":"Weymouth Cir",
    "iso:country":"US",
    "sg:address":"106 Weymouth Cir",
    "sg:city":"Lansdale",
    "sg:phone":"+1   ",
    "sg:postcode":"19446",
    "sg:province":"PA",
    "sg:tags":[
        "equipment",
        "commercial"
    ],
    "wof:name":"Appel Services",
    "wof:placetype":"venue"
},
  "geometry": {"coordinates":[-75.233355,40.250724],"type":"Point"}
}