{
  "type": "Feature",
  "properties": {
    "iso:country":"US",
    "sg:address":"1375 Washington Pike",
    "sg:city":"Bridgeville",
    "sg:classifiers":[
        {
            "category":"Museum",
            "type":"Entertainment"
        }
    ],
    "sg:phone":"+1 412 221 0348",
    "sg:postcode":"15017",
    "sg:province":"PA",
    "wof:name":"Woodville Plantation Home Of",
    "wof:placetype":"venue"
},
  "geometry": {"coordinates":[-80.09578399999999,40.379712],"type":"Point"}
}