{
  "type": "Feature",
  "properties": {
    "addr:full":"407 22nd St Windber PA 15963",
    "addr:housenumber":"407",
    "addr:postcode":"15963",
    "addr:street":"22Nd St",
    "iso:country":"US",
    "sg:address":"407 22nd St",
    "sg:city":"Windber",
    "sg:classifiers":[
        {
            "category":"Organizations",
            "subcategory":"Professional Association",
            "type":"Services"
        }
    ],
    "sg:phone":"+1 814 467 8656",
    "sg:postcode":"15963",
    "sg:province":"PA",
    "sg:tags":[
        "business"
    ],
    "wof:name":"Abbruzzi Lodge",
    "wof:placetype":"venue"
},
  "geometry": {"coordinates":[-78.825614,40.230506],"type":"Point"}
}