{
  "type": "Feature",
  "properties": {
    "addr:full":"23 Sunrise Ln Pittston PA 18640",
    "addr:housenumber":"23",
    "addr:postcode":"18640",
    "addr:street":"Sunrise Ln",
    "iso:country":"US",
    "sg:address":"23 Sunrise Ln",
    "sg:city":"Pittston",
    "sg:classifiers":[
        {
            "category":"Real Estate",
            "subcategory":"Real Estate Agent",
            "type":"Services"
        }
    ],
    "sg:phone":"+1   ",
    "sg:postcode":"18640",
    "sg:province":"PA",
    "wof:name":"Walker Realty",
    "wof:placetype":"venue"
},
  "geometry": {"coordinates":[-75.775178,41.326301],"type":"Point"}
}