{
  "type": "Feature",
  "properties": {
    "iso:country":"US",
    "sg:address":"1177 S 6th St",
    "sg:city":"Indiana",
    "sg:classifiers":[
        {
            "category":"Health Services",
            "subcategory":"Doctor",
            "type":"Services"
        }
    ],
    "sg:phone":"+1   ",
    "sg:postcode":"15701",
    "sg:province":"PA",
    "wof:name":"Dr Raemore & Dr Brumbaugh DMD",
    "wof:placetype":"venue"
},
  "geometry": {"coordinates":[-79.14678000000001,40.600638],"type":"Point"}
}