{
  "type": "Feature",
  "properties": {
    "addr:full":"1165 Meadowbrook Cir W Allentown PA 18103",
    "addr:housenumber":"1165",
    "addr:postcode":"18103",
    "addr:street":"Meadowbrook Cir W",
    "iso:country":"US",
    "sg:address":"1165 Meadowbrook Cir W",
    "sg:city":"Allentown",
    "sg:classifiers":[
        {
            "category":"Organizations",
            "subcategory":"Religious Organization",
            "type":"Services"
        }
    ],
    "sg:phone":"+1 610 820 5065",
    "sg:postcode":"18103",
    "sg:province":"PA",
    "sg:tags":[
        "clergy"
    ],
    "wof:name":"David G Volk",
    "wof:placetype":"venue"
},
  "geometry": {"coordinates":[-75.51473799999999,40.569979],"type":"Point"}
}