{
  "type": "Feature",
  "properties": {
    "iso:country":"US",
    "sg:address":"2959 Roosevelt Dr",
    "sg:city":"Chambersburg",
    "sg:classifiers":[
        {
            "category":"Wholesale",
            "subcategory":"Plants",
            "type":"Manufacturing & Wholesale Goods"
        }
    ],
    "sg:phone":"+1   ",
    "sg:postcode":"17201",
    "sg:province":"PA",
    "sg:tags":[
        "supply"
    ],
    "wof:name":"American Rose Society",
    "wof:placetype":"venue"
},
  "geometry": {"coordinates":[-77.63328,39.977023],"type":"Point"}
}