{
  "type": "Feature",
  "properties": {
    "iso:country":"US",
    "sg:address":"2101 Mack Blvd",
    "sg:city":"Allentown",
    "sg:classifiers":[
        {
            "category":"Organizations",
            "subcategory":"Labor Organization",
            "type":"Services"
        }
    ],
    "sg:phone":"+1 610 797 7720",
    "sg:postcode":"18103",
    "sg:province":"PA",
    "sg:website":"www.uaw677.org",
    "wof:name":"UAW",
    "wof:placetype":"venue"
},
  "geometry": {"coordinates":[-75.470682,40.574008],"type":"Point"}
}