{
  "type": "Feature",
  "properties": {
    "iso:country":"US",
    "sg:address":"6707 Old York Rd",
    "sg:city":"Philadelphia",
    "sg:classifiers":[
        {
            "category":"Education",
            "subcategory":"School",
            "type":"Public Place"
        }
    ],
    "sg:phone":"+1 215 927 7770",
    "sg:postcode":"19126",
    "sg:province":"PA",
    "sg:tags":[
        "high"
    ],
    "wof:name":"Hope Church School The",
    "wof:placetype":"venue"
},
  "geometry": {"coordinates":[-75.140748,40.055027],"type":"Point"}
}