{
  "type": "Feature",
  "properties": {
    "iso:country":"US",
    "sg:address":"3521 Sheffield St",
    "sg:city":"Philadelphia",
    "sg:classifiers":[
        {
            "category":"Manufacturing",
            "subcategory":"Printing",
            "type":"Manufacturing & Wholesale Goods"
        }
    ],
    "sg:phone":"+1   ",
    "sg:postcode":"19136",
    "sg:province":"PA",
    "sg:tags":[
        "commercial"
    ],
    "wof:name":"Dooltech Inc",
    "wof:placetype":"venue"
},
  "geometry": {"coordinates":[-75.033579,40.039877],"type":"Point"}
}