{
  "type": "Feature",
  "properties": {
    "addr:full":"305 Tavistock Dr Royersford PA 19468",
    "addr:housenumber":"305",
    "addr:postcode":"19468",
    "addr:street":"Tavistock Dr",
    "iso:country":"US",
    "sg:address":"305 Tavistock Dr",
    "sg:city":"Royersford",
    "sg:classifiers":[
        {
            "category":"Professional",
            "type":"Services"
        }
    ],
    "sg:phone":"+1   ",
    "sg:postcode":"19468",
    "sg:province":"PA",
    "wof:name":"Philadelphia Meridian Users",
    "wof:placetype":"venue"
},
  "geometry": {"coordinates":[-75.544799,40.202047],"type":"Point"}
}