{
  "type": "Feature",
  "properties": {
    "addr:full":"66 S County Line Rd Souderton PA 18964",
    "addr:housenumber":"66",
    "addr:postcode":"18964",
    "addr:street":"S County Line Rd",
    "iso:country":"US",
    "sg:address":"66 S County Line Rd",
    "sg:city":"Souderton",
    "sg:classifiers":[
        {
            "category":"Real Estate",
            "subcategory":"Real Estate Operator",
            "type":"Services"
        }
    ],
    "sg:phone":"+1   ",
    "sg:postcode":"18964",
    "sg:province":"PA",
    "sg:tags":[
        "mobile",
        "home",
        "site"
    ],
    "wof:name":"Hidden Spring Realty Inc",
    "wof:placetype":"venue"
},
  "geometry": {"coordinates":[-75.307761,40.312662],"type":"Point"}
}