{
  "type": "Feature",
  "properties": {
    "iso:country":"US",
    "sg:address":"106 Main St W",
    "sg:city":"Rural Valley",
    "sg:classifiers":[
        {
            "category":"Restaurant",
            "type":"Food & Drink"
        }
    ],
    "sg:phone":"+1 724 783 2299",
    "sg:postcode":"16249",
    "sg:province":"PA",
    "wof:name":"Dimaio Ristorante",
    "wof:placetype":"venue"
},
  "geometry": {"coordinates":[-79.329301,40.799817],"type":"Point"}
}