{
  "type": "Feature",
  "properties": {
    "iso:country":"US",
    "sg:address":"2100 Lake St",
    "sg:city":"Lake City",
    "sg:classifiers":[
        {
            "category":"Professional",
            "subcategory":"Accounting & Tax Preparation",
            "type":"Services"
        }
    ],
    "sg:phone":"+1 814 774 2931",
    "sg:postcode":"16423",
    "sg:province":"PA",
    "sg:tags":[
        "bookkeeping",
        "general"
    ],
    "wof:name":"Chase Accounting Svc",
    "wof:placetype":"venue"
},
  "geometry": {"coordinates":[-80.34540800000001,42.014239],"type":"Point"}
}