{
  "type": "Feature",
  "properties": {
    "iso:country":"US",
    "sg:address":"240 E Montana St",
    "sg:city":"Philadelphia",
    "sg:classifiers":[
        {
            "category":"Freight",
            "type":"Transportation"
        }
    ],
    "sg:phone":"+1   ",
    "sg:postcode":"19119",
    "sg:province":"PA",
    "wof:name":"Look At ME Now Moving",
    "wof:placetype":"venue"
},
  "geometry": {"coordinates":[-75.18001599999999,40.053831],"type":"Point"}
}