{
  "type": "Feature",
  "properties": {
    "iso:country":"US",
    "sg:address":"7968 Dungan Rd",
    "sg:city":"Philadelphia",
    "sg:classifiers":[
        {
            "category":"Freight",
            "type":"Transportation"
        }
    ],
    "sg:phone":"+1 215 342 5299",
    "sg:postcode":"19111",
    "sg:province":"PA",
    "sg:tags":[
        "warehouse",
        "self",
        "storage"
    ],
    "wof:name":"Louis Galasso",
    "wof:placetype":"venue"
},
  "geometry": {"coordinates":[-75.06904900000001,40.066633],"type":"Point"}
}