{
  "type": "Feature",
  "properties": {
    "addr:full":"822 N Broad St Philadelphia PA 19130",
    "addr:housenumber":"822",
    "addr:postcode":"19130",
    "addr:street":"N Broad St",
    "iso:country":"US",
    "sg:address":"822 N Broad St",
    "sg:city":"Philadelphia",
    "sg:classifiers":[
        {
            "category":"Bars & Pubs",
            "subcategory":"Sports Bar",
            "type":"Food & Drink"
        }
    ],
    "sg:phone":"+1 267 318 7689",
    "sg:postcode":"19130",
    "sg:province":"PA",
    "sg:website":"coossportsbar.com",
    "wof:name":"Coo's Sports Bar & Lounge",
    "wof:placetype":"venue"
},
  "geometry": {"coordinates":[-75.160515,39.968763],"type":"Point"}
}