{
  "type": "Feature",
  "properties": {
    "iso:country":"US",
    "sg:address":"123 W 10th St",
    "sg:city":"Erie",
    "sg:classifiers":[
        {
            "category":"Organizations",
            "subcategory":"Religious Organization",
            "type":"Services"
        }
    ],
    "sg:phone":"+1 814 459 4722",
    "sg:postcode":"16502",
    "sg:province":"PA",
    "sg:tags":[
        "church"
    ],
    "sg:website":"www.gfc-erie.org",
    "wof:name":"Grace Fellowship Church",
    "wof:placetype":"venue"
},
  "geometry": {"coordinates":[-80.0848,42.124627],"type":"Point"}
}