{
  "type": "Feature",
  "properties": {
    "iso:country":"US",
    "sg:address":"404 Main St",
    "sg:city":"Pennsburg",
    "sg:classifiers":[
        {
            "category":"Real Estate",
            "subcategory":"Real Estate Agent",
            "type":"Services"
        }
    ],
    "sg:phone":"+1 215 679 4200",
    "sg:postcode":"18073",
    "sg:province":"PA",
    "sg:tags":[
        "broker",
        "sales"
    ],
    "sg:website":"www.brodeandbrooks.com",
    "wof:name":"Brode & Brooks Realtors",
    "wof:placetype":"venue"
},
  "geometry": {"coordinates":[-75.496865,40.39822],"type":"Point"}
}