{
  "type": "Feature",
  "properties": {
    "addr:full":"505 E Pittsburgh St Greensburg PA 15601",
    "addr:housenumber":"505",
    "addr:postcode":"15601",
    "addr:street":"E Pittsburgh St",
    "iso:country":"US",
    "sg:address":"505 E Pittsburgh St",
    "sg:city":"Greensburg",
    "sg:classifiers":[
        {
            "category":"Retail",
            "subcategory":"Funeral Services",
            "type":"Services"
        }
    ],
    "sg:phone":"+1 724 834 1421",
    "sg:postcode":"15601",
    "sg:province":"PA",
    "wof:name":"Barnhart Funeral Home",
    "wof:placetype":"venue"
},
  "geometry": {"coordinates":[-79.533647,40.303197],"type":"Point"}
}