{
  "type": "Feature",
  "properties": {
    "iso:country":"US",
    "sg:address":"129 Birch St",
    "sg:city":"Kane",
    "sg:classifiers":[
        {
            "category":"Building & Trades",
            "subcategory":"Construction",
            "type":"Services"
        }
    ],
    "sg:phone":"+1   ",
    "sg:postcode":"16735",
    "sg:province":"PA",
    "sg:tags":[
        "house"
    ],
    "wof:name":"Milliron Small Construction",
    "wof:placetype":"venue"
},
  "geometry": {"coordinates":[-78.81778300000001,41.660041],"type":"Point"}
}