{
  "type": "Feature",
  "properties": {
    "addr:full":"412 S Tulpehocken Rd Reading PA 19601",
    "addr:housenumber":"412",
    "addr:postcode":"19601",
    "addr:street":"S Tulpehocken Rd",
    "iso:country":"US",
    "sg:address":"412 S Tulpehocken Rd",
    "sg:city":"Reading",
    "sg:classifiers":[
        {
            "category":"Professional",
            "subcategory":"Business Services",
            "type":"Services"
        }
    ],
    "sg:phone":"+1   ",
    "sg:postcode":"19601",
    "sg:province":"PA",
    "sg:tags":[
        "furniture"
    ],
    "wof:name":"Geri Huey Design",
    "wof:placetype":"venue"
},
  "geometry": {"coordinates":[-75.95429799999999,40.35789],"type":"Point"}
}