{
  "type": "Feature",
  "properties": {
    "iso:country":"US",
    "sg:address":"121 Long Rd",
    "sg:city":"Myerstown",
    "sg:classifiers":[
        {
            "category":"Farming",
            "subcategory":"Farm",
            "type":"Manufacturing & Wholesale Goods"
        }
    ],
    "sg:phone":"+1   ",
    "sg:postcode":"17048",
    "sg:province":"PA",
    "sg:tags":[
        "crop",
        "general"
    ],
    "wof:name":"Kenneth Grumbine",
    "wof:placetype":"venue"
},
  "geometry": {"coordinates":[-76.7654,40.601946],"type":"Point"}
}