{
  "type": "Feature",
  "properties": {
    "addr:full":"1250 Bethlehem Pike Hatfield PA 19440",
    "addr:housenumber":"1250",
    "addr:postcode":"19440",
    "addr:street":"Bethlehem Pike",
    "iso:country":"US",
    "sg:address":"1250 Bethlehem Pike",
    "sg:city":"Hatfield",
    "sg:classifiers":[
        {
            "category":"Restaurant",
            "type":"Food & Drink"
        }
    ],
    "sg:menulink":"http://www.allmenus.com/pa/hatfield/241619-formosa/menu/",
    "sg:phone":"+1 215 822 7882",
    "sg:postcode":"19440",
    "sg:province":"PA",
    "sg:tags":[
        "asian",
        "chinese"
    ],
    "wof:name":"Formosa",
    "wof:placetype":"venue"
},
  "geometry": {"coordinates":[-75.265247,40.287303],"type":"Point"}
}