{
  "type": "Feature",
  "properties": {
    "addr:full":"2404 Milford Square Pike Quakertown PA 18951",
    "addr:housenumber":"2404",
    "addr:postcode":"18951",
    "addr:street":"Milford Square Pike",
    "iso:country":"US",
    "sg:address":"2404 Milford Square Pike",
    "sg:city":"Quakertown",
    "sg:classifiers":[
        {
            "category":"Food & Beverages",
            "subcategory":"Groceries & Convenience Stores",
            "type":"Retail Goods"
        }
    ],
    "sg:phone":"+1   ",
    "sg:postcode":"18951",
    "sg:province":"PA",
    "sg:tags":[
        "station",
        "gasoline"
    ],
    "wof:name":"Q-Town Food Mart",
    "wof:placetype":"venue"
},
  "geometry": {"coordinates":[-75.384563,40.438793],"type":"Point"}
}