{
  "type": "Feature",
  "properties": {
    "iso:country":"US",
    "sg:address":"167 Ridge Blvd",
    "sg:city":"Brookhaven",
    "sg:classifiers":[
        {
            "category":"Real Estate",
            "subcategory":"Developer",
            "type":"Services"
        }
    ],
    "sg:phone":"+1 610 494 8627",
    "sg:postcode":"19015",
    "sg:province":"PA",
    "wof:name":"Pyramid Land Development Co",
    "wof:placetype":"venue"
},
  "geometry": {"coordinates":[-75.387494,39.874932],"type":"Point"}
}