{
  "type": "Feature",
  "properties": {
    "iso:country":"US",
    "sg:address":"601 Centre St",
    "sg:city":"Ashland",
    "sg:classifiers":[
        {
            "category":"Health Services",
            "subcategory":"Chiropractor",
            "type":"Services"
        }
    ],
    "sg:phone":"+1 570 875 1919",
    "sg:postcode":"17921",
    "sg:province":"PA",
    "wof:name":"W B Kenesky DC",
    "wof:placetype":"venue"
},
  "geometry": {"coordinates":[-76.34053299999999,40.782652],"type":"Point"}
}