{
  "type": "Feature",
  "properties": {
    "iso:country":"US",
    "sg:address":"7619 Saltsburg Rd",
    "sg:city":"Pittsburgh",
    "sg:classifiers":[
        {
            "category":"Health Services",
            "subcategory":"Doctor",
            "type":"Services"
        }
    ],
    "sg:phone":"+1 412 795 7717",
    "sg:postcode":"15239",
    "sg:province":"PA",
    "sg:tags":[
        "denture",
        "dentists-prosthodontists",
        "center"
    ],
    "wof:name":"Scott, Robert H Dmd",
    "wof:placetype":"venue"
},
  "geometry": {"coordinates":[-79.77762199999999,40.475666],"type":"Point"}
}