{
  "type": "Feature",
  "properties": {
    "iso:country":"US",
    "sg:address":"910 W Duncannon Ave",
    "sg:city":"Philadelphia",
    "sg:classifiers":[
        {
            "category":"Professional",
            "type":"Services"
        }
    ],
    "sg:phone":"+1 215 455 9783",
    "sg:postcode":"19141",
    "sg:province":"PA",
    "sg:tags":[
        "establishment"
    ],
    "wof:name":"Luckcash LLC",
    "wof:placetype":"venue"
},
  "geometry": {"coordinates":[-75.137692,40.031079],"type":"Point"}
}