{
  "type": "Feature",
  "properties": {
    "iso:country":"US",
    "sg:address":"505 Benyou Ln",
    "sg:city":"New Cumberland",
    "sg:classifiers":[
        {
            "category":"Restaurant",
            "type":"Food & Drink"
        }
    ],
    "sg:phone":"+1   ",
    "sg:postcode":"17070",
    "sg:province":"PA",
    "sg:tags":[
        "eating"
    ],
    "wof:name":"Whitehill Cafe Inc",
    "wof:placetype":"venue"
},
  "geometry": {"coordinates":[-76.85641200000001,40.184556],"type":"Point"}
}