{
  "type": "Feature",
  "properties": {
    "addr:full":"221 E High St Pottstown PA 19464",
    "addr:housenumber":"221",
    "addr:postcode":"19464",
    "addr:street":"E High St",
    "iso:country":"US",
    "sg:address":"221 E High St",
    "sg:city":"Pottstown",
    "sg:classifiers":[
        {
            "category":"Shopping",
            "subcategory":"Used Merchandise",
            "type":"Retail Goods"
        }
    ],
    "sg:phone":"+1   ",
    "sg:postcode":"19464",
    "sg:province":"PA",
    "wof:name":"Mc Carthys Used Furn & Antq",
    "wof:placetype":"venue"
},
  "geometry": {"coordinates":[-75.649693,40.245669],"type":"Point"}
}