{
  "type": "Feature",
  "properties": {
    "addr:full":"149 N Fourth St Telford PA 18969",
    "addr:housenumber":"149",
    "addr:postcode":"18969",
    "addr:street":"N Fourth",
    "iso:country":"US",
    "sg:address":"149 N Fourth St",
    "sg:city":"Telford",
    "sg:classifiers":[
        {
            "category":"Real Estate",
            "subcategory":"Real Estate Operator",
            "type":"Services"
        }
    ],
    "sg:phone":"+1 215 723 6115",
    "sg:postcode":"18969",
    "sg:province":"PA",
    "sg:tags":[
        "apartment"
    ],
    "wof:name":"Telford Garden Apartments",
    "wof:placetype":"venue"
},
  "geometry": {"coordinates":[-75.334721,40.320505],"type":"Point"}
}