{
  "type": "Feature",
  "properties": {
    "iso:country":"US",
    "sg:address":"5641 Peach St",
    "sg:city":"Erie",
    "sg:classifiers":[
        {
            "category":"Home & Garden",
            "subcategory":"Furniture",
            "type":"Retail Goods"
        }
    ],
    "sg:phone":"+1 814 868 1911",
    "sg:postcode":"16509",
    "sg:province":"PA",
    "sg:tags":[
        "equipment",
        "cabinet",
        "work",
        "kitchen",
        "custom"
    ],
    "wof:name":"Amish Kitchens Plus Inc",
    "wof:placetype":"venue"
},
  "geometry": {"coordinates":[-80.09353900000001,42.073607],"type":"Point"}
}