{
  "type": "Feature",
  "properties": {
    "iso:country":"US",
    "sg:address":"1708 Lynbrooke Dr",
    "sg:city":"Morrisville",
    "sg:classifiers":[
        {
            "category":"Health Services",
            "subcategory":"Doctor",
            "type":"Services"
        }
    ],
    "sg:phone":"+1   ",
    "sg:postcode":"19067",
    "sg:province":"PA",
    "sg:tags":[
        "medical"
    ],
    "wof:name":"Suburban Orthopedics",
    "wof:placetype":"venue"
},
  "geometry": {"coordinates":[-74.877461,40.207898],"type":"Point"}
}