{
  "type": "Feature",
  "properties": {
    "iso:country":"US",
    "sg:address":"1516 Greentree Rd",
    "sg:city":"Pittsburgh",
    "sg:classifiers":[
        {
            "category":"Shopping",
            "subcategory":"Music",
            "type":"Retail Goods"
        }
    ],
    "sg:phone":"+1   ",
    "sg:postcode":"15220",
    "sg:province":"PA",
    "wof:name":"Greyko Recording Co Inc",
    "wof:placetype":"venue"
},
  "geometry": {"coordinates":[-80.063197,40.401303],"type":"Point"}
}