{
  "type": "Feature",
  "properties": {
    "iso:country":"US",
    "sg:address":"955 Reedsdale St",
    "sg:city":"Pittsburgh",
    "sg:classifiers":[
        {
            "category":"Freight",
            "type":"Transportation"
        }
    ],
    "sg:phone":"+1   ",
    "sg:postcode":"15212",
    "sg:province":"PA",
    "sg:tags":[
        "distance",
        "long",
        "trucking"
    ],
    "wof:name":"Liberty Transportation Inc",
    "wof:placetype":"venue"
},
  "geometry": {"coordinates":[-80.01675400000001,40.448142],"type":"Point"}
}