{
  "type": "Feature",
  "properties": {
    "iso:country":"US",
    "sg:address":"767 Sandra Ln",
    "sg:city":"Norristown",
    "sg:classifiers":[
        {
            "category":"Wholesale",
            "subcategory":"Computers",
            "type":"Manufacturing & Wholesale Goods"
        }
    ],
    "sg:phone":"+1 610 635 0330",
    "sg:postcode":"19403",
    "sg:province":"PA",
    "sg:tags":[
        "equipment"
    ],
    "sg:website":"http://www.amcandassociates.net/",
    "wof:name":"Amc",
    "wof:placetype":"venue"
},
  "geometry": {"coordinates":[-75.35685599999999,40.149677],"type":"Point"}
}