{
  "type": "Feature",
  "properties": {
    "addr:full":"420 Wood St Pittsburgh PA 15222",
    "addr:housenumber":"420",
    "addr:postcode":"15222",
    "addr:street":"Wood St",
    "iso:country":"US",
    "sg:address":"420 Wood St",
    "sg:city":"Pittsburgh",
    "sg:classifiers":[
        {
            "category":"Health Services",
            "subcategory":"Optometrist",
            "type":"Services"
        },
        {
            "category":"Shopping",
            "subcategory":"Optician",
            "type":"Retail Goods"
        }
    ],
    "sg:phone":"+1 412 281 6891",
    "sg:postcode":"15222",
    "sg:province":"PA",
    "sg:tags":[
        "eyewear"
    ],
    "wof:name":"Diamond Edward J Optometrist",
    "wof:placetype":"venue"
},
  "geometry": {"coordinates":[-80.000702,40.439999],"type":"Point"}
}