{
  "type": "Feature",
  "properties": {
    "addr:full":"315 N Point Dr Pittsburgh PA 15233",
    "addr:housenumber":"315",
    "addr:postcode":"15233",
    "addr:street":"N Point Dr",
    "iso:country":"US",
    "sg:address":"315 N Point Dr",
    "sg:city":"Pittsburgh",
    "sg:classifiers":[
        {
            "category":"Wholesale",
            "subcategory":"Electrical",
            "type":"Manufacturing & Wholesale Goods"
        }
    ],
    "sg:phone":"+1   ",
    "sg:postcode":"15233",
    "sg:province":"PA",
    "sg:tags":[
        "equipment"
    ],
    "wof:name":"Mosebach Electric & Supply",
    "wof:placetype":"venue"
},
  "geometry": {"coordinates":[-80.026546,40.448211],"type":"Point"}
}