{
  "type": "Feature",
  "properties": {
    "iso:country":"US",
    "sg:address":"2141 Cottman Ave",
    "sg:city":"Philadelphia",
    "sg:classifiers":[
        {
            "category":"Shopping",
            "subcategory":"Shoes",
            "type":"Retail Goods"
        }
    ],
    "sg:phone":"+1 215 725 7463",
    "sg:postcode":"19149",
    "sg:province":"PA",
    "sg:tags":[
        "store"
    ],
    "wof:name":"Feet First, Inc",
    "wof:placetype":"venue"
},
  "geometry": {"coordinates":[-75.06356,40.049809],"type":"Point"}
}