{
  "type": "Feature",
  "properties": {
    "addr:full":"9 N 3rd St Philadelphia PA 19106",
    "addr:housenumber":"9",
    "addr:postcode":"19106",
    "addr:street":"N 3Rd St",
    "iso:country":"US",
    "sg:address":"9 N 3rd St",
    "sg:city":"Philadelphia",
    "sg:classifiers":[
        {
            "category":"Building & Trades",
            "subcategory":"Locksmith",
            "type":"Services"
        }
    ],
    "sg:phone":"+1 267 502 2027",
    "sg:postcode":"19106",
    "sg:province":"PA",
    "sg:tags":[
        "lock",
        "industrial",
        "locksmiths-commercial"
    ],
    "wof:name":"Philadelphia Locksmith",
    "wof:placetype":"venue"
},
  "geometry": {"coordinates":[-75.14560400000001,39.95054],"type":"Point"}
}