{
  "type": "Feature",
  "properties": {
    "iso:country":"US",
    "sg:address":"189 Ridgeview Rd S",
    "sg:city":"Elizabethtown",
    "sg:classifiers":[
        {
            "category":"Banks & Credit Unions",
            "subcategory":"Financial Services",
            "type":"Services"
        }
    ],
    "sg:phone":"+1   ",
    "sg:postcode":"17022",
    "sg:province":"PA",
    "sg:tags":[
        "co",
        "holding",
        "real estate"
    ],
    "wof:name":"Sweigart Partnership",
    "wof:placetype":"venue"
},
  "geometry": {"coordinates":[-76.571709,40.160569],"type":"Point"}
}