{
  "type": "Feature",
  "properties": {
    "iso:country":"US",
    "sg:address":"1433 N 2nd St",
    "sg:city":"Harrisburg",
    "sg:classifiers":[
        {
            "category":"Health Services",
            "subcategory":"Doctor",
            "type":"Services"
        }
    ],
    "sg:phone":"+1 717 234 4674",
    "sg:postcode":"17102",
    "sg:province":"PA",
    "sg:tags":[
        "medical"
    ],
    "wof:name":"Maingi Naresh MD",
    "wof:placetype":"venue"
},
  "geometry": {"coordinates":[-76.892601,40.2701],"type":"Point"}
}