{
  "type": "Feature",
  "properties": {
    "addr:full":"504 N Wales Rd North Wales PA 19454",
    "addr:housenumber":"504",
    "addr:postcode":"19454",
    "addr:street":"N Wales Rd",
    "iso:country":"US",
    "sg:address":"504 N Wales Rd",
    "sg:city":"North Wales",
    "sg:classifiers":[
        {
            "category":"Building & Trades",
            "subcategory":"Plumbing",
            "type":"Services"
        }
    ],
    "sg:phone":"+1   ",
    "sg:postcode":"19454",
    "sg:province":"PA",
    "sg:tags":[
        "plumbing",
        "heating",
        "air"
    ],
    "wof:name":"A T Chadwick Co Inc",
    "wof:placetype":"venue"
},
  "geometry": {"coordinates":[-75.282183,40.206264],"type":"Point"}
}