{
  "type": "Feature",
  "properties": {
    "iso:country":"US",
    "sg:address":"660 Newtown Yardley Rd",
    "sg:city":"Newtown",
    "sg:classifiers":[
        {
            "category":"Social Services",
            "type":"Services"
        }
    ],
    "sg:phone":"+1   ",
    "sg:postcode":"18940",
    "sg:province":"PA",
    "wof:name":"John D Rosella",
    "wof:placetype":"venue"
},
  "geometry": {"coordinates":[-74.920698,40.229268],"type":"Point"}
}