{
  "type": "Feature",
  "properties": {
    "iso:country":"US",
    "sg:address":"106 Mazza St",
    "sg:city":"Homer City",
    "sg:classifiers":[
        {
            "category":"Building & Trades",
            "subcategory":"Construction",
            "type":"Services"
        }
    ],
    "sg:phone":"+1   ",
    "sg:postcode":"15748",
    "sg:province":"PA",
    "sg:tags":[
        "house"
    ],
    "wof:name":"Mumau Building & Remodeling Co",
    "wof:placetype":"venue"
},
  "geometry": {"coordinates":[-79.158361,40.547561],"type":"Point"}
}