{
  "type": "Feature",
  "properties": {
    "iso:country":"US",
    "sg:address":"RR 1",
    "sg:city":"Vanderbilt",
    "sg:classifiers":[
        {
            "category":"Personal",
            "type":"Services"
        },
        {
            "category":"Retail",
            "subcategory":"Auto Repair",
            "type":"Services"
        }
    ],
    "sg:phone":"+1 724 529 7800",
    "sg:postcode":"15486",
    "sg:province":"PA",
    "sg:tags":[
        "towing"
    ],
    "wof:name":"Roger's Auto Service",
    "wof:placetype":"venue"
},
  "geometry": {"coordinates":[-79.714996,40.030399],"type":"Point"}
}