{
  "type": "Feature",
  "properties": {
    "iso:country":"US",
    "sg:address":"1908 Shumaker Rd",
    "sg:city":"Manheim",
    "sg:classifiers":[
        {
            "category":"Farming",
            "subcategory":"Poultry Farm",
            "type":"Manufacturing & Wholesale Goods"
        }
    ],
    "sg:phone":"+1   ",
    "sg:postcode":"17545",
    "sg:province":"PA",
    "sg:tags":[
        "egg"
    ],
    "wof:name":"Lamar Zimmerman",
    "wof:placetype":"venue"
},
  "geometry": {"coordinates":[-76.44421800000001,40.186479],"type":"Point"}
}