{
  "type": "Feature",
  "properties": {
    "iso:country":"US",
    "sg:address":"2969 Old Tree Dr",
    "sg:city":"Lancaster",
    "sg:classifiers":[
        {
            "category":"Wholesale",
            "subcategory":"Machinery & Supplies",
            "type":"Manufacturing & Wholesale Goods"
        }
    ],
    "sg:phone":"+1 717 295 1800",
    "sg:postcode":"17603",
    "sg:province":"PA",
    "sg:tags":[
        "equipment",
        "material",
        "handling",
        "lease"
    ],
    "sg:website":"www.liftincorporated.com",
    "wof:name":"Lift Inc",
    "wof:placetype":"venue"
},
  "geometry": {"coordinates":[-76.39075,40.049586],"type":"Point"}
}