{
  "type": "Feature",
  "properties": {
    "addr:full":"1321 Roosevelt Rd Pittsburgh PA 15237",
    "addr:housenumber":"1321",
    "addr:postcode":"15237",
    "addr:street":"Roosevelt Rd",
    "iso:country":"US",
    "sg:address":"1321 Roosevelt Rd",
    "sg:city":"Pittsburgh",
    "sg:phone":"+1   ",
    "sg:postcode":"15237",
    "sg:province":"PA",
    "sg:tags":[
        "farm",
        "grain",
        "cash"
    ],
    "wof:name":"Paul Reismier",
    "wof:placetype":"venue"
},
  "geometry": {"coordinates":[-80.09535700000001,40.540945],"type":"Point"}
}