{
  "type": "Feature",
  "properties": {
    "addr:full":"451 W Chew St Ste 301 Allentown PA 18102",
    "addr:housenumber":"451",
    "addr:postcode":"18102",
    "addr:street":"W Chew St Ste 301",
    "iso:country":"US",
    "sg:address":"451 W Chew St Ste 301",
    "sg:city":"Allentown",
    "sg:classifiers":[
        {
            "category":"Health Services",
            "subcategory":"Doctor",
            "type":"Services"
        }
    ],
    "sg:phone":"+1 610 434 4445",
    "sg:postcode":"18102",
    "sg:province":"PA",
    "wof:name":"Terreros Pavel",
    "wof:placetype":"venue"
},
  "geometry": {"coordinates":[-75.46939500000001,40.607743],"type":"Point"}
}