{
  "type": "Feature",
  "properties": {
    "iso:country":"US",
    "sg:address":"933 Mason Ave",
    "sg:city":"Drexel Hill",
    "sg:classifiers":[
        {
            "category":"Building & Trades",
            "subcategory":"Plumbing",
            "type":"Services"
        }
    ],
    "sg:phone":"+1 610 446 0233",
    "sg:postcode":"19026",
    "sg:province":"PA",
    "sg:tags":[
        "conditioning",
        "air",
        "system",
        "contractor"
    ],
    "wof:name":"Ryan Heating & Air Cond",
    "wof:placetype":"venue"
},
  "geometry": {"coordinates":[-75.304216,39.956755],"type":"Point"}
}