{
  "type": "Feature",
  "properties": {
    "iso:country":"US",
    "sg:address":"1513 Scalp Ave",
    "sg:city":"Johnstown",
    "sg:classifiers":[
        {
            "category":"Health Services",
            "subcategory":"Optometrist",
            "type":"Services"
        }
    ],
    "sg:phone":"+1 814 266 7611",
    "sg:postcode":"15904",
    "sg:province":"PA",
    "sg:tags":[
        "optical",
        "merchandise",
        "g"
    ],
    "wof:name":"Johnstown Family Vision",
    "wof:placetype":"venue"
},
  "geometry": {"coordinates":[-78.857291,40.270103],"type":"Point"}
}