{
  "type": "Feature",
  "properties": {
    "iso:country":"US",
    "sg:address":"3602 Chestnut St",
    "sg:city":"Philadelphia",
    "sg:classifiers":[
        {
            "category":"Cafe",
            "type":"Food & Drink"
        }
    ],
    "sg:menulink":"http://www.allmenus.com/pa/philadelphia/19847-cafe-rustica/menu/",
    "sg:phone":"+1 215 895 3490",
    "sg:postcode":"19104",
    "sg:province":"PA",
    "sg:tags":[
        "sandwich",
        "salad",
        "soup",
        "american",
        "wrap",
        "pizza"
    ],
    "wof:name":"Cafe Rustica",
    "wof:placetype":"venue"
},
  "geometry": {"coordinates":[-75.194602,39.954636],"type":"Point"}
}