{
  "type": "Feature",
  "properties": {
    "iso:country":"US",
    "sg:address":"467 N Maple St",
    "sg:city":"Ephrata",
    "sg:classifiers":[
        {
            "category":"Animal Shelter",
            "type":"Public Place"
        },
        {
            "category":"Retail",
            "subcategory":"Pet Boarding",
            "type":"Services"
        },
        {
            "category":"Retail",
            "subcategory":"Animal Services",
            "type":"Services"
        },
        {
            "category":"Retail",
            "subcategory":"Veterinary Services",
            "type":"Services"
        }
    ],
    "sg:phone":"+1 717 738 3370",
    "sg:postcode":"17522",
    "sg:province":"PA",
    "sg:tags":[
        "kennel",
        "exercising",
        "specialty",
        "sitting"
    ],
    "sg:website":"http://www.petwatch-plus.com",
    "wof:name":"Petwatch Plus",
    "wof:placetype":"venue"
},
  "geometry": {"coordinates":[-76.164243,40.178478],"type":"Point"}
}