{
  "type": "Feature",
  "properties": {
    "iso:country":"US",
    "sg:address":"125 Briercliff Rd",
    "sg:city":"Beaver Falls",
    "sg:classifiers":[
        {
            "category":"Travel",
            "subcategory":"Campground",
            "type":"Entertainment"
        }
    ],
    "sg:phone":"+1   ",
    "sg:postcode":"15010",
    "sg:province":"PA",
    "sg:tags":[
        "basketball",
        "camp"
    ],
    "wof:name":"Drill For Skill Bsketball Camp",
    "wof:placetype":"venue"
},
  "geometry": {"coordinates":[-80.371174,40.772931],"type":"Point"}
}