{
  "type": "Feature",
  "properties": {
    "addr:full":"1589 Ulster Ln West Chester PA 19380",
    "addr:housenumber":"1589",
    "addr:postcode":"19380",
    "addr:street":"Ulster Ln",
    "iso:country":"US",
    "sg:address":"1589 Ulster Ln",
    "sg:city":"West Chester",
    "sg:classifiers":[
        {
            "category":"Manufacturing",
            "subcategory":"Printing",
            "type":"Manufacturing & Wholesale Goods"
        }
    ],
    "sg:phone":"+1   ",
    "sg:postcode":"19380",
    "sg:province":"PA",
    "sg:tags":[
        "publishing"
    ],
    "wof:name":"Merit Press",
    "wof:placetype":"venue"
},
  "geometry": {"coordinates":[-75.570986,40.001316],"type":"Point"}
}