{
  "type": "Feature",
  "properties": {
    "iso:country":"US",
    "sg:address":"43 N 9th St",
    "sg:city":"Allentown",
    "sg:classifiers":[
        {
            "category":"Professional",
            "subcategory":"Accounting & Tax Preparation",
            "type":"Services"
        }
    ],
    "sg:phone":"+1 610 432 7737",
    "sg:postcode":"18101",
    "sg:province":"PA",
    "sg:tags":[
        "return",
        "filing"
    ],
    "wof:name":"Colbert Ball Tax Svc",
    "wof:placetype":"venue"
},
  "geometry": {"coordinates":[-75.47605799999999,40.602592],"type":"Point"}
}