{
  "type": "Feature",
  "properties": {
    "iso:country":"US",
    "sg:address":"601 Penn Ave",
    "sg:city":"Pittsburgh",
    "sg:classifiers":[
        {
            "category":"Building & Trades",
            "subcategory":"Locksmith",
            "type":"Services"
        }
    ],
    "sg:phone":"+1 412 208 4041",
    "sg:postcode":"15222",
    "sg:province":"PA",
    "sg:tags":[
        "key"
    ],
    "wof:name":"Locksmith & Locks-24 7 Emergency",
    "wof:placetype":"venue"
},
  "geometry": {"coordinates":[-80.002235,40.442903],"type":"Point"}
}