{
  "type": "Feature",
  "properties": {
    "addr:full":"9987 Bustleton Ave Philadelphia PA 19115",
    "addr:housenumber":"9987",
    "addr:postcode":"19115",
    "addr:street":"Bustleton Ave",
    "iso:country":"US",
    "sg:address":"9987 Bustleton Ave",
    "sg:city":"Philadelphia",
    "sg:phone":"+1 215 464 7075",
    "sg:postcode":"19115",
    "sg:province":"PA",
    "wof:name":"Italomoda At Red Lion Incorporated",
    "wof:placetype":"venue"
},
  "geometry": {"coordinates":[-75.029348,40.101358],"type":"Point"}
}