{
  "type": "Feature",
  "properties": {
    "addr:full":"430 Reading Ave West Reading PA 19611",
    "addr:housenumber":"430",
    "addr:postcode":"19611",
    "addr:street":"Reading Ave",
    "iso:country":"US",
    "sg:address":"430 Reading Ave",
    "sg:city":"West Reading",
    "sg:classifiers":[
        {
            "category":"Health Services",
            "subcategory":"Clinic",
            "type":"Services"
        }
    ],
    "sg:phone":"+1 610 320 6140",
    "sg:postcode":"19611",
    "sg:province":"PA",
    "wof:name":"Healthcare Solutions LLC",
    "wof:placetype":"venue"
},
  "geometry": {"coordinates":[-75.946119,40.336462],"type":"Point"}
}