{
  "type": "Feature",
  "properties": {
    "addr:full":"1220 Mercer Grove City Rd Mercer PA 16137",
    "addr:housenumber":"1220",
    "addr:postcode":"16137",
    "addr:street":"Mercer Grove City Rd",
    "iso:country":"US",
    "sg:address":"1220 Mercer Grove City Rd",
    "sg:city":"Mercer",
    "sg:classifiers":[
        {
            "category":"Shopping",
            "subcategory":"Shoes",
            "type":"Retail Goods"
        }
    ],
    "sg:phone":"+1   ",
    "sg:postcode":"16137",
    "sg:province":"PA",
    "wof:name":"Adidas Outlet Inc",
    "wof:placetype":"venue"
},
  "geometry": {"coordinates":[-80.18781,41.205652],"type":"Point"}
}