{
  "type": "Feature",
  "properties": {
    "iso:country":"US",
    "sg:address":"2310 Weiss Rd",
    "sg:city":"Quakertown",
    "sg:classifiers":[
        {
            "category":"Wholesale",
            "subcategory":"Farm Supplies",
            "type":"Manufacturing & Wholesale Goods"
        }
    ],
    "sg:phone":"+1   ",
    "sg:postcode":"18951",
    "sg:province":"PA",
    "sg:tags":[
        "livestock"
    ],
    "wof:name":"Peter Weiss",
    "wof:placetype":"venue"
},
  "geometry": {"coordinates":[-75.415312,40.446422],"type":"Point"}
}