{
  "type": "Feature",
  "properties": {
    "addr:full":"113 E Water St Muncy PA 17756",
    "addr:housenumber":"113",
    "addr:postcode":"17756",
    "addr:street":"E Water St",
    "iso:country":"US",
    "sg:address":"113 E Water St",
    "sg:city":"Muncy",
    "sg:classifiers":[
        {
            "category":"Cinema",
            "subcategory":"Movie Rental",
            "type":"Entertainment"
        }
    ],
    "sg:phone":"+1 570 546 3145",
    "sg:postcode":"17756",
    "sg:province":"PA",
    "sg:tags":[
        "leasing",
        "video",
        "disc",
        "tape"
    ],
    "wof:name":"Movie Gallery",
    "wof:placetype":"venue"
},
  "geometry": {"coordinates":[-76.78308199999999,41.206181],"type":"Point"}
}