{
  "type": "Feature",
  "properties": {
    "iso:country":"US",
    "sg:address":"6445 Frankford Ave Ste 2",
    "sg:city":"Philadelphia",
    "sg:classifiers":[
        {
            "category":"Professional",
            "subcategory":"Detective & Security Services",
            "type":"Services"
        }
    ],
    "sg:phone":"+1 215 338 3995",
    "sg:postcode":"19135",
    "sg:province":"PA",
    "sg:tags":[
        "information",
        "bureau"
    ],
    "wof:name":"Alpha Card Svc",
    "wof:placetype":"venue"
},
  "geometry": {"coordinates":[-75.056642,40.029116],"type":"Point"}
}