{
  "type": "Feature",
  "properties": {
    "addr:full":"105 Reed St New Kensington PA 15068",
    "addr:housenumber":"105",
    "addr:postcode":"15068",
    "addr:street":"Reed St",
    "iso:country":"US",
    "sg:address":"105 Reed St",
    "sg:city":"New Kensington",
    "sg:classifiers":[
        {
            "category":"Building & Trades",
            "subcategory":"Construction",
            "type":"Services"
        }
    ],
    "sg:phone":"+1   ",
    "sg:postcode":"15068",
    "sg:province":"PA",
    "sg:tags":[
        "architectural",
        "contractor"
    ],
    "wof:name":"Farkas Joel A",
    "wof:placetype":"venue"
},
  "geometry": {"coordinates":[-79.74173999999999,40.589206],"type":"Point"}
}