{
  "type": "Feature",
  "properties": {
    "iso:country":"US",
    "sg:address":"185 Chamberlin Rd",
    "sg:city":"Shippensburg",
    "sg:classifiers":[
        {
            "category":"Organizations",
            "subcategory":"Religious Organization",
            "type":"Services"
        },
        {
            "category":"Arts & Performance",
            "subcategory":"Theater",
            "type":"Entertainment"
        }
    ],
    "sg:phone":"+1 717 532 2770",
    "sg:postcode":"17257",
    "sg:province":"PA",
    "sg:tags":[
        "group"
    ],
    "wof:name":"Willing Servants Ministries",
    "wof:placetype":"venue"
},
  "geometry": {"coordinates":[-77.547022,40.101422],"type":"Point"}
}