{
  "type": "Feature",
  "properties": {
    "iso:country":"US",
    "sg:address":"3823 Foxborough Ct",
    "sg:city":"Stroudsburg",
    "sg:classifiers":[
        {
            "category":"Professional",
            "subcategory":"Employment Agencies",
            "type":"Services"
        }
    ],
    "sg:phone":"+1   ",
    "sg:postcode":"18352",
    "sg:province":"PA",
    "sg:tags":[
        "help",
        "supply"
    ],
    "wof:name":"Transpol",
    "wof:placetype":"venue"
},
  "geometry": {"coordinates":[-75.311413,41.01695],"type":"Point"}
}