{
  "type": "Feature",
  "properties": {
    "iso:country":"US",
    "sg:address":"115 Brenckle Ln",
    "sg:city":"Evans City",
    "sg:classifiers":[
        {
            "category":"Professional",
            "subcategory":"Advertising",
            "type":"Services"
        }
    ],
    "sg:phone":"+1 724 898 3040",
    "sg:postcode":"16033",
    "sg:province":"PA",
    "sg:tags":[
        "distribution"
    ],
    "wof:name":"Winn First Class",
    "wof:placetype":"venue"
},
  "geometry": {"coordinates":[-80.036913,40.846344],"type":"Point"}
}