{
  "type": "Feature",
  "properties": {
    "addr:full":"1801 N 12th St Reading PA 19604",
    "addr:housenumber":"1801",
    "addr:postcode":"19604",
    "addr:street":"N 12Th St",
    "iso:country":"US",
    "sg:address":"1801 N 12th St",
    "sg:city":"Reading",
    "sg:classifiers":[
        {
            "category":"Manufacturing",
            "subcategory":"Textiles",
            "type":"Manufacturing & Wholesale Goods"
        }
    ],
    "sg:phone":"+1 610 939 9900",
    "sg:postcode":"19604",
    "sg:province":"PA",
    "sg:tags":[
        "material",
        "needlework"
    ],
    "wof:name":"Dimensions Inc",
    "wof:placetype":"venue"
},
  "geometry": {"coordinates":[-75.913416,40.363716],"type":"Point"}
}