{
  "type": "Feature",
  "properties": {
    "iso:country":"US",
    "sg:address":"397 Russell St",
    "sg:city":"Sharon",
    "sg:classifiers":[
        {
            "category":"Building & Trades",
            "subcategory":"Construction",
            "type":"Services"
        }
    ],
    "sg:phone":"+1 724 347 7082",
    "sg:postcode":"16146",
    "sg:province":"PA",
    "sg:tags":[
        "system",
        "specialty",
        "heating",
        "contractor",
        "air conditioning"
    ],
    "wof:name":"Knapp Heating & Cooling",
    "wof:placetype":"venue"
},
  "geometry": {"coordinates":[-80.516437,41.23922],"type":"Point"}
}