{
  "type": "Feature",
  "properties": {
    "iso:country":"US",
    "sg:address":"8405 Bull Rd",
    "sg:city":"Lewisberry",
    "sg:classifiers":[
        {
            "category":"Wholesale",
            "subcategory":"Durable Goods & Equipment",
            "type":"Manufacturing & Wholesale Goods"
        }
    ],
    "sg:phone":"+1 717 938 6595",
    "sg:postcode":"17339",
    "sg:province":"PA",
    "wof:name":"Campbell Logging & Firewood",
    "wof:placetype":"venue"
},
  "geometry": {"coordinates":[-76.86332400000001,40.116037],"type":"Point"}
}