{
  "type": "Feature",
  "properties": {
    "iso:country":"US",
    "sg:address":"101 5th St",
    "sg:city":"Freeport",
    "sg:classifiers":[
        {
            "category":"Organizations",
            "subcategory":"Community Association",
            "type":"Services"
        }
    ],
    "sg:phone":"+1   ",
    "sg:postcode":"16229",
    "sg:province":"PA",
    "wof:name":"Foe 1732",
    "wof:placetype":"venue"
},
  "geometry": {"coordinates":[-79.684843,40.672211],"type":"Point"}
}