{
  "type": "Feature",
  "properties": {
    "iso:country":"US",
    "sg:address":"514 W Southern Ave",
    "sg:city":"Williamsport",
    "sg:classifiers":[
        {
            "category":"Shopping",
            "subcategory":"Discount & Variety Stores",
            "type":"Retail Goods"
        }
    ],
    "sg:phone":"+1 570 321 8210",
    "sg:postcode":"17702",
    "sg:province":"PA",
    "wof:name":"Dollar General",
    "wof:placetype":"venue"
},
  "geometry": {"coordinates":[-77.001161,41.23125],"type":"Point"}
}