{
  "type": "Feature",
  "properties": {
    "iso:country":"US",
    "sg:address":"930 S 9th St",
    "sg:city":"Philadelphia",
    "sg:classifiers":[
        {
            "category":"Restaurant",
            "type":"Food & Drink"
        },
        {
            "category":"Food & Beverages",
            "subcategory":"Bakery",
            "type":"Retail Goods"
        },
        {
            "category":"Food & Beverages",
            "subcategory":"Cheese",
            "type":"Retail Goods"
        }
    ],
    "sg:phone":"+1 215 922 2876",
    "sg:postcode":"19147",
    "sg:province":"PA",
    "sg:tags":[
        "shop",
        "sandwich",
        "italian"
    ],
    "sg:website":"www.dibruno.com",
    "wof:name":"Di Bruno Bros",
    "wof:placetype":"venue"
},
  "geometry": {"coordinates":[-75.15809900000001,39.938309],"type":"Point"}
}