{
  "type": "Feature",
  "properties": {
    "iso:country":"US",
    "sg:address":"1819 John F Kennedy Blvd",
    "sg:city":"Philadelphia",
    "sg:classifiers":[
        {
            "category":"Professional",
            "subcategory":"Lawyer & Legal Services",
            "type":"Services"
        }
    ],
    "sg:phone":"+1 215 569 1904",
    "sg:postcode":"19103",
    "sg:province":"PA",
    "wof:name":"Acc Financial Corporation",
    "wof:placetype":"venue"
},
  "geometry": {"coordinates":[-75.169999,39.954371],"type":"Point"}
}