{
  "type": "Feature",
  "properties": {
    "addr:full":"77 D St Johnstown PA 15906",
    "addr:housenumber":"77",
    "addr:postcode":"15906",
    "addr:street":"D St",
    "iso:country":"US",
    "sg:address":"77 D St",
    "sg:city":"Johnstown",
    "sg:classifiers":[
        {
            "category":"Wholesale",
            "subcategory":"Meat",
            "type":"Manufacturing & Wholesale Goods"
        }
    ],
    "sg:phone":"+1 814 535 7694",
    "sg:postcode":"15906",
    "sg:province":"PA",
    "sg:tags":[
        "me",
        "mfg",
        "prepared"
    ],
    "wof:name":"Alex Froehlich Packing Co",
    "wof:placetype":"venue"
},
  "geometry": {"coordinates":[-78.944487,40.338937],"type":"Point"}
}