{
  "type": "Feature",
  "properties": {
    "iso:country":"US",
    "sg:address":"1011 Pine St",
    "sg:city":"Philadelphia",
    "sg:classifiers":[
        {
            "category":"Real Estate",
            "subcategory":"Real Estate Agent",
            "type":"Services"
        }
    ],
    "sg:phone":"+1   ",
    "sg:postcode":"19107",
    "sg:province":"PA",
    "wof:name":"Kelly Wolfington Associates",
    "wof:placetype":"venue"
},
  "geometry": {"coordinates":[-75.159651,39.944964],"type":"Point"}
}