{
  "type": "Feature",
  "properties": {
    "iso:country":"US",
    "sg:address":"935 Tire Hill Rd",
    "sg:city":"Johnstown",
    "sg:classifiers":[
        {
            "category":"Shopping",
            "type":"Retail Goods"
        }
    ],
    "sg:phone":"+1 814 288 1087",
    "sg:postcode":"15905",
    "sg:province":"PA",
    "sg:tags":[
        "monument"
    ],
    "wof:name":"Shetler Memorials Inc",
    "wof:placetype":"venue"
},
  "geometry": {"coordinates":[-78.912786,40.267081],"type":"Point"}
}