{
  "type": "Feature",
  "properties": {
    "addr:full":"806 N Henderson Rd King Of Prussia PA 19406",
    "addr:housenumber":"806",
    "addr:postcode":"19406",
    "addr:street":"N Henderson Rd",
    "iso:country":"US",
    "sg:address":"806 N Henderson Rd",
    "sg:city":"King Of Prussia",
    "sg:classifiers":[
        {
            "category":"Personal",
            "subcategory":"Tanning Parlor",
            "type":"Services"
        }
    ],
    "sg:phone":"+1 610 337 8826",
    "sg:postcode":"19406",
    "sg:province":"PA",
    "sg:tags":[
        "salon"
    ],
    "wof:name":"A Tropical Touch",
    "wof:placetype":"venue"
},
  "geometry": {"coordinates":[-75.37827799999999,40.114201],"type":"Point"}
}