{
  "type": "Feature",
  "properties": {
    "addr:full":"1401 W 4th St Williamsport PA 17701",
    "addr:housenumber":"1401",
    "addr:postcode":"17701",
    "addr:street":"W 4Th St",
    "iso:country":"US",
    "sg:address":"1401 W 4th St",
    "sg:city":"Williamsport",
    "sg:classifiers":[
        {
            "category":"Autos & Motor Vehicles",
            "subcategory":"Fuel & Gas Station",
            "type":"Retail Goods"
        }
    ],
    "sg:phone":"+1   ",
    "sg:postcode":"17701",
    "sg:province":"PA",
    "sg:tags":[
        "gasoline"
    ],
    "wof:name":"Amoco",
    "wof:placetype":"venue"
},
  "geometry": {"coordinates":[-77.03239499999999,41.239228],"type":"Point"}
}