{
  "type": "Feature",
  "properties": {
    "iso:country":"US",
    "sg:address":"375 Main St",
    "sg:city":"Saegertown",
    "sg:classifiers":[
        {
            "category":"Organizations",
            "subcategory":"Non-profit Organization",
            "type":"Services"
        }
    ],
    "sg:phone":"+1 814 763 6755",
    "sg:postcode":"16433",
    "sg:province":"PA",
    "wof:name":"Charity Bear Co",
    "wof:placetype":"venue"
},
  "geometry": {"coordinates":[-80.148292,41.718339],"type":"Point"}
}