{
  "type": "Feature",
  "properties": {
    "iso:country":"US",
    "sg:address":"1764 W Market St",
    "sg:city":"Pottsville",
    "sg:classifiers":[
        {
            "category":"Personal",
            "type":"Services"
        }
    ],
    "sg:phone":"+1 570 622 4116",
    "sg:postcode":"17901",
    "sg:province":"PA",
    "sg:tags":[
        "miscellaneous"
    ],
    "wof:name":"J L Personal Care",
    "wof:placetype":"venue"
},
  "geometry": {"coordinates":[-76.215889,40.677935],"type":"Point"}
}