{
  "type": "Feature",
  "properties": {
    "addr:full":"116 S 11th St Philadelphia PA 19107",
    "addr:housenumber":"116",
    "addr:postcode":"19107",
    "addr:street":"S 11Th St",
    "iso:country":"US",
    "sg:address":"116 S 11th St",
    "sg:city":"Philadelphia",
    "sg:classifiers":[
        {
            "category":"Personal",
            "subcategory":"Beauty Salon",
            "type":"Services"
        }
    ],
    "sg:phone":"+1 215 238 1200",
    "sg:postcode":"19107",
    "sg:province":"PA",
    "wof:name":"Julie Fashion Nail Salon Inc",
    "wof:placetype":"venue"
},
  "geometry": {"coordinates":[-75.15877,39.950062],"type":"Point"}
}