{
  "type": "Feature",
  "properties": {
    "iso:country":"US",
    "sg:address":"140 E Broad St",
    "sg:city":"Quakertown",
    "sg:classifiers":[
        {
            "category":"Restaurant",
            "type":"Food & Drink"
        }
    ],
    "sg:phone":"+1 215 536 2248",
    "sg:postcode":"18951",
    "sg:province":"PA",
    "sg:tags":[
        "eating",
        "caterer"
    ],
    "wof:name":"Sunday's Deli & Restaurant",
    "wof:placetype":"venue"
},
  "geometry": {"coordinates":[-75.334452,40.441375],"type":"Point"}
}