{
  "type": "Feature",
  "properties": {
    "iso:country":"US",
    "sg:address":"120 S York Rd",
    "sg:city":"Hatboro",
    "sg:classifiers":[
        {
            "category":"Professional",
            "subcategory":"Employment Agencies",
            "type":"Services"
        }
    ],
    "sg:phone":"+1 215 672 1686",
    "sg:postcode":"19040",
    "sg:province":"PA",
    "sg:tags":[
        "opportunity"
    ],
    "wof:name":"Pro Em Personnel Svc",
    "wof:placetype":"venue"
},
  "geometry": {"coordinates":[-75.106892,40.174819],"type":"Point"}
}