{
  "type": "Feature",
  "properties": {
    "addr:full":"810 Main St Honesdale PA 18431",
    "addr:housenumber":"810",
    "addr:postcode":"18431",
    "addr:street":"Main St",
    "iso:country":"US",
    "sg:address":"810 Main St",
    "sg:city":"Honesdale",
    "sg:classifiers":[
        {
            "category":"Museum",
            "type":"Entertainment"
        }
    ],
    "sg:phone":"+1 570 253 3240",
    "sg:postcode":"18431",
    "sg:province":"PA",
    "wof:name":"Wayne Cnty Historical Society",
    "wof:placetype":"venue"
},
  "geometry": {"coordinates":[-75.256269,41.573246],"type":"Point"}
}