{
  "type": "Feature",
  "properties": {
    "iso:country":"US",
    "sg:address":"70 Main St",
    "sg:city":"White Mills",
    "sg:classifiers":[
        {
            "category":"Shopping",
            "subcategory":"Used Merchandise",
            "type":"Retail Goods"
        }
    ],
    "sg:phone":"+1 570 253 8899",
    "sg:postcode":"18445",
    "sg:province":"PA",
    "sg:tags":[
        "antique"
    ],
    "wof:name":"White Mills Antiques & Auction",
    "wof:placetype":"venue"
},
  "geometry": {"coordinates":[-75.330094,41.290994],"type":"Point"}
}