{
  "type": "Feature",
  "properties": {
    "iso:country":"US",
    "sg:address":"381 Beech St",
    "sg:city":"Pottstown",
    "sg:classifiers":[
        {
            "category":"Organizations",
            "subcategory":"Religious Organization",
            "type":"Services"
        }
    ],
    "sg:phone":"+1 610 323 7616",
    "sg:postcode":"19464",
    "sg:province":"PA",
    "sg:tags":[
        "church"
    ],
    "wof:name":"Household Of Faith Mission",
    "wof:placetype":"venue"
},
  "geometry": {"coordinates":[-75.64448400000001,40.249041],"type":"Point"}
}