{
  "type": "Feature",
  "properties": {
    "addr:full":"2679 Fry Rd Jamestown PA 16134",
    "addr:housenumber":"2679",
    "addr:postcode":"16134",
    "addr:street":"Fry Rd",
    "iso:country":"US",
    "sg:address":"2679 Fry Rd",
    "sg:city":"Jamestown",
    "sg:classifiers":[
        {
            "category":"Real Estate",
            "subcategory":"Developer",
            "type":"Services"
        }
    ],
    "sg:phone":"+1   ",
    "sg:postcode":"16134",
    "sg:province":"PA",
    "sg:tags":[
        "cemetery"
    ],
    "wof:name":"Park Lawn Cemetery Assn",
    "wof:placetype":"venue"
},
  "geometry": {"coordinates":[-80.46493599999999,41.493881],"type":"Point"}
}