{
  "type": "Feature",
  "properties": {
    "addr:full":"2617 Swede Rd Norristown PA 19401",
    "addr:housenumber":"2617",
    "addr:postcode":"19401",
    "addr:street":"Swede Rd",
    "iso:country":"US",
    "sg:address":"2617 Swede Rd",
    "sg:city":"Norristown",
    "sg:classifiers":[
        {
            "category":"Building & Trades",
            "subcategory":"Construction",
            "type":"Services"
        }
    ],
    "sg:phone":"+1 610 277 7450",
    "sg:postcode":"19401",
    "sg:province":"PA",
    "sg:tags":[
        "painter"
    ],
    "wof:name":"Ernie Marcon Painting & Paperhanging",
    "wof:placetype":"venue"
},
  "geometry": {"coordinates":[-75.32550000000001,40.141602],"type":"Point"}
}