{
  "type": "Feature",
  "properties": {
    "iso:country":"US",
    "sg:address":"1641 Butler Plank Rd",
    "sg:city":"Glenshaw",
    "sg:classifiers":[
        {
            "category":"Wholesale",
            "subcategory":"Machinery & Supplies",
            "type":"Manufacturing & Wholesale Goods"
        }
    ],
    "sg:phone":"+1 412 782 0941",
    "sg:postcode":"15116",
    "sg:province":"PA",
    "sg:tags":[
        "equipment",
        "industrial",
        "steam",
        "cleaning"
    ],
    "wof:name":"Baillie's Service & Supply",
    "wof:placetype":"venue"
},
  "geometry": {"coordinates":[-79.959884,40.532122],"type":"Point"}
}