{
  "type": "Feature",
  "properties": {
    "iso:country":"US",
    "sg:address":"901 Western Ave",
    "sg:city":"Pittsburgh",
    "sg:classifiers":[
        {
            "category":"Organizations",
            "subcategory":"Community Association",
            "type":"Services"
        }
    ],
    "sg:phone":"+1   ",
    "sg:postcode":"15233",
    "sg:province":"PA",
    "wof:name":"Allegheny West Civic Council",
    "wof:placetype":"venue"
},
  "geometry": {"coordinates":[-80.018897,40.451518],"type":"Point"}
}