{
  "type": "Feature",
  "properties": {
    "iso:country":"US",
    "sg:address":"1011 Green Valley Rd",
    "sg:city":"Aleppo",
    "sg:classifiers":[
        {
            "category":"Education",
            "subcategory":"School",
            "type":"Public Place"
        }
    ],
    "sg:phone":"+1 724 428 5266",
    "sg:postcode":"15310",
    "sg:province":"PA",
    "wof:name":"Aleppo Elementary School",
    "wof:placetype":"venue"
},
  "geometry": {"coordinates":[-80.46222299999999,39.824528],"type":"Point"}
}