{
  "type": "Feature",
  "properties": {
    "addr:full":"1665 Rock Hollow Rd Birdsboro PA 19508",
    "addr:housenumber":"1665",
    "addr:postcode":"19508",
    "addr:street":"Rock Hollow Rd",
    "iso:country":"US",
    "sg:address":"1665 Rock Hollow Rd",
    "sg:city":"Birdsboro",
    "sg:classifiers":[
        {
            "category":"Recreation",
            "type":"Entertainment"
        }
    ],
    "sg:phone":"+1 610 582 5672",
    "sg:postcode":"19508",
    "sg:province":"PA",
    "sg:tags":[
        "hall",
        "auditorium"
    ],
    "wof:name":"Hillcrest Hall",
    "wof:placetype":"venue"
},
  "geometry": {"coordinates":[-75.846864,40.275167],"type":"Point"}
}