{
  "type": "Feature",
  "properties": {
    "iso:country":"US",
    "sg:address":"Four Tower Bridge 200 Barr Harbor Drive, Suite 400",
    "sg:city":"Conshohocken",
    "sg:classifiers":[
        {
            "category":"Professional",
            "subcategory":"Research",
            "type":"Services"
        }
    ],
    "sg:phone":"+1 484 879 2800",
    "sg:postcode":"19428",
    "sg:province":"PA",
    "sg:website":"http://www.othera.com/",
    "wof:name":"Othera Pharmaceuticals",
    "wof:placetype":"venue"
},
  "geometry": {"coordinates":[-75.28459599999999,40.08743],"type":"Point"}
}