{
  "type": "Feature",
  "properties": {
    "addr:full":"117 E Chelten Ave Philadelphia PA 19144",
    "addr:housenumber":"117",
    "addr:postcode":"19144",
    "addr:street":"E Chelten Ave",
    "iso:country":"US",
    "sg:address":"117 E Chelten Ave",
    "sg:city":"Philadelphia",
    "sg:classifiers":[
        {
            "category":"Banks & Credit Unions",
            "subcategory":"Bank",
            "type":"Services"
        }
    ],
    "sg:phone":"+1 215 848 4673",
    "sg:postcode":"19144",
    "sg:province":"PA",
    "sg:tags":[
        "cashing",
        "check"
    ],
    "wof:name":"Fast Cash Inc",
    "wof:placetype":"venue"
},
  "geometry": {"coordinates":[-75.17213599999999,40.038357],"type":"Point"}
}