{
  "type": "Feature",
  "properties": {
    "iso:country":"US",
    "sg:address":"904 Purdue Mountain Rd",
    "sg:city":"Bellefonte",
    "sg:classifiers":[
        {
            "category":"Wholesale",
            "subcategory":"Construction Materials",
            "type":"Manufacturing & Wholesale Goods"
        }
    ],
    "sg:phone":"+1 814 237 6699",
    "sg:postcode":"16823",
    "sg:province":"PA",
    "sg:tags":[
        "repair",
        "cont",
        "carpentry"
    ],
    "wof:name":"Advance Overhead Garage Door",
    "wof:placetype":"venue"
},
  "geometry": {"coordinates":[-77.880954,40.886056],"type":"Point"}
}