{
  "type": "Feature",
  "properties": {
    "addr:full":"1121 Brackenridge Ave Brackenridge PA 15014",
    "addr:housenumber":"1121",
    "addr:postcode":"15014",
    "addr:street":"Brackenridge Ave",
    "iso:country":"US",
    "sg:address":"1121 Brackenridge Ave",
    "sg:city":"Brackenridge",
    "sg:classifiers":[
        {
            "category":"Education",
            "subcategory":"Special Training",
            "type":"Public Place"
        }
    ],
    "sg:phone":"+1 724 226 0521",
    "sg:postcode":"15014",
    "sg:province":"PA",
    "sg:tags":[
        "center"
    ],
    "wof:name":"ICD Learning Ctr",
    "wof:placetype":"venue"
},
  "geometry": {"coordinates":[-79.734932,40.60629],"type":"Point"}
}