{
  "type": "Feature",
  "properties": {
    "iso:country":"US",
    "sg:address":"451 Fullerton Ave",
    "sg:city":"Cambridge Spgs",
    "sg:classifiers":[
        {
            "category":"Government",
            "subcategory":"Office",
            "type":"Public Place"
        }
    ],
    "sg:phone":"+1 814 398 1807",
    "sg:postcode":"16403",
    "sg:province":"PA",
    "sg:tags":[
        "state",
        "program",
        "health"
    ],
    "wof:name":"Prison Health Svc Inc",
    "wof:placetype":"venue"
},
  "geometry": {"coordinates":[-80.057468,41.798799],"type":"Point"}
}