{
  "type": "Feature",
  "properties": {
    "addr:full":"1831 Mile Hill Rd Sunbury PA 17801",
    "addr:housenumber":"1831",
    "addr:postcode":"17801",
    "addr:street":"Mile Hill Rd",
    "iso:country":"US",
    "sg:address":"1831 Mile Hill Rd",
    "sg:city":"Sunbury",
    "sg:classifiers":[
        {
            "category":"Shopping",
            "subcategory":"Gifts & Souvenirs",
            "type":"Retail Goods"
        }
    ],
    "sg:phone":"+1 570 988 1818",
    "sg:postcode":"17801",
    "sg:province":"PA",
    "sg:tags":[
        "shop"
    ],
    "wof:name":"Dogwood Farm",
    "wof:placetype":"venue"
},
  "geometry": {"coordinates":[-76.75212000000001,40.883625],"type":"Point"}
}