{
  "type": "Feature",
  "properties": {
    "iso:country":"US",
    "sg:address":"1831 Mile Hill Rd",
    "sg:city":"Sunbury",
    "sg:classifiers":[
        {
            "category":"Shopping",
            "subcategory":"Gifts & Souvenirs",
            "type":"Retail Goods"
        }
    ],
    "sg:phone":"+1 570 988 1818",
    "sg:postcode":"17801",
    "sg:province":"PA",
    "sg:tags":[
        "shop"
    ],
    "wof:name":"Dogwood Farm",
    "wof:placetype":"venue"
},
  "geometry": {"coordinates":[-76.75212,40.883625],"type":"Point"}
}