{
  "type": "Feature",
  "properties": {
    "iso:country":"US",
    "sg:address":"47 Parrish St",
    "sg:city":"Dallas",
    "sg:classifiers":[
        {
            "category":"Wholesale",
            "subcategory":"Groceries",
            "type":"Manufacturing & Wholesale Goods"
        }
    ],
    "sg:phone":"+1   ",
    "sg:postcode":"18612",
    "sg:province":"PA",
    "sg:tags":[
        "food",
        "snack"
    ],
    "wof:name":"Lance Inc",
    "wof:placetype":"venue"
},
  "geometry": {"coordinates":[-75.96299500000001,41.330111],"type":"Point"}
}