{
  "type": "Feature",
  "properties": {
    "iso:country":"US",
    "sg:address":"102 S 60th St",
    "sg:city":"Philadelphia",
    "sg:classifiers":[
        {
            "category":"Personal",
            "subcategory":"Beauty Salon",
            "type":"Services"
        }
    ],
    "sg:phone":"+1   ",
    "sg:postcode":"19139",
    "sg:province":"PA",
    "sg:tags":[
        "shop"
    ],
    "wof:name":"A J Unisex Inc",
    "wof:placetype":"venue"
},
  "geometry": {"coordinates":[-75.241298,39.959749],"type":"Point"}
}