{
  "type": "Feature",
  "properties": {
    "addr:full":"157 Waterford Pike Brookville PA 15825",
    "addr:housenumber":"157",
    "addr:postcode":"15825",
    "addr:street":"Waterford Pike",
    "iso:country":"US",
    "sg:address":"157 Waterford Pike",
    "sg:city":"Brookville",
    "sg:classifiers":[
        {
            "category":"Home & Garden",
            "subcategory":"Furniture",
            "type":"Retail Goods"
        }
    ],
    "sg:phone":"+1 814 849 4800",
    "sg:postcode":"15825",
    "sg:province":"PA",
    "sg:tags":[
        "store"
    ],
    "sg:website":"http://www.lindbergfurniture.com",
    "wof:name":"Lindberg Furniture",
    "wof:placetype":"venue"
},
  "geometry": {"coordinates":[-79.098574,41.166023],"type":"Point"}
}