{
  "type": "Feature",
  "properties": {
    "addr:full":"2453 Kingston Ct York PA 17402",
    "addr:housenumber":"2453",
    "addr:postcode":"17402",
    "addr:street":"Kingston Ct",
    "iso:country":"US",
    "sg:address":"2453 Kingston Ct",
    "sg:city":"York",
    "sg:classifiers":[
        {
            "category":"Professional",
            "subcategory":"Engineering",
            "type":"Services"
        }
    ],
    "sg:phone":"+1 717 755 9445",
    "sg:postcode":"17402",
    "sg:province":"PA",
    "sg:tags":[
        "general",
        "contractor"
    ],
    "wof:name":"Mid Atlantic Region Engr",
    "wof:placetype":"venue"
},
  "geometry": {"coordinates":[-76.676922,39.970998],"type":"Point"}
}