{
  "type": "Feature",
  "properties": {
    "iso:country":"US",
    "sg:address":"303 Maple Ave Ste 7",
    "sg:city":"Harleysville",
    "sg:classifiers":[
        {
            "category":"Building & Trades",
            "subcategory":"Construction",
            "type":"Services"
        }
    ],
    "sg:phone":"+1 215 256 0600",
    "sg:postcode":"19438",
    "sg:province":"PA",
    "sg:tags":[
        "contractor"
    ],
    "sg:website":"www.mericon.com",
    "wof:name":"Mericon Inc",
    "wof:placetype":"venue"
},
  "geometry": {"coordinates":[-75.387923,40.279502],"type":"Point"}
}