{
  "type": "Feature",
  "properties": {
    "iso:country":"US",
    "sg:address":"2212 Lincoln Blvd",
    "sg:city":"Elizabeth",
    "sg:classifiers":[
        {
            "category":"Freight",
            "type":"Transportation"
        }
    ],
    "sg:phone":"+1   ",
    "sg:postcode":"15037",
    "sg:province":"PA",
    "sg:tags":[
        "operator",
        "local",
        "trucking"
    ],
    "wof:name":"Diane M Ross Trucking",
    "wof:placetype":"venue"
},
  "geometry": {"coordinates":[-79.869153,40.285109],"type":"Point"}
}