{
  "type": "Feature",
  "properties": {
    "iso:country":"US",
    "sg:address":"718 S Blakely St",
    "sg:city":"Scranton",
    "sg:classifiers":[
        {
            "category":"Building & Trades",
            "subcategory":"Construction",
            "type":"Services"
        }
    ],
    "sg:phone":"+1 570 347 3177",
    "sg:postcode":"18510",
    "sg:province":"PA",
    "sg:tags":[
        "excavating",
        "contractor"
    ],
    "wof:name":"Gentile's Excavating",
    "wof:placetype":"venue"
},
  "geometry": {"coordinates":[-75.643333,41.415554],"type":"Point"}
}