{
  "type": "Feature",
  "properties": {
    "iso:country":"US",
    "sg:address":"328 6th Ave",
    "sg:city":"Pittsburgh",
    "sg:classifiers":[
        {
            "category":"Organizations",
            "subcategory":"Religious Organization",
            "type":"Services"
        }
    ],
    "sg:phone":"+1   ",
    "sg:postcode":"15222",
    "sg:province":"PA",
    "sg:tags":[
        "church"
    ],
    "wof:name":"Trinity Cathedral",
    "wof:placetype":"venue"
},
  "geometry": {"coordinates":[-79.99781299999999,40.441411],"type":"Point"}
}