{
  "type": "Feature",
  "properties": {
    "iso:country":"US",
    "sg:address":"256 Cedar Blvd",
    "sg:city":"Mt Lebanon",
    "sg:classifiers":[
        {
            "category":"Shopping",
            "type":"Retail Goods"
        }
    ],
    "sg:phone":"+1 412 914 0520",
    "sg:postcode":"15228",
    "sg:province":"PA",
    "sg:tags":[
        "pet",
        "food",
        "supply"
    ],
    "wof:name":"Pet Pantry",
    "wof:placetype":"venue"
},
  "geometry": {"coordinates":[-80.05144,40.38087],"type":"Point"}
}