{
  "type": "Feature",
  "properties": {
    "iso:country":"US",
    "sg:address":"135 E Elm St",
    "sg:city":"Homer City",
    "sg:classifiers":[
        {
            "category":"Organizations",
            "subcategory":"Religious Organization",
            "type":"Services"
        }
    ],
    "sg:phone":"+1 724 479 8583",
    "sg:postcode":"15748",
    "sg:province":"PA",
    "sg:tags":[
        "clergy"
    ],
    "wof:name":"James F Cook",
    "wof:placetype":"venue"
},
  "geometry": {"coordinates":[-79.157279,40.54238],"type":"Point"}
}