{
  "type": "Feature",
  "properties": {
    "iso:country":"US",
    "sg:address":"961 N Chester Rd",
    "sg:city":"West Chester",
    "sg:classifiers":[
        {
            "category":"Social Services",
            "type":"Services"
        }
    ],
    "sg:phone":"+1 610 696 1860",
    "sg:postcode":"19380",
    "sg:province":"PA",
    "sg:tags":[
        "instruction",
        "health",
        "care"
    ],
    "wof:name":"Advent Nutrition LLC",
    "wof:placetype":"venue"
},
  "geometry": {"coordinates":[-75.547043,40.00118],"type":"Point"}
}