{
  "type": "Feature",
  "properties": {
    "addr:full":"1401 N 2nd St Harrisburg PA 17102",
    "addr:housenumber":"1401",
    "addr:postcode":"17102",
    "addr:street":"N 2Nd St",
    "iso:country":"US",
    "sg:address":"1401 N 2nd St",
    "sg:city":"Harrisburg",
    "sg:classifiers":[
        {
            "category":"Retail",
            "subcategory":"Laundry & Dry Cleaning",
            "type":"Services"
        }
    ],
    "sg:phone":"+1 717 233 6626",
    "sg:postcode":"17102",
    "sg:province":"PA",
    "sg:tags":[
        "cleaners"
    ],
    "wof:name":"Clean Scene Coin Laundry Clean",
    "wof:placetype":"venue"
},
  "geometry": {"coordinates":[-76.89260299999999,40.270077],"type":"Point"}
}