{
  "type": "Feature",
  "properties": {
    "iso:country":"US",
    "sg:address":"29 Mechanic St",
    "sg:city":"Wind Gap",
    "sg:classifiers":[
        {
            "category":"Government",
            "subcategory":"Office",
            "type":"Public Place"
        }
    ],
    "sg:phone":"+1   ",
    "sg:postcode":"18091",
    "sg:province":"PA",
    "wof:name":"Wind Gap Borough of",
    "wof:placetype":"venue"
},
  "geometry": {"coordinates":[-75.296434,40.84758],"type":"Point"}
}