{
  "type": "Feature",
  "properties": {
    "iso:country":"US",
    "sg:address":"5506 Chester Ave",
    "sg:city":"Philadelphia",
    "sg:classifiers":[
        {
            "category":"Home & Garden",
            "subcategory":"Hardware",
            "type":"Retail Goods"
        }
    ],
    "sg:phone":"+1 215 729 5854",
    "sg:postcode":"19143",
    "sg:province":"PA",
    "sg:tags":[
        "store"
    ],
    "wof:name":"R & H Hardware",
    "wof:placetype":"venue"
},
  "geometry": {"coordinates":[-75.22438,39.938476],"type":"Point"}
}