{
  "type": "Feature",
  "properties": {
    "addr:full":"100 E Butler Ave Ambler PA 19002",
    "addr:housenumber":"100",
    "addr:postcode":"19002",
    "addr:street":"E Butler Ave",
    "iso:country":"US",
    "sg:address":"100 E Butler Ave",
    "sg:city":"Ambler",
    "sg:classifiers":[
        {
            "category":"Ice Cream",
            "type":"Food & Drink"
        }
    ],
    "sg:menulink":"http://www.allmenus.com/pa/ambler/234783-ritas-ice-custard-happiness/menu/",
    "sg:phone":"+1 215 793 9080",
    "sg:postcode":"19002",
    "sg:province":"PA",
    "sg:tags":[
        "american"
    ],
    "wof:name":"Rita's Ice Custard Happiness",
    "wof:placetype":"venue"
},
  "geometry": {"coordinates":[-75.22151700000001,40.154679],"type":"Point"}
}