{
  "type": "Feature",
  "properties": {
    "iso:country":"US",
    "sg:address":"144 E Water St",
    "sg:city":"Saxonburg",
    "sg:classifiers":[
        {
            "category":"Professional",
            "type":"Services"
        }
    ],
    "sg:phone":"+1   ",
    "sg:postcode":"16056",
    "sg:province":"PA",
    "wof:name":"Satt Studios",
    "wof:placetype":"venue"
},
  "geometry": {"coordinates":[-79.807271,40.754581],"type":"Point"}
}