{
  "type": "Feature",
  "properties": {
    "iso:country":"US",
    "sg:address":"431 Louella Dr",
    "sg:city":"Windber",
    "sg:classifiers":[
        {
            "category":"Farming",
            "subcategory":"Livestock Farm",
            "type":"Manufacturing & Wholesale Goods"
        }
    ],
    "sg:phone":"+1   ",
    "sg:postcode":"15963",
    "sg:province":"PA",
    "sg:tags":[
        "equine"
    ],
    "wof:name":"Kj Equine Center",
    "wof:placetype":"venue"
},
  "geometry": {"coordinates":[-78.804164,40.209115],"type":"Point"}
}