{
  "type": "Feature",
  "properties": {
    "iso:country":"US",
    "sg:address":"44 College Ave",
    "sg:city":"Flourtown",
    "sg:classifiers":[
        {
            "category":"Manufacturing",
            "subcategory":"Metals",
            "type":"Manufacturing & Wholesale Goods"
        }
    ],
    "sg:phone":"+1   ",
    "sg:postcode":"19031",
    "sg:province":"PA",
    "sg:tags":[
        "copper",
        "foundry"
    ],
    "wof:name":"Wwwehbbrasscom",
    "wof:placetype":"venue"
},
  "geometry": {"coordinates":[-75.214595,40.104387],"type":"Point"}
}