{
  "type": "Feature",
  "properties": {
    "iso:country":"US",
    "sg:address":"1010 Green Ln",
    "sg:city":"Secane",
    "sg:classifiers":[
        {
            "category":"Retail",
            "subcategory":"Repair Shop",
            "type":"Services"
        }
    ],
    "sg:phone":"+1 610 623 1892",
    "sg:postcode":"19018",
    "sg:province":"PA",
    "sg:tags":[
        "appliance"
    ],
    "wof:name":"Tilli Appliance Repair",
    "wof:placetype":"venue"
},
  "geometry": {"coordinates":[-75.299279,39.915483],"type":"Point"}
}