{
  "type": "Feature",
  "properties": {
    "iso:country":"US",
    "sg:address":"420 Apple St",
    "sg:city":"Pottstown",
    "sg:classifiers":[
        {
            "category":"Building & Trades",
            "subcategory":"Equipment Rental",
            "type":"Services"
        },
        {
            "category":"Communications",
            "subcategory":"Film & Video Production",
            "type":"Services"
        },
        {
            "category":"Professional",
            "subcategory":"Art Services",
            "type":"Services"
        },
        {
            "category":"Shopping",
            "subcategory":"Computers & Home Electronics",
            "type":"Retail Goods"
        }
    ],
    "sg:phone":"+1 610 326 0373",
    "sg:postcode":"19464",
    "sg:province":"PA",
    "sg:tags":[
        "stereo",
        "leasing",
        "creative",
        "audio",
        "equipment-renting",
        "audio-visual"
    ],
    "wof:name":"Global Meeting Partners",
    "wof:placetype":"venue"
},
  "geometry": {"coordinates":[-75.64399299999999,40.244304],"type":"Point"}
}