{
  "type": "Feature",
  "properties": {
    "addr:full":"5 Country Club Shopping Center Dallas PA 18612",
    "addr:housenumber":"5",
    "addr:postcode":"18612",
    "addr:street":"Country;Shopping Center",
    "iso:country":"US",
    "sg:address":"5 Country Club Shopping Center",
    "sg:city":"Dallas",
    "sg:classifiers":[
        {
            "category":"Restaurant",
            "type":"Food & Drink"
        }
    ],
    "sg:phone":"+1   ",
    "sg:postcode":"18612",
    "sg:province":"PA",
    "sg:tags":[
        "eating"
    ],
    "wof:name":"Mama & Papas Ice Cream Parlor",
    "wof:placetype":"venue"
},
  "geometry": {"coordinates":[-75.96051,41.347329],"type":"Point"}
}