{
  "type": "Feature",
  "properties": {
    "iso:country":"US",
    "sg:address":"4079 Dominion Dr",
    "sg:city":"Erie",
    "sg:classifiers":[
        {
            "category":"Real Estate",
            "subcategory":"Real Estate Services",
            "type":"Services"
        }
    ],
    "sg:phone":"+1 814 899 1811",
    "sg:postcode":"16510",
    "sg:province":"PA",
    "sg:tags":[
        "company",
        "title"
    ],
    "wof:name":"United General Title Ins Co",
    "wof:placetype":"venue"
},
  "geometry": {"coordinates":[-79.989332,42.136749],"type":"Point"}
}