{
  "type": "Feature",
  "properties": {
    "iso:country":"US",
    "sg:address":"5163 Mill Rd",
    "sg:city":"Emmaus",
    "sg:classifiers":[
        {
            "category":"Building & Trades",
            "subcategory":"Construction",
            "type":"Services"
        }
    ],
    "sg:phone":"+1 610 965 7837",
    "sg:postcode":"18049",
    "sg:province":"PA",
    "sg:tags":[
        "house",
        "improvement",
        "home"
    ],
    "wof:name":"Reed L Harris Construction",
    "wof:placetype":"venue"
},
  "geometry": {"coordinates":[-75.53052700000001,40.511166],"type":"Point"}
}