{
  "type": "Feature",
  "properties": {
    "iso:country":"US",
    "sg:address":"555 N Duke St",
    "sg:city":"Lancaster",
    "sg:classifiers":[
        {
            "category":"Insurance",
            "subcategory":"Insurance Agent",
            "type":"Services"
        }
    ],
    "sg:phone":"+1 717 672 0391",
    "sg:postcode":"17602",
    "sg:province":"PA",
    "wof:name":"Coresource Inc",
    "wof:placetype":"venue"
},
  "geometry": {"coordinates":[-76.30537099999999,40.047083],"type":"Point"}
}