{
  "type": "Feature",
  "properties": {
    "iso:country":"US",
    "sg:address":"38 Walnut Bottom Rd",
    "sg:city":"Shippensburg",
    "sg:classifiers":[
        {
            "category":"Fast Food",
            "type":"Food & Drink"
        },
        {
            "category":"Restaurant",
            "type":"Food & Drink"
        }
    ],
    "sg:phone":"+1 717 530 5464",
    "sg:postcode":"17257",
    "sg:province":"PA",
    "sg:tags":[
        "american",
        "hot",
        "hamburger",
        "dog"
    ],
    "sg:website":"http://www.bk.com",
    "wof:name":"Burger King",
    "wof:placetype":"venue"
},
  "geometry": {"coordinates":[-77.503951,40.058813],"type":"Point"}
}