{
  "type": "Feature",
  "properties": {
    "addr:full":"535 Allie Buck Rd Nanty Glo PA 15943",
    "addr:housenumber":"535",
    "addr:postcode":"15943",
    "addr:street":"Allie Buck Rd",
    "iso:country":"US",
    "sg:address":"535 Allie Buck Rd",
    "sg:city":"Nanty Glo",
    "sg:classifiers":[
        {
            "category":"Building & Trades",
            "subcategory":"Landscaping Services",
            "type":"Services"
        }
    ],
    "sg:phone":"+1   ",
    "sg:postcode":"15943",
    "sg:province":"PA",
    "sg:tags":[
        "lawn",
        "garden"
    ],
    "wof:name":"Novak Robert & Sons",
    "wof:placetype":"venue"
},
  "geometry": {"coordinates":[-78.803252,40.488749],"type":"Point"}
}