{
  "type": "Feature",
  "properties": {
    "iso:country":"US",
    "sg:address":"3268 Frankford Ave",
    "sg:city":"Philadelphia",
    "sg:classifiers":[
        {
            "category":"Restaurant",
            "type":"Food & Drink"
        }
    ],
    "sg:phone":"+1 215 427 2770",
    "sg:postcode":"19134",
    "sg:province":"PA",
    "sg:tags":[
        "eating"
    ],
    "wof:name":"Teddy's Luncheonette",
    "wof:placetype":"venue"
},
  "geometry": {"coordinates":[-75.108149,39.994051],"type":"Point"}
}