{
  "type": "Feature",
  "properties": {
    "addr:full":"306 Station Rd Robesonia PA 19551",
    "addr:housenumber":"306",
    "addr:postcode":"19551",
    "addr:street":"Station Rd",
    "iso:country":"US",
    "sg:address":"306 Station Rd",
    "sg:city":"Robesonia",
    "sg:classifiers":[
        {
            "category":"Manufacturing",
            "subcategory":"Lumber",
            "type":"Manufacturing & Wholesale Goods"
        }
    ],
    "sg:phone":"+1 610 488 1483",
    "sg:postcode":"19551",
    "sg:province":"PA",
    "sg:tags":[
        "pipe",
        "lining",
        "coating"
    ],
    "wof:name":"Texas Eastern Trans Corp A Duke Energy Co",
    "wof:placetype":"venue"
},
  "geometry": {"coordinates":[-76.15038300000001,40.410218],"type":"Point"}
}