{
  "type": "Feature",
  "properties": {
    "iso:country":"US",
    "sg:address":"9 E Athens Ave",
    "sg:city":"Ardmore",
    "sg:classifiers":[
        {
            "category":"Professional",
            "subcategory":"Lawyer & Legal Services",
            "type":"Services"
        }
    ],
    "sg:phone":"+1 610 896 3700",
    "sg:postcode":"19003",
    "sg:province":"PA",
    "sg:tags":[
        "attorney"
    ],
    "wof:name":"Richard F Weinstein",
    "wof:placetype":"venue"
},
  "geometry": {"coordinates":[-75.292936,40.006812],"type":"Point"}
}