{
  "type": "Feature",
  "properties": {
    "addr:full":"77 N Main St Greenville PA 16125",
    "addr:housenumber":"77",
    "addr:postcode":"16125",
    "addr:street":"N Main St",
    "iso:country":"US",
    "sg:address":"77 N Main St",
    "sg:city":"Greenville",
    "sg:classifiers":[
        {
            "category":"Health Services",
            "subcategory":"Doctor",
            "type":"Services"
        }
    ],
    "sg:phone":"+1   ",
    "sg:postcode":"16125",
    "sg:province":"PA",
    "sg:tags":[
        "medical"
    ],
    "wof:name":"Muelller Henry M MD",
    "wof:placetype":"venue"
},
  "geometry": {"coordinates":[-80.373768,41.410712],"type":"Point"}
}