{
  "type": "Feature",
  "properties": {
    "iso:country":"US",
    "sg:address":"1211 Deerfield Dr",
    "sg:city":"State College",
    "sg:classifiers":[
        {
            "category":"Professional",
            "subcategory":"Computer Services",
            "type":"Services"
        }
    ],
    "sg:phone":"+1   ",
    "sg:postcode":"16803",
    "sg:province":"PA",
    "sg:tags":[
        "programming",
        "related",
        "custom"
    ],
    "wof:name":"R M Associates",
    "wof:placetype":"venue"
},
  "geometry": {"coordinates":[-77.921137,40.783038],"type":"Point"}
}