{
  "type": "Feature",
  "properties": {
    "iso:country":"US",
    "sg:address":"209 N Furnace St",
    "sg:city":"Birdsboro",
    "sg:classifiers":[
        {
            "category":"Restaurant",
            "type":"Food & Drink"
        }
    ],
    "sg:phone":"+1 610 582 5665",
    "sg:postcode":"19508",
    "sg:province":"PA",
    "sg:tags":[
        "pizza"
    ],
    "wof:name":"Vinnie's Pizzeria & Restaurant",
    "wof:placetype":"venue"
},
  "geometry": {"coordinates":[-75.807829,40.264865],"type":"Point"}
}