{
  "type": "Feature",
  "properties": {
    "addr:full":"2060 Lincoln Hwy E Lancaster PA 17602",
    "addr:housenumber":"2060",
    "addr:postcode":"17602",
    "addr:street":"Lincoln Hwy E",
    "iso:country":"US",
    "sg:address":"2060 Lincoln Hwy E",
    "sg:city":"Lancaster",
    "sg:classifiers":[
        {
            "category":"Autos & Motor Vehicles",
            "subcategory":"Automobile Sales",
            "type":"Retail Goods"
        }
    ],
    "sg:phone":"+1 717 509 2707",
    "sg:postcode":"17602",
    "sg:province":"PA",
    "sg:tags":[
        "car",
        "used",
        "dealer"
    ],
    "wof:name":"R B Autolink Inc",
    "wof:placetype":"venue"
},
  "geometry": {"coordinates":[-76.23527799999999,40.03082],"type":"Point"}
}