{
  "type": "Feature",
  "properties": {
    "iso:country":"US",
    "sg:address":"1046 W Jefferson St",
    "sg:city":"Philadelphia",
    "sg:classifiers":[
        {
            "category":"Professional",
            "type":"Services"
        }
    ],
    "sg:phone":"+1   ",
    "sg:postcode":"19122",
    "sg:province":"PA",
    "wof:name":"Imani Phoenix Inc",
    "wof:placetype":"venue"
},
  "geometry": {"coordinates":[-75.15309000000001,39.975067],"type":"Point"}
}