{
  "type": "Feature",
  "properties": {
    "addr:full":"8961 Lincoln Hwy Irwin PA 15642",
    "addr:housenumber":"8961",
    "addr:postcode":"15642",
    "addr:street":"Lincoln Hwy",
    "iso:country":"US",
    "sg:address":"8961 Lincoln Hwy",
    "sg:city":"Irwin",
    "sg:classifiers":[
        {
            "category":"Home & Garden",
            "subcategory":"Furniture",
            "type":"Retail Goods"
        }
    ],
    "sg:phone":"+1 724 864 9794",
    "sg:postcode":"15642",
    "sg:province":"PA",
    "sg:tags":[
        "mattress"
    ],
    "wof:name":"Mattress Discounters 4186",
    "wof:placetype":"venue"
},
  "geometry": {"coordinates":[-79.691152,40.320171],"type":"Point"}
}