{
  "type": "Feature",
  "properties": {
    "iso:country":"US",
    "sg:address":"90 Main St",
    "sg:city":"Yorkana",
    "sg:classifiers":[
        {
            "category":"Shopping",
            "type":"Retail Goods"
        },
        {
            "category":"Retail",
            "subcategory":"Animal Services",
            "type":"Services"
        }
    ],
    "sg:phone":"+1 717 757 1691",
    "sg:postcode":"17406",
    "sg:province":"PA",
    "sg:tags":[
        "pet",
        "boarding",
        "merchandise",
        "sitting"
    ],
    "wof:name":"Kefauver Pet Supply",
    "wof:placetype":"venue"
},
  "geometry": {"coordinates":[-76.579465,39.980491],"type":"Point"}
}