{
  "type": "Feature",
  "properties": {
    "addr:full":"1165 Harrisburg Pike Carlisle PA 17013",
    "addr:housenumber":"1165",
    "addr:postcode":"17013",
    "addr:street":"Harrisburg Pike",
    "iso:country":"US",
    "sg:address":"1165 Harrisburg Pike",
    "sg:city":"Carlisle",
    "sg:classifiers":[
        {
            "category":"Autos & Motor Vehicles",
            "subcategory":"Fuel & Gas Station",
            "type":"Retail Goods"
        },
        {
            "category":"Food & Beverages",
            "subcategory":"Groceries & Convenience Stores",
            "type":"Retail Goods"
        }
    ],
    "sg:phone":"+1 717 240 0055",
    "sg:postcode":"17013",
    "sg:province":"PA",
    "wof:name":"Pilot Corp",
    "wof:placetype":"venue"
},
  "geometry": {"coordinates":[-77.148201,40.229198],"type":"Point"}
}