{
  "type": "Feature",
  "properties": {
    "iso:country":"US",
    "sg:address":"878 Baltimore Pike",
    "sg:city":"Chadds Ford",
    "sg:classifiers":[
        {
            "category":"Restaurant",
            "type":"Food & Drink"
        }
    ],
    "sg:phone":"+1 610 388 2000",
    "sg:postcode":"19317",
    "sg:province":"PA",
    "sg:tags":[
        "traditional",
        "american",
        "brunch",
        "breakfast"
    ],
    "sg:website":"www.brandywineriverantiques.com/...",
    "wof:name":"Mushroom Cafe",
    "wof:placetype":"venue"
},
  "geometry": {"coordinates":[-75.635638,39.874614],"type":"Point"}
}