{
  "type": "Feature",
  "properties": {
    "iso:country":"US",
    "sg:address":"7802 Arthur St",
    "sg:city":"Masury",
    "sg:classifiers":[
        {
            "category":"Building & Trades",
            "subcategory":"Landscaping Services",
            "type":"Services"
        }
    ],
    "sg:phone":"+1 330 448 7867",
    "sg:postcode":"44438",
    "sg:province":"PA",
    "wof:name":"Logan Outdoor Maintenance",
    "wof:placetype":"venue"
},
  "geometry": {"coordinates":[-80.537339,41.202136],"type":"Point"}
}