{
  "type": "Feature",
  "properties": {
    "addr:full":"2985 Four Mile Dr Montoursville PA 17754",
    "addr:housenumber":"2985",
    "addr:postcode":"17754",
    "addr:street":"Four Mile Dr",
    "iso:country":"US",
    "sg:address":"2985 Four Mile Dr",
    "sg:city":"Montoursville",
    "sg:classifiers":[
        {
            "category":"Social Services",
            "subcategory":"Adult Care",
            "type":"Services"
        }
    ],
    "sg:phone":"+1 570 368 2076",
    "sg:postcode":"17754",
    "sg:province":"PA",
    "sg:tags":[
        "home",
        "residential"
    ],
    "wof:name":"Outlook Pointe At Loyalsock",
    "wof:placetype":"venue"
},
  "geometry": {"coordinates":[-76.939058,41.26119],"type":"Point"}
}