{
  "type": "Feature",
  "properties": {
    "addr:full":"32 S 5th St Easton PA 18042",
    "addr:housenumber":"32",
    "addr:postcode":"18042",
    "addr:street":"S 5Th St",
    "iso:country":"US",
    "sg:address":"32 S 5th St",
    "sg:city":"Easton",
    "sg:classifiers":[
        {
            "category":"Professional",
            "subcategory":"Art Services",
            "type":"Services"
        }
    ],
    "sg:phone":"+1 610 250 1955",
    "sg:postcode":"18042",
    "sg:province":"PA",
    "sg:tags":[
        "photographer"
    ],
    "wof:name":"Dan Marshall",
    "wof:placetype":"venue"
},
  "geometry": {"coordinates":[-75.21286000000001,40.689557],"type":"Point"}
}