{
  "type": "Feature",
  "properties": {
    "iso:country":"US",
    "sg:address":"1450 E Main St",
    "sg:city":"Reynoldsville",
    "sg:classifiers":[
        {
            "category":"Insurance",
            "subcategory":"Insurance Agent",
            "type":"Services"
        }
    ],
    "sg:phone":"+1 814 653 2359",
    "sg:postcode":"15851",
    "sg:province":"PA",
    "wof:name":"Kengersky Agency",
    "wof:placetype":"venue"
},
  "geometry": {"coordinates":[-78.87570100000001,41.087087],"type":"Point"}
}