{
  "type": "Feature",
  "properties": {
    "addr:full":"198 W Lincoln Ave Myerstown PA 17067",
    "addr:housenumber":"198",
    "addr:postcode":"17067",
    "addr:street":"W Lincoln Ave",
    "iso:country":"US",
    "sg:address":"198 W Lincoln Ave",
    "sg:city":"Myerstown",
    "sg:classifiers":[
        {
            "category":"Restaurant",
            "type":"Food & Drink"
        }
    ],
    "sg:menulink":"http://www.allmenus.com/pa/myerstown/154716-hardees/menu/",
    "sg:phone":"+1 717 866 5522",
    "sg:postcode":"17067",
    "sg:province":"PA",
    "sg:tags":[
        "burger",
        "american"
    ],
    "wof:name":"Hardee's",
    "wof:placetype":"venue"
},
  "geometry": {"coordinates":[-76.31053900000001,40.377705],"type":"Point"}
}