{
  "type": "Feature",
  "properties": {
    "iso:country":"US",
    "sg:address":"135 Mountain Rd",
    "sg:city":"White Deer",
    "sg:classifiers":[
        {
            "category":"Retail",
            "subcategory":"Auto Repair",
            "type":"Services"
        }
    ],
    "sg:phone":"+1 570 538 1792",
    "sg:postcode":"17820",
    "sg:province":"PA",
    "sg:tags":[
        "recreational",
        "vehicle"
    ],
    "wof:name":"Beaver's RV Svc",
    "wof:placetype":"venue"
},
  "geometry": {"coordinates":[-76.416888,40.964691],"type":"Point"}
}