{
  "type": "Feature",
  "properties": {
    "iso:country":"US",
    "sg:address":"1132 Miller Rd",
    "sg:city":"Wind Gap",
    "sg:classifiers":[
        {
            "category":"Freight",
            "type":"Transportation"
        }
    ],
    "sg:phone":"+1   ",
    "sg:postcode":"18091",
    "sg:province":"PA",
    "sg:tags":[
        "local",
        "trucking"
    ],
    "wof:name":"William Greeby Trucking",
    "wof:placetype":"venue"
},
  "geometry": {"coordinates":[-75.327883,40.798152],"type":"Point"}
}