{
  "type": "Feature",
  "properties": {
    "iso:country":"US",
    "sg:address":"52 Riverside Ave",
    "sg:city":"Lancaster",
    "sg:classifiers":[
        {
            "category":"Building & Trades",
            "subcategory":"Construction",
            "type":"Services"
        }
    ],
    "sg:phone":"+1   ",
    "sg:postcode":"17602",
    "sg:province":"PA",
    "sg:tags":[
        "hanging",
        "contractor"
    ],
    "wof:name":"Harmon Painting",
    "wof:placetype":"venue"
},
  "geometry": {"coordinates":[-76.27719999999999,40.042299],"type":"Point"}
}