{
  "type": "Feature",
  "properties": {
    "addr:full":"4747 Tackawanna St Philadelphia PA 19124",
    "addr:postcode":"4747;19124",
    "addr:street":"Tackawanna St",
    "iso:country":"US",
    "sg:address":"4747 Tackawanna St",
    "sg:city":"Philadelphia",
    "sg:classifiers":[
        {
            "category":"Real Estate",
            "subcategory":"Real Estate Agent",
            "type":"Services"
        }
    ],
    "sg:phone":"+1 215 684 5977",
    "sg:postcode":"19124",
    "sg:province":"PA",
    "sg:tags":[
        "authorities",
        "housing"
    ],
    "wof:name":"Philadelphia Housing Authority",
    "wof:placetype":"venue"
},
  "geometry": {"coordinates":[-75.07742500000001,40.014599],"type":"Point"}
}