{
  "type": "Feature",
  "properties": {
    "iso:country":"US",
    "sg:address":"41 N 3rd St",
    "sg:city":"Philadelphia",
    "sg:classifiers":[
        {
            "category":"Professional",
            "type":"Services"
        }
    ],
    "sg:phone":"+1 215 925 9050",
    "sg:postcode":"19106",
    "sg:province":"PA",
    "sg:tags":[
        "establishment"
    ],
    "wof:name":"Metropolitian Concierge",
    "wof:placetype":"venue"
},
  "geometry": {"coordinates":[-75.145419,39.950885],"type":"Point"}
}