{
  "type": "Feature",
  "properties": {
    "addr:full":"84 Colebrook Rd Middletown PA 17057",
    "addr:housenumber":"84",
    "addr:postcode":"17057",
    "addr:street":"Colebrook Rd",
    "iso:country":"US",
    "sg:address":"84 Colebrook Rd",
    "sg:city":"Middletown",
    "sg:classifiers":[
        {
            "category":"Building & Trades",
            "subcategory":"Construction",
            "type":"Services"
        }
    ],
    "sg:phone":"+1   ",
    "sg:postcode":"17057",
    "sg:province":"PA",
    "sg:tags":[
        "painting",
        "contractor"
    ],
    "wof:name":"Kostyak Painting Co",
    "wof:placetype":"venue"
},
  "geometry": {"coordinates":[-76.705258,40.196825],"type":"Point"}
}