{
  "type": "Feature",
  "properties": {
    "iso:country":"US",
    "sg:address":"1901 Butler St",
    "sg:city":"Easton",
    "sg:classifiers":[
        {
            "category":"Retail",
            "subcategory":"Auto Repair",
            "type":"Services"
        }
    ],
    "sg:phone":"+1 610 252 3112",
    "sg:postcode":"18042",
    "sg:province":"PA",
    "sg:tags":[
        "repairing",
        "automobile"
    ],
    "wof:name":"Ken's Garage",
    "wof:placetype":"venue"
},
  "geometry": {"coordinates":[-75.23901600000001,40.684514],"type":"Point"}
}