{
  "type": "Feature",
  "properties": {
    "iso:country":"US",
    "sg:address":"125 N Main St # 2",
    "sg:city":"Taylor",
    "sg:classifiers":[
        {
            "category":"Health Services",
            "subcategory":"Clinic",
            "type":"Services"
        },
        {
            "category":"Health Services",
            "subcategory":"Health Practitioner",
            "type":"Services"
        },
        {
            "category":"Health Services",
            "subcategory":"Chiropractor",
            "type":"Services"
        }
    ],
    "sg:phone":"+1 570 207 4238",
    "sg:postcode":"18517",
    "sg:province":"PA",
    "sg:tags":[
        "injury",
        "chiropractic",
        "therapist",
        "therapy",
        "treatment",
        "medicine",
        "sport",
        "physical"
    ],
    "sg:website":"http://www.wellness.com/dir/456455/chiropractor/pa/scranton/william-krah",
    "wof:name":"Krah William J",
    "wof:placetype":"venue"
},
  "geometry": {"coordinates":[-75.70919600000001,41.384189],"type":"Point"}
}