{
  "type": "Feature",
  "properties": {
    "iso:country":"US",
    "sg:address":"200 S Center St",
    "sg:city":"Ebensburg",
    "sg:classifiers":[
        {
            "category":"Government",
            "subcategory":"Office",
            "type":"Public Place"
        }
    ],
    "sg:phone":"+1 814 472 1606",
    "sg:postcode":"15931",
    "sg:province":"PA",
    "wof:name":"Cambria County Commissioners",
    "wof:placetype":"venue"
},
  "geometry": {"coordinates":[-78.72497799999999,40.484287],"type":"Point"}
}