{
  "type": "Feature",
  "properties": {
    "iso:country":"US",
    "sg:address":"1241 Carpenter St 3rd Fl",
    "sg:city":"Philadelphia",
    "sg:classifiers":[
        {
            "category":"Arts & Performance",
            "subcategory":"Art Gallery",
            "type":"Entertainment"
        }
    ],
    "sg:postcode":"19147",
    "sg:province":"PA",
    "sg:website":"www.artatsophi.com/",
    "wof:name":"Art@Sophi",
    "wof:placetype":"venue"
},
  "geometry": {"coordinates":[-75.163427,39.938686],"type":"Point"}
}