{
  "type": "Feature",
  "properties": {
    "iso:country":"US",
    "sg:address":"1238 Millersville Pike",
    "sg:city":"Lancaster",
    "sg:classifiers":[
        {
            "category":"Shopping",
            "subcategory":"Computers & Home Electronics",
            "type":"Retail Goods"
        }
    ],
    "sg:phone":"+1 717 299 5805",
    "sg:postcode":"17603",
    "sg:province":"PA",
    "sg:tags":[
        "equipment",
        "electronic",
        "supply"
    ],
    "sg:website":"www.radioshack.com",
    "wof:name":"Radio Shack",
    "wof:placetype":"venue"
},
  "geometry": {"coordinates":[-76.324173,40.028919],"type":"Point"}
}