{
  "type": "Feature",
  "properties": {
    "addr:full":"1203 Mall Run Rd Uniontown PA 15401",
    "addr:housenumber":"1203",
    "addr:postcode":"15401",
    "addr:street":"Mall Run Rd",
    "iso:country":"US",
    "sg:address":"1203 Mall Run Rd",
    "sg:city":"Uniontown",
    "sg:classifiers":[
        {
            "category":"Shopping",
            "subcategory":"Gifts & Souvenirs",
            "type":"Retail Goods"
        }
    ],
    "sg:phone":"+1 724 437 2420",
    "sg:postcode":"15401",
    "sg:province":"PA",
    "sg:tags":[
        "shop"
    ],
    "wof:name":"Hello Shop",
    "wof:placetype":"venue"
},
  "geometry": {"coordinates":[-79.74605,39.903667],"type":"Point"}
}