{
  "type": "Feature",
  "properties": {
    "addr:full":"1034 Spruce St Philadelphia PA 19107",
    "addr:housenumber":"1034",
    "addr:postcode":"19107",
    "addr:street":"Spruce St",
    "iso:country":"US",
    "sg:address":"1034 Spruce St",
    "sg:city":"Philadelphia",
    "sg:classifiers":[
        {
            "category":"Restaurant",
            "type":"Food & Drink"
        }
    ],
    "sg:phone":"+1 215 925 1706",
    "sg:postcode":"19107",
    "sg:province":"PA",
    "sg:tags":[
        "eating"
    ],
    "wof:name":"Wof & Tofu",
    "wof:placetype":"venue"
},
  "geometry": {"coordinates":[-75.158811,39.946254],"type":"Point"}
}