{
  "type": "Feature",
  "properties": {
    "addr:full":"3 Rockland Way Glenmoore PA 19343",
    "addr:housenumber":"3",
    "addr:postcode":"19343",
    "addr:street":"Rockland Way",
    "iso:country":"US",
    "sg:address":"3 Rockland Way",
    "sg:city":"Glenmoore",
    "sg:classifiers":[
        {
            "category":"Building & Trades",
            "subcategory":"Construction",
            "type":"Services"
        }
    ],
    "sg:phone":"+1   ",
    "sg:postcode":"19343",
    "sg:province":"PA",
    "sg:tags":[
        "carpentry",
        "contractor"
    ],
    "wof:name":"Mark S Elliott Carpentry",
    "wof:placetype":"venue"
},
  "geometry": {"coordinates":[-75.81836699999999,40.061008],"type":"Point"}
}