{
  "type": "Feature",
  "properties": {
    "iso:country":"US",
    "sg:address":"1201 Arbor Ct",
    "sg:city":"Quakertown",
    "sg:classifiers":[
        {
            "category":"Building & Trades",
            "subcategory":"Construction",
            "type":"Services"
        }
    ],
    "sg:phone":"+1   ",
    "sg:postcode":"18951",
    "sg:province":"PA",
    "sg:tags":[
        "contractor"
    ],
    "wof:name":"Walnut Bank Farm",
    "wof:placetype":"venue"
},
  "geometry": {"coordinates":[-75.34186099999999,40.451096],"type":"Point"}
}