{
  "type": "Feature",
  "properties": {
    "iso:country":"US",
    "sg:address":"240 S Pennell Rd",
    "sg:city":"Media",
    "sg:classifiers":[
        {
            "category":"Retail",
            "subcategory":"Auto Repair",
            "type":"Services"
        }
    ],
    "sg:phone":"+1   ",
    "sg:postcode":"19063",
    "sg:province":"PA",
    "sg:tags":[
        "general"
    ],
    "wof:name":"Chucks Red Barn Garage",
    "wof:placetype":"venue"
},
  "geometry": {"coordinates":[-75.437364,39.899612],"type":"Point"}
}