{
  "type": "Feature",
  "properties": {
    "iso:country":"US",
    "sg:address":"800 N 23rd St",
    "sg:city":"Philadelphia",
    "sg:classifiers":[
        {
            "category":"Communications",
            "subcategory":"Radio Station",
            "type":"Services"
        }
    ],
    "sg:phone":"+1 215 765 2727",
    "sg:postcode":"19130",
    "sg:province":"PA",
    "wof:name":"Ukrainian American Youth Association Cym",
    "wof:placetype":"venue"
},
  "geometry": {"coordinates":[-75.174797,39.969799],"type":"Point"}
}