{
  "type": "Feature",
  "properties": {
    "iso:country":"US",
    "sg:address":"10106 Valley Forge Cir",
    "sg:city":"King Of Prussia",
    "sg:classifiers":[
        {
            "category":"Health Services",
            "subcategory":"Optometrist",
            "type":"Services"
        }
    ],
    "sg:phone":"+1   ",
    "sg:postcode":"19406",
    "sg:province":"PA",
    "wof:name":"Marcus Steven E",
    "wof:placetype":"venue"
},
  "geometry": {"coordinates":[-75.41262399999999,40.106941],"type":"Point"}
}