{
  "type": "Feature",
  "properties": {
    "addr:full":"10403 Rte 322 Shippenville PA 16254",
    "addr:housenumber":"10403",
    "addr:postcode":"16254",
    "addr:street":"Rte 322 Shippenville",
    "iso:country":"US",
    "sg:address":"10403 Rte 322",
    "sg:city":"Shippenville",
    "sg:classifiers":[
        {
            "category":"Shopping",
            "subcategory":"Used Merchandise",
            "type":"Retail Goods"
        }
    ],
    "sg:phone":"+1 814 226 4420",
    "sg:postcode":"16254",
    "sg:province":"PA",
    "sg:tags":[
        "antique"
    ],
    "wof:name":"Clarion Antique Mall",
    "wof:placetype":"venue"
},
  "geometry": {"coordinates":[-79.424673,41.241794],"type":"Point"}
}