{
  "type": "Feature",
  "properties": {
    "addr:full":"606 Lexington Ave Warren PA 16365",
    "addr:housenumber":"606",
    "addr:postcode":"16365",
    "addr:street":"Lexington Ave",
    "iso:country":"US",
    "sg:address":"606 Lexington Ave",
    "sg:city":"Warren",
    "sg:classifiers":[
        {
            "category":"Wholesale",
            "subcategory":"Electrical",
            "type":"Manufacturing & Wholesale Goods"
        }
    ],
    "sg:phone":"+1   ",
    "sg:postcode":"16365",
    "sg:province":"PA",
    "sg:tags":[
        "bulb",
        "light"
    ],
    "wof:name":"Specialty Lamp International",
    "wof:placetype":"venue"
},
  "geometry": {"coordinates":[-79.135248,41.838266],"type":"Point"}
}