{
  "type": "Feature",
  "properties": {
    "iso:country":"US",
    "sg:address":"205 6th St",
    "sg:city":"Cresson",
    "sg:classifiers":[
        {
            "category":"Education",
            "subcategory":"School",
            "type":"Public Place"
        }
    ],
    "sg:phone":"+1 814 886 8166",
    "sg:postcode":"16630",
    "sg:province":"PA",
    "wof:name":"Penn Cambria Pre Primary",
    "wof:placetype":"venue"
},
  "geometry": {"coordinates":[-78.581014,40.463938],"type":"Point"}
}