{
  "type": "Feature",
  "properties": {
    "addr:full":"415 Pine Run Rd Linden PA 17744",
    "addr:housenumber":"415",
    "addr:postcode":"17744",
    "addr:street":"Pine Run Rd",
    "iso:country":"US",
    "sg:address":"415 Pine Run Rd",
    "sg:city":"Linden",
    "sg:classifiers":[
        {
            "category":"Food & Beverages",
            "subcategory":"Specialty",
            "type":"Retail Goods"
        }
    ],
    "sg:phone":"+1   ",
    "sg:postcode":"17744",
    "sg:province":"PA",
    "wof:name":"Ethel Donley",
    "wof:placetype":"venue"
},
  "geometry": {"coordinates":[-77.18446400000001,41.220568],"type":"Point"}
}