{
  "type": "Feature",
  "properties": {
    "addr:full":"7000 Old York Rd Philadelphia PA 19126",
    "addr:housenumber":"7000",
    "addr:postcode":"19126",
    "addr:street":"Old York Rd",
    "iso:country":"US",
    "sg:address":"7000 Old York Rd",
    "sg:city":"Philadelphia",
    "sg:classifiers":[
        {
            "category":"Organizations",
            "subcategory":"Religious Organization",
            "type":"Services"
        }
    ],
    "sg:phone":"+1 215 548 2304",
    "sg:postcode":"19126",
    "sg:province":"PA",
    "sg:tags":[
        "clergy"
    ],
    "wof:name":"Sang Man Lim",
    "wof:placetype":"venue"
},
  "geometry": {"coordinates":[-75.13764500000001,40.060324],"type":"Point"}
}