{
  "type": "Feature",
  "properties": {
    "iso:country":"US",
    "sg:address":"416 7th Ave",
    "sg:city":"Pittsburgh",
    "sg:classifiers":[
        {
            "category":"Autos & Motor Vehicles",
            "subcategory":"Automobile Sales",
            "type":"Retail Goods"
        }
    ],
    "sg:phone":"+1 412 244 1300",
    "sg:postcode":"15219",
    "sg:province":"PA",
    "sg:tags":[
        "car"
    ],
    "wof:name":"Bob's Auto Sales",
    "wof:placetype":"venue"
},
  "geometry": {"coordinates":[-79.99630000000001,40.442501],"type":"Point"}
}