{
  "type": "Feature",
  "properties": {
    "addr:full":"903 Franklin Mills Cir Philadelphia PA 19154",
    "addr:housenumber":"903",
    "addr:postcode":"19154",
    "addr:street":"Franklin Mills Cir",
    "iso:country":"US",
    "sg:address":"903 Franklin Mills Cir",
    "sg:city":"Philadelphia",
    "sg:classifiers":[
        {
            "category":"Place Of Worship",
            "subcategory":"Church",
            "type":"Public Place"
        },
        {
            "category":"Place Of Worship",
            "type":"Public Place"
        }
    ],
    "sg:phone":"+1 215 725 2230",
    "sg:postcode":"19154",
    "sg:province":"PA",
    "sg:tags":[
        "churches-non-denominational"
    ],
    "wof:name":"Bethel Fellowship Community Church",
    "wof:placetype":"venue"
},
  "geometry": {"coordinates":[-74.959328,40.08474],"type":"Point"}
}