{
  "type": "Feature",
  "properties": {
    "iso:country":"US",
    "sg:address":"150 Rainbow Ridge Ln",
    "sg:city":"Harmony",
    "sg:classifiers":[
        {
            "category":"Manufacturing",
            "subcategory":"Retail Goods",
            "type":"Manufacturing & Wholesale Goods"
        }
    ],
    "sg:phone":"+1   ",
    "sg:postcode":"16037",
    "sg:province":"PA",
    "sg:tags":[
        "marking",
        "devices",
        "mfg"
    ],
    "wof:name":"Manna Rubber Stamp",
    "wof:placetype":"venue"
},
  "geometry": {"coordinates":[-80.135957,40.83025],"type":"Point"}
}