{
  "type": "Feature",
  "properties": {
    "iso:country":"US",
    "sg:address":"4770 Liberty Ave",
    "sg:city":"Pittsburgh",
    "sg:classifiers":[
        {
            "category":"Restaurant",
            "type":"Food & Drink"
        }
    ],
    "sg:phone":"+1 412 605 0114",
    "sg:postcode":"15224",
    "sg:province":"PA",
    "wof:name":"Hermies Gyros",
    "wof:placetype":"venue"
},
  "geometry": {"coordinates":[-79.947378,40.460687],"type":"Point"}
}