{
  "type": "Feature",
  "properties": {
    "addr:full":"1175 Freeport Rd Pittsburgh PA 15238",
    "addr:housenumber":"1175",
    "addr:postcode":"15238",
    "addr:street":"Freeport Rd",
    "iso:country":"US",
    "sg:address":"1175 Freeport Rd",
    "sg:city":"Pittsburgh",
    "sg:classifiers":[
        {
            "category":"Ice Cream",
            "type":"Food & Drink"
        }
    ],
    "sg:menulink":"http://www.allmenus.com/pa/ohara/234952-ritas-ice-custard-happiness/menu/",
    "sg:phone":"+1 412 784 1549",
    "sg:postcode":"15238",
    "sg:province":"PA",
    "sg:tags":[
        "american"
    ],
    "wof:name":"Rita's Ice Custard Happiness",
    "wof:placetype":"venue"
},
  "geometry": {"coordinates":[-79.879938,40.487985],"type":"Point"}
}