{
  "type": "Feature",
  "properties": {
    "iso:country":"US",
    "sg:address":"144 Main St",
    "sg:city":"Landisville",
    "sg:classifiers":[
        {
            "category":"Shopping",
            "subcategory":"Clothing, Apparel, & Fashions",
            "type":"Retail Goods"
        }
    ],
    "sg:phone":"+1 717 898 9388",
    "sg:postcode":"17538",
    "sg:province":"PA",
    "sg:tags":[
        "salvage",
        "surplus",
        "merchandise"
    ],
    "wof:name":"Surplus Saver Inc",
    "wof:placetype":"venue"
},
  "geometry": {"coordinates":[-76.432374,40.103615],"type":"Point"}
}