{
  "type": "Feature",
  "properties": {
    "iso:country":"US",
    "sg:address":"9481 Lincoln Hwy",
    "sg:city":"Bedford",
    "sg:classifiers":[
        {
            "category":"Wholesale",
            "subcategory":"Painting Supplies",
            "type":"Manufacturing & Wholesale Goods"
        },
        {
            "category":"Manufacturing",
            "subcategory":"Tools & Machinery",
            "type":"Manufacturing & Wholesale Goods"
        },
        {
            "category":"Building & Trades",
            "subcategory":"Construction",
            "type":"Services"
        },
        {
            "category":"Home & Garden",
            "subcategory":"Building Materials",
            "type":"Retail Goods"
        },
        {
            "category":"Manufacturing",
            "subcategory":"Chemicals & Compounds",
            "type":"Manufacturing & Wholesale Goods"
        },
        {
            "category":"Autos & Motor Vehicles",
            "subcategory":"Auto Supplies",
            "type":"Retail Goods"
        },
        {
            "category":"Building & Trades",
            "subcategory":"Equipment Rental",
            "type":"Services"
        },
        {
            "category":"Manufacturing",
            "subcategory":"Building Materials",
            "type":"Manufacturing & Wholesale Goods"
        }
    ],
    "sg:phone":"+1 814 624 0047",
    "sg:postcode":"15522",
    "sg:province":"PA",
    "sg:tags":[
        "shop",
        "spraying",
        "wall",
        "automobile",
        "wallpaper",
        "coating",
        "contractor",
        "paint-wholesale",
        "paint",
        "body",
        "wallcoverings-installation",
        "wallcoverings",
        "improvement",
        "equipment-renting",
        "painter",
        "manufacturer"
    ],
    "sg:website":"http://www.citysearch.com/profile/external/8647204/bedford_pa/sherwin_williams.html?publisher=yellowpages&reference_id=1&placement=ypwebsitemip",
    "wof:name":"Sherwin-Williams",
    "wof:placetype":"venue"
},
  "geometry": {"coordinates":[-78.522961,40.036369],"type":"Point"}
}