{
  "type": "Feature",
  "properties": {
    "addr:full":"212 W Vine St New Wilmington PA 16142",
    "addr:housenumber":"212",
    "addr:postcode":"16142",
    "addr:street":"W Vine St",
    "iso:country":"US",
    "sg:address":"212 W Vine St",
    "sg:city":"New Wilmington",
    "sg:classifiers":[
        {
            "category":"Health Services",
            "subcategory":"Doctor",
            "type":"Services"
        }
    ],
    "sg:phone":"+1   ",
    "sg:postcode":"16142",
    "sg:province":"PA",
    "wof:name":"Kenneth C Woods DMD",
    "wof:placetype":"venue"
},
  "geometry": {"coordinates":[-80.335414,41.121347],"type":"Point"}
}