{
  "type": "Feature",
  "properties": {
    "iso:country":"US",
    "sg:address":"4 Grenwd Sq",
    "sg:city":"Bensalem",
    "sg:classifiers":[
        {
            "category":"Professional",
            "subcategory":"Lawyer & Legal Services",
            "type":"Services"
        }
    ],
    "sg:phone":"+1 215 638 9330",
    "sg:postcode":"19020",
    "sg:province":"PA",
    "sg:tags":[
        "divorce",
        "law",
        "family"
    ],
    "wof:name":"Groen Lamm Goldberg & Rubenstone Llc",
    "wof:placetype":"venue"
},
  "geometry": {"coordinates":[-74.944199,40.112598],"type":"Point"}
}