{
  "type": "Feature",
  "properties": {
    "iso:country":"US",
    "sg:address":"317 Limestone Rd",
    "sg:city":"Oxford",
    "sg:classifiers":[
        {
            "category":"Building & Trades",
            "subcategory":"Construction",
            "type":"Services"
        }
    ],
    "sg:phone":"+1 610 998 9220",
    "sg:postcode":"19363",
    "sg:province":"PA",
    "sg:tags":[
        "contractor"
    ],
    "wof:name":"Hunter Construction",
    "wof:placetype":"venue"
},
  "geometry": {"coordinates":[-75.974197,39.797546],"type":"Point"}
}