{
  "type": "Feature",
  "properties": {
    "iso:country":"US",
    "sg:address":"50 Virginia Ter",
    "sg:city":"Kingston",
    "sg:classifiers":[
        {
            "category":"Home & Garden",
            "subcategory":"Building Materials",
            "type":"Retail Goods"
        },
        {
            "category":"Building & Trades",
            "subcategory":"Construction",
            "type":"Services"
        }
    ],
    "sg:phone":"+1 570 288 3515",
    "sg:postcode":"18704",
    "sg:province":"PA",
    "sg:tags":[
        "concrete",
        "staining",
        "contractor"
    ],
    "wof:name":"William Bempkins Construction",
    "wof:placetype":"venue"
},
  "geometry": {"coordinates":[-75.880257,41.276562],"type":"Point"}
}