{
  "type": "Feature",
  "properties": {
    "iso:country":"US",
    "sg:address":"215 Chestnut Hill Rd",
    "sg:city":"Hanover",
    "sg:classifiers":[
        {
            "category":"Manufacturing",
            "subcategory":"Food",
            "type":"Manufacturing & Wholesale Goods"
        },
        {
            "category":"Farming",
            "subcategory":"Farm",
            "type":"Manufacturing & Wholesale Goods"
        }
    ],
    "sg:phone":"+1 717 359 7207",
    "sg:postcode":"17331",
    "sg:province":"PA",
    "sg:tags":[
        "corn",
        "product"
    ],
    "wof:name":"Lindsey, R Donald Farmer",
    "wof:placetype":"venue"
},
  "geometry": {"coordinates":[-77.037808,39.743394],"type":"Point"}
}