{
  "type": "Feature",
  "properties": {
    "iso:country":"US",
    "sg:address":"251 Mason Dr",
    "sg:city":"Ephrata",
    "sg:classifiers":[
        {
            "category":"Building & Trades",
            "subcategory":"Electrical",
            "type":"Services"
        }
    ],
    "sg:phone":"+1   ",
    "sg:postcode":"17522",
    "sg:province":"PA",
    "sg:tags":[
        "electrical",
        "contractor"
    ],
    "wof:name":"Lancaster Electric Company",
    "wof:placetype":"venue"
},
  "geometry": {"coordinates":[-76.18232500000001,40.171457],"type":"Point"}
}