{
  "type": "Feature",
  "properties": {
    "iso:country":"US",
    "sg:address":"450 Racetrack Rd",
    "sg:city":"Washington",
    "sg:classifiers":[
        {
            "category":"Professional",
            "subcategory":"Management & Consulting",
            "type":"Services"
        }
    ],
    "sg:phone":"+1   ",
    "sg:postcode":"15301",
    "sg:province":"PA",
    "wof:name":"Edstern Region Headquarters",
    "wof:placetype":"venue"
},
  "geometry": {"coordinates":[-80.197354,40.214383],"type":"Point"}
}