{
  "type": "Feature",
  "properties": {
    "addr:full":"137 E Market St York PA 17401",
    "addr:housenumber":"137",
    "addr:postcode":"17401",
    "addr:street":"E Market St",
    "iso:country":"US",
    "sg:address":"137 E Market St",
    "sg:city":"York",
    "sg:classifiers":[
        {
            "category":"Organizations",
            "subcategory":"Religious Organization",
            "type":"Services"
        }
    ],
    "sg:phone":"+1   ",
    "sg:postcode":"17401",
    "sg:province":"PA",
    "wof:name":"Pennsylvania Immigration",
    "wof:placetype":"venue"
},
  "geometry": {"coordinates":[-76.724502,39.963508],"type":"Point"}
}