{
  "type": "Feature",
  "properties": {
    "addr:full":"4204 Greenridge Rd Pittsburgh PA 15234",
    "addr:housenumber":"4204",
    "addr:postcode":"15234",
    "addr:street":"Greenridge Rd",
    "iso:country":"US",
    "sg:address":"4204 Greenridge Rd",
    "sg:city":"Pittsburgh",
    "sg:classifiers":[
        {
            "category":"Professional",
            "subcategory":"Business Services",
            "type":"Services"
        }
    ],
    "sg:phone":"+1 412 563 4442",
    "sg:postcode":"15234",
    "sg:province":"PA",
    "sg:tags":[
        "building",
        "home",
        "inspector",
        "inspection"
    ],
    "wof:name":"Falcone Building Inspections",
    "wof:placetype":"venue"
},
  "geometry": {"coordinates":[-80.035202,40.356701],"type":"Point"}
}