{
  "type": "Feature",
  "properties": {
    "addr:full":"278 Cope Rd Perryopolis PA 15473",
    "addr:housenumber":"278",
    "addr:postcode":"15473",
    "addr:street":"Cope Rd",
    "iso:country":"US",
    "sg:address":"278 Cope Rd",
    "sg:city":"Perryopolis",
    "sg:classifiers":[
        {
            "category":"Retail",
            "subcategory":"Repair Shop",
            "type":"Services"
        }
    ],
    "sg:phone":"+1 724 326 8860",
    "sg:postcode":"15473",
    "sg:province":"PA",
    "sg:tags":[
        "taxidermist"
    ],
    "wof:name":"Whitetail Taxidermy",
    "wof:placetype":"venue"
},
  "geometry": {"coordinates":[-79.79169899999999,40.0803],"type":"Point"}
}