{
  "type": "Feature",
  "properties": {
    "addr:full":"260 Race St Catasauqua PA 18032",
    "addr:housenumber":"260",
    "addr:postcode":"18032",
    "addr:street":"Race St",
    "iso:country":"US",
    "sg:address":"260 Race St",
    "sg:city":"Catasauqua",
    "sg:classifiers":[
        {
            "category":"Manufacturing",
            "subcategory":"Metals",
            "type":"Manufacturing & Wholesale Goods"
        }
    ],
    "sg:phone":"+1 610 264 2815",
    "sg:postcode":"18032",
    "sg:province":"PA",
    "sg:tags":[
        "plate",
        "work",
        "fabricated",
        "mfg"
    ],
    "wof:name":"Allentown Steel Fabricating Co",
    "wof:placetype":"venue"
},
  "geometry": {"coordinates":[-75.46563500000001,40.650457],"type":"Point"}
}