{
  "type": "Feature",
  "properties": {
    "iso:country":"US",
    "sg:address":"1221 Fairmount Ave # 210",
    "sg:city":"Philadelphia",
    "sg:classifiers":[
        {
            "category":"Organizations",
            "subcategory":"Religious Organization",
            "type":"Services"
        }
    ],
    "sg:phone":"+1 484 661 0393",
    "sg:postcode":"19123",
    "sg:province":"PA",
    "wof:name":"Tribe Of Life",
    "wof:placetype":"venue"
},
  "geometry": {"coordinates":[-75.156997,39.966196],"type":"Point"}
}