{
  "type": "Feature",
  "properties": {
    "iso:country":"US",
    "sg:address":"1590 Medical Dr",
    "sg:city":"Pottstown",
    "sg:classifiers":[
        {
            "category":"Health Services",
            "subcategory":"Doctor",
            "type":"Services"
        }
    ],
    "sg:phone":"+1   ",
    "sg:postcode":"19464",
    "sg:province":"PA",
    "wof:name":"Galletto L J DDS",
    "wof:placetype":"venue"
},
  "geometry": {"coordinates":[-75.613338,40.239046],"type":"Point"}
}