{
  "type": "Feature",
  "properties": {
    "iso:country":"US",
    "sg:address":"3839 Bath Pike",
    "sg:city":"Bethlehem",
    "sg:classifiers":[
        {
            "category":"Retail",
            "subcategory":"Repair Shop",
            "type":"Services"
        }
    ],
    "sg:phone":"+1 610 758 9430",
    "sg:postcode":"18017",
    "sg:province":"PA",
    "sg:tags":[
        "appliance"
    ],
    "wof:name":"Mark's Appliance Svc",
    "wof:placetype":"venue"
},
  "geometry": {"coordinates":[-75.385304,40.668554],"type":"Point"}
}