{
  "type": "Feature",
  "properties": {
    "addr:full":"453 Center Oak Dr Pittsburgh PA 15237",
    "addr:housenumber":"453",
    "addr:postcode":"15237",
    "addr:street":"Center Oak Dr",
    "iso:country":"US",
    "sg:address":"453 Center Oak Dr",
    "sg:city":"Pittsburgh",
    "sg:classifiers":[
        {
            "category":"Professional",
            "subcategory":"Management & Consulting",
            "type":"Services"
        }
    ],
    "sg:phone":"+1 412 366 2441",
    "sg:postcode":"15237",
    "sg:province":"PA",
    "sg:tags":[
        "food",
        "consultant",
        "beverage",
        "facility"
    ],
    "sg:website":"http://www.sensorydirection.com",
    "wof:name":"Sensory Direction",
    "wof:placetype":"venue"
},
  "geometry": {"coordinates":[-80.026245,40.583771],"type":"Point"}
}