{
  "type": "Feature",
  "properties": {
    "iso:country":"US",
    "sg:address":"407 E Pennsylvania Blvd",
    "sg:city":"Feastervl Trvs",
    "sg:classifiers":[
        {
            "category":"Professional",
            "subcategory":"Advertising",
            "type":"Services"
        },
        {
            "category":"Arena",
            "subcategory":"Sports Club",
            "type":"Entertainment"
        }
    ],
    "sg:phone":"+1 215 364 9000",
    "sg:postcode":"19053",
    "sg:province":"PA",
    "sg:tags":[
        "manager",
        "recruiter",
        "promoter"
    ],
    "wof:name":"Joe Hand Promotions Inc",
    "wof:placetype":"venue"
},
  "geometry": {"coordinates":[-75.01006099999999,40.151749],"type":"Point"}
}