{
  "type": "Feature",
  "properties": {
    "iso:country":"US",
    "sg:address":"18 E Centre St",
    "sg:city":"Shenandoah",
    "sg:classifiers":[
        {
            "category":"Personal",
            "subcategory":"Beauty Salon",
            "type":"Services"
        }
    ],
    "sg:phone":"+1 570 462 2070",
    "sg:postcode":"17976",
    "sg:province":"PA",
    "wof:name":"Melissa's Hair Design",
    "wof:placetype":"venue"
},
  "geometry": {"coordinates":[-76.201211,40.820486],"type":"Point"}
}