{
  "type": "Feature",
  "properties": {
    "iso:country":"US",
    "sg:address":"530 E Swedesford Rd",
    "sg:city":"Wayne",
    "sg:classifiers":[
        {
            "category":"Professional",
            "subcategory":"Employment Agencies",
            "type":"Services"
        },
        {
            "category":"Professional",
            "subcategory":"Computer Services",
            "type":"Services"
        }
    ],
    "sg:phone":"+1 610 687 1409",
    "sg:postcode":"19087",
    "sg:province":"PA",
    "sg:tags":[
        "consultant",
        "search",
        "executive",
        "consulting"
    ],
    "wof:name":"Conversion Sciences Inc",
    "wof:placetype":"venue"
},
  "geometry": {"coordinates":[-75.419909,40.077348],"type":"Point"}
}