{
  "type": "Feature",
  "properties": {
    "iso:country":"US",
    "sg:address":"517 S Main St",
    "sg:city":"Du Bois",
    "sg:classifiers":[
        {
            "category":"Building & Trades",
            "subcategory":"Construction",
            "type":"Services"
        }
    ],
    "sg:phone":"+1 814 371 8948",
    "sg:postcode":"15801",
    "sg:province":"PA",
    "sg:tags":[
        "general",
        "contractor"
    ],
    "wof:name":"Spicher Construction",
    "wof:placetype":"venue"
},
  "geometry": {"coordinates":[-78.770837,41.116124],"type":"Point"}
}