{
  "type": "Feature",
  "properties": {
    "addr:full":"4110 Juneau Rd Punxsutawney PA 15767",
    "addr:housenumber":"4110",
    "addr:postcode":"15767",
    "addr:street":"Juneau Rd",
    "iso:country":"US",
    "sg:address":"4110 Juneau Rd",
    "sg:city":"Punxsutawney",
    "sg:classifiers":[
        {
            "category":"Organizations",
            "subcategory":"Religious Organization",
            "type":"Services"
        }
    ],
    "sg:phone":"+1 814 938 3145",
    "sg:postcode":"15767",
    "sg:province":"PA",
    "sg:tags":[
        "church"
    ],
    "wof:name":"Valley Chapel United Meth Ch",
    "wof:placetype":"venue"
},
  "geometry": {"coordinates":[-78.95371400000001,40.903299],"type":"Point"}
}