{
  "type": "Feature",
  "properties": {
    "iso:country":"US",
    "sg:address":"980 Seely Run Rd",
    "sg:city":"Jersey Shore",
    "sg:classifiers":[
        {
            "category":"Farming",
            "subcategory":"Dairy Farm",
            "type":"Manufacturing & Wholesale Goods"
        }
    ],
    "sg:phone":"+1   ",
    "sg:postcode":"17740",
    "sg:province":"PA",
    "wof:name":"English Dairy Farm",
    "wof:placetype":"venue"
},
  "geometry": {"coordinates":[-77.207984,41.249432],"type":"Point"}
}