{
  "type": "Feature",
  "properties": {
    "iso:country":"US",
    "sg:address":"7763 Old York Rd",
    "sg:city":"Elkins Park",
    "sg:classifiers":[
        {
            "category":"Recreation",
            "type":"Entertainment"
        }
    ],
    "sg:phone":"+1   ",
    "sg:postcode":"19027",
    "sg:province":"PA",
    "sg:tags":[
        "camp",
        "day"
    ],
    "wof:name":"Adath Jeshurun Synagogue",
    "wof:placetype":"venue"
},
  "geometry": {"coordinates":[-75.13387,40.070701],"type":"Point"}
}