{
  "type": "Feature",
  "properties": {
    "iso:country":"US",
    "sg:address":"823 W Walnut St",
    "sg:city":"Allentown",
    "sg:classifiers":[
        {
            "category":"Health Services",
            "subcategory":"Doctor",
            "type":"Services"
        }
    ],
    "sg:phone":"+1 484 664 7300",
    "sg:postcode":"18102",
    "sg:province":"PA",
    "wof:name":"Saavedra Geraldo A MD",
    "wof:placetype":"venue"
},
  "geometry": {"coordinates":[-75.473855,40.600181],"type":"Point"}
}