{
  "type": "Feature",
  "properties": {
    "addr:full":"27 Walden Rd Lebanon PA 17042",
    "addr:housenumber":"27",
    "addr:postcode":"17042",
    "addr:street":"Walden Rd",
    "iso:country":"US",
    "sg:address":"27 Walden Rd",
    "sg:city":"Lebanon",
    "sg:classifiers":[
        {
            "category":"Organizations",
            "subcategory":"Community Association",
            "type":"Services"
        }
    ],
    "sg:phone":"+1   ",
    "sg:postcode":"17042",
    "sg:province":"PA",
    "wof:name":"Carlton Square Hm Owners Assn",
    "wof:placetype":"venue"
},
  "geometry": {"coordinates":[-76.455906,40.326474],"type":"Point"}
}