{
  "type": "Feature",
  "properties": {
    "addr:full":"35 Diller Ave New Holland PA 17557",
    "addr:housenumber":"35",
    "addr:postcode":"17557",
    "addr:street":"Diller Ave",
    "iso:country":"US",
    "sg:address":"35 Diller Ave",
    "sg:city":"New Holland",
    "sg:classifiers":[
        {
            "category":"Cinema",
            "subcategory":"Movie Theater",
            "type":"Entertainment"
        }
    ],
    "sg:phone":"+1 717 355 2915",
    "sg:postcode":"17557",
    "sg:province":"PA",
    "wof:name":"Imagination Children's Theatre",
    "wof:placetype":"venue"
},
  "geometry": {"coordinates":[-76.096538,40.099587],"type":"Point"}
}