{
  "type": "Feature",
  "properties": {
    "iso:country":"US",
    "sg:address":"10330 Perry Hwy",
    "sg:city":"Wexford",
    "sg:classifiers":[
        {
            "category":"Autos & Motor Vehicles",
            "subcategory":"Automobile Sales",
            "type":"Retail Goods"
        }
    ],
    "sg:phone":"+1 724 934 4203",
    "sg:postcode":"15090",
    "sg:province":"PA",
    "sg:tags":[
        "car",
        "dealer"
    ],
    "wof:name":"Scharpf Motor Cars",
    "wof:placetype":"venue"
},
  "geometry": {"coordinates":[-80.053104,40.609584],"type":"Point"}
}