{
  "type": "Feature",
  "properties": {
    "addr:full":"328 Sunbury St Minersville PA 17954",
    "addr:housenumber":"328",
    "addr:postcode":"17954",
    "addr:street":"Sunbury St",
    "iso:country":"US",
    "sg:address":"328 Sunbury St",
    "sg:city":"Minersville",
    "sg:classifiers":[
        {
            "category":"Retail",
            "subcategory":"Funeral Services",
            "type":"Services"
        }
    ],
    "sg:phone":"+1 570 544 6775",
    "sg:postcode":"17954",
    "sg:province":"PA",
    "sg:tags":[
        "director"
    ],
    "wof:name":"Donald J Butler Funeral Home",
    "wof:placetype":"venue"
},
  "geometry": {"coordinates":[-76.263159,40.691655],"type":"Point"}
}