{
  "type": "Feature",
  "properties": {
    "iso:country":"US",
    "sg:address":"339 Pontiac Ave",
    "sg:city":"Pittsburgh",
    "sg:classifiers":[
        {
            "category":"Building & Trades",
            "subcategory":"Construction",
            "type":"Services"
        }
    ],
    "sg:phone":"+1   ",
    "sg:postcode":"15237",
    "sg:province":"PA",
    "sg:tags":[
        "residential"
    ],
    "wof:name":"William E Hospodor Inc",
    "wof:placetype":"venue"
},
  "geometry": {"coordinates":[-80.042771,40.56833],"type":"Point"}
}