{
  "type": "Feature",
  "properties": {
    "addr:full":"1135 W Cheltenham Ave Elkins Park PA 19027",
    "addr:housenumber":"1135",
    "addr:postcode":"19027",
    "addr:street":"W Cheltenham Ave",
    "iso:country":"US",
    "sg:address":"1135 W Cheltenham Ave",
    "sg:city":"Elkins Park",
    "sg:classifiers":[
        {
            "category":"Health Services",
            "subcategory":"Health Practitioner",
            "type":"Services"
        }
    ],
    "sg:phone":"+1 215 635 3393",
    "sg:postcode":"19027",
    "sg:province":"PA",
    "sg:tags":[
        "nutritionist"
    ],
    "wof:name":"Insung Natural Of Pa",
    "wof:placetype":"venue"
},
  "geometry": {"coordinates":[-75.13373199999999,40.059999],"type":"Point"}
}