{
  "type": "Feature",
  "properties": {
    "iso:country":"US",
    "sg:address":"309 2nd Ave",
    "sg:city":"Jessup",
    "sg:classifiers":[
        {
            "category":"Bars & Pubs",
            "type":"Food & Drink"
        }
    ],
    "sg:phone":"+1 570 489 1242",
    "sg:postcode":"18434",
    "sg:province":"PA",
    "sg:tags":[
        "drinking"
    ],
    "wof:name":"Adams 2nd Ave",
    "wof:placetype":"venue"
},
  "geometry": {"coordinates":[-75.568128,41.475161],"type":"Point"}
}