{
  "type": "Feature",
  "properties": {
    "iso:country":"US",
    "sg:address":"347 W Main St",
    "sg:city":"Mount Joy",
    "sg:classifiers":[
        {
            "category":"Retail",
            "subcategory":"Auto Repair",
            "type":"Services"
        }
    ],
    "sg:phone":"+1   ",
    "sg:postcode":"17552",
    "sg:province":"PA",
    "sg:tags":[
        "automotive"
    ],
    "wof:name":"Daggett Automotive Serv Inc",
    "wof:placetype":"venue"
},
  "geometry": {"coordinates":[-76.512317,40.112046],"type":"Point"}
}