{
  "type": "Feature",
  "properties": {
    "iso:country":"US",
    "sg:address":"247 Market St",
    "sg:city":"Philadelphia",
    "sg:classifiers":[
        {
            "category":"Bars & Pubs",
            "type":"Food & Drink"
        }
    ],
    "sg:phone":"+1 215 413 1433",
    "sg:postcode":"19106",
    "sg:province":"PA",
    "sg:website":"www.lucys215.com",
    "wof:name":"Lucy's Hat Shop",
    "wof:placetype":"venue"
},
  "geometry": {"coordinates":[-75.1455,39.950001],"type":"Point"}
}