{
  "type": "Feature",
  "properties": {
    "addr:full":"1110 Valleyview Dr Lawrence PA 15055",
    "addr:housenumber":"1110",
    "addr:postcode":"15055",
    "addr:street":"Valleyview Dr",
    "iso:country":"US",
    "sg:address":"1110 Valleyview Dr",
    "sg:city":"Lawrence",
    "sg:classifiers":[
        {
            "category":"Professional",
            "subcategory":"Management & Consulting",
            "type":"Services"
        }
    ],
    "sg:phone":"+1 724 873 1814",
    "sg:postcode":"15055",
    "sg:province":"PA",
    "sg:tags":[
        "consultant"
    ],
    "wof:name":"Dls Management, Inc.",
    "wof:placetype":"venue"
},
  "geometry": {"coordinates":[-80.130894,40.305808],"type":"Point"}
}