{
  "type": "Feature",
  "properties": {
    "iso:country":"US",
    "sg:address":"440 Pellis Rd",
    "sg:city":"Greensburg",
    "sg:classifiers":[
        {
            "category":"Shopping",
            "type":"Retail Goods"
        }
    ],
    "sg:phone":"+1 724 834 9117",
    "sg:postcode":"15601",
    "sg:province":"PA",
    "sg:tags":[
        "hearing",
        "equipment",
        "supply",
        "impaired"
    ],
    "wof:name":"Beltone Hearing Aid Ctr",
    "wof:placetype":"venue"
},
  "geometry": {"coordinates":[-79.520263,40.295959],"type":"Point"}
}