{
  "type": "Feature",
  "properties": {
    "iso:country":"US",
    "sg:address":"139 W Market St",
    "sg:city":"Clearfield",
    "sg:classifiers":[
        {
            "category":"Shopping",
            "subcategory":"Gifts & Souvenirs",
            "type":"Retail Goods"
        }
    ],
    "sg:phone":"+1   ",
    "sg:postcode":"16830",
    "sg:province":"PA",
    "wof:name":"Your Party & Event Center",
    "wof:placetype":"venue"
},
  "geometry": {"coordinates":[-78.44215,41.022151],"type":"Point"}
}