{
  "type": "Feature",
  "properties": {
    "iso:country":"US",
    "sg:address":"1042 Tenby Rd",
    "sg:city":"Berwyn",
    "sg:classifiers":[
        {
            "category":"Professional",
            "subcategory":"Engineering",
            "type":"Services"
        }
    ],
    "sg:phone":"+1   ",
    "sg:postcode":"19312",
    "sg:province":"PA",
    "wof:name":"Kachele Group The",
    "wof:placetype":"venue"
},
  "geometry": {"coordinates":[-75.43436699999999,40.02393],"type":"Point"}
}