{
  "type": "Feature",
  "properties": {
    "iso:country":"US",
    "sg:address":"325 Chestnut St",
    "sg:city":"Philadelphia",
    "sg:classifiers":[
        {
            "category":"Restaurant",
            "type":"Food & Drink"
        }
    ],
    "sg:phone":"+1   ",
    "sg:postcode":"19106",
    "sg:province":"PA",
    "sg:tags":[
        "eating"
    ],
    "wof:name":"D&A",
    "wof:placetype":"venue"
},
  "geometry": {"coordinates":[-75.147273,39.948863],"type":"Point"}
}