{
  "type": "Feature",
  "properties": {
    "addr:full":"2548 Macarthur Rd Whitehall PA 18052",
    "addr:housenumber":"2548",
    "addr:postcode":"18052",
    "addr:street":"Macarthur Rd",
    "iso:country":"US",
    "sg:address":"2548 Macarthur Rd",
    "sg:city":"Whitehall",
    "sg:classifiers":[
        {
            "category":"Retail",
            "subcategory":"Portrait Studio",
            "type":"Services"
        }
    ],
    "sg:phone":"+1 610 433 1660",
    "sg:postcode":"18052",
    "sg:province":"PA",
    "sg:tags":[
        "photographer"
    ],
    "sg:website":"www.lindelle.com",
    "wof:name":"Lindelle Studios",
    "wof:placetype":"venue"
},
  "geometry": {"coordinates":[-75.49186400000001,40.643541],"type":"Point"}
}