{
  "type": "Feature",
  "properties": {
    "iso:country":"US",
    "sg:address":"1041 Reading Ave",
    "sg:city":"Boyertown",
    "sg:classifiers":[
        {
            "category":"Wholesale",
            "subcategory":"Durable Goods & Equipment",
            "type":"Manufacturing & Wholesale Goods"
        }
    ],
    "sg:phone":"+1 610 367 0076",
    "sg:postcode":"19512",
    "sg:province":"PA",
    "sg:tags":[
        "used",
        "merchandise"
    ],
    "wof:name":"Greshville Antiques",
    "wof:placetype":"venue"
},
  "geometry": {"coordinates":[-75.668616,40.317913],"type":"Point"}
}