{
  "type": "Feature",
  "properties": {
    "iso:country":"US",
    "sg:address":"602 Cornwall Rd",
    "sg:city":"Lebanon",
    "sg:classifiers":[
        {
            "category":"Retail",
            "subcategory":"Veterinary Services",
            "type":"Services"
        }
    ],
    "sg:phone":"+1   ",
    "sg:postcode":"17042",
    "sg:province":"PA",
    "wof:name":"Animal Hospital of Lebanon",
    "wof:placetype":"venue"
},
  "geometry": {"coordinates":[-76.425816,40.330841],"type":"Point"}
}