{
  "type": "Feature",
  "properties": {
    "addr:full":"430 Centerville Rd Gordonville PA 17529",
    "addr:housenumber":"430",
    "addr:postcode":"17529",
    "addr:street":"Centerville Rd",
    "iso:country":"US",
    "sg:address":"430 Centerville Rd",
    "sg:city":"Gordonville",
    "sg:classifiers":[
        {
            "category":"Wholesale",
            "subcategory":"Furniture",
            "type":"Manufacturing & Wholesale Goods"
        }
    ],
    "sg:phone":"+1 717 355 9414",
    "sg:postcode":"17529",
    "sg:province":"PA",
    "sg:tags":[
        "custom"
    ],
    "wof:name":"J & S Furniture",
    "wof:placetype":"venue"
},
  "geometry": {"coordinates":[-76.112852,40.059578],"type":"Point"}
}