{
  "type": "Feature",
  "properties": {
    "iso:country":"US",
    "sg:address":"3445 5th Ave",
    "sg:city":"North Versailles",
    "sg:classifiers":[
        {
            "category":"Retail",
            "subcategory":"Auto Repair",
            "type":"Services"
        }
    ],
    "sg:phone":"+1 412 664 1856",
    "sg:postcode":"15137",
    "sg:province":"PA",
    "sg:tags":[
        "repairing",
        "automobile"
    ],
    "wof:name":"Security Auto Svc",
    "wof:placetype":"venue"
},
  "geometry": {"coordinates":[-79.81943200000001,40.367135],"type":"Point"}
}