{
  "type": "Feature",
  "properties": {
    "iso:country":"US",
    "sg:address":"4670 Schantz Rd",
    "sg:city":"Allentown",
    "sg:classifiers":[
        {
            "category":"Shopping",
            "subcategory":"Gifts & Souvenirs",
            "type":"Retail Goods"
        }
    ],
    "sg:phone":"+1   ",
    "sg:postcode":"18104",
    "sg:province":"PA",
    "sg:tags":[
        "cards",
        "greeting"
    ],
    "wof:name":"The Spinning Wheel",
    "wof:placetype":"venue"
},
  "geometry": {"coordinates":[-75.55343499999999,40.578064],"type":"Point"}
}