{
  "type": "Feature",
  "properties": {
    "addr:full":"2700 Saw Mill Run Blvd Pittsburgh PA 15234",
    "addr:housenumber":"2700",
    "addr:postcode":"15234",
    "addr:street":"Saw Mill Run Blvd",
    "iso:country":"US",
    "sg:address":"2700 Saw Mill Run Blvd",
    "sg:city":"Pittsburgh",
    "sg:classifiers":[
        {
            "category":"Wholesale",
            "subcategory":"Hardware",
            "type":"Manufacturing & Wholesale Goods"
        }
    ],
    "sg:phone":"+1 412 884 4800",
    "sg:postcode":"15234",
    "sg:province":"PA",
    "sg:tags":[
        "supply",
        "fixture",
        "heating",
        "equipment",
        "fitting",
        "plumbing"
    ],
    "wof:name":"Three Brothers Plumbing Sups",
    "wof:placetype":"venue"
},
  "geometry": {"coordinates":[-79.994033,40.379773],"type":"Point"}
}