{
  "type": "Feature",
  "properties": {
    "iso:country":"US",
    "sg:address":"1432 Rte 66",
    "sg:city":"New Bethlehem",
    "sg:classifiers":[
        {
            "category":"Manufacturing",
            "subcategory":"Tools & Machinery",
            "type":"Manufacturing & Wholesale Goods"
        }
    ],
    "sg:phone":"+1 814 275 2000",
    "sg:postcode":"16242",
    "sg:province":"PA",
    "sg:tags":[
        "machine",
        "shop"
    ],
    "wof:name":"Valco Machine Svc",
    "wof:placetype":"venue"
},
  "geometry": {"coordinates":[-79.33135799999999,41.012122],"type":"Point"}
}