{
  "type": "Feature",
  "properties": {
    "addr:full":"130 2nd St Bridgeport PA 19405",
    "addr:housenumber":"130",
    "addr:postcode":"19405",
    "addr:street":"2Nd St",
    "iso:country":"US",
    "sg:address":"130 2nd St",
    "sg:city":"Bridgeport",
    "sg:classifiers":[
        {
            "category":"Organizations",
            "subcategory":"Religious Organization",
            "type":"Services"
        }
    ],
    "sg:phone":"+1   ",
    "sg:postcode":"19405",
    "sg:province":"PA",
    "wof:name":"Living Word Assembly of God",
    "wof:placetype":"venue"
},
  "geometry": {"coordinates":[-75.344613,40.107403],"type":"Point"}
}