{
  "type": "Feature",
  "properties": {
    "addr:full":"1250 Furnace Rd Airville PA 17302",
    "addr:housenumber":"1250",
    "addr:postcode":"17302",
    "addr:street":"Furnace Rd",
    "iso:country":"US",
    "sg:address":"1250 Furnace Rd",
    "sg:city":"Airville",
    "sg:classifiers":[
        {
            "category":"Organizations",
            "subcategory":"Professional Association",
            "type":"Services"
        }
    ],
    "sg:phone":"+1 610 286 0388",
    "sg:postcode":"17302",
    "sg:province":"PA",
    "wof:name":"Haycreek Valley Historical",
    "wof:placetype":"venue"
},
  "geometry": {"coordinates":[-76.386836,39.887011],"type":"Point"}
}