{
  "type": "Feature",
  "properties": {
    "iso:country":"US",
    "sg:address":"2289 Barrett Rd",
    "sg:city":"Woodland",
    "sg:classifiers":[
        {
            "category":"Government",
            "subcategory":"Office",
            "type":"Public Place"
        }
    ],
    "sg:phone":"+1 814 857 7057",
    "sg:postcode":"16881",
    "sg:province":"PA",
    "sg:tags":[
        "city",
        "taxation"
    ],
    "wof:name":"Bradford Twp Tax Office",
    "wof:placetype":"venue"
},
  "geometry": {"coordinates":[-78.349237,41.010151],"type":"Point"}
}