{
  "type": "Feature",
  "properties": {
    "iso:country":"US",
    "sg:address":"301 Grant St Level Three",
    "sg:city":"Pittsburgh",
    "sg:classifiers":[
        {
            "category":"Restaurant",
            "type":"Food & Drink"
        }
    ],
    "sg:phone":"+1 412 392 0225",
    "sg:postcode":"15219",
    "sg:province":"PA",
    "sg:tags":[
        "italian"
    ],
    "sg:website":"www.paradisoristorante.biz",
    "wof:name":"Paradiso Ristorante",
    "wof:placetype":"venue"
},
  "geometry": {"coordinates":[-79.998815,40.438126],"type":"Point"}
}