{
  "type": "Feature",
  "properties": {
    "iso:country":"US",
    "sg:address":"717 15th St",
    "sg:city":"Franklin",
    "sg:classifiers":[
        {
            "category":"Retail",
            "subcategory":"Auto Repair",
            "type":"Services"
        }
    ],
    "sg:phone":"+1 814 432 7734",
    "sg:postcode":"16323",
    "sg:province":"PA",
    "sg:tags":[
        "body",
        "automobile",
        "painting"
    ],
    "wof:name":"Auto Body Works",
    "wof:placetype":"venue"
},
  "geometry": {"coordinates":[-79.836918,41.394978],"type":"Point"}
}