{
  "type": "Feature",
  "properties": {
    "iso:country":"US",
    "sg:address":"1885 E Pleasant Valley Blvd",
    "sg:city":"Altoona",
    "sg:classifiers":[
        {
            "category":"Building & Trades",
            "subcategory":"Equipment Rental",
            "type":"Services"
        },
        {
            "category":"Communications",
            "type":"Services"
        },
        {
            "category":"Shopping",
            "subcategory":"Computers & Home Electronics",
            "type":"Retail Goods"
        }
    ],
    "sg:phone":"+1 814 944 4596",
    "sg:postcode":"16602",
    "sg:province":"PA",
    "sg:tags":[
        "sound",
        "audio-visual",
        "leasing",
        "system",
        "equipment-renting"
    ],
    "sg:website":"http://www.galaxysoundinc.com",
    "wof:name":"Galaxy SOund & COmmunications, Ic",
    "wof:placetype":"venue"
},
  "geometry": {"coordinates":[-78.391707,40.50003],"type":"Point"}
}