{
  "type": "Feature",
  "properties": {
    "addr:full":"700 Scranton Carbondale Hwy Eynon PA 18403",
    "addr:housenumber":"700",
    "addr:postcode":"18403",
    "addr:street":"Scranton Carbondale Hwy",
    "iso:country":"US",
    "sg:address":"700 Scranton Carbondale Hwy",
    "sg:city":"Eynon",
    "sg:classifiers":[
        {
            "category":"Retail",
            "subcategory":"Auto Rental",
            "type":"Services"
        }
    ],
    "sg:phone":"+1 570 876 5896",
    "sg:postcode":"18403",
    "sg:province":"PA",
    "sg:tags":[
        "renting",
        "truck",
        "leasing"
    ],
    "wof:name":"U-Haul Co",
    "wof:placetype":"venue"
},
  "geometry": {"coordinates":[-75.581288,41.50044],"type":"Point"}
}