{
  "type": "Feature",
  "properties": {
    "iso:country":"US",
    "sg:address":"55 Snyder Ln",
    "sg:city":"Ephrata",
    "sg:classifiers":[
        {
            "category":"Shopping",
            "subcategory":"Mobile Phones",
            "type":"Retail Goods"
        },
        {
            "category":"Building & Trades",
            "subcategory":"Construction",
            "type":"Services"
        }
    ],
    "sg:phone":"+1 717 733 7304",
    "sg:postcode":"17522",
    "sg:province":"PA",
    "sg:tags":[
        "manufactured",
        "housing-communities",
        "home"
    ],
    "wof:name":"Green Meadows Mobile Homes",
    "wof:placetype":"venue"
},
  "geometry": {"coordinates":[-76.240891,40.215721],"type":"Point"}
}