{
  "type": "Feature",
  "properties": {
    "addr:full":"513 Allentown Rd Souderton PA 18964",
    "addr:housenumber":"513",
    "addr:postcode":"18964",
    "addr:street":"Allentown Rd",
    "iso:country":"US",
    "sg:address":"513 Allentown Rd",
    "sg:city":"Souderton",
    "sg:classifiers":[
        {
            "category":"Personal",
            "type":"Services"
        },
        {
            "category":"Restaurant",
            "type":"Food & Drink"
        },
        {
            "category":"Coffee & Tea",
            "type":"Food & Drink"
        }
    ],
    "sg:phone":"+1 215 721 1525",
    "sg:postcode":"18964",
    "sg:province":"PA",
    "sg:tags":[
        "party",
        "planning",
        "espresso",
        "event"
    ],
    "wof:name":"Franconia Square Cafe & Market",
    "wof:placetype":"venue"
},
  "geometry": {"coordinates":[-75.35722,40.307273],"type":"Point"}
}