{
  "type": "Feature",
  "properties": {
    "iso:country":"US",
    "sg:address":"711 Walnut St",
    "sg:city":"Reading",
    "sg:classifiers":[
        {
            "category":"Social Services",
            "type":"Services"
        }
    ],
    "sg:phone":"+1 610 370 4522",
    "sg:postcode":"19601",
    "sg:province":"PA",
    "sg:tags":[
        "worker"
    ],
    "wof:name":"Craig R Schollenberger",
    "wof:placetype":"venue"
},
  "geometry": {"coordinates":[-75.922911,40.338375],"type":"Point"}
}