{
  "type": "Feature",
  "properties": {
    "addr:full":"35 N Main St Greensburg PA 15601",
    "addr:housenumber":"35",
    "addr:postcode":"15601",
    "addr:street":"N Main St",
    "iso:country":"US",
    "sg:address":"35 N Main St",
    "sg:city":"Greensburg",
    "sg:classifiers":[
        {
            "category":"Professional",
            "subcategory":"Lawyer & Legal Services",
            "type":"Services"
        }
    ],
    "sg:phone":"+1 724 837 8484",
    "sg:postcode":"15601",
    "sg:province":"PA",
    "sg:tags":[
        "attorney"
    ],
    "wof:name":"Jacobs & Assoc",
    "wof:placetype":"venue"
},
  "geometry": {"coordinates":[-79.544633,40.303787],"type":"Point"}
}