{
  "type": "Feature",
  "properties": {
    "iso:country":"US",
    "sg:address":"1925 State Rte 72",
    "sg:city":"Lebanon",
    "sg:classifiers":[
        {
            "category":"Retail",
            "subcategory":"Auto Repair",
            "type":"Services"
        }
    ],
    "sg:phone":"+1   ",
    "sg:postcode":"17046",
    "sg:province":"PA",
    "sg:tags":[
        "automotive"
    ],
    "wof:name":"Robert Blouch Specializing",
    "wof:placetype":"venue"
},
  "geometry": {"coordinates":[-76.473277,40.378472],"type":"Point"}
}