{
  "type": "Feature",
  "properties": {
    "iso:country":"US",
    "sg:address":"424 S Turnpike Rd",
    "sg:city":"Dalton",
    "sg:classifiers":[
        {
            "category":"Building & Trades",
            "subcategory":"Plumbing",
            "type":"Services"
        }
    ],
    "sg:phone":"+1   ",
    "sg:postcode":"18414",
    "sg:province":"PA",
    "sg:tags":[
        "contractor"
    ],
    "wof:name":"Wayne J Pisanchyn Plumbing",
    "wof:placetype":"venue"
},
  "geometry": {"coordinates":[-75.734256,41.525713],"type":"Point"}
}