{
  "type": "Feature",
  "properties": {
    "addr:full":"912 Western Ave Pittsburgh PA 15233",
    "addr:housenumber":"912",
    "addr:postcode":"15233",
    "addr:street":"Western Ave",
    "iso:country":"US",
    "sg:address":"912 Western Ave",
    "sg:city":"Pittsburgh",
    "sg:classifiers":[
        {
            "category":"Professional",
            "subcategory":"Accounting & Tax Preparation",
            "type":"Services"
        },
        {
            "category":"Professional",
            "subcategory":"Lawyer & Legal Services",
            "type":"Services"
        }
    ],
    "sg:phone":"+1 412 322 8430",
    "sg:postcode":"15233",
    "sg:province":"PA",
    "sg:tags":[
        "accountant"
    ],
    "wof:name":"Krauland & Mabon PC",
    "wof:placetype":"venue"
},
  "geometry": {"coordinates":[-80.017403,40.4519],"type":"Point"}
}