{
  "type": "Feature",
  "properties": {
    "addr:full":"301 E Washington St Shenandoah PA 17976",
    "addr:housenumber":"301",
    "addr:postcode":"17976",
    "addr:street":"E Washington St",
    "iso:country":"US",
    "sg:address":"301 E Washington St",
    "sg:city":"Shenandoah",
    "sg:classifiers":[
        {
            "category":"Manufacturing",
            "subcategory":"Metals",
            "type":"Manufacturing & Wholesale Goods"
        }
    ],
    "sg:phone":"+1 570 462 4941",
    "sg:postcode":"17976",
    "sg:province":"PA",
    "sg:tags":[
        "steel",
        "fabricator",
        "miscellaneous",
        "structural"
    ],
    "wof:name":"Tri-Way Metal Workers Inc",
    "wof:placetype":"venue"
},
  "geometry": {"coordinates":[-76.196235,40.824234],"type":"Point"}
}