{
  "type": "Feature",
  "properties": {
    "iso:country":"US",
    "sg:address":"558 Willowbrook Rd",
    "sg:city":"Havertown",
    "sg:classifiers":[
        {
            "category":"Professional",
            "type":"Services"
        }
    ],
    "sg:phone":"+1   ",
    "sg:postcode":"19083",
    "sg:province":"PA",
    "wof:name":"Andrew C Russo",
    "wof:placetype":"venue"
},
  "geometry": {"coordinates":[-75.309466,39.970423],"type":"Point"}
}