{
  "type": "Feature",
  "properties": {
    "iso:country":"US",
    "sg:address":"517 Big Bend Rd",
    "sg:city":"Lancaster",
    "sg:classifiers":[
        {
            "category":"Organizations",
            "subcategory":"Religious Organization",
            "type":"Services"
        }
    ],
    "sg:phone":"+1 717 392 1056",
    "sg:postcode":"17603",
    "sg:province":"PA",
    "sg:tags":[
        "clergy"
    ],
    "wof:name":"John W Anderson Rev",
    "wof:placetype":"venue"
},
  "geometry": {"coordinates":[-76.336873,40.027799],"type":"Point"}
}