{
  "type": "Feature",
  "properties": {
    "addr:full":"2061 E Glenwood Ave Philadelphia PA 19124",
    "addr:housenumber":"2061",
    "addr:postcode":"19124",
    "addr:street":"E Glenwood Ave",
    "iso:country":"US",
    "sg:address":"2061 E Glenwood Ave",
    "sg:city":"Philadelphia",
    "sg:classifiers":[
        {
            "category":"Manufacturing",
            "subcategory":"Retail Goods",
            "type":"Manufacturing & Wholesale Goods"
        }
    ],
    "sg:phone":"+1 215 288 8030",
    "sg:postcode":"19124",
    "sg:province":"PA",
    "sg:tags":[
        "manufacturer"
    ],
    "wof:name":"Ecology Systems Equipment Mfg",
    "wof:placetype":"venue"
},
  "geometry": {"coordinates":[-75.09941499999999,40.001032],"type":"Point"}
}