{
  "type": "Feature",
  "properties": {
    "iso:country":"US",
    "sg:address":"465 Norwood Rd",
    "sg:city":"Columbia",
    "sg:classifiers":[
        {
            "category":"Real Estate",
            "subcategory":"Real Estate Agent",
            "type":"Services"
        }
    ],
    "sg:phone":"+1 717 684 5043",
    "sg:postcode":"17512",
    "sg:province":"PA",
    "wof:name":"SBA Properties Inc",
    "wof:placetype":"venue"
},
  "geometry": {"coordinates":[-76.49047899999999,40.046357],"type":"Point"}
}