{
  "type": "Feature",
  "properties": {
    "iso:country":"US",
    "sg:address":"914 Merchant St",
    "sg:city":"Ambridge",
    "sg:classifiers":[
        {
            "category":"Wholesale",
            "subcategory":"Machinery & Supplies",
            "type":"Manufacturing & Wholesale Goods"
        }
    ],
    "sg:phone":"+1 724 266 1077",
    "sg:postcode":"15003",
    "sg:province":"PA",
    "sg:tags":[
        "salon",
        "beauty"
    ],
    "sg:website":"www.italyhairfashion.com",
    "wof:name":"Hairtech International Inc",
    "wof:placetype":"venue"
},
  "geometry": {"coordinates":[-80.229944,40.59144],"type":"Point"}
}