{
  "type": "Feature",
  "properties": {
    "iso:country":"US",
    "sg:address":"190 Carlisle Ave",
    "sg:city":"York",
    "sg:classifiers":[
        {
            "category":"Manufacturing",
            "subcategory":"Metals",
            "type":"Manufacturing & Wholesale Goods"
        }
    ],
    "sg:phone":"+1 717 845 1651",
    "sg:postcode":"17404",
    "sg:province":"PA",
    "sg:tags":[
        "sheet",
        "metalwork",
        "electrical",
        "m",
        "mfg"
    ],
    "wof:name":"Gamlet Inc",
    "wof:placetype":"venue"
},
  "geometry": {"coordinates":[-76.748926,39.957697],"type":"Point"}
}