{
  "type": "Feature",
  "properties": {
    "iso:country":"US",
    "sg:address":"90 Shenango St",
    "sg:city":"Greenville",
    "sg:classifiers":[
        {
            "category":"Health Services",
            "subcategory":"Doctor",
            "type":"Services"
        }
    ],
    "sg:phone":"+1 724 588 4240",
    "sg:postcode":"16125",
    "sg:province":"PA",
    "sg:tags":[
        "physician",
        "pediatrics",
        "surgeons",
        "internal",
        "medicine",
        "surgeon"
    ],
    "wof:name":"Shams, Ameer, Md - Greenville Medical Ctr",
    "wof:placetype":"venue"
},
  "geometry": {"coordinates":[-80.38485,41.407372],"type":"Point"}
}