{
  "type": "Feature",
  "properties": {
    "iso:country":"US",
    "sg:address":"567 Sherman Ln",
    "sg:city":"Morrisville",
    "sg:classifiers":[
        {
            "category":"Restaurant",
            "type":"Food & Drink"
        }
    ],
    "sg:phone":"+1   ",
    "sg:postcode":"19067",
    "sg:province":"PA",
    "sg:tags":[
        "eating"
    ],
    "wof:name":"Bella Pasta",
    "wof:placetype":"venue"
},
  "geometry": {"coordinates":[-74.79277399999999,40.20655],"type":"Point"}
}