{
  "type": "Feature",
  "properties": {
    "addr:full":"712 Belmont Ter Bala Cynwyd PA 19004",
    "addr:housenumber":"712",
    "addr:postcode":"19004",
    "addr:street":"Belmont Ter",
    "iso:country":"US",
    "sg:address":"712 Belmont Ter",
    "sg:city":"Bala Cynwyd",
    "sg:classifiers":[
        {
            "category":"Building & Trades",
            "subcategory":"Pest Control",
            "type":"Services"
        }
    ],
    "sg:phone":"+1   ",
    "sg:postcode":"19004",
    "sg:province":"PA",
    "wof:name":"AAA Pest Wildlife Co",
    "wof:placetype":"venue"
},
  "geometry": {"coordinates":[-75.23102400000001,40.019465],"type":"Point"}
}