{
  "type": "Feature",
  "properties": {
    "addr:full":"3715 Walnut St Harrisburg PA 17109",
    "addr:housenumber":"3715",
    "addr:postcode":"17109",
    "addr:street":"Walnut St",
    "iso:country":"US",
    "sg:address":"3715 Walnut St",
    "sg:city":"Harrisburg",
    "sg:classifiers":[
        {
            "category":"Shopping",
            "subcategory":"Gifts & Souvenirs",
            "type":"Retail Goods"
        }
    ],
    "sg:phone":"+1   ",
    "sg:postcode":"17109",
    "sg:province":"PA",
    "sg:tags":[
        "wig",
        "balloon",
        "costume"
    ],
    "wof:name":"Balloonalot & Christas Costume",
    "wof:placetype":"venue"
},
  "geometry": {"coordinates":[-76.835553,40.2893],"type":"Point"}
}