{
  "type": "Feature",
  "properties": {
    "iso:country":"US",
    "sg:address":"137 Link Ln",
    "sg:city":"Slippery Rock",
    "sg:classifiers":[
        {
            "category":"Real Estate",
            "subcategory":"Surveying",
            "type":"Services"
        }
    ],
    "sg:phone":"+1 724 530 6889",
    "sg:postcode":"16057",
    "sg:province":"PA",
    "sg:tags":[
        "surveyor"
    ],
    "wof:name":"Shuty North Inc",
    "wof:placetype":"venue"
},
  "geometry": {"coordinates":[-80.133099,41.020694],"type":"Point"}
}