{
  "type": "Feature",
  "properties": {
    "iso:country":"US",
    "sg:address":"191 Beaver Dr",
    "sg:city":"Du Bois",
    "sg:classifiers":[
        {
            "category":"Banks & Credit Unions",
            "subcategory":"Bank",
            "type":"Services"
        }
    ],
    "sg:phone":"+1 814 375 0123",
    "sg:postcode":"15801",
    "sg:province":"PA",
    "wof:name":"Members Choice-Pa FEDERAL Cu",
    "wof:placetype":"venue"
},
  "geometry": {"coordinates":[-78.75152300000001,41.123311],"type":"Point"}
}