{
  "type": "Feature",
  "properties": {
    "addr:full":"819 Broadway St Mc Kees Rocks PA 15136",
    "addr:housenumber":"819",
    "addr:postcode":"15136",
    "addr:street":"Broadway St Mc Kees Rocks",
    "iso:country":"US",
    "sg:address":"819 Broadway St",
    "sg:city":"Mc Kees Rocks",
    "sg:classifiers":[
        {
            "category":"Personal",
            "subcategory":"Beauty Salon",
            "type":"Services"
        }
    ],
    "sg:phone":"+1 412 331 3536",
    "sg:postcode":"15136",
    "sg:province":"PA",
    "sg:tags":[
        "manicuring"
    ],
    "wof:name":"Star Nail Salon",
    "wof:placetype":"venue"
},
  "geometry": {"coordinates":[-80.076116,40.473319],"type":"Point"}
}