{
  "type": "Feature",
  "properties": {
    "addr:full":"50 Davis St Bradford PA 16701",
    "addr:housenumber":"50",
    "addr:postcode":"16701",
    "addr:street":"Davis St",
    "iso:country":"US",
    "sg:address":"50 Davis St",
    "sg:city":"Bradford",
    "sg:classifiers":[
        {
            "category":"Travel",
            "subcategory":"Travel Agent",
            "type":"Entertainment"
        }
    ],
    "sg:phone":"+1 814 362 6884",
    "sg:postcode":"16701",
    "sg:province":"PA",
    "sg:tags":[
        "agency",
        "bureau"
    ],
    "sg:website":"www.bradfordtravel.com",
    "wof:name":"Bradford Travel Svc",
    "wof:placetype":"venue"
},
  "geometry": {"coordinates":[-78.64507999999999,41.95748],"type":"Point"}
}