{
  "type": "Feature",
  "properties": {
    "addr:full":"241 S Pittsburgh St Connellsville PA 15425",
    "addr:housenumber":"241",
    "addr:postcode":"15425",
    "addr:street":"S Pittsburgh St",
    "iso:country":"US",
    "sg:address":"241 S Pittsburgh St",
    "sg:city":"Connellsville",
    "sg:classifiers":[
        {
            "category":"Food & Beverages",
            "subcategory":"Liquor & Beverages",
            "type":"Retail Goods"
        }
    ],
    "sg:phone":"+1 724 626 3001",
    "sg:postcode":"15425",
    "sg:province":"PA",
    "wof:name":"State Liquor Store",
    "wof:placetype":"venue"
},
  "geometry": {"coordinates":[-79.588892,40.016433],"type":"Point"}
}