{
  "type": "Feature",
  "properties": {
    "iso:country":"US",
    "sg:address":"109 Willows",
    "sg:city":"Darby",
    "sg:classifiers":[
        {
            "category":"Manufacturing",
            "subcategory":"Metals",
            "type":"Manufacturing & Wholesale Goods"
        }
    ],
    "sg:phone":"+1   ",
    "sg:postcode":"19023",
    "sg:province":"PA",
    "sg:tags":[
        "anodizing",
        "electroplating"
    ],
    "wof:name":"Multi-Flex Planting",
    "wof:placetype":"venue"
},
  "geometry": {"coordinates":[-75.28376,39.908683],"type":"Point"}
}