{
  "type": "Feature",
  "properties": {
    "iso:country":"US",
    "sg:address":"230 Levittown Pkwy",
    "sg:city":"Levittown",
    "sg:classifiers":[
        {
            "category":"Building & Trades",
            "subcategory":"Locksmith",
            "type":"Services"
        }
    ],
    "sg:phone":"+1 267 587 8664",
    "sg:postcode":"19054",
    "sg:province":"PA",
    "sg:tags":[
        "key"
    ],
    "wof:name":"A 1 Emergency Locksmith",
    "wof:placetype":"venue"
},
  "geometry": {"coordinates":[-74.82064699999999,40.144947],"type":"Point"}
}