{
  "type": "Feature",
  "properties": {
    "iso:country":"US",
    "sg:address":"1664 Glendale Valley Blvd",
    "sg:city":"Fallentimber",
    "sg:classifiers":[
        {
            "category":"Government",
            "subcategory":"Post Office",
            "type":"Public Place"
        }
    ],
    "sg:phone":"+1 814 000 1111",
    "sg:postcode":"16639",
    "sg:province":"PA",
    "wof:name":"US Post Office",
    "wof:placetype":"venue"
},
  "geometry": {"coordinates":[-78.50027799999999,40.688659],"type":"Point"}
}