{
  "type": "Feature",
  "properties": {
    "addr:full":"8136 Germantown Ave Philadelphia PA 19118",
    "addr:housenumber":"8136",
    "addr:postcode":"19118",
    "addr:street":"Germantown Ave",
    "iso:country":"US",
    "sg:address":"8136 Germantown Ave",
    "sg:city":"Philadelphia",
    "sg:classifiers":[
        {
            "category":"Restaurant",
            "type":"Food & Drink"
        }
    ],
    "sg:phone":"+1 215 248 0800",
    "sg:postcode":"19118",
    "sg:province":"PA",
    "sg:tags":[
        "soul"
    ],
    "wof:name":"Soul Group Inc",
    "wof:placetype":"venue"
},
  "geometry": {"coordinates":[-75.202084,40.072435],"type":"Point"}
}