{
  "type": "Feature",
  "properties": {
    "iso:country":"US",
    "sg:address":"218 E 11th St",
    "sg:city":"Erie",
    "sg:classifiers":[
        {
            "category":"Social Services",
            "type":"Services"
        }
    ],
    "sg:phone":"+1 814 459 8754",
    "sg:postcode":"16503",
    "sg:province":"PA",
    "wof:name":"Emmaus Soup Kitchen",
    "wof:placetype":"venue"
},
  "geometry": {"coordinates":[-80.076188,42.126664],"type":"Point"}
}