{
  "type": "Feature",
  "properties": {
    "iso:country":"US",
    "sg:address":"325 N Lansdowne Ave",
    "sg:city":"Lansdowne",
    "sg:classifiers":[
        {
            "category":"Health Services",
            "subcategory":"Chiropractor",
            "type":"Services"
        }
    ],
    "sg:phone":"+1 610 626 0200",
    "sg:postcode":"19050",
    "sg:province":"PA",
    "wof:name":"Dougherty Chiropractic Center",
    "wof:placetype":"venue"
},
  "geometry": {"coordinates":[-75.278147,39.947777],"type":"Point"}
}