{
  "type": "Feature",
  "properties": {
    "iso:country":"US",
    "sg:address":"14 Front St",
    "sg:city":"Frenchtown",
    "sg:classifiers":[
        {
            "category":"Restaurant",
            "type":"Food & Drink"
        }
    ],
    "sg:phone":"+1   ",
    "sg:postcode":"08825",
    "sg:province":"PA",
    "sg:tags":[
        "eating"
    ],
    "wof:name":"Zabb Thai",
    "wof:placetype":"venue"
},
  "geometry": {"coordinates":[-75.062802,40.525938],"type":"Point"}
}