{
  "type": "Feature",
  "properties": {
    "iso:country":"US",
    "sg:address":"2019 N 2nd St",
    "sg:city":"Harrisburg",
    "sg:classifiers":[
        {
            "category":"Manufacturing",
            "subcategory":"Metals",
            "type":"Manufacturing & Wholesale Goods"
        }
    ],
    "sg:phone":"+1 717 238 4211",
    "sg:postcode":"17102",
    "sg:province":"PA",
    "sg:tags":[
        "scrap",
        "product"
    ],
    "wof:name":"M Greenberg Co",
    "wof:placetype":"venue"
},
  "geometry": {"coordinates":[-76.89727499999999,40.276542],"type":"Point"}
}