{
  "type": "Feature",
  "properties": {
    "iso:country":"US",
    "sg:address":"535 Broadway St",
    "sg:city":"Scranton",
    "sg:classifiers":[
        {
            "category":"Bars & Pubs",
            "type":"Food & Drink"
        }
    ],
    "sg:phone":"+1 570 341 9733",
    "sg:postcode":"18505",
    "sg:province":"PA",
    "sg:tags":[
        "drinking"
    ],
    "wof:name":"Shaughnessy's Tavern",
    "wof:placetype":"venue"
},
  "geometry": {"coordinates":[-75.676078,41.405893],"type":"Point"}
}