{
  "type": "Feature",
  "properties": {
    "addr:full":"2 Maryland Cir Apt 223 Whitehall PA 18052",
    "addr:housenumber":"2;223",
    "addr:postcode":"18052",
    "addr:street":"Maryland Cir Apt",
    "iso:country":"US",
    "sg:address":"2 Maryland Cir Apt 223",
    "sg:city":"Whitehall",
    "sg:classifiers":[
        {
            "category":"Real Estate",
            "subcategory":"Real Estate Operator",
            "type":"Services"
        }
    ],
    "sg:phone":"+1 610 432 3600",
    "sg:postcode":"18052",
    "sg:province":"PA",
    "sg:tags":[
        "apartment"
    ],
    "wof:name":"Lehigh Valley Apartments",
    "wof:placetype":"venue"
},
  "geometry": {"coordinates":[-75.47959899999999,40.626099],"type":"Point"}
}