{
  "type": "Feature",
  "properties": {
    "addr:full":"9335 W Main Rd North East PA 16428",
    "addr:housenumber":"9335",
    "addr:postcode":"16428",
    "addr:street":"W Main Rd",
    "iso:country":"US",
    "sg:address":"9335 W Main Rd",
    "sg:city":"North East",
    "sg:classifiers":[
        {
            "category":"Organizations",
            "subcategory":"Religious Organization",
            "type":"Services"
        }
    ],
    "sg:phone":"+1 814 725 2711",
    "sg:postcode":"16428",
    "sg:province":"PA",
    "sg:tags":[
        "church"
    ],
    "wof:name":"Jehovah's Witnesses",
    "wof:placetype":"venue"
},
  "geometry": {"coordinates":[-79.89456300000001,42.194237],"type":"Point"}
}