{
  "type": "Feature",
  "properties": {
    "iso:country":"US",
    "sg:address":"234 Mifflin Ave",
    "sg:city":"Scranton",
    "sg:classifiers":[
        {
            "category":"Education",
            "subcategory":"Dance Studio",
            "type":"Public Place"
        }
    ],
    "sg:phone":"+1   ",
    "sg:postcode":"18503",
    "sg:province":"PA",
    "wof:name":"Civic Dance Centre",
    "wof:placetype":"venue"
},
  "geometry": {"coordinates":[-75.66801599999999,41.410894],"type":"Point"}
}