{
  "type": "Feature",
  "properties": {
    "iso:country":"US",
    "sg:address":"620 Pine Hill Rd",
    "sg:city":"Hummelstown",
    "sg:classifiers":[
        {
            "category":"Building & Trades",
            "subcategory":"Plumbing",
            "type":"Services"
        }
    ],
    "sg:phone":"+1 717 566 7491",
    "sg:postcode":"17036",
    "sg:province":"PA",
    "sg:tags":[
        "me",
        "sheet",
        "heating",
        "air",
        "conditioning",
        "mechanical",
        "plumbing"
    ],
    "wof:name":"Folk & Garber Inc",
    "wof:placetype":"venue"
},
  "geometry": {"coordinates":[-76.732353,40.282962],"type":"Point"}
}