{
  "type": "Feature",
  "properties": {
    "addr:full":"36046 Lake Rd Union City PA 16438",
    "addr:housenumber":"36046",
    "addr:postcode":"16438",
    "addr:street":"Lake Rd",
    "iso:country":"US",
    "sg:address":"36046 Lake Rd",
    "sg:city":"Union City",
    "sg:classifiers":[
        {
            "category":"Recreation",
            "type":"Entertainment"
        }
    ],
    "sg:phone":"+1 814 694 3608",
    "sg:postcode":"16438",
    "sg:province":"PA",
    "wof:name":"Canadohta Lake Roller Rink",
    "wof:placetype":"venue"
},
  "geometry": {"coordinates":[-79.829514,41.810774],"type":"Point"}
}