{
  "type": "Feature",
  "properties": {
    "addr:full":"5883 Ellsworth Ave Pittsburgh PA 15232",
    "addr:housenumber":"5883",
    "addr:postcode":"15232",
    "addr:street":"Ellsworth Ave",
    "iso:country":"US",
    "sg:address":"5883 Ellsworth Ave",
    "sg:city":"Pittsburgh",
    "sg:classifiers":[
        {
            "category":"Personal",
            "type":"Services"
        }
    ],
    "sg:phone":"+1 412 361 2154",
    "sg:postcode":"15232",
    "sg:province":"PA",
    "sg:tags":[
        "therapist",
        "massage"
    ],
    "wof:name":"Bare Tan Inc",
    "wof:placetype":"venue"
},
  "geometry": {"coordinates":[-79.929192,40.457266],"type":"Point"}
}