{
  "type": "Feature",
  "properties": {
    "iso:country":"US",
    "sg:address":"12 Russell Ct",
    "sg:city":"Coatesville",
    "sg:classifiers":[
        {
            "category":"Building & Trades",
            "subcategory":"Construction",
            "type":"Services"
        }
    ],
    "sg:phone":"+1 610 383 6525",
    "sg:postcode":"19320",
    "sg:province":"PA",
    "sg:tags":[
        "swimming",
        "enclosure",
        "pool",
        "contractor"
    ],
    "wof:name":"Kruspansky Fencing",
    "wof:placetype":"venue"
},
  "geometry": {"coordinates":[-75.848603,39.953758],"type":"Point"}
}