{
  "type": "Feature",
  "properties": {
    "addr:full":"301 E 1st Ave Tarentum PA 15084",
    "addr:housenumber":"301",
    "addr:postcode":"15084",
    "addr:street":"E 1St Ave",
    "iso:country":"US",
    "sg:address":"301 E 1st Ave",
    "sg:city":"Tarentum",
    "sg:classifiers":[
        {
            "category":"Health Services",
            "subcategory":"Doctor",
            "type":"Services"
        }
    ],
    "sg:phone":"+1 724 224 3113",
    "sg:postcode":"15084",
    "sg:province":"PA",
    "sg:tags":[
        "physician",
        "surgeon"
    ],
    "wof:name":"Digestive Disease Consultants",
    "wof:placetype":"venue"
},
  "geometry": {"coordinates":[-79.752608,40.600069],"type":"Point"}
}