{
  "type": "Feature",
  "properties": {
    "iso:country":"US",
    "sg:address":"161 S Mountain Blvd",
    "sg:city":"Mountain Top",
    "sg:classifiers":[
        {
            "category":"Professional",
            "type":"Services"
        }
    ],
    "sg:phone":"+1   ",
    "sg:postcode":"18707",
    "sg:province":"PA",
    "wof:name":"Little Teapot",
    "wof:placetype":"venue"
},
  "geometry": {"coordinates":[-75.895516,41.150447],"type":"Point"}
}