{
  "type": "Feature",
  "properties": {
    "addr:full":"425 Easton Rd Warrington PA 18976",
    "addr:housenumber":"425",
    "addr:postcode":"18976",
    "addr:street":"Easton Rd",
    "iso:country":"US",
    "sg:address":"425 Easton Rd",
    "sg:city":"Warrington",
    "sg:classifiers":[
        {
            "category":"Home & Garden",
            "subcategory":"Building Materials",
            "type":"Retail Goods"
        }
    ],
    "sg:phone":"+1   ",
    "sg:postcode":"18976",
    "sg:province":"PA",
    "wof:name":"Lowes",
    "wof:placetype":"venue"
},
  "geometry": {"coordinates":[-75.139881,40.222433],"type":"Point"}
}