{
  "type": "Feature",
  "properties": {
    "addr:full":"493 Kutztown Rd Myerstown PA 17067",
    "addr:housenumber":"493",
    "addr:postcode":"17067",
    "addr:street":"Kutztown Rd",
    "iso:country":"US",
    "sg:address":"493 Kutztown Rd",
    "sg:city":"Myerstown",
    "sg:classifiers":[
        {
            "category":"Freight",
            "type":"Transportation"
        }
    ],
    "sg:phone":"+1   ",
    "sg:postcode":"17067",
    "sg:province":"PA",
    "sg:tags":[
        "operator",
        "local",
        "trucking"
    ],
    "wof:name":"Eddie Mike Smith Trucking",
    "wof:placetype":"venue"
},
  "geometry": {"coordinates":[-76.32196500000001,40.394039],"type":"Point"}
}