{
  "type": "Feature",
  "properties": {
    "iso:country":"US",
    "sg:address":"226 Bunger St",
    "sg:city":"Ligonier",
    "sg:classifiers":[
        {
            "category":"Building & Trades",
            "subcategory":"Plumbing",
            "type":"Services"
        }
    ],
    "sg:phone":"+1   ",
    "sg:postcode":"15658",
    "sg:province":"PA",
    "sg:tags":[
        "contractor"
    ],
    "wof:name":"Robert E Ruff Plbg Repair",
    "wof:placetype":"venue"
},
  "geometry": {"coordinates":[-79.23696099999999,40.246928],"type":"Point"}
}