{
  "type": "Feature",
  "properties": {
    "addr:full":"424 Waupelani Dr State College PA 16801",
    "addr:housenumber":"424",
    "addr:postcode":"16801",
    "addr:street":"Waupelani Dr",
    "iso:country":"US",
    "sg:address":"424 Waupelani Dr",
    "sg:city":"State College",
    "sg:classifiers":[
        {
            "category":"Real Estate",
            "subcategory":"Real Estate Operator",
            "type":"Services"
        }
    ],
    "sg:phone":"+1 814 238 2600",
    "sg:postcode":"16801",
    "sg:province":"PA",
    "sg:tags":[
        "building",
        "apartment"
    ],
    "wof:name":"Lions Gate Apartments",
    "wof:placetype":"venue"
},
  "geometry": {"coordinates":[-77.85574200000001,40.776303],"type":"Point"}
}