{
  "type": "Feature",
  "properties": {
    "addr:full":"294 Freedom Rd Williamsport PA 17701",
    "addr:housenumber":"294",
    "addr:postcode":"17701",
    "addr:street":"Freedom Rd",
    "iso:country":"US",
    "sg:address":"294 Freedom Rd",
    "sg:city":"Williamsport",
    "sg:classifiers":[
        {
            "category":"Manufacturing",
            "subcategory":"Glass & Minerals",
            "type":"Manufacturing & Wholesale Goods"
        }
    ],
    "sg:phone":"+1 570 326 4428",
    "sg:postcode":"17701",
    "sg:province":"PA",
    "sg:tags":[
        "ready"
    ],
    "wof:name":"Wolyniec Construction Inc",
    "wof:placetype":"venue"
},
  "geometry": {"coordinates":[-77.00957,41.263027],"type":"Point"}
}