{
  "type": "Feature",
  "properties": {
    "addr:full":"1 Dogwood Ln Cleona PA 17042",
    "addr:housenumber":"1",
    "addr:postcode":"17042",
    "addr:street":"Dogwood Ln",
    "iso:country":"US",
    "sg:address":"1 Dogwood Ln",
    "sg:city":"Cleona",
    "sg:classifiers":[
        {
            "category":"Real Estate",
            "subcategory":"Real Estate Agent",
            "type":"Services"
        }
    ],
    "sg:phone":"+1 717 274 2784",
    "sg:postcode":"17042",
    "sg:province":"PA",
    "wof:name":"Walnut Mill",
    "wof:placetype":"venue"
},
  "geometry": {"coordinates":[-76.475025,40.334435],"type":"Point"}
}