{
  "type": "Feature",
  "properties": {
    "iso:country":"US",
    "sg:address":"2132 E Carson St",
    "sg:city":"Pittsburgh",
    "sg:classifiers":[
        {
            "category":"Bars & Pubs",
            "type":"Food & Drink"
        }
    ],
    "sg:phone":"+1   ",
    "sg:postcode":"15203",
    "sg:province":"PA",
    "sg:tags":[
        "drinking"
    ],
    "wof:name":"Bills Wild Sports Bar",
    "wof:placetype":"venue"
},
  "geometry": {"coordinates":[-79.975127,40.428366],"type":"Point"}
}