{
  "type": "Feature",
  "properties": {
    "iso:country":"US",
    "sg:address":"1145 Old Rte 220 N",
    "sg:city":"Duncansville",
    "sg:classifiers":[
        {
            "category":"Building & Trades",
            "subcategory":"Construction",
            "type":"Services"
        }
    ],
    "sg:phone":"+1 814 695 6609",
    "sg:postcode":"16635",
    "sg:province":"PA",
    "sg:tags":[
        "contractor"
    ],
    "sg:website":"www.holidaypoolsandspas.net",
    "wof:name":"Holiday Pools & Spas",
    "wof:placetype":"venue"
},
  "geometry": {"coordinates":[-78.41668199999999,40.432028],"type":"Point"}
}