{
  "type": "Feature",
  "properties": {
    "addr:full":"20273 Route 19 Cranberry Twp PA 16066",
    "addr:housenumber":"20273",
    "addr:postcode":"16066",
    "addr:street":"Route 19",
    "iso:country":"US",
    "sg:address":"20273 Route 19",
    "sg:city":"Cranberry Twp",
    "sg:classifiers":[
        {
            "category":"Arena",
            "subcategory":"Sports Club",
            "type":"Entertainment"
        }
    ],
    "sg:phone":"+1 724 776 3740",
    "sg:postcode":"16066",
    "sg:province":"PA",
    "sg:tags":[
        "martial art"
    ],
    "wof:name":"Sifu Slaughter's Chinese Martial Arts",
    "wof:placetype":"venue"
},
  "geometry": {"coordinates":[-80.102569,40.688573],"type":"Point"}
}