{
  "type": "Feature",
  "properties": {
    "iso:country":"US",
    "sg:address":"2698 Keefer Rd",
    "sg:city":"Chambersburg",
    "sg:classifiers":[
        {
            "category":"Farming",
            "subcategory":"Nursery",
            "type":"Manufacturing & Wholesale Goods"
        }
    ],
    "sg:phone":"+1   ",
    "sg:postcode":"17201",
    "sg:province":"PA",
    "sg:tags":[
        "ornamental"
    ],
    "wof:name":"Danice Greenery",
    "wof:placetype":"venue"
},
  "geometry": {"coordinates":[-77.69719600000001,39.970182],"type":"Point"}
}