{
  "type": "Feature",
  "properties": {
    "iso:country":"US",
    "sg:address":"1219 E Luzerne St",
    "sg:city":"Philadelphia",
    "sg:classifiers":[
        {
            "category":"Food & Beverages",
            "subcategory":"Groceries & Convenience Stores",
            "type":"Retail Goods"
        }
    ],
    "sg:phone":"+1   ",
    "sg:postcode":"19124",
    "sg:province":"PA",
    "wof:name":"Arts Food Market",
    "wof:placetype":"venue"
},
  "geometry": {"coordinates":[-75.103628,40.007902],"type":"Point"}
}