{
  "type": "Feature",
  "properties": {
    "addr:full":"1239 Horseshoe Pike Downingtown PA 19335",
    "addr:housenumber":"1239",
    "addr:postcode":"19335",
    "addr:street":"Horseshoe Pike",
    "iso:country":"US",
    "sg:address":"1239 Horseshoe Pike",
    "sg:city":"Downingtown",
    "sg:classifiers":[
        {
            "category":"Food & Beverages",
            "subcategory":"Liquor & Beverages",
            "type":"Retail Goods"
        }
    ],
    "sg:phone":"+1   ",
    "sg:postcode":"19335",
    "sg:province":"PA",
    "sg:tags":[
        "store"
    ],
    "wof:name":"Wine & Spirits Shoppe 1521",
    "wof:placetype":"venue"
},
  "geometry": {"coordinates":[-75.76852599999999,40.036307],"type":"Point"}
}