{
  "type": "Feature",
  "properties": {
    "addr:full":"14 Water Ln Pottsville PA 17901",
    "addr:housenumber":"14",
    "addr:postcode":"17901",
    "addr:street":"Water Ln",
    "iso:country":"US",
    "sg:address":"14 Water Ln",
    "sg:city":"Pottsville",
    "sg:classifiers":[
        {
            "category":"Government",
            "subcategory":"Office",
            "type":"Public Place"
        },
        {
            "category":"Government",
            "subcategory":"Fire Station",
            "type":"Public Place"
        }
    ],
    "sg:phone":"+1 570 544 2805",
    "sg:postcode":"17901",
    "sg:province":"PA",
    "sg:tags":[
        "department",
        "executive"
    ],
    "wof:name":"South Cass Citizen's Fire Co",
    "wof:placetype":"venue"
},
  "geometry": {"coordinates":[-76.282854,40.698695],"type":"Point"}
}