{
  "type": "Feature",
  "properties": {
    "iso:country":"US",
    "sg:address":"475 N Weaber St",
    "sg:city":"Annville",
    "sg:classifiers":[
        {
            "category":"Health Services",
            "subcategory":"Doctor",
            "type":"Services"
        }
    ],
    "sg:phone":"+1   ",
    "sg:postcode":"17003",
    "sg:province":"PA",
    "sg:tags":[
        "medical"
    ],
    "wof:name":"Gary A Luken MD",
    "wof:placetype":"venue"
},
  "geometry": {"coordinates":[-76.49906900000001,40.33639],"type":"Point"}
}