{
  "type": "Feature",
  "properties": {
    "addr:full":"860 Duncan Ave Washington PA 15301",
    "addr:housenumber":"860",
    "addr:postcode":"15301",
    "addr:street":"Duncan Ave",
    "iso:country":"US",
    "sg:address":"860 Duncan Ave",
    "sg:city":"Washington",
    "sg:classifiers":[
        {
            "category":"Shopping",
            "subcategory":"Computers & Home Electronics",
            "type":"Retail Goods"
        }
    ],
    "sg:phone":"+1   ",
    "sg:postcode":"15301",
    "sg:province":"PA",
    "wof:name":"Rl Computers",
    "wof:placetype":"venue"
},
  "geometry": {"coordinates":[-80.25934599999999,40.181181],"type":"Point"}
}