{
  "type": "Feature",
  "properties": {
    "iso:country":"US",
    "sg:address":"944 Walnut Bottom Rd",
    "sg:city":"Carlisle",
    "sg:classifiers":[
        {
            "category":"Autos & Motor Vehicles",
            "subcategory":"Auto Supplies",
            "type":"Retail Goods"
        }
    ],
    "sg:phone":"+1 717 258 8030",
    "sg:postcode":"17013",
    "sg:province":"PA",
    "sg:tags":[
        "tire"
    ],
    "sg:website":"www.monro.com",
    "wof:name":"Monro Muffler Brake & Service",
    "wof:placetype":"venue"
},
  "geometry": {"coordinates":[-77.212997,40.183998],"type":"Point"}
}