{
  "type": "Feature",
  "properties": {
    "iso:country":"US",
    "sg:address":"538 Centre Ave",
    "sg:city":"Reading",
    "sg:classifiers":[
        {
            "category":"Professional",
            "subcategory":"Business Services",
            "type":"Services"
        }
    ],
    "sg:phone":"+1 610 373 4838",
    "sg:postcode":"19601",
    "sg:province":"PA",
    "sg:tags":[
        "notary"
    ],
    "wof:name":"Rosemary D Mullenberg",
    "wof:placetype":"venue"
},
  "geometry": {"coordinates":[-75.92904,40.344186],"type":"Point"}
}