{
  "type": "Feature",
  "properties": {
    "iso:country":"US",
    "sg:address":"392 Yorkshire Way",
    "sg:city":"Bryn Mawr",
    "sg:classifiers":[
        {
            "category":"Insurance",
            "subcategory":"Insurance Agent",
            "type":"Services"
        }
    ],
    "sg:phone":"+1   ",
    "sg:postcode":"19010",
    "sg:province":"PA",
    "sg:tags":[
        "broker"
    ],
    "wof:name":"Allen Associates",
    "wof:placetype":"venue"
},
  "geometry": {"coordinates":[-75.34648,40.020488],"type":"Point"}
}