{
  "type": "Feature",
  "properties": {
    "addr:full":"601 52nd St Pittsburgh PA 15201",
    "addr:housenumber":"601",
    "addr:postcode":"15201",
    "addr:street":"52Nd St",
    "iso:country":"US",
    "sg:address":"601 52nd St",
    "sg:city":"Pittsburgh",
    "sg:classifiers":[
        {
            "category":"Food & Beverages",
            "subcategory":"Groceries & Convenience Stores",
            "type":"Retail Goods"
        }
    ],
    "sg:phone":"+1 412 781 4144",
    "sg:postcode":"15201",
    "sg:province":"PA",
    "wof:name":"Bloomfield Market",
    "wof:placetype":"venue"
},
  "geometry": {"coordinates":[-79.95175999999999,40.478514],"type":"Point"}
}