{
  "type": "Feature",
  "properties": {
    "addr:full":"3105 W Scenic Dr Danielsville PA 18038",
    "addr:housenumber":"3105",
    "addr:postcode":"18038",
    "addr:street":"W Scenic Dr",
    "iso:country":"US",
    "sg:address":"3105 W Scenic Dr",
    "sg:city":"Danielsville",
    "sg:classifiers":[
        {
            "category":"Real Estate",
            "subcategory":"Real Estate Agent",
            "type":"Services"
        }
    ],
    "sg:phone":"+1   ",
    "sg:postcode":"18038",
    "sg:province":"PA",
    "wof:name":"Praxis",
    "wof:placetype":"venue"
},
  "geometry": {"coordinates":[-75.462103,40.792827],"type":"Point"}
}