{
  "type": "Feature",
  "properties": {
    "addr:full":"6101 Limekiln Pike Philadelphia PA 19141",
    "addr:housenumber":"6101",
    "addr:postcode":"19141",
    "addr:street":"Limekiln Pike",
    "iso:country":"US",
    "sg:address":"6101 Limekiln Pike",
    "sg:city":"Philadelphia",
    "sg:classifiers":[
        {
            "category":"Social Services",
            "type":"Services"
        }
    ],
    "sg:phone":"+1   ",
    "sg:postcode":"19141",
    "sg:province":"PA",
    "sg:tags":[
        "organization",
        "membership"
    ],
    "wof:name":"School and Family Together",
    "wof:placetype":"venue"
},
  "geometry": {"coordinates":[-75.150047,40.047408],"type":"Point"}
}