{
  "type": "Feature",
  "properties": {
    "iso:country":"US",
    "sg:address":"440 Gateway Ave",
    "sg:city":"Chambersburg",
    "sg:classifiers":[
        {
            "category":"Wholesale",
            "subcategory":"Medical Equipment & Supplies",
            "type":"Manufacturing & Wholesale Goods"
        },
        {
            "category":"Health Services",
            "subcategory":"Hospital",
            "type":"Services"
        },
        {
            "category":"Recreation",
            "subcategory":"Water Park",
            "type":"Entertainment"
        },
        {
            "category":"Manufacturing",
            "subcategory":"Petroleum Products",
            "type":"Manufacturing & Wholesale Goods"
        }
    ],
    "sg:phone":"+1 717 264 1799",
    "sg:postcode":"17201",
    "sg:province":"PA",
    "sg:tags":[
        "equipment-wholesale",
        "therapy",
        "oxygen",
        "manufacturer"
    ],
    "sg:website":"http://www.dickshomecare.com",
    "wof:name":"Dicks Homecare",
    "wof:placetype":"venue"
},
  "geometry": {"coordinates":[-77.633105,39.936707],"type":"Point"}
}