{
  "type": "Feature",
  "properties": {
    "iso:country":"US",
    "sg:address":"10 Union Hill Rd",
    "sg:city":"Conshohocken",
    "sg:classifiers":[
        {
            "category":"Wholesale",
            "subcategory":"Groceries",
            "type":"Manufacturing & Wholesale Goods"
        }
    ],
    "sg:phone":"+1   ",
    "sg:postcode":"19428",
    "sg:province":"PA",
    "wof:name":"Thomas A Campbell Company",
    "wof:placetype":"venue"
},
  "geometry": {"coordinates":[-75.32577499999999,40.068711],"type":"Point"}
}