{
  "type": "Feature",
  "properties": {
    "iso:country":"US",
    "sg:address":"190 Lloyd St",
    "sg:city":"Allentown",
    "sg:classifiers":[
        {
            "category":"Retail",
            "subcategory":"Auto Repair",
            "type":"Services"
        }
    ],
    "sg:phone":"+1 610 264 2124",
    "sg:postcode":"18109",
    "sg:province":"PA",
    "sg:tags":[
        "repairing",
        "automobile"
    ],
    "wof:name":"Hanover Service Center",
    "wof:placetype":"venue"
},
  "geometry": {"coordinates":[-75.43650100000001,40.634998],"type":"Point"}
}