{
  "type": "Feature",
  "properties": {
    "iso:country":"US",
    "sg:address":"2621 Centre Ave",
    "sg:city":"Pittsburgh",
    "sg:classifiers":[
        {
            "category":"Organizations",
            "subcategory":"Professional Association",
            "type":"Services"
        }
    ],
    "sg:phone":"+1 412 621 1762",
    "sg:postcode":"15219",
    "sg:province":"PA",
    "wof:name":"YMCA",
    "wof:placetype":"venue"
},
  "geometry": {"coordinates":[-79.96772,40.44703],"type":"Point"}
}