{
  "type": "Feature",
  "properties": {
    "addr:full":"28 Airport Sq North Wales PA 19454",
    "addr:housenumber":"28",
    "addr:postcode":"19454",
    "addr:street":"Airport Sq",
    "iso:country":"US",
    "sg:address":"28 Airport Sq",
    "sg:city":"North Wales",
    "sg:classifiers":[
        {
            "category":"Restaurant",
            "type":"Food & Drink"
        }
    ],
    "sg:menulink":"http://www.allmenus.com/pa/montgomery/172949-wendys/menu/",
    "sg:phone":"+1 215 362 9559",
    "sg:postcode":"19454",
    "sg:province":"PA",
    "sg:tags":[
        "burger",
        "american",
        "soup"
    ],
    "wof:name":"Wendy's",
    "wof:placetype":"venue"
},
  "geometry": {"coordinates":[-75.24300700000001,40.238945],"type":"Point"}
}