{
  "type": "Feature",
  "properties": {
    "addr:full":"714 Nazareth Pike Nazareth PA 18064",
    "addr:housenumber":"714",
    "addr:postcode":"18064",
    "addr:street":"Nazareth Pike",
    "iso:country":"US",
    "sg:address":"714 Nazareth Pike",
    "sg:city":"Nazareth",
    "sg:classifiers":[
        {
            "category":"Utilities",
            "subcategory":"Fuel Oil & Lpg",
            "type":"Services"
        }
    ],
    "sg:phone":"+1   ",
    "sg:postcode":"18064",
    "sg:province":"PA",
    "sg:tags":[
        "wholesale",
        "retail",
        "petroleum",
        "liquefied"
    ],
    "wof:name":"Suburban Propane",
    "wof:placetype":"venue"
},
  "geometry": {"coordinates":[-75.314027,40.730121],"type":"Point"}
}