{
  "type": "Feature",
  "properties": {
    "iso:country":"US",
    "sg:address":"210 High St",
    "sg:city":"Freeport",
    "sg:classifiers":[
        {
            "category":"Home & Garden",
            "subcategory":"Home Furnishings",
            "type":"Retail Goods"
        },
        {
            "category":"Shopping",
            "subcategory":"Gifts & Souvenirs",
            "type":"Retail Goods"
        }
    ],
    "sg:phone":"+1 724 295 2730",
    "sg:postcode":"16229",
    "sg:province":"PA",
    "sg:tags":[
        "shop",
        "pottery",
        "arts",
        "craft"
    ],
    "wof:name":"Sheltering Tree Inc",
    "wof:placetype":"venue"
},
  "geometry": {"coordinates":[-79.689381,40.672788],"type":"Point"}
}