{
  "type": "Feature",
  "properties": {
    "addr:full":"1800 West St Homestead PA 15120",
    "addr:housenumber":"1800",
    "addr:postcode":"15120",
    "addr:street":"West St",
    "iso:country":"US",
    "sg:address":"1800 West St",
    "sg:city":"Homestead",
    "sg:classifiers":[
        {
            "category":"Health Services",
            "subcategory":"Clinic",
            "type":"Services"
        }
    ],
    "sg:phone":"+1   ",
    "sg:postcode":"15120",
    "sg:province":"PA",
    "sg:tags":[
        "home",
        "care"
    ],
    "wof:name":"South Hills Hlth Systm Home",
    "wof:placetype":"venue"
},
  "geometry": {"coordinates":[-79.904797,40.399733],"type":"Point"}
}