{
  "type": "Feature",
  "properties": {
    "addr:full":"3615 Levans Rd Coplay PA 18037",
    "addr:housenumber":"3615",
    "addr:postcode":"18037",
    "addr:street":"Levans Rd",
    "iso:country":"US",
    "sg:address":"3615 Levans Rd",
    "sg:city":"Coplay",
    "sg:classifiers":[
        {
            "category":"Personal",
            "type":"Services"
        }
    ],
    "sg:phone":"+1 610 799 3293",
    "sg:postcode":"18037",
    "sg:province":"PA",
    "sg:tags":[
        "sewing",
        "alteration"
    ],
    "wof:name":"Sharon's Sewing",
    "wof:placetype":"venue"
},
  "geometry": {"coordinates":[-75.5457,40.675701],"type":"Point"}
}