{
  "type": "Feature",
  "properties": {
    "iso:country":"US",
    "sg:address":"600 Arch St",
    "sg:city":"Philadelphia",
    "sg:classifiers":[
        {
            "category":"Building & Trades",
            "subcategory":"Construction",
            "type":"Services"
        }
    ],
    "sg:phone":"+1 215 861 3189",
    "sg:postcode":"19106",
    "sg:province":"PA",
    "sg:tags":[
        "wallcoverings-installation",
        "wallpaper",
        "painting",
        "contractor"
    ],
    "wof:name":"Just Plain Bills",
    "wof:placetype":"venue"
},
  "geometry": {"coordinates":[-75.149933,39.952759],"type":"Point"}
}