{
  "type": "Feature",
  "properties": {
    "iso:country":"US",
    "sg:address":"1411 Ash St",
    "sg:city":"Scranton",
    "sg:classifiers":[
        {
            "category":"Personal",
            "subcategory":"Beauty Salon",
            "type":"Services"
        }
    ],
    "sg:phone":"+1 570 344 5751",
    "sg:postcode":"18510",
    "sg:province":"PA",
    "sg:tags":[
        "shop"
    ],
    "wof:name":"Hair Team",
    "wof:placetype":"venue"
},
  "geometry": {"coordinates":[-75.642537,41.411454],"type":"Point"}
}