{
  "type": "Feature",
  "properties": {
    "addr:full":"506 Old Waynesburg Rd Carmichaels PA 15320",
    "addr:housenumber":"506",
    "addr:postcode":"15320",
    "addr:street":"Old Waynesburg Rd",
    "iso:country":"US",
    "sg:address":"506 Old Waynesburg Rd",
    "sg:city":"Carmichaels",
    "sg:classifiers":[
        {
            "category":"Banks & Credit Unions",
            "subcategory":"Financial Services",
            "type":"Services"
        }
    ],
    "sg:phone":"+1   ",
    "sg:postcode":"15320",
    "sg:province":"PA",
    "sg:tags":[
        "investor"
    ],
    "wof:name":"Little Chicago Investment",
    "wof:placetype":"venue"
},
  "geometry": {"coordinates":[-79.97656600000001,39.891354],"type":"Point"}
}