{
  "type": "Feature",
  "properties": {
    "iso:country":"US",
    "sg:address":"41 Dennis Dr",
    "sg:city":"Reading",
    "sg:classifiers":[
        {
            "category":"Manufacturing",
            "subcategory":"Metals",
            "type":"Manufacturing & Wholesale Goods"
        }
    ],
    "sg:phone":"+1   ",
    "sg:postcode":"19606",
    "sg:province":"PA",
    "sg:tags":[
        "screw",
        "washer",
        "clip",
        "mfg"
    ],
    "wof:name":"Mfg Plant-Shipping",
    "wof:placetype":"venue"
},
  "geometry": {"coordinates":[-75.842545,40.283087],"type":"Point"}
}