{
  "type": "Feature",
  "properties": {
    "iso:country":"US",
    "sg:address":"914 Trenton Rd",
    "sg:city":"Fairless Hills",
    "sg:classifiers":[
        {
            "category":"Building & Trades",
            "subcategory":"Cleaning & Sanitation",
            "type":"Services"
        }
    ],
    "sg:phone":"+1   ",
    "sg:postcode":"19030",
    "sg:province":"PA",
    "sg:tags":[
        "rebuilding",
        "chimney"
    ],
    "wof:name":"E & E Chimney Sweeps Inc",
    "wof:placetype":"venue"
},
  "geometry": {"coordinates":[-74.831389,40.186731],"type":"Point"}
}