{
  "type": "Feature",
  "properties": {
    "iso:country":"US",
    "sg:address":"1025 Oley St",
    "sg:city":"Reading",
    "sg:classifiers":[
        {
            "category":"Food & Beverages",
            "subcategory":"Bakery",
            "type":"Retail Goods"
        },
        {
            "category":"Bakery",
            "type":"Food & Drink"
        }
    ],
    "sg:phone":"+1 610 478 1436",
    "sg:postcode":"19604",
    "sg:province":"PA",
    "sg:tags":[
        "bakers-wholesale"
    ],
    "wof:name":"La Seybana Bakery",
    "wof:placetype":"venue"
},
  "geometry": {"coordinates":[-75.916847,40.34581],"type":"Point"}
}