{
  "type": "Feature",
  "properties": {
    "iso:country":"US",
    "sg:address":"841 Highland Ave",
    "sg:city":"Jenkintown",
    "sg:classifiers":[
        {
            "category":"Professional",
            "type":"Services"
        }
    ],
    "sg:phone":"+1 215 572 1371",
    "sg:postcode":"19046",
    "sg:province":"PA",
    "sg:tags":[
        "establishment"
    ],
    "wof:name":"Jenkib'Ns Tomorrow",
    "wof:placetype":"venue"
},
  "geometry": {"coordinates":[-75.13174100000001,40.108928],"type":"Point"}
}