{
  "type": "Feature",
  "properties": {
    "iso:country":"US",
    "sg:address":"5689 West Rd",
    "sg:city":"Mc Kean",
    "sg:classifiers":[
        {
            "category":"Wholesale",
            "subcategory":"Stationery",
            "type":"Manufacturing & Wholesale Goods"
        }
    ],
    "sg:phone":"+1 814 476 7500",
    "sg:postcode":"16426",
    "sg:province":"PA",
    "sg:tags":[
        "sup"
    ],
    "wof:name":"Burrell Enterprises",
    "wof:placetype":"venue"
},
  "geometry": {"coordinates":[-80.158322,41.996814],"type":"Point"}
}