{
  "type": "Feature",
  "properties": {
    "iso:country":"US",
    "sg:address":"121 Main St",
    "sg:city":"Dallas",
    "sg:classifiers":[
        {
            "category":"Building & Trades",
            "subcategory":"Landscaping Services",
            "type":"Services"
        },
        {
            "category":"Home & Garden",
            "subcategory":"Garden Supply",
            "type":"Retail Goods"
        }
    ],
    "sg:phone":"+1 570 675 2926",
    "sg:postcode":"18612",
    "sg:province":"PA",
    "sg:tags":[
        "equipment",
        "lawn",
        "maintenance",
        "landscape",
        "contractor"
    ],
    "wof:name":"Summit Lanscaping",
    "wof:placetype":"venue"
},
  "geometry": {"coordinates":[-75.95977999999999,41.333731],"type":"Point"}
}