{
  "type": "Feature",
  "properties": {
    "addr:full":"13208 John Lindsay Rd Greencastle PA 17225",
    "addr:housenumber":"13208",
    "addr:postcode":"17225",
    "addr:street":"John Lindsay Rd",
    "iso:country":"US",
    "sg:address":"13208 John Lindsay Rd",
    "sg:city":"Greencastle",
    "sg:classifiers":[
        {
            "category":"Building & Trades",
            "subcategory":"Construction",
            "type":"Services"
        }
    ],
    "sg:phone":"+1   ",
    "sg:postcode":"17225",
    "sg:province":"PA",
    "sg:tags":[
        "contractor"
    ],
    "wof:name":"Dwight D Dofflemyer Mason",
    "wof:placetype":"venue"
},
  "geometry": {"coordinates":[-77.864909,39.752269],"type":"Point"}
}