{
  "type": "Feature",
  "properties": {
    "iso:country":"US",
    "sg:address":"3716 Mcclelland Ave",
    "sg:city":"Erie",
    "sg:phone":"+1 814 454 6421",
    "sg:postcode":"16510",
    "sg:province":"PA",
    "sg:website":"http://www.connectoelectric.com",
    "wof:name":"Connecto Electric Inc",
    "wof:placetype":"venue"
},
  "geometry": {"coordinates":[-80.017278,42.121734],"type":"Point"}
}