{
  "type": "Feature",
  "properties": {
    "iso:country":"US",
    "sg:address":"2610 W Chester Pike",
    "sg:city":"Broomall",
    "sg:classifiers":[
        {
            "category":"Autos & Motor Vehicles",
            "subcategory":"Auto Supplies",
            "type":"Retail Goods"
        }
    ],
    "sg:phone":"+1 610 356 6300",
    "sg:postcode":"19008",
    "sg:province":"PA",
    "sg:tags":[
        "tire"
    ],
    "wof:name":"Valley Forge Tire & Auto Ctr",
    "wof:placetype":"venue"
},
  "geometry": {"coordinates":[-75.359465,39.981476],"type":"Point"}
}