{
  "type": "Feature",
  "properties": {
    "iso:country":"US",
    "sg:address":"1620 N Main Ave",
    "sg:city":"Scranton",
    "sg:classifiers":[
        {
            "category":"Building & Trades",
            "subcategory":"Construction",
            "type":"Services"
        }
    ],
    "sg:phone":"+1 570 348 0775",
    "sg:postcode":"18508",
    "sg:province":"PA",
    "sg:tags":[
        "water",
        "laboratory",
        "control",
        "testing",
        "pollution"
    ],
    "sg:website":"http://www.neelaboratories.com",
    "wof:name":"Northeastern Environmental Assocs Inc",
    "wof:placetype":"venue"
},
  "geometry": {"coordinates":[-75.66116700000001,41.434317],"type":"Point"}
}