{
  "type": "Feature",
  "properties": {
    "addr:full":"1615 W Crawford Ave Connellsville PA 15425",
    "addr:housenumber":"1615",
    "addr:postcode":"15425",
    "addr:street":"W Crawford Ave",
    "iso:country":"US",
    "sg:address":"1615 W Crawford Ave",
    "sg:city":"Connellsville",
    "sg:classifiers":[
        {
            "category":"Retail",
            "subcategory":"Auto Repair",
            "type":"Services"
        }
    ],
    "sg:phone":"+1   ",
    "sg:postcode":"15425",
    "sg:province":"PA",
    "sg:tags":[
        "general"
    ],
    "wof:name":"Stoots Auto",
    "wof:placetype":"venue"
},
  "geometry": {"coordinates":[-79.60977,40.012789],"type":"Point"}
}