{
  "type": "Feature",
  "properties": {
    "iso:country":"US",
    "sg:address":"614 Wyandotte St",
    "sg:city":"Catasauqua",
    "sg:classifiers":[
        {
            "category":"Building & Trades",
            "subcategory":"Construction",
            "type":"Services"
        }
    ],
    "sg:phone":"+1   ",
    "sg:postcode":"18032",
    "sg:province":"PA",
    "sg:tags":[
        "house"
    ],
    "wof:name":"Rucci General Contracting",
    "wof:placetype":"venue"
},
  "geometry": {"coordinates":[-75.475812,40.666971],"type":"Point"}
}