{
  "type": "Feature",
  "properties": {
    "addr:full":"926 Rockledge Dr Carlisle PA 17013",
    "addr:housenumber":"926",
    "addr:postcode":"17013",
    "addr:street":"Rockledge Dr",
    "iso:country":"US",
    "sg:address":"926 Rockledge Dr",
    "sg:city":"Carlisle",
    "sg:classifiers":[
        {
            "category":"Shopping",
            "type":"Retail Goods"
        }
    ],
    "sg:phone":"+1   ",
    "sg:postcode":"17013",
    "sg:province":"PA",
    "sg:tags":[
        "merchandise"
    ],
    "wof:name":"U Lovepets",
    "wof:placetype":"venue"
},
  "geometry": {"coordinates":[-77.20716899999999,40.186626],"type":"Point"}
}