{
  "type": "Feature",
  "properties": {
    "iso:country":"US",
    "sg:address":"1275 S Cedar Crest Blvd",
    "sg:city":"Allentown",
    "sg:classifiers":[
        {
            "category":"Manufacturing",
            "subcategory":"Printing",
            "type":"Manufacturing & Wholesale Goods"
        }
    ],
    "sg:phone":"+1   ",
    "sg:postcode":"18103",
    "sg:province":"PA",
    "sg:tags":[
        "commercial",
        "offset"
    ],
    "wof:name":"Tre Graphics Etc Inc",
    "wof:placetype":"venue"
},
  "geometry": {"coordinates":[-75.51863899999999,40.56747],"type":"Point"}
}