{
  "type": "Feature",
  "properties": {
    "addr:full":"1104 Trindle Rd Carlisle PA 17013",
    "addr:housenumber":"1104",
    "addr:postcode":"17013",
    "addr:street":"Trindle Rd",
    "iso:country":"US",
    "sg:address":"1104 Trindle Rd",
    "sg:city":"Carlisle",
    "sg:classifiers":[
        {
            "category":"Shopping",
            "subcategory":"Books",
            "type":"Retail Goods"
        }
    ],
    "sg:phone":"+1 717 258 5652",
    "sg:postcode":"17013",
    "sg:province":"PA",
    "sg:tags":[
        "dealer"
    ],
    "wof:name":"JMJ Catholic Shop",
    "wof:placetype":"venue"
},
  "geometry": {"coordinates":[-77.16302399999999,40.199339],"type":"Point"}
}