{
  "type": "Feature",
  "properties": {
    "iso:country":"US",
    "sg:address":"134 6th St",
    "sg:city":"Pittsburgh",
    "sg:classifiers":[
        {
            "category":"Mining & Drilling",
            "type":"Manufacturing & Wholesale Goods"
        }
    ],
    "sg:phone":"+1 412 434 5570",
    "sg:postcode":"15222",
    "sg:province":"PA",
    "sg:tags":[
        "stone"
    ],
    "wof:name":"Carl Stone",
    "wof:placetype":"venue"
},
  "geometry": {"coordinates":[-80.002809,40.444047],"type":"Point"}
}