{
  "type": "Feature",
  "properties": {
    "iso:country":"US",
    "sg:address":"1483 The Spangler Rd",
    "sg:city":"New Oxford",
    "sg:classifiers":[
        {
            "category":"Real Estate",
            "subcategory":"Real Estate Operator",
            "type":"Services"
        }
    ],
    "sg:phone":"+1   ",
    "sg:postcode":"17350",
    "sg:province":"PA",
    "sg:tags":[
        "property",
        "lessor"
    ],
    "wof:name":"Murphy John",
    "wof:placetype":"venue"
},
  "geometry": {"coordinates":[-77.057366,39.896518],"type":"Point"}
}