{
  "type": "Feature",
  "properties": {
    "iso:country":"US",
    "sg:address":"302 York St",
    "sg:city":"Gettysburg",
    "sg:classifiers":[
        {
            "category":"Recreation",
            "type":"Entertainment"
        }
    ],
    "sg:phone":"+1   ",
    "sg:postcode":"17325",
    "sg:province":"PA",
    "sg:tags":[
        "tour",
        "operation"
    ],
    "wof:name":"Trf Cncssion Spcialists of Fla",
    "wof:placetype":"venue"
},
  "geometry": {"coordinates":[-77.22533199999999,39.831739],"type":"Point"}
}