{
  "type": "Feature",
  "properties": {
    "iso:country":"US",
    "sg:address":"3015 Forest St",
    "sg:city":"Lehighton",
    "sg:classifiers":[
        {
            "category":"Social Services",
            "subcategory":"Child Care",
            "type":"Services"
        }
    ],
    "sg:phone":"+1 610 377 6720",
    "sg:postcode":"18235",
    "sg:province":"PA",
    "wof:name":"Dream Horizon Early Learning",
    "wof:placetype":"venue"
},
  "geometry": {"coordinates":[-75.615287,40.895892],"type":"Point"}
}