{
  "type": "Feature",
  "properties": {
    "iso:country":"US",
    "sg:address":"429 Market St",
    "sg:city":"Williamsport",
    "sg:classifiers":[
        {
            "category":"Professional",
            "subcategory":"Lawyer & Legal Services",
            "type":"Services"
        }
    ],
    "sg:phone":"+1   ",
    "sg:postcode":"17701",
    "sg:province":"PA",
    "sg:tags":[
        "attorney"
    ],
    "wof:name":"Perciballi Henry P",
    "wof:placetype":"venue"
},
  "geometry": {"coordinates":[-77.00219800000001,41.242297],"type":"Point"}
}