{
  "type": "Feature",
  "properties": {
    "iso:country":"US",
    "sg:address":"453 Leedom St",
    "sg:city":"Jenkintown",
    "sg:classifiers":[
        {
            "category":"Wholesale",
            "subcategory":"Machinery & Supplies",
            "type":"Manufacturing & Wholesale Goods"
        }
    ],
    "sg:phone":"+1 215 885 8655",
    "sg:postcode":"19046",
    "sg:province":"PA",
    "sg:tags":[
        "machine",
        "stencil",
        "cutting"
    ],
    "wof:name":"Custom Stencils & Repair Svc",
    "wof:placetype":"venue"
},
  "geometry": {"coordinates":[-75.127289,40.098822],"type":"Point"}
}