{
  "type": "Feature",
  "properties": {
    "addr:full":"3420 Simpson Ferry Rd Camp Hill PA 17011",
    "addr:housenumber":"3420",
    "addr:postcode":"17011",
    "addr:street":"Simpson Ferry Rd",
    "iso:country":"US",
    "sg:address":"3420 Simpson Ferry Rd",
    "sg:city":"Camp Hill",
    "sg:classifiers":[
        {
            "category":"Manufacturing",
            "subcategory":"Motor Vehicles & Parts",
            "type":"Manufacturing & Wholesale Goods"
        }
    ],
    "sg:phone":"+1 717 761 3690",
    "sg:postcode":"17011",
    "sg:province":"PA",
    "sg:tags":[
        "equipment",
        "railroad"
    ],
    "wof:name":"ASF-Keystone Inc",
    "wof:placetype":"venue"
},
  "geometry": {"coordinates":[-76.93663100000001,40.226797],"type":"Point"}
}