{
  "type": "Feature",
  "properties": {
    "addr:full":"1005 Heilman Rd Montoursville PA 17754",
    "addr:housenumber":"1005",
    "addr:postcode":"17754",
    "addr:street":"Heilman Rd",
    "iso:country":"US",
    "sg:address":"1005 Heilman Rd",
    "sg:city":"Montoursville",
    "sg:classifiers":[
        {
            "category":"Autos & Motor Vehicles",
            "subcategory":"Fuel & Gas Station",
            "type":"Retail Goods"
        }
    ],
    "sg:phone":"+1 570 326 3927",
    "sg:postcode":"17754",
    "sg:province":"PA",
    "sg:tags":[
        "oil"
    ],
    "wof:name":"Williamsport Exxon",
    "wof:placetype":"venue"
},
  "geometry": {"coordinates":[-76.82625400000001,41.310321],"type":"Point"}
}