{
  "type": "Feature",
  "properties": {
    "addr:full":"9 Oak Dr Pittsburgh PA 15214",
    "addr:housenumber":"9",
    "addr:postcode":"15214",
    "addr:street":"Oak Dr",
    "iso:country":"US",
    "sg:address":"9 Oak Dr",
    "sg:city":"Pittsburgh",
    "sg:classifiers":[
        {
            "category":"Organizations",
            "subcategory":"Labor Organization",
            "type":"Services"
        }
    ],
    "sg:phone":"+1 412 931 0194",
    "sg:postcode":"15214",
    "sg:province":"PA",
    "wof:name":"Pennsylvania State Correction",
    "wof:placetype":"venue"
},
  "geometry": {"coordinates":[-80.03442099999999,40.495914],"type":"Point"}
}