{
  "type": "Feature",
  "properties": {
    "addr:full":"427 E Broad St Tamaqua PA 18252",
    "addr:housenumber":"427",
    "addr:postcode":"18252",
    "addr:street":"E Broad St",
    "iso:country":"US",
    "sg:address":"427 E Broad St",
    "sg:city":"Tamaqua",
    "sg:classifiers":[
        {
            "category":"Autos & Motor Vehicles",
            "subcategory":"Auto Supplies",
            "type":"Retail Goods"
        },
        {
            "category":"Retail",
            "subcategory":"Auto Repair",
            "type":"Services"
        }
    ],
    "sg:phone":"+1 570 668 5240",
    "sg:postcode":"18252",
    "sg:province":"PA",
    "sg:tags":[
        "equipment",
        "automobile",
        "air",
        "conditioning",
        "general"
    ],
    "wof:name":"Joe's Auto Repair",
    "wof:placetype":"venue"
},
  "geometry": {"coordinates":[-75.96160500000001,40.79775],"type":"Point"}
}