{
  "type": "Feature",
  "properties": {
    "iso:country":"US",
    "sg:address":"100 S Broad St",
    "sg:city":"Lansdale",
    "sg:classifiers":[
        {
            "category":"Professional",
            "subcategory":"Detective & Security Services",
            "type":"Services"
        }
    ],
    "sg:phone":"+1 215 393 7100",
    "sg:postcode":"19446",
    "sg:province":"PA",
    "sg:tags":[
        "investigator"
    ],
    "wof:name":"K & S Investigations Inc",
    "wof:placetype":"venue"
},
  "geometry": {"coordinates":[-75.286062,40.239274],"type":"Point"}
}