{
  "type": "Feature",
  "properties": {
    "iso:country":"US",
    "sg:address":"4725 McKnight Rd",
    "sg:city":"Pittsburgh",
    "sg:classifiers":[
        {
            "category":"Health Services",
            "subcategory":"Medical Lab",
            "type":"Services"
        }
    ],
    "sg:phone":"+1 412 366 6660",
    "sg:postcode":"15237",
    "sg:province":"PA",
    "sg:tags":[
        "laboratory"
    ],
    "wof:name":"Quest Diagnostics Inc",
    "wof:placetype":"venue"
},
  "geometry": {"coordinates":[-80.009593,40.504513],"type":"Point"}
}