{
  "type": "Feature",
  "properties": {
    "addr:full":"200 W Mahoning St Punxsutawney PA 15767",
    "addr:housenumber":"200",
    "addr:postcode":"15767",
    "addr:street":"W Mahoning St",
    "iso:country":"US",
    "sg:address":"200 W Mahoning St",
    "sg:city":"Punxsutawney",
    "sg:classifiers":[
        {
            "category":"Insurance",
            "subcategory":"Insurance Agent",
            "type":"Services"
        }
    ],
    "sg:phone":"+1 814 938 3092",
    "sg:postcode":"15767",
    "sg:province":"PA",
    "wof:name":"Nationwide Insurance",
    "wof:placetype":"venue"
},
  "geometry": {"coordinates":[-78.972325,40.943219],"type":"Point"}
}