{
  "type": "Feature",
  "properties": {
    "addr:full":"4817 N Broad St Philadelphia PA 19141",
    "addr:housenumber":"4817",
    "addr:postcode":"19141",
    "addr:street":"N Broad St",
    "iso:country":"US",
    "sg:address":"4817 N Broad St",
    "sg:city":"Philadelphia",
    "sg:classifiers":[
        {
            "category":"Health Services",
            "subcategory":"Doctor",
            "type":"Services"
        }
    ],
    "sg:phone":"+1 215 457 7700",
    "sg:postcode":"19141",
    "sg:province":"PA",
    "wof:name":"Olney-Logan Medical Center",
    "wof:placetype":"venue"
},
  "geometry": {"coordinates":[-75.147598,40.026501],"type":"Point"}
}