{
  "type": "Feature",
  "properties": {
    "iso:country":"US",
    "sg:address":"20 Old Lincoln Hwy W",
    "sg:city":"Ligonier",
    "sg:classifiers":[
        {
            "category":"Wholesale",
            "subcategory":"Petroleum",
            "type":"Manufacturing & Wholesale Goods"
        }
    ],
    "sg:phone":"+1 724 238 9601",
    "sg:postcode":"15658",
    "sg:province":"PA",
    "wof:name":"Luther P Miller Inc",
    "wof:placetype":"venue"
},
  "geometry": {"coordinates":[-79.260908,40.252818],"type":"Point"}
}