{
  "type": "Feature",
  "properties": {
    "addr:full":"400 Market St Kingston PA 18704",
    "addr:housenumber":"400",
    "addr:postcode":"18704",
    "addr:street":"Market St",
    "iso:country":"US",
    "sg:address":"400 Market St",
    "sg:city":"Kingston",
    "sg:classifiers":[
        {
            "category":"Food & Beverages",
            "subcategory":"Groceries & Convenience Stores",
            "type":"Retail Goods"
        }
    ],
    "sg:phone":"+1 570 288 3103",
    "sg:postcode":"18704",
    "sg:province":"PA",
    "sg:website":"www.unimart.com",
    "wof:name":"Uni-Mart",
    "wof:placetype":"venue"
},
  "geometry": {"coordinates":[-75.892606,41.256668],"type":"Point"}
}