{
  "type": "Feature",
  "properties": {
    "iso:country":"US",
    "sg:address":"3145 Lehigh St",
    "sg:city":"Allentown",
    "sg:classifiers":[
        {
            "category":"Shopping",
            "subcategory":"Gifts & Souvenirs",
            "type":"Retail Goods"
        }
    ],
    "sg:phone":"+1 610 797 1222",
    "sg:postcode":"18103",
    "sg:province":"PA",
    "sg:tags":[
        "party",
        "balloon",
        "supply"
    ],
    "wof:name":"Paper Outlet the",
    "wof:placetype":"venue"
},
  "geometry": {"coordinates":[-75.48809799999999,40.5578],"type":"Point"}
}