{
  "type": "Feature",
  "properties": {
    "iso:country":"US",
    "sg:address":"1376 Market St",
    "sg:city":"Marcus Hook",
    "sg:classifiers":[
        {
            "category":"Utilities",
            "subcategory":"Mobile Phone",
            "type":"Services"
        }
    ],
    "sg:phone":"+1 610 859 0000",
    "sg:postcode":"19061",
    "sg:province":"PA",
    "sg:tags":[
        "telephone",
        "cellular"
    ],
    "wof:name":"Euro Wireless",
    "wof:placetype":"venue"
},
  "geometry": {"coordinates":[-75.420413,39.82402],"type":"Point"}
}