{
  "type": "Feature",
  "properties": {
    "addr:full":"2080 Milford Rd East Stroudsburg PA 18301",
    "addr:housenumber":"2080",
    "addr:postcode":"18301",
    "addr:street":"Milford Rd",
    "iso:country":"US",
    "sg:address":"2080 Milford Rd",
    "sg:city":"East Stroudsburg",
    "sg:classifiers":[
        {
            "category":"Restaurant",
            "type":"Food & Drink"
        }
    ],
    "sg:phone":"+1 570 476 9390",
    "sg:postcode":"18301",
    "sg:province":"PA",
    "wof:name":"Tre Amici Restaurant",
    "wof:placetype":"venue"
},
  "geometry": {"coordinates":[-75.17083100000001,41.024921],"type":"Point"}
}