{
  "type": "Feature",
  "properties": {
    "iso:country":"US",
    "sg:address":"2465 Maryland Rd",
    "sg:city":"Willow Grove",
    "sg:classifiers":[
        {
            "category":"Wholesale",
            "subcategory":"Machinery & Supplies",
            "type":"Manufacturing & Wholesale Goods"
        }
    ],
    "sg:phone":"+1 215 657 2700",
    "sg:postcode":"19090",
    "sg:province":"PA",
    "sg:tags":[
        "equipment",
        "material",
        "handling"
    ],
    "sg:website":"www.arbor-inc.com",
    "wof:name":"Arbor Handling Svc Inc",
    "wof:placetype":"venue"
},
  "geometry": {"coordinates":[-75.133048,40.159544],"type":"Point"}
}