{
  "type": "Feature",
  "properties": {
    "iso:country":"US",
    "sg:address":"138 Billen Ave",
    "sg:city":"Monongahela",
    "sg:classifiers":[
        {
            "category":"Building & Trades",
            "subcategory":"Construction",
            "type":"Services"
        }
    ],
    "sg:phone":"+1   ",
    "sg:postcode":"15063",
    "sg:province":"PA",
    "sg:tags":[
        "grading"
    ],
    "wof:name":"Joe Wujcik",
    "wof:placetype":"venue"
},
  "geometry": {"coordinates":[-79.969904,40.193411],"type":"Point"}
}