{
  "type": "Feature",
  "properties": {
    "addr:full":"401 N 17th St Allentown PA 18104",
    "addr:housenumber":"401",
    "addr:postcode":"18104",
    "addr:street":"N 17Th St",
    "iso:country":"US",
    "sg:address":"401 N 17th St",
    "sg:city":"Allentown",
    "sg:classifiers":[
        {
            "category":"Health Services",
            "subcategory":"Doctor",
            "type":"Services"
        }
    ],
    "sg:phone":"+1 610 432 6862",
    "sg:postcode":"18104",
    "sg:province":"PA",
    "sg:tags":[
        "physician",
        "surgeon"
    ],
    "wof:name":"Medical Associates Of Lehigh",
    "wof:placetype":"venue"
},
  "geometry": {"coordinates":[-75.49551,40.603494],"type":"Point"}
}