{
  "type": "Feature",
  "properties": {
    "addr:full":"1100 S 58th St Philadelphia PA 19143",
    "addr:housenumber":"1100",
    "addr:postcode":"19143",
    "addr:street":"S 58Th St",
    "iso:country":"US",
    "sg:address":"1100 S 58th St",
    "sg:city":"Philadelphia",
    "sg:classifiers":[
        {
            "category":"Real Estate",
            "subcategory":"Real Estate Operator",
            "type":"Services"
        }
    ],
    "sg:phone":"+1 215 748 1100",
    "sg:postcode":"19143",
    "sg:province":"PA",
    "sg:tags":[
        "building",
        "apartment"
    ],
    "wof:name":"Hoffman Place Apts",
    "wof:placetype":"venue"
},
  "geometry": {"coordinates":[-75.23876799999999,39.944578],"type":"Point"}
}