{
  "type": "Feature",
  "properties": {
    "addr:full":"100 Pennzoil Dr Johnstown PA 15909",
    "addr:housenumber":"100",
    "addr:postcode":"15909",
    "addr:street":"Pennzoil Dr",
    "iso:country":"US",
    "sg:address":"100 Pennzoil Dr",
    "sg:city":"Johnstown",
    "sg:phone":"+1   ",
    "sg:postcode":"15909",
    "sg:province":"PA",
    "sg:tags":[
        "product",
        "petroleum"
    ],
    "wof:name":"Warren Oil Company Inc",
    "wof:placetype":"venue"
},
  "geometry": {"coordinates":[-78.83501800000001,40.443309],"type":"Point"}
}