{
  "type": "Feature",
  "properties": {
    "addr:full":"235 Market St Lewisburg PA 17837",
    "addr:housenumber":"235",
    "addr:postcode":"17837",
    "addr:street":"Market St",
    "iso:country":"US",
    "sg:address":"235 Market St",
    "sg:city":"Lewisburg",
    "sg:classifiers":[
        {
            "category":"Shopping",
            "subcategory":"Gifts & Souvenirs",
            "type":"Retail Goods"
        }
    ],
    "sg:phone":"+1 570 523 0200",
    "sg:postcode":"17837",
    "sg:province":"PA",
    "wof:name":"Lewisburg Card Shoppe",
    "wof:placetype":"venue"
},
  "geometry": {"coordinates":[-76.883911,40.964767],"type":"Point"}
}