{
  "type": "Feature",
  "properties": {
    "iso:country":"US",
    "sg:address":"218 W Governor Rd",
    "sg:city":"Hershey",
    "sg:classifiers":[
        {
            "category":"Health Services",
            "subcategory":"Doctor",
            "type":"Services"
        }
    ],
    "sg:phone":"+1 717 533 2500",
    "sg:postcode":"17033",
    "sg:province":"PA",
    "wof:name":"Backenstose D L MD",
    "wof:placetype":"venue"
},
  "geometry": {"coordinates":[-76.655285,40.273042],"type":"Point"}
}