{
  "type": "Feature",
  "properties": {
    "iso:country":"US",
    "sg:address":"372 Lawn St",
    "sg:city":"Pittsburgh",
    "sg:classifiers":[
        {
            "category":"Social Services",
            "subcategory":"Adult Care",
            "type":"Services"
        }
    ],
    "sg:phone":"+1   ",
    "sg:postcode":"15213",
    "sg:province":"PA",
    "sg:tags":[
        "residential"
    ],
    "wof:name":"Comm Resdtl Rehab Dom",
    "wof:placetype":"venue"
},
  "geometry": {"coordinates":[-79.96137400000001,40.433613],"type":"Point"}
}