{
  "type": "Feature",
  "properties": {
    "addr:full":"1955 Locust St Philadelphia PA 19103",
    "addr:housenumber":"1955",
    "addr:postcode":"19103",
    "addr:street":"Locust St",
    "iso:country":"US",
    "sg:address":"1955 Locust St",
    "sg:city":"Philadelphia",
    "sg:classifiers":[
        {
            "category":"Professional",
            "type":"Services"
        },
        {
            "category":"Professional",
            "subcategory":"Research",
            "type":"Services"
        }
    ],
    "sg:phone":"+1 215 568 3636",
    "sg:postcode":"19103",
    "sg:province":"PA",
    "sg:tags":[
        "physician",
        "mental",
        "psychiatrist",
        "surgeons",
        "health",
        "psychiatry"
    ],
    "wof:name":"Institute For Experimental Psychiatry",
    "wof:placetype":"venue"
},
  "geometry": {"coordinates":[-75.173698,39.949501],"type":"Point"}
}