{
  "type": "Feature",
  "properties": {
    "addr:full":"7328 Castor Ave Philadelphia PA 19152",
    "addr:housenumber":"7328",
    "addr:postcode":"19152",
    "addr:street":"Castor Ave",
    "iso:country":"US",
    "sg:address":"7328 Castor Ave",
    "sg:city":"Philadelphia",
    "sg:classifiers":[
        {
            "category":"Recreation",
            "type":"Entertainment"
        }
    ],
    "sg:phone":"+1 215 742 1560",
    "sg:postcode":"19152",
    "sg:province":"PA",
    "sg:tags":[
        "martial",
        "arts",
        "instruction"
    ],
    "wof:name":"TKJR Martial Arts & Fitness",
    "wof:placetype":"venue"
},
  "geometry": {"coordinates":[-75.06477700000001,40.052563],"type":"Point"}
}