{
  "type": "Feature",
  "properties": {
    "iso:country":"US",
    "sg:address":"1415 Woods Run Ave",
    "sg:city":"Pittsburgh",
    "sg:classifiers":[
        {
            "category":"Building & Trades",
            "subcategory":"Construction",
            "type":"Services"
        }
    ],
    "sg:phone":"+1 412 766 1013",
    "sg:postcode":"15212",
    "sg:province":"PA",
    "sg:tags":[
        "painter"
    ],
    "wof:name":"Steel City Painting Svc",
    "wof:placetype":"venue"
},
  "geometry": {"coordinates":[-80.034848,40.475216],"type":"Point"}
}