{
  "type": "Feature",
  "properties": {
    "addr:full":"561 E Main St Annville PA 17003",
    "addr:housenumber":"561",
    "addr:postcode":"17003",
    "addr:street":"E Main St",
    "iso:country":"US",
    "sg:address":"561 E Main St",
    "sg:city":"Annville",
    "sg:classifiers":[
        {
            "category":"Health Services",
            "subcategory":"Nursing And Care Facility",
            "type":"Services"
        }
    ],
    "sg:phone":"+1 717 867 2273",
    "sg:postcode":"17003",
    "sg:province":"PA",
    "sg:tags":[
        "personal",
        "home"
    ],
    "wof:name":"Annville Personal Care Homes",
    "wof:placetype":"venue"
},
  "geometry": {"coordinates":[-76.506034,40.331085],"type":"Point"}
}