{
  "type": "Feature",
  "properties": {
    "iso:country":"US",
    "sg:address":"738 Mahoning Dr E",
    "sg:city":"Lehighton",
    "sg:classifiers":[
        {
            "category":"Recreation",
            "type":"Entertainment"
        }
    ],
    "sg:phone":"+1 570 386 5599",
    "sg:postcode":"18235",
    "sg:province":"PA",
    "sg:tags":[
        "club",
        "membership",
        "sporting"
    ],
    "wof:name":"Maple Tree Inn Tennis Club",
    "wof:placetype":"venue"
},
  "geometry": {"coordinates":[-75.74162099999999,40.825181],"type":"Point"}
}