{
  "type": "Feature",
  "properties": {
    "iso:country":"US",
    "sg:address":"598 Oak Ridge Rd",
    "sg:city":"Hazleton",
    "sg:classifiers":[
        {
            "category":"Recreation",
            "type":"Entertainment"
        }
    ],
    "sg:phone":"+1 570 384 0550",
    "sg:postcode":"18202",
    "sg:province":"PA",
    "sg:tags":[
        "center"
    ],
    "wof:name":"Paragon Adventure Park",
    "wof:placetype":"venue"
},
  "geometry": {"coordinates":[-76.04766600000001,40.928413],"type":"Point"}
}