{
  "type": "Feature",
  "properties": {
    "iso:country":"US",
    "sg:address":"4025 Chestnut St",
    "sg:city":"Philadelphia",
    "sg:classifiers":[
        {
            "category":"Professional",
            "type":"Services"
        }
    ],
    "sg:phone":"+1 215 243 1640",
    "sg:postcode":"19104",
    "sg:province":"PA",
    "sg:tags":[
        "establishment"
    ],
    "sg:website":"www.ali-aba.org",
    "wof:name":"Practical Tax Lawyer",
    "wof:placetype":"venue"
},
  "geometry": {"coordinates":[-75.204041,39.955911],"type":"Point"}
}