{
  "type": "Feature",
  "properties": {
    "iso:country":"US",
    "sg:address":"750 Ohio River Blvd",
    "sg:city":"Rochester",
    "sg:classifiers":[
        {
            "category":"Shopping",
            "subcategory":"Used Merchandise",
            "type":"Retail Goods"
        }
    ],
    "sg:phone":"+1   ",
    "sg:postcode":"15074",
    "sg:province":"PA",
    "wof:name":"Goodwill Industries Pittsburgh",
    "wof:placetype":"venue"
},
  "geometry": {"coordinates":[-80.273414,40.698911],"type":"Point"}
}