{
  "type": "Feature",
  "properties": {
    "iso:country":"US",
    "sg:address":"12 W Pittsburgh St",
    "sg:city":"Greensburg",
    "sg:classifiers":[
        {
            "category":"Social Services",
            "type":"Services"
        }
    ],
    "sg:phone":"+1 724 853 7600",
    "sg:postcode":"15601",
    "sg:province":"PA",
    "sg:tags":[
        "guidance",
        "child"
    ],
    "wof:name":"Visionquest",
    "wof:placetype":"venue"
},
  "geometry": {"coordinates":[-79.544544,40.302311],"type":"Point"}
}