{
  "type": "Feature",
  "properties": {
    "iso:country":"US",
    "sg:address":"22 Walnut Dr",
    "sg:city":"Richboro",
    "sg:classifiers":[
        {
            "category":"Building & Trades",
            "subcategory":"Construction",
            "type":"Services"
        }
    ],
    "sg:phone":"+1 215 740 3326",
    "sg:postcode":"18954",
    "sg:province":"PA",
    "sg:tags":[
        "wallpaper"
    ],
    "wof:name":"Wall Covering Specialty Svc",
    "wof:placetype":"venue"
},
  "geometry": {"coordinates":[-75.000485,40.215952],"type":"Point"}
}