{
  "type": "Feature",
  "properties": {
    "addr:full":"700 N Chester Rd West Chester PA 19380",
    "addr:housenumber":"700",
    "addr:postcode":"19380",
    "addr:street":"N Chester Rd",
    "iso:country":"US",
    "sg:address":"700 N Chester Rd",
    "sg:city":"West Chester",
    "sg:classifiers":[
        {
            "category":"Health Services",
            "subcategory":"Nursing And Care Facility",
            "type":"Services"
        }
    ],
    "sg:phone":"+1 610 696 5211",
    "sg:postcode":"19380",
    "sg:province":"PA",
    "sg:tags":[
        "convalescent",
        "hospital",
        "skilled",
        "specialty",
        "home"
    ],
    "wof:name":"Barclay Friends Home",
    "wof:placetype":"venue"
},
  "geometry": {"coordinates":[-75.543162,39.987496],"type":"Point"}
}