{
  "type": "Feature",
  "properties": {
    "addr:full":"130 S 9th St Philadelphia PA 19107",
    "addr:housenumber":"130",
    "addr:postcode":"19107",
    "addr:street":"S 9Th St",
    "iso:country":"US",
    "sg:address":"130 S 9th St",
    "sg:city":"Philadelphia",
    "sg:classifiers":[
        {
            "category":"Health Services",
            "subcategory":"Doctor",
            "type":"Services"
        }
    ],
    "sg:phone":"+1 215 955 2001",
    "sg:postcode":"19107",
    "sg:province":"PA",
    "sg:tags":[
        "physician",
        "medical",
        "orthopedics",
        "surgeons"
    ],
    "wof:name":"Jerome M Cotler Md",
    "wof:placetype":"venue"
},
  "geometry": {"coordinates":[-75.15565700000001,39.948979],"type":"Point"}
}