{
  "type": "Feature",
  "properties": {
    "addr:full":"942 Brookline Blvd Pittsburgh PA 15226",
    "addr:housenumber":"942",
    "addr:postcode":"15226",
    "addr:street":"Brookline Blvd",
    "iso:country":"US",
    "sg:address":"942 Brookline Blvd",
    "sg:city":"Pittsburgh",
    "sg:classifiers":[
        {
            "category":"Personal",
            "subcategory":"Tanning Parlor",
            "type":"Services"
        }
    ],
    "sg:phone":"+1 412 341 6641",
    "sg:postcode":"15226",
    "sg:province":"PA",
    "sg:tags":[
        "salon"
    ],
    "wof:name":"Wanna Be Tan",
    "wof:placetype":"venue"
},
  "geometry": {"coordinates":[-80.018444,40.392621],"type":"Point"}
}