{
  "type": "Feature",
  "properties": {
    "addr:full":"16470 Davis Rd Meadville PA 16335",
    "addr:housenumber":"16470",
    "addr:postcode":"16335",
    "addr:street":"Davis Rd",
    "iso:country":"US",
    "sg:address":"16470 Davis Rd",
    "sg:city":"Meadville",
    "sg:classifiers":[
        {
            "category":"Retail",
            "subcategory":"Repair Shop",
            "type":"Services"
        }
    ],
    "sg:phone":"+1 814 336 3717",
    "sg:postcode":"16335",
    "sg:province":"PA",
    "sg:tags":[
        "reupholstery",
        "furniture"
    ],
    "wof:name":"Carrara Upholstery",
    "wof:placetype":"venue"
},
  "geometry": {"coordinates":[-80.208129,41.644221],"type":"Point"}
}