{
  "type": "Feature",
  "properties": {
    "iso:country":"US",
    "sg:address":"1 Cleveland Ave",
    "sg:city":"Narberth",
    "sg:classifiers":[
        {
            "category":"Shopping",
            "subcategory":"Florist",
            "type":"Retail Goods"
        }
    ],
    "sg:phone":"+1 610 664 7444",
    "sg:postcode":"19072",
    "sg:province":"PA",
    "wof:name":"Singing Balloon Company the",
    "wof:placetype":"venue"
},
  "geometry": {"coordinates":[-75.25599699999999,40.012299],"type":"Point"}
}