{
  "type": "Feature",
  "properties": {
    "iso:country":"US",
    "sg:address":"613 E 3rd St",
    "sg:city":"Williamsport",
    "sg:classifiers":[
        {
            "category":"Professional",
            "type":"Services"
        }
    ],
    "sg:phone":"+1   ",
    "sg:postcode":"17701",
    "sg:province":"PA",
    "wof:name":"Altimate Adz",
    "wof:placetype":"venue"
},
  "geometry": {"coordinates":[-76.991591,41.245168],"type":"Point"}
}