{
  "type": "Feature",
  "properties": {
    "iso:country":"US",
    "sg:address":"197 Turkey Run Rd",
    "sg:city":"Mifflinburg",
    "sg:classifiers":[
        {
            "category":"Wholesale",
            "subcategory":"Computers",
            "type":"Manufacturing & Wholesale Goods"
        }
    ],
    "sg:phone":"+1 570 966 7293",
    "sg:postcode":"17844",
    "sg:province":"PA",
    "sg:tags":[
        "equipment"
    ],
    "wof:name":"Siegrist Computer",
    "wof:placetype":"venue"
},
  "geometry": {"coordinates":[-76.97002500000001,40.909952],"type":"Point"}
}