{
  "type": "Feature",
  "properties": {
    "iso:country":"US",
    "sg:address":"2651 Durham Rd",
    "sg:city":"Bristol",
    "sg:classifiers":[
        {
            "category":"Retail",
            "subcategory":"Self-service Laundry",
            "type":"Services"
        }
    ],
    "sg:phone":"+1 215 781 0816",
    "sg:postcode":"19047",
    "sg:province":"PA",
    "sg:tags":[
        "coin"
    ],
    "wof:name":"Clean Stock Laundromat",
    "wof:placetype":"venue"
},
  "geometry": {"coordinates":[-74.883105,40.12754],"type":"Point"}
}