{
  "type": "Feature",
  "properties": {
    "iso:country":"US",
    "sg:address":"303 Julian Dr E",
    "sg:city":"Warminster",
    "sg:classifiers":[
        {
            "category":"Wholesale",
            "subcategory":"Durable Goods & Equipment",
            "type":"Manufacturing & Wholesale Goods"
        }
    ],
    "sg:phone":"+1   ",
    "sg:postcode":"18974",
    "sg:province":"PA",
    "wof:name":"John Ruggero",
    "wof:placetype":"venue"
},
  "geometry": {"coordinates":[-75.083029,40.224479],"type":"Point"}
}