{
  "type": "Feature",
  "properties": {
    "iso:country":"US",
    "sg:address":"2835 E Carson St",
    "sg:city":"Pittsburgh",
    "sg:classifiers":[
        {
            "category":"Professional",
            "type":"Services"
        }
    ],
    "sg:phone":"+1 412 488 7565",
    "sg:postcode":"15203",
    "sg:province":"PA",
    "sg:tags":[
        "establishment"
    ],
    "wof:name":"Great Expectations",
    "wof:placetype":"venue"
},
  "geometry": {"coordinates":[-79.964528,40.425416],"type":"Point"}
}