{
  "type": "Feature",
  "properties": {
    "iso:country":"US",
    "sg:address":"121 Crestwood Dr",
    "sg:city":"Lansdale",
    "sg:classifiers":[
        {
            "category":"Insurance",
            "subcategory":"Insurance Agent",
            "type":"Services"
        }
    ],
    "sg:phone":"+1 215 855 9394",
    "sg:postcode":"19446",
    "sg:province":"PA",
    "wof:name":"Neiburg Agency Inc",
    "wof:placetype":"venue"
},
  "geometry": {"coordinates":[-75.254614,40.248394],"type":"Point"}
}