{
  "type": "Feature",
  "properties": {
    "addr:full":"560 Old Berwick Rd Bloomsburg PA 17815",
    "addr:housenumber":"560",
    "addr:postcode":"17815",
    "addr:street":"Old Berwick Rd",
    "iso:country":"US",
    "sg:address":"560 Old Berwick Rd",
    "sg:city":"Bloomsburg",
    "sg:classifiers":[
        {
            "category":"Freight",
            "type":"Transportation"
        }
    ],
    "sg:phone":"+1 570 784 6144",
    "sg:postcode":"17815",
    "sg:province":"PA",
    "sg:tags":[
        "local",
        "without",
        "storage",
        "hauling"
    ],
    "wof:name":"Gold Star Lines Inc",
    "wof:placetype":"venue"
},
  "geometry": {"coordinates":[-76.441897,41.001429],"type":"Point"}
}