{
  "type": "Feature",
  "properties": {
    "addr:full":"37 N 2nd St Coplay PA 18037",
    "addr:housenumber":"37",
    "addr:postcode":"18037",
    "addr:street":"N 2Nd St",
    "iso:country":"US",
    "sg:address":"37 N 2nd St",
    "sg:city":"Coplay",
    "sg:classifiers":[
        {
            "category":"Sports & Exercise",
            "subcategory":"Bicycle Rental",
            "type":"Entertainment"
        }
    ],
    "sg:phone":"+1 610 262 8104",
    "sg:postcode":"18037",
    "sg:province":"PA",
    "sg:tags":[
        "wear"
    ],
    "wof:name":"Coplay Sporting Goods",
    "wof:placetype":"venue"
},
  "geometry": {"coordinates":[-75.49250000000001,40.673698],"type":"Point"}
}