{
  "type": "Feature",
  "properties": {
    "iso:country":"US",
    "sg:address":"1717 Lotus Dr",
    "sg:city":"Orefield",
    "sg:classifiers":[
        {
            "category":"Professional",
            "subcategory":"Management & Consulting",
            "type":"Services"
        }
    ],
    "sg:phone":"+1 610 395 2547",
    "sg:postcode":"18069",
    "sg:province":"PA",
    "sg:tags":[
        "consultant"
    ],
    "wof:name":"Language Works",
    "wof:placetype":"venue"
},
  "geometry": {"coordinates":[-75.59786,40.604638],"type":"Point"}
}