{
  "type": "Feature",
  "properties": {
    "iso:country":"US",
    "sg:address":"2400 Highland Rd",
    "sg:city":"Hermitage",
    "sg:classifiers":[
        {
            "category":"Health Services",
            "subcategory":"Doctor",
            "type":"Services"
        }
    ],
    "sg:phone":"+1   ",
    "sg:postcode":"16148",
    "sg:province":"PA",
    "sg:tags":[
        "medical"
    ],
    "wof:name":"Gallagher John P MD",
    "wof:placetype":"venue"
},
  "geometry": {"coordinates":[-80.468343,41.239207],"type":"Point"}
}