{
  "type": "Feature",
  "properties": {
    "addr:full":"350 Skippack Pike Blue Bell PA 19422",
    "addr:housenumber":"350",
    "addr:postcode":"19422",
    "addr:street":"Skippack Pike",
    "iso:country":"US",
    "sg:address":"350 Skippack Pike",
    "sg:city":"Blue Bell",
    "sg:classifiers":[
        {
            "category":"Retail",
            "subcategory":"Photofinishing",
            "type":"Services"
        }
    ],
    "sg:phone":"+1   ",
    "sg:postcode":"19422",
    "sg:province":"PA",
    "sg:tags":[
        "laboratory"
    ],
    "wof:name":"Proart Photo",
    "wof:placetype":"venue"
},
  "geometry": {"coordinates":[-75.25528,40.145571],"type":"Point"}
}