{
  "type": "Feature",
  "properties": {
    "iso:country":"US",
    "sg:address":"810 Broad St",
    "sg:city":"Washington",
    "sg:classifiers":[
        {
            "category":"Home & Garden",
            "subcategory":"Furniture",
            "type":"Retail Goods"
        }
    ],
    "sg:phone":"+1 724 222 6638",
    "sg:postcode":"15301",
    "sg:province":"PA",
    "wof:name":"Bill's Furniture",
    "wof:placetype":"venue"
},
  "geometry": {"coordinates":[-80.26448000000001,40.171596],"type":"Point"}
}