{
  "type": "Feature",
  "properties": {
    "iso:country":"US",
    "sg:address":"1003 Newark Rd",
    "sg:city":"Toughkenamon",
    "sg:classifiers":[
        {
            "category":"Wholesale",
            "subcategory":"Non-durable Goods",
            "type":"Manufacturing & Wholesale Goods"
        }
    ],
    "sg:phone":"+1   ",
    "sg:postcode":"19374",
    "sg:province":"PA",
    "sg:tags":[
        "merchandise"
    ],
    "wof:name":"Lainee Limited",
    "wof:placetype":"venue"
},
  "geometry": {"coordinates":[-75.754079,39.82335],"type":"Point"}
}