{
  "type": "Feature",
  "properties": {
    "addr:full":"136 Granite Hill Ct Langhorne PA 19047",
    "addr:housenumber":"136",
    "addr:postcode":"19047",
    "addr:street":"Granite Hill Ct",
    "iso:country":"US",
    "sg:address":"136 Granite Hill Ct",
    "sg:city":"Langhorne",
    "sg:classifiers":[
        {
            "category":"Professional",
            "subcategory":"Computer Services",
            "type":"Services"
        }
    ],
    "sg:phone":"+1   ",
    "sg:postcode":"19047",
    "sg:province":"PA",
    "sg:tags":[
        "design",
        "system"
    ],
    "wof:name":"Q N E International Inc",
    "wof:placetype":"venue"
},
  "geometry": {"coordinates":[-74.92883,40.214358],"type":"Point"}
}