{
  "type": "Feature",
  "properties": {
    "iso:country":"US",
    "sg:address":"414 Hidden Valley Rd",
    "sg:city":"New Cumberland",
    "sg:classifiers":[
        {
            "category":"Professional",
            "subcategory":"Computer Services",
            "type":"Services"
        }
    ],
    "sg:phone":"+1   ",
    "sg:postcode":"17070",
    "sg:province":"PA",
    "sg:tags":[
        "design",
        "system"
    ],
    "wof:name":"Jericho Networks Ltd",
    "wof:placetype":"venue"
},
  "geometry": {"coordinates":[-76.85550600000001,40.182327],"type":"Point"}
}