{
  "type": "Feature",
  "properties": {
    "iso:country":"US",
    "sg:address":"290 Krug Rd",
    "sg:city":"Littlestown",
    "sg:classifiers":[
        {
            "category":"Building & Trades",
            "subcategory":"Construction",
            "type":"Services"
        }
    ],
    "sg:phone":"+1 717 359 0909",
    "sg:postcode":"17340",
    "sg:province":"PA",
    "sg:tags":[
        "paving",
        "contractor"
    ],
    "wof:name":"Midkiff Paving Co Inc",
    "wof:placetype":"venue"
},
  "geometry": {"coordinates":[-77.151487,39.749431],"type":"Point"}
}