{
  "type": "Feature",
  "properties": {
    "iso:country":"US",
    "sg:address":"58 Old York Rd",
    "sg:city":"Dillsburg",
    "sg:classifiers":[
        {
            "category":"Autos & Motor Vehicles",
            "subcategory":"Automobile Sales",
            "type":"Retail Goods"
        }
    ],
    "sg:phone":"+1 717 432 8225",
    "sg:postcode":"17019",
    "sg:province":"PA",
    "sg:tags":[
        "car",
        "dealer"
    ],
    "wof:name":"Jeff's Auto Sales",
    "wof:placetype":"venue"
},
  "geometry": {"coordinates":[-77.02276999999999,40.105524],"type":"Point"}
}