{
  "type": "Feature",
  "properties": {
    "iso:country":"US",
    "sg:address":"106 Pinehurst Dr",
    "sg:city":"Cranberry Twp",
    "sg:classifiers":[
        {
            "category":"Professional",
            "subcategory":"Employment Agencies",
            "type":"Services"
        }
    ],
    "sg:phone":"+1 724 538 3434",
    "sg:postcode":"16066",
    "sg:province":"PA",
    "sg:website":"www.hiredemand.com",
    "wof:name":"Hire Demand",
    "wof:placetype":"venue"
},
  "geometry": {"coordinates":[-80.083319,40.725967],"type":"Point"}
}