{
  "type": "Feature",
  "properties": {
    "addr:full":"299 Hurley Rd Coatesville PA 19320",
    "addr:housenumber":"299",
    "addr:postcode":"19320",
    "addr:street":"Hurley Rd",
    "iso:country":"US",
    "sg:address":"299 Hurley Rd",
    "sg:city":"Coatesville",
    "sg:classifiers":[
        {
            "category":"Health Services",
            "subcategory":"Doctor",
            "type":"Services"
        }
    ],
    "sg:phone":"+1 610 384 4114",
    "sg:postcode":"19320",
    "sg:province":"PA",
    "sg:tags":[
        "dentist"
    ],
    "wof:name":"John C Gentile DDS",
    "wof:placetype":"venue"
},
  "geometry": {"coordinates":[-75.79086599999999,40.014427],"type":"Point"}
}