{
  "type": "Feature",
  "properties": {
    "iso:country":"US",
    "sg:address":"944 Indian Hill Rd",
    "sg:city":"Leechburg",
    "sg:classifiers":[
        {
            "category":"Building & Trades",
            "subcategory":"Construction",
            "type":"Services"
        }
    ],
    "sg:phone":"+1 724 845 3100",
    "sg:postcode":"15656",
    "sg:province":"PA",
    "sg:tags":[
        "contractor"
    ],
    "wof:name":"Todd Hrobak Construction",
    "wof:placetype":"venue"
},
  "geometry": {"coordinates":[-79.64273900000001,40.646498],"type":"Point"}
}