{
  "type": "Feature",
  "properties": {
    "iso:country":"US",
    "sg:address":"145 Tedwill Dr",
    "sg:city":"Fountainville",
    "sg:classifiers":[
        {
            "category":"Freight",
            "type":"Transportation"
        }
    ],
    "sg:phone":"+1   ",
    "sg:postcode":"18923",
    "sg:province":"PA",
    "sg:tags":[
        "operator",
        "local",
        "trucking"
    ],
    "wof:name":"Reeser Trucking Inc",
    "wof:placetype":"venue"
},
  "geometry": {"coordinates":[-75.15155900000001,40.338888],"type":"Point"}
}