{
  "type": "Feature",
  "properties": {
    "iso:country":"US",
    "sg:address":"1701 Market St",
    "sg:city":"Philadelphia",
    "sg:classifiers":[
        {
            "category":"Professional",
            "subcategory":"Lawyer & Legal Services",
            "type":"Services"
        }
    ],
    "sg:phone":"+1 215 963 5210",
    "sg:postcode":"19103",
    "sg:province":"PA",
    "sg:tags":[
        "attorney"
    ],
    "wof:name":"Robert D Comfort",
    "wof:placetype":"venue"
},
  "geometry": {"coordinates":[-75.170007,39.953171],"type":"Point"}
}