{
  "type": "Feature",
  "properties": {
    "iso:country":"US",
    "sg:address":"701 N Hermitage Rd",
    "sg:city":"Hermitage",
    "sg:classifiers":[
        {
            "category":"Health Services",
            "subcategory":"Doctor",
            "type":"Services"
        },
        {
            "category":"Social Services",
            "type":"Services"
        },
        {
            "category":"Personal",
            "type":"Services"
        }
    ],
    "sg:phone":"+1 724 346 4510",
    "sg:postcode":"16148",
    "sg:province":"PA",
    "sg:tags":[
        "family",
        "counselors-licensed",
        "psychologist",
        "individual",
        "marriage",
        "child",
        "professional",
        "counselor"
    ],
    "sg:website":"http://www.drmaterna.com",
    "wof:name":"Materna Psychological Services",
    "wof:placetype":"venue"
},
  "geometry": {"coordinates":[-80.449921,41.242981],"type":"Point"}
}