{
  "type": "Feature",
  "properties": {
    "iso:country":"US",
    "sg:address":"2307 W 12th St",
    "sg:city":"Erie",
    "sg:classifiers":[
        {
            "category":"Home & Garden",
            "subcategory":"Carpets & Floor Coverings",
            "type":"Retail Goods"
        }
    ],
    "sg:phone":"+1 814 454 1624",
    "sg:postcode":"16505",
    "sg:province":"PA",
    "wof:name":"Floor Decor Of Erie Inc",
    "wof:placetype":"venue"
},
  "geometry": {"coordinates":[-80.132212,42.104639],"type":"Point"}
}