{
  "type": "Feature",
  "properties": {
    "addr:full":"53 Kurtz Rd Schwenksville PA 19473",
    "addr:housenumber":"53",
    "addr:postcode":"19473",
    "addr:street":"Kurtz Rd",
    "iso:country":"US",
    "sg:address":"53 Kurtz Rd",
    "sg:city":"Schwenksville",
    "sg:classifiers":[
        {
            "category":"Building & Trades",
            "subcategory":"Construction",
            "type":"Services"
        }
    ],
    "sg:phone":"+1 610 287 8619",
    "sg:postcode":"19473",
    "sg:province":"PA",
    "sg:tags":[
        "contractor"
    ],
    "wof:name":"Atlantic Pool Specialties",
    "wof:placetype":"venue"
},
  "geometry": {"coordinates":[-75.55116200000001,40.261586],"type":"Point"}
}