{
  "type": "Feature",
  "properties": {
    "addr:full":"55 Sunset Dr Boyertown PA 19512",
    "addr:housenumber":"55",
    "addr:postcode":"19512",
    "addr:street":"Sunset Dr",
    "iso:country":"US",
    "sg:address":"55 Sunset Dr",
    "sg:city":"Boyertown",
    "sg:classifiers":[
        {
            "category":"Building & Trades",
            "subcategory":"Construction",
            "type":"Services"
        }
    ],
    "sg:phone":"+1 610 367 2932",
    "sg:postcode":"19512",
    "sg:province":"PA",
    "sg:tags":[
        "repairing",
        "remodeling",
        "contractor"
    ],
    "wof:name":"Roger's Remodeling & Rnvtn",
    "wof:placetype":"venue"
},
  "geometry": {"coordinates":[-75.659542,40.301168],"type":"Point"}
}