{
  "type": "Feature",
  "properties": {
    "iso:country":"US",
    "sg:address":"1030 Andrew Dr",
    "sg:city":"West Chester",
    "sg:classifiers":[
        {
            "category":"Social Services",
            "subcategory":"Child Care",
            "type":"Services"
        }
    ],
    "sg:phone":"+1 610 429 5437",
    "sg:postcode":"19380",
    "sg:province":"PA",
    "wof:name":"Kid's Academy Day Care",
    "wof:placetype":"venue"
},
  "geometry": {"coordinates":[-75.59134400000001,39.986378],"type":"Point"}
}