{
  "type": "Feature",
  "properties": {
    "addr:full":"35 Walsh Rd Pittsburgh PA 15205",
    "addr:housenumber":"35",
    "addr:postcode":"15205",
    "addr:street":"Walsh Rd",
    "iso:country":"US",
    "sg:address":"35 Walsh Rd",
    "sg:city":"Pittsburgh",
    "sg:classifiers":[
        {
            "category":"Retail",
            "subcategory":"Laundry & Dry Cleaning",
            "type":"Services"
        }
    ],
    "sg:phone":"+1 412 922 6090",
    "sg:postcode":"15205",
    "sg:province":"PA",
    "sg:tags":[
        "laundries-self",
        "operated",
        "washer",
        "dryer",
        "coin"
    ],
    "wof:name":"Crafton Ingram Laundromat",
    "wof:placetype":"venue"
},
  "geometry": {"coordinates":[-80.071079,40.43926],"type":"Point"}
}