{
  "type": "Feature",
  "properties": {
    "addr:full":"1100 E Philadelphia Ave Gilbertsville PA 19525",
    "addr:housenumber":"1100 e",
    "addr:postcode":"19525",
    "addr:street":"Philadelphia Ave",
    "iso:country":"US",
    "sg:address":"1100 E Philadelphia Ave",
    "sg:city":"Gilbertsville",
    "sg:classifiers":[
        {
            "category":"Shopping",
            "subcategory":"Computers & Home Electronics",
            "type":"Retail Goods"
        }
    ],
    "sg:phone":"+1 610 473 1349",
    "sg:postcode":"19525",
    "sg:province":"PA",
    "sg:tags":[
        "equipment",
        "dealer"
    ],
    "wof:name":"Affordable Computers",
    "wof:placetype":"venue"
},
  "geometry": {"coordinates":[-75.61615999999999,40.322353],"type":"Point"}
}