{
  "type": "Feature",
  "properties": {
    "iso:country":"US",
    "sg:address":"1945 State Rte 72",
    "sg:city":"Lebanon",
    "sg:classifiers":[
        {
            "category":"Autos & Motor Vehicles",
            "subcategory":"Automobile Sales",
            "type":"Retail Goods"
        }
    ],
    "sg:phone":"+1 717 861 5483",
    "sg:postcode":"17046",
    "sg:province":"PA",
    "sg:tags":[
        "car",
        "used",
        "dealer"
    ],
    "wof:name":"Adams Auto Sales Inc",
    "wof:placetype":"venue"
},
  "geometry": {"coordinates":[-76.472853,40.377483],"type":"Point"}
}