{
  "type": "Feature",
  "properties": {
    "addr:full":"2047 Outlook Dr Pittsburgh PA 15241",
    "addr:housenumber":"2047",
    "addr:postcode":"15241",
    "addr:street":"Outlook Dr",
    "iso:country":"US",
    "sg:address":"2047 Outlook Dr",
    "sg:city":"Pittsburgh",
    "sg:classifiers":[
        {
            "category":"Wholesale",
            "subcategory":"Metals & Minerals",
            "type":"Manufacturing & Wholesale Goods"
        }
    ],
    "sg:phone":"+1   ",
    "sg:postcode":"15241",
    "sg:province":"PA",
    "sg:tags":[
        "center"
    ],
    "wof:name":"Tesco Resources Inc",
    "wof:placetype":"venue"
},
  "geometry": {"coordinates":[-80.07454199999999,40.342311],"type":"Point"}
}