{
  "type": "Feature",
  "properties": {
    "addr:full":"827 Pinewood Dr Pottsville PA 17901",
    "addr:housenumber":"827",
    "addr:postcode":"17901",
    "addr:street":"Pinewood Dr",
    "iso:country":"US",
    "sg:address":"827 Pinewood Dr",
    "sg:city":"Pottsville",
    "sg:classifiers":[
        {
            "category":"Professional",
            "subcategory":"Management & Consulting",
            "type":"Services"
        },
        {
            "category":"Professional",
            "subcategory":"Engineering",
            "type":"Services"
        }
    ],
    "sg:phone":"+1 570 622 0111",
    "sg:postcode":"17901",
    "sg:province":"PA",
    "sg:tags":[
        "environmental",
        "ecological",
        "engineer",
        "consultant"
    ],
    "wof:name":"B & D Environmental Inspection",
    "wof:placetype":"venue"
},
  "geometry": {"coordinates":[-76.22535499999999,40.689993],"type":"Point"}
}