{
  "type": "Feature",
  "properties": {
    "iso:country":"US",
    "sg:address":"500 Mifflin St",
    "sg:city":"West Mifflin",
    "sg:classifiers":[
        {
            "category":"Health Services",
            "subcategory":"Hospital",
            "type":"Services"
        }
    ],
    "sg:phone":"+1   ",
    "sg:postcode":"15122",
    "sg:province":"PA",
    "sg:tags":[
        "general"
    ],
    "wof:name":"Southewestern Ambu Surg",
    "wof:placetype":"venue"
},
  "geometry": {"coordinates":[-79.854415,40.361157],"type":"Point"}
}