{
  "type": "Feature",
  "properties": {
    "iso:country":"US",
    "sg:address":"3649 Bull Rd",
    "sg:city":"York",
    "sg:classifiers":[
        {
            "category":"Restaurant",
            "type":"Food & Drink"
        }
    ],
    "sg:phone":"+1 717 292 3562",
    "sg:postcode":"17408",
    "sg:province":"PA",
    "sg:tags":[
        "pizza"
    ],
    "wof:name":"Pops Pizza",
    "wof:placetype":"venue"
},
  "geometry": {"coordinates":[-76.813395,40.015865],"type":"Point"}
}