{
  "type": "Feature",
  "properties": {
    "addr:full":"142 Ruby St Lancaster PA 17603",
    "addr:housenumber":"142",
    "addr:postcode":"17603",
    "addr:street":"Ruby St",
    "iso:country":"US",
    "sg:address":"142 Ruby St",
    "sg:city":"Lancaster",
    "sg:classifiers":[
        {
            "category":"Building & Trades",
            "subcategory":"Construction",
            "type":"Services"
        }
    ],
    "sg:phone":"+1 717 396 9626",
    "sg:postcode":"17603",
    "sg:province":"PA",
    "sg:tags":[
        "roofing",
        "contractor"
    ],
    "wof:name":"Your House Roofing",
    "wof:placetype":"venue"
},
  "geometry": {"coordinates":[-76.320511,40.035724],"type":"Point"}
}