{
  "type": "Feature",
  "properties": {
    "iso:country":"US",
    "sg:address":"426 Princess Ave",
    "sg:city":"Croydon",
    "sg:classifiers":[
        {
            "category":"Building & Trades",
            "subcategory":"Plumbing",
            "type":"Services"
        }
    ],
    "sg:phone":"+1   ",
    "sg:postcode":"19021",
    "sg:province":"PA",
    "sg:tags":[
        "contractor"
    ],
    "wof:name":"Johnstons Mechanical Serv",
    "wof:placetype":"venue"
},
  "geometry": {"coordinates":[-74.91017600000001,40.090158],"type":"Point"}
}