{
  "type": "Feature",
  "properties": {
    "iso:country":"US",
    "sg:address":"25 W 3rd St",
    "sg:city":"Bethlehem",
    "sg:classifiers":[
        {
            "category":"Education",
            "subcategory":"Special Training",
            "type":"Public Place"
        }
    ],
    "sg:phone":"+1 610 332 1300",
    "sg:postcode":"18015",
    "sg:province":"PA",
    "sg:tags":[
        "school",
        "art"
    ],
    "wof:name":"Artsquest",
    "wof:placetype":"venue"
},
  "geometry": {"coordinates":[-75.379601,40.611801],"type":"Point"}
}