{
  "type": "Feature",
  "properties": {
    "iso:country":"US",
    "sg:address":"348 Shady Dell Rd",
    "sg:city":"Port Matilda",
    "sg:classifiers":[
        {
            "category":"Utilities",
            "subcategory":"Refuse",
            "type":"Services"
        },
        {
            "category":"Utilities",
            "type":"Services"
        }
    ],
    "sg:phone":"+1 814 692 8835",
    "sg:postcode":"16870",
    "sg:province":"PA",
    "sg:tags":[
        "sanitary",
        "sanitation"
    ],
    "wof:name":"Williams Sanitation",
    "wof:placetype":"venue"
},
  "geometry": {"coordinates":[-78.088016,40.813536],"type":"Point"}
}