{
  "type": "Feature",
  "properties": {
    "iso:country":"US",
    "sg:address":"113 Bent Tree Dr",
    "sg:city":"Lancaster",
    "sg:classifiers":[
        {
            "category":"Real Estate",
            "subcategory":"Real Estate Agent",
            "type":"Services"
        }
    ],
    "sg:phone":"+1 717 394 6665",
    "sg:postcode":"17603",
    "sg:province":"PA",
    "wof:name":"Bonnie Miller Realtor",
    "wof:placetype":"venue"
},
  "geometry": {"coordinates":[-76.391814,40.03584],"type":"Point"}
}