{
  "type": "Feature",
  "properties": {
    "addr:full":"2546 Gillingham St Philadelphia PA 19137",
    "addr:housenumber":"2546",
    "addr:postcode":"19137",
    "addr:street":"Gillingham St",
    "iso:country":"US",
    "sg:address":"2546 Gillingham St",
    "sg:city":"Philadelphia",
    "sg:classifiers":[
        {
            "category":"Building & Trades",
            "subcategory":"Construction",
            "type":"Services"
        }
    ],
    "sg:phone":"+1   ",
    "sg:postcode":"19137",
    "sg:province":"PA",
    "sg:tags":[
        "house"
    ],
    "wof:name":"Atlantic 3 Construction Co",
    "wof:placetype":"venue"
},
  "geometry": {"coordinates":[-75.077634,40.000743],"type":"Point"}
}