{
  "type": "Feature",
  "properties": {
    "iso:country":"US",
    "sg:address":"1001 W 3rd St",
    "sg:city":"Chester",
    "sg:classifiers":[
        {
            "category":"Food & Beverages",
            "subcategory":"Candy",
            "type":"Retail Goods"
        }
    ],
    "sg:phone":"+1 610 874 7888",
    "sg:postcode":"19013",
    "sg:province":"PA",
    "sg:tags":[
        "confectionery"
    ],
    "wof:name":"John Brown",
    "wof:placetype":"venue"
},
  "geometry": {"coordinates":[-75.373249,39.841143],"type":"Point"}
}