{
  "type": "Feature",
  "properties": {
    "iso:country":"US",
    "sg:address":"819 E Baltimore Ave",
    "sg:city":"Lansdowne",
    "sg:classifiers":[
        {
            "category":"Insurance",
            "subcategory":"Insurance Agent",
            "type":"Services"
        }
    ],
    "sg:phone":"+1 610 623 8710",
    "sg:postcode":"19050",
    "sg:province":"PA",
    "wof:name":"University Insurance Limited",
    "wof:placetype":"venue"
},
  "geometry": {"coordinates":[-75.257768,39.940903],"type":"Point"}
}