{
  "type": "Feature",
  "properties": {
    "addr:full":"456 Mount Rock Rd Newville PA 17241",
    "addr:housenumber":"456",
    "addr:postcode":"17241",
    "addr:street":"Mount Rock Rd",
    "iso:country":"US",
    "sg:address":"456 Mount Rock Rd",
    "sg:city":"Newville",
    "sg:classifiers":[
        {
            "category":"Building & Trades",
            "subcategory":"Landscaping Services",
            "type":"Services"
        }
    ],
    "sg:phone":"+1 717 776 2326",
    "sg:postcode":"17241",
    "sg:province":"PA",
    "sg:tags":[
        "landscape",
        "contractor"
    ],
    "wof:name":"Calaman's Lawn Svc",
    "wof:placetype":"venue"
},
  "geometry": {"coordinates":[-77.340345,40.162164],"type":"Point"}
}