{
  "type": "Feature",
  "properties": {
    "iso:country":"US",
    "sg:address":"1493 E Philadelphia Ave",
    "sg:city":"Gilbertsville",
    "sg:classifiers":[
        {
            "category":"Autos & Motor Vehicles",
            "subcategory":"Auto Supplies",
            "type":"Retail Goods"
        }
    ],
    "sg:phone":"+1   ",
    "sg:postcode":"19525",
    "sg:province":"PA",
    "sg:tags":[
        "repair",
        "general"
    ],
    "wof:name":"Franks Tire Service",
    "wof:placetype":"venue"
},
  "geometry": {"coordinates":[-75.608778,40.318518],"type":"Point"}
}