{
  "type": "Feature",
  "properties": {
    "iso:country":"US",
    "sg:address":"294 State Rte 217",
    "sg:city":"Derry",
    "sg:classifiers":[
        {
            "category":"Building & Trades",
            "subcategory":"Plumbing",
            "type":"Services"
        }
    ],
    "sg:phone":"+1 724 694 2711",
    "sg:postcode":"15627",
    "sg:province":"PA",
    "sg:tags":[
        "heating",
        "contractor"
    ],
    "wof:name":"Barsoum Refrigeration",
    "wof:placetype":"venue"
},
  "geometry": {"coordinates":[-79.29939299999999,40.329895],"type":"Point"}
}