{
  "type": "Feature",
  "properties": {
    "addr:full":"251 Cynwyd Rd Bala Cynwyd PA 19004",
    "addr:housenumber":"251",
    "addr:postcode":"19004",
    "addr:street":"Cynwyd Rd",
    "iso:country":"US",
    "sg:address":"251 Cynwyd Rd",
    "sg:city":"Bala Cynwyd",
    "sg:classifiers":[
        {
            "category":"Insurance",
            "subcategory":"Insurance Agent",
            "type":"Services"
        }
    ],
    "sg:phone":"+1 610 664 8000",
    "sg:postcode":"19004",
    "sg:province":"PA",
    "wof:name":"HSA Corp",
    "wof:placetype":"venue"
},
  "geometry": {"coordinates":[-75.23409100000001,40.005516],"type":"Point"}
}