{
  "type": "Feature",
  "properties": {
    "iso:country":"US",
    "sg:address":"1918 Upper Snake Spring Rd R",
    "sg:city":"Everett",
    "sg:classifiers":[
        {
            "category":"Building & Trades",
            "subcategory":"Construction",
            "type":"Services"
        }
    ],
    "sg:phone":"+1 814 652 6645",
    "sg:postcode":"15537",
    "sg:province":"PA",
    "sg:tags":[
        "wallcoverings-installation",
        "wallpaper",
        "painting",
        "contractor"
    ],
    "wof:name":"Kcs Pro Painting",
    "wof:placetype":"venue"
},
  "geometry": {"coordinates":[-78.391499,40.077814],"type":"Point"}
}