{
  "type": "Feature",
  "properties": {
    "iso:country":"US",
    "sg:address":"4232 Germantown Ave",
    "sg:city":"Philadelphia",
    "sg:classifiers":[
        {
            "category":"Professional",
            "subcategory":"Business Services",
            "type":"Services"
        }
    ],
    "sg:phone":"+1 215 329 9066",
    "sg:postcode":"19140",
    "sg:province":"PA",
    "sg:tags":[
        "recording",
        "studio"
    ],
    "wof:name":"Outta Reach Entertainment",
    "wof:placetype":"venue"
},
  "geometry": {"coordinates":[-75.15613399999999,40.019608],"type":"Point"}
}