{
  "type": "Feature",
  "properties": {
    "addr:full":"255 Shaffer Ave Du Bois PA 15801",
    "addr:housenumber":"255",
    "addr:postcode":"15801",
    "addr:street":"Shaffer Ave Du Bois",
    "iso:country":"US",
    "sg:address":"255 Shaffer Ave",
    "sg:city":"Du Bois",
    "sg:classifiers":[
        {
            "category":"Food & Beverages",
            "subcategory":"Specialty",
            "type":"Retail Goods"
        }
    ],
    "sg:phone":"+1 814 371 9912",
    "sg:postcode":"15801",
    "sg:province":"PA",
    "sg:tags":[
        "health",
        "diet"
    ],
    "wof:name":"General Nutrition Ctr",
    "wof:placetype":"venue"
},
  "geometry": {"coordinates":[-78.76483500000001,41.113249],"type":"Point"}
}