{
  "type": "Feature",
  "properties": {
    "iso:country":"US",
    "sg:address":"7561 Main St",
    "sg:city":"Fairview",
    "sg:classifiers":[
        {
            "category":"Recreation",
            "type":"Entertainment"
        }
    ],
    "sg:phone":"+1 814 474 3424",
    "sg:postcode":"16415",
    "sg:province":"PA",
    "sg:tags":[
        "martial",
        "arts",
        "instruction"
    ],
    "wof:name":"John Barton King Cobra Karate",
    "wof:placetype":"venue"
},
  "geometry": {"coordinates":[-80.256421,42.030542],"type":"Point"}
}