{
  "type": "Feature",
  "properties": {
    "iso:country":"US",
    "sg:address":"314 Meadowlark Dr",
    "sg:city":"Uniontown",
    "sg:classifiers":[
        {
            "category":"Food & Beverages",
            "subcategory":"Bakery",
            "type":"Retail Goods"
        }
    ],
    "sg:phone":"+1 724 437 5204",
    "sg:postcode":"15401",
    "sg:province":"PA",
    "sg:tags":[
        "baker"
    ],
    "wof:name":"Judy Jean Pastry Shop",
    "wof:placetype":"venue"
},
  "geometry": {"coordinates":[-79.729292,39.884169],"type":"Point"}
}