{
  "type": "Feature",
  "properties": {
    "iso:country":"US",
    "sg:address":"101 Summerhill Ave",
    "sg:city":"Berwick",
    "sg:classifiers":[
        {
            "category":"Restaurant",
            "type":"Food & Drink"
        }
    ],
    "sg:phone":"+1   ",
    "sg:postcode":"18603",
    "sg:province":"PA",
    "sg:tags":[
        "eating"
    ],
    "wof:name":"Amys Restaurant",
    "wof:placetype":"venue"
},
  "geometry": {"coordinates":[-76.24233599999999,41.066492],"type":"Point"}
}