{
  "type": "Feature",
  "properties": {
    "iso:country":"US",
    "sg:address":"20 Briarcrest Sq",
    "sg:city":"Hershey",
    "sg:classifiers":[
        {
            "category":"Health Services",
            "subcategory":"Doctor",
            "type":"Services"
        }
    ],
    "sg:phone":"+1 717 533 0600",
    "sg:postcode":"17033",
    "sg:province":"PA",
    "sg:tags":[
        "psychiatrist"
    ],
    "wof:name":"Fernando Chona G MD & Associates",
    "wof:placetype":"venue"
},
  "geometry": {"coordinates":[-76.672302,40.270599],"type":"Point"}
}