{
  "type": "Feature",
  "properties": {
    "addr:full":"2208 Northampton Ave Northampton PA 18067",
    "addr:housenumber":"2208",
    "addr:postcode":"18067",
    "addr:street":"Northampton Ave",
    "iso:country":"US",
    "sg:address":"2208 Northampton Ave",
    "sg:city":"Northampton",
    "sg:classifiers":[
        {
            "category":"Building & Trades",
            "subcategory":"Landscaping Services",
            "type":"Services"
        }
    ],
    "sg:phone":"+1   ",
    "sg:postcode":"18067",
    "sg:province":"PA",
    "wof:name":"Artistic Landscaping Inc",
    "wof:placetype":"venue"
},
  "geometry": {"coordinates":[-75.49550000000001,40.695078],"type":"Point"}
}