{
  "type": "Feature",
  "properties": {
    "iso:country":"US",
    "sg:address":"44 Conway St",
    "sg:city":"Carlisle",
    "sg:classifiers":[
        {
            "category":"Autos & Motor Vehicles",
            "subcategory":"Auto Supplies",
            "type":"Retail Goods"
        }
    ],
    "sg:phone":"+1   ",
    "sg:postcode":"17013",
    "sg:province":"PA",
    "wof:name":"Legend Cars of Central PA",
    "wof:placetype":"venue"
},
  "geometry": {"coordinates":[-77.200185,40.201769],"type":"Point"}
}