{
  "type": "Feature",
  "properties": {
    "addr:full":"406 Bowmansville Rd Mohnton PA 19540",
    "addr:housenumber":"406",
    "addr:postcode":"19540",
    "addr:street":"Bowmansville Rd",
    "iso:country":"US",
    "sg:address":"406 Bowmansville Rd",
    "sg:city":"Mohnton",
    "sg:classifiers":[
        {
            "category":"Building & Trades",
            "subcategory":"Construction",
            "type":"Services"
        }
    ],
    "sg:phone":"+1 610 507 8430",
    "sg:postcode":"19540",
    "sg:province":"PA",
    "sg:tags":[
        "handyman"
    ],
    "wof:name":"Kachel Fork Lift Repair",
    "wof:placetype":"venue"
},
  "geometry": {"coordinates":[-75.963511,40.213483],"type":"Point"}
}