{
  "type": "Feature",
  "properties": {
    "addr:full":"80 Allegheny River Blvd Verona PA 15147",
    "addr:housenumber":"80",
    "addr:postcode":"15147",
    "addr:street":"Allegheny River Blvd",
    "iso:country":"US",
    "sg:address":"80 Allegheny River Blvd",
    "sg:city":"Verona",
    "sg:classifiers":[
        {
            "category":"Bars & Pubs",
            "type":"Food & Drink"
        },
        {
            "category":"Restaurant",
            "type":"Food & Drink"
        }
    ],
    "sg:phone":"+1 412 826 1500",
    "sg:postcode":"15147",
    "sg:province":"PA",
    "wof:name":"Somma Pizza & Sports Bar",
    "wof:placetype":"venue"
},
  "geometry": {"coordinates":[-79.843238,40.500116],"type":"Point"}
}