{
  "type": "Feature",
  "properties": {
    "addr:full":"5818 Schoolhouse Rd Elizabethtown PA 17022",
    "addr:housenumber":"5818",
    "addr:postcode":"17022",
    "addr:street":"Schoolhouse Rd",
    "iso:country":"US",
    "sg:address":"5818 Schoolhouse Rd",
    "sg:city":"Elizabethtown",
    "sg:classifiers":[
        {
            "category":"Professional",
            "subcategory":"Computer Services",
            "type":"Services"
        }
    ],
    "sg:phone":"+1   ",
    "sg:postcode":"17022",
    "sg:province":"PA",
    "sg:tags":[
        "fantasy",
        "sport"
    ],
    "wof:name":"Rotoplaycom",
    "wof:placetype":"venue"
},
  "geometry": {"coordinates":[-76.625124,40.221288],"type":"Point"}
}