{
  "type": "Feature",
  "properties": {
    "addr:full":"4206 Baltimore Ave Philadelphia PA 19104",
    "addr:housenumber":"4206",
    "addr:postcode":"19104",
    "addr:street":"Baltimore Ave",
    "iso:country":"US",
    "sg:address":"4206 Baltimore Ave",
    "sg:city":"Philadelphia",
    "sg:classifiers":[
        {
            "category":"Professional",
            "subcategory":"Business Services",
            "type":"Services"
        }
    ],
    "sg:phone":"+1 215 222 9440",
    "sg:postcode":"19104",
    "sg:province":"PA",
    "wof:name":"Penn Business Network",
    "wof:placetype":"venue"
},
  "geometry": {"coordinates":[-75.207742,39.949689],"type":"Point"}
}