{
  "type": "Feature",
  "properties": {
    "iso:country":"US",
    "sg:address":"25 Forgedale Rd",
    "sg:city":"Fleetwood",
    "sg:classifiers":[
        {
            "category":"Real Estate",
            "subcategory":"Real Estate Agent",
            "type":"Services"
        }
    ],
    "sg:phone":"+1 610 987 3300",
    "sg:postcode":"19522",
    "sg:province":"PA",
    "wof:name":"William J Strachan Realty",
    "wof:placetype":"venue"
},
  "geometry": {"coordinates":[-75.762,40.414705],"type":"Point"}
}