{
  "type": "Feature",
  "properties": {
    "iso:country":"US",
    "sg:address":"2417 E State St",
    "sg:city":"Hermitage",
    "sg:classifiers":[
        {
            "category":"Fast Food",
            "type":"Food & Drink"
        },
        {
            "category":"Restaurant",
            "type":"Food & Drink"
        }
    ],
    "sg:phone":"+1 724 981 0634",
    "sg:postcode":"16148",
    "sg:province":"PA",
    "sg:tags":[
        "take",
        "pizza"
    ],
    "wof:name":"Plaza Pizza",
    "wof:placetype":"venue"
},
  "geometry": {"coordinates":[-80.465571,41.233382],"type":"Point"}
}