{
  "type": "Feature",
  "properties": {
    "iso:country":"US",
    "sg:address":"662 2nd Street Pike",
    "sg:city":"Southampton",
    "sg:classifiers":[
        {
            "category":"Home & Garden",
            "subcategory":"Carpets & Floor Coverings",
            "type":"Retail Goods"
        }
    ],
    "sg:phone":"+1 215 322 6736",
    "sg:postcode":"18966",
    "sg:province":"PA",
    "sg:tags":[
        "distributor",
        "rug",
        "manufacturer"
    ],
    "wof:name":"New Look Carpet, Inc.",
    "wof:placetype":"venue"
},
  "geometry": {"coordinates":[-75.04417599999999,40.173256],"type":"Point"}
}