{
  "type": "Feature",
  "properties": {
    "iso:country":"US",
    "sg:address":"1917 Smallman St",
    "sg:city":"Pittsburgh",
    "sg:classifiers":[
        {
            "category":"Restaurant",
            "type":"Food & Drink"
        }
    ],
    "sg:phone":"+1 412 281 1004",
    "sg:postcode":"15222",
    "sg:province":"PA",
    "sg:tags":[
        "pizza"
    ],
    "wof:name":"Piece of the Strip",
    "wof:placetype":"venue"
},
  "geometry": {"coordinates":[-79.98528899999999,40.451517],"type":"Point"}
}