{
  "type": "Feature",
  "properties": {
    "addr:full":"5020 Walnut St Mc Keesport PA 15132",
    "addr:housenumber":"5020",
    "addr:postcode":"15132",
    "addr:street":"Walnut St",
    "iso:country":"US",
    "sg:address":"5020 Walnut St",
    "sg:city":"Mc Keesport",
    "sg:classifiers":[
        {
            "category":"Retail",
            "subcategory":"Repair Shop",
            "type":"Services"
        }
    ],
    "sg:phone":"+1   ",
    "sg:postcode":"15132",
    "sg:province":"PA",
    "sg:tags":[
        "a",
        "television",
        "appliance"
    ],
    "wof:name":"Eddies TV & Appliance Service",
    "wof:placetype":"venue"
},
  "geometry": {"coordinates":[-79.831731,40.315647],"type":"Point"}
}