{
  "type": "Feature",
  "properties": {
    "iso:country":"US",
    "sg:address":"1737 E 3rd St",
    "sg:city":"Williamsport",
    "sg:classifiers":[
        {
            "category":"Real Estate",
            "subcategory":"Real Estate Agent",
            "type":"Services"
        }
    ],
    "sg:phone":"+1 570 322 1991",
    "sg:postcode":"17701",
    "sg:province":"PA",
    "sg:website":"www.welcomehomepa.com",
    "wof:name":"Real Estate Excel",
    "wof:placetype":"venue"
},
  "geometry": {"coordinates":[-76.96852699999999,41.249801],"type":"Point"}
}