{
  "type": "Feature",
  "properties": {
    "addr:full":"2800 Welsh Rd Philadelphia PA 19152",
    "addr:housenumber":"2800",
    "addr:postcode":"19152",
    "addr:street":"Welsh Rd",
    "iso:country":"US",
    "sg:address":"2800 Welsh Rd",
    "sg:city":"Philadelphia",
    "sg:classifiers":[
        {
            "category":"Real Estate",
            "subcategory":"Real Estate Operator",
            "type":"Services"
        }
    ],
    "sg:phone":"+1 215 969 3348",
    "sg:postcode":"19152",
    "sg:province":"PA",
    "sg:tags":[
        "building",
        "apartment"
    ],
    "wof:name":"Manchester Apartments",
    "wof:placetype":"venue"
},
  "geometry": {"coordinates":[-75.02823600000001,40.063357],"type":"Point"}
}