{
  "type": "Feature",
  "properties": {
    "iso:country":"US",
    "sg:address":"3400 W Chester Pike",
    "sg:city":"Newtown Square",
    "sg:classifiers":[
        {
            "category":"Building & Trades",
            "subcategory":"Construction",
            "type":"Services"
        }
    ],
    "sg:phone":"+1   ",
    "sg:postcode":"19073",
    "sg:province":"PA",
    "sg:tags":[
        "house"
    ],
    "wof:name":"T Daniel Mullray Builders",
    "wof:placetype":"venue"
},
  "geometry": {"coordinates":[-75.385531,39.984225],"type":"Point"}
}