{
  "type": "Feature",
  "properties": {
    "iso:country":"US",
    "sg:address":"744 Buchdale Dr",
    "sg:city":"Manheim",
    "sg:classifiers":[
        {
            "category":"Autos & Motor Vehicles",
            "subcategory":"Automobile Sales",
            "type":"Retail Goods"
        }
    ],
    "sg:phone":"+1 717 664 4002",
    "sg:postcode":"17545",
    "sg:province":"PA",
    "sg:tags":[
        "repair",
        "used",
        "automotive"
    ],
    "wof:name":"Ace Auto Co",
    "wof:placetype":"venue"
},
  "geometry": {"coordinates":[-76.38126200000001,40.14723],"type":"Point"}
}