{
  "type": "Feature",
  "properties": {
    "iso:country":"US",
    "sg:address":"4930 W Chester Pike",
    "sg:city":"Newtown Square",
    "sg:classifiers":[
        {
            "category":"Wholesale",
            "subcategory":"Durable Goods & Equipment",
            "type":"Manufacturing & Wholesale Goods"
        }
    ],
    "sg:phone":"+1 610 429 9638",
    "sg:postcode":"19073",
    "sg:province":"PA",
    "sg:tags":[
        "representative",
        "manufacturer"
    ],
    "wof:name":"Confident Controls",
    "wof:placetype":"venue"
},
  "geometry": {"coordinates":[-75.444872,39.974935],"type":"Point"}
}