{
  "type": "Feature",
  "properties": {
    "iso:country":"US",
    "sg:address":"101 E Hancock St",
    "sg:city":"Lansdale",
    "sg:classifiers":[
        {
            "category":"Retail",
            "subcategory":"Auto Repair",
            "type":"Services"
        }
    ],
    "sg:phone":"+1 215 855 9323",
    "sg:postcode":"19446",
    "sg:province":"PA",
    "sg:tags":[
        "repairing",
        "automobile"
    ],
    "wof:name":"Hauck's Garage",
    "wof:placetype":"venue"
},
  "geometry": {"coordinates":[-75.286697,40.235901],"type":"Point"}
}