{
  "type": "Feature",
  "properties": {
    "iso:country":"US",
    "sg:address":"4910 N Salem Church Rd",
    "sg:city":"Dover",
    "sg:classifiers":[
        {
            "category":"Real Estate",
            "subcategory":"Developer",
            "type":"Services"
        }
    ],
    "sg:phone":"+1   ",
    "sg:postcode":"17315",
    "sg:province":"PA",
    "sg:tags":[
        "cemetery"
    ],
    "wof:name":"Salem Cemetary",
    "wof:placetype":"venue"
},
  "geometry": {"coordinates":[-76.858889,39.990997],"type":"Point"}
}