{
  "type": "Feature",
  "properties": {
    "iso:country":"US",
    "sg:address":"1332 Main St",
    "sg:city":"Pittsburgh",
    "sg:classifiers":[
        {
            "category":"Building & Trades",
            "subcategory":"Plumbing",
            "type":"Services"
        }
    ],
    "sg:phone":"+1   ",
    "sg:postcode":"15215",
    "sg:province":"PA",
    "sg:tags":[
        "contractor"
    ],
    "wof:name":"Harrover A Heating & AC",
    "wof:placetype":"venue"
},
  "geometry": {"coordinates":[-79.929491,40.494322],"type":"Point"}
}