{
  "type": "Feature",
  "properties": {
    "iso:country":"US",
    "sg:address":"168 S Sanatoga Rd",
    "sg:city":"Pottstown",
    "sg:classifiers":[
        {
            "category":"Health Services",
            "subcategory":"Doctor",
            "type":"Services"
        }
    ],
    "sg:phone":"+1   ",
    "sg:postcode":"19464",
    "sg:province":"PA",
    "sg:tags":[
        "medical"
    ],
    "wof:name":"George F Gowen MD",
    "wof:placetype":"venue"
},
  "geometry": {"coordinates":[-75.588229,40.240301],"type":"Point"}
}