{
  "type": "Feature",
  "properties": {
    "iso:country":"US",
    "sg:address":"80 Van Burren Rd",
    "sg:city":"Jersey Shore",
    "sg:classifiers":[
        {
            "category":"Home & Garden",
            "subcategory":"Garden Supply",
            "type":"Retail Goods"
        }
    ],
    "sg:phone":"+1 570 745 3600",
    "sg:postcode":"17740",
    "sg:province":"PA",
    "sg:tags":[
        "repair",
        "lawn",
        "mower"
    ],
    "wof:name":"Jim's Small Engine Repair",
    "wof:placetype":"venue"
},
  "geometry": {"coordinates":[-77.20675,41.140637],"type":"Point"}
}