{
  "type": "Feature",
  "properties": {
    "iso:country":"US",
    "sg:address":"309 W 9th Ave",
    "sg:city":"Tarentum",
    "sg:classifiers":[
        {
            "category":"Professional",
            "type":"Services"
        }
    ],
    "sg:phone":"+1   ",
    "sg:postcode":"15084",
    "sg:province":"PA",
    "wof:name":"James David Pugh",
    "wof:placetype":"venue"
},
  "geometry": {"coordinates":[-79.764404,40.600279],"type":"Point"}
}