{
  "type": "Feature",
  "properties": {
    "iso:country":"US",
    "sg:address":"1141 W Saw Mill Rd",
    "sg:city":"Quakertown",
    "sg:classifiers":[
        {
            "category":"Building & Trades",
            "subcategory":"Construction",
            "type":"Services"
        }
    ],
    "sg:phone":"+1   ",
    "sg:postcode":"18951",
    "sg:province":"PA",
    "sg:tags":[
        "house"
    ],
    "wof:name":"W C Otto Crpentry/Construction",
    "wof:placetype":"venue"
},
  "geometry": {"coordinates":[-75.281729,40.488411],"type":"Point"}
}