{
  "type": "Feature",
  "properties": {
    "iso:country":"US",
    "sg:address":"1225 N Darby Rd",
    "sg:city":"Hermitage",
    "sg:classifiers":[
        {
            "category":"Personal",
            "subcategory":"Beauty Salon",
            "type":"Services"
        }
    ],
    "sg:phone":"+1 724 962 3266",
    "sg:postcode":"16148",
    "sg:province":"PA",
    "wof:name":"Gerald Kulka Beauty Salon",
    "wof:placetype":"venue"
},
  "geometry": {"coordinates":[-80.406246,41.250441],"type":"Point"}
}