{
  "type": "Feature",
  "properties": {
    "iso:country":"US",
    "sg:address":"1617 Trindle Rd",
    "sg:city":"Carlisle",
    "sg:classifiers":[
        {
            "category":"Retail",
            "subcategory":"Veterinary Services",
            "type":"Services"
        }
    ],
    "sg:phone":"+1 717 243 8706",
    "sg:postcode":"17013",
    "sg:province":"PA",
    "sg:tags":[
        "veterinarian"
    ],
    "wof:name":"Kindred Spirit Veterinary Hospital",
    "wof:placetype":"venue"
},
  "geometry": {"coordinates":[-77.125999,40.196499],"type":"Point"}
}