{
  "type": "Feature",
  "properties": {
    "iso:country":"US",
    "sg:address":"1645 2nd St",
    "sg:city":"Beaver",
    "sg:classifiers":[
        {
            "category":"Manufacturing",
            "subcategory":"Printing",
            "type":"Manufacturing & Wholesale Goods"
        }
    ],
    "sg:phone":"+1   ",
    "sg:postcode":"15009",
    "sg:province":"PA",
    "sg:tags":[
        "commercial"
    ],
    "wof:name":"Paper Patch",
    "wof:placetype":"venue"
},
  "geometry": {"coordinates":[-80.317984,40.68731],"type":"Point"}
}