{
  "type": "Feature",
  "properties": {
    "addr:full":"6 W State St Media PA 19063",
    "addr:housenumber":"6",
    "addr:postcode":"19063",
    "addr:street":"W State St",
    "iso:country":"US",
    "sg:address":"6 W State St",
    "sg:city":"Media",
    "sg:classifiers":[
        {
            "category":"Restaurant",
            "type":"Food & Drink"
        }
    ],
    "sg:menulink":"http://www.allmenus.com/pa/media/19187-margaret-kuos-media/menu/",
    "sg:phone":"+1 610 892 0115",
    "sg:postcode":"19063",
    "sg:province":"PA",
    "sg:tags":[
        "asian",
        "chinese"
    ],
    "wof:name":"Margaret Kuo's",
    "wof:placetype":"venue"
},
  "geometry": {"coordinates":[-75.38966000000001,39.917973],"type":"Point"}
}