{
  "type": "Feature",
  "properties": {
    "iso:country":"US",
    "sg:address":"2619 W Chester Pike",
    "sg:city":"Broomall",
    "sg:classifiers":[
        {
            "category":"Health Services",
            "subcategory":"Doctor",
            "type":"Services"
        }
    ],
    "sg:phone":"+1 610 356 8011",
    "sg:postcode":"19008",
    "sg:province":"PA",
    "sg:tags":[
        "denture",
        "dentists-prosthodontists",
        "center"
    ],
    "wof:name":"Watson Thomas C Dds",
    "wof:placetype":"venue"
},
  "geometry": {"coordinates":[-75.362261,39.982125],"type":"Point"}
}