{
  "type": "Feature",
  "properties": {
    "addr:full":"100 N Bank St Phoenixville PA 19460",
    "addr:housenumber":"100",
    "addr:postcode":"19460",
    "addr:street":"N Bank St",
    "iso:country":"US",
    "sg:address":"100 N Bank St",
    "sg:city":"Phoenixville",
    "sg:classifiers":[
        {
            "category":"Restaurant",
            "type":"Food & Drink"
        }
    ],
    "sg:phone":"+1 610 933 3030",
    "sg:postcode":"19460",
    "sg:province":"PA",
    "sg:tags":[
        "eating"
    ],
    "wof:name":"Domino's Pizza",
    "wof:placetype":"venue"
},
  "geometry": {"coordinates":[-75.517149,40.134726],"type":"Point"}
}