{
  "type": "Feature",
  "properties": {
    "addr:full":"6216 Elmwood Ave Philadelphia PA 19142",
    "addr:housenumber":"6216",
    "addr:postcode":"19142",
    "addr:street":"Elmwood Ave",
    "iso:country":"US",
    "sg:address":"6216 Elmwood Ave",
    "sg:city":"Philadelphia",
    "sg:classifiers":[
        {
            "category":"Place Of Worship",
            "subcategory":"Church",
            "type":"Public Place"
        },
        {
            "category":"Place Of Worship",
            "type":"Public Place"
        }
    ],
    "sg:phone":"+1 215 729 7900",
    "sg:postcode":"19142",
    "sg:province":"PA",
    "sg:tags":[
        "churches-interdenominational",
        "churches-various",
        "denomination"
    ],
    "wof:name":"Spirit Of Hope International Ministries",
    "wof:placetype":"venue"
},
  "geometry": {"coordinates":[-75.22689800000001,39.924629],"type":"Point"}
}