{
  "type": "Feature",
  "properties": {
    "iso:country":"US",
    "sg:address":"405 Mccracken Rd",
    "sg:city":"Danville",
    "sg:classifiers":[
        {
            "category":"Home & Garden",
            "subcategory":"Carpets & Floor Coverings",
            "type":"Retail Goods"
        }
    ],
    "sg:phone":"+1 570 275 8305",
    "sg:postcode":"17821",
    "sg:province":"PA",
    "sg:tags":[
        "installation"
    ],
    "wof:name":"Kline Jim Carpet Installation",
    "wof:placetype":"venue"
},
  "geometry": {"coordinates":[-76.623181,41.001754],"type":"Point"}
}