{
  "type": "Feature",
  "properties": {
    "addr:full":"1601 W Lehigh Ave Philadelphia PA 19132",
    "addr:housenumber":"1601",
    "addr:postcode":"19132",
    "addr:street":"W Lehigh Ave",
    "iso:country":"US",
    "sg:address":"1601 W Lehigh Ave",
    "sg:city":"Philadelphia",
    "sg:classifiers":[
        {
            "category":"Professional",
            "type":"Services"
        }
    ],
    "sg:phone":"+1 215 221 1837",
    "sg:postcode":"19132",
    "sg:province":"PA",
    "sg:tags":[
        "establishment"
    ],
    "wof:name":"V M R Corp Inc",
    "wof:placetype":"venue"
},
  "geometry": {"coordinates":[-75.15835800000001,39.994382],"type":"Point"}
}