{
  "type": "Feature",
  "properties": {
    "iso:country":"US",
    "sg:address":"1811 W 8th St",
    "sg:city":"Erie",
    "sg:classifiers":[
        {
            "category":"Retail",
            "subcategory":"Laundry & Dry Cleaning",
            "type":"Services"
        }
    ],
    "sg:phone":"+1   ",
    "sg:postcode":"16505",
    "sg:province":"PA",
    "sg:tags":[
        "drycleaning",
        "plant"
    ],
    "wof:name":"Reliable Tailors & Dry Clrs",
    "wof:placetype":"venue"
},
  "geometry": {"coordinates":[-80.125908,42.111925],"type":"Point"}
}