{
  "type": "Feature",
  "properties": {
    "addr:full":"3811 Broadway Allentown PA 18104",
    "addr:housenumber":"3811",
    "addr:postcode":"18104",
    "addr:street":"Broadway",
    "iso:country":"US",
    "sg:address":"3811 Broadway",
    "sg:city":"Allentown",
    "sg:classifiers":[
        {
            "category":"Health Services",
            "subcategory":"Doctor",
            "type":"Services"
        }
    ],
    "sg:phone":"+1 610 435 1812",
    "sg:postcode":"18104",
    "sg:province":"PA",
    "wof:name":"Hudock John A Dr",
    "wof:placetype":"venue"
},
  "geometry": {"coordinates":[-75.53703400000001,40.584503],"type":"Point"}
}