{
  "type": "Feature",
  "properties": {
    "addr:full":"301 E Chelten Ave Philadelphia PA 19144",
    "addr:housenumber":"301",
    "addr:postcode":"19144",
    "addr:street":"E Chelten Ave",
    "iso:country":"US",
    "sg:address":"301 E Chelten Ave",
    "sg:city":"Philadelphia",
    "sg:classifiers":[
        {
            "category":"Health Services",
            "subcategory":"Clinic",
            "type":"Services"
        }
    ],
    "sg:phone":"+1 215 842 2866",
    "sg:postcode":"19144",
    "sg:province":"PA",
    "sg:tags":[
        "welfare"
    ],
    "wof:name":"Northwest Center Inc Comprehensive Mental Health",
    "wof:placetype":"venue"
},
  "geometry": {"coordinates":[-75.171631,40.038841],"type":"Point"}
}