{
  "type": "Feature",
  "properties": {
    "iso:country":"US",
    "sg:address":"132 Old Kennett Rd",
    "sg:city":"Kennett Square",
    "sg:classifiers":[
        {
            "category":"Building & Trades",
            "subcategory":"Plumbing",
            "type":"Services"
        }
    ],
    "sg:phone":"+1   ",
    "sg:postcode":"19348",
    "sg:province":"PA",
    "sg:tags":[
        "contractor"
    ],
    "wof:name":"Steven Davis Heating Service",
    "wof:placetype":"venue"
},
  "geometry": {"coordinates":[-75.697259,39.828814],"type":"Point"}
}