{
  "type": "Feature",
  "properties": {
    "iso:country":"US",
    "sg:address":"4 W 4th St",
    "sg:city":"Bethlehem",
    "sg:classifiers":[
        {
            "category":"Restaurant",
            "type":"Food & Drink"
        }
    ],
    "sg:phone":"+1   ",
    "sg:postcode":"18015",
    "sg:province":"PA",
    "sg:tags":[
        "eating"
    ],
    "wof:name":"Piggees",
    "wof:placetype":"venue"
},
  "geometry": {"coordinates":[-75.37964599999999,40.610335],"type":"Point"}
}