{
  "type": "Feature",
  "properties": {
    "addr:full":"121 Grant Ave Vandergrift PA 15690",
    "addr:housenumber":"121",
    "addr:postcode":"15690",
    "addr:street":"Grant Ave",
    "iso:country":"US",
    "sg:address":"121 Grant Ave",
    "sg:city":"Vandergrift",
    "sg:classifiers":[
        {
            "category":"Restaurant",
            "type":"Food & Drink"
        }
    ],
    "sg:phone":"+1   ",
    "sg:postcode":"15690",
    "sg:province":"PA",
    "sg:tags":[
        "eating"
    ],
    "wof:name":"Great Wall Restaurant",
    "wof:placetype":"venue"
},
  "geometry": {"coordinates":[-79.563597,40.603671],"type":"Point"}
}