{
  "type": "Feature",
  "properties": {
    "iso:country":"US",
    "sg:address":"94 Locust St",
    "sg:city":"Etna",
    "sg:classifiers":[
        {
            "category":"Organizations",
            "subcategory":"Religious Organization",
            "type":"Services"
        }
    ],
    "sg:phone":"+1 412 781 3056",
    "sg:postcode":"15223",
    "sg:province":"PA",
    "sg:tags":[
        "church"
    ],
    "wof:name":"Calvert Memorial Presbyterian",
    "wof:placetype":"venue"
},
  "geometry": {"coordinates":[-79.94474700000001,40.498728],"type":"Point"}
}