{
  "type": "Feature",
  "properties": {
    "iso:country":"US",
    "sg:address":"1257 Lancaster Ave",
    "sg:city":"Berwyn",
    "sg:classifiers":[
        {
            "category":"Fast Food",
            "type":"Food & Drink"
        },
        {
            "category":"Restaurant",
            "type":"Food & Drink"
        }
    ],
    "sg:phone":"+1 610 695 2398",
    "sg:postcode":"19312",
    "sg:province":"PA",
    "sg:tags":[
        "hamburger",
        "hot",
        "dog",
        "american",
        "take",
        "chicken"
    ],
    "sg:website":"http://www.mcdonalds.com",
    "wof:name":"McDonald's",
    "wof:placetype":"venue"
},
  "geometry": {"coordinates":[-75.45422000000001,40.042948],"type":"Point"}
}