{
  "type": "Feature",
  "properties": {
    "iso:country":"US",
    "sg:address":"834 Chestnut St",
    "sg:city":"Philadelphia",
    "sg:classifiers":[
        {
            "category":"Professional",
            "subcategory":"Advertising",
            "type":"Services"
        }
    ],
    "sg:phone":"+1   ",
    "sg:postcode":"19107",
    "sg:province":"PA",
    "sg:tags":[
        "graphic",
        "design",
        "agency"
    ],
    "wof:name":"Lf Banks & Associates",
    "wof:placetype":"venue"
},
  "geometry": {"coordinates":[-75.155084,39.949667],"type":"Point"}
}