{
  "type": "Feature",
  "properties": {
    "iso:country":"US",
    "sg:address":"257 Brook St",
    "sg:city":"Forest City",
    "sg:classifiers":[
        {
            "category":"Professional",
            "subcategory":"Management & Consulting",
            "type":"Services"
        }
    ],
    "sg:phone":"+1   ",
    "sg:postcode":"18421",
    "sg:province":"PA",
    "wof:name":"Rasbeck Enterprises",
    "wof:placetype":"venue"
},
  "geometry": {"coordinates":[-75.454978,41.649656],"type":"Point"}
}