{
  "type": "Feature",
  "properties": {
    "iso:country":"US",
    "sg:address":"968 Wayne Ave",
    "sg:city":"Indiana",
    "sg:classifiers":[
        {
            "category":"Education",
            "subcategory":"Special Training",
            "type":"Public Place"
        }
    ],
    "sg:phone":"+1   ",
    "sg:postcode":"15701",
    "sg:province":"PA",
    "sg:tags":[
        "instrument",
        "musical"
    ],
    "wof:name":"Ogoreuc Music Shop",
    "wof:placetype":"venue"
},
  "geometry": {"coordinates":[-79.15634900000001,40.61458],"type":"Point"}
}