{
  "type": "Feature",
  "properties": {
    "addr:full":"340 Black Rock Rd Hanover PA 17331",
    "addr:housenumber":"340",
    "addr:postcode":"17331",
    "addr:street":"Black Rock Rd",
    "iso:country":"US",
    "sg:address":"340 Black Rock Rd",
    "sg:city":"Hanover",
    "sg:classifiers":[
        {
            "category":"Retail",
            "subcategory":"Animal Services",
            "type":"Services"
        }
    ],
    "sg:phone":"+1 717 632 2288",
    "sg:postcode":"17331",
    "sg:province":"PA",
    "sg:tags":[
        "pet",
        "grooming",
        "washing"
    ],
    "wof:name":"SHAGS",
    "wof:placetype":"venue"
},
  "geometry": {"coordinates":[-76.95491800000001,39.781465],"type":"Point"}
}