{
  "type": "Feature",
  "properties": {
    "iso:country":"US",
    "sg:address":"250 Jefferson Dr",
    "sg:city":"Mc Kees Rocks",
    "sg:classifiers":[
        {
            "category":"Health Services",
            "subcategory":"Nursing And Care Facility",
            "type":"Services"
        }
    ],
    "sg:phone":"+1 412 331 4633",
    "sg:postcode":"15136",
    "sg:province":"PA",
    "sg:tags":[
        "home",
        "retirement",
        "community"
    ],
    "wof:name":"Ohioview Towers",
    "wof:placetype":"venue"
},
  "geometry": {"coordinates":[-80.07420399999999,40.47888],"type":"Point"}
}