{
  "type": "Feature",
  "properties": {
    "iso:country":"US",
    "sg:address":"9214 Frankford Ave",
    "sg:city":"Philadelphia",
    "sg:classifiers":[
        {
            "category":"Autos & Motor Vehicles",
            "subcategory":"Fuel & Gas Station",
            "type":"Retail Goods"
        }
    ],
    "sg:phone":"+1   ",
    "sg:postcode":"19114",
    "sg:province":"PA",
    "sg:tags":[
        "station",
        "gasoline"
    ],
    "wof:name":"Gamils Mart",
    "wof:placetype":"venue"
},
  "geometry": {"coordinates":[-75.00323400000001,40.055874],"type":"Point"}
}