{
  "type": "Feature",
  "properties": {
    "iso:country":"US",
    "sg:address":"851 Old Rte 220 N",
    "sg:city":"Duncansville",
    "sg:classifiers":[
        {
            "category":"Home & Garden",
            "subcategory":"Carpets & Floor Coverings",
            "type":"Retail Goods"
        }
    ],
    "sg:phone":"+1 814 695 1111",
    "sg:postcode":"16635",
    "sg:province":"PA",
    "sg:tags":[
        "material"
    ],
    "sg:website":"www.degol.com",
    "wof:name":"De Gol Brothers Carpet",
    "wof:placetype":"venue"
},
  "geometry": {"coordinates":[-78.417338,40.431064],"type":"Point"}
}