{
  "type": "Feature",
  "properties": {
    "iso:country":"US",
    "sg:address":"735 County Line Rd",
    "sg:city":"Horsham",
    "sg:classifiers":[
        {
            "category":"Building & Trades",
            "subcategory":"Locksmith",
            "type":"Services"
        }
    ],
    "sg:phone":"+1 267 960 5134",
    "sg:postcode":"19044",
    "sg:province":"PA",
    "sg:tags":[
        "key"
    ],
    "wof:name":"Always Affective Available Emergency Locksmith",
    "wof:placetype":"venue"
},
  "geometry": {"coordinates":[-75.138547,40.210986],"type":"Point"}
}