{
  "type": "Feature",
  "properties": {
    "iso:country":"US",
    "sg:address":"528 Fayette St",
    "sg:city":"Conshohocken",
    "sg:classifiers":[
        {
            "category":"Professional",
            "subcategory":"Lawyer & Legal Services",
            "type":"Services"
        }
    ],
    "sg:phone":"+1   ",
    "sg:postcode":"19428",
    "sg:province":"PA",
    "wof:name":"Senior Brett & Associates",
    "wof:placetype":"venue"
},
  "geometry": {"coordinates":[-75.302432,40.077858],"type":"Point"}
}