{
  "type": "Feature",
  "properties": {
    "iso:country":"US",
    "sg:address":"101 Pheasant Run",
    "sg:city":"Newtown",
    "sg:classifiers":[
        {
            "category":"Banks & Credit Unions",
            "subcategory":"Financial Services",
            "type":"Services"
        }
    ],
    "sg:phone":"+1   ",
    "sg:postcode":"18940",
    "sg:province":"PA",
    "sg:tags":[
        "company",
        "holding",
        "real estate"
    ],
    "wof:name":"101 Pheasant Run Inc",
    "wof:placetype":"venue"
},
  "geometry": {"coordinates":[-74.90976999999999,40.225356],"type":"Point"}
}