{
  "type": "Feature",
  "properties": {
    "addr:full":"2360 Catasauqua Rd Bethlehem PA 18018",
    "addr:housenumber":"2360",
    "addr:postcode":"18018",
    "addr:street":"Catasauqua Rd",
    "iso:country":"US",
    "sg:address":"2360 Catasauqua Rd",
    "sg:city":"Bethlehem",
    "sg:classifiers":[
        {
            "category":"Home & Garden",
            "subcategory":"Household Appliances",
            "type":"Retail Goods"
        }
    ],
    "sg:phone":"+1 610 867 5779",
    "sg:postcode":"18018",
    "sg:province":"PA",
    "sg:tags":[
        "cleaners",
        "vacuum"
    ],
    "wof:name":"Electrolux",
    "wof:placetype":"venue"
},
  "geometry": {"coordinates":[-75.427221,40.642954],"type":"Point"}
}