{
  "type": "Feature",
  "properties": {
    "iso:country":"US",
    "sg:address":"2113 Sassafras St",
    "sg:city":"Erie",
    "sg:classifiers":[
        {
            "category":"Organizations",
            "subcategory":"Religious Organization",
            "type":"Services"
        }
    ],
    "sg:phone":"+1 814 452 2870",
    "sg:postcode":"16502",
    "sg:province":"PA",
    "sg:tags":[
        "church"
    ],
    "wof:name":"Simpson United Methodist Chr",
    "wof:placetype":"venue"
},
  "geometry": {"coordinates":[-80.079497,42.114009],"type":"Point"}
}