{
  "type": "Feature",
  "properties": {
    "iso:country":"US",
    "sg:address":"171 Locust Ln",
    "sg:city":"Abbottstown",
    "sg:classifiers":[
        {
            "category":"Professional",
            "type":"Services"
        }
    ],
    "sg:phone":"+1   ",
    "sg:postcode":"17301",
    "sg:province":"PA",
    "wof:name":"Staron Corporation",
    "wof:placetype":"venue"
},
  "geometry": {"coordinates":[-76.99538099999999,39.909659],"type":"Point"}
}