{
  "type": "Feature",
  "properties": {
    "iso:country":"US",
    "sg:address":"130 7th St Ste 201",
    "sg:city":"Pittsburgh",
    "sg:classifiers":[
        {
            "category":"Real Estate",
            "subcategory":"Architect",
            "type":"Services"
        }
    ],
    "sg:phone":"+1 412 281 2280",
    "sg:postcode":"15222",
    "sg:province":"PA",
    "wof:name":"Hhsdr Architects & Engineers",
    "wof:placetype":"venue"
},
  "geometry": {"coordinates":[-80.000749,40.443632],"type":"Point"}
}