{
  "type": "Feature",
  "properties": {
    "iso:country":"US",
    "sg:address":"232 Wilson Ave",
    "sg:city":"Washington",
    "sg:classifiers":[
        {
            "category":"Professional",
            "subcategory":"Computer Services",
            "type":"Services"
        }
    ],
    "sg:phone":"+1 724 228 6478",
    "sg:postcode":"15301",
    "sg:province":"PA",
    "sg:tags":[
        "consultant",
        "designer"
    ],
    "wof:name":"Computers Services Tech",
    "wof:placetype":"venue"
},
  "geometry": {"coordinates":[-80.245479,40.182347],"type":"Point"}
}