{
  "type": "Feature",
  "properties": {
    "iso:country":"US",
    "sg:address":"2451 Parkwood Dr",
    "sg:city":"Allentown",
    "sg:classifiers":[
        {
            "category":"Professional",
            "subcategory":"Engineering",
            "type":"Services"
        }
    ],
    "sg:phone":"+1 610 791 2252",
    "sg:postcode":"18103",
    "sg:province":"PA",
    "sg:tags":[
        "engineer"
    ],
    "wof:name":"Pidcock Co",
    "wof:placetype":"venue"
},
  "geometry": {"coordinates":[-75.49805600000001,40.566509],"type":"Point"}
}