{
  "type": "Feature",
  "properties": {
    "iso:country":"US",
    "sg:address":"431 W Lincoln Ave",
    "sg:city":"Myerstown",
    "sg:classifiers":[
        {
            "category":"Health Services",
            "subcategory":"Doctor",
            "type":"Services"
        }
    ],
    "sg:phone":"+1 717 866 5755",
    "sg:postcode":"17067",
    "sg:province":"PA",
    "sg:tags":[
        "physician",
        "surgeon"
    ],
    "wof:name":"Myerstown Family Practice",
    "wof:placetype":"venue"
},
  "geometry": {"coordinates":[-76.319828,40.374528],"type":"Point"}
}