{
  "type": "Feature",
  "properties": {
    "iso:country":"US",
    "sg:address":"1427 Vine St",
    "sg:city":"Philadelphia",
    "sg:classifiers":[
        {
            "category":"Health Services",
            "subcategory":"Doctor",
            "type":"Services"
        }
    ],
    "sg:phone":"+1 215 762 6890",
    "sg:postcode":"19102",
    "sg:province":"PA",
    "sg:tags":[
        "physician",
        "surgeon"
    ],
    "wof:name":"ALS Clinical Svc Ctr",
    "wof:placetype":"venue"
},
  "geometry": {"coordinates":[-75.16379000000001,39.957941],"type":"Point"}
}