{
  "type": "Feature",
  "properties": {
    "iso:country":"US",
    "sg:address":"3747 Derry St",
    "sg:city":"Harrisburg",
    "sg:classifiers":[
        {
            "category":"Professional",
            "subcategory":"Lawyer & Legal Services",
            "type":"Services"
        }
    ],
    "sg:phone":"+1 717 561 2677",
    "sg:postcode":"17111",
    "sg:province":"PA",
    "sg:tags":[
        "attorney"
    ],
    "wof:name":"William T Smith",
    "wof:placetype":"venue"
},
  "geometry": {"coordinates":[-76.82341700000001,40.258214],"type":"Point"}
}