{
  "type": "Feature",
  "properties": {
    "iso:country":"US",
    "sg:address":"12600 Hively Rd",
    "sg:city":"Brogue",
    "sg:phone":"+1   ",
    "sg:postcode":"17309",
    "sg:province":"PA",
    "sg:tags":[
        "farm",
        "grain",
        "cash"
    ],
    "wof:name":"Howard C Grove",
    "wof:placetype":"venue"
},
  "geometry": {"coordinates":[-76.433235,39.862713],"type":"Point"}
}