{
  "type": "Feature",
  "properties": {
    "addr:full":"109 Groffdale Church Rd Leola PA 17540",
    "addr:housenumber":"109",
    "addr:postcode":"17540",
    "addr:street":"Groffdale Church Rd",
    "iso:country":"US",
    "sg:address":"109 Groffdale Church Rd",
    "sg:city":"Leola",
    "sg:classifiers":[
        {
            "category":"Manufacturing",
            "subcategory":"Wood Products",
            "type":"Manufacturing & Wholesale Goods"
        }
    ],
    "sg:phone":"+1 717 656 8310",
    "sg:postcode":"17540",
    "sg:province":"PA",
    "sg:tags":[
        "mfg"
    ],
    "wof:name":"Zimmerman Woodcraft & Bending",
    "wof:placetype":"venue"
},
  "geometry": {"coordinates":[-76.149204,40.107125],"type":"Point"}
}