{
  "type": "Feature",
  "properties": {
    "iso:country":"US",
    "sg:address":"604 7th St",
    "sg:city":"Altoona",
    "sg:classifiers":[
        {
            "category":"Food & Beverages",
            "subcategory":"Groceries & Convenience Stores",
            "type":"Retail Goods"
        }
    ],
    "sg:phone":"+1 814 946 8095",
    "sg:postcode":"16602",
    "sg:province":"PA",
    "wof:name":"Martin General Store",
    "wof:placetype":"venue"
},
  "geometry": {"coordinates":[-78.39286800000001,40.517452],"type":"Point"}
}