{
  "type": "Feature",
  "properties": {
    "iso:country":"US",
    "sg:address":"860 Enterprise St",
    "sg:city":"Dickson City",
    "sg:classifiers":[
        {
            "category":"Wholesale",
            "subcategory":"Machinery & Supplies",
            "type":"Manufacturing & Wholesale Goods"
        }
    ],
    "sg:phone":"+1 570 489 3642",
    "sg:postcode":"18519",
    "sg:province":"PA",
    "sg:tags":[
        "equipment",
        "construction",
        "tractor",
        "general"
    ],
    "wof:name":"F & S Supply Company",
    "wof:placetype":"venue"
},
  "geometry": {"coordinates":[-75.62033599999999,41.460394],"type":"Point"}
}