{
  "type": "Feature",
  "properties": {
    "iso:country":"US",
    "sg:address":"35 Grant Ave",
    "sg:city":"Duquesne",
    "sg:classifiers":[
        {
            "category":"Banks & Credit Unions",
            "subcategory":"Bank",
            "type":"Services"
        }
    ],
    "sg:phone":"+1 412 469 0400",
    "sg:postcode":"15110",
    "sg:province":"PA",
    "sg:tags":[
        "state",
        "commercial"
    ],
    "wof:name":"National City Bank",
    "wof:placetype":"venue"
},
  "geometry": {"coordinates":[-79.845472,40.373427],"type":"Point"}
}