{
  "type": "Feature",
  "properties": {
    "iso:country":"US",
    "sg:address":"300 Willow Rd",
    "sg:city":"Karns City",
    "sg:classifiers":[
        {
            "category":"Autos & Motor Vehicles",
            "subcategory":"Fuel & Gas Station",
            "type":"Retail Goods"
        }
    ],
    "sg:phone":"+1   ",
    "sg:postcode":"16041",
    "sg:province":"PA",
    "sg:tags":[
        "station",
        "gasoline"
    ],
    "wof:name":"Rottmans Service Center",
    "wof:placetype":"venue"
},
  "geometry": {"coordinates":[-79.690155,41.006954],"type":"Point"}
}