{
  "type": "Feature",
  "properties": {
    "iso:country":"US",
    "sg:address":"412 W Water St",
    "sg:city":"Smethport",
    "sg:classifiers":[
        {
            "category":"Retail",
            "subcategory":"Veterinary Services",
            "type":"Services"
        }
    ],
    "sg:phone":"+1 814 887 7747",
    "sg:postcode":"16749",
    "sg:province":"PA",
    "sg:tags":[
        "veterinarian"
    ],
    "wof:name":"H & S Animal Hospital",
    "wof:placetype":"venue"
},
  "geometry": {"coordinates":[-78.445582,41.808745],"type":"Point"}
}