{
  "type": "Feature",
  "properties": {
    "iso:country":"US",
    "sg:address":"2500 Tuscarawas Rd",
    "sg:city":"Beaver",
    "sg:classifiers":[
        {
            "category":"Building & Trades",
            "subcategory":"Electrical",
            "type":"Services"
        }
    ],
    "sg:phone":"+1   ",
    "sg:postcode":"15009",
    "sg:province":"PA",
    "sg:tags":[
        "electrical",
        "contractor"
    ],
    "wof:name":"Bowan Electric",
    "wof:placetype":"venue"
},
  "geometry": {"coordinates":[-80.364384,40.695782],"type":"Point"}
}