{
  "type": "Feature",
  "properties": {
    "iso:country":"US",
    "sg:address":"6700 Frankford Ave",
    "sg:city":"Philadelphia",
    "sg:classifiers":[
        {
            "category":"Retail",
            "subcategory":"Auto Repair",
            "type":"Services"
        }
    ],
    "sg:phone":"+1   ",
    "sg:postcode":"19135",
    "sg:province":"PA",
    "sg:tags":[
        "state",
        "pa",
        "computer",
        "diagnostics",
        "general"
    ],
    "wof:name":"Andys Auto Repair",
    "wof:placetype":"venue"
},
  "geometry": {"coordinates":[-75.050972,40.032323],"type":"Point"}
}