{
  "type": "Feature",
  "properties": {
    "iso:country":"US",
    "sg:address":"500 Blackhawk Rd",
    "sg:city":"Beaver Falls",
    "sg:classifiers":[
        {
            "category":"Education",
            "subcategory":"School",
            "type":"Public Place"
        }
    ],
    "sg:phone":"+1 724 846 9600",
    "sg:postcode":"15010",
    "sg:province":"PA",
    "sg:tags":[
        "high"
    ],
    "sg:website":"www.bsd.k12.pa.us",
    "wof:name":"Blackhawk High School",
    "wof:placetype":"venue"
},
  "geometry": {"coordinates":[-80.403148,40.762119],"type":"Point"}
}