{
  "type": "Feature",
  "properties": {
    "iso:country":"US",
    "sg:address":"2121 Clermont St",
    "sg:city":"Bethlehem",
    "sg:classifiers":[
        {
            "category":"Wholesale",
            "subcategory":"Vending Machines",
            "type":"Manufacturing & Wholesale Goods"
        }
    ],
    "sg:phone":"+1 610 882 1139",
    "sg:postcode":"18017",
    "sg:province":"PA",
    "sg:tags":[
        "merchandise"
    ],
    "wof:name":"Honor Snack Inc.",
    "wof:placetype":"venue"
},
  "geometry": {"coordinates":[-75.344301,40.642606],"type":"Point"}
}