{
  "type": "Feature",
  "properties": {
    "iso:country":"US",
    "sg:address":"1027 W Main St",
    "sg:city":"Mount Pleasant",
    "sg:classifiers":[
        {
            "category":"Health Services",
            "subcategory":"Doctor",
            "type":"Services"
        }
    ],
    "sg:phone":"+1   ",
    "sg:postcode":"15666",
    "sg:province":"PA",
    "sg:tags":[
        "medical"
    ],
    "wof:name":"M M Zaitoon MD",
    "wof:placetype":"venue"
},
  "geometry": {"coordinates":[-79.55135799999999,40.15349],"type":"Point"}
}