{
  "type": "Feature",
  "properties": {
    "iso:country":"US",
    "sg:address":"211 S Main St",
    "sg:city":"Ambler",
    "sg:classifiers":[
        {
            "category":"Retail",
            "subcategory":"Auto Repair",
            "type":"Services"
        }
    ],
    "sg:phone":"+1 215 643 2997",
    "sg:postcode":"19002",
    "sg:province":"PA",
    "sg:tags":[
        "general"
    ],
    "wof:name":"Talese Motors Inc",
    "wof:placetype":"venue"
},
  "geometry": {"coordinates":[-75.22047999999999,40.1487],"type":"Point"}
}