{
  "type": "Feature",
  "properties": {
    "iso:country":"US",
    "sg:address":"1822 Old York Rd",
    "sg:city":"Abington",
    "sg:classifiers":[
        {
            "category":"Real Estate",
            "subcategory":"Real Estate Services",
            "type":"Services"
        },
        {
            "category":"Real Estate",
            "subcategory":"Surveying",
            "type":"Services"
        },
        {
            "category":"Real Estate",
            "subcategory":"Real Estate Agent",
            "type":"Services"
        }
    ],
    "sg:phone":"+1 215 657 9590",
    "sg:postcode":"19001",
    "sg:province":"PA",
    "sg:tags":[
        "industrial",
        "appraisers-commercial",
        "broker",
        "management",
        "buyer",
        "appraiser"
    ],
    "wof:name":"Frolove Realty Group Inc",
    "wof:placetype":"venue"
},
  "geometry": {"coordinates":[-75.11451700000001,40.135578],"type":"Point"}
}