{
  "type": "Feature",
  "properties": {
    "addr:full":"6579 Heil Rd Germansville PA 18053",
    "addr:housenumber":"6579",
    "addr:postcode":"18053",
    "addr:street":"Heil Rd",
    "iso:country":"US",
    "sg:address":"6579 Heil Rd",
    "sg:city":"Germansville",
    "sg:classifiers":[
        {
            "category":"Building & Trades",
            "subcategory":"Electrical",
            "type":"Services"
        }
    ],
    "sg:phone":"+1   ",
    "sg:postcode":"18053",
    "sg:province":"PA",
    "sg:tags":[
        "electrical",
        "contractor"
    ],
    "wof:name":"Fred Selig",
    "wof:placetype":"venue"
},
  "geometry": {"coordinates":[-75.72674600000001,40.694669],"type":"Point"}
}