{
  "type": "Feature",
  "properties": {
    "addr:full":"800 Streets Run Rd Pittsburgh PA 15236",
    "addr:housenumber":"800",
    "addr:postcode":"15236",
    "addr:street":"Streets Run Rd",
    "iso:country":"US",
    "sg:address":"800 Streets Run Rd",
    "sg:city":"Pittsburgh",
    "sg:classifiers":[
        {
            "category":"Retail",
            "subcategory":"Auto Repair",
            "type":"Services"
        }
    ],
    "sg:phone":"+1   ",
    "sg:postcode":"15236",
    "sg:province":"PA",
    "sg:tags":[
        "general"
    ],
    "wof:name":"RMS Services",
    "wof:placetype":"venue"
},
  "geometry": {"coordinates":[-79.97157300000001,40.348161],"type":"Point"}
}