{
  "type": "Feature",
  "properties": {
    "iso:country":"US",
    "sg:address":"17 S 6th St",
    "sg:city":"Youngwood",
    "sg:classifiers":[
        {
            "category":"Professional",
            "subcategory":"Engineering",
            "type":"Services"
        }
    ],
    "sg:phone":"+1 724 925 1744",
    "sg:postcode":"15697",
    "sg:province":"PA",
    "sg:tags":[
        "engineer"
    ],
    "wof:name":"Karfelt Associates",
    "wof:placetype":"venue"
},
  "geometry": {"coordinates":[-79.58062,40.240679],"type":"Point"}
}