{
  "type": "Feature",
  "properties": {
    "addr:full":"2 Misty Hollow Dr West Grove PA 19390",
    "addr:housenumber":"2",
    "addr:postcode":"19390",
    "addr:street":"Misty Hollow Dr",
    "iso:country":"US",
    "sg:address":"2 Misty Hollow Dr",
    "sg:city":"West Grove",
    "sg:classifiers":[
        {
            "category":"Retail",
            "subcategory":"Laundry & Dry Cleaning",
            "type":"Services"
        }
    ],
    "sg:phone":"+1 610 869 8679",
    "sg:postcode":"19390",
    "sg:province":"PA",
    "sg:tags":[
        "cleaners",
        "rug",
        "carpet"
    ],
    "wof:name":"Specialty Cleaning Svc",
    "wof:placetype":"venue"
},
  "geometry": {"coordinates":[-75.82328099999999,39.829969],"type":"Point"}
}