{
  "type": "Feature",
  "properties": {
    "addr:full":"701 E 3rd St Bethlehem PA 18015",
    "addr:housenumber":"701",
    "addr:postcode":"18015",
    "addr:street":"E 3Rd St",
    "iso:country":"US",
    "sg:address":"701 E 3rd St",
    "sg:city":"Bethlehem",
    "sg:classifiers":[
        {
            "category":"Wholesale",
            "subcategory":"Durable Goods & Equipment",
            "type":"Manufacturing & Wholesale Goods"
        }
    ],
    "sg:phone":"+1   ",
    "sg:postcode":"18015",
    "sg:province":"PA",
    "wof:name":"Fisher Safety America",
    "wof:placetype":"venue"
},
  "geometry": {"coordinates":[-75.366393,40.612327],"type":"Point"}
}