{
  "type": "Feature",
  "properties": {
    "iso:country":"US",
    "sg:address":"5255 Schrimper Rd",
    "sg:city":"Erie",
    "sg:classifiers":[
        {
            "category":"Autos & Motor Vehicles",
            "subcategory":"Motorcycle Sales",
            "type":"Retail Goods"
        }
    ],
    "sg:phone":"+1 814 825 3254",
    "sg:postcode":"16510",
    "sg:province":"PA",
    "sg:tags":[
        "sporting"
    ],
    "wof:name":"K K Speed & Sport",
    "wof:placetype":"venue"
},
  "geometry": {"coordinates":[-80.019633,42.102382],"type":"Point"}
}