{
  "type": "Feature",
  "properties": {
    "iso:country":"US",
    "sg:address":"2501 Bethlehem Pike",
    "sg:city":"Hilltown",
    "sg:classifiers":[
        {
            "category":"Arena",
            "subcategory":"Sports Club",
            "type":"Entertainment"
        }
    ],
    "sg:phone":"+1 215 822 8828",
    "sg:postcode":"18927",
    "sg:province":"PA",
    "sg:tags":[
        "martial art"
    ],
    "wof:name":"Shuto Karate Club",
    "wof:placetype":"venue"
},
  "geometry": {"coordinates":[-75.284784,40.298842],"type":"Point"}
}