{
  "type": "Feature",
  "properties": {
    "iso:country":"US",
    "sg:address":"140 W Market St",
    "sg:city":"Hellam",
    "sg:classifiers":[
        {
            "category":"Personal",
            "subcategory":"Beauty Salon",
            "type":"Services"
        }
    ],
    "sg:phone":"+1 717 757 6023",
    "sg:postcode":"17406",
    "sg:province":"PA",
    "wof:name":"Linda Kline Beauty Salon",
    "wof:placetype":"venue"
},
  "geometry": {"coordinates":[-76.606713,40.00427],"type":"Point"}
}