{
  "type": "Feature",
  "properties": {
    "addr:full":"227 Herbst Rd Coraopolis PA 15108",
    "addr:housenumber":"227",
    "addr:postcode":"15108",
    "addr:street":"Herbst Rd",
    "iso:country":"US",
    "sg:address":"227 Herbst Rd",
    "sg:city":"Coraopolis",
    "sg:classifiers":[
        {
            "category":"Organizations",
            "subcategory":"Religious Organization",
            "type":"Services"
        }
    ],
    "sg:phone":"+1 412 771 1335",
    "sg:postcode":"15108",
    "sg:province":"PA",
    "sg:tags":[
        "church"
    ],
    "wof:name":"Church Of Jesus Christ",
    "wof:placetype":"venue"
},
  "geometry": {"coordinates":[-80.114728,40.486934],"type":"Point"}
}