{
  "type": "Feature",
  "properties": {
    "iso:country":"US",
    "sg:address":"1209 N Chester Rd",
    "sg:city":"West Chester",
    "sg:classifiers":[
        {
            "category":"Real Estate",
            "subcategory":"Real Estate Agent",
            "type":"Services"
        }
    ],
    "sg:phone":"+1   ",
    "sg:postcode":"19380",
    "sg:province":"PA",
    "wof:name":"Byron R Clark",
    "wof:placetype":"venue"
},
  "geometry": {"coordinates":[-75.548242,40.018295],"type":"Point"}
}