{
  "type": "Feature",
  "properties": {
    "iso:country":"US",
    "sg:address":"1614 Macdade Blvd",
    "sg:city":"Folsom",
    "sg:classifiers":[
        {
            "category":"Wholesale",
            "subcategory":"Electrical",
            "type":"Manufacturing & Wholesale Goods"
        }
    ],
    "sg:phone":"+1 610 461 7060",
    "sg:postcode":"19033",
    "sg:province":"PA",
    "sg:tags":[
        "laboratory",
        "supply",
        "equipment"
    ],
    "wof:name":"Ah Koch Service Laboratories Inc",
    "wof:placetype":"venue"
},
  "geometry": {"coordinates":[-75.317851,39.894689],"type":"Point"}
}