{
  "type": "Feature",
  "properties": {
    "addr:full":"175 6th St Clymer PA 15728",
    "addr:housenumber":"175",
    "addr:postcode":"15728",
    "addr:street":"6Th St",
    "iso:country":"US",
    "sg:address":"175 6th St",
    "sg:city":"Clymer",
    "sg:classifiers":[
        {
            "category":"Home & Garden",
            "subcategory":"Furniture",
            "type":"Retail Goods"
        },
        {
            "category":"Home & Garden",
            "subcategory":"Carpets & Floor Coverings",
            "type":"Retail Goods"
        }
    ],
    "sg:phone":"+1 724 254 2400",
    "sg:postcode":"15728",
    "sg:province":"PA",
    "sg:tags":[
        "rug",
        "business",
        "dealer"
    ],
    "wof:name":"Clymer Furniture Inc",
    "wof:placetype":"venue"
},
  "geometry": {"coordinates":[-79.01188500000001,40.668301],"type":"Point"}
}