{
  "type": "Feature",
  "properties": {
    "addr:full":"743 N 44th St Philadelphia PA 19104",
    "addr:housenumber":"743",
    "addr:postcode":"19104",
    "addr:street":"N 44Th St",
    "iso:country":"US",
    "sg:address":"743 N 44th St",
    "sg:city":"Philadelphia",
    "sg:classifiers":[
        {
            "category":"Retail",
            "subcategory":"Auto Repair",
            "type":"Services"
        }
    ],
    "sg:phone":"+1 215 387 6880",
    "sg:postcode":"19104",
    "sg:province":"PA",
    "sg:tags":[
        "body"
    ],
    "wof:name":"True Christian Fellowship",
    "wof:placetype":"venue"
},
  "geometry": {"coordinates":[-75.21092299999999,39.96541],"type":"Point"}
}