{
  "type": "Feature",
  "properties": {
    "addr:full":"111 N Market St Carmichaels PA 15320",
    "addr:housenumber":"111",
    "addr:postcode":"15320",
    "addr:street":"N Market St",
    "iso:country":"US",
    "sg:address":"111 N Market St",
    "sg:city":"Carmichaels",
    "sg:classifiers":[
        {
            "category":"Government",
            "subcategory":"Post Office",
            "type":"Public Place"
        }
    ],
    "sg:phone":"+1 724 966 5231",
    "sg:postcode":"15320",
    "sg:province":"PA",
    "sg:tags":[
        "postal",
        "us"
    ],
    "wof:name":"US Post Office",
    "wof:placetype":"venue"
},
  "geometry": {"coordinates":[-79.975308,39.896983],"type":"Point"}
}