{
  "type": "Feature",
  "properties": {
    "addr:full":"36820 Lake Rd Union City PA 16438",
    "addr:housenumber":"36820",
    "addr:postcode":"16438",
    "addr:street":"Lake Rd",
    "iso:country":"US",
    "sg:address":"36820 Lake Rd",
    "sg:city":"Union City",
    "sg:classifiers":[
        {
            "category":"Wholesale",
            "subcategory":"Machinery & Supplies",
            "type":"Manufacturing & Wholesale Goods"
        }
    ],
    "sg:phone":"+1 814 694 2237",
    "sg:postcode":"16438",
    "sg:province":"PA",
    "sg:tags":[
        "fire",
        "department",
        "equipment"
    ],
    "wof:name":"Kolaja Fire Equipment Sales",
    "wof:placetype":"venue"
},
  "geometry": {"coordinates":[-79.81701,41.819417],"type":"Point"}
}