{
  "type": "Feature",
  "properties": {
    "iso:country":"US",
    "sg:address":"1543 Devereaux Ave",
    "sg:city":"Philadelphia",
    "sg:classifiers":[
        {
            "category":"Food & Beverages",
            "subcategory":"Liquor & Beverages",
            "type":"Retail Goods"
        }
    ],
    "sg:phone":"+1 215 288 2768",
    "sg:postcode":"19149",
    "sg:province":"PA",
    "sg:tags":[
        "bottler",
        "beverages-distributors"
    ],
    "wof:name":"Delipallas Vassilios",
    "wof:placetype":"venue"
},
  "geometry": {"coordinates":[-75.07646699999999,40.035162],"type":"Point"}
}