{
  "type": "Feature",
  "properties": {
    "addr:full":"1240 N 22nd St Allentown PA 18104",
    "addr:housenumber":"1240",
    "addr:postcode":"18104",
    "addr:street":"N 22Nd St",
    "iso:country":"US",
    "sg:address":"1240 N 22nd St",
    "sg:city":"Allentown",
    "sg:classifiers":[
        {
            "category":"Banks & Credit Unions",
            "subcategory":"Financial Services",
            "type":"Services"
        }
    ],
    "sg:phone":"+1   ",
    "sg:postcode":"18104",
    "sg:province":"PA",
    "sg:tags":[
        "company",
        "holding"
    ],
    "wof:name":"Danrich Holdings Inc",
    "wof:placetype":"venue"
},
  "geometry": {"coordinates":[-75.51185700000001,40.612734],"type":"Point"}
}