{
  "type": "Feature",
  "properties": {
    "iso:country":"US",
    "sg:address":"111 W Drinker St",
    "sg:city":"Scranton",
    "sg:classifiers":[
        {
            "category":"Real Estate",
            "subcategory":"Real Estate Agent",
            "type":"Services"
        }
    ],
    "sg:phone":"+1   ",
    "sg:postcode":"18512",
    "sg:province":"PA",
    "wof:name":"Joseph Goodman",
    "wof:placetype":"venue"
},
  "geometry": {"coordinates":[-75.631184,41.422325],"type":"Point"}
}