{
  "type": "Feature",
  "properties": {
    "iso:country":"US",
    "sg:address":"2076 W Main St",
    "sg:city":"Norristown",
    "sg:classifiers":[
        {
            "category":"Building & Trades",
            "subcategory":"Cleaning & Sanitation",
            "type":"Services"
        },
        {
            "category":"Retail",
            "subcategory":"Laundry & Dry Cleaning",
            "type":"Services"
        }
    ],
    "sg:phone":"+1 610 539 3295",
    "sg:postcode":"19403",
    "sg:province":"PA",
    "sg:tags":[
        "cleaner",
        "floor",
        "rug",
        "contractor",
        "waxing",
        "cleaning-industrial",
        "polishing",
        "janitorial",
        "carpet"
    ],
    "sg:website":"http://dillonchem.com",
    "wof:name":"Dillon William F & Son Janitorial & Floor Cleaning",
    "wof:placetype":"venue"
},
  "geometry": {"coordinates":[-75.380205,40.134273],"type":"Point"}
}