{
  "type": "Feature",
  "properties": {
    "addr:full":"2422 Kensington Ave Philadelphia PA 19125",
    "addr:housenumber":"2422",
    "addr:postcode":"19125",
    "addr:street":"Kensington Ave",
    "iso:country":"US",
    "sg:address":"2422 Kensington Ave",
    "sg:city":"Philadelphia",
    "sg:classifiers":[
        {
            "category":"Shopping",
            "subcategory":"Discount & Variety Stores",
            "type":"Retail Goods"
        }
    ],
    "sg:phone":"+1   ",
    "sg:postcode":"19125",
    "sg:province":"PA",
    "wof:name":"Payless",
    "wof:placetype":"venue"
},
  "geometry": {"coordinates":[-75.131907,39.986306],"type":"Point"}
}