{
  "type": "Feature",
  "properties": {
    "iso:country":"US",
    "sg:address":"2237 Hartranft St",
    "sg:city":"Philadelphia",
    "sg:classifiers":[
        {
            "category":"Organizations",
            "subcategory":"Labor Organization",
            "type":"Services"
        }
    ],
    "sg:phone":"+1 215 952 2106",
    "sg:postcode":"19145",
    "sg:province":"PA",
    "wof:name":"I A T S E Local 52",
    "wof:placetype":"venue"
},
  "geometry": {"coordinates":[-75.18682,39.910908],"type":"Point"}
}