{
  "type": "Feature",
  "properties": {
    "iso:country":"US",
    "sg:address":"2820 W 23rd St",
    "sg:city":"Erie",
    "sg:classifiers":[
        {
            "category":"Social Services",
            "type":"Services"
        },
        {
            "category":"Professional",
            "type":"Services"
        },
        {
            "category":"Personal",
            "type":"Services"
        },
        {
            "category":"Professional",
            "subcategory":"Lawyer & Legal Services",
            "type":"Services"
        }
    ],
    "sg:phone":"+1 814 881 5240",
    "sg:postcode":"16506",
    "sg:province":"PA",
    "sg:tags":[
        "family",
        "divorce",
        "assistance",
        "mediation",
        "individual",
        "marriage",
        "child",
        "counseling",
        "counselor"
    ],
    "wof:name":"Relationships For Life",
    "wof:placetype":"venue"
},
  "geometry": {"coordinates":[-80.137378,42.091517],"type":"Point"}
}