{
  "type": "Feature",
  "properties": {
    "iso:country":"US",
    "sg:address":"955 Chester Ave",
    "sg:city":"Lansdowne",
    "sg:classifiers":[
        {
            "category":"Community Center",
            "type":"Public Place"
        }
    ],
    "sg:phone":"+1 610 249 0420",
    "sg:postcode":"19050",
    "sg:province":"PA",
    "sg:tags":[
        "medical"
    ],
    "wof:name":"Crothall Healthcare Inc",
    "wof:placetype":"venue"
},
  "geometry": {"coordinates":[-75.245566,39.927104],"type":"Point"}
}