{
  "type": "Feature",
  "properties": {
    "iso:country":"US",
    "sg:address":"1360 Colony Way",
    "sg:city":"Yardley",
    "sg:classifiers":[
        {
            "category":"Professional",
            "subcategory":"Accounting & Tax Preparation",
            "type":"Services"
        }
    ],
    "sg:phone":"+1 215 321 9498",
    "sg:postcode":"19067",
    "sg:province":"PA",
    "sg:tags":[
        "accountant"
    ],
    "wof:name":"Paula Cutter",
    "wof:placetype":"venue"
},
  "geometry": {"coordinates":[-74.857629,40.231056],"type":"Point"}
}