{
  "type": "Feature",
  "properties": {
    "iso:country":"US",
    "sg:address":"30 Kremp Rd",
    "sg:city":"Mohnton",
    "sg:classifiers":[
        {
            "category":"Freight",
            "type":"Transportation"
        }
    ],
    "sg:phone":"+1 610 856 7305",
    "sg:postcode":"19540",
    "sg:province":"PA",
    "sg:tags":[
        "commercial",
        "storage"
    ],
    "sg:website":"www.archivesone.com",
    "wof:name":"Storage Stables",
    "wof:placetype":"venue"
},
  "geometry": {"coordinates":[-75.933707,40.240535],"type":"Point"}
}