{
  "type": "Feature",
  "properties": {
    "iso:country":"US",
    "sg:address":"2800 S 20th St",
    "sg:city":"Philadelphia",
    "sg:classifiers":[
        {
            "category":"Real Estate",
            "subcategory":"Real Estate Agent",
            "type":"Services"
        }
    ],
    "sg:phone":"+1   ",
    "sg:postcode":"19145",
    "sg:province":"PA",
    "wof:name":"Defense Realty LLC",
    "wof:placetype":"venue"
},
  "geometry": {"coordinates":[-75.181149,39.917369],"type":"Point"}
}