{
  "type": "Feature",
  "properties": {
    "addr:full":"849 Henderson Ave Washington PA 15301",
    "addr:housenumber":"849",
    "addr:postcode":"15301",
    "addr:street":"Henderson Ave",
    "iso:country":"US",
    "sg:address":"849 Henderson Ave",
    "sg:city":"Washington",
    "sg:classifiers":[
        {
            "category":"Wholesale",
            "subcategory":"Hardware",
            "type":"Manufacturing & Wholesale Goods"
        },
        {
            "category":"Wholesale",
            "subcategory":"Metals & Minerals",
            "type":"Manufacturing & Wholesale Goods"
        }
    ],
    "sg:phone":"+1 724 225 5610",
    "sg:postcode":"15301",
    "sg:province":"PA",
    "sg:tags":[
        "pipe",
        "plumbing"
    ],
    "wof:name":"Interstate Pipe & Supply Co",
    "wof:placetype":"venue"
},
  "geometry": {"coordinates":[-80.26871800000001,40.196912],"type":"Point"}
}