{
  "type": "Feature",
  "properties": {
    "addr:full":"4135 N George St Exd Manchester PA 17345",
    "addr:housenumber":"4135",
    "addr:postcode":"17345",
    "addr:street":"N George St Exd",
    "iso:country":"US",
    "sg:address":"4135 N George St Exd",
    "sg:city":"Manchester",
    "sg:classifiers":[
        {
            "category":"Professional",
            "type":"Services"
        }
    ],
    "sg:phone":"+1 717 266 5053",
    "sg:postcode":"17345",
    "sg:province":"PA",
    "sg:tags":[
        "establishment"
    ],
    "wof:name":"Appleby Systems",
    "wof:placetype":"venue"
},
  "geometry": {"coordinates":[-76.724639,40.041746],"type":"Point"}
}