{
  "type": "Feature",
  "properties": {
    "addr:full":"119 Long Beach Dr Osterburg PA 16667",
    "addr:housenumber":"119",
    "addr:postcode":"16667",
    "addr:street":"Long Beach Dr",
    "iso:country":"US",
    "sg:address":"119 Long Beach Dr",
    "sg:city":"Osterburg",
    "sg:classifiers":[
        {
            "category":"Professional",
            "type":"Services"
        }
    ],
    "sg:phone":"+1 814 276 3193",
    "sg:postcode":"16667",
    "sg:province":"PA",
    "wof:name":"Central Locating Svc",
    "wof:placetype":"venue"
},
  "geometry": {"coordinates":[-78.5168,40.174531],"type":"Point"}
}