{
  "type": "Feature",
  "properties": {
    "iso:country":"US",
    "sg:address":"127 W Street Rd",
    "sg:city":"Kennett Square",
    "sg:classifiers":[
        {
            "category":"Health Services",
            "subcategory":"Doctor",
            "type":"Services"
        }
    ],
    "sg:phone":"+1 610 444 1212",
    "sg:postcode":"19348",
    "sg:province":"PA",
    "wof:name":"Zimmerman Karl MD",
    "wof:placetype":"venue"
},
  "geometry": {"coordinates":[-75.721603,39.874001],"type":"Point"}
}