{
  "type": "Feature",
  "properties": {
    "iso:country":"US",
    "sg:address":"619 E High St",
    "sg:city":"Waynesburg",
    "sg:classifiers":[
        {
            "category":"Real Estate",
            "subcategory":"Real Estate Agent",
            "type":"Services"
        }
    ],
    "sg:phone":"+1 724 852 2660",
    "sg:postcode":"15370",
    "sg:province":"PA",
    "wof:name":"Heritage Realty",
    "wof:placetype":"venue"
},
  "geometry": {"coordinates":[-80.178701,39.896465],"type":"Point"}
}