{
  "type": "Feature",
  "properties": {
    "iso:country":"US",
    "sg:address":"2661 Clearview Rd",
    "sg:city":"Allison Park",
    "sg:classifiers":[
        {
            "category":"Home & Garden",
            "subcategory":"Building Materials",
            "type":"Retail Goods"
        }
    ],
    "sg:phone":"+1 412 487 3211",
    "sg:postcode":"15101",
    "sg:province":"PA",
    "sg:tags":[
        "shower",
        "door",
        "enclosure"
    ],
    "wof:name":"Dave's Custom Mirrors & Shower",
    "wof:placetype":"venue"
},
  "geometry": {"coordinates":[-79.95479400000001,40.56424],"type":"Point"}
}