{
  "type": "Feature",
  "properties": {
    "iso:country":"US",
    "sg:address":"1514 W Marshall St",
    "sg:city":"Norristown",
    "sg:classifiers":[
        {
            "category":"Manufacturing",
            "subcategory":"Metals",
            "type":"Manufacturing & Wholesale Goods"
        }
    ],
    "sg:phone":"+1 610 635 4166",
    "sg:postcode":"19403",
    "sg:province":"PA",
    "sg:tags":[
        "closer",
        "door",
        "check"
    ],
    "wof:name":"Mc Fadden Locksmiths",
    "wof:placetype":"venue"
},
  "geometry": {"coordinates":[-75.36576599999999,40.129543],"type":"Point"}
}