{
  "type": "Feature",
  "properties": {
    "iso:country":"US",
    "sg:address":"6480 Library Rd",
    "sg:city":"Library",
    "sg:classifiers":[
        {
            "category":"Insurance",
            "subcategory":"Insurance Agent",
            "type":"Services"
        }
    ],
    "sg:phone":"+1 412 831 3125",
    "sg:postcode":"15129",
    "sg:province":"PA",
    "sg:tags":[
        "life",
        "carrier"
    ],
    "wof:name":"State Farm Insurance",
    "wof:placetype":"venue"
},
  "geometry": {"coordinates":[-80.027402,40.289295],"type":"Point"}
}