{
  "type": "Feature",
  "properties": {
    "iso:country":"US",
    "sg:address":"209 Bradford Park Rd",
    "sg:city":"Baden",
    "sg:classifiers":[
        {
            "category":"Real Estate",
            "subcategory":"Real Estate Operator",
            "type":"Services"
        }
    ],
    "sg:phone":"+1   ",
    "sg:postcode":"15005",
    "sg:province":"PA",
    "sg:tags":[
        "building",
        "apartment"
    ],
    "wof:name":"Ld Apartment Rentals",
    "wof:placetype":"venue"
},
  "geometry": {"coordinates":[-80.15929199999999,40.663281],"type":"Point"}
}