{
  "type": "Feature",
  "properties": {
    "iso:country":"US",
    "sg:address":"1001 W 4th St",
    "sg:city":"Lewistown",
    "sg:classifiers":[
        {
            "category":"Autos & Motor Vehicles",
            "subcategory":"Automobile Sales",
            "type":"Retail Goods"
        }
    ],
    "sg:phone":"+1 717 242 3730",
    "sg:postcode":"17044",
    "sg:province":"PA",
    "sg:tags":[
        "car",
        "used",
        "dealer"
    ],
    "wof:name":"Jim's Auto Sales",
    "wof:placetype":"venue"
},
  "geometry": {"coordinates":[-77.59678,40.590589],"type":"Point"}
}