{
  "type": "Feature",
  "properties": {
    "iso:country":"US",
    "sg:address":"2400 Ardmore Blvd",
    "sg:city":"Wilkinsburg",
    "sg:classifiers":[
        {
            "category":"Professional",
            "subcategory":"Management & Consulting",
            "type":"Services"
        }
    ],
    "sg:phone":"+1 412 271 5231",
    "sg:postcode":"15221",
    "sg:province":"PA",
    "sg:tags":[
        "consultant",
        "telecommunication"
    ],
    "wof:name":"GRP Svc",
    "wof:placetype":"venue"
},
  "geometry": {"coordinates":[-79.84520500000001,40.413465],"type":"Point"}
}