{
  "type": "Feature",
  "properties": {
    "iso:country":"US",
    "sg:address":"500 Exeter Ave",
    "sg:city":"Pittston",
    "sg:classifiers":[
        {
            "category":"Shopping",
            "subcategory":"Books",
            "type":"Retail Goods"
        }
    ],
    "sg:phone":"+1   ",
    "sg:postcode":"18643",
    "sg:province":"PA",
    "wof:name":"Time Tunnel Comics",
    "wof:placetype":"venue"
},
  "geometry": {"coordinates":[-75.79864499999999,41.333065],"type":"Point"}
}