{
  "type": "Feature",
  "properties": {
    "iso:country":"US",
    "sg:address":"43 S Harvest Rd",
    "sg:city":"Bird In Hand",
    "sg:classifiers":[
        {
            "category":"Travel",
            "subcategory":"Hotels & Motels",
            "type":"Entertainment"
        }
    ],
    "sg:phone":"+1 717 768 3644",
    "sg:postcode":"17505",
    "sg:province":"PA",
    "sg:tags":[
        "operation"
    ],
    "wof:name":"Orchard View Motel",
    "wof:placetype":"venue"
},
  "geometry": {"coordinates":[-76.148347,40.028636],"type":"Point"}
}