{
  "type": "Feature",
  "properties": {
    "addr:full":"6655 McCallum St Philadelphia PA 19119",
    "addr:housenumber":"6655",
    "addr:postcode":"19119",
    "addr:street":"Mccallum St",
    "iso:country":"US",
    "sg:address":"6655 McCallum St",
    "sg:city":"Philadelphia",
    "sg:classifiers":[
        {
            "category":"Real Estate",
            "subcategory":"Real Estate Agent",
            "type":"Services"
        },
        {
            "category":"Real Estate",
            "subcategory":"Real Estate Operator",
            "type":"Services"
        }
    ],
    "sg:phone":"+1 215 849 7115",
    "sg:postcode":"19119",
    "sg:province":"PA",
    "sg:tags":[
        "condominium"
    ],
    "wof:name":"Malvern Hall Condominiums",
    "wof:placetype":"venue"
},
  "geometry": {"coordinates":[-75.19149400000001,40.04518],"type":"Point"}
}