{
  "type": "Feature",
  "properties": {
    "addr:full":"6612 Haverford Ave Philadelphia PA 19151",
    "addr:housenumber":"6612",
    "addr:postcode":"19151",
    "addr:street":"Haverford Ave",
    "iso:country":"US",
    "sg:address":"6612 Haverford Ave",
    "sg:city":"Philadelphia",
    "sg:classifiers":[
        {
            "category":"Social Services",
            "subcategory":"Child Care",
            "type":"Services"
        }
    ],
    "sg:phone":"+1 215 476 4101",
    "sg:postcode":"19151",
    "sg:province":"PA",
    "sg:tags":[
        "day"
    ],
    "wof:name":"Little Shepards Christian Learning Center",
    "wof:placetype":"venue"
},
  "geometry": {"coordinates":[-75.252403,39.972401],"type":"Point"}
}