{
  "type": "Feature",
  "properties": {
    "iso:country":"US",
    "sg:address":"110 Hemlock Dr",
    "sg:city":"Canonsburg",
    "sg:classifiers":[
        {
            "category":"Health Services",
            "subcategory":"Doctor",
            "type":"Services"
        }
    ],
    "sg:phone":"+1 724 941 6769",
    "sg:postcode":"15317",
    "sg:province":"PA",
    "sg:tags":[
        "physician",
        "surgeon"
    ],
    "wof:name":"Meta Louis D MD",
    "wof:placetype":"venue"
},
  "geometry": {"coordinates":[-80.136597,40.2799],"type":"Point"}
}