{
  "type": "Feature",
  "properties": {
    "iso:country":"US",
    "sg:address":"5040 Ritter Rd",
    "sg:city":"Mechanicsburg",
    "sg:classifiers":[
        {
            "category":"Professional",
            "subcategory":"Accounting & Tax Preparation",
            "type":"Services"
        }
    ],
    "sg:phone":"+1 717 697 6800",
    "sg:postcode":"17055",
    "sg:province":"PA",
    "sg:tags":[
        "bookkeeping"
    ],
    "wof:name":"Eur Systems",
    "wof:placetype":"venue"
},
  "geometry": {"coordinates":[-76.963886,40.203065],"type":"Point"}
}