{
  "type": "Feature",
  "properties": {
    "addr:full":"411 Harrison Ave Jeannette PA 15644",
    "addr:housenumber":"411",
    "addr:postcode":"15644",
    "addr:street":"Harrison Ave",
    "iso:country":"US",
    "sg:address":"411 Harrison Ave",
    "sg:city":"Jeannette",
    "sg:classifiers":[
        {
            "category":"Recreation",
            "type":"Entertainment"
        }
    ],
    "sg:phone":"+1 724 527 1966",
    "sg:postcode":"15644",
    "sg:province":"PA",
    "sg:tags":[
        "karate",
        "judo",
        "instr"
    ],
    "wof:name":"Matrisch Martial Arts",
    "wof:placetype":"venue"
},
  "geometry": {"coordinates":[-79.60563,40.331414],"type":"Point"}
}