{
  "type": "Feature",
  "properties": {
    "addr:full":"188 Beach Lake Hwy Honesdale PA 18431",
    "addr:housenumber":"188",
    "addr:postcode":"18431",
    "addr:street":"Beach Lake Hwy",
    "iso:country":"US",
    "sg:address":"188 Beach Lake Hwy",
    "sg:city":"Honesdale",
    "sg:classifiers":[
        {
            "category":"Building & Trades",
            "subcategory":"Plumbing",
            "type":"Services"
        },
        {
            "category":"Retail",
            "subcategory":"Repair Shop",
            "type":"Services"
        },
        {
            "category":"Wholesale",
            "subcategory":"Machinery & Supplies",
            "type":"Manufacturing & Wholesale Goods"
        },
        {
            "category":"Building & Trades",
            "subcategory":"Cleaning & Sanitation",
            "type":"Services"
        }
    ],
    "sg:phone":"+1 570 253 3660",
    "sg:postcode":"18431",
    "sg:province":"PA",
    "sg:tags":[
        "cleaner",
        "repairer",
        "pump",
        "sewer",
        "pumps-service",
        "plumbing-drain"
    ],
    "sg:website":"http://www.koberleinenvironmental.com",
    "wof:name":"Koberlein Environmental Services",
    "wof:placetype":"venue"
},
  "geometry": {"coordinates":[-75.207449,41.55755],"type":"Point"}
}