{
  "type": "Feature",
  "properties": {
    "addr:full":"711 Penn Ave Reading PA 19611",
    "addr:housenumber":"711",
    "addr:postcode":"19611",
    "addr:street":"Penn Ave",
    "iso:country":"US",
    "sg:address":"711 Penn Ave",
    "sg:city":"Reading",
    "sg:classifiers":[
        {
            "category":"Professional",
            "type":"Services"
        },
        {
            "category":"Shopping",
            "subcategory":"Gifts & Souvenirs",
            "type":"Retail Goods"
        }
    ],
    "sg:phone":"+1 610 208 0326",
    "sg:postcode":"19611",
    "sg:province":"PA",
    "sg:tags":[
        "shop"
    ],
    "wof:name":"Devis",
    "wof:placetype":"venue"
},
  "geometry": {"coordinates":[-75.95350999999999,40.336082],"type":"Point"}
}