{
  "type": "Feature",
  "properties": {
    "addr:full":"5859 Ellsworth Ave Pittsburgh PA 15232",
    "addr:housenumber":"5859",
    "addr:postcode":"15232",
    "addr:street":"Ellsworth Ave",
    "iso:country":"US",
    "sg:address":"5859 Ellsworth Ave",
    "sg:city":"Pittsburgh",
    "sg:classifiers":[
        {
            "category":"Retail",
            "subcategory":"Self-service Laundry",
            "type":"Services"
        }
    ],
    "sg:phone":"+1 412 361 1200",
    "sg:postcode":"15232",
    "sg:province":"PA",
    "sg:tags":[
        "coin"
    ],
    "wof:name":"Laundry Factory",
    "wof:placetype":"venue"
},
  "geometry": {"coordinates":[-79.927943,40.458051],"type":"Point"}
}