{
  "type": "Feature",
  "properties": {
    "addr:full":"381 N Hoover Ave New Holland PA 17557",
    "addr:housenumber":"381",
    "addr:postcode":"17557",
    "addr:street":"N Hoover Ave",
    "iso:country":"US",
    "sg:address":"381 N Hoover Ave",
    "sg:city":"New Holland",
    "sg:classifiers":[
        {
            "category":"Building & Trades",
            "subcategory":"Construction",
            "type":"Services"
        }
    ],
    "sg:phone":"+1 717 354 5584",
    "sg:postcode":"17557",
    "sg:province":"PA",
    "sg:tags":[
        "excavation",
        "contractor"
    ],
    "wof:name":"Nolt Excavating",
    "wof:placetype":"venue"
},
  "geometry": {"coordinates":[-76.10799900000001,40.11125],"type":"Point"}
}