{
  "type": "Feature",
  "properties": {
    "addr:full":"131 2nd Street Pike Southampton PA 18966",
    "addr:housenumber":"131",
    "addr:postcode":"18966",
    "addr:street":"2Nd Street Pike",
    "iso:country":"US",
    "sg:address":"131 2nd Street Pike",
    "sg:city":"Southampton",
    "sg:classifiers":[
        {
            "category":"Social Services",
            "subcategory":"Child Care",
            "type":"Services"
        }
    ],
    "sg:phone":"+1 215 322 7200",
    "sg:postcode":"18966",
    "sg:province":"PA",
    "sg:tags":[
        "day"
    ],
    "sg:website":"www.schoolhouse.net",
    "wof:name":"Schoolhouse Learning Center",
    "wof:placetype":"venue"
},
  "geometry": {"coordinates":[-75.046063,40.1663],"type":"Point"}
}