{
  "type": "Feature",
  "properties": {
    "iso:country":"US",
    "sg:address":"175 Hykes Rd E",
    "sg:city":"Greencastle",
    "sg:classifiers":[
        {
            "category":"Professional",
            "subcategory":"Printing & Photocopies",
            "type":"Services"
        }
    ],
    "sg:phone":"+1 717 593 9243",
    "sg:postcode":"17225",
    "sg:province":"PA",
    "sg:tags":[
        "duplicating",
        "copying"
    ],
    "wof:name":"Ams Services & Designs",
    "wof:placetype":"venue"
},
  "geometry": {"coordinates":[-77.720704,39.731234],"type":"Point"}
}