{
  "type": "Feature",
  "properties": {
    "addr:full":"1 N Hanover St Carlisle PA 17013",
    "addr:housenumber":"1",
    "addr:postcode":"17013",
    "addr:street":"N Hanover St",
    "iso:country":"US",
    "sg:address":"1 N Hanover St",
    "sg:city":"Carlisle",
    "sg:classifiers":[
        {
            "category":"Organizations",
            "subcategory":"Religious Organization",
            "type":"Services"
        }
    ],
    "sg:phone":"+1 717 243 4220",
    "sg:postcode":"17013",
    "sg:province":"PA",
    "sg:tags":[
        "church"
    ],
    "sg:website":"www.stjohnscarlisle.org",
    "wof:name":"St John's Episcopal Church",
    "wof:placetype":"venue"
},
  "geometry": {"coordinates":[-77.188885,40.203021],"type":"Point"}
}