{
  "type": "Feature",
  "properties": {
    "iso:country":"US",
    "sg:address":"1400 Bolde Dr",
    "sg:city":"Hermitage",
    "sg:classifiers":[
        {
            "category":"Real Estate",
            "subcategory":"Real Estate Operator",
            "type":"Services"
        }
    ],
    "sg:phone":"+1 724 981 4900",
    "sg:postcode":"16148",
    "sg:province":"PA",
    "sg:tags":[
        "apartment"
    ],
    "wof:name":"Shenango Park Apartments",
    "wof:placetype":"venue"
},
  "geometry": {"coordinates":[-80.469796,41.214289],"type":"Point"}
}