{
  "type": "Feature",
  "properties": {
    "iso:country":"US",
    "sg:address":"539 W Mahoning St",
    "sg:city":"Punxsutawney",
    "sg:classifiers":[
        {
            "category":"Banks & Credit Unions",
            "subcategory":"Bank",
            "type":"Services"
        }
    ],
    "sg:phone":"+1 814 000 1111",
    "sg:postcode":"15767",
    "sg:province":"PA",
    "wof:name":"S & T Bank",
    "wof:placetype":"venue"
},
  "geometry": {"coordinates":[-78.978533,40.942504],"type":"Point"}
}