{
  "type": "Feature",
  "properties": {
    "iso:country":"US",
    "sg:address":"600 Grant St",
    "sg:city":"Pittsburgh",
    "sg:classifiers":[
        {
            "category":"Professional",
            "subcategory":"Lawyer & Legal Services",
            "type":"Services"
        }
    ],
    "sg:phone":"+1 412 391 2101",
    "sg:postcode":"15219",
    "sg:province":"PA",
    "sg:website":"www.edgarsnyder.com",
    "wof:name":"Berkey Todd Atty",
    "wof:placetype":"venue"
},
  "geometry": {"coordinates":[-79.995221,40.441532],"type":"Point"}
}