{
  "type": "Feature",
  "properties": {
    "iso:country":"US",
    "sg:address":"145 Larch St",
    "sg:city":"Hollidaysburg",
    "sg:classifiers":[
        {
            "category":"Organizations",
            "subcategory":"Community Association",
            "type":"Services"
        }
    ],
    "sg:phone":"+1 814 693 9811",
    "sg:postcode":"16648",
    "sg:province":"PA",
    "sg:tags":[
        "club"
    ],
    "wof:name":"Blairmont Club",
    "wof:placetype":"venue"
},
  "geometry": {"coordinates":[-78.38914200000001,40.445313],"type":"Point"}
}