{
  "type": "Feature",
  "properties": {
    "iso:country":"US",
    "sg:address":"1400 Lee Dr",
    "sg:city":"Coraopolis",
    "sg:classifiers":[
        {
            "category":"Building & Trades",
            "subcategory":"Cleaning & Sanitation",
            "type":"Services"
        }
    ],
    "sg:phone":"+1 412 264 5510",
    "sg:postcode":"15108",
    "sg:province":"PA",
    "sg:tags":[
        "maintenance"
    ],
    "wof:name":"Beaver Grade Construction Co",
    "wof:placetype":"venue"
},
  "geometry": {"coordinates":[-80.190066,40.525522],"type":"Point"}
}