{
  "type": "Feature",
  "properties": {
    "addr:full":"435 Main St Saegertown PA 16434",
    "addr:housenumber":"435",
    "addr:postcode":"16434",
    "addr:street":"Main St",
    "iso:country":"US",
    "sg:address":"435 Main St",
    "sg:city":"Saegertown",
    "sg:classifiers":[
        {
            "category":"Personal",
            "subcategory":"Beauty Salon",
            "type":"Services"
        }
    ],
    "sg:phone":"+1 814 763 3430",
    "sg:postcode":"16434",
    "sg:province":"PA",
    "wof:name":"Just Teasin'",
    "wof:placetype":"venue"
},
  "geometry": {"coordinates":[-80.14856399999999,41.719681],"type":"Point"}
}