{
  "type": "Feature",
  "properties": {
    "addr:full":"301 Main St Landisville PA 17538",
    "addr:housenumber":"301",
    "addr:postcode":"17538",
    "addr:street":"Main St",
    "iso:country":"US",
    "sg:address":"301 Main St",
    "sg:city":"Landisville",
    "sg:classifiers":[
        {
            "category":"Restaurant",
            "type":"Food & Drink"
        }
    ],
    "sg:phone":"+1 717 898 3707",
    "sg:postcode":"17538",
    "sg:province":"PA",
    "sg:tags":[
        "pizza"
    ],
    "wof:name":"Original Italian Pizza",
    "wof:placetype":"venue"
},
  "geometry": {"coordinates":[-76.433001,40.103577],"type":"Point"}
}