{
  "type": "Feature",
  "properties": {
    "iso:country":"US",
    "sg:address":"1991 Eaton Ave",
    "sg:city":"Bethlehem",
    "sg:classifiers":[
        {
            "category":"Health Services",
            "subcategory":"Chiropractor",
            "type":"Services"
        }
    ],
    "sg:phone":"+1 610 865 1763",
    "sg:postcode":"18018",
    "sg:province":"PA",
    "wof:name":"Robert F Swift Jr DC",
    "wof:placetype":"venue"
},
  "geometry": {"coordinates":[-75.41291699999999,40.629226],"type":"Point"}
}