{
  "type": "Feature",
  "properties": {
    "addr:full":"205 Ave G Matamoras PA 18336",
    "addr:housenumber":"205",
    "addr:postcode":"18336",
    "addr:street":"Ave G",
    "iso:country":"US",
    "sg:address":"205 Ave G",
    "sg:city":"Matamoras",
    "sg:classifiers":[
        {
            "category":"Organizations",
            "subcategory":"Religious Organization",
            "type":"Services"
        }
    ],
    "sg:phone":"+1 570 491 2676",
    "sg:postcode":"18336",
    "sg:province":"PA",
    "sg:tags":[
        "church"
    ],
    "wof:name":"New Life Christian Fellowship",
    "wof:placetype":"venue"
},
  "geometry": {"coordinates":[-74.702448,41.371376],"type":"Point"}
}