{
  "type": "Feature",
  "properties": {
    "addr:full":"4523 N 5th St Philadelphia PA 19140",
    "addr:housenumber":"4523",
    "addr:postcode":"19140",
    "addr:street":"N 5Th St",
    "iso:country":"US",
    "sg:address":"4523 N 5th St",
    "sg:city":"Philadelphia",
    "sg:classifiers":[
        {
            "category":"Health Services",
            "subcategory":"Doctor",
            "type":"Services"
        }
    ],
    "sg:phone":"+1   ",
    "sg:postcode":"19140",
    "sg:province":"PA",
    "sg:tags":[
        "clinic",
        "dentist"
    ],
    "wof:name":"Suarez Dental Lab",
    "wof:placetype":"venue"
},
  "geometry": {"coordinates":[-75.134058,40.019721],"type":"Point"}
}