{
  "type": "Feature",
  "properties": {
    "iso:country":"US",
    "sg:address":"1067 Dekalb St",
    "sg:city":"Bridgeport",
    "sg:classifiers":[
        {
            "category":"Food & Beverages",
            "subcategory":"Groceries & Convenience Stores",
            "type":"Retail Goods"
        }
    ],
    "sg:phone":"+1 610 279 7999",
    "sg:postcode":"19405",
    "sg:province":"PA",
    "wof:name":"In & Out Food Stores",
    "wof:placetype":"venue"
},
  "geometry": {"coordinates":[-75.349279,40.101496],"type":"Point"}
}