{
  "type": "Feature",
  "properties": {
    "addr:full":"184 Veterans St Hollsopple PA 15935",
    "addr:housenumber":"184",
    "addr:postcode":"15935",
    "addr:street":"Veterans St",
    "iso:country":"US",
    "sg:address":"184 Veterans St",
    "sg:city":"Hollsopple",
    "sg:classifiers":[
        {
            "category":"Organizations",
            "subcategory":"Religious Organization",
            "type":"Services"
        }
    ],
    "sg:phone":"+1 814 479 4236",
    "sg:postcode":"15935",
    "sg:province":"PA",
    "sg:tags":[
        "church"
    ],
    "wof:name":"Apostolic Gospel Church",
    "wof:placetype":"venue"
},
  "geometry": {"coordinates":[-78.930587,40.210796],"type":"Point"}
}