{
  "type": "Feature",
  "properties": {
    "iso:country":"US",
    "sg:address":"141 E High St",
    "sg:city":"Waynesburg",
    "sg:classifiers":[
        {
            "category":"Professional",
            "subcategory":"Advertising",
            "type":"Services"
        }
    ],
    "sg:phone":"+1 724 627 2040",
    "sg:postcode":"15370",
    "sg:province":"PA",
    "wof:name":"Direct Results",
    "wof:placetype":"venue"
},
  "geometry": {"coordinates":[-80.18492999999999,39.896516],"type":"Point"}
}