{
  "type": "Feature",
  "properties": {
    "addr:full":"1600 Church Rd Wyncote PA 19095",
    "addr:housenumber":"1600",
    "addr:postcode":"19095",
    "addr:street":"Church Rd",
    "iso:country":"US",
    "sg:address":"1600 Church Rd",
    "sg:city":"Wyncote",
    "sg:classifiers":[
        {
            "category":"Real Estate",
            "subcategory":"Real Estate Agent",
            "type":"Services"
        },
        {
            "category":"Real Estate",
            "subcategory":"Real Estate Operator",
            "type":"Services"
        }
    ],
    "sg:phone":"+1 215 885 2403",
    "sg:postcode":"19095",
    "sg:province":"PA",
    "sg:tags":[
        "condominium"
    ],
    "wof:name":"1600 Church Road Condominiums",
    "wof:placetype":"venue"
},
  "geometry": {"coordinates":[-75.156724,40.090113],"type":"Point"}
}