{
  "type": "Feature",
  "properties": {
    "iso:country":"US",
    "sg:address":"1306 Shoemaker St",
    "sg:city":"Nanty Glo",
    "sg:classifiers":[
        {
            "category":"Banks & Credit Unions",
            "subcategory":"Bank",
            "type":"Services"
        }
    ],
    "sg:phone":"+1 814 749 8649",
    "sg:postcode":"15943",
    "sg:province":"PA",
    "wof:name":"C & G Savings Bank",
    "wof:placetype":"venue"
},
  "geometry": {"coordinates":[-78.836411,40.467711],"type":"Point"}
}