{
  "type": "Feature",
  "properties": {
    "addr:full":"195 S 1st St Lehighton PA 18235",
    "addr:housenumber":"195",
    "addr:postcode":"18235",
    "addr:street":"S 1St St",
    "iso:country":"US",
    "sg:address":"195 S 1st St",
    "sg:city":"Lehighton",
    "sg:classifiers":[
        {
            "category":"Social Services",
            "type":"Services"
        }
    ],
    "sg:phone":"+1   ",
    "sg:postcode":"18235",
    "sg:province":"PA",
    "wof:name":"Assoction For Rtarded Citizens",
    "wof:placetype":"venue"
},
  "geometry": {"coordinates":[-75.708339,40.831742],"type":"Point"}
}