{
  "type": "Feature",
  "properties": {
    "iso:country":"US",
    "sg:address":"2824 William Penn Ave",
    "sg:city":"Johnstown",
    "sg:classifiers":[
        {
            "category":"Building & Trades",
            "subcategory":"Construction",
            "type":"Services"
        }
    ],
    "sg:phone":"+1 814 322 3120",
    "sg:postcode":"15909",
    "sg:province":"PA",
    "sg:tags":[
        "excavating",
        "contractor"
    ],
    "wof:name":"Snyder Excavating",
    "wof:placetype":"venue"
},
  "geometry": {"coordinates":[-78.86049,40.413437],"type":"Point"}
}