{
  "type": "Feature",
  "properties": {
    "addr:full":"5 Foster Sq Pittsburgh PA 15212",
    "addr:housenumber":"5",
    "addr:postcode":"15212",
    "addr:street":"Foster Sq",
    "iso:country":"US",
    "sg:address":"5 Foster Sq",
    "sg:city":"Pittsburgh",
    "sg:classifiers":[
        {
            "category":"Professional",
            "subcategory":"Detective & Security Services",
            "type":"Services"
        }
    ],
    "sg:phone":"+1   ",
    "sg:postcode":"15212",
    "sg:province":"PA",
    "sg:tags":[
        "car"
    ],
    "wof:name":"Ips",
    "wof:placetype":"venue"
},
  "geometry": {"coordinates":[-80.00812500000001,40.451788],"type":"Point"}
}