{
  "type": "Feature",
  "properties": {
    "addr:full":"4095 Blanche Rd Bensalem PA 19020",
    "addr:housenumber":"4095",
    "addr:postcode":"19020",
    "addr:street":"Blanche Rd",
    "iso:country":"US",
    "sg:address":"4095 Blanche Rd",
    "sg:city":"Bensalem",
    "sg:classifiers":[
        {
            "category":"Freight",
            "type":"Transportation"
        }
    ],
    "sg:phone":"+1 215 244 0888",
    "sg:postcode":"19020",
    "sg:province":"PA",
    "sg:tags":[
        "operator",
        "local",
        "trucking"
    ],
    "sg:website":"www.estes-express.com",
    "wof:name":"Estes Express Inc",
    "wof:placetype":"venue"
},
  "geometry": {"coordinates":[-74.929422,40.102814],"type":"Point"}
}