{
  "type": "Feature",
  "properties": {
    "iso:country":"US",
    "sg:address":"701 Denver St",
    "sg:city":"Jamestown",
    "sg:classifiers":[
        {
            "category":"Organizations",
            "subcategory":"Religious Organization",
            "type":"Services"
        }
    ],
    "sg:phone":"+1 724 932 5959",
    "sg:postcode":"16134",
    "sg:province":"PA",
    "sg:tags":[
        "church"
    ],
    "wof:name":"St Margarets Catholic Church",
    "wof:placetype":"venue"
},
  "geometry": {"coordinates":[-80.44147700000001,41.491752],"type":"Point"}
}