{
  "type": "Feature",
  "properties": {
    "addr:full":"1920 Creek Rd Glenmoore PA 19343",
    "addr:housenumber":"1920",
    "addr:postcode":"19343",
    "addr:street":"Creek Rd",
    "iso:country":"US",
    "sg:address":"1920 Creek Rd",
    "sg:city":"Glenmoore",
    "sg:classifiers":[
        {
            "category":"Organizations",
            "subcategory":"Religious Organization",
            "type":"Services"
        }
    ],
    "sg:phone":"+1 610 942 2324",
    "sg:postcode":"19343",
    "sg:province":"PA",
    "sg:tags":[
        "place",
        "worship",
        "church"
    ],
    "wof:name":"Glenmoore United Methodist Church",
    "wof:placetype":"venue"
},
  "geometry": {"coordinates":[-75.771519,40.088039],"type":"Point"}
}