{
  "type": "Feature",
  "properties": {
    "addr:full":"106 Provan Pl Pittsburgh PA 15229",
    "addr:housenumber":"106",
    "addr:postcode":"15229",
    "addr:street":"Provan Pl",
    "iso:country":"US",
    "sg:address":"106 Provan Pl",
    "sg:city":"Pittsburgh",
    "sg:classifiers":[
        {
            "category":"Building & Trades",
            "subcategory":"Construction",
            "type":"Services"
        }
    ],
    "sg:phone":"+1 412 366 5952",
    "sg:postcode":"15229",
    "sg:province":"PA",
    "sg:tags":[
        "plastering",
        "contractor"
    ],
    "wof:name":"D J L Inc",
    "wof:placetype":"venue"
},
  "geometry": {"coordinates":[-80.032113,40.533493],"type":"Point"}
}