{
  "type": "Feature",
  "properties": {
    "iso:country":"US",
    "sg:address":"19 Yankee Ridge Rd",
    "sg:city":"Mercer",
    "sg:classifiers":[
        {
            "category":"Autos & Motor Vehicles",
            "subcategory":"Auto Supplies",
            "type":"Retail Goods"
        },
        {
            "category":"Retail",
            "subcategory":"Repair Shop",
            "type":"Services"
        }
    ],
    "sg:phone":"+1 724 981 7941",
    "sg:postcode":"16137",
    "sg:province":"PA",
    "sg:tags":[
        "upholstery",
        "upholsterer",
        "automobile",
        "refinish",
        "covers",
        "seat",
        "top",
        "furniture"
    ],
    "wof:name":"C & W Custom Upholstering",
    "wof:placetype":"venue"
},
  "geometry": {"coordinates":[-80.357403,41.214076],"type":"Point"}
}