{
  "type": "Feature",
  "properties": {
    "iso:country":"US",
    "sg:address":"217 Center St",
    "sg:city":"Tamaqua",
    "sg:classifiers":[
        {
            "category":"Government",
            "subcategory":"Office",
            "type":"Public Place"
        }
    ],
    "sg:phone":"+1 570 668 4300",
    "sg:postcode":"18252",
    "sg:province":"PA",
    "wof:name":"Careerlink Ctr",
    "wof:placetype":"venue"
},
  "geometry": {"coordinates":[-75.968097,40.79469],"type":"Point"}
}