{
  "type": "Feature",
  "properties": {
    "iso:country":"US",
    "sg:address":"6603 Oakland St",
    "sg:city":"Philadelphia",
    "sg:classifiers":[
        {
            "category":"Shopping",
            "subcategory":"Clothing, Apparel, & Fashions",
            "type":"Retail Goods"
        }
    ],
    "sg:phone":"+1 215 342 1466",
    "sg:postcode":"19149",
    "sg:province":"PA",
    "sg:tags":[
        "t"
    ],
    "wof:name":"School Yard Legends",
    "wof:placetype":"venue"
},
  "geometry": {"coordinates":[-75.068804,40.040312],"type":"Point"}
}