{
  "type": "Feature",
  "properties": {
    "addr:full":"700 Grant St Pittsburgh PA 15219",
    "addr:housenumber":"700",
    "addr:postcode":"15219",
    "addr:street":"Grant St",
    "iso:country":"US",
    "sg:address":"700 Grant St",
    "sg:city":"Pittsburgh",
    "sg:classifiers":[
        {
            "category":"Professional",
            "subcategory":"Secretarial Services",
            "type":"Services"
        }
    ],
    "sg:phone":"+1 412 261 0802",
    "sg:postcode":"15219",
    "sg:province":"PA",
    "sg:tags":[
        "convention",
        "court",
        "reporter"
    ],
    "wof:name":"Richard T Ford",
    "wof:placetype":"venue"
},
  "geometry": {"coordinates":[-79.993809,40.443788],"type":"Point"}
}