{
  "type": "Feature",
  "properties": {
    "iso:country":"US",
    "sg:address":"315 Summit Ave",
    "sg:city":"Canonsburg",
    "sg:classifiers":[
        {
            "category":"Building & Trades",
            "subcategory":"Construction",
            "type":"Services"
        }
    ],
    "sg:phone":"+1   ",
    "sg:postcode":"15317",
    "sg:province":"PA",
    "sg:tags":[
        "contractor"
    ],
    "wof:name":"All Seasons Fencing",
    "wof:placetype":"venue"
},
  "geometry": {"coordinates":[-80.187347,40.250379],"type":"Point"}
}