{
  "type": "Feature",
  "properties": {
    "iso:country":"US",
    "sg:address":"142 Old Gate Rd",
    "sg:city":"Trafford",
    "sg:classifiers":[
        {
            "category":"Professional",
            "type":"Services"
        }
    ],
    "sg:phone":"+1   ",
    "sg:postcode":"15085",
    "sg:province":"PA",
    "wof:name":"Coyle & Gestrich Inc",
    "wof:placetype":"venue"
},
  "geometry": {"coordinates":[-79.725368,40.395244],"type":"Point"}
}