{
  "type": "Feature",
  "properties": {
    "addr:full":"3600 Lancaster Ave Philadelphia PA 19104",
    "addr:housenumber":"3600",
    "addr:postcode":"19104",
    "addr:street":"Lancaster Ave",
    "iso:country":"US",
    "sg:address":"3600 Lancaster Ave",
    "sg:city":"Philadelphia",
    "sg:classifiers":[
        {
            "category":"Restaurant",
            "type":"Food & Drink"
        }
    ],
    "sg:phone":"+1 215 895 0139",
    "sg:postcode":"19104",
    "sg:province":"PA",
    "sg:tags":[
        "mexican"
    ],
    "sg:website":"www.zocalophilly.com/",
    "wof:name":"Zocalo",
    "wof:placetype":"venue"
},
  "geometry": {"coordinates":[-75.19360399999999,39.958698],"type":"Point"}
}