{
  "type": "Feature",
  "properties": {
    "addr:full":"46 Rte 519 Eighty Four PA 15330",
    "addr:housenumber":"46",
    "addr:postcode":"15330",
    "addr:street":"Rte 519 Eighty",
    "iso:country":"US",
    "sg:address":"46 Rte 519",
    "sg:city":"Eighty Four",
    "sg:classifiers":[
        {
            "category":"Manufacturing",
            "subcategory":"Metals",
            "type":"Manufacturing & Wholesale Goods"
        }
    ],
    "sg:phone":"+1 724 225 6563",
    "sg:postcode":"15330",
    "sg:province":"PA",
    "sg:tags":[
        "fabrication",
        "structural"
    ],
    "wof:name":"Ritter Industries Inc",
    "wof:placetype":"venue"
},
  "geometry": {"coordinates":[-80.134624,40.128189],"type":"Point"}
}