{
  "type": "Feature",
  "properties": {
    "addr:full":"202 Locust St Harrisburg PA 17101",
    "addr:housenumber":"202",
    "addr:postcode":"17101",
    "addr:street":"Locust St",
    "iso:country":"US",
    "sg:address":"202 Locust St",
    "sg:city":"Harrisburg",
    "sg:classifiers":[
        {
            "category":"Bars & Pubs",
            "type":"Food & Drink"
        },
        {
            "category":"Restaurant",
            "type":"Food & Drink"
        }
    ],
    "sg:phone":"+1 717 232 9914",
    "sg:postcode":"17101",
    "sg:province":"PA",
    "sg:website":"www.mcgrathspub.net/",
    "wof:name":"McGrath's Pub",
    "wof:placetype":"venue"
},
  "geometry": {"coordinates":[-76.88359800000001,40.261002],"type":"Point"}
}