{
  "type": "Feature",
  "properties": {
    "iso:country":"US",
    "sg:address":"2948 Washington Rd",
    "sg:city":"Mc Murray",
    "sg:classifiers":[
        {
            "category":"Real Estate",
            "subcategory":"Real Estate Agent",
            "type":"Services"
        }
    ],
    "sg:phone":"+1 724 941 8680",
    "sg:postcode":"15317",
    "sg:province":"PA",
    "wof:name":"Frontier Realty",
    "wof:placetype":"venue"
},
  "geometry": {"coordinates":[-80.098472,40.300786],"type":"Point"}
}