{
  "type": "Feature",
  "properties": {
    "addr:full":"420 Alexandra Dr Norristown PA 19403",
    "addr:housenumber":"420",
    "addr:postcode":"19403",
    "addr:street":"Alexandra Dr",
    "iso:country":"US",
    "sg:address":"420 Alexandra Dr",
    "sg:city":"Norristown",
    "sg:classifiers":[
        {
            "category":"Building & Trades",
            "subcategory":"Landscaping Services",
            "type":"Services"
        }
    ],
    "sg:phone":"+1   ",
    "sg:postcode":"19403",
    "sg:province":"PA",
    "sg:tags":[
        "landscape"
    ],
    "wof:name":"Topieniak Landscape",
    "wof:placetype":"venue"
},
  "geometry": {"coordinates":[-75.384216,40.150323],"type":"Point"}
}