{
  "type": "Feature",
  "properties": {
    "addr:full":"345 Wyoming Ave Scranton PA 18503",
    "addr:housenumber":"345",
    "addr:postcode":"18503",
    "addr:street":"Wyoming Ave",
    "iso:country":"US",
    "sg:address":"345 Wyoming Ave",
    "sg:city":"Scranton",
    "sg:classifiers":[
        {
            "category":"Professional",
            "subcategory":"Lawyer & Legal Services",
            "type":"Services"
        }
    ],
    "sg:phone":"+1 570 961 1850",
    "sg:postcode":"18503",
    "sg:province":"PA",
    "sg:tags":[
        "attorney"
    ],
    "wof:name":"Herlands Rothenberg Levine",
    "wof:placetype":"venue"
},
  "geometry": {"coordinates":[-75.66301900000001,41.410663],"type":"Point"}
}