{
  "type": "Feature",
  "properties": {
    "iso:country":"US",
    "sg:address":"2320 Sheffield Rd",
    "sg:city":"Aliquippa",
    "sg:classifiers":[
        {
            "category":"Restaurant",
            "type":"Food & Drink"
        }
    ],
    "sg:phone":"+1 724 378 7800",
    "sg:postcode":"15001",
    "sg:province":"PA",
    "wof:name":"Quip Stop Bar & Grill",
    "wof:placetype":"venue"
},
  "geometry": {"coordinates":[-80.282346,40.60617],"type":"Point"}
}