{
  "type": "Feature",
  "properties": {
    "addr:full":"114 S 6th St Emmaus PA 18049",
    "addr:housenumber":"114",
    "addr:postcode":"18049",
    "addr:street":"S 6Th St",
    "iso:country":"US",
    "sg:address":"114 S 6th St",
    "sg:city":"Emmaus",
    "sg:classifiers":[
        {
            "category":"Professional",
            "subcategory":"Lawyer & Legal Services",
            "type":"Services"
        }
    ],
    "sg:phone":"+1 610 966 7669",
    "sg:postcode":"18049",
    "sg:province":"PA",
    "sg:tags":[
        "plan"
    ],
    "wof:name":"Matthew Lichtenwalner",
    "wof:placetype":"venue"
},
  "geometry": {"coordinates":[-75.49421700000001,40.53091],"type":"Point"}
}