{
  "type": "Feature",
  "properties": {
    "addr:full":"41 Ruthland Ave Malvern PA 19355",
    "addr:housenumber":"41",
    "addr:postcode":"19355",
    "addr:street":"Ruthland Ave",
    "iso:country":"US",
    "sg:address":"41 Ruthland Ave",
    "sg:city":"Malvern",
    "sg:classifiers":[
        {
            "category":"Building & Trades",
            "subcategory":"Construction",
            "type":"Services"
        }
    ],
    "sg:phone":"+1 610 296 7773",
    "sg:postcode":"19355",
    "sg:province":"PA",
    "sg:tags":[
        "home",
        "general",
        "family",
        "contractor"
    ],
    "wof:name":"Rabena Brothers Inc",
    "wof:placetype":"venue"
},
  "geometry": {"coordinates":[-75.50895,40.037559],"type":"Point"}
}