{
  "type": "Feature",
  "properties": {
    "iso:country":"US",
    "sg:address":"200 Harvey Rd",
    "sg:city":"Wallingford",
    "sg:classifiers":[
        {
            "category":"Manufacturing",
            "subcategory":"Printing",
            "type":"Manufacturing & Wholesale Goods"
        }
    ],
    "sg:phone":"+1   ",
    "sg:postcode":"19086",
    "sg:province":"PA",
    "sg:tags":[
        "commercial"
    ],
    "wof:name":"Klb Printing",
    "wof:placetype":"venue"
},
  "geometry": {"coordinates":[-75.368454,39.874988],"type":"Point"}
}