{
  "type": "Feature",
  "properties": {
    "addr:full":"1300 Providence Ave Chester PA 19013",
    "addr:housenumber":"1300",
    "addr:postcode":"19013",
    "addr:street":"Providence Ave",
    "iso:country":"US",
    "sg:address":"1300 Providence Ave",
    "sg:city":"Chester",
    "sg:classifiers":[
        {
            "category":"Travel",
            "subcategory":"Hotels & Motels",
            "type":"Entertainment"
        }
    ],
    "sg:phone":"+1 610 876 7211",
    "sg:postcode":"19013",
    "sg:province":"PA",
    "wof:name":"Days Inn",
    "wof:placetype":"venue"
},
  "geometry": {"coordinates":[-75.360315,39.858465],"type":"Point"}
}