{
  "type": "Feature",
  "properties": {
    "addr:full":"610 Elaine Dr Pittsburgh PA 15236",
    "addr:housenumber":"610",
    "addr:postcode":"15236",
    "addr:street":"Elaine Dr",
    "iso:country":"US",
    "sg:address":"610 Elaine Dr",
    "sg:city":"Pittsburgh",
    "sg:classifiers":[
        {
            "category":"Manufacturing",
            "subcategory":"Glass & Minerals",
            "type":"Manufacturing & Wholesale Goods"
        }
    ],
    "sg:phone":"+1 412 835 8011",
    "sg:postcode":"15236",
    "sg:province":"PA",
    "sg:tags":[
        "structural"
    ],
    "wof:name":"Premiere Glass Block",
    "wof:placetype":"venue"
},
  "geometry": {"coordinates":[-80.005882,40.344091],"type":"Point"}
}