{
  "type": "Feature",
  "properties": {
    "iso:country":"US",
    "sg:address":"300 W High St",
    "sg:city":"Womelsdorf",
    "sg:classifiers":[
        {
            "category":"Place Of Worship",
            "subcategory":"Church",
            "type":"Public Place"
        },
        {
            "category":"Place Of Worship",
            "type":"Public Place"
        }
    ],
    "sg:phone":"+1 610 589 4130",
    "sg:postcode":"19567",
    "sg:province":"PA",
    "sg:tags":[
        "lutheran",
        "america",
        "churches-lutheran",
        "churches-lutheran-evangelical"
    ],
    "wof:name":"Zion Evangelical Lutheran Church",
    "wof:placetype":"venue"
},
  "geometry": {"coordinates":[-76.18901099999999,40.364071],"type":"Point"}
}