{
  "type": "Feature",
  "properties": {
    "addr:full":"3034 Knights Rd Bensalem PA 19020",
    "addr:housenumber":"3034",
    "addr:postcode":"19020",
    "addr:street":"Knights Rd",
    "iso:country":"US",
    "sg:address":"3034 Knights Rd",
    "sg:city":"Bensalem",
    "sg:classifiers":[
        {
            "category":"Community Center",
            "type":"Public Place"
        }
    ],
    "sg:phone":"+1 215 639 0931",
    "sg:postcode":"19020",
    "sg:province":"PA",
    "sg:tags":[
        "medical"
    ],
    "wof:name":"Isn Sleep Center Of Bensalem L",
    "wof:placetype":"venue"
},
  "geometry": {"coordinates":[-74.949905,40.105652],"type":"Point"}
}