{
  "type": "Feature",
  "properties": {
    "iso:country":"US",
    "sg:address":"3301 S Galloway St",
    "sg:city":"Philadelphia",
    "sg:classifiers":[
        {
            "category":"Wholesale",
            "subcategory":"Fruits & Vegetables",
            "type":"Manufacturing & Wholesale Goods"
        }
    ],
    "sg:phone":"+1   ",
    "sg:postcode":"19148",
    "sg:province":"PA",
    "wof:name":"Klayman Produce Company Inc",
    "wof:placetype":"venue"
},
  "geometry": {"coordinates":[-75.1553,39.907352],"type":"Point"}
}