{
  "type": "Feature",
  "properties": {
    "iso:country":"US",
    "sg:address":"126 W Harrisburg St",
    "sg:city":"Dillsburg",
    "sg:classifiers":[
        {
            "category":"Real Estate",
            "subcategory":"Real Estate Agent",
            "type":"Services"
        }
    ],
    "sg:phone":"+1 717 432 1436",
    "sg:postcode":"17019",
    "sg:province":"PA",
    "sg:website":"www.a1realtypa.com",
    "wof:name":"Re/Max A-1 Realty",
    "wof:placetype":"venue"
},
  "geometry": {"coordinates":[-77.03939699999999,40.111035],"type":"Point"}
}