{
  "type": "Feature",
  "properties": {
    "iso:country":"US",
    "sg:address":"412 S State St",
    "sg:city":"Clarks Summit",
    "sg:classifiers":[
        {
            "category":"Real Estate",
            "subcategory":"Real Estate Agent",
            "type":"Services"
        }
    ],
    "sg:phone":"+1 570 586 2911",
    "sg:postcode":"18411",
    "sg:province":"PA",
    "sg:website":"www.oboylerealestate.com",
    "wof:name":"O'Boyle Real Estate",
    "wof:placetype":"venue"
},
  "geometry": {"coordinates":[-75.70114700000001,41.493321],"type":"Point"}
}