{
  "type": "Feature",
  "properties": {
    "iso:country":"US",
    "sg:address":"60 Eagleville Rd",
    "sg:city":"Norristown",
    "sg:classifiers":[
        {
            "category":"Building & Trades",
            "subcategory":"Construction",
            "type":"Services"
        }
    ],
    "sg:phone":"+1   ",
    "sg:postcode":"19403",
    "sg:province":"PA",
    "sg:tags":[
        "house"
    ],
    "wof:name":"Decks Plus",
    "wof:placetype":"venue"
},
  "geometry": {"coordinates":[-75.411342,40.156435],"type":"Point"}
}