{
  "type": "Feature",
  "properties": {
    "iso:country":"US",
    "sg:address":"65 N 5th St",
    "sg:city":"Lemoyne",
    "sg:classifiers":[
        {
            "category":"Shopping",
            "type":"Retail Goods"
        }
    ],
    "sg:phone":"+1 717 737 0483",
    "sg:postcode":"17043",
    "sg:province":"PA",
    "sg:tags":[
        "equipment",
        "wine",
        "supply"
    ],
    "wof:name":"Scotzin Brothers",
    "wof:placetype":"venue"
},
  "geometry": {"coordinates":[-76.897091,40.246389],"type":"Point"}
}