{
  "type": "Feature",
  "properties": {
    "iso:country":"US",
    "sg:address":"754 NAZARETH PIKE",
    "sg:city":"NAZARETH",
    "sg:classifiers":[
        {
            "category":"Insurance",
            "subcategory":"Insurance Agent",
            "type":"Services"
        },
        {
            "category":"Insurance",
            "subcategory":"Hazard Insurance",
            "type":"Services"
        },
        {
            "category":"Insurance",
            "subcategory":"Title Insurance",
            "type":"Services"
        }
    ],
    "sg:phone":"+1 610 759 6920",
    "sg:postcode":"18064",
    "sg:province":"PA",
    "sg:tags":[
        "auto",
        "homeowner"
    ],
    "sg:website":"http://www.wolfinsurance.com",
    "wof:name":"Wolf Insurance",
    "wof:placetype":"venue"
},
  "geometry": {"coordinates":[-75.31760800000001,40.724334],"type":"Point"}
}