{
  "type": "Feature",
  "properties": {
    "addr:full":"562 W Broad St Hazleton PA 18201",
    "addr:housenumber":"562",
    "addr:postcode":"18201",
    "addr:street":"W Broad St",
    "iso:country":"US",
    "sg:address":"562 W Broad St",
    "sg:city":"Hazleton",
    "sg:classifiers":[
        {
            "category":"Shopping",
            "subcategory":"Discount & Variety Stores",
            "type":"Retail Goods"
        }
    ],
    "sg:phone":"+1 570 459 8650",
    "sg:postcode":"18201",
    "sg:province":"PA",
    "wof:name":"Dollar Tree",
    "wof:placetype":"venue"
},
  "geometry": {"coordinates":[-75.98609500000001,40.956991],"type":"Point"}
}