{
  "type": "Feature",
  "properties": {
    "addr:full":"1400 Little Mountain Rd Bethel PA 19507",
    "addr:housenumber":"1400",
    "addr:postcode":"19507",
    "addr:street":"Little Mountain Rd",
    "iso:country":"US",
    "sg:address":"1400 Little Mountain Rd",
    "sg:city":"Bethel",
    "sg:classifiers":[
        {
            "category":"Farming",
            "subcategory":"Livestock Farm",
            "type":"Manufacturing & Wholesale Goods"
        }
    ],
    "sg:phone":"+1   ",
    "sg:postcode":"19507",
    "sg:province":"PA",
    "sg:tags":[
        "beef",
        "feedlot",
        "cattle"
    ],
    "wof:name":"Daniel Musselman",
    "wof:placetype":"venue"
},
  "geometry": {"coordinates":[-76.36188799999999,40.48229],"type":"Point"}
}