{
  "type": "Feature",
  "properties": {
    "addr:full":"4019 Skippack Pike Skippack PA 19473",
    "addr:postcode":"4019;19473",
    "addr:street":"Skippack Pike",
    "iso:country":"US",
    "sg:address":"4019 Skippack Pike",
    "sg:city":"Skippack",
    "sg:classifiers":[
        {
            "category":"Personal",
            "subcategory":"Tanning Parlor",
            "type":"Services"
        },
        {
            "category":"Personal",
            "type":"Services"
        },
        {
            "category":"Personal",
            "subcategory":"Nail Salon",
            "type":"Services"
        }
    ],
    "sg:phone":"+1 610 584 7840",
    "sg:postcode":"19473",
    "sg:province":"PA",
    "sg:tags":[
        "party",
        "planning",
        "event"
    ],
    "wof:name":"Skippack Stylekrafters",
    "wof:placetype":"venue"
},
  "geometry": {"coordinates":[-75.399103,40.223125],"type":"Point"}
}