{
  "type": "Feature",
  "properties": {
    "iso:country":"US",
    "sg:address":"200 Sharon Park Dr",
    "sg:city":"Folcroft",
    "sg:classifiers":[
        {
            "category":"Building & Trades",
            "subcategory":"Plumbing",
            "type":"Services"
        },
        {
            "category":"Building & Trades",
            "subcategory":"Construction",
            "type":"Services"
        }
    ],
    "sg:phone":"+1 610 522 9460",
    "sg:postcode":"19032",
    "sg:province":"PA",
    "sg:tags":[
        "plumber",
        "industrial",
        "system",
        "specialty",
        "heating",
        "contractors-commercial",
        "contractor",
        "air conditioning"
    ],
    "wof:name":"Eddie's Plumbing And Heating",
    "wof:placetype":"venue"
},
  "geometry": {"coordinates":[-75.277687,39.903549],"type":"Point"}
}