{
  "type": "Feature",
  "properties": {
    "addr:full":"1037 Wilkes Barre Township Blvd Wilkes Barre PA 18702",
    "addr:housenumber":"1037",
    "addr:postcode":"18702",
    "addr:street":"Wilkes Barre Township Blvd",
    "iso:country":"US",
    "sg:address":"1037 Wilkes Barre Township Blvd",
    "sg:city":"Wilkes Barre",
    "sg:classifiers":[
        {
            "category":"Restaurant",
            "type":"Food & Drink"
        }
    ],
    "sg:menulink":"http://www.allmenus.com/pa/wilkes-barre/215111-taco-bell/menu/",
    "sg:phone":"+1 570 826 8911",
    "sg:postcode":"18702",
    "sg:province":"PA",
    "sg:tags":[
        "mexican"
    ],
    "wof:name":"Taco Bell",
    "wof:placetype":"venue"
},
  "geometry": {"coordinates":[-75.88214499999999,41.222906],"type":"Point"}
}