{
  "type": "Feature",
  "properties": {
    "addr:full":"1028 Harrison St Philadelphia PA 19124",
    "addr:housenumber":"1028",
    "addr:postcode":"19124",
    "addr:street":"Harrison St",
    "iso:country":"US",
    "sg:address":"1028 Harrison St",
    "sg:city":"Philadelphia",
    "sg:classifiers":[
        {
            "category":"Wholesale",
            "subcategory":"Machinery & Supplies",
            "type":"Manufacturing & Wholesale Goods"
        }
    ],
    "sg:phone":"+1 215 289 2212",
    "sg:postcode":"19124",
    "sg:province":"PA",
    "sg:tags":[
        "industrial",
        "tools-wholesale",
        "tool",
        "commercial",
        "equipment",
        "construction",
        "manufacturer"
    ],
    "wof:name":"American Tools & Fasteners Inc",
    "wof:placetype":"venue"
},
  "geometry": {"coordinates":[-75.089808,40.023467],"type":"Point"}
}