{
  "type": "Feature",
  "properties": {
    "addr:full":"434 W 5th Ave Conshohocken PA 19428",
    "addr:housenumber":"434",
    "addr:postcode":"19428",
    "addr:street":"W 5Th Ave",
    "iso:country":"US",
    "sg:address":"434 W 5th Ave",
    "sg:city":"Conshohocken",
    "sg:classifiers":[
        {
            "category":"Real Estate",
            "subcategory":"Real Estate Operator",
            "type":"Services"
        }
    ],
    "sg:phone":"+1   ",
    "sg:postcode":"19428",
    "sg:province":"PA",
    "sg:tags":[
        "building",
        "nonresidential"
    ],
    "wof:name":"C Two Properties",
    "wof:placetype":"venue"
},
  "geometry": {"coordinates":[-75.30825,40.080293],"type":"Point"}
}