{
  "type": "Feature",
  "properties": {
    "addr:full":"673 Stein Ln Lewisburg PA 17837",
    "addr:housenumber":"673",
    "addr:postcode":"17837",
    "addr:street":"Stein Ln",
    "iso:country":"US",
    "sg:address":"673 Stein Ln",
    "sg:city":"Lewisburg",
    "sg:classifiers":[
        {
            "category":"Professional",
            "subcategory":"Accounting & Tax Preparation",
            "type":"Services"
        }
    ],
    "sg:phone":"+1 570 524 7575",
    "sg:postcode":"17837",
    "sg:province":"PA",
    "sg:tags":[
        "accountant"
    ],
    "wof:name":"Frederick A Ressler CPA",
    "wof:placetype":"venue"
},
  "geometry": {"coordinates":[-76.898757,40.947962],"type":"Point"}
}