{
  "type": "Feature",
  "properties": {
    "addr:full":"50 Airport Rd Hanover PA 17331",
    "addr:housenumber":"50",
    "addr:postcode":"17331",
    "addr:street":"Airport Rd",
    "iso:country":"US",
    "sg:address":"50 Airport Rd",
    "sg:city":"Hanover",
    "sg:classifiers":[
        {
            "category":"Building & Trades",
            "subcategory":"Landscaping Services",
            "type":"Services"
        }
    ],
    "sg:phone":"+1 717 630 8884",
    "sg:postcode":"17331",
    "sg:province":"PA",
    "sg:tags":[
        "lawn",
        "maintenance",
        "grounds"
    ],
    "wof:name":"Keith's Lawn Cuttery",
    "wof:placetype":"venue"
},
  "geometry": {"coordinates":[-77.02094,39.795327],"type":"Point"}
}