{
  "type": "Feature",
  "properties": {
    "iso:country":"US",
    "sg:address":"204 6th St",
    "sg:city":"Port Royal",
    "sg:classifiers":[
        {
            "category":"Personal",
            "subcategory":"Beauty Salon",
            "type":"Services"
        }
    ],
    "sg:phone":"+1 717 527 2431",
    "sg:postcode":"17082",
    "sg:province":"PA",
    "wof:name":"C K Hair Designs",
    "wof:placetype":"venue"
},
  "geometry": {"coordinates":[-77.38947899999999,40.534129],"type":"Point"}
}