{
  "type": "Feature",
  "properties": {
    "iso:country":"US",
    "sg:address":"5455 Brownsville Rd",
    "sg:city":"Pittsburgh",
    "sg:classifiers":[
        {
            "category":"Retail",
            "subcategory":"Repair Shop",
            "type":"Services"
        }
    ],
    "sg:phone":"+1 412 653 9550",
    "sg:postcode":"15236",
    "sg:province":"PA",
    "sg:tags":[
        "refinishing",
        "furniture"
    ],
    "wof:name":"Danyo Furniture Svc",
    "wof:placetype":"venue"
},
  "geometry": {"coordinates":[-79.984583,40.336775],"type":"Point"}
}