{
  "type": "Feature",
  "properties": {
    "iso:country":"US",
    "sg:address":"28 3rd St",
    "sg:city":"Akron",
    "sg:classifiers":[
        {
            "category":"Building & Trades",
            "subcategory":"Construction",
            "type":"Services"
        }
    ],
    "sg:phone":"+1   ",
    "sg:postcode":"17501",
    "sg:province":"PA",
    "sg:tags":[
        "house"
    ],
    "wof:name":"Rickenbach Homes Inc",
    "wof:placetype":"venue"
},
  "geometry": {"coordinates":[-76.21148599999999,40.159191],"type":"Point"}
}