{
  "type": "Feature",
  "properties": {
    "addr:full":"2100 Pumping Station Rd Fairfield PA 17320",
    "addr:housenumber":"2100",
    "addr:postcode":"17320",
    "addr:street":"Pumping Station Rd",
    "iso:country":"US",
    "sg:address":"2100 Pumping Station Rd",
    "sg:city":"Fairfield",
    "sg:classifiers":[
        {
            "category":"Communications",
            "subcategory":"Radio Station",
            "type":"Services"
        }
    ],
    "sg:phone":"+1   ",
    "sg:postcode":"17320",
    "sg:province":"PA",
    "sg:tags":[
        "broadcast"
    ],
    "wof:name":"F M Williams Inc",
    "wof:placetype":"venue"
},
  "geometry": {"coordinates":[-77.313158,39.765795],"type":"Point"}
}