{
  "type": "Feature",
  "properties": {
    "iso:country":"US",
    "sg:address":"10 Clearfield Avenue",
    "sg:city":"Trooper",
    "sg:classifiers":[
        {
            "category":"Health Services",
            "subcategory":"Optometrist",
            "type":"Services"
        }
    ],
    "sg:phone":"+1 610 631 1142",
    "sg:postcode":"19403",
    "sg:province":"PA",
    "sg:website":"www.burrellfamilyeyecare.com/",
    "wof:name":"John J. Burrell Jr, OD",
    "wof:placetype":"venue"
},
  "geometry": {"coordinates":[-75.392242,40.143261],"type":"Point"}
}