{
  "type": "Feature",
  "properties": {
    "addr:full":"667 Winding Rd Orangeville PA 17859",
    "addr:housenumber":"667",
    "addr:postcode":"17859",
    "addr:street":"Winding Rd",
    "iso:country":"US",
    "sg:address":"667 Winding Rd",
    "sg:city":"Orangeville",
    "sg:classifiers":[
        {
            "category":"Organizations",
            "subcategory":"Religious Organization",
            "type":"Services"
        }
    ],
    "sg:phone":"+1 570 864 3606",
    "sg:postcode":"17859",
    "sg:province":"PA",
    "sg:tags":[
        "church"
    ],
    "wof:name":"Zion United Church Of Christ",
    "wof:placetype":"venue"
},
  "geometry": {"coordinates":[-76.310548,41.127755],"type":"Point"}
}