{
  "type": "Feature",
  "properties": {
    "addr:full":"920 N Chester Rd West Chester PA 19380",
    "addr:housenumber":"920",
    "addr:postcode":"19380",
    "addr:street":"N Chester Rd",
    "iso:country":"US",
    "sg:address":"920 N Chester Rd",
    "sg:city":"West Chester",
    "sg:classifiers":[
        {
            "category":"Retail",
            "subcategory":"Laundry & Dry Cleaning",
            "type":"Services"
        }
    ],
    "sg:phone":"+1 610 692 5295",
    "sg:postcode":"19380",
    "sg:province":"PA",
    "sg:tags":[
        "cleaners",
        "rug",
        "carpet"
    ],
    "wof:name":"Quality Cleaning Svc",
    "wof:placetype":"venue"
},
  "geometry": {"coordinates":[-75.545418,39.997299],"type":"Point"}
}