{
  "type": "Feature",
  "properties": {
    "addr:full":"83 Cedar Manor Elizabethtown PA 17022",
    "addr:housenumber":"83",
    "addr:postcode":"17022",
    "addr:street":"Cedar Manor",
    "iso:country":"US",
    "sg:address":"83 Cedar Manor",
    "sg:city":"Elizabethtown",
    "sg:classifiers":[
        {
            "category":"Building & Trades",
            "subcategory":"Cleaning & Sanitation",
            "type":"Services"
        }
    ],
    "sg:phone":"+1 717 367 6202",
    "sg:postcode":"17022",
    "sg:province":"PA",
    "sg:tags":[
        "maintenance"
    ],
    "wof:name":"Beaver Window Cleaning",
    "wof:placetype":"venue"
},
  "geometry": {"coordinates":[-76.649316,40.173371],"type":"Point"}
}