{
  "type": "Feature",
  "properties": {
    "iso:country":"US",
    "sg:address":"903 E Lincoln Hwy",
    "sg:city":"Exton",
    "sg:classifiers":[
        {
            "category":"Professional",
            "subcategory":"Detective & Security Services",
            "type":"Services"
        }
    ],
    "sg:phone":"+1 610 280 3840",
    "sg:postcode":"19341",
    "sg:province":"PA",
    "sg:tags":[
        "information",
        "bureau"
    ],
    "wof:name":"Spanpro Services Group",
    "wof:placetype":"venue"
},
  "geometry": {"coordinates":[-75.595984,40.031634],"type":"Point"}
}