{
  "type": "Feature",
  "properties": {
    "addr:full":"5 Evergreen Ave Warminster PA 18974",
    "addr:housenumber":"5",
    "addr:postcode":"18974",
    "addr:street":"Evergreen Ave",
    "iso:country":"US",
    "sg:address":"5 Evergreen Ave",
    "sg:city":"Warminster",
    "sg:classifiers":[
        {
            "category":"Recreation",
            "type":"Entertainment"
        }
    ],
    "sg:phone":"+1 215 674 3940",
    "sg:postcode":"18974",
    "sg:province":"PA",
    "sg:tags":[
        "instruction",
        "yoga"
    ],
    "wof:name":"My Yoga Room",
    "wof:placetype":"venue"
},
  "geometry": {"coordinates":[-75.10164899999999,40.190573],"type":"Point"}
}