{
  "type": "Feature",
  "properties": {
    "addr:full":"1128 Greenwood Rd Stroudsburg PA 18360",
    "addr:housenumber":"1128",
    "addr:postcode":"18360",
    "addr:street":"Greenwood Rd",
    "iso:country":"US",
    "sg:address":"1128 Greenwood Rd",
    "sg:city":"Stroudsburg",
    "sg:classifiers":[
        {
            "category":"Building & Trades",
            "subcategory":"Construction",
            "type":"Services"
        }
    ],
    "sg:phone":"+1 570 420 0650",
    "sg:postcode":"18360",
    "sg:province":"PA",
    "sg:tags":[
        "home",
        "improvement"
    ],
    "wof:name":"Northgate Construction Inc",
    "wof:placetype":"venue"
},
  "geometry": {"coordinates":[-75.204224,40.989547],"type":"Point"}
}