{
  "type": "Feature",
  "properties": {
    "iso:country":"US",
    "sg:address":"2250 Neshaminy Blvd",
    "sg:city":"Bensalem",
    "sg:classifiers":[
        {
            "category":"Shopping",
            "subcategory":"Pharmacy",
            "type":"Retail Goods"
        }
    ],
    "sg:phone":"+1 215 757 5200",
    "sg:postcode":"19020",
    "sg:province":"PA",
    "wof:name":"CVS Pharmacy",
    "wof:placetype":"venue"
},
  "geometry": {"coordinates":[-74.92503000000001,40.13323],"type":"Point"}
}