{
  "type": "Feature",
  "properties": {
    "addr:full":"1706 Painters Run Rd Pittsburgh PA 15241",
    "addr:housenumber":"1706",
    "addr:postcode":"15241",
    "addr:street":"Painters Run Rd",
    "iso:country":"US",
    "sg:address":"1706 Painters Run Rd",
    "sg:city":"Pittsburgh",
    "sg:classifiers":[
        {
            "category":"Building & Trades",
            "subcategory":"Plumbing",
            "type":"Services"
        }
    ],
    "sg:phone":"+1   ",
    "sg:postcode":"15241",
    "sg:province":"PA",
    "sg:tags":[
        "plumbing",
        "heating",
        "contractor"
    ],
    "wof:name":"Dan Vanzin Plumbing & Heating",
    "wof:placetype":"venue"
},
  "geometry": {"coordinates":[-80.0744,40.358938],"type":"Point"}
}