{
  "type": "Feature",
  "properties": {
    "iso:country":"US",
    "sg:address":"50 Grant Ave",
    "sg:city":"Pittsburgh",
    "sg:classifiers":[
        {
            "category":"Retail",
            "subcategory":"Repair Shop",
            "type":"Services"
        }
    ],
    "sg:phone":"+1   ",
    "sg:postcode":"15223",
    "sg:province":"PA",
    "sg:tags":[
        "furniture"
    ],
    "wof:name":"Nock On Wood Upholstery",
    "wof:placetype":"venue"
},
  "geometry": {"coordinates":[-79.94910299999999,40.504121],"type":"Point"}
}