{
  "type": "Feature",
  "properties": {
    "addr:full":"407 Lincoln Hwy Exton PA 19320",
    "addr:housenumber":"407",
    "addr:postcode":"19320",
    "addr:street":"Lincoln Hwy",
    "iso:country":"US",
    "sg:address":"407 Lincoln Hwy",
    "sg:city":"Exton",
    "sg:classifiers":[
        {
            "category":"Health Services",
            "subcategory":"Optometrist",
            "type":"Services"
        }
    ],
    "sg:phone":"+1   ",
    "sg:postcode":"19320",
    "sg:province":"PA",
    "wof:name":"Robert Kuczynski Od",
    "wof:placetype":"venue"
},
  "geometry": {"coordinates":[-75.833268,39.980732],"type":"Point"}
}