{
  "type": "Feature",
  "properties": {
    "iso:country":"US",
    "sg:address":"2515 N 11th St",
    "sg:city":"Philadelphia",
    "sg:classifiers":[
        {
            "category":"Home & Garden",
            "subcategory":"Hardware",
            "type":"Retail Goods"
        },
        {
            "category":"Utilities",
            "subcategory":"Cable",
            "type":"Services"
        }
    ],
    "sg:phone":"+1 215 221 6321",
    "sg:postcode":"19133",
    "sg:province":"PA",
    "sg:tags":[
        "cable-non-electric",
        "wire",
        "cable-electric"
    ],
    "wof:name":"Neotech Power And Signal",
    "wof:placetype":"venue"
},
  "geometry": {"coordinates":[-75.14986,39.990392],"type":"Point"}
}