{
  "type": "Feature",
  "properties": {
    "addr:full":"7105 Reynolds St Pittsburgh PA 15208",
    "addr:housenumber":"7105",
    "addr:postcode":"15208",
    "addr:street":"Reynolds St",
    "iso:country":"US",
    "sg:address":"7105 Reynolds St",
    "sg:city":"Pittsburgh",
    "sg:classifiers":[
        {
            "category":"Personal",
            "subcategory":"Barber",
            "type":"Services"
        }
    ],
    "sg:phone":"+1 412 243 0212",
    "sg:postcode":"15208",
    "sg:province":"PA",
    "sg:website":"http://www.thebarbershop.com",
    "wof:name":"Joe's Barber Shop",
    "wof:placetype":"venue"
},
  "geometry": {"coordinates":[-79.905238,40.447127],"type":"Point"}
}