{
  "type": "Feature",
  "properties": {
    "addr:full":"1915 Kennedy Blvd Aliquippa PA 15001",
    "addr:housenumber":"1915",
    "addr:postcode":"15001",
    "addr:street":"Kennedy Blvd",
    "iso:country":"US",
    "sg:address":"1915 Kennedy Blvd",
    "sg:city":"Aliquippa",
    "sg:classifiers":[
        {
            "category":"Professional",
            "subcategory":"Lawyer & Legal Services",
            "type":"Services"
        }
    ],
    "sg:phone":"+1 724 846 7200",
    "sg:postcode":"15001",
    "sg:province":"PA",
    "sg:tags":[
        "attorney"
    ],
    "wof:name":"Stephen M Otto Law Ofc",
    "wof:placetype":"venue"
},
  "geometry": {"coordinates":[-80.274029,40.609263],"type":"Point"}
}