{
  "type": "Feature",
  "properties": {
    "addr:full":"6835 Ridge Ave Philadelphia PA 19128",
    "addr:housenumber":"6835",
    "addr:postcode":"19128",
    "addr:street":"Ridge Ave",
    "iso:country":"US",
    "sg:address":"6835 Ridge Ave",
    "sg:city":"Philadelphia",
    "sg:classifiers":[
        {
            "category":"Retail",
            "subcategory":"Funeral Services",
            "type":"Services"
        }
    ],
    "sg:phone":"+1 215 482 5200",
    "sg:postcode":"19128",
    "sg:province":"PA",
    "wof:name":"Koller Funeral Home Inc",
    "wof:placetype":"venue"
},
  "geometry": {"coordinates":[-75.227075,40.042986],"type":"Point"}
}