{
  "type": "Feature",
  "properties": {
    "iso:country":"US",
    "sg:address":"748 Quaker Valley Rd",
    "sg:city":"New Paris",
    "sg:classifiers":[
        {
            "category":"Social Services",
            "subcategory":"Child Care",
            "type":"Services"
        }
    ],
    "sg:phone":"+1 814 839 4536",
    "sg:postcode":"15554",
    "sg:province":"PA",
    "sg:tags":[
        "kindergarten",
        "academic",
        "school"
    ],
    "wof:name":"Noah's Ark Preschool",
    "wof:placetype":"venue"
},
  "geometry": {"coordinates":[-78.548284,40.103891],"type":"Point"}
}