{
  "type": "Feature",
  "properties": {
    "addr:full":"517 Twin Oak Dr Pittsburgh PA 15235",
    "addr:housenumber":"517",
    "addr:postcode":"15235",
    "addr:street":"Twin Oak Dr",
    "iso:country":"US",
    "sg:address":"517 Twin Oak Dr",
    "sg:city":"Pittsburgh",
    "sg:classifiers":[
        {
            "category":"Recreation",
            "type":"Entertainment"
        }
    ],
    "sg:phone":"+1   ",
    "sg:postcode":"15235",
    "sg:province":"PA",
    "wof:name":"Penn Hills Deckhockey Center",
    "wof:placetype":"venue"
},
  "geometry": {"coordinates":[-79.786518,40.477932],"type":"Point"}
}