{
  "type": "Feature",
  "properties": {
    "addr:full":"4221 Lincoln Hwy Parkesburg PA 19365",
    "addr:housenumber":"4221",
    "addr:postcode":"19365",
    "addr:street":"Lincoln Hwy",
    "iso:country":"US",
    "sg:address":"4221 Lincoln Hwy",
    "sg:city":"Parkesburg",
    "sg:classifiers":[
        {
            "category":"Wholesale",
            "subcategory":"Construction Materials",
            "type":"Manufacturing & Wholesale Goods"
        }
    ],
    "sg:phone":"+1   ",
    "sg:postcode":"19365",
    "sg:province":"PA",
    "wof:name":"International Mill Service",
    "wof:placetype":"venue"
},
  "geometry": {"coordinates":[-75.944671,39.984844],"type":"Point"}
}