{
  "type": "Feature",
  "properties": {
    "iso:country":"US",
    "sg:address":"1529 Luzerne St",
    "sg:city":"Reading",
    "sg:classifiers":[
        {
            "category":"Retail",
            "subcategory":"Repair Shop",
            "type":"Services"
        }
    ],
    "sg:phone":"+1 610 376 2080",
    "sg:postcode":"19601",
    "sg:province":"PA",
    "sg:tags":[
        "refrigeration"
    ],
    "wof:name":"Superior Dispensing Systems",
    "wof:placetype":"venue"
},
  "geometry": {"coordinates":[-75.951876,40.357916],"type":"Point"}
}