{
  "type": "Feature",
  "properties": {
    "iso:country":"US",
    "sg:address":"856 Parkside Ave",
    "sg:city":"West Chester",
    "sg:classifiers":[
        {
            "category":"Professional",
            "subcategory":"Computer Services",
            "type":"Services"
        }
    ],
    "sg:phone":"+1 610 344 0646",
    "sg:postcode":"19382",
    "sg:province":"PA",
    "sg:tags":[
        "repair"
    ],
    "sg:website":"www.ctwestchester.com",
    "wof:name":"Computer Troubleshooters",
    "wof:placetype":"venue"
},
  "geometry": {"coordinates":[-75.59486699999999,39.945834],"type":"Point"}
}