{
  "type": "Feature",
  "properties": {
    "addr:full":"375 Southpointe Blvd # 220 Canonsburg PA 15317",
    "addr:housenumber":"375",
    "addr:postcode":"15317",
    "addr:street":"Southpointe Blvd # 220",
    "iso:country":"US",
    "sg:address":"375 Southpointe Blvd # 220",
    "sg:city":"Canonsburg",
    "sg:classifiers":[
        {
            "category":"Professional",
            "subcategory":"Management & Consulting",
            "type":"Services"
        }
    ],
    "sg:phone":"+1 724 942 9393",
    "sg:postcode":"15317",
    "sg:province":"PA",
    "sg:tags":[
        "consultant"
    ],
    "wof:name":"Jl Associates",
    "wof:placetype":"venue"
},
  "geometry": {"coordinates":[-80.174368,40.293586],"type":"Point"}
}