{
  "type": "Feature",
  "properties": {
    "iso:country":"US",
    "sg:address":"118 S Center Ave",
    "sg:city":"Somerset",
    "sg:classifiers":[
        {
            "category":"Government",
            "subcategory":"Office",
            "type":"Public Place"
        }
    ],
    "sg:phone":"+1 814 445 7675",
    "sg:postcode":"15501",
    "sg:province":"PA",
    "wof:name":"Senator Richard A Kasunic",
    "wof:placetype":"venue"
},
  "geometry": {"coordinates":[-79.078715,40.00828],"type":"Point"}
}