{
  "type": "Feature",
  "properties": {
    "addr:full":"2817 S Eagle Rd Newtown PA 18940",
    "addr:housenumber":"2817",
    "addr:postcode":"18940",
    "addr:street":"S Eagle Rd",
    "iso:country":"US",
    "sg:address":"2817 S Eagle Rd",
    "sg:city":"Newtown",
    "sg:classifiers":[
        {
            "category":"Restaurant",
            "type":"Food & Drink"
        }
    ],
    "sg:phone":"+1 215 860 5511",
    "sg:postcode":"18940",
    "sg:province":"PA",
    "sg:website":"http://www.eatoishi.com",
    "wof:name":"Oishi Japanese Thai & Korean",
    "wof:placetype":"venue"
},
  "geometry": {"coordinates":[-74.940853,40.234276],"type":"Point"}
}