{
  "type": "Feature",
  "properties": {
    "addr:full":"2100 Whitaker Way Homestead PA 15120",
    "addr:housenumber":"2100",
    "addr:postcode":"15120",
    "addr:street":"Whitaker Way",
    "iso:country":"US",
    "sg:address":"2100 Whitaker Way",
    "sg:city":"Homestead",
    "sg:classifiers":[
        {
            "category":"Building & Trades",
            "subcategory":"Plumbing",
            "type":"Services"
        }
    ],
    "sg:phone":"+1   ",
    "sg:postcode":"15120",
    "sg:province":"PA",
    "sg:tags":[
        "contractor"
    ],
    "wof:name":"Lesko Plumbing & Heating",
    "wof:placetype":"venue"
},
  "geometry": {"coordinates":[-79.888379,40.401686],"type":"Point"}
}