{
  "type": "Feature",
  "properties": {
    "addr:full":"155 Phillips Park Dr Williamsport PA 17702",
    "addr:housenumber":"155",
    "addr:postcode":"17702",
    "addr:street":"Phillips Park Dr",
    "iso:country":"US",
    "sg:address":"155 Phillips Park Dr",
    "sg:city":"Williamsport",
    "sg:classifiers":[
        {
            "category":"Recreation",
            "type":"Entertainment"
        }
    ],
    "sg:phone":"+1 570 323 9630",
    "sg:postcode":"17702",
    "sg:province":"PA",
    "sg:tags":[
        "martial",
        "arts",
        "instruction"
    ],
    "wof:name":"Shido Seimei Martial Arts",
    "wof:placetype":"venue"
},
  "geometry": {"coordinates":[-77.01597099999999,41.227325],"type":"Point"}
}