{
  "type": "Feature",
  "properties": {
    "iso:country":"US",
    "sg:address":"2500 Market St",
    "sg:city":"Harrisburg",
    "sg:classifiers":[
        {
            "category":"Real Estate",
            "subcategory":"Developer",
            "type":"Services"
        }
    ],
    "sg:phone":"+1   ",
    "sg:postcode":"17103",
    "sg:province":"PA",
    "sg:tags":[
        "cemetery"
    ],
    "wof:name":"Prospect Hills Cemetery",
    "wof:placetype":"venue"
},
  "geometry": {"coordinates":[-76.846009,40.272963],"type":"Point"}
}