{
  "type": "Feature",
  "properties": {
    "iso:country":"US",
    "sg:address":"703 Lewisville Rd",
    "sg:city":"Oxford",
    "sg:classifiers":[
        {
            "category":"Farming",
            "subcategory":"Farm",
            "type":"Manufacturing & Wholesale Goods"
        }
    ],
    "sg:phone":"+1 610 932 3630",
    "sg:postcode":"19363",
    "sg:province":"PA",
    "sg:tags":[
        "crop",
        "general"
    ],
    "wof:name":"Farm HSC",
    "wof:placetype":"venue"
},
  "geometry": {"coordinates":[-75.907274,39.745253],"type":"Point"}
}