{
  "type": "Feature",
  "properties": {
    "iso:country":"US",
    "sg:address":"615 Pembroke Rd",
    "sg:city":"Bryn Mawr",
    "sg:classifiers":[
        {
            "category":"Professional",
            "type":"Services"
        }
    ],
    "sg:phone":"+1   ",
    "sg:postcode":"19010",
    "sg:province":"PA",
    "wof:name":"B Wilford Fell",
    "wof:placetype":"venue"
},
  "geometry": {"coordinates":[-75.30616000000001,40.024962],"type":"Point"}
}