{
  "type": "Feature",
  "properties": {
    "iso:country":"US",
    "sg:address":"114 Fairview Rd",
    "sg:city":"Lewisburg",
    "sg:classifiers":[
        {
            "category":"Building & Trades",
            "subcategory":"Construction",
            "type":"Services"
        }
    ],
    "sg:phone":"+1 570 524 0615",
    "sg:postcode":"17837",
    "sg:province":"PA",
    "sg:tags":[
        "home",
        "builder"
    ],
    "wof:name":"G & S Home Products",
    "wof:placetype":"venue"
},
  "geometry": {"coordinates":[-76.87461,40.934037],"type":"Point"}
}