{
  "type": "Feature",
  "properties": {
    "iso:country":"US",
    "sg:address":"1530 Pittsburgh Rd",
    "sg:city":"Franklin",
    "sg:classifiers":[
        {
            "category":"Organizations",
            "subcategory":"Religious Organization",
            "type":"Services"
        }
    ],
    "sg:phone":"+1 814 437 3435",
    "sg:postcode":"16323",
    "sg:province":"PA",
    "sg:tags":[
        "church"
    ],
    "wof:name":"Franklin Assembly",
    "wof:placetype":"venue"
},
  "geometry": {"coordinates":[-79.86312100000001,41.3659],"type":"Point"}
}