{
  "type": "Feature",
  "properties": {
    "addr:full":"1218 Chestnut St Ste 607 Philadelphia PA 19107",
    "addr:housenumber":"1218",
    "addr:postcode":"19107",
    "addr:street":"Chestnut St Ste 607",
    "iso:country":"US",
    "sg:address":"1218 Chestnut St Ste 607",
    "sg:city":"Philadelphia",
    "sg:classifiers":[
        {
            "category":"Health Services",
            "subcategory":"Clinic",
            "type":"Services"
        }
    ],
    "sg:phone":"+1 215 625 9655",
    "sg:postcode":"19107",
    "sg:province":"PA",
    "sg:tags":[
        "counseling",
        "mental"
    ],
    "wof:name":"Lowey Robin PHD & Assoc",
    "wof:placetype":"venue"
},
  "geometry": {"coordinates":[-75.1605,39.9505],"type":"Point"}
}