{
  "type": "Feature",
  "properties": {
    "iso:country":"US",
    "sg:address":"1290 Blakeslee Boulevard Dr W",
    "sg:city":"Lehighton",
    "sg:classifiers":[
        {
            "category":"Building & Trades",
            "subcategory":"Construction",
            "type":"Services"
        }
    ],
    "sg:phone":"+1 570 386 3309",
    "sg:postcode":"18235",
    "sg:province":"PA",
    "sg:tags":[
        "general",
        "contractor"
    ],
    "wof:name":"Blue Mountain Home Builders",
    "wof:placetype":"venue"
},
  "geometry": {"coordinates":[-75.794528,40.790711],"type":"Point"}
}