{
  "type": "Feature",
  "properties": {
    "iso:country":"US",
    "sg:address":"321 Clay Ave",
    "sg:city":"Mars",
    "sg:classifiers":[
        {
            "category":"Health Services",
            "subcategory":"Chiropractor",
            "type":"Services"
        }
    ],
    "sg:phone":"+1 724 625 3390",
    "sg:postcode":"16046",
    "sg:province":"PA",
    "wof:name":"Bettermann Chiropractic Center",
    "wof:placetype":"venue"
},
  "geometry": {"coordinates":[-80.041496,40.681702],"type":"Point"}
}