{
  "type": "Feature",
  "properties": {
    "addr:full":"24 W King St York PA 17401",
    "addr:housenumber":"24",
    "addr:postcode":"17401",
    "addr:street":"W King St",
    "iso:country":"US",
    "sg:address":"24 W King St",
    "sg:city":"York",
    "sg:classifiers":[
        {
            "category":"Insurance",
            "subcategory":"Insurance Agent",
            "type":"Services"
        }
    ],
    "sg:phone":"+1 717 848 1641",
    "sg:postcode":"17401",
    "sg:province":"PA",
    "wof:name":"Yorco Agency Inc",
    "wof:placetype":"venue"
},
  "geometry": {"coordinates":[-76.727104,39.96095],"type":"Point"}
}