{
  "type": "Feature",
  "properties": {
    "iso:country":"US",
    "sg:address":"70 E Swedesford Rd",
    "sg:city":"Malvern",
    "sg:classifiers":[
        {
            "category":"Home & Garden",
            "subcategory":"Building Materials",
            "type":"Retail Goods"
        }
    ],
    "sg:phone":"+1   ",
    "sg:postcode":"19355",
    "sg:province":"PA",
    "sg:tags":[
        "classroom",
        "modular",
        "commercial",
        "build",
        "space"
    ],
    "wof:name":"Vanguard Modular Building",
    "wof:placetype":"venue"
},
  "geometry": {"coordinates":[-75.517259,40.056045],"type":"Point"}
}