{
  "type": "Feature",
  "properties": {
    "addr:full":"917-921 Arch St Philadelphia PA 19107",
    "addr:housenumber":"917-921",
    "addr:postcode":"19107",
    "addr:street":"Arch St",
    "iso:country":"US",
    "sg:address":"917-921 Arch St",
    "sg:city":"Philadelphia",
    "sg:classifiers":[
        {
            "category":"Food & Beverages",
            "subcategory":"Groceries & Convenience Stores",
            "type":"Retail Goods"
        }
    ],
    "sg:phone":"+1 215 925 0198",
    "sg:postcode":"19107",
    "sg:province":"PA",
    "wof:name":"Wan Sheng Supermarket",
    "wof:placetype":"venue"
},
  "geometry": {"coordinates":[-75.15545,39.953453],"type":"Point"}
}