{
  "type": "Feature",
  "properties": {
    "iso:country":"US",
    "sg:address":"6 W 4th St",
    "sg:city":"Emporium",
    "sg:classifiers":[
        {
            "category":"Manufacturing",
            "subcategory":"Printing",
            "type":"Manufacturing & Wholesale Goods"
        }
    ],
    "sg:phone":"+1 814 486 1400",
    "sg:postcode":"15834",
    "sg:province":"PA",
    "sg:tags":[
        "newspaper"
    ],
    "wof:name":"Endeavor Media",
    "wof:placetype":"venue"
},
  "geometry": {"coordinates":[-78.2379,41.511595],"type":"Point"}
}