{
  "type": "Feature",
  "properties": {
    "iso:country":"US",
    "sg:address":"775 Eisenhower Rd",
    "sg:city":"Palmyra",
    "sg:classifiers":[
        {
            "category":"Freight",
            "type":"Transportation"
        }
    ],
    "sg:phone":"+1   ",
    "sg:postcode":"17078",
    "sg:province":"PA",
    "sg:tags":[
        "special"
    ],
    "wof:name":"Convenient Self Storage",
    "wof:placetype":"venue"
},
  "geometry": {"coordinates":[-76.613839,40.344506],"type":"Point"}
}