{
  "type": "Feature",
  "properties": {
    "iso:country":"US",
    "sg:address":"5 Ski Run Trl",
    "sg:city":"Fairfield",
    "sg:classifiers":[
        {
            "category":"Building & Trades",
            "subcategory":"Construction",
            "type":"Services"
        }
    ],
    "sg:phone":"+1   ",
    "sg:postcode":"17320",
    "sg:province":"PA",
    "sg:tags":[
        "builder",
        "operative"
    ],
    "wof:name":"T L S Construction",
    "wof:placetype":"venue"
},
  "geometry": {"coordinates":[-77.380807,39.771263],"type":"Point"}
}