{
  "type": "Feature",
  "properties": {
    "iso:country":"US",
    "sg:address":"140 W Eagle Rd",
    "sg:city":"Havertown",
    "sg:classifiers":[
        {
            "category":"Personal",
            "subcategory":"Beauty Salon",
            "type":"Services"
        }
    ],
    "sg:phone":"+1 610 446 5030",
    "sg:postcode":"19083",
    "sg:province":"PA",
    "sg:tags":[
        "shop"
    ],
    "wof:name":"Imagine LTD",
    "wof:placetype":"venue"
},
  "geometry": {"coordinates":[-75.314767,39.985384],"type":"Point"}
}