{
  "type": "Feature",
  "properties": {
    "iso:country":"US",
    "sg:address":"21 Donaldson St",
    "sg:city":"Doylestown",
    "sg:classifiers":[
        {
            "category":"Place Of Worship",
            "subcategory":"Church",
            "type":"Public Place"
        },
        {
            "category":"Place Of Worship",
            "type":"Public Place"
        },
        {
            "category":"Community Center",
            "type":"Public Place"
        },
        {
            "category":"Organizations",
            "subcategory":"Religious Organization",
            "type":"Services"
        }
    ],
    "sg:phone":"+1 215 348 2253",
    "sg:postcode":"18901",
    "sg:province":"PA",
    "sg:tags":[
        "christian",
        "room",
        "science",
        "churches-religious",
        "reading",
        "churches-christian"
    ],
    "wof:name":"Christian Science Reading Room",
    "wof:placetype":"venue"
},
  "geometry": {"coordinates":[-75.12906599999999,40.309669],"type":"Point"}
}