{
  "type": "Feature",
  "properties": {
    "iso:country":"US",
    "sg:address":"2915 Leechburg Rd",
    "sg:city":"New Kensington",
    "sg:classifiers":[
        {
            "category":"Health Services",
            "subcategory":"Doctor",
            "type":"Services"
        }
    ],
    "sg:phone":"+1 724 335 1330",
    "sg:postcode":"15068",
    "sg:province":"PA",
    "wof:name":"Rudy J Mattioli DDS",
    "wof:placetype":"venue"
},
  "geometry": {"coordinates":[-79.723761,40.589224],"type":"Point"}
}