{
  "type": "Feature",
  "properties": {
    "addr:full":"701 Bloserville Rd Newville PA 17241",
    "addr:housenumber":"701",
    "addr:postcode":"17241",
    "addr:street":"Bloserville Rd",
    "iso:country":"US",
    "sg:address":"701 Bloserville Rd",
    "sg:city":"Newville",
    "sg:classifiers":[
        {
            "category":"Freight",
            "type":"Transportation"
        }
    ],
    "sg:phone":"+1 717 776 3733",
    "sg:postcode":"17241",
    "sg:province":"PA",
    "sg:tags":[
        "commercial",
        "storage"
    ],
    "wof:name":"Bloserville Storage",
    "wof:placetype":"venue"
},
  "geometry": {"coordinates":[-77.362793,40.234293],"type":"Point"}
}