{
  "type": "Feature",
  "properties": {
    "iso:country":"US",
    "sg:address":"104 Old Cabin Hollow Rd",
    "sg:city":"Dillsburg",
    "sg:phone":"+1   ",
    "sg:postcode":"17019",
    "sg:province":"PA",
    "sg:tags":[
        "farm",
        "field",
        "crop"
    ],
    "wof:name":"Richard Arnold",
    "wof:placetype":"venue"
},
  "geometry": {"coordinates":[-77.03241199999999,40.077923],"type":"Point"}
}