{
  "type": "Feature",
  "properties": {
    "iso:country":"US",
    "sg:address":"4575 Torresdale Ave Suite 1A",
    "sg:city":"Philadelphia",
    "sg:classifiers":[
        {
            "category":"Autos & Motor Vehicles",
            "subcategory":"Automobile Sales",
            "type":"Retail Goods"
        },
        {
            "category":"Utilities",
            "subcategory":"Refuse",
            "type":"Services"
        },
        {
            "category":"Autos & Motor Vehicles",
            "subcategory":"Auto Supplies",
            "type":"Retail Goods"
        },
        {
            "category":"Utilities",
            "subcategory":"Recycling",
            "type":"Services"
        }
    ],
    "sg:phone":"+1 877 300 8993",
    "sg:postcode":"19124",
    "sg:province":"PA",
    "sg:tags":[
        "container",
        "rubbish",
        "garbage",
        "trucks-industrial-parts",
        "removal",
        "trucks-industrial",
        "collection",
        "dumpster",
        "trash"
    ],
    "sg:website":"http://www.americandisposalsystems.com/rolloff.html",
    "wof:name":"American Disposal Systems",
    "wof:placetype":"venue"
},
  "geometry": {"coordinates":[-75.080139,40.010049],"type":"Point"}
}