{
  "type": "Feature",
  "properties": {
    "iso:country":"US",
    "sg:address":"106 Elizabeth St",
    "sg:city":"Ellwood City",
    "sg:classifiers":[
        {
            "category":"Retail",
            "subcategory":"Auto Repair",
            "type":"Services"
        }
    ],
    "sg:phone":"+1 724 752 3711",
    "sg:postcode":"16115",
    "sg:province":"PA",
    "sg:tags":[
        "body"
    ],
    "sg:website":"www.signsbysam.com",
    "wof:name":"Signs By Sam",
    "wof:placetype":"venue"
},
  "geometry": {"coordinates":[-80.408486,40.81778],"type":"Point"}
}