{
  "type": "Feature",
  "properties": {
    "iso:country":"US",
    "sg:address":"130 Wabash St",
    "sg:city":"Pittsburgh",
    "sg:classifiers":[
        {
            "category":"Wholesale",
            "subcategory":"Durable Goods & Equipment",
            "type":"Manufacturing & Wholesale Goods"
        }
    ],
    "sg:phone":"+1 412 921 7700",
    "sg:postcode":"15220",
    "sg:province":"PA",
    "sg:tags":[
        "instrument",
        "mfr",
        "representative",
        "apparatus",
        "scientific"
    ],
    "wof:name":"Scientific Pittsburgh",
    "wof:placetype":"venue"
},
  "geometry": {"coordinates":[-80.03431,40.436463],"type":"Point"}
}