{
  "type": "Feature",
  "properties": {
    "addr:full":"1043 Irvin Rd Huntingdon Valley PA 19006",
    "addr:housenumber":"1043",
    "addr:postcode":"19006",
    "addr:street":"Irvin Rd",
    "iso:country":"US",
    "sg:address":"1043 Irvin Rd",
    "sg:city":"Huntingdon Valley",
    "sg:classifiers":[
        {
            "category":"Professional",
            "type":"Services"
        }
    ],
    "sg:phone":"+1   ",
    "sg:postcode":"19006",
    "sg:province":"PA",
    "wof:name":"M Holland Robin",
    "wof:placetype":"venue"
},
  "geometry": {"coordinates":[-75.08832099999999,40.09313],"type":"Point"}
}