{
  "type": "Feature",
  "properties": {
    "iso:country":"US",
    "sg:address":"441 Smithfield St",
    "sg:city":"Pittsburgh",
    "sg:classifiers":[
        {
            "category":"Government",
            "subcategory":"Office",
            "type":"Public Place"
        }
    ],
    "sg:phone":"+1 412 350 1026",
    "sg:postcode":"15222",
    "sg:province":"PA",
    "sg:tags":[
        "county",
        "program",
        "adm"
    ],
    "wof:name":"Economic Developement",
    "wof:placetype":"venue"
},
  "geometry": {"coordinates":[-79.999544,40.438725],"type":"Point"}
}