{
  "type": "Feature",
  "properties": {
    "addr:full":"2307 Reading Blvd Reading PA 19609",
    "addr:housenumber":"2307",
    "addr:postcode":"19609",
    "addr:street":"Reading Blvd",
    "iso:country":"US",
    "sg:address":"2307 Reading Blvd",
    "sg:city":"Reading",
    "sg:classifiers":[
        {
            "category":"Personal",
            "type":"Services"
        }
    ],
    "sg:phone":"+1 610 670 7340",
    "sg:postcode":"19609",
    "sg:province":"PA",
    "sg:tags":[
        "therapist",
        "massage"
    ],
    "wof:name":"New Life Massage Therapy",
    "wof:placetype":"venue"
},
  "geometry": {"coordinates":[-75.99379999999999,40.323281],"type":"Point"}
}