{
  "type": "Feature",
  "properties": {
    "iso:country":"US",
    "sg:address":"2405 N Front St",
    "sg:city":"Harrisburg",
    "sg:classifiers":[
        {
            "category":"Organizations",
            "subcategory":"Professional Association",
            "type":"Services"
        }
    ],
    "sg:phone":"+1   ",
    "sg:postcode":"17110",
    "sg:province":"PA",
    "sg:tags":[
        "business"
    ],
    "wof:name":"Pacb Foundation",
    "wof:placetype":"venue"
},
  "geometry": {"coordinates":[-76.902827,40.284336],"type":"Point"}
}