{
  "type": "Feature",
  "properties": {
    "addr:full":"2131 Northampton St Easton PA 18042",
    "addr:housenumber":"2131",
    "addr:postcode":"18042",
    "addr:street":"Northampton St",
    "iso:country":"US",
    "sg:address":"2131 Northampton St",
    "sg:city":"Easton",
    "sg:classifiers":[
        {
            "category":"Health Services",
            "subcategory":"Doctor",
            "type":"Services"
        }
    ],
    "sg:phone":"+1   ",
    "sg:postcode":"18042",
    "sg:province":"PA",
    "wof:name":"Enea DDS Pasqual J",
    "wof:placetype":"venue"
},
  "geometry": {"coordinates":[-75.248892,40.687898],"type":"Point"}
}