{
  "type": "Feature",
  "properties": {
    "iso:country":"US",
    "sg:address":"165 Brandt St",
    "sg:city":"Parkesburg",
    "sg:classifiers":[
        {
            "category":"Shopping",
            "subcategory":"Florist",
            "type":"Retail Goods"
        }
    ],
    "sg:phone":"+1 610 857 9290",
    "sg:postcode":"19365",
    "sg:province":"PA",
    "wof:name":"Polk's Country Flower Shop",
    "wof:placetype":"venue"
},
  "geometry": {"coordinates":[-75.91503,39.958493],"type":"Point"}
}