{
  "type": "Feature",
  "properties": {
    "iso:country":"US",
    "sg:address":"710 E Main St",
    "sg:city":"Norristown",
    "sg:classifiers":[
        {
            "category":"Wholesale",
            "subcategory":"Beer",
            "type":"Manufacturing & Wholesale Goods"
        }
    ],
    "sg:phone":"+1 610 275 0285",
    "sg:postcode":"19401",
    "sg:province":"PA",
    "sg:website":"www.gretzbeer.com",
    "wof:name":"Gretz Beer Co",
    "wof:placetype":"venue"
},
  "geometry": {"coordinates":[-75.32993,40.109224],"type":"Point"}
}