{
  "type": "Feature",
  "properties": {
    "iso:country":"US",
    "sg:address":"290 King of Prussia Rd",
    "sg:city":"Wayne",
    "sg:classifiers":[
        {
            "category":"Real Estate",
            "subcategory":"Real Estate Agent",
            "type":"Services"
        }
    ],
    "sg:phone":"+1   ",
    "sg:postcode":"19087",
    "sg:province":"PA",
    "wof:name":"Cox Vernon D Jr",
    "wof:placetype":"venue"
},
  "geometry": {"coordinates":[-75.359582,40.044086],"type":"Point"}
}