{
  "type": "Feature",
  "properties": {
    "iso:country":"US",
    "sg:address":"1401 Lake Rd",
    "sg:city":"Mercer",
    "sg:classifiers":[
        {
            "category":"Manufacturing",
            "subcategory":"Metals",
            "type":"Manufacturing & Wholesale Goods"
        }
    ],
    "sg:phone":"+1   ",
    "sg:postcode":"16137",
    "sg:province":"PA",
    "sg:tags":[
        "dock",
        "aluminum",
        "boat",
        "mfg"
    ],
    "wof:name":"Combustion Consultants",
    "wof:placetype":"venue"
},
  "geometry": {"coordinates":[-80.297822,41.262772],"type":"Point"}
}