{
  "type": "Feature",
  "properties": {
    "addr:full":"822 Richmont St Scranton PA 18509",
    "addr:housenumber":"822",
    "addr:postcode":"18509",
    "addr:street":"Richmont St",
    "iso:country":"US",
    "sg:address":"822 Richmont St",
    "sg:city":"Scranton",
    "sg:classifiers":[
        {
            "category":"Communications",
            "subcategory":"Film & Video Production",
            "type":"Services"
        }
    ],
    "sg:phone":"+1   ",
    "sg:postcode":"18509",
    "sg:province":"PA",
    "sg:tags":[
        "motion",
        "se"
    ],
    "wof:name":"Quasar Video",
    "wof:placetype":"venue"
},
  "geometry": {"coordinates":[-75.644769,41.43316],"type":"Point"}
}