{
  "type": "Feature",
  "properties": {
    "iso:country":"US",
    "sg:address":"2711 Lisburn Rd",
    "sg:city":"Camp Hill",
    "sg:classifiers":[
        {
            "category":"Wholesale",
            "subcategory":"Machinery & Supplies",
            "type":"Manufacturing & Wholesale Goods"
        }
    ],
    "sg:phone":"+1 717 737 7672",
    "sg:postcode":"17011",
    "sg:province":"PA",
    "sg:tags":[
        "compressor",
        "gas"
    ],
    "wof:name":"Air Equipment Co",
    "wof:placetype":"venue"
},
  "geometry": {"coordinates":[-76.93464400000001,40.207589],"type":"Point"}
}