{
  "type": "Feature",
  "properties": {
    "addr:full":"5 Village Row New Hope PA 18938",
    "addr:housenumber":"5",
    "addr:postcode":"18938",
    "addr:street":"Village Row New",
    "iso:country":"US",
    "sg:address":"5 Village Row",
    "sg:city":"New Hope",
    "sg:classifiers":[
        {
            "category":"Personal",
            "subcategory":"Beauty Salon",
            "type":"Services"
        }
    ],
    "sg:phone":"+1 215 862 6770",
    "sg:postcode":"18938",
    "sg:province":"PA",
    "sg:tags":[
        "shop"
    ],
    "wof:name":"Aahs Salon",
    "wof:placetype":"venue"
},
  "geometry": {"coordinates":[-74.975872,40.357398],"type":"Point"}
}