{
  "type": "Feature",
  "properties": {
    "addr:full":"1227 Old Concord Rd Monroeville PA 15146",
    "addr:housenumber":"1227",
    "addr:postcode":"15146",
    "addr:street":"Old Concord Rd",
    "iso:country":"US",
    "sg:address":"1227 Old Concord Rd",
    "sg:city":"Monroeville",
    "sg:classifiers":[
        {
            "category":"Education",
            "subcategory":"Dance Studio",
            "type":"Public Place"
        }
    ],
    "sg:phone":"+1 412 373 8850",
    "sg:postcode":"15146",
    "sg:province":"PA",
    "sg:tags":[
        "instruction",
        "dancing"
    ],
    "wof:name":"Walker East Side Acad-Ballet",
    "wof:placetype":"venue"
},
  "geometry": {"coordinates":[-79.74898399999999,40.413479],"type":"Point"}
}