{
  "type": "Feature",
  "properties": {
    "iso:country":"US",
    "sg:address":"310 Depot St",
    "sg:city":"Youngwood",
    "sg:classifiers":[
        {
            "category":"Personal",
            "subcategory":"Barber",
            "type":"Services"
        }
    ],
    "sg:phone":"+1 724 925 8334",
    "sg:postcode":"15697",
    "sg:province":"PA",
    "wof:name":"Luther Koring Barbershop",
    "wof:placetype":"venue"
},
  "geometry": {"coordinates":[-79.577929,40.240027],"type":"Point"}
}