{
  "type": "Feature",
  "properties": {
    "addr:full":"23 W Second St Media PA 19063",
    "addr:housenumber":"23",
    "addr:postcode":"19063",
    "addr:street":"W Second St",
    "iso:country":"US",
    "sg:address":"23 W Second St",
    "sg:city":"Media",
    "sg:classifiers":[
        {
            "category":"Professional",
            "subcategory":"Lawyer & Legal Services",
            "type":"Services"
        },
        {
            "category":"Professional",
            "subcategory":"Computer Services",
            "type":"Services"
        }
    ],
    "sg:phone":"+1 610 566 1700",
    "sg:postcode":"19063",
    "sg:province":"PA",
    "sg:tags":[
        "attorney",
        "dwi",
        "estate",
        "duo",
        "divorce",
        "planning",
        "criminal",
        "technology",
        "law"
    ],
    "sg:website":"http://www.mcintoshlawyers.com",
    "wof:name":"McIntosh Joe ESQ",
    "wof:placetype":"venue"
},
  "geometry": {"coordinates":[-75.38946799999999,39.919729],"type":"Point"}
}