{
  "type": "Feature",
  "properties": {
    "iso:country":"US",
    "sg:address":"43 N Bailey Rd",
    "sg:city":"Thorndale",
    "sg:classifiers":[
        {
            "category":"Restaurant",
            "type":"Food & Drink"
        }
    ],
    "sg:phone":"+1 610 384 6560",
    "sg:postcode":"19372",
    "sg:province":"PA",
    "sg:website":"www.ruffinis.com",
    "wof:name":"Ruffini's Rest",
    "wof:placetype":"venue"
},
  "geometry": {"coordinates":[-75.761093,39.99408],"type":"Point"}
}