{
  "type": "Feature",
  "properties": {
    "iso:country":"US",
    "sg:address":"500 Water St",
    "sg:city":"Indiana",
    "sg:classifiers":[
        {
            "category":"Organizations",
            "subcategory":"Religious Organization",
            "type":"Services"
        }
    ],
    "sg:phone":"+1 724 465 4732",
    "sg:postcode":"15701",
    "sg:province":"PA",
    "wof:name":"First Christian Church",
    "wof:placetype":"venue"
},
  "geometry": {"coordinates":[-79.149473,40.624289],"type":"Point"}
}