{
  "type": "Feature",
  "properties": {
    "addr:full":"Reading Terminl Market 1136 Arch St Philadelphia PA 19107",
    "addr:housenumber":"1136",
    "addr:postcode":"19107",
    "addr:street":"Arch St",
    "iso:country":"US",
    "sg:address":"Reading Terminl Market 1136 Arch St",
    "sg:city":"Philadelphia",
    "sg:classifiers":[
        {
            "category":"Food & Beverages",
            "subcategory":"Specialty",
            "type":"Retail Goods"
        }
    ],
    "sg:phone":"+1 215 592 8555",
    "sg:postcode":"19107",
    "sg:province":"PA",
    "sg:website":"www.spiceterminal.com",
    "wof:name":"Spice Terminal",
    "wof:placetype":"venue"
},
  "geometry": {"coordinates":[-75.158464,39.953828],"type":"Point"}
}