{
  "type": "Feature",
  "properties": {
    "addr:full":"5329 Tamarack Dr Sharpsville PA 16150",
    "addr:housenumber":"5329",
    "addr:postcode":"16150",
    "addr:street":"Tamarack Dr Sharpsville",
    "iso:country":"US",
    "sg:address":"5329 Tamarack Dr",
    "sg:city":"Sharpsville",
    "sg:classifiers":[
        {
            "category":"Insurance",
            "subcategory":"Hazard Insurance",
            "type":"Services"
        },
        {
            "category":"Banks & Credit Unions",
            "subcategory":"Financial Services",
            "type":"Services"
        },
        {
            "category":"Organizations",
            "subcategory":"Membership Organization",
            "type":"Services"
        }
    ],
    "sg:phone":"+1 724 962 9123",
    "sg:postcode":"16150",
    "sg:province":"PA",
    "sg:tags":[
        "consultant",
        "planning",
        "fraternal"
    ],
    "sg:website":"http://www.modern-woodmen.org",
    "wof:name":"Modern Woodmen of America",
    "wof:placetype":"venue"
},
  "geometry": {"coordinates":[-80.514618,41.308394],"type":"Point"}
}