{
  "type": "Feature",
  "properties": {
    "addr:full":"1137 Coventry Rd Cheltenham PA 19012",
    "addr:housenumber":"1137",
    "addr:postcode":"19012",
    "addr:street":"Coventry Rd",
    "iso:country":"US",
    "sg:address":"1137 Coventry Rd",
    "sg:city":"Cheltenham",
    "sg:classifiers":[
        {
            "category":"Health Services",
            "subcategory":"Doctor",
            "type":"Services"
        }
    ],
    "sg:phone":"+1 215 635 0200",
    "sg:postcode":"19012",
    "sg:province":"PA",
    "sg:tags":[
        "dentist"
    ],
    "wof:name":"Goodhart Glenn P DDS",
    "wof:placetype":"venue"
},
  "geometry": {"coordinates":[-75.11741000000001,40.061937],"type":"Point"}
}