{
  "type": "Feature",
  "properties": {
    "iso:country":"US",
    "sg:address":"2939 N Taney St",
    "sg:city":"Philadelphia",
    "sg:classifiers":[
        {
            "category":"Professional",
            "subcategory":"Printing & Photocopies",
            "type":"Services"
        }
    ],
    "sg:phone":"+1 215 221 6524",
    "sg:postcode":"19132",
    "sg:province":"PA",
    "sg:tags":[
        "lithographer"
    ],
    "wof:name":"Cig Fashion Printing",
    "wof:placetype":"venue"
},
  "geometry": {"coordinates":[-75.17416900000001,40.000251],"type":"Point"}
}