{
  "type": "Feature",
  "properties": {
    "iso:country":"US",
    "sg:address":"430 Penn Ave",
    "sg:city":"Scranton",
    "sg:classifiers":[
        {
            "category":"Professional",
            "type":"Services"
        }
    ],
    "sg:phone":"+1 570 343 4745",
    "sg:postcode":"18503",
    "sg:province":"PA",
    "sg:tags":[
        "establishment"
    ],
    "wof:name":"Catholic Agency",
    "wof:placetype":"venue"
},
  "geometry": {"coordinates":[-75.662631,41.412761],"type":"Point"}
}