{
  "type": "Feature",
  "properties": {
    "addr:full":"617 Greenleaf Dr Monroeville PA 15146",
    "addr:housenumber":"617",
    "addr:postcode":"15146",
    "addr:street":"Greenleaf Dr",
    "iso:country":"US",
    "sg:address":"617 Greenleaf Dr",
    "sg:city":"Monroeville",
    "sg:classifiers":[
        {
            "category":"Professional",
            "subcategory":"Business Services",
            "type":"Services"
        }
    ],
    "sg:phone":"+1   ",
    "sg:postcode":"15146",
    "sg:province":"PA",
    "sg:tags":[
        "interior",
        "decorating"
    ],
    "wof:name":"Lorne Rash",
    "wof:placetype":"venue"
},
  "geometry": {"coordinates":[-79.779383,40.448195],"type":"Point"}
}