{
  "type": "Feature",
  "properties": {
    "iso:country":"US",
    "sg:address":"3201 Magee Ave",
    "sg:city":"Philadelphia",
    "sg:classifiers":[
        {
            "category":"Personal",
            "subcategory":"Beauty Salon",
            "type":"Services"
        }
    ],
    "sg:phone":"+1 215 331 2200",
    "sg:postcode":"19149",
    "sg:province":"PA",
    "sg:tags":[
        "hair",
        "stylist"
    ],
    "wof:name":"Hair Razor",
    "wof:placetype":"venue"
},
  "geometry": {"coordinates":[-75.056068,40.031361],"type":"Point"}
}