{
  "type": "Feature",
  "properties": {
    "iso:country":"US",
    "sg:address":"1212 Wallace Dr",
    "sg:city":"Fort Washington",
    "sg:classifiers":[
        {
            "category":"Autos & Motor Vehicles",
            "subcategory":"Automobile Sales",
            "type":"Retail Goods"
        }
    ],
    "sg:phone":"+1   ",
    "sg:postcode":"19034",
    "sg:province":"PA",
    "sg:tags":[
        "used"
    ],
    "wof:name":"Old Towne Motor Cars Ltd",
    "wof:placetype":"venue"
},
  "geometry": {"coordinates":[-75.197581,40.147101],"type":"Point"}
}