{
  "type": "Feature",
  "properties": {
    "addr:full":"106 Mason Dr Glenshaw PA 15116",
    "addr:housenumber":"106",
    "addr:postcode":"15116",
    "addr:street":"Mason Dr",
    "iso:country":"US",
    "sg:address":"106 Mason Dr",
    "sg:city":"Glenshaw",
    "sg:classifiers":[
        {
            "category":"Retail",
            "subcategory":"Repair Shop",
            "type":"Services"
        }
    ],
    "sg:phone":"+1   ",
    "sg:postcode":"15116",
    "sg:province":"PA",
    "sg:tags":[
        "equipment"
    ],
    "wof:name":"Aftanas Business Eqp & Svcs",
    "wof:placetype":"venue"
},
  "geometry": {"coordinates":[-79.96796500000001,40.525647],"type":"Point"}
}