{
  "type": "Feature",
  "properties": {
    "iso:country":"US",
    "sg:address":"1328 Capouse Ave",
    "sg:city":"Scranton",
    "sg:classifiers":[
        {
            "category":"Building & Trades",
            "subcategory":"Pest Control",
            "type":"Services"
        }
    ],
    "sg:phone":"+1 570 343 3606",
    "sg:postcode":"18509",
    "sg:province":"PA",
    "wof:name":"Expert Exterminating Co",
    "wof:placetype":"venue"
},
  "geometry": {"coordinates":[-75.65161500000001,41.424386],"type":"Point"}
}