{
  "type": "Feature",
  "properties": {
    "addr:full":"298 Frost Ln Newtown PA 18940",
    "addr:housenumber":"298",
    "addr:postcode":"18940",
    "addr:street":"Frost Ln",
    "iso:country":"US",
    "sg:address":"298 Frost Ln",
    "sg:city":"Newtown",
    "sg:classifiers":[
        {
            "category":"Education",
            "subcategory":"School",
            "type":"Public Place"
        }
    ],
    "sg:phone":"+1   ",
    "sg:postcode":"18940",
    "sg:province":"PA",
    "wof:name":"Goodnoe Elementary School",
    "wof:placetype":"venue"
},
  "geometry": {"coordinates":[-74.927031,40.235458],"type":"Point"}
}