{
  "type": "Feature",
  "properties": {
    "iso:country":"US",
    "sg:address":"138 Leland St",
    "sg:city":"Friedens",
    "sg:classifiers":[
        {
            "category":"Building & Trades",
            "subcategory":"Landscaping Services",
            "type":"Services"
        }
    ],
    "sg:phone":"+1 814 444 9223",
    "sg:postcode":"15541",
    "sg:province":"PA",
    "sg:tags":[
        "landscape",
        "contractor"
    ],
    "wof:name":"Dependable Lawn Svc Inc",
    "wof:placetype":"venue"
},
  "geometry": {"coordinates":[-78.992605,40.053399],"type":"Point"}
}