{
  "type": "Feature",
  "properties": {
    "iso:country":"US",
    "sg:address":"50 Grumbacher Rd",
    "sg:city":"York",
    "sg:classifiers":[
        {
            "category":"Manufacturing",
            "subcategory":"Tools & Machinery",
            "type":"Manufacturing & Wholesale Goods"
        }
    ],
    "sg:phone":"+1   ",
    "sg:postcode":"17406",
    "sg:province":"PA",
    "sg:tags":[
        "connector",
        "electrical",
        "mfg",
        "electronic",
        "automotive"
    ],
    "wof:name":"Fci Electrical",
    "wof:placetype":"venue"
},
  "geometry": {"coordinates":[-76.742102,40.039897],"type":"Point"}
}