{
  "type": "Feature",
  "properties": {
    "iso:country":"US",
    "sg:address":"309 Chestnut St",
    "sg:city":"Bangor",
    "sg:classifiers":[
        {
            "category":"Building & Trades",
            "subcategory":"Landscaping Services",
            "type":"Services"
        }
    ],
    "sg:phone":"+1 610 588 3463",
    "sg:postcode":"18013",
    "sg:province":"PA",
    "sg:tags":[
        "landscape",
        "contractor"
    ],
    "wof:name":"ELEGANT Lawncare",
    "wof:placetype":"venue"
},
  "geometry": {"coordinates":[-75.20979699999999,40.865079],"type":"Point"}
}