{
  "type": "Feature",
  "properties": {
    "iso:country":"US",
    "sg:address":"1110 de Victor Pl",
    "sg:city":"Pittsburgh",
    "sg:classifiers":[
        {
            "category":"Shopping",
            "subcategory":"Musical Instruments",
            "type":"Retail Goods"
        }
    ],
    "sg:phone":"+1 412 661 2238",
    "sg:postcode":"15206",
    "sg:province":"PA",
    "wof:name":"Orchid Guitars",
    "wof:placetype":"venue"
},
  "geometry": {"coordinates":[-79.915379,40.474197],"type":"Point"}
}