{
  "type": "Feature",
  "properties": {
    "iso:country":"US",
    "sg:address":"1212 Market St",
    "sg:city":"Lewisburg",
    "sg:classifiers":[
        {
            "category":"Banks & Credit Unions",
            "subcategory":"Investment Brokerage",
            "type":"Services"
        }
    ],
    "sg:phone":"+1 570 524 2832",
    "sg:postcode":"17837",
    "sg:province":"PA",
    "sg:tags":[
        "consultant",
        "planning",
        "financial"
    ],
    "wof:name":"B & L Assoc",
    "wof:placetype":"venue"
},
  "geometry": {"coordinates":[-76.896359,40.959368],"type":"Point"}
}