{
  "type": "Feature",
  "properties": {
    "addr:full":"105 Hillcrest Shopping Center Lower Burrell PA 15068",
    "addr:housenumber":"105",
    "addr:postcode":"15068",
    "addr:street":"Hillcrest Shopping",
    "iso:country":"US",
    "sg:address":"105 Hillcrest Shopping Center",
    "sg:city":"Lower Burrell",
    "sg:classifiers":[
        {
            "category":"Building & Trades",
            "subcategory":"Equipment Rental",
            "type":"Services"
        }
    ],
    "sg:phone":"+1 724 337 7700",
    "sg:postcode":"15068",
    "sg:province":"PA",
    "sg:tags":[
        "yard"
    ],
    "wof:name":"Rent-A-Center",
    "wof:placetype":"venue"
},
  "geometry": {"coordinates":[-79.709069,40.582973],"type":"Point"}
}