{
  "type": "Feature",
  "properties": {
    "addr:full":"215 Fairland Rd Manheim PA 17545",
    "addr:housenumber":"215",
    "addr:postcode":"17545",
    "addr:street":"Fairland Rd",
    "iso:country":"US",
    "sg:address":"215 Fairland Rd",
    "sg:city":"Manheim",
    "sg:classifiers":[
        {
            "category":"Manufacturing",
            "subcategory":"Toys & Sporting Goods",
            "type":"Manufacturing & Wholesale Goods"
        }
    ],
    "sg:phone":"+1   ",
    "sg:postcode":"17545",
    "sg:province":"PA",
    "sg:tags":[
        "mfg"
    ],
    "wof:name":"Country Kits and Crafts",
    "wof:placetype":"venue"
},
  "geometry": {"coordinates":[-76.349632,40.14631],"type":"Point"}
}