{
  "type": "Feature",
  "properties": {
    "iso:country":"US",
    "sg:address":"9 E Baltimore St",
    "sg:city":"Greencastle",
    "sg:classifiers":[
        {
            "category":"Shopping",
            "subcategory":"Florist",
            "type":"Retail Goods"
        }
    ],
    "sg:phone":"+1 717 597 9004",
    "sg:postcode":"17225",
    "sg:province":"PA",
    "wof:name":"Bob's Florist & Gift Shop",
    "wof:placetype":"venue"
},
  "geometry": {"coordinates":[-77.727165,39.790047],"type":"Point"}
}