{
  "type": "Feature",
  "properties": {
    "addr:full":"11115 Hunter Rd Mercersburg PA 17236",
    "addr:housenumber":"11115",
    "addr:postcode":"17236",
    "addr:street":"Hunter Rd",
    "iso:country":"US",
    "sg:address":"11115 Hunter Rd",
    "sg:city":"Mercersburg",
    "sg:classifiers":[
        {
            "category":"Building & Trades",
            "subcategory":"Construction",
            "type":"Services"
        }
    ],
    "sg:phone":"+1   ",
    "sg:postcode":"17236",
    "sg:province":"PA",
    "sg:tags":[
        "house"
    ],
    "wof:name":"Fogelsonger S Constructio",
    "wof:placetype":"venue"
},
  "geometry": {"coordinates":[-77.914053,39.752319],"type":"Point"}
}