{
  "type": "Feature",
  "properties": {
    "addr:full":"1829 W Market St York PA 17404",
    "addr:housenumber":"1829",
    "addr:postcode":"17404",
    "addr:street":"W Market St",
    "iso:country":"US",
    "sg:address":"1829 W Market St",
    "sg:city":"York",
    "sg:classifiers":[
        {
            "category":"Health Services",
            "subcategory":"Doctor",
            "type":"Services"
        }
    ],
    "sg:phone":"+1 717 845 9685",
    "sg:postcode":"17404",
    "sg:province":"PA",
    "wof:name":"Scott S Markey DDS",
    "wof:placetype":"venue"
},
  "geometry": {"coordinates":[-76.76684299999999,39.95312],"type":"Point"}
}