{
  "type": "Feature",
  "properties": {
    "iso:country":"US",
    "sg:address":"410 Vaux Ln",
    "sg:city":"Phoenixville",
    "sg:classifiers":[
        {
            "category":"Professional",
            "subcategory":"Computer Services",
            "type":"Services"
        }
    ],
    "sg:phone":"+1   ",
    "sg:postcode":"19460",
    "sg:province":"PA",
    "sg:tags":[
        "consulting",
        "processing",
        "datum"
    ],
    "wof:name":"Columbus Consulting Corp",
    "wof:placetype":"venue"
},
  "geometry": {"coordinates":[-75.445289,40.114927],"type":"Point"}
}