{
  "type": "Feature",
  "properties": {
    "iso:country":"US",
    "sg:address":"6 Spring Mill Dr",
    "sg:city":"Malvern",
    "sg:classifiers":[
        {
            "category":"Health Services",
            "subcategory":"Clinic",
            "type":"Services"
        }
    ],
    "sg:phone":"+1 610 647 3850",
    "sg:postcode":"19355",
    "sg:province":"PA",
    "sg:tags":[
        "home"
    ],
    "wof:name":"Coram Hemophilia Svc",
    "wof:placetype":"venue"
},
  "geometry": {"coordinates":[-75.55319299999999,40.069388],"type":"Point"}
}