{
  "type": "Feature",
  "properties": {
    "iso:country":"US",
    "sg:address":"451 Granite Run Dr",
    "sg:city":"Lancaster",
    "sg:classifiers":[
        {
            "category":"Banks & Credit Unions",
            "subcategory":"Bank",
            "type":"Services"
        }
    ],
    "sg:phone":"+1 717 581 3214",
    "sg:postcode":"17601",
    "sg:province":"PA",
    "sg:tags":[
        "state",
        "commercial"
    ],
    "wof:name":"Fulton Bank",
    "wof:placetype":"venue"
},
  "geometry": {"coordinates":[-76.329115,40.075883],"type":"Point"}
}