{
  "type": "Feature",
  "properties": {
    "iso:country":"US",
    "sg:address":"3604 Route 378",
    "sg:city":"Bethlehem",
    "sg:classifiers":[
        {
            "category":"Retail",
            "subcategory":"Veterinary Services",
            "type":"Services"
        },
        {
            "category":"Retail",
            "subcategory":"Animal Services",
            "type":"Services"
        }
    ],
    "sg:phone":"+1 610 867 0800",
    "sg:postcode":"18015",
    "sg:province":"PA",
    "sg:tags":[
        "pet",
        "hospital",
        "specialty",
        "clinic",
        "veterinarian",
        "grooming"
    ],
    "sg:website":"www.northsauconanimalhospital.ve...",
    "wof:name":"North Saucon Animal Hospital",
    "wof:placetype":"venue"
},
  "geometry": {"coordinates":[-75.3881,40.580898],"type":"Point"}
}