{
  "type": "Feature",
  "properties": {
    "iso:country":"US",
    "sg:address":"1331 N Chatham Rd",
    "sg:city":"Coatesville",
    "sg:classifiers":[
        {
            "category":"Retail",
            "subcategory":"Auto Repair",
            "type":"Services"
        }
    ],
    "sg:phone":"+1 610 384 8197",
    "sg:postcode":"19320",
    "sg:province":"PA",
    "wof:name":"Springdell Garage",
    "wof:placetype":"venue"
},
  "geometry": {"coordinates":[-75.83445399999999,39.904395],"type":"Point"}
}