{
  "type": "Feature",
  "properties": {
    "addr:full":"36 Bedford St Bradford PA 16701",
    "addr:housenumber":"36",
    "addr:postcode":"16701",
    "addr:street":"Bedford St",
    "iso:country":"US",
    "sg:address":"36 Bedford St",
    "sg:city":"Bradford",
    "sg:classifiers":[
        {
            "category":"Wholesale",
            "subcategory":"Machinery & Supplies",
            "type":"Manufacturing & Wholesale Goods"
        }
    ],
    "sg:phone":"+1 814 368 8416",
    "sg:postcode":"16701",
    "sg:province":"PA",
    "sg:tags":[
        "equipment",
        "printing"
    ],
    "wof:name":"Highland Printed Products",
    "wof:placetype":"venue"
},
  "geometry": {"coordinates":[-78.649609,41.945839],"type":"Point"}
}