{
  "type": "Feature",
  "properties": {
    "addr:full":"27 W 8th St Wyoming PA 18644",
    "addr:housenumber":"27",
    "addr:postcode":"18644",
    "addr:street":"W 8Th St",
    "iso:country":"US",
    "sg:address":"27 W 8th St",
    "sg:city":"Wyoming",
    "sg:classifiers":[
        {
            "category":"Shopping",
            "subcategory":"Clothing, Apparel, & Fashions",
            "type":"Retail Goods"
        }
    ],
    "sg:phone":"+1 570 613 1224",
    "sg:postcode":"18644",
    "sg:province":"PA",
    "sg:tags":[
        "hair",
        "supply"
    ],
    "wof:name":"Hairwear",
    "wof:placetype":"venue"
},
  "geometry": {"coordinates":[-75.837875,41.311883],"type":"Point"}
}