{
  "type": "Feature",
  "properties": {
    "iso:country":"US",
    "sg:address":"208 W Front St",
    "sg:city":"Media",
    "sg:classifiers":[
        {
            "category":"Banks & Credit Unions",
            "subcategory":"Investment Brokerage",
            "type":"Services"
        }
    ],
    "sg:phone":"+1   ",
    "sg:postcode":"19063",
    "sg:province":"PA",
    "sg:tags":[
        "security"
    ],
    "wof:name":"Bestvest Investments",
    "wof:placetype":"venue"
},
  "geometry": {"coordinates":[-75.392736,39.919268],"type":"Point"}
}