{
  "type": "Feature",
  "properties": {
    "iso:country":"US",
    "sg:address":"70 Bridge Rd",
    "sg:city":"Collegeville",
    "sg:classifiers":[
        {
            "category":"Manufacturing",
            "subcategory":"Tools & Machinery",
            "type":"Manufacturing & Wholesale Goods"
        }
    ],
    "sg:phone":"+1 610 831 5095",
    "sg:postcode":"19426",
    "sg:province":"PA",
    "sg:tags":[
        "equipment",
        "conveyor",
        "conveying"
    ],
    "wof:name":"Valley Forge Conveyors Inc",
    "wof:placetype":"venue"
},
  "geometry": {"coordinates":[-75.45919000000001,40.208337],"type":"Point"}
}