{
  "type": "Feature",
  "properties": {
    "addr:full":"316 Chelsea Dr Greensburg PA 15601",
    "addr:housenumber":"316",
    "addr:postcode":"15601",
    "addr:street":"Chelsea Dr",
    "iso:country":"US",
    "sg:address":"316 Chelsea Dr",
    "sg:city":"Greensburg",
    "sg:classifiers":[
        {
            "category":"Professional",
            "subcategory":"Detective & Security Services",
            "type":"Services"
        }
    ],
    "sg:phone":"+1   ",
    "sg:postcode":"15601",
    "sg:province":"PA",
    "sg:tags":[
        "guard"
    ],
    "wof:name":"Centry Industrial Security",
    "wof:placetype":"venue"
},
  "geometry": {"coordinates":[-79.511028,40.272402],"type":"Point"}
}