{
  "type": "Feature",
  "properties": {
    "addr:full":"3400 High Point Blvd Bethlehem PA 18017",
    "addr:housenumber":"3400",
    "addr:postcode":"18017",
    "addr:street":"High Point Blvd",
    "iso:country":"US",
    "sg:address":"3400 High Point Blvd",
    "sg:city":"Bethlehem",
    "sg:classifiers":[
        {
            "category":"Real Estate",
            "subcategory":"Developer",
            "type":"Services"
        }
    ],
    "sg:phone":"+1   ",
    "sg:postcode":"18017",
    "sg:province":"PA",
    "wof:name":"D & M Properties",
    "wof:placetype":"venue"
},
  "geometry": {"coordinates":[-75.41672699999999,40.661305],"type":"Point"}
}