{
  "type": "Feature",
  "properties": {
    "addr:full":"4060 Frankford Ave Philadelphia PA 19124",
    "addr:housenumber":"4060",
    "addr:postcode":"19124",
    "addr:street":"Frankford Ave",
    "iso:country":"US",
    "sg:address":"4060 Frankford Ave",
    "sg:city":"Philadelphia",
    "sg:classifiers":[
        {
            "category":"Autos & Motor Vehicles",
            "subcategory":"Automobile Sales",
            "type":"Retail Goods"
        }
    ],
    "sg:phone":"+1 215 831 9240",
    "sg:postcode":"19124",
    "sg:province":"PA",
    "sg:tags":[
        "car",
        "used"
    ],
    "wof:name":"Clarke's Auto Sales",
    "wof:placetype":"venue"
},
  "geometry": {"coordinates":[-75.091435,40.00665],"type":"Point"}
}