{
  "type": "Feature",
  "properties": {
    "iso:country":"US",
    "sg:address":"572 Main St",
    "sg:city":"Stroudsburg",
    "sg:classifiers":[
        {
            "category":"Restaurant",
            "type":"Food & Drink"
        }
    ],
    "sg:phone":"+1 570 420 1810",
    "sg:postcode":"18360",
    "sg:province":"PA",
    "wof:name":"Blimpie Subs & Salads",
    "wof:placetype":"venue"
},
  "geometry": {"coordinates":[-75.19231000000001,40.985899],"type":"Point"}
}