{
  "type": "Feature",
  "properties": {
    "iso:country":"US",
    "sg:address":"3025 W 17th St",
    "sg:city":"Erie",
    "sg:classifiers":[
        {
            "category":"Freight",
            "type":"Transportation"
        }
    ],
    "sg:phone":"+1   ",
    "sg:postcode":"16505",
    "sg:province":"PA",
    "sg:tags":[
        "arrangement"
    ],
    "wof:name":"C C Eastern Inc",
    "wof:placetype":"venue"
},
  "geometry": {"coordinates":[-80.144724,42.095188],"type":"Point"}
}