{
  "type": "Feature",
  "properties": {
    "iso:country":"US",
    "sg:address":"657 E Lincoln Hwy Apt 1",
    "sg:city":"Coatesville",
    "sg:classifiers":[
        {
            "category":"Restaurant",
            "type":"Food & Drink"
        }
    ],
    "sg:phone":"+1 610 384 5887",
    "sg:postcode":"19320",
    "sg:province":"PA",
    "sg:tags":[
        "asian",
        "chinese",
        "pan"
    ],
    "sg:website":"http://www.chinaking.org",
    "wof:name":"China King Restaurant",
    "wof:placetype":"venue"
},
  "geometry": {"coordinates":[-75.81181100000001,39.985008],"type":"Point"}
}