{
  "type": "Feature",
  "properties": {
    "addr:full":"4412 Newton Cir Emmaus PA 18049",
    "addr:housenumber":"4412",
    "addr:postcode":"18049",
    "addr:street":"Newton Cir",
    "iso:country":"US",
    "sg:address":"4412 Newton Cir",
    "sg:city":"Emmaus",
    "sg:phone":"+1 610 965 6616",
    "sg:postcode":"18049",
    "sg:province":"PA",
    "sg:tags":[
        "lubricant"
    ],
    "wof:name":"Lanco Sales Co",
    "wof:placetype":"venue"
},
  "geometry": {"coordinates":[-75.52398700000001,40.531018],"type":"Point"}
}