{
  "type": "Feature",
  "properties": {
    "iso:country":"US",
    "sg:address":"2086 E Haines St",
    "sg:city":"Philadelphia",
    "sg:classifiers":[
        {
            "category":"Retail",
            "subcategory":"Auto Repair",
            "type":"Services"
        }
    ],
    "sg:phone":"+1 215 927 2212",
    "sg:postcode":"19138",
    "sg:province":"PA",
    "sg:tags":[
        "body",
        "automobile",
        "painting"
    ],
    "wof:name":"East Coast Collision Ctr",
    "wof:placetype":"venue"
},
  "geometry": {"coordinates":[-75.155525,40.057315],"type":"Point"}
}