{
  "type": "Feature",
  "properties": {
    "iso:country":"US",
    "sg:address":"12 E Oregon Ave",
    "sg:city":"Philadelphia",
    "sg:classifiers":[
        {
            "category":"Banks & Credit Unions",
            "subcategory":"Bank",
            "type":"Services"
        }
    ],
    "sg:phone":"+1 215 755 5691",
    "sg:postcode":"19148",
    "sg:province":"PA",
    "sg:tags":[
        "loan",
        "real estate"
    ],
    "wof:name":"Collateral One Mortgage Corp",
    "wof:placetype":"venue"
},
  "geometry": {"coordinates":[-75.149894,39.91392],"type":"Point"}
}