{
  "type": "Feature",
  "properties": {
    "iso:country":"US",
    "sg:address":"3450 Bear Creek Blvd",
    "sg:city":"Bear Creek Twp",
    "sg:classifiers":[
        {
            "category":"Building & Trades",
            "subcategory":"Construction",
            "type":"Services"
        }
    ],
    "sg:phone":"+1 570 826 2386",
    "sg:postcode":"18702",
    "sg:province":"PA",
    "sg:tags":[
        "road",
        "contractor"
    ],
    "wof:name":"Highway Maintenance",
    "wof:placetype":"venue"
},
  "geometry": {"coordinates":[-75.787779,41.20209],"type":"Point"}
}