{
  "type": "Feature",
  "properties": {
    "addr:full":"1238 Egypt Rd Phoenixville PA 19460",
    "addr:housenumber":"1238",
    "addr:postcode":"19460",
    "addr:street":"Egypt Rd",
    "iso:country":"US",
    "sg:address":"1238 Egypt Rd",
    "sg:city":"Phoenixville",
    "sg:classifiers":[
        {
            "category":"Bakery",
            "type":"Food & Drink"
        }
    ],
    "sg:phone":"+1 610 666 7664",
    "sg:postcode":"19460",
    "sg:province":"PA",
    "wof:name":"Martin's Famous Pastry Shoppe Inc",
    "wof:placetype":"venue"
},
  "geometry": {"coordinates":[-75.445503,40.134102],"type":"Point"}
}