{
  "type": "Feature",
  "properties": {
    "iso:country":"US",
    "sg:address":"2311 Seipstown Rd",
    "sg:city":"Fogelsville",
    "sg:classifiers":[
        {
            "category":"Arts & Performance",
            "subcategory":"Theater",
            "type":"Entertainment"
        }
    ],
    "sg:phone":"+1   ",
    "sg:postcode":"18051",
    "sg:province":"PA",
    "sg:tags":[
        "theatrical"
    ],
    "wof:name":"Resolution Pictures",
    "wof:placetype":"venue"
},
  "geometry": {"coordinates":[-75.682271,40.590027],"type":"Point"}
}