{
  "type": "Feature",
  "properties": {
    "addr:full":"6701 Oxford Ave Philadelphia PA 19111",
    "addr:housenumber":"6701",
    "addr:postcode":"19111",
    "addr:street":"Oxford Ave",
    "iso:country":"US",
    "sg:address":"6701 Oxford Ave",
    "sg:city":"Philadelphia",
    "sg:classifiers":[
        {
            "category":"Professional",
            "subcategory":"Business Services",
            "type":"Services"
        }
    ],
    "sg:phone":"+1 215 676 4080",
    "sg:postcode":"19111",
    "sg:province":"PA",
    "sg:tags":[
        "consultant",
        "coach"
    ],
    "wof:name":"Healthy Ways Consultants",
    "wof:placetype":"venue"
},
  "geometry": {"coordinates":[-75.086197,40.050041],"type":"Point"}
}