{
  "type": "Feature",
  "properties": {
    "iso:country":"US",
    "sg:address":"41 Smiley Rd",
    "sg:city":"Washington",
    "sg:classifiers":[
        {
            "category":"Real Estate",
            "subcategory":"Surveying",
            "type":"Services"
        }
    ],
    "sg:phone":"+1   ",
    "sg:postcode":"15301",
    "sg:province":"PA",
    "wof:name":"Stein Surveying",
    "wof:placetype":"venue"
},
  "geometry": {"coordinates":[-80.33505,40.203205],"type":"Point"}
}