{
  "type": "Feature",
  "properties": {
    "addr:full":"635 Sunshine Ave Central City PA 15926",
    "addr:housenumber":"635",
    "addr:postcode":"15926",
    "addr:street":"Sunshine Ave",
    "iso:country":"US",
    "sg:address":"635 Sunshine Ave",
    "sg:city":"Central City",
    "sg:classifiers":[
        {
            "category":"Organizations",
            "subcategory":"Religious Organization",
            "type":"Services"
        }
    ],
    "sg:phone":"+1 814 754 5110",
    "sg:postcode":"15926",
    "sg:province":"PA",
    "wof:name":"St Mary's Ladies Alter Society",
    "wof:placetype":"venue"
},
  "geometry": {"coordinates":[-78.801659,40.111062],"type":"Point"}
}