{
  "type": "Feature",
  "properties": {
    "iso:country":"US",
    "sg:address":"151 Fairlawn Ave",
    "sg:city":"State College",
    "sg:classifiers":[
        {
            "category":"Shopping",
            "subcategory":"Florist",
            "type":"Retail Goods"
        }
    ],
    "sg:phone":"+1   ",
    "sg:postcode":"16801",
    "sg:province":"PA",
    "sg:tags":[
        "advisory",
        "investment"
    ],
    "wof:name":"Keepsake Flowers",
    "wof:placetype":"venue"
},
  "geometry": {"coordinates":[-77.82838599999999,40.824715],"type":"Point"}
}