{
  "type": "Feature",
  "properties": {
    "iso:country":"US",
    "sg:address":"1021 Mill Creek Rd",
    "sg:city":"Feasterville Trevose",
    "sg:classifiers":[
        {
            "category":"Insurance",
            "subcategory":"Insurance Agent",
            "type":"Services"
        }
    ],
    "sg:phone":"+1   ",
    "sg:postcode":"19035",
    "sg:province":"PA",
    "wof:name":"Krum Insurance Service",
    "wof:placetype":"venue"
},
  "geometry": {"coordinates":[-75.266142,40.034202],"type":"Point"}
}