{
  "type": "Feature",
  "properties": {
    "iso:country":"US",
    "sg:address":"195 Phillips Park Dr",
    "sg:city":"S Williamsport",
    "sg:classifiers":[
        {
            "category":"Home & Garden",
            "subcategory":"Building Materials",
            "type":"Retail Goods"
        }
    ],
    "sg:phone":"+1 570 323 1848",
    "sg:postcode":"17702",
    "sg:province":"PA",
    "sg:tags":[
        "windows"
    ],
    "wof:name":"Mike's Window Svc",
    "wof:placetype":"venue"
},
  "geometry": {"coordinates":[-77.015227,41.22744],"type":"Point"}
}