{
  "type": "Feature",
  "properties": {
    "iso:country":"US",
    "sg:address":"127 Ivy Ln",
    "sg:city":"Bedford",
    "sg:classifiers":[
        {
            "category":"Building & Trades",
            "subcategory":"Plumbing",
            "type":"Services"
        }
    ],
    "sg:phone":"+1 814 847 9224",
    "sg:postcode":"15522",
    "sg:province":"PA",
    "sg:tags":[
        "plumber"
    ],
    "wof:name":"Robert W Turkovich Sr",
    "wof:placetype":"venue"
},
  "geometry": {"coordinates":[-78.462469,39.952161],"type":"Point"}
}