{
  "type": "Feature",
  "properties": {
    "iso:country":"US",
    "sg:address":"112 Tor Cir",
    "sg:city":"Gibsonia",
    "sg:classifiers":[
        {
            "category":"Professional",
            "subcategory":"Advertising",
            "type":"Services"
        }
    ],
    "sg:phone":"+1 724 935 3850",
    "sg:postcode":"15044",
    "sg:province":"PA",
    "wof:name":"Heffner Outdoor Advertising",
    "wof:placetype":"venue"
},
  "geometry": {"coordinates":[-80.020602,40.626059],"type":"Point"}
}