{
  "type": "Feature",
  "properties": {
    "iso:country":"US",
    "sg:address":"217 Moon Clinton Rd",
    "sg:city":"Coraopolis",
    "sg:classifiers":[
        {
            "category":"Building & Trades",
            "subcategory":"Plumbing",
            "type":"Services"
        }
    ],
    "sg:phone":"+1 412 262 9221",
    "sg:postcode":"15108",
    "sg:province":"PA",
    "sg:tags":[
        "plumbing",
        "contractor"
    ],
    "wof:name":"Fragale Plumbing Heating & AC",
    "wof:placetype":"venue"
},
  "geometry": {"coordinates":[-80.22589499999999,40.512912],"type":"Point"}
}