{
  "type": "Feature",
  "properties": {
    "addr:full":"114 Southpointe Blvd Ste 102 Canonsburg PA 15317",
    "addr:housenumber":"114",
    "addr:postcode":"15317",
    "addr:street":"Southpointe Blvd Ste 102",
    "iso:country":"US",
    "sg:address":"114 Southpointe Blvd Ste 102",
    "sg:city":"Canonsburg",
    "sg:classifiers":[
        {
            "category":"Banks & Credit Unions",
            "subcategory":"Financial Services",
            "type":"Services"
        }
    ],
    "sg:phone":"+1 724 745 1113",
    "sg:postcode":"15317",
    "sg:province":"PA",
    "sg:tags":[
        "broker",
        "mortgage"
    ],
    "wof:name":"Mohsin Mortgage",
    "wof:placetype":"venue"
},
  "geometry": {"coordinates":[-80.161824,40.271229],"type":"Point"}
}