{
  "type": "Feature",
  "properties": {
    "iso:country":"US",
    "sg:address":"4137 Pechin St",
    "sg:city":"Philadelphia",
    "sg:classifiers":[
        {
            "category":"Travel",
            "subcategory":"Travel Agent",
            "type":"Entertainment"
        }
    ],
    "sg:phone":"+1 215 483 0835",
    "sg:postcode":"19128",
    "sg:province":"PA",
    "sg:tags":[
        "agency",
        "services-commercial"
    ],
    "wof:name":"Get Up & Go Travel",
    "wof:placetype":"venue"
},
  "geometry": {"coordinates":[-75.213187,40.025919],"type":"Point"}
}