{
  "type": "Feature",
  "properties": {
    "addr:full":"8109 Frankford Ave Philadelphia PA 19136",
    "addr:housenumber":"8109",
    "addr:postcode":"19136",
    "addr:street":"Frankford Ave",
    "iso:country":"US",
    "sg:address":"8109 Frankford Ave",
    "sg:city":"Philadelphia",
    "sg:classifiers":[
        {
            "category":"Home & Garden",
            "subcategory":"Furniture",
            "type":"Retail Goods"
        }
    ],
    "sg:phone":"+1 215 333 8300",
    "sg:postcode":"19136",
    "sg:province":"PA",
    "sg:tags":[
        "dinette",
        "set"
    ],
    "wof:name":"Morrys Dinettes",
    "wof:placetype":"venue"
},
  "geometry": {"coordinates":[-75.02396,40.042831],"type":"Point"}
}