{
  "type": "Feature",
  "properties": {
    "iso:country":"US",
    "sg:address":"50 E Butler Ave",
    "sg:city":"Ambler",
    "sg:classifiers":[
        {
            "category":"Personal",
            "subcategory":"Beauty Salon",
            "type":"Services"
        }
    ],
    "sg:phone":"+1 215 643 5994",
    "sg:postcode":"19002",
    "sg:province":"PA",
    "sg:tags":[
        "university",
        "college",
        "school"
    ],
    "wof:name":"Ambler Beauty Academy",
    "wof:placetype":"venue"
},
  "geometry": {"coordinates":[-75.222314,40.15435],"type":"Point"}
}