{
  "type": "Feature",
  "properties": {
    "addr:full":"538 E 21st St Northampton PA 18067",
    "addr:housenumber":"538",
    "addr:postcode":"18067",
    "addr:street":"E 21St St",
    "iso:country":"US",
    "sg:address":"538 E 21st St",
    "sg:city":"Northampton",
    "sg:classifiers":[
        {
            "category":"Home & Garden",
            "subcategory":"Carpets & Floor Coverings",
            "type":"Retail Goods"
        }
    ],
    "sg:phone":"+1 610 261 2260",
    "sg:postcode":"18067",
    "sg:province":"PA",
    "sg:tags":[
        "installation"
    ],
    "wof:name":"C R C Carpet Service",
    "wof:placetype":"venue"
},
  "geometry": {"coordinates":[-75.49281000000001,40.693359],"type":"Point"}
}