{
  "type": "Feature",
  "properties": {
    "iso:country":"US",
    "sg:address":"217 S McKean St",
    "sg:city":"Kittanning",
    "sg:classifiers":[
        {
            "category":"Food & Beverages",
            "subcategory":"Candy",
            "type":"Retail Goods"
        }
    ],
    "sg:phone":"+1 724 543 9080",
    "sg:postcode":"16201",
    "sg:province":"PA",
    "wof:name":"Candy Plus",
    "wof:placetype":"venue"
},
  "geometry": {"coordinates":[-79.517107,40.813319],"type":"Point"}
}