{
  "type": "Feature",
  "properties": {
    "iso:country":"US",
    "sg:address":"6465 Phillips Ave",
    "sg:city":"Pittsburgh",
    "sg:classifiers":[
        {
            "category":"Building & Trades",
            "subcategory":"Construction",
            "type":"Services"
        }
    ],
    "sg:phone":"+1 412 521 2212",
    "sg:postcode":"15217",
    "sg:province":"PA",
    "sg:tags":[
        "general",
        "contractor"
    ],
    "wof:name":"Aaron Fox",
    "wof:placetype":"venue"
},
  "geometry": {"coordinates":[-79.912871,40.432587],"type":"Point"}
}