{
  "type": "Feature",
  "properties": {
    "iso:country":"US",
    "sg:address":"109 Cheryl Ann",
    "sg:city":"Mount Joy",
    "sg:classifiers":[
        {
            "category":"Real Estate",
            "subcategory":"Real Estate Agent",
            "type":"Services"
        }
    ],
    "sg:phone":"+1   ",
    "sg:postcode":"17584",
    "sg:province":"PA",
    "wof:name":"Distinctive Realty Services",
    "wof:placetype":"venue"
},
  "geometry": {"coordinates":[-76.28288000000001,39.991523],"type":"Point"}
}