{
  "type": "Feature",
  "properties": {
    "iso:country":"US",
    "sg:address":"257 S Cottage Rd",
    "sg:city":"Mercer",
    "sg:classifiers":[
        {
            "category":"Restaurant",
            "type":"Food & Drink"
        }
    ],
    "sg:phone":"+1   ",
    "sg:postcode":"16137",
    "sg:province":"PA",
    "sg:tags":[
        "eating"
    ],
    "wof:name":"Mama & Papa Bairs Family Rest",
    "wof:placetype":"venue"
},
  "geometry": {"coordinates":[-80.172487,41.256264],"type":"Point"}
}