{
  "type": "Feature",
  "properties": {
    "iso:country":"US",
    "sg:address":"226 Bainbridge St",
    "sg:city":"Philadelphia",
    "sg:classifiers":[
        {
            "category":"Wholesale",
            "subcategory":"Non-durable Goods",
            "type":"Manufacturing & Wholesale Goods"
        }
    ],
    "sg:phone":"+1 215 627 8215",
    "sg:postcode":"19147",
    "sg:province":"PA",
    "sg:tags":[
        "souvenir"
    ],
    "wof:name":"Artos International Inc",
    "wof:placetype":"venue"
},
  "geometry": {"coordinates":[-75.14727999999999,39.940392],"type":"Point"}
}