{
  "type": "Feature",
  "properties": {
    "iso:country":"US",
    "sg:address":"5537 Germantown Ave",
    "sg:city":"Philadelphia",
    "sg:classifiers":[
        {
            "category":"Health Services",
            "subcategory":"Health Practitioner",
            "type":"Services"
        }
    ],
    "sg:phone":"+1   ",
    "sg:postcode":"19144",
    "sg:province":"PA",
    "wof:name":"Wayne Chelten Medical Pavilion",
    "wof:placetype":"venue"
},
  "geometry": {"coordinates":[-75.17353,40.034906],"type":"Point"}
}