{
  "type": "Feature",
  "properties": {
    "iso:country":"US",
    "sg:address":"1318 Buffalo Rd",
    "sg:city":"Erie",
    "sg:classifiers":[
        {
            "category":"Personal",
            "subcategory":"Beauty Salon",
            "type":"Services"
        }
    ],
    "sg:phone":"+1   ",
    "sg:postcode":"16503",
    "sg:province":"PA",
    "sg:tags":[
        "shop"
    ],
    "wof:name":"Dawson Barber & Beauty",
    "wof:placetype":"venue"
},
  "geometry": {"coordinates":[-80.045514,42.128103],"type":"Point"}
}