{
  "type": "Feature",
  "properties": {
    "iso:country":"US",
    "sg:address":"2 Rich St",
    "sg:city":"Oil City",
    "sg:classifiers":[
        {
            "category":"Insurance",
            "subcategory":"Insurance Agent",
            "type":"Services"
        }
    ],
    "sg:phone":"+1   ",
    "sg:postcode":"16301",
    "sg:province":"PA",
    "wof:name":"Michael P McMahon Ins",
    "wof:placetype":"venue"
},
  "geometry": {"coordinates":[-79.711271,41.420196],"type":"Point"}
}