{
  "type": "Feature",
  "properties": {
    "addr:full":"2 S 2nd St Harrisburg PA 17104",
    "addr:housenumber":"2",
    "addr:postcode":"17104",
    "addr:street":"S 2Nd St",
    "iso:country":"US",
    "sg:address":"2 S 2nd St",
    "sg:city":"Harrisburg",
    "sg:classifiers":[
        {
            "category":"Government",
            "subcategory":"Office",
            "type":"Public Place"
        }
    ],
    "sg:phone":"+1 717 255 2741",
    "sg:postcode":"17104",
    "sg:province":"PA",
    "wof:name":"Dauphin County Commissioner",
    "wof:placetype":"venue"
},
  "geometry": {"coordinates":[-76.881016,40.259296],"type":"Point"}
}