{
  "type": "Feature",
  "properties": {
    "iso:country":"US",
    "sg:address":"41 1st St",
    "sg:city":"Mansfield",
    "sg:classifiers":[
        {
            "category":"Organizations",
            "subcategory":"Non-profit Organization",
            "type":"Services"
        }
    ],
    "sg:phone":"+1 570 662 3094",
    "sg:postcode":"16933",
    "sg:province":"PA",
    "sg:tags":[
        "human"
    ],
    "wof:name":"Martha Lloyd Community Svc",
    "wof:placetype":"venue"
},
  "geometry": {"coordinates":[-77.076285,41.802789],"type":"Point"}
}