{
  "type": "Feature",
  "properties": {
    "addr:full":"5031 Lytle St Pittsburgh PA 15207",
    "addr:housenumber":"5031",
    "addr:postcode":"15207",
    "addr:street":"Lytle St",
    "iso:country":"US",
    "sg:address":"5031 Lytle St",
    "sg:city":"Pittsburgh",
    "sg:classifiers":[
        {
            "category":"Building & Trades",
            "subcategory":"Construction",
            "type":"Services"
        }
    ],
    "sg:phone":"+1 412 521 8925",
    "sg:postcode":"15207",
    "sg:province":"PA",
    "sg:tags":[
        "general",
        "contractor"
    ],
    "wof:name":"Avanti Construction Inc",
    "wof:placetype":"venue"
},
  "geometry": {"coordinates":[-79.94526,40.406776],"type":"Point"}
}