{
  "type": "Feature",
  "properties": {
    "iso:country":"US",
    "sg:address":"312 E Northampton St",
    "sg:city":"Wilkes Barre",
    "sg:classifiers":[
        {
            "category":"Restaurant",
            "type":"Food & Drink"
        }
    ],
    "sg:phone":"+1   ",
    "sg:postcode":"18702",
    "sg:province":"PA",
    "sg:tags":[
        "eating"
    ],
    "wof:name":"Billys Pizza & Subs",
    "wof:placetype":"venue"
},
  "geometry": {"coordinates":[-75.87789100000001,41.23729],"type":"Point"}
}