{
  "type": "Feature",
  "properties": {
    "iso:country":"US",
    "sg:address":"1625 Market St",
    "sg:city":"Philadelphia",
    "sg:classifiers":[
        {
            "category":"Restaurant",
            "type":"Food & Drink"
        }
    ],
    "sg:phone":"+1 215 557 9691",
    "sg:postcode":"19103",
    "sg:province":"PA",
    "sg:tags":[
        "eating"
    ],
    "wof:name":"Bistro Sensation Of Liberty Pl",
    "wof:placetype":"venue"
},
  "geometry": {"coordinates":[-75.16813399999999,39.953],"type":"Point"}
}