{
  "type": "Feature",
  "properties": {
    "iso:country":"US",
    "sg:address":"107 Raisley Ln",
    "sg:city":"Butler",
    "sg:classifiers":[
        {
            "category":"Retail",
            "subcategory":"Animal Services",
            "type":"Services"
        }
    ],
    "sg:phone":"+1 724 283 1725",
    "sg:postcode":"16001",
    "sg:province":"PA",
    "sg:tags":[
        "training",
        "dog"
    ],
    "wof:name":"K-9 Basics & Beyond",
    "wof:placetype":"venue"
},
  "geometry": {"coordinates":[-79.992874,40.887806],"type":"Point"}
}