{
  "type": "Feature",
  "properties": {
    "addr:full":"121 S Whitfield St Pittsburgh PA 15206",
    "addr:housenumber":"121",
    "addr:postcode":"15206",
    "addr:street":"S Whitfield St",
    "iso:country":"US",
    "sg:address":"121 S Whitfield St",
    "sg:city":"Pittsburgh",
    "sg:classifiers":[
        {
            "category":"Manufacturing",
            "subcategory":"Printing",
            "type":"Manufacturing & Wholesale Goods"
        }
    ],
    "sg:phone":"+1 412 367 2219",
    "sg:postcode":"15206",
    "sg:province":"PA",
    "sg:tags":[
        "publisher"
    ],
    "wof:name":"Pittsburgh Woman Inc",
    "wof:placetype":"venue"
},
  "geometry": {"coordinates":[-79.926528,40.460826],"type":"Point"}
}