{
  "type": "Feature",
  "properties": {
    "addr:full":"145 Valvoline Dr East Butler PA 16029",
    "addr:housenumber":"145",
    "addr:postcode":"16029",
    "addr:street":"Valvoline Dr East",
    "iso:country":"US",
    "sg:address":"145 Valvoline Dr",
    "sg:city":"East Butler",
    "sg:classifiers":[
        {
            "category":"Building & Trades",
            "subcategory":"Construction",
            "type":"Services"
        }
    ],
    "sg:phone":"+1 724 285 6495",
    "sg:postcode":"16029",
    "sg:province":"PA",
    "sg:tags":[
        "fabricator",
        "metal"
    ],
    "wof:name":"Ken-Fab & Weld Inc",
    "wof:placetype":"venue"
},
  "geometry": {"coordinates":[-79.851995,40.879687],"type":"Point"}
}