{
  "type": "Feature",
  "properties": {
    "iso:country":"US",
    "sg:address":"437 Cement Dr",
    "sg:city":"Jersey Shore",
    "sg:classifiers":[
        {
            "category":"Building & Trades",
            "subcategory":"Construction",
            "type":"Services"
        }
    ],
    "sg:phone":"+1 570 398 7297",
    "sg:postcode":"17740",
    "sg:province":"PA",
    "sg:tags":[
        "house",
        "maker",
        "cabinet"
    ],
    "wof:name":"R J Eisley Wood Products",
    "wof:placetype":"venue"
},
  "geometry": {"coordinates":[-77.259216,41.211083],"type":"Point"}
}