{
  "type": "Feature",
  "properties": {
    "iso:country":"US",
    "sg:address":"2547 W State St",
    "sg:city":"New Castle",
    "sg:classifiers":[
        {
            "category":"Banks & Credit Unions",
            "subcategory":"Bank",
            "type":"Services"
        }
    ],
    "sg:phone":"+1   ",
    "sg:postcode":"16101",
    "sg:province":"PA",
    "sg:tags":[
        "state",
        "commercial"
    ],
    "wof:name":"First Commonwealth Bank",
    "wof:placetype":"venue"
},
  "geometry": {"coordinates":[-80.389915,41.010202],"type":"Point"}
}