{
  "type": "Feature",
  "properties": {
    "iso:country":"US",
    "sg:address":"106 W Liberty St",
    "sg:city":"Sykesville",
    "sg:classifiers":[
        {
            "category":"Organizations",
            "subcategory":"Community Association",
            "type":"Services"
        }
    ],
    "sg:phone":"+1 814 894 2222",
    "sg:postcode":"15865",
    "sg:province":"PA",
    "sg:tags":[
        "military"
    ],
    "wof:name":"American Legion",
    "wof:placetype":"venue"
},
  "geometry": {"coordinates":[-78.82173899999999,41.049167],"type":"Point"}
}