{
  "type": "Feature",
  "properties": {
    "iso:country":"US",
    "sg:address":"4717 Butler St",
    "sg:city":"Pittsburgh",
    "sg:classifiers":[
        {
            "category":"Manufacturing",
            "subcategory":"Electronics",
            "type":"Manufacturing & Wholesale Goods"
        }
    ],
    "sg:phone":"+1   ",
    "sg:postcode":"15201",
    "sg:province":"PA",
    "sg:tags":[
        "equipment",
        "mfg",
        "home"
    ],
    "wof:name":"Joes Audio",
    "wof:placetype":"venue"
},
  "geometry": {"coordinates":[-79.957752,40.475226],"type":"Point"}
}