{
  "type": "Feature",
  "properties": {
    "iso:country":"US",
    "sg:address":"502 Main St",
    "sg:city":"Ford City",
    "sg:classifiers":[
        {
            "category":"Restaurant",
            "type":"Food & Drink"
        }
    ],
    "sg:phone":"+1 724 763 3312",
    "sg:postcode":"16226",
    "sg:province":"PA",
    "sg:tags":[
        "eating"
    ],
    "wof:name":"Hunan Chinese Restaurant",
    "wof:placetype":"venue"
},
  "geometry": {"coordinates":[-79.52745,40.765547],"type":"Point"}
}