{
  "type": "Feature",
  "properties": {
    "addr:full":"455 American Bangor Rd Bangor PA 18013",
    "addr:housenumber":"455",
    "addr:postcode":"18013",
    "addr:street":"American Bangor Rd",
    "iso:country":"US",
    "sg:address":"455 American Bangor Rd",
    "sg:city":"Bangor",
    "sg:classifiers":[
        {
            "category":"Restaurant",
            "type":"Food & Drink"
        }
    ],
    "sg:phone":"+1 610 588 2695",
    "sg:postcode":"18013",
    "sg:province":"PA",
    "wof:name":"Bangor Bowling Ctr",
    "wof:placetype":"venue"
},
  "geometry": {"coordinates":[-75.232726,40.868844],"type":"Point"}
}