{
  "type": "Feature",
  "properties": {
    "iso:country":"US",
    "sg:address":"158 Oak Spring Rd",
    "sg:city":"Washington",
    "sg:classifiers":[
        {
            "category":"Building & Trades",
            "subcategory":"Electrical",
            "type":"Services"
        }
    ],
    "sg:phone":"+1 724 228 5869",
    "sg:postcode":"15301",
    "sg:province":"PA",
    "sg:tags":[
        "electrician"
    ],
    "wof:name":"Schultz Electric",
    "wof:placetype":"venue"
},
  "geometry": {"coordinates":[-80.23893,40.184999],"type":"Point"}
}