{
  "type": "Feature",
  "properties": {
    "iso:country":"US",
    "sg:address":"827 Media St",
    "sg:city":"Bethlehem",
    "sg:classifiers":[
        {
            "category":"Arts & Performance",
            "subcategory":"Dance",
            "type":"Entertainment"
        }
    ],
    "sg:phone":"+1 610 691 1453",
    "sg:postcode":"18017",
    "sg:province":"PA",
    "sg:tags":[
        "instruction",
        "dancing"
    ],
    "wof:name":"Rain Dance Comm Inc",
    "wof:placetype":"venue"
},
  "geometry": {"coordinates":[-75.358711,40.631124],"type":"Point"}
}