{
  "type": "Feature",
  "properties": {
    "iso:country":"US",
    "sg:address":"525 W Chester Pike",
    "sg:city":"Havertown",
    "sg:classifiers":[
        {
            "category":"Real Estate",
            "subcategory":"Real Estate Agent",
            "type":"Services"
        }
    ],
    "sg:phone":"+1 610 449 3900",
    "sg:postcode":"19083",
    "sg:province":"PA",
    "sg:tags":[
        "management",
        "appraisal"
    ],
    "sg:website":"www.lrodinassoc.com",
    "wof:name":"Lewis R Rodin & Associates",
    "wof:placetype":"venue"
},
  "geometry": {"coordinates":[-75.307327,39.970834],"type":"Point"}
}