{
  "type": "Feature",
  "properties": {
    "iso:country":"US",
    "sg:address":"321 W Welsh Dr",
    "sg:city":"Douglassville",
    "sg:classifiers":[
        {
            "category":"Manufacturing",
            "subcategory":"Tools & Machinery",
            "type":"Manufacturing & Wholesale Goods"
        }
    ],
    "sg:phone":"+1 610 385 0500",
    "sg:postcode":"19518",
    "sg:province":"PA",
    "sg:tags":[
        "devices"
    ],
    "wof:name":"Thermo Electron Corp",
    "wof:placetype":"venue"
},
  "geometry": {"coordinates":[-75.744317,40.269642],"type":"Point"}
}