{
  "type": "Feature",
  "properties": {
    "addr:full":"14 W Evergreen Ave Philadelphia PA 19118",
    "addr:housenumber":"14",
    "addr:postcode":"19118",
    "addr:street":"W Evergreen Ave",
    "iso:country":"US",
    "sg:address":"14 W Evergreen Ave",
    "sg:city":"Philadelphia",
    "sg:classifiers":[
        {
            "category":"Real Estate",
            "subcategory":"Real Estate Agent",
            "type":"Services"
        }
    ],
    "sg:phone":"+1   ",
    "sg:postcode":"19118",
    "sg:province":"PA",
    "sg:tags":[
        "broker"
    ],
    "wof:name":"Prudential Fox Roach Realtors",
    "wof:placetype":"venue"
},
  "geometry": {"coordinates":[-75.207436,40.076626],"type":"Point"}
}