{
  "type": "Feature",
  "properties": {
    "addr:full":"238 W Union St Somerset PA 15501",
    "addr:housenumber":"238",
    "addr:postcode":"15501",
    "addr:street":"W Union St",
    "iso:country":"US",
    "sg:address":"238 W Union St",
    "sg:city":"Somerset",
    "sg:classifiers":[
        {
            "category":"Professional",
            "subcategory":"Lawyer & Legal Services",
            "type":"Services"
        }
    ],
    "sg:phone":"+1 814 443 2337",
    "sg:postcode":"15501",
    "sg:province":"PA",
    "sg:tags":[
        "attorney"
    ],
    "wof:name":"Sandra W Upor",
    "wof:placetype":"venue"
},
  "geometry": {"coordinates":[-79.0829,40.00936],"type":"Point"}
}