{
  "type": "Feature",
  "properties": {
    "addr:full":"8 Cynwyd Rd Bala Cynwyd PA 19004",
    "addr:housenumber":"8",
    "addr:postcode":"19004",
    "addr:street":"Cynwyd Rd",
    "iso:country":"US",
    "sg:address":"8 Cynwyd Rd",
    "sg:city":"Bala Cynwyd",
    "sg:classifiers":[
        {
            "category":"Health Services",
            "subcategory":"Dentist",
            "type":"Services"
        }
    ],
    "sg:phone":"+1 610 664 8466",
    "sg:postcode":"19004",
    "sg:province":"PA",
    "wof:name":"Sexton Tara DMD",
    "wof:placetype":"venue"
},
  "geometry": {"coordinates":[-75.230598,40.0037],"type":"Point"}
}