{
  "type": "Feature",
  "properties": {
    "iso:country":"US",
    "sg:address":"5800 Baltimore Ave",
    "sg:city":"Philadelphia",
    "sg:classifiers":[
        {
            "category":"Place Of Worship",
            "subcategory":"Church",
            "type":"Public Place"
        },
        {
            "category":"Place Of Worship",
            "type":"Public Place"
        }
    ],
    "sg:phone":"+1 215 921 6703",
    "sg:postcode":"19143",
    "sg:province":"PA",
    "sg:tags":[
        "churches-apostolic",
        "churches-pentecostal-apostolic"
    ],
    "wof:name":"Christ Apostolic Church",
    "wof:placetype":"venue"
},
  "geometry": {"coordinates":[-75.240013,39.94593],"type":"Point"}
}