{
  "type": "Feature",
  "properties": {
    "addr:full":"31 W State Street Suite A Doylestown PA 18901",
    "addr:housenumber":"31",
    "addr:postcode":"18901",
    "addr:street":"W State Street Suite A",
    "iso:country":"US",
    "sg:address":"31 W State Street Suite A",
    "sg:city":"Doylestown",
    "sg:classifiers":[
        {
            "category":"Shopping",
            "subcategory":"Clothing, Apparel, & Fashions",
            "type":"Retail Goods"
        }
    ],
    "sg:phone":"+1 215 340 0444",
    "sg:postcode":"18901",
    "sg:province":"PA",
    "sg:tags":[
        "clothing",
        "women's"
    ],
    "wof:name":"Something Else",
    "wof:placetype":"venue"
},
  "geometry": {"coordinates":[-75.131215,40.309634],"type":"Point"}
}