{
  "type": "Feature",
  "properties": {
    "iso:country":"US",
    "sg:address":"2240 Old Pittston Blvd",
    "sg:city":"Wilkes Barre",
    "sg:classifiers":[
        {
            "category":"Freight",
            "type":"Transportation"
        }
    ],
    "sg:phone":"+1   ",
    "sg:postcode":"18702",
    "sg:province":"PA",
    "sg:tags":[
        "operator",
        "local",
        "trucking"
    ],
    "wof:name":"Joseph Pascucci Trucking",
    "wof:placetype":"venue"
},
  "geometry": {"coordinates":[-75.78236200000001,41.263274],"type":"Point"}
}