{
  "type": "Feature",
  "properties": {
    "addr:full":"110 S State St Newtown PA 18940",
    "addr:housenumber":"110",
    "addr:postcode":"18940",
    "addr:street":"S State St",
    "iso:country":"US",
    "sg:address":"110 S State St",
    "sg:city":"Newtown",
    "sg:classifiers":[
        {
            "category":"Personal",
            "subcategory":"Beauty Salon",
            "type":"Services"
        }
    ],
    "sg:phone":"+1 215 860 2300",
    "sg:postcode":"18940",
    "sg:province":"PA",
    "sg:tags":[
        "shop"
    ],
    "wof:name":"Fingertips & Tootsies",
    "wof:placetype":"venue"
},
  "geometry": {"coordinates":[-74.937021,40.227679],"type":"Point"}
}