{
  "type": "Feature",
  "properties": {
    "iso:country":"US",
    "sg:address":"27 Price Rd",
    "sg:city":"Presto",
    "sg:classifiers":[
        {
            "category":"Home & Garden",
            "subcategory":"Carpets & Floor Coverings",
            "type":"Retail Goods"
        }
    ],
    "sg:phone":"+1   ",
    "sg:postcode":"15142",
    "sg:province":"PA",
    "wof:name":"Carpets Etc",
    "wof:placetype":"venue"
},
  "geometry": {"coordinates":[-80.118512,40.374285],"type":"Point"}
}