{
  "type": "Feature",
  "properties": {
    "iso:country":"US",
    "sg:address":"30 E College St",
    "sg:city":"Canonsburg",
    "sg:classifiers":[
        {
            "category":"Retail",
            "subcategory":"Funeral Services",
            "type":"Services"
        }
    ],
    "sg:phone":"+1 724 746 1000",
    "sg:postcode":"15317",
    "sg:province":"PA",
    "sg:tags":[
        "cemetery"
    ],
    "sg:website":"www.sollon.com",
    "wof:name":"Sollon Funeral Home Ltd",
    "wof:placetype":"venue"
},
  "geometry": {"coordinates":[-80.186401,40.2603],"type":"Point"}
}