{
  "type": "Feature",
  "properties": {
    "addr:full":"290 Swihart Rd Canonsburg PA 15317",
    "addr:housenumber":"290",
    "addr:postcode":"15317",
    "addr:street":"Swihart Rd",
    "iso:country":"US",
    "sg:address":"290 Swihart Rd",
    "sg:city":"Canonsburg",
    "sg:classifiers":[
        {
            "category":"Professional",
            "type":"Services"
        }
    ],
    "sg:phone":"+1   ",
    "sg:postcode":"15317",
    "sg:province":"PA",
    "wof:name":"John Novotny",
    "wof:placetype":"venue"
},
  "geometry": {"coordinates":[-80.231002,40.297447],"type":"Point"}
}