{
  "type": "Feature",
  "properties": {
    "iso:country":"US",
    "sg:address":"3100 Versailles Ave",
    "sg:city":"Mckeesport",
    "sg:classifiers":[
        {
            "category":"Restaurant",
            "type":"Food & Drink"
        }
    ],
    "sg:phone":"+1 412 672 7202",
    "sg:postcode":"15132",
    "sg:province":"PA",
    "sg:tags":[
        "out"
    ],
    "wof:name":"Passing Fancy",
    "wof:placetype":"venue"
},
  "geometry": {"coordinates":[-79.840614,40.345137],"type":"Point"}
}