{
  "type": "Feature",
  "properties": {
    "iso:country":"US",
    "sg:address":"622 Union Blvd",
    "sg:city":"Allentown",
    "sg:classifiers":[
        {
            "category":"Education",
            "subcategory":"Music School",
            "type":"Public Place"
        },
        {
            "category":"Shopping",
            "subcategory":"Computers & Home Electronics",
            "type":"Retail Goods"
        }
    ],
    "sg:phone":"+1 610 820 5600",
    "sg:postcode":"18109",
    "sg:province":"PA",
    "sg:tags":[
        "instrument",
        "teacher",
        "musical"
    ],
    "wof:name":"Dave Phillips Music & Sound",
    "wof:placetype":"venue"
},
  "geometry": {"coordinates":[-75.449303,40.623699],"type":"Point"}
}