{
  "type": "Feature",
  "properties": {
    "addr:full":"7024 City Ave Philadelphia PA 19151",
    "addr:housenumber":"7024",
    "addr:postcode":"19151",
    "addr:street":"City Ave",
    "iso:country":"US",
    "sg:address":"7024 City Ave",
    "sg:city":"Philadelphia",
    "sg:classifiers":[
        {
            "category":"Bus Charters",
            "type":"Transportation"
        }
    ],
    "sg:phone":"+1 215 877 7011",
    "sg:postcode":"19151",
    "sg:province":"PA",
    "wof:name":"A 1 Charter Bus Co",
    "wof:placetype":"venue"
},
  "geometry": {"coordinates":[-75.263654,39.982669],"type":"Point"}
}