{
  "type": "Feature",
  "properties": {
    "addr:full":"1602 E 18th St Erie PA 16510",
    "addr:housenumber":"1602",
    "addr:postcode":"16510",
    "addr:street":"E 18Th St",
    "iso:country":"US",
    "sg:address":"1602 E 18th St",
    "sg:city":"Erie",
    "sg:classifiers":[
        {
            "category":"Building & Trades",
            "subcategory":"Plumbing",
            "type":"Services"
        }
    ],
    "sg:phone":"+1 814 456 7014",
    "sg:postcode":"16510",
    "sg:province":"PA",
    "sg:tags":[
        "plumbing",
        "contractor"
    ],
    "sg:website":"www.wmtspaeder.com",
    "wof:name":"William T Spaeder Co Inc",
    "wof:placetype":"venue"
},
  "geometry": {"coordinates":[-80.03985900000001,42.132825],"type":"Point"}
}