{
  "type": "Feature",
  "properties": {
    "iso:country":"US",
    "sg:address":"1349 Beach Dr",
    "sg:city":"Monongahela",
    "sg:classifiers":[
        {
            "category":"Building & Trades",
            "subcategory":"Construction",
            "type":"Services"
        }
    ],
    "sg:phone":"+1 724 483 2351",
    "sg:postcode":"15063",
    "sg:province":"PA",
    "sg:tags":[
        "altering",
        "remodeling",
        "contractor"
    ],
    "wof:name":"Shane T Cox",
    "wof:placetype":"venue"
},
  "geometry": {"coordinates":[-79.9233,40.171131],"type":"Point"}
}