{
  "type": "Feature",
  "properties": {
    "iso:country":"US",
    "sg:address":"971 Soap Hollow Rd",
    "sg:city":"Hollsopple",
    "sg:classifiers":[
        {
            "category":"Shopping",
            "type":"Retail Goods"
        }
    ],
    "sg:phone":"+1 814 270 2381",
    "sg:postcode":"15935",
    "sg:province":"PA",
    "sg:tags":[
        "merchandise"
    ],
    "wof:name":"Rocketry Warehouse",
    "wof:placetype":"venue"
},
  "geometry": {"coordinates":[-78.94905799999999,40.251669],"type":"Point"}
}