{
  "type": "Feature",
  "properties": {
    "iso:country":"US",
    "sg:address":"424 W Penn St",
    "sg:city":"Bedford",
    "sg:classifiers":[
        {
            "category":"Manufacturing",
            "subcategory":"Printing",
            "type":"Manufacturing & Wholesale Goods"
        }
    ],
    "sg:phone":"+1 814 623 1151",
    "sg:postcode":"15522",
    "sg:province":"PA",
    "sg:tags":[
        "newspaper"
    ],
    "sg:website":"www.bedfordgazette.com",
    "wof:name":"Bedford Gazette",
    "wof:placetype":"venue"
},
  "geometry": {"coordinates":[-78.509196,40.017799],"type":"Point"}
}