{
  "type": "Feature",
  "properties": {
    "iso:country":"US",
    "sg:address":"1924 Monongahela Ave",
    "sg:city":"Pittsburgh",
    "sg:classifiers":[
        {
            "category":"Personal",
            "subcategory":"Beauty Salon",
            "type":"Services"
        }
    ],
    "sg:phone":"+1 412 271 2297",
    "sg:postcode":"15218",
    "sg:province":"PA",
    "wof:name":"The Beauty Box",
    "wof:placetype":"venue"
},
  "geometry": {"coordinates":[-79.889975,40.421169],"type":"Point"}
}