{
  "type": "Feature",
  "properties": {
    "iso:country":"US",
    "sg:address":"128 W Market St",
    "sg:city":"Scranton",
    "sg:classifiers":[
        {
            "category":"Health Services",
            "subcategory":"Doctor",
            "type":"Services"
        }
    ],
    "sg:phone":"+1 570 347 1177",
    "sg:postcode":"18508",
    "sg:province":"PA",
    "sg:tags":[
        "physician",
        "surgeon"
    ],
    "wof:name":"Prime Med",
    "wof:placetype":"venue"
},
  "geometry": {"coordinates":[-75.657596,41.438325],"type":"Point"}
}