{
  "type": "Feature",
  "properties": {
    "iso:country":"US",
    "sg:address":"441 N George St",
    "sg:city":"Millersville",
    "sg:classifiers":[
        {
            "category":"Retail",
            "subcategory":"Funeral Services",
            "type":"Services"
        }
    ],
    "sg:phone":"+1 717 872 5041",
    "sg:postcode":"17551",
    "sg:province":"PA",
    "sg:tags":[
        "home"
    ],
    "sg:website":"www.snyderfuneralhome.com",
    "wof:name":"Charles F Snyder Funeral Home",
    "wof:placetype":"venue"
},
  "geometry": {"coordinates":[-76.357815,40.006052],"type":"Point"}
}