{
  "type": "Feature",
  "properties": {
    "iso:country":"US",
    "sg:address":"75 Cooper Rd",
    "sg:city":"Curwensville",
    "sg:classifiers":[
        {
            "category":"Wholesale",
            "subcategory":"Construction Materials",
            "type":"Manufacturing & Wholesale Goods"
        }
    ],
    "sg:phone":"+1   ",
    "sg:postcode":"16833",
    "sg:province":"PA",
    "sg:tags":[
        "veneer"
    ],
    "wof:name":"Pennsylvania Veneer Corp",
    "wof:placetype":"venue"
},
  "geometry": {"coordinates":[-78.518298,40.969692],"type":"Point"}
}