{
  "type": "Feature",
  "properties": {
    "iso:country":"US",
    "sg:address":"5830 Meridian Rd",
    "sg:city":"Gibsonia",
    "sg:classifiers":[
        {
            "category":"Health Services",
            "subcategory":"Clinic",
            "type":"Services"
        }
    ],
    "sg:phone":"+1 724 444 5502",
    "sg:postcode":"15044",
    "sg:province":"PA",
    "sg:tags":[
        "home"
    ],
    "sg:website":"www.stbarnabashealthsystem.com",
    "wof:name":"St Barnabas Home Care",
    "wof:placetype":"venue"
},
  "geometry": {"coordinates":[-79.959349,40.652043],"type":"Point"}
}