{
  "type": "Feature",
  "properties": {
    "iso:country":"US",
    "sg:address":"1955 Bremen Rd",
    "sg:city":"Hatfield",
    "sg:classifiers":[
        {
            "category":"Building & Trades",
            "subcategory":"Construction",
            "type":"Services"
        }
    ],
    "sg:phone":"+1   ",
    "sg:postcode":"19440",
    "sg:province":"PA",
    "wof:name":"Keystone Scada",
    "wof:placetype":"venue"
},
  "geometry": {"coordinates":[-75.329365,40.265594],"type":"Point"}
}