{
  "type": "Feature",
  "properties": {
    "addr:full":"2919 Samuel Dr Bensalem PA 19020",
    "addr:housenumber":"2919",
    "addr:postcode":"19020",
    "addr:street":"Samuel Dr",
    "iso:country":"US",
    "sg:address":"2919 Samuel Dr",
    "sg:city":"Bensalem",
    "sg:classifiers":[
        {
            "category":"Freight",
            "type":"Transportation"
        }
    ],
    "sg:phone":"+1 215 639 9410",
    "sg:postcode":"19020",
    "sg:province":"PA",
    "sg:tags":[
        "general",
        "warehousing"
    ],
    "wof:name":"G & A Warehouses Inc",
    "wof:placetype":"venue"
},
  "geometry": {"coordinates":[-74.93487399999999,40.079435],"type":"Point"}
}