{
  "type": "Feature",
  "properties": {
    "iso:country":"US",
    "sg:address":"11027 Kipling Ln",
    "sg:city":"Philadelphia",
    "sg:classifiers":[
        {
            "category":"Place Of Worship",
            "subcategory":"Monastery",
            "type":"Public Place"
        }
    ],
    "sg:phone":"+1 215 637 3599",
    "sg:postcode":"19154",
    "sg:province":"PA",
    "sg:tags":[
        "convent"
    ],
    "wof:name":"Our Lady Help Of Christians Church Rectory",
    "wof:placetype":"venue"
},
  "geometry": {"coordinates":[-74.979439,40.079262],"type":"Point"}
}