{
  "type": "Feature",
  "properties": {
    "iso:country":"US",
    "sg:address":"720 Macdade Blvd",
    "sg:city":"Collingdale",
    "sg:classifiers":[
        {
            "category":"Professional",
            "subcategory":"Business Services",
            "type":"Services"
        }
    ],
    "sg:phone":"+1 610 237 1111",
    "sg:postcode":"19023",
    "sg:province":"PA",
    "sg:tags":[
        "telemarketing"
    ],
    "sg:website":"www.abestanswer.com",
    "wof:name":"Phone Works",
    "wof:placetype":"venue"
},
  "geometry": {"coordinates":[-75.277278,39.911719],"type":"Point"}
}