{
  "type": "Feature",
  "properties": {
    "addr:full":"2045 Centre Ave Reading PA 19605",
    "addr:housenumber":"2045",
    "addr:postcode":"19605",
    "addr:street":"Centre Ave",
    "iso:country":"US",
    "sg:address":"2045 Centre Ave",
    "sg:city":"Reading",
    "sg:classifiers":[
        {
            "category":"Shopping",
            "subcategory":"Stationery & Office Supplies",
            "type":"Retail Goods"
        }
    ],
    "sg:phone":"+1 610 299 4497",
    "sg:postcode":"19605",
    "sg:province":"PA",
    "wof:name":"Advanced Information Systems",
    "wof:placetype":"venue"
},
  "geometry": {"coordinates":[-75.932514,40.365099],"type":"Point"}
}