{
  "type": "Feature",
  "properties": {
    "addr:full":"170 Walnut Ln Pottsville PA 17901",
    "addr:housenumber":"170",
    "addr:postcode":"17901",
    "addr:street":"Walnut Ln",
    "iso:country":"US",
    "sg:address":"170 Walnut Ln",
    "sg:city":"Pottsville",
    "sg:classifiers":[
        {
            "category":"Mining & Drilling",
            "type":"Manufacturing & Wholesale Goods"
        }
    ],
    "sg:phone":"+1 570 622 4747",
    "sg:postcode":"17901",
    "sg:province":"PA",
    "sg:website":"http://www.worldresourcescompany.com",
    "wof:name":"World Resources Company",
    "wof:placetype":"venue"
},
  "geometry": {"coordinates":[-76.194776,40.693738],"type":"Point"}
}