{
  "type": "Feature",
  "properties": {
    "iso:country":"US",
    "sg:address":"1950 Fruitville Pike",
    "sg:city":"Lancaster",
    "sg:classifiers":[
        {
            "category":"Utilities",
            "subcategory":"Mobile Phone",
            "type":"Services"
        },
        {
            "category":"Coffee & Tea",
            "type":"Food & Drink"
        }
    ],
    "sg:phone":"+1 717 519 8730",
    "sg:postcode":"17601",
    "sg:province":"PA",
    "sg:tags":[
        "shop",
        "restaurant",
        "brewing",
        "espresso",
        "hotspot",
        "device",
        "wi-fi"
    ],
    "sg:website":"http://www.starbuckscoffee.com",
    "wof:name":"Starbucks Coffee",
    "wof:placetype":"venue"
},
  "geometry": {"coordinates":[-76.322403,40.075165],"type":"Point"}
}