{
  "type": "Feature",
  "properties": {
    "iso:country":"US",
    "sg:address":"188 Airport Rd",
    "sg:city":"Marietta",
    "sg:classifiers":[
        {
            "category":"Organizations",
            "subcategory":"Community Association",
            "type":"Services"
        }
    ],
    "sg:phone":"+1 717 653 0422",
    "sg:postcode":"17547",
    "sg:province":"PA",
    "sg:tags":[
        "equipment",
        "transportation"
    ],
    "wof:name":"Maytown Sport Parachute Club",
    "wof:placetype":"venue"
},
  "geometry": {"coordinates":[-76.570527,40.08949],"type":"Point"}
}