{
  "type": "Feature",
  "properties": {
    "addr:full":"36 S 4th St Columbia PA 17512",
    "addr:housenumber":"36",
    "addr:postcode":"17512",
    "addr:street":"S 4Th St",
    "iso:country":"US",
    "sg:address":"36 S 4th St",
    "sg:city":"Columbia",
    "sg:classifiers":[
        {
            "category":"Building & Trades",
            "subcategory":"Electrical",
            "type":"Services"
        }
    ],
    "sg:phone":"+1 717 684 7848",
    "sg:postcode":"17512",
    "sg:province":"PA",
    "sg:tags":[
        "electric",
        "contractor"
    ],
    "wof:name":"L M & S Electrical Contractor",
    "wof:placetype":"venue"
},
  "geometry": {"coordinates":[-76.50012099999999,40.031927],"type":"Point"}
}