{
  "type": "Feature",
  "properties": {
    "iso:country":"US",
    "sg:address":"493 Glen Eagle Sq",
    "sg:city":"Chadds Ford",
    "sg:classifiers":[
        {
            "category":"Shopping",
            "subcategory":"Crafts & Fabrics",
            "type":"Retail Goods"
        }
    ],
    "sg:phone":"+1 610 558 8000",
    "sg:postcode":"19317",
    "sg:province":"PA",
    "sg:tags":[
        "art"
    ],
    "wof:name":"Mykonos",
    "wof:placetype":"venue"
},
  "geometry": {"coordinates":[-75.60700199999999,39.862701],"type":"Point"}
}