{
  "type": "Feature",
  "properties": {
    "iso:country":"US",
    "sg:address":"3101 S Lawrence St",
    "sg:city":"Philadelphia",
    "sg:classifiers":[
        {
            "category":"Freight",
            "type":"Transportation"
        }
    ],
    "sg:phone":"+1 215 336 0300",
    "sg:postcode":"19148",
    "sg:province":"PA",
    "sg:tags":[
        "warehouse",
        "storage"
    ],
    "wof:name":"Lawrence Warehousing",
    "wof:placetype":"venue"
},
  "geometry": {"coordinates":[-75.15843099999999,39.903462],"type":"Point"}
}