{
  "type": "Feature",
  "properties": {
    "addr:full":"20835 Morris Rd Conneautville PA 16406",
    "addr:housenumber":"20835",
    "addr:postcode":"16406",
    "addr:street":"Morris Rd",
    "iso:country":"US",
    "sg:address":"20835 Morris Rd",
    "sg:city":"Conneautville",
    "sg:classifiers":[
        {
            "category":"Manufacturing",
            "subcategory":"Textiles",
            "type":"Manufacturing & Wholesale Goods"
        }
    ],
    "sg:phone":"+1 814 587 3879",
    "sg:postcode":"16406",
    "sg:province":"PA",
    "sg:tags":[
        "rope"
    ],
    "wof:name":"Troyer's Rope Co",
    "wof:placetype":"venue"
},
  "geometry": {"coordinates":[-80.282993,41.753395],"type":"Point"}
}