{
  "type": "Feature",
  "properties": {
    "addr:full":"350 N Main St Chalfont PA 18914",
    "addr:housenumber":"350",
    "addr:postcode":"18914",
    "addr:street":"N Main St",
    "iso:country":"US",
    "sg:address":"350 N Main St",
    "sg:city":"Chalfont",
    "sg:classifiers":[
        {
            "category":"Manufacturing",
            "subcategory":"Tools & Machinery",
            "type":"Manufacturing & Wholesale Goods"
        },
        {
            "category":"Wholesale",
            "subcategory":"Machinery & Supplies",
            "type":"Manufacturing & Wholesale Goods"
        }
    ],
    "sg:phone":"+1 908 218 9200",
    "sg:postcode":"18914",
    "sg:province":"PA",
    "sg:tags":[
        "control",
        "pumps-wholesale",
        "flood",
        "equipment",
        "pump",
        "manufacturer"
    ],
    "wof:name":"Sulzer Pumps (Us) Inc",
    "wof:placetype":"venue"
},
  "geometry": {"coordinates":[-75.214838,40.292459],"type":"Point"}
}