{
  "type": "Feature",
  "properties": {
    "addr:full":"70 McKnight St Pittsburgh PA 15220",
    "addr:housenumber":"70",
    "addr:postcode":"15220",
    "addr:street":"Mcknight St",
    "iso:country":"US",
    "sg:address":"70 McKnight St",
    "sg:city":"Pittsburgh",
    "sg:classifiers":[
        {
            "category":"Organizations",
            "subcategory":"Religious Organization",
            "type":"Services"
        }
    ],
    "sg:phone":"+1 724 452 0634",
    "sg:postcode":"15220",
    "sg:province":"PA",
    "wof:name":"Glade Run Lutheran Services",
    "wof:placetype":"venue"
},
  "geometry": {"coordinates":[-80.03036400000001,40.433797],"type":"Point"}
}