{
  "type": "Feature",
  "properties": {
    "iso:country":"US",
    "sg:address":"3912 Library Rd",
    "sg:city":"Castle Shannon",
    "sg:classifiers":[
        {
            "category":"Autos & Motor Vehicles",
            "subcategory":"Auto Supplies",
            "type":"Retail Goods"
        }
    ],
    "sg:phone":"+1 412 531 1690",
    "sg:postcode":"15234",
    "sg:province":"PA",
    "sg:tags":[
        "battery",
        "equipment",
        "electrical"
    ],
    "sg:website":"www.batteriesplus.com",
    "wof:name":"Batteries Plus",
    "wof:placetype":"venue"
},
  "geometry": {"coordinates":[-80.02778000000001,40.362553],"type":"Point"}
}