{
  "type": "Feature",
  "properties": {
    "addr:full":"6201 N Front St Philadelphia PA 19120",
    "addr:housenumber":"6201",
    "addr:postcode":"19120",
    "addr:street":"N Front St",
    "iso:country":"US",
    "sg:address":"6201 N Front St",
    "sg:city":"Philadelphia",
    "sg:classifiers":[
        {
            "category":"Professional",
            "type":"Services"
        }
    ],
    "sg:phone":"+1 215 224 2244",
    "sg:postcode":"19120",
    "sg:province":"PA",
    "sg:tags":[
        "establishment"
    ],
    "wof:name":"Musictown Corp",
    "wof:placetype":"venue"
},
  "geometry": {"coordinates":[-75.119248,40.045521],"type":"Point"}
}