{
  "type": "Feature",
  "properties": {
    "addr:full":"1900 N Ringgold St Philadelphia PA 19121",
    "addr:housenumber":"1900",
    "addr:postcode":"19121",
    "addr:street":"N Ringgold St",
    "iso:country":"US",
    "sg:address":"1900 N Ringgold St",
    "sg:city":"Philadelphia",
    "sg:classifiers":[
        {
            "category":"Food & Beverages",
            "subcategory":"Groceries & Convenience Stores",
            "type":"Retail Goods"
        }
    ],
    "sg:phone":"+1 215 769 0294",
    "sg:postcode":"19121",
    "sg:province":"PA",
    "wof:name":"Duran's Grocery",
    "wof:placetype":"venue"
},
  "geometry": {"coordinates":[-75.174004,39.983891],"type":"Point"}
}