{
  "type": "Feature",
  "properties": {
    "addr:full":"401 Jones St Minersville PA 17954",
    "addr:housenumber":"401",
    "addr:postcode":"17954",
    "addr:street":"Jones St",
    "iso:country":"US",
    "sg:address":"401 Jones St",
    "sg:city":"Minersville",
    "sg:classifiers":[
        {
            "category":"Building & Trades",
            "subcategory":"Construction",
            "type":"Services"
        },
        {
            "category":"Professional",
            "subcategory":"Management & Consulting",
            "type":"Services"
        }
    ],
    "sg:phone":"+1 570 544 4400",
    "sg:postcode":"17954",
    "sg:province":"PA",
    "sg:tags":[
        "industrial",
        "nonresidential"
    ],
    "wof:name":"Quandel Group Inc",
    "wof:placetype":"venue"
},
  "geometry": {"coordinates":[-76.263606,40.696324],"type":"Point"}
}