{
  "type": "Feature",
  "properties": {
    "iso:country":"US",
    "sg:address":"946 Rostraver Rd",
    "sg:city":"Belle Vernon",
    "sg:classifiers":[
        {
            "category":"Wholesale",
            "subcategory":"Beer",
            "type":"Manufacturing & Wholesale Goods"
        }
    ],
    "sg:phone":"+1 724 929 5141",
    "sg:postcode":"15012",
    "sg:province":"PA",
    "sg:tags":[
        "ale"
    ],
    "wof:name":"Beer Arena Of Belle Vernon",
    "wof:placetype":"venue"
},
  "geometry": {"coordinates":[-79.841983,40.140446],"type":"Point"}
}