{
  "type": "Feature",
  "properties": {
    "iso:country":"US",
    "sg:address":"555 E City Ave Ste 1170",
    "sg:city":"Bala Cynwyd",
    "sg:classifiers":[
        {
            "category":"Health Services",
            "subcategory":"Doctor",
            "type":"Services"
        }
    ],
    "sg:phone":"+1 610 667 0100",
    "sg:postcode":"19004",
    "sg:province":"PA",
    "wof:name":"Plastic Surgery Associates",
    "wof:placetype":"venue"
},
  "geometry": {"coordinates":[-75.21880299999999,40.004902],"type":"Point"}
}