{
  "type": "Feature",
  "properties": {
    "iso:country":"US",
    "sg:address":"10101 Verree Rd ",
    "sg:city":"Philadelphia",
    "sg:classifiers":[
        {
            "category":"Restaurant",
            "type":"Food & Drink"
        }
    ],
    "sg:menulink":"http://www.allmenus.com/pa/philadelphia/289743-katerinas-pizza/menu/",
    "sg:phone":"+1 215 677 6511",
    "sg:postcode":"19116",
    "sg:province":"PA",
    "sg:tags":[
        "american",
        "pizza"
    ],
    "wof:name":"Katerina's Pizza",
    "wof:placetype":"venue"
},
  "geometry": {"coordinates":[-75.031066,40.105888],"type":"Point"}
}