{
  "type": "Feature",
  "properties": {
    "addr:full":"143 S 13th St Philadelphia PA 19107",
    "addr:housenumber":"143",
    "addr:postcode":"19107",
    "addr:street":"S 13Th St",
    "iso:country":"US",
    "sg:address":"143 S 13th St",
    "sg:city":"Philadelphia",
    "sg:classifiers":[
        {
            "category":"Professional",
            "subcategory":"Management & Consulting",
            "type":"Services"
        }
    ],
    "sg:phone":"+1   ",
    "sg:postcode":"19107",
    "sg:province":"PA",
    "sg:tags":[
        "set",
        "communications",
        "consultant",
        "show",
        "up",
        "to",
        "other",
        "how"
    ],
    "wof:name":"Prepaid Retailers S 13th St",
    "wof:placetype":"venue"
},
  "geometry": {"coordinates":[-75.162004,39.94928],"type":"Point"}
}