{
  "type": "Feature",
  "properties": {
    "addr:full":"3664 N Hereford Ln Philadelphia PA 19114",
    "addr:housenumber":"3664",
    "addr:postcode":"19114",
    "addr:street":"N Hereford Ln",
    "iso:country":"US",
    "sg:address":"3664 N Hereford Ln",
    "sg:city":"Philadelphia",
    "sg:classifiers":[
        {
            "category":"Health Services",
            "subcategory":"Clinic",
            "type":"Services"
        }
    ],
    "sg:phone":"+1 215 612 2902",
    "sg:postcode":"19114",
    "sg:province":"PA",
    "sg:tags":[
        "welfare"
    ],
    "wof:name":"Home Health Care",
    "wof:placetype":"venue"
},
  "geometry": {"coordinates":[-74.98380299999999,40.06933],"type":"Point"}
}