{
  "type": "Feature",
  "properties": {
    "addr:full":"925 Lewisberry Rd Lewisberry PA 17339",
    "addr:housenumber":"925",
    "addr:postcode":"17339",
    "addr:street":"Lewisberry Rd",
    "iso:country":"US",
    "sg:address":"925 Lewisberry Rd",
    "sg:city":"Lewisberry",
    "sg:classifiers":[
        {
            "category":"Autos & Motor Vehicles",
            "subcategory":"Automobile Sales",
            "type":"Retail Goods"
        },
        {
            "category":"Retail",
            "subcategory":"Auto Repair",
            "type":"Services"
        }
    ],
    "sg:phone":"+1 717 938 0618",
    "sg:postcode":"17339",
    "sg:province":"PA",
    "sg:tags":[
        "dealers-used",
        "new",
        "used",
        "cars-wholesale",
        "car"
    ],
    "wof:name":"Abc Auto Ii Inc",
    "wof:placetype":"venue"
},
  "geometry": {"coordinates":[-76.88515099999999,40.164409],"type":"Point"}
}