{
  "type": "Feature",
  "properties": {
    "iso:country":"US",
    "sg:address":"808 Bunting Ln",
    "sg:city":"Primos",
    "sg:classifiers":[
        {
            "category":"Insurance",
            "subcategory":"Hazard Insurance",
            "type":"Services"
        }
    ],
    "sg:phone":"+1 610 394 0097",
    "sg:postcode":"19018",
    "sg:province":"PA",
    "sg:tags":[
        "commercial",
        "business"
    ],
    "wof:name":"Delco Insurance Solutions",
    "wof:placetype":"venue"
},
  "geometry": {"coordinates":[-75.30037900000001,39.923143],"type":"Point"}
}