{
  "type": "Feature",
  "properties": {
    "addr:full":"504 Sunbury St Minersville PA 17954",
    "addr:housenumber":"504",
    "addr:postcode":"17954",
    "addr:street":"Sunbury St",
    "iso:country":"US",
    "sg:address":"504 Sunbury St",
    "sg:city":"Minersville",
    "sg:classifiers":[
        {
            "category":"Autos & Motor Vehicles",
            "subcategory":"Fuel & Gas Station",
            "type":"Retail Goods"
        }
    ],
    "sg:phone":"+1   ",
    "sg:postcode":"17954",
    "sg:province":"PA",
    "sg:tags":[
        "station",
        "gasoline"
    ],
    "wof:name":"Murphys Gulf Gas Stn Cyri",
    "wof:placetype":"venue"
},
  "geometry": {"coordinates":[-76.26855,40.692463],"type":"Point"}
}