{
  "type": "Feature",
  "properties": {
    "addr:full":"605 E Main St Westfield PA 16950",
    "addr:housenumber":"605",
    "addr:postcode":"16950",
    "addr:street":"E Main St",
    "iso:country":"US",
    "sg:address":"605 E Main St",
    "sg:city":"Westfield",
    "sg:classifiers":[
        {
            "category":"Food & Beverages",
            "subcategory":"Groceries & Convenience Stores",
            "type":"Retail Goods"
        }
    ],
    "sg:phone":"+1 814 367 2707",
    "sg:postcode":"16950",
    "sg:province":"PA",
    "wof:name":"Hurler's Grocery Store",
    "wof:placetype":"venue"
},
  "geometry": {"coordinates":[-77.53076900000001,41.922222],"type":"Point"}
}