{
  "type": "Feature",
  "properties": {
    "iso:country":"US",
    "sg:address":"6245 Greene St",
    "sg:city":"Philadelphia",
    "sg:classifiers":[
        {
            "category":"Professional",
            "subcategory":"Management & Consulting",
            "type":"Services"
        }
    ],
    "sg:phone":"+1 267 295 1023",
    "sg:postcode":"19144",
    "sg:province":"PA",
    "sg:tags":[
        "consultant",
        "wine"
    ],
    "wof:name":"Wine School Of Philadelphia",
    "wof:placetype":"venue"
},
  "geometry": {"coordinates":[-75.184383,40.039072],"type":"Point"}
}