{
  "type": "Feature",
  "properties": {
    "iso:country":"US",
    "sg:address":"1737 W Ontario St",
    "sg:city":"Philadelphia",
    "sg:classifiers":[
        {
            "category":"Building & Trades",
            "subcategory":"Construction",
            "type":"Services"
        }
    ],
    "sg:phone":"+1 215 223 7313",
    "sg:postcode":"19140",
    "sg:province":"PA",
    "sg:tags":[
        "roofing",
        "contractor"
    ],
    "wof:name":"S & R Roofing",
    "wof:placetype":"venue"
},
  "geometry": {"coordinates":[-75.15736,40.005391],"type":"Point"}
}