{
  "type": "Feature",
  "properties": {
    "addr:full":"561 W Chocolate Ave Hershey PA 17033",
    "addr:housenumber":"561",
    "addr:postcode":"17033",
    "addr:street":"W Chocolate Ave",
    "iso:country":"US",
    "sg:address":"561 W Chocolate Ave",
    "sg:city":"Hershey",
    "sg:classifiers":[
        {
            "category":"Social Services",
            "type":"Services"
        }
    ],
    "sg:phone":"+1   ",
    "sg:postcode":"17033",
    "sg:province":"PA",
    "wof:name":"Mazzitti & Sullivan E A P Svcs",
    "wof:placetype":"venue"
},
  "geometry": {"coordinates":[-76.66210100000001,40.281278],"type":"Point"}
}