{
  "type": "Feature",
  "properties": {
    "iso:country":"US",
    "sg:address":"1228 Elk St",
    "sg:city":"Franklin",
    "sg:classifiers":[
        {
            "category":"Health Services",
            "subcategory":"Doctor",
            "type":"Services"
        }
    ],
    "sg:phone":"+1 814 432 2145",
    "sg:postcode":"16323",
    "sg:province":"PA",
    "sg:tags":[
        "medical"
    ],
    "wof:name":"Franklin Medical Group",
    "wof:placetype":"venue"
},
  "geometry": {"coordinates":[-79.827912,41.398588],"type":"Point"}
}