{
  "type": "Feature",
  "properties": {
    "addr:full":"708 S Old Middletown Rd Media PA 19063",
    "addr:housenumber":"708",
    "addr:postcode":"19063",
    "addr:street":"S Old Middletown Rd",
    "iso:country":"US",
    "sg:address":"708 S Old Middletown Rd",
    "sg:city":"Media",
    "sg:classifiers":[
        {
            "category":"Organizations",
            "subcategory":"Religious Organization",
            "type":"Services"
        }
    ],
    "sg:phone":"+1 610 891 7110",
    "sg:postcode":"19063",
    "sg:province":"PA",
    "sg:tags":[
        "church"
    ],
    "sg:website":"www.ccdelco.com",
    "wof:name":"Calvary Chapel Delaware County",
    "wof:placetype":"venue"
},
  "geometry": {"coordinates":[-75.39946399999999,39.879832],"type":"Point"}
}