{
  "type": "Feature",
  "properties": {
    "iso:country":"US",
    "sg:address":"264 Valley Ln",
    "sg:city":"Annville",
    "sg:classifiers":[
        {
            "category":"Building & Trades",
            "subcategory":"Construction",
            "type":"Services"
        }
    ],
    "sg:phone":"+1 717 867 8383",
    "sg:postcode":"17003",
    "sg:province":"PA",
    "sg:tags":[
        "roofing",
        "contractor"
    ],
    "wof:name":"Osborne's Roofing & Siding",
    "wof:placetype":"venue"
},
  "geometry": {"coordinates":[-76.539124,40.274833],"type":"Point"}
}