{
  "type": "Feature",
  "properties": {
    "iso:country":"US",
    "sg:address":"203 N Wales Rd",
    "sg:city":"North Wales",
    "sg:classifiers":[
        {
            "category":"Professional",
            "type":"Services"
        }
    ],
    "sg:phone":"+1   ",
    "sg:postcode":"19446",
    "sg:province":"PA",
    "wof:name":"Alliance Actuarial Services",
    "wof:placetype":"venue"
},
  "geometry": {"coordinates":[-75.259242,40.231381],"type":"Point"}
}