{
  "type": "Feature",
  "properties": {
    "iso:country":"US",
    "sg:address":"3301 N 6th St",
    "sg:city":"Harrisburg",
    "sg:classifiers":[
        {
            "category":"Wholesale",
            "subcategory":"Non-durable Goods",
            "type":"Manufacturing & Wholesale Goods"
        }
    ],
    "sg:phone":"+1 717 233 8844",
    "sg:postcode":"17110",
    "sg:province":"PA",
    "sg:tags":[
        "advertising"
    ],
    "sg:website":"www.philiplevin.com",
    "wof:name":"Philip Levin Co",
    "wof:placetype":"venue"
},
  "geometry": {"coordinates":[-76.896034,40.300579],"type":"Point"}
}