{
  "type": "Feature",
  "properties": {
    "iso:country":"US",
    "sg:address":"500 Arcola Rd",
    "sg:city":"Collegeville",
    "sg:classifiers":[
        {
            "category":"Banks & Credit Unions",
            "subcategory":"Bank",
            "type":"Services"
        }
    ],
    "sg:phone":"+1 484 865 7031",
    "sg:postcode":"19426",
    "sg:province":"PA",
    "sg:tags":[
        "federal"
    ],
    "sg:website":"http://www.benchmarkfcu.org",
    "wof:name":"Collegeville",
    "wof:placetype":"venue"
},
  "geometry": {"coordinates":[-75.46948999999999,40.16235],"type":"Point"}
}