{
  "type": "Feature",
  "properties": {
    "addr:full":"5219 Market St Philadelphia PA 19139",
    "addr:housenumber":"5219",
    "addr:postcode":"19139",
    "addr:street":"Market St",
    "iso:country":"US",
    "sg:address":"5219 Market St",
    "sg:city":"Philadelphia",
    "sg:classifiers":[
        {
            "category":"Shopping",
            "subcategory":"Clothing, Apparel, & Fashions",
            "type":"Retail Goods"
        }
    ],
    "sg:phone":"+1 215 476 2737",
    "sg:postcode":"19139",
    "sg:province":"PA",
    "sg:tags":[
        "clothing",
        "uniforms-accessories",
        "store",
        "uniform"
    ],
    "wof:name":"50 2nd Scrub Station",
    "wof:placetype":"venue"
},
  "geometry": {"coordinates":[-75.225498,39.960121],"type":"Point"}
}