{
  "type": "Feature",
  "properties": {
    "iso:country":"US",
    "sg:address":"8791 Barnes Lake Rd",
    "sg:city":"Irwin",
    "sg:classifiers":[
        {
            "category":"Professional",
            "subcategory":"Employment Agencies",
            "type":"Services"
        }
    ],
    "sg:phone":"+1 724 864 1600",
    "sg:postcode":"15642",
    "sg:province":"PA",
    "sg:tags":[
        "opportunity"
    ],
    "sg:website":"www.huntptnr.com",
    "wof:name":"Hundington Partners Inc",
    "wof:placetype":"venue"
},
  "geometry": {"coordinates":[-79.686346,40.317887],"type":"Point"}
}