{
  "type": "Feature",
  "properties": {
    "addr:full":"1637 Main St Northampton PA 18067",
    "addr:housenumber":"1637",
    "addr:postcode":"18067",
    "addr:street":"Main St",
    "iso:country":"US",
    "sg:address":"1637 Main St",
    "sg:city":"Northampton",
    "sg:classifiers":[
        {
            "category":"Shopping",
            "type":"Retail Goods"
        }
    ],
    "sg:phone":"+1 610 262 8669",
    "sg:postcode":"18067",
    "sg:province":"PA",
    "sg:tags":[
        "merchandise"
    ],
    "wof:name":"All Things Framed",
    "wof:placetype":"venue"
},
  "geometry": {"coordinates":[-75.49611,40.685622],"type":"Point"}
}