{
  "type": "Feature",
  "properties": {
    "addr:full":"259 E 3rd St Pottstown PA 19464",
    "addr:housenumber":"259",
    "addr:postcode":"19464",
    "addr:street":"E 3Rd St",
    "iso:country":"US",
    "sg:address":"259 E 3rd St",
    "sg:city":"Pottstown",
    "sg:classifiers":[
        {
            "category":"Building & Trades",
            "subcategory":"Plumbing",
            "type":"Services"
        }
    ],
    "sg:phone":"+1   ",
    "sg:postcode":"19464",
    "sg:province":"PA",
    "sg:tags":[
        "contractor"
    ],
    "wof:name":"Timothy L Gibble Inc",
    "wof:placetype":"venue"
},
  "geometry": {"coordinates":[-75.646674,40.25006],"type":"Point"}
}