{
  "type": "Feature",
  "properties": {
    "addr:full":"112 Stillwell Ct Pittsburgh PA 15228",
    "addr:housenumber":"112",
    "addr:postcode":"15228",
    "addr:street":"Stillwell Ct",
    "iso:country":"US",
    "sg:address":"112 Stillwell Ct",
    "sg:city":"Pittsburgh",
    "sg:classifiers":[
        {
            "category":"Wholesale",
            "subcategory":"Hardware",
            "type":"Manufacturing & Wholesale Goods"
        }
    ],
    "sg:phone":"+1   ",
    "sg:postcode":"15228",
    "sg:province":"PA",
    "sg:tags":[
        "plumbing",
        "heating",
        "supply"
    ],
    "wof:name":"Rich Turian",
    "wof:placetype":"venue"
},
  "geometry": {"coordinates":[-80.03824899999999,40.35768],"type":"Point"}
}