{
  "type": "Feature",
  "properties": {
    "iso:country":"US",
    "sg:address":"300 6th Ave",
    "sg:city":"Pittsburgh",
    "sg:classifiers":[
        {
            "category":"Restaurant",
            "type":"Food & Drink"
        }
    ],
    "sg:menulink":"http://www.allmenus.com/pa/pittsburgh/258893-dominos-pizza/menu/",
    "sg:phone":"+1 412 432 3232",
    "sg:postcode":"15222",
    "sg:province":"PA",
    "sg:tags":[
        "american",
        "wing",
        "pizza"
    ],
    "wof:name":"Domino's Pizza",
    "wof:placetype":"venue"
},
  "geometry": {"coordinates":[-79.999398,40.441994],"type":"Point"}
}