{
  "type": "Feature",
  "properties": {
    "iso:country":"US",
    "sg:address":"123 Brown Rd",
    "sg:city":"Pittston",
    "sg:classifiers":[
        {
            "category":"Retail",
            "subcategory":"Auto Repair",
            "type":"Services"
        }
    ],
    "sg:phone":"+1 570 602 5283",
    "sg:postcode":"18640",
    "sg:province":"PA",
    "sg:tags":[
        "wrecker"
    ],
    "wof:name":"Falzone Towing",
    "wof:placetype":"venue"
},
  "geometry": {"coordinates":[-75.77529800000001,41.304291],"type":"Point"}
}