{
  "type": "Feature",
  "properties": {
    "iso:country":"US",
    "sg:address":"683 Clearfield Rd",
    "sg:city":"Nazareth",
    "sg:classifiers":[
        {
            "category":"Retail",
            "subcategory":"Laundry & Dry Cleaning",
            "type":"Services"
        }
    ],
    "sg:phone":"+1 610 746 0500",
    "sg:postcode":"18064",
    "sg:province":"PA",
    "sg:tags":[
        "cleaners",
        "rug",
        "carpet"
    ],
    "wof:name":"High-Tech Carpet Cleaning",
    "wof:placetype":"venue"
},
  "geometry": {"coordinates":[-75.339657,40.775368],"type":"Point"}
}