{
  "type": "Feature",
  "properties": {
    "iso:country":"US",
    "sg:address":"1186 Walnut Bottom Rd Frnt",
    "sg:city":"Carlisle",
    "sg:classifiers":[
        {
            "category":"Personal",
            "subcategory":"Barber",
            "type":"Services"
        }
    ],
    "sg:phone":"+1 717 245 2159",
    "sg:postcode":"17015",
    "sg:province":"PA",
    "wof:name":"Holiday Hair",
    "wof:placetype":"venue"
},
  "geometry": {"coordinates":[-77.21870199999999,40.180242],"type":"Point"}
}