{
  "type": "Feature",
  "properties": {
    "addr:full":"2724 Oak St Altoona PA 16601",
    "addr:housenumber":"2724",
    "addr:postcode":"16601",
    "addr:street":"Oak St",
    "iso:country":"US",
    "sg:address":"2724 Oak St",
    "sg:city":"Altoona",
    "sg:classifiers":[
        {
            "category":"Professional",
            "subcategory":"Business Services",
            "type":"Services"
        }
    ],
    "sg:phone":"+1 814 931 1526",
    "sg:postcode":"16601",
    "sg:province":"PA",
    "sg:tags":[
        "organizing",
        "services-household"
    ],
    "wof:name":"Stever Management",
    "wof:placetype":"venue"
},
  "geometry": {"coordinates":[-78.40489599999999,40.534875],"type":"Point"}
}