{
  "type": "Feature",
  "properties": {
    "iso:country":"US",
    "sg:address":"39 Pleasant Valley Dr",
    "sg:city":"Monongahela",
    "sg:classifiers":[
        {
            "category":"Organizations",
            "subcategory":"Community Association",
            "type":"Services"
        }
    ],
    "sg:phone":"+1   ",
    "sg:postcode":"15063",
    "sg:province":"PA",
    "wof:name":"Fallowfield Lions Club",
    "wof:placetype":"venue"
},
  "geometry": {"coordinates":[-79.944574,40.149955],"type":"Point"}
}