{
  "type": "Feature",
  "properties": {
    "iso:country":"US",
    "sg:address":"252 S State St Ste 3",
    "sg:city":"Newtown",
    "sg:classifiers":[
        {
            "category":"Personal",
            "subcategory":"Beauty Salon",
            "type":"Services"
        }
    ],
    "sg:phone":"+1 215 968 0103",
    "sg:postcode":"18940",
    "sg:province":"PA",
    "sg:tags":[
        "hair",
        "stylist"
    ],
    "wof:name":"Faces Hair Design",
    "wof:placetype":"venue"
},
  "geometry": {"coordinates":[-74.936307,40.224311],"type":"Point"}
}