{
  "type": "Feature",
  "properties": {
    "iso:country":"US",
    "sg:address":"736 Allegheny River Blvd",
    "sg:city":"Verona",
    "sg:classifiers":[
        {
            "category":"Banks & Credit Unions",
            "subcategory":"Bank",
            "type":"Services"
        }
    ],
    "sg:phone":"+1   ",
    "sg:postcode":"15147",
    "sg:province":"PA",
    "sg:tags":[
        "savings",
        "institution"
    ],
    "wof:name":"Parkvale Savings Bank",
    "wof:placetype":"venue"
},
  "geometry": {"coordinates":[-79.843041,40.505956],"type":"Point"}
}