{
  "type": "Feature",
  "properties": {
    "addr:full":"2330 Aramingo Ave Philadelphia PA 19125",
    "addr:housenumber":"2330",
    "addr:postcode":"19125",
    "addr:street":"Aramingo Ave",
    "iso:country":"US",
    "sg:address":"2330 Aramingo Ave",
    "sg:city":"Philadelphia",
    "sg:classifiers":[
        {
            "category":"Autos & Motor Vehicles",
            "subcategory":"Fuel & Gas Station",
            "type":"Retail Goods"
        }
    ],
    "sg:phone":"+1 215 739 3807",
    "sg:postcode":"19125",
    "sg:province":"PA",
    "sg:tags":[
        "gasoline"
    ],
    "wof:name":"Exxon",
    "wof:placetype":"venue"
},
  "geometry": {"coordinates":[-75.12188500000001,39.974711],"type":"Point"}
}