{
  "type": "Feature",
  "properties": {
    "addr:full":"283 S Main St Pittston PA 18640",
    "addr:housenumber":"283",
    "addr:postcode":"18640",
    "addr:street":"S Main St",
    "iso:country":"US",
    "sg:address":"283 S Main St",
    "sg:city":"Pittston",
    "sg:classifiers":[
        {
            "category":"Autos & Motor Vehicles",
            "subcategory":"Automobile Sales",
            "type":"Retail Goods"
        },
        {
            "category":"Professional",
            "subcategory":"Business Services",
            "type":"Services"
        }
    ],
    "sg:phone":"+1 570 654 8605",
    "sg:postcode":"18640",
    "sg:province":"PA",
    "sg:tags":[
        "notary",
        "used"
    ],
    "wof:name":"Allan's Auto Sales",
    "wof:placetype":"venue"
},
  "geometry": {"coordinates":[-75.796054,41.316039],"type":"Point"}
}