{
  "type": "Feature",
  "properties": {
    "addr:full":"1580 Charlestown Rd Phoenixville PA 19460",
    "addr:housenumber":"1580",
    "addr:postcode":"19460",
    "addr:street":"Charlestown Rd",
    "iso:country":"US",
    "sg:address":"1580 Charlestown Rd",
    "sg:city":"Phoenixville",
    "sg:classifiers":[
        {
            "category":"Education",
            "subcategory":"School",
            "type":"Public Place"
        }
    ],
    "sg:phone":"+1   ",
    "sg:postcode":"19460",
    "sg:province":"PA",
    "wof:name":"Center For Arts & Technology",
    "wof:placetype":"venue"
},
  "geometry": {"coordinates":[-75.54274599999999,40.118399],"type":"Point"}
}