{
  "type": "Feature",
  "properties": {
    "addr:full":"1500 Ridgeview Dr Allentown PA 18104",
    "addr:housenumber":"1500",
    "addr:postcode":"18104",
    "addr:street":"Ridgeview Dr",
    "iso:country":"US",
    "sg:address":"1500 Ridgeview Dr",
    "sg:city":"Allentown",
    "sg:classifiers":[
        {
            "category":"Organizations",
            "subcategory":"Religious Organization",
            "type":"Services"
        }
    ],
    "sg:phone":"+1 610 398 1900",
    "sg:postcode":"18104",
    "sg:province":"PA",
    "sg:website":"www.sijpa.org",
    "wof:name":"Shia Ithna-Asheri Jamaat of Pennsylvania",
    "wof:placetype":"venue"
},
  "geometry": {"coordinates":[-75.562798,40.610298],"type":"Point"}
}