{
  "type": "Feature",
  "properties": {
    "iso:country":"US",
    "sg:address":"2550 Kingston Rd Suite 303",
    "sg:city":"York",
    "sg:classifiers":[
        {
            "category":"Professional",
            "subcategory":"Accounting & Tax Preparation",
            "type":"Services"
        }
    ],
    "sg:phone":"+1 717 801 1127",
    "sg:postcode":"17402",
    "sg:province":"PA",
    "sg:tags":[
        "bookkeeping",
        "return",
        "representative",
        "preparation-business",
        "taxes-consultants"
    ],
    "sg:website":"http://www.firstcapitaltax.com/",
    "wof:name":"First Capital Tax and Accounting Services",
    "wof:placetype":"venue"
},
  "geometry": {"coordinates":[-76.6757,39.970483],"type":"Point"}
}