{
  "type": "Feature",
  "properties": {
    "iso:country":"US",
    "sg:address":"298 Mc Allister Church Rd",
    "sg:city":"Carlisle",
    "sg:classifiers":[
        {
            "category":"Shopping",
            "subcategory":"Florist",
            "type":"Retail Goods"
        }
    ],
    "sg:phone":"+1   ",
    "sg:postcode":"17013",
    "sg:province":"PA",
    "sg:tags":[
        "landscape"
    ],
    "wof:name":"Moutian Lakes Farm Market",
    "wof:placetype":"venue"
},
  "geometry": {"coordinates":[-77.273647,40.201428],"type":"Point"}
}