{
  "type": "Feature",
  "properties": {
    "iso:country":"US",
    "sg:address":"411 Doylestown Rd Suite J-2",
    "sg:city":"Montgomeryville",
    "sg:classifiers":[
        {
            "category":"Shopping",
            "subcategory":"Pets & Pet Supplies",
            "type":"Retail Goods"
        },
        {
            "category":"Retail",
            "subcategory":"Veterinary Services",
            "type":"Services"
        },
        {
            "category":"Retail",
            "subcategory":"Animal Services",
            "type":"Services"
        }
    ],
    "sg:phone":"+1 215 361 3800",
    "sg:postcode":"19446",
    "sg:province":"PA",
    "sg:tags":[
        "veterinarian",
        "store"
    ],
    "wof:name":"American Pet Care Center",
    "wof:placetype":"venue"
},
  "geometry": {"coordinates":[-75.241165,40.249115],"type":"Point"}
}