{
  "type": "Feature",
  "properties": {
    "addr:full":"1415 Jefferson Ave Washington PA 15301",
    "addr:housenumber":"1415",
    "addr:postcode":"15301",
    "addr:street":"Jefferson Ave",
    "iso:country":"US",
    "sg:address":"1415 Jefferson Ave",
    "sg:city":"Washington",
    "sg:classifiers":[
        {
            "category":"Recreation",
            "type":"Entertainment"
        }
    ],
    "sg:phone":"+1 724 228 4226",
    "sg:postcode":"15301",
    "sg:province":"PA",
    "sg:tags":[
        "sport",
        "amateur",
        "center",
        "team"
    ],
    "wof:name":"Brownson House",
    "wof:placetype":"venue"
},
  "geometry": {"coordinates":[-80.269402,40.186901],"type":"Point"}
}