{
  "type": "Feature",
  "properties": {
    "iso:country":"US",
    "sg:address":"9 Weirwood Rd",
    "sg:city":"Wayne",
    "sg:classifiers":[
        {
            "category":"Building & Trades",
            "subcategory":"Construction",
            "type":"Services"
        }
    ],
    "sg:phone":"+1 610 687 9330",
    "sg:postcode":"19087",
    "sg:province":"PA",
    "sg:tags":[
        "wallcoverings-installation",
        "wallpaper",
        "painting",
        "contractor"
    ],
    "wof:name":"David Ryder Painting",
    "wof:placetype":"venue"
},
  "geometry": {"coordinates":[-75.36601400000001,40.057868],"type":"Point"}
}