{
  "type": "Feature",
  "properties": {
    "addr:full":"227 Whiteland Ave Downingtown PA 19335",
    "addr:housenumber":"227",
    "addr:postcode":"19335",
    "addr:street":"Whiteland Ave",
    "iso:country":"US",
    "sg:address":"227 Whiteland Ave",
    "sg:city":"Downingtown",
    "sg:classifiers":[
        {
            "category":"Shopping",
            "subcategory":"Music",
            "type":"Retail Goods"
        }
    ],
    "sg:phone":"+1   ",
    "sg:postcode":"19335",
    "sg:province":"PA",
    "sg:tags":[
        "compact",
        "accessory",
        "record",
        "disc",
        "tape",
        "t"
    ],
    "wof:name":"Beggars Banquet",
    "wof:placetype":"venue"
},
  "geometry": {"coordinates":[-75.69389700000001,40.009679],"type":"Point"}
}