{
  "type": "Feature",
  "properties": {
    "iso:country":"US",
    "sg:address":"731 E Dorset St",
    "sg:city":"Philadelphia",
    "sg:classifiers":[
        {
            "category":"Professional",
            "subcategory":"Management & Consulting",
            "type":"Services"
        }
    ],
    "sg:phone":"+1 215 843 3325",
    "sg:postcode":"19119",
    "sg:province":"PA",
    "sg:tags":[
        "consultant",
        "business"
    ],
    "wof:name":"MIS Consultants",
    "wof:placetype":"venue"
},
  "geometry": {"coordinates":[-75.175659,40.062865],"type":"Point"}
}