{
  "type": "Feature",
  "properties": {
    "addr:full":"18th & Locust Philadelphia PA 19102",
    "addr:postcode":"19102",
    "iso:country":"US",
    "sg:address":"18th & Locust",
    "sg:city":"Philadelphia",
    "sg:classifiers":[
        {
            "category":"Shopping",
            "subcategory":"Florist",
            "type":"Retail Goods"
        }
    ],
    "sg:phone":"+1 215 732 1100",
    "sg:postcode":"19102",
    "sg:province":"PA",
    "wof:name":"Thoughts In Bloom",
    "wof:placetype":"venue"
},
  "geometry": {"coordinates":[-75.17092700000001,39.949],"type":"Point"}
}