{
  "type": "Feature",
  "properties": {
    "iso:country":"US",
    "sg:address":"111 W Long Ave",
    "sg:city":"Du Bois",
    "sg:classifiers":[
        {
            "category":"Real Estate",
            "subcategory":"Real Estate Operator",
            "type":"Services"
        }
    ],
    "sg:phone":"+1 814 371 1200",
    "sg:postcode":"15801",
    "sg:province":"PA",
    "sg:tags":[
        "building",
        "apartment"
    ],
    "wof:name":"Saint Michael Terrace",
    "wof:placetype":"venue"
},
  "geometry": {"coordinates":[-78.764191,41.120284],"type":"Point"}
}