{
  "type": "Feature",
  "properties": {
    "iso:country":"US",
    "sg:address":"167 Church Rd",
    "sg:city":"Leechburg",
    "sg:classifiers":[
        {
            "category":"Building & Trades",
            "subcategory":"Construction",
            "type":"Services"
        }
    ],
    "sg:phone":"+1 724 845 2330",
    "sg:postcode":"15656",
    "sg:province":"PA",
    "sg:tags":[
        "excavation",
        "contractor"
    ],
    "wof:name":"H & L Excavation",
    "wof:placetype":"venue"
},
  "geometry": {"coordinates":[-79.657375,40.647434],"type":"Point"}
}