{
  "type": "Feature",
  "properties": {
    "iso:country":"US",
    "sg:address":"200 Neshaminy Mall",
    "sg:city":"Bensalem",
    "sg:classifiers":[
        {
            "category":"Shopping",
            "subcategory":"Department Store",
            "type":"Retail Goods"
        },
        {
            "category":"Shopping",
            "subcategory":"Optician",
            "type":"Retail Goods"
        }
    ],
    "sg:phone":"+1 215 953 5900",
    "sg:postcode":"19020",
    "sg:province":"PA",
    "sg:tags":[
        "eyewear"
    ],
    "wof:name":"Boscov's Hearing Aid Ctr",
    "wof:placetype":"venue"
},
  "geometry": {"coordinates":[-74.954903,40.1366],"type":"Point"}
}