{
  "type": "Feature",
  "properties": {
    "iso:country":"US",
    "sg:address":"530 Vera Cir",
    "sg:city":"Bethlehem",
    "sg:classifiers":[
        {
            "category":"Arena",
            "subcategory":"Sports Club",
            "type":"Entertainment"
        }
    ],
    "sg:phone":"+1 610 867 5064",
    "sg:postcode":"18017",
    "sg:province":"PA",
    "sg:tags":[
        "martial art",
        "instruction"
    ],
    "wof:name":"M Power Martial Arts",
    "wof:placetype":"venue"
},
  "geometry": {"coordinates":[-75.3671,40.645444],"type":"Point"}
}