{
  "type": "Feature",
  "properties": {
    "addr:full":"841 N 18th St Allentown PA 18104",
    "addr:housenumber":"841",
    "addr:postcode":"18104",
    "addr:street":"N 18Th St",
    "iso:country":"US",
    "sg:address":"841 N 18th St",
    "sg:city":"Allentown",
    "sg:classifiers":[
        {
            "category":"Building & Trades",
            "subcategory":"Construction",
            "type":"Services"
        }
    ],
    "sg:phone":"+1   ",
    "sg:postcode":"18104",
    "sg:province":"PA",
    "sg:tags":[
        "contractor"
    ],
    "wof:name":"Capco Sheet Metal",
    "wof:placetype":"venue"
},
  "geometry": {"coordinates":[-75.500281,40.608685],"type":"Point"}
}