{
  "type": "Feature",
  "properties": {
    "iso:country":"US",
    "sg:address":"2340 W Lehigh Ave",
    "sg:city":"Philadelphia",
    "sg:classifiers":[
        {
            "category":"Organizations",
            "subcategory":"Religious Organization",
            "type":"Services"
        }
    ],
    "sg:phone":"+1 215 225 2127",
    "sg:postcode":"19132",
    "sg:province":"PA",
    "wof:name":"St Martin Deporres Center",
    "wof:placetype":"venue"
},
  "geometry": {"coordinates":[-75.169899,39.995998],"type":"Point"}
}