{
  "type": "Feature",
  "properties": {
    "addr:full":"255 Butler Ave Lancaster PA 17601",
    "addr:housenumber":"255",
    "addr:postcode":"17601",
    "addr:street":"Butler Ave",
    "iso:country":"US",
    "sg:address":"255 Butler Ave",
    "sg:city":"Lancaster",
    "sg:classifiers":[
        {
            "category":"Professional",
            "subcategory":"Lawyer & Legal Services",
            "type":"Services"
        },
        {
            "category":"Banks & Credit Unions",
            "subcategory":"Financial Services",
            "type":"Services"
        }
    ],
    "sg:phone":"+1 717 209 7077",
    "sg:postcode":"17601",
    "sg:province":"PA",
    "sg:tags":[
        "attorney",
        "law",
        "bankruptcy"
    ],
    "sg:website":"http://www.cdllawoffice.com/",
    "wof:name":"Case, DiGiamberardino & Lutz PC",
    "wof:placetype":"venue"
},
  "geometry": {"coordinates":[-76.301215,40.067285],"type":"Point"}
}