{
  "type": "Feature",
  "properties": {
    "iso:country":"US",
    "sg:address":"132 Parkridge Apt C",
    "sg:city":"Apollo",
    "sg:classifiers":[
        {
            "category":"Restaurant",
            "type":"Food & Drink"
        }
    ],
    "sg:phone":"+1 724 478 1902",
    "sg:postcode":"15613",
    "sg:province":"PA",
    "sg:tags":[
        "pizza"
    ],
    "wof:name":"Tucks Pizza",
    "wof:placetype":"venue"
},
  "geometry": {"coordinates":[-79.574495,40.576361],"type":"Point"}
}