{
  "type": "Feature",
  "properties": {
    "iso:country":"US",
    "sg:address":"600 S George St",
    "sg:city":"York",
    "sg:classifiers":[
        {
            "category":"Autos & Motor Vehicles",
            "subcategory":"Automobile Sales",
            "type":"Retail Goods"
        }
    ],
    "sg:phone":"+1 717 845 4204",
    "sg:postcode":"17403",
    "sg:province":"PA",
    "sg:tags":[
        "used"
    ],
    "wof:name":"George Street Auto Sales",
    "wof:placetype":"venue"
},
  "geometry": {"coordinates":[-76.723221,39.953617],"type":"Point"}
}