{
  "type": "Feature",
  "properties": {
    "addr:full":"1025 Old Wyomissing Rd Reading PA 19611",
    "addr:housenumber":"1025",
    "addr:postcode":"19611",
    "addr:street":"Old Wyomissing Rd",
    "iso:country":"US",
    "sg:address":"1025 Old Wyomissing Rd",
    "sg:city":"Reading",
    "sg:classifiers":[
        {
            "category":"Education",
            "subcategory":"School",
            "type":"Public Place"
        }
    ],
    "sg:phone":"+1 610 371 5919",
    "sg:postcode":"19611",
    "sg:province":"PA",
    "wof:name":"Reading Education Center",
    "wof:placetype":"venue"
},
  "geometry": {"coordinates":[-75.95191800000001,40.324698],"type":"Point"}
}