{
  "type": "Feature",
  "properties": {
    "iso:country":"US",
    "sg:address":"324 2nd Street Pike",
    "sg:city":"Southampton",
    "sg:classifiers":[
        {
            "category":"Shopping",
            "subcategory":"Bicycles & Sporting Goods",
            "type":"Retail Goods"
        }
    ],
    "sg:phone":"+1 215 357 7381",
    "sg:postcode":"18966",
    "sg:province":"PA",
    "sg:tags":[
        "bait",
        "fishing"
    ],
    "wof:name":"Robinson's Gunsmithing",
    "wof:placetype":"venue"
},
  "geometry": {"coordinates":[-75.045873,40.16759],"type":"Point"}
}