{
  "type": "Feature",
  "properties": {
    "iso:country":"US",
    "sg:address":"116 Heather Dr",
    "sg:city":"New Hope",
    "sg:classifiers":[
        {
            "category":"Professional",
            "type":"Services"
        },
        {
            "category":"Manufacturing",
            "subcategory":"Tools & Machinery",
            "type":"Manufacturing & Wholesale Goods"
        }
    ],
    "sg:phone":"+1 215 862 1678",
    "sg:postcode":"18938",
    "sg:province":"PA",
    "sg:tags":[
        "bearing",
        "mfg",
        "friction",
        "anti",
        "seal",
        "establishment"
    ],
    "wof:name":"SKF USA Inc",
    "wof:placetype":"venue"
},
  "geometry": {"coordinates":[-74.991525,40.346559],"type":"Point"}
}