{
  "type": "Feature",
  "properties": {
    "iso:country":"US",
    "sg:address":"304 Railroad St",
    "sg:city":"Danville",
    "sg:classifiers":[
        {
            "category":"Professional",
            "type":"Services"
        }
    ],
    "sg:phone":"+1 570 275 5676",
    "sg:postcode":"17821",
    "sg:province":"PA",
    "wof:name":"Darla Farr Lsw",
    "wof:placetype":"venue"
},
  "geometry": {"coordinates":[-76.60997,40.959471],"type":"Point"}
}