{
  "type": "Feature",
  "properties": {
    "iso:country":"US",
    "sg:address":"1063 Neely Rd",
    "sg:city":"Clarion",
    "sg:classifiers":[
        {
            "category":"Home & Garden",
            "subcategory":"Household Appliances",
            "type":"Retail Goods"
        }
    ],
    "sg:phone":"+1 814 745 3121",
    "sg:postcode":"16214",
    "sg:province":"PA",
    "sg:tags":[
        "equipment",
        "purifying",
        "cleaning",
        "air"
    ],
    "wof:name":"Pure Life",
    "wof:placetype":"venue"
},
  "geometry": {"coordinates":[-79.422768,41.157566],"type":"Point"}
}