{
  "type": "Feature",
  "properties": {
    "iso:country":"US",
    "sg:address":"1002 W York St",
    "sg:city":"Philadelphia",
    "sg:classifiers":[
        {
            "category":"Retail",
            "subcategory":"Repair Shop",
            "type":"Services"
        }
    ],
    "sg:phone":"+1   ",
    "sg:postcode":"19133",
    "sg:province":"PA",
    "wof:name":"Rucker Gene Refinishing",
    "wof:placetype":"venue"
},
  "geometry": {"coordinates":[-75.150226,39.988606],"type":"Point"}
}