{
  "type": "Feature",
  "properties": {
    "addr:full":"1133 Hyatt St Chester PA 19013",
    "addr:housenumber":"1133",
    "addr:postcode":"19013",
    "addr:street":"Hyatt St",
    "iso:country":"US",
    "sg:address":"1133 Hyatt St",
    "sg:city":"Chester",
    "sg:classifiers":[
        {
            "category":"Real Estate",
            "subcategory":"Real Estate Agent",
            "type":"Services"
        }
    ],
    "sg:phone":"+1   ",
    "sg:postcode":"19013",
    "sg:province":"PA",
    "wof:name":"Jeffereys Sqaure",
    "wof:placetype":"venue"
},
  "geometry": {"coordinates":[-75.35355,39.858927],"type":"Point"}
}