{
  "type": "Feature",
  "properties": {
    "iso:country":"US",
    "sg:address":"118 Kittanning St",
    "sg:city":"Chicora",
    "sg:classifiers":[
        {
            "category":"Real Estate",
            "subcategory":"Real Estate Operator",
            "type":"Services"
        }
    ],
    "sg:phone":"+1 724 445 3999",
    "sg:postcode":"16025",
    "sg:province":"PA",
    "sg:tags":[
        "apartment"
    ],
    "wof:name":"Chicora Commons LTD Prtnshp",
    "wof:placetype":"venue"
},
  "geometry": {"coordinates":[-79.73948900000001,40.950548],"type":"Point"}
}