{
  "type": "Feature",
  "properties": {
    "iso:country":"US",
    "sg:address":"1857 N Broad St",
    "sg:city":"Lansdale",
    "sg:classifiers":[
        {
            "category":"Professional",
            "subcategory":"Management & Consulting",
            "type":"Services"
        }
    ],
    "sg:phone":"+1   ",
    "sg:postcode":"19446",
    "sg:province":"PA",
    "sg:tags":[
        "regional",
        "administrative"
    ],
    "wof:name":"Keystone Regional Office",
    "wof:placetype":"venue"
},
  "geometry": {"coordinates":[-75.266655,40.25731],"type":"Point"}
}