{
  "type": "Feature",
  "properties": {
    "addr:full":"360 E Wyomissing Ave Mohnton PA 19540",
    "addr:housenumber":"360",
    "addr:postcode":"19540",
    "addr:street":"E Wyomissing Ave",
    "iso:country":"US",
    "sg:address":"360 E Wyomissing Ave",
    "sg:city":"Mohnton",
    "sg:classifiers":[
        {
            "category":"Building & Trades",
            "subcategory":"Construction",
            "type":"Services"
        }
    ],
    "sg:phone":"+1   ",
    "sg:postcode":"19540",
    "sg:province":"PA",
    "sg:tags":[
        "hanging",
        "contractor"
    ],
    "wof:name":"West Lancaster Ave Associates",
    "wof:placetype":"venue"
},
  "geometry": {"coordinates":[-75.979057,40.291323],"type":"Point"}
}