{
  "type": "Feature",
  "properties": {
    "addr:full":"1406 E Mermaid Ln Glenside PA 19038",
    "addr:housenumber":"1406",
    "addr:postcode":"19038",
    "addr:street":"E Mermaid Ln",
    "iso:country":"US",
    "sg:address":"1406 E Mermaid Ln",
    "sg:city":"Glenside",
    "sg:classifiers":[
        {
            "category":"Manufacturing",
            "subcategory":"Textiles",
            "type":"Manufacturing & Wholesale Goods"
        }
    ],
    "sg:phone":"+1 215 922 8717",
    "sg:postcode":"19038",
    "sg:province":"PA",
    "sg:tags":[
        "fabric"
    ],
    "wof:name":"Bassett Mc Nab Co",
    "wof:placetype":"venue"
},
  "geometry": {"coordinates":[-75.179777,40.085435],"type":"Point"}
}