{
  "type": "Feature",
  "properties": {
    "iso:country":"US",
    "sg:address":"287 Camp Green Lane Rd",
    "sg:city":"Sumneytown",
    "sg:classifiers":[
        {
            "category":"Wholesale",
            "subcategory":"Durable Goods & Equipment",
            "type":"Manufacturing & Wholesale Goods"
        }
    ],
    "sg:phone":"+1 215 234 8830",
    "sg:postcode":"18054",
    "sg:province":"PA",
    "sg:tags":[
        "fire",
        "extinguisher"
    ],
    "wof:name":"Fire Protection Svc Co",
    "wof:placetype":"venue"
},
  "geometry": {"coordinates":[-75.42970099999999,40.327992],"type":"Point"}
}