{
  "type": "Feature",
  "properties": {
    "iso:country":"US",
    "sg:address":"495 Mansfield Ave",
    "sg:city":"Pittsburgh",
    "sg:classifiers":[
        {
            "category":"Professional",
            "subcategory":"Computer Services",
            "type":"Services"
        }
    ],
    "sg:phone":"+1 877 944 3822",
    "sg:postcode":"15205",
    "sg:province":"PA",
    "sg:tags":[
        "gift-card",
        "gift-cards",
        "prepaid-cards",
        "visa-gift-card",
        "mastercard-gift-card",
        "mastercard",
        "visa",
        "greeting-card"
    ],
    "sg:website":"http://www.giftcards.com",
    "wof:name":"GiftCards.com",
    "wof:placetype":"venue"
},
  "geometry": {"coordinates":[-80.054046,40.420334],"type":"Point"}
}