{
  "type": "Feature",
  "properties": {
    "iso:country":"US",
    "sg:address":"1550 Cherry Ln",
    "sg:city":"Jenkintown",
    "sg:classifiers":[
        {
            "category":"Food & Beverages",
            "subcategory":"Specialty",
            "type":"Retail Goods"
        }
    ],
    "sg:phone":"+1   ",
    "sg:postcode":"19046",
    "sg:province":"PA",
    "wof:name":"Genes Health World",
    "wof:placetype":"venue"
},
  "geometry": {"coordinates":[-75.111465,40.111504],"type":"Point"}
}