{
  "type": "Feature",
  "properties": {
    "iso:country":"US",
    "sg:address":"57 Main St",
    "sg:city":"Harleysville",
    "sg:classifiers":[
        {
            "category":"Organizations",
            "subcategory":"Community Association",
            "type":"Services"
        }
    ],
    "sg:phone":"+1   ",
    "sg:postcode":"19438",
    "sg:province":"PA",
    "wof:name":"Analytical Laboratory Services",
    "wof:placetype":"venue"
},
  "geometry": {"coordinates":[-75.36110600000001,40.257215],"type":"Point"}
}