{
  "type": "Feature",
  "properties": {
    "iso:country":"US",
    "sg:address":"90 S Newtown Street Rd",
    "sg:city":"Newtown Square",
    "sg:classifiers":[
        {
            "category":"Government",
            "subcategory":"Office",
            "type":"Public Place"
        }
    ],
    "sg:phone":"+1   ",
    "sg:postcode":"19073",
    "sg:province":"PA",
    "sg:tags":[
        "collection"
    ],
    "wof:name":"Newtown Square District Office",
    "wof:placetype":"venue"
},
  "geometry": {"coordinates":[-75.397936,39.982102],"type":"Point"}
}