{
  "type": "Feature",
  "properties": {
    "iso:country":"US",
    "sg:address":"8 Washington Ave # &",
    "sg:city":"Philadelphia",
    "sg:classifiers":[
        {
            "category":"Food & Beverages",
            "subcategory":"Meat & Fish",
            "type":"Retail Goods"
        }
    ],
    "sg:phone":"+1 215 336 8333",
    "sg:postcode":"19147",
    "sg:province":"PA",
    "sg:tags":[
        "seafood",
        "market"
    ],
    "wof:name":"Captain Jesse G Inc",
    "wof:placetype":"venue"
},
  "geometry": {"coordinates":[-75.15709699999999,39.938],"type":"Point"}
}