{
  "type": "Feature",
  "properties": {
    "addr:full":"1929 McCracken Dr New Castle PA 16101",
    "addr:housenumber":"1929",
    "addr:postcode":"16101",
    "addr:street":"Mccracken Dr",
    "iso:country":"US",
    "sg:address":"1929 McCracken Dr",
    "sg:city":"New Castle",
    "sg:classifiers":[
        {
            "category":"Organizations",
            "subcategory":"Labor Organization",
            "type":"Services"
        }
    ],
    "sg:phone":"+1 724 652 0799",
    "sg:postcode":"16101",
    "sg:province":"PA",
    "wof:name":"United Transportation Union",
    "wof:placetype":"venue"
},
  "geometry": {"coordinates":[-80.378204,40.992059],"type":"Point"}
}