{
  "type": "Feature",
  "properties": {
    "addr:full":"877 Pump Station Rd Summerhill PA 15958",
    "addr:housenumber":"877",
    "addr:postcode":"15958",
    "addr:street":"Pump Station Rd",
    "iso:country":"US",
    "sg:address":"877 Pump Station Rd",
    "sg:city":"Summerhill",
    "sg:classifiers":[
        {
            "category":"Building & Trades",
            "subcategory":"Construction",
            "type":"Services"
        }
    ],
    "sg:phone":"+1   ",
    "sg:postcode":"15958",
    "sg:province":"PA",
    "sg:tags":[
        "contractor"
    ],
    "wof:name":"Jeff Hampton",
    "wof:placetype":"venue"
},
  "geometry": {"coordinates":[-78.690004,40.381952],"type":"Point"}
}