{
  "type": "Feature",
  "properties": {
    "addr:full":"2 New Market St Freeburg PA 17827",
    "addr:housenumber":"2",
    "addr:postcode":"17827",
    "addr:street":"New Market St",
    "iso:country":"US",
    "sg:address":"2 New Market St",
    "sg:city":"Freeburg",
    "sg:classifiers":[
        {
            "category":"Building & Trades",
            "subcategory":"Construction",
            "type":"Services"
        }
    ],
    "sg:phone":"+1 570 374 0690",
    "sg:postcode":"17827",
    "sg:province":"PA",
    "sg:tags":[
        "house",
        "siding",
        "contractor"
    ],
    "wof:name":"Joel Newnan Home Improvement",
    "wof:placetype":"venue"
},
  "geometry": {"coordinates":[-76.941368,40.764779],"type":"Point"}
}