{
  "type": "Feature",
  "properties": {
    "iso:country":"US",
    "sg:address":"11000 Parker Dr",
    "sg:city":"Irwin",
    "sg:classifiers":[
        {
            "category":"Manufacturing",
            "subcategory":"Tools & Machinery",
            "type":"Manufacturing & Wholesale Goods"
        }
    ],
    "sg:phone":"+1 412 751 5122",
    "sg:postcode":"15642",
    "sg:province":"PA",
    "sg:tags":[
        "industrial",
        "mfg"
    ],
    "wof:name":"Nedco",
    "wof:placetype":"venue"
},
  "geometry": {"coordinates":[-79.77789,40.33416],"type":"Point"}
}