{
  "type": "Feature",
  "properties": {
    "iso:country":"US",
    "sg:address":"40 E Market St",
    "sg:city":"Blairsville",
    "sg:classifiers":[
        {
            "category":"Health Services",
            "subcategory":"Podiatrist",
            "type":"Services"
        }
    ],
    "sg:phone":"+1   ",
    "sg:postcode":"15717",
    "sg:province":"PA",
    "wof:name":"Dr Richard L Reilly Jr",
    "wof:placetype":"venue"
},
  "geometry": {"coordinates":[-79.263499,40.430817],"type":"Point"}
}