{
  "type": "Feature",
  "properties": {
    "iso:country":"US",
    "sg:address":"6349 Crescent Ave",
    "sg:city":"Bensalem",
    "sg:classifiers":[
        {
            "category":"Professional",
            "subcategory":"Detective & Security Services",
            "type":"Services"
        }
    ],
    "sg:phone":"+1 215 702 0968",
    "sg:postcode":"19020",
    "sg:province":"PA",
    "sg:tags":[
        "car"
    ],
    "wof:name":"New Security",
    "wof:placetype":"venue"
},
  "geometry": {"coordinates":[-74.901195,40.132078],"type":"Point"}
}