{
  "type": "Feature",
  "properties": {
    "iso:country":"US",
    "sg:address":"23 Canal St",
    "sg:city":"Greenville",
    "sg:classifiers":[
        {
            "category":"Insurance",
            "subcategory":"Insurance Agent",
            "type":"Services"
        }
    ],
    "sg:phone":"+1 724 588 4331",
    "sg:postcode":"16125",
    "sg:province":"PA",
    "wof:name":"Eckles, Dennis R Agency",
    "wof:placetype":"venue"
},
  "geometry": {"coordinates":[-80.38861300000001,41.404395],"type":"Point"}
}