{
  "type": "Feature",
  "properties": {
    "iso:country":"US",
    "sg:address":"2619 New Butler Rd",
    "sg:city":"New Castle",
    "sg:classifiers":[
        {
            "category":"Real Estate",
            "subcategory":"Real Estate Agent",
            "type":"Services"
        }
    ],
    "sg:phone":"+1   ",
    "sg:postcode":"16101",
    "sg:province":"PA",
    "wof:name":"3 D Properties",
    "wof:placetype":"venue"
},
  "geometry": {"coordinates":[-80.28885699999999,40.97663],"type":"Point"}
}