{
  "type": "Feature",
  "properties": {
    "iso:country":"US",
    "sg:address":"206 E Main St",
    "sg:city":"Lock Haven",
    "sg:classifiers":[
        {
            "category":"Wholesale",
            "subcategory":"Electrical",
            "type":"Manufacturing & Wholesale Goods"
        }
    ],
    "sg:phone":"+1 570 748 7834",
    "sg:postcode":"17745",
    "sg:province":"PA",
    "sg:tags":[
        "equipment",
        "electric",
        "supply"
    ],
    "wof:name":"Denney Electric Supply Co",
    "wof:placetype":"venue"
},
  "geometry": {"coordinates":[-77.44386299999999,41.136891],"type":"Point"}
}