{
  "type": "Feature",
  "properties": {
    "iso:country":"US",
    "sg:address":"428 N Ott St",
    "sg:city":"Allentown",
    "sg:classifiers":[
        {
            "category":"Organizations",
            "subcategory":"Religious Organization",
            "type":"Services"
        }
    ],
    "sg:phone":"+1 610 782 9386",
    "sg:postcode":"18104",
    "sg:province":"PA",
    "sg:tags":[
        "clergy"
    ],
    "wof:name":"David P Focht Rev",
    "wof:placetype":"venue"
},
  "geometry": {"coordinates":[-75.51511000000001,40.597266],"type":"Point"}
}