{
  "type": "Feature",
  "properties": {
    "iso:country":"US",
    "sg:address":"300 Lionville Station Rd",
    "sg:city":"Chester Springs",
    "sg:classifiers":[
        {
            "category":"Freight",
            "type":"Transportation"
        }
    ],
    "sg:phone":"+1   ",
    "sg:postcode":"19425",
    "sg:province":"PA",
    "sg:tags":[
        "petroleum",
        "carrier",
        "based",
        "common"
    ],
    "wof:name":"Penn Tank Lines Inc",
    "wof:placetype":"venue"
},
  "geometry": {"coordinates":[-75.658102,40.076143],"type":"Point"}
}