{
  "type": "Feature",
  "properties": {
    "iso:country":"US",
    "sg:address":"3715 Elmwood Ave",
    "sg:city":"Erie",
    "sg:classifiers":[
        {
            "category":"Health Services",
            "subcategory":"Chiropractor",
            "type":"Services"
        }
    ],
    "sg:phone":"+1   ",
    "sg:postcode":"16508",
    "sg:province":"PA",
    "wof:name":"Roll Donald V Dr",
    "wof:placetype":"venue"
},
  "geometry": {"coordinates":[-80.09293700000001,42.092667],"type":"Point"}
}