{
  "type": "Feature",
  "properties": {
    "iso:country":"US",
    "sg:address":"10 Snyder Ave",
    "sg:city":"Pine Grove",
    "sg:classifiers":[
        {
            "category":"Wholesale",
            "subcategory":"Farm Supplies",
            "type":"Manufacturing & Wholesale Goods"
        },
        {
            "category":"Shopping",
            "type":"Retail Goods"
        }
    ],
    "sg:phone":"+1 570 345 3309",
    "sg:postcode":"17963",
    "sg:province":"PA",
    "sg:tags":[
        "feed",
        "merchandise"
    ],
    "wof:name":"Lehr's Feed & Farm Supplies",
    "wof:placetype":"venue"
},
  "geometry": {"coordinates":[-76.38473399999999,40.549216],"type":"Point"}
}