{
  "type": "Feature",
  "properties": {
    "addr:full":"214 W Main St Bath PA 18014",
    "addr:housenumber":"214",
    "addr:postcode":"18014",
    "addr:street":"W Main St",
    "iso:country":"US",
    "sg:address":"214 W Main St",
    "sg:city":"Bath",
    "sg:classifiers":[
        {
            "category":"Travel",
            "subcategory":"Travel Agent",
            "type":"Entertainment"
        }
    ],
    "sg:phone":"+1 610 837 6731",
    "sg:postcode":"18014",
    "sg:province":"PA",
    "sg:tags":[
        "bureau",
        "passenger",
        "agency",
        "transportation",
        "arrangement"
    ],
    "wof:name":"Mary Fashion Travel Svc",
    "wof:placetype":"venue"
},
  "geometry": {"coordinates":[-75.394379,40.725883],"type":"Point"}
}