{
  "type": "Feature",
  "properties": {
    "iso:country":"US",
    "sg:address":"250 Mount Lebanon Blvd",
    "sg:city":"Pittsburgh",
    "sg:classifiers":[
        {
            "category":"Building & Trades",
            "subcategory":"Construction",
            "type":"Services"
        }
    ],
    "sg:phone":"+1   ",
    "sg:postcode":"15234",
    "sg:province":"PA",
    "sg:tags":[
        "contractor"
    ],
    "wof:name":"Laco Inc",
    "wof:placetype":"venue"
},
  "geometry": {"coordinates":[-80.040053,40.367575],"type":"Point"}
}