{
  "type": "Feature",
  "properties": {
    "iso:country":"US",
    "sg:address":"1405 Cottage Ave",
    "sg:city":"Bethlehem",
    "sg:classifiers":[
        {
            "category":"Real Estate",
            "subcategory":"Real Estate Agent",
            "type":"Services"
        }
    ],
    "sg:phone":"+1   ",
    "sg:postcode":"18018",
    "sg:province":"PA",
    "wof:name":"Onesorce Prty Mngmnt Hme Inprv",
    "wof:placetype":"venue"
},
  "geometry": {"coordinates":[-75.40342,40.615382],"type":"Point"}
}