{
  "type": "Feature",
  "properties": {
    "addr:full":"6250 Baltimore Ave Yeadon PA 19050",
    "addr:housenumber":"6250",
    "addr:postcode":"19050",
    "addr:street":"Baltimore Ave",
    "iso:country":"US",
    "sg:address":"6250 Baltimore Ave",
    "sg:city":"Yeadon",
    "sg:classifiers":[
        {
            "category":"Manufacturing",
            "subcategory":"Tools & Machinery",
            "type":"Manufacturing & Wholesale Goods"
        }
    ],
    "sg:phone":"+1 610 259 5534",
    "sg:postcode":"19050",
    "sg:province":"PA",
    "sg:tags":[
        "equipment",
        "janitor",
        "supply"
    ],
    "wof:name":"Ridgeway Industries Inc",
    "wof:placetype":"venue"
},
  "geometry": {"coordinates":[-75.249352,39.942448],"type":"Point"}
}