{
  "type": "Feature",
  "properties": {
    "iso:country":"US",
    "sg:address":"1109 W Main St",
    "sg:city":"Somerset",
    "sg:classifiers":[
        {
            "category":"Insurance",
            "subcategory":"Insurance Agent",
            "type":"Services"
        }
    ],
    "sg:phone":"+1 814 443 1696",
    "sg:postcode":"15501",
    "sg:province":"PA",
    "sg:tags":[
        "homeowner"
    ],
    "sg:website":"http://www.nationwide.com/agent/Somerset-PENNSYLVANIA-insurance-agent/donald-holsopple/office.html",
    "wof:name":"Donald B Holsopple - Nationwide Insurance",
    "wof:placetype":"venue"
},
  "geometry": {"coordinates":[-79.099358,40.00938],"type":"Point"}
}