{
  "type": "Feature",
  "properties": {
    "iso:country":"US",
    "sg:address":"1533 Monsey Ave",
    "sg:city":"Scranton",
    "sg:classifiers":[
        {
            "category":"Building & Trades",
            "subcategory":"Plumbing",
            "type":"Services"
        },
        {
            "category":"Wholesale",
            "subcategory":"Books, Periodicals, & Newspapers",
            "type":"Manufacturing & Wholesale Goods"
        }
    ],
    "sg:phone":"+1 570 963 9280",
    "sg:postcode":"18509",
    "sg:province":"PA",
    "sg:tags":[
        "boilers-wholesale",
        "clean",
        "boilers-repair",
        "manufacturer"
    ],
    "sg:website":"http://www.raypak.com",
    "wof:name":"Raypak, Inc.",
    "wof:placetype":"venue"
},
  "geometry": {"coordinates":[-75.65145800000001,41.427072],"type":"Point"}
}