{
  "type": "Feature",
  "properties": {
    "iso:country":"US",
    "sg:address":"160 Chapel View Dr",
    "sg:city":"Reinholds",
    "sg:classifiers":[
        {
            "category":"Organizations",
            "subcategory":"Religious Organization",
            "type":"Services"
        }
    ],
    "sg:phone":"+1 717 335 0515",
    "sg:postcode":"17569",
    "sg:province":"PA",
    "sg:tags":[
        "church"
    ],
    "wof:name":"Living Waters Mennonite",
    "wof:placetype":"venue"
},
  "geometry": {"coordinates":[-76.112415,40.265922],"type":"Point"}
}