{
  "type": "Feature",
  "properties": {
    "iso:country":"US",
    "sg:address":"1795 Brodhead Rd",
    "sg:city":"Aliquippa",
    "sg:classifiers":[
        {
            "category":"Utilities",
            "subcategory":"Fuel Oil & Lpg",
            "type":"Services"
        }
    ],
    "sg:phone":"+1 724 378 2000",
    "sg:postcode":"15001",
    "sg:province":"PA",
    "sg:tags":[
        "firewood"
    ],
    "wof:name":"Crystal Garden & Landscape Co",
    "wof:placetype":"venue"
},
  "geometry": {"coordinates":[-80.27142499999999,40.593702],"type":"Point"}
}