{
  "type": "Feature",
  "properties": {
    "iso:country":"US",
    "sg:address":"98 Highland Dr",
    "sg:city":"Media",
    "sg:classifiers":[
        {
            "category":"Professional",
            "subcategory":"Research",
            "type":"Services"
        }
    ],
    "sg:phone":"+1 610 666 1300",
    "sg:postcode":"19063",
    "sg:province":"PA",
    "sg:tags":[
        "laboratory"
    ],
    "wof:name":"Aquatic Laboratories Svc Inc",
    "wof:placetype":"venue"
},
  "geometry": {"coordinates":[-75.47837199999999,39.899519],"type":"Point"}
}