{
  "type": "Feature",
  "properties": {
    "iso:country":"US",
    "sg:address":"218 Smithfield Rd",
    "sg:city":"Masontown",
    "sg:classifiers":[
        {
            "category":"Farming",
            "subcategory":"Dairy Farm",
            "type":"Manufacturing & Wholesale Goods"
        }
    ],
    "sg:phone":"+1 724 583 2671",
    "sg:postcode":"15461",
    "sg:province":"PA",
    "wof:name":"City View Dairy Farms",
    "wof:placetype":"venue"
},
  "geometry": {"coordinates":[-79.89294700000001,39.846832],"type":"Point"}
}