{
  "type": "Feature",
  "properties": {
    "iso:country":"US",
    "sg:address":"1386 Dutch Ln",
    "sg:city":"Hermitage",
    "sg:classifiers":[
        {
            "category":"Building & Trades",
            "subcategory":"Construction",
            "type":"Services"
        },
        {
            "category":"Building & Trades",
            "subcategory":"Electrical",
            "type":"Services"
        }
    ],
    "sg:phone":"+1 724 962 2244",
    "sg:postcode":"16148",
    "sg:province":"PA",
    "sg:tags":[
        "electrician",
        "system",
        "specialty",
        "furnaces-heating",
        "heating",
        "ventilating",
        "contractor",
        "air conditioning"
    ],
    "wof:name":"Hermitage Heating & Cooling",
    "wof:placetype":"venue"
},
  "geometry": {"coordinates":[-80.456785,41.251603],"type":"Point"}
}