{
  "type": "Feature",
  "properties": {
    "addr:full":"91 Rotterdam Rd N Southampton PA 18966",
    "addr:housenumber":"91",
    "addr:postcode":"18966",
    "addr:street":"Rotterdam Rd N",
    "iso:country":"US",
    "sg:address":"91 Rotterdam Rd N",
    "sg:city":"Southampton",
    "sg:classifiers":[
        {
            "category":"Wholesale",
            "subcategory":"Machinery & Supplies",
            "type":"Manufacturing & Wholesale Goods"
        }
    ],
    "sg:phone":"+1   ",
    "sg:postcode":"18966",
    "sg:province":"PA",
    "sg:tags":[
        "equipment",
        "industrial",
        "representative",
        "manufacturer"
    ],
    "wof:name":"Edward A Boll Co Inc",
    "wof:placetype":"venue"
},
  "geometry": {"coordinates":[-74.978106,40.197909],"type":"Point"}
}