{
  "type": "Feature",
  "properties": {
    "iso:country":"US",
    "sg:address":"7581 W Ridge Rd",
    "sg:city":"Fairview",
    "sg:classifiers":[
        {
            "category":"Personal",
            "subcategory":"Beauty Salon",
            "type":"Services"
        }
    ],
    "sg:phone":"+1 814 474 3194",
    "sg:postcode":"16415",
    "sg:province":"PA",
    "wof:name":"Wave Lengths Hair Styling",
    "wof:placetype":"venue"
},
  "geometry": {"coordinates":[-80.257046,42.029712],"type":"Point"}
}