{
  "type": "Feature",
  "properties": {
    "iso:country":"US",
    "sg:address":"467 N 7th St",
    "sg:city":"Philadelphia",
    "sg:classifiers":[
        {
            "category":"Wholesale",
            "subcategory":"Office Equipment",
            "type":"Manufacturing & Wholesale Goods"
        },
        {
            "category":"Shopping",
            "subcategory":"Computers & Home Electronics",
            "type":"Retail Goods"
        }
    ],
    "sg:phone":"+1 215 925 1808",
    "sg:postcode":"19123",
    "sg:province":"PA",
    "sg:tags":[
        "scanning",
        "printer",
        "plotting",
        "supply"
    ],
    "wof:name":"Trade Brazil",
    "wof:placetype":"venue"
},
  "geometry": {"coordinates":[-75.150093,39.96007],"type":"Point"}
}