{
  "type": "Feature",
  "properties": {
    "addr:full":"158 E Butler Ave Chalfont PA 18914",
    "addr:housenumber":"158",
    "addr:postcode":"18914",
    "addr:street":"E Butler Ave",
    "iso:country":"US",
    "sg:address":"158 E Butler Ave",
    "sg:city":"Chalfont",
    "sg:classifiers":[
        {
            "category":"Retail",
            "subcategory":"Laundry & Dry Cleaning",
            "type":"Services"
        }
    ],
    "sg:phone":"+1 215 822 8724",
    "sg:postcode":"18914",
    "sg:province":"PA",
    "wof:name":"Dan's Cleaners",
    "wof:placetype":"venue"
},
  "geometry": {"coordinates":[-75.2052,40.287701],"type":"Point"}
}