{
  "type": "Feature",
  "properties": {
    "iso:country":"US",
    "sg:address":"1614 Rowan St",
    "sg:city":"Philadelphia",
    "sg:classifiers":[
        {
            "category":"Home & Garden",
            "subcategory":"Home Furnishings",
            "type":"Retail Goods"
        },
        {
            "category":"Manufacturing",
            "subcategory":"Petroleum Products",
            "type":"Manufacturing & Wholesale Goods"
        }
    ],
    "sg:phone":"+1 215 457 3535",
    "sg:postcode":"19140",
    "sg:province":"PA",
    "sg:tags":[
        "candle",
        "candles-wholesale",
        "manufacturer"
    ],
    "wof:name":"Scented Candles",
    "wof:placetype":"venue"
},
  "geometry": {"coordinates":[-75.152484,40.019761],"type":"Point"}
}