{
  "type": "Feature",
  "properties": {
    "iso:country":"US",
    "sg:address":"4 Brookhill Rd",
    "sg:city":"Sugarloaf",
    "sg:classifiers":[
        {
            "category":"Professional",
            "subcategory":"Business Services",
            "type":"Services"
        }
    ],
    "sg:phone":"+1 570 788 7571",
    "sg:postcode":"18249",
    "sg:province":"PA",
    "sg:tags":[
        "interior",
        "curtain",
        "retail",
        "design",
        "custom"
    ],
    "wof:name":"Dubatto Designs",
    "wof:placetype":"venue"
},
  "geometry": {"coordinates":[-76.071141,40.994015],"type":"Point"}
}