{
  "type": "Feature",
  "properties": {
    "iso:country":"US",
    "sg:address":"74 Victory Way",
    "sg:city":"Royersford",
    "sg:classifiers":[
        {
            "category":"Food & Beverages",
            "subcategory":"Specialty",
            "type":"Retail Goods"
        }
    ],
    "sg:phone":"+1   ",
    "sg:postcode":"19468",
    "sg:province":"PA",
    "wof:name":"Usana Health Sciences",
    "wof:placetype":"venue"
},
  "geometry": {"coordinates":[-75.532095,40.221791],"type":"Point"}
}