{
  "type": "Feature",
  "properties": {
    "iso:country":"US",
    "sg:address":"35 N 2nd St",
    "sg:city":"Philadelphia",
    "sg:classifiers":[
        {
            "category":"Professional",
            "type":"Services"
        }
    ],
    "sg:phone":"+1   ",
    "sg:postcode":"19106",
    "sg:province":"PA",
    "wof:name":"L E David & Co",
    "wof:placetype":"venue"
},
  "geometry": {"coordinates":[-75.143495,39.950578],"type":"Point"}
}