{
  "type": "Feature",
  "properties": {
    "iso:country":"US",
    "sg:address":"29 W Market St",
    "sg:city":"Lewistown",
    "sg:classifiers":[
        {
            "category":"Retail",
            "subcategory":"Portrait Studio",
            "type":"Services"
        },
        {
            "category":"Retail",
            "subcategory":"Photofinishing",
            "type":"Services"
        }
    ],
    "sg:phone":"+1 717 248 0903",
    "sg:postcode":"17044",
    "sg:province":"PA",
    "sg:tags":[
        "photographer",
        "suppl",
        "laboratory"
    ],
    "wof:name":"Myers Ron Photography",
    "wof:placetype":"venue"
},
  "geometry": {"coordinates":[-77.575132,40.597171],"type":"Point"}
}