{
  "type": "Feature",
  "properties": {
    "iso:country":"US",
    "sg:address":"2 Fairlane Ave",
    "sg:city":"Myerstown",
    "sg:classifiers":[
        {
            "category":"Building & Trades",
            "subcategory":"Construction",
            "type":"Services"
        }
    ],
    "sg:phone":"+1   ",
    "sg:postcode":"17067",
    "sg:province":"PA",
    "sg:tags":[
        "warehouse"
    ],
    "wof:name":"Spangler Construction",
    "wof:placetype":"venue"
},
  "geometry": {"coordinates":[-76.324474,40.373103],"type":"Point"}
}