{
  "type": "Feature",
  "properties": {
    "addr:full":"2873 Brick Rd Ebensburg PA 15931",
    "addr:housenumber":"2873",
    "addr:postcode":"15931",
    "addr:street":"Brick Rd",
    "iso:country":"US",
    "sg:address":"2873 Brick Rd",
    "sg:city":"Ebensburg",
    "sg:classifiers":[
        {
            "category":"Wholesale",
            "subcategory":"Machinery & Supplies",
            "type":"Manufacturing & Wholesale Goods"
        }
    ],
    "sg:phone":"+1 814 344 2110",
    "sg:postcode":"15931",
    "sg:province":"PA",
    "sg:tags":[
        "equipment",
        "industrial"
    ],
    "wof:name":"R R Food Equipment Sales",
    "wof:placetype":"venue"
},
  "geometry": {"coordinates":[-78.69261899999999,40.574772],"type":"Point"}
}