{
  "type": "Feature",
  "properties": {
    "addr:full":"6338 Emlenton Clintonville Rd Emlenton PA 16373",
    "addr:housenumber":"6338",
    "addr:postcode":"16373",
    "addr:street":"Emlenton Clintonville Rd",
    "iso:country":"US",
    "sg:address":"6338 Emlenton Clintonville Rd",
    "sg:city":"Emlenton",
    "sg:phone":"+1 724 867 8761",
    "sg:postcode":"16373",
    "sg:province":"PA",
    "sg:tags":[
        "oil"
    ],
    "wof:name":"Snyder Brothers",
    "wof:placetype":"venue"
},
  "geometry": {"coordinates":[-79.74191,41.176787],"type":"Point"}
}