{
  "type": "Feature",
  "properties": {
    "iso:country":"US",
    "sg:address":"7 Palmyra Bellegrove Rd",
    "sg:city":"Annville",
    "sg:classifiers":[
        {
            "category":"Building & Trades",
            "subcategory":"Construction",
            "type":"Services"
        }
    ],
    "sg:phone":"+1 717 838 3932",
    "sg:postcode":"17003",
    "sg:province":"PA",
    "sg:tags":[
        "general"
    ],
    "wof:name":"Cedar Ridge Construction",
    "wof:placetype":"venue"
},
  "geometry": {"coordinates":[-76.58463500000001,40.330847],"type":"Point"}
}