{
  "type": "Feature",
  "properties": {
    "addr:full":"1130 Harrisburg Pike Carlisle PA 17013",
    "addr:housenumber":"1130",
    "addr:postcode":"17013",
    "addr:street":"Harrisburg Pike",
    "iso:country":"US",
    "sg:address":"1130 Harrisburg Pike",
    "sg:city":"Carlisle",
    "sg:classifiers":[
        {
            "category":"Autos & Motor Vehicles",
            "subcategory":"Automobile Sales",
            "type":"Retail Goods"
        }
    ],
    "sg:phone":"+1 717 245 2322",
    "sg:postcode":"17013",
    "sg:province":"PA",
    "sg:tags":[
        "car",
        "used",
        "dealer"
    ],
    "wof:name":"Auto Drive Used Cars Inc",
    "wof:placetype":"venue"
},
  "geometry": {"coordinates":[-77.16144,40.221887],"type":"Point"}
}