{
  "type": "Feature",
  "properties": {
    "iso:country":"US",
    "sg:address":"804 Bethany Dr",
    "sg:city":"Pittsburgh",
    "sg:classifiers":[
        {
            "category":"Professional",
            "subcategory":"Management & Consulting",
            "type":"Services"
        }
    ],
    "sg:phone":"+1   ",
    "sg:postcode":"15243",
    "sg:province":"PA",
    "wof:name":"Lieberman Group",
    "wof:placetype":"venue"
},
  "geometry": {"coordinates":[-80.071792,40.366276],"type":"Point"}
}