{
  "type": "Feature",
  "properties": {
    "iso:country":"US",
    "sg:address":"475 N Penn St",
    "sg:city":"Spring City",
    "sg:classifiers":[
        {
            "category":"Manufacturing",
            "subcategory":"Signs",
            "type":"Manufacturing & Wholesale Goods"
        }
    ],
    "sg:phone":"+1 610 948 0287",
    "sg:postcode":"19475",
    "sg:province":"PA",
    "wof:name":"Roberts Signs",
    "wof:placetype":"venue"
},
  "geometry": {"coordinates":[-75.552526,40.184071],"type":"Point"}
}