{
  "type": "Feature",
  "properties": {
    "iso:country":"US",
    "sg:address":"215 Baron Ave",
    "sg:city":"Clairton",
    "sg:classifiers":[
        {
            "category":"Organizations",
            "subcategory":"Religious Organization",
            "type":"Services"
        }
    ],
    "sg:phone":"+1 412 233 8238",
    "sg:postcode":"15025",
    "sg:province":"PA",
    "wof:name":"Callaway W C Rev",
    "wof:placetype":"venue"
},
  "geometry": {"coordinates":[-79.878899,40.2869],"type":"Point"}
}