{
  "type": "Feature",
  "properties": {
    "iso:country":"US",
    "sg:address":"200 Camp Hill Rd",
    "sg:city":"Fort Washington",
    "sg:classifiers":[
        {
            "category":"Social Services",
            "subcategory":"Child Care",
            "type":"Services"
        }
    ],
    "sg:phone":"+1   ",
    "sg:postcode":"19034",
    "sg:province":"PA",
    "sg:tags":[
        "childcare",
        "preschool"
    ],
    "wof:name":"Play and Learn Centers",
    "wof:placetype":"venue"
},
  "geometry": {"coordinates":[-75.191643,40.127571],"type":"Point"}
}