{
  "type": "Feature",
  "properties": {
    "iso:country":"US",
    "sg:address":"111 W Main St",
    "sg:city":"Ligonier",
    "sg:classifiers":[
        {
            "category":"Shopping",
            "subcategory":"Florist",
            "type":"Retail Goods"
        }
    ],
    "sg:phone":"+1 724 238 6626",
    "sg:postcode":"15658",
    "sg:province":"PA",
    "wof:name":"Ligonier Floral Gift Emporium",
    "wof:placetype":"venue"
},
  "geometry": {"coordinates":[-79.23806,40.243118],"type":"Point"}
}