{
  "type": "Feature",
  "properties": {
    "iso:country":"US",
    "sg:address":"226 Highland Rd",
    "sg:city":"Atglen",
    "sg:classifiers":[
        {
            "category":"Education",
            "subcategory":"School",
            "type":"Public Place"
        }
    ],
    "sg:phone":"+1 610 593 8253",
    "sg:postcode":"19310",
    "sg:province":"PA",
    "sg:website":"www.octorara.k12.pa.us",
    "wof:name":"Octorara High School 9-12",
    "wof:placetype":"venue"
},
  "geometry": {"coordinates":[-75.949938,39.926871],"type":"Point"}
}