{
  "type": "Feature",
  "properties": {
    "addr:full":"128 Sylvan Glen Dr Ebensburg PA 15931",
    "addr:housenumber":"128",
    "addr:postcode":"15931",
    "addr:street":"Sylvan Glen Dr",
    "iso:country":"US",
    "sg:address":"128 Sylvan Glen Dr",
    "sg:city":"Ebensburg",
    "sg:classifiers":[
        {
            "category":"Professional",
            "subcategory":"Lawyer & Legal Services",
            "type":"Services"
        }
    ],
    "sg:phone":"+1 814 471 2768",
    "sg:postcode":"15931",
    "sg:province":"PA",
    "sg:tags":[
        "attorney"
    ],
    "wof:name":"Law Offices Gary D Ginsberg",
    "wof:placetype":"venue"
},
  "geometry": {"coordinates":[-78.790538,40.49894],"type":"Point"}
}