{
  "type": "Feature",
  "properties": {
    "iso:country":"US",
    "sg:address":"2455 Park Ave",
    "sg:city":"Easton",
    "sg:classifiers":[
        {
            "category":"Shopping",
            "subcategory":"Jewelry",
            "type":"Retail Goods"
        }
    ],
    "sg:phone":"+1   ",
    "sg:postcode":"18045",
    "sg:province":"PA",
    "wof:name":"Portland State University",
    "wof:placetype":"venue"
},
  "geometry": {"coordinates":[-75.260468,40.694664],"type":"Point"}
}