{
  "type": "Feature",
  "properties": {
    "addr:full":"164 Rockland Cranberry Rd Kennerdell PA 16374",
    "addr:housenumber":"164",
    "addr:postcode":"16374",
    "addr:street":"Rockland Cranberry Rd",
    "iso:country":"US",
    "sg:address":"164 Rockland Cranberry Rd",
    "sg:city":"Kennerdell",
    "sg:classifiers":[
        {
            "category":"Education",
            "subcategory":"School",
            "type":"Public Place"
        }
    ],
    "sg:phone":"+1 814 498 2221",
    "sg:postcode":"16374",
    "sg:province":"PA",
    "wof:name":"Rockland Elementary School",
    "wof:placetype":"venue"
},
  "geometry": {"coordinates":[-79.748319,41.2827],"type":"Point"}
}