{
  "type": "Feature",
  "properties": {
    "iso:country":"US",
    "sg:address":"116 Saint Andrews Dr",
    "sg:city":"Avondale",
    "sg:classifiers":[
        {
            "category":"Wholesale",
            "subcategory":"Chemicals & Plastics",
            "type":"Manufacturing & Wholesale Goods"
        }
    ],
    "sg:phone":"+1   ",
    "sg:postcode":"19311",
    "sg:province":"PA",
    "wof:name":"Office Anesthesia",
    "wof:placetype":"venue"
},
  "geometry": {"coordinates":[-75.72709999999999,39.802347],"type":"Point"}
}