{
  "type": "Feature",
  "properties": {
    "addr:full":"6242 Stenton Ave Philadelphia PA 19138",
    "addr:housenumber":"6242",
    "addr:postcode":"19138",
    "addr:street":"Stenton Ave",
    "iso:country":"US",
    "sg:address":"6242 Stenton Ave",
    "sg:city":"Philadelphia",
    "sg:classifiers":[
        {
            "category":"Professional",
            "type":"Services"
        },
        {
            "category":"Restaurant",
            "type":"Food & Drink"
        },
        {
            "category":"Fast Food",
            "type":"Food & Drink"
        }
    ],
    "sg:phone":"+1 215 548 6137",
    "sg:postcode":"19138",
    "sg:province":"PA",
    "sg:tags":[
        "delivery",
        "take",
        "pizza"
    ],
    "sg:website":"http://www.pizzahut.com",
    "wof:name":"Pizza Hut",
    "wof:placetype":"venue"
},
  "geometry": {"coordinates":[-75.16377799999999,40.058589],"type":"Point"}
}