{
  "type": "Feature",
  "properties": {
    "iso:country":"US",
    "sg:address":"320 Pine Grove Rd",
    "sg:city":"Gardners",
    "sg:classifiers":[
        {
            "category":"Building & Trades",
            "subcategory":"Construction",
            "type":"Services"
        }
    ],
    "sg:phone":"+1 717 486 0049",
    "sg:postcode":"17324",
    "sg:province":"PA",
    "sg:tags":[
        "concrete",
        "contractor"
    ],
    "wof:name":"Premier Concrete Svc",
    "wof:placetype":"venue"
},
  "geometry": {"coordinates":[-77.21547700000001,40.067328],"type":"Point"}
}