{
  "type": "Feature",
  "properties": {
    "iso:country":"US",
    "sg:address":"1260 W Chester Pike",
    "sg:city":"Havertown",
    "sg:classifiers":[
        {
            "category":"Coffee & Tea",
            "type":"Food & Drink"
        }
    ],
    "sg:menulink":"http://www.allmenus.com/pa/haverford/125171-starbucks-coffee/menu/",
    "sg:phone":"+1 610 853 3320",
    "sg:postcode":"19083",
    "sg:province":"PA",
    "sg:tags":[
        "american"
    ],
    "wof:name":"Starbucks Coffee",
    "wof:placetype":"venue"
},
  "geometry": {"coordinates":[-75.318624,39.972833],"type":"Point"}
}