{
  "type": "Feature",
  "properties": {
    "addr:full":"109 Willows Ave Darby PA 19023",
    "addr:housenumber":"109",
    "addr:postcode":"19023",
    "addr:street":"Willows Ave",
    "iso:country":"US",
    "sg:address":"109 Willows Ave",
    "sg:city":"Darby",
    "sg:classifiers":[
        {
            "category":"Manufacturing",
            "subcategory":"Tools & Machinery",
            "type":"Manufacturing & Wholesale Goods"
        }
    ],
    "sg:phone":"+1 484 652 1100",
    "sg:postcode":"19023",
    "sg:province":"PA",
    "sg:tags":[
        "springs-wholesale",
        "manufacturer"
    ],
    "wof:name":"Liberty Spring Usa",
    "wof:placetype":"venue"
},
  "geometry": {"coordinates":[-75.283376,39.908128],"type":"Point"}
}