{
  "type": "Feature",
  "properties": {
    "addr:full":"2310 N Howard St Philadelphia PA 19133",
    "addr:housenumber":"2310",
    "addr:postcode":"19133",
    "addr:street":"N Howard St",
    "iso:country":"US",
    "sg:address":"2310 N Howard St",
    "sg:city":"Philadelphia",
    "sg:classifiers":[
        {
            "category":"Personal",
            "type":"Services"
        },
        {
            "category":"Retail",
            "subcategory":"Auto Rental",
            "type":"Services"
        }
    ],
    "sg:phone":"+1 800 468 4285",
    "sg:postcode":"19133",
    "sg:province":"PA",
    "sg:tags":[
        "car",
        "mover",
        "truck"
    ],
    "wof:name":"U-Haul Co.",
    "wof:placetype":"venue"
},
  "geometry": {"coordinates":[-75.1332,39.985103],"type":"Point"}
}