{
  "type": "Feature",
  "properties": {
    "iso:country":"US",
    "sg:address":"24 Montgomery St",
    "sg:city":"Montgomery",
    "sg:classifiers":[
        {
            "category":"Government",
            "subcategory":"Fire Station",
            "type":"Public Place"
        }
    ],
    "sg:phone":"+1 570 547 1380",
    "sg:postcode":"17752",
    "sg:province":"PA",
    "sg:tags":[
        "department"
    ],
    "sg:website":"www.fighting13.com",
    "wof:name":"Montgomery Volunteer Fire Co",
    "wof:placetype":"venue"
},
  "geometry": {"coordinates":[-76.875367,41.170077],"type":"Point"}
}