{
  "type": "Feature",
  "properties": {
    "iso:country":"US",
    "sg:address":"2333 Welsh Rd Ste 9",
    "sg:city":"Lansdale",
    "sg:classifiers":[
        {
            "category":"Personal",
            "type":"Services"
        }
    ],
    "sg:phone":"+1 215 361 6940",
    "sg:postcode":"19446",
    "sg:province":"PA",
    "sg:tags":[
        "mover"
    ],
    "sg:website":"www.gopackagingstore.com",
    "wof:name":"Packaging Store",
    "wof:placetype":"venue"
},
  "geometry": {"coordinates":[-75.31755200000001,40.262016],"type":"Point"}
}