{
  "type": "Feature",
  "properties": {
    "iso:country":"US",
    "sg:address":"111 Beaumont Dr",
    "sg:city":"Newtown",
    "sg:classifiers":[
        {
            "category":"Professional",
            "subcategory":"Engineering",
            "type":"Services"
        }
    ],
    "sg:phone":"+1 215 504 8250",
    "sg:postcode":"18940",
    "sg:province":"PA",
    "sg:tags":[
        "engineer"
    ],
    "wof:name":"Brindley Newell Inc",
    "wof:placetype":"venue"
},
  "geometry": {"coordinates":[-74.92391600000001,40.295469],"type":"Point"}
}