{
  "type": "Feature",
  "properties": {
    "iso:country":"US",
    "sg:address":"4717 Carlisle Pike",
    "sg:city":"Mechanicsburg",
    "sg:classifiers":[
        {
            "category":"Cinema",
            "subcategory":"Movie Rental",
            "type":"Entertainment"
        }
    ],
    "sg:phone":"+1 717 737 5902",
    "sg:postcode":"17050",
    "sg:province":"PA",
    "sg:tags":[
        "video",
        "tape"
    ],
    "sg:website":"www.hollywoodvideo.com",
    "wof:name":"Hollywood Video",
    "wof:placetype":"venue"
},
  "geometry": {"coordinates":[-76.96499799999999,40.237526],"type":"Point"}
}