{
  "type": "Feature",
  "properties": {
    "iso:country":"US",
    "sg:address":"2508 Hampden Blvd",
    "sg:city":"Reading",
    "sg:classifiers":[
        {
            "category":"Health Services",
            "subcategory":"Doctor",
            "type":"Services"
        }
    ],
    "sg:phone":"+1 610 921 3924",
    "sg:postcode":"19604",
    "sg:province":"PA",
    "sg:tags":[
        "physician",
        "surgeon"
    ],
    "wof:name":"C L Killian Md",
    "wof:placetype":"venue"
},
  "geometry": {"coordinates":[-75.89828900000001,40.371413],"type":"Point"}
}