{
  "type": "Feature",
  "properties": {
    "iso:country":"US",
    "sg:address":"38 Water St",
    "sg:city":"Wind Gap",
    "sg:classifiers":[
        {
            "category":"Building & Trades",
            "subcategory":"Landscaping Services",
            "type":"Services"
        }
    ],
    "sg:phone":"+1 610 863 8663",
    "sg:postcode":"18091",
    "sg:province":"PA",
    "sg:tags":[
        "lawn",
        "maintenance",
        "grounds"
    ],
    "wof:name":"Anthony's Lawn Care",
    "wof:placetype":"venue"
},
  "geometry": {"coordinates":[-75.29317,40.847883],"type":"Point"}
}