{
  "type": "Feature",
  "properties": {
    "iso:country":"US",
    "sg:address":"209 S Delaware Ave",
    "sg:city":"Minersville",
    "sg:classifiers":[
        {
            "category":"Shopping",
            "subcategory":"Catalog Store",
            "type":"Retail Goods"
        }
    ],
    "sg:phone":"+1 570 544 6356",
    "sg:postcode":"17954",
    "sg:province":"PA",
    "sg:tags":[
        "mail",
        "order",
        "online"
    ],
    "wof:name":"Dee Dee's Healthy Herbs",
    "wof:placetype":"venue"
},
  "geometry": {"coordinates":[-76.25751200000001,40.688065],"type":"Point"}
}