{
  "type": "Feature",
  "properties": {
    "iso:country":"US",
    "sg:address":"2545 W Chester Pike",
    "sg:city":"Broomall",
    "sg:classifiers":[
        {
            "category":"Personal",
            "subcategory":"Beauty Salon",
            "type":"Services"
        }
    ],
    "sg:phone":"+1 610 353 6360",
    "sg:postcode":"19008",
    "sg:province":"PA",
    "sg:tags":[
        "shop"
    ],
    "wof:name":"Pink Nails",
    "wof:placetype":"venue"
},
  "geometry": {"coordinates":[-75.35898299999999,39.981559],"type":"Point"}
}