{
  "type": "Feature",
  "properties": {
    "iso:country":"US",
    "sg:address":"4408 Carlisle Pike",
    "sg:city":"Camp Hill",
    "sg:classifiers":[
        {
            "category":"Communications",
            "subcategory":"Film & Video Production",
            "type":"Services"
        }
    ],
    "sg:phone":"+1   ",
    "sg:postcode":"17011",
    "sg:province":"PA",
    "sg:tags":[
        "motion"
    ],
    "wof:name":"Tri Video Services",
    "wof:placetype":"venue"
},
  "geometry": {"coordinates":[-76.958941,40.237805],"type":"Point"}
}