{
  "type": "Feature",
  "properties": {
    "addr:full":"138 Maple Dr Hamburg PA 19526",
    "addr:housenumber":"138",
    "addr:postcode":"19526",
    "addr:street":"Maple Dr",
    "iso:country":"US",
    "sg:address":"138 Maple Dr",
    "sg:city":"Hamburg",
    "sg:classifiers":[
        {
            "category":"Organizations",
            "subcategory":"Religious Organization",
            "type":"Services"
        }
    ],
    "sg:phone":"+1 610 562 8802",
    "sg:postcode":"19526",
    "sg:province":"PA",
    "wof:name":"Faith Bible Baptist Church",
    "wof:placetype":"venue"
},
  "geometry": {"coordinates":[-75.998312,40.552763],"type":"Point"}
}