{
  "type": "Feature",
  "properties": {
    "addr:full":"18 E Germantown Pike Norristown PA 19401",
    "addr:housenumber":"18",
    "addr:postcode":"19401",
    "addr:street":"E Germantown Pike",
    "iso:country":"US",
    "sg:address":"18 E Germantown Pike",
    "sg:city":"Norristown",
    "sg:classifiers":[
        {
            "category":"Restaurant",
            "type":"Food & Drink"
        }
    ],
    "sg:menulink":"http://www.allmenus.com/pa/east-norriton/147281-boston-market/menu/",
    "sg:phone":"+1 610 275 4334",
    "sg:postcode":"19401",
    "sg:province":"PA",
    "sg:tags":[
        "barbecue",
        "american",
        "soup"
    ],
    "wof:name":"Boston Market",
    "wof:placetype":"venue"
},
  "geometry": {"coordinates":[-75.31107900000001,40.140236],"type":"Point"}
}