{
  "type": "Feature",
  "properties": {
    "iso:country":"US",
    "sg:address":"13 W Butler Ave",
    "sg:city":"Ambler",
    "sg:classifiers":[
        {
            "category":"Shopping",
            "type":"Retail Goods"
        }
    ],
    "sg:phone":"+1 215 654 9106",
    "sg:postcode":"19002",
    "sg:province":"PA",
    "sg:tags":[
        "picture",
        "frame"
    ],
    "wof:name":"No Bare Walls Framing Studios",
    "wof:placetype":"venue"
},
  "geometry": {"coordinates":[-75.22429,40.153684],"type":"Point"}
}