{
  "type": "Feature",
  "properties": {
    "iso:country":"US",
    "sg:address":"22 S Clifton Ave",
    "sg:city":"Clifton Heights",
    "sg:classifiers":[
        {
            "category":"Food & Beverages",
            "subcategory":"Groceries & Convenience Stores",
            "type":"Retail Goods"
        }
    ],
    "sg:phone":"+1 610 623 7288",
    "sg:postcode":"19018",
    "sg:province":"PA",
    "wof:name":"Clifton Deli",
    "wof:placetype":"venue"
},
  "geometry": {"coordinates":[-75.28668,39.921872],"type":"Point"}
}