{
  "type": "Feature",
  "properties": {
    "addr:full":"4615 Buffalo Rd Erie PA 16510",
    "addr:housenumber":"4615",
    "addr:postcode":"16510",
    "addr:street":"Buffalo Rd",
    "iso:country":"US",
    "sg:address":"4615 Buffalo Rd",
    "sg:city":"Erie",
    "sg:classifiers":[
        {
            "category":"Real Estate",
            "subcategory":"Real Estate Services",
            "type":"Services"
        },
        {
            "category":"Real Estate",
            "subcategory":"Real Estate Agent",
            "type":"Services"
        }
    ],
    "sg:phone":"+1 814 899 1316",
    "sg:postcode":"16510",
    "sg:province":"PA",
    "sg:tags":[
        "buyer",
        "broker"
    ],
    "wof:name":"New Horizon Realtors",
    "wof:placetype":"venue"
},
  "geometry": {"coordinates":[-79.998728,42.148283],"type":"Point"}
}