{
  "type": "Feature",
  "properties": {
    "addr:full":"1800 Mearns Rd Warminster PA 18974",
    "addr:housenumber":"1800",
    "addr:postcode":"18974",
    "addr:street":"Mearns Rd",
    "iso:country":"US",
    "sg:address":"1800 Mearns Rd",
    "sg:city":"Warminster",
    "sg:phone":"+1 215 675 9915",
    "sg:postcode":"18974",
    "sg:province":"PA",
    "sg:tags":[
        "equipment",
        "station"
    ],
    "wof:name":"Mullin Contracting Inc",
    "wof:placetype":"venue"
},
  "geometry": {"coordinates":[-75.067837,40.227266],"type":"Point"}
}