{
  "type": "Feature",
  "properties": {
    "iso:country":"US",
    "sg:address":"15267 Tionesta Rd",
    "sg:city":"Pleasantville",
    "sg:classifiers":[
        {
            "category":"Utilities",
            "subcategory":"Water",
            "type":"Services"
        },
        {
            "category":"Utilities",
            "subcategory":"Fuel Oil & Lpg",
            "type":"Services"
        }
    ],
    "sg:phone":"+1 814 589 7025",
    "sg:postcode":"16341",
    "sg:province":"PA",
    "sg:tags":[
        "pump",
        "well",
        "drilling",
        "contractor"
    ],
    "wof:name":"S & T Service & Supply",
    "wof:placetype":"venue"
},
  "geometry": {"coordinates":[-79.513125,41.54688],"type":"Point"}
}