{
  "type": "Feature",
  "properties": {
    "iso:country":"US",
    "sg:address":"1080 Berkshire Blvd",
    "sg:city":"Reading",
    "sg:classifiers":[
        {
            "category":"Shopping",
            "subcategory":"Clothing, Apparel, & Fashions",
            "type":"Retail Goods"
        }
    ],
    "sg:phone":"+1 610 373 5805",
    "sg:postcode":"19610",
    "sg:province":"PA",
    "wof:name":"Talbots",
    "wof:placetype":"venue"
},
  "geometry": {"coordinates":[-75.97316499999999,40.345269],"type":"Point"}
}