{
  "type": "Feature",
  "properties": {
    "iso:country":"US",
    "sg:address":"731 N Loyalsock Ave",
    "sg:city":"Montoursville",
    "sg:classifiers":[
        {
            "category":"Shopping",
            "subcategory":"Discount & Variety Stores",
            "type":"Retail Goods"
        }
    ],
    "sg:phone":"+1 570 368 4765",
    "sg:postcode":"17754",
    "sg:province":"PA",
    "wof:name":"Dollar General",
    "wof:placetype":"venue"
},
  "geometry": {"coordinates":[-76.91740299999999,41.259205],"type":"Point"}
}