{
  "type": "Feature",
  "properties": {
    "addr:full":"5862 Larchwood Ave Philadelphia PA 19143",
    "addr:housenumber":"5862",
    "addr:postcode":"19143",
    "addr:street":"Larchwood Ave",
    "iso:country":"US",
    "sg:address":"5862 Larchwood Ave",
    "sg:city":"Philadelphia",
    "sg:classifiers":[
        {
            "category":"Restaurant",
            "type":"Food & Drink"
        }
    ],
    "sg:phone":"+1 215 472 2131",
    "sg:postcode":"19143",
    "sg:province":"PA",
    "wof:name":"Hollywood Cafe",
    "wof:placetype":"venue"
},
  "geometry": {"coordinates":[-75.239504,39.953502],"type":"Point"}
}