{
  "type": "Feature",
  "properties": {
    "iso:country":"US",
    "sg:address":"415 Birmingham Rd",
    "sg:city":"West Chester",
    "sg:classifiers":[
        {
            "category":"Building & Trades",
            "subcategory":"Construction",
            "type":"Services"
        }
    ],
    "sg:phone":"+1 610 692 2218",
    "sg:postcode":"19382",
    "sg:province":"PA",
    "sg:tags":[
        "contractor"
    ],
    "wof:name":"Drury Development Co Inc",
    "wof:placetype":"venue"
},
  "geometry": {"coordinates":[-75.622101,39.9319],"type":"Point"}
}