{
  "type": "Feature",
  "properties": {
    "addr:full":"27 E Ferdinand St Manheim PA 17545",
    "addr:housenumber":"27",
    "addr:postcode":"17545",
    "addr:street":"E Ferdinand St",
    "iso:country":"US",
    "sg:address":"27 E Ferdinand St",
    "sg:city":"Manheim",
    "sg:classifiers":[
        {
            "category":"Professional",
            "subcategory":"Art Services",
            "type":"Services"
        }
    ],
    "sg:phone":"+1   ",
    "sg:postcode":"17545",
    "sg:province":"PA",
    "sg:tags":[
        "commercial",
        "design"
    ],
    "wof:name":"Wwwpromolitescom",
    "wof:placetype":"venue"
},
  "geometry": {"coordinates":[-76.39175899999999,40.162668],"type":"Point"}
}