{
  "type": "Feature",
  "properties": {
    "addr:full":"7 Hog Island Rd Philadelphia PA 19153",
    "addr:housenumber":"7",
    "addr:postcode":"19153",
    "addr:street":"Hog Island Rd",
    "iso:country":"US",
    "sg:address":"7 Hog Island Rd",
    "sg:city":"Philadelphia",
    "sg:classifiers":[
        {
            "category":"Professional",
            "subcategory":"Engineering",
            "type":"Services"
        }
    ],
    "sg:phone":"+1   ",
    "sg:postcode":"19153",
    "sg:province":"PA",
    "wof:name":"Skc Hangar Partners",
    "wof:placetype":"venue"
},
  "geometry": {"coordinates":[-75.21917500000001,39.873856],"type":"Point"}
}