{
  "type": "Feature",
  "properties": {
    "iso:country":"US",
    "sg:address":"16 Bitter Rd",
    "sg:city":"Hegins",
    "sg:classifiers":[
        {
            "category":"Autos & Motor Vehicles",
            "subcategory":"Auto Supplies",
            "type":"Retail Goods"
        },
        {
            "category":"Wholesale",
            "subcategory":"Auto Parts",
            "type":"Manufacturing & Wholesale Goods"
        }
    ],
    "sg:phone":"+1   ",
    "sg:postcode":"17938",
    "sg:province":"PA",
    "sg:tags":[
        "used"
    ],
    "wof:name":"Shadleas Auto Parts & ACC",
    "wof:placetype":"venue"
},
  "geometry": {"coordinates":[-76.535588,40.636771],"type":"Point"}
}