{
  "type": "Feature",
  "properties": {
    "addr:full":"201 State St Erie PA 16501",
    "addr:housenumber":"201",
    "addr:postcode":"16501",
    "addr:street":"State St",
    "iso:country":"US",
    "sg:address":"201 State St",
    "sg:city":"Erie",
    "sg:classifiers":[
        {
            "category":"Education",
            "subcategory":"Library",
            "type":"Public Place"
        },
        {
            "category":"Professional",
            "subcategory":"Management & Consulting",
            "type":"Services"
        }
    ],
    "sg:phone":"+1 814 877 6000",
    "sg:postcode":"16501",
    "sg:province":"PA",
    "sg:tags":[
        "special",
        "interest"
    ],
    "wof:name":"Hamot Medical Center",
    "wof:placetype":"venue"
},
  "geometry": {"coordinates":[-80.087176,42.132346],"type":"Point"}
}