{
  "type": "Feature",
  "properties": {
    "iso:country":"US",
    "sg:address":"5 Fawn Dr",
    "sg:city":"Hazleton",
    "sg:classifiers":[
        {
            "category":"Professional",
            "type":"Services"
        }
    ],
    "sg:phone":"+1   ",
    "sg:postcode":"18202",
    "sg:province":"PA",
    "wof:name":"Makr Co",
    "wof:placetype":"venue"
},
  "geometry": {"coordinates":[-76.01239,40.969362],"type":"Point"}
}