{
  "type": "Feature",
  "properties": {
    "iso:country":"US",
    "sg:address":"1148 Broadrun Rd",
    "sg:city":"Coatesville",
    "sg:classifiers":[
        {
            "category":"Professional",
            "type":"Services"
        }
    ],
    "sg:phone":"+1   ",
    "sg:postcode":"19320",
    "sg:province":"PA",
    "wof:name":"You and Methreads",
    "wof:placetype":"venue"
},
  "geometry": {"coordinates":[-75.729788,39.954828],"type":"Point"}
}