{
  "type": "Feature",
  "properties": {
    "addr:full":"2542 Eastern Blvd York PA 17402",
    "addr:housenumber":"2542",
    "addr:postcode":"17402",
    "addr:street":"Eastern Blvd",
    "iso:country":"US",
    "sg:address":"2542 Eastern Blvd",
    "sg:city":"York",
    "sg:classifiers":[
        {
            "category":"Banks & Credit Unions",
            "subcategory":"Bank",
            "type":"Services"
        }
    ],
    "sg:phone":"+1   ",
    "sg:postcode":"17402",
    "sg:province":"PA",
    "sg:tags":[
        "company",
        "consumer",
        "finance"
    ],
    "wof:name":"HFC",
    "wof:placetype":"venue"
},
  "geometry": {"coordinates":[-76.673695,39.973024],"type":"Point"}
}