{
  "type": "Feature",
  "properties": {
    "iso:country":"US",
    "sg:address":"54 Friendly Dr",
    "sg:city":"Quarryville",
    "sg:classifiers":[
        {
            "category":"Insurance",
            "subcategory":"Insurance Agent",
            "type":"Services"
        }
    ],
    "sg:phone":"+1   ",
    "sg:postcode":"17566",
    "sg:province":"PA",
    "wof:name":"Kline Pat",
    "wof:placetype":"venue"
},
  "geometry": {"coordinates":[-76.22612599999999,39.870621],"type":"Point"}
}