{
  "type": "Feature",
  "properties": {
    "iso:country":"US",
    "sg:address":"975 State Rte 18",
    "sg:city":"Aliquippa",
    "sg:classifiers":[
        {
            "category":"Freight",
            "type":"Transportation"
        }
    ],
    "sg:phone":"+1   ",
    "sg:postcode":"15001",
    "sg:province":"PA",
    "sg:tags":[
        "operator",
        "trucking"
    ],
    "wof:name":"US Bulk Transport Inc",
    "wof:placetype":"venue"
},
  "geometry": {"coordinates":[-80.3995,40.61237],"type":"Point"}
}