{
  "type": "Feature",
  "properties": {
    "iso:country":"US",
    "sg:address":"570 N Wales Rd",
    "sg:city":"North Wales",
    "sg:classifiers":[
        {
            "category":"Home & Garden",
            "subcategory":"Garden Supply",
            "type":"Retail Goods"
        }
    ],
    "sg:phone":"+1 215 699 2207",
    "sg:postcode":"19454",
    "sg:province":"PA",
    "sg:tags":[
        "supp",
        "sup"
    ],
    "sg:website":"www.rhoadsgarden.com",
    "wof:name":"Rhoads Garden Inc",
    "wof:placetype":"venue"
},
  "geometry": {"coordinates":[-75.283361,40.20491],"type":"Point"}
}