{
  "type": "Feature",
  "properties": {
    "addr:full":"5580 Fairfield Rd Fairfield PA 17320",
    "addr:housenumber":"5580",
    "addr:postcode":"17320",
    "addr:street":"Fairfield Rd",
    "iso:country":"US",
    "sg:address":"5580 Fairfield Rd",
    "sg:city":"Fairfield",
    "sg:classifiers":[
        {
            "category":"Real Estate",
            "subcategory":"Real Estate Agent",
            "type":"Services"
        }
    ],
    "sg:phone":"+1   ",
    "sg:postcode":"17320",
    "sg:province":"PA",
    "sg:tags":[
        "broker"
    ],
    "wof:name":"Century 21",
    "wof:placetype":"venue"
},
  "geometry": {"coordinates":[-77.381772,39.76402],"type":"Point"}
}