{
  "type": "Feature",
  "properties": {
    "addr:full":"604 Cleveland St Lilly PA 15938",
    "addr:housenumber":"604",
    "addr:postcode":"15938",
    "addr:street":"Cleveland St",
    "iso:country":"US",
    "sg:address":"604 Cleveland St",
    "sg:city":"Lilly",
    "sg:classifiers":[
        {
            "category":"Organizations",
            "subcategory":"Religious Organization",
            "type":"Services"
        }
    ],
    "sg:phone":"+1 814 886 2222",
    "sg:postcode":"15938",
    "sg:province":"PA",
    "sg:tags":[
        "church"
    ],
    "wof:name":"St Lukes Lutheran Church",
    "wof:placetype":"venue"
},
  "geometry": {"coordinates":[-78.619005,40.42509],"type":"Point"}
}