{
  "type": "Feature",
  "properties": {
    "addr:full":"338 Lincoln Rd Gallitzin PA 16641",
    "addr:housenumber":"338",
    "addr:postcode":"16641",
    "addr:street":"Lincoln Rd",
    "iso:country":"US",
    "sg:address":"338 Lincoln Rd",
    "sg:city":"Gallitzin",
    "sg:classifiers":[
        {
            "category":"Building & Trades",
            "subcategory":"Construction",
            "type":"Services"
        }
    ],
    "sg:phone":"+1 814 886 2175",
    "sg:postcode":"16641",
    "sg:province":"PA",
    "sg:tags":[
        "excavation",
        "contractor"
    ],
    "wof:name":"Hanlon, Philip Excavating",
    "wof:placetype":"venue"
},
  "geometry": {"coordinates":[-78.59733199999999,40.512911],"type":"Point"}
}