{
  "type": "Feature",
  "properties": {
    "addr:full":"527 McNeilly Rd Pittsburgh PA 15226",
    "addr:housenumber":"527",
    "addr:postcode":"15226",
    "addr:street":"Mcneilly Rd",
    "iso:country":"US",
    "sg:address":"527 McNeilly Rd",
    "sg:city":"Pittsburgh",
    "sg:classifiers":[
        {
            "category":"Building & Trades",
            "subcategory":"Construction",
            "type":"Services"
        }
    ],
    "sg:phone":"+1 412 341 5012",
    "sg:postcode":"15226",
    "sg:province":"PA",
    "sg:tags":[
        "contractor"
    ],
    "wof:name":"C & C",
    "wof:placetype":"venue"
},
  "geometry": {"coordinates":[-80.01041600000001,40.382852],"type":"Point"}
}