{
  "type": "Feature",
  "properties": {
    "iso:country":"US",
    "sg:address":"255 S 17th St Ste 2102",
    "sg:city":"Philadelphia",
    "sg:classifiers":[
        {
            "category":"Personal",
            "subcategory":"Beauty Salon",
            "type":"Services"
        }
    ],
    "sg:phone":"+1 215 599 9409",
    "sg:postcode":"19103",
    "sg:province":"PA",
    "sg:tags":[
        "spa"
    ],
    "sg:website":"www.americanlaser.com",
    "wof:name":"American Laser Centers",
    "wof:placetype":"venue"
},
  "geometry": {"coordinates":[-75.169296,39.948179],"type":"Point"}
}