{
  "type": "Feature",
  "properties": {
    "addr:full":"1535 Banksville Rd Pittsburgh PA 15216",
    "addr:housenumber":"1535",
    "addr:postcode":"15216",
    "addr:street":"Banksville Rd",
    "iso:country":"US",
    "sg:address":"1535 Banksville Rd",
    "sg:city":"Pittsburgh",
    "sg:classifiers":[
        {
            "category":"Retail",
            "subcategory":"Car Wash",
            "type":"Services"
        }
    ],
    "sg:phone":"+1 412 561 5922",
    "sg:postcode":"15216",
    "sg:province":"PA",
    "sg:tags":[
        "polishing",
        "automatic",
        "washing"
    ],
    "wof:name":"Supersonic Car Wash Ent Inc",
    "wof:placetype":"venue"
},
  "geometry": {"coordinates":[-80.03064000000001,40.412801],"type":"Point"}
}