{
  "type": "Feature",
  "properties": {
    "iso:country":"US",
    "sg:address":"913 Miller St",
    "sg:city":"Luzerne",
    "sg:classifiers":[
        {
            "category":"Building & Trades",
            "subcategory":"Construction",
            "type":"Services"
        }
    ],
    "sg:phone":"+1   ",
    "sg:postcode":"18709",
    "sg:province":"PA",
    "sg:tags":[
        "excavating",
        "demolition",
        "contractor"
    ],
    "wof:name":"Buck Mountain Quarry",
    "wof:placetype":"venue"
},
  "geometry": {"coordinates":[-75.897167,41.292048],"type":"Point"}
}