{
  "type": "Feature",
  "properties": {
    "iso:country":"US",
    "sg:address":"8019 Pine Rd",
    "sg:city":"Philadelphia",
    "sg:classifiers":[
        {
            "category":"Building & Trades",
            "subcategory":"Electrical",
            "type":"Services"
        }
    ],
    "sg:phone":"+1   ",
    "sg:postcode":"19111",
    "sg:province":"PA",
    "sg:tags":[
        "electrical",
        "contractor"
    ],
    "wof:name":"GL Higgins Electrical",
    "wof:placetype":"venue"
},
  "geometry": {"coordinates":[-75.084096,40.078312],"type":"Point"}
}