{
  "type": "Feature",
  "properties": {
    "addr:full":"1208 Railroad St Bethlehem PA 18015",
    "addr:housenumber":"1208",
    "addr:postcode":"18015",
    "addr:street":"Railroad St",
    "iso:country":"US",
    "sg:address":"1208 Railroad St",
    "sg:city":"Bethlehem",
    "sg:classifiers":[
        {
            "category":"Building & Trades",
            "subcategory":"Landscaping Services",
            "type":"Services"
        }
    ],
    "sg:phone":"+1 610 868 1661",
    "sg:postcode":"18015",
    "sg:province":"PA",
    "sg:tags":[
        "lawn",
        "stump",
        "tree",
        "grinding",
        "removal",
        "maintenance"
    ],
    "wof:name":"Rjm Tree Service",
    "wof:placetype":"venue"
},
  "geometry": {"coordinates":[-75.359728,40.613294],"type":"Point"}
}