{
  "type": "Feature",
  "properties": {
    "iso:country":"US",
    "sg:address":"720 Main St",
    "sg:city":"Saxton",
    "sg:classifiers":[
        {
            "category":"Restaurant",
            "type":"Food & Drink"
        }
    ],
    "sg:phone":"+1 814 635 9102",
    "sg:postcode":"16678",
    "sg:province":"PA",
    "wof:name":"Open Door Cafe",
    "wof:placetype":"venue"
},
  "geometry": {"coordinates":[-78.24326000000001,40.215673],"type":"Point"}
}