{
  "type": "Feature",
  "properties": {
    "iso:country":"US",
    "sg:address":"420 Main St",
    "sg:city":"Towanda",
    "sg:classifiers":[
        {
            "category":"Professional",
            "type":"Services"
        }
    ],
    "sg:phone":"+1   ",
    "sg:postcode":"18848",
    "sg:province":"PA",
    "wof:name":"David Bombay",
    "wof:placetype":"venue"
},
  "geometry": {"coordinates":[-76.44318,41.766175],"type":"Point"}
}