{
  "type": "Feature",
  "properties": {
    "iso:country":"US",
    "sg:address":"707 Bristol Pike",
    "sg:city":"Bensalem",
    "sg:classifiers":[
        {
            "category":"Shopping",
            "subcategory":"Optical Goods",
            "type":"Retail Goods"
        }
    ],
    "sg:phone":"+1 215 781 0622",
    "sg:postcode":"19020",
    "sg:province":"PA",
    "wof:name":"Eye Care For You",
    "wof:placetype":"venue"
},
  "geometry": {"coordinates":[-74.97620499999999,40.065405],"type":"Point"}
}