{
  "type": "Feature",
  "properties": {
    "iso:country":"US",
    "sg:address":"2566 Industry Ln",
    "sg:city":"Norristown",
    "sg:classifiers":[
        {
            "category":"Real Estate",
            "subcategory":"Surveying",
            "type":"Services"
        }
    ],
    "sg:phone":"+1   ",
    "sg:postcode":"19403",
    "sg:province":"PA",
    "wof:name":"CTA Surveys",
    "wof:placetype":"venue"
},
  "geometry": {"coordinates":[-75.37562,40.154047],"type":"Point"}
}