{
  "type": "Feature",
  "properties": {
    "iso:country":"US",
    "sg:address":"771 5th Ave",
    "sg:city":"King Of Prussia",
    "sg:classifiers":[
        {
            "category":"Professional",
            "subcategory":"Computer Services",
            "type":"Services"
        }
    ],
    "sg:phone":"+1 610 337 9266",
    "sg:postcode":"19406",
    "sg:province":"PA",
    "sg:tags":[
        "repair"
    ],
    "wof:name":"Systems Maintenance Svc",
    "wof:placetype":"venue"
},
  "geometry": {"coordinates":[-75.405365,40.103248],"type":"Point"}
}