{
  "type": "Feature",
  "properties": {
    "iso:country":"US",
    "sg:address":"1309 Sunset Dr",
    "sg:city":"Butler",
    "sg:classifiers":[
        {
            "category":"Manufacturing",
            "subcategory":"Metals",
            "type":"Manufacturing & Wholesale Goods"
        },
        {
            "category":"Manufacturing",
            "subcategory":"Building Materials",
            "type":"Manufacturing & Wholesale Goods"
        }
    ],
    "sg:phone":"+1 724 287 5934",
    "sg:postcode":"16001",
    "sg:province":"PA",
    "sg:tags":[
        "windows-metal",
        "window",
        "door",
        "storm"
    ],
    "wof:name":"Snyder Storm Window Co",
    "wof:placetype":"venue"
},
  "geometry": {"coordinates":[-79.964513,40.94613],"type":"Point"}
}