{
  "type": "Feature",
  "properties": {
    "iso:country":"US",
    "sg:address":"52 N Lehigh Ave",
    "sg:city":"Frackville",
    "sg:classifiers":[
        {
            "category":"Autos & Motor Vehicles",
            "subcategory":"Automobile Sales",
            "type":"Retail Goods"
        }
    ],
    "sg:phone":"+1 570 874 0901",
    "sg:postcode":"17931",
    "sg:province":"PA",
    "sg:tags":[
        "car",
        "dealer"
    ],
    "wof:name":"Atlantic Motors Inc",
    "wof:placetype":"venue"
},
  "geometry": {"coordinates":[-76.231336,40.785843],"type":"Point"}
}