{
  "type": "Feature",
  "properties": {
    "iso:country":"US",
    "sg:address":"106 Inverness Dr",
    "sg:city":"Blue Bell",
    "sg:classifiers":[
        {
            "category":"Professional",
            "subcategory":"Engineering",
            "type":"Services"
        }
    ],
    "sg:phone":"+1 610 270 3922",
    "sg:postcode":"19422",
    "sg:province":"PA",
    "sg:tags":[
        "engineer"
    ],
    "wof:name":"Stanley P Halbert Inc",
    "wof:placetype":"venue"
},
  "geometry": {"coordinates":[-75.285236,40.1788],"type":"Point"}
}