{
  "type": "Feature",
  "properties": {
    "iso:country":"US",
    "sg:address":"703 S Kettle St",
    "sg:city":"Altoona",
    "sg:classifiers":[
        {
            "category":"Professional",
            "subcategory":"Business Services",
            "type":"Services"
        },
        {
            "category":"Manufacturing",
            "subcategory":"Printing",
            "type":"Manufacturing & Wholesale Goods"
        }
    ],
    "sg:phone":"+1 814 946 3482",
    "sg:postcode":"16602",
    "sg:province":"PA",
    "sg:tags":[
        "commercial",
        "embroidery"
    ],
    "wof:name":"E & E Logo's",
    "wof:placetype":"venue"
},
  "geometry": {"coordinates":[-78.37483899999999,40.519202],"type":"Point"}
}