{
  "type": "Feature",
  "properties": {
    "addr:full":"872 7th St New Kensington PA 15068",
    "addr:housenumber":"872",
    "addr:postcode":"15068",
    "addr:street":"7Th St",
    "iso:country":"US",
    "sg:address":"872 7th St",
    "sg:city":"New Kensington",
    "sg:classifiers":[
        {
            "category":"Bars & Pubs",
            "type":"Food & Drink"
        }
    ],
    "sg:phone":"+1 724 337 3300",
    "sg:postcode":"15068",
    "sg:province":"PA",
    "wof:name":"Valleys",
    "wof:placetype":"venue"
},
  "geometry": {"coordinates":[-79.75935200000001,40.563133],"type":"Point"}
}