{
  "type": "Feature",
  "properties": {
    "iso:country":"US",
    "sg:address":"121 E 4th St",
    "sg:city":"Gray",
    "sg:classifiers":[
        {
            "category":"Retail",
            "subcategory":"Auto Repair",
            "type":"Services"
        }
    ],
    "sg:phone":"+1 814 629 9320",
    "sg:postcode":"15544",
    "sg:province":"PA",
    "sg:tags":[
        "repairing",
        "automobile"
    ],
    "wof:name":"Merrill's Auto Repair",
    "wof:placetype":"venue"
},
  "geometry": {"coordinates":[-79.089241,40.136213],"type":"Point"}
}