{
  "type": "Feature",
  "properties": {
    "addr:full":"22 Mill St Uniontown PA 15401",
    "addr:housenumber":"22",
    "addr:postcode":"15401",
    "addr:street":"Mill St",
    "iso:country":"US",
    "sg:address":"22 Mill St",
    "sg:city":"Uniontown",
    "sg:classifiers":[
        {
            "category":"Health Services",
            "subcategory":"Doctor",
            "type":"Services"
        }
    ],
    "sg:phone":"+1 724 437 1582",
    "sg:postcode":"15401",
    "sg:province":"PA",
    "sg:tags":[
        "physician",
        "surgeon"
    ],
    "sg:website":"www.fhcinc.org",
    "wof:name":"Family Health Council Inc",
    "wof:placetype":"venue"
},
  "geometry": {"coordinates":[-79.729175,39.900113],"type":"Point"}
}