{
  "type": "Feature",
  "properties": {
    "iso:country":"US",
    "sg:address":"201 E Doris Ave",
    "sg:city":"State College",
    "sg:classifiers":[
        {
            "category":"Banks & Credit Unions",
            "subcategory":"Investment Brokerage",
            "type":"Services"
        }
    ],
    "sg:phone":"+1 814 234 2001",
    "sg:postcode":"16801",
    "sg:province":"PA",
    "sg:tags":[
        "stock",
        "bond"
    ],
    "wof:name":"Finberg Financial Svc FASI",
    "wof:placetype":"venue"
},
  "geometry": {"coordinates":[-77.84092800000001,40.781163],"type":"Point"}
}