{
  "type": "Feature",
  "properties": {
    "iso:country":"US",
    "sg:address":"284 Main St",
    "sg:city":"Exton",
    "sg:classifiers":[
        {
            "category":"Shopping",
            "subcategory":"Used Merchandise",
            "type":"Retail Goods"
        }
    ],
    "sg:phone":"+1 610 594 0186",
    "sg:postcode":"19341",
    "sg:province":"PA",
    "sg:tags":[
        "antique"
    ],
    "sg:website":"www.bombaycompany.com",
    "wof:name":"Bombay Co",
    "wof:placetype":"venue"
},
  "geometry": {"coordinates":[-75.62763200000001,40.02228],"type":"Point"}
}