{
  "type": "Feature",
  "properties": {
    "iso:country":"US",
    "sg:address":"228 E Walnut St",
    "sg:city":"Titusville",
    "sg:classifiers":[
        {
            "category":"Banks & Credit Unions",
            "subcategory":"Bank",
            "type":"Services"
        }
    ],
    "sg:phone":"+1 814 827 6893",
    "sg:postcode":"16354",
    "sg:province":"PA",
    "wof:name":"Washington Mutual",
    "wof:placetype":"venue"
},
  "geometry": {"coordinates":[-79.670328,41.629521],"type":"Point"}
}