{
  "type": "Feature",
  "properties": {
    "iso:country":"US",
    "sg:address":"125 S 4th St",
    "sg:city":"Sunbury",
    "sg:classifiers":[
        {
            "category":"Retail",
            "subcategory":"Auto Repair",
            "type":"Services"
        }
    ],
    "sg:phone":"+1 570 648 9857",
    "sg:postcode":"17801",
    "sg:province":"PA",
    "sg:tags":[
        "repairing",
        "automobile"
    ],
    "wof:name":"Dans Service Ctr",
    "wof:placetype":"venue"
},
  "geometry": {"coordinates":[-76.792143,40.859264],"type":"Point"}
}