{
  "type": "Feature",
  "properties": {
    "iso:country":"US",
    "sg:address":"2507 Mill St",
    "sg:city":"Aliquippa",
    "sg:classifiers":[
        {
            "category":"Autos & Motor Vehicles",
            "subcategory":"Auto Supplies",
            "type":"Retail Goods"
        }
    ],
    "sg:phone":"+1 724 378 3396",
    "sg:postcode":"15001",
    "sg:province":"PA",
    "sg:tags":[
        "tire"
    ],
    "wof:name":"Smiley's Wholesale Tire Co",
    "wof:placetype":"venue"
},
  "geometry": {"coordinates":[-80.288419,40.604424],"type":"Point"}
}