{
  "type": "Feature",
  "properties": {
    "addr:full":"856 Joan Dr North Versailles PA 15137",
    "addr:housenumber":"856",
    "addr:postcode":"15137",
    "addr:street":"Joan Dr",
    "iso:country":"US",
    "sg:address":"856 Joan Dr",
    "sg:city":"North Versailles",
    "sg:classifiers":[
        {
            "category":"Shopping",
            "subcategory":"Jewelry",
            "type":"Retail Goods"
        }
    ],
    "sg:phone":"+1   ",
    "sg:postcode":"15137",
    "sg:province":"PA",
    "wof:name":"Heart of Gld Fine Jewelry",
    "wof:placetype":"venue"
},
  "geometry": {"coordinates":[-79.801391,40.365977],"type":"Point"}
}