{
  "type": "Feature",
  "properties": {
    "iso:country":"US",
    "sg:address":"530 Lycoming Mall Dr",
    "sg:city":"Muncy",
    "sg:classifiers":[
        {
            "category":"Autos & Motor Vehicles",
            "subcategory":"Auto Supplies",
            "type":"Retail Goods"
        }
    ],
    "sg:phone":"+1 570 546 8455",
    "sg:postcode":"17756",
    "sg:province":"PA",
    "sg:tags":[
        "automobile",
        "accessory"
    ],
    "wof:name":"Auto Trim Design",
    "wof:placetype":"venue"
},
  "geometry": {"coordinates":[-76.81744,41.235656],"type":"Point"}
}