{
  "type": "Feature",
  "properties": {
    "iso:country":"US",
    "sg:address":"244 Moyer Ridge Dr",
    "sg:city":"Manheim",
    "sg:classifiers":[
        {
            "category":"Manufacturing",
            "subcategory":"Food",
            "type":"Manufacturing & Wholesale Goods"
        },
        {
            "category":"Farming",
            "subcategory":"Farm",
            "type":"Manufacturing & Wholesale Goods"
        }
    ],
    "sg:phone":"+1 717 665 6914",
    "sg:postcode":"17545",
    "sg:province":"PA",
    "sg:tags":[
        "corn",
        "product"
    ],
    "wof:name":"Chet Crouse",
    "wof:placetype":"venue"
},
  "geometry": {"coordinates":[-76.41983,40.177052],"type":"Point"}
}