{
  "type": "Feature",
  "properties": {
    "iso:country":"US",
    "sg:address":"641 S Ramona Rd",
    "sg:city":"Myerstown",
    "sg:classifiers":[
        {
            "category":"Farming",
            "subcategory":"Dairy Farm",
            "type":"Manufacturing & Wholesale Goods"
        }
    ],
    "sg:phone":"+1   ",
    "sg:postcode":"17067",
    "sg:province":"PA",
    "wof:name":"Vincent A & Juliet Wagner",
    "wof:placetype":"venue"
},
  "geometry": {"coordinates":[-76.326718,40.337012],"type":"Point"}
}