{
  "type": "Feature",
  "properties": {
    "iso:country":"US",
    "sg:address":"431 Burmont Rd",
    "sg:city":"Drexel Hill",
    "sg:classifiers":[
        {
            "category":"Health Services",
            "subcategory":"Clinic",
            "type":"Services"
        }
    ],
    "sg:phone":"+1 610 872 2482",
    "sg:postcode":"19026",
    "sg:province":"PA",
    "sg:tags":[
        "holistic",
        "practitioner"
    ],
    "wof:name":"Ralph E Nigro",
    "wof:placetype":"venue"
},
  "geometry": {"coordinates":[-75.29836899999999,39.944898],"type":"Point"}
}