{
  "type": "Feature",
  "properties": {
    "iso:country":"US",
    "sg:address":"686 Pennsy Rd",
    "sg:city":"Willow Street",
    "sg:classifiers":[
        {
            "category":"Real Estate",
            "subcategory":"Real Estate Operator",
            "type":"Services"
        }
    ],
    "sg:phone":"+1   ",
    "sg:postcode":"17584",
    "sg:province":"PA",
    "sg:tags":[
        "mobile",
        "home",
        "site"
    ],
    "wof:name":"Smithville Mobile Home Village",
    "wof:placetype":"venue"
},
  "geometry": {"coordinates":[-76.25685900000001,39.926595],"type":"Point"}
}