{
  "type": "Feature",
  "properties": {
    "addr:full":"606 Hastings St S Williamsport PA 17702",
    "addr:housenumber":"606",
    "addr:postcode":"17702",
    "addr:street":"Hastings St S",
    "iso:country":"US",
    "sg:address":"606 Hastings St",
    "sg:city":"S Williamsport",
    "sg:classifiers":[
        {
            "category":"Restaurant",
            "type":"Food & Drink"
        }
    ],
    "sg:phone":"+1 570 323 2762",
    "sg:postcode":"17702",
    "sg:province":"PA",
    "wof:name":"Mark Restaurant",
    "wof:placetype":"venue"
},
  "geometry": {"coordinates":[-76.990188,41.228631],"type":"Point"}
}