{
  "type": "Feature",
  "properties": {
    "iso:country":"US",
    "sg:address":"1326 Freeport Rd",
    "sg:city":"Pittsburgh",
    "sg:classifiers":[
        {
            "category":"Health Services",
            "subcategory":"Clinic",
            "type":"Services"
        }
    ],
    "sg:phone":"+1 412 963 8090",
    "sg:postcode":"15238",
    "sg:province":"PA",
    "sg:tags":[
        "organization",
        "medical",
        "surgical"
    ],
    "wof:name":"American Adjustments Inc",
    "wof:placetype":"venue"
},
  "geometry": {"coordinates":[-79.876848,40.488812],"type":"Point"}
}