{
  "type": "Feature",
  "properties": {
    "iso:country":"US",
    "sg:address":"3854 Brighton Rd",
    "sg:city":"Pittsburgh",
    "sg:classifiers":[
        {
            "category":"Education",
            "subcategory":"School",
            "type":"Public Place"
        }
    ],
    "sg:phone":"+1 412 734 4096",
    "sg:postcode":"15212",
    "sg:province":"PA",
    "wof:name":"St Cyril School",
    "wof:placetype":"venue"
},
  "geometry": {"coordinates":[-80.0364,40.486099],"type":"Point"}
}