{
  "type": "Feature",
  "properties": {
    "iso:country":"US",
    "sg:address":"128 Commons Ct",
    "sg:city":"Chadds Ford",
    "sg:classifiers":[
        {
            "category":"Professional",
            "subcategory":"Lawyer & Legal Services",
            "type":"Services"
        }
    ],
    "sg:phone":"+1 610 558 4300",
    "sg:postcode":"19317",
    "sg:province":"PA",
    "wof:name":"Bria Robert B ESQ",
    "wof:placetype":"venue"
},
  "geometry": {"coordinates":[-75.566299,39.874901],"type":"Point"}
}