{
  "type": "Feature",
  "properties": {
    "iso:country":"US",
    "sg:address":"626 Lititz Manor Dr",
    "sg:city":"Lititz",
    "sg:classifiers":[
        {
            "category":"Real Estate",
            "subcategory":"Real Estate Operator",
            "type":"Services"
        }
    ],
    "sg:phone":"+1   ",
    "sg:postcode":"17543",
    "sg:province":"PA",
    "sg:tags":[
        "building",
        "apartment"
    ],
    "wof:name":"Lititz Manor",
    "wof:placetype":"venue"
},
  "geometry": {"coordinates":[-76.303544,40.144352],"type":"Point"}
}