{
  "type": "Feature",
  "properties": {
    "iso:country":"US",
    "sg:address":"135 Noble Rd",
    "sg:city":"Girard",
    "sg:classifiers":[
        {
            "category":"Manufacturing",
            "subcategory":"Rubber & Plastics",
            "type":"Manufacturing & Wholesale Goods"
        }
    ],
    "sg:phone":"+1 814 774 3491",
    "sg:postcode":"16417",
    "sg:province":"PA",
    "wof:name":"Girard Plastics LLC",
    "wof:placetype":"venue"
},
  "geometry": {"coordinates":[-80.32380000000001,41.99578],"type":"Point"}
}