{
  "type": "Feature",
  "properties": {
    "iso:country":"US",
    "sg:address":"131 Logan Rd",
    "sg:city":"New Castle",
    "sg:classifiers":[
        {
            "category":"Wholesale",
            "subcategory":"Electrical",
            "type":"Manufacturing & Wholesale Goods"
        }
    ],
    "sg:phone":"+1 724 657 5411",
    "sg:postcode":"16102",
    "sg:province":"PA",
    "sg:tags":[
        "control"
    ],
    "wof:name":"Torque Controls Inc",
    "wof:placetype":"venue"
},
  "geometry": {"coordinates":[-80.381539,40.921924],"type":"Point"}
}