{
  "type": "Feature",
  "properties": {
    "addr:full":"139 Supervisors Rd Lancaster PA 17603",
    "addr:housenumber":"139",
    "addr:postcode":"17603",
    "addr:street":"Supervisors Rd",
    "iso:country":"US",
    "sg:address":"139 Supervisors Rd",
    "sg:city":"Lancaster",
    "sg:classifiers":[
        {
            "category":"Building & Trades",
            "subcategory":"Plumbing",
            "type":"Services"
        }
    ],
    "sg:phone":"+1 717 871 6616",
    "sg:postcode":"17603",
    "sg:province":"PA",
    "sg:tags":[
        "conditioning",
        "air",
        "system",
        "contractor"
    ],
    "wof:name":"RSC Heating & Air Cond Co",
    "wof:placetype":"venue"
},
  "geometry": {"coordinates":[-76.411618,39.998584],"type":"Point"}
}