{
  "type": "Feature",
  "properties": {
    "iso:country":"US",
    "sg:address":"100 Park Cir",
    "sg:city":"Terre Hill",
    "sg:classifiers":[
        {
            "category":"Retail",
            "subcategory":"Auto Repair",
            "type":"Services"
        }
    ],
    "sg:phone":"+1 717 445 4340",
    "sg:postcode":"17581",
    "sg:province":"PA",
    "sg:tags":[
        "repairing",
        "tire"
    ],
    "wof:name":"New Holland Tire Co",
    "wof:placetype":"venue"
},
  "geometry": {"coordinates":[-76.05107599999999,40.159627],"type":"Point"}
}