{
  "type": "Feature",
  "properties": {
    "iso:country":"US",
    "sg:address":"200 Pleasant St",
    "sg:city":"Bradford",
    "sg:classifiers":[
        {
            "category":"Health Services",
            "subcategory":"Nursing And Care Facility",
            "type":"Services"
        }
    ],
    "sg:phone":"+1 814 362 4533",
    "sg:postcode":"16701",
    "sg:province":"PA",
    "sg:tags":[
        "skilled"
    ],
    "wof:name":"Bradford Nursing Pavilion",
    "wof:placetype":"venue"
},
  "geometry": {"coordinates":[-78.658221,41.960574],"type":"Point"}
}