{
  "type": "Feature",
  "properties": {
    "addr:full":"10 Abbey Rd New Freedom PA 17349",
    "addr:housenumber":"10",
    "addr:postcode":"17349",
    "addr:street":"Abbey Rd",
    "iso:country":"US",
    "sg:address":"10 Abbey Rd",
    "sg:city":"New Freedom",
    "sg:classifiers":[
        {
            "category":"Professional",
            "type":"Services"
        }
    ],
    "sg:phone":"+1   ",
    "sg:postcode":"17349",
    "sg:province":"PA",
    "wof:name":"Karentiques",
    "wof:placetype":"venue"
},
  "geometry": {"coordinates":[-76.679669,39.744961],"type":"Point"}
}