{
  "type": "Feature",
  "properties": {
    "iso:country":"US",
    "sg:address":"129 S Arch St",
    "sg:city":"Connellsville",
    "sg:classifiers":[
        {
            "category":"Health Services",
            "subcategory":"Doctor",
            "type":"Services"
        }
    ],
    "sg:phone":"+1 724 628 4640",
    "sg:postcode":"15425",
    "sg:province":"PA",
    "sg:tags":[
        "dentist"
    ],
    "wof:name":"John O Fishell Jr DDS",
    "wof:placetype":"venue"
},
  "geometry": {"coordinates":[-79.59116299999999,40.016878],"type":"Point"}
}