{
  "type": "Feature",
  "properties": {
    "iso:country":"US",
    "sg:address":"621 Jeffers Cir",
    "sg:city":"Exton",
    "sg:classifiers":[
        {
            "category":"Wholesale",
            "subcategory":"Metals & Minerals",
            "type":"Manufacturing & Wholesale Goods"
        }
    ],
    "sg:phone":"+1 610 524 6600",
    "sg:postcode":"19341",
    "sg:province":"PA",
    "sg:tags":[
        "product",
        "foundry"
    ],
    "wof:name":"RFP Technologies Inc",
    "wof:placetype":"venue"
},
  "geometry": {"coordinates":[-75.654372,40.010471],"type":"Point"}
}