{
  "type": "Feature",
  "properties": {
    "iso:country":"US",
    "sg:address":"800 N Front St",
    "sg:city":"Wormleysburg",
    "sg:classifiers":[
        {
            "category":"Organizations",
            "subcategory":"Community Association",
            "type":"Services"
        }
    ],
    "sg:phone":"+1 717 730 9100",
    "sg:postcode":"17043",
    "sg:province":"PA",
    "sg:tags":[
        "military"
    ],
    "sg:website":"www.pa-legion.com",
    "wof:name":"American Legion Dept Of Pa",
    "wof:placetype":"venue"
},
  "geometry": {"coordinates":[-76.909746,40.265789],"type":"Point"}
}