{
  "type": "Feature",
  "properties": {
    "iso:country":"US",
    "sg:address":"2217 Linden St",
    "sg:city":"Bethlehem",
    "sg:classifiers":[
        {
            "category":"Professional",
            "subcategory":"Accounting & Tax Preparation",
            "type":"Services"
        }
    ],
    "sg:phone":"+1 610 868 5457",
    "sg:postcode":"18017",
    "sg:province":"PA",
    "sg:tags":[
        "accountant"
    ],
    "wof:name":"Maureen G O'Connell CPA",
    "wof:placetype":"venue"
},
  "geometry": {"coordinates":[-75.363462,40.643871],"type":"Point"}
}