{
  "type": "Feature",
  "properties": {
    "iso:country":"US",
    "sg:address":"1650 Mudlick Rd",
    "sg:city":"Julian",
    "sg:classifiers":[
        {
            "category":"Wholesale",
            "subcategory":"Construction Materials",
            "type":"Manufacturing & Wholesale Goods"
        }
    ],
    "sg:phone":"+1 814 692 5041",
    "sg:postcode":"16844",
    "sg:province":"PA",
    "sg:tags":[
        "building",
        "materials-wholesale",
        "manufacturer"
    ],
    "wof:name":"Thomas Brown",
    "wof:placetype":"venue"
},
  "geometry": {"coordinates":[-78.01003300000001,40.872559],"type":"Point"}
}