{
  "type": "Feature",
  "properties": {
    "addr:full":"716 E 2nd St Oil City PA 16301",
    "addr:housenumber":"716",
    "addr:postcode":"16301",
    "addr:street":"E 2Nd St",
    "iso:country":"US",
    "sg:address":"716 E 2nd St",
    "sg:city":"Oil City",
    "sg:classifiers":[
        {
            "category":"Social Services",
            "subcategory":"Adult Care",
            "type":"Services"
        }
    ],
    "sg:phone":"+1   ",
    "sg:postcode":"16301",
    "sg:province":"PA",
    "sg:tags":[
        "residential"
    ],
    "wof:name":"Domestic Vlnce Rape Crisis Svc",
    "wof:placetype":"venue"
},
  "geometry": {"coordinates":[-79.70397699999999,41.426164],"type":"Point"}
}