{
  "type": "Feature",
  "properties": {
    "iso:country":"US",
    "sg:address":"7927 National Pike",
    "sg:city":"Addison",
    "sg:classifiers":[
        {
            "category":"Building & Trades",
            "subcategory":"Landscaping Services",
            "type":"Services"
        }
    ],
    "sg:phone":"+1   ",
    "sg:postcode":"15411",
    "sg:province":"PA",
    "wof:name":"Mountain View Stump Grinding",
    "wof:placetype":"venue"
},
  "geometry": {"coordinates":[-79.321128,39.735824],"type":"Point"}
}