{
  "type": "Feature",
  "properties": {
    "addr:full":"1257 Carmont Dr Meadville PA 16335",
    "addr:housenumber":"1257",
    "addr:postcode":"16335",
    "addr:street":"Carmont Dr",
    "iso:country":"US",
    "sg:address":"1257 Carmont Dr",
    "sg:city":"Meadville",
    "sg:classifiers":[
        {
            "category":"Wholesale",
            "subcategory":"Construction Materials",
            "type":"Manufacturing & Wholesale Goods"
        }
    ],
    "sg:phone":"+1   ",
    "sg:postcode":"16335",
    "sg:province":"PA",
    "sg:tags":[
        "roofing"
    ],
    "wof:name":"Cooley Incorporated",
    "wof:placetype":"venue"
},
  "geometry": {"coordinates":[-80.149044,41.625586],"type":"Point"}
}