{
  "type": "Feature",
  "properties": {
    "iso:country":"US",
    "sg:address":"3905 Washington Rd",
    "sg:city":"Canonsburg",
    "sg:classifiers":[
        {
            "category":"Restaurant",
            "type":"Food & Drink"
        }
    ],
    "sg:phone":"+1 724 225 3557",
    "sg:postcode":"15317",
    "sg:province":"PA",
    "sg:tags":[
        "pizza"
    ],
    "wof:name":"Susy Bees",
    "wof:placetype":"venue"
},
  "geometry": {"coordinates":[-80.127594,40.27196],"type":"Point"}
}