{
  "type": "Feature",
  "properties": {
    "addr:full":"7030 Grovers Ave Philadelphia PA 19153",
    "addr:housenumber":"7030",
    "addr:postcode":"19153",
    "addr:street":"Grovers Ave",
    "iso:country":"US",
    "sg:address":"7030 Grovers Ave",
    "sg:city":"Philadelphia",
    "sg:classifiers":[
        {
            "category":"Restaurant",
            "type":"Food & Drink"
        }
    ],
    "sg:phone":"+1 215 937 0499",
    "sg:postcode":"19153",
    "sg:province":"PA",
    "wof:name":"China House II",
    "wof:placetype":"venue"
},
  "geometry": {"coordinates":[-75.23397799999999,39.913441],"type":"Point"}
}