{
  "type": "Feature",
  "properties": {
    "addr:full":"736 S Duke St Lancaster PA 17602",
    "addr:housenumber":"736",
    "addr:postcode":"17602",
    "addr:street":"S Duke St",
    "iso:country":"US",
    "sg:address":"736 S Duke St",
    "sg:city":"Lancaster",
    "sg:classifiers":[
        {
            "category":"Organizations",
            "subcategory":"Religious Organization",
            "type":"Services"
        }
    ],
    "sg:phone":"+1 717 295 1971",
    "sg:postcode":"17602",
    "sg:province":"PA",
    "sg:tags":[
        "church"
    ],
    "wof:name":"Semple Methodist Church Africn",
    "wof:placetype":"venue"
},
  "geometry": {"coordinates":[-76.296376,40.030857],"type":"Point"}
}