{
  "type": "Feature",
  "properties": {
    "iso:country":"US",
    "sg:address":"253 Main St",
    "sg:city":"Mohnton",
    "sg:classifiers":[
        {
            "category":"Professional",
            "type":"Services"
        }
    ],
    "sg:phone":"+1   ",
    "sg:postcode":"19540",
    "sg:province":"PA",
    "wof:name":"Rowe Dorismarie",
    "wof:placetype":"venue"
},
  "geometry": {"coordinates":[-75.981104,40.277645],"type":"Point"}
}