{
  "type": "Feature",
  "properties": {
    "iso:country":"US",
    "sg:address":"270 Kathy St",
    "sg:city":"Philipsburg",
    "sg:classifiers":[
        {
            "category":"Education",
            "subcategory":"Kindergarten",
            "type":"Public Place"
        }
    ],
    "sg:phone":"+1 814 342 3689",
    "sg:postcode":"16866",
    "sg:province":"PA",
    "sg:tags":[
        "parenting-centers",
        "birth"
    ],
    "sg:website":"http://www.winbeam.net",
    "wof:name":"Everyday Miracles Birthin",
    "wof:placetype":"venue"
},
  "geometry": {"coordinates":[-78.213553,40.887428],"type":"Point"}
}