{
  "type": "Feature",
  "properties": {
    "iso:country":"US",
    "sg:address":"1520 Locust St",
    "sg:city":"Philadelphia",
    "sg:classifiers":[
        {
            "category":"Professional",
            "subcategory":"Lawyer & Legal Services",
            "type":"Services"
        }
    ],
    "sg:phone":"+1 215 545 3000",
    "sg:postcode":"19102",
    "sg:province":"PA",
    "wof:name":"Manochi Glenn A Atty",
    "wof:placetype":"venue"
},
  "geometry": {"coordinates":[-75.166496,39.948399],"type":"Point"}
}