{
  "type": "Feature",
  "properties": {
    "iso:country":"US",
    "sg:address":"21 W 2nd St",
    "sg:city":"Wind Gap",
    "sg:classifiers":[
        {
            "category":"Insurance",
            "subcategory":"Insurance Agent",
            "type":"Services"
        }
    ],
    "sg:phone":"+1 610 863 3300",
    "sg:postcode":"18091",
    "sg:province":"PA",
    "wof:name":"All State Insurance",
    "wof:placetype":"venue"
},
  "geometry": {"coordinates":[-75.29667600000001,40.841021],"type":"Point"}
}