{
  "type": "Feature",
  "properties": {
    "addr:full":"901 Washington St Conshohocken PA 19428",
    "addr:housenumber":"901",
    "addr:postcode":"19428",
    "addr:street":"Washington St",
    "iso:country":"US",
    "sg:address":"901 Washington St",
    "sg:city":"Conshohocken",
    "sg:classifiers":[
        {
            "category":"Manufacturing",
            "subcategory":"Chemicals & Compounds",
            "type":"Manufacturing & Wholesale Goods"
        }
    ],
    "sg:phone":"+1 610 825 1900",
    "sg:postcode":"19428",
    "sg:province":"PA",
    "sg:tags":[
        "mfg"
    ],
    "wof:name":"Finnaren & Haley Inc",
    "wof:placetype":"venue"
},
  "geometry": {"coordinates":[-75.297562,40.072195],"type":"Point"}
}