{
  "type": "Feature",
  "properties": {
    "iso:country":"US",
    "sg:address":"5207 Walnut St",
    "sg:city":"Philadelphia",
    "sg:classifiers":[
        {
            "category":"Shopping",
            "subcategory":"Clothing, Apparel, & Fashions",
            "type":"Retail Goods"
        }
    ],
    "sg:phone":"+1 215 476 3234",
    "sg:postcode":"19139",
    "sg:province":"PA",
    "wof:name":"Tooba Fashions",
    "wof:placetype":"venue"
},
  "geometry": {"coordinates":[-75.225854,39.957262],"type":"Point"}
}