{
  "type": "Feature",
  "properties": {
    "iso:country":"US",
    "sg:address":"161 N Richard St",
    "sg:city":"Bedford",
    "sg:classifiers":[
        {
            "category":"Autos & Motor Vehicles",
            "subcategory":"Fuel & Gas Station",
            "type":"Retail Goods"
        }
    ],
    "sg:phone":"+1 814 623 6181",
    "sg:postcode":"15522",
    "sg:province":"PA",
    "sg:tags":[
        "oil"
    ],
    "wof:name":"Ressler's Bedford Exxon Svc",
    "wof:placetype":"venue"
},
  "geometry": {"coordinates":[-78.502105,40.021915],"type":"Point"}
}