{
  "type": "Feature",
  "properties": {
    "iso:country":"US",
    "sg:address":"317 1st St",
    "sg:city":"Donora",
    "sg:classifiers":[
        {
            "category":"Organizations",
            "subcategory":"Religious Organization",
            "type":"Services"
        }
    ],
    "sg:phone":"+1 724 379 5507",
    "sg:postcode":"15033",
    "sg:province":"PA",
    "sg:tags":[
        "church"
    ],
    "wof:name":"Quinn Chapel AME",
    "wof:placetype":"venue"
},
  "geometry": {"coordinates":[-79.859163,40.17264],"type":"Point"}
}