{
  "type": "Feature",
  "properties": {
    "iso:country":"US",
    "sg:address":"206 S Broad St",
    "sg:city":"Lititz",
    "sg:classifiers":[
        {
            "category":"Building & Trades",
            "subcategory":"Construction",
            "type":"Services"
        }
    ],
    "sg:phone":"+1 717 627 1468",
    "sg:postcode":"17543",
    "sg:province":"PA",
    "sg:tags":[
        "painter"
    ],
    "wof:name":"Hamilton Painting",
    "wof:placetype":"venue"
},
  "geometry": {"coordinates":[-76.30722799999999,40.15177],"type":"Point"}
}