{
  "type": "Feature",
  "properties": {
    "addr:full":"147 Prospect St Tobyhanna PA 18466",
    "addr:housenumber":"147",
    "addr:postcode":"18466",
    "addr:street":"Prospect St",
    "iso:country":"US",
    "sg:address":"147 Prospect St",
    "sg:city":"Tobyhanna",
    "sg:classifiers":[
        {
            "category":"Building & Trades",
            "subcategory":"Construction",
            "type":"Services"
        }
    ],
    "sg:phone":"+1 570 839 7764",
    "sg:postcode":"18466",
    "sg:province":"PA",
    "sg:tags":[
        "home",
        "contractor",
        "general",
        "family",
        "residential"
    ],
    "wof:name":"Pobar Homes",
    "wof:placetype":"venue"
},
  "geometry": {"coordinates":[-75.418837,41.176309],"type":"Point"}
}