{
  "type": "Feature",
  "properties": {
    "addr:full":"2333 E Cambria St Philadelphia PA 19134",
    "addr:housenumber":"2333",
    "addr:postcode":"19134",
    "addr:street":"E Cambria St",
    "iso:country":"US",
    "sg:address":"2333 E Cambria St",
    "sg:city":"Philadelphia",
    "sg:classifiers":[
        {
            "category":"Banks & Credit Unions",
            "subcategory":"Bank",
            "type":"Services"
        }
    ],
    "sg:phone":"+1 215 739 7785",
    "sg:postcode":"19134",
    "sg:province":"PA",
    "sg:tags":[
        "cashing",
        "check"
    ],
    "wof:name":"Fast Cash Atm",
    "wof:placetype":"venue"
},
  "geometry": {"coordinates":[-75.11412300000001,39.985932],"type":"Point"}
}