{
  "type": "Feature",
  "properties": {
    "iso:country":"US",
    "sg:address":"706 Game Reserve Rd",
    "sg:city":"Butler",
    "sg:classifiers":[
        {
            "category":"Building & Trades",
            "subcategory":"Landscaping Services",
            "type":"Services"
        }
    ],
    "sg:phone":"+1   ",
    "sg:postcode":"16002",
    "sg:province":"PA",
    "sg:tags":[
        "tree"
    ],
    "wof:name":"Steve K Allen",
    "wof:placetype":"venue"
},
  "geometry": {"coordinates":[-79.77688999999999,40.899582],"type":"Point"}
}