{
  "type": "Feature",
  "properties": {
    "iso:country":"US",
    "sg:address":"6 Stauffer Industrial Park",
    "sg:city":"Taylor",
    "sg:classifiers":[
        {
            "category":"Wholesale",
            "subcategory":"Office Equipment",
            "type":"Manufacturing & Wholesale Goods"
        },
        {
            "category":"Professional",
            "subcategory":"Printing & Photocopies",
            "type":"Services"
        },
        {
            "category":"Shopping",
            "subcategory":"Computers & Home Electronics",
            "type":"Retail Goods"
        }
    ],
    "sg:phone":"+1 570 562 3060",
    "sg:postcode":"18517",
    "sg:province":"PA",
    "sg:tags":[
        "lithographer",
        "scanning",
        "printer",
        "plotting",
        "supply"
    ],
    "sg:website":"http://www.artprintco.com",
    "wof:name":"Art-Print Company",
    "wof:placetype":"venue"
},
  "geometry": {"coordinates":[-75.70188899999999,41.393291],"type":"Point"}
}