{
  "type": "Feature",
  "properties": {
    "addr:full":"2770 Oakland Rd Dover PA 17315",
    "addr:housenumber":"2770",
    "addr:postcode":"17315",
    "addr:street":"Oakland Rd",
    "iso:country":"US",
    "sg:address":"2770 Oakland Rd",
    "sg:city":"Dover",
    "sg:classifiers":[
        {
            "category":"Retail",
            "subcategory":"Repair Shop",
            "type":"Services"
        }
    ],
    "sg:phone":"+1 717 764 3185",
    "sg:postcode":"17315",
    "sg:province":"PA",
    "sg:tags":[
        "taxidermist"
    ],
    "wof:name":"Terry's Taxidermy",
    "wof:placetype":"venue"
},
  "geometry": {"coordinates":[-76.83103300000001,39.973169],"type":"Point"}
}