{
  "type": "Feature",
  "properties": {
    "iso:country":"US",
    "sg:address":"6290 Allentown Blvd",
    "sg:city":"Harrisburg",
    "sg:classifiers":[
        {
            "category":"Restaurant",
            "type":"Food & Drink"
        }
    ],
    "sg:phone":"+1 717 657 2908",
    "sg:postcode":"17112",
    "sg:province":"PA",
    "sg:tags":[
        "family"
    ],
    "wof:name":"Geo's Family Restaurant",
    "wof:placetype":"venue"
},
  "geometry": {"coordinates":[-76.785336,40.323766],"type":"Point"}
}