{
  "type": "Feature",
  "properties": {
    "iso:country":"US",
    "sg:address":"1313 S Pennsylvania Ave",
    "sg:city":"Morrisville",
    "sg:classifiers":[
        {
            "category":"Freight",
            "type":"Transportation"
        }
    ],
    "sg:phone":"+1 215 295 8877",
    "sg:postcode":"19067",
    "sg:province":"PA",
    "wof:name":"Labor & Logistics",
    "wof:placetype":"venue"
},
  "geometry": {"coordinates":[-74.76888099999999,40.19567],"type":"Point"}
}