{
  "type": "Feature",
  "properties": {
    "addr:full":"742 Clifford St Warminster PA 18974",
    "addr:housenumber":"742",
    "addr:postcode":"18974",
    "addr:street":"Clifford St",
    "iso:country":"US",
    "sg:address":"742 Clifford St",
    "sg:city":"Warminster",
    "sg:classifiers":[
        {
            "category":"Home & Garden",
            "subcategory":"Garden Supply",
            "type":"Retail Goods"
        }
    ],
    "sg:phone":"+1 215 672 9366",
    "sg:postcode":"18974",
    "sg:province":"PA",
    "sg:tags":[
        "equipment",
        "landscaping"
    ],
    "wof:name":"Tomeo Landscaping",
    "wof:placetype":"venue"
},
  "geometry": {"coordinates":[-75.119579,40.224501],"type":"Point"}
}