{
  "type": "Feature",
  "properties": {
    "iso:country":"US",
    "sg:address":"2548 W Chester Pike",
    "sg:city":"Broomall",
    "sg:classifiers":[
        {
            "category":"Shopping",
            "subcategory":"Clothing, Apparel, & Fashions",
            "type":"Retail Goods"
        }
    ],
    "sg:phone":"+1   ",
    "sg:postcode":"19008",
    "sg:province":"PA",
    "sg:tags":[
        "shop",
        "bridal",
        "tailoring",
        "alteration"
    ],
    "wof:name":"Lillians Bridal Salon",
    "wof:placetype":"venue"
},
  "geometry": {"coordinates":[-75.358833,39.981394],"type":"Point"}
}