{
  "type": "Feature",
  "properties": {
    "iso:country":"US",
    "sg:address":"1108 Harpers Xing",
    "sg:city":"Langhorne",
    "sg:classifiers":[
        {
            "category":"Wholesale",
            "subcategory":"Poultry",
            "type":"Manufacturing & Wholesale Goods"
        }
    ],
    "sg:phone":"+1 215 917 4463",
    "sg:postcode":"19047",
    "sg:province":"PA",
    "sg:tags":[
        "farm"
    ],
    "wof:name":"Tri-State Meat And Poultry Inc",
    "wof:placetype":"venue"
},
  "geometry": {"coordinates":[-74.882599,40.193261],"type":"Point"}
}