{
  "type": "Feature",
  "properties": {
    "addr:full":"550 Sleepy Hollow Rd Pittsburgh PA 15228",
    "addr:housenumber":"550",
    "addr:postcode":"15228",
    "addr:street":"Sleepy Hollow Rd",
    "iso:country":"US",
    "sg:address":"550 Sleepy Hollow Rd",
    "sg:city":"Pittsburgh",
    "sg:classifiers":[
        {
            "category":"Organizations",
            "subcategory":"Membership Organization",
            "type":"Services"
        }
    ],
    "sg:phone":"+1   ",
    "sg:postcode":"15228",
    "sg:province":"PA",
    "wof:name":"Saint Winafred Food Pantry",
    "wof:placetype":"venue"
},
  "geometry": {"coordinates":[-80.022919,40.375958],"type":"Point"}
}