{
  "type": "Feature",
  "properties": {
    "iso:country":"US",
    "sg:address":"1240 Scalp Ave",
    "sg:city":"Johnstown",
    "sg:classifiers":[
        {
            "category":"Home & Garden",
            "subcategory":"Carpets & Floor Coverings",
            "type":"Retail Goods"
        }
    ],
    "sg:phone":"+1   ",
    "sg:postcode":"15904",
    "sg:province":"PA",
    "wof:name":"R E C Carpeting",
    "wof:placetype":"venue"
},
  "geometry": {"coordinates":[-78.860923,40.277084],"type":"Point"}
}