{
  "type": "Feature",
  "properties": {
    "addr:full":"280 Red Lion Rd Huntingdon Valley PA 19006",
    "addr:housenumber":"280",
    "addr:postcode":"19006",
    "addr:street":"Red Lion Rd",
    "iso:country":"US",
    "sg:address":"280 Red Lion Rd",
    "sg:city":"Huntingdon Valley",
    "sg:classifiers":[
        {
            "category":"Building & Trades",
            "subcategory":"Construction",
            "type":"Services"
        }
    ],
    "sg:phone":"+1   ",
    "sg:postcode":"19006",
    "sg:province":"PA",
    "sg:tags":[
        "concrete",
        "contractor"
    ],
    "wof:name":"William E Gentry Jr Concr",
    "wof:placetype":"venue"
},
  "geometry": {"coordinates":[-75.055154,40.117659],"type":"Point"}
}