{
  "type": "Feature",
  "properties": {
    "iso:country":"US",
    "sg:address":"1601 E Carson St",
    "sg:city":"Pittsburgh",
    "sg:classifiers":[
        {
            "category":"Bars & Pubs",
            "type":"Food & Drink"
        }
    ],
    "sg:phone":"+1 412 481 6880",
    "sg:postcode":"15203",
    "sg:province":"PA",
    "sg:tags":[
        "club",
        "nightlife",
        "night"
    ],
    "sg:website":"www.nicksfatcity.com",
    "wof:name":"Nick's Fat City",
    "wof:placetype":"venue"
},
  "geometry": {"coordinates":[-79.98249800000001,40.429001],"type":"Point"}
}