{
  "type": "Feature",
  "properties": {
    "iso:country":"US",
    "sg:address":"407 13th St",
    "sg:city":"New Brighton",
    "sg:classifiers":[
        {
            "category":"Professional",
            "subcategory":"Accounting & Tax Preparation",
            "type":"Services"
        }
    ],
    "sg:phone":"+1 724 847 7271",
    "sg:postcode":"15066",
    "sg:province":"PA",
    "sg:tags":[
        "accountant"
    ],
    "wof:name":"Louis Capo CPA",
    "wof:placetype":"venue"
},
  "geometry": {"coordinates":[-80.308468,40.731034],"type":"Point"}
}