{
  "type": "Feature",
  "properties": {
    "addr:full":"11 Roselawn Ln Malvern PA 19355",
    "addr:housenumber":"11",
    "addr:postcode":"19355",
    "addr:street":"Roselawn Ln",
    "iso:country":"US",
    "sg:address":"11 Roselawn Ln",
    "sg:city":"Malvern",
    "sg:classifiers":[
        {
            "category":"Shopping",
            "subcategory":"Computers & Home Electronics",
            "type":"Retail Goods"
        }
    ],
    "sg:phone":"+1   ",
    "sg:postcode":"19355",
    "sg:province":"PA",
    "wof:name":"Cutting Edge Technologies Inc",
    "wof:placetype":"venue"
},
  "geometry": {"coordinates":[-75.516597,39.997199],"type":"Point"}
}