{
  "type": "Feature",
  "properties": {
    "iso:country":"US",
    "sg:address":"14 E Main St",
    "sg:city":"Lititz",
    "sg:classifiers":[
        {
            "category":"Professional",
            "type":"Services"
        }
    ],
    "sg:phone":"+1   ",
    "sg:postcode":"17543",
    "sg:province":"PA",
    "wof:name":"Grand Cru Ltd",
    "wof:placetype":"venue"
},
  "geometry": {"coordinates":[-76.30718899999999,40.157138],"type":"Point"}
}