{
  "type": "Feature",
  "properties": {
    "iso:country":"US",
    "sg:address":"1703 Grand Blvd",
    "sg:city":"Monessen",
    "sg:classifiers":[
        {
            "category":"Wholesale",
            "subcategory":"Machinery & Supplies",
            "type":"Manufacturing & Wholesale Goods"
        }
    ],
    "sg:phone":"+1 724 684 8333",
    "sg:postcode":"15062",
    "sg:province":"PA",
    "sg:tags":[
        "baker"
    ],
    "wof:name":"Dzimiera Flour Co",
    "wof:placetype":"venue"
},
  "geometry": {"coordinates":[-79.881698,40.14582],"type":"Point"}
}