{
  "type": "Feature",
  "properties": {
    "iso:country":"US",
    "sg:address":"601 Mason St",
    "sg:city":"Phoenixville",
    "sg:classifiers":[
        {
            "category":"Building & Trades",
            "subcategory":"Construction",
            "type":"Services"
        }
    ],
    "sg:phone":"+1   ",
    "sg:postcode":"19460",
    "sg:province":"PA",
    "sg:tags":[
        "house"
    ],
    "wof:name":"Harkings Builders Inc",
    "wof:placetype":"venue"
},
  "geometry": {"coordinates":[-75.529245,40.131104],"type":"Point"}
}