{
  "type": "Feature",
  "properties": {
    "addr:full":"4148 Lancaster Ave Philadelphia PA 19104",
    "addr:housenumber":"4148",
    "addr:postcode":"19104",
    "addr:street":"Lancaster Ave",
    "iso:country":"US",
    "sg:address":"4148 Lancaster Ave",
    "sg:city":"Philadelphia",
    "sg:classifiers":[
        {
            "category":"Health Services",
            "subcategory":"Doctor",
            "type":"Services"
        }
    ],
    "sg:phone":"+1 215 662 0119",
    "sg:postcode":"19104",
    "sg:province":"PA",
    "sg:tags":[
        "physician",
        "surgeons",
        "manipulative",
        "osteopathic",
        "treatment",
        "surgeon"
    ],
    "wof:name":"David, Izola B, Do - Pcom Healthcare Ctr",
    "wof:placetype":"venue"
},
  "geometry": {"coordinates":[-75.206687,39.965843],"type":"Point"}
}