{
  "type": "Feature",
  "properties": {
    "iso:country":"US",
    "sg:address":"1453 Lake Ariel Hwy",
    "sg:city":"Lake Ariel",
    "sg:classifiers":[
        {
            "category":"Building & Trades",
            "subcategory":"Construction",
            "type":"Services"
        }
    ],
    "sg:phone":"+1 570 698 6870",
    "sg:postcode":"18436",
    "sg:province":"PA",
    "sg:tags":[
        "acoustical",
        "contractor"
    ],
    "wof:name":"Verrastro Insulation",
    "wof:placetype":"venue"
},
  "geometry": {"coordinates":[-75.36993699999999,41.457632],"type":"Point"}
}