{
  "type": "Feature",
  "properties": {
    "iso:country":"US",
    "sg:address":"1435 Buffalo Rd",
    "sg:city":"Erie",
    "sg:classifiers":[
        {
            "category":"Autos & Motor Vehicles",
            "subcategory":"Automobile Sales",
            "type":"Retail Goods"
        }
    ],
    "sg:phone":"+1 814 459 4309",
    "sg:postcode":"16503",
    "sg:province":"PA",
    "sg:tags":[
        "car",
        "dealer"
    ],
    "wof:name":"Erie Auto Sales",
    "wof:placetype":"venue"
},
  "geometry": {"coordinates":[-80.042824,42.128956],"type":"Point"}
}