{
  "type": "Feature",
  "properties": {
    "iso:country":"US",
    "sg:address":"1600 Coraopolis Heights Rd",
    "sg:city":"Coraopolis",
    "sg:classifiers":[
        {
            "category":"Health Services",
            "subcategory":"Doctor",
            "type":"Services"
        }
    ],
    "sg:phone":"+1 412 655 8650",
    "sg:postcode":"15108",
    "sg:province":"PA",
    "sg:tags":[
        "physician",
        "surgeon"
    ],
    "wof:name":"Allegheny Integrated Hlth Grp",
    "wof:placetype":"venue"
},
  "geometry": {"coordinates":[-80.20634699999999,40.499263],"type":"Point"}
}