{
  "type": "Feature",
  "properties": {
    "iso:country":"US",
    "sg:address":"115 W Newton Rd",
    "sg:city":"Herminie",
    "sg:classifiers":[
        {
            "category":"Education",
            "subcategory":"School",
            "type":"Public Place"
        }
    ],
    "sg:phone":"+1   ",
    "sg:postcode":"15637",
    "sg:province":"PA",
    "wof:name":"H W Good Elemetary",
    "wof:placetype":"venue"
},
  "geometry": {"coordinates":[-79.720321,40.258847],"type":"Point"}
}