{
  "type": "Feature",
  "properties": {
    "iso:country":"US",
    "sg:address":"204 National Ave",
    "sg:city":"Langhorne",
    "sg:classifiers":[
        {
            "category":"Education",
            "subcategory":"Special Training",
            "type":"Public Place"
        }
    ],
    "sg:phone":"+1 215 752 1549",
    "sg:postcode":"19047",
    "sg:province":"PA",
    "sg:tags":[
        "program"
    ],
    "wof:name":"Heart Safe",
    "wof:placetype":"venue"
},
  "geometry": {"coordinates":[-74.91673,40.178012],"type":"Point"}
}