{
  "type": "Feature",
  "properties": {
    "addr:full":"1200 Yocumtown Rd Etters PA 17319",
    "addr:housenumber":"1200",
    "addr:postcode":"17319",
    "addr:street":"Yocumtown Rd",
    "iso:country":"US",
    "sg:address":"1200 Yocumtown Rd",
    "sg:city":"Etters",
    "sg:classifiers":[
        {
            "category":"Freight",
            "type":"Transportation"
        }
    ],
    "sg:phone":"+1   ",
    "sg:postcode":"17319",
    "sg:province":"PA",
    "sg:tags":[
        "general"
    ],
    "wof:name":"Johnnies Escavating",
    "wof:placetype":"venue"
},
  "geometry": {"coordinates":[-76.805296,40.15767],"type":"Point"}
}