{
  "type": "Feature",
  "properties": {
    "iso:country":"US",
    "sg:address":"6 Timber Mill Ln",
    "sg:city":"Landenberg",
    "sg:classifiers":[
        {
            "category":"Banks & Credit Unions",
            "subcategory":"Investment Brokerage",
            "type":"Services"
        }
    ],
    "sg:phone":"+1 610 274 2127",
    "sg:postcode":"19350",
    "sg:province":"PA",
    "sg:tags":[
        "investing"
    ],
    "wof:name":"Qubit Investments Llc",
    "wof:placetype":"venue"
},
  "geometry": {"coordinates":[-75.772858,39.775651],"type":"Point"}
}