{
  "type": "Feature",
  "properties": {
    "addr:full":"1372 Harrington Rd Havertown PA 19083",
    "addr:housenumber":"1372",
    "addr:postcode":"19083",
    "addr:street":"Harrington Rd",
    "iso:country":"US",
    "sg:address":"1372 Harrington Rd",
    "sg:city":"Havertown",
    "sg:classifiers":[
        {
            "category":"Professional",
            "type":"Services"
        }
    ],
    "sg:phone":"+1   ",
    "sg:postcode":"19083",
    "sg:province":"PA",
    "wof:name":"Steven Malandra",
    "wof:placetype":"venue"
},
  "geometry": {"coordinates":[-75.322129,39.98152],"type":"Point"}
}