{
  "type": "Feature",
  "properties": {
    "addr:full":"10 E Franklin St New Freedom PA 17349",
    "addr:housenumber":"10",
    "addr:postcode":"17349",
    "addr:street":"E Franklin St",
    "iso:country":"US",
    "sg:address":"10 E Franklin St",
    "sg:city":"New Freedom",
    "sg:classifiers":[
        {
            "category":"Restaurant",
            "type":"Food & Drink"
        }
    ],
    "sg:phone":"+1 717 227 1122",
    "sg:postcode":"17349",
    "sg:province":"PA",
    "wof:name":"Fox's Pizza",
    "wof:placetype":"venue"
},
  "geometry": {"coordinates":[-76.69999300000001,39.739067],"type":"Point"}
}