{
  "type": "Feature",
  "properties": {
    "iso:country":"US",
    "sg:address":"2847 Bristol Pike",
    "sg:city":"Bensalem",
    "sg:classifiers":[
        {
            "category":"Retail",
            "subcategory":"Repair Shop",
            "type":"Services"
        }
    ],
    "sg:phone":"+1 215 639 6404",
    "sg:postcode":"19020",
    "sg:province":"PA",
    "sg:tags":[
        "equipment",
        "telephone",
        "system"
    ],
    "wof:name":"Us Connect",
    "wof:placetype":"venue"
},
  "geometry": {"coordinates":[-74.93661299999999,40.08356],"type":"Point"}
}