{
  "type": "Feature",
  "properties": {
    "addr:full":"324 Beechwood Rd Berwyn PA 19312",
    "addr:housenumber":"324",
    "addr:postcode":"19312",
    "addr:street":"Beechwood Rd",
    "iso:country":"US",
    "sg:address":"324 Beechwood Rd",
    "sg:city":"Berwyn",
    "sg:classifiers":[
        {
            "category":"Retail",
            "subcategory":"Auto Rental",
            "type":"Services"
        }
    ],
    "sg:phone":"+1   ",
    "sg:postcode":"19312",
    "sg:province":"PA",
    "sg:tags":[
        "passenger",
        "car"
    ],
    "wof:name":"Steve Avis",
    "wof:placetype":"venue"
},
  "geometry": {"coordinates":[-75.46203800000001,40.052724],"type":"Point"}
}