{
  "type": "Feature",
  "properties": {
    "addr:full":"213 E Main St Carnegie PA 15106",
    "addr:housenumber":"213",
    "addr:postcode":"15106",
    "addr:street":"E Main St",
    "iso:country":"US",
    "sg:address":"213 E Main St",
    "sg:city":"Carnegie",
    "sg:classifiers":[
        {
            "category":"Professional",
            "subcategory":"Management & Consulting",
            "type":"Services"
        }
    ],
    "sg:phone":"+1 412 279 8060",
    "sg:postcode":"15106",
    "sg:province":"PA",
    "sg:tags":[
        "consultant",
        "business"
    ],
    "wof:name":"Corfield Good Consulting Group",
    "wof:placetype":"venue"
},
  "geometry": {"coordinates":[-80.08516899999999,40.408504],"type":"Point"}
}