{
  "type": "Feature",
  "properties": {
    "addr:full":"1 Poplar St Pittsburgh PA 15205",
    "addr:housenumber":"1",
    "addr:postcode":"15205",
    "addr:street":"Poplar St",
    "iso:country":"US",
    "sg:address":"1 Poplar St",
    "sg:city":"Pittsburgh",
    "sg:classifiers":[
        {
            "category":"Restaurant",
            "type":"Food & Drink"
        }
    ],
    "sg:menulink":"http://www.allmenus.com/pa/green-tree/206768-mcdonalds/menu/",
    "sg:phone":"+1 412 921 3132",
    "sg:postcode":"15205",
    "sg:province":"PA",
    "sg:tags":[
        "burger",
        "american"
    ],
    "wof:name":"McDonald's",
    "wof:placetype":"venue"
},
  "geometry": {"coordinates":[-80.053364,40.42765],"type":"Point"}
}