{
  "type": "Feature",
  "properties": {
    "addr:full":"1269 Dekalb Pike Blue Bell PA 19422",
    "addr:housenumber":"1269",
    "addr:postcode":"19422",
    "addr:street":"Dekalb Pike",
    "iso:country":"US",
    "sg:address":"1269 Dekalb Pike",
    "sg:city":"Blue Bell",
    "sg:classifiers":[
        {
            "category":"Retail",
            "subcategory":"Car Wash",
            "type":"Services"
        }
    ],
    "sg:phone":"+1 610 296 9000",
    "sg:postcode":"19422",
    "sg:province":"PA",
    "wof:name":"Duke's Firehose Company Car & Truck Safety Wash",
    "wof:placetype":"venue"
},
  "geometry": {"coordinates":[-75.29540299999999,40.161701],"type":"Point"}
}