{
  "type": "Feature",
  "properties": {
    "addr:full":"500 Lincoln Ave Bellevue PA 15202",
    "addr:housenumber":"500",
    "addr:postcode":"15202",
    "addr:street":"Lincoln Ave",
    "iso:country":"US",
    "sg:address":"500 Lincoln Ave",
    "sg:city":"Bellevue",
    "sg:classifiers":[
        {
            "category":"Autos & Motor Vehicles",
            "subcategory":"Automobile Sales",
            "type":"Retail Goods"
        }
    ],
    "sg:phone":"+1 412 734 5000",
    "sg:postcode":"15202",
    "sg:province":"PA",
    "sg:tags":[
        "car",
        "dealer"
    ],
    "sg:website":"www.classicchevroletpgh.com",
    "wof:name":"Classic Chevrolet Geo",
    "wof:placetype":"venue"
},
  "geometry": {"coordinates":[-80.056302,40.495927],"type":"Point"}
}