{
  "type": "Feature",
  "properties": {
    "addr:full":"6539 Roosevelt Blvd Philadelphia PA 19149",
    "addr:housenumber":"6539",
    "addr:postcode":"19149",
    "addr:street":"Roosevelt Blvd",
    "iso:country":"US",
    "sg:address":"6539 Roosevelt Blvd",
    "sg:city":"Philadelphia",
    "sg:classifiers":[
        {
            "category":"Restaurant",
            "type":"Food & Drink"
        }
    ],
    "sg:menulink":"http://www.allmenus.com/pa/philadelphia/262574-spanish-island-restaurant/menu/",
    "sg:phone":"+1 215 744 5225",
    "sg:postcode":"19149",
    "sg:province":"PA",
    "sg:tags":[
        "spanish"
    ],
    "wof:name":"Spanish Island Restaurant",
    "wof:placetype":"venue"
},
  "geometry": {"coordinates":[-75.06605500000001,40.035785],"type":"Point"}
}