{
  "type": "Feature",
  "properties": {
    "iso:country":"US",
    "sg:address":"5593 Pleasant Ridge Rd",
    "sg:city":"Needmore",
    "sg:classifiers":[
        {
            "category":"Restaurant",
            "type":"Food & Drink"
        }
    ],
    "sg:phone":"+1   ",
    "sg:postcode":"17238",
    "sg:province":"PA",
    "sg:tags":[
        "eating"
    ],
    "wof:name":"Daves Funnel Cakes",
    "wof:placetype":"venue"
},
  "geometry": {"coordinates":[-78.111498,39.926179],"type":"Point"}
}