{
  "type": "Feature",
  "properties": {
    "addr:full":"636 Foote Ave Duryea PA 18642",
    "addr:housenumber":"636",
    "addr:postcode":"18642",
    "addr:street":"Foote Ave",
    "iso:country":"US",
    "sg:address":"636 Foote Ave",
    "sg:city":"Duryea",
    "sg:classifiers":[
        {
            "category":"Real Estate",
            "subcategory":"Real Estate Operator",
            "type":"Services"
        }
    ],
    "sg:phone":"+1 570 451 0693",
    "sg:postcode":"18642",
    "sg:province":"PA",
    "sg:tags":[
        "building",
        "apartment"
    ],
    "wof:name":"School House Apartments",
    "wof:placetype":"venue"
},
  "geometry": {"coordinates":[-75.755092,41.348723],"type":"Point"}
}