{
  "type": "Feature",
  "properties": {
    "iso:country":"US",
    "sg:address":"2099 S Breezewood Rd",
    "sg:city":"Breezewood",
    "sg:classifiers":[
        {
            "category":"Organizations",
            "subcategory":"Membership Organization",
            "type":"Services"
        }
    ],
    "sg:phone":"+1 814 735 4278",
    "sg:postcode":"15533",
    "sg:province":"PA",
    "wof:name":"Breezewood Veterans Home Assoc",
    "wof:placetype":"venue"
},
  "geometry": {"coordinates":[-78.244947,39.95462],"type":"Point"}
}