{
  "type": "Feature",
  "properties": {
    "addr:full":"600 W Chester Rd West Chester PA 19382",
    "addr:housenumber":"600",
    "addr:postcode":"19382",
    "addr:street":"W Chester Rd",
    "iso:country":"US",
    "sg:address":"600 W Chester Rd",
    "sg:city":"West Chester",
    "sg:classifiers":[
        {
            "category":"Professional",
            "subcategory":"Engineering",
            "type":"Services"
        }
    ],
    "sg:phone":"+1 610 431 3525",
    "sg:postcode":"19382",
    "sg:province":"PA",
    "sg:tags":[
        "engineer"
    ],
    "wof:name":"Valicor Pharmaplan",
    "wof:placetype":"venue"
},
  "geometry": {"coordinates":[-75.54539,39.910821],"type":"Point"}
}