{
  "type": "Feature",
  "properties": {
    "addr:full":"240 S Chestnut St Pittsburgh PA 15202",
    "addr:housenumber":"240",
    "addr:postcode":"15202",
    "addr:street":"S Chestnut St",
    "iso:country":"US",
    "sg:address":"240 S Chestnut St",
    "sg:city":"Pittsburgh",
    "sg:classifiers":[
        {
            "category":"Professional",
            "type":"Services"
        }
    ],
    "sg:phone":"+1   ",
    "sg:postcode":"15202",
    "sg:province":"PA",
    "wof:name":"Luther Brittany",
    "wof:placetype":"venue"
},
  "geometry": {"coordinates":[-80.066947,40.498731],"type":"Point"}
}