{
  "type": "Feature",
  "properties": {
    "addr:full":"2706 S 17th St Philadelphia PA 19145",
    "addr:housenumber":"2706",
    "addr:postcode":"19145",
    "addr:street":"S 17Th St",
    "iso:country":"US",
    "sg:address":"2706 S 17th St",
    "sg:city":"Philadelphia",
    "sg:classifiers":[
        {
            "category":"Building & Trades",
            "subcategory":"Cleaning & Sanitation",
            "type":"Services"
        }
    ],
    "sg:phone":"+1 215 668 1966",
    "sg:postcode":"19145",
    "sg:province":"PA",
    "sg:tags":[
        "butler",
        "maid"
    ],
    "wof:name":"Tidytouch Maid Svc",
    "wof:placetype":"venue"
},
  "geometry": {"coordinates":[-75.176512,39.916202],"type":"Point"}
}