{
  "type": "Feature",
  "properties": {
    "addr:full":"701 N Clewell St Bethlehem PA 18015",
    "addr:housenumber":"701",
    "addr:postcode":"18015",
    "addr:street":"N Clewell St",
    "iso:country":"US",
    "sg:address":"701 N Clewell St",
    "sg:city":"Bethlehem",
    "sg:classifiers":[
        {
            "category":"Freight",
            "type":"Transportation"
        }
    ],
    "sg:phone":"+1 610 954 0600",
    "sg:postcode":"18015",
    "sg:province":"PA",
    "sg:tags":[
        "storage",
        "commercial",
        "special"
    ],
    "wof:name":"Fountain Hill Self Storage",
    "wof:placetype":"venue"
},
  "geometry": {"coordinates":[-75.393861,40.604727],"type":"Point"}
}