{
  "type": "Feature",
  "properties": {
    "addr:full":"241 Broad St New Bethlehem PA 16242",
    "addr:housenumber":"241",
    "addr:postcode":"16242",
    "addr:street":"Broad St",
    "iso:country":"US",
    "sg:address":"241 Broad St",
    "sg:city":"New Bethlehem",
    "sg:classifiers":[
        {
            "category":"Health Services",
            "subcategory":"Medical Lab",
            "type":"Services"
        }
    ],
    "sg:phone":"+1 814 275 4427",
    "sg:postcode":"16242",
    "sg:province":"PA",
    "sg:tags":[
        "laboratory",
        "dental"
    ],
    "wof:name":"Ruby Dental Lab",
    "wof:placetype":"venue"
},
  "geometry": {"coordinates":[-79.33994300000001,41.000242],"type":"Point"}
}