{
  "type": "Feature",
  "properties": {
    "iso:country":"US",
    "sg:address":"1229 Leister Rd",
    "sg:city":"Fairhope",
    "sg:classifiers":[
        {
            "category":"Building & Trades",
            "subcategory":"Plumbing",
            "type":"Services"
        }
    ],
    "sg:phone":"+1   ",
    "sg:postcode":"15538",
    "sg:province":"PA",
    "sg:tags":[
        "contractor"
    ],
    "wof:name":"Martz Electric & Plumbing",
    "wof:placetype":"venue"
},
  "geometry": {"coordinates":[-78.85158,39.876474],"type":"Point"}
}