{
  "type": "Feature",
  "properties": {
    "iso:country":"US",
    "sg:address":"421 S Potomac St",
    "sg:city":"Waynesboro",
    "sg:classifiers":[
        {
            "category":"Wholesale",
            "subcategory":"Durable Goods & Equipment",
            "type":"Manufacturing & Wholesale Goods"
        }
    ],
    "sg:phone":"+1   ",
    "sg:postcode":"17268",
    "sg:province":"PA",
    "wof:name":"Barry L Punt Jr",
    "wof:placetype":"venue"
},
  "geometry": {"coordinates":[-77.58659,39.749798],"type":"Point"}
}