{
  "type": "Feature",
  "properties": {
    "addr:full":"110 E Katherine Ave Washington PA 15301",
    "addr:housenumber":"110",
    "addr:postcode":"15301",
    "addr:street":"E Katherine Ave",
    "iso:country":"US",
    "sg:address":"110 E Katherine Ave",
    "sg:city":"Washington",
    "sg:classifiers":[
        {
            "category":"Freight",
            "type":"Transportation"
        }
    ],
    "sg:phone":"+1 724 222 0434",
    "sg:postcode":"15301",
    "sg:province":"PA",
    "wof:name":"New Millenium Transport",
    "wof:placetype":"venue"
},
  "geometry": {"coordinates":[-80.24524,40.180305],"type":"Point"}
}