{
  "type": "Feature",
  "properties": {
    "iso:country":"US",
    "sg:address":"1717 Somerset St",
    "sg:city":"Dresher",
    "sg:classifiers":[
        {
            "category":"Insurance",
            "subcategory":"Insurance Agent",
            "type":"Services"
        }
    ],
    "sg:phone":"+1   ",
    "sg:postcode":"19025",
    "sg:province":"PA",
    "wof:name":"Debra Schachter Insurance",
    "wof:placetype":"venue"
},
  "geometry": {"coordinates":[-75.15582499999999,40.158351],"type":"Point"}
}