{
  "type": "Feature",
  "properties": {
    "addr:full":"396 Blossom Hill Dr Lancaster PA 17601",
    "addr:housenumber":"396",
    "addr:postcode":"17601",
    "addr:street":"Blossom Hill Dr",
    "iso:country":"US",
    "sg:address":"396 Blossom Hill Dr",
    "sg:city":"Lancaster",
    "sg:classifiers":[
        {
            "category":"Professional",
            "subcategory":"Detective & Security Services",
            "type":"Services"
        }
    ],
    "sg:phone":"+1   ",
    "sg:postcode":"17601",
    "sg:province":"PA",
    "sg:tags":[
        "system"
    ],
    "wof:name":"Superior Security Systems Inc",
    "wof:placetype":"venue"
},
  "geometry": {"coordinates":[-76.325577,40.089343],"type":"Point"}
}