{
  "type": "Feature",
  "properties": {
    "iso:country":"US",
    "sg:address":"102 Grandview Rd",
    "sg:city":"Boyertown",
    "sg:classifiers":[
        {
            "category":"Professional",
            "type":"Services"
        }
    ],
    "sg:phone":"+1   ",
    "sg:postcode":"19512",
    "sg:province":"PA",
    "wof:name":"Hitchcock Walls & Windows Inc",
    "wof:placetype":"venue"
},
  "geometry": {"coordinates":[-75.682864,40.342887],"type":"Point"}
}