{
  "type": "Feature",
  "properties": {
    "addr:full":"401 Coraopolis Rd Coraopolis PA 15108",
    "addr:housenumber":"401",
    "addr:postcode":"15108",
    "addr:street":"Coraopolis Rd",
    "iso:country":"US",
    "sg:address":"401 Coraopolis Rd",
    "sg:city":"Coraopolis",
    "sg:classifiers":[
        {
            "category":"Freight",
            "type":"Transportation"
        }
    ],
    "sg:phone":"+1 412 264 9100",
    "sg:postcode":"15108",
    "sg:province":"PA",
    "sg:tags":[
        "commercial",
        "storage"
    ],
    "wof:name":"A-1 Self Storage Ctr",
    "wof:placetype":"venue"
},
  "geometry": {"coordinates":[-80.137563,40.503607],"type":"Point"}
}