{
  "type": "Feature",
  "properties": {
    "iso:country":"US",
    "sg:address":"133 Possum Hollow Rd",
    "sg:city":"Pottstown",
    "sg:classifiers":[
        {
            "category":"Professional",
            "type":"Services"
        },
        {
            "category":"Professional",
            "subcategory":"Management & Consulting",
            "type":"Services"
        }
    ],
    "sg:phone":"+1 610 495 8110",
    "sg:postcode":"19464",
    "sg:province":"PA",
    "sg:tags":[
        "party",
        "planning"
    ],
    "sg:website":"www.partiesevents.com",
    "wof:name":"Parties Events & More Inc",
    "wof:placetype":"venue"
},
  "geometry": {"coordinates":[-75.56369100000001,40.234087],"type":"Point"}
}