{
  "type": "Feature",
  "properties": {
    "addr:full":"5025 Wayne Ave Philadelphia PA 19144",
    "addr:housenumber":"5025",
    "addr:postcode":"19144",
    "addr:street":"Wayne Ave",
    "iso:country":"US",
    "sg:address":"5025 Wayne Ave",
    "sg:city":"Philadelphia",
    "sg:classifiers":[
        {
            "category":"Retail",
            "subcategory":"Laundry & Dry Cleaning",
            "type":"Services"
        }
    ],
    "sg:phone":"+1 215 842 4904",
    "sg:postcode":"19144",
    "sg:province":"PA",
    "sg:tags":[
        "carpet"
    ],
    "wof:name":"Precision Carpet Cleaning by Watts",
    "wof:placetype":"venue"
},
  "geometry": {"coordinates":[-75.16860200000001,40.025799],"type":"Point"}
}