{
  "type": "Feature",
  "properties": {
    "addr:full":"601 Seneca St Essington PA 19029",
    "addr:housenumber":"601",
    "addr:postcode":"19029",
    "addr:street":"Seneca St",
    "iso:country":"US",
    "sg:address":"601 Seneca St",
    "sg:city":"Essington",
    "sg:classifiers":[
        {
            "category":"Organizations",
            "subcategory":"Religious Organization",
            "type":"Services"
        }
    ],
    "sg:phone":"+1   ",
    "sg:postcode":"19029",
    "sg:province":"PA",
    "wof:name":"St Johns Luth Church",
    "wof:placetype":"venue"
},
  "geometry": {"coordinates":[-75.283716,39.872192],"type":"Point"}
}