{
  "type": "Feature",
  "properties": {
    "addr:full":"4921 Locust St Philadelphia PA 19139",
    "addr:housenumber":"4921",
    "addr:postcode":"19139",
    "addr:street":"Locust St",
    "iso:country":"US",
    "sg:address":"4921 Locust St",
    "sg:city":"Philadelphia",
    "sg:classifiers":[
        {
            "category":"Social Services",
            "subcategory":"Child Care",
            "type":"Services"
        }
    ],
    "sg:phone":"+1 215 472 5155",
    "sg:postcode":"19139",
    "sg:province":"PA",
    "wof:name":"Where Kids Can Be Kids",
    "wof:placetype":"venue"
},
  "geometry": {"coordinates":[-75.220524,39.955172],"type":"Point"}
}