{
  "type": "Feature",
  "properties": {
    "addr:full":"90 Upper Sayre Park Rd Bethlehem PA 18015",
    "addr:housenumber":"90",
    "addr:postcode":"18015",
    "addr:street":"Upper Sayre Park Rd",
    "iso:country":"US",
    "sg:address":"90 Upper Sayre Park Rd",
    "sg:city":"Bethlehem",
    "sg:classifiers":[
        {
            "category":"Organizations",
            "subcategory":"Membership Organization",
            "type":"Services"
        }
    ],
    "sg:phone":"+1 610 974 2413",
    "sg:postcode":"18015",
    "sg:province":"PA",
    "sg:tags":[
        "fraternal"
    ],
    "wof:name":"Phi Sigma Kappa 90",
    "wof:placetype":"venue"
},
  "geometry": {"coordinates":[-75.380124,40.602303],"type":"Point"}
}