{
  "type": "Feature",
  "properties": {
    "iso:country":"US",
    "sg:address":"20 E Hancock St",
    "sg:city":"Lansdale",
    "sg:classifiers":[
        {
            "category":"Bars & Pubs",
            "type":"Food & Drink"
        }
    ],
    "sg:phone":"+1   ",
    "sg:postcode":"19446",
    "sg:province":"PA",
    "sg:tags":[
        "drinking",
        "eating"
    ],
    "wof:name":"Patio Snack Bar Inc",
    "wof:placetype":"venue"
},
  "geometry": {"coordinates":[-75.28738800000001,40.23611],"type":"Point"}
}