{
  "type": "Feature",
  "properties": {
    "addr:full":"117 S 16th St Allentown PA 18102",
    "addr:housenumber":"117",
    "addr:postcode":"18102",
    "addr:street":"S 16Th St",
    "iso:country":"US",
    "sg:address":"117 S 16th St",
    "sg:city":"Allentown",
    "sg:classifiers":[
        {
            "category":"Professional",
            "subcategory":"Management & Consulting",
            "type":"Services"
        }
    ],
    "sg:phone":"+1   ",
    "sg:postcode":"18102",
    "sg:province":"PA",
    "sg:tags":[
        "business"
    ],
    "wof:name":"Romancheck Associates",
    "wof:placetype":"venue"
},
  "geometry": {"coordinates":[-75.488871,40.594687],"type":"Point"}
}