{
  "type": "Feature",
  "properties": {
    "iso:country":"US",
    "sg:address":"230 Bristol Pike",
    "sg:city":"Bristol",
    "sg:classifiers":[
        {
            "category":"Professional",
            "type":"Services"
        }
    ],
    "sg:phone":"+1 215 788 9290",
    "sg:postcode":"19007",
    "sg:province":"PA",
    "sg:tags":[
        "establishment"
    ],
    "wof:name":"Bucks County Kawasaki",
    "wof:placetype":"venue"
},
  "geometry": {"coordinates":[-74.87446,40.09827],"type":"Point"}
}