{
  "type": "Feature",
  "properties": {
    "iso:country":"US",
    "sg:address":"1225 Livey St",
    "sg:city":"Archbald",
    "sg:classifiers":[
        {
            "category":"Building & Trades",
            "subcategory":"Electrical",
            "type":"Services"
        }
    ],
    "sg:phone":"+1 570 347 9194",
    "sg:postcode":"18403",
    "sg:province":"PA",
    "sg:tags":[
        "contractor"
    ],
    "wof:name":"Kempa Brothers Contracting",
    "wof:placetype":"venue"
},
  "geometry": {"coordinates":[-75.54701300000001,41.485443],"type":"Point"}
}