{
  "type": "Feature",
  "properties": {
    "addr:full":"22 N Diamond St York PA 17404",
    "addr:housenumber":"22",
    "addr:postcode":"17404",
    "addr:street":"N Diamond St",
    "iso:country":"US",
    "sg:address":"22 N Diamond St",
    "sg:city":"York",
    "sg:classifiers":[
        {
            "category":"Professional",
            "type":"Services"
        }
    ],
    "sg:phone":"+1   ",
    "sg:postcode":"17404",
    "sg:province":"PA",
    "wof:name":"Gerald Cooper",
    "wof:placetype":"venue"
},
  "geometry": {"coordinates":[-76.768832,39.952894],"type":"Point"}
}