{
  "type": "Feature",
  "properties": {
    "iso:country":"US",
    "sg:address":"3865 N Gratz St",
    "sg:city":"Philadelphia",
    "sg:classifiers":[
        {
            "category":"Organizations",
            "subcategory":"Religious Organization",
            "type":"Services"
        }
    ],
    "sg:phone":"+1 215 229 6376",
    "sg:postcode":"19140",
    "sg:province":"PA",
    "sg:tags":[
        "clergy"
    ],
    "wof:name":"Ralph E Blanks",
    "wof:placetype":"venue"
},
  "geometry": {"coordinates":[-75.157793,40.012269],"type":"Point"}
}