{
  "type": "Feature",
  "properties": {
    "addr:full":"424 River Rd Dauphin PA 17018",
    "addr:housenumber":"424",
    "addr:postcode":"17018",
    "addr:street":"River Rd",
    "iso:country":"US",
    "sg:address":"424 River Rd",
    "sg:city":"Dauphin",
    "sg:classifiers":[
        {
            "category":"Building & Trades",
            "subcategory":"Construction",
            "type":"Services"
        }
    ],
    "sg:phone":"+1   ",
    "sg:postcode":"17018",
    "sg:province":"PA",
    "wof:name":"Spicher Enterprises Inc",
    "wof:placetype":"venue"
},
  "geometry": {"coordinates":[-76.948095,40.368268],"type":"Point"}
}