{
  "type": "Feature",
  "properties": {
    "iso:country":"US",
    "sg:address":"5009 Springfield Ave",
    "sg:city":"Philadelphia",
    "sg:classifiers":[
        {
            "category":"Home & Garden",
            "subcategory":"Household Appliances",
            "type":"Retail Goods"
        }
    ],
    "sg:phone":"+1 215 726 1410",
    "sg:postcode":"19143",
    "sg:province":"PA",
    "wof:name":"Robinson Appliance",
    "wof:placetype":"venue"
},
  "geometry": {"coordinates":[-75.219522,39.944118],"type":"Point"}
}