{
  "type": "Feature",
  "properties": {
    "iso:country":"US",
    "sg:address":"2 E Lancaster Ave",
    "sg:city":"Ardmore",
    "sg:classifiers":[
        {
            "category":"Banks & Credit Unions",
            "subcategory":"Bank",
            "type":"Services"
        }
    ],
    "sg:phone":"+1   ",
    "sg:postcode":"19003",
    "sg:province":"PA",
    "sg:tags":[
        "broker",
        "mortgage"
    ],
    "wof:name":"Hem",
    "wof:placetype":"venue"
},
  "geometry": {"coordinates":[-75.28998799999999,40.007362],"type":"Point"}
}