{
  "type": "Feature",
  "properties": {
    "iso:country":"US",
    "sg:address":"125 S Walnut St",
    "sg:city":"Slatington",
    "sg:classifiers":[
        {
            "category":"Real Estate",
            "subcategory":"Real Estate Services",
            "type":"Services"
        }
    ],
    "sg:phone":"+1   ",
    "sg:postcode":"18080",
    "sg:province":"PA",
    "sg:tags":[
        "abstract",
        "title"
    ],
    "wof:name":"Lehigh Settlement Services",
    "wof:placetype":"venue"
},
  "geometry": {"coordinates":[-75.605495,40.75058],"type":"Point"}
}