{
  "type": "Feature",
  "properties": {
    "addr:full":"2400 Taneytown Rd Gettysburg PA 17325",
    "addr:postcode":"2400;17325",
    "addr:street":"Taneytown Rd",
    "iso:country":"US",
    "sg:address":"2400 Taneytown Rd",
    "sg:city":"Gettysburg",
    "sg:classifiers":[
        {
            "category":"Building & Trades",
            "subcategory":"Construction",
            "type":"Services"
        }
    ],
    "sg:phone":"+1   ",
    "sg:postcode":"17325",
    "sg:province":"PA",
    "sg:tags":[
        "excavation",
        "contractor"
    ],
    "wof:name":"David A Woodward Excavating",
    "wof:placetype":"venue"
},
  "geometry": {"coordinates":[-77.22999,39.755496],"type":"Point"}
}