{
  "type": "Feature",
  "properties": {
    "iso:country":"US",
    "sg:address":"1690 S Market St",
    "sg:city":"Mechanicsburg",
    "sg:classifiers":[
        {
            "category":"Freight",
            "type":"Transportation"
        }
    ],
    "sg:phone":"+1 717 697 9109",
    "sg:postcode":"17055",
    "sg:province":"PA",
    "wof:name":"B & S Transportation Co",
    "wof:placetype":"venue"
},
  "geometry": {"coordinates":[-76.992198,40.18461],"type":"Point"}
}