{
  "type": "Feature",
  "properties": {
    "iso:country":"US",
    "sg:address":"22 E Orange St",
    "sg:city":"Lancaster",
    "sg:classifiers":[
        {
            "category":"Coffee & Tea",
            "type":"Food & Drink"
        },
        {
            "category":"Restaurant",
            "type":"Food & Drink"
        }
    ],
    "sg:phone":"+1 717 299 5788",
    "sg:postcode":"17602",
    "sg:province":"PA",
    "sg:tags":[
        "espresso"
    ],
    "wof:name":"It's All Good Cafe",
    "wof:placetype":"venue"
},
  "geometry": {"coordinates":[-76.304973,40.039641],"type":"Point"}
}