{
  "type": "Feature",
  "properties": {
    "addr:full":"325 W Lincoln Hwy Langhorne PA 19047",
    "addr:housenumber":"325",
    "addr:postcode":"19047",
    "addr:street":"W Lincoln Hwy Langhorne Pa",
    "iso:country":"US",
    "sg:address":"325 W Lincoln Hwy",
    "sg:city":"Langhorne",
    "sg:classifiers":[
        {
            "category":"Insurance",
            "subcategory":"Insurance Agent",
            "type":"Services"
        },
        {
            "category":"Insurance",
            "subcategory":"Hazard Insurance",
            "type":"Services"
        }
    ],
    "sg:phone":"+1 215 752 2080",
    "sg:postcode":"19047",
    "sg:province":"PA",
    "sg:tags":[
        "auto",
        "recreational",
        "motorcycle",
        "vehicle",
        "marine",
        "boat"
    ],
    "sg:website":"http://www.aprogressiveagent.com",
    "wof:name":"Neshaminy Insurance",
    "wof:placetype":"venue"
},
  "geometry": {"coordinates":[-74.919012,40.156986],"type":"Point"}
}