{
  "type": "Feature",
  "properties": {
    "iso:country":"US",
    "sg:address":"5320 William Flynn Hwy",
    "sg:city":"Gibsonia",
    "sg:classifiers":[
        {
            "category":"Retail",
            "subcategory":"Laundry & Dry Cleaning",
            "type":"Services"
        }
    ],
    "sg:phone":"+1 724 444 6500",
    "sg:postcode":"15044",
    "sg:province":"PA",
    "sg:tags":[
        "cleaners"
    ],
    "wof:name":"Imperial 1 Hour Cleaners",
    "wof:placetype":"venue"
},
  "geometry": {"coordinates":[-79.946506,40.615882],"type":"Point"}
}