{
  "type": "Feature",
  "properties": {
    "iso:country":"US",
    "sg:address":"3384 Seanor Rd",
    "sg:city":"Hollsopple",
    "sg:classifiers":[
        {
            "category":"Bars & Pubs",
            "type":"Food & Drink"
        }
    ],
    "sg:phone":"+1 814 479 4466",
    "sg:postcode":"15935",
    "sg:province":"PA",
    "sg:tags":[
        "tavern",
        "drinking"
    ],
    "wof:name":"Wooden Indian Tavern",
    "wof:placetype":"venue"
},
  "geometry": {"coordinates":[-78.92729199999999,40.210121],"type":"Point"}
}