{
  "type": "Feature",
  "properties": {
    "iso:country":"US",
    "sg:address":"1445 City Ave Ste 1-2",
    "sg:city":"Wynnewood",
    "sg:classifiers":[
        {
            "category":"Health Services",
            "subcategory":"Health Practitioner",
            "type":"Services"
        }
    ],
    "sg:phone":"+1 610 642 4029",
    "sg:postcode":"19096",
    "sg:province":"PA",
    "sg:tags":[
        "addiction-information",
        "therapist",
        "treatment",
        "gambling",
        "occupational"
    ],
    "wof:name":"Occupational Therapy Consultant Inc",
    "wof:placetype":"venue"
},
  "geometry": {"coordinates":[-75.271339,39.979271],"type":"Point"}
}