{
  "type": "Feature",
  "properties": {
    "iso:country":"US",
    "sg:address":"103 Mill Run Rd",
    "sg:city":"Normalville",
    "sg:classifiers":[
        {
            "category":"Restaurant",
            "type":"Food & Drink"
        }
    ],
    "sg:phone":"+1 724 455 3520",
    "sg:postcode":"15469",
    "sg:province":"PA",
    "wof:name":"Laurel Dairy Bar",
    "wof:placetype":"venue"
},
  "geometry": {"coordinates":[-79.44636199999999,39.996036],"type":"Point"}
}