{
  "type": "Feature",
  "properties": {
    "iso:country":"US",
    "sg:address":"836 Cedar Crest Ave",
    "sg:city":"Lebanon",
    "sg:classifiers":[
        {
            "category":"Manufacturing",
            "subcategory":"Tools & Machinery",
            "type":"Manufacturing & Wholesale Goods"
        }
    ],
    "sg:phone":"+1   ",
    "sg:postcode":"17046",
    "sg:province":"PA",
    "sg:tags":[
        "sales"
    ],
    "wof:name":"Gradall Company",
    "wof:placetype":"venue"
},
  "geometry": {"coordinates":[-76.395715,40.351742],"type":"Point"}
}