{
  "type": "Feature",
  "properties": {
    "addr:full":"2420 Bethlehem Pike Hatfield PA 19440",
    "addr:housenumber":"2420",
    "addr:postcode":"19440",
    "addr:street":"Bethlehem Pike",
    "iso:country":"US",
    "sg:address":"2420 Bethlehem Pike",
    "sg:city":"Hatfield",
    "sg:classifiers":[
        {
            "category":"Sports & Exercise",
            "subcategory":"Gym",
            "type":"Entertainment"
        }
    ],
    "sg:phone":"+1 215 822 6177",
    "sg:postcode":"19440",
    "sg:province":"PA",
    "sg:tags":[
        "club",
        "health"
    ],
    "sg:website":"www.hatfieldathleticclub.com",
    "wof:name":"Hatfield Athletic Club",
    "wof:placetype":"venue"
},
  "geometry": {"coordinates":[-75.282898,40.297798],"type":"Point"}
}