{
  "type": "Feature",
  "properties": {
    "addr:full":"525 Mt Joy Rd Mt Joy PA 17552",
    "addr:housenumber":"525",
    "addr:postcode":"17552",
    "addr:street":"Mt Joy Rd",
    "iso:country":"US",
    "sg:address":"525 Mt Joy Rd",
    "sg:city":"Mt Joy",
    "sg:classifiers":[
        {
            "category":"Shopping",
            "subcategory":"Pharmacy",
            "type":"Retail Goods"
        }
    ],
    "sg:phone":"+1 717 653 4450",
    "sg:postcode":"17552",
    "sg:province":"PA",
    "sg:website":"www.cvs.com",
    "wof:name":"CVS Pharmacy",
    "wof:placetype":"venue"
},
  "geometry": {"coordinates":[-76.49099699999999,40.119493],"type":"Point"}
}