{
  "type": "Feature",
  "properties": {
    "iso:country":"US",
    "sg:address":"33 Main St",
    "sg:city":"Felton",
    "sg:classifiers":[
        {
            "category":"Personal",
            "subcategory":"Beauty Salon",
            "type":"Services"
        }
    ],
    "sg:phone":"+1   ",
    "sg:postcode":"17322",
    "sg:province":"PA",
    "sg:tags":[
        "shop"
    ],
    "wof:name":"Main Street Beauty Shop",
    "wof:placetype":"venue"
},
  "geometry": {"coordinates":[-76.567054,39.855392],"type":"Point"}
}