{
  "type": "Feature",
  "properties": {
    "addr:full":"4411 Howley St Pittsburgh PA 15224",
    "addr:housenumber":"4411",
    "addr:postcode":"15224",
    "addr:street":"Howley St",
    "iso:country":"US",
    "sg:address":"4411 Howley St",
    "sg:city":"Pittsburgh",
    "sg:classifiers":[
        {
            "category":"Shopping",
            "subcategory":"Pharmacy",
            "type":"Retail Goods"
        }
    ],
    "sg:phone":"+1 412 621 9987",
    "sg:postcode":"15224",
    "sg:province":"PA",
    "sg:tags":[
        "drug",
        "store"
    ],
    "wof:name":"Eckerd",
    "wof:placetype":"venue"
},
  "geometry": {"coordinates":[-79.952378,40.464447],"type":"Point"}
}