{
  "type": "Feature",
  "properties": {
    "addr:full":"4727 Verona Rd Verona PA 15147",
    "addr:housenumber":"4727",
    "addr:postcode":"15147",
    "addr:street":"Verona Rd",
    "iso:country":"US",
    "sg:address":"4727 Verona Rd",
    "sg:city":"Verona",
    "sg:classifiers":[
        {
            "category":"Retail",
            "subcategory":"Auto Repair",
            "type":"Services"
        }
    ],
    "sg:phone":"+1 412 793 4030",
    "sg:postcode":"15147",
    "sg:province":"PA",
    "sg:tags":[
        "transmission"
    ],
    "wof:name":"Verona Transmission",
    "wof:placetype":"venue"
},
  "geometry": {"coordinates":[-79.84602099999999,40.478007],"type":"Point"}
}