{
  "type": "Feature",
  "properties": {
    "addr:full":"7 Commercial Ln Blakeslee PA 18651",
    "addr:housenumber":"7",
    "addr:postcode":"18651",
    "addr:street":"Commercial Ln",
    "iso:country":"US",
    "sg:address":"7 Commercial Ln",
    "sg:city":"Blakeslee",
    "sg:classifiers":[
        {
            "category":"Home & Garden",
            "subcategory":"Carpets & Floor Coverings",
            "type":"Retail Goods"
        }
    ],
    "sg:phone":"+1 570 643 3556",
    "sg:postcode":"18651",
    "sg:province":"PA",
    "sg:tags":[
        "dealer",
        "rug"
    ],
    "wof:name":"American Carpet East LTD",
    "wof:placetype":"venue"
},
  "geometry": {"coordinates":[-75.944226,41.241637],"type":"Point"}
}