{
  "type": "Feature",
  "properties": {
    "addr:full":"11 Storm St Stroudsburg PA 18360",
    "addr:housenumber":"11",
    "addr:postcode":"18360",
    "addr:street":"Storm St",
    "iso:country":"US",
    "sg:address":"11 Storm St",
    "sg:city":"Stroudsburg",
    "sg:classifiers":[
        {
            "category":"Real Estate",
            "subcategory":"Real Estate Agent",
            "type":"Services"
        }
    ],
    "sg:phone":"+1   ",
    "sg:postcode":"18360",
    "sg:province":"PA",
    "sg:tags":[
        "manager",
        "sharing",
        "condominium",
        "time"
    ],
    "wof:name":"Coconut Bay Resort Properties",
    "wof:placetype":"venue"
},
  "geometry": {"coordinates":[-75.187285,40.986099],"type":"Point"}
}