{
  "type": "Feature",
  "properties": {
    "iso:country":"US",
    "sg:address":"250 Briggs St",
    "sg:city":"Coal Center",
    "sg:classifiers":[
        {
            "category":"Building & Trades",
            "subcategory":"Construction",
            "type":"Services"
        }
    ],
    "sg:phone":"+1 724 326 4185",
    "sg:postcode":"15423",
    "sg:province":"PA",
    "sg:tags":[
        "excavation",
        "contractor"
    ],
    "wof:name":"Blackson Excavating",
    "wof:placetype":"venue"
},
  "geometry": {"coordinates":[-79.857891,40.093863],"type":"Point"}
}