{
  "type": "Feature",
  "properties": {
    "addr:full":"107 W Fisher Ave Philadelphia PA 19120",
    "addr:housenumber":"107",
    "addr:postcode":"19120",
    "addr:street":"W Fisher Ave",
    "iso:country":"US",
    "sg:address":"107 W Fisher Ave",
    "sg:city":"Philadelphia",
    "sg:classifiers":[
        {
            "category":"Wholesale",
            "subcategory":"Auto Parts",
            "type":"Manufacturing & Wholesale Goods"
        }
    ],
    "sg:phone":"+1   ",
    "sg:postcode":"19120",
    "sg:province":"PA",
    "wof:name":"Bobs Auto Radiator Service",
    "wof:placetype":"venue"
},
  "geometry": {"coordinates":[-75.123035,40.030855],"type":"Point"}
}