{
  "type": "Feature",
  "properties": {
    "iso:country":"US",
    "sg:address":"110 College Ave",
    "sg:city":"Monroeton",
    "sg:classifiers":[
        {
            "category":"Government",
            "subcategory":"Police Station",
            "type":"Public Place"
        }
    ],
    "sg:phone":"+1 570 265 3584",
    "sg:postcode":"18832",
    "sg:province":"PA",
    "sg:tags":[
        "department"
    ],
    "wof:name":"Monroeton Police Dept",
    "wof:placetype":"venue"
},
  "geometry": {"coordinates":[-76.472319,41.711245],"type":"Point"}
}