{
  "type": "Feature",
  "properties": {
    "iso:country":"US",
    "sg:address":"3333 E State St",
    "sg:city":"Hermitage",
    "sg:classifiers":[
        {
            "category":"Shopping",
            "subcategory":"Clothing, Apparel, & Fashions",
            "type":"Retail Goods"
        }
    ],
    "sg:phone":"+1   ",
    "sg:postcode":"16148",
    "sg:province":"PA",
    "wof:name":"Aeropostale 506",
    "wof:placetype":"venue"
},
  "geometry": {"coordinates":[-80.449225,41.233471],"type":"Point"}
}