{
  "type": "Feature",
  "properties": {
    "iso:country":"US",
    "sg:address":"1008 N Chester Rd",
    "sg:city":"West Chester",
    "sg:classifiers":[
        {
            "category":"Freight",
            "type":"Transportation"
        }
    ],
    "sg:phone":"+1 610 918 6100",
    "sg:postcode":"19380",
    "sg:province":"PA",
    "sg:tags":[
        "special"
    ],
    "wof:name":"All Seasons Storage",
    "wof:placetype":"venue"
},
  "geometry": {"coordinates":[-75.546215,40.004408],"type":"Point"}
}