{
  "type": "Feature",
  "properties": {
    "addr:full":"710 E Cumberland St Lebanon PA 17042",
    "addr:housenumber":"710",
    "addr:postcode":"17042",
    "addr:street":"E Cumberland St",
    "iso:country":"US",
    "sg:address":"710 E Cumberland St",
    "sg:city":"Lebanon",
    "sg:classifiers":[
        {
            "category":"Restaurant",
            "type":"Food & Drink"
        }
    ],
    "sg:menulink":"http://www.allmenus.com/pa/south-lebanon/170710-burger-king/menu/",
    "sg:phone":"+1 717 274 0621",
    "sg:postcode":"17042",
    "sg:province":"PA",
    "sg:tags":[
        "burger",
        "american"
    ],
    "wof:name":"Burger King",
    "wof:placetype":"venue"
},
  "geometry": {"coordinates":[-76.398646,40.342382],"type":"Point"}
}