{
  "type": "Feature",
  "properties": {
    "iso:country":"US",
    "sg:address":"220 W Plum St",
    "sg:city":"Edinboro",
    "sg:classifiers":[
        {
            "category":"Building & Trades",
            "subcategory":"Construction",
            "type":"Services"
        }
    ],
    "sg:phone":"+1   ",
    "sg:postcode":"16412",
    "sg:province":"PA",
    "sg:tags":[
        "house"
    ],
    "wof:name":"Double A Construction",
    "wof:placetype":"venue"
},
  "geometry": {"coordinates":[-80.132729,41.875914],"type":"Point"}
}