{
  "type": "Feature",
  "properties": {
    "addr:full":"10 S Main St Mexico PA 17099",
    "addr:housenumber":"10",
    "addr:postcode":"17099",
    "addr:street":"S Main St",
    "iso:country":"US",
    "sg:address":"10 S Main St",
    "sg:city":"Mexico",
    "sg:classifiers":[
        {
            "category":"Banks & Credit Unions",
            "subcategory":"Investment Brokerage",
            "type":"Services"
        }
    ],
    "sg:phone":"+1 717 436 5150",
    "sg:postcode":"17099",
    "sg:province":"PA",
    "sg:tags":[
        "commodity"
    ],
    "wof:name":"Leaches' Enterprise",
    "wof:placetype":"venue"
},
  "geometry": {"coordinates":[-77.578064,40.640645],"type":"Point"}
}