{
  "type": "Feature",
  "properties": {
    "iso:country":"US",
    "sg:address":"5 True Temper Dr",
    "sg:city":"Carlisle",
    "sg:classifiers":[
        {
            "category":"Professional",
            "type":"Services"
        }
    ],
    "sg:phone":"+1 717 258 3325",
    "sg:postcode":"17013",
    "sg:province":"PA",
    "sg:tags":[
        "establishment"
    ],
    "wof:name":"Exel",
    "wof:placetype":"venue"
},
  "geometry": {"coordinates":[-77.238097,40.173589],"type":"Point"}
}