{
  "type": "Feature",
  "properties": {
    "addr:full":"916 Spring Rd Lincroft PA 17022",
    "addr:housenumber":"916",
    "addr:postcode":"17022",
    "addr:street":"Spring Rd",
    "iso:country":"US",
    "sg:address":"916 Spring Rd",
    "sg:city":"Lincroft",
    "sg:classifiers":[
        {
            "category":"Wholesale",
            "subcategory":"Durable Goods & Equipment",
            "type":"Manufacturing & Wholesale Goods"
        }
    ],
    "sg:phone":"+1 732 925 1414",
    "sg:postcode":"17022",
    "sg:province":"PA",
    "sg:tags":[
        "environmental",
        "ecological",
        "prod"
    ],
    "wof:name":"Castlebar Industries",
    "wof:placetype":"venue"
},
  "geometry": {"coordinates":[-76.57903,40.153201],"type":"Point"}
}