{
  "type": "Feature",
  "properties": {
    "addr:full":"2000 Corporate Dr Wexford PA 15090",
    "addr:housenumber":"2000",
    "addr:postcode":"15090",
    "addr:street":"Corporate Dr",
    "iso:country":"US",
    "sg:address":"2000 Corporate Dr",
    "sg:city":"Wexford",
    "sg:classifiers":[
        {
            "category":"Wholesale",
            "subcategory":"Electrical",
            "type":"Manufacturing & Wholesale Goods"
        }
    ],
    "sg:phone":"+1   ",
    "sg:postcode":"15090",
    "sg:province":"PA",
    "sg:tags":[
        "communications",
        "telephone"
    ],
    "wof:name":"N E C Bus Netwrk Solutions",
    "wof:placetype":"venue"
},
  "geometry": {"coordinates":[-80.08850700000001,40.612757],"type":"Point"}
}