{
  "type": "Feature",
  "properties": {
    "iso:country":"US",
    "sg:address":"5240 Library Rd",
    "sg:city":"Bethel Park",
    "sg:classifiers":[
        {
            "category":"Fast Food",
            "type":"Food & Drink"
        },
        {
            "category":"Food & Beverages",
            "subcategory":"Meat & Fish",
            "type":"Retail Goods"
        }
    ],
    "sg:phone":"+1 412 851 4213",
    "sg:postcode":"15102",
    "sg:province":"PA",
    "sg:tags":[
        "burger",
        "hot",
        "dog"
    ],
    "sg:website":"www.burgerking.com",
    "wof:name":"Burger King",
    "wof:placetype":"venue"
},
  "geometry": {"coordinates":[-80.02288299999999,40.331561],"type":"Point"}
}