{
  "type": "Feature",
  "properties": {
    "addr:full":"124 W Pike St Houston PA 15342",
    "addr:housenumber":"124",
    "addr:postcode":"15342",
    "addr:street":"W Pike St",
    "iso:country":"US",
    "sg:address":"124 W Pike St",
    "sg:city":"Houston",
    "sg:classifiers":[
        {
            "category":"Shopping",
            "subcategory":"Department Store",
            "type":"Retail Goods"
        }
    ],
    "sg:phone":"+1 724 746 3269",
    "sg:postcode":"15342",
    "sg:province":"PA",
    "sg:tags":[
        "shop"
    ],
    "wof:name":"Dollar General",
    "wof:placetype":"venue"
},
  "geometry": {"coordinates":[-80.210195,40.249195],"type":"Point"}
}