{
  "type": "Feature",
  "properties": {
    "addr:full":"804 Bethlehem Pike Colmar PA 18915",
    "addr:housenumber":"804",
    "addr:postcode":"18915",
    "addr:street":"Bethlehem Pike",
    "iso:country":"US",
    "sg:address":"804 Bethlehem Pike",
    "sg:city":"Colmar",
    "sg:classifiers":[
        {
            "category":"Shopping",
            "subcategory":"Clothing, Apparel, & Fashions",
            "type":"Retail Goods"
        }
    ],
    "sg:phone":"+1 215 361 1030",
    "sg:postcode":"18915",
    "sg:province":"PA",
    "sg:tags":[
        "garment"
    ],
    "wof:name":"Pro Image",
    "wof:placetype":"venue"
},
  "geometry": {"coordinates":[-75.26194,40.280901],"type":"Point"}
}