{
  "type": "Feature",
  "properties": {
    "addr:full":"73 E Forrest Ave Shrewsbury PA 17361",
    "addr:housenumber":"73",
    "addr:postcode":"17361",
    "addr:street":"E Forrest Ave",
    "iso:country":"US",
    "sg:address":"73 E Forrest Ave",
    "sg:city":"Shrewsbury",
    "sg:classifiers":[
        {
            "category":"Real Estate",
            "subcategory":"Real Estate Agent",
            "type":"Services"
        }
    ],
    "sg:phone":"+1 717 235 3814",
    "sg:postcode":"17361",
    "sg:province":"PA",
    "wof:name":"Coldwell Banker",
    "wof:placetype":"venue"
},
  "geometry": {"coordinates":[-76.674398,39.770209],"type":"Point"}
}