{
  "type": "Feature",
  "properties": {
    "iso:country":"US",
    "sg:address":"1303 S 6th St",
    "sg:city":"Philadelphia",
    "sg:classifiers":[
        {
            "category":"Real Estate",
            "subcategory":"Real Estate Services",
            "type":"Services"
        },
        {
            "category":"Real Estate",
            "subcategory":"Real Estate Agent",
            "type":"Services"
        }
    ],
    "sg:phone":"+1 215 334 6200",
    "sg:postcode":"19147",
    "sg:province":"PA",
    "sg:tags":[
        "buyer",
        "consultant",
        "management",
        "broker"
    ],
    "wof:name":"Jpc Realty",
    "wof:placetype":"venue"
},
  "geometry": {"coordinates":[-75.15450199999999,39.932343],"type":"Point"}
}