{
  "type": "Feature",
  "properties": {
    "iso:country":"US",
    "sg:address":"151 N East St",
    "sg:city":"Williamstown",
    "sg:classifiers":[
        {
            "category":"Health Services",
            "subcategory":"Doctor",
            "type":"Services"
        }
    ],
    "sg:phone":"+1 717 647 7101",
    "sg:postcode":"17098",
    "sg:province":"PA",
    "sg:tags":[
        "physician",
        "surgeon",
        "medical"
    ],
    "wof:name":"Arthur J Hodge MD",
    "wof:placetype":"venue"
},
  "geometry": {"coordinates":[-76.61778,40.581548],"type":"Point"}
}