{
  "type": "Feature",
  "properties": {
    "addr:full":"2532 Norcross Rd Erie PA 16510",
    "addr:housenumber":"2532",
    "addr:postcode":"16510",
    "addr:street":"Norcross Rd",
    "iso:country":"US",
    "sg:address":"2532 Norcross Rd",
    "sg:city":"Erie",
    "sg:classifiers":[
        {
            "category":"Retail",
            "subcategory":"Funeral Services",
            "type":"Services"
        }
    ],
    "sg:phone":"+1 814 825 0458",
    "sg:postcode":"16510",
    "sg:province":"PA",
    "sg:tags":[
        "director"
    ],
    "wof:name":"Burton Funeral Homes",
    "wof:placetype":"venue"
},
  "geometry": {"coordinates":[-80.001817,42.110961],"type":"Point"}
}