{
  "type": "Feature",
  "properties": {
    "iso:country":"US",
    "sg:address":"5321 Oxford Ave",
    "sg:city":"Philadelphia",
    "sg:classifiers":[
        {
            "category":"Restaurant",
            "type":"Food & Drink"
        }
    ],
    "sg:phone":"+1 215 743 1180",
    "sg:postcode":"19124",
    "sg:province":"PA",
    "sg:tags":[
        "pizzeria",
        "eating",
        "pizza"
    ],
    "wof:name":"Original Champion Pizza Inc",
    "wof:placetype":"venue"
},
  "geometry": {"coordinates":[-75.085403,40.029202],"type":"Point"}
}