{
  "type": "Feature",
  "properties": {
    "iso:country":"US",
    "sg:address":"501 Washington Ln Ste 203",
    "sg:city":"Jenkintown",
    "sg:classifiers":[
        {
            "category":"Professional",
            "subcategory":"Advertising",
            "type":"Services"
        }
    ],
    "sg:phone":"+1 215 884 0310",
    "sg:postcode":"19046",
    "sg:province":"PA",
    "sg:tags":[
        "agency",
        "specialty"
    ],
    "sg:website":"http://www.kaufmanadvertising.com",
    "wof:name":"Medmark",
    "wof:placetype":"venue"
},
  "geometry": {"coordinates":[-75.126259,40.091831],"type":"Point"}
}