{
  "type": "Feature",
  "properties": {
    "iso:country":"US",
    "sg:address":"4290 N Susquehanna Trl",
    "sg:city":"York",
    "sg:classifiers":[
        {
            "category":"Autos & Motor Vehicles",
            "subcategory":"Automobile Sales",
            "type":"Retail Goods"
        }
    ],
    "sg:phone":"+1 717 268 0008",
    "sg:postcode":"17406",
    "sg:province":"PA",
    "sg:tags":[
        "dealers-used",
        "car",
        "used",
        "cars-wholesale",
        "new"
    ],
    "wof:name":"Loveland, Raymond K Auto Sales",
    "wof:placetype":"venue"
},
  "geometry": {"coordinates":[-76.747154,40.024061],"type":"Point"}
}