{
  "type": "Feature",
  "properties": {
    "iso:country":"US",
    "sg:address":"555 Rentzel Rd",
    "sg:city":"Gettysburg",
    "sg:classifiers":[
        {
            "category":"Travel",
            "subcategory":"Travel Agent",
            "type":"Entertainment"
        }
    ],
    "sg:phone":"+1   ",
    "sg:postcode":"17325",
    "sg:province":"PA",
    "sg:tags":[
        "agency"
    ],
    "wof:name":"Ocean Holiday",
    "wof:placetype":"venue"
},
  "geometry": {"coordinates":[-77.193054,39.908597],"type":"Point"}
}