{
  "type": "Feature",
  "properties": {
    "addr:full":"9130 Academy Rd Philadelphia PA 19114",
    "addr:housenumber":"9130",
    "addr:postcode":"19114",
    "addr:street":"Academy Rd",
    "iso:country":"US",
    "sg:address":"9130 Academy Rd",
    "sg:city":"Philadelphia",
    "sg:classifiers":[
        {
            "category":"Education",
            "subcategory":"School",
            "type":"Public Place"
        }
    ],
    "sg:phone":"+1   ",
    "sg:postcode":"19114",
    "sg:province":"PA",
    "sg:tags":[
        "elementary",
        "k"
    ],
    "wof:name":"Holme Thomas Elementary School",
    "wof:placetype":"venue"
},
  "geometry": {"coordinates":[-75.008669,40.057527],"type":"Point"}
}