{
  "type": "Feature",
  "properties": {
    "iso:country":"US",
    "sg:address":"412 Mt Joy Rd",
    "sg:city":"Mt Joy",
    "sg:classifiers":[
        {
            "category":"Professional",
            "subcategory":"Lawyer & Legal Services",
            "type":"Services"
        }
    ],
    "sg:phone":"+1 717 653 5037",
    "sg:postcode":"17552",
    "sg:province":"PA",
    "sg:tags":[
        "attorney"
    ],
    "wof:name":"Gibbel Kraybill & Hess",
    "wof:placetype":"venue"
},
  "geometry": {"coordinates":[-76.498801,40.11632],"type":"Point"}
}