{
  "type": "Feature",
  "properties": {
    "iso:country":"US",
    "sg:address":"2893 W 26th St",
    "sg:city":"Erie",
    "sg:classifiers":[
        {
            "category":"Wholesale",
            "subcategory":"Machinery & Supplies",
            "type":"Manufacturing & Wholesale Goods"
        },
        {
            "category":"Shopping",
            "subcategory":"Beauty & Cosmetics",
            "type":"Retail Goods"
        }
    ],
    "sg:phone":"+1 814 838 6919",
    "sg:postcode":"16506",
    "sg:province":"PA",
    "sg:tags":[
        "equipment",
        "salon"
    ],
    "wof:name":"Sally Beauty Supply 2061",
    "wof:placetype":"venue"
},
  "geometry": {"coordinates":[-80.13669299999999,42.088472],"type":"Point"}
}