{
  "type": "Feature",
  "properties": {
    "addr:full":"1200 Dorothy Ave Phoenixville PA 19460",
    "addr:housenumber":"1200",
    "addr:postcode":"19460",
    "addr:street":"Dorothy Ave",
    "iso:country":"US",
    "sg:address":"1200 Dorothy Ave",
    "sg:city":"Phoenixville",
    "sg:classifiers":[
        {
            "category":"Building & Trades",
            "subcategory":"Landscaping Services",
            "type":"Services"
        }
    ],
    "sg:phone":"+1 610 935 8271",
    "sg:postcode":"19460",
    "sg:province":"PA",
    "wof:name":"Cornerstone Lawn & Landscape",
    "wof:placetype":"venue"
},
  "geometry": {"coordinates":[-75.51500299999999,40.117882],"type":"Point"}
}