{
  "type": "Feature",
  "properties": {
    "addr:full":"1221 New Hampshire Ln Downingtown PA 19335",
    "addr:housenumber":"1221",
    "addr:postcode":"19335",
    "addr:street":"New Hampshire Ln",
    "iso:country":"US",
    "sg:address":"1221 New Hampshire Ln",
    "sg:city":"Downingtown",
    "sg:classifiers":[
        {
            "category":"Professional",
            "subcategory":"Business Services",
            "type":"Services"
        }
    ],
    "sg:phone":"+1 610 269 9360",
    "sg:postcode":"19335",
    "sg:province":"PA",
    "sg:tags":[
        "interior",
        "consultant",
        "designer",
        "design",
        "decorator"
    ],
    "wof:name":"Stanton Design Associates Inc",
    "wof:placetype":"venue"
},
  "geometry": {"coordinates":[-75.694536,39.97297],"type":"Point"}
}