{
  "type": "Feature",
  "properties": {
    "iso:country":"US",
    "sg:address":"104 Willow Ave",
    "sg:city":"Olyphant",
    "sg:classifiers":[
        {
            "category":"Shopping",
            "subcategory":"Tobacco",
            "type":"Retail Goods"
        }
    ],
    "sg:phone":"+1 570 489 3199",
    "sg:postcode":"18447",
    "sg:province":"PA",
    "sg:tags":[
        "cigarette",
        "product",
        "cigar",
        "dealer"
    ],
    "wof:name":"Smoke Rings 2",
    "wof:placetype":"venue"
},
  "geometry": {"coordinates":[-75.604496,41.470432],"type":"Point"}
}