{
  "type": "Feature",
  "properties": {
    "iso:country":"US",
    "sg:address":"851 Graffius Rd",
    "sg:city":"York",
    "sg:classifiers":[
        {
            "category":"Government",
            "subcategory":"Office",
            "type":"Public Place"
        }
    ],
    "sg:phone":"+1   ",
    "sg:postcode":"17404",
    "sg:province":"PA",
    "sg:tags":[
        "management"
    ],
    "wof:name":"Dover Township",
    "wof:placetype":"venue"
},
  "geometry": {"coordinates":[-76.80289399999999,40.014163],"type":"Point"}
}