{
  "type": "Feature",
  "properties": {
    "iso:country":"US",
    "sg:address":"200 Jones St",
    "sg:city":"Verona",
    "sg:classifiers":[
        {
            "category":"Manufacturing",
            "subcategory":"Rubber & Plastics",
            "type":"Manufacturing & Wholesale Goods"
        }
    ],
    "sg:phone":"+1 412 826 1825",
    "sg:postcode":"15147",
    "sg:province":"PA",
    "sg:tags":[
        "pipe"
    ],
    "sg:website":"www.normandyproducts.com",
    "wof:name":"Normandy Products",
    "wof:placetype":"venue"
},
  "geometry": {"coordinates":[-79.843588,40.501857],"type":"Point"}
}