{
  "type": "Feature",
  "properties": {
    "addr:full":"6738 Rte 66 Fairmount City PA 16224",
    "addr:housenumber":"6738",
    "addr:postcode":"16224",
    "addr:street":"Rte 66",
    "iso:country":"US",
    "sg:address":"6738 Rte 66",
    "sg:city":"Fairmount City",
    "sg:classifiers":[
        {
            "category":"Building & Trades",
            "subcategory":"Construction",
            "type":"Services"
        }
    ],
    "sg:phone":"+1 814 275 0053",
    "sg:postcode":"16224",
    "sg:province":"PA",
    "sg:tags":[
        "boring",
        "drilling",
        "contractor"
    ],
    "wof:name":"Howard Drilling",
    "wof:placetype":"venue"
},
  "geometry": {"coordinates":[-79.320814,41.096993],"type":"Point"}
}