{
  "type": "Feature",
  "properties": {
    "addr:full":"5505 Upper Ridge Rd Pennsburg PA 18073",
    "addr:housenumber":"5505",
    "addr:postcode":"18073",
    "addr:street":"Upper Ridge Rd",
    "iso:country":"US",
    "sg:address":"5505 Upper Ridge Rd",
    "sg:city":"Pennsburg",
    "sg:classifiers":[
        {
            "category":"Travel",
            "subcategory":"Campground",
            "type":"Entertainment"
        }
    ],
    "sg:phone":"+1 215 234 4588",
    "sg:postcode":"18073",
    "sg:province":"PA",
    "sg:tags":[
        "camp"
    ],
    "wof:name":"Delmont Scout Reservation",
    "wof:placetype":"venue"
},
  "geometry": {"coordinates":[-75.44583,40.353728],"type":"Point"}
}