{
  "type": "Feature",
  "properties": {
    "iso:country":"US",
    "sg:address":"49 W Union St",
    "sg:city":"Kingston",
    "sg:classifiers":[
        {
            "category":"Personal",
            "subcategory":"Beauty Salon",
            "type":"Services"
        }
    ],
    "sg:phone":"+1 570 718 1380",
    "sg:postcode":"18704",
    "sg:province":"PA",
    "wof:name":"Abracadeborah",
    "wof:placetype":"venue"
},
  "geometry": {"coordinates":[-75.887276,41.272393],"type":"Point"}
}