{
  "type": "Feature",
  "properties": {
    "iso:country":"US",
    "sg:address":"1361 Bridgetown Pike",
    "sg:city":"Feastervl Trvs",
    "sg:classifiers":[
        {
            "category":"Health Services",
            "subcategory":"Health Practitioner",
            "type":"Services"
        }
    ],
    "sg:phone":"+1 215 354 1426",
    "sg:postcode":"19053",
    "sg:province":"PA",
    "sg:tags":[
        "nurse",
        "registry"
    ],
    "wof:name":"Independent Nursing Svc Inc",
    "wof:placetype":"venue"
},
  "geometry": {"coordinates":[-74.998132,40.155287],"type":"Point"}
}