{
  "type": "Feature",
  "properties": {
    "iso:country":"US",
    "sg:address":"271 Wyoming Ave",
    "sg:city":"Kingston",
    "sg:classifiers":[
        {
            "category":"Real Estate",
            "subcategory":"Real Estate Services",
            "type":"Services"
        }
    ],
    "sg:phone":"+1   ",
    "sg:postcode":"18704",
    "sg:province":"PA",
    "sg:tags":[
        "abstract",
        "title"
    ],
    "wof:name":"First American Title Company",
    "wof:placetype":"venue"
},
  "geometry": {"coordinates":[-75.89720199999999,41.261787],"type":"Point"}
}