{
  "type": "Feature",
  "properties": {
    "iso:country":"US",
    "sg:address":"223 W Girard Ave",
    "sg:city":"Philadelphia",
    "sg:classifiers":[
        {
            "category":"Building & Trades",
            "subcategory":"Cleaning & Sanitation",
            "type":"Services"
        }
    ],
    "sg:phone":"+1 215 740 5522",
    "sg:postcode":"19123",
    "sg:province":"PA",
    "sg:tags":[
        "home"
    ],
    "sg:website":"www.dosfunnyfrogs.com/",
    "wof:name":"Dos Funny Frogs",
    "wof:placetype":"venue"
},
  "geometry": {"coordinates":[-75.140354,39.969801],"type":"Point"}
}