{
  "type": "Feature",
  "properties": {
    "iso:country":"US",
    "sg:address":"51 N 39th St",
    "sg:city":"Philadelphia",
    "sg:classifiers":[
        {
            "category":"Health Services",
            "subcategory":"Doctor",
            "type":"Services"
        }
    ],
    "sg:phone":"+1 215 662 8100",
    "sg:postcode":"19104",
    "sg:province":"PA",
    "sg:tags":[
        "physician",
        "surgeon",
        "medical"
    ],
    "wof:name":"Scheie Eye Institute",
    "wof:placetype":"venue"
},
  "geometry": {"coordinates":[-75.199501,39.957298],"type":"Point"}
}