{
  "type": "Feature",
  "properties": {
    "iso:country":"US",
    "sg:address":"150 Wilson Ave",
    "sg:city":"Greensburg",
    "sg:classifiers":[
        {
            "category":"Wholesale",
            "subcategory":"Machinery & Supplies",
            "type":"Manufacturing & Wholesale Goods"
        },
        {
            "category":"Wholesale",
            "subcategory":"Durable Goods & Equipment",
            "type":"Manufacturing & Wholesale Goods"
        }
    ],
    "sg:phone":"+1 724 834 3665",
    "sg:postcode":"15601",
    "sg:province":"PA",
    "sg:tags":[
        "fire",
        "extinguisher",
        "safety",
        "fighting"
    ],
    "wof:name":"A B C Fire Equipment Corp",
    "wof:placetype":"venue"
},
  "geometry": {"coordinates":[-79.539276,40.305241],"type":"Point"}
}