{
  "type": "Feature",
  "properties": {
    "iso:country":"US",
    "sg:address":"386 Maiden Ln",
    "sg:city":"King Of Prussia",
    "sg:classifiers":[
        {
            "category":"Wholesale",
            "subcategory":"Drugs",
            "type":"Manufacturing & Wholesale Goods"
        }
    ],
    "sg:phone":"+1   ",
    "sg:postcode":"19406",
    "sg:province":"PA",
    "sg:tags":[
        "chemical",
        "specialty",
        "synthesis"
    ],
    "wof:name":"Isosciences LLC",
    "wof:placetype":"venue"
},
  "geometry": {"coordinates":[-75.37853800000001,40.099421],"type":"Point"}
}