{
  "type": "Feature",
  "properties": {
    "iso:country":"US",
    "sg:address":"2401 Vare Ave",
    "sg:city":"Philadelphia",
    "sg:classifiers":[
        {
            "category":"Food & Beverages",
            "subcategory":"Liquor & Beverages",
            "type":"Retail Goods"
        }
    ],
    "sg:phone":"+1 215 952 1022",
    "sg:postcode":"19145",
    "sg:province":"PA",
    "sg:tags":[
        "store"
    ],
    "wof:name":"State Liquor Stores",
    "wof:placetype":"venue"
},
  "geometry": {"coordinates":[-75.19308100000001,39.925116],"type":"Point"}
}