{
  "type": "Feature",
  "properties": {
    "iso:country":"US",
    "sg:address":"3528 Sassafras St",
    "sg:city":"Erie",
    "sg:classifiers":[
        {
            "category":"Real Estate",
            "subcategory":"Architect",
            "type":"Services"
        }
    ],
    "sg:phone":"+1 814 452 2414",
    "sg:postcode":"16508",
    "sg:province":"PA",
    "wof:name":"Kidder Architects",
    "wof:placetype":"venue"
},
  "geometry": {"coordinates":[-80.071527,42.102731],"type":"Point"}
}