{
  "type": "Feature",
  "properties": {
    "iso:country":"US",
    "sg:address":"1590 Oakland Ave",
    "sg:city":"Indiana",
    "sg:classifiers":[
        {
            "category":"Cinema",
            "subcategory":"Movie Rental",
            "type":"Entertainment"
        }
    ],
    "sg:phone":"+1 724 465 0550",
    "sg:postcode":"15701",
    "sg:province":"PA",
    "sg:tags":[
        "leasing",
        "video",
        "disc",
        "tape"
    ],
    "wof:name":"Blockbuster Video",
    "wof:placetype":"venue"
},
  "geometry": {"coordinates":[-79.17173200000001,40.614979],"type":"Point"}
}