{
  "type": "Feature",
  "properties": {
    "iso:country":"US",
    "sg:address":"216 Noble St",
    "sg:city":"Sellersville",
    "sg:classifiers":[
        {
            "category":"Manufacturing",
            "subcategory":"Printing",
            "type":"Manufacturing & Wholesale Goods"
        }
    ],
    "sg:phone":"+1   ",
    "sg:postcode":"18960",
    "sg:province":"PA",
    "sg:tags":[
        "commercial",
        "lithographic"
    ],
    "wof:name":"Sellersville Printing Co",
    "wof:placetype":"venue"
},
  "geometry": {"coordinates":[-75.317988,40.360668],"type":"Point"}
}