{
  "type": "Feature",
  "properties": {
    "iso:country":"US",
    "sg:address":"1165 Maiden St",
    "sg:city":"Fredericktown",
    "sg:classifiers":[
        {
            "category":"Building & Trades",
            "subcategory":"Construction",
            "type":"Services"
        }
    ],
    "sg:phone":"+1 724 632 2424",
    "sg:postcode":"15333",
    "sg:province":"PA",
    "sg:tags":[
        "excavating",
        "contractor"
    ],
    "wof:name":"Theakston Construction Co",
    "wof:placetype":"venue"
},
  "geometry": {"coordinates":[-80.02479099999999,40.060774],"type":"Point"}
}