{
  "type": "Feature",
  "properties": {
    "iso:country":"US",
    "sg:address":"653 Skippack Pike",
    "sg:city":"Blue Bell",
    "sg:classifiers":[
        {
            "category":"Government",
            "subcategory":"Court House",
            "type":"Public Place"
        }
    ],
    "sg:phone":"+1   ",
    "sg:postcode":"19422",
    "sg:province":"PA",
    "wof:name":"Magisterial District 38-1-21",
    "wof:placetype":"venue"
},
  "geometry": {"coordinates":[-75.268225,40.153644],"type":"Point"}
}