{
  "type": "Feature",
  "properties": {
    "addr:full":"5705 Meade St Mckeesport PA 15135",
    "addr:housenumber":"5705",
    "addr:postcode":"15135",
    "addr:street":"Meade St",
    "iso:country":"US",
    "sg:address":"5705 Meade St",
    "sg:city":"Mckeesport",
    "sg:classifiers":[
        {
            "category":"Personal",
            "subcategory":"Beauty Salon",
            "type":"Services"
        }
    ],
    "sg:phone":"+1 412 751 9910",
    "sg:postcode":"15135",
    "sg:province":"PA",
    "sg:tags":[
        "shop"
    ],
    "wof:name":"Bridge To Beauty Salon",
    "wof:placetype":"venue"
},
  "geometry": {"coordinates":[-79.82348399999999,40.310548],"type":"Point"}
}