{
  "type": "Feature",
  "properties": {
    "iso:country":"US",
    "sg:address":"417 Haverford Rd",
    "sg:city":"Wynnewood",
    "sg:classifiers":[
        {
            "category":"Structure",
            "subcategory":"Warehouse",
            "type":"Public Place"
        }
    ],
    "sg:phone":"+1 484 614 9750",
    "sg:postcode":"19096",
    "sg:province":"PA",
    "sg:tags":[
        "warehouses-merchandise",
        "warehouses-public-commercial"
    ],
    "wof:name":"Mastercrafters",
    "wof:placetype":"venue"
},
  "geometry": {"coordinates":[-75.280227,39.99039],"type":"Point"}
}