{
  "type": "Feature",
  "properties": {
    "iso:country":"US",
    "sg:address":"900 Commerce Dr",
    "sg:city":"Coraopolis",
    "sg:classifiers":[
        {
            "category":"Professional",
            "subcategory":"Management & Consulting",
            "type":"Services"
        }
    ],
    "sg:phone":"+1 412 637 1000",
    "sg:postcode":"15108",
    "sg:province":"PA",
    "sg:tags":[
        "personnel",
        "consultant"
    ],
    "wof:name":"Cyna Med",
    "wof:placetype":"venue"
},
  "geometry": {"coordinates":[-80.211675,40.503463],"type":"Point"}
}