{
  "type": "Feature",
  "properties": {
    "iso:country":"US",
    "sg:address":"101 Park Pl E",
    "sg:city":"Shippensburg",
    "sg:classifiers":[
        {
            "category":"Education",
            "subcategory":"School",
            "type":"Public Place"
        }
    ],
    "sg:phone":"+1 717 530 2750",
    "sg:postcode":"17257",
    "sg:province":"PA",
    "sg:website":"www.ship.k12.pa.us",
    "wof:name":"Shippensburg Middle School",
    "wof:placetype":"venue"
},
  "geometry": {"coordinates":[-77.53752799999999,40.044677],"type":"Point"}
}