{
  "type": "Feature",
  "properties": {
    "iso:country":"US",
    "sg:address":"1305 E 10th St",
    "sg:city":"Erie",
    "sg:classifiers":[
        {
            "category":"Manufacturing",
            "subcategory":"Tools & Machinery",
            "type":"Manufacturing & Wholesale Goods"
        }
    ],
    "sg:phone":"+1 814 454 1701",
    "sg:postcode":"16503",
    "sg:province":"PA",
    "sg:tags":[
        "shop",
        "die"
    ],
    "wof:name":"D & F Tool Inc",
    "wof:placetype":"venue"
},
  "geometry": {"coordinates":[-80.05270299999999,42.136449],"type":"Point"}
}