{
  "type": "Feature",
  "properties": {
    "addr:full":"1 Signal Hill Dr Wall PA 15148",
    "addr:housenumber":"1",
    "addr:postcode":"15148",
    "addr:street":"Signal Hill Dr",
    "iso:country":"US",
    "sg:address":"1 Signal Hill Dr",
    "sg:city":"Wall",
    "sg:classifiers":[
        {
            "category":"Organizations",
            "subcategory":"Religious Organization",
            "type":"Services"
        }
    ],
    "sg:phone":"+1 412 824 3900",
    "sg:postcode":"15148",
    "sg:province":"PA",
    "sg:website":"www.ctvn.org",
    "wof:name":"CORNERSTONE Television Inc",
    "wof:placetype":"venue"
},
  "geometry": {"coordinates":[-79.780642,40.392023],"type":"Point"}
}