{
  "type": "Feature",
  "properties": {
    "iso:country":"US",
    "sg:address":"995 Deveaux St",
    "sg:city":"Elmora",
    "sg:classifiers":[
        {
            "category":"Building & Trades",
            "subcategory":"Construction",
            "type":"Services"
        }
    ],
    "sg:phone":"+1 814 344 8030",
    "sg:postcode":"15737",
    "sg:province":"PA",
    "sg:tags":[
        "mason",
        "masonry",
        "industrial",
        "contractors-commercial",
        "contractor"
    ],
    "sg:website":"http://www.bassettmasonry.com",
    "wof:name":"Bassett Masonry, Inc",
    "wof:placetype":"venue"
},
  "geometry": {"coordinates":[-78.756274,40.611649],"type":"Point"}
}