{
  "type": "Feature",
  "properties": {
    "addr:full":"86 Edgegrove Rd Hanover PA 17331",
    "addr:housenumber":"86",
    "addr:postcode":"17331",
    "addr:street":"Edgegrove Rd",
    "iso:country":"US",
    "sg:address":"86 Edgegrove Rd",
    "sg:city":"Hanover",
    "sg:classifiers":[
        {
            "category":"Freight",
            "type":"Transportation"
        }
    ],
    "sg:phone":"+1 717 359 4483",
    "sg:postcode":"17331",
    "sg:province":"PA",
    "sg:tags":[
        "storage"
    ],
    "wof:name":"West Manheim Storage",
    "wof:placetype":"venue"
},
  "geometry": {"coordinates":[-77.053039,39.825621],"type":"Point"}
}