{
  "type": "Feature",
  "properties": {
    "iso:country":"US",
    "sg:address":"2725 W Main St",
    "sg:city":"Norristown",
    "sg:classifiers":[
        {
            "category":"Personal",
            "subcategory":"Tanning Parlor",
            "type":"Services"
        }
    ],
    "sg:phone":"+1 610 630 0266",
    "sg:postcode":"19403",
    "sg:province":"PA",
    "wof:name":"Gym and Tan Line Studio the",
    "wof:placetype":"venue"
},
  "geometry": {"coordinates":[-75.393501,40.144901],"type":"Point"}
}