{
  "type": "Feature",
  "properties": {
    "addr:full":"125 Monica Dr Pittsburgh PA 15239",
    "addr:housenumber":"125",
    "addr:postcode":"15239",
    "addr:street":"Monica Dr",
    "iso:country":"US",
    "sg:address":"125 Monica Dr",
    "sg:city":"Pittsburgh",
    "sg:classifiers":[
        {
            "category":"Professional",
            "type":"Services"
        }
    ],
    "sg:phone":"+1   ",
    "sg:postcode":"15239",
    "sg:province":"PA",
    "wof:name":"New Image Detailers",
    "wof:placetype":"venue"
},
  "geometry": {"coordinates":[-79.76528,40.468622],"type":"Point"}
}