{
  "type": "Feature",
  "properties": {
    "iso:country":"US",
    "sg:address":"1 E Marion St",
    "sg:city":"Lancaster",
    "sg:classifiers":[
        {
            "category":"Government",
            "subcategory":"Office",
            "type":"Public Place"
        }
    ],
    "sg:phone":"+1 717 291 4802",
    "sg:postcode":"17602",
    "sg:province":"PA",
    "sg:tags":[
        "city",
        "taxation"
    ],
    "wof:name":"Lancaster City Treasury",
    "wof:placetype":"venue"
},
  "geometry": {"coordinates":[-76.30409299999999,40.040504],"type":"Point"}
}