{
  "type": "Feature",
  "properties": {
    "addr:full":"154 Exton Square Mall Exton PA 19341",
    "addr:housenumber":"154",
    "addr:postcode":"19341",
    "addr:street":"Exton Square Mall",
    "iso:country":"US",
    "sg:address":"154 Exton Square Mall",
    "sg:city":"Exton",
    "sg:classifiers":[
        {
            "category":"Shopping",
            "subcategory":"Jewelry",
            "type":"Retail Goods"
        }
    ],
    "sg:phone":"+1 484 875 2960",
    "sg:postcode":"19341",
    "sg:province":"PA",
    "sg:tags":[
        "jeweler"
    ],
    "wof:name":"Littman Jewelers",
    "wof:placetype":"venue"
},
  "geometry": {"coordinates":[-75.627376,40.030341],"type":"Point"}
}