{
  "type": "Feature",
  "properties": {
    "iso:country":"US",
    "sg:address":"2376 Quarry Rd",
    "sg:city":"Lebanon",
    "sg:classifiers":[
        {
            "category":"Arts & Performance",
            "subcategory":"Theater",
            "type":"Entertainment"
        }
    ],
    "sg:phone":"+1 717 865 0773",
    "sg:postcode":"17046",
    "sg:province":"PA",
    "sg:tags":[
        "entertainer",
        "business"
    ],
    "sg:website":"www.cddiscjockeys.com",
    "wof:name":"C D Disc Jockeys",
    "wof:placetype":"venue"
},
  "geometry": {"coordinates":[-76.47393599999999,40.406791],"type":"Point"}
}