{
  "type": "Feature",
  "properties": {
    "iso:country":"US",
    "sg:address":"1092 Dunnings Creek Rd",
    "sg:city":"New Paris",
    "sg:classifiers":[
        {
            "category":"Building & Trades",
            "subcategory":"Construction",
            "type":"Services"
        }
    ],
    "sg:phone":"+1   ",
    "sg:postcode":"15554",
    "sg:province":"PA",
    "sg:tags":[
        "house"
    ],
    "wof:name":"Miller Gary L Building & Rmdlg",
    "wof:placetype":"venue"
},
  "geometry": {"coordinates":[-78.59242399999999,40.164276],"type":"Point"}
}