{
  "type": "Feature",
  "properties": {
    "addr:full":"359 Mowry Run Rd Frenchville PA 16836",
    "addr:housenumber":"359",
    "addr:postcode":"16836",
    "addr:street":"Mowry Run Rd",
    "iso:country":"US",
    "sg:address":"359 Mowry Run Rd",
    "sg:city":"Frenchville",
    "sg:classifiers":[
        {
            "category":"Farming",
            "subcategory":"Livestock Farm",
            "type":"Manufacturing & Wholesale Goods"
        }
    ],
    "sg:phone":"+1   ",
    "sg:postcode":"16836",
    "sg:province":"PA",
    "sg:tags":[
        "feedlot",
        "field",
        "crop",
        "beef",
        "cattle"
    ],
    "wof:name":"Wilbur Mc Faye",
    "wof:placetype":"venue"
},
  "geometry": {"coordinates":[-78.166124,41.070931],"type":"Point"}
}