{
  "type": "Feature",
  "properties": {
    "iso:country":"US",
    "sg:address":"109 Mayfield Dr",
    "sg:city":"Butler",
    "sg:classifiers":[
        {
            "category":"Home & Garden",
            "subcategory":"Carpets & Floor Coverings",
            "type":"Retail Goods"
        }
    ],
    "sg:phone":"+1   ",
    "sg:postcode":"16001",
    "sg:province":"PA",
    "wof:name":"Americas Carpet",
    "wof:placetype":"venue"
},
  "geometry": {"coordinates":[-79.902041,40.890029],"type":"Point"}
}