{
  "type": "Feature",
  "properties": {
    "iso:country":"US",
    "sg:address":"3375 Richmond St",
    "sg:city":"Philadelphia",
    "sg:classifiers":[
        {
            "category":"Autos & Motor Vehicles",
            "subcategory":"Automobile Sales",
            "type":"Retail Goods"
        }
    ],
    "sg:phone":"+1 215 426 6323",
    "sg:postcode":"19134",
    "sg:province":"PA",
    "sg:tags":[
        "new",
        "car"
    ],
    "wof:name":"Jeca Corp",
    "wof:placetype":"venue"
},
  "geometry": {"coordinates":[-75.09729400000001,39.985148],"type":"Point"}
}