{
  "type": "Feature",
  "properties": {
    "iso:country":"US",
    "sg:address":"300 Brandywine Ave",
    "sg:city":"Downingtown",
    "sg:classifiers":[
        {
            "category":"Manufacturing",
            "subcategory":"Paper Products",
            "type":"Manufacturing & Wholesale Goods"
        }
    ],
    "sg:phone":"+1 610 269 3300",
    "sg:postcode":"19335",
    "sg:province":"PA",
    "sg:tags":[
        "paperboard",
        "mills"
    ],
    "wof:name":"Sonoco Products Co",
    "wof:placetype":"venue"
},
  "geometry": {"coordinates":[-75.70218199999999,40.000975],"type":"Point"}
}