{
  "type": "Feature",
  "properties": {
    "iso:country":"US",
    "sg:address":"895 E Maple Dr",
    "sg:city":"Southampton",
    "sg:classifiers":[
        {
            "category":"Wholesale",
            "subcategory":"Hardware",
            "type":"Manufacturing & Wholesale Goods"
        }
    ],
    "sg:phone":"+1 215 355 6655",
    "sg:postcode":"18966",
    "sg:province":"PA",
    "sg:tags":[
        "hardware-wholesale",
        "manufacturer"
    ],
    "wof:name":"Eugene A Lieberman",
    "wof:placetype":"venue"
},
  "geometry": {"coordinates":[-75.028852,40.171539],"type":"Point"}
}