{
  "type": "Feature",
  "properties": {
    "iso:country":"US",
    "sg:address":"296 Griffen St",
    "sg:city":"Phoenixville",
    "sg:classifiers":[
        {
            "category":"Building & Trades",
            "subcategory":"Construction",
            "type":"Services"
        }
    ],
    "sg:phone":"+1   ",
    "sg:postcode":"19460",
    "sg:province":"PA",
    "sg:tags":[
        "carpentry",
        "contractor"
    ],
    "wof:name":"Dw Construction",
    "wof:placetype":"venue"
},
  "geometry": {"coordinates":[-75.518681,40.123352],"type":"Point"}
}