{
  "type": "Feature",
  "properties": {
    "addr:full":"28 S 3rd St Harrisburg PA 17101",
    "addr:housenumber":"28",
    "addr:postcode":"17101",
    "addr:street":"S 3Rd St",
    "iso:country":"US",
    "sg:address":"28 S 3rd St",
    "sg:city":"Harrisburg",
    "sg:classifiers":[
        {
            "category":"Recreation",
            "type":"Entertainment"
        }
    ],
    "sg:phone":"+1 717 233 5116",
    "sg:postcode":"17101",
    "sg:province":"PA",
    "sg:tags":[
        "parlor",
        "billiard"
    ],
    "wof:name":"Casino II Billiards",
    "wof:placetype":"venue"
},
  "geometry": {"coordinates":[-76.879323,40.260011],"type":"Point"}
}