{
  "type": "Feature",
  "properties": {
    "addr:full":"2400 N Hancock St Philadelphia PA 19133",
    "addr:housenumber":"2400",
    "addr:postcode":"19133",
    "addr:street":"N Hancock St",
    "iso:country":"US",
    "sg:address":"2400 N Hancock St",
    "sg:city":"Philadelphia",
    "sg:classifiers":[
        {
            "category":"Food & Beverages",
            "subcategory":"Groceries & Convenience Stores",
            "type":"Retail Goods"
        }
    ],
    "sg:phone":"+1 215 423 2029",
    "sg:postcode":"19133",
    "sg:province":"PA",
    "wof:name":"N N Minimarket",
    "wof:placetype":"venue"
},
  "geometry": {"coordinates":[-75.134945,39.986719],"type":"Point"}
}