{
  "type": "Feature",
  "properties": {
    "iso:country":"US",
    "sg:address":"1950 E 3rd St",
    "sg:city":"Williamsport",
    "sg:classifiers":[
        {
            "category":"Retail",
            "subcategory":"Auto Repair",
            "type":"Services"
        }
    ],
    "sg:phone":"+1 570 326 3796",
    "sg:postcode":"17701",
    "sg:province":"PA",
    "sg:tags":[
        "repairing",
        "automobile",
        "automotive",
        "tire",
        "general"
    ],
    "wof:name":"Pecht Tire Co Inc",
    "wof:placetype":"venue"
},
  "geometry": {"coordinates":[-76.962538,41.248581],"type":"Point"}
}