{
  "type": "Feature",
  "properties": {
    "addr:full":"63 Keith St Hanover Twp PA 18706",
    "addr:housenumber":"63",
    "addr:postcode":"18706",
    "addr:street":"Keith St",
    "iso:country":"US",
    "sg:address":"63 Keith St",
    "sg:city":"Hanover Twp",
    "sg:classifiers":[
        {
            "category":"Manufacturing",
            "subcategory":"Petroleum Products",
            "type":"Manufacturing & Wholesale Goods"
        }
    ],
    "sg:phone":"+1 570 824 5708",
    "sg:postcode":"18706",
    "sg:province":"PA",
    "sg:tags":[
        "asphalt"
    ],
    "wof:name":"Slusser Brothers Excavating Co",
    "wof:placetype":"venue"
},
  "geometry": {"coordinates":[-75.919681,41.231351],"type":"Point"}
}