{
  "type": "Feature",
  "properties": {
    "addr:full":"2400 E Venango St Philadelphia PA 19134",
    "addr:housenumber":"2400",
    "addr:postcode":"19134",
    "addr:street":"E Venango St",
    "iso:country":"US",
    "sg:address":"2400 E Venango St",
    "sg:city":"Philadelphia",
    "sg:classifiers":[
        {
            "category":"Autos & Motor Vehicles",
            "subcategory":"Automobile Sales",
            "type":"Retail Goods"
        },
        {
            "category":"Retail",
            "subcategory":"Auto Rental",
            "type":"Services"
        },
        {
            "category":"Building & Trades",
            "subcategory":"Equipment Rental",
            "type":"Services"
        }
    ],
    "sg:phone":"+1 215 305 8493",
    "sg:postcode":"19134",
    "sg:province":"PA",
    "sg:tags":[
        "truck",
        "used",
        "moving"
    ],
    "sg:website":"http://budgettruck.com/IYP_tl",
    "wof:name":"Venango Truck Rental DBA/Budget Truck Rental",
    "wof:placetype":"venue"
},
  "geometry": {"coordinates":[-75.096611,39.992962],"type":"Point"}
}