{
  "type": "Feature",
  "properties": {
    "addr:full":"60 W Broad St Bethlehem PA 18018",
    "addr:housenumber":"60",
    "addr:postcode":"18018",
    "addr:street":"W Broad St",
    "iso:country":"US",
    "sg:address":"60 W Broad St",
    "sg:city":"Bethlehem",
    "sg:classifiers":[
        {
            "category":"Manufacturing",
            "subcategory":"Metals",
            "type":"Manufacturing & Wholesale Goods"
        }
    ],
    "sg:phone":"+1   ",
    "sg:postcode":"18018",
    "sg:province":"PA",
    "sg:tags":[
        "product",
        "fabricated",
        "mfg"
    ],
    "wof:name":"ASC",
    "wof:placetype":"venue"
},
  "geometry": {"coordinates":[-75.381276,40.62242],"type":"Point"}
}