{
  "type": "Feature",
  "properties": {
    "addr:full":"5125 Jonestown Rd Harrisburg PA 17112",
    "addr:housenumber":"5125",
    "addr:postcode":"17112",
    "addr:street":"Jonestown Rd",
    "iso:country":"US",
    "sg:address":"5125 Jonestown Rd",
    "sg:city":"Harrisburg",
    "sg:classifiers":[
        {
            "category":"Utilities",
            "subcategory":"Mobile Phone",
            "type":"Services"
        },
        {
            "category":"Shopping",
            "subcategory":"Computers & Home Electronics",
            "type":"Retail Goods"
        }
    ],
    "sg:phone":"+1 717 260 5243",
    "sg:postcode":"17112",
    "sg:province":"PA",
    "sg:tags":[
        "consumer",
        "theater",
        "system",
        "cellular",
        "telephone"
    ],
    "sg:website":"http://www.hhgregg.com",
    "wof:name":"H H Gregg Wireless",
    "wof:placetype":"venue"
},
  "geometry": {"coordinates":[-76.80014799999999,40.31258],"type":"Point"}
}