{
  "type": "Feature",
  "properties": {
    "addr:full":"870 E Chelten Ave Philadelphia PA 19138",
    "addr:housenumber":"870",
    "addr:postcode":"19138",
    "addr:street":"E Chelten Ave",
    "iso:country":"US",
    "sg:address":"870 E Chelten Ave",
    "sg:city":"Philadelphia",
    "sg:classifiers":[
        {
            "category":"Shopping",
            "subcategory":"Used Merchandise",
            "type":"Retail Goods"
        }
    ],
    "sg:phone":"+1   ",
    "sg:postcode":"19138",
    "sg:province":"PA",
    "wof:name":"Annique",
    "wof:placetype":"venue"
},
  "geometry": {"coordinates":[-75.16348000000001,40.046564],"type":"Point"}
}