{
  "type": "Feature",
  "properties": {
    "iso:country":"US",
    "sg:address":"119 Blackwood Ln",
    "sg:city":"Douglassville",
    "sg:classifiers":[
        {
            "category":"Shopping",
            "subcategory":"Computers & Home Electronics",
            "type":"Retail Goods"
        }
    ],
    "sg:phone":"+1 610 385 0350",
    "sg:postcode":"19518",
    "sg:province":"PA",
    "sg:tags":[
        "software"
    ],
    "wof:name":"MSC Software Corp",
    "wof:placetype":"venue"
},
  "geometry": {"coordinates":[-75.73828399999999,40.238986],"type":"Point"}
}