{
  "type": "Feature",
  "properties": {
    "iso:country":"US",
    "sg:address":"138 Hilands Place",
    "sg:city":"Pittsburgh",
    "sg:classifiers":[
        {
            "category":"Professional",
            "subcategory":"Advertising",
            "type":"Services"
        }
    ],
    "sg:phone":"+1 412 366 4274",
    "sg:postcode":"15237",
    "sg:province":"PA",
    "sg:tags":[
        "broker",
        "brokers",
        "business-for-sale",
        "business-opportunities",
        "business-valuation",
        "businesses-for-sale",
        "buy-a-business",
        "buying-a-business",
        "convenience-stores-for-sale",
        "franchise",
        "franchise-for-sale",
        "franchises",
        "franchisor",
        "home-business",
        "new-business-online"
    ],
    "sg:website":"http://www.sellbiztoday.com",
    "wof:name":"SellBizToday",
    "wof:placetype":"venue"
},
  "geometry": {"coordinates":[-80.003519,40.518896],"type":"Point"}
}