{
  "type": "Feature",
  "properties": {
    "addr:full":"708 Latona St Philadelphia PA 19147",
    "addr:housenumber":"708",
    "addr:postcode":"19147",
    "addr:street":"Latona St",
    "iso:country":"US",
    "sg:address":"708 Latona St",
    "sg:city":"Philadelphia",
    "sg:classifiers":[
        {
            "category":"Professional",
            "subcategory":"Accounting & Tax Preparation",
            "type":"Services"
        }
    ],
    "sg:phone":"+1 215 952 0827",
    "sg:postcode":"19147",
    "sg:province":"PA",
    "sg:tags":[
        "return",
        "filing"
    ],
    "wof:name":"1040 Now",
    "wof:placetype":"venue"
},
  "geometry": {"coordinates":[-75.15736099999999,39.93329],"type":"Point"}
}