{
  "type": "Feature",
  "properties": {
    "addr:full":"3337 Hamilton Blvd Allentown PA 18103",
    "addr:housenumber":"3337",
    "addr:postcode":"18103",
    "addr:street":"Hamilton Blvd",
    "iso:country":"US",
    "sg:address":"3337 Hamilton Blvd",
    "sg:city":"Allentown",
    "sg:classifiers":[
        {
            "category":"Restaurant",
            "type":"Food & Drink"
        }
    ],
    "sg:phone":"+1 610 435 2500",
    "sg:postcode":"18103",
    "sg:province":"PA",
    "sg:website":"www.subway.com/",
    "wof:name":"Subway",
    "wof:placetype":"venue"
},
  "geometry": {"coordinates":[-75.524852,40.578468],"type":"Point"}
}