{
  "type": "Feature",
  "properties": {
    "iso:country":"US",
    "sg:address":"10 Industry Dr",
    "sg:city":"Lancaster",
    "sg:classifiers":[
        {
            "category":"Wholesale",
            "subcategory":"Electrical",
            "type":"Manufacturing & Wholesale Goods"
        }
    ],
    "sg:phone":"+1 717 393 3143",
    "sg:postcode":"17603",
    "sg:province":"PA",
    "sg:tags":[
        "control"
    ],
    "wof:name":"Herley Industries Inc",
    "wof:placetype":"venue"
},
  "geometry": {"coordinates":[-76.386534,40.043093],"type":"Point"}
}