{
  "type": "Feature",
  "properties": {
    "addr:full":"126 Water St Bruin PA 16022",
    "addr:housenumber":"126",
    "addr:postcode":"16022",
    "addr:street":"Water St",
    "iso:country":"US",
    "sg:address":"126 Water St",
    "sg:city":"Bruin",
    "sg:classifiers":[
        {
            "category":"Retail",
            "subcategory":"Repair Shop",
            "type":"Services"
        }
    ],
    "sg:phone":"+1 724 753 2472",
    "sg:postcode":"16022",
    "sg:province":"PA",
    "sg:tags":[
        "taxidermist"
    ],
    "wof:name":"Larry's Wildlife Artistry",
    "wof:placetype":"venue"
},
  "geometry": {"coordinates":[-79.72765,41.055214],"type":"Point"}
}