{
  "type": "Feature",
  "properties": {
    "iso:country":"US",
    "sg:address":"2000 Delmar Dr ",
    "sg:city":"Folcroft",
    "sg:classifiers":[
        {
            "category":"Restaurant",
            "type":"Food & Drink"
        }
    ],
    "sg:menulink":"http://www.allmenus.com/pa/folcroft/288985-folcroft-pizza/menu/",
    "sg:phone":"+1 610 532 5100",
    "sg:postcode":"19032",
    "sg:province":"PA",
    "sg:tags":[
        "american",
        "pizza"
    ],
    "wof:name":"Folcroft Pizza",
    "wof:placetype":"venue"
},
  "geometry": {"coordinates":[-75.285098,39.890204],"type":"Point"}
}