{
  "type": "Feature",
  "properties": {
    "iso:country":"US",
    "sg:address":"19 S Olive St",
    "sg:city":"Media",
    "sg:classifiers":[
        {
            "category":"Personal",
            "subcategory":"Tattoo Parlor",
            "type":"Services"
        }
    ],
    "sg:phone":"+1 610 892 8711",
    "sg:postcode":"19063",
    "sg:province":"PA",
    "sg:tags":[
        "tattooing"
    ],
    "wof:name":"Bad Karma Tattoo",
    "wof:placetype":"venue"
},
  "geometry": {"coordinates":[-75.391006,39.918176],"type":"Point"}
}