{
  "type": "Feature",
  "properties": {
    "addr:full":"9 Tara Dr Stroudsburg PA 18301",
    "addr:housenumber":"9",
    "addr:postcode":"18301",
    "addr:street":"Tara Dr",
    "iso:country":"US",
    "sg:address":"9 Tara Dr",
    "sg:city":"Stroudsburg",
    "sg:classifiers":[
        {
            "category":"Utilities",
            "subcategory":"Refuse",
            "type":"Services"
        }
    ],
    "sg:phone":"+1 570 421 2646",
    "sg:postcode":"18301",
    "sg:province":"PA",
    "sg:tags":[
        "garbage",
        "collection"
    ],
    "wof:name":"Lord's Carting",
    "wof:placetype":"venue"
},
  "geometry": {"coordinates":[-75.273037,41.037277],"type":"Point"}
}