{
  "type": "Feature",
  "properties": {
    "addr:full":"27 E Washington St New Castle PA 16101",
    "addr:housenumber":"27",
    "addr:postcode":"16101",
    "addr:street":"E Washington St",
    "iso:country":"US",
    "sg:address":"27 E Washington St",
    "sg:city":"New Castle",
    "sg:classifiers":[
        {
            "category":"Banks & Credit Unions",
            "subcategory":"Bank",
            "type":"Services"
        }
    ],
    "sg:phone":"+1   ",
    "sg:postcode":"16101",
    "sg:province":"PA",
    "sg:tags":[
        "state",
        "commercial"
    ],
    "wof:name":"Peoples Bank of Western PA",
    "wof:placetype":"venue"
},
  "geometry": {"coordinates":[-80.345766,41.000029],"type":"Point"}
}