{
  "type": "Feature",
  "properties": {
    "iso:country":"US",
    "sg:address":"4 Woods Way",
    "sg:city":"Reading",
    "sg:classifiers":[
        {
            "category":"Professional",
            "subcategory":"Business Services",
            "type":"Services"
        }
    ],
    "sg:phone":"+1 610 781 7784",
    "sg:postcode":"19610",
    "sg:province":"PA",
    "sg:tags":[
        "holding"
    ],
    "wof:name":"Blue Marsh Recovery",
    "wof:placetype":"venue"
},
  "geometry": {"coordinates":[-75.99337800000001,40.358742],"type":"Point"}
}