{
  "type": "Feature",
  "properties": {
    "iso:country":"US",
    "sg:address":"205 Gibson Rd",
    "sg:city":"Bentleyville",
    "sg:classifiers":[
        {
            "category":"Social Services",
            "subcategory":"Child Care",
            "type":"Services"
        }
    ],
    "sg:phone":"+1 724 239 4969",
    "sg:postcode":"15314",
    "sg:province":"PA",
    "sg:tags":[
        "kindergarten",
        "academic",
        "school"
    ],
    "wof:name":"Community Action Southwest",
    "wof:placetype":"venue"
},
  "geometry": {"coordinates":[-79.99617600000001,40.132189],"type":"Point"}
}