{
  "type": "Feature",
  "properties": {
    "iso:country":"US",
    "sg:address":"219 High St",
    "sg:city":"Burlington",
    "sg:classifiers":[
        {
            "category":"Restaurant",
            "type":"Food & Drink"
        }
    ],
    "sg:phone":"+1 609 386 6150",
    "sg:postcode":"18847",
    "sg:province":"PA",
    "wof:name":"Cafe Gallery",
    "wof:placetype":"venue"
},
  "geometry": {"coordinates":[-75.60372,41.943243],"type":"Point"}
}