{
  "type": "Feature",
  "properties": {
    "iso:country":"US",
    "sg:address":"2000 Corporate Dr",
    "sg:city":"Wexford",
    "sg:classifiers":[
        {
            "category":"Wholesale",
            "subcategory":"Metals & Minerals",
            "type":"Manufacturing & Wholesale Goods"
        }
    ],
    "sg:phone":"+1   ",
    "sg:postcode":"15090",
    "sg:province":"PA",
    "sg:tags":[
        "other",
        "nickel",
        "primary",
        "nonferrous"
    ],
    "wof:name":"International Nickel",
    "wof:placetype":"venue"
},
  "geometry": {"coordinates":[-80.08850700000001,40.612757],"type":"Point"}
}