{
  "type": "Feature",
  "properties": {
    "addr:full":"327 W Cedar St Kennett Square PA 19348",
    "addr:housenumber":"327",
    "addr:postcode":"19348",
    "addr:street":"W Cedar St",
    "iso:country":"US",
    "sg:address":"327 W Cedar St",
    "sg:city":"Kennett Square",
    "sg:classifiers":[
        {
            "category":"Retail",
            "subcategory":"Car Wash",
            "type":"Services"
        }
    ],
    "sg:phone":"+1 610 444 2177",
    "sg:postcode":"19348",
    "sg:province":"PA",
    "sg:tags":[
        "polishing",
        "washing"
    ],
    "wof:name":"Regal Car Washes Inc",
    "wof:placetype":"venue"
},
  "geometry": {"coordinates":[-75.713988,39.841939],"type":"Point"}
}