{
  "type": "Feature",
  "properties": {
    "iso:country":"US",
    "sg:address":"3651 Route 208",
    "sg:city":"Knox",
    "sg:classifiers":[
        {
            "category":"Retail",
            "subcategory":"Repair Shop",
            "type":"Services"
        },
        {
            "category":"Home & Garden",
            "subcategory":"Building Materials",
            "type":"Retail Goods"
        },
        {
            "category":"Building & Trades",
            "subcategory":"Construction",
            "type":"Services"
        },
        {
            "category":"Building & Trades",
            "subcategory":"Electrical",
            "type":"Services"
        }
    ],
    "sg:phone":"+1 814 797 0090",
    "sg:postcode":"16232",
    "sg:province":"PA",
    "sg:tags":[
        "industrial",
        "electrician",
        "electric",
        "improvement",
        "generators-electric-service",
        "contractors-commercial",
        "maintenance"
    ],
    "sg:website":"http://www.mrelectric.com",
    "wof:name":"Mr. Electric Of Northwestern Pennsylvania",
    "wof:placetype":"venue"
},
  "geometry": {"coordinates":[-79.620022,41.228159],"type":"Point"}
}