{
  "type": "Feature",
  "properties": {
    "addr:full":"1100 W Valley Rd Ste 5 Wayne PA 19087",
    "addr:housenumber":"1100",
    "addr:postcode":"19087",
    "addr:street":"W Valley Rd Ste 5",
    "iso:country":"US",
    "sg:address":"1100 W Valley Rd Ste 5",
    "sg:city":"Wayne",
    "sg:classifiers":[
        {
            "category":"Insurance",
            "subcategory":"Insurance Agent",
            "type":"Services"
        },
        {
            "category":"Personal",
            "type":"Services"
        },
        {
            "category":"Banks & Credit Unions",
            "subcategory":"Financial Services",
            "type":"Services"
        }
    ],
    "sg:phone":"+1 610 687 3928",
    "sg:postcode":"19087",
    "sg:province":"PA",
    "sg:tags":[
        "counseling",
        "debt",
        "adjuster"
    ],
    "wof:name":"Porreca Rita MA LMFT",
    "wof:placetype":"venue"
},
  "geometry": {"coordinates":[-75.42719700000001,40.073891],"type":"Point"}
}