{
  "type": "Feature",
  "properties": {
    "iso:country":"US",
    "sg:address":"230 E Millsboro Rd",
    "sg:city":"East Millsboro",
    "sg:classifiers":[
        {
            "category":"Manufacturing",
            "subcategory":"Tools & Machinery",
            "type":"Manufacturing & Wholesale Goods"
        }
    ],
    "sg:phone":"+1   ",
    "sg:postcode":"15433",
    "sg:province":"PA",
    "sg:tags":[
        "construction",
        "mfg"
    ],
    "wof:name":"Lent Brothers Excvating",
    "wof:placetype":"venue"
},
  "geometry": {"coordinates":[-79.99352,39.979774],"type":"Point"}
}