{
  "type": "Feature",
  "properties": {
    "iso:country":"US",
    "sg:address":"2681 Bristol Pike",
    "sg:city":"Bensalem",
    "sg:classifiers":[
        {
            "category":"Autos & Motor Vehicles",
            "subcategory":"Auto Supplies",
            "type":"Retail Goods"
        },
        {
            "category":"Retail",
            "subcategory":"Car Wash",
            "type":"Services"
        }
    ],
    "sg:phone":"+1 215 645 1056",
    "sg:postcode":"19020",
    "sg:province":"PA",
    "sg:tags":[
        "stereo",
        "automobile",
        "detailing",
        "system",
        "tinting",
        "window",
        "radio"
    ],
    "wof:name":"3 Brothers Detailing",
    "wof:placetype":"venue"
},
  "geometry": {"coordinates":[-74.941368,40.081823],"type":"Point"}
}