{
  "type": "Feature",
  "properties": {
    "iso:country":"US",
    "sg:address":"218 Center St",
    "sg:city":"Jim Thorpe",
    "sg:classifiers":[
        {
            "category":"Travel",
            "subcategory":"Hotels & Motels",
            "type":"Entertainment"
        }
    ],
    "sg:phone":"+1 570 325 8260",
    "sg:postcode":"18229",
    "sg:province":"PA",
    "wof:name":"Tiffany's Grand Victoria",
    "wof:placetype":"venue"
},
  "geometry": {"coordinates":[-75.73375,40.871491],"type":"Point"}
}