{
  "type": "Feature",
  "properties": {
    "iso:country":"US",
    "sg:address":"1929 Lincoln Hwy E Ste 20",
    "sg:city":"Lancaster",
    "sg:classifiers":[
        {
            "category":"Professional",
            "subcategory":"Business Services",
            "type":"Services"
        },
        {
            "category":"Real Estate",
            "subcategory":"Architect",
            "type":"Services"
        }
    ],
    "sg:phone":"+1 717 394 9690",
    "sg:postcode":"17602",
    "sg:province":"PA",
    "sg:tags":[
        "architects'",
        "specification",
        "drafting",
        "builders'",
        "construction",
        "architectural"
    ],
    "wof:name":"Constructive Concepts Ltd",
    "wof:placetype":"venue"
},
  "geometry": {"coordinates":[-76.247612,40.033505],"type":"Point"}
}