{
  "type": "Feature",
  "properties": {
    "iso:country":"US",
    "sg:address":"810 Chestnut St",
    "sg:city":"Philadelphia",
    "sg:classifiers":[
        {
            "category":"Banks & Credit Unions",
            "subcategory":"Financial Services",
            "type":"Services"
        }
    ],
    "sg:phone":"+1 215 238 5701",
    "sg:postcode":"19107",
    "sg:province":"PA",
    "sg:tags":[
        "cashing",
        "check"
    ],
    "sg:website":"http://www.acecashexpress.com",
    "wof:name":"ACE Cash Express",
    "wof:placetype":"venue"
},
  "geometry": {"coordinates":[-75.154061,39.94964],"type":"Point"}
}