{
  "type": "Feature",
  "properties": {
    "addr:full":"2820 W 7th St Chester PA 19013",
    "addr:housenumber":"2820",
    "addr:postcode":"19013",
    "addr:street":"W 7Th St",
    "iso:country":"US",
    "sg:address":"2820 W 7th St",
    "sg:city":"Chester",
    "sg:classifiers":[
        {
            "category":"Education",
            "subcategory":"School",
            "type":"Public Place"
        }
    ],
    "sg:phone":"+1 610 447 3777",
    "sg:postcode":"19013",
    "sg:province":"PA",
    "sg:tags":[
        "middle"
    ],
    "wof:name":"Parry Middle School",
    "wof:placetype":"venue"
},
  "geometry": {"coordinates":[-75.394609,39.834772],"type":"Point"}
}