{
  "type": "Feature",
  "properties": {
    "addr:full":"200 Blattenberger St Martinsburg PA 16662",
    "addr:housenumber":"200",
    "addr:postcode":"16662",
    "addr:street":"Blattenberger St",
    "iso:country":"US",
    "sg:address":"200 Blattenberger St",
    "sg:city":"Martinsburg",
    "sg:classifiers":[
        {
            "category":"Government",
            "subcategory":"Office",
            "type":"Public Place"
        },
        {
            "category":"Real Estate",
            "subcategory":"Real Estate Operator",
            "type":"Services"
        }
    ],
    "sg:phone":"+1 814 793 4273",
    "sg:postcode":"16662",
    "sg:province":"PA",
    "sg:tags":[
        "program",
        "housing",
        "apartment"
    ],
    "wof:name":"Showalter Apartments",
    "wof:placetype":"venue"
},
  "geometry": {"coordinates":[-78.33217999999999,40.313693],"type":"Point"}
}