{
  "type": "Feature",
  "properties": {
    "addr:full":"560 N 6th St Bangor PA 18013",
    "addr:housenumber":"560",
    "addr:postcode":"18013",
    "addr:street":"N 6Th St",
    "iso:country":"US",
    "sg:address":"560 N 6th St",
    "sg:city":"Bangor",
    "sg:classifiers":[
        {
            "category":"Organizations",
            "subcategory":"Religious Organization",
            "type":"Services"
        }
    ],
    "sg:phone":"+1 610 588 2183",
    "sg:postcode":"18013",
    "sg:province":"PA",
    "sg:tags":[
        "church"
    ],
    "wof:name":"Our Lady Of Mt Carmel",
    "wof:placetype":"venue"
},
  "geometry": {"coordinates":[-75.21414300000001,40.873661],"type":"Point"}
}