{
  "type": "Feature",
  "properties": {
    "iso:country":"US",
    "sg:address":"351 W Main St",
    "sg:city":"Dalton",
    "sg:classifiers":[
        {
            "category":"Building & Trades",
            "subcategory":"Construction",
            "type":"Services"
        }
    ],
    "sg:phone":"+1   ",
    "sg:postcode":"18414",
    "sg:province":"PA",
    "sg:tags":[
        "house"
    ],
    "wof:name":"Beechcroft Furniture",
    "wof:placetype":"venue"
},
  "geometry": {"coordinates":[-75.738995,41.534894],"type":"Point"}
}