{
  "type": "Feature",
  "properties": {
    "iso:country":"US",
    "sg:address":"5131 Barness Ct",
    "sg:city":"Doylestown",
    "sg:classifiers":[
        {
            "category":"Communications",
            "subcategory":"Film & Video Production",
            "type":"Services"
        },
        {
            "category":"Professional",
            "type":"Services"
        }
    ],
    "sg:phone":"+1 267 880 0396",
    "sg:postcode":"18902",
    "sg:province":"PA",
    "sg:tags":[
        "motion",
        "establishment"
    ],
    "wof:name":"Top Hat Productions LLC",
    "wof:placetype":"venue"
},
  "geometry": {"coordinates":[-77.457076,39.854168],"type":"Point"}
}