{
  "type": "Feature",
  "properties": {
    "iso:country":"US",
    "sg:address":"6051 Ogontz Ave",
    "sg:city":"Philadelphia",
    "sg:classifiers":[
        {
            "category":"Building & Trades",
            "subcategory":"Construction",
            "type":"Services"
        }
    ],
    "sg:phone":"+1 215 572 8106",
    "sg:postcode":"19141",
    "sg:province":"PA",
    "sg:tags":[
        "general",
        "contractor"
    ],
    "wof:name":"John Frazier Inc",
    "wof:placetype":"venue"
},
  "geometry": {"coordinates":[-75.150976,40.047392],"type":"Point"}
}