{
  "type": "Feature",
  "properties": {
    "addr:full":"715 Valley Rd Hamburg PA 19526",
    "addr:housenumber":"715",
    "addr:postcode":"19526",
    "addr:street":"Valley Rd",
    "iso:country":"US",
    "sg:address":"715 Valley Rd",
    "sg:city":"Hamburg",
    "sg:classifiers":[
        {
            "category":"Manufacturing",
            "subcategory":"Food",
            "type":"Manufacturing & Wholesale Goods"
        },
        {
            "category":"Farming",
            "subcategory":"Farm",
            "type":"Manufacturing & Wholesale Goods"
        }
    ],
    "sg:phone":"+1 610 562 7667",
    "sg:postcode":"19526",
    "sg:province":"PA",
    "sg:tags":[
        "corn",
        "product"
    ],
    "wof:name":"Paul Reidenhour",
    "wof:placetype":"venue"
},
  "geometry": {"coordinates":[-75.95738900000001,40.572662],"type":"Point"}
}