{
  "type": "Feature",
  "properties": {
    "iso:country":"US",
    "sg:address":"6694 Knollwood Dr",
    "sg:city":"Fairview",
    "sg:classifiers":[
        {
            "category":"Real Estate",
            "subcategory":"Real Estate Agent",
            "type":"Services"
        }
    ],
    "sg:phone":"+1   ",
    "sg:postcode":"16415",
    "sg:province":"PA",
    "wof:name":"Dugan Property Management LLC",
    "wof:placetype":"venue"
},
  "geometry": {"coordinates":[-80.233448,42.057612],"type":"Point"}
}