{
  "type": "Feature",
  "properties": {
    "addr:full":"247 N 10th St Allentown PA 18102",
    "addr:housenumber":"247",
    "addr:postcode":"18102",
    "addr:street":"N 10Th St",
    "iso:country":"US",
    "sg:address":"247 N 10th St",
    "sg:city":"Allentown",
    "sg:classifiers":[
        {
            "category":"Personal",
            "subcategory":"Barber",
            "type":"Services"
        }
    ],
    "sg:phone":"+1 610 432 6178",
    "sg:postcode":"18102",
    "sg:province":"PA",
    "wof:name":"Inner City Barber Shop",
    "wof:placetype":"venue"
},
  "geometry": {"coordinates":[-75.479782,40.604552],"type":"Point"}
}