{
  "type": "Feature",
  "properties": {
    "addr:full":"4818 Curly Hill Rd Doylestown PA 18901",
    "addr:housenumber":"4818",
    "addr:postcode":"18901",
    "addr:street":"Curly Hill Rd",
    "iso:country":"US",
    "sg:address":"4818 Curly Hill Rd",
    "sg:city":"Doylestown",
    "sg:classifiers":[
        {
            "category":"Farming",
            "subcategory":"Dairy Farm",
            "type":"Manufacturing & Wholesale Goods"
        }
    ],
    "sg:phone":"+1   ",
    "sg:postcode":"18901",
    "sg:province":"PA",
    "wof:name":"David Bishop",
    "wof:placetype":"venue"
},
  "geometry": {"coordinates":[-75.137294,40.375845],"type":"Point"}
}