{
  "type": "Feature",
  "properties": {
    "iso:country":"US",
    "sg:address":"4016 Butler St",
    "sg:city":"Pittsburgh",
    "sg:classifiers":[
        {
            "category":"Restaurant",
            "type":"Food & Drink"
        }
    ],
    "sg:phone":"+1 412 687 2555",
    "sg:postcode":"15201",
    "sg:province":"PA",
    "wof:name":"Anna Misiaszek Restaurant",
    "wof:placetype":"venue"
},
  "geometry": {"coordinates":[-79.9615,40.46923],"type":"Point"}
}