{
  "type": "Feature",
  "properties": {
    "iso:country":"US",
    "sg:address":"543 Sinking Springs Ln",
    "sg:city":"York",
    "sg:classifiers":[
        {
            "category":"Home & Garden",
            "subcategory":"Hardware",
            "type":"Retail Goods"
        }
    ],
    "sg:phone":"+1   ",
    "sg:postcode":"17404",
    "sg:province":"PA",
    "wof:name":"Roundtown Hardware",
    "wof:placetype":"venue"
},
  "geometry": {"coordinates":[-76.751531,40.015977],"type":"Point"}
}