{
  "type": "Feature",
  "properties": {
    "iso:country":"US",
    "sg:address":"945 Ohio River Blvd",
    "sg:city":"Avalon",
    "sg:classifiers":[
        {
            "category":"Home & Garden",
            "subcategory":"Building Materials",
            "type":"Retail Goods"
        }
    ],
    "sg:phone":"+1 412 731 3700",
    "sg:postcode":"15202",
    "sg:province":"PA",
    "sg:tags":[
        "glass",
        "window",
        "plate"
    ],
    "wof:name":"Glass Master's",
    "wof:placetype":"venue"
},
  "geometry": {"coordinates":[-80.065862,40.495371],"type":"Point"}
}