{
  "type": "Feature",
  "properties": {
    "iso:country":"US",
    "sg:address":"27 Chambersburg St",
    "sg:city":"Gettysburg",
    "sg:classifiers":[
        {
            "category":"Travel",
            "subcategory":"Hotels & Motels",
            "type":"Entertainment"
        }
    ],
    "sg:phone":"+1 717 337 1334",
    "sg:postcode":"17325",
    "sg:province":"PA",
    "sg:tags":[
        "operation",
        "eating",
        "breakfast",
        "bed",
        "accommodation"
    ],
    "sg:website":"www.jamesgettyshotel.com",
    "wof:name":"James Gettys Hotel The",
    "wof:placetype":"venue"
},
  "geometry": {"coordinates":[-77.2329,39.830993],"type":"Point"}
}