{
  "type": "Feature",
  "properties": {
    "iso:country":"US",
    "sg:address":"388 Everson Valley Rd",
    "sg:city":"Connellsville",
    "sg:classifiers":[
        {
            "category":"Autos & Motor Vehicles",
            "subcategory":"Automobile Sales",
            "type":"Retail Goods"
        },
        {
            "category":"Autos & Motor Vehicles",
            "subcategory":"Auto Supplies",
            "type":"Retail Goods"
        }
    ],
    "sg:phone":"+1 724 887 3881",
    "sg:postcode":"15425",
    "sg:province":"PA",
    "sg:tags":[
        "car",
        "used",
        "dealer"
    ],
    "wof:name":"Dan's Tire",
    "wof:placetype":"venue"
},
  "geometry": {"coordinates":[-79.57928099999999,40.08531],"type":"Point"}
}