{
  "type": "Feature",
  "properties": {
    "iso:country":"US",
    "sg:address":"79 Baker Ave",
    "sg:city":"Hermitage",
    "sg:classifiers":[
        {
            "category":"Retail",
            "subcategory":"Laundry & Dry Cleaning",
            "type":"Services"
        }
    ],
    "sg:phone":"+1 724 981 4779",
    "sg:postcode":"16148",
    "sg:province":"PA",
    "sg:tags":[
        "drycleaning",
        "plant"
    ],
    "wof:name":"Smock Cleaners",
    "wof:placetype":"venue"
},
  "geometry": {"coordinates":[-80.480186,41.232453],"type":"Point"}
}