{
  "type": "Feature",
  "properties": {
    "iso:country":"US",
    "sg:address":"737 Cherokee St",
    "sg:city":"Bethlehem",
    "sg:classifiers":[
        {
            "category":"Home & Garden",
            "subcategory":"Furniture",
            "type":"Retail Goods"
        }
    ],
    "sg:phone":"+1 610 691 6797",
    "sg:postcode":"18015",
    "sg:province":"PA",
    "sg:tags":[
        "store"
    ],
    "wof:name":"Furniture Medic by Lambert Restorations",
    "wof:placetype":"venue"
},
  "geometry": {"coordinates":[-75.389,40.60742],"type":"Point"}
}