{
  "type": "Feature",
  "properties": {
    "iso:country":"US",
    "sg:address":"2006 Derry St",
    "sg:city":"Harrisburg",
    "sg:classifiers":[
        {
            "category":"Personal",
            "subcategory":"Beauty Salon",
            "type":"Services"
        }
    ],
    "sg:phone":"+1 717 232 3061",
    "sg:postcode":"17104",
    "sg:province":"PA",
    "sg:tags":[
        "nail",
        "shop",
        "manicuring"
    ],
    "wof:name":"Express Nails Salon",
    "wof:placetype":"venue"
},
  "geometry": {"coordinates":[-76.8554,40.261002],"type":"Point"}
}