{
  "type": "Feature",
  "properties": {
    "addr:full":"4600 N Sherman St Exd Mt Wolf PA 17347",
    "addr:housenumber":"4600",
    "addr:postcode":"17347",
    "addr:street":"N Sherman St Exd",
    "iso:country":"US",
    "sg:address":"4600 N Sherman St Exd",
    "sg:city":"Mt Wolf",
    "sg:classifiers":[
        {
            "category":"Organizations",
            "subcategory":"Religious Organization",
            "type":"Services"
        }
    ],
    "sg:phone":"+1 717 266 6064",
    "sg:postcode":"17347",
    "sg:province":"PA",
    "sg:tags":[
        "church"
    ],
    "wof:name":"Christ Lutheran Church",
    "wof:placetype":"venue"
},
  "geometry": {"coordinates":[-76.690782,40.048781],"type":"Point"}
}