{
  "type": "Feature",
  "properties": {
    "addr:full":"721 Anderson Rd Linden PA 17744",
    "addr:housenumber":"721",
    "addr:postcode":"17744",
    "addr:street":"Anderson Rd",
    "iso:country":"US",
    "sg:address":"721 Anderson Rd",
    "sg:city":"Linden",
    "sg:classifiers":[
        {
            "category":"Manufacturing",
            "subcategory":"Lumber",
            "type":"Manufacturing & Wholesale Goods"
        }
    ],
    "sg:phone":"+1   ",
    "sg:postcode":"17744",
    "sg:province":"PA",
    "sg:tags":[
        "mill"
    ],
    "wof:name":"Paulhamus Sawmill",
    "wof:placetype":"venue"
},
  "geometry": {"coordinates":[-77.14165300000001,41.286294],"type":"Point"}
}