{
  "type": "Feature",
  "properties": {
    "iso:country":"US",
    "sg:address":"1135 Simmontown Rd",
    "sg:city":"Gap",
    "sg:classifiers":[
        {
            "category":"Building & Trades",
            "subcategory":"Construction",
            "type":"Services"
        }
    ],
    "sg:phone":"+1 610 593 2822",
    "sg:postcode":"17527",
    "sg:province":"PA",
    "sg:tags":[
        "contractor"
    ],
    "wof:name":"Virgil Engel Builders",
    "wof:placetype":"venue"
},
  "geometry": {"coordinates":[-75.989116,39.966863],"type":"Point"}
}