{
  "type": "Feature",
  "properties": {
    "iso:country":"US",
    "sg:address":"171 Scranton Carbondale Hwy",
    "sg:city":"Archbald",
    "sg:classifiers":[
        {
            "category":"Real Estate",
            "subcategory":"Real Estate Services",
            "type":"Services"
        }
    ],
    "sg:phone":"+1   ",
    "sg:postcode":"18403",
    "sg:province":"PA",
    "sg:tags":[
        "abstract",
        "title"
    ],
    "wof:name":"Rudalavage Law Office",
    "wof:placetype":"venue"
},
  "geometry": {"coordinates":[-75.582926,41.498335],"type":"Point"}
}