{
  "type": "Feature",
  "properties": {
    "addr:full":"341 Beaumont Rd Devon PA 19333",
    "addr:housenumber":"341",
    "addr:postcode":"19333",
    "addr:street":"Beaumont Rd",
    "iso:country":"US",
    "sg:address":"341 Beaumont Rd",
    "sg:city":"Devon",
    "sg:classifiers":[
        {
            "category":"Professional",
            "type":"Services"
        }
    ],
    "sg:phone":"+1   ",
    "sg:postcode":"19333",
    "sg:province":"PA",
    "wof:name":"Campo & Co",
    "wof:placetype":"venue"
},
  "geometry": {"coordinates":[-75.421201,40.029325],"type":"Point"}
}