{
  "type": "Feature",
  "properties": {
    "iso:country":"US",
    "sg:address":"1301 Lincoln Rd",
    "sg:city":"Lititz",
    "sg:classifiers":[
        {
            "category":"Farming",
            "subcategory":"Livestock Farm",
            "type":"Manufacturing & Wholesale Goods"
        }
    ],
    "sg:phone":"+1   ",
    "sg:postcode":"17543",
    "sg:province":"PA",
    "sg:tags":[
        "beef",
        "feedlot",
        "cattle"
    ],
    "wof:name":"Lloyd Z Nolt Inc",
    "wof:placetype":"venue"
},
  "geometry": {"coordinates":[-76.242048,40.187472],"type":"Point"}
}