{
  "type": "Feature",
  "properties": {
    "addr:full":"621 Park Ave Hershey PA 17033",
    "addr:housenumber":"621",
    "addr:postcode":"17033",
    "addr:street":"Park Ave",
    "iso:country":"US",
    "sg:address":"621 Park Ave",
    "sg:city":"Hershey",
    "sg:classifiers":[
        {
            "category":"Coffee & Tea",
            "type":"Food & Drink"
        },
        {
            "category":"Donuts",
            "subcategory":"None",
            "type":"Food & Drink"
        }
    ],
    "sg:phone":"+1 717 533 2080",
    "sg:postcode":"17033",
    "sg:province":"PA",
    "sg:tags":[
        "shop",
        "espresso",
        "restaurant"
    ],
    "sg:website":"http://www.dunkindonuts.com",
    "wof:name":"Dunkin' Donuts",
    "wof:placetype":"venue"
},
  "geometry": {"coordinates":[-76.65227,40.293745],"type":"Point"}
}