{
  "type": "Feature",
  "properties": {
    "addr:full":"742 Red Lion Rd Philadelphia PA 19115",
    "addr:housenumber":"742",
    "addr:postcode":"19115",
    "addr:street":"Red Lion Rd",
    "iso:country":"US",
    "sg:address":"742 Red Lion Rd",
    "sg:city":"Philadelphia",
    "sg:classifiers":[
        {
            "category":"Restaurant",
            "type":"Food & Drink"
        }
    ],
    "sg:menulink":"http://www.allmenus.com/pa/philadelphia/288203-sorrento-pizza/menu/",
    "sg:phone":"+1 215 673 6842",
    "sg:postcode":"19115",
    "sg:province":"PA",
    "sg:tags":[
        "american",
        "pizza"
    ],
    "wof:name":"Sorrento Bona Pizza",
    "wof:placetype":"venue"
},
  "geometry": {"coordinates":[-75.033405,40.105345],"type":"Point"}
}