{
  "type": "Feature",
  "properties": {
    "iso:country":"US",
    "sg:address":"4601 Butler St",
    "sg:city":"Pittsburgh",
    "sg:classifiers":[
        {
            "category":"Bars & Pubs",
            "type":"Food & Drink"
        }
    ],
    "sg:phone":"+1 412 682 2340",
    "sg:postcode":"15201",
    "sg:province":"PA",
    "sg:tags":[
        "drinking"
    ],
    "wof:name":"Partner's",
    "wof:placetype":"venue"
},
  "geometry": {"coordinates":[-79.958322,40.473479],"type":"Point"}
}