{
  "type": "Feature",
  "properties": {
    "addr:full":"10 Rittenhouse Pl Ardmore PA 19003",
    "addr:housenumber":"10",
    "addr:postcode":"19003",
    "addr:street":"Rittenhouse Pl",
    "iso:country":"US",
    "sg:address":"10 Rittenhouse Pl",
    "sg:city":"Ardmore",
    "sg:classifiers":[
        {
            "category":"Restaurant",
            "type":"Food & Drink"
        }
    ],
    "sg:menulink":"http://www.allmenus.com/pa/lower-merion/17545-ardmore-pizza/menu/",
    "sg:phone":"+1 610 649 7320",
    "sg:postcode":"19003",
    "sg:province":"PA",
    "sg:tags":[
        "american",
        "pizza"
    ],
    "wof:name":"Ardmore Pizza",
    "wof:placetype":"venue"
},
  "geometry": {"coordinates":[-75.28942600000001,40.006642],"type":"Point"}
}