{
  "type": "Feature",
  "properties": {
    "addr:full":"2115 E Chelten Ave Philadelphia PA 19138",
    "addr:housenumber":"2115",
    "addr:postcode":"19138",
    "addr:street":"E Chelten Ave",
    "iso:country":"US",
    "sg:address":"2115 E Chelten Ave",
    "sg:city":"Philadelphia",
    "sg:classifiers":[
        {
            "category":"Shopping",
            "subcategory":"Discount & Variety Stores",
            "type":"Retail Goods"
        }
    ],
    "sg:phone":"+1 215 549 1115",
    "sg:postcode":"19138",
    "sg:province":"PA",
    "wof:name":"Lindsay Variety Store",
    "wof:placetype":"venue"
},
  "geometry": {"coordinates":[-75.156756,40.051978],"type":"Point"}
}