{
  "type": "Feature",
  "properties": {
    "iso:country":"US",
    "sg:address":"5943 Linglestown Rd",
    "sg:city":"Harrisburg",
    "sg:classifiers":[
        {
            "category":"Shopping",
            "subcategory":"Beauty & Cosmetics",
            "type":"Retail Goods"
        },
        {
            "category":"Personal",
            "subcategory":"Beauty Salon",
            "type":"Services"
        }
    ],
    "sg:phone":"+1 717 545 8500",
    "sg:postcode":"17112",
    "sg:province":"PA",
    "sg:tags":[
        "perfume",
        "salons-equipment",
        "supply"
    ],
    "sg:website":"http://www.firstimps.com",
    "wof:name":"First Impressions Boutique And Design",
    "wof:placetype":"venue"
},
  "geometry": {"coordinates":[-76.794392,40.34304],"type":"Point"}
}