{
  "type": "Feature",
  "properties": {
    "iso:country":"US",
    "sg:address":"3001 Columbia Ave",
    "sg:city":"Camp Hill",
    "sg:classifiers":[
        {
            "category":"Organizations",
            "subcategory":"Professional Association",
            "type":"Services"
        }
    ],
    "sg:phone":"+1 717 763 9072",
    "sg:postcode":"17011",
    "sg:province":"PA",
    "wof:name":"Hoke & Nester Assn",
    "wof:placetype":"venue"
},
  "geometry": {"coordinates":[-76.931037,40.234048],"type":"Point"}
}