{
  "type": "Feature",
  "properties": {
    "iso:country":"US",
    "sg:address":"906 4th Ave",
    "sg:city":"Coraopolis",
    "sg:classifiers":[
        {
            "category":"Retail",
            "subcategory":"Car Wash",
            "type":"Services"
        }
    ],
    "sg:phone":"+1 412 264 3555",
    "sg:postcode":"15108",
    "sg:province":"PA",
    "sg:tags":[
        "carwash",
        "automobile",
        "detail",
        "clean"
    ],
    "wof:name":"Terry's Auto Detailing",
    "wof:placetype":"venue"
},
  "geometry": {"coordinates":[-80.164188,40.518502],"type":"Point"}
}