{
  "type": "Feature",
  "properties": {
    "iso:country":"US",
    "sg:address":"1360 E Lisburn Rd",
    "sg:city":"Mechanicsburg",
    "sg:classifiers":[
        {
            "category":"Building & Trades",
            "subcategory":"Landscaping Services",
            "type":"Services"
        }
    ],
    "sg:phone":"+1 717 697 4439",
    "sg:postcode":"17055",
    "sg:province":"PA",
    "sg:tags":[
        "lawn",
        "garden"
    ],
    "sg:website":"www.blacklandscape.com",
    "wof:name":"Black Landscape Contracting",
    "wof:placetype":"venue"
},
  "geometry": {"coordinates":[-76.930482,40.171675],"type":"Point"}
}