{
  "type": "Feature",
  "properties": {
    "iso:country":"US",
    "sg:address":"1518 Cecil B Moore Ave",
    "sg:city":"Philadelphia",
    "sg:classifiers":[
        {
            "category":"Professional",
            "subcategory":"Detective & Security Services",
            "type":"Services"
        }
    ],
    "sg:phone":"+1 215 236 2689",
    "sg:postcode":"19121",
    "sg:province":"PA",
    "sg:tags":[
        "car",
        "armored",
        "private",
        "investigator"
    ],
    "wof:name":"Allied Security",
    "wof:placetype":"venue"
},
  "geometry": {"coordinates":[-75.16033899999999,39.979],"type":"Point"}
}