{
  "type": "Feature",
  "properties": {
    "iso:country":"US",
    "sg:address":"6240 Wister St",
    "sg:city":"Philadelphia",
    "sg:classifiers":[
        {
            "category":"Building & Trades",
            "subcategory":"Cleaning & Sanitation",
            "type":"Services"
        }
    ],
    "sg:phone":"+1 215 438 6183",
    "sg:postcode":"19138",
    "sg:province":"PA",
    "sg:tags":[
        "cleaning-industrial",
        "contractor"
    ],
    "wof:name":"April Fresh Cleaning Svcs",
    "wof:placetype":"venue"
},
  "geometry": {"coordinates":[-75.157892,40.049772],"type":"Point"}
}