{
  "type": "Feature",
  "properties": {
    "iso:country":"US",
    "sg:address":"375 Weadley Rd",
    "sg:city":"King Of Prussia",
    "sg:classifiers":[
        {
            "category":"Manufacturing",
            "subcategory":"Rubber & Plastics",
            "type":"Manufacturing & Wholesale Goods"
        }
    ],
    "sg:phone":"+1   ",
    "sg:postcode":"19406",
    "sg:province":"PA",
    "sg:tags":[
        "profile",
        "shape",
        "engineering",
        "mfg"
    ],
    "wof:name":"Jeffreys Flex-Flow Co",
    "wof:placetype":"venue"
},
  "geometry": {"coordinates":[-75.363203,40.074455],"type":"Point"}
}