{
  "type": "Feature",
  "properties": {
    "iso:country":"US",
    "sg:address":"45 N Market St",
    "sg:city":"Lancaster",
    "sg:classifiers":[
        {
            "category":"Shopping",
            "type":"Retail Goods"
        }
    ],
    "sg:phone":"+1 717 299 5888",
    "sg:postcode":"17603",
    "sg:province":"PA",
    "sg:tags":[
        "religious"
    ],
    "wof:name":"Triumph Triune Spiritual Items",
    "wof:placetype":"venue"
},
  "geometry": {"coordinates":[-76.306641,40.037889],"type":"Point"}
}