{
  "type": "Feature",
  "properties": {
    "iso:country":"US",
    "sg:address":"704 E 5th St",
    "sg:city":"Mt Carmel",
    "sg:classifiers":[
        {
            "category":"Retail",
            "subcategory":"Auto Repair",
            "type":"Services"
        }
    ],
    "sg:phone":"+1 570 339 3224",
    "sg:postcode":"17851",
    "sg:province":"PA",
    "sg:tags":[
        "body",
        "automotive",
        "painting",
        "automobile"
    ],
    "wof:name":"Hubers Collision & Towing",
    "wof:placetype":"venue"
},
  "geometry": {"coordinates":[-76.40541899999999,40.795961],"type":"Point"}
}