{
  "type": "Feature",
  "properties": {
    "iso:country":"US",
    "sg:address":"202 W Plank Rd",
    "sg:city":"Altoona",
    "sg:classifiers":[
        {
            "category":"Personal",
            "subcategory":"Beauty Salon",
            "type":"Services"
        }
    ],
    "sg:phone":"+1 814 941 1241",
    "sg:postcode":"16602",
    "sg:province":"PA",
    "sg:tags":[
        "shop"
    ],
    "wof:name":"Above and Beyond Styling",
    "wof:placetype":"venue"
},
  "geometry": {"coordinates":[-78.404202,40.476974],"type":"Point"}
}