{
  "type": "Feature",
  "properties": {
    "iso:country":"US",
    "sg:address":"5223 Catharine St",
    "sg:city":"Philadelphia",
    "sg:classifiers":[
        {
            "category":"Professional",
            "subcategory":"Research",
            "type":"Services"
        }
    ],
    "sg:phone":"+1   ",
    "sg:postcode":"19143",
    "sg:province":"PA",
    "sg:tags":[
        "nonphysical",
        "commercial"
    ],
    "wof:name":"Jermaine Jones",
    "wof:placetype":"venue"
},
  "geometry": {"coordinates":[-75.228799,39.949228],"type":"Point"}
}