{
  "type": "Feature",
  "properties": {
    "addr:full":"777 Cherry Tree Ct Ste 3 Hanover PA 17331",
    "addr:housenumber":"777",
    "addr:postcode":"17331",
    "addr:street":"Cherry Tree Ct Ste 3",
    "iso:country":"US",
    "sg:address":"777 Cherry Tree Ct Ste 3",
    "sg:city":"Hanover",
    "sg:classifiers":[
        {
            "category":"Health Services",
            "subcategory":"Hospital",
            "type":"Services"
        },
        {
            "category":"Health Services",
            "subcategory":"Clinic",
            "type":"Services"
        }
    ],
    "sg:phone":"+1 717 632 1559",
    "sg:postcode":"17331",
    "sg:province":"PA",
    "sg:tags":[
        "treatment",
        "cancer"
    ],
    "wof:name":"Blood & Cancer Center",
    "wof:placetype":"venue"
},
  "geometry": {"coordinates":[-76.964354,39.815677],"type":"Point"}
}