{
  "type": "Feature",
  "properties": {
    "iso:country":"US",
    "sg:address":"1386 Dutch Ln",
    "sg:city":"Hermitage",
    "sg:classifiers":[
        {
            "category":"Building & Trades",
            "subcategory":"Electrical",
            "type":"Services"
        }
    ],
    "sg:phone":"+1   ",
    "sg:postcode":"16148",
    "sg:province":"PA",
    "sg:tags":[
        "electrical",
        "contractor"
    ],
    "wof:name":"Hermitage Htg & Coolg & Elec",
    "wof:placetype":"venue"
},
  "geometry": {"coordinates":[-80.456187,41.243317],"type":"Point"}
}