{
  "type": "Feature",
  "properties": {
    "addr:full":"457 Leearden Rd Hershey PA 17033",
    "addr:housenumber":"457",
    "addr:postcode":"17033",
    "addr:street":"Leearden Rd",
    "iso:country":"US",
    "sg:address":"457 Leearden Rd",
    "sg:city":"Hershey",
    "sg:classifiers":[
        {
            "category":"Restaurant",
            "type":"Food & Drink"
        }
    ],
    "sg:phone":"+1   ",
    "sg:postcode":"17033",
    "sg:province":"PA",
    "sg:tags":[
        "eating"
    ],
    "wof:name":"Seasons Wok Chinese Restaurant",
    "wof:placetype":"venue"
},
  "geometry": {"coordinates":[-76.65156899999999,40.262416],"type":"Point"}
}