{
  "type": "Feature",
  "properties": {
    "addr:full":"1503 Quentin Rd Lebanon PA 17042",
    "addr:housenumber":"1503",
    "addr:postcode":"17042",
    "addr:street":"Quentin Rd",
    "iso:country":"US",
    "sg:address":"1503 Quentin Rd",
    "sg:city":"Lebanon",
    "sg:classifiers":[
        {
            "category":"Wholesale",
            "subcategory":"Electrical",
            "type":"Manufacturing & Wholesale Goods"
        }
    ],
    "sg:phone":"+1   ",
    "sg:postcode":"17042",
    "sg:province":"PA",
    "sg:tags":[
        "equipment"
    ],
    "wof:name":"Lebanon Electric Supply C",
    "wof:placetype":"venue"
},
  "geometry": {"coordinates":[-76.423328,40.317429],"type":"Point"}
}