{
  "type": "Feature",
  "properties": {
    "addr:full":"502 Main St Towanda PA 18848",
    "addr:housenumber":"502",
    "addr:postcode":"18848",
    "addr:street":"Main St",
    "iso:country":"US",
    "sg:address":"502 Main St",
    "sg:city":"Towanda",
    "sg:classifiers":[
        {
            "category":"Manufacturing",
            "subcategory":"Metals",
            "type":"Manufacturing & Wholesale Goods"
        }
    ],
    "sg:phone":"+1 570 265 3621",
    "sg:postcode":"18848",
    "sg:province":"PA",
    "sg:tags":[
        "engraver"
    ],
    "wof:name":"C & G Wilcox Engravings",
    "wof:placetype":"venue"
},
  "geometry": {"coordinates":[-76.443156,41.765354],"type":"Point"}
}