{
  "type": "Feature",
  "properties": {
    "iso:country":"US",
    "sg:address":"518 Main St",
    "sg:city":"Harleysville",
    "sg:classifiers":[
        {
            "category":"Personal",
            "subcategory":"Beauty Salon",
            "type":"Services"
        }
    ],
    "sg:phone":"+1 215 256 9702",
    "sg:postcode":"19438",
    "sg:province":"PA",
    "wof:name":"Salon Allure",
    "wof:placetype":"venue"
},
  "geometry": {"coordinates":[-75.38854499999999,40.280032],"type":"Point"}
}