{
  "type": "Feature",
  "properties": {
    "addr:full":"4600 Jonestown Rd Harrisburg PA 17109",
    "addr:postcode":"4600;17109",
    "addr:street":"Jonestown Rd",
    "iso:country":"US",
    "sg:address":"4600 Jonestown Rd",
    "sg:city":"Harrisburg",
    "sg:classifiers":[
        {
            "category":"Shopping",
            "subcategory":"Department Store",
            "type":"Retail Goods"
        }
    ],
    "sg:phone":"+1 717 540 4000",
    "sg:postcode":"17109",
    "sg:province":"PA",
    "sg:website":"www.sears.com/",
    "wof:name":"Sears",
    "wof:placetype":"venue"
},
  "geometry": {"coordinates":[-76.82011799999999,40.3001],"type":"Point"}
}