{
  "type": "Feature",
  "properties": {
    "iso:country":"US",
    "sg:address":"20 Woods Ln",
    "sg:city":"Barto",
    "sg:classifiers":[
        {
            "category":"Wholesale",
            "subcategory":"Groceries",
            "type":"Manufacturing & Wholesale Goods"
        }
    ],
    "sg:phone":"+1   ",
    "sg:postcode":"19504",
    "sg:province":"PA",
    "wof:name":"Franola Products Inc",
    "wof:placetype":"venue"
},
  "geometry": {"coordinates":[-75.597779,40.425371],"type":"Point"}
}