{
  "type": "Feature",
  "properties": {
    "iso:country":"US",
    "sg:address":"1610 4th St",
    "sg:city":"Monongahela",
    "sg:classifiers":[
        {
            "category":"Manufacturing",
            "subcategory":"Printing",
            "type":"Manufacturing & Wholesale Goods"
        }
    ],
    "sg:phone":"+1 724 258 0582",
    "sg:postcode":"15063",
    "sg:province":"PA",
    "sg:tags":[
        "printer",
        "form"
    ],
    "wof:name":"Business Forms Inc",
    "wof:placetype":"venue"
},
  "geometry": {"coordinates":[-79.95534499999999,40.191553],"type":"Point"}
}