{
  "type": "Feature",
  "properties": {
    "addr:full":"347 Logan Ave Glenside PA 19038",
    "addr:housenumber":"347",
    "addr:postcode":"19038",
    "addr:street":"Logan Ave",
    "iso:country":"US",
    "sg:address":"347 Logan Ave",
    "sg:city":"Glenside",
    "sg:classifiers":[
        {
            "category":"Recreation",
            "type":"Entertainment"
        }
    ],
    "sg:phone":"+1 215 887 8785",
    "sg:postcode":"19038",
    "sg:province":"PA",
    "sg:tags":[
        "pool",
        "swimming"
    ],
    "wof:name":"Upper Dublin Twp Comm Pool",
    "wof:placetype":"venue"
},
  "geometry": {"coordinates":[-75.169224,40.118263],"type":"Point"}
}