{
  "type": "Feature",
  "properties": {
    "addr:full":"4433 Howley St Pittsburgh PA 15224",
    "addr:housenumber":"4433",
    "addr:postcode":"15224",
    "addr:street":"Howley St",
    "iso:country":"US",
    "sg:address":"4433 Howley St",
    "sg:city":"Pittsburgh",
    "sg:classifiers":[
        {
            "category":"Manufacturing",
            "subcategory":"Printing",
            "type":"Manufacturing & Wholesale Goods"
        }
    ],
    "sg:phone":"+1 412 683 1300",
    "sg:postcode":"15224",
    "sg:province":"PA",
    "sg:tags":[
        "print",
        "lithographic"
    ],
    "sg:website":"www.newimagepress.com",
    "wof:name":"New Image Press Inc",
    "wof:placetype":"venue"
},
  "geometry": {"coordinates":[-79.952878,40.464048],"type":"Point"}
}