{
  "type": "Feature",
  "properties": {
    "iso:country":"US",
    "sg:address":"140 E 6th St",
    "sg:city":"Erie",
    "sg:classifiers":[
        {
            "category":"Utilities",
            "subcategory":"Telephone",
            "type":"Services"
        }
    ],
    "sg:phone":"+1 814 456 0162",
    "sg:postcode":"16501",
    "sg:province":"PA",
    "sg:tags":[
        "company"
    ],
    "wof:name":"Inmate Telephone Inc",
    "wof:placetype":"venue"
},
  "geometry": {"coordinates":[-80.082274,42.130519],"type":"Point"}
}