{
  "type": "Feature",
  "properties": {
    "addr:full":"732 Chestnut St Philadelphia PA 19106",
    "addr:housenumber":"732",
    "addr:postcode":"19106",
    "addr:street":"Chestnut St",
    "iso:country":"US",
    "sg:address":"732 Chestnut St",
    "sg:city":"Philadelphia",
    "sg:classifiers":[
        {
            "category":"Shopping",
            "subcategory":"Jewelry",
            "type":"Retail Goods"
        }
    ],
    "sg:phone":"+1 215 627 9282",
    "sg:postcode":"19106",
    "sg:province":"PA",
    "sg:tags":[
        "watch"
    ],
    "wof:name":"Jewelers'row Money Loan",
    "wof:placetype":"venue"
},
  "geometry": {"coordinates":[-75.153801,39.949799],"type":"Point"}
}