{
  "type": "Feature",
  "properties": {
    "iso:country":"US",
    "sg:address":"915 Radley St",
    "sg:city":"Bethlehem",
    "sg:classifiers":[
        {
            "category":"Building & Trades",
            "subcategory":"Construction",
            "type":"Services"
        }
    ],
    "sg:phone":"+1 610 258 3670",
    "sg:postcode":"18018",
    "sg:province":"PA",
    "sg:tags":[
        "contractor"
    ],
    "wof:name":"Elliot Building Grp LTD",
    "wof:placetype":"venue"
},
  "geometry": {"coordinates":[-75.379369,40.626499],"type":"Point"}
}