{
  "type": "Feature",
  "properties": {
    "iso:country":"US",
    "sg:address":"2535 W State St",
    "sg:city":"New Castle",
    "sg:classifiers":[
        {
            "category":"Shopping",
            "subcategory":"Clothing, Apparel, & Fashions",
            "type":"Retail Goods"
        }
    ],
    "sg:phone":"+1 724 656 0401",
    "sg:postcode":"16101",
    "sg:province":"PA",
    "wof:name":"Nu Look",
    "wof:placetype":"venue"
},
  "geometry": {"coordinates":[-80.390159,41.010328],"type":"Point"}
}