{
  "type": "Feature",
  "properties": {
    "iso:country":"US",
    "sg:address":"300 Cypress St",
    "sg:city":"Lehighton",
    "sg:classifiers":[
        {
            "category":"Insurance",
            "subcategory":"Insurance Agent",
            "type":"Services"
        },
        {
            "category":"Insurance",
            "subcategory":"Hazard Insurance",
            "type":"Services"
        },
        {
            "category":"Insurance",
            "subcategory":"Title Insurance",
            "type":"Services"
        }
    ],
    "sg:phone":"+1 610 377 1120",
    "sg:postcode":"18235",
    "sg:province":"PA",
    "sg:tags":[
        "business",
        "fire",
        "auto",
        "commercial",
        "homeowner",
        "renter"
    ],
    "sg:website":"http://www.laroseinsurance.com",
    "wof:name":"GEORGE I. LAROSE INSURANCE LTD.",
    "wof:placetype":"venue"
},
  "geometry": {"coordinates":[-75.712311,40.835369],"type":"Point"}
}