{
  "type": "Feature",
  "properties": {
    "addr:full":"403 W Chester Pike Havertown PA 19083",
    "addr:housenumber":"403",
    "addr:postcode":"19083",
    "addr:street":"W Chester Pike",
    "iso:country":"US",
    "sg:address":"403 W Chester Pike",
    "sg:city":"Havertown",
    "sg:classifiers":[
        {
            "category":"Personal",
            "type":"Services"
        }
    ],
    "sg:phone":"+1 610 789 4418",
    "sg:postcode":"19083",
    "sg:province":"PA",
    "sg:tags":[
        "miscellaneous"
    ],
    "wof:name":"Personal Fitness Group LLC",
    "wof:placetype":"venue"
},
  "geometry": {"coordinates":[-75.304067,39.970355],"type":"Point"}
}