{
  "type": "Feature",
  "properties": {
    "addr:full":"2500 Kingston Rd York PA 17402",
    "addr:housenumber":"2500",
    "addr:postcode":"17402",
    "addr:street":"Kingston Rd",
    "iso:country":"US",
    "sg:address":"2500 Kingston Rd",
    "sg:city":"York",
    "sg:classifiers":[
        {
            "category":"Real Estate",
            "subcategory":"Surveying",
            "type":"Services"
        },
        {
            "category":"Professional",
            "subcategory":"Business Services",
            "type":"Services"
        }
    ],
    "sg:phone":"+1 717 840 1768",
    "sg:postcode":"17402",
    "sg:province":"PA",
    "sg:tags":[
        "appraiser"
    ],
    "wof:name":"Cauchon Appraisals",
    "wof:placetype":"venue"
},
  "geometry": {"coordinates":[-76.676109,39.97118],"type":"Point"}
}