{
  "type": "Feature",
  "properties": {
    "iso:country":"US",
    "sg:address":"129 Robbins Station Rd",
    "sg:city":"Irwin",
    "sg:classifiers":[
        {
            "category":"Professional",
            "subcategory":"Advertising",
            "type":"Services"
        },
        {
            "category":"Manufacturing",
            "subcategory":"Printing",
            "type":"Manufacturing & Wholesale Goods"
        }
    ],
    "sg:phone":"+1 724 861 4300",
    "sg:postcode":"15642",
    "sg:province":"PA",
    "sg:tags":[
        "counselor"
    ],
    "wof:name":"G A Communications",
    "wof:placetype":"venue"
},
  "geometry": {"coordinates":[-79.73694,40.328207],"type":"Point"}
}