{
  "type": "Feature",
  "properties": {
    "addr:full":"830 Main St Dickson City PA 18519",
    "addr:housenumber":"830",
    "addr:postcode":"18519",
    "addr:street":"Main St",
    "iso:country":"US",
    "sg:address":"830 Main St",
    "sg:city":"Dickson City",
    "sg:classifiers":[
        {
            "category":"Personal",
            "subcategory":"Beauty Salon",
            "type":"Services"
        }
    ],
    "sg:phone":"+1 570 489 0075",
    "sg:postcode":"18519",
    "sg:province":"PA",
    "wof:name":"A Cut Above",
    "wof:placetype":"venue"
},
  "geometry": {"coordinates":[-75.62272900000001,41.461034],"type":"Point"}
}