{
  "type": "Feature",
  "properties": {
    "addr:full":"1000 E Market St Orwigsburg PA 17961",
    "addr:housenumber":"1000",
    "addr:postcode":"17961",
    "addr:street":"E Market St",
    "iso:country":"US",
    "sg:address":"1000 E Market St",
    "sg:city":"Orwigsburg",
    "sg:classifiers":[
        {
            "category":"Organizations",
            "subcategory":"Community Association",
            "type":"Services"
        }
    ],
    "sg:phone":"+1 570 366 1385",
    "sg:postcode":"17961",
    "sg:province":"PA",
    "sg:tags":[
        "fraternal"
    ],
    "wof:name":"Schuylkill Lodge 138",
    "wof:placetype":"venue"
},
  "geometry": {"coordinates":[-76.087413,40.649595],"type":"Point"}
}