{
  "type": "Feature",
  "properties": {
    "addr:full":"50 N Penn St Windsor PA 17366",
    "addr:housenumber":"50",
    "addr:postcode":"17366",
    "addr:street":"N Penn St",
    "iso:country":"US",
    "sg:address":"50 N Penn St",
    "sg:city":"Windsor",
    "sg:classifiers":[
        {
            "category":"Building & Trades",
            "subcategory":"Construction",
            "type":"Services"
        }
    ],
    "sg:phone":"+1   ",
    "sg:postcode":"17366",
    "sg:province":"PA",
    "sg:tags":[
        "house"
    ],
    "wof:name":"Dunlap Construction Co",
    "wof:placetype":"venue"
},
  "geometry": {"coordinates":[-76.580434,39.91713],"type":"Point"}
}