{
  "type": "Feature",
  "properties": {
    "iso:country":"US",
    "sg:address":"1011 Hill St",
    "sg:city":"Philipsburg",
    "sg:classifiers":[
        {
            "category":"Real Estate",
            "subcategory":"Real Estate Operator",
            "type":"Services"
        }
    ],
    "sg:phone":"+1 814 342 1538",
    "sg:postcode":"16866",
    "sg:province":"PA",
    "sg:tags":[
        "apartment"
    ],
    "wof:name":"Sunny Slope Apartments",
    "wof:placetype":"venue"
},
  "geometry": {"coordinates":[-78.233796,40.889654],"type":"Point"}
}