{
  "type": "Feature",
  "properties": {
    "iso:country":"US",
    "sg:address":"37 Lenker Ave",
    "sg:city":"Selinsgrove",
    "sg:classifiers":[
        {
            "category":"Building & Trades",
            "subcategory":"Construction",
            "type":"Services"
        }
    ],
    "sg:phone":"+1 570 374 0765",
    "sg:postcode":"17870",
    "sg:province":"PA",
    "sg:tags":[
        "excavation",
        "contractor"
    ],
    "wof:name":"D & H Construction",
    "wof:placetype":"venue"
},
  "geometry": {"coordinates":[-76.84740600000001,40.822098],"type":"Point"}
}