{
  "type": "Feature",
  "properties": {
    "addr:full":"2222 W Grandview Blvd Erie PA 16506",
    "addr:housenumber":"2222",
    "addr:postcode":"16506",
    "addr:street":"W Grandview Blvd",
    "iso:country":"US",
    "sg:address":"2222 W Grandview Blvd",
    "sg:city":"Erie",
    "sg:classifiers":[
        {
            "category":"Professional",
            "subcategory":"Lawyer & Legal Services",
            "type":"Services"
        }
    ],
    "sg:phone":"+1   ",
    "sg:postcode":"16506",
    "sg:province":"PA",
    "wof:name":"Kevin M Monahan",
    "wof:placetype":"venue"
},
  "geometry": {"coordinates":[-80.11109399999999,42.077587],"type":"Point"}
}