{
  "type": "Feature",
  "properties": {
    "addr:full":"1703 Duss Ave Ambridge PA 15003",
    "addr:housenumber":"1703",
    "addr:postcode":"15003",
    "addr:street":"Duss Ave",
    "iso:country":"US",
    "sg:address":"1703 Duss Ave",
    "sg:city":"Ambridge",
    "sg:classifiers":[
        {
            "category":"Organizations",
            "subcategory":"Religious Organization",
            "type":"Services"
        }
    ],
    "sg:phone":"+1 724 266 1705",
    "sg:postcode":"15003",
    "sg:province":"PA",
    "sg:tags":[
        "monastery",
        "convent"
    ],
    "wof:name":"Sisters of St Joseph",
    "wof:placetype":"venue"
},
  "geometry": {"coordinates":[-80.226297,40.600456],"type":"Point"}
}