{
  "type": "Feature",
  "properties": {
    "iso:country":"US",
    "sg:address":"229 S Mount Vernon Ave",
    "sg:city":"Uniontown",
    "sg:classifiers":[
        {
            "category":"Recreation",
            "type":"Entertainment"
        }
    ],
    "sg:phone":"+1   ",
    "sg:postcode":"15401",
    "sg:province":"PA",
    "sg:tags":[
        "club",
        "house",
        "membership",
        "co"
    ],
    "wof:name":"South Uniontwn Amrcanzd Benfcl",
    "wof:placetype":"venue"
},
  "geometry": {"coordinates":[-79.740019,39.894417],"type":"Point"}
}