{
  "type": "Feature",
  "properties": {
    "iso:country":"US",
    "sg:address":"1435 Dorchester Rd",
    "sg:city":"Havertown",
    "sg:classifiers":[
        {
            "category":"Building & Trades",
            "subcategory":"Construction",
            "type":"Services"
        }
    ],
    "sg:phone":"+1   ",
    "sg:postcode":"19083",
    "sg:province":"PA",
    "sg:tags":[
        "hanging",
        "business",
        "contractor"
    ],
    "wof:name":"Decor Painting",
    "wof:placetype":"venue"
},
  "geometry": {"coordinates":[-75.323153,39.976868],"type":"Point"}
}