{
  "type": "Feature",
  "properties": {
    "addr:full":"3 N Pine St Gettysburg PA 17325",
    "addr:housenumber":"3",
    "addr:postcode":"17325",
    "addr:street":"N Pine St",
    "iso:country":"US",
    "sg:address":"3 N Pine St",
    "sg:city":"Gettysburg",
    "sg:classifiers":[
        {
            "category":"Freight",
            "type":"Transportation"
        }
    ],
    "sg:phone":"+1   ",
    "sg:postcode":"17325",
    "sg:province":"PA",
    "sg:tags":[
        "general"
    ],
    "wof:name":"Martins Self-Storage",
    "wof:placetype":"venue"
},
  "geometry": {"coordinates":[-77.138391,39.815014],"type":"Point"}
}