{
  "type": "Feature",
  "properties": {
    "addr:full":"4304 Walnut St Mckeesport PA 15132",
    "addr:housenumber":"4304",
    "addr:postcode":"15132",
    "addr:street":"Walnut St",
    "iso:country":"US",
    "sg:address":"4304 Walnut St",
    "sg:city":"Mckeesport",
    "sg:classifiers":[
        {
            "category":"Communications",
            "subcategory":"Radio Station",
            "type":"Services"
        }
    ],
    "sg:phone":"+1 412 751 6322",
    "sg:postcode":"15132",
    "sg:province":"PA",
    "sg:tags":[
        "company",
        "broadcasting"
    ],
    "wof:name":"Castle AM & Co",
    "wof:placetype":"venue"
},
  "geometry": {"coordinates":[-79.836127,40.320637],"type":"Point"}
}