{
  "type": "Feature",
  "properties": {
    "iso:country":"US",
    "sg:address":"10 Delphi Rd",
    "sg:city":"Schwenksville",
    "sg:classifiers":[
        {
            "category":"Professional",
            "subcategory":"Art Services",
            "type":"Services"
        }
    ],
    "sg:phone":"+1 610 287 7086",
    "sg:postcode":"19473",
    "sg:province":"PA",
    "sg:tags":[
        "interior",
        "designer",
        "decorator"
    ],
    "wof:name":"Barbara J Zucker Designs",
    "wof:placetype":"venue"
},
  "geometry": {"coordinates":[-75.47447,40.272332],"type":"Point"}
}