{
  "type": "Feature",
  "properties": {
    "addr:full":"5711 Friendship Ave Pittsburgh PA 15232",
    "addr:housenumber":"5711",
    "addr:postcode":"15232",
    "addr:street":"Friendship Ave",
    "iso:country":"US",
    "sg:address":"5711 Friendship Ave",
    "sg:city":"Pittsburgh",
    "sg:classifiers":[
        {
            "category":"Professional",
            "type":"Services"
        }
    ],
    "sg:phone":"+1   ",
    "sg:postcode":"15232",
    "sg:province":"PA",
    "wof:name":"Gregory Mims",
    "wof:placetype":"venue"
},
  "geometry": {"coordinates":[-79.93204299999999,40.46064],"type":"Point"}
}