{
  "type": "Feature",
  "properties": {
    "iso:country":"US",
    "sg:address":"7526 Center St",
    "sg:city":"Pittsburgh",
    "sg:classifiers":[
        {
            "category":"Restaurant",
            "type":"Food & Drink"
        }
    ],
    "sg:phone":"+1   ",
    "sg:postcode":"15218",
    "sg:province":"PA",
    "sg:tags":[
        "eating"
    ],
    "wof:name":"TS Restaurant & Lodge",
    "wof:placetype":"venue"
},
  "geometry": {"coordinates":[-79.88606799999999,40.421233],"type":"Point"}
}