{
  "type": "Feature",
  "properties": {
    "iso:country":"US",
    "sg:address":"12 Briarwood Ct",
    "sg:city":"Camp Hill",
    "sg:classifiers":[
        {
            "category":"Communications",
            "subcategory":"Film & Video Production",
            "type":"Services"
        }
    ],
    "sg:phone":"+1 717 761 3838",
    "sg:postcode":"17011",
    "sg:province":"PA",
    "sg:tags":[
        "taping"
    ],
    "sg:website":"www.raeproductions.net",
    "wof:name":"Radio Active Entertainment",
    "wof:placetype":"venue"
},
  "geometry": {"coordinates":[-76.95047099999999,40.254428],"type":"Point"}
}