{
  "type": "Feature",
  "properties": {
    "iso:country":"US",
    "sg:address":"267 Ridgeview Rd",
    "sg:city":"Cooperstown",
    "sg:classifiers":[
        {
            "category":"Farming",
            "subcategory":"Livestock Farm",
            "type":"Manufacturing & Wholesale Goods"
        }
    ],
    "sg:phone":"+1   ",
    "sg:postcode":"16317",
    "sg:province":"PA",
    "sg:tags":[
        "beef",
        "feedlot",
        "cattle"
    ],
    "wof:name":"Maple Knoll Farm",
    "wof:placetype":"venue"
},
  "geometry": {"coordinates":[-79.85364300000001,41.556636],"type":"Point"}
}