{
  "type": "Feature",
  "properties": {
    "iso:country":"US",
    "sg:address":"53 E Market St",
    "sg:city":"Blairsville",
    "sg:classifiers":[
        {
            "category":"Banks & Credit Unions",
            "subcategory":"Bank",
            "type":"Services"
        }
    ],
    "sg:phone":"+1 724 459 6780",
    "sg:postcode":"15717",
    "sg:province":"PA",
    "sg:tags":[
        "commercial",
        "saving"
    ],
    "sg:website":"http://fcbanking.com",
    "wof:name":"First Commonwealth Bank",
    "wof:placetype":"venue"
},
  "geometry": {"coordinates":[-79.263744,40.430852],"type":"Point"}
}