{
  "type": "Feature",
  "properties": {
    "addr:full":"156 Schaeffer Rd Newmanstown PA 17073",
    "addr:housenumber":"156",
    "addr:postcode":"17073",
    "addr:street":"Schaeffer Rd",
    "iso:country":"US",
    "sg:address":"156 Schaeffer Rd",
    "sg:city":"Newmanstown",
    "sg:classifiers":[
        {
            "category":"Real Estate",
            "subcategory":"Real Estate Agent",
            "type":"Services"
        }
    ],
    "sg:phone":"+1   ",
    "sg:postcode":"17073",
    "sg:province":"PA",
    "wof:name":"Keller Real Estate Assocs",
    "wof:placetype":"venue"
},
  "geometry": {"coordinates":[-76.318478,40.29673],"type":"Point"}
}