{
  "type": "Feature",
  "properties": {
    "iso:country":"US",
    "sg:address":"112 Market St",
    "sg:city":"Harrisburg",
    "sg:classifiers":[
        {
            "category":"Government",
            "subcategory":"Office",
            "type":"Public Place"
        }
    ],
    "sg:phone":"+1 717 255 2796",
    "sg:postcode":"17101",
    "sg:province":"PA",
    "wof:name":"Dauphin County Domestic Rltns",
    "wof:placetype":"venue"
},
  "geometry": {"coordinates":[-76.882706,40.258728],"type":"Point"}
}