{
  "type": "Feature",
  "properties": {
    "iso:country":"US",
    "sg:address":"2410 Loop Rd",
    "sg:city":"Chambersburg",
    "sg:classifiers":[
        {
            "category":"Building & Trades",
            "subcategory":"Construction",
            "type":"Services"
        }
    ],
    "sg:phone":"+1   ",
    "sg:postcode":"17202",
    "sg:province":"PA",
    "sg:tags":[
        "house"
    ],
    "wof:name":"Coopers Construction",
    "wof:placetype":"venue"
},
  "geometry": {"coordinates":[-80.255608,40.168279],"type":"Point"}
}