{
  "type": "Feature",
  "properties": {
    "addr:full":"6736 Germantown Ave Philadelphia PA 19119",
    "addr:housenumber":"6736",
    "addr:postcode":"19119",
    "addr:street":"Germantown Ave",
    "iso:country":"US",
    "sg:address":"6736 Germantown Ave",
    "sg:city":"Philadelphia",
    "sg:classifiers":[
        {
            "category":"Retail",
            "subcategory":"Laundry & Dry Cleaning",
            "type":"Services"
        }
    ],
    "sg:phone":"+1 215 843 3054",
    "sg:postcode":"19119",
    "sg:province":"PA",
    "sg:tags":[
        "cleaners"
    ],
    "wof:name":"Ever-Ready Cleaners",
    "wof:placetype":"venue"
},
  "geometry": {"coordinates":[-75.185868,40.052435],"type":"Point"}
}