{
  "type": "Feature",
  "properties": {
    "addr:full":"1223 Evergreen Rd Yardley PA 19067",
    "addr:housenumber":"1223",
    "addr:postcode":"19067",
    "addr:street":"Evergreen Rd",
    "iso:country":"US",
    "sg:address":"1223 Evergreen Rd",
    "sg:city":"Yardley",
    "sg:classifiers":[
        {
            "category":"Banks & Credit Unions",
            "subcategory":"Investment Brokerage",
            "type":"Services"
        }
    ],
    "sg:phone":"+1 215 736 0362",
    "sg:postcode":"19067",
    "sg:province":"PA",
    "sg:tags":[
        "stock",
        "bond"
    ],
    "wof:name":"Merrill Lynch",
    "wof:placetype":"venue"
},
  "geometry": {"coordinates":[-74.80376099999999,40.218502],"type":"Point"}
}