{
  "type": "Feature",
  "properties": {
    "iso:country":"US",
    "sg:address":"5800 Bradley Rd",
    "sg:city":"Greencastle",
    "sg:classifiers":[
        {
            "category":"Building & Trades",
            "subcategory":"Construction",
            "type":"Services"
        }
    ],
    "sg:phone":"+1 717 597 7644",
    "sg:postcode":"17225",
    "sg:province":"PA",
    "sg:tags":[
        "roofing",
        "contractor"
    ],
    "wof:name":"James Vosburg Roofing",
    "wof:placetype":"venue"
},
  "geometry": {"coordinates":[-77.818662,39.777189],"type":"Point"}
}