{
  "type": "Feature",
  "properties": {
    "iso:country":"US",
    "sg:address":"308 5th St",
    "sg:city":"Reading",
    "sg:classifiers":[
        {
            "category":"Personal",
            "subcategory":"Beauty Salon",
            "type":"Services"
        }
    ],
    "sg:phone":"+1   ",
    "sg:postcode":"19601",
    "sg:province":"PA",
    "sg:tags":[
        "shop"
    ],
    "wof:name":"W Huston",
    "wof:placetype":"venue"
},
  "geometry": {"coordinates":[-75.927778,40.341437],"type":"Point"}
}