{
  "type": "Feature",
  "properties": {
    "addr:full":"1656 W Main St Ephrata PA 17522",
    "addr:housenumber":"1656",
    "addr:postcode":"17522",
    "addr:street":"W Main St",
    "iso:country":"US",
    "sg:address":"1656 W Main St",
    "sg:city":"Ephrata",
    "sg:classifiers":[
        {
            "category":"Building & Trades",
            "subcategory":"Construction",
            "type":"Services"
        }
    ],
    "sg:phone":"+1 717 733 1536",
    "sg:postcode":"17522",
    "sg:province":"PA",
    "sg:tags":[
        "house",
        "contractor"
    ],
    "wof:name":"Landmark Builders Inc",
    "wof:placetype":"venue"
},
  "geometry": {"coordinates":[-76.20346499999999,40.198491],"type":"Point"}
}