{
  "type": "Feature",
  "properties": {
    "iso:country":"US",
    "sg:address":"3605 Vartan Way Ste 301",
    "sg:city":"Harrisburg",
    "sg:classifiers":[
        {
            "category":"Real Estate",
            "subcategory":"Architect",
            "type":"Services"
        }
    ],
    "sg:phone":"+1 717 221 1188",
    "sg:postcode":"17110",
    "sg:province":"PA",
    "wof:name":"Millman Technical Services Inc",
    "wof:placetype":"venue"
},
  "geometry": {"coordinates":[-76.853798,40.317001],"type":"Point"}
}