{
  "type": "Feature",
  "properties": {
    "iso:country":"US",
    "sg:address":"2030 N 63rd St",
    "sg:city":"Philadelphia",
    "sg:classifiers":[
        {
            "category":"Professional",
            "type":"Services"
        }
    ],
    "sg:phone":"+1   ",
    "sg:postcode":"19151",
    "sg:province":"PA",
    "wof:name":"Scrub Foundation",
    "wof:placetype":"venue"
},
  "geometry": {"coordinates":[-75.248476,39.986733],"type":"Point"}
}