{
  "type": "Feature",
  "properties": {
    "iso:country":"US",
    "sg:address":"2370 Forster St",
    "sg:city":"Harrisburg",
    "sg:classifiers":[
        {
            "category":"Building & Trades",
            "subcategory":"Construction",
            "type":"Services"
        }
    ],
    "sg:phone":"+1   ",
    "sg:postcode":"17103",
    "sg:province":"PA",
    "sg:tags":[
        "contractor"
    ],
    "wof:name":"Mateers Cstm Cbnets Cntertops",
    "wof:placetype":"venue"
},
  "geometry": {"coordinates":[-76.85469500000001,40.27687],"type":"Point"}
}