{
  "type": "Feature",
  "properties": {
    "iso:country":"US",
    "sg:address":"512 Market St",
    "sg:city":"Johnsonburg",
    "sg:classifiers":[
        {
            "category":"Restaurant",
            "type":"Food & Drink"
        }
    ],
    "sg:phone":"+1 814 965 5318",
    "sg:postcode":"15845",
    "sg:province":"PA",
    "wof:name":"Allegretto's",
    "wof:placetype":"venue"
},
  "geometry": {"coordinates":[-78.682785,41.495873],"type":"Point"}
}