{
  "type": "Feature",
  "properties": {
    "addr:full":"370 Hetrick Rd Beavertown PA 17813",
    "addr:housenumber":"370",
    "addr:postcode":"17813",
    "addr:street":"Hetrick Rd",
    "iso:country":"US",
    "sg:address":"370 Hetrick Rd",
    "sg:city":"Beavertown",
    "sg:classifiers":[
        {
            "category":"Personal",
            "type":"Services"
        },
        {
            "category":"Professional",
            "subcategory":"Art Services",
            "type":"Services"
        }
    ],
    "sg:phone":"+1 570 765 4030",
    "sg:postcode":"17813",
    "sg:province":"PA",
    "sg:tags":[
        "photography",
        "videography",
        "wedding"
    ],
    "wof:name":"Rickie B Photography",
    "wof:placetype":"venue"
},
  "geometry": {"coordinates":[-77.17538999999999,40.761304],"type":"Point"}
}