{
  "type": "Feature",
  "properties": {
    "addr:full":"333 Summit Ave Conshohocken PA 19428",
    "addr:housenumber":"333",
    "addr:postcode":"19428",
    "addr:street":"Summit Ave",
    "iso:country":"US",
    "sg:address":"333 Summit Ave",
    "sg:city":"Conshohocken",
    "sg:classifiers":[
        {
            "category":"Building & Trades",
            "subcategory":"Construction",
            "type":"Services"
        }
    ],
    "sg:phone":"+1   ",
    "sg:postcode":"19428",
    "sg:province":"PA",
    "sg:tags":[
        "home",
        "contractor",
        "general",
        "residential"
    ],
    "wof:name":"David J Pizzico Construction",
    "wof:placetype":"venue"
},
  "geometry": {"coordinates":[-75.28797400000001,40.08167],"type":"Point"}
}