{
  "type": "Feature",
  "properties": {
    "addr:full":"45 McMurray Rd Pittsburgh PA 15241",
    "addr:housenumber":"45",
    "addr:postcode":"15241",
    "addr:street":"Mcmurray Rd",
    "iso:country":"US",
    "sg:address":"45 McMurray Rd",
    "sg:city":"Pittsburgh",
    "sg:classifiers":[
        {
            "category":"Health Services",
            "subcategory":"Nursing And Care Facility",
            "type":"Services"
        }
    ],
    "sg:phone":"+1   ",
    "sg:postcode":"15241",
    "sg:province":"PA",
    "sg:tags":[
        "living",
        "assisted"
    ],
    "wof:name":"Grand Rsdnce At Upper St Clair",
    "wof:placetype":"venue"
},
  "geometry": {"coordinates":[-80.06561600000001,40.326197],"type":"Point"}
}