{
  "type": "Feature",
  "properties": {
    "iso:country":"US",
    "sg:address":"5715 Ashland Ave",
    "sg:city":"Philadelphia",
    "sg:classifiers":[
        {
            "category":"Shopping",
            "subcategory":"Computers & Home Electronics",
            "type":"Retail Goods"
        }
    ],
    "sg:phone":"+1   ",
    "sg:postcode":"19143",
    "sg:province":"PA",
    "wof:name":"Universal Network Inc",
    "wof:placetype":"venue"
},
  "geometry": {"coordinates":[-75.23705099999999,39.943413],"type":"Point"}
}