{
  "type": "Feature",
  "properties": {
    "iso:country":"US",
    "sg:address":"1940 Market St",
    "sg:city":"Camp Hill",
    "sg:classifiers":[
        {
            "category":"Health Services",
            "subcategory":"Podiatrist",
            "type":"Services"
        }
    ],
    "sg:phone":"+1 717 761 8085",
    "sg:postcode":"17011",
    "sg:province":"PA",
    "wof:name":"Foot Care Ctr",
    "wof:placetype":"venue"
},
  "geometry": {"coordinates":[-76.916865,40.240073],"type":"Point"}
}