{
  "type": "Feature",
  "properties": {
    "iso:country":"US",
    "sg:address":"150 Center Ave",
    "sg:city":"Burgettstown",
    "sg:classifiers":[
        {
            "category":"Freight",
            "type":"Transportation"
        }
    ],
    "sg:phone":"+1 724 947 9000",
    "sg:postcode":"15021",
    "sg:province":"PA",
    "sg:tags":[
        "special"
    ],
    "wof:name":"Star Lake Self Storage",
    "wof:placetype":"venue"
},
  "geometry": {"coordinates":[-80.389517,40.384104],"type":"Point"}
}