{
  "type": "Feature",
  "properties": {
    "iso:country":"US",
    "sg:address":"341 E 2nd Ave",
    "sg:city":"Williamsport",
    "sg:classifiers":[
        {
            "category":"Social Services",
            "subcategory":"Child Care",
            "type":"Services"
        }
    ],
    "sg:phone":"+1   ",
    "sg:postcode":"17702",
    "sg:province":"PA",
    "sg:tags":[
        "day"
    ],
    "wof:name":"Dell Sylvan Nursery",
    "wof:placetype":"venue"
},
  "geometry": {"coordinates":[-76.99239300000001,41.236593],"type":"Point"}
}