{
  "type": "Feature",
  "properties": {
    "iso:country":"US",
    "sg:address":"1883 Whiteford Rd",
    "sg:city":"York",
    "sg:classifiers":[
        {
            "category":"Shopping",
            "type":"Retail Goods"
        }
    ],
    "sg:phone":"+1   ",
    "sg:postcode":"17402",
    "sg:province":"PA",
    "sg:tags":[
        "merchandise"
    ],
    "wof:name":"Fox Pool Corporation",
    "wof:placetype":"venue"
},
  "geometry": {"coordinates":[-76.687325,39.983128],"type":"Point"}
}