{
  "type": "Feature",
  "properties": {
    "iso:country":"US",
    "sg:address":"2340 Mount Vernon Ave",
    "sg:city":"Export",
    "sg:classifiers":[
        {
            "category":"Organizations",
            "subcategory":"Non-profit Organization",
            "type":"Services"
        }
    ],
    "sg:phone":"+1   ",
    "sg:postcode":"15632",
    "sg:province":"PA",
    "sg:tags":[
        "social"
    ],
    "wof:name":"Daughters of Nile",
    "wof:placetype":"venue"
},
  "geometry": {"coordinates":[-79.635465,40.401643],"type":"Point"}
}