{
  "type": "Feature",
  "properties": {
    "iso:country":"US",
    "sg:address":"156 Old Leacock Rd",
    "sg:city":"Gordonville",
    "sg:classifiers":[
        {
            "category":"Food & Beverages",
            "subcategory":"Bakery",
            "type":"Retail Goods"
        }
    ],
    "sg:phone":"+1   ",
    "sg:postcode":"17529",
    "sg:province":"PA",
    "wof:name":"Taste of Home Bake Shop Inc",
    "wof:placetype":"venue"
},
  "geometry": {"coordinates":[-76.132761,40.021558],"type":"Point"}
}