{
  "type": "Feature",
  "properties": {
    "addr:full":"836 Brandywine Rd Downingtown PA 19335",
    "addr:housenumber":"836",
    "addr:postcode":"19335",
    "addr:street":"Brandywine Rd",
    "iso:country":"US",
    "sg:address":"836 Brandywine Rd",
    "sg:city":"Downingtown",
    "sg:classifiers":[
        {
            "category":"Wholesale",
            "subcategory":"Durable Goods & Equipment",
            "type":"Manufacturing & Wholesale Goods"
        }
    ],
    "sg:phone":"+1 610 269 4436",
    "sg:postcode":"19335",
    "sg:province":"PA",
    "sg:tags":[
        "representative",
        "manufacturer"
    ],
    "wof:name":"Donovan Associates",
    "wof:placetype":"venue"
},
  "geometry": {"coordinates":[-75.657404,39.994273],"type":"Point"}
}