{
  "type": "Feature",
  "properties": {
    "addr:full":"118 4th St Shoemakersville PA 19555",
    "addr:housenumber":"118",
    "addr:postcode":"19555",
    "addr:street":"4Th St",
    "iso:country":"US",
    "sg:address":"118 4th St",
    "sg:city":"Shoemakersville",
    "sg:classifiers":[
        {
            "category":"Wholesale",
            "subcategory":"Furniture",
            "type":"Manufacturing & Wholesale Goods"
        }
    ],
    "sg:phone":"+1   ",
    "sg:postcode":"19555",
    "sg:province":"PA",
    "wof:name":"Buy-Rite Equipment Co Inc",
    "wof:placetype":"venue"
},
  "geometry": {"coordinates":[-75.967626,40.498896],"type":"Point"}
}