{
  "type": "Feature",
  "properties": {
    "iso:country":"US",
    "sg:address":"4 Church Rd",
    "sg:city":"Tunkhannock",
    "sg:classifiers":[
        {
            "category":"Building & Trades",
            "subcategory":"Landscaping Services",
            "type":"Services"
        }
    ],
    "sg:phone":"+1 570 836 3595",
    "sg:postcode":"18657",
    "sg:province":"PA",
    "sg:tags":[
        "landscape",
        "supply"
    ],
    "wof:name":"Creekside Gardens",
    "wof:placetype":"venue"
},
  "geometry": {"coordinates":[-75.962338,41.515765],"type":"Point"}
}