{
  "type": "Feature",
  "properties": {
    "iso:country":"US",
    "sg:address":"347 Sweet Arrow Lake Rd",
    "sg:city":"Pine Grove",
    "sg:classifiers":[
        {
            "category":"Organizations",
            "subcategory":"Religious Organization",
            "type":"Services"
        }
    ],
    "sg:phone":"+1 570 345 4962",
    "sg:postcode":"17963",
    "sg:province":"PA",
    "sg:tags":[
        "church"
    ],
    "wof:name":"Schuylkill Church Of Brethren",
    "wof:placetype":"venue"
},
  "geometry": {"coordinates":[-76.374748,40.57154],"type":"Point"}
}