{
  "type": "Feature",
  "properties": {
    "iso:country":"US",
    "sg:address":"80 Cross Roads Blvd",
    "sg:city":"Coalport",
    "sg:classifiers":[
        {
            "category":"Personal",
            "subcategory":"Beauty Salon",
            "type":"Services"
        }
    ],
    "sg:phone":"+1 814 687 4372",
    "sg:postcode":"16627",
    "sg:province":"PA",
    "wof:name":"Brenda Beers Beauty Shop",
    "wof:placetype":"venue"
},
  "geometry": {"coordinates":[-78.469542,40.74393],"type":"Point"}
}