{
  "type": "Feature",
  "properties": {
    "iso:country":"US",
    "sg:address":"2944 Laird Ave",
    "sg:city":"Erie",
    "sg:classifiers":[
        {
            "category":"Retail",
            "subcategory":"Repair Shop",
            "type":"Services"
        }
    ],
    "sg:phone":"+1 814 833 8863",
    "sg:postcode":"16505",
    "sg:province":"PA",
    "sg:tags":[
        "repairing",
        "organs"
    ],
    "wof:name":"Fischer Pipe Organ Sales & Svc",
    "wof:placetype":"venue"
},
  "geometry": {"coordinates":[-80.149047,42.100843],"type":"Point"}
}