{
  "type": "Feature",
  "properties": {
    "addr:full":"501 Lowries Run Rd Pittsburgh PA 15237",
    "addr:housenumber":"501",
    "addr:postcode":"15237",
    "addr:street":"Lowries Run Rd",
    "iso:country":"US",
    "sg:address":"501 Lowries Run Rd",
    "sg:city":"Pittsburgh",
    "sg:classifiers":[
        {
            "category":"Retail",
            "subcategory":"Car Wash",
            "type":"Services"
        }
    ],
    "sg:phone":"+1 412 364 2200",
    "sg:postcode":"15237",
    "sg:province":"PA",
    "sg:tags":[
        "polishing",
        "washing"
    ],
    "wof:name":"Milo C Ritton Inc",
    "wof:placetype":"venue"
},
  "geometry": {"coordinates":[-80.056229,40.534214],"type":"Point"}
}