{
  "type": "Feature",
  "properties": {
    "iso:country":"US",
    "sg:address":"2353 Jalice Cir",
    "sg:city":"State College",
    "sg:classifiers":[
        {
            "category":"Personal",
            "subcategory":"Beauty Salon",
            "type":"Services"
        }
    ],
    "sg:phone":"+1   ",
    "sg:postcode":"16801",
    "sg:province":"PA",
    "sg:tags":[
        "shop"
    ],
    "wof:name":"Audrey Beauty Salon",
    "wof:placetype":"venue"
},
  "geometry": {"coordinates":[-77.807016,40.821552],"type":"Point"}
}