{
  "type": "Feature",
  "properties": {
    "iso:country":"US",
    "sg:address":"2043 Webster Ave",
    "sg:city":"Pittsburgh",
    "sg:classifiers":[
        {
            "category":"Organizations",
            "subcategory":"Religious Organization",
            "type":"Services"
        }
    ],
    "sg:phone":"+1 412 261 4950",
    "sg:postcode":"15219",
    "sg:province":"PA",
    "sg:tags":[
        "church"
    ],
    "wof:name":"Zion Hill Full Gospel Bapt Chr",
    "wof:placetype":"venue"
},
  "geometry": {"coordinates":[-79.98038,40.446367],"type":"Point"}
}