{
  "type": "Feature",
  "properties": {
    "addr:full":"24 Livingston St Hanover Twp PA 18706",
    "addr:housenumber":"24",
    "addr:postcode":"18706",
    "addr:street":"Livingston St",
    "iso:country":"US",
    "sg:address":"24 Livingston St",
    "sg:city":"Hanover Twp",
    "sg:classifiers":[
        {
            "category":"Shopping",
            "subcategory":"Hobbies, Toys, & Games",
            "type":"Retail Goods"
        }
    ],
    "sg:phone":"+1 570 823 1888",
    "sg:postcode":"18706",
    "sg:province":"PA",
    "sg:tags":[
        "model",
        "supply"
    ],
    "wof:name":"Jacks Uncle Train Shop",
    "wof:placetype":"venue"
},
  "geometry": {"coordinates":[-75.945857,41.223455],"type":"Point"}
}