{
  "type": "Feature",
  "properties": {
    "iso:country":"US",
    "sg:address":"2901 Stewart Dr",
    "sg:city":"State College",
    "sg:classifiers":[
        {
            "category":"Freight",
            "type":"Transportation"
        }
    ],
    "sg:phone":"+1 814 234 4550",
    "sg:postcode":"16801",
    "sg:province":"PA",
    "sg:tags":[
        "trucking"
    ],
    "wof:name":"Hipp Trucking",
    "wof:placetype":"venue"
},
  "geometry": {"coordinates":[-77.796477,40.832321],"type":"Point"}
}