{
  "type": "Feature",
  "properties": {
    "iso:country":"US",
    "sg:address":"2001 Market St",
    "sg:city":"Philadelphia",
    "sg:classifiers":[
        {
            "category":"Professional",
            "subcategory":"Printing & Photocopies",
            "type":"Services"
        }
    ],
    "sg:phone":"+1 215 556 1517",
    "sg:postcode":"19103",
    "sg:province":"PA",
    "wof:name":"Kinko's",
    "wof:placetype":"venue"
},
  "geometry": {"coordinates":[-75.172997,39.953602],"type":"Point"}
}