{
  "type": "Feature",
  "properties": {
    "iso:country":"US",
    "sg:address":"496 Brights Ln",
    "sg:city":"Penllyn",
    "sg:classifiers":[
        {
            "category":"Health Services",
            "subcategory":"Doctor",
            "type":"Services"
        }
    ],
    "sg:phone":"+1 215 628 3396",
    "sg:postcode":"19422",
    "sg:province":"PA",
    "sg:tags":[
        "dentist"
    ],
    "wof:name":"Martin Oberman DDS",
    "wof:placetype":"venue"
},
  "geometry": {"coordinates":[-75.237067,40.169094],"type":"Point"}
}