{
  "type": "Feature",
  "properties": {
    "addr:full":"POB 82670 Pittsburgh PA 15218",
    "addr:postcode":"82670;15218",
    "iso:country":"US",
    "sg:address":"POB 82670",
    "sg:city":"Pittsburgh",
    "sg:classifiers":[
        {
            "category":"Professional",
            "subcategory":"Research",
            "type":"Services"
        }
    ],
    "sg:phone":"+1 412 571 2622",
    "sg:postcode":"15218",
    "sg:province":"PA",
    "sg:website":"http://www.thermaltherapeutics.com",
    "wof:name":"ThermalTherapeuticSystems",
    "wof:placetype":"venue"
},
  "geometry": {"coordinates":[-79.889803,40.42361],"type":"Point"}
}