{
  "type": "Feature",
  "properties": {
    "iso:country":"US",
    "sg:address":"783 Pine Valley Dr",
    "sg:city":"Pittsburgh",
    "sg:classifiers":[
        {
            "category":"Health Services",
            "subcategory":"Chiropractor",
            "type":"Services"
        },
        {
            "category":"Social Services",
            "subcategory":"Job Training",
            "type":"Services"
        }
    ],
    "sg:phone":"+1 724 733 2225",
    "sg:postcode":"15239",
    "sg:province":"PA",
    "sg:tags":[
        "rehabilitation"
    ],
    "wof:name":"Pine Valley Chiropractic Inc",
    "wof:placetype":"venue"
},
  "geometry": {"coordinates":[-79.711243,40.455285],"type":"Point"}
}