{
  "type": "Feature",
  "properties": {
    "iso:country":"US",
    "sg:address":"75 W 9th St",
    "sg:city":"Chester",
    "sg:classifiers":[
        {
            "category":"Autos & Motor Vehicles",
            "subcategory":"Automobile Sales",
            "type":"Retail Goods"
        }
    ],
    "sg:phone":"+1   ",
    "sg:postcode":"19013",
    "sg:province":"PA",
    "sg:tags":[
        "heavy",
        "duty",
        "class",
        "8"
    ],
    "wof:name":"Liberty Kenworth Truck Sales",
    "wof:placetype":"venue"
},
  "geometry": {"coordinates":[-75.36391,39.85137],"type":"Point"}
}