{
  "type": "Feature",
  "properties": {
    "iso:country":"US",
    "sg:address":"1212 Edgemont Rd",
    "sg:city":"Harrisburg",
    "sg:classifiers":[
        {
            "category":"Organizations",
            "subcategory":"Religious Organization",
            "type":"Services"
        }
    ],
    "sg:phone":"+1 717 233 4247",
    "sg:postcode":"17109",
    "sg:province":"PA",
    "sg:tags":[
        "church"
    ],
    "sg:website":"www.churchofgod.cc",
    "wof:name":"Faith Chapel Church of God In Christ",
    "wof:placetype":"venue"
},
  "geometry": {"coordinates":[-76.85610200000001,40.2831],"type":"Point"}
}