{
  "type": "Feature",
  "properties": {
    "iso:country":"US",
    "sg:address":"1349 Chester Pike",
    "sg:city":"Sharon Hill",
    "sg:classifiers":[
        {
            "category":"Health Services",
            "subcategory":"Chiropractor",
            "type":"Services"
        }
    ],
    "sg:phone":"+1 610 461 5222",
    "sg:postcode":"19079",
    "sg:province":"PA",
    "wof:name":"A-100 Percent Health Feinberg",
    "wof:placetype":"venue"
},
  "geometry": {"coordinates":[-75.27737999999999,39.906538],"type":"Point"}
}