{
  "type": "Feature",
  "properties": {
    "iso:country":"US",
    "sg:address":"1028 Fawcett Ave",
    "sg:city":"Mc Keesport",
    "sg:classifiers":[
        {
            "category":"Organizations",
            "subcategory":"Religious Organization",
            "type":"Services"
        }
    ],
    "sg:phone":"+1   ",
    "sg:postcode":"15132",
    "sg:province":"PA",
    "wof:name":"First Church of Christ",
    "wof:placetype":"venue"
},
  "geometry": {"coordinates":[-79.826241,40.3529],"type":"Point"}
}