{
  "type": "Feature",
  "properties": {
    "iso:country":"US",
    "sg:address":"301 S Woodbine Ave",
    "sg:city":"Narberth",
    "sg:classifiers":[
        {
            "category":"Utilities",
            "subcategory":"Telephone",
            "type":"Services"
        }
    ],
    "sg:phone":"+1   ",
    "sg:postcode":"19072",
    "sg:province":"PA",
    "sg:tags":[
        "web"
    ],
    "wof:name":"Eminent Domains Inc",
    "wof:placetype":"venue"
},
  "geometry": {"coordinates":[-75.255217,40.013481],"type":"Point"}
}