{
  "type": "Feature",
  "properties": {
    "iso:country":"US",
    "sg:address":"122 N Franklin St",
    "sg:city":"Titusville",
    "sg:classifiers":[
        {
            "category":"Health Services",
            "subcategory":"Podiatrist",
            "type":"Services"
        }
    ],
    "sg:phone":"+1 814 827 2841",
    "sg:postcode":"16354",
    "sg:province":"PA",
    "wof:name":"Timothy S Brooks DPM",
    "wof:placetype":"venue"
},
  "geometry": {"coordinates":[-79.67334099999999,41.628295],"type":"Point"}
}