{
  "type": "Feature",
  "properties": {
    "iso:country":"US",
    "sg:address":"89 Elm Ave",
    "sg:city":"Sharon",
    "sg:classifiers":[
        {
            "category":"Health Services",
            "subcategory":"Doctor",
            "type":"Services"
        }
    ],
    "sg:phone":"+1   ",
    "sg:postcode":"16146",
    "sg:province":"OH",
    "sg:tags":[
        "medical"
    ],
    "wof:name":"Kevin Hicks MD",
    "wof:placetype":"venue"
},
  "geometry": {"coordinates":[-80.497938,41.233155],"type":"Point"}
}