{
  "type": "Feature",
  "properties": {
    "iso:country":"US",
    "sg:address":"521 Avondale Rd",
    "sg:city":"Wallingford",
    "sg:classifiers":[
        {
            "category":"Museum",
            "type":"Entertainment"
        }
    ],
    "sg:phone":"+1 610 566 6365",
    "sg:postcode":"19086",
    "sg:province":"PA",
    "sg:tags":[
        "gallery"
    ],
    "wof:name":"Leiper Historic House",
    "wof:placetype":"venue"
},
  "geometry": {"coordinates":[-75.358621,39.892041],"type":"Point"}
}