{
  "type": "Feature",
  "properties": {
    "iso:country":"US",
    "sg:address":"2925 W Liberty Ave",
    "sg:city":"Pittsburgh",
    "sg:classifiers":[
        {
            "category":"Retail",
            "subcategory":"Auto Repair",
            "type":"Services"
        }
    ],
    "sg:phone":"+1 412 561 9585",
    "sg:postcode":"15216",
    "sg:province":"PA",
    "sg:tags":[
        "body",
        "shop"
    ],
    "wof:name":"Bill's Auto Service",
    "wof:placetype":"venue"
},
  "geometry": {"coordinates":[-80.03479799999999,40.394501],"type":"Point"}
}