{
  "type": "Feature",
  "properties": {
    "iso:country":"US",
    "sg:address":"308 Mill Race Ln",
    "sg:city":"Newtown",
    "sg:classifiers":[
        {
            "category":"Insurance",
            "subcategory":"Insurance Agent",
            "type":"Services"
        }
    ],
    "sg:phone":"+1   ",
    "sg:postcode":"18940",
    "sg:province":"PA",
    "wof:name":"S Kyriakodis",
    "wof:placetype":"venue"
},
  "geometry": {"coordinates":[-74.926767,40.288982],"type":"Point"}
}