{
  "type": "Feature",
  "properties": {
    "iso:country":"US",
    "sg:address":"120 Mall Blvd",
    "sg:city":"Monroeville",
    "sg:classifiers":[
        {
            "category":"Shopping",
            "subcategory":"Department Store",
            "type":"Retail Goods"
        }
    ],
    "sg:phone":"+1 412 373 3811",
    "sg:postcode":"15146",
    "sg:province":"PA",
    "wof:name":"Kmart",
    "wof:placetype":"venue"
},
  "geometry": {"coordinates":[-79.79169899999999,40.431325],"type":"Point"}
}