{
  "type": "Feature",
  "properties": {
    "iso:country":"US",
    "sg:address":"708 Payne Ave",
    "sg:city":"Erie",
    "sg:classifiers":[
        {
            "category":"Bars & Pubs",
            "type":"Food & Drink"
        }
    ],
    "sg:phone":"+1 814 456 1745",
    "sg:postcode":"16503",
    "sg:province":"PA",
    "sg:tags":[
        "tavern",
        "drinking"
    ],
    "wof:name":"Carol' Still Inc",
    "wof:placetype":"venue"
},
  "geometry": {"coordinates":[-80.054124,42.138765],"type":"Point"}
}