{
  "type": "Feature",
  "properties": {
    "iso:country":"US",
    "sg:address":"223 Miller Farm Rd",
    "sg:city":"Uniontown",
    "sg:classifiers":[
        {
            "category":"Wholesale",
            "subcategory":"Scrap",
            "type":"Manufacturing & Wholesale Goods"
        }
    ],
    "sg:phone":"+1 724 245 7475",
    "sg:postcode":"15401",
    "sg:province":"PA",
    "sg:tags":[
        "metal",
        "iron"
    ],
    "wof:name":"Edward Fields & Co",
    "wof:placetype":"venue"
},
  "geometry": {"coordinates":[-79.802693,39.930203],"type":"Point"}
}