{
  "type": "Feature",
  "properties": {
    "iso:country":"US",
    "sg:address":"66 Pius St",
    "sg:city":"Pittsburgh",
    "sg:classifiers":[
        {
            "category":"Building & Trades",
            "subcategory":"Construction",
            "type":"Services"
        }
    ],
    "sg:phone":"+1   ",
    "sg:postcode":"15203",
    "sg:province":"PA",
    "sg:tags":[
        "specializing",
        "condominium",
        "contractor"
    ],
    "wof:name":"Pius Street Development Corp",
    "wof:placetype":"venue"
},
  "geometry": {"coordinates":[-79.98431600000001,40.424738],"type":"Point"}
}