{
  "type": "Feature",
  "properties": {
    "iso:country":"US",
    "sg:address":"10 Heather Hill",
    "sg:city":"Danville",
    "sg:classifiers":[
        {
            "category":"Manufacturing",
            "subcategory":"Printing",
            "type":"Manufacturing & Wholesale Goods"
        }
    ],
    "sg:phone":"+1   ",
    "sg:postcode":"17821",
    "sg:province":"PA",
    "sg:tags":[
        "newspaper"
    ],
    "wof:name":"Danville News The",
    "wof:placetype":"venue"
},
  "geometry": {"coordinates":[-76.568595,40.973354],"type":"Point"}
}