{
  "type": "Feature",
  "properties": {
    "iso:country":"US",
    "sg:address":"2533 Salmon St",
    "sg:city":"Philadelphia",
    "sg:classifiers":[
        {
            "category":"Recreation",
            "type":"Entertainment"
        }
    ],
    "sg:phone":"+1 215 423 7990",
    "sg:postcode":"19125",
    "sg:province":"PA",
    "sg:tags":[
        "club",
        "membership",
        "drinking"
    ],
    "wof:name":"Tribecca",
    "wof:placetype":"venue"
},
  "geometry": {"coordinates":[-75.11622800000001,39.975969],"type":"Point"}
}