{
  "type": "Feature",
  "properties": {
    "iso:country":"US",
    "sg:address":"1105 W Main St",
    "sg:city":"Somerset",
    "sg:classifiers":[
        {
            "category":"Banks & Credit Unions",
            "subcategory":"Bank",
            "type":"Services"
        }
    ],
    "sg:phone":"+1 814 443 6189",
    "sg:postcode":"15501",
    "sg:province":"PA",
    "sg:tags":[
        "loan"
    ],
    "wof:name":"Freedom Consumer Discount Co",
    "wof:placetype":"venue"
},
  "geometry": {"coordinates":[-79.09900500000001,40.009252],"type":"Point"}
}