{
  "type": "Feature",
  "properties": {
    "iso:country":"US",
    "sg:address":"1135 York Rd",
    "sg:city":"Willow Grove",
    "sg:classifiers":[
        {
            "category":"Ice Cream",
            "type":"Food & Drink"
        }
    ],
    "sg:menulink":"http://www.allmenus.com/pa/upper-moreland/234996-ritas-ice-custard-happiness/menu/",
    "sg:phone":"+1 215 659 1047",
    "sg:postcode":"19090",
    "sg:province":"PA",
    "sg:tags":[
        "american"
    ],
    "wof:name":"Rita's Ice Custard Happiness",
    "wof:placetype":"venue"
},
  "geometry": {"coordinates":[-75.112174,40.157579],"type":"Point"}
}