{
  "type": "Feature",
  "properties": {
    "addr:full":"715 Walnut St Easton PA 18042",
    "addr:housenumber":"715",
    "addr:postcode":"18042",
    "addr:street":"Walnut St",
    "iso:country":"US",
    "sg:address":"715 Walnut St",
    "sg:city":"Easton",
    "sg:classifiers":[
        {
            "category":"Autos & Motor Vehicles",
            "subcategory":"Auto Supplies",
            "type":"Retail Goods"
        },
        {
            "category":"Retail",
            "subcategory":"Auto Repair",
            "type":"Services"
        }
    ],
    "sg:phone":"+1 610 559 1750",
    "sg:postcode":"18042",
    "sg:province":"PA",
    "sg:tags":[
        "classic",
        "automobile",
        "accessory",
        "part",
        "restoration-antique"
    ],
    "sg:website":"http://www.yankeetrading.com",
    "wof:name":"Yankee Auto Works",
    "wof:placetype":"venue"
},
  "geometry": {"coordinates":[-75.218468,40.68816],"type":"Point"}
}