{
  "type": "Feature",
  "properties": {
    "addr:full":"3540 State Rte 151 Aliquippa PA 15001",
    "addr:housenumber":"3540",
    "addr:postcode":"15001",
    "addr:street":"State Rte 151",
    "iso:country":"US",
    "sg:address":"3540 State Rte 151",
    "sg:city":"Aliquippa",
    "sg:classifiers":[
        {
            "category":"Utilities",
            "subcategory":"Fuel Oil & Lpg",
            "type":"Services"
        }
    ],
    "sg:phone":"+1   ",
    "sg:postcode":"15001",
    "sg:province":"PA",
    "sg:tags":[
        "liquefied",
        "gas",
        "petroleum"
    ],
    "wof:name":"AmeriGas",
    "wof:placetype":"venue"
},
  "geometry": {"coordinates":[-80.325013,40.547438],"type":"Point"}
}