{
  "type": "Feature",
  "properties": {
    "addr:full":"300 E Lancaster Ave Devon PA 19333",
    "addr:housenumber":"300",
    "addr:postcode":"19333",
    "addr:street":"E Lancaster Ave",
    "iso:country":"US",
    "sg:address":"300 E Lancaster Ave",
    "sg:city":"Devon",
    "sg:classifiers":[
        {
            "category":"Shopping",
            "type":"Retail Goods"
        },
        {
            "category":"Professional",
            "subcategory":"Business Services",
            "type":"Services"
        }
    ],
    "sg:phone":"+1 610 293 0660",
    "sg:postcode":"19333",
    "sg:province":"PA",
    "sg:tags":[
        "gift",
        "specialty",
        "award",
        "item",
        "embroidery",
        "sportswear"
    ],
    "sg:website":"www.giftpa.com",
    "wof:name":"Pennsylvania Gifts & Awards",
    "wof:placetype":"venue"
},
  "geometry": {"coordinates":[-75.42859799999999,40.044439],"type":"Point"}
}