{
  "type": "Feature",
  "properties": {
    "addr:full":"1350 N River Rd Granville PA 17029",
    "addr:housenumber":"1350",
    "addr:postcode":"17029",
    "addr:street":"N River Rd",
    "iso:country":"US",
    "sg:address":"1350 N River Rd",
    "sg:city":"Granville",
    "sg:classifiers":[
        {
            "category":"Autos & Motor Vehicles",
            "subcategory":"Boat Sales",
            "type":"Retail Goods"
        },
        {
            "category":"Retail",
            "subcategory":"Repair Shop",
            "type":"Services"
        }
    ],
    "sg:phone":"+1 717 248 1200",
    "sg:postcode":"17029",
    "sg:province":"PA",
    "sg:tags":[
        "equipment",
        "upholsterer",
        "supply"
    ],
    "wof:name":"Johnson's Upolstery",
    "wof:placetype":"venue"
},
  "geometry": {"coordinates":[-77.62412999999999,40.555014],"type":"Point"}
}