{
  "type": "Feature",
  "properties": {
    "iso:country":"US",
    "sg:address":"5020 Old York Rd",
    "sg:city":"Philadelphia",
    "sg:classifiers":[
        {
            "category":"Shopping",
            "subcategory":"Crafts & Fabrics",
            "type":"Retail Goods"
        }
    ],
    "sg:phone":"+1 215 329 7011",
    "sg:postcode":"19141",
    "sg:province":"PA",
    "sg:tags":[
        "store"
    ],
    "wof:name":"Ngoci African Fashions & Fabrics",
    "wof:placetype":"venue"
},
  "geometry": {"coordinates":[-75.14619,40.029855],"type":"Point"}
}