{
  "type": "Feature",
  "properties": {
    "iso:country":"US",
    "sg:address":"99 Sharon Ave",
    "sg:city":"Darby",
    "sg:classifiers":[
        {
            "category":"Professional",
            "type":"Services"
        },
        {
            "category":"Shopping",
            "type":"Retail Goods"
        }
    ],
    "sg:phone":"+1 610 583 3527",
    "sg:postcode":"19023",
    "sg:province":"PA",
    "sg:tags":[
        "wheel",
        "supply",
        "scooter",
        "equipment",
        "chair",
        "medical"
    ],
    "wof:name":"Reliant Care",
    "wof:placetype":"venue"
},
  "geometry": {"coordinates":[-75.275673,39.911129],"type":"Point"}
}