{
  "type": "Feature",
  "properties": {
    "addr:full":"1736 Sweet Arrow Lake Rd Pottsville PA 17901",
    "addr:housenumber":"1736",
    "addr:postcode":"17901",
    "addr:street":"Sweet Arrow Lake Rd",
    "iso:country":"US",
    "sg:address":"1736 Sweet Arrow Lake Rd",
    "sg:city":"Pottsville",
    "sg:classifiers":[
        {
            "category":"Retail",
            "subcategory":"Repair Shop",
            "type":"Services"
        }
    ],
    "sg:phone":"+1 570 739 2500",
    "sg:postcode":"17901",
    "sg:province":"PA",
    "sg:tags":[
        "lock",
        "locksmith"
    ],
    "wof:name":"Dwayne's Locksmith Shop",
    "wof:placetype":"venue"
},
  "geometry": {"coordinates":[-76.21947900000001,40.622095],"type":"Point"}
}