{
  "type": "Feature",
  "properties": {
    "iso:country":"US",
    "sg:address":"2834 Hunterstown Hampton Rd",
    "sg:city":"New Oxford",
    "sg:classifiers":[
        {
            "category":"Professional",
            "type":"Services"
        }
    ],
    "sg:phone":"+1   ",
    "sg:postcode":"17350",
    "sg:province":"PA",
    "wof:name":"Samuel Starner",
    "wof:placetype":"venue"
},
  "geometry": {"coordinates":[-77.07418699999999,39.915829],"type":"Point"}
}