{
  "type": "Feature",
  "properties": {
    "addr:full":"109 N 3rd St Clearfield PA 16830",
    "addr:housenumber":"109",
    "addr:postcode":"16830",
    "addr:street":"N 3Rd St",
    "iso:country":"US",
    "sg:address":"109 N 3rd St",
    "sg:city":"Clearfield",
    "sg:classifiers":[
        {
            "category":"Shopping",
            "subcategory":"Florist",
            "type":"Retail Goods"
        }
    ],
    "sg:phone":"+1 814 765 4334",
    "sg:postcode":"16830",
    "sg:province":"PA",
    "wof:name":"Clearfield Florists",
    "wof:placetype":"venue"
},
  "geometry": {"coordinates":[-78.43625,41.023758],"type":"Point"}
}