{
  "type": "Feature",
  "properties": {
    "addr:full":"3 Harry Ln Oakdale PA 15021",
    "addr:housenumber":"3",
    "addr:postcode":"15021",
    "addr:street":"Harry Ln",
    "iso:country":"US",
    "sg:address":"3 Harry Ln",
    "sg:city":"Oakdale",
    "sg:classifiers":[
        {
            "category":"Government",
            "subcategory":"Office",
            "type":"Public Place"
        }
    ],
    "sg:phone":"+1   ",
    "sg:postcode":"15021",
    "sg:province":"PA",
    "sg:tags":[
        "national",
        "security"
    ],
    "wof:name":"DSI",
    "wof:placetype":"venue"
},
  "geometry": {"coordinates":[-80.51321799999999,40.473448],"type":"Point"}
}