{
  "type": "Feature",
  "properties": {
    "iso:country":"US",
    "sg:address":"717 Sansom St",
    "sg:city":"Philadelphia",
    "sg:classifiers":[
        {
            "category":"Retail",
            "subcategory":"Repair Shop",
            "type":"Services"
        }
    ],
    "sg:phone":"+1 215 627 5920",
    "sg:postcode":"19106",
    "sg:province":"PA",
    "sg:tags":[
        "jewelry"
    ],
    "wof:name":"Irv Diamond",
    "wof:placetype":"venue"
},
  "geometry": {"coordinates":[-75.153869,39.948821],"type":"Point"}
}