{
  "type": "Feature",
  "properties": {
    "addr:full":"2504 Halfmoon Valley Rd Port Matilda PA 16870",
    "addr:housenumber":"2504",
    "addr:postcode":"16870",
    "addr:street":"Halfmoon Valley Rd",
    "iso:country":"US",
    "sg:address":"2504 Halfmoon Valley Rd",
    "sg:city":"Port Matilda",
    "sg:classifiers":[
        {
            "category":"Farming",
            "subcategory":"Dairy Farm",
            "type":"Manufacturing & Wholesale Goods"
        }
    ],
    "sg:phone":"+1   ",
    "sg:postcode":"16870",
    "sg:province":"PA",
    "wof:name":"Weaver Bros Farm",
    "wof:placetype":"venue"
},
  "geometry": {"coordinates":[-78.029799,40.784175],"type":"Point"}
}