{
  "type": "Feature",
  "properties": {
    "addr:full":"2101 S Beechwood St Philadelphia PA 19145",
    "addr:housenumber":"2101",
    "addr:postcode":"19145",
    "addr:street":"S Beechwood St",
    "iso:country":"US",
    "sg:address":"2101 S Beechwood St",
    "sg:city":"Philadelphia",
    "sg:classifiers":[
        {
            "category":"Banks & Credit Unions",
            "subcategory":"Financial Services",
            "type":"Services"
        }
    ],
    "sg:phone":"+1 215 468 4938",
    "sg:postcode":"19145",
    "sg:province":"PA",
    "sg:tags":[
        "cashing",
        "check"
    ],
    "sg:website":"http://www.unitedfsg.com",
    "wof:name":"United Check Cashing",
    "wof:placetype":"venue"
},
  "geometry": {"coordinates":[-75.182182,39.92598],"type":"Point"}
}