{
  "type": "Feature",
  "properties": {
    "iso:country":"US",
    "sg:address":"323 Main St",
    "sg:city":"Greenville",
    "sg:classifiers":[
        {
            "category":"Organizations",
            "subcategory":"Religious Organization",
            "type":"Services"
        }
    ],
    "sg:phone":"+1   ",
    "sg:postcode":"16125",
    "sg:province":"PA",
    "sg:tags":[
        "child",
        "day",
        "care"
    ],
    "wof:name":"Kids of The Kingdom",
    "wof:placetype":"venue"
},
  "geometry": {"coordinates":[-80.379822,41.407919],"type":"Point"}
}