{
  "type": "Feature",
  "properties": {
    "iso:country":"US",
    "sg:address":"415 Park Ave",
    "sg:city":"New Cumberland",
    "sg:classifiers":[
        {
            "category":"Insurance",
            "subcategory":"Insurance Agent",
            "type":"Services"
        }
    ],
    "sg:phone":"+1 717 774 7103",
    "sg:postcode":"17070",
    "sg:province":"PA",
    "wof:name":"Wilbur N Macivor",
    "wof:placetype":"venue"
},
  "geometry": {"coordinates":[-76.876311,40.230016],"type":"Point"}
}