{
  "type": "Feature",
  "properties": {
    "addr:full":"1920 Franklin Mills Cir Philadelphia PA 19154",
    "addr:housenumber":"1920",
    "addr:postcode":"19154",
    "addr:street":"Franklin Mills Cir",
    "iso:country":"US",
    "sg:address":"1920 Franklin Mills Cir",
    "sg:city":"Philadelphia",
    "sg:classifiers":[
        {
            "category":"Professional",
            "type":"Services"
        }
    ],
    "sg:phone":"+1 215 632 8515",
    "sg:postcode":"19154",
    "sg:province":"PA",
    "sg:tags":[
        "establishment"
    ],
    "wof:name":"K M L Intl Inc",
    "wof:placetype":"venue"
},
  "geometry": {"coordinates":[-74.964028,40.082013],"type":"Point"}
}