{
  "type": "Feature",
  "properties": {
    "iso:country":"US",
    "sg:address":"17 E Eppley Dr",
    "sg:city":"Carlisle",
    "sg:classifiers":[
        {
            "category":"Professional",
            "subcategory":"Employment Agencies",
            "type":"Services"
        }
    ],
    "sg:phone":"+1 717 245 9985",
    "sg:postcode":"17013",
    "sg:province":"PA",
    "wof:name":"Pinnacle Search Associates Inc",
    "wof:placetype":"venue"
},
  "geometry": {"coordinates":[-77.15979799999999,40.170898],"type":"Point"}
}