{
  "type": "Feature",
  "properties": {
    "iso:country":"US",
    "sg:address":"5423 Upland Way",
    "sg:city":"Philadelphia",
    "sg:classifiers":[
        {
            "category":"Social Services",
            "subcategory":"Child Care",
            "type":"Services"
        }
    ],
    "sg:phone":"+1 215 477 3305",
    "sg:postcode":"19131",
    "sg:province":"PA",
    "wof:name":"M & M Child Care",
    "wof:placetype":"venue"
},
  "geometry": {"coordinates":[-75.23305499999999,39.983348],"type":"Point"}
}