{
  "type": "Feature",
  "properties": {
    "iso:country":"US",
    "sg:address":"172 E Main St",
    "sg:city":"Brookville",
    "sg:classifiers":[
        {
            "category":"Museum",
            "type":"Entertainment"
        }
    ],
    "sg:phone":"+1 814 849 0077",
    "sg:postcode":"15825",
    "sg:province":"PA",
    "wof:name":"Jefferson County Historical",
    "wof:placetype":"venue"
},
  "geometry": {"coordinates":[-79.079041,41.160394],"type":"Point"}
}