{
  "type": "Feature",
  "properties": {
    "iso:country":"US",
    "sg:address":"507 Bethel Ave",
    "sg:city":"Aston",
    "sg:classifiers":[
        {
            "category":"Autos & Motor Vehicles",
            "subcategory":"Auto Supplies",
            "type":"Retail Goods"
        }
    ],
    "sg:phone":"+1   ",
    "sg:postcode":"19014",
    "sg:province":"PA",
    "wof:name":"Action Discount Tire Inc",
    "wof:placetype":"venue"
},
  "geometry": {"coordinates":[-75.424447,39.845115],"type":"Point"}
}