{
  "type": "Feature",
  "properties": {
    "iso:country":"US",
    "sg:address":"46 Nemeth Ln",
    "sg:city":"Clarington",
    "sg:classifiers":[
        {
            "category":"Personal",
            "subcategory":"Beauty Salon",
            "type":"Services"
        }
    ],
    "sg:phone":"+1 814 752 2869",
    "sg:postcode":"15828",
    "sg:province":"PA",
    "sg:tags":[
        "hair",
        "stylist"
    ],
    "wof:name":"Amys Family Hair Place",
    "wof:placetype":"venue"
},
  "geometry": {"coordinates":[-79.169973,41.309953],"type":"Point"}
}