{
  "type": "Feature",
  "properties": {
    "addr:full":"316 N Madison St Allentown PA 18102",
    "addr:housenumber":"316",
    "addr:postcode":"18102",
    "addr:street":"N Madison St",
    "iso:country":"US",
    "sg:address":"316 N Madison St",
    "sg:city":"Allentown",
    "sg:classifiers":[
        {
            "category":"Building & Trades",
            "subcategory":"Plumbing",
            "type":"Services"
        }
    ],
    "sg:phone":"+1   ",
    "sg:postcode":"18102",
    "sg:province":"PA",
    "sg:tags":[
        "heating",
        "air",
        "r",
        "refrigeration",
        "conditioning",
        "contractor"
    ],
    "wof:name":"DYNAMIC HEATING AIR CONDITIONI",
    "wof:placetype":"venue"
},
  "geometry": {"coordinates":[-75.487402,40.603716],"type":"Point"}
}