{
  "type": "Feature",
  "properties": {
    "addr:full":"210 Strawberry Sq Harrisburg PA 17101",
    "addr:housenumber":"210",
    "addr:postcode":"17101",
    "addr:street":"Strawberry Sq",
    "iso:country":"US",
    "sg:address":"210 Strawberry Sq",
    "sg:city":"Harrisburg",
    "sg:classifiers":[
        {
            "category":"Restaurant",
            "type":"Food & Drink"
        }
    ],
    "sg:menulink":"http://www.allmenus.com/pa/harrisburg/27361-chef-chens-express/menu/",
    "sg:phone":"+1 717 236 6888",
    "sg:postcode":"17101",
    "sg:province":"PA",
    "sg:tags":[
        "asian",
        "chinese"
    ],
    "wof:name":"Chef Chen's Express",
    "wof:placetype":"venue"
},
  "geometry": {"coordinates":[-76.881269,40.261497],"type":"Point"}
}