{
  "type": "Feature",
  "properties": {
    "iso:country":"US",
    "sg:address":"5470 Mount Pisgah Rd",
    "sg:city":"York",
    "sg:classifiers":[
        {
            "category":"Farming",
            "subcategory":"Livestock Farm",
            "type":"Manufacturing & Wholesale Goods"
        }
    ],
    "sg:phone":"+1   ",
    "sg:postcode":"17406",
    "sg:province":"PA",
    "sg:tags":[
        "breeder",
        "angus",
        "racehorse",
        "cattle"
    ],
    "wof:name":"Jonalee Farms Inc",
    "wof:placetype":"venue"
},
  "geometry": {"coordinates":[-76.568102,39.989004],"type":"Point"}
}