{
  "type": "Feature",
  "properties": {
    "iso:country":"US",
    "sg:address":"39 Adamson St",
    "sg:city":"Easton",
    "sg:classifiers":[
        {
            "category":"Manufacturing",
            "subcategory":"Glass & Minerals",
            "type":"Manufacturing & Wholesale Goods"
        }
    ],
    "sg:phone":"+1 610 559 0992",
    "sg:postcode":"18042",
    "sg:province":"PA",
    "sg:tags":[
        "pipe",
        "drain"
    ],
    "wof:name":"United Pipe & Steel Corp",
    "wof:placetype":"venue"
},
  "geometry": {"coordinates":[-75.23112399999999,40.680887],"type":"Point"}
}