{
  "type": "Feature",
  "properties": {
    "addr:full":"4900 Frankford Ave Philadelphia PA 19124",
    "addr:housenumber":"4900",
    "addr:postcode":"19124",
    "addr:street":"Frankford Ave",
    "iso:country":"US",
    "sg:address":"4900 Frankford Ave",
    "sg:city":"Philadelphia",
    "sg:classifiers":[
        {
            "category":"Health Services",
            "subcategory":"Doctor",
            "type":"Services"
        }
    ],
    "sg:phone":"+1 215 637 0440",
    "sg:postcode":"19124",
    "sg:province":"PA",
    "sg:tags":[
        "physician",
        "surgeon"
    ],
    "wof:name":"Parish Dermatology",
    "wof:placetype":"venue"
},
  "geometry": {"coordinates":[-75.07991800000001,40.020832],"type":"Point"}
}