{
  "type": "Feature",
  "properties": {
    "addr:full":"8 W High St Nazareth PA 18064",
    "addr:housenumber":"8",
    "addr:postcode":"18064",
    "addr:street":"W High St",
    "iso:country":"US",
    "sg:address":"8 W High St",
    "sg:city":"Nazareth",
    "sg:classifiers":[
        {
            "category":"Professional",
            "type":"Services"
        }
    ],
    "sg:phone":"+1   ",
    "sg:postcode":"18064",
    "sg:province":"PA",
    "wof:name":"Ollie Koers",
    "wof:placetype":"venue"
},
  "geometry": {"coordinates":[-75.312088,40.746822],"type":"Point"}
}