{
  "type": "Feature",
  "properties": {
    "iso:country":"US",
    "sg:address":"119 S 13th Street",
    "sg:city":"Philadelphia",
    "sg:classifiers":[
        {
            "category":"Ice Cream",
            "type":"Food & Drink"
        }
    ],
    "sg:phone":"+1 215 351 0900",
    "sg:postcode":"19107",
    "sg:province":"PA",
    "sg:tags":[
        "frozen",
        "yogurt"
    ],
    "sg:website":"www.capogirogelato.com",
    "wof:name":"Capogiro Gelato",
    "wof:placetype":"venue"
},
  "geometry": {"coordinates":[-75.161717,39.949888],"type":"Point"}
}