{
  "type": "Feature",
  "properties": {
    "iso:country":"US",
    "sg:address":"8 Meadowbrook Ln",
    "sg:city":"Chalfont",
    "sg:classifiers":[
        {
            "category":"Health Services",
            "subcategory":"Doctor",
            "type":"Services"
        }
    ],
    "sg:phone":"+1   ",
    "sg:postcode":"18914",
    "sg:province":"PA",
    "wof:name":"Celfon Dental Care",
    "wof:placetype":"venue"
},
  "geometry": {"coordinates":[-75.21485800000001,40.283424],"type":"Point"}
}