{
  "type": "Feature",
  "properties": {
    "addr:full":"313 W Liberty St Lancaster PA 17603",
    "addr:housenumber":"313",
    "addr:postcode":"17603",
    "addr:street":"W Liberty St",
    "iso:country":"US",
    "sg:address":"313 W Liberty St",
    "sg:city":"Lancaster",
    "sg:classifiers":[
        {
            "category":"Cinema",
            "subcategory":"Movie Theater",
            "type":"Entertainment"
        }
    ],
    "sg:phone":"+1   ",
    "sg:postcode":"17603",
    "sg:province":"PA",
    "sg:tags":[
        "motion",
        "picture"
    ],
    "wof:name":"Liberty Pl Thter Cnfrnce Cente",
    "wof:placetype":"venue"
},
  "geometry": {"coordinates":[-76.316272,40.051466],"type":"Point"}
}