{
  "type": "Feature",
  "properties": {
    "iso:country":"US",
    "sg:address":"12707 Frankstown Rd",
    "sg:city":"Pittsburgh",
    "sg:classifiers":[
        {
            "category":"Real Estate",
            "subcategory":"Developer",
            "type":"Services"
        }
    ],
    "sg:phone":"+1   ",
    "sg:postcode":"15235",
    "sg:province":"PA",
    "sg:tags":[
        "cemetery"
    ],
    "wof:name":"Mount Hope Cmtry Chpel Msoleum",
    "wof:placetype":"venue"
},
  "geometry": {"coordinates":[-79.822586,40.478856],"type":"Point"}
}