{
  "type": "Feature",
  "properties": {
    "iso:country":"US",
    "sg:address":"235 Wood St",
    "sg:city":"California",
    "sg:classifiers":[
        {
            "category":"Restaurant",
            "type":"Food & Drink"
        }
    ],
    "sg:phone":"+1 724 938 9008",
    "sg:postcode":"15419",
    "sg:province":"PA",
    "sg:tags":[
        "eating"
    ],
    "wof:name":"Just A Bite",
    "wof:placetype":"venue"
},
  "geometry": {"coordinates":[-79.889743,40.067524],"type":"Point"}
}