{
  "type": "Feature",
  "properties": {
    "iso:country":"US",
    "sg:address":"1616 E Wadsworth Ave",
    "sg:city":"Philadelphia",
    "sg:classifiers":[
        {
            "category":"Restaurant",
            "type":"Food & Drink"
        }
    ],
    "sg:phone":"+1 215 247 2300",
    "sg:postcode":"19150",
    "sg:province":"PA",
    "wof:name":"Garden Of Bilal",
    "wof:placetype":"venue"
},
  "geometry": {"coordinates":[-75.172269,40.080683],"type":"Point"}
}