{
  "type": "Feature",
  "properties": {
    "addr:full":"1222 Welsh Rd North Wales PA 19454",
    "addr:housenumber":"1222",
    "addr:postcode":"19454",
    "addr:street":"Welsh Rd",
    "iso:country":"US",
    "sg:address":"1222 Welsh Rd",
    "sg:city":"North Wales",
    "sg:classifiers":[
        {
            "category":"Food & Beverages",
            "subcategory":"Liquor & Beverages",
            "type":"Retail Goods"
        }
    ],
    "sg:phone":"+1 215 393 7900",
    "sg:postcode":"19454",
    "sg:province":"PA",
    "sg:tags":[
        "beer",
        "spirit",
        "wine"
    ],
    "wof:name":"Family Beverage Ltd",
    "wof:placetype":"venue"
},
  "geometry": {"coordinates":[-75.24720000000001,40.229198],"type":"Point"}
}