{
  "type": "Feature",
  "properties": {
    "iso:country":"US",
    "sg:address":"303 Robinson Rd",
    "sg:city":"Imperial",
    "sg:classifiers":[
        {
            "category":"Manufacturing",
            "subcategory":"Tools & Machinery",
            "type":"Manufacturing & Wholesale Goods"
        }
    ],
    "sg:phone":"+1 724 695 9000",
    "sg:postcode":"15126",
    "sg:province":"PA",
    "sg:tags":[
        "motion",
        "mfr",
        "industrial",
        "controller",
        "robot"
    ],
    "wof:name":"American Robot Corporation",
    "wof:placetype":"venue"
},
  "geometry": {"coordinates":[-80.26038699999999,40.454579],"type":"Point"}
}