{
  "type": "Feature",
  "properties": {
    "iso:country":"US",
    "sg:address":"2571 Huntingdon Pike",
    "sg:city":"Huntingdon Vly",
    "sg:classifiers":[
        {
            "category":"Building & Trades",
            "subcategory":"Construction",
            "type":"Services"
        }
    ],
    "sg:phone":"+1 215 357 0343",
    "sg:postcode":"19006",
    "sg:province":"PA",
    "sg:tags":[
        "drainage",
        "contractor"
    ],
    "wof:name":"Sam Wexler Plumbing Inc",
    "wof:placetype":"venue"
},
  "geometry": {"coordinates":[-75.064104,40.122904],"type":"Point"}
}