{
  "type": "Feature",
  "properties": {
    "addr:full":"8716 Norwin Ave Irwin PA 15642",
    "addr:housenumber":"8716",
    "addr:postcode":"15642",
    "addr:street":"Norwin Ave",
    "iso:country":"US",
    "sg:address":"8716 Norwin Ave",
    "sg:city":"Irwin",
    "sg:classifiers":[
        {
            "category":"Autos & Motor Vehicles",
            "subcategory":"Auto Supplies",
            "type":"Retail Goods"
        }
    ],
    "sg:phone":"+1 724 861 8818",
    "sg:postcode":"15642",
    "sg:province":"PA",
    "sg:tags":[
        "automotive",
        "parts",
        "automobile"
    ],
    "wof:name":"Advance Auto Parts",
    "wof:placetype":"venue"
},
  "geometry": {"coordinates":[-79.690281,40.31952],"type":"Point"}
}