{
  "type": "Feature",
  "properties": {
    "iso:country":"US",
    "sg:address":"RR 113",
    "sg:city":"Creamery",
    "sg:classifiers":[
        {
            "category":"Shopping",
            "subcategory":"Antiques",
            "type":"Retail Goods"
        }
    ],
    "sg:phone":"+1 610 409 9479",
    "sg:postcode":"19430",
    "sg:province":"PA",
    "wof:name":"Jerry's Antiques & Used Furniture",
    "wof:placetype":"venue"
},
  "geometry": {"coordinates":[-75.405098,40.229198],"type":"Point"}
}