{
  "type": "Feature",
  "properties": {
    "iso:country":"US",
    "sg:address":"1948 Halfmoon Valley Rd",
    "sg:city":"Port Matilda",
    "sg:classifiers":[
        {
            "category":"Real Estate",
            "subcategory":"Real Estate Agent",
            "type":"Services"
        }
    ],
    "sg:phone":"+1   ",
    "sg:postcode":"16870",
    "sg:province":"PA",
    "sg:tags":[
        "appraisal"
    ],
    "wof:name":"21st Century Appraisals Inc",
    "wof:placetype":"venue"
},
  "geometry": {"coordinates":[-77.997803,40.806171],"type":"Point"}
}