{
  "type": "Feature",
  "properties": {
    "addr:full":"890 Brandon Dr Chambersburg PA 17201",
    "addr:housenumber":"890",
    "addr:postcode":"17201",
    "addr:street":"Brandon Dr",
    "iso:country":"US",
    "sg:address":"890 Brandon Dr",
    "sg:city":"Chambersburg",
    "sg:classifiers":[
        {
            "category":"Manufacturing",
            "subcategory":"Furniture",
            "type":"Manufacturing & Wholesale Goods"
        }
    ],
    "sg:phone":"+1   ",
    "sg:postcode":"17201",
    "sg:province":"PA",
    "sg:tags":[
        "wooden",
        "mfg"
    ],
    "wof:name":"Rickrode Furniture",
    "wof:placetype":"venue"
},
  "geometry": {"coordinates":[-77.644126,39.915822],"type":"Point"}
}