{
  "type": "Feature",
  "properties": {
    "iso:country":"US",
    "sg:address":"140 Garrett Rd",
    "sg:city":"Upper Darby",
    "sg:classifiers":[
        {
            "category":"Shopping",
            "subcategory":"Pharmacy",
            "type":"Retail Goods"
        }
    ],
    "sg:phone":"+1 610 352 2477",
    "sg:postcode":"19082",
    "sg:province":"PA",
    "sg:tags":[
        "drugstore"
    ],
    "wof:name":"Garrett Pharmacy",
    "wof:placetype":"venue"
},
  "geometry": {"coordinates":[-75.26329800000001,39.9604],"type":"Point"}
}