{
  "type": "Feature",
  "properties": {
    "iso:country":"US",
    "sg:address":"7715 Castor Ave",
    "sg:city":"Philadelphia",
    "sg:classifiers":[
        {
            "category":"Social Services",
            "subcategory":"Job Training",
            "type":"Services"
        }
    ],
    "sg:phone":"+1 215 722 2127",
    "sg:postcode":"19152",
    "sg:province":"PA",
    "sg:tags":[
        "rehabilitation"
    ],
    "wof:name":"Rehab & Fitness",
    "wof:placetype":"venue"
},
  "geometry": {"coordinates":[-75.059693,40.058084],"type":"Point"}
}