{
  "type": "Feature",
  "properties": {
    "iso:country":"US",
    "sg:address":"100 S Independence Mall W",
    "sg:city":"Philadelphia",
    "sg:classifiers":[
        {
            "category":"Building & Trades",
            "subcategory":"Equipment Rental",
            "type":"Services"
        }
    ],
    "sg:phone":"+1 215 592 3074",
    "sg:postcode":"19106",
    "sg:province":"PA",
    "sg:tags":[
        "consultant",
        "valuation",
        "business"
    ],
    "wof:name":"Business Process Analyst",
    "wof:placetype":"venue"
},
  "geometry": {"coordinates":[-75.150719,39.949223],"type":"Point"}
}