{
  "type": "Feature",
  "properties": {
    "iso:country":"US",
    "sg:address":"447 Career Ln",
    "sg:city":"Shippenville",
    "sg:classifiers":[
        {
            "category":"Social Services",
            "subcategory":"Job Training",
            "type":"Services"
        }
    ],
    "sg:phone":"+1   ",
    "sg:postcode":"16254",
    "sg:province":"PA",
    "wof:name":"New Choices/New Options",
    "wof:placetype":"venue"
},
  "geometry": {"coordinates":[-79.429957,41.229431],"type":"Point"}
}