{
  "type": "Feature",
  "properties": {
    "iso:country":"US",
    "sg:address":"1701 W Doe Run Rd ",
    "sg:city":"Kennett Square",
    "sg:classifiers":[
        {
            "category":"Restaurant",
            "type":"Food & Drink"
        }
    ],
    "sg:menulink":"http://www.allmenus.com/pa/east-marlborough/289480-catherines-restaurant/menu/",
    "sg:phone":"+1 610 347 2227",
    "sg:postcode":"19348",
    "sg:province":"PA",
    "sg:tags":[
        "new",
        "american"
    ],
    "wof:name":"Catherine's Restaurant",
    "wof:placetype":"venue"
},
  "geometry": {"coordinates":[-75.73435499999999,39.895467],"type":"Point"}
}