{
  "type": "Feature",
  "properties": {
    "addr:full":"306 3rd St Mc Donald PA 15057",
    "addr:housenumber":"306",
    "addr:postcode":"15057",
    "addr:street":"3Rd St",
    "iso:country":"US",
    "sg:address":"306 3rd St",
    "sg:city":"Mc Donald",
    "sg:classifiers":[
        {
            "category":"Professional",
            "type":"Services"
        }
    ],
    "sg:phone":"+1   ",
    "sg:postcode":"15057",
    "sg:province":"PA",
    "wof:name":"Pro Care Systems",
    "wof:placetype":"venue"
},
  "geometry": {"coordinates":[-80.238817,40.370708],"type":"Point"}
}