{
  "type": "Feature",
  "properties": {
    "addr:full":"124 Abbey Dr Royersford PA 19468",
    "addr:housenumber":"124",
    "addr:postcode":"19468",
    "addr:street":"Abbey Dr",
    "iso:country":"US",
    "sg:address":"124 Abbey Dr",
    "sg:city":"Royersford",
    "sg:classifiers":[
        {
            "category":"Building & Trades",
            "subcategory":"Cleaning & Sanitation",
            "type":"Services"
        },
        {
            "category":"Professional",
            "subcategory":"Employment Agencies",
            "type":"Services"
        }
    ],
    "sg:phone":"+1 610 792 1654",
    "sg:postcode":"19468",
    "sg:province":"PA",
    "sg:tags":[
        "house",
        "help",
        "supply"
    ],
    "wof:name":"Reflections Housecleaning Svc",
    "wof:placetype":"venue"
},
  "geometry": {"coordinates":[-75.540768,40.199548],"type":"Point"}
}