{
  "type": "Feature",
  "properties": {
    "iso:country":"US",
    "sg:address":"5477 Durham Rd",
    "sg:city":"Pipersville",
    "sg:classifiers":[
        {
            "category":"Food & Beverages",
            "subcategory":"Bakery",
            "type":"Retail Goods"
        },
        {
            "category":"Food & Beverages",
            "subcategory":"Groceries & Convenience Stores",
            "type":"Retail Goods"
        }
    ],
    "sg:phone":"+1 215 766 0840",
    "sg:postcode":"18947",
    "sg:province":"PA",
    "sg:tags":[
        "deli",
        "baker"
    ],
    "wof:name":"Eorio's Deli and Bakery Inc",
    "wof:placetype":"venue"
},
  "geometry": {"coordinates":[-75.117599,40.398102],"type":"Point"}
}