{
  "type": "Feature",
  "properties": {
    "addr:full":"3325 Saw Mill Run Blvd Pittsburgh PA 15227",
    "addr:housenumber":"3325",
    "addr:postcode":"15227",
    "addr:street":"Saw Mill Run Blvd",
    "iso:country":"US",
    "sg:address":"3325 Saw Mill Run Blvd",
    "sg:city":"Pittsburgh",
    "sg:classifiers":[
        {
            "category":"Home & Garden",
            "subcategory":"Home Furnishings",
            "type":"Retail Goods"
        }
    ],
    "sg:phone":"+1   ",
    "sg:postcode":"15227",
    "sg:province":"PA",
    "wof:name":"Cover My Windows",
    "wof:placetype":"venue"
},
  "geometry": {"coordinates":[-79.98279100000001,40.374868],"type":"Point"}
}