{
  "type": "Feature",
  "properties": {
    "iso:country":"US",
    "sg:address":"1030 Reeves St Unit 700",
    "sg:city":"Dunmore",
    "sg:classifiers":[
        {
            "category":"Government",
            "subcategory":"Post Office",
            "type":"Public Place"
        }
    ],
    "sg:phone":"+1 570 241 8466",
    "sg:postcode":"18512",
    "sg:province":"PA",
    "sg:tags":[
        "delivery",
        "courier"
    ],
    "wof:name":"Jpi Express Couriers",
    "wof:placetype":"venue"
},
  "geometry": {"coordinates":[-75.611226,41.430937],"type":"Point"}
}