{
  "type": "Feature",
  "properties": {
    "iso:country":"US",
    "sg:address":"2300 Gettysburg Rd",
    "sg:city":"Camp Hill",
    "sg:classifiers":[
        {
            "category":"Personal",
            "subcategory":"Beauty Salon",
            "type":"Services"
        }
    ],
    "sg:phone":"+1   ",
    "sg:postcode":"17011",
    "sg:province":"PA",
    "sg:tags":[
        "shop"
    ],
    "wof:name":"Testarossa Mia Salon",
    "wof:placetype":"venue"
},
  "geometry": {"coordinates":[-76.92185000000001,40.228753],"type":"Point"}
}