{
  "type": "Feature",
  "properties": {
    "iso:country":"US",
    "sg:address":"834 California Ave",
    "sg:city":"Avalon",
    "sg:classifiers":[
        {
            "category":"Health Services",
            "subcategory":"Doctor",
            "type":"Services"
        }
    ],
    "sg:phone":"+1 412 766 5016",
    "sg:postcode":"15202",
    "sg:province":"PA",
    "sg:tags":[
        "dentist"
    ],
    "wof:name":"Richard J Dahar DDS",
    "wof:placetype":"venue"
},
  "geometry": {"coordinates":[-80.064227,40.499464],"type":"Point"}
}