{
  "type": "Feature",
  "properties": {
    "addr:full":"1530 Whitman St Williamsport PA 17701",
    "addr:housenumber":"1530",
    "addr:postcode":"17701",
    "addr:street":"Whitman St",
    "iso:country":"US",
    "sg:address":"1530 Whitman St",
    "sg:city":"Williamsport",
    "sg:classifiers":[
        {
            "category":"Education",
            "subcategory":"Special Training",
            "type":"Public Place"
        }
    ],
    "sg:phone":"+1 570 321 9000",
    "sg:postcode":"17701",
    "sg:province":"PA",
    "sg:tags":[
        "instruction",
        "driving"
    ],
    "wof:name":"Driving Clinic",
    "wof:placetype":"venue"
},
  "geometry": {"coordinates":[-76.99157099999999,41.257012],"type":"Point"}
}