{
  "type": "Feature",
  "properties": {
    "iso:country":"US",
    "sg:address":"10293 Perry Hwy Ste 3",
    "sg:city":"Wexford",
    "sg:classifiers":[
        {
            "category":"Food & Beverages",
            "subcategory":"Groceries & Convenience Stores",
            "type":"Retail Goods"
        }
    ],
    "sg:phone":"+1 724 935 1115",
    "sg:postcode":"15090",
    "sg:province":"PA",
    "wof:name":"Mana Indo Mart",
    "wof:placetype":"venue"
},
  "geometry": {"coordinates":[-80.04982,40.602446],"type":"Point"}
}