{
  "type": "Feature",
  "properties": {
    "iso:country":"US",
    "sg:address":"6097 Lincoln Way W",
    "sg:city":"St Thomas",
    "sg:classifiers":[
        {
            "category":"Restaurant",
            "type":"Food & Drink"
        }
    ],
    "sg:phone":"+1 717 369 4340",
    "sg:postcode":"17252",
    "sg:province":"PA",
    "wof:name":"New Oak Forest Restaurant",
    "wof:placetype":"venue"
},
  "geometry": {"coordinates":[-77.790954,39.91917],"type":"Point"}
}