{
  "type": "Feature",
  "properties": {
    "addr:full":"200 S Main St Perkasie PA 18944",
    "addr:housenumber":"200",
    "addr:postcode":"18944",
    "addr:street":"S Main St",
    "iso:country":"US",
    "sg:address":"200 S Main St",
    "sg:city":"Perkasie",
    "sg:classifiers":[
        {
            "category":"Manufacturing",
            "subcategory":"Pet Food",
            "type":"Manufacturing & Wholesale Goods"
        }
    ],
    "sg:phone":"+1 215 257 2139",
    "sg:postcode":"18944",
    "sg:province":"PA",
    "sg:tags":[
        "feed",
        "mfg",
        "prepared"
    ],
    "wof:name":"Richland Feed Company",
    "wof:placetype":"venue"
},
  "geometry": {"coordinates":[-75.288865,40.361617],"type":"Point"}
}