{
  "type": "Feature",
  "properties": {
    "iso:country":"US",
    "sg:address":"1425 Adams Rd Ste 3",
    "sg:city":"Bensalem",
    "sg:classifiers":[
        {
            "category":"Retail",
            "subcategory":"Auto Repair",
            "type":"Services"
        }
    ],
    "sg:phone":"+1 215 639 6600",
    "sg:postcode":"19020",
    "sg:province":"PA",
    "wof:name":"Wholesale Auto & Truck Service",
    "wof:placetype":"venue"
},
  "geometry": {"coordinates":[-74.92523199999999,40.109211],"type":"Point"}
}