{
  "type": "Feature",
  "properties": {
    "iso:country":"US",
    "sg:address":"11566 Perry Hwy Ste 3",
    "sg:city":"Wexford",
    "sg:classifiers":[
        {
            "category":"Shopping",
            "subcategory":"Tobacco",
            "type":"Retail Goods"
        },
        {
            "category":"Food & Beverages",
            "subcategory":"Liquor & Beverages",
            "type":"Retail Goods"
        }
    ],
    "sg:phone":"+1 724 940 1720",
    "sg:postcode":"15090",
    "sg:province":"PA",
    "sg:tags":[
        "shop",
        "beer",
        "spirit",
        "wine"
    ],
    "sg:website":"www.pinebeerandcigars.com",
    "wof:name":"Pine Beer & Cigars",
    "wof:placetype":"venue"
},
  "geometry": {"coordinates":[-80.056459,40.62946],"type":"Point"}
}