{
  "type": "Feature",
  "properties": {
    "iso:country":"US",
    "sg:address":"3606 Baker St",
    "sg:city":"Collegeville",
    "sg:classifiers":[
        {
            "category":"Building & Trades",
            "subcategory":"Construction",
            "type":"Services"
        }
    ],
    "sg:phone":"+1   ",
    "sg:postcode":"19426",
    "sg:province":"PA",
    "sg:tags":[
        "house"
    ],
    "wof:name":"Vernons Enterprises",
    "wof:placetype":"venue"
},
  "geometry": {"coordinates":[-75.42236200000001,40.166241],"type":"Point"}
}