{
  "type": "Feature",
  "properties": {
    "iso:country":"US",
    "sg:address":"2600 Langhorne Yardley Rd",
    "sg:city":"Langhorne",
    "sg:classifiers":[
        {
            "category":"Social Services",
            "type":"Services"
        }
    ],
    "sg:phone":"+1 215 860 7880",
    "sg:postcode":"19047",
    "sg:province":"PA",
    "sg:website":"www.youthservicesagency.org",
    "wof:name":"Youth Services Of Bucks County",
    "wof:placetype":"venue"
},
  "geometry": {"coordinates":[-74.88723400000001,40.212202],"type":"Point"}
}