{
  "type": "Feature",
  "properties": {
    "iso:country":"US",
    "sg:address":"786 Ellis Woods Rd",
    "sg:city":"Pottstown",
    "sg:classifiers":[
        {
            "category":"Professional",
            "subcategory":"Advertising",
            "type":"Services"
        }
    ],
    "sg:phone":"+1 610 326 8626",
    "sg:postcode":"19465",
    "sg:province":"PA",
    "sg:tags":[
        "mail",
        "direct"
    ],
    "wof:name":"High Road Enterprises Inc",
    "wof:placetype":"venue"
},
  "geometry": {"coordinates":[-75.618353,40.198281],"type":"Point"}
}