{
  "type": "Feature",
  "properties": {
    "addr:full":"702 N 7th St Allentown PA 18102",
    "addr:housenumber":"702",
    "addr:postcode":"18102",
    "addr:street":"N 7Th St",
    "iso:country":"US",
    "sg:address":"702 N 7th St",
    "sg:city":"Allentown",
    "sg:classifiers":[
        {
            "category":"Banks & Credit Unions",
            "subcategory":"Bank",
            "type":"Services"
        }
    ],
    "sg:phone":"+1 610 821 2380",
    "sg:postcode":"18102",
    "sg:province":"PA",
    "sg:website":"www.wachovia.com",
    "wof:name":"Wachovia",
    "wof:placetype":"venue"
},
  "geometry": {"coordinates":[-75.476347,40.611944],"type":"Point"}
}