{
  "type": "Feature",
  "properties": {
    "iso:country":"US",
    "sg:address":"1211 Kinzua Rd",
    "sg:city":"Warren",
    "sg:classifiers":[
        {
            "category":"Utilities",
            "subcategory":"Electric",
            "type":"Services"
        }
    ],
    "sg:phone":"+1   ",
    "sg:postcode":"16365",
    "sg:province":"PA",
    "wof:name":"Firstenergy",
    "wof:placetype":"venue"
},
  "geometry": {"coordinates":[-79.073337,41.834005],"type":"Point"}
}