{
  "type": "Feature",
  "properties": {
    "addr:full":"315 N Centre St Pottsville PA 17901",
    "addr:housenumber":"315",
    "addr:postcode":"17901",
    "addr:street":"N Centre St",
    "iso:country":"US",
    "sg:address":"315 N Centre St",
    "sg:city":"Pottsville",
    "sg:classifiers":[
        {
            "category":"Professional",
            "subcategory":"Lawyer & Legal Services",
            "type":"Services"
        }
    ],
    "sg:phone":"+1 570 628 3931",
    "sg:postcode":"17901",
    "sg:province":"PA",
    "wof:name":"Midpenn Legal Svc",
    "wof:placetype":"venue"
},
  "geometry": {"coordinates":[-76.196732,40.68702],"type":"Point"}
}