{
  "type": "Feature",
  "properties": {
    "iso:country":"US",
    "sg:address":"3611 Concord Rd",
    "sg:city":"Aston",
    "sg:classifiers":[
        {
            "category":"Personal",
            "subcategory":"Massage",
            "type":"Services"
        },
        {
            "category":"Personal",
            "subcategory":"Beauty Salon",
            "type":"Services"
        },
        {
            "category":"Health Services",
            "subcategory":"Health Practitioner",
            "type":"Services"
        },
        {
            "category":"Health Services",
            "subcategory":"Clinic",
            "type":"Services"
        }
    ],
    "sg:phone":"+1 610 494 2999",
    "sg:postcode":"19014",
    "sg:province":"PA",
    "sg:tags":[
        "therapist",
        "therapy",
        "physical"
    ],
    "wof:name":"All About U By Carol Anne",
    "wof:placetype":"venue"
},
  "geometry": {"coordinates":[-75.429424,39.869545],"type":"Point"}
}