{
  "type": "Feature",
  "properties": {
    "iso:country":"US",
    "sg:address":"1355 Freeport Rd",
    "sg:city":"Pittsburgh",
    "sg:classifiers":[
        {
            "category":"Personal",
            "subcategory":"Beauty Salon",
            "type":"Services"
        }
    ],
    "sg:phone":"+1 412 782 5122",
    "sg:postcode":"15238",
    "sg:province":"PA",
    "sg:tags":[
        "manicuring"
    ],
    "wof:name":"Perfect Ten",
    "wof:placetype":"venue"
},
  "geometry": {"coordinates":[-79.8733,40.489587],"type":"Point"}
}