{
  "type": "Feature",
  "properties": {
    "iso:country":"US",
    "sg:address":"230 3rd Ave",
    "sg:city":"Pittsburgh",
    "sg:classifiers":[
        {
            "category":"Professional",
            "subcategory":"Engineering",
            "type":"Services"
        }
    ],
    "sg:phone":"+1   ",
    "sg:postcode":"15219",
    "sg:province":"PA",
    "sg:tags":[
        "consulting",
        "business"
    ],
    "wof:name":"R T Patterson Company Inc",
    "wof:placetype":"venue"
},
  "geometry": {"coordinates":[-80.00216,40.439014],"type":"Point"}
}