{
  "type": "Feature",
  "properties": {
    "addr:full":"519 Coachwood Ct Newtown PA 18940",
    "addr:housenumber":"519",
    "addr:postcode":"18940",
    "addr:street":"Coachwood Ct",
    "iso:country":"US",
    "sg:address":"519 Coachwood Ct",
    "sg:city":"Newtown",
    "sg:classifiers":[
        {
            "category":"Utilities",
            "subcategory":"Mobile Phone",
            "type":"Services"
        },
        {
            "category":"Utilities",
            "subcategory":"Telephone",
            "type":"Services"
        }
    ],
    "sg:phone":"+1 215 968 6979",
    "sg:postcode":"18940",
    "sg:province":"PA",
    "sg:tags":[
        "communication",
        "cellular"
    ],
    "wof:name":"Comparacell",
    "wof:placetype":"venue"
},
  "geometry": {"coordinates":[-74.953926,40.261806],"type":"Point"}
}