{
  "type": "Feature",
  "properties": {
    "iso:country":"US",
    "sg:address":"156 State Rte 239",
    "sg:city":"Shickshinny",
    "sg:classifiers":[
        {
            "category":"Food & Beverages",
            "subcategory":"Groceries & Convenience Stores",
            "type":"Retail Goods"
        }
    ],
    "sg:phone":"+1 570 542 4780",
    "sg:postcode":"18655",
    "sg:province":"PA",
    "sg:tags":[
        "grocer"
    ],
    "wof:name":"Wolfie's Grocery Store",
    "wof:placetype":"venue"
},
  "geometry": {"coordinates":[-76.139251,41.141301],"type":"Point"}
}