{
  "type": "Feature",
  "properties": {
    "addr:full":"5710 Summit St Gibsonia PA 15044",
    "addr:housenumber":"5710",
    "addr:postcode":"15044",
    "addr:street":"Summit St",
    "iso:country":"US",
    "sg:address":"5710 Summit St",
    "sg:city":"Gibsonia",
    "sg:classifiers":[
        {
            "category":"Building & Trades",
            "subcategory":"Construction",
            "type":"Services"
        }
    ],
    "sg:phone":"+1   ",
    "sg:postcode":"15044",
    "sg:province":"PA",
    "sg:tags":[
        "carpentry",
        "contractor"
    ],
    "wof:name":"Macik Construction",
    "wof:placetype":"venue"
},
  "geometry": {"coordinates":[-79.95404000000001,40.641257],"type":"Point"}
}