{
  "type": "Feature",
  "properties": {
    "addr:full":"119 Dogwood Dr Alburtis PA 18011",
    "addr:housenumber":"119",
    "addr:postcode":"18011",
    "addr:street":"Dogwood Dr Alburtis",
    "iso:country":"US",
    "sg:address":"119 Dogwood Dr",
    "sg:city":"Alburtis",
    "sg:classifiers":[
        {
            "category":"Retail",
            "subcategory":"Auto Repair",
            "type":"Services"
        }
    ],
    "sg:phone":"+1 610 682 4151",
    "sg:postcode":"18011",
    "sg:province":"PA",
    "wof:name":"Rohrbach's Garage",
    "wof:placetype":"venue"
},
  "geometry": {"coordinates":[-75.643754,40.480163],"type":"Point"}
}