{
  "type": "Feature",
  "properties": {
    "iso:country":"US",
    "sg:address":"231 N Pennsylvania Ave",
    "sg:city":"Centre Hall",
    "sg:classifiers":[
        {
            "category":"Food & Beverages",
            "subcategory":"Meat & Fish",
            "type":"Retail Goods"
        }
    ],
    "sg:phone":"+1 814 364 1164",
    "sg:postcode":"16828",
    "sg:province":"PA",
    "sg:tags":[
        "shop"
    ],
    "wof:name":"Mel's Market",
    "wof:placetype":"venue"
},
  "geometry": {"coordinates":[-77.687299,40.84756],"type":"Point"}
}