{
  "type": "Feature",
  "properties": {
    "iso:country":"US",
    "sg:address":"1530 Hamilton Rd",
    "sg:city":"Pittsburgh",
    "sg:classifiers":[
        {
            "category":"Recreation",
            "type":"Entertainment"
        }
    ],
    "sg:phone":"+1   ",
    "sg:postcode":"15234",
    "sg:province":"PA",
    "wof:name":"Golden Air Gold Center",
    "wof:placetype":"venue"
},
  "geometry": {"coordinates":[-80.01151900000001,40.351743],"type":"Point"}
}