{
  "type": "Feature",
  "properties": {
    "iso:country":"US",
    "sg:address":"368 Fairview Rd",
    "sg:city":"Glenmoore",
    "sg:classifiers":[
        {
            "category":"Professional",
            "subcategory":"Management & Consulting",
            "type":"Services"
        }
    ],
    "sg:phone":"+1   ",
    "sg:postcode":"19343",
    "sg:province":"PA",
    "sg:tags":[
        "business"
    ],
    "wof:name":"E O & D Inc",
    "wof:placetype":"venue"
},
  "geometry": {"coordinates":[-75.798743,40.091047],"type":"Point"}
}