{
  "type": "Feature",
  "properties": {
    "iso:country":"US",
    "sg:address":"63 Gerald Ave",
    "sg:city":"Dallas",
    "sg:classifiers":[
        {
            "category":"Personal",
            "subcategory":"Beauty Salon",
            "type":"Services"
        }
    ],
    "sg:phone":"+1 570 675 5298",
    "sg:postcode":"18612",
    "sg:province":"PA",
    "wof:name":"Robyn's Hair Salon",
    "wof:placetype":"venue"
},
  "geometry": {"coordinates":[-75.97344699999999,41.339648],"type":"Point"}
}