{
  "type": "Feature",
  "properties": {
    "iso:country":"US",
    "sg:address":"207 Prestonwood Ln",
    "sg:city":"Canonsburg",
    "sg:classifiers":[
        {
            "category":"Education",
            "subcategory":"School",
            "type":"Public Place"
        }
    ],
    "sg:phone":"+1   ",
    "sg:postcode":"15317",
    "sg:province":"PA",
    "wof:name":"Walnut Ridge Vineyards Inc",
    "wof:placetype":"venue"
},
  "geometry": {"coordinates":[-80.11338499999999,40.292804],"type":"Point"}
}