{
  "type": "Feature",
  "properties": {
    "iso:country":"US",
    "sg:address":"375 Pheasant Run",
    "sg:city":"Newtown",
    "sg:classifiers":[
        {
            "category":"Health Services",
            "subcategory":"Medical Lab",
            "type":"Services"
        }
    ],
    "sg:phone":"+1 215 968 3550",
    "sg:postcode":"18940",
    "sg:province":"PA",
    "sg:tags":[
        "laboratory",
        "testing"
    ],
    "wof:name":"FIDR",
    "wof:placetype":"venue"
},
  "geometry": {"coordinates":[-74.90927499999999,40.225397],"type":"Point"}
}