{
  "type": "Feature",
  "properties": {
    "addr:full":"6th & Lehigh Ave Philadelphia PA 19102",
    "addr:postcode":"19102",
    "addr:street":"Ave",
    "iso:country":"US",
    "sg:address":"6th & Lehigh Ave",
    "sg:city":"Philadelphia",
    "sg:classifiers":[
        {
            "category":"Education",
            "subcategory":"Library",
            "type":"Public Place"
        }
    ],
    "sg:phone":"+1 215 685 9794",
    "sg:postcode":"19102",
    "sg:province":"PA",
    "wof:name":"Free Library of Phila",
    "wof:placetype":"venue"
},
  "geometry": {"coordinates":[-75.142174,39.99236],"type":"Point"}
}