{
  "type": "Feature",
  "properties": {
    "addr:full":"1105 S 2nd St Clearfield PA 16830",
    "addr:housenumber":"1105",
    "addr:postcode":"16830",
    "addr:street":"S 2Nd St",
    "iso:country":"US",
    "sg:address":"1105 S 2nd St",
    "sg:city":"Clearfield",
    "sg:classifiers":[
        {
            "category":"Travel",
            "subcategory":"Hotels & Motels",
            "type":"Entertainment"
        }
    ],
    "sg:phone":"+1   ",
    "sg:postcode":"16830",
    "sg:province":"PA",
    "wof:name":"Riverside Motel",
    "wof:placetype":"venue"
},
  "geometry": {"coordinates":[-78.451616,41.00805],"type":"Point"}
}