{
  "type": "Feature",
  "properties": {
    "iso:country":"US",
    "sg:address":"2349 Mill St Ste 201",
    "sg:city":"Aliquippa",
    "sg:classifiers":[
        {
            "category":"Health Services",
            "subcategory":"Nursing And Care Facility",
            "type":"Services"
        },
        {
            "category":"Health Services",
            "subcategory":"Health Practitioner",
            "type":"Services"
        }
    ],
    "sg:phone":"+1 724 857 9919",
    "sg:postcode":"15001",
    "sg:province":"PA",
    "sg:tags":[
        "home",
        "eldercare-home"
    ],
    "wof:name":"Anova Home Health Care Services Inc",
    "wof:placetype":"venue"
},
  "geometry": {"coordinates":[-80.283722,40.607658],"type":"Point"}
}