{
  "type": "Feature",
  "properties": {
    "iso:country":"US",
    "sg:address":"261 Lower State Rd",
    "sg:city":"Chalfont",
    "sg:classifiers":[
        {
            "category":"Farming",
            "subcategory":"Nursery",
            "type":"Manufacturing & Wholesale Goods"
        }
    ],
    "sg:phone":"+1   ",
    "sg:postcode":"18914",
    "sg:province":"PA",
    "sg:tags":[
        "ornamental"
    ],
    "wof:name":"Hejazi Ziaaddin Farm",
    "wof:placetype":"venue"
},
  "geometry": {"coordinates":[-75.19060399999999,40.24481],"type":"Point"}
}