{
  "type": "Feature",
  "properties": {
    "iso:country":"US",
    "sg:address":"1343 W Olney Ave",
    "sg:city":"Philadelphia",
    "sg:classifiers":[
        {
            "category":"Food & Beverages",
            "subcategory":"Meat & Fish",
            "type":"Retail Goods"
        }
    ],
    "sg:phone":"+1 215 424 5000",
    "sg:postcode":"19141",
    "sg:province":"PA",
    "sg:tags":[
        "eating"
    ],
    "wof:name":"Lane Meadow Barbeque",
    "wof:placetype":"venue"
},
  "geometry": {"coordinates":[-75.144548,40.039092],"type":"Point"}
}