{
  "type": "Feature",
  "properties": {
    "iso:country":"US",
    "sg:address":"131 Olin Ave",
    "sg:city":"Girard",
    "sg:classifiers":[
        {
            "category":"Professional",
            "type":"Services"
        }
    ],
    "sg:phone":"+1   ",
    "sg:postcode":"16417",
    "sg:province":"PA",
    "wof:name":"Susan B Mueller",
    "wof:placetype":"venue"
},
  "geometry": {"coordinates":[-80.317594,42.00313],"type":"Point"}
}