{
  "type": "Feature",
  "properties": {
    "iso:country":"US",
    "sg:address":"3344 Trindle Rd",
    "sg:city":"Camp Hill",
    "sg:classifiers":[
        {
            "category":"Professional",
            "subcategory":"Lawyer & Legal Services",
            "type":"Services"
        }
    ],
    "sg:phone":"+1 717 214 3700",
    "sg:postcode":"17011",
    "sg:province":"PA",
    "sg:tags":[
        "personal",
        "injury"
    ],
    "wof:name":"Law Office of Charles P Mackin",
    "wof:placetype":"venue"
},
  "geometry": {"coordinates":[-76.936203,40.2379],"type":"Point"}
}