{
  "type": "Feature",
  "properties": {
    "iso:country":"US",
    "sg:address":"5440 Towanda Dr",
    "sg:city":"Bethlehem",
    "sg:classifiers":[
        {
            "category":"Personal",
            "subcategory":"Beauty Salon",
            "type":"Services"
        }
    ],
    "sg:phone":"+1   ",
    "sg:postcode":"18017",
    "sg:province":"PA",
    "sg:tags":[
        "shop",
        "animal"
    ],
    "wof:name":"Nails Ta Tails",
    "wof:placetype":"venue"
},
  "geometry": {"coordinates":[-75.43470600000001,40.682659],"type":"Point"}
}