{
  "type": "Feature",
  "properties": {
    "addr:full":"402 Delaware Ave Oakmont PA 15139",
    "addr:housenumber":"402",
    "addr:postcode":"15139",
    "addr:street":"Delaware Ave",
    "iso:country":"US",
    "sg:address":"402 Delaware Ave",
    "sg:city":"Oakmont",
    "sg:classifiers":[
        {
            "category":"Professional",
            "type":"Services"
        }
    ],
    "sg:phone":"+1 412 826 9295",
    "sg:postcode":"15139",
    "sg:province":"PA",
    "sg:tags":[
        "establishment"
    ],
    "wof:name":"Oakmont's Boulevard Project",
    "wof:placetype":"venue"
},
  "geometry": {"coordinates":[-79.840688,40.517391],"type":"Point"}
}