{
  "type": "Feature",
  "properties": {
    "iso:country":"US",
    "sg:address":"807 W Street Rd",
    "sg:city":"West Chester",
    "sg:classifiers":[
        {
            "category":"Professional",
            "type":"Services"
        }
    ],
    "sg:phone":"+1   ",
    "sg:postcode":"19382",
    "sg:province":"PA",
    "wof:name":"Allison Durinci",
    "wof:placetype":"venue"
},
  "geometry": {"coordinates":[-75.594442,39.912016],"type":"Point"}
}