{
  "type": "Feature",
  "properties": {
    "addr:full":"1809 Arbor Ct Jamison PA 18929",
    "addr:housenumber":"1809",
    "addr:postcode":"18929",
    "addr:street":"Arbor Ct",
    "iso:country":"US",
    "sg:address":"1809 Arbor Ct",
    "sg:city":"Jamison",
    "sg:classifiers":[
        {
            "category":"Banks & Credit Unions",
            "subcategory":"Bank",
            "type":"Services"
        }
    ],
    "sg:phone":"+1 215 491 1694",
    "sg:postcode":"18929",
    "sg:province":"PA",
    "sg:tags":[
        "loan",
        "real estate"
    ],
    "wof:name":"United Mortgage Group",
    "wof:placetype":"venue"
},
  "geometry": {"coordinates":[-75.095574,40.251862],"type":"Point"}
}