{
  "type": "Feature",
  "properties": {
    "addr:full":"2617 Dekalb Pike Norristown PA 19401",
    "addr:housenumber":"2617",
    "addr:postcode":"19401",
    "addr:street":"Dekalb Pike",
    "iso:country":"US",
    "sg:address":"2617 Dekalb Pike",
    "sg:city":"Norristown",
    "sg:classifiers":[
        {
            "category":"Organizations",
            "subcategory":"Religious Organization",
            "type":"Services"
        }
    ],
    "sg:phone":"+1 610 277 8600",
    "sg:postcode":"19401",
    "sg:province":"PA",
    "sg:tags":[
        "church"
    ],
    "wof:name":"Entheos Ministries",
    "wof:placetype":"venue"
},
  "geometry": {"coordinates":[-75.31276200000001,40.141586],"type":"Point"}
}