{
  "type": "Feature",
  "properties": {
    "addr:full":"208 E Fairwood Dr Chalfont PA 18914",
    "addr:housenumber":"208",
    "addr:postcode":"18914",
    "addr:street":"E Fairwood Dr",
    "iso:country":"US",
    "sg:address":"208 E Fairwood Dr",
    "sg:city":"Chalfont",
    "sg:classifiers":[
        {
            "category":"Professional",
            "subcategory":"Business Services",
            "type":"Services"
        }
    ],
    "sg:phone":"+1   ",
    "sg:postcode":"18914",
    "sg:province":"PA",
    "sg:tags":[
        "clothing"
    ],
    "wof:name":"Friedman Assocs",
    "wof:placetype":"venue"
},
  "geometry": {"coordinates":[-75.198097,40.302049],"type":"Point"}
}