{
  "type": "Feature",
  "properties": {
    "iso:country":"US",
    "sg:address":"1905 State Rd",
    "sg:city":"Croydon",
    "sg:classifiers":[
        {
            "category":"Professional",
            "type":"Services"
        }
    ],
    "sg:phone":"+1   ",
    "sg:postcode":"19021",
    "sg:province":"PA",
    "wof:name":"Baldwin CL Rev",
    "wof:placetype":"venue"
},
  "geometry": {"coordinates":[-74.892957,40.090477],"type":"Point"}
}