{
  "type": "Feature",
  "properties": {
    "iso:country":"US",
    "sg:address":"239 4th Ave",
    "sg:city":"West Mifflin",
    "sg:classifiers":[
        {
            "category":"Arts & Performance",
            "subcategory":"Theater",
            "type":"Entertainment"
        }
    ],
    "sg:phone":"+1 412 434 1666",
    "sg:postcode":"15122",
    "sg:province":"PA",
    "sg:tags":[
        "theatrical",
        "agency"
    ],
    "wof:name":"Nancy Mosser Casting",
    "wof:placetype":"venue"
},
  "geometry": {"coordinates":[-79.88478000000001,40.388201],"type":"Point"}
}