{
  "type": "Feature",
  "properties": {
    "iso:country":"US",
    "sg:address":"3905 N 17th St",
    "sg:city":"Philadelphia",
    "sg:classifiers":[
        {
            "category":"Organizations",
            "subcategory":"Religious Organization",
            "type":"Services"
        }
    ],
    "sg:phone":"+1 215 229 5246",
    "sg:postcode":"19140",
    "sg:province":"PA",
    "sg:tags":[
        "clergy"
    ],
    "wof:name":"Michael Draper",
    "wof:placetype":"venue"
},
  "geometry": {"coordinates":[-75.15496400000001,40.014378],"type":"Point"}
}