{
  "type": "Feature",
  "properties": {
    "iso:country":"US",
    "sg:address":"120 E Tioga St",
    "sg:city":"Tunkhannock",
    "sg:classifiers":[
        {
            "category":"Food & Beverages",
            "subcategory":"Liquor & Beverages",
            "type":"Retail Goods"
        },
        {
            "category":"Professional",
            "subcategory":"Management & Consulting",
            "type":"Services"
        }
    ],
    "sg:phone":"+1 570 836 2221",
    "sg:postcode":"18657",
    "sg:province":"PA",
    "sg:tags":[
        "product",
        "ale",
        "beer"
    ],
    "wof:name":"Wyoming County Beverage Co",
    "wof:placetype":"venue"
},
  "geometry": {"coordinates":[-75.943663,41.538254],"type":"Point"}
}