{
  "type": "Feature",
  "properties": {
    "iso:country":"US",
    "sg:address":"1335 Hottle Ave",
    "sg:city":"Bethlehem",
    "sg:classifiers":[
        {
            "category":"Local Transit",
            "type":"Transportation"
        }
    ],
    "sg:phone":"+1 610 866 9313",
    "sg:postcode":"18018",
    "sg:province":"PA",
    "sg:tags":[
        "limousine",
        "limo"
    ],
    "wof:name":"Executrans Limousine Services",
    "wof:placetype":"venue"
},
  "geometry": {"coordinates":[-75.374663,40.631474],"type":"Point"}
}