{
  "type": "Feature",
  "properties": {
    "addr:full":"40 N Market St Lancaster PA 17603",
    "addr:housenumber":"40",
    "addr:postcode":"17603",
    "addr:street":"N Market St",
    "iso:country":"US",
    "sg:address":"40 N Market St",
    "sg:city":"Lancaster",
    "sg:classifiers":[
        {
            "category":"Parking",
            "type":"Transportation"
        }
    ],
    "sg:phone":"+1   ",
    "sg:postcode":"17603",
    "sg:province":"PA",
    "sg:tags":[
        "automobile"
    ],
    "wof:name":"Hager Parking Lots",
    "wof:placetype":"venue"
},
  "geometry": {"coordinates":[-76.307132,40.039378],"type":"Point"}
}