{
  "type": "Feature",
  "properties": {
    "addr:full":"142 N Washington Ave Scranton PA 18503",
    "addr:housenumber":"142",
    "addr:postcode":"18503",
    "addr:street":"N Washington Ave",
    "iso:country":"US",
    "sg:address":"142 N Washington Ave",
    "sg:city":"Scranton",
    "sg:classifiers":[
        {
            "category":"Professional",
            "subcategory":"Lawyer & Legal Services",
            "type":"Services"
        }
    ],
    "sg:phone":"+1 570 344 6141",
    "sg:postcode":"18503",
    "sg:province":"PA",
    "sg:tags":[
        "attorney"
    ],
    "wof:name":"Kenowski & Kenowski",
    "wof:placetype":"venue"
},
  "geometry": {"coordinates":[-75.66387,41.407648],"type":"Point"}
}