{
  "type": "Feature",
  "properties": {
    "iso:country":"US",
    "sg:address":"345 Homestead Dr",
    "sg:city":"Harleysville",
    "sg:classifiers":[
        {
            "category":"Building & Trades",
            "subcategory":"Electrical",
            "type":"Services"
        }
    ],
    "sg:phone":"+1   ",
    "sg:postcode":"19438",
    "sg:province":"PA",
    "sg:tags":[
        "electrical",
        "contractor"
    ],
    "wof:name":"Catanzaro Electric LLC",
    "wof:placetype":"venue"
},
  "geometry": {"coordinates":[-75.411103,40.289688],"type":"Point"}
}