{
  "type": "Feature",
  "properties": {
    "addr:full":"323 Blvd of the Allies Pittsburgh PA 15222",
    "addr:housenumber":"323",
    "addr:postcode":"15222",
    "addr:street":"Blvd Of The Allies",
    "iso:country":"US",
    "sg:address":"323 Blvd of the Allies",
    "sg:city":"Pittsburgh",
    "sg:classifiers":[
        {
            "category":"Wholesale",
            "subcategory":"Computers",
            "type":"Manufacturing & Wholesale Goods"
        }
    ],
    "sg:phone":"+1 412 642 7750",
    "sg:postcode":"15222",
    "sg:province":"PA",
    "wof:name":"Computer Centers of America Isg",
    "wof:placetype":"venue"
},
  "geometry": {"coordinates":[-80.001503,40.4384],"type":"Point"}
}