{
  "type": "Feature",
  "properties": {
    "iso:country":"US",
    "sg:address":"RR 5",
    "sg:city":"Bellefonte",
    "sg:classifiers":[
        {
            "category":"Food & Beverages",
            "subcategory":"Meat & Fish",
            "type":"Retail Goods"
        }
    ],
    "sg:phone":"+1 814 383 2410",
    "sg:postcode":"16823",
    "sg:province":"PA",
    "sg:tags":[
        "shop"
    ],
    "wof:name":"Nittany Meats",
    "wof:placetype":"venue"
},
  "geometry": {"coordinates":[-77.769203,40.912498],"type":"Point"}
}