{
  "type": "Feature",
  "properties": {
    "iso:country":"US",
    "sg:address":"1001 Johnson Rd",
    "sg:city":"Ulysses",
    "sg:classifiers":[
        {
            "category":"Building & Trades",
            "subcategory":"Construction",
            "type":"Services"
        }
    ],
    "sg:phone":"+1   ",
    "sg:postcode":"16948",
    "sg:province":"PA",
    "sg:tags":[
        "carpentry",
        "contractor"
    ],
    "wof:name":"Leon Merkey Carpentry",
    "wof:placetype":"venue"
},
  "geometry": {"coordinates":[-77.721023,41.940141],"type":"Point"}
}