{
  "type": "Feature",
  "properties": {
    "addr:full":"7239 Mansfield Ave Philadelphia PA 19138",
    "addr:housenumber":"7239",
    "addr:postcode":"19138",
    "addr:street":"Mansfield Ave",
    "iso:country":"US",
    "sg:address":"7239 Mansfield Ave",
    "sg:city":"Philadelphia",
    "sg:classifiers":[
        {
            "category":"Travel",
            "subcategory":"Travel Agent",
            "type":"Entertainment"
        }
    ],
    "sg:phone":"+1   ",
    "sg:postcode":"19138",
    "sg:province":"PA",
    "sg:tags":[
        "agency"
    ],
    "wof:name":"Great Escapes Travel Agency",
    "wof:placetype":"venue"
},
  "geometry": {"coordinates":[-75.162111,40.058705],"type":"Point"}
}