{
  "type": "Feature",
  "properties": {
    "iso:country":"US",
    "sg:address":"801 Adams St",
    "sg:city":"Windber",
    "sg:classifiers":[
        {
            "category":"Shopping",
            "subcategory":"Gifts & Souvenirs",
            "type":"Retail Goods"
        }
    ],
    "sg:phone":"+1   ",
    "sg:postcode":"15963",
    "sg:province":"PA",
    "sg:tags":[
        "flower",
        "dried",
        "arrangement"
    ],
    "wof:name":"Personal Thoughts",
    "wof:placetype":"venue"
},
  "geometry": {"coordinates":[-78.84552600000001,40.236799],"type":"Point"}
}