{
  "type": "Feature",
  "properties": {
    "iso:country":"US",
    "sg:address":"346 Main St",
    "sg:city":"Wellsville",
    "sg:classifiers":[
        {
            "category":"Freight",
            "type":"Transportation"
        }
    ],
    "sg:phone":"+1   ",
    "sg:postcode":"17365",
    "sg:province":"PA",
    "sg:tags":[
        "operator",
        "trucking"
    ],
    "wof:name":"Cross Keys Transport",
    "wof:placetype":"venue"
},
  "geometry": {"coordinates":[-76.944547,40.051716],"type":"Point"}
}