{
  "type": "Feature",
  "properties": {
    "addr:full":"987 Greentree Rd Pittsburgh PA 15220",
    "addr:housenumber":"987",
    "addr:postcode":"15220",
    "addr:street":"Greentree Rd",
    "iso:country":"US",
    "sg:address":"987 Greentree Rd",
    "sg:city":"Pittsburgh",
    "sg:classifiers":[
        {
            "category":"Food & Beverages",
            "subcategory":"Groceries & Convenience Stores",
            "type":"Retail Goods"
        }
    ],
    "sg:phone":"+1 412 921 2078",
    "sg:postcode":"15220",
    "sg:province":"PA",
    "sg:website":"www.7-eleven.com",
    "wof:name":"7-Eleven Stores",
    "wof:placetype":"venue"
},
  "geometry": {"coordinates":[-80.04540299999999,40.418201],"type":"Point"}
}