{
  "type": "Feature",
  "properties": {
    "iso:country":"US",
    "sg:address":"822 Beverly Dr",
    "sg:city":"Plymouth",
    "sg:classifiers":[
        {
            "category":"Building & Trades",
            "subcategory":"Cleaning & Sanitation",
            "type":"Services"
        }
    ],
    "sg:phone":"+1 570 779 3780",
    "sg:postcode":"18651",
    "sg:province":"PA",
    "sg:tags":[
        "janitorial"
    ],
    "wof:name":"C & C Cleaning",
    "wof:placetype":"venue"
},
  "geometry": {"coordinates":[-75.964967,41.235055],"type":"Point"}
}