{
  "type": "Feature",
  "properties": {
    "iso:country":"US",
    "sg:address":"1935 Washington Ave",
    "sg:city":"Philadelphia",
    "sg:classifiers":[
        {
            "category":"Shopping",
            "subcategory":"Beauty & Cosmetics",
            "type":"Retail Goods"
        }
    ],
    "sg:phone":"+1 215 735 6380",
    "sg:postcode":"19146",
    "sg:province":"PA",
    "sg:tags":[
        "merchandise"
    ],
    "sg:website":"www.misacosmetics.com",
    "wof:name":"Misa Cosmetic Products",
    "wof:placetype":"venue"
},
  "geometry": {"coordinates":[-75.175883,39.939027],"type":"Point"}
}