{
  "type": "Feature",
  "properties": {
    "addr:full":"803 W Mahoning St Punxsutawney PA 15767",
    "addr:housenumber":"803",
    "addr:postcode":"15767",
    "addr:street":"W Mahoning St",
    "iso:country":"US",
    "sg:address":"803 W Mahoning St",
    "sg:city":"Punxsutawney",
    "sg:classifiers":[
        {
            "category":"Health Services",
            "subcategory":"Doctor",
            "type":"Services"
        }
    ],
    "sg:phone":"+1 814 938 0123",
    "sg:postcode":"15767",
    "sg:province":"PA",
    "sg:tags":[
        "medical"
    ],
    "wof:name":"George Cherian MD",
    "wof:placetype":"venue"
},
  "geometry": {"coordinates":[-78.98738299999999,40.942582],"type":"Point"}
}