{
  "type": "Feature",
  "properties": {
    "iso:country":"US",
    "sg:address":"2225 Jackson St",
    "sg:city":"Scranton",
    "sg:classifiers":[
        {
            "category":"Bars & Pubs",
            "type":"Food & Drink"
        },
        {
            "category":"Restaurant",
            "type":"Food & Drink"
        }
    ],
    "sg:phone":"+1 570 342 5197",
    "sg:postcode":"18504",
    "sg:province":"PA",
    "sg:tags":[
        "grill",
        "brew",
        "tavern"
    ],
    "wof:name":"Rep's Place",
    "wof:placetype":"venue"
},
  "geometry": {"coordinates":[-75.694818,41.419621],"type":"Point"}
}