{
  "type": "Feature",
  "properties": {
    "iso:country":"US",
    "sg:address":"46 E Main St",
    "sg:city":"Palmyra",
    "sg:classifiers":[
        {
            "category":"Real Estate",
            "subcategory":"Real Estate Services",
            "type":"Services"
        }
    ],
    "sg:phone":"+1 717 838 6430",
    "sg:postcode":"17078",
    "sg:province":"PA",
    "sg:tags":[
        "company",
        "title"
    ],
    "wof:name":"Terra Transfer Co",
    "wof:placetype":"venue"
},
  "geometry": {"coordinates":[-76.59493500000001,40.307848],"type":"Point"}
}