{
  "type": "Feature",
  "properties": {
    "iso:country":"US",
    "sg:address":"1130 Cocoa Ave",
    "sg:city":"Hershey",
    "sg:classifiers":[
        {
            "category":"Coffee & Tea",
            "type":"Food & Drink"
        },
        {
            "category":"Food & Beverages",
            "subcategory":"Bakery",
            "type":"Retail Goods"
        }
    ],
    "sg:phone":"+1 717 298 1118",
    "sg:postcode":"17033",
    "sg:province":"PA",
    "sg:tags":[
        "sandwich"
    ],
    "sg:website":"www.cocoaperkcafe.com",
    "wof:name":"Cocoa Perk Cafe",
    "wof:placetype":"venue"
},
  "geometry": {"coordinates":[-76.648155,40.270428],"type":"Point"}
}