{
  "type": "Feature",
  "properties": {
    "iso:country":"US",
    "sg:address":"919 Jordan Dr",
    "sg:city":"Whitehall",
    "sg:classifiers":[
        {
            "category":"Real Estate",
            "subcategory":"Real Estate Operator",
            "type":"Services"
        }
    ],
    "sg:phone":"+1 610 439 3414",
    "sg:postcode":"18052",
    "sg:province":"PA",
    "sg:tags":[
        "apartment"
    ],
    "wof:name":"Jordan Park Apartments",
    "wof:placetype":"venue"
},
  "geometry": {"coordinates":[-75.479826,40.624023],"type":"Point"}
}