{
  "type": "Feature",
  "properties": {
    "iso:country":"US",
    "sg:address":"2409 Shady Ave",
    "sg:city":"Pittsburgh",
    "sg:classifiers":[
        {
            "category":"Education",
            "subcategory":"School",
            "type":"Public Place"
        }
    ],
    "sg:phone":"+1 412 422 4800",
    "sg:postcode":"15217",
    "sg:province":"PA",
    "wof:name":"Taylor Allderdice High School",
    "wof:placetype":"venue"
},
  "geometry": {"coordinates":[-79.920708,40.42953],"type":"Point"}
}