{
  "type": "Feature",
  "properties": {
    "iso:country":"US",
    "sg:address":"23 Main St",
    "sg:city":"Eldred",
    "sg:classifiers":[
        {
            "category":"Restaurant",
            "type":"Food & Drink"
        }
    ],
    "sg:phone":"+1 814 225 4988",
    "sg:postcode":"16731",
    "sg:province":"PA",
    "sg:tags":[
        "eating",
        "pizza"
    ],
    "wof:name":"Chubby's Pizza",
    "wof:placetype":"venue"
},
  "geometry": {"coordinates":[-78.384652,41.953058],"type":"Point"}
}