{
  "type": "Feature",
  "properties": {
    "iso:country":"US",
    "sg:address":"103 Dogwood Ln",
    "sg:city":"Pittsburgh",
    "sg:classifiers":[
        {
            "category":"Professional",
            "subcategory":"Business Services",
            "type":"Services"
        }
    ],
    "sg:phone":"+1   ",
    "sg:postcode":"15238",
    "sg:province":"PA",
    "sg:tags":[
        "valuation",
        "appraisal"
    ],
    "wof:name":"Business Valuation Associates",
    "wof:placetype":"venue"
},
  "geometry": {"coordinates":[-79.889281,40.549516],"type":"Point"}
}