{
  "type": "Feature",
  "properties": {
    "iso:country":"US",
    "sg:address":"2398 New Market Sq S",
    "sg:city":"Bensalem",
    "sg:classifiers":[
        {
            "category":"Building & Trades",
            "subcategory":"Construction",
            "type":"Services"
        }
    ],
    "sg:phone":"+1 215 638 4195",
    "sg:postcode":"19020",
    "sg:province":"PA",
    "sg:tags":[
        "contractor"
    ],
    "wof:name":"New Eastern Construction Company Incorporated",
    "wof:placetype":"venue"
},
  "geometry": {"coordinates":[-74.951897,40.088501],"type":"Point"}
}