{
  "type": "Feature",
  "properties": {
    "iso:country":"US",
    "sg:address":"361 Harrison Ave",
    "sg:city":"Upper Darby",
    "sg:classifiers":[
        {
            "category":"Retail",
            "subcategory":"Auto Repair",
            "type":"Services"
        }
    ],
    "sg:phone":"+1 610 352 1272",
    "sg:postcode":"19082",
    "sg:province":"PA",
    "sg:tags":[
        "body",
        "shop"
    ],
    "wof:name":"J & J Auto Body",
    "wof:placetype":"venue"
},
  "geometry": {"coordinates":[-75.253304,39.953201],"type":"Point"}
}