{
  "type": "Feature",
  "properties": {
    "addr:full":"835 Vine Rd St Marys PA 15857",
    "addr:housenumber":"835",
    "addr:postcode":"15857",
    "addr:street":"Vine Rd",
    "iso:country":"US",
    "sg:address":"835 Vine Rd",
    "sg:city":"St Marys",
    "sg:classifiers":[
        {
            "category":"Manufacturing",
            "subcategory":"Signs",
            "type":"Manufacturing & Wholesale Goods"
        }
    ],
    "sg:phone":"+1 814 834 1080",
    "sg:postcode":"15857",
    "sg:province":"PA",
    "sg:tags":[
        "specialty",
        "mfg"
    ],
    "wof:name":"Kennedy Signs",
    "wof:placetype":"venue"
},
  "geometry": {"coordinates":[-78.548141,41.413952],"type":"Point"}
}