{
  "type": "Feature",
  "properties": {
    "addr:full":"116 S 5th St Reading PA 19602",
    "addr:housenumber":"116",
    "addr:postcode":"19602",
    "addr:street":"S 5Th St",
    "iso:country":"US",
    "sg:address":"116 S 5th St",
    "sg:city":"Reading",
    "sg:classifiers":[
        {
            "category":"Real Estate",
            "subcategory":"Real Estate Agent",
            "type":"Services"
        }
    ],
    "sg:phone":"+1 610 374 4022",
    "sg:postcode":"19602",
    "sg:province":"PA",
    "sg:tags":[
        "appraiser"
    ],
    "wof:name":"Associated Realty & Appraisals",
    "wof:placetype":"venue"
},
  "geometry": {"coordinates":[-75.928044,40.332426],"type":"Point"}
}