{
  "type": "Feature",
  "properties": {
    "iso:country":"US",
    "sg:address":"633 N Sumner Ave",
    "sg:city":"Scranton",
    "sg:classifiers":[
        {
            "category":"Building & Trades",
            "subcategory":"Construction",
            "type":"Services"
        }
    ],
    "sg:phone":"+1   ",
    "sg:postcode":"18504",
    "sg:province":"PA",
    "sg:tags":[
        "housing",
        "family"
    ],
    "wof:name":"M R Construction Inc",
    "wof:placetype":"venue"
},
  "geometry": {"coordinates":[-75.677706,41.420869],"type":"Point"}
}