{
  "type": "Feature",
  "properties": {
    "addr:full":"110 Jeremy Ct Easton PA 18045",
    "addr:housenumber":"110",
    "addr:postcode":"18045",
    "addr:street":"Jeremy Ct",
    "iso:country":"US",
    "sg:address":"110 Jeremy Ct",
    "sg:city":"Easton",
    "sg:classifiers":[
        {
            "category":"Retail",
            "subcategory":"Animal Services",
            "type":"Services"
        }
    ],
    "sg:phone":"+1 610 348 1151",
    "sg:postcode":"18045",
    "sg:province":"PA",
    "sg:tags":[
        "pet",
        "boarding",
        "sitting"
    ],
    "wof:name":"Kritter Sitters",
    "wof:placetype":"venue"
},
  "geometry": {"coordinates":[-75.261038,40.716803],"type":"Point"}
}