{
  "type": "Feature",
  "properties": {
    "addr:full":"3423 Indian Queen Ln Philadelphia PA 19129",
    "addr:housenumber":"3423",
    "addr:postcode":"19129",
    "addr:street":"Indian Queen Ln",
    "iso:country":"US",
    "sg:address":"3423 Indian Queen Ln",
    "sg:city":"Philadelphia",
    "sg:classifiers":[
        {
            "category":"Professional",
            "subcategory":"Management & Consulting",
            "type":"Services"
        }
    ],
    "sg:phone":"+1   ",
    "sg:postcode":"19129",
    "sg:province":"PA",
    "sg:tags":[
        "public",
        "relations"
    ],
    "wof:name":"Noel David Sperry",
    "wof:placetype":"venue"
},
  "geometry": {"coordinates":[-75.18629799999999,40.011953],"type":"Point"}
}