{
  "type": "Feature",
  "properties": {
    "iso:country":"US",
    "sg:address":"1040 1st Ave",
    "sg:city":"King Of Prussia",
    "sg:classifiers":[
        {
            "category":"Food & Beverages",
            "subcategory":"Groceries & Convenience Stores",
            "type":"Retail Goods"
        }
    ],
    "sg:phone":"+1 610 354 8820",
    "sg:postcode":"19406",
    "sg:province":"PA",
    "sg:tags":[
        "market"
    ],
    "wof:name":"E Market Capital",
    "wof:placetype":"venue"
},
  "geometry": {"coordinates":[-75.408337,40.095183],"type":"Point"}
}