{
  "type": "Feature",
  "properties": {
    "iso:country":"US",
    "sg:address":"535 E Mahoning St",
    "sg:city":"Punxsutawney",
    "sg:classifiers":[
        {
            "category":"Restaurant",
            "type":"Food & Drink"
        }
    ],
    "sg:phone":"+1   ",
    "sg:postcode":"15767",
    "sg:province":"PA",
    "sg:tags":[
        "eating"
    ],
    "wof:name":"Luigis",
    "wof:placetype":"venue"
},
  "geometry": {"coordinates":[-78.96325299999999,40.944377],"type":"Point"}
}