{
  "type": "Feature",
  "properties": {
    "addr:full":"248 Bethel Church Rd Warfordsburg PA 17267",
    "addr:housenumber":"248",
    "addr:postcode":"17267",
    "addr:street":"Bethel Church Rd",
    "iso:country":"US",
    "sg:address":"248 Bethel Church Rd",
    "sg:city":"Warfordsburg",
    "sg:classifiers":[
        {
            "category":"Farming",
            "subcategory":"Farm",
            "type":"Manufacturing & Wholesale Goods"
        }
    ],
    "sg:phone":"+1   ",
    "sg:postcode":"17267",
    "sg:province":"PA",
    "sg:tags":[
        "crop",
        "general"
    ],
    "wof:name":"M&M Farms",
    "wof:placetype":"venue"
},
  "geometry": {"coordinates":[-78.191755,39.77922],"type":"Point"}
}