{
  "type": "Feature",
  "properties": {
    "iso:country":"US",
    "sg:address":"610 Reading Ave",
    "sg:city":"Reading",
    "sg:classifiers":[
        {
            "category":"Transit Center",
            "subcategory":"Freight",
            "type":"Transportation"
        },
        {
            "category":"Freight",
            "type":"Transportation"
        }
    ],
    "sg:phone":"+1 610 373 7886",
    "sg:postcode":"19611",
    "sg:province":"PA",
    "sg:tags":[
        "trucking-motor",
        "trucking"
    ],
    "wof:name":"Courtesy Transport Inc",
    "wof:placetype":"venue"
},
  "geometry": {"coordinates":[-75.949793,40.336872],"type":"Point"}
}