{
  "type": "Feature",
  "properties": {
    "addr:full":"451 Susquehanna Rd Huntingdon Valley PA 19006",
    "addr:housenumber":"451",
    "addr:postcode":"19006",
    "addr:street":"Susquehanna Rd",
    "iso:country":"US",
    "sg:address":"451 Susquehanna Rd",
    "sg:city":"Huntingdon Valley",
    "sg:classifiers":[
        {
            "category":"Home & Garden",
            "subcategory":"Carpets & Floor Coverings",
            "type":"Retail Goods"
        }
    ],
    "sg:phone":"+1   ",
    "sg:postcode":"19006",
    "sg:province":"PA",
    "wof:name":"Tri Store Mechanical",
    "wof:placetype":"venue"
},
  "geometry": {"coordinates":[-75.085763,40.093903],"type":"Point"}
}