{
  "type": "Feature",
  "properties": {
    "iso:country":"US",
    "sg:address":"1605 Powell Rd",
    "sg:city":"Coatesville",
    "sg:classifiers":[
        {
            "category":"Airport",
            "type":"Transportation"
        }
    ],
    "sg:phone":"+1   ",
    "sg:postcode":"19320",
    "sg:province":"PA",
    "wof:name":"Boone County Aero",
    "wof:placetype":"venue"
},
  "geometry": {"coordinates":[-75.736294,39.924121],"type":"Point"}
}