{
  "type": "Feature",
  "properties": {
    "iso:country":"US",
    "sg:address":"3790 Burns Rd",
    "sg:city":"Huntingdon Valley",
    "sg:classifiers":[
        {
            "category":"Retail",
            "subcategory":"Auto Repair",
            "type":"Services"
        }
    ],
    "sg:phone":"+1   ",
    "sg:postcode":"19006",
    "sg:province":"PA",
    "sg:tags":[
        "automotive",
        "general"
    ],
    "wof:name":"Vics Auto Repair",
    "wof:placetype":"venue"
},
  "geometry": {"coordinates":[-75.03545200000001,40.143128],"type":"Point"}
}