{
  "type": "Feature",
  "properties": {
    "addr:full":"514 Ridge Ave Media PA 19063",
    "addr:housenumber":"514",
    "addr:postcode":"19063",
    "addr:street":"Ridge Ave",
    "iso:country":"US",
    "sg:address":"514 Ridge Ave",
    "sg:city":"Media",
    "sg:classifiers":[
        {
            "category":"Professional",
            "subcategory":"Advertising",
            "type":"Services"
        }
    ],
    "sg:phone":"+1 610 566 4682",
    "sg:postcode":"19063",
    "sg:province":"PA",
    "sg:tags":[
        "product",
        "advertising-promotional",
        "specialty"
    ],
    "wof:name":"Mccorkle Promotions",
    "wof:placetype":"venue"
},
  "geometry": {"coordinates":[-75.40002200000001,39.894235],"type":"Point"}
}