{
  "type": "Feature",
  "properties": {
    "iso:country":"US",
    "sg:address":"35 S Manheim St",
    "sg:city":"Annville",
    "sg:classifiers":[
        {
            "category":"Organizations",
            "subcategory":"Community Association",
            "type":"Services"
        }
    ],
    "sg:phone":"+1   ",
    "sg:postcode":"17003",
    "sg:province":"PA",
    "wof:name":"American Legion Post 559",
    "wof:placetype":"venue"
},
  "geometry": {"coordinates":[-76.513904,40.329167],"type":"Point"}
}