{
  "type": "Feature",
  "properties": {
    "iso:country":"US",
    "sg:address":"942 Main St",
    "sg:city":"Honesdale",
    "sg:classifiers":[
        {
            "category":"Health Services",
            "subcategory":"Clinic",
            "type":"Services"
        }
    ],
    "sg:phone":"+1   ",
    "sg:postcode":"18431",
    "sg:province":"PA",
    "sg:tags":[
        "home",
        "care"
    ],
    "wof:name":"Interim Services",
    "wof:placetype":"venue"
},
  "geometry": {"coordinates":[-75.25675200000001,41.574065],"type":"Point"}
}