{
  "type": "Feature",
  "properties": {
    "iso:country":"US",
    "sg:address":"409 Paxinosa Rd E",
    "sg:city":"Easton",
    "sg:classifiers":[
        {
            "category":"Real Estate",
            "subcategory":"Real Estate Services",
            "type":"Services"
        },
        {
            "category":"Real Estate",
            "subcategory":"Real Estate Agent",
            "type":"Services"
        }
    ],
    "sg:phone":"+1 610 258 6113",
    "sg:postcode":"18040",
    "sg:province":"PA",
    "sg:tags":[
        "management"
    ],
    "wof:name":"Seymour Jacowitz",
    "wof:placetype":"venue"
},
  "geometry": {"coordinates":[-75.203553,40.713968],"type":"Point"}
}