{
  "type": "Feature",
  "properties": {
    "iso:country":"US",
    "sg:address":"1431 Pueblo Dr",
    "sg:city":"Pittsburgh",
    "sg:classifiers":[
        {
            "category":"Banks & Credit Unions",
            "subcategory":"Investment Brokerage",
            "type":"Services"
        }
    ],
    "sg:phone":"+1 412 343 4795",
    "sg:postcode":"15228",
    "sg:province":"PA",
    "sg:tags":[
        "investing"
    ],
    "wof:name":"Chiappetta Emily & Anthony J",
    "wof:placetype":"venue"
},
  "geometry": {"coordinates":[-80.046599,40.358352],"type":"Point"}
}