{
  "type": "Feature",
  "properties": {
    "iso:country":"US",
    "sg:address":"777 Nottingham Rd",
    "sg:city":"Peach Bottom",
    "sg:classifiers":[
        {
            "category":"Government",
            "subcategory":"Office",
            "type":"Public Place"
        }
    ],
    "sg:phone":"+1 717 548 3514",
    "sg:postcode":"17563",
    "sg:province":"PA",
    "sg:tags":[
        "village"
    ],
    "wof:name":"Fulton Township Supervisors",
    "wof:placetype":"venue"
},
  "geometry": {"coordinates":[-76.17447199999999,39.773644],"type":"Point"}
}