{
  "type": "Feature",
  "properties": {
    "iso:country":"US",
    "sg:address":"1790 Yardley Langhorne Rd",
    "sg:city":"Morrisville",
    "sg:classifiers":[
        {
            "category":"Health Services",
            "subcategory":"Optometrist",
            "type":"Services"
        }
    ],
    "sg:phone":"+1   ",
    "sg:postcode":"19067",
    "sg:province":"PA",
    "wof:name":"Reinholt Arthur B Od",
    "wof:placetype":"venue"
},
  "geometry": {"coordinates":[-74.87259899999999,40.22518],"type":"Point"}
}