{
  "type": "Feature",
  "properties": {
    "iso:country":"US",
    "sg:address":"1518 Walnut St Ste 1010",
    "sg:city":"Philadelphia",
    "sg:classifiers":[
        {
            "category":"Health Services",
            "subcategory":"Health Practitioner",
            "type":"Services"
        }
    ],
    "sg:phone":"+1 215 262 3103",
    "sg:postcode":"19102",
    "sg:province":"PA",
    "sg:tags":[
        "acupuncture"
    ],
    "sg:website":"www.healingwithease.net",
    "wof:name":"Ease",
    "wof:placetype":"venue"
},
  "geometry": {"coordinates":[-75.16693600000001,39.949638],"type":"Point"}
}