{
  "type": "Feature",
  "properties": {
    "iso:country":"US",
    "sg:address":"691 Washington Rd",
    "sg:city":"Pittsburgh",
    "sg:classifiers":[
        {
            "category":"Shopping",
            "subcategory":"Jewelry",
            "type":"Retail Goods"
        }
    ],
    "sg:phone":"+1 412 341 2299",
    "sg:postcode":"15228",
    "sg:province":"PA",
    "wof:name":"Kool Kat Designs",
    "wof:placetype":"venue"
},
  "geometry": {"coordinates":[-80.044301,40.380682],"type":"Point"}
}