{
  "type": "Feature",
  "properties": {
    "iso:country":"US",
    "sg:address":"769 N Lewis Rd",
    "sg:city":"Royersford",
    "sg:classifiers":[
        {
            "category":"Professional",
            "subcategory":"Lawyer & Legal Services",
            "type":"Services"
        }
    ],
    "sg:phone":"+1 610 495 5220",
    "sg:postcode":"19468",
    "sg:province":"PA",
    "sg:tags":[
        "attorney"
    ],
    "wof:name":"Peter Platten",
    "wof:placetype":"venue"
},
  "geometry": {"coordinates":[-75.534672,40.227504],"type":"Point"}
}