{
  "type": "Feature",
  "properties": {
    "addr:full":"1300 Virginia Dr Fort Washington PA 19034",
    "addr:housenumber":"1300",
    "addr:postcode":"19034",
    "addr:street":"Virginia Dr",
    "iso:country":"US",
    "sg:address":"1300 Virginia Dr",
    "sg:city":"Fort Washington",
    "sg:classifiers":[
        {
            "category":"Insurance",
            "subcategory":"Insurance Agent",
            "type":"Services"
        }
    ],
    "sg:phone":"+1   ",
    "sg:postcode":"19034",
    "sg:province":"PA",
    "sg:tags":[
        "broker"
    ],
    "wof:name":"Bankers Life",
    "wof:placetype":"venue"
},
  "geometry": {"coordinates":[-75.168792,40.142054],"type":"Point"}
}