{
  "type": "Feature",
  "properties": {
    "iso:country":"US",
    "sg:address":"147 W Dorrance St",
    "sg:city":"Kingston",
    "sg:classifiers":[
        {
            "category":"Shopping",
            "subcategory":"Bicycles & Sporting Goods",
            "type":"Retail Goods"
        }
    ],
    "sg:phone":"+1   ",
    "sg:postcode":"18704",
    "sg:province":"PA",
    "wof:name":"James Gun Clinic",
    "wof:placetype":"venue"
},
  "geometry": {"coordinates":[-75.891007,41.27413],"type":"Point"}
}