{
  "type": "Feature",
  "properties": {
    "iso:country":"US",
    "sg:address":"422 Dorset Rd",
    "sg:city":"Devon",
    "sg:classifiers":[
        {
            "category":"Professional",
            "type":"Services"
        }
    ],
    "sg:phone":"+1   ",
    "sg:postcode":"19333",
    "sg:province":"PA",
    "wof:name":"Veronica T Iorio",
    "wof:placetype":"venue"
},
  "geometry": {"coordinates":[-75.415842,40.039001],"type":"Point"}
}