{
  "type": "Feature",
  "properties": {
    "iso:country":"US",
    "sg:address":"436 N Oak Ave",
    "sg:city":"Clifton Heights",
    "sg:classifiers":[
        {
            "category":"Recreation",
            "type":"Entertainment"
        }
    ],
    "sg:phone":"+1 610 626 5119",
    "sg:postcode":"19018",
    "sg:province":"PA",
    "sg:tags":[
        "amusement"
    ],
    "wof:name":"Miss Margie's Pee Wee Gym",
    "wof:placetype":"venue"
},
  "geometry": {"coordinates":[-75.305395,39.931831],"type":"Point"}
}