{
  "type": "Feature",
  "properties": {
    "iso:country":"US",
    "sg:address":"1615 N West End Blvd",
    "sg:city":"Quakertown",
    "sg:classifiers":[
        {
            "category":"Building & Trades",
            "subcategory":"Landscaping Services",
            "type":"Services"
        }
    ],
    "sg:phone":"+1 215 538 7695",
    "sg:postcode":"18951",
    "sg:province":"PA",
    "sg:tags":[
        "landscape",
        "contractor"
    ],
    "wof:name":"Kaiser Landscaping Management",
    "wof:placetype":"venue"
},
  "geometry": {"coordinates":[-75.378041,40.486111],"type":"Point"}
}