{
  "type": "Feature",
  "properties": {
    "addr:full":"105 Grover Hollow Rd Genesee PA 16923",
    "addr:housenumber":"105",
    "addr:postcode":"16923",
    "addr:street":"Grover Hollow Rd",
    "iso:country":"US",
    "sg:address":"105 Grover Hollow Rd",
    "sg:city":"Genesee",
    "sg:classifiers":[
        {
            "category":"Organizations",
            "subcategory":"Religious Organization",
            "type":"Services"
        }
    ],
    "sg:phone":"+1 814 228 3605",
    "sg:postcode":"16923",
    "sg:province":"PA",
    "sg:tags":[
        "clergy"
    ],
    "wof:name":"Melvin Ternes",
    "wof:placetype":"venue"
},
  "geometry": {"coordinates":[-77.85647899999999,41.97626],"type":"Point"}
}