{
  "type": "Feature",
  "properties": {
    "iso:country":"US",
    "sg:address":"5661 N 5th St",
    "sg:city":"Philadelphia",
    "sg:classifiers":[
        {
            "category":"Utilities",
            "subcategory":"Mobile Phone",
            "type":"Services"
        },
        {
            "category":"Utilities",
            "subcategory":"Telephone",
            "type":"Services"
        },
        {
            "category":"Communications",
            "type":"Services"
        },
        {
            "category":"Manufacturing",
            "subcategory":"Electronics",
            "type":"Manufacturing & Wholesale Goods"
        }
    ],
    "sg:phone":"+1 215 276 0156",
    "sg:postcode":"19120",
    "sg:province":"PA",
    "sg:tags":[
        "telecommunications-equipment",
        "supply",
        "consultant",
        "system",
        "equipment",
        "cellular",
        "engineer"
    ],
    "wof:name":"United Telecard Alliance Inc",
    "wof:placetype":"venue"
},
  "geometry": {"coordinates":[-75.130313,40.037378],"type":"Point"}
}