{
  "type": "Feature",
  "properties": {
    "addr:full":"200 Park City Ctr Lancaster PA 17601",
    "addr:housenumber":"200",
    "addr:postcode":"17601",
    "addr:street":"Park",
    "iso:country":"US",
    "sg:address":"200 Park City Ctr",
    "sg:city":"Lancaster",
    "sg:classifiers":[
        {
            "category":"Professional",
            "subcategory":"Accounting & Tax Preparation",
            "type":"Services"
        },
        {
            "category":"Banks & Credit Unions",
            "subcategory":"Financial Services",
            "type":"Services"
        }
    ],
    "sg:phone":"+1 717 295 5511",
    "sg:postcode":"17601",
    "sg:province":"PA",
    "sg:tags":[
        "return",
        "preparation-business",
        "taxes-consultants",
        "loan",
        "reporting",
        "representative",
        "alternative",
        "bookkeeping"
    ],
    "sg:website":"http://www.hrblock.com",
    "wof:name":"H&R Block",
    "wof:placetype":"venue"
},
  "geometry": {"coordinates":[-76.340321,40.065512],"type":"Point"}
}