{
  "type": "Feature",
  "properties": {
    "iso:country":"US",
    "sg:address":"3370 Morris Rd",
    "sg:city":"Lansdale",
    "sg:classifiers":[
        {
            "category":"Wholesale",
            "subcategory":"Machinery & Supplies",
            "type":"Manufacturing & Wholesale Goods"
        },
        {
            "category":"Manufacturing",
            "subcategory":"Soap",
            "type":"Manufacturing & Wholesale Goods"
        }
    ],
    "sg:phone":"+1 610 584 6426",
    "sg:postcode":"19446",
    "sg:province":"PA",
    "sg:tags":[
        "detergent",
        "mfg"
    ],
    "wof:name":"Doris Harkins Enterprises",
    "wof:placetype":"venue"
},
  "geometry": {"coordinates":[-75.348298,40.225183],"type":"Point"}
}