{
  "type": "Feature",
  "properties": {
    "addr:full":"20 Cocalico Creek Rd Ephrata PA 17522",
    "addr:housenumber":"20",
    "addr:postcode":"17522",
    "addr:street":"Cocalico Creek Rd",
    "iso:country":"US",
    "sg:address":"20 Cocalico Creek Rd",
    "sg:city":"Ephrata",
    "sg:classifiers":[
        {
            "category":"Manufacturing",
            "subcategory":"Tools & Machinery",
            "type":"Manufacturing & Wholesale Goods"
        }
    ],
    "sg:phone":"+1 717 859 4977",
    "sg:postcode":"17522",
    "sg:province":"PA",
    "sg:tags":[
        "machine",
        "equipment",
        "woodworking",
        "shop",
        "supply"
    ],
    "wof:name":"Keystone Machinery Corporation",
    "wof:placetype":"venue"
},
  "geometry": {"coordinates":[-76.21188600000001,40.143895],"type":"Point"}
}