{
  "type": "Feature",
  "properties": {
    "iso:country":"US",
    "sg:address":"929 Mount Zion Rd",
    "sg:city":"Lebanon",
    "sg:classifiers":[
        {
            "category":"Professional",
            "subcategory":"Testing Lab",
            "type":"Services"
        }
    ],
    "sg:phone":"+1 717 274 8310",
    "sg:postcode":"17046",
    "sg:province":"PA",
    "sg:tags":[
        "correction",
        "radon"
    ],
    "wof:name":"Key Technology Inc",
    "wof:placetype":"venue"
},
  "geometry": {"coordinates":[-76.392213,40.367509],"type":"Point"}
}