{
  "type": "Feature",
  "properties": {
    "iso:country":"US",
    "sg:address":"1106 Providence Rd",
    "sg:city":"Springfield",
    "sg:classifiers":[
        {
            "category":"Building & Trades",
            "subcategory":"Electrical",
            "type":"Services"
        }
    ],
    "sg:phone":"+1 610 566 9090",
    "sg:postcode":"19064",
    "sg:province":"PA",
    "sg:tags":[
        "electric",
        "contractor"
    ],
    "wof:name":"Lex Electric Co",
    "wof:placetype":"venue"
},
  "geometry": {"coordinates":[-75.320019,39.915046],"type":"Point"}
}