{
  "type": "Feature",
  "properties": {
    "iso:country":"US",
    "sg:address":"222 W Edison Ave",
    "sg:city":"New Castle",
    "sg:classifiers":[
        {
            "category":"Health Services",
            "subcategory":"Nursing And Care Facility",
            "type":"Services"
        }
    ],
    "sg:phone":"+1 724 652 6340",
    "sg:postcode":"16101",
    "sg:province":"PA",
    "sg:tags":[
        "home",
        "skilled",
        "convalescent"
    ],
    "wof:name":"Indian Creek Nursing Center",
    "wof:placetype":"venue"
},
  "geometry": {"coordinates":[-80.352419,41.011112],"type":"Point"}
}