{
  "type": "Feature",
  "properties": {
    "iso:country":"US",
    "sg:address":"7001 W Chester Pike",
    "sg:city":"Upper Darby",
    "sg:classifiers":[
        {
            "category":"Shopping",
            "type":"Retail Goods"
        }
    ],
    "sg:phone":"+1 610 630 7654",
    "sg:postcode":"19082",
    "sg:province":"PA",
    "sg:tags":[
        "telephone",
        "cellular"
    ],
    "wof:name":"KNB Wireless",
    "wof:placetype":"venue"
},
  "geometry": {"coordinates":[-75.262478,39.961956],"type":"Point"}
}