{
  "type": "Feature",
  "properties": {
    "iso:country":"US",
    "sg:address":"403 W 10th St",
    "sg:city":"Erie",
    "sg:classifiers":[
        {
            "category":"Professional",
            "subcategory":"Accounting & Tax Preparation",
            "type":"Services"
        }
    ],
    "sg:phone":"+1 814 454 6317",
    "sg:postcode":"16502",
    "sg:province":"PA",
    "sg:tags":[
        "bookkeeping",
        "return",
        "public",
        "accountants-certified"
    ],
    "sg:website":"http://www.demarcowachter.com",
    "wof:name":"DeMarco, Wachter & Co",
    "wof:placetype":"venue"
},
  "geometry": {"coordinates":[-80.09115199999999,42.122354],"type":"Point"}
}