{
  "type": "Feature",
  "properties": {
    "addr:full":"252 Mill St Danville PA 17821",
    "addr:housenumber":"252",
    "addr:postcode":"17821",
    "addr:street":"Mill St",
    "iso:country":"US",
    "sg:address":"252 Mill St",
    "sg:city":"Danville",
    "sg:classifiers":[
        {
            "category":"Shopping",
            "subcategory":"Discount & Variety Stores",
            "type":"Retail Goods"
        }
    ],
    "sg:phone":"+1 570 275 6747",
    "sg:postcode":"17821",
    "sg:province":"PA",
    "wof:name":"Dollar General",
    "wof:placetype":"venue"
},
  "geometry": {"coordinates":[-76.6176,40.96199],"type":"Point"}
}