{
  "type": "Feature",
  "properties": {
    "addr:full":"1420 Harriet Ave Allentown PA 18103",
    "addr:housenumber":"1420",
    "addr:postcode":"18103",
    "addr:street":"Harriet Ave",
    "iso:country":"US",
    "sg:address":"1420 Harriet Ave",
    "sg:city":"Allentown",
    "sg:classifiers":[
        {
            "category":"Shopping",
            "subcategory":"Antiques",
            "type":"Retail Goods"
        }
    ],
    "sg:phone":"+1 610 797 9398",
    "sg:postcode":"18103",
    "sg:province":"PA",
    "wof:name":"Siegfried Randy Furniture Repair",
    "wof:placetype":"venue"
},
  "geometry": {"coordinates":[-75.421881,40.586909],"type":"Point"}
}