{
  "type": "Feature",
  "properties": {
    "iso:country":"US",
    "sg:address":"241 McAleer Rd",
    "sg:city":"Sewickley",
    "sg:classifiers":[
        {
            "category":"Professional",
            "subcategory":"Research",
            "type":"Services"
        }
    ],
    "sg:phone":"+1 412 367 0515",
    "sg:postcode":"15143",
    "sg:province":"PA",
    "sg:tags":[
        "environmental",
        "ecological"
    ],
    "wof:name":"United Environmental Group Inc",
    "wof:placetype":"venue"
},
  "geometry": {"coordinates":[-80.086303,40.556583],"type":"Point"}
}