{
  "type": "Feature",
  "properties": {
    "iso:country":"US",
    "sg:address":"128 Loller Rd Ste 201",
    "sg:city":"Hatboro",
    "sg:classifiers":[
        {
            "category":"Community Center",
            "subcategory":"Senior",
            "type":"Public Place"
        },
        {
            "category":"Social Services",
            "subcategory":"Job Training",
            "type":"Services"
        },
        {
            "category":"Health Services",
            "subcategory":"Nursing And Care Facility",
            "type":"Services"
        },
        {
            "category":"Health Services",
            "subcategory":"Health Practitioner",
            "type":"Services"
        }
    ],
    "sg:phone":"+1 215 672 8090",
    "sg:postcode":"19040",
    "sg:province":"PA",
    "sg:tags":[
        "home",
        "eldercare-home",
        "homes-skilled",
        "citizen"
    ],
    "wof:name":"Aging With Grace",
    "wof:placetype":"venue"
},
  "geometry": {"coordinates":[-75.114527,40.170347],"type":"Point"}
}