{
  "type": "Feature",
  "properties": {
    "addr:full":"10900 Knights Rd Philadelphia PA 19154",
    "addr:housenumber":"10900",
    "addr:postcode":"19154",
    "addr:street":"Knights Rd",
    "iso:country":"US",
    "sg:address":"10900 Knights Rd",
    "sg:city":"Philadelphia",
    "sg:classifiers":[
        {
            "category":"Health Services",
            "subcategory":"Doctor",
            "type":"Services"
        }
    ],
    "sg:phone":"+1   ",
    "sg:postcode":"19154",
    "sg:province":"PA",
    "sg:tags":[
        "medical"
    ],
    "wof:name":"Thomas J Leichner Jr MD",
    "wof:placetype":"venue"
},
  "geometry": {"coordinates":[-74.97985199999999,40.074732],"type":"Point"}
}