{
  "type": "Feature",
  "properties": {
    "addr:full":"3024 W 4th St Williamsport PA 17701",
    "addr:housenumber":"3024",
    "addr:postcode":"17701",
    "addr:street":"W 4Th St",
    "iso:country":"US",
    "sg:address":"3024 W 4th St",
    "sg:city":"Williamsport",
    "sg:classifiers":[
        {
            "category":"Manufacturing",
            "subcategory":"Tools & Machinery",
            "type":"Manufacturing & Wholesale Goods"
        }
    ],
    "sg:phone":"+1 570 322 1494",
    "sg:postcode":"17701",
    "sg:province":"PA",
    "sg:tags":[
        "machine",
        "shop"
    ],
    "wof:name":"Greenawalts Machine Shop",
    "wof:placetype":"venue"
},
  "geometry": {"coordinates":[-77.07275799999999,41.23615],"type":"Point"}
}