{
  "type": "Feature",
  "properties": {
    "iso:country":"US",
    "sg:address":"803 E Chelten Ave",
    "sg:city":"Philadelphia",
    "sg:classifiers":[
        {
            "category":"Personal",
            "subcategory":"Beauty Salon",
            "type":"Services"
        }
    ],
    "sg:phone":"+1 215 849 7363",
    "sg:postcode":"19138",
    "sg:province":"PA",
    "sg:tags":[
        "hair",
        "stylist"
    ],
    "wof:name":"Two Sisters African Hair Braid",
    "wof:placetype":"venue"
},
  "geometry": {"coordinates":[-75.164766,40.045549],"type":"Point"}
}