{
  "type": "Feature",
  "properties": {
    "iso:country":"US",
    "sg:address":"345 Market St",
    "sg:city":"Leechburg",
    "sg:classifiers":[
        {
            "category":"Organizations",
            "subcategory":"Community Association",
            "type":"Services"
        }
    ],
    "sg:phone":"+1   ",
    "sg:postcode":"15656",
    "sg:province":"PA",
    "wof:name":"Masonic Building Assoc of",
    "wof:placetype":"venue"
},
  "geometry": {"coordinates":[-79.60207800000001,40.626066],"type":"Point"}
}