{
  "type": "Feature",
  "properties": {
    "iso:country":"US",
    "sg:address":"2 W Lafayette St Ste 400",
    "sg:city":"Norristown",
    "sg:classifiers":[
        {
            "category":"Insurance",
            "subcategory":"Hazard Insurance",
            "type":"Services"
        }
    ],
    "sg:phone":"+1 610 992 3500",
    "sg:postcode":"19401",
    "sg:province":"PA",
    "sg:tags":[
        "commercial",
        "business"
    ],
    "wof:name":"Hub International Pa",
    "wof:placetype":"venue"
},
  "geometry": {"coordinates":[-75.34513099999999,40.113811],"type":"Point"}
}