{
  "type": "Feature",
  "properties": {
    "addr:full":"101 Sunridge Dr Pittsburgh PA 15234",
    "addr:housenumber":"101",
    "addr:postcode":"15234",
    "addr:street":"Sunridge Dr",
    "iso:country":"US",
    "sg:address":"101 Sunridge Dr",
    "sg:city":"Pittsburgh",
    "sg:classifiers":[
        {
            "category":"Shopping",
            "subcategory":"Bicycles & Sporting Goods",
            "type":"Retail Goods"
        }
    ],
    "sg:phone":"+1 412 833 1924",
    "sg:postcode":"15234",
    "sg:province":"PA",
    "sg:website":"www.coopersports.com",
    "wof:name":"Cooper Sports",
    "wof:placetype":"venue"
},
  "geometry": {"coordinates":[-80.04613999999999,40.355004],"type":"Point"}
}