{
  "type": "Feature",
  "properties": {
    "iso:country":"US",
    "sg:address":"RR 8",
    "sg:city":"Valencia",
    "sg:classifiers":[
        {
            "category":"Home & Garden",
            "subcategory":"Furniture",
            "type":"Retail Goods"
        }
    ],
    "sg:phone":"+1 724 898 3200",
    "sg:postcode":"16059",
    "sg:province":"PA",
    "sg:tags":[
        "store"
    ],
    "wof:name":"Wood'n Things",
    "wof:placetype":"venue"
},
  "geometry": {"coordinates":[-79.936203,40.702202],"type":"Point"}
}