{
  "type": "Feature",
  "properties": {
    "iso:country":"US",
    "sg:address":"120 E 21st St",
    "sg:city":"Northampton",
    "sg:classifiers":[
        {
            "category":"Building & Trades",
            "subcategory":"Electrical",
            "type":"Services"
        }
    ],
    "sg:phone":"+1 610 262 4101",
    "sg:postcode":"18067",
    "sg:province":"PA",
    "sg:tags":[
        "electrician",
        "contractor"
    ],
    "wof:name":"Schmidt Rick Electric Inc",
    "wof:placetype":"venue"
},
  "geometry": {"coordinates":[-75.497704,40.691002],"type":"Point"}
}