{
  "type": "Feature",
  "properties": {
    "iso:country":"US",
    "sg:address":"1812 State Hill Rd",
    "sg:city":"Reading",
    "sg:classifiers":[
        {
            "category":"Wholesale",
            "subcategory":"Metals & Minerals",
            "type":"Manufacturing & Wholesale Goods"
        }
    ],
    "sg:phone":"+1   ",
    "sg:postcode":"19610",
    "sg:province":"PA",
    "sg:tags":[
        "foundry",
        "center",
        "nonferrous"
    ],
    "wof:name":"Castings Co Inc",
    "wof:placetype":"venue"
},
  "geometry": {"coordinates":[-75.973843,40.338444],"type":"Point"}
}