{
  "type": "Feature",
  "properties": {
    "iso:country":"US",
    "sg:address":"741 Anaheim St",
    "sg:city":"Pittsburgh",
    "sg:classifiers":[
        {
            "category":"Shopping",
            "subcategory":"Gifts & Souvenirs",
            "type":"Retail Goods"
        }
    ],
    "sg:phone":"+1 412 621 6145",
    "sg:postcode":"15219",
    "sg:province":"PA",
    "sg:tags":[
        "novelty"
    ],
    "wof:name":"Rah Rah Rattle Company",
    "wof:placetype":"venue"
},
  "geometry": {"coordinates":[-79.961568,40.452412],"type":"Point"}
}