{
  "type": "Feature",
  "properties": {
    "addr:full":"1919 E Street Rd Bensalem PA 19020",
    "addr:housenumber":"1919",
    "addr:postcode":"19020",
    "addr:street":"E Street Rd",
    "iso:country":"US",
    "sg:address":"1919 E Street Rd",
    "sg:city":"Bensalem",
    "sg:classifiers":[
        {
            "category":"Food & Beverages",
            "subcategory":"Liquor & Beverages",
            "type":"Retail Goods"
        }
    ],
    "sg:phone":"+1 215 639 4790",
    "sg:postcode":"19020",
    "sg:province":"PA",
    "sg:tags":[
        "alcoholic"
    ],
    "wof:name":"Bensalem Beer & Soda Inc",
    "wof:placetype":"venue"
},
  "geometry": {"coordinates":[-74.945047,40.09618],"type":"Point"}
}