{
  "type": "Feature",
  "properties": {
    "iso:country":"US",
    "sg:address":"1480 W High St",
    "sg:city":"Pottstown",
    "sg:classifiers":[
        {
            "category":"Shopping",
            "subcategory":"Department Store",
            "type":"Retail Goods"
        }
    ],
    "sg:phone":"+1 610 718 9441",
    "sg:postcode":"19464",
    "sg:province":"PA",
    "sg:tags":[
        "shop"
    ],
    "wof:name":"Dollar General",
    "wof:placetype":"venue"
},
  "geometry": {"coordinates":[-75.68522400000001,40.2454],"type":"Point"}
}