{
  "type": "Feature",
  "properties": {
    "addr:full":"338 Bloomfield St Johnstown PA 15904",
    "addr:housenumber":"338",
    "addr:postcode":"15904",
    "addr:street":"Bloomfield St",
    "iso:country":"US",
    "sg:address":"338 Bloomfield St",
    "sg:city":"Johnstown",
    "sg:classifiers":[
        {
            "category":"Organizations",
            "subcategory":"Non-profit Organization",
            "type":"Services"
        },
        {
            "category":"Social Services",
            "subcategory":"Adult Care",
            "type":"Services"
        }
    ],
    "sg:phone":"+1 814 266 1829",
    "sg:postcode":"15904",
    "sg:province":"PA",
    "sg:tags":[
        "residential",
        "management"
    ],
    "wof:name":"Cambria Residential Services",
    "wof:placetype":"venue"
},
  "geometry": {"coordinates":[-78.84778300000001,40.274916],"type":"Point"}
}