{
  "type": "Feature",
  "properties": {
    "iso:country":"US",
    "sg:address":"777 Henderson Blvd",
    "sg:city":"Folcroft",
    "sg:classifiers":[
        {
            "category":"Airline",
            "type":"Transportation"
        }
    ],
    "sg:phone":"+1 610 532 6577",
    "sg:postcode":"19032",
    "sg:province":"PA",
    "sg:tags":[
        "cargo",
        "air"
    ],
    "wof:name":"Clare Freight Intl",
    "wof:placetype":"venue"
},
  "geometry": {"coordinates":[-75.279129,39.889842],"type":"Point"}
}