{
  "type": "Feature",
  "properties": {
    "iso:country":"US",
    "sg:address":"995 Fitzwatertown Rd",
    "sg:city":"Abington",
    "sg:classifiers":[
        {
            "category":"Utilities",
            "subcategory":"Refuse",
            "type":"Services"
        }
    ],
    "sg:phone":"+1 215 517 4112",
    "sg:postcode":"19001",
    "sg:province":"PA",
    "sg:tags":[
        "garbage",
        "collection"
    ],
    "wof:name":"Onyx Waste Svc Inc",
    "wof:placetype":"venue"
},
  "geometry": {"coordinates":[-75.159882,40.128494],"type":"Point"}
}