{
  "type": "Feature",
  "properties": {
    "iso:country":"US",
    "sg:address":"1040 Kenneth Ave",
    "sg:city":"New Kensington",
    "sg:classifiers":[
        {
            "category":"Organizations",
            "subcategory":"Religious Organization",
            "type":"Services"
        }
    ],
    "sg:phone":"+1   ",
    "sg:postcode":"15068",
    "sg:province":"PA",
    "wof:name":"Bibleway Christian Fellowship",
    "wof:placetype":"venue"
},
  "geometry": {"coordinates":[-79.76298300000001,40.567056],"type":"Point"}
}