{
  "type": "Feature",
  "properties": {
    "iso:country":"US",
    "sg:address":"4015 New Rodgers Rd",
    "sg:city":"Levittown",
    "sg:classifiers":[
        {
            "category":"Food & Beverages",
            "subcategory":"Groceries & Convenience Stores",
            "type":"Retail Goods"
        }
    ],
    "sg:phone":"+1 215 949 3020",
    "sg:postcode":"19056",
    "sg:province":"PA",
    "sg:tags":[
        "grocer"
    ],
    "wof:name":"Avdhut Cash & Carry",
    "wof:placetype":"venue"
},
  "geometry": {"coordinates":[-74.882801,40.129862],"type":"Point"}
}