{
  "type": "Feature",
  "properties": {
    "iso:country":"US",
    "sg:address":"3407 Grand Ave",
    "sg:city":"Pittsburgh",
    "sg:classifiers":[
        {
            "category":"Professional",
            "subcategory":"Management & Consulting",
            "type":"Services"
        }
    ],
    "sg:phone":"+1   ",
    "sg:postcode":"15225",
    "sg:province":"PA",
    "sg:tags":[
        "agency",
        "sales"
    ],
    "wof:name":"BK Engineered Sales",
    "wof:placetype":"venue"
},
  "geometry": {"coordinates":[-80.124002,40.509719],"type":"Point"}
}