{
  "type": "Feature",
  "properties": {
    "iso:country":"US",
    "sg:address":"5451 Marsden St",
    "sg:city":"Philadelphia",
    "sg:classifiers":[
        {
            "category":"Building & Trades",
            "subcategory":"Construction",
            "type":"Services"
        }
    ],
    "sg:phone":"+1 267 997 7165",
    "sg:postcode":"19124",
    "sg:province":"PA",
    "sg:tags":[
        "cabinet",
        "contractor",
        "maker",
        "carpentry"
    ],
    "wof:name":"Michael Gallus",
    "wof:placetype":"venue"
},
  "geometry": {"coordinates":[-75.06577,40.014973],"type":"Point"}
}