{
  "type": "Feature",
  "properties": {
    "iso:country":"US",
    "sg:address":"20125 Route 19",
    "sg:city":"Cranberry Twp",
    "sg:classifiers":[
        {
            "category":"Bakery",
            "type":"Food & Drink"
        }
    ],
    "sg:menulink":"http://www.allmenus.com/pa/cranberry/121357-krispy-kreme/menu/",
    "sg:phone":"+1 724 741 0600",
    "sg:postcode":"16066",
    "sg:province":"PA",
    "sg:tags":[
        "american",
        "pastry"
    ],
    "wof:name":"Krispy Kreme",
    "wof:placetype":"venue"
},
  "geometry": {"coordinates":[-80.10149199999999,40.683772],"type":"Point"}
}