{
  "type": "Feature",
  "properties": {
    "iso:country":"US",
    "sg:address":"538 E Street Rd",
    "sg:city":"Southampton",
    "sg:classifiers":[
        {
            "category":"Professional",
            "subcategory":"Art Services",
            "type":"Services"
        }
    ],
    "sg:phone":"+1 215 355 8197",
    "sg:postcode":"18966",
    "sg:province":"PA",
    "sg:tags":[
        "graphic",
        "designer"
    ],
    "wof:name":"Modern Graphix & Design",
    "wof:placetype":"venue"
},
  "geometry": {"coordinates":[-75.04614100000001,40.175736],"type":"Point"}
}