{
  "type": "Feature",
  "properties": {
    "addr:full":"618 Morton Ave Butler PA 16001",
    "addr:housenumber":"618",
    "addr:postcode":"16001",
    "addr:street":"Morton Ave",
    "iso:country":"US",
    "sg:address":"618 Morton Ave",
    "sg:city":"Butler",
    "sg:classifiers":[
        {
            "category":"Professional",
            "subcategory":"Computer Services",
            "type":"Services"
        }
    ],
    "sg:phone":"+1   ",
    "sg:postcode":"16001",
    "sg:province":"PA",
    "wof:name":"R&S Enterprises",
    "wof:placetype":"venue"
},
  "geometry": {"coordinates":[-79.888375,40.846797],"type":"Point"}
}