{
  "type": "Feature",
  "properties": {
    "addr:full":"1401 Astor St Norristown PA 19401",
    "addr:housenumber":"1401",
    "addr:postcode":"19401",
    "addr:street":"Astor St",
    "iso:country":"US",
    "sg:address":"1401 Astor St",
    "sg:city":"Norristown",
    "sg:classifiers":[
        {
            "category":"Building & Trades",
            "subcategory":"Cleaning & Sanitation",
            "type":"Services"
        }
    ],
    "sg:phone":"+1   ",
    "sg:postcode":"19401",
    "sg:province":"PA",
    "sg:tags":[
        "maintenance"
    ],
    "wof:name":"Neatfreaks Cleaning Service",
    "wof:placetype":"venue"
},
  "geometry": {"coordinates":[-75.33929500000001,40.12871],"type":"Point"}
}