{
  "type": "Feature",
  "properties": {
    "addr:full":"1115 Cochrans Mill Rd Pittsburgh PA 15236",
    "addr:housenumber":"1115",
    "addr:postcode":"15236",
    "addr:street":"Cochrans Mill Rd",
    "iso:country":"US",
    "sg:address":"1115 Cochrans Mill Rd",
    "sg:city":"Pittsburgh",
    "sg:classifiers":[
        {
            "category":"Wholesale",
            "subcategory":"Construction Materials",
            "type":"Manufacturing & Wholesale Goods"
        }
    ],
    "sg:phone":"+1   ",
    "sg:postcode":"15236",
    "sg:province":"PA",
    "sg:tags":[
        "window",
        "wood",
        "door",
        "sash",
        "frame"
    ],
    "wof:name":"Allpine Sash Company Inc",
    "wof:placetype":"venue"
},
  "geometry": {"coordinates":[-79.982663,40.321355],"type":"Point"}
}