{
  "type": "Feature",
  "properties": {
    "addr:full":"32 Maple Ln Newtown PA 18940",
    "addr:housenumber":"32",
    "addr:postcode":"18940",
    "addr:street":"Maple Ln",
    "iso:country":"US",
    "sg:address":"32 Maple Ln",
    "sg:city":"Newtown",
    "sg:classifiers":[
        {
            "category":"Building & Trades",
            "subcategory":"Construction",
            "type":"Services"
        }
    ],
    "sg:phone":"+1 215 579 7789",
    "sg:postcode":"18940",
    "sg:province":"PA",
    "sg:tags":[
        "painter"
    ],
    "sg:website":"www.scenicinnovations.com",
    "wof:name":"Scenic Innovations Inc",
    "wof:placetype":"venue"
},
  "geometry": {"coordinates":[-74.951048,40.241529],"type":"Point"}
}