{
  "type": "Feature",
  "properties": {
    "iso:country":"US",
    "sg:address":"676 Freeport Rd",
    "sg:city":"Freeport",
    "sg:classifiers":[
        {
            "category":"Farming",
            "subcategory":"Dairy Farm",
            "type":"Manufacturing & Wholesale Goods"
        }
    ],
    "sg:phone":"+1   ",
    "sg:postcode":"16229",
    "sg:province":"PA",
    "wof:name":"Roger Baker",
    "wof:placetype":"venue"
},
  "geometry": {"coordinates":[-79.641702,40.761061],"type":"Point"}
}