{
  "type": "Feature",
  "properties": {
    "iso:country":"US",
    "sg:address":"79 Greenwood Rd",
    "sg:city":"Belleville",
    "sg:classifiers":[
        {
            "category":"Building & Trades",
            "subcategory":"Construction",
            "type":"Services"
        }
    ],
    "sg:phone":"+1   ",
    "sg:postcode":"17004",
    "sg:province":"PA",
    "wof:name":"Ken Stoltzfus",
    "wof:placetype":"venue"
},
  "geometry": {"coordinates":[-77.731984,40.604829],"type":"Point"}
}