{
  "type": "Feature",
  "properties": {
    "iso:country":"US",
    "sg:address":"17 Main St",
    "sg:city":"Hop Bottom",
    "sg:classifiers":[
        {
            "category":"Restaurant",
            "type":"Food & Drink"
        }
    ],
    "sg:phone":"+1 570 289 0888",
    "sg:postcode":"18824",
    "sg:province":"PA",
    "wof:name":"Tubby's Deli",
    "wof:placetype":"venue"
},
  "geometry": {"coordinates":[-75.765916,41.705544],"type":"Point"}
}