{
  "type": "Feature",
  "properties": {
    "iso:country":"US",
    "sg:address":"1241 Mercer Grove City Rd",
    "sg:city":"Mercer",
    "sg:classifiers":[
        {
            "category":"Restaurant",
            "type":"Food & Drink"
        }
    ],
    "sg:phone":"+1   ",
    "sg:postcode":"16137",
    "sg:province":"PA",
    "sg:tags":[
        "eating"
    ],
    "wof:name":"Rudys Restaurant",
    "wof:placetype":"venue"
},
  "geometry": {"coordinates":[-80.18601099999999,41.205089],"type":"Point"}
}