{
  "type": "Feature",
  "properties": {
    "iso:country":"US",
    "sg:address":"714 E Francis Ave",
    "sg:city":"Connellsville",
    "sg:classifiers":[
        {
            "category":"Building & Trades",
            "subcategory":"Electrical",
            "type":"Services"
        }
    ],
    "sg:phone":"+1 724 628 8240",
    "sg:postcode":"15425",
    "sg:province":"PA",
    "sg:tags":[
        "electrical",
        "contractor"
    ],
    "wof:name":"City Electric Co",
    "wof:placetype":"venue"
},
  "geometry": {"coordinates":[-79.58130800000001,40.025791],"type":"Point"}
}