{
  "type": "Feature",
  "properties": {
    "iso:country":"US",
    "sg:address":"601 E Main St",
    "sg:city":"Norristown",
    "sg:classifiers":[
        {
            "category":"Personal",
            "subcategory":"Beauty Salon",
            "type":"Services"
        }
    ],
    "sg:phone":"+1 610 279 2027",
    "sg:postcode":"19401",
    "sg:province":"PA",
    "sg:tags":[
        "shop"
    ],
    "wof:name":"Shear Elegence's Hair Boutique",
    "wof:placetype":"venue"
},
  "geometry": {"coordinates":[-75.328063,40.108896],"type":"Point"}
}