{
  "type": "Feature",
  "properties": {
    "addr:full":"297 Pittsburgh Rd Butler PA 16002",
    "addr:housenumber":"297",
    "addr:postcode":"16002",
    "addr:street":"Pittsburgh Rd",
    "iso:country":"US",
    "sg:address":"297 Pittsburgh Rd",
    "sg:city":"Butler",
    "sg:classifiers":[
        {
            "category":"Shopping",
            "subcategory":"Computers & Home Electronics",
            "type":"Retail Goods"
        }
    ],
    "sg:phone":"+1   ",
    "sg:postcode":"16002",
    "sg:province":"PA",
    "wof:name":"Custom Auto",
    "wof:placetype":"venue"
},
  "geometry": {"coordinates":[-79.92756199999999,40.808968],"type":"Point"}
}