{
  "type": "Feature",
  "properties": {
    "iso:country":"US",
    "sg:address":"2500 W Somerset St",
    "sg:city":"Philadelphia",
    "sg:classifiers":[
        {
            "category":"Real Estate",
            "subcategory":"Real Estate Agent",
            "type":"Services"
        }
    ],
    "sg:phone":"+1 215 227 1650",
    "sg:postcode":"19132",
    "sg:province":"PA",
    "sg:tags":[
        "insurance"
    ],
    "wof:name":"Edwards Herbert Real Estate",
    "wof:placetype":"venue"
},
  "geometry": {"coordinates":[-75.171997,39.997898],"type":"Point"}
}