{
  "type": "Feature",
  "properties": {
    "iso:country":"US",
    "sg:address":"401 S Newtown Street Rd",
    "sg:city":"Newtown Square",
    "sg:classifiers":[
        {
            "category":"Professional",
            "subcategory":"Management & Consulting",
            "type":"Services"
        }
    ],
    "sg:phone":"+1   ",
    "sg:postcode":"19073",
    "sg:province":"PA",
    "sg:tags":[
        "educational",
        "technology",
        "sales"
    ],
    "wof:name":"Navarro & Associates Inc",
    "wof:placetype":"venue"
},
  "geometry": {"coordinates":[-75.39796200000001,39.969857],"type":"Point"}
}