{
  "type": "Feature",
  "properties": {
    "addr:full":"3758 Willow Ave Pittsburgh PA 15234",
    "addr:housenumber":"3758",
    "addr:postcode":"15234",
    "addr:street":"Willow Ave",
    "iso:country":"US",
    "sg:address":"3758 Willow Ave",
    "sg:city":"Pittsburgh",
    "sg:classifiers":[
        {
            "category":"Food & Beverages",
            "subcategory":"Groceries & Convenience Stores",
            "type":"Retail Goods"
        }
    ],
    "sg:phone":"+1 412 531 8411",
    "sg:postcode":"15234",
    "sg:province":"PA",
    "sg:tags":[
        "meat"
    ],
    "wof:name":"Moses Quality Market",
    "wof:placetype":"venue"
},
  "geometry": {"coordinates":[-80.021439,40.36575],"type":"Point"}
}