{
  "type": "Feature",
  "properties": {
    "iso:country":"US",
    "sg:address":"322 Conchester Hwy",
    "sg:city":"Glen Mills",
    "sg:classifiers":[
        {
            "category":"Sports & Exercise",
            "subcategory":"Golf",
            "type":"Entertainment"
        }
    ],
    "sg:phone":"+1 610 459 9973",
    "sg:postcode":"19342",
    "sg:province":"PA",
    "sg:tags":[
        "course"
    ],
    "wof:name":"Clayton Concord Golf Course",
    "wof:placetype":"venue"
},
  "geometry": {"coordinates":[-75.50037399999999,39.871225],"type":"Point"}
}