{
  "type": "Feature",
  "properties": {
    "addr:full":"5279 Lincoln Hwy Gap PA 17527",
    "addr:housenumber":"5279",
    "addr:postcode":"17527",
    "addr:street":"Lincoln Hwy",
    "iso:country":"US",
    "sg:address":"5279 Lincoln Hwy",
    "sg:city":"Gap",
    "sg:classifiers":[
        {
            "category":"Health Services",
            "subcategory":"Doctor",
            "type":"Services"
        },
        {
            "category":"Health Services",
            "subcategory":"Dentist",
            "type":"Services"
        }
    ],
    "sg:phone":"+1 717 442 9537",
    "sg:postcode":"17527",
    "sg:province":"PA",
    "sg:tags":[
        "dentists-oral",
        "physician",
        "maxillofacial",
        "dental",
        "surgeons",
        "clinic",
        "surgery",
        "oral"
    ],
    "wof:name":"Whitley Robert D DMD",
    "wof:placetype":"venue"
},
  "geometry": {"coordinates":[-76.02633299999999,39.992921],"type":"Point"}
}