{
  "type": "Feature",
  "properties": {
    "iso:country":"US",
    "sg:address":"3726 State Rte 257",
    "sg:city":"Seneca",
    "sg:classifiers":[
        {
            "category":"Professional",
            "subcategory":"Business Services",
            "type":"Services"
        }
    ],
    "sg:phone":"+1 814 676 8877",
    "sg:postcode":"16346",
    "sg:province":"PA",
    "wof:name":"Cranberry Tax Svc",
    "wof:placetype":"venue"
},
  "geometry": {"coordinates":[-79.70444999999999,41.397863],"type":"Point"}
}