{
  "type": "Feature",
  "properties": {
    "iso:country":"US",
    "sg:address":"2 Water St",
    "sg:city":"Washingtonville",
    "sg:classifiers":[
        {
            "category":"Bars & Pubs",
            "type":"Food & Drink"
        }
    ],
    "sg:phone":"+1 570 437 9113",
    "sg:postcode":"17884",
    "sg:province":"PA",
    "wof:name":"Dens' Grill & Bar",
    "wof:placetype":"venue"
},
  "geometry": {"coordinates":[-76.67597499999999,41.051629],"type":"Point"}
}