{
  "type": "Feature",
  "properties": {
    "addr:full":"421 Union Ave Kittanning PA 16201",
    "addr:housenumber":"421",
    "addr:postcode":"16201",
    "addr:street":"Union Ave",
    "iso:country":"US",
    "sg:address":"421 Union Ave",
    "sg:city":"Kittanning",
    "sg:classifiers":[
        {
            "category":"Organizations",
            "subcategory":"Membership Organization",
            "type":"Services"
        }
    ],
    "sg:phone":"+1 724 543 2331",
    "sg:postcode":"16201",
    "sg:province":"PA",
    "wof:name":"Child Evangelism Fellowship",
    "wof:placetype":"venue"
},
  "geometry": {"coordinates":[-79.520735,40.821154],"type":"Point"}
}