{
  "type": "Feature",
  "properties": {
    "addr:full":"711 S 52nd St Philadelphia PA 19143",
    "addr:housenumber":"711",
    "addr:postcode":"19143",
    "addr:street":"S 52Nd St",
    "iso:country":"US",
    "sg:address":"711 S 52nd St",
    "sg:city":"Philadelphia",
    "sg:classifiers":[
        {
            "category":"Manufacturing",
            "subcategory":"Printing",
            "type":"Manufacturing & Wholesale Goods"
        }
    ],
    "sg:phone":"+1 215 472 7778",
    "sg:postcode":"19143",
    "sg:province":"PA",
    "sg:tags":[
        "printer",
        "commercial"
    ],
    "wof:name":"711 Copy & Printing Ink2",
    "wof:placetype":"venue"
},
  "geometry": {"coordinates":[-75.22713299999999,39.948867],"type":"Point"}
}