{
  "type": "Feature",
  "properties": {
    "iso:country":"US",
    "sg:address":"117 Church St",
    "sg:city":"Big Run",
    "sg:classifiers":[
        {
            "category":"Organizations",
            "subcategory":"Religious Organization",
            "type":"Services"
        }
    ],
    "sg:phone":"+1 814 427 2974",
    "sg:postcode":"15715",
    "sg:province":"PA",
    "sg:tags":[
        "church"
    ],
    "wof:name":"Christian Church",
    "wof:placetype":"venue"
},
  "geometry": {"coordinates":[-78.87060099999999,40.969128],"type":"Point"}
}