{
  "type": "Feature",
  "properties": {
    "iso:country":"US",
    "sg:address":"458 E Broad St",
    "sg:city":"Tamaqua",
    "sg:classifiers":[
        {
            "category":"Health Services",
            "subcategory":"Chiropractor",
            "type":"Services"
        }
    ],
    "sg:phone":"+1 570 668 1300",
    "sg:postcode":"18252",
    "sg:province":"PA",
    "wof:name":"Trainer Chiropractic Office",
    "wof:placetype":"venue"
},
  "geometry": {"coordinates":[-75.96222899999999,40.797569],"type":"Point"}
}