{
  "type": "Feature",
  "properties": {
    "addr:full":"3047 Industrial Blvd Bethel Park PA 15102",
    "addr:housenumber":"3047",
    "addr:postcode":"15102",
    "addr:street":"Industrial Blvd",
    "iso:country":"US",
    "sg:address":"3047 Industrial Blvd",
    "sg:city":"Bethel Park",
    "sg:classifiers":[
        {
            "category":"Retail",
            "subcategory":"Auto Rental",
            "type":"Services"
        }
    ],
    "sg:phone":"+1   ",
    "sg:postcode":"15102",
    "sg:province":"PA",
    "sg:tags":[
        "truck"
    ],
    "wof:name":"Ryder",
    "wof:placetype":"venue"
},
  "geometry": {"coordinates":[-80.04385000000001,40.324937],"type":"Point"}
}