{
  "type": "Feature",
  "properties": {
    "addr:full":"1212 S Main Ave Scranton PA 18504",
    "addr:housenumber":"1212",
    "addr:postcode":"18504",
    "addr:street":"S Main Ave",
    "iso:country":"US",
    "sg:address":"1212 S Main Ave",
    "sg:city":"Scranton",
    "sg:classifiers":[
        {
            "category":"Education",
            "subcategory":"Dance Studio",
            "type":"Public Place"
        }
    ],
    "sg:phone":"+1 570 342 5436",
    "sg:postcode":"18504",
    "sg:province":"PA",
    "sg:tags":[
        "instruction",
        "dancing"
    ],
    "wof:name":"Dave Ragnacci School Of Dance",
    "wof:placetype":"venue"
},
  "geometry": {"coordinates":[-75.688061,41.399025],"type":"Point"}
}