{
  "type": "Feature",
  "properties": {
    "iso:country":"US",
    "sg:address":"955 Chesterbrook Blvd",
    "sg:city":"Wayne",
    "sg:classifiers":[
        {
            "category":"Real Estate",
            "subcategory":"Developer",
            "type":"Services"
        }
    ],
    "sg:phone":"+1   ",
    "sg:postcode":"19087",
    "sg:province":"PA",
    "sg:tags":[
        "development"
    ],
    "wof:name":"F V Associates",
    "wof:placetype":"venue"
},
  "geometry": {"coordinates":[-75.46213,40.066387],"type":"Point"}
}