{
  "type": "Feature",
  "properties": {
    "iso:country":"US",
    "sg:address":"924 River Oaks Dr",
    "sg:city":"Pittsburgh",
    "sg:classifiers":[
        {
            "category":"Real Estate",
            "subcategory":"Real Estate Agent",
            "type":"Services"
        }
    ],
    "sg:phone":"+1 412 782 3681",
    "sg:postcode":"15215",
    "sg:province":"PA",
    "wof:name":"Est Of J Bendel Associate",
    "wof:placetype":"venue"
},
  "geometry": {"coordinates":[-79.905604,40.496769],"type":"Point"}
}