{
  "type": "Feature",
  "properties": {
    "addr:full":"5 Sterling Rd Mount Pocono PA 18344",
    "addr:housenumber":"5",
    "addr:postcode":"18344",
    "addr:street":"Sterling Rd",
    "iso:country":"US",
    "sg:address":"5 Sterling Rd",
    "sg:city":"Mount Pocono",
    "sg:classifiers":[
        {
            "category":"Restaurant",
            "type":"Food & Drink"
        }
    ],
    "sg:menulink":"http://www.allmenus.com/pa/mount-pocono/72096-pizza-hut/menu/",
    "sg:phone":"+1 570 839 7753",
    "sg:postcode":"18344",
    "sg:province":"PA",
    "sg:tags":[
        "american",
        "pizza"
    ],
    "wof:name":"Pizza Hut",
    "wof:placetype":"venue"
},
  "geometry": {"coordinates":[-75.360462,41.138256],"type":"Point"}
}