{
  "type": "Feature",
  "properties": {
    "iso:country":"US",
    "sg:address":"181 Mikron Rd",
    "sg:city":"Bethlehem",
    "sg:classifiers":[
        {
            "category":"Manufacturing",
            "subcategory":"Metals",
            "type":"Manufacturing & Wholesale Goods"
        }
    ],
    "sg:phone":"+1 610 746 7401",
    "sg:postcode":"18020",
    "sg:province":"PA",
    "sg:tags":[
        "stampings"
    ],
    "wof:name":"CMSP USA",
    "wof:placetype":"venue"
},
  "geometry": {"coordinates":[-75.33727399999999,40.680276],"type":"Point"}
}