{
  "type": "Feature",
  "properties": {
    "iso:country":"US",
    "sg:address":"322 E College Ave",
    "sg:city":"State College",
    "sg:classifiers":[
        {
            "category":"Shopping",
            "subcategory":"Gifts & Souvenirs",
            "type":"Retail Goods"
        }
    ],
    "sg:phone":"+1 814 238 3040",
    "sg:postcode":"16801",
    "sg:province":"PA",
    "sg:tags":[
        "shop",
        "novelty"
    ],
    "wof:name":"Artifax",
    "wof:placetype":"venue"
},
  "geometry": {"coordinates":[-77.858073,40.796902],"type":"Point"}
}