{
  "type": "Feature",
  "properties": {
    "addr:full":"2981 Elizabethtown Rd Hershey PA 17022",
    "addr:housenumber":"2981",
    "addr:postcode":"17022",
    "addr:street":"Elizabethtown Rd",
    "iso:country":"US",
    "sg:address":"2981 Elizabethtown Rd",
    "sg:city":"Hershey",
    "sg:classifiers":[
        {
            "category":"Building & Trades",
            "subcategory":"Construction",
            "type":"Services"
        }
    ],
    "sg:phone":"+1 717 533 6565",
    "sg:postcode":"17022",
    "sg:province":"PA",
    "sg:tags":[
        "distributor",
        "blasting",
        "explosive"
    ],
    "sg:website":"www.hallexplosives.com",
    "wof:name":"Hall Explosives Inc",
    "wof:placetype":"venue"
},
  "geometry": {"coordinates":[-76.622529,40.232291],"type":"Point"}
}