{
  "type": "Feature",
  "properties": {
    "iso:country":"US",
    "sg:address":"413 Paper Mill Rd",
    "sg:city":"Glenside",
    "sg:classifiers":[
        {
            "category":"Professional",
            "subcategory":"Management & Consulting",
            "type":"Services"
        }
    ],
    "sg:phone":"+1 215 836 2383",
    "sg:postcode":"19038",
    "sg:province":"PA",
    "sg:tags":[
        "consultant",
        "business"
    ],
    "wof:name":"IPO Assoc LTD",
    "wof:placetype":"venue"
},
  "geometry": {"coordinates":[-75.209974,40.087993],"type":"Point"}
}