{
  "type": "Feature",
  "properties": {
    "addr:full":"1 Parish Park East Stroudsburg PA 18301",
    "addr:housenumber":"1",
    "addr:postcode":"18301",
    "addr:street":"Park East",
    "iso:country":"US",
    "sg:address":"1 Parish Park",
    "sg:city":"East Stroudsburg",
    "sg:classifiers":[
        {
            "category":"Real Estate",
            "subcategory":"Real Estate Operator",
            "type":"Services"
        }
    ],
    "sg:phone":"+1 570 420 1771",
    "sg:postcode":"18301",
    "sg:province":"PA",
    "sg:tags":[
        "apartment"
    ],
    "wof:name":"Prospect Hill Apartments",
    "wof:placetype":"venue"
},
  "geometry": {"coordinates":[-75.167902,40.989525],"type":"Point"}
}