{
  "type": "Feature",
  "properties": {
    "iso:country":"US",
    "sg:address":"34 N Corporation St",
    "sg:city":"Newville",
    "sg:classifiers":[
        {
            "category":"Sports & Exercise",
            "subcategory":"Gym",
            "type":"Entertainment"
        }
    ],
    "sg:phone":"+1 717 776 6888",
    "sg:postcode":"17241",
    "sg:province":"PA",
    "sg:tags":[
        "club",
        "health",
        "studio",
        "gymnasium"
    ],
    "wof:name":"Curves For Women",
    "wof:placetype":"venue"
},
  "geometry": {"coordinates":[-77.400423,40.176087],"type":"Point"}
}