{
  "type": "Feature",
  "properties": {
    "iso:country":"US",
    "sg:address":"896 Plaza Blvd",
    "sg:city":"Lancaster",
    "sg:classifiers":[
        {
            "category":"Shopping",
            "subcategory":"Musical Instruments",
            "type":"Retail Goods"
        }
    ],
    "sg:phone":"+1   ",
    "sg:postcode":"17601",
    "sg:province":"PA",
    "wof:name":"Don Randall Music & Arts Ctr",
    "wof:placetype":"venue"
},
  "geometry": {"coordinates":[-76.340974,40.07098],"type":"Point"}
}