{
  "type": "Feature",
  "properties": {
    "iso:country":"US",
    "sg:address":"820 Suismon St",
    "sg:city":"Pittsburgh",
    "sg:classifiers":[
        {
            "category":"Retail",
            "subcategory":"Auto Repair",
            "type":"Services"
        }
    ],
    "sg:phone":"+1 412 736 3477",
    "sg:postcode":"15212",
    "sg:province":"PA",
    "sg:tags":[
        "repairing",
        "automobile"
    ],
    "wof:name":"ANG Automotive",
    "wof:placetype":"venue"
},
  "geometry": {"coordinates":[-79.996887,40.455849],"type":"Point"}
}