{
  "type": "Feature",
  "properties": {
    "iso:country":"US",
    "sg:address":"3701 Perkiomen Ave",
    "sg:city":"Reading",
    "sg:classifiers":[
        {
            "category":"Real Estate",
            "subcategory":"Real Estate Agent",
            "type":"Services"
        }
    ],
    "sg:phone":"+1 610 779 1400",
    "sg:postcode":"19606",
    "sg:province":"PA",
    "wof:name":"Keystone Commercial & Ind",
    "wof:placetype":"venue"
},
  "geometry": {"coordinates":[-75.873418,40.317631],"type":"Point"}
}