{
  "type": "Feature",
  "properties": {
    "addr:full":"1670 Republic Rd Huntingdon Vly PA 19006",
    "addr:housenumber":"1670",
    "addr:postcode":"19006",
    "addr:street":"Republic Rd",
    "iso:country":"US",
    "sg:address":"1670 Republic Rd",
    "sg:city":"Huntingdon Vly",
    "sg:classifiers":[
        {
            "category":"Autos & Motor Vehicles",
            "subcategory":"Motorcycle Sales",
            "type":"Retail Goods"
        },
        {
            "category":"Wholesale",
            "subcategory":"Auto Parts",
            "type":"Manufacturing & Wholesale Goods"
        }
    ],
    "sg:phone":"+1 215 322 0415",
    "sg:postcode":"19006",
    "sg:province":"PA",
    "sg:tags":[
        "scooter"
    ],
    "wof:name":"Romaha Distributing Co",
    "wof:placetype":"venue"
},
  "geometry": {"coordinates":[-75.063097,40.161818],"type":"Point"}
}