{
  "type": "Feature",
  "properties": {
    "iso:country":"US",
    "sg:address":"1851 Chapman St",
    "sg:city":"Pittsburgh",
    "sg:classifiers":[
        {
            "category":"Manufacturing",
            "subcategory":"Tools & Machinery",
            "type":"Manufacturing & Wholesale Goods"
        }
    ],
    "sg:phone":"+1   ",
    "sg:postcode":"15215",
    "sg:province":"PA",
    "sg:tags":[
        "sun",
        "mfg",
        "glasses"
    ],
    "wof:name":"Tradewinds Eyewear LLC",
    "wof:placetype":"venue"
},
  "geometry": {"coordinates":[-79.919934,40.495397],"type":"Point"}
}