{
  "type": "Feature",
  "properties": {
    "iso:country":"US",
    "sg:address":"1555 Kleinfeltersville Rd",
    "sg:city":"Stevens",
    "sg:classifiers":[
        {
            "category":"Retail",
            "subcategory":"Auto Repair",
            "type":"Services"
        }
    ],
    "sg:phone":"+1 717 733 7468",
    "sg:postcode":"17578",
    "sg:province":"PA",
    "wof:name":"Paul W Landis",
    "wof:placetype":"venue"
},
  "geometry": {"coordinates":[-76.245192,40.253432],"type":"Point"}
}