{
  "type": "Feature",
  "properties": {
    "iso:country":"US",
    "sg:address":"3723 Elmwood Ave",
    "sg:city":"Erie",
    "sg:classifiers":[
        {
            "category":"Shopping",
            "type":"Retail Goods"
        }
    ],
    "sg:phone":"+1 814 866 9834",
    "sg:postcode":"16508",
    "sg:province":"PA",
    "sg:tags":[
        "hearing",
        "equipment",
        "supply",
        "impaired"
    ],
    "wof:name":"Alessi Hear Again Hearing Aid",
    "wof:placetype":"venue"
},
  "geometry": {"coordinates":[-80.092973,42.09274],"type":"Point"}
}