{
  "type": "Feature",
  "properties": {
    "addr:full":"10 Duff Rd Pittsburgh PA 15235",
    "addr:housenumber":"10",
    "addr:postcode":"15235",
    "addr:street":"Duff Rd",
    "iso:country":"US",
    "sg:address":"10 Duff Rd",
    "sg:city":"Pittsburgh",
    "sg:classifiers":[
        {
            "category":"Banks & Credit Unions",
            "subcategory":"Investment Brokerage",
            "type":"Services"
        },
        {
            "category":"Real Estate",
            "subcategory":"Real Estate Agent",
            "type":"Services"
        }
    ],
    "sg:phone":"+1 412 244 0500",
    "sg:postcode":"15235",
    "sg:province":"PA",
    "sg:tags":[
        "advisory",
        "management"
    ],
    "wof:name":"Duff Office Center",
    "wof:placetype":"venue"
},
  "geometry": {"coordinates":[-79.82852699999999,40.463958],"type":"Point"}
}