{
  "type": "Feature",
  "properties": {
    "iso:country":"US",
    "sg:address":"121 Furnace St",
    "sg:city":"Allentown",
    "sg:classifiers":[
        {
            "category":"Professional",
            "subcategory":"Lawyer & Legal Services",
            "type":"Services"
        }
    ],
    "sg:phone":"+1 610 776 1501",
    "sg:postcode":"18102",
    "sg:province":"PA",
    "sg:tags":[
        "attorney",
        "law",
        "business",
        "bankruptcy"
    ],
    "wof:name":"Winegar Wilhelm Glynn & Roemersma",
    "wof:placetype":"venue"
},
  "geometry": {"coordinates":[-75.461606,40.617456],"type":"Point"}
}