{
  "type": "Feature",
  "properties": {
    "iso:country":"US",
    "sg:address":"11 Beaver Dr",
    "sg:city":"Du Bois",
    "sg:classifiers":[
        {
            "category":"Health Services",
            "subcategory":"Doctor",
            "type":"Services"
        }
    ],
    "sg:phone":"+1 814 371 4970",
    "sg:postcode":"15801",
    "sg:province":"PA",
    "sg:tags":[
        "dentist"
    ],
    "wof:name":"Ronald N Statler DMD",
    "wof:placetype":"venue"
},
  "geometry": {"coordinates":[-78.756472,41.124448],"type":"Point"}
}