{
  "type": "Feature",
  "properties": {
    "iso:country":"US",
    "sg:address":"64 Shore Ave",
    "sg:city":"Douglassville",
    "sg:classifiers":[
        {
            "category":"Manufacturing",
            "subcategory":"Metals",
            "type":"Manufacturing & Wholesale Goods"
        }
    ],
    "sg:phone":"+1   ",
    "sg:postcode":"19518",
    "sg:province":"PA",
    "sg:tags":[
        "metalwork",
        "sheet",
        "mfg"
    ],
    "wof:name":"Boyertown Sheet Met Fbricators",
    "wof:placetype":"venue"
},
  "geometry": {"coordinates":[-75.73578000000001,40.317706],"type":"Point"}
}