{
  "type": "Feature",
  "properties": {
    "iso:country":"US",
    "sg:address":"42 Sequoia Dr",
    "sg:city":"Newtown",
    "sg:classifiers":[
        {
            "category":"Professional",
            "subcategory":"Management & Consulting",
            "type":"Services"
        }
    ],
    "sg:phone":"+1   ",
    "sg:postcode":"18940",
    "sg:province":"PA",
    "sg:tags":[
        "remediation",
        "environmental"
    ],
    "wof:name":"Brown Environmental Services",
    "wof:placetype":"venue"
},
  "geometry": {"coordinates":[-74.955079,40.264371],"type":"Point"}
}