{
  "type": "Feature",
  "properties": {
    "addr:full":"11632 Frankstown Rd Pittsburgh PA 15235",
    "addr:housenumber":"11632",
    "addr:postcode":"15235",
    "addr:street":"Frankstown Rd",
    "iso:country":"US",
    "sg:address":"11632 Frankstown Rd",
    "sg:city":"Pittsburgh",
    "sg:classifiers":[
        {
            "category":"Manufacturing",
            "subcategory":"Printing",
            "type":"Manufacturing & Wholesale Goods"
        }
    ],
    "sg:phone":"+1   ",
    "sg:postcode":"15235",
    "sg:province":"PA",
    "sg:tags":[
        "newspaper",
        "publication"
    ],
    "wof:name":"Sbn Magazine",
    "wof:placetype":"venue"
},
  "geometry": {"coordinates":[-79.828114,40.464943],"type":"Point"}
}