{
  "type": "Feature",
  "properties": {
    "addr:full":"44 S Antrim Way Greencastle PA 17225",
    "addr:housenumber":"44",
    "addr:postcode":"17225",
    "addr:street":"S Antrim Way",
    "iso:country":"US",
    "sg:address":"44 S Antrim Way",
    "sg:city":"Greencastle",
    "sg:classifiers":[
        {
            "category":"Sports & Exercise",
            "subcategory":"Gym",
            "type":"Entertainment"
        }
    ],
    "sg:phone":"+1 717 597 8737",
    "sg:postcode":"17225",
    "sg:province":"PA",
    "sg:tags":[
        "fitness",
        "physical",
        "facility"
    ],
    "wof:name":"Curves For Women",
    "wof:placetype":"venue"
},
  "geometry": {"coordinates":[-77.73125400000001,39.790746],"type":"Point"}
}