{
  "type": "Feature",
  "properties": {
    "addr:full":"25 Hitchcock Ln Glen Mills PA 19342",
    "addr:housenumber":"25",
    "addr:postcode":"19342",
    "addr:street":"Hitchcock Ln",
    "iso:country":"US",
    "sg:address":"25 Hitchcock Ln",
    "sg:city":"Glen Mills",
    "sg:classifiers":[
        {
            "category":"Professional",
            "type":"Services"
        }
    ],
    "sg:phone":"+1   ",
    "sg:postcode":"19342",
    "sg:province":"PA",
    "wof:name":"Gary Clingempeel",
    "wof:placetype":"venue"
},
  "geometry": {"coordinates":[-75.49646199999999,39.907911],"type":"Point"}
}