{
  "type": "Feature",
  "properties": {
    "iso:country":"US",
    "sg:address":"7942 Saltsburg Rd",
    "sg:city":"Pittsburgh",
    "sg:classifiers":[
        {
            "category":"Retail",
            "subcategory":"Auto Repair",
            "type":"Services"
        }
    ],
    "sg:phone":"+1   ",
    "sg:postcode":"15239",
    "sg:province":"PA",
    "sg:tags":[
        "automotive",
        "general"
    ],
    "wof:name":"Dale Shrleys Prof Auto Svc Ctr",
    "wof:placetype":"venue"
},
  "geometry": {"coordinates":[-79.76380899999999,40.476122],"type":"Point"}
}