{
  "type": "Feature",
  "properties": {
    "iso:country":"US",
    "sg:address":"1108 Dawn Dr",
    "sg:city":"West Chester",
    "sg:classifiers":[
        {
            "category":"Building & Trades",
            "subcategory":"Construction",
            "type":"Services"
        }
    ],
    "sg:phone":"+1   ",
    "sg:postcode":"19380",
    "sg:province":"PA",
    "sg:tags":[
        "house"
    ],
    "wof:name":"Pecone Homes",
    "wof:placetype":"venue"
},
  "geometry": {"coordinates":[-75.581034,39.974843],"type":"Point"}
}