{
  "type": "Feature",
  "properties": {
    "iso:country":"US",
    "sg:address":"44 Miller Ave",
    "sg:city":"Braddock",
    "sg:classifiers":[
        {
            "category":"Place Of Worship",
            "subcategory":"Church",
            "type":"Public Place"
        },
        {
            "category":"Place Of Worship",
            "type":"Public Place"
        }
    ],
    "sg:phone":"+1 412 271 2664",
    "sg:postcode":"15104",
    "sg:province":"PA",
    "sg:tags":[
        "churches-apostolic",
        "churches-pentecostal-apostolic"
    ],
    "wof:name":"Apostolic Faith Church",
    "wof:placetype":"venue"
},
  "geometry": {"coordinates":[-79.883653,40.415662],"type":"Point"}
}