{
  "type": "Feature",
  "properties": {
    "addr:full":"2401 W Allegheny Ave Philadelphia PA 19132",
    "addr:housenumber":"2401",
    "addr:postcode":"19132",
    "addr:street":"W Allegheny Ave",
    "iso:country":"US",
    "sg:address":"2401 W Allegheny Ave",
    "sg:city":"Philadelphia",
    "sg:classifiers":[
        {
            "category":"Retail",
            "subcategory":"Auto Repair",
            "type":"Services"
        }
    ],
    "sg:phone":"+1 215 227 7889",
    "sg:postcode":"19132",
    "sg:province":"PA",
    "sg:tags":[
        "repairing",
        "automobile"
    ],
    "wof:name":"K & M Auto Repair",
    "wof:placetype":"venue"
},
  "geometry": {"coordinates":[-75.16989599999999,40.003781],"type":"Point"}
}