{
  "type": "Feature",
  "properties": {
    "iso:country":"US",
    "sg:address":"101 W Frederick St",
    "sg:city":"Millersville",
    "sg:classifiers":[
        {
            "category":"Restaurant",
            "type":"Food & Drink"
        }
    ],
    "sg:menulink":"http://www.allmenus.com/pa/millersville/272249-house-of-pizza/menu/",
    "sg:phone":"+1 717 872 2131",
    "sg:postcode":"17551",
    "sg:province":"PA",
    "sg:tags":[
        "american",
        "pizza"
    ],
    "wof:name":"House of Pizza",
    "wof:placetype":"venue"
},
  "geometry": {"coordinates":[-76.35928699999999,39.996708],"type":"Point"}
}