{
  "type": "Feature",
  "properties": {
    "addr:full":"39344 Centerville Rd Centerville PA 16404",
    "addr:housenumber":"39344",
    "addr:postcode":"16404",
    "addr:street":"Centerville Rd",
    "iso:country":"US",
    "sg:address":"39344 Centerville Rd",
    "sg:city":"Centerville",
    "sg:classifiers":[
        {
            "category":"Government",
            "subcategory":"City Hall",
            "type":"Public Place"
        },
        {
            "category":"Government",
            "subcategory":"Office",
            "type":"Public Place"
        }
    ],
    "sg:phone":"+1 814 654 7730",
    "sg:postcode":"16404",
    "sg:province":"PA",
    "sg:tags":[
        "town",
        "township",
        "planner",
        "government-city",
        "village"
    ],
    "wof:name":"Borough Of Centerville",
    "wof:placetype":"venue"
},
  "geometry": {"coordinates":[-79.768051,41.735806],"type":"Point"}
}