{
  "type": "Feature",
  "properties": {
    "iso:country":"US",
    "sg:address":"323 Broadway",
    "sg:city":"Hanover",
    "sg:classifiers":[
        {
            "category":"Retail",
            "subcategory":"Veterinary Services",
            "type":"Services"
        }
    ],
    "sg:phone":"+1 717 632 6711",
    "sg:postcode":"17331",
    "sg:province":"PA",
    "sg:tags":[
        "hospital"
    ],
    "wof:name":"Hanover Veterinary Hospital",
    "wof:placetype":"venue"
},
  "geometry": {"coordinates":[-76.981072,39.803304],"type":"Point"}
}