{
  "type": "Feature",
  "properties": {
    "addr:full":"562 Coleman Ave Johnstown PA 15902",
    "addr:housenumber":"562",
    "addr:postcode":"15902",
    "addr:street":"Coleman Ave",
    "iso:country":"US",
    "sg:address":"562 Coleman Ave",
    "sg:city":"Johnstown",
    "sg:classifiers":[
        {
            "category":"Arts & Performance",
            "subcategory":"Theater",
            "type":"Entertainment"
        }
    ],
    "sg:phone":"+1 814 539 7173",
    "sg:postcode":"15902",
    "sg:province":"PA",
    "sg:tags":[
        "live",
        "music"
    ],
    "wof:name":"D J Dancin Dan",
    "wof:placetype":"venue"
},
  "geometry": {"coordinates":[-78.91180300000001,40.297384],"type":"Point"}
}