{
  "type": "Feature",
  "properties": {
    "addr:full":"805 Blakeslee Boulevard Dr E Lehighton PA 18235",
    "addr:housenumber":"805",
    "addr:postcode":"18235",
    "addr:street":"Blakeslee Boulevard Dr E",
    "iso:country":"US",
    "sg:address":"805 Blakeslee Boulevard Dr E",
    "sg:city":"Lehighton",
    "sg:classifiers":[
        {
            "category":"Banks & Credit Unions",
            "subcategory":"Investment Brokerage",
            "type":"Services"
        }
    ],
    "sg:phone":"+1   ",
    "sg:postcode":"18235",
    "sg:province":"PA",
    "sg:tags":[
        "dealer"
    ],
    "wof:name":"SunAmerica",
    "wof:placetype":"venue"
},
  "geometry": {"coordinates":[-75.721403,40.821079],"type":"Point"}
}