{
  "type": "Feature",
  "properties": {
    "addr:full":"27 W Market St Hellam PA 17406",
    "addr:housenumber":"27",
    "addr:postcode":"17406",
    "addr:street":"W Market St",
    "iso:country":"US",
    "sg:address":"27 W Market St",
    "sg:city":"Hellam",
    "sg:classifiers":[
        {
            "category":"Restaurant",
            "type":"Food & Drink"
        }
    ],
    "sg:phone":"+1 717 755 7510",
    "sg:postcode":"17406",
    "sg:province":"PA",
    "sg:tags":[
        "tea",
        "rooms"
    ],
    "wof:name":"Front Porch",
    "wof:placetype":"venue"
},
  "geometry": {"coordinates":[-76.60545399999999,40.004765],"type":"Point"}
}