{
  "type": "Feature",
  "properties": {
    "iso:country":"US",
    "sg:address":"175 King Rd",
    "sg:city":"Gettysburg",
    "sg:classifiers":[
        {
            "category":"Farming",
            "subcategory":"Dairy Farm",
            "type":"Manufacturing & Wholesale Goods"
        }
    ],
    "sg:phone":"+1   ",
    "sg:postcode":"17325",
    "sg:province":"PA",
    "wof:name":"Michael Danner",
    "wof:placetype":"venue"
},
  "geometry": {"coordinates":[-77.18886500000001,39.76355],"type":"Point"}
}