{
  "type": "Feature",
  "properties": {
    "addr:full":"364 Crooked Ln King Of Prussia PA 19406",
    "addr:housenumber":"364",
    "addr:postcode":"19406",
    "addr:street":"Crooked Ln",
    "iso:country":"US",
    "sg:address":"364 Crooked Ln",
    "sg:city":"King Of Prussia",
    "sg:classifiers":[
        {
            "category":"Building & Trades",
            "subcategory":"Construction",
            "type":"Services"
        }
    ],
    "sg:phone":"+1 610 277 5100",
    "sg:postcode":"19406",
    "sg:province":"PA",
    "sg:tags":[
        "concrete",
        "contractor"
    ],
    "wof:name":"Dorie Construction Co Inc",
    "wof:placetype":"venue"
},
  "geometry": {"coordinates":[-75.347819,40.09121],"type":"Point"}
}