{
  "type": "Feature",
  "properties": {
    "iso:country":"US",
    "sg:address":"300 Rising Sun Ln",
    "sg:city":"Millersburg",
    "sg:classifiers":[
        {
            "category":"Insurance",
            "subcategory":"Hazard Insurance",
            "type":"Services"
        },
        {
            "category":"Insurance",
            "subcategory":"Insurance Agent",
            "type":"Services"
        },
        {
            "category":"Insurance",
            "subcategory":"Life Insurance",
            "type":"Services"
        }
    ],
    "sg:phone":"+1 717 692 4717",
    "sg:postcode":"17061",
    "sg:province":"PA",
    "sg:tags":[
        "auto",
        "commercial",
        "business"
    ],
    "sg:website":"http://www.erdmanagency.com",
    "wof:name":"The Erdman Agency",
    "wof:placetype":"venue"
},
  "geometry": {"coordinates":[-76.94455,40.541851],"type":"Point"}
}