{
  "type": "Feature",
  "properties": {
    "iso:country":"US",
    "sg:address":"1052 Highland Ave",
    "sg:city":"Ambridge",
    "sg:classifiers":[
        {
            "category":"Building & Trades",
            "subcategory":"Construction",
            "type":"Services"
        }
    ],
    "sg:phone":"+1 724 266 6730",
    "sg:postcode":"15003",
    "sg:province":"PA",
    "sg:tags":[
        "contractor"
    ],
    "wof:name":"C & M Contracting",
    "wof:placetype":"venue"
},
  "geometry": {"coordinates":[-80.214589,40.594162],"type":"Point"}
}