{
  "type": "Feature",
  "properties": {
    "addr:full":"56 N Main St Washington PA 15301",
    "addr:housenumber":"56",
    "addr:postcode":"15301",
    "addr:street":"N Main St",
    "iso:country":"US",
    "sg:address":"56 N Main St",
    "sg:city":"Washington",
    "sg:classifiers":[
        {
            "category":"Museum",
            "type":"Entertainment"
        }
    ],
    "sg:phone":"+1 724 225 4663",
    "sg:postcode":"15301",
    "sg:province":"PA",
    "sg:tags":[
        "gallery",
        "merchandise"
    ],
    "wof:name":"World West Galleries",
    "wof:placetype":"venue"
},
  "geometry": {"coordinates":[-80.245608,40.171774],"type":"Point"}
}