{
  "type": "Feature",
  "properties": {
    "iso:country":"US",
    "sg:address":"800 Court St",
    "sg:city":"Sunbury",
    "sg:classifiers":[
        {
            "category":"Health Services",
            "subcategory":"Nursing And Care Facility",
            "type":"Services"
        }
    ],
    "sg:phone":"+1   ",
    "sg:postcode":"17801",
    "sg:province":"PA",
    "sg:tags":[
        "skilled"
    ],
    "wof:name":"Manorcare Hlth Srvices-Sunbury",
    "wof:placetype":"venue"
},
  "geometry": {"coordinates":[-76.786439,40.859077],"type":"Point"}
}