{
  "type": "Feature",
  "properties": {
    "addr:full":"723 Foster Rd Cheltenham PA 19012",
    "addr:housenumber":"723",
    "addr:postcode":"19012",
    "addr:street":"Foster Rd",
    "iso:country":"US",
    "sg:address":"723 Foster Rd",
    "sg:city":"Cheltenham",
    "sg:classifiers":[
        {
            "category":"Education",
            "subcategory":"Special Training",
            "type":"Public Place"
        }
    ],
    "sg:phone":"+1 215 663 1775",
    "sg:postcode":"19012",
    "sg:province":"PA",
    "sg:tags":[
        "instruction",
        "music"
    ],
    "wof:name":"Livinston School Of Music",
    "wof:placetype":"venue"
},
  "geometry": {"coordinates":[-75.099204,40.060649],"type":"Point"}
}