{
  "type": "Feature",
  "properties": {
    "iso:country":"US",
    "sg:address":"240 N Chester Rd",
    "sg:city":"West Chester",
    "sg:classifiers":[
        {
            "category":"Recreation",
            "type":"Entertainment"
        },
        {
            "category":"Travel",
            "subcategory":"Campground",
            "type":"Entertainment"
        }
    ],
    "sg:phone":"+1 610 644 1435",
    "sg:postcode":"19380",
    "sg:province":"PA",
    "sg:tags":[
        "camp"
    ],
    "sg:website":"www.arrowheaddaycamp.com",
    "wof:name":"Arrowhead Day Camp Inc",
    "wof:placetype":"venue"
},
  "geometry": {"coordinates":[-75.531083,39.971214],"type":"Point"}
}