{
  "type": "Feature",
  "properties": {
    "iso:country":"US",
    "sg:address":"4300 Silverwood St",
    "sg:city":"Philadelphia",
    "sg:classifiers":[
        {
            "category":"Park",
            "type":"Public Place"
        }
    ],
    "sg:postcode":"19127",
    "sg:province":"PA",
    "wof:name":"Pretzel Park",
    "wof:placetype":"venue"
},
  "geometry": {"coordinates":[-75.220884,40.026063],"type":"Point"}
}