{
  "type": "Feature",
  "properties": {
    "iso:country":"US",
    "sg:address":"1912 Philadelphia Ave",
    "sg:city":"Chambersburg",
    "sg:classifiers":[
        {
            "category":"Manufacturing",
            "subcategory":"Printing",
            "type":"Manufacturing & Wholesale Goods"
        }
    ],
    "sg:phone":"+1 717 264 0400",
    "sg:postcode":"17201",
    "sg:province":"PA",
    "sg:tags":[
        "printer"
    ],
    "wof:name":"Minuteman Press",
    "wof:placetype":"venue"
},
  "geometry": {"coordinates":[-77.642094,39.959356],"type":"Point"}
}