{
  "type": "Feature",
  "properties": {
    "addr:full":"12458 Gearhart Rd Greencastle PA 17225",
    "addr:postcode":"12458;17225",
    "addr:street":"Gearhart Rd",
    "iso:country":"US",
    "sg:address":"12458 Gearhart Rd",
    "sg:city":"Greencastle",
    "sg:phone":"+1   ",
    "sg:postcode":"17225",
    "sg:province":"PA",
    "sg:tags":[
        "farm",
        "field",
        "crop"
    ],
    "wof:name":"Martin Mahlon",
    "wof:placetype":"venue"
},
  "geometry": {"coordinates":[-77.679125,39.771186],"type":"Point"}
}