{
  "type": "Feature",
  "properties": {
    "iso:country":"US",
    "sg:address":"10892 Tanyard Hill Rd",
    "sg:city":"Orrstown",
    "sg:classifiers":[
        {
            "category":"Farming",
            "subcategory":"Livestock Farm",
            "type":"Manufacturing & Wholesale Goods"
        }
    ],
    "sg:phone":"+1   ",
    "sg:postcode":"17244",
    "sg:province":"PA",
    "sg:tags":[
        "beef",
        "feedlot",
        "cattle"
    ],
    "wof:name":"Harold Kyle",
    "wof:placetype":"venue"
},
  "geometry": {"coordinates":[-77.61893999999999,40.061448],"type":"Point"}
}