{
  "type": "Feature",
  "properties": {
    "iso:country":"US",
    "sg:address":"368 Pine Run Rd",
    "sg:city":"Doylestown",
    "sg:classifiers":[
        {
            "category":"Professional",
            "subcategory":"Detective & Security Services",
            "type":"Services"
        }
    ],
    "sg:phone":"+1 215 340 2206",
    "sg:postcode":"18901",
    "sg:province":"PA",
    "sg:tags":[
        "private",
        "investigator"
    ],
    "wof:name":"D Boyle",
    "wof:placetype":"venue"
},
  "geometry": {"coordinates":[-75.157838,40.321918],"type":"Point"}
}