{
  "type": "Feature",
  "properties": {
    "addr:full":"9 Pennsylvania Ave Corry PA 16407",
    "addr:housenumber":"9",
    "addr:postcode":"16407",
    "addr:street":"Pennsylvania Ave",
    "iso:country":"US",
    "sg:address":"9 Pennsylvania Ave",
    "sg:city":"Corry",
    "sg:classifiers":[
        {
            "category":"Manufacturing",
            "subcategory":"Metals",
            "type":"Manufacturing & Wholesale Goods"
        }
    ],
    "sg:phone":"+1 814 664 9069",
    "sg:postcode":"16407",
    "sg:province":"PA",
    "sg:tags":[
        "stamping"
    ],
    "wof:name":"Chase Manufacturing",
    "wof:placetype":"venue"
},
  "geometry": {"coordinates":[-79.634179,41.921792],"type":"Point"}
}