{
  "type": "Feature",
  "properties": {
    "addr:full":"315 S Allen St State College PA 16801",
    "addr:housenumber":"315",
    "addr:postcode":"16801",
    "addr:street":"S Allen St",
    "iso:country":"US",
    "sg:address":"315 S Allen St",
    "sg:city":"State College",
    "sg:classifiers":[
        {
            "category":"Government",
            "subcategory":"Office",
            "type":"Public Place"
        }
    ],
    "sg:phone":"+1   ",
    "sg:postcode":"16801",
    "sg:province":"PA",
    "sg:tags":[
        "fish",
        "wildlife"
    ],
    "wof:name":"Pennsylvania Ecological Svcs",
    "wof:placetype":"venue"
},
  "geometry": {"coordinates":[-77.857929,40.792146],"type":"Point"}
}