{
  "type": "Feature",
  "properties": {
    "iso:country":"US",
    "sg:address":"650 Ridge Dr",
    "sg:city":"Danville",
    "sg:classifiers":[
        {
            "category":"Restaurant",
            "type":"Food & Drink"
        }
    ],
    "sg:phone":"+1   ",
    "sg:postcode":"17821",
    "sg:province":"PA",
    "sg:tags":[
        "eating"
    ],
    "wof:name":"Susquehanna Chef",
    "wof:placetype":"venue"
},
  "geometry": {"coordinates":[-76.547963,40.95757],"type":"Point"}
}