{
  "type": "Feature",
  "properties": {
    "iso:country":"US",
    "sg:address":"615 S Washington Ave",
    "sg:city":"Jermyn",
    "sg:classifiers":[
        {
            "category":"Restaurant",
            "type":"Food & Drink"
        }
    ],
    "sg:phone":"+1 570 876 4411",
    "sg:postcode":"18433",
    "sg:province":"PA",
    "wof:name":"Longworth's Restaurant",
    "wof:placetype":"venue"
},
  "geometry": {"coordinates":[-75.544791,41.532015],"type":"Point"}
}