{
  "type": "Feature",
  "properties": {
    "iso:country":"US",
    "sg:address":"2422 S 17th St",
    "sg:city":"Philadelphia",
    "sg:classifiers":[
        {
            "category":"Organizations",
            "subcategory":"Religious Organization",
            "type":"Services"
        }
    ],
    "sg:phone":"+1   ",
    "sg:postcode":"19145",
    "sg:province":"PA",
    "wof:name":"Saint Monica Convent",
    "wof:placetype":"venue"
},
  "geometry": {"coordinates":[-75.17533,39.921262],"type":"Point"}
}