{
  "type": "Feature",
  "properties": {
    "iso:country":"US",
    "sg:address":"4158 Library Rd",
    "sg:city":"Pittsburgh",
    "sg:classifiers":[
        {
            "category":"Sports & Exercise",
            "subcategory":"Gym",
            "type":"Entertainment"
        }
    ],
    "sg:phone":"+1 412 563 1807",
    "sg:postcode":"15234",
    "sg:province":"PA",
    "sg:tags":[
        "pilate",
        "yoga"
    ],
    "sg:website":"www.phipilatesstudio.com",
    "wof:name":"Phi Pilates Studio",
    "wof:placetype":"venue"
},
  "geometry": {"coordinates":[-80.028611,40.356879],"type":"Point"}
}