{
  "type": "Feature",
  "properties": {
    "iso:country":"US",
    "sg:address":"480 Cooks Mill Rd",
    "sg:city":"Hyndman",
    "sg:classifiers":[
        {
            "category":"Train Station",
            "subcategory":"Rail",
            "type":"Transportation"
        }
    ],
    "sg:phone":"+1 814 842 9632",
    "sg:postcode":"15545",
    "sg:province":"PA",
    "sg:tags":[
        "railroad"
    ],
    "wof:name":"Csx",
    "wof:placetype":"venue"
},
  "geometry": {"coordinates":[-78.740306,39.75032],"type":"Point"}
}