{
  "type": "Feature",
  "properties": {
    "iso:country":"US",
    "sg:address":"6100 Walton Ave",
    "sg:city":"Philadelphia",
    "sg:classifiers":[
        {
            "category":"Food & Beverages",
            "subcategory":"Groceries & Convenience Stores",
            "type":"Retail Goods"
        }
    ],
    "sg:phone":"+1 215 471 6505",
    "sg:postcode":"19143",
    "sg:province":"PA",
    "sg:tags":[
        "grocer"
    ],
    "wof:name":"Walton Avenue Grocery Inc",
    "wof:placetype":"venue"
},
  "geometry": {"coordinates":[-75.246844,39.952188],"type":"Point"}
}