{
  "type": "Feature",
  "properties": {
    "addr:full":"1001 E College Ave Bellefonte PA 16823",
    "addr:housenumber":"1001",
    "addr:postcode":"16823",
    "addr:street":"E College Ave",
    "iso:country":"US",
    "sg:address":"1001 E College Ave",
    "sg:city":"Bellefonte",
    "sg:classifiers":[
        {
            "category":"Manufacturing",
            "subcategory":"Petroleum Products",
            "type":"Manufacturing & Wholesale Goods"
        }
    ],
    "sg:phone":"+1 814 359 3462",
    "sg:postcode":"16823",
    "sg:province":"PA",
    "sg:tags":[
        "asphalt"
    ],
    "wof:name":"Eby Paving & Construction",
    "wof:placetype":"venue"
},
  "geometry": {"coordinates":[-77.684499,40.906797],"type":"Point"}
}