{
  "type": "Feature",
  "properties": {
    "iso:country":"US",
    "sg:address":"116 Lake St",
    "sg:city":"Stoneboro",
    "sg:classifiers":[
        {
            "category":"Professional",
            "type":"Services"
        }
    ],
    "sg:phone":"+1 724 376 7376",
    "sg:postcode":"16153",
    "sg:province":"PA",
    "sg:tags":[
        "establishment"
    ],
    "wof:name":"Kargo Quality Cars & Truck Inc",
    "wof:placetype":"venue"
},
  "geometry": {"coordinates":[-80.10714299999999,41.34112],"type":"Point"}
}