{
  "type": "Feature",
  "properties": {
    "addr:full":"6089 Fountain Rd Zionsville PA 18092",
    "addr:housenumber":"6089",
    "addr:postcode":"18092",
    "addr:street":"Fountain Rd",
    "iso:country":"US",
    "sg:address":"6089 Fountain Rd",
    "sg:city":"Zionsville",
    "sg:classifiers":[
        {
            "category":"Shopping",
            "subcategory":"Used Merchandise",
            "type":"Retail Goods"
        }
    ],
    "sg:phone":"+1 610 967 4742",
    "sg:postcode":"18092",
    "sg:province":"PA",
    "wof:name":"Grave Country Period Antiques",
    "wof:placetype":"venue"
},
  "geometry": {"coordinates":[-75.523757,40.482812],"type":"Point"}
}