{
  "type": "Feature",
  "properties": {
    "iso:country":"US",
    "sg:address":"115 E Bell Ave",
    "sg:city":"Altoona",
    "sg:classifiers":[
        {
            "category":"Professional",
            "subcategory":"Art Services",
            "type":"Services"
        }
    ],
    "sg:phone":"+1 814 931 4977",
    "sg:postcode":"16602",
    "sg:province":"PA",
    "sg:tags":[
        "taxidermist"
    ],
    "wof:name":"All Seasons Taxidermy",
    "wof:placetype":"venue"
},
  "geometry": {"coordinates":[-78.380472,40.519571],"type":"Point"}
}