{
  "type": "Feature",
  "properties": {
    "iso:country":"US",
    "sg:address":"362 S Front St",
    "sg:city":"Steelton",
    "sg:classifiers":[
        {
            "category":"Taxi",
            "type":"Transportation"
        },
        {
            "category":"Airline",
            "type":"Transportation"
        }
    ],
    "sg:phone":"+1 717 939 6363",
    "sg:postcode":"17113",
    "sg:province":"PA",
    "sg:tags":[
        "shuttle",
        "airport"
    ],
    "wof:name":"Capital City Cab Service",
    "wof:placetype":"venue"
},
  "geometry": {"coordinates":[-76.834,40.230301],"type":"Point"}
}