{
  "type": "Feature",
  "properties": {
    "addr:full":"3401 Grand Ave Pittsburgh PA 15225",
    "addr:housenumber":"3401",
    "addr:postcode":"15225",
    "addr:street":"Grand Ave",
    "iso:country":"US",
    "sg:address":"3401 Grand Ave",
    "sg:city":"Pittsburgh",
    "sg:classifiers":[
        {
            "category":"Manufacturing",
            "subcategory":"Printing",
            "type":"Manufacturing & Wholesale Goods"
        }
    ],
    "sg:phone":"+1 412 777 5101",
    "sg:postcode":"15225",
    "sg:province":"PA",
    "sg:tags":[
        "periodical"
    ],
    "wof:name":"Press Power",
    "wof:placetype":"venue"
},
  "geometry": {"coordinates":[-80.12403399999999,40.509731],"type":"Point"}
}