{
  "type": "Feature",
  "properties": {
    "addr:full":"1174 Jefferson Heights Rd Pittsburgh PA 15235",
    "addr:housenumber":"1174",
    "addr:postcode":"15235",
    "addr:street":"Jefferson Heights Rd",
    "iso:country":"US",
    "sg:address":"1174 Jefferson Heights Rd",
    "sg:city":"Pittsburgh",
    "sg:classifiers":[
        {
            "category":"Restaurant",
            "type":"Food & Drink"
        }
    ],
    "sg:menulink":"http://www.allmenus.com/pa/penn-hills/287060-bradlios-pizzeria/menu/",
    "sg:phone":"+1 412 374 9011",
    "sg:postcode":"15235",
    "sg:province":"PA",
    "sg:tags":[
        "american",
        "pizza"
    ],
    "wof:name":"Bradlios Pizzeria",
    "wof:placetype":"venue"
},
  "geometry": {"coordinates":[-79.813355,40.44531],"type":"Point"}
}