{
  "type": "Feature",
  "properties": {
    "iso:country":"US",
    "sg:address":"4011 Edgmont Ave",
    "sg:city":"Brookhaven",
    "sg:classifiers":[
        {
            "category":"Restaurant",
            "type":"Food & Drink"
        }
    ],
    "sg:menulink":"http://www.allmenus.com/pa/brookhaven/17147-abruzzi-pizza/menu/",
    "sg:phone":"+1 610 874 9220",
    "sg:postcode":"19015",
    "sg:province":"PA",
    "sg:tags":[
        "american",
        "pizza"
    ],
    "wof:name":"Abruzzi Pizza",
    "wof:placetype":"venue"
},
  "geometry": {"coordinates":[-75.38758,39.872335],"type":"Point"}
}