{
  "type": "Feature",
  "properties": {
    "iso:country":"US",
    "sg:address":"305 Old Kennett Rd",
    "sg:city":"Kennett Square",
    "sg:classifiers":[
        {
            "category":"Shopping",
            "subcategory":"Bicycles & Sporting Goods",
            "type":"Retail Goods"
        }
    ],
    "sg:phone":"+1 610 444 0482",
    "sg:postcode":"19348",
    "sg:province":"PA",
    "sg:tags":[
        "gun",
        "gunsmith"
    ],
    "wof:name":"Pete's Outdoor Store",
    "wof:placetype":"venue"
},
  "geometry": {"coordinates":[-75.664168,39.82452],"type":"Point"}
}