{
  "type": "Feature",
  "properties": {
    "iso:country":"US",
    "sg:address":"1182 Park Ave",
    "sg:city":"Meadville",
    "sg:classifiers":[
        {
            "category":"Retail",
            "subcategory":"Auto Repair",
            "type":"Services"
        }
    ],
    "sg:phone":"+1 814 333 4137",
    "sg:postcode":"16335",
    "sg:province":"PA",
    "sg:tags":[
        "repairing",
        "automobile"
    ],
    "wof:name":"Carpenter's Automotive Svc",
    "wof:placetype":"venue"
},
  "geometry": {"coordinates":[-80.15519,41.631643],"type":"Point"}
}