{
  "type": "Feature",
  "properties": {
    "addr:full":"626 W Penn Ave Reading PA 19608",
    "addr:housenumber":"626",
    "addr:postcode":"19608",
    "addr:street":"W Penn Ave",
    "iso:country":"US",
    "sg:address":"626 W Penn Ave",
    "sg:city":"Reading",
    "sg:classifiers":[
        {
            "category":"Personal",
            "subcategory":"Beauty Salon",
            "type":"Services"
        }
    ],
    "sg:phone":"+1 610 478 7167",
    "sg:postcode":"19608",
    "sg:province":"PA",
    "wof:name":"Kids Cuts",
    "wof:placetype":"venue"
},
  "geometry": {"coordinates":[-76.024821,40.325092],"type":"Point"}
}