{
  "type": "Feature",
  "properties": {
    "iso:country":"US",
    "sg:address":"1202 Market St",
    "sg:city":"Lewisburg",
    "sg:classifiers":[
        {
            "category":"Professional",
            "subcategory":"Lawyer & Legal Services",
            "type":"Services"
        }
    ],
    "sg:phone":"+1 570 524 6020",
    "sg:postcode":"17837",
    "sg:province":"PA",
    "sg:tags":[
        "attorney"
    ],
    "wof:name":"Brian Kerstetter Law Office",
    "wof:placetype":"venue"
},
  "geometry": {"coordinates":[-76.896272,40.959387],"type":"Point"}
}