{
  "type": "Feature",
  "properties": {
    "iso:country":"US",
    "sg:address":"1127 Northern Blvd",
    "sg:city":"Clarks Summit",
    "sg:classifiers":[
        {
            "category":"Restaurant",
            "type":"Food & Drink"
        }
    ],
    "sg:menulink":"http://www.allmenus.com/pa/south-abington/205986-mcdonalds/menu/",
    "sg:phone":"+1 570 585 0209",
    "sg:postcode":"18411",
    "sg:province":"PA",
    "sg:tags":[
        "burger",
        "american"
    ],
    "wof:name":"McDonald's",
    "wof:placetype":"venue"
},
  "geometry": {"coordinates":[-75.685388,41.478807],"type":"Point"}
}