{
  "type": "Feature",
  "properties": {
    "iso:country":"US",
    "sg:address":"PO Box 1833",
    "sg:city":"Cranberry Twp",
    "sg:classifiers":[
        {
            "category":"Shopping",
            "subcategory":"Florist",
            "type":"Retail Goods"
        }
    ],
    "sg:phone":"+1 724 776 3953",
    "sg:postcode":"16066",
    "sg:province":"PA",
    "wof:name":"Lasting Expressions",
    "wof:placetype":"venue"
},
  "geometry": {"coordinates":[-80.1045,40.697399],"type":"Point"}
}