{
  "type": "Feature",
  "properties": {
    "iso:country":"US",
    "sg:address":"1939 Makefield Rd",
    "sg:city":"Yardley",
    "sg:classifiers":[
        {
            "category":"Social Services",
            "subcategory":"Child Care",
            "type":"Services"
        }
    ],
    "sg:phone":"+1 215 369 0733",
    "sg:postcode":"19067",
    "sg:province":"PA",
    "wof:name":"Kids Care Pensbury",
    "wof:placetype":"venue"
},
  "geometry": {"coordinates":[-74.81964499999999,40.222526],"type":"Point"}
}