{
  "type": "Feature",
  "properties": {
    "iso:country":"US",
    "sg:address":"1599 State Rd",
    "sg:city":"Croydon",
    "sg:classifiers":[
        {
            "category":"Manufacturing",
            "subcategory":"Metals",
            "type":"Manufacturing & Wholesale Goods"
        },
        {
            "category":"Building & Trades",
            "subcategory":"Construction",
            "type":"Services"
        },
        {
            "category":"Manufacturing",
            "subcategory":"Building Materials",
            "type":"Manufacturing & Wholesale Goods"
        }
    ],
    "sg:phone":"+1 215 785 1333",
    "sg:postcode":"19021",
    "sg:province":"PA",
    "sg:tags":[
        "work-manufacturers",
        "fabricator",
        "work",
        "sheet",
        "welder"
    ],
    "wof:name":"R M S Mfg",
    "wof:placetype":"venue"
},
  "geometry": {"coordinates":[-74.89669000000001,40.089298],"type":"Point"}
}