{
  "type": "Feature",
  "properties": {
    "iso:country":"US",
    "sg:address":"824 Paxinosa Ave",
    "sg:city":"Easton",
    "sg:classifiers":[
        {
            "category":"Building & Trades",
            "subcategory":"Construction",
            "type":"Services"
        }
    ],
    "sg:phone":"+1   ",
    "sg:postcode":"18042",
    "sg:province":"PA",
    "sg:tags":[
        "contractor"
    ],
    "wof:name":"Cross Cntry Fd Svc Installers",
    "wof:placetype":"venue"
},
  "geometry": {"coordinates":[-75.20456,40.707215],"type":"Point"}
}