{
  "type": "Feature",
  "properties": {
    "iso:country":"US",
    "sg:address":"1286 Washington Pike",
    "sg:city":"Bridgeville",
    "sg:classifiers":[
        {
            "category":"Retail",
            "subcategory":"Auto Repair",
            "type":"Services"
        }
    ],
    "sg:phone":"+1 412 221 8801",
    "sg:postcode":"15017",
    "sg:province":"PA",
    "sg:tags":[
        "automobile",
        "rustproofing",
        "undercoating"
    ],
    "wof:name":"Elias Rust-Proofing & Coating",
    "wof:placetype":"venue"
},
  "geometry": {"coordinates":[-80.098922,40.374178],"type":"Point"}
}