{
  "type": "Feature",
  "properties": {
    "iso:country":"US",
    "sg:address":"100 Banyon Dr",
    "sg:city":"Pittsburgh",
    "sg:classifiers":[
        {
            "category":"Personal",
            "subcategory":"Beauty Salon",
            "type":"Services"
        }
    ],
    "sg:phone":"+1 412 247 3643",
    "sg:postcode":"15235",
    "sg:province":"PA",
    "wof:name":"Moj African Hair Braiding",
    "wof:placetype":"venue"
},
  "geometry": {"coordinates":[-79.834053,40.46619],"type":"Point"}
}