{
  "type": "Feature",
  "properties": {
    "iso:country":"US",
    "sg:address":"9630 Bustleton Ave",
    "sg:city":"Philadelphia",
    "sg:classifiers":[
        {
            "category":"Health Services",
            "subcategory":"Doctor",
            "type":"Services"
        }
    ],
    "sg:phone":"+1 215 969 0300",
    "sg:postcode":"19115",
    "sg:province":"PA",
    "sg:tags":[
        "physician",
        "surgeon"
    ],
    "wof:name":"Dr Igor Benenson",
    "wof:placetype":"venue"
},
  "geometry": {"coordinates":[-75.034868,40.088061],"type":"Point"}
}