{
  "type": "Feature",
  "properties": {
    "addr:full":"637 Easterly Pkwy State College PA 16801",
    "addr:housenumber":"637",
    "addr:postcode":"16801",
    "addr:street":"Easterly Pkwy",
    "iso:country":"US",
    "sg:address":"637 Easterly Pkwy",
    "sg:city":"State College",
    "sg:classifiers":[
        {
            "category":"Professional",
            "subcategory":"Advertising",
            "type":"Services"
        }
    ],
    "sg:phone":"+1 814 231 0505",
    "sg:postcode":"16801",
    "sg:province":"PA",
    "sg:tags":[
        "counselor"
    ],
    "wof:name":"Fran Fisher & Assoc",
    "wof:placetype":"venue"
},
  "geometry": {"coordinates":[-77.844369,40.794634],"type":"Point"}
}