{
  "type": "Feature",
  "properties": {
    "iso:country":"US",
    "sg:address":"1060 Zeigler Rd",
    "sg:city":"Wellsville",
    "sg:classifiers":[
        {
            "category":"Education",
            "subcategory":"School",
            "type":"Public Place"
        }
    ],
    "sg:phone":"+1 717 432 8696",
    "sg:postcode":"17365",
    "sg:province":"PA",
    "wof:name":"Wellsville Elementary School",
    "wof:placetype":"venue"
},
  "geometry": {"coordinates":[-76.937999,40.050171],"type":"Point"}
}