{
  "type": "Feature",
  "properties": {
    "iso:country":"US",
    "sg:address":"131 Washington St",
    "sg:city":"East Greenville",
    "sg:classifiers":[
        {
            "category":"Manufacturing",
            "subcategory":"Food",
            "type":"Manufacturing & Wholesale Goods"
        }
    ],
    "sg:phone":"+1 215 679 2603",
    "sg:postcode":"18041",
    "sg:province":"PA",
    "sg:tags":[
        "ice"
    ],
    "wof:name":"Nolt's Ice Plant",
    "wof:placetype":"venue"
},
  "geometry": {"coordinates":[-75.498379,40.404035],"type":"Point"}
}