{
  "type": "Feature",
  "properties": {
    "iso:country":"US",
    "sg:address":"2221 Forster St Ste G13",
    "sg:city":"Harrisburg",
    "sg:classifiers":[
        {
            "category":"Government",
            "subcategory":"Office",
            "type":"Public Place"
        }
    ],
    "sg:phone":"+1 717 787 7003",
    "sg:postcode":"17103",
    "sg:province":"PA",
    "sg:tags":[
        "government-united",
        "state"
    ],
    "sg:website":"http://www.penndotcrm.org",
    "wof:name":"External Audit Division",
    "wof:placetype":"venue"
},
  "geometry": {"coordinates":[-76.857778,40.277014],"type":"Point"}
}