{
  "type": "Feature",
  "properties": {
    "addr:full":"3401 N Broad St Philadelphia PA 19140",
    "addr:housenumber":"3401",
    "addr:postcode":"19140",
    "addr:street":"N Broad St",
    "iso:country":"US",
    "sg:address":"3401 N Broad St",
    "sg:city":"Philadelphia",
    "sg:classifiers":[
        {
            "category":"Health Services",
            "subcategory":"Doctor",
            "type":"Services"
        }
    ],
    "sg:phone":"+1 215 707 3851",
    "sg:postcode":"19140",
    "sg:province":"PA",
    "sg:tags":[
        "physician",
        "surgeon"
    ],
    "wof:name":"Jackson Chevalier Clinic",
    "wof:placetype":"venue"
},
  "geometry": {"coordinates":[-75.15191900000001,40.006167],"type":"Point"}
}