{
  "type": "Feature",
  "properties": {
    "addr:full":"1400 N Providence Rd Media PA 19063",
    "addr:housenumber":"1400",
    "addr:postcode":"19063",
    "addr:street":"N Providence Rd",
    "iso:country":"US",
    "sg:address":"1400 N Providence Rd",
    "sg:city":"Media",
    "sg:classifiers":[
        {
            "category":"Banks & Credit Unions",
            "subcategory":"Investment Brokerage",
            "type":"Services"
        }
    ],
    "sg:phone":"+1 484 621 0012",
    "sg:postcode":"19063",
    "sg:province":"PA",
    "sg:tags":[
        "advisory"
    ],
    "wof:name":"Apache Investments",
    "wof:placetype":"venue"
},
  "geometry": {"coordinates":[-75.391273,39.935322],"type":"Point"}
}