{
  "type": "Feature",
  "properties": {
    "iso:country":"US",
    "sg:address":"1618 Mall Run Rd",
    "sg:city":"Uniontown",
    "sg:classifiers":[
        {
            "category":"Shopping",
            "subcategory":"Jewelry",
            "type":"Retail Goods"
        }
    ],
    "sg:phone":"+1 724 437 0888",
    "sg:postcode":"15401",
    "sg:province":"PA",
    "sg:tags":[
        "jeweler"
    ],
    "wof:name":"Edmunds Art Carved Diamond Ctr",
    "wof:placetype":"venue"
},
  "geometry": {"coordinates":[-79.745189,39.905774],"type":"Point"}
}