{
  "type": "Feature",
  "properties": {
    "iso:country":"US",
    "sg:address":"1700 W Street Rd",
    "sg:city":"Warrington",
    "sg:classifiers":[
        {
            "category":"Organizations",
            "subcategory":"Non-profit Organization",
            "type":"Services"
        },
        {
            "category":"Health Services",
            "subcategory":"Clinic",
            "type":"Services"
        }
    ],
    "sg:phone":"+1 215 491 0166",
    "sg:postcode":"18976",
    "sg:province":"PA",
    "sg:tags":[
        "info",
        "residential",
        "specialty",
        "drug",
        "outpatient",
        "abuse",
        "treatment",
        "addiction",
        "care"
    ],
    "sg:website":"www.projecttransition.com",
    "wof:name":"Project Transition",
    "wof:placetype":"venue"
},
  "geometry": {"coordinates":[-75.12893699999999,40.223349],"type":"Point"}
}