{
  "type": "Feature",
  "properties": {
    "iso:country":"US",
    "sg:address":"1113 Church Rd",
    "sg:city":"East Greenville",
    "sg:classifiers":[
        {
            "category":"Professional",
            "subcategory":"Employment Agencies",
            "type":"Services"
        }
    ],
    "sg:phone":"+1   ",
    "sg:postcode":"18041",
    "sg:province":"PA",
    "wof:name":"Edward K Hildenbrand Mrs Rn",
    "wof:placetype":"venue"
},
  "geometry": {"coordinates":[-75.514456,40.402163],"type":"Point"}
}