{
  "type": "Feature",
  "properties": {
    "iso:country":"US",
    "sg:address":"514 Ridgewood Rd",
    "sg:city":"Shippenville",
    "sg:classifiers":[
        {
            "category":"Building & Trades",
            "subcategory":"Plumbing",
            "type":"Services"
        }
    ],
    "sg:phone":"+1   ",
    "sg:postcode":"16254",
    "sg:province":"PA",
    "sg:tags":[
        "refrigeration"
    ],
    "wof:name":"Mackinney Mechanical",
    "wof:placetype":"venue"
},
  "geometry": {"coordinates":[-79.42488400000001,41.246838],"type":"Point"}
}