{
  "type": "Feature",
  "properties": {
    "iso:country":"US",
    "sg:address":"65 N Main St",
    "sg:city":"Shrewsbury",
    "sg:classifiers":[
        {
            "category":"Social Services",
            "type":"Services"
        }
    ],
    "sg:phone":"+1 717 235 9441",
    "sg:postcode":"17361",
    "sg:province":"PA",
    "wof:name":"Accessible Cpr & First Aid",
    "wof:placetype":"venue"
},
  "geometry": {"coordinates":[-76.67833,39.759745],"type":"Point"}
}