{
  "type": "Feature",
  "properties": {
    "iso:country":"US",
    "sg:address":"311 Porter Ave",
    "sg:city":"Scottdale",
    "sg:classifiers":[
        {
            "category":"Freight",
            "type":"Transportation"
        }
    ],
    "sg:phone":"+1 724 887 7550",
    "sg:postcode":"15683",
    "sg:province":"PA",
    "sg:tags":[
        "operator",
        "local",
        "trucking"
    ],
    "wof:name":"Snyder Reon Trucking",
    "wof:placetype":"venue"
},
  "geometry": {"coordinates":[-79.57993500000001,40.109321],"type":"Point"}
}