{
  "type": "Feature",
  "properties": {
    "iso:country":"US",
    "sg:address":"14 W Pauline Dr",
    "sg:city":"Clearfield",
    "sg:classifiers":[
        {
            "category":"Home & Garden",
            "subcategory":"Carpets & Floor Coverings",
            "type":"Retail Goods"
        }
    ],
    "sg:phone":"+1 814 238 5552",
    "sg:postcode":"16830",
    "sg:province":"PA",
    "sg:tags":[
        "dealer",
        "rug"
    ],
    "wof:name":"Floor Coverings Intl",
    "wof:placetype":"venue"
},
  "geometry": {"coordinates":[-78.405091,41.017116],"type":"Point"}
}