{
  "type": "Feature",
  "properties": {
    "iso:country":"US",
    "sg:address":"12 Simpson Rd",
    "sg:city":"Ardmore",
    "sg:classifiers":[
        {
            "category":"Health Services",
            "subcategory":"Clinic",
            "type":"Services"
        }
    ],
    "sg:phone":"+1   ",
    "sg:postcode":"19003",
    "sg:province":"PA",
    "wof:name":"Center of Macrobiotic Studies",
    "wof:placetype":"venue"
},
  "geometry": {"coordinates":[-75.288494,40.006197],"type":"Point"}
}