{
  "type": "Feature",
  "properties": {
    "iso:country":"US",
    "sg:address":"305 Fisk Ave",
    "sg:city":"Pittsburgh",
    "sg:classifiers":[
        {
            "category":"Building & Trades",
            "subcategory":"Construction",
            "type":"Services"
        }
    ],
    "sg:phone":"+1   ",
    "sg:postcode":"15202",
    "sg:province":"PA",
    "sg:tags":[
        "hanging",
        "contractor"
    ],
    "wof:name":"Andrews Painting",
    "wof:placetype":"venue"
},
  "geometry": {"coordinates":[-80.073044,40.503334],"type":"Point"}
}