{
  "type": "Feature",
  "properties": {
    "iso:country":"US",
    "sg:address":"1922 W Allen St",
    "sg:city":"Allentown",
    "sg:classifiers":[
        {
            "category":"Restaurant",
            "type":"Food & Drink"
        }
    ],
    "sg:phone":"+1   ",
    "sg:postcode":"18104",
    "sg:province":"PA",
    "sg:tags":[
        "eating"
    ],
    "wof:name":"OBriens",
    "wof:placetype":"venue"
},
  "geometry": {"coordinates":[-75.50246799999999,40.60312],"type":"Point"}
}