{
  "type": "Feature",
  "properties": {
    "addr:full":"216 W 8th Ave Homestead PA 15120",
    "addr:housenumber":"216",
    "addr:postcode":"15120",
    "addr:street":"W 8Th Ave",
    "iso:country":"US",
    "sg:address":"216 W 8th Ave",
    "sg:city":"Homestead",
    "sg:classifiers":[
        {
            "category":"Shopping",
            "type":"Retail Goods"
        },
        {
            "category":"Manufacturing",
            "subcategory":"Glass & Minerals",
            "type":"Manufacturing & Wholesale Goods"
        }
    ],
    "sg:phone":"+1 412 461 1228",
    "sg:postcode":"15120",
    "sg:province":"PA",
    "sg:tags":[
        "mfg",
        "cut",
        "monument",
        "merchandise",
        "trade"
    ],
    "wof:name":"Homestead Monuments Works",
    "wof:placetype":"venue"
},
  "geometry": {"coordinates":[-79.915036,40.403972],"type":"Point"}
}