{
  "type": "Feature",
  "properties": {
    "addr:full":"526 N 18th St Allentown PA 18104",
    "addr:housenumber":"526",
    "addr:postcode":"18104",
    "addr:street":"N 18Th St",
    "iso:country":"US",
    "sg:address":"526 N 18th St",
    "sg:city":"Allentown",
    "sg:classifiers":[
        {
            "category":"Retail",
            "subcategory":"Repair Shop",
            "type":"Services"
        }
    ],
    "sg:phone":"+1 610 434 0380",
    "sg:postcode":"18104",
    "sg:province":"PA",
    "sg:tags":[
        "equipment",
        "merchandise"
    ],
    "wof:name":"Hartan's Sales & Service",
    "wof:placetype":"venue"
},
  "geometry": {"coordinates":[-75.497902,40.603802],"type":"Point"}
}