{
  "type": "Feature",
  "properties": {
    "iso:country":"US",
    "sg:address":"The Whitaker Ctr 222 Market St, Fl 2",
    "sg:city":"Harrisburg",
    "sg:classifiers":[
        {
            "category":"Coffee & Tea",
            "type":"Food & Drink"
        }
    ],
    "sg:phone":"+1 717 635 2529",
    "sg:postcode":"17101",
    "sg:province":"PA",
    "sg:website":"www.starbucks.com",
    "wof:name":"Starbucks",
    "wof:placetype":"venue"
},
  "geometry": {"coordinates":[-76.880905,40.260634],"type":"Point"}
}