{
  "type": "Feature",
  "properties": {
    "iso:country":"US",
    "sg:address":"200 S Chestnut St",
    "sg:city":"Elizabethtown",
    "sg:classifiers":[
        {
            "category":"Wholesale",
            "subcategory":"Books, Periodicals, & Newspapers",
            "type":"Manufacturing & Wholesale Goods"
        }
    ],
    "sg:phone":"+1 717 367 3670",
    "sg:postcode":"17022",
    "sg:province":"PA",
    "sg:tags":[
        "printers-books"
    ],
    "sg:website":"http://www.continentalpress.com",
    "wof:name":"Itp Of Usa, Inc.",
    "wof:placetype":"venue"
},
  "geometry": {"coordinates":[-76.595978,40.151279],"type":"Point"}
}