{
  "type": "Feature",
  "properties": {
    "addr:full":"231 Schoolhouse Rd Palmyra PA 17078",
    "addr:housenumber":"231",
    "addr:postcode":"17078",
    "addr:street":"Schoolhouse Rd",
    "iso:country":"US",
    "sg:address":"231 Schoolhouse Rd",
    "sg:city":"Palmyra",
    "sg:classifiers":[
        {
            "category":"Farming",
            "subcategory":"Livestock Farm",
            "type":"Manufacturing & Wholesale Goods"
        }
    ],
    "sg:phone":"+1   ",
    "sg:postcode":"17078",
    "sg:province":"PA",
    "wof:name":"Rick Goss",
    "wof:placetype":"venue"
},
  "geometry": {"coordinates":[-76.58834299999999,40.275158],"type":"Point"}
}