{
  "type": "Feature",
  "properties": {
    "iso:country":"US",
    "sg:address":"209 E 21st St",
    "sg:city":"Erie",
    "sg:classifiers":[
        {
            "category":"Professional",
            "type":"Services"
        }
    ],
    "sg:phone":"+1 814 454 4512",
    "sg:postcode":"16503",
    "sg:province":"PA",
    "sg:tags":[
        "establishment"
    ],
    "wof:name":"M & B Enterprises Inc",
    "wof:placetype":"venue"
},
  "geometry": {"coordinates":[-80.070359,42.118175],"type":"Point"}
}