{
  "type": "Feature",
  "properties": {
    "addr:full":"516 Fayette St Conshohocken PA 19428",
    "addr:housenumber":"516",
    "addr:postcode":"19428",
    "addr:street":"Fayette St",
    "iso:country":"US",
    "sg:address":"516 Fayette St",
    "sg:city":"Conshohocken",
    "sg:classifiers":[
        {
            "category":"Retail",
            "subcategory":"Funeral Services",
            "type":"Services"
        }
    ],
    "sg:phone":"+1 610 828 1336",
    "sg:postcode":"19428",
    "sg:province":"PA",
    "sg:tags":[
        "director"
    ],
    "wof:name":"Emil J Ciavarelli Funeral Home",
    "wof:placetype":"venue"
},
  "geometry": {"coordinates":[-75.30230899999999,40.07796],"type":"Point"}
}