{
  "type": "Feature",
  "properties": {
    "iso:country":"US",
    "sg:address":"281 E Allegheny Ave",
    "sg:city":"Philadelphia",
    "sg:classifiers":[
        {
            "category":"Freight",
            "type":"Transportation"
        }
    ],
    "sg:phone":"+1 215 739 9311",
    "sg:postcode":"19134",
    "sg:province":"PA",
    "sg:tags":[
        "dry",
        "bulk",
        "trucking"
    ],
    "wof:name":"Linden Bulk Transportation Co",
    "wof:placetype":"venue"
},
  "geometry": {"coordinates":[-75.125742,39.998179],"type":"Point"}
}