{
  "type": "Feature",
  "properties": {
    "iso:country":"US",
    "sg:address":"950 Pennsylvania Blvd",
    "sg:city":"Feasterville Trevose",
    "sg:classifiers":[
        {
            "category":"Insurance",
            "subcategory":"Insurance Agent",
            "type":"Services"
        }
    ],
    "sg:phone":"+1 215 322 0815",
    "sg:postcode":"19053",
    "sg:province":"PA",
    "sg:tags":[
        "agency",
        "general"
    ],
    "wof:name":"Little Michaels & Kennedy",
    "wof:placetype":"venue"
},
  "geometry": {"coordinates":[-75.01048900000001,40.153673],"type":"Point"}
}