{
  "type": "Feature",
  "properties": {
    "iso:country":"US",
    "sg:address":"3415 W Chester Pike",
    "sg:city":"Newtown Square",
    "sg:classifiers":[
        {
            "category":"Social Services",
            "subcategory":"Adult Care",
            "type":"Services"
        }
    ],
    "sg:phone":"+1   ",
    "sg:postcode":"19073",
    "sg:province":"PA",
    "sg:tags":[
        "shelter",
        "homeless"
    ],
    "wof:name":"Trevors Campaign For Homeless",
    "wof:placetype":"venue"
},
  "geometry": {"coordinates":[-75.39227099999999,39.985012],"type":"Point"}
}