{
  "type": "Feature",
  "properties": {
    "iso:country":"US",
    "sg:address":"9 W Packer Ave",
    "sg:city":"Bethlehem",
    "sg:classifiers":[
        {
            "category":"Shopping",
            "subcategory":"Books",
            "type":"Retail Goods"
        }
    ],
    "sg:phone":"+1 610 758 3375",
    "sg:postcode":"18015",
    "sg:province":"PA",
    "sg:tags":[
        "bookstore"
    ],
    "wof:name":"Lehigh University Bookstore",
    "wof:placetype":"venue"
},
  "geometry": {"coordinates":[-75.377899,40.6082],"type":"Point"}
}