{
  "type": "Feature",
  "properties": {
    "addr:full":"3536 W Highland St Allentown PA 18104",
    "addr:housenumber":"3536",
    "addr:postcode":"18104",
    "addr:street":"W Highland St",
    "iso:country":"US",
    "sg:address":"3536 W Highland St",
    "sg:city":"Allentown",
    "sg:classifiers":[
        {
            "category":"Retail",
            "subcategory":"Auto Repair",
            "type":"Services"
        }
    ],
    "sg:phone":"+1   ",
    "sg:postcode":"18104",
    "sg:province":"PA",
    "sg:tags":[
        "general"
    ],
    "wof:name":"Andrew S Automotive Adv I",
    "wof:placetype":"venue"
},
  "geometry": {"coordinates":[-75.539373,40.603067],"type":"Point"}
}