{
  "type": "Feature",
  "properties": {
    "iso:country":"US",
    "sg:address":"9001 Perry Hwy",
    "sg:city":"Pittsburgh",
    "sg:classifiers":[
        {
            "category":"Banks & Credit Unions",
            "subcategory":"Bank",
            "type":"Services"
        },
        {
            "category":"Banks & Credit Unions",
            "subcategory":"Financial Services",
            "type":"Services"
        }
    ],
    "sg:phone":"+1 412 364 1913",
    "sg:postcode":"15237",
    "sg:province":"PA",
    "sg:tags":[
        "state",
        "holding"
    ],
    "wof:name":"Wvs Financial Corp.",
    "wof:placetype":"venue"
},
  "geometry": {"coordinates":[-80.037453,40.569321],"type":"Point"}
}