{
  "type": "Feature",
  "properties": {
    "iso:country":"US",
    "sg:address":"3630 Horizon Dr",
    "sg:city":"King Of Prussia",
    "sg:classifiers":[
        {
            "category":"Banks & Credit Unions",
            "subcategory":"Bank",
            "type":"Services"
        }
    ],
    "sg:phone":"+1 610 272 7658",
    "sg:postcode":"19406",
    "sg:province":"PA",
    "sg:tags":[
        "loan",
        "real estate"
    ],
    "wof:name":"P G Properties",
    "wof:placetype":"venue"
},
  "geometry": {"coordinates":[-75.33971,40.087718],"type":"Point"}
}