{
  "type": "Feature",
  "properties": {
    "addr:full":"1201 W Allegheny Ave Philadelphia PA 19133",
    "addr:housenumber":"1201",
    "addr:postcode":"19133",
    "addr:street":"W Allegheny Ave",
    "iso:country":"US",
    "sg:address":"1201 W Allegheny Ave",
    "sg:city":"Philadelphia",
    "sg:classifiers":[
        {
            "category":"Education",
            "subcategory":"School",
            "type":"Public Place"
        }
    ],
    "sg:phone":"+1   ",
    "sg:postcode":"19133",
    "sg:province":"PA",
    "wof:name":"Cep Partnership School",
    "wof:placetype":"venue"
},
  "geometry": {"coordinates":[-75.148409,40.001066],"type":"Point"}
}