{
  "type": "Feature",
  "properties": {
    "addr:full":"7425 Old York Rd Cheltenham PA 19027",
    "addr:housenumber":"7425",
    "addr:postcode":"19027",
    "addr:street":"Old York Rd",
    "iso:country":"US",
    "sg:address":"7425 Old York Rd",
    "sg:city":"Cheltenham",
    "sg:classifiers":[
        {
            "category":"Professional",
            "type":"Services"
        },
        {
            "category":"Education",
            "subcategory":"Special Training",
            "type":"Public Place"
        }
    ],
    "sg:phone":"+1 215 635 6311",
    "sg:postcode":"19027",
    "sg:province":"PA",
    "sg:tags":[
        "arranger",
        "music",
        "composer"
    ],
    "wof:name":"Cheltenham Music & Art School",
    "wof:placetype":"venue"
},
  "geometry": {"coordinates":[-75.135598,40.063621],"type":"Point"}
}