{
  "type": "Feature",
  "properties": {
    "iso:country":"US",
    "sg:address":"520 Limekiln Pike",
    "sg:city":"Ambler",
    "sg:classifiers":[
        {
            "category":"Health Services",
            "subcategory":"Doctor",
            "type":"Services"
        }
    ],
    "sg:phone":"CTN1",
    "sg:postcode":"19002",
    "sg:province":"PA",
    "sg:tags":[
        "dentist",
        "dentists-pediatric",
        "dentistry"
    ],
    "sg:website":"http://www.mapleglendentist.com/",
    "wof:name":"Aesthetic Dentistry",
    "wof:placetype":"venue"
},
  "geometry": {"coordinates":[-75.18304500000001,40.178392],"type":"Point"}
}