{
  "type": "Feature",
  "properties": {
    "iso:country":"US",
    "sg:address":"210 W Chelten Ave",
    "sg:city":"Philadelphia",
    "sg:classifiers":[
        {
            "category":"Restaurant",
            "type":"Food & Drink"
        }
    ],
    "sg:phone":"+1 215 848 7160",
    "sg:postcode":"19144",
    "sg:province":"PA",
    "sg:tags":[
        "eating"
    ],
    "wof:name":"Gennaro's Famous Pizza",
    "wof:placetype":"venue"
},
  "geometry": {"coordinates":[-75.180125,40.0305],"type":"Point"}
}