{
  "type": "Feature",
  "properties": {
    "iso:country":"US",
    "sg:address":"4991 Hamilton Blvd",
    "sg:city":"Wescosville",
    "sg:classifiers":[
        {
            "category":"Freight",
            "type":"Transportation"
        }
    ],
    "sg:phone":"+1 610 395 2630",
    "sg:postcode":"18106",
    "sg:province":"PA",
    "sg:tags":[
        "trucking"
    ],
    "wof:name":"J & E Trucking",
    "wof:placetype":"venue"
},
  "geometry": {"coordinates":[-75.55664400000001,40.56528],"type":"Point"}
}