{
  "type": "Feature",
  "properties": {
    "addr:full":"11279 Center Hwy Irwin PA 15642",
    "addr:housenumber":"11279",
    "addr:postcode":"15642",
    "addr:street":"Center Hwy",
    "iso:country":"US",
    "sg:address":"11279 Center Hwy",
    "sg:city":"Irwin",
    "sg:classifiers":[
        {
            "category":"Shopping",
            "subcategory":"Gifts & Souvenirs",
            "type":"Retail Goods"
        }
    ],
    "sg:phone":"+1 724 861 4624",
    "sg:postcode":"15642",
    "sg:province":"PA",
    "sg:tags":[
        "shop"
    ],
    "wof:name":"Buchanan Shelley",
    "wof:placetype":"venue"
},
  "geometry": {"coordinates":[-79.73083099999999,40.329894],"type":"Point"}
}