{
  "type": "Feature",
  "properties": {
    "iso:country":"US",
    "sg:address":"1715 Wilson Ave",
    "sg:city":"Chambersburg",
    "sg:classifiers":[
        {
            "category":"Communications",
            "subcategory":"Radio Station",
            "type":"Services"
        }
    ],
    "sg:phone":"+1 717 264 5026",
    "sg:postcode":"17201",
    "sg:province":"PA",
    "sg:tags":[
        "company",
        "broadcasting"
    ],
    "wof:name":"WJAL TV",
    "wof:placetype":"venue"
},
  "geometry": {"coordinates":[-77.64165,39.955039],"type":"Point"}
}