{
  "type": "Feature",
  "properties": {
    "iso:country":"US",
    "sg:address":"545 Main St",
    "sg:city":"Schwenksville",
    "sg:classifiers":[
        {
            "category":"Health Services",
            "subcategory":"Doctor",
            "type":"Services"
        }
    ],
    "sg:phone":"+1   ",
    "sg:postcode":"19473",
    "sg:province":"PA",
    "sg:tags":[
        "medical"
    ],
    "wof:name":"Leonard A Frank MD",
    "wof:placetype":"venue"
},
  "geometry": {"coordinates":[-75.46420999999999,40.258047],"type":"Point"}
}