{
  "type": "Feature",
  "properties": {
    "iso:country":"US",
    "sg:address":"1845 Walnut St Ste 1500",
    "sg:city":"Philadelphia",
    "sg:classifiers":[
        {
            "category":"Professional",
            "subcategory":"Lawyer & Legal Services",
            "type":"Services"
        }
    ],
    "sg:phone":"+1 215 972 3888",
    "sg:postcode":"19103",
    "sg:province":"PA",
    "wof:name":"Greek Francis J Atty",
    "wof:placetype":"venue"
},
  "geometry": {"coordinates":[-75.171402,39.950298],"type":"Point"}
}