{
  "type": "Feature",
  "properties": {
    "iso:country":"US",
    "sg:address":"3820 Columbia Blvd",
    "sg:city":"Bloomsburg",
    "sg:classifiers":[
        {
            "category":"Building & Trades",
            "subcategory":"Construction",
            "type":"Services"
        }
    ],
    "sg:phone":"+1   ",
    "sg:postcode":"17815",
    "sg:province":"PA",
    "sg:tags":[
        "builder",
        "operative"
    ],
    "wof:name":"F & N Homes",
    "wof:placetype":"venue"
},
  "geometry": {"coordinates":[-76.41818499999999,41.009823],"type":"Point"}
}