{
  "type": "Feature",
  "properties": {
    "iso:country":"US",
    "sg:address":"1133 W Hamilton St",
    "sg:city":"Allentown",
    "sg:classifiers":[
        {
            "category":"Banks & Credit Unions",
            "subcategory":"Investment Brokerage",
            "type":"Services"
        }
    ],
    "sg:phone":"+1 610 432 9090",
    "sg:postcode":"18101",
    "sg:province":"PA",
    "wof:name":"ABA Investment Management",
    "wof:placetype":"venue"
},
  "geometry": {"coordinates":[-75.481675,40.599575],"type":"Point"}
}