{
  "type": "Feature",
  "properties": {
    "addr:full":"543 N Monroe St Butler PA 16001",
    "addr:housenumber":"543",
    "addr:postcode":"16001",
    "addr:street":"N Monroe St",
    "iso:country":"US",
    "sg:address":"543 N Monroe St",
    "sg:city":"Butler",
    "sg:classifiers":[
        {
            "category":"Shopping",
            "subcategory":"Gifts & Souvenirs",
            "type":"Retail Goods"
        }
    ],
    "sg:phone":"+1   ",
    "sg:postcode":"16001",
    "sg:province":"PA",
    "sg:tags":[
        "novelty"
    ],
    "wof:name":"Global Sales",
    "wof:placetype":"venue"
},
  "geometry": {"coordinates":[-79.8887,40.86798],"type":"Point"}
}