{
  "type": "Feature",
  "properties": {
    "iso:country":"US",
    "sg:address":"167 Hogan Blvd",
    "sg:city":"Mill Hall",
    "sg:classifiers":[
        {
            "category":"Personal",
            "subcategory":"Beauty Salon",
            "type":"Services"
        }
    ],
    "sg:phone":"+1 570 893 6588",
    "sg:postcode":"17751",
    "sg:province":"PA",
    "wof:name":"Smart Style Family Hair Salon",
    "wof:placetype":"venue"
},
  "geometry": {"coordinates":[-77.474448,41.118097],"type":"Point"}
}