{
  "type": "Feature",
  "properties": {
    "addr:full":"295 Flagstone Dr Bethlehem PA 18017",
    "addr:housenumber":"295",
    "addr:postcode":"18017",
    "addr:street":"Flagstone Dr",
    "iso:country":"US",
    "sg:address":"295 Flagstone Dr",
    "sg:city":"Bethlehem",
    "sg:classifiers":[
        {
            "category":"Building & Trades",
            "subcategory":"Construction",
            "type":"Services"
        }
    ],
    "sg:phone":"+1   ",
    "sg:postcode":"18017",
    "sg:province":"PA",
    "sg:tags":[
        "nonresidential"
    ],
    "wof:name":"Michael J Kuehn Cnstr Co",
    "wof:placetype":"venue"
},
  "geometry": {"coordinates":[-75.376187,40.652358],"type":"Point"}
}