{
  "type": "Feature",
  "properties": {
    "addr:full":"101 Progress Dr Doylestown PA 18901",
    "addr:housenumber":"101",
    "addr:postcode":"18901",
    "addr:street":"Progress Dr",
    "iso:country":"US",
    "sg:address":"101 Progress Dr",
    "sg:city":"Doylestown",
    "sg:classifiers":[
        {
            "category":"Health Services",
            "subcategory":"Health Practitioner",
            "type":"Services"
        }
    ],
    "sg:phone":"+1 215 489 8550",
    "sg:postcode":"18901",
    "sg:province":"PA",
    "sg:tags":[
        "therapist",
        "physical"
    ],
    "wof:name":"Nova Care",
    "wof:placetype":"venue"
},
  "geometry": {"coordinates":[-75.144002,40.302952],"type":"Point"}
}