{
  "type": "Feature",
  "properties": {
    "iso:country":"US",
    "sg:address":"114 Van Ness St",
    "sg:city":"Sykesville",
    "sg:classifiers":[
        {
            "category":"Personal",
            "subcategory":"Beauty Salon",
            "type":"Services"
        }
    ],
    "sg:phone":"+1 814 894 2770",
    "sg:postcode":"15865",
    "sg:province":"PA",
    "wof:name":"Deters Beauty Salon Inc",
    "wof:placetype":"venue"
},
  "geometry": {"coordinates":[-78.822074,41.053914],"type":"Point"}
}