{
  "type": "Feature",
  "properties": {
    "iso:country":"US",
    "sg:address":"1 S Main St",
    "sg:city":"Nazareth",
    "sg:classifiers":[
        {
            "category":"Professional",
            "subcategory":"Lawyer & Legal Services",
            "type":"Services"
        }
    ],
    "sg:phone":"+1 610 759 1530",
    "sg:postcode":"18064",
    "sg:province":"PA",
    "sg:tags":[
        "attorney"
    ],
    "wof:name":"Peters Moritz Peischl Zulick",
    "wof:placetype":"venue"
},
  "geometry": {"coordinates":[-75.31188400000001,40.740607],"type":"Point"}
}