{
  "type": "Feature",
  "properties": {
    "iso:country":"US",
    "sg:address":"6140 York Rd",
    "sg:city":"New Oxford",
    "sg:classifiers":[
        {
            "category":"Shopping",
            "subcategory":"Gifts & Souvenirs",
            "type":"Retail Goods"
        }
    ],
    "sg:phone":"+1 717 624 4166",
    "sg:postcode":"17350",
    "sg:province":"PA",
    "sg:tags":[
        "shop"
    ],
    "wof:name":"Fenton Art Glass",
    "wof:placetype":"venue"
},
  "geometry": {"coordinates":[-77.02350300000001,39.872551],"type":"Point"}
}