{
  "type": "Feature",
  "properties": {
    "iso:country":"US",
    "sg:address":"672 Regency Dr",
    "sg:city":"Pittsburgh",
    "sg:classifiers":[
        {
            "category":"Organizations",
            "subcategory":"Community Association",
            "type":"Services"
        }
    ],
    "sg:phone":"+1   ",
    "sg:postcode":"15239",
    "sg:province":"PA",
    "wof:name":"Pennsylvania Bass Chapter",
    "wof:placetype":"venue"
},
  "geometry": {"coordinates":[-79.77958,40.485438],"type":"Point"}
}