{
  "type": "Feature",
  "properties": {
    "iso:country":"US",
    "sg:address":"301 Three Square Hollow Rd",
    "sg:city":"Newburg",
    "sg:classifiers":[
        {
            "category":"Professional",
            "type":"Services"
        }
    ],
    "sg:phone":"+1 717 423 6081",
    "sg:postcode":"17240",
    "sg:province":"PA",
    "sg:tags":[
        "establishment"
    ],
    "wof:name":"Eggs Newburg",
    "wof:placetype":"venue"
},
  "geometry": {"coordinates":[-77.55655,40.146944],"type":"Point"}
}