{
  "type": "Feature",
  "properties": {
    "iso:country":"US",
    "sg:address":"257 E Lancaster Ave # 100",
    "sg:city":"Wynnewood",
    "sg:classifiers":[
        {
            "category":"Real Estate",
            "subcategory":"Real Estate Operator",
            "type":"Services"
        }
    ],
    "sg:phone":"+1 610 649 4600",
    "sg:postcode":"19096",
    "sg:province":"PA",
    "sg:tags":[
        "apartment"
    ],
    "wof:name":"Edgehill Associates",
    "wof:placetype":"venue"
},
  "geometry": {"coordinates":[-75.281278,40.003077],"type":"Point"}
}