{
  "type": "Feature",
  "properties": {
    "addr:full":"827 E Lake Rd Transfer PA 16154",
    "addr:housenumber":"827",
    "addr:postcode":"16154",
    "addr:street":"E Lake Rd",
    "iso:country":"US",
    "sg:address":"827 E Lake Rd",
    "sg:city":"Transfer",
    "sg:classifiers":[
        {
            "category":"Health Services",
            "subcategory":"Doctor",
            "type":"Services"
        }
    ],
    "sg:phone":"+1   ",
    "sg:postcode":"16154",
    "sg:province":"PA",
    "sg:tags":[
        "medical"
    ],
    "wof:name":"Gilbert A Lawrence MD PC",
    "wof:placetype":"venue"
},
  "geometry": {"coordinates":[-80.40030899999999,41.30106],"type":"Point"}
}