{
  "type": "Feature",
  "properties": {
    "iso:country":"US",
    "sg:address":"8 Beverly Dr",
    "sg:city":"Myerstown",
    "sg:classifiers":[
        {
            "category":"Building & Trades",
            "subcategory":"Construction",
            "type":"Services"
        }
    ],
    "sg:phone":"+1 717 272 5338",
    "sg:postcode":"17067",
    "sg:province":"PA",
    "sg:tags":[
        "masonry",
        "contractor"
    ],
    "wof:name":"Minnich & Kelly Masonry Contrs",
    "wof:placetype":"venue"
},
  "geometry": {"coordinates":[-76.32807099999999,40.395357],"type":"Point"}
}