{
  "type": "Feature",
  "properties": {
    "addr:full":"4873 Hardt Rd Gibsonia PA 15044",
    "addr:housenumber":"4873",
    "addr:postcode":"15044",
    "addr:street":"Hardt Rd",
    "iso:country":"US",
    "sg:address":"4873 Hardt Rd",
    "sg:city":"Gibsonia",
    "sg:classifiers":[
        {
            "category":"Organizations",
            "subcategory":"Labor Organization",
            "type":"Services"
        }
    ],
    "sg:phone":"+1   ",
    "sg:postcode":"15044",
    "sg:province":"PA",
    "wof:name":"American Flint Glass Work",
    "wof:placetype":"venue"
},
  "geometry": {"coordinates":[-79.97948599999999,40.599669],"type":"Point"}
}