{
  "type": "Feature",
  "properties": {
    "iso:country":"US",
    "sg:address":"295 E Main St",
    "sg:city":"Leola",
    "sg:classifiers":[
        {
            "category":"Home & Garden",
            "subcategory":"Furniture",
            "type":"Retail Goods"
        }
    ],
    "sg:phone":"+1 717 661 6565",
    "sg:postcode":"17540",
    "sg:province":"PA",
    "sg:tags":[
        "cabinet"
    ],
    "wof:name":"Quality Custom Cabinetry",
    "wof:placetype":"venue"
},
  "geometry": {"coordinates":[-76.154956,40.092268],"type":"Point"}
}