{
  "type": "Feature",
  "properties": {
    "iso:country":"US",
    "sg:address":"2231 E Ontario St",
    "sg:city":"Philadelphia",
    "sg:classifiers":[
        {
            "category":"Manufacturing",
            "subcategory":"Tools & Machinery",
            "type":"Manufacturing & Wholesale Goods"
        }
    ],
    "sg:phone":"+1 215 743 3500",
    "sg:postcode":"19134",
    "sg:province":"PA",
    "sg:tags":[
        "textile",
        "parts"
    ],
    "sg:website":"www.haskelldawes.com",
    "wof:name":"Haskell-Dawes Inc",
    "wof:placetype":"venue"
},
  "geometry": {"coordinates":[-75.103787,39.993773],"type":"Point"}
}