{
  "type": "Feature",
  "properties": {
    "addr:full":"3925 Nazareth Pike Bethlehem PA 18020",
    "addr:postcode":"3925;18020",
    "addr:street":"Nazareth Pike",
    "iso:country":"US",
    "sg:address":"3925 Nazareth Pike",
    "sg:city":"Bethlehem",
    "sg:classifiers":[
        {
            "category":"Restaurant",
            "type":"Food & Drink"
        }
    ],
    "sg:phone":"+1   ",
    "sg:postcode":"18020",
    "sg:province":"PA",
    "sg:tags":[
        "eating"
    ],
    "wof:name":"McDonalds",
    "wof:placetype":"venue"
},
  "geometry": {"coordinates":[-75.34250900000001,40.678381],"type":"Point"}
}