{
  "type": "Feature",
  "properties": {
    "iso:country":"US",
    "sg:address":"70 Rocky Wood Ln",
    "sg:city":"Lewisberry",
    "sg:classifiers":[
        {
            "category":"Professional",
            "subcategory":"Business Services",
            "type":"Services"
        },
        {
            "category":"Education",
            "subcategory":"School",
            "type":"Public Place"
        }
    ],
    "sg:phone":"+1 717 697 2141",
    "sg:postcode":"17339",
    "sg:province":"PA",
    "wof:name":"Infinity Programs For Gifted C",
    "wof:placetype":"venue"
},
  "geometry": {"coordinates":[-76.90458599999999,40.107779],"type":"Point"}
}