{
  "type": "Feature",
  "properties": {
    "iso:country":"US",
    "sg:address":"1301 Kendall Rd",
    "sg:city":"Swarthmore",
    "sg:classifiers":[
        {
            "category":"Social Services",
            "subcategory":"Child Care",
            "type":"Services"
        }
    ],
    "sg:phone":"+1 610 543 3688",
    "sg:postcode":"19081",
    "sg:province":"PA",
    "sg:tags":[
        "day"
    ],
    "wof:name":"Forsythe Schools",
    "wof:placetype":"venue"
},
  "geometry": {"coordinates":[-75.351815,39.889963],"type":"Point"}
}