{
  "type": "Feature",
  "properties": {
    "addr:full":"318 School St Indiana PA 15701",
    "addr:housenumber":"318",
    "addr:postcode":"15701",
    "addr:street":"School St",
    "iso:country":"US",
    "sg:address":"318 School St",
    "sg:city":"Indiana",
    "sg:classifiers":[
        {
            "category":"Building & Trades",
            "subcategory":"Plumbing",
            "type":"Services"
        }
    ],
    "sg:phone":"+1   ",
    "sg:postcode":"15701",
    "sg:province":"PA",
    "sg:tags":[
        "contractor"
    ],
    "wof:name":"Andersons Heating & AC",
    "wof:placetype":"venue"
},
  "geometry": {"coordinates":[-79.143979,40.620482],"type":"Point"}
}