{
  "type": "Feature",
  "properties": {
    "iso:country":"US",
    "sg:address":"17 N Centre Ave",
    "sg:city":"Leesport",
    "sg:classifiers":[
        {
            "category":"Place Of Worship",
            "subcategory":"Church",
            "type":"Public Place"
        },
        {
            "category":"Place Of Worship",
            "type":"Public Place"
        }
    ],
    "sg:phone":"+1 610 926 0688",
    "sg:postcode":"19533",
    "sg:province":"PA",
    "sg:tags":[
        "testament",
        "churches-church",
        "christ-new",
        "christ"
    ],
    "sg:website":"http://www.trinitycu.org",
    "wof:name":"Trinity United Church Of Chris",
    "wof:placetype":"venue"
},
  "geometry": {"coordinates":[-75.96447000000001,40.448957],"type":"Point"}
}