{
  "type": "Feature",
  "properties": {
    "addr:full":"547 Greenfield Ave Pittsburgh PA 15207",
    "addr:housenumber":"547",
    "addr:postcode":"15207",
    "addr:street":"Greenfield Ave",
    "iso:country":"US",
    "sg:address":"547 Greenfield Ave",
    "sg:city":"Pittsburgh",
    "sg:classifiers":[
        {
            "category":"Organizations",
            "subcategory":"Community Association",
            "type":"Services"
        }
    ],
    "sg:phone":"+1 412 521 9935",
    "sg:postcode":"15207",
    "sg:province":"PA",
    "sg:tags":[
        "club"
    ],
    "wof:name":"Frankstown Club",
    "wof:placetype":"venue"
},
  "geometry": {"coordinates":[-79.940313,40.426129],"type":"Point"}
}