{
  "type": "Feature",
  "properties": {
    "iso:country":"US",
    "sg:address":"5240 Main St",
    "sg:city":"East Petersburg",
    "sg:classifiers":[
        {
            "category":"Autos & Motor Vehicles",
            "subcategory":"Automobile Sales",
            "type":"Retail Goods"
        }
    ],
    "sg:phone":"+1 717 391 7691",
    "sg:postcode":"17520",
    "sg:province":"PA",
    "sg:tags":[
        "car",
        "dealer"
    ],
    "wof:name":"Henry Mearig KIA",
    "wof:placetype":"venue"
},
  "geometry": {"coordinates":[-76.346165,40.088459],"type":"Point"}
}