{
  "type": "Feature",
  "properties": {
    "addr:full":"274 State Rte 87 Montoursville PA 17754",
    "addr:housenumber":"274",
    "addr:postcode":"17754",
    "addr:street":"State Rte 87",
    "iso:country":"US",
    "sg:address":"274 State Rte 87",
    "sg:city":"Montoursville",
    "sg:classifiers":[
        {
            "category":"Banks & Credit Unions",
            "subcategory":"Bank",
            "type":"Services"
        }
    ],
    "sg:phone":"+1 570 000 1111",
    "sg:postcode":"17754",
    "sg:province":"PA",
    "sg:tags":[
        "federal"
    ],
    "wof:name":"Sovereign Bank",
    "wof:placetype":"venue"
},
  "geometry": {"coordinates":[-76.913083,41.266784],"type":"Point"}
}