{
  "type": "Feature",
  "properties": {
    "iso:country":"US",
    "sg:address":"1522 Washington Pike",
    "sg:city":"Bridgeville",
    "sg:classifiers":[
        {
            "category":"Restaurant",
            "type":"Food & Drink"
        }
    ],
    "sg:menulink":"http://www.allmenus.com/pa/collier/35282-the-hottest-dog/menu/",
    "sg:phone":"+1 412 429 3330",
    "sg:postcode":"15017",
    "sg:province":"PA",
    "sg:tags":[
        "american",
        "hot",
        "dog"
    ],
    "wof:name":"The Hottest Dog",
    "wof:placetype":"venue"
},
  "geometry": {"coordinates":[-80.094668,40.38138],"type":"Point"}
}