{
  "type": "Feature",
  "properties": {
    "iso:country":"US",
    "sg:address":"491 Mill Rd",
    "sg:city":"Sidman",
    "sg:classifiers":[
        {
            "category":"Utilities",
            "subcategory":"Water",
            "type":"Services"
        }
    ],
    "sg:phone":"+1 814 487 7056",
    "sg:postcode":"15955",
    "sg:province":"PA",
    "sg:tags":[
        "company",
        "sewage"
    ],
    "wof:name":"Tri-Township Water Authority",
    "wof:placetype":"venue"
},
  "geometry": {"coordinates":[-78.714924,40.336742],"type":"Point"}
}