{
  "type": "Feature",
  "properties": {
    "addr:full":"RR 202 Blue Bell PA 19422",
    "addr:housenumber":"202",
    "addr:postcode":"19422",
    "iso:country":"US",
    "sg:address":"RR 202",
    "sg:city":"Blue Bell",
    "sg:classifiers":[
        {
            "category":"Shopping",
            "subcategory":"Beauty & Cosmetics",
            "type":"Retail Goods"
        },
        {
            "category":"Personal",
            "subcategory":"Nail Salon",
            "type":"Services"
        }
    ],
    "sg:phone":"+1 610 275 1514",
    "sg:postcode":"19422",
    "sg:province":"PA",
    "sg:tags":[
        "supply"
    ],
    "wof:name":"Shear Waves",
    "wof:placetype":"venue"
},
  "geometry": {"coordinates":[-75.275902,40.1511],"type":"Point"}
}