{
  "type": "Feature",
  "properties": {
    "iso:country":"US",
    "sg:address":"260 S Cedarbrook Rd",
    "sg:city":"Allentown",
    "sg:classifiers":[
        {
            "category":"Government",
            "subcategory":"Office",
            "type":"Public Place"
        }
    ],
    "sg:phone":"+1   ",
    "sg:postcode":"18104",
    "sg:province":"PA",
    "sg:tags":[
        "wildlife",
        "conservation",
        "mineral",
        "land"
    ],
    "wof:name":"Parks & Recreation Bureau of",
    "wof:placetype":"venue"
},
  "geometry": {"coordinates":[-75.54285400000001,40.577804],"type":"Point"}
}