{
  "type": "Feature",
  "properties": {
    "addr:full":"7600 Roosevelt Blvd Philadelphia PA 19152",
    "addr:housenumber":"7600",
    "addr:postcode":"19152",
    "addr:street":"Roosevelt Blvd",
    "iso:country":"US",
    "sg:address":"7600 Roosevelt Blvd",
    "sg:city":"Philadelphia",
    "sg:classifiers":[
        {
            "category":"Real Estate",
            "subcategory":"Real Estate Operator",
            "type":"Services"
        }
    ],
    "sg:phone":"+1 215 624 5612",
    "sg:postcode":"19152",
    "sg:province":"PA",
    "sg:tags":[
        "condominium"
    ],
    "wof:name":"Valmont Towers",
    "wof:placetype":"venue"
},
  "geometry": {"coordinates":[-75.051542,40.049634],"type":"Point"}
}