{
  "type": "Feature",
  "properties": {
    "iso:country":"US",
    "sg:address":"2215 Hill Rd",
    "sg:city":"Perkiomenville",
    "sg:classifiers":[
        {
            "category":"Wholesale",
            "subcategory":"Durable Goods & Equipment",
            "type":"Manufacturing & Wholesale Goods"
        }
    ],
    "sg:phone":"+1   ",
    "sg:postcode":"18074",
    "sg:province":"PA",
    "wof:name":"DJS Supply",
    "wof:placetype":"venue"
},
  "geometry": {"coordinates":[-75.528717,40.354988],"type":"Point"}
}