{
  "type": "Feature",
  "properties": {
    "iso:country":"US",
    "sg:address":"136 Elm Rd",
    "sg:city":"Allentown",
    "sg:classifiers":[
        {
            "category":"Building & Trades",
            "subcategory":"Construction",
            "type":"Services"
        }
    ],
    "sg:phone":"+1 610 820 7677",
    "sg:postcode":"18104",
    "sg:province":"PA",
    "sg:tags":[
        "concrete",
        "contractor"
    ],
    "wof:name":"Classic Blacktop Paving",
    "wof:placetype":"venue"
},
  "geometry": {"coordinates":[-75.59437,40.582013],"type":"Point"}
}