{
  "type": "Feature",
  "properties": {
    "iso:country":"US",
    "sg:address":"220 W 18th St",
    "sg:city":"Hazleton",
    "sg:classifiers":[
        {
            "category":"Shopping",
            "subcategory":"Florist",
            "type":"Retail Goods"
        }
    ],
    "sg:phone":"+1 570 454 8951",
    "sg:postcode":"18201",
    "sg:province":"PA",
    "sg:tags":[
        "lawn",
        "maintenance"
    ],
    "wof:name":"Swsf Lawn & Garden Center",
    "wof:placetype":"venue"
},
  "geometry": {"coordinates":[-75.977913,40.96962],"type":"Point"}
}