{
  "type": "Feature",
  "properties": {
    "iso:country":"US",
    "sg:address":"409 11th St",
    "sg:city":"Beaver Falls",
    "sg:classifiers":[
        {
            "category":"Organizations",
            "subcategory":"Religious Organization",
            "type":"Services"
        }
    ],
    "sg:phone":"+1 724 846 2899",
    "sg:postcode":"15010",
    "sg:province":"PA",
    "sg:tags":[
        "church"
    ],
    "wof:name":"Christ Evangelical Lutheran",
    "wof:placetype":"venue"
},
  "geometry": {"coordinates":[-80.31586299999999,40.75186],"type":"Point"}
}