{
  "type": "Feature",
  "properties": {
    "addr:full":"1326 Freeport Rd Pittsburgh PA 15238",
    "addr:housenumber":"1326",
    "addr:postcode":"15238",
    "addr:street":"Freeport Rd",
    "iso:country":"US",
    "sg:address":"1326 Freeport Rd",
    "sg:city":"Pittsburgh",
    "sg:classifiers":[
        {
            "category":"Health Services",
            "subcategory":"Doctor",
            "type":"Services"
        }
    ],
    "sg:phone":"+1   ",
    "sg:postcode":"15238",
    "sg:province":"PA",
    "wof:name":"James N Edmonds Lpd",
    "wof:placetype":"venue"
},
  "geometry": {"coordinates":[-79.876848,40.488812],"type":"Point"}
}