{
  "type": "Feature",
  "properties": {
    "iso:country":"US",
    "sg:address":"601 Pembroke Rd",
    "sg:city":"Bryn Mawr",
    "sg:classifiers":[
        {
            "category":"Professional",
            "type":"Services"
        }
    ],
    "sg:phone":"+1   ",
    "sg:postcode":"19010",
    "sg:province":"PA",
    "wof:name":"Psalm 103 Foundation",
    "wof:placetype":"venue"
},
  "geometry": {"coordinates":[-75.30827600000001,40.025283],"type":"Point"}
}