{
  "type": "Feature",
  "properties": {
    "addr:full":"428 E Main St Middletown PA 17057",
    "addr:housenumber":"428",
    "addr:postcode":"17057",
    "addr:street":"E Main St",
    "iso:country":"US",
    "sg:address":"428 E Main St",
    "sg:city":"Middletown",
    "sg:classifiers":[
        {
            "category":"Shopping",
            "subcategory":"Tobacco",
            "type":"Retail Goods"
        }
    ],
    "sg:phone":"+1 717 944 2792",
    "sg:postcode":"17057",
    "sg:province":"PA",
    "sg:tags":[
        "cigarette",
        "cigar",
        "dealer"
    ],
    "wof:name":"Puff 'n Snuff",
    "wof:placetype":"venue"
},
  "geometry": {"coordinates":[-76.721492,40.200958],"type":"Point"}
}