{
  "type": "Feature",
  "properties": {
    "iso:country":"US",
    "sg:address":"320 Saw Mill Rd",
    "sg:city":"Greentown",
    "sg:classifiers":[
        {
            "category":"Professional",
            "subcategory":"Art Services",
            "type":"Services"
        }
    ],
    "sg:phone":"+1 570 676 1188",
    "sg:postcode":"18426",
    "sg:province":"PA",
    "sg:tags":[
        "designer",
        "display",
        "producer"
    ],
    "wof:name":"Rylly Enterprises",
    "wof:placetype":"venue"
},
  "geometry": {"coordinates":[-75.277327,41.303699],"type":"Point"}
}