{
  "type": "Feature",
  "properties": {
    "iso:country":"US",
    "sg:address":"2361 Huntingdon Pike",
    "sg:city":"Huntingdon Valley",
    "sg:classifiers":[
        {
            "category":"Health Services",
            "subcategory":"Doctor",
            "type":"Services"
        }
    ],
    "sg:phone":"+1   ",
    "sg:postcode":"19006",
    "sg:province":"PA",
    "sg:tags":[
        "medical"
    ],
    "wof:name":"Joseph N Dibello MD",
    "wof:placetype":"venue"
},
  "geometry": {"coordinates":[-75.065759,40.121037],"type":"Point"}
}