{
  "type": "Feature",
  "properties": {
    "iso:country":"US",
    "sg:address":"149 Market St",
    "sg:city":"Moscow",
    "sg:classifiers":[
        {
            "category":"Autos & Motor Vehicles",
            "subcategory":"Automobile Sales",
            "type":"Retail Goods"
        }
    ],
    "sg:phone":"+1 570 842 1830",
    "sg:postcode":"18444",
    "sg:province":"PA",
    "sg:tags":[
        "car",
        "used",
        "dealer"
    ],
    "wof:name":"D & R Auto Sales",
    "wof:placetype":"venue"
},
  "geometry": {"coordinates":[-75.516882,41.33837],"type":"Point"}
}