{
  "type": "Feature",
  "properties": {
    "iso:country":"US",
    "sg:address":"601 N 6th St",
    "sg:city":"Allentown",
    "sg:classifiers":[
        {
            "category":"Communications",
            "type":"Services"
        }
    ],
    "sg:phone":"+1 610 434 9327",
    "sg:postcode":"18102",
    "sg:province":"PA",
    "sg:tags":[
        "recording",
        "rehearsal",
        "studio"
    ],
    "wof:name":"Antares Productions",
    "wof:placetype":"venue"
},
  "geometry": {"coordinates":[-75.47380099999999,40.611099],"type":"Point"}
}