{
  "type": "Feature",
  "properties": {
    "addr:full":"245 N Memorial Hwy Shavertown PA 18708",
    "addr:housenumber":"245",
    "addr:postcode":"18708",
    "addr:street":"N Memorial Hwy",
    "iso:country":"US",
    "sg:address":"245 N Memorial Hwy",
    "sg:city":"Shavertown",
    "sg:classifiers":[
        {
            "category":"Health Services",
            "subcategory":"Doctor",
            "type":"Services"
        }
    ],
    "sg:phone":"+1 570 674 2256",
    "sg:postcode":"18708",
    "sg:province":"PA",
    "sg:tags":[
        "physician",
        "surgeon"
    ],
    "wof:name":"Advanced Laparoscopic Surgeons",
    "wof:placetype":"venue"
},
  "geometry": {"coordinates":[-75.94320500000001,41.323798],"type":"Point"}
}