{
  "type": "Feature",
  "properties": {
    "iso:country":"US",
    "sg:address":"3 Walnut St Brg",
    "sg:city":"Lemoyne",
    "sg:classifiers":[
        {
            "category":"Health Services",
            "subcategory":"Medical Lab",
            "type":"Services"
        }
    ],
    "sg:phone":"+1 717 737 3037",
    "sg:postcode":"17043",
    "sg:province":"PA",
    "sg:tags":[
        "x"
    ],
    "wof:name":"Heritage Diagnostic Ctr",
    "wof:placetype":"venue"
},
  "geometry": {"coordinates":[-76.89239499999999,40.251123],"type":"Point"}
}