{
  "type": "Feature",
  "properties": {
    "iso:country":"US",
    "sg:address":"202 E 10th St",
    "sg:city":"Erie",
    "sg:classifiers":[
        {
            "category":"Health Services",
            "subcategory":"Nursing And Care Facility",
            "type":"Services"
        }
    ],
    "sg:phone":"+1 814 456 6689",
    "sg:postcode":"16503",
    "sg:province":"PA",
    "sg:tags":[
        "skilled"
    ],
    "wof:name":"Hospice Of Metropolitan Erie",
    "wof:placetype":"venue"
},
  "geometry": {"coordinates":[-80.07650099999999,42.127758],"type":"Point"}
}