{
  "type": "Feature",
  "properties": {
    "iso:country":"US",
    "sg:address":"10 Stewart Rd",
    "sg:city":"Oil City",
    "sg:classifiers":[
        {
            "category":"Organizations",
            "subcategory":"Religious Organization",
            "type":"Services"
        }
    ],
    "sg:phone":"+1 814 676 0959",
    "sg:postcode":"16301",
    "sg:province":"PA",
    "sg:tags":[
        "church"
    ],
    "wof:name":"Oakland United Methodist Chr",
    "wof:placetype":"venue"
},
  "geometry": {"coordinates":[-79.688138,41.443731],"type":"Point"}
}