{
  "type": "Feature",
  "properties": {
    "addr:full":"8120 Ohio River Blvd Pittsburgh PA 15202",
    "addr:housenumber":"8120",
    "addr:postcode":"15202",
    "addr:street":"Ohio River Blvd",
    "iso:country":"US",
    "sg:address":"8120 Ohio River Blvd",
    "sg:city":"Pittsburgh",
    "sg:classifiers":[
        {
            "category":"Retail",
            "subcategory":"Auto Repair",
            "type":"Services"
        }
    ],
    "sg:phone":"+1 412 766 7639",
    "sg:postcode":"15202",
    "sg:province":"PA",
    "sg:tags":[
        "body",
        "automobile",
        "painting"
    ],
    "wof:name":"New Earl Scheib Paint & Body",
    "wof:placetype":"venue"
},
  "geometry": {"coordinates":[-80.095685,40.510397],"type":"Point"}
}