{
  "type": "Feature",
  "properties": {
    "addr:full":"2150 Industrial Dr Bethlehem PA 18017",
    "addr:housenumber":"2150",
    "addr:postcode":"18017",
    "addr:street":"Industrial Dr",
    "iso:country":"US",
    "sg:address":"2150 Industrial Dr",
    "sg:city":"Bethlehem",
    "sg:classifiers":[
        {
            "category":"Food & Beverages",
            "subcategory":"Liquor & Beverages",
            "type":"Retail Goods"
        }
    ],
    "sg:phone":"+1 610 807 5300",
    "sg:postcode":"18017",
    "sg:province":"PA",
    "sg:tags":[
        "beer",
        "spirit",
        "wine"
    ],
    "wof:name":"Coca Cola Bottling Co of the Lehigh Valley",
    "wof:placetype":"venue"
},
  "geometry": {"coordinates":[-75.419197,40.650101],"type":"Point"}
}