{
  "type": "Feature",
  "properties": {
    "addr:full":"3300 Wilmington Rd New Castle PA 16105",
    "addr:housenumber":"3300",
    "addr:postcode":"16105",
    "addr:street":"Wilmington Rd New",
    "iso:country":"US",
    "sg:address":"3300 Wilmington Rd",
    "sg:city":"New Castle",
    "sg:classifiers":[
        {
            "category":"Restaurant",
            "type":"Food & Drink"
        }
    ],
    "sg:menulink":"http://www.allmenus.com/pa/neshannock/214842-ponderosa-steak-house/menu/",
    "sg:phone":"+1 724 652 8435",
    "sg:postcode":"16105",
    "sg:province":"PA",
    "sg:tags":[
        "american",
        "steakhouse"
    ],
    "wof:name":"Ponderosa Steak House",
    "wof:placetype":"venue"
},
  "geometry": {"coordinates":[-80.35738499999999,41.056006],"type":"Point"}
}