{
  "type": "Feature",
  "properties": {
    "addr:full":"1027 Serrill Ave Lansdowne PA 19050",
    "addr:housenumber":"1027",
    "addr:postcode":"19050",
    "addr:street":"Serrill Ave",
    "iso:country":"US",
    "sg:address":"1027 Serrill Ave",
    "sg:city":"Lansdowne",
    "sg:classifiers":[
        {
            "category":"Health Services",
            "subcategory":"Hospital",
            "type":"Services"
        }
    ],
    "sg:phone":"+1 484 469 4692",
    "sg:postcode":"19050",
    "sg:province":"PA",
    "sg:tags":[
        "nurse",
        "registry"
    ],
    "wof:name":"Binty Nurses Inc",
    "wof:placetype":"venue"
},
  "geometry": {"coordinates":[-75.248867,39.927262],"type":"Point"}
}