{
  "type": "Feature",
  "properties": {
    "addr:full":"2 Chatham Ctr Ste 1410 Pittsburgh PA 15219",
    "addr:housenumber":"2",
    "addr:postcode":"15219",
    "addr:street":"Chatham Ctr Ste 1410",
    "iso:country":"US",
    "sg:address":"2 Chatham Ctr Ste 1410",
    "sg:city":"Pittsburgh",
    "sg:classifiers":[
        {
            "category":"Professional",
            "subcategory":"Lawyer & Legal Services",
            "type":"Services"
        }
    ],
    "sg:phone":"+1 412 281 8541",
    "sg:postcode":"15219",
    "sg:province":"PA",
    "wof:name":"Cain Ackerman & McCormick PC",
    "wof:placetype":"venue"
},
  "geometry": {"coordinates":[-79.99099699999999,40.4394],"type":"Point"}
}