{
  "type": "Feature",
  "properties": {
    "iso:country":"US",
    "sg:address":"1916 Barton Dr",
    "sg:city":"Lancaster",
    "sg:classifiers":[
        {
            "category":"Manufacturing",
            "subcategory":"Printing",
            "type":"Manufacturing & Wholesale Goods"
        }
    ],
    "sg:phone":"+1   ",
    "sg:postcode":"17603",
    "sg:province":"PA",
    "sg:tags":[
        "book"
    ],
    "wof:name":"Gaslight Publishers",
    "wof:placetype":"venue"
},
  "geometry": {"coordinates":[-76.338213,40.00184],"type":"Point"}
}