{
  "type": "Feature",
  "properties": {
    "iso:country":"US",
    "sg:address":"600 Old Pond Rd",
    "sg:city":"Bridgeville",
    "sg:classifiers":[
        {
            "category":"Professional",
            "subcategory":"Engineering",
            "type":"Services"
        }
    ],
    "sg:phone":"+1 412 221 9433",
    "sg:postcode":"15017",
    "sg:province":"PA",
    "sg:tags":[
        "engineer"
    ],
    "wof:name":"Gannett Fleming Inc",
    "wof:placetype":"venue"
},
  "geometry": {"coordinates":[-80.119305,40.351895],"type":"Point"}
}