{
  "type": "Feature",
  "properties": {
    "addr:full":"253 S Tulpehocken St Pine Grove PA 17963",
    "addr:housenumber":"253",
    "addr:postcode":"17963",
    "addr:street":"S Tulpehocken St",
    "iso:country":"US",
    "sg:address":"253 S Tulpehocken St",
    "sg:city":"Pine Grove",
    "sg:classifiers":[
        {
            "category":"Professional",
            "type":"Services"
        }
    ],
    "sg:phone":"+1   ",
    "sg:postcode":"17963",
    "sg:province":"PA",
    "wof:name":"Kurt H Wessner",
    "wof:placetype":"venue"
},
  "geometry": {"coordinates":[-76.385486,40.544761],"type":"Point"}
}