{
  "type": "Feature",
  "properties": {
    "iso:country":"US",
    "sg:address":"101 Eastman Ave",
    "sg:city":"Lancaster",
    "sg:classifiers":[
        {
            "category":"Personal",
            "subcategory":"Beauty Salon",
            "type":"Services"
        }
    ],
    "sg:phone":"+1 717 392 8776",
    "sg:postcode":"17603",
    "sg:province":"PA",
    "sg:tags":[
        "shop",
        "barber"
    ],
    "wof:name":"J R's Hair Nails & Body Works",
    "wof:placetype":"venue"
},
  "geometry": {"coordinates":[-76.35574099999999,40.035708],"type":"Point"}
}