{
  "type": "Feature",
  "properties": {
    "iso:country":"US",
    "sg:address":"333 Broad St",
    "sg:city":"Terre Hill",
    "sg:classifiers":[
        {
            "category":"Wholesale",
            "subcategory":"Machinery & Supplies",
            "type":"Manufacturing & Wholesale Goods"
        }
    ],
    "sg:phone":"+1   ",
    "sg:postcode":"17581",
    "sg:province":"PA",
    "sg:tags":[
        "water",
        "equipment",
        "conditioning"
    ],
    "wof:name":"JD Eberly Services",
    "wof:placetype":"venue"
},
  "geometry": {"coordinates":[-76.052696,40.162503],"type":"Point"}
}