{
  "type": "Feature",
  "properties": {
    "iso:country":"US",
    "sg:address":"2022 Penn Ave",
    "sg:city":"Jeannette",
    "sg:classifiers":[
        {
            "category":"Restaurant",
            "type":"Food & Drink"
        }
    ],
    "sg:phone":"+1 724 744 3003",
    "sg:postcode":"15644",
    "sg:province":"PA",
    "sg:tags":[
        "eating"
    ],
    "wof:name":"Amilis Pizzeria",
    "wof:placetype":"venue"
},
  "geometry": {"coordinates":[-79.63329400000001,40.33025],"type":"Point"}
}