{
  "type": "Feature",
  "properties": {
    "addr:full":"5 Chase Cir Fort Washington PA 19034",
    "addr:housenumber":"5",
    "addr:postcode":"19034",
    "addr:street":"Chase Cir",
    "iso:country":"US",
    "sg:address":"5 Chase Cir",
    "sg:city":"Fort Washington",
    "sg:classifiers":[
        {
            "category":"Shopping",
            "subcategory":"Gifts & Souvenirs",
            "type":"Retail Goods"
        }
    ],
    "sg:phone":"+1   ",
    "sg:postcode":"19034",
    "sg:province":"PA",
    "wof:name":"From The Heart Inc",
    "wof:placetype":"venue"
},
  "geometry": {"coordinates":[-75.190203,40.142421],"type":"Point"}
}