{
  "type": "Feature",
  "properties": {
    "iso:country":"US",
    "sg:address":"1630 E High St",
    "sg:city":"Pottstown",
    "sg:classifiers":[
        {
            "category":"Manufacturing",
            "subcategory":"Tools & Machinery",
            "type":"Manufacturing & Wholesale Goods"
        }
    ],
    "sg:phone":"+1 610 323 4988",
    "sg:postcode":"19464",
    "sg:province":"PA",
    "sg:tags":[
        "optical"
    ],
    "wof:name":"B J Optical Svc",
    "wof:placetype":"venue"
},
  "geometry": {"coordinates":[-75.61076,40.243939],"type":"Point"}
}