{
  "type": "Feature",
  "properties": {
    "addr:full":"125 2nd St Olyphant PA 18447",
    "addr:housenumber":"125",
    "addr:postcode":"18447",
    "addr:street":"2Nd St",
    "iso:country":"US",
    "sg:address":"125 2nd St",
    "sg:city":"Olyphant",
    "sg:classifiers":[
        {
            "category":"Home & Garden",
            "subcategory":"Home Furnishings",
            "type":"Retail Goods"
        }
    ],
    "sg:phone":"+1 570 689 0994",
    "sg:postcode":"18447",
    "sg:province":"PA",
    "sg:tags":[
        "blind",
        "window",
        "vertical",
        "covering"
    ],
    "wof:name":"Special Touch Window Treatment",
    "wof:placetype":"venue"
},
  "geometry": {"coordinates":[-75.60927700000001,41.473799],"type":"Point"}
}