{
  "type": "Feature",
  "properties": {
    "iso:country":"US",
    "sg:address":"2066 W Penn Pike",
    "sg:city":"New Ringgold",
    "sg:classifiers":[
        {
            "category":"Retail",
            "subcategory":"Animal Services",
            "type":"Services"
        }
    ],
    "sg:phone":"+1   ",
    "sg:postcode":"17960",
    "sg:province":"PA",
    "wof:name":"Kountry Kennels Inc",
    "wof:placetype":"venue"
},
  "geometry": {"coordinates":[-75.856571,40.719966],"type":"Point"}
}