{
  "type": "Feature",
  "properties": {
    "addr:full":"2601 River Rd Reading PA 19605",
    "addr:housenumber":"2601",
    "addr:postcode":"19605",
    "addr:street":"River Rd",
    "iso:country":"US",
    "sg:address":"2601 River Rd",
    "sg:city":"Reading",
    "sg:classifiers":[
        {
            "category":"Government",
            "subcategory":"Office",
            "type":"Public Place"
        }
    ],
    "sg:phone":"+1 610 929 4553",
    "sg:postcode":"19605",
    "sg:province":"PA",
    "sg:tags":[
        "state",
        "security",
        "national"
    ],
    "sg:website":"www.paguard.com",
    "wof:name":"Army National Guard Recruiter",
    "wof:placetype":"venue"
},
  "geometry": {"coordinates":[-75.951995,40.368862],"type":"Point"}
}