{
  "type": "Feature",
  "properties": {
    "addr:full":"601 S Prince St Lancaster PA 17603",
    "addr:housenumber":"601",
    "addr:postcode":"17603",
    "addr:street":"S Prince St",
    "iso:country":"US",
    "sg:address":"601 S Prince St",
    "sg:city":"Lancaster",
    "sg:classifiers":[
        {
            "category":"Food & Beverages",
            "subcategory":"Groceries & Convenience Stores",
            "type":"Retail Goods"
        }
    ],
    "sg:phone":"+1 717 390 9088",
    "sg:postcode":"17603",
    "sg:province":"PA",
    "wof:name":"Latin Grocery Store",
    "wof:placetype":"venue"
},
  "geometry": {"coordinates":[-76.305543,40.026409],"type":"Point"}
}