{
  "type": "Feature",
  "properties": {
    "iso:country":"US",
    "sg:address":"836 N Washington St",
    "sg:city":"Wilkes Barre",
    "sg:classifiers":[
        {
            "category":"Health Services",
            "subcategory":"Doctor",
            "type":"Services"
        }
    ],
    "sg:phone":"+1   ",
    "sg:postcode":"18705",
    "sg:province":"PA",
    "sg:tags":[
        "medical"
    ],
    "wof:name":"John M Prater MD",
    "wof:placetype":"venue"
},
  "geometry": {"coordinates":[-75.857613,41.259696],"type":"Point"}
}