{
  "type": "Feature",
  "properties": {
    "iso:country":"US",
    "sg:address":"531 N Center Ave",
    "sg:city":"Somerset",
    "sg:classifiers":[
        {
            "category":"Restaurant",
            "type":"Food & Drink"
        }
    ],
    "sg:phone":"+1   ",
    "sg:postcode":"15501",
    "sg:province":"PA",
    "sg:tags":[
        "eating"
    ],
    "wof:name":"Sum Shop",
    "wof:placetype":"venue"
},
  "geometry": {"coordinates":[-79.078654,40.0123],"type":"Point"}
}