{
  "type": "Feature",
  "properties": {
    "iso:country":"US",
    "sg:address":"181 E Court St",
    "sg:city":"Doylestown",
    "sg:classifiers":[
        {
            "category":"Education",
            "subcategory":"Special Training",
            "type":"Public Place"
        }
    ],
    "sg:phone":"+1 215 340 7979",
    "sg:postcode":"18901",
    "sg:province":"PA",
    "sg:tags":[
        "instruction",
        "music"
    ],
    "sg:website":"www.communityconservatory.org",
    "wof:name":"Community Conservatory Music",
    "wof:placetype":"venue"
},
  "geometry": {"coordinates":[-75.12755799999999,40.313831],"type":"Point"}
}