{
  "type": "Feature",
  "properties": {
    "addr:full":"7607 Lindbergh Blvd Philadelphia PA 19153",
    "addr:housenumber":"7607",
    "addr:postcode":"19153",
    "addr:street":"Lindbergh Blvd",
    "iso:country":"US",
    "sg:address":"7607 Lindbergh Blvd",
    "sg:city":"Philadelphia",
    "sg:classifiers":[
        {
            "category":"Shopping",
            "subcategory":"Stationery & Office Supplies",
            "type":"Retail Goods"
        },
        {
            "category":"Professional",
            "subcategory":"Printing & Photocopies",
            "type":"Services"
        }
    ],
    "sg:phone":"+1 215 492 9001",
    "sg:postcode":"19153",
    "sg:province":"PA",
    "sg:tags":[
        "equipment"
    ],
    "sg:website":"www.staples.com",
    "wof:name":"Staples",
    "wof:placetype":"venue"
},
  "geometry": {"coordinates":[-75.237396,39.904999],"type":"Point"}
}