{
  "type": "Feature",
  "properties": {
    "addr:full":"590 Scotrun Ave Scotrun PA 18355",
    "addr:housenumber":"590",
    "addr:postcode":"18355",
    "addr:street":"Scotrun Ave",
    "iso:country":"US",
    "sg:address":"590 Scotrun Ave",
    "sg:city":"Scotrun",
    "sg:classifiers":[
        {
            "category":"Retail",
            "subcategory":"Repair Shop",
            "type":"Services"
        }
    ],
    "sg:phone":"+1 570 620 2166",
    "sg:postcode":"18355",
    "sg:province":"PA",
    "sg:tags":[
        "clocks",
        "parts"
    ],
    "wof:name":"BNL Birds",
    "wof:placetype":"venue"
},
  "geometry": {"coordinates":[-75.320362,41.065903],"type":"Point"}
}