{
  "type": "Feature",
  "properties": {
    "iso:country":"US",
    "sg:address":"887 Main St",
    "sg:city":"Darby",
    "sg:classifiers":[
        {
            "category":"Insurance",
            "subcategory":"Insurance Agent",
            "type":"Services"
        },
        {
            "category":"Insurance",
            "subcategory":"Hazard Insurance",
            "type":"Services"
        },
        {
            "category":"Banks & Credit Unions",
            "subcategory":"Financial Services",
            "type":"Services"
        }
    ],
    "sg:phone":"+1 484 953 5111",
    "sg:postcode":"19023",
    "sg:province":"PA",
    "sg:tags":[
        "consultant",
        "analyst"
    ],
    "wof:name":"Main Street Insurance Doctors",
    "wof:placetype":"venue"
},
  "geometry": {"coordinates":[-75.26206000000001,39.918471],"type":"Point"}
}