{
  "type": "Feature",
  "properties": {
    "iso:country":"US",
    "sg:address":"7700 Ridge Ave",
    "sg:city":"Philadelphia",
    "sg:classifiers":[
        {
            "category":"Home & Garden",
            "subcategory":"Hardware",
            "type":"Retail Goods"
        }
    ],
    "sg:phone":"+1 215 483 3924",
    "sg:postcode":"19128",
    "sg:province":"PA",
    "wof:name":"Hopkins Corner",
    "wof:placetype":"venue"
},
  "geometry": {"coordinates":[-75.236234,40.052738],"type":"Point"}
}