{
  "type": "Feature",
  "properties": {
    "iso:country":"US",
    "sg:address":"115 W Market St",
    "sg:city":"Orwigsburg",
    "sg:classifiers":[
        {
            "category":"Personal",
            "subcategory":"Beauty Salon",
            "type":"Services"
        }
    ],
    "sg:phone":"+1   ",
    "sg:postcode":"17961",
    "sg:province":"PA",
    "sg:tags":[
        "shop"
    ],
    "wof:name":"Jennifers Family Hair Center",
    "wof:placetype":"venue"
},
  "geometry": {"coordinates":[-76.10188100000001,40.655109],"type":"Point"}
}