{
  "type": "Feature",
  "properties": {
    "iso:country":"US",
    "sg:address":"645 McMahon Ave",
    "sg:city":"Monessen",
    "sg:classifiers":[
        {
            "category":"Retail",
            "subcategory":"Funeral Services",
            "type":"Services"
        }
    ],
    "sg:phone":"+1 724 684 4877",
    "sg:postcode":"15062",
    "sg:province":"PA",
    "wof:name":"William R Taylor Funeral Home",
    "wof:placetype":"venue"
},
  "geometry": {"coordinates":[-79.89032,40.157595],"type":"Point"}
}