{
  "type": "Feature",
  "properties": {
    "addr:full":"117 N 8th St Shamokin PA 17872",
    "addr:housenumber":"117",
    "addr:postcode":"17872",
    "addr:street":"N 8Th St",
    "iso:country":"US",
    "sg:address":"117 N 8th St",
    "sg:city":"Shamokin",
    "sg:classifiers":[
        {
            "category":"Organizations",
            "subcategory":"Religious Organization",
            "type":"Services"
        }
    ],
    "sg:phone":"+1 570 648 6101",
    "sg:postcode":"17872",
    "sg:province":"PA",
    "sg:tags":[
        "church"
    ],
    "wof:name":"St John's United Church-Christ",
    "wof:placetype":"venue"
},
  "geometry": {"coordinates":[-76.55575899999999,40.789588],"type":"Point"}
}