{
  "type": "Feature",
  "properties": {
    "iso:country":"US",
    "sg:address":"658 W Lancaster Ave",
    "sg:city":"Bryn Mawr",
    "sg:classifiers":[
        {
            "category":"Restaurant",
            "type":"Food & Drink"
        }
    ],
    "sg:menulink":"http://www.allmenus.com/pa/haverford/17912-bryn-mawr-pizza/menu/",
    "sg:phone":"+1 610 525 4421",
    "sg:postcode":"19010",
    "sg:province":"PA",
    "sg:tags":[
        "sandwich",
        "burger",
        "gyro",
        "calzones",
        "american",
        "wrap",
        "chicken",
        "wing",
        "pizza"
    ],
    "wof:name":"Bryn Mawr Pizza",
    "wof:placetype":"venue"
},
  "geometry": {"coordinates":[-75.312439,40.018676],"type":"Point"}
}