{
  "type": "Feature",
  "properties": {
    "iso:country":"US",
    "sg:address":"32 N 6th St Frnt",
    "sg:city":"Allentown",
    "sg:classifiers":[
        {
            "category":"Professional",
            "subcategory":"Lawyer & Legal Services",
            "type":"Services"
        }
    ],
    "sg:phone":"+1 610 770 1400",
    "sg:postcode":"18101",
    "sg:province":"PA",
    "sg:tags":[
        "divorce",
        "law",
        "family"
    ],
    "wof:name":"Bernstein Jos C Atty",
    "wof:placetype":"venue"
},
  "geometry": {"coordinates":[-75.4701,40.6035],"type":"Point"}
}