{
  "type": "Feature",
  "properties": {
    "iso:country":"US",
    "sg:address":"141 Frosty Valley Rd",
    "sg:city":"Danville",
    "sg:classifiers":[
        {
            "category":"Farming",
            "subcategory":"Farm",
            "type":"Manufacturing & Wholesale Goods"
        }
    ],
    "sg:phone":"+1 570 275 8786",
    "sg:postcode":"17821",
    "sg:province":"PA",
    "wof:name":"Frosty Valley Farm",
    "wof:placetype":"venue"
},
  "geometry": {"coordinates":[-76.565268,40.999821],"type":"Point"}
}