{
  "type": "Feature",
  "properties": {
    "iso:country":"US",
    "sg:address":"78 Kennard Dale Ave",
    "sg:city":"Stewartstown",
    "sg:classifiers":[
        {
            "category":"Building & Trades",
            "subcategory":"Construction",
            "type":"Services"
        }
    ],
    "sg:phone":"+1 717 993 8292",
    "sg:postcode":"17363",
    "sg:province":"PA",
    "sg:tags":[
        "general",
        "contractor"
    ],
    "wof:name":"Rujo Inc",
    "wof:placetype":"venue"
},
  "geometry": {"coordinates":[-76.584474,39.750313],"type":"Point"}
}