{
  "type": "Feature",
  "properties": {
    "iso:country":"US",
    "sg:address":"8250 Enterprise Ave",
    "sg:city":"Philadelphia",
    "sg:classifiers":[
        {
            "category":"Building & Trades",
            "subcategory":"Construction",
            "type":"Services"
        }
    ],
    "sg:phone":"+1 215 365 5320",
    "sg:postcode":"19153",
    "sg:province":"PA",
    "sg:tags":[
        "contractor"
    ],
    "wof:name":"James Anderson Construction Company",
    "wof:placetype":"venue"
},
  "geometry": {"coordinates":[-75.21903,39.885935],"type":"Point"}
}