{
  "type": "Feature",
  "properties": {
    "iso:country":"US",
    "sg:address":"306 Barbara Dr",
    "sg:city":"Monongahela",
    "sg:classifiers":[
        {
            "category":"Building & Trades",
            "subcategory":"Construction",
            "type":"Services"
        }
    ],
    "sg:phone":"+1 724 258 0116",
    "sg:postcode":"15063",
    "sg:province":"PA",
    "sg:tags":[
        "contractor"
    ],
    "wof:name":"Mine Services and Construction Co Inc",
    "wof:placetype":"venue"
},
  "geometry": {"coordinates":[-79.947304,40.1856],"type":"Point"}
}