{
  "type": "Feature",
  "properties": {
    "addr:full":"705 W Market St Perkasie PA 18944",
    "addr:housenumber":"705",
    "addr:postcode":"18944",
    "addr:street":"W Market St",
    "iso:country":"US",
    "sg:address":"705 W Market St",
    "sg:city":"Perkasie",
    "sg:classifiers":[
        {
            "category":"Government",
            "subcategory":"Court House",
            "type":"Public Place"
        }
    ],
    "sg:phone":"+1 215 257 5181",
    "sg:postcode":"18944",
    "sg:province":"PA",
    "sg:tags":[
        "county"
    ],
    "wof:name":"District Court",
    "wof:placetype":"venue"
},
  "geometry": {"coordinates":[-75.295997,40.374859],"type":"Point"}
}