{
  "type": "Feature",
  "properties": {
    "addr:full":"912 Allen Dr Lansdowne PA 19050",
    "addr:housenumber":"912",
    "addr:postcode":"19050",
    "addr:street":"Allen Dr",
    "iso:country":"US",
    "sg:address":"912 Allen Dr",
    "sg:city":"Lansdowne",
    "sg:classifiers":[
        {
            "category":"Building & Trades",
            "subcategory":"Cleaning & Sanitation",
            "type":"Services"
        }
    ],
    "sg:phone":"+1   ",
    "sg:postcode":"19050",
    "sg:province":"PA",
    "sg:tags":[
        "maintenance"
    ],
    "wof:name":"McGhees Janitorial Service",
    "wof:placetype":"venue"
},
  "geometry": {"coordinates":[-75.252224,39.924171],"type":"Point"}
}