{
  "type": "Feature",
  "properties": {
    "iso:country":"US",
    "sg:address":"401 Lloyd Ave",
    "sg:city":"Latrobe",
    "sg:classifiers":[
        {
            "category":"Food & Beverages",
            "subcategory":"Liquor & Beverages",
            "type":"Retail Goods"
        }
    ],
    "sg:phone":"+1 724 537 7764",
    "sg:postcode":"15650",
    "sg:province":"PA",
    "sg:tags":[
        "beer",
        "ale",
        "bottler",
        "beverages-distributors"
    ],
    "wof:name":"Mosso Beverage Inc",
    "wof:placetype":"venue"
},
  "geometry": {"coordinates":[-79.392348,40.31002],"type":"Point"}
}