{
  "type": "Feature",
  "properties": {
    "addr:full":"520 S Hanover St Nanticoke PA 18634",
    "addr:housenumber":"520",
    "addr:postcode":"18634",
    "addr:street":"S Hanover St",
    "iso:country":"US",
    "sg:address":"520 S Hanover St",
    "sg:city":"Nanticoke",
    "sg:classifiers":[
        {
            "category":"Organizations",
            "subcategory":"Religious Organization",
            "type":"Services"
        }
    ],
    "sg:phone":"+1 570 735 2281",
    "sg:postcode":"18634",
    "sg:province":"PA",
    "sg:tags":[
        "church"
    ],
    "wof:name":"Holy Trinity Church",
    "wof:placetype":"venue"
},
  "geometry": {"coordinates":[-76.004294,41.198779],"type":"Point"}
}