{
  "type": "Feature",
  "properties": {
    "iso:country":"US",
    "sg:address":"3304 Mountain Rd",
    "sg:city":"Hamburg",
    "sg:classifiers":[
        {
            "category":"Farming",
            "subcategory":"Poultry Farm",
            "type":"Manufacturing & Wholesale Goods"
        }
    ],
    "sg:phone":"+1   ",
    "sg:postcode":"19526",
    "sg:province":"PA",
    "sg:tags":[
        "hatchery"
    ],
    "wof:name":"Patrick Shea",
    "wof:placetype":"venue"
},
  "geometry": {"coordinates":[-76.08820900000001,40.529117],"type":"Point"}
}