{
  "type": "Feature",
  "properties": {
    "iso:country":"US",
    "sg:address":"111 Kimberly Dr",
    "sg:city":"Sarver",
    "sg:classifiers":[
        {
            "category":"Professional",
            "subcategory":"Business Services",
            "type":"Services"
        }
    ],
    "sg:phone":"+1 724 353 1976",
    "sg:postcode":"16055",
    "sg:province":"PA",
    "sg:tags":[
        "consultant",
        "coach"
    ],
    "wof:name":"Timothy Sample",
    "wof:placetype":"venue"
},
  "geometry": {"coordinates":[-79.76684899999999,40.714578],"type":"Point"}
}