{
  "type": "Feature",
  "properties": {
    "iso:country":"US",
    "sg:address":"2199 Wyndtree Ln",
    "sg:city":"Malvern",
    "sg:classifiers":[
        {
            "category":"Professional",
            "subcategory":"Management & Consulting",
            "type":"Services"
        }
    ],
    "sg:phone":"+1 610 722 0334",
    "sg:postcode":"19355",
    "sg:province":"PA",
    "sg:tags":[
        "consultant"
    ],
    "wof:name":"Calabrese & Assoc",
    "wof:placetype":"venue"
},
  "geometry": {"coordinates":[-75.497412,40.059203],"type":"Point"}
}