{
  "type": "Feature",
  "properties": {
    "addr:full":"9944 Sandy Rd Philadelphia PA 19115",
    "addr:housenumber":"9944",
    "addr:postcode":"19115",
    "addr:street":"Sandy Rd",
    "iso:country":"US",
    "sg:address":"9944 Sandy Rd",
    "sg:city":"Philadelphia",
    "sg:classifiers":[
        {
            "category":"Taxi",
            "type":"Transportation"
        }
    ],
    "sg:phone":"+1 215 673 2062",
    "sg:postcode":"19115",
    "sg:province":"PA",
    "wof:name":"Adeline Cab Company Inc",
    "wof:placetype":"venue"
},
  "geometry": {"coordinates":[-75.02147600000001,40.093282],"type":"Point"}
}