{
  "type": "Feature",
  "properties": {
    "iso:country":"US",
    "sg:address":"107 Oakglen Rd",
    "sg:city":"Pittsburgh",
    "sg:classifiers":[
        {
            "category":"Retail",
            "subcategory":"Auto Repair",
            "type":"Services"
        }
    ],
    "sg:phone":"+1 412 367 4441",
    "sg:postcode":"15237",
    "sg:province":"PA",
    "sg:tags":[
        "body",
        "automobile",
        "painting"
    ],
    "wof:name":"Brian's Like New Shop",
    "wof:placetype":"venue"
},
  "geometry": {"coordinates":[-80.014117,40.520974],"type":"Point"}
}