{
  "type": "Feature",
  "properties": {
    "iso:country":"US",
    "sg:address":"3050 N 5th Street Hwy",
    "sg:city":"Reading",
    "sg:classifiers":[
        {
            "category":"Restaurant",
            "type":"Food & Drink"
        }
    ],
    "sg:phone":"+1 610 929 3611",
    "sg:postcode":"19605",
    "sg:province":"PA",
    "wof:name":"Gatto Pizza",
    "wof:placetype":"venue"
},
  "geometry": {"coordinates":[-75.92755,40.383165],"type":"Point"}
}