{
  "type": "Feature",
  "properties": {
    "addr:full":"4401 Buffalo Rd Erie PA 16510",
    "addr:housenumber":"4401",
    "addr:postcode":"16510",
    "addr:street":"Buffalo Rd",
    "iso:country":"US",
    "sg:address":"4401 Buffalo Rd",
    "sg:city":"Erie",
    "sg:classifiers":[
        {
            "category":"Retail",
            "subcategory":"Portrait Studio",
            "type":"Services"
        }
    ],
    "sg:phone":"+1 814 897 8710",
    "sg:postcode":"16510",
    "sg:province":"PA",
    "sg:tags":[
        "photographer"
    ],
    "wof:name":"Olan Mills Portrait Studio",
    "wof:placetype":"venue"
},
  "geometry": {"coordinates":[-79.99998600000001,42.147718],"type":"Point"}
}