{
  "type": "Feature",
  "properties": {
    "iso:country":"US",
    "sg:address":"4337 Jacksonville Rd",
    "sg:city":"Howard",
    "sg:classifiers":[
        {
            "category":"Government",
            "subcategory":"Office",
            "type":"Public Place"
        }
    ],
    "sg:phone":"+1 814 625 2799",
    "sg:postcode":"16841",
    "sg:province":"PA",
    "sg:tags":[
        "village"
    ],
    "wof:name":"Marion Twp Office",
    "wof:placetype":"venue"
},
  "geometry": {"coordinates":[-77.62934300000001,40.993831],"type":"Point"}
}