{
  "type": "Feature",
  "properties": {
    "iso:country":"US",
    "sg:address":"410 Cowpath Rd",
    "sg:city":"Aliquippa",
    "sg:classifiers":[
        {
            "category":"Building & Trades",
            "subcategory":"Construction",
            "type":"Services"
        }
    ],
    "sg:phone":"+1 724 375 4590",
    "sg:postcode":"15001",
    "sg:province":"PA",
    "sg:tags":[
        "contractor"
    ],
    "wof:name":"Corsi Interior Systems",
    "wof:placetype":"venue"
},
  "geometry": {"coordinates":[-80.31465799999999,40.565063],"type":"Point"}
}