{
  "type": "Feature",
  "properties": {
    "addr:full":"1334 Bridgetown Pike Feasterville Trevose PA 19053",
    "addr:housenumber":"1334",
    "addr:postcode":"19053",
    "addr:street":"Bridgetown Pike",
    "iso:country":"US",
    "sg:address":"1334 Bridgetown Pike",
    "sg:city":"Feasterville Trevose",
    "sg:classifiers":[
        {
            "category":"Professional",
            "subcategory":"Accounting & Tax Preparation",
            "type":"Services"
        }
    ],
    "sg:phone":"+1   ",
    "sg:postcode":"19053",
    "sg:province":"PA",
    "sg:tags":[
        "prepackaged",
        "se",
        "software"
    ],
    "wof:name":"Cast Services",
    "wof:placetype":"venue"
},
  "geometry": {"coordinates":[-74.99723299999999,40.155839],"type":"Point"}
}