{
  "type": "Feature",
  "properties": {
    "addr:full":"7889 Mark Dr Verona PA 15147",
    "addr:housenumber":"7889",
    "addr:postcode":"15147",
    "addr:street":"Mark Dr",
    "iso:country":"US",
    "sg:address":"7889 Mark Dr",
    "sg:city":"Verona",
    "sg:classifiers":[
        {
            "category":"Professional",
            "type":"Services"
        }
    ],
    "sg:phone":"+1   ",
    "sg:postcode":"15147",
    "sg:province":"PA",
    "wof:name":"Ip Squared Inc",
    "wof:placetype":"venue"
},
  "geometry": {"coordinates":[-79.870487,40.469465],"type":"Point"}
}