{
  "type": "Feature",
  "properties": {
    "addr:full":"303 E North St New Castle PA 16101",
    "addr:housenumber":"303",
    "addr:postcode":"16101",
    "addr:street":"E North St",
    "iso:country":"US",
    "sg:address":"303 E North St",
    "sg:city":"New Castle",
    "sg:classifiers":[
        {
            "category":"Banks & Credit Unions",
            "subcategory":"Bank",
            "type":"Services"
        }
    ],
    "sg:phone":"+1   ",
    "sg:postcode":"16101",
    "sg:province":"PA",
    "sg:tags":[
        "state",
        "commercial"
    ],
    "wof:name":"Sky Bank",
    "wof:placetype":"venue"
},
  "geometry": {"coordinates":[-80.34157,41.001505],"type":"Point"}
}