{
  "type": "Feature",
  "properties": {
    "addr:full":"115 Westgate Dr Carbondale PA 18407",
    "addr:housenumber":"115",
    "addr:postcode":"18407",
    "addr:street":"Westgate Dr",
    "iso:country":"US",
    "sg:address":"115 Westgate Dr",
    "sg:city":"Carbondale",
    "sg:classifiers":[
        {
            "category":"Retail",
            "subcategory":"Photofinishing",
            "type":"Services"
        }
    ],
    "sg:phone":"+1   ",
    "sg:postcode":"18407",
    "sg:province":"PA",
    "sg:tags":[
        "laboratory"
    ],
    "wof:name":"Mackrell Photo",
    "wof:placetype":"venue"
},
  "geometry": {"coordinates":[-75.51111299999999,41.571014],"type":"Point"}
}