{
  "type": "Feature",
  "properties": {
    "iso:country":"US",
    "sg:address":"148 Golden City Rd",
    "sg:city":"Saxonburg",
    "sg:classifiers":[
        {
            "category":"Farming",
            "subcategory":"Farm",
            "type":"Manufacturing & Wholesale Goods"
        }
    ],
    "sg:phone":"+1 724 352 2508",
    "sg:postcode":"16056",
    "sg:province":"PA",
    "sg:tags":[
        "crop",
        "general"
    ],
    "wof:name":"Bramblewood Farm",
    "wof:placetype":"venue"
},
  "geometry": {"coordinates":[-79.84799599999999,40.747651],"type":"Point"}
}