{
  "type": "Feature",
  "properties": {
    "iso:country":"US",
    "sg:address":"1090 Wayne Ave",
    "sg:city":"Chambersburg",
    "sg:classifiers":[
        {
            "category":"Organizations",
            "subcategory":"Religious Organization",
            "type":"Services"
        }
    ],
    "sg:phone":"+1 717 709 1126",
    "sg:postcode":"17201",
    "sg:province":"PA",
    "sg:tags":[
        "church"
    ],
    "sg:website":"www.whocenter.org",
    "wof:name":"World Harvest Outreach",
    "wof:placetype":"venue"
},
  "geometry": {"coordinates":[-77.65199800000001,39.912611],"type":"Point"}
}