{
  "type": "Feature",
  "properties": {
    "iso:country":"US",
    "sg:address":"635 W Erie Ave",
    "sg:city":"Philadelphia",
    "sg:classifiers":[
        {
            "category":"Real Estate",
            "subcategory":"Real Estate Services",
            "type":"Services"
        },
        {
            "category":"Banks & Credit Unions",
            "subcategory":"Investment Brokerage",
            "type":"Services"
        }
    ],
    "sg:phone":"+1 215 226 6050",
    "sg:postcode":"19140",
    "sg:province":"PA",
    "sg:tags":[
        "investing"
    ],
    "wof:name":"Munoz Real Estate",
    "wof:placetype":"venue"
},
  "geometry": {"coordinates":[-75.140297,40.007702],"type":"Point"}
}