{
  "type": "Feature",
  "properties": {
    "iso:country":"US",
    "sg:address":"30 Barbara Rd",
    "sg:city":"Hatboro",
    "sg:classifiers":[
        {
            "category":"Retail",
            "subcategory":"Portrait Studio",
            "type":"Services"
        }
    ],
    "sg:phone":"+1   ",
    "sg:postcode":"19040",
    "sg:province":"PA",
    "sg:tags":[
        "photo"
    ],
    "wof:name":"JM Photography",
    "wof:placetype":"venue"
},
  "geometry": {"coordinates":[-75.104837,40.187361],"type":"Point"}
}