{
  "type": "Feature",
  "properties": {
    "iso:country":"US",
    "sg:address":"221 Sheas Ter",
    "sg:city":"Ardmore",
    "sg:classifiers":[
        {
            "category":"Cinema",
            "subcategory":"Movie Rental",
            "type":"Entertainment"
        }
    ],
    "sg:phone":"+1 610 642 2371",
    "sg:postcode":"19003",
    "sg:province":"PA",
    "sg:tags":[
        "leasing",
        "video",
        "disc",
        "tape"
    ],
    "wof:name":"G F Video & Dvd Production",
    "wof:placetype":"venue"
},
  "geometry": {"coordinates":[-75.29524499999999,40.0017],"type":"Point"}
}