{
  "type": "Feature",
  "properties": {
    "iso:country":"US",
    "sg:address":"230 Poplar Rd",
    "sg:city":"Fleetwood",
    "sg:classifiers":[
        {
            "category":"Building & Trades",
            "subcategory":"Construction",
            "type":"Services"
        }
    ],
    "sg:phone":"+1 610 944 6055",
    "sg:postcode":"19522",
    "sg:province":"PA",
    "sg:tags":[
        "concrete",
        "contractor",
        "general"
    ],
    "wof:name":"Snyder's Construction Co",
    "wof:placetype":"venue"
},
  "geometry": {"coordinates":[-75.83515800000001,40.440553],"type":"Point"}
}