{
  "type": "Feature",
  "properties": {
    "iso:country":"US",
    "sg:address":"3120 Faronia St",
    "sg:city":"Pittsburgh",
    "sg:classifiers":[
        {
            "category":"Retail",
            "subcategory":"Laundry & Dry Cleaning",
            "type":"Services"
        }
    ],
    "sg:phone":"+1   ",
    "sg:postcode":"15204",
    "sg:province":"PA",
    "wof:name":"Lidias Creation",
    "wof:placetype":"venue"
},
  "geometry": {"coordinates":[-80.065968,40.451403],"type":"Point"}
}