{
  "type": "Feature",
  "properties": {
    "iso:country":"US",
    "sg:address":"10058 S Mountain Rd",
    "sg:city":"South Mountain",
    "sg:classifiers":[
        {
            "category":"Health Services",
            "subcategory":"Hospital",
            "type":"Services"
        },
        {
            "category":"Organizations",
            "subcategory":"Professional Association",
            "type":"Services"
        }
    ],
    "sg:phone":"+1 717 749 3355",
    "sg:postcode":"17261",
    "sg:province":"PA",
    "sg:tags":[
        "medical",
        "center"
    ],
    "wof:name":"South Mountain Restoration Ctr",
    "wof:placetype":"venue"
},
  "geometry": {"coordinates":[-77.48419699999999,39.845003],"type":"Point"}
}