{
  "type": "Feature",
  "properties": {
    "addr:full":"753 Wambold Rd Souderton PA 18964",
    "addr:housenumber":"753",
    "addr:postcode":"18964",
    "addr:street":"Wambold Rd",
    "iso:country":"US",
    "sg:address":"753 Wambold Rd",
    "sg:city":"Souderton",
    "sg:classifiers":[
        {
            "category":"Wholesale",
            "subcategory":"Durable Goods & Equipment",
            "type":"Manufacturing & Wholesale Goods"
        }
    ],
    "sg:phone":"+1 215 721 9595",
    "sg:postcode":"18964",
    "sg:province":"PA",
    "sg:tags":[
        "representative",
        "manufacturer"
    ],
    "sg:website":"www.airoil.com",
    "wof:name":"Air Oil System Inc",
    "wof:placetype":"venue"
},
  "geometry": {"coordinates":[-75.344714,40.266203],"type":"Point"}
}