{
  "type": "Feature",
  "properties": {
    "iso:country":"US",
    "sg:address":"202 4th St",
    "sg:city":"Irwin",
    "sg:classifiers":[
        {
            "category":"Banks & Credit Unions",
            "subcategory":"Bank",
            "type":"Services"
        }
    ],
    "sg:phone":"+1 724 861 8620",
    "sg:postcode":"15642",
    "sg:province":"PA",
    "sg:tags":[
        "loan",
        "real estate"
    ],
    "wof:name":"Capital Savings & Mortgage",
    "wof:placetype":"venue"
},
  "geometry": {"coordinates":[-79.71034299999999,40.331766],"type":"Point"}
}