{
  "type": "Feature",
  "properties": {
    "iso:country":"US",
    "sg:address":"17 S Washington St",
    "sg:city":"Canton",
    "sg:classifiers":[
        {
            "category":"Government",
            "subcategory":"Office",
            "type":"Public Place"
        }
    ],
    "sg:phone":"+1 570 000 1111",
    "sg:postcode":"17724",
    "sg:province":"PA",
    "sg:tags":[
        "village"
    ],
    "wof:name":"Canton Ambulance",
    "wof:placetype":"venue"
},
  "geometry": {"coordinates":[-76.84825600000001,41.654017],"type":"Point"}
}