{
  "type": "Feature",
  "properties": {
    "iso:country":"US",
    "sg:address":"84 N Ronks Rd",
    "sg:city":"Ronks",
    "sg:classifiers":[
        {
            "category":"Travel",
            "subcategory":"Hotels & Motels",
            "type":"Entertainment"
        }
    ],
    "sg:phone":"+1 717 687 7646",
    "sg:postcode":"17572",
    "sg:province":"PA",
    "wof:name":"Cherry Lane Motor Inn",
    "wof:placetype":"venue"
},
  "geometry": {"coordinates":[-76.167304,40.022663],"type":"Point"}
}