{
  "type": "Feature",
  "properties": {
    "iso:country":"US",
    "sg:address":"2200 E High St",
    "sg:city":"Pottstown",
    "sg:classifiers":[
        {
            "category":"Shopping",
            "subcategory":"Shoes",
            "type":"Retail Goods"
        }
    ],
    "sg:phone":"+1   ",
    "sg:postcode":"19464",
    "sg:province":"PA",
    "sg:tags":[
        "shoe",
        "store"
    ],
    "wof:name":"Meldisco K-M E High St PA Inc",
    "wof:placetype":"venue"
},
  "geometry": {"coordinates":[-75.59509199999999,40.245074],"type":"Point"}
}