{
  "type": "Feature",
  "properties": {
    "iso:country":"US",
    "sg:address":"2701 E Lehigh Ave",
    "sg:city":"Philadelphia",
    "sg:classifiers":[
        {
            "category":"Retail",
            "subcategory":"Laundry & Dry Cleaning",
            "type":"Services"
        },
        {
            "category":"Building & Trades",
            "subcategory":"Cleaning & Sanitation",
            "type":"Services"
        }
    ],
    "sg:phone":"+1 215 380 1085",
    "sg:postcode":"19125",
    "sg:province":"PA",
    "sg:tags":[
        "cleaner",
        "upholstery",
        "rug",
        "carpet"
    ],
    "wof:name":"CarpetSmart",
    "wof:placetype":"venue"
},
  "geometry": {"coordinates":[-75.11428100000001,39.978008],"type":"Point"}
}