{
  "type": "Feature",
  "properties": {
    "iso:country":"US",
    "sg:address":"701 Pennsylvania Ave",
    "sg:city":"Matamoras",
    "sg:classifiers":[
        {
            "category":"Restaurant",
            "type":"Food & Drink"
        }
    ],
    "sg:phone":"+1 570 491 2015",
    "sg:postcode":"18336",
    "sg:province":"PA",
    "sg:tags":[
        "eating"
    ],
    "wof:name":"Stewart's Family Restaurant",
    "wof:placetype":"venue"
},
  "geometry": {"coordinates":[-74.70343699999999,41.365815],"type":"Point"}
}