{
  "type": "Feature",
  "properties": {
    "addr:full":"928 Emerson St Allentown PA 18103",
    "addr:housenumber":"928",
    "addr:postcode":"18103",
    "addr:street":"Emerson St",
    "iso:country":"US",
    "sg:address":"928 Emerson St",
    "sg:city":"Allentown",
    "sg:classifiers":[
        {
            "category":"Professional",
            "subcategory":"Accounting & Tax Preparation",
            "type":"Services"
        }
    ],
    "sg:phone":"+1   ",
    "sg:postcode":"18103",
    "sg:province":"PA",
    "sg:tags":[
        "return"
    ],
    "wof:name":"Tax Lady",
    "wof:placetype":"venue"
},
  "geometry": {"coordinates":[-75.50771,40.579746],"type":"Point"}
}