{
  "type": "Feature",
  "properties": {
    "iso:country":"US",
    "sg:address":"80 Glenwood Ave",
    "sg:city":"Bradford",
    "sg:classifiers":[
        {
            "category":"Retail",
            "subcategory":"Animal Services",
            "type":"Services"
        }
    ],
    "sg:phone":"+1 814 362 8850",
    "sg:postcode":"16701",
    "sg:province":"PA",
    "sg:tags":[
        "shelter"
    ],
    "wof:name":"Mc KEAN County SPCA",
    "wof:placetype":"venue"
},
  "geometry": {"coordinates":[-78.624942,41.970721],"type":"Point"}
}