{
  "type": "Feature",
  "properties": {
    "addr:full":"25 Moyer Rd Collegeville PA 19426",
    "addr:housenumber":"25",
    "addr:postcode":"19426",
    "addr:street":"Moyer Rd",
    "iso:country":"US",
    "sg:address":"25 Moyer Rd",
    "sg:city":"Collegeville",
    "sg:classifiers":[
        {
            "category":"Building & Trades",
            "subcategory":"Construction",
            "type":"Services"
        }
    ],
    "sg:phone":"+1   ",
    "sg:postcode":"19426",
    "sg:province":"PA",
    "sg:tags":[
        "house"
    ],
    "wof:name":"K T M P Home Improvements",
    "wof:placetype":"venue"
},
  "geometry": {"coordinates":[-75.43174,40.158988],"type":"Point"}
}