{
  "type": "Feature",
  "properties": {
    "iso:country":"US",
    "sg:address":"9088 Wesleyan Rd",
    "sg:city":"Philadelphia",
    "sg:classifiers":[
        {
            "category":"Building & Trades",
            "subcategory":"Construction",
            "type":"Services"
        }
    ],
    "sg:phone":"+1 215 969 0124",
    "sg:postcode":"19136",
    "sg:province":"PA",
    "sg:tags":[
        "roofing",
        "contractor"
    ],
    "wof:name":"Edward G Foisy",
    "wof:placetype":"venue"
},
  "geometry": {"coordinates":[-75.018247,40.058945],"type":"Point"}
}