{
  "type": "Feature",
  "properties": {
    "iso:country":"US",
    "sg:address":"10670 Hwy 18",
    "sg:city":"Conneaut Lake",
    "sg:classifiers":[
        {
            "category":"Organizations",
            "subcategory":"Religious Organization",
            "type":"Services"
        }
    ],
    "sg:phone":"+1 814 382 9496",
    "sg:postcode":"16316",
    "sg:province":"PA",
    "sg:tags":[
        "church"
    ],
    "sg:website":"www.victoryfwc.org",
    "wof:name":"Victory Family Worship Ctr",
    "wof:placetype":"venue"
},
  "geometry": {"coordinates":[-80.28755099999999,41.605903],"type":"Point"}
}