{
  "type": "Feature",
  "properties": {
    "iso:country":"US",
    "sg:address":"120 E 6th St",
    "sg:city":"Chester",
    "sg:classifiers":[
        {
            "category":"Building & Trades",
            "subcategory":"Cleaning & Sanitation",
            "type":"Services"
        }
    ],
    "sg:phone":"+1 610 447 3855",
    "sg:postcode":"19013",
    "sg:province":"PA",
    "sg:tags":[
        "maintenance"
    ],
    "wof:name":"Chester Upland School Dist",
    "wof:placetype":"venue"
},
  "geometry": {"coordinates":[-75.358165,39.850575],"type":"Point"}
}