{
  "type": "Feature",
  "properties": {
    "addr:full":"1754 Costner Dr Warrington PA 18976",
    "addr:postcode":"1754;18976",
    "addr:street":"Costner Dr",
    "iso:country":"US",
    "sg:address":"1754 Costner Dr",
    "sg:city":"Warrington",
    "sg:classifiers":[
        {
            "category":"Banks & Credit Unions",
            "subcategory":"Investment Brokerage",
            "type":"Services"
        }
    ],
    "sg:phone":"+1 215 343 7730",
    "sg:postcode":"18976",
    "sg:province":"PA",
    "sg:tags":[
        "advisory",
        "accountant"
    ],
    "sg:website":"www.coreoutsource.com",
    "wof:name":"Core Financial Outsourcing, Inc.",
    "wof:placetype":"venue"
},
  "geometry": {"coordinates":[-75.131674,40.221357],"type":"Point"}
}