{
  "type": "Feature",
  "properties": {
    "addr:full":"350 Stevenson Blvd New Kensington PA 15068",
    "addr:housenumber":"350",
    "addr:postcode":"15068",
    "addr:street":"Stevenson Blvd",
    "iso:country":"US",
    "sg:address":"350 Stevenson Blvd",
    "sg:city":"New Kensington",
    "sg:classifiers":[
        {
            "category":"Insurance",
            "subcategory":"Insurance Agent",
            "type":"Services"
        }
    ],
    "sg:phone":"+1 724 334 3743",
    "sg:postcode":"15068",
    "sg:province":"PA",
    "wof:name":"Dennis Tunney Insurance",
    "wof:placetype":"venue"
},
  "geometry": {"coordinates":[-79.75946500000001,40.556602],"type":"Point"}
}