{
  "type": "Feature",
  "properties": {
    "iso:country":"US",
    "sg:address":"1800 E Race St",
    "sg:city":"Allentown",
    "sg:classifiers":[
        {
            "category":"Utilities",
            "subcategory":"Telephone",
            "type":"Services"
        }
    ],
    "sg:phone":"+1 610 820 4300",
    "sg:postcode":"18109",
    "sg:province":"PA",
    "sg:tags":[
        "telecommunication"
    ],
    "wof:name":"Verizon Communications",
    "wof:placetype":"venue"
},
  "geometry": {"coordinates":[-75.42676299999999,40.661968],"type":"Point"}
}