{
  "type": "Feature",
  "properties": {
    "iso:country":"US",
    "sg:address":"721 S Chester Rd",
    "sg:city":"Swarthmore",
    "sg:classifiers":[
        {
            "category":"Shopping",
            "subcategory":"Discount & Variety Stores",
            "type":"Retail Goods"
        }
    ],
    "sg:phone":"+1 610 544 8750",
    "sg:postcode":"19081",
    "sg:province":"PA",
    "sg:tags":[
        "merchandise",
        "general"
    ],
    "wof:name":"Dollar Magic",
    "wof:placetype":"venue"
},
  "geometry": {"coordinates":[-75.355082,39.88823],"type":"Point"}
}