{
  "type": "Feature",
  "properties": {
    "iso:country":"US",
    "sg:address":"1163 Marcus Dr",
    "sg:city":"Pottstown",
    "sg:classifiers":[
        {
            "category":"Building & Trades",
            "subcategory":"Construction",
            "type":"Services"
        }
    ],
    "sg:phone":"+1 610 326 2605",
    "sg:postcode":"19465",
    "sg:province":"PA",
    "sg:tags":[
        "furniture",
        "equipment-installation",
        "contractor"
    ],
    "wof:name":"Quittner Contracting",
    "wof:placetype":"venue"
},
  "geometry": {"coordinates":[-75.64984699999999,40.225208],"type":"Point"}
}