{
  "type": "Feature",
  "properties": {
    "addr:full":"2994 S Madden Rd Hustontown PA 17229",
    "addr:housenumber":"2994",
    "addr:postcode":"17229",
    "addr:street":"S Madden Rd",
    "iso:country":"US",
    "sg:address":"2994 S Madden Rd",
    "sg:city":"Hustontown",
    "sg:classifiers":[
        {
            "category":"Farming",
            "subcategory":"Farm",
            "type":"Manufacturing & Wholesale Goods"
        }
    ],
    "sg:phone":"+1 717 485 5558",
    "sg:postcode":"17229",
    "sg:province":"PA",
    "wof:name":"Huston Hollow Farm",
    "wof:placetype":"venue"
},
  "geometry": {"coordinates":[-78.018951,40.073659],"type":"Point"}
}