{
  "type": "Feature",
  "properties": {
    "addr:full":"7963 Rextown Rd Slatington PA 18080",
    "addr:housenumber":"7963",
    "addr:postcode":"18080",
    "addr:street":"Rextown Rd",
    "iso:country":"US",
    "sg:address":"7963 Rextown Rd",
    "sg:city":"Slatington",
    "sg:classifiers":[
        {
            "category":"Professional",
            "subcategory":"Business Services",
            "type":"Services"
        }
    ],
    "sg:phone":"+1   ",
    "sg:postcode":"18080",
    "sg:province":"PA",
    "wof:name":"EA Christman",
    "wof:placetype":"venue"
},
  "geometry": {"coordinates":[-75.64069600000001,40.742973],"type":"Point"}
}