{
  "type": "Feature",
  "properties": {
    "iso:country":"US",
    "sg:address":"1190 N Penryn Rd",
    "sg:city":"Manheim",
    "sg:classifiers":[
        {
            "category":"Professional",
            "subcategory":"Management & Consulting",
            "type":"Services"
        }
    ],
    "sg:phone":"+1   ",
    "sg:postcode":"17545",
    "sg:province":"PA",
    "sg:tags":[
        "retail",
        "direct",
        "sales"
    ],
    "wof:name":"Avon Saleswoman",
    "wof:placetype":"venue"
},
  "geometry": {"coordinates":[-76.37212700000001,40.200459],"type":"Point"}
}