{
  "type": "Feature",
  "properties": {
    "iso:country":"US",
    "sg:address":"14 Greeves St",
    "sg:city":"Kane",
    "sg:classifiers":[
        {
            "category":"Utilities",
            "subcategory":"Natural Gas",
            "type":"Services"
        }
    ],
    "sg:phone":"+1 814 837 6441",
    "sg:postcode":"16735",
    "sg:province":"PA",
    "wof:name":"Sergeant Gas Co",
    "wof:placetype":"venue"
},
  "geometry": {"coordinates":[-78.810292,41.659231],"type":"Point"}
}