{
  "type": "Feature",
  "properties": {
    "iso:country":"US",
    "sg:address":"3801 Ridge Ave",
    "sg:city":"Philadelphia",
    "sg:classifiers":[
        {
            "category":"Shopping",
            "subcategory":"Stationery & Office Supplies",
            "type":"Retail Goods"
        }
    ],
    "sg:phone":"+1 215 229 0500",
    "sg:postcode":"19132",
    "sg:province":"PA",
    "sg:tags":[
        "equipment"
    ],
    "wof:name":"Telrose Corporation",
    "wof:placetype":"venue"
},
  "geometry": {"coordinates":[-75.187044,40.002897],"type":"Point"}
}