{
  "type": "Feature",
  "properties": {
    "addr:full":"40 Longview Rd Birdsboro PA 19508",
    "addr:housenumber":"40",
    "addr:postcode":"19508",
    "addr:street":"Longview Rd",
    "iso:country":"US",
    "sg:address":"40 Longview Rd",
    "sg:city":"Birdsboro",
    "sg:classifiers":[
        {
            "category":"Freight",
            "type":"Transportation"
        }
    ],
    "sg:phone":"+1 610 404 7299",
    "sg:postcode":"19508",
    "sg:province":"PA",
    "sg:tags":[
        "trucking"
    ],
    "wof:name":"Kimberly's Hauling",
    "wof:placetype":"venue"
},
  "geometry": {"coordinates":[-75.78064500000001,40.294547],"type":"Point"}
}