{
  "type": "Feature",
  "properties": {
    "addr:full":"725 2nd Street Pike Richboro PA 18954",
    "addr:housenumber":"725",
    "addr:postcode":"18954",
    "addr:street":"2Nd Street Pike",
    "iso:country":"US",
    "sg:address":"725 2nd Street Pike",
    "sg:city":"Richboro",
    "sg:classifiers":[
        {
            "category":"Restaurant",
            "type":"Food & Drink"
        }
    ],
    "sg:phone":"+1 215 322 7804",
    "sg:postcode":"18954",
    "sg:province":"PA",
    "sg:tags":[
        "eating"
    ],
    "wof:name":"Pizza Hut",
    "wof:placetype":"venue"
},
  "geometry": {"coordinates":[-75.015508,40.207976],"type":"Point"}
}