{
  "type": "Feature",
  "properties": {
    "iso:country":"US",
    "sg:address":"950 Mercer Rd",
    "sg:city":"Butler",
    "sg:classifiers":[
        {
            "category":"Social Services",
            "subcategory":"Child Care",
            "type":"Services"
        },
        {
            "category":"Social Services",
            "type":"Services"
        }
    ],
    "sg:phone":"+1 724 282 2233",
    "sg:postcode":"16001",
    "sg:province":"PA",
    "sg:tags":[
        "organization",
        "day",
        "welfare"
    ],
    "wof:name":"Butler Y M C A Child Care",
    "wof:placetype":"venue"
},
  "geometry": {"coordinates":[-79.92897000000001,40.902103],"type":"Point"}
}