{
  "type": "Feature",
  "properties": {
    "addr:full":"2005 S Easton Rd Ste 307 Doylestown PA 18901",
    "addr:housenumber":"2005",
    "addr:postcode":"18901",
    "addr:street":"S Easton Rd Ste 307",
    "iso:country":"US",
    "sg:address":"2005 S Easton Rd Ste 307",
    "sg:city":"Doylestown",
    "sg:classifiers":[
        {
            "category":"Real Estate",
            "subcategory":"Real Estate Services",
            "type":"Services"
        }
    ],
    "sg:phone":"+1 215 933 0300",
    "sg:postcode":"18901",
    "sg:province":"PA",
    "sg:tags":[
        "management",
        "property"
    ],
    "wof:name":"Doylestown Real Estate Inc",
    "wof:placetype":"venue"
},
  "geometry": {"coordinates":[-75.127488,40.292847],"type":"Point"}
}