{
  "type": "Feature",
  "properties": {
    "iso:country":"US",
    "sg:address":"11 Pecan Trl",
    "sg:city":"Fairfield",
    "sg:classifiers":[
        {
            "category":"Building & Trades",
            "subcategory":"Construction",
            "type":"Services"
        }
    ],
    "sg:phone":"+1   ",
    "sg:postcode":"17320",
    "sg:province":"PA",
    "sg:tags":[
        "excavation",
        "contractor"
    ],
    "wof:name":"Mountainview Excavating",
    "wof:placetype":"venue"
},
  "geometry": {"coordinates":[-77.381443,39.734445],"type":"Point"}
}