{
  "type": "Feature",
  "properties": {
    "addr:full":"6812 Ardleigh St Philadelphia PA 19119",
    "addr:housenumber":"6812",
    "addr:postcode":"19119",
    "addr:street":"Ardleigh St",
    "iso:country":"US",
    "sg:address":"6812 Ardleigh St",
    "sg:city":"Philadelphia",
    "sg:classifiers":[
        {
            "category":"Professional",
            "subcategory":"Management & Consulting",
            "type":"Services"
        }
    ],
    "sg:phone":"+1 215 843 7277",
    "sg:postcode":"19119",
    "sg:province":"PA",
    "sg:tags":[
        "consultant",
        "business"
    ],
    "wof:name":"Stand By Systems Inc",
    "wof:placetype":"venue"
},
  "geometry": {"coordinates":[-75.180301,40.061745],"type":"Point"}
}