{
  "type": "Feature",
  "properties": {
    "iso:country":"US",
    "sg:address":"5027 E Trindle Rd",
    "sg:city":"Mechanicsburg",
    "sg:classifiers":[
        {
            "category":"Banks & Credit Unions",
            "subcategory":"Investment Brokerage",
            "type":"Services"
        }
    ],
    "sg:phone":"+1 717 697 6659",
    "sg:postcode":"17050",
    "sg:province":"PA",
    "sg:tags":[
        "consultant",
        "planning",
        "financial"
    ],
    "wof:name":"Waddell & Reed Financial Svc",
    "wof:placetype":"venue"
},
  "geometry": {"coordinates":[-76.971323,40.225485],"type":"Point"}
}