{
  "type": "Feature",
  "properties": {
    "addr:full":"629 Greythorne Rd Wynnewood PA 19096",
    "addr:housenumber":"629",
    "addr:postcode":"19096",
    "addr:street":"Greythorne Rd",
    "iso:country":"US",
    "sg:address":"629 Greythorne Rd",
    "sg:city":"Wynnewood",
    "sg:classifiers":[
        {
            "category":"Manufacturing",
            "subcategory":"Textiles",
            "type":"Manufacturing & Wholesale Goods"
        }
    ],
    "sg:phone":"+1 610 649 1666",
    "sg:postcode":"19096",
    "sg:province":"PA",
    "wof:name":"Liberty Textile Group Inc",
    "wof:placetype":"venue"
},
  "geometry": {"coordinates":[-75.285895,39.994392],"type":"Point"}
}