{
  "type": "Feature",
  "properties": {
    "addr:full":"1200 S Main St Phoenixville PA 19460",
    "addr:housenumber":"1200",
    "addr:postcode":"19460",
    "addr:street":"S Main St",
    "iso:country":"US",
    "sg:address":"1200 S Main St",
    "sg:city":"Phoenixville",
    "sg:classifiers":[
        {
            "category":"Organizations",
            "subcategory":"Religious Organization",
            "type":"Services"
        }
    ],
    "sg:phone":"+1 610 933 7805",
    "sg:postcode":"19460",
    "sg:province":"PA",
    "sg:tags":[
        "church"
    ],
    "wof:name":"First Christian Science Church",
    "wof:placetype":"venue"
},
  "geometry": {"coordinates":[-75.516116,40.120093],"type":"Point"}
}