{
  "type": "Feature",
  "properties": {
    "addr:full":"999 Berkshire Blvd Ste. 180 Reading PA 19610",
    "addr:housenumber":"999",
    "addr:postcode":"19610",
    "addr:street":"Berkshire Blvd Ste. 180",
    "iso:country":"US",
    "sg:address":"999 Berkshire Blvd Ste. 180",
    "sg:city":"Reading",
    "sg:classifiers":[
        {
            "category":"Professional",
            "subcategory":"Employment Agencies",
            "type":"Services"
        }
    ],
    "sg:phone":"+1 877 237 4790",
    "sg:postcode":"19610",
    "sg:province":"PA",
    "sg:tags":[
        "opportunity",
        "consultant",
        "temporary",
        "contractor"
    ],
    "sg:website":"http://www-aerotek-com.netsolads.com/?LEC-6UM982376821&_nsag=33207",
    "wof:name":"Aerotek",
    "wof:placetype":"venue"
},
  "geometry": {"coordinates":[-75.971619,40.347172],"type":"Point"}
}