{
  "type": "Feature",
  "properties": {
    "iso:country":"US",
    "sg:address":"2845 W Highland St",
    "sg:city":"Allentown",
    "sg:classifiers":[
        {
            "category":"Building & Trades",
            "subcategory":"Construction",
            "type":"Services"
        }
    ],
    "sg:phone":"+1 610 820 5542",
    "sg:postcode":"18104",
    "sg:province":"PA",
    "sg:tags":[
        "altering",
        "contractor",
        "remodeling",
        "hanging"
    ],
    "wof:name":"J C Kessler Painting Plus",
    "wof:placetype":"venue"
},
  "geometry": {"coordinates":[-75.52421,40.605867],"type":"Point"}
}