{
  "type": "Feature",
  "properties": {
    "addr:full":"339 Walnut St Johnstown PA 15901",
    "addr:housenumber":"339",
    "addr:postcode":"15901",
    "addr:street":"Walnut St",
    "iso:country":"US",
    "sg:address":"339 Walnut St",
    "sg:city":"Johnstown",
    "sg:classifiers":[
        {
            "category":"Shopping",
            "subcategory":"Pharmacy",
            "type":"Retail Goods"
        }
    ],
    "sg:phone":"+1 814 535 3203",
    "sg:postcode":"15901",
    "sg:province":"PA",
    "wof:name":"Johnstown Pharmacy",
    "wof:placetype":"venue"
},
  "geometry": {"coordinates":[-78.923732,40.32403],"type":"Point"}
}