{
  "type": "Feature",
  "properties": {
    "addr:full":"207 Sweitzer Rd Mount Pleasant PA 15666",
    "addr:housenumber":"207",
    "addr:postcode":"15666",
    "addr:street":"Sweitzer Rd",
    "iso:country":"US",
    "sg:address":"207 Sweitzer Rd",
    "sg:city":"Mount Pleasant",
    "sg:phone":"+1   ",
    "sg:postcode":"15666",
    "sg:province":"PA",
    "sg:tags":[
        "farm",
        "corn",
        "crop",
        "general",
        "field",
        "animal"
    ],
    "wof:name":"Larry Husak Farm",
    "wof:placetype":"venue"
},
  "geometry": {"coordinates":[-79.47811900000001,40.113189],"type":"Point"}
}