{
  "type": "Feature",
  "properties": {
    "addr:full":"5270 Logan Ferry Rd Murrysville PA 15668",
    "addr:housenumber":"5270",
    "addr:postcode":"15668",
    "addr:street":"Logan Ferry Rd",
    "iso:country":"US",
    "sg:address":"5270 Logan Ferry Rd",
    "sg:city":"Murrysville",
    "sg:classifiers":[
        {
            "category":"Professional",
            "type":"Services"
        },
        {
            "category":"Professional",
            "subcategory":"Computer Services",
            "type":"Services"
        }
    ],
    "sg:phone":"+1 724 733 8700",
    "sg:postcode":"15668",
    "sg:province":"PA",
    "sg:tags":[
        "establishment",
        "suppl",
        "programing",
        "custom"
    ],
    "sg:website":"www.asarebar.com",
    "wof:name":"Applied Systems Associates Inc",
    "wof:placetype":"venue"
},
  "geometry": {"coordinates":[-79.695611,40.486505],"type":"Point"}
}