{
  "type": "Feature",
  "properties": {
    "addr:full":"670 Rock Rd Pine Grove PA 17963",
    "addr:housenumber":"670",
    "addr:postcode":"17963",
    "addr:street":"Rock Rd",
    "iso:country":"US",
    "sg:address":"670 Rock Rd",
    "sg:city":"Pine Grove",
    "sg:classifiers":[
        {
            "category":"Organizations",
            "subcategory":"Community Association",
            "type":"Services"
        }
    ],
    "sg:phone":"+1 570 345 6340",
    "sg:postcode":"17963",
    "sg:province":"PA",
    "sg:tags":[
        "club"
    ],
    "wof:name":"Flying Dutchmen Motor Cycle",
    "wof:placetype":"venue"
},
  "geometry": {"coordinates":[-76.323534,40.545492],"type":"Point"}
}