{
  "type": "Feature",
  "properties": {
    "iso:country":"US",
    "sg:address":"17 N 23rd St",
    "sg:city":"Reading",
    "sg:classifiers":[
        {
            "category":"Health Services",
            "subcategory":"Doctor",
            "type":"Services"
        }
    ],
    "sg:phone":"+1 610 779 8394",
    "sg:postcode":"19606",
    "sg:province":"PA",
    "sg:tags":[
        "dentist"
    ],
    "wof:name":"Glenn D Ruoss DDS",
    "wof:placetype":"venue"
},
  "geometry": {"coordinates":[-75.89160800000001,40.328531],"type":"Point"}
}