{
  "type": "Feature",
  "properties": {
    "addr:full":"198 Colonial Village Dr Pittsburgh PA 15235",
    "addr:housenumber":"198",
    "addr:postcode":"15235",
    "addr:street":"Colonial Village Dr",
    "iso:country":"US",
    "sg:address":"198 Colonial Village Dr",
    "sg:city":"Pittsburgh",
    "sg:classifiers":[
        {
            "category":"Building & Trades",
            "subcategory":"Construction",
            "type":"Services"
        }
    ],
    "sg:phone":"+1   ",
    "sg:postcode":"15235",
    "sg:province":"PA",
    "sg:tags":[
        "home"
    ],
    "wof:name":"Nicholas Spclzed Constructions",
    "wof:placetype":"venue"
},
  "geometry": {"coordinates":[-79.79084400000001,40.47509],"type":"Point"}
}