{
  "type": "Feature",
  "properties": {
    "iso:country":"US",
    "sg:address":"2385 N Penn Rd",
    "sg:city":"Hatfield",
    "sg:classifiers":[
        {
            "category":"Manufacturing",
            "subcategory":"Tools & Machinery",
            "type":"Manufacturing & Wholesale Goods"
        }
    ],
    "sg:phone":"+1 215 822 1963",
    "sg:postcode":"19440",
    "sg:province":"PA",
    "sg:tags":[
        "water"
    ],
    "sg:website":"www.keystone-filter.com",
    "wof:name":"Keystone Filter",
    "wof:placetype":"venue"
},
  "geometry": {"coordinates":[-75.28864299999999,40.292634],"type":"Point"}
}