{
  "type": "Feature",
  "properties": {
    "iso:country":"US",
    "sg:address":"750 Barclay Dr",
    "sg:city":"Bedford",
    "sg:classifiers":[
        {
            "category":"Communications",
            "subcategory":"Radio Station",
            "type":"Services"
        }
    ],
    "sg:phone":"+1   ",
    "sg:postcode":"15522",
    "sg:province":"PA",
    "sg:tags":[
        "educational"
    ],
    "wof:name":"William Letrent",
    "wof:placetype":"venue"
},
  "geometry": {"coordinates":[-78.50943700000001,40.008711],"type":"Point"}
}