{
  "type": "Feature",
  "properties": {
    "addr:full":"657 Cherry Tree Ln Uniontown PA 15401",
    "addr:housenumber":"657",
    "addr:postcode":"15401",
    "addr:street":"Cherry Tree Ln",
    "iso:country":"US",
    "sg:address":"657 Cherry Tree Ln",
    "sg:city":"Uniontown",
    "sg:classifiers":[
        {
            "category":"Professional",
            "subcategory":"Lawyer & Legal Services",
            "type":"Services"
        }
    ],
    "sg:phone":"+1 724 438 3020",
    "sg:postcode":"15401",
    "sg:province":"PA",
    "sg:tags":[
        "attorney"
    ],
    "wof:name":"Kunkel & Fink",
    "wof:placetype":"venue"
},
  "geometry": {"coordinates":[-79.752692,39.899339],"type":"Point"}
}