{
  "type": "Feature",
  "properties": {
    "addr:full":"6500 Chapmans Rd Allentown PA 18106",
    "addr:postcode":"6500;18106",
    "addr:street":"Chapmans Rd",
    "iso:country":"US",
    "sg:address":"6500 Chapmans Rd",
    "sg:city":"Allentown",
    "sg:classifiers":[
        {
            "category":"Manufacturing",
            "subcategory":"Tools & Machinery",
            "type":"Manufacturing & Wholesale Goods"
        }
    ],
    "sg:phone":"+1   ",
    "sg:postcode":"18106",
    "sg:province":"PA",
    "sg:tags":[
        "newspaper",
        "inserting"
    ],
    "wof:name":"Nb Systems LLC",
    "wof:placetype":"venue"
},
  "geometry": {"coordinates":[-75.600908,40.586198],"type":"Point"}
}