{
  "type": "Feature",
  "properties": {
    "addr:full":"1615 Shepard Dr Ambler PA 19002",
    "addr:housenumber":"1615",
    "addr:postcode":"19002",
    "addr:street":"Shepard Dr",
    "iso:country":"US",
    "sg:address":"1615 Shepard Dr",
    "sg:city":"Ambler",
    "sg:classifiers":[
        {
            "category":"Manufacturing",
            "subcategory":"Signs",
            "type":"Manufacturing & Wholesale Goods"
        }
    ],
    "sg:phone":"+1 215 793 4931",
    "sg:postcode":"19002",
    "sg:province":"PA",
    "sg:tags":[
        "specialty",
        "mfg"
    ],
    "wof:name":"Pearce Signs",
    "wof:placetype":"venue"
},
  "geometry": {"coordinates":[-75.181066,40.167483],"type":"Point"}
}