{
  "type": "Feature",
  "properties": {
    "iso:country":"US",
    "sg:address":"611 Lombard St",
    "sg:city":"Philadelphia",
    "sg:classifiers":[
        {
            "category":"Real Estate",
            "subcategory":"Architect",
            "type":"Services"
        }
    ],
    "sg:phone":"+1 215 627 3667",
    "sg:postcode":"19147",
    "sg:province":"PA",
    "wof:name":"Roth Robert B Jr Aia",
    "wof:placetype":"venue"
},
  "geometry": {"coordinates":[-75.152252,39.943175],"type":"Point"}
}