{
  "type": "Feature",
  "properties": {
    "addr:full":"924 Constitution Blvd New Kensington PA 15068",
    "addr:housenumber":"924",
    "addr:postcode":"15068",
    "addr:street":"Constitution Blvd",
    "iso:country":"US",
    "sg:address":"924 Constitution Blvd",
    "sg:city":"New Kensington",
    "sg:classifiers":[
        {
            "category":"Social Services",
            "subcategory":"Child Care",
            "type":"Services"
        }
    ],
    "sg:phone":"+1 724 339 6180",
    "sg:postcode":"15068",
    "sg:province":"PA",
    "wof:name":"YMCA Of New Kensington Ctr",
    "wof:placetype":"venue"
},
  "geometry": {"coordinates":[-79.76397,40.566383],"type":"Point"}
}