{
  "type": "Feature",
  "properties": {
    "iso:country":"US",
    "sg:address":"7321 W Market St",
    "sg:city":"Mercer",
    "sg:classifiers":[
        {
            "category":"Professional",
            "subcategory":"Lawyer & Legal Services",
            "type":"Services"
        }
    ],
    "sg:phone":"+1 724 346 5621",
    "sg:postcode":"16137",
    "sg:province":"PA",
    "sg:tags":[
        "attorney"
    ],
    "wof:name":"Thomas Macmurdo",
    "wof:placetype":"venue"
},
  "geometry": {"coordinates":[-80.347845,41.236198],"type":"Point"}
}