{
  "type": "Feature",
  "properties": {
    "iso:country":"US",
    "sg:address":"227 Wild Cherry Ln",
    "sg:city":"Northumberland",
    "sg:classifiers":[
        {
            "category":"Organizations",
            "subcategory":"Membership Organization",
            "type":"Services"
        }
    ],
    "sg:phone":"+1   ",
    "sg:postcode":"17857",
    "sg:province":"PA",
    "wof:name":"Roll Foundation",
    "wof:placetype":"venue"
},
  "geometry": {"coordinates":[-76.790466,40.899373],"type":"Point"}
}