{
  "type": "Feature",
  "properties": {
    "iso:country":"US",
    "sg:address":"119 N Swarthmore Ave",
    "sg:city":"Ridley Park",
    "sg:classifiers":[
        {
            "category":"Wholesale",
            "subcategory":"Construction Materials",
            "type":"Manufacturing & Wholesale Goods"
        }
    ],
    "sg:phone":"+1 610 595 2290",
    "sg:postcode":"19078",
    "sg:province":"PA",
    "sg:tags":[
        "equipment",
        "roofing",
        "supply"
    ],
    "wof:name":"Commercial Roofing Solutions",
    "wof:placetype":"venue"
},
  "geometry": {"coordinates":[-75.32365,39.878756],"type":"Point"}
}