{
  "type": "Feature",
  "properties": {
    "addr:full":"7434 Derry St Harrisburg PA 17111",
    "addr:housenumber":"7434",
    "addr:postcode":"17111",
    "addr:street":"Derry St",
    "iso:country":"US",
    "sg:address":"7434 Derry St",
    "sg:city":"Harrisburg",
    "sg:classifiers":[
        {
            "category":"Restaurant",
            "type":"Food & Drink"
        }
    ],
    "sg:phone":"+1 717 561 8688",
    "sg:postcode":"17111",
    "sg:province":"PA",
    "sg:tags":[
        "asian",
        "chinese",
        "pan"
    ],
    "wof:name":"Happy Dragon Chinese Rest Inc",
    "wof:placetype":"venue"
},
  "geometry": {"coordinates":[-76.761264,40.265149],"type":"Point"}
}