{
  "type": "Feature",
  "properties": {
    "addr:full":"1 Oxford Valley Rd Fairless Hills PA 19030",
    "addr:housenumber":"1",
    "addr:postcode":"19030",
    "addr:street":"Oxford Valley Rd",
    "iso:country":"US",
    "sg:address":"1 Oxford Valley Rd",
    "sg:city":"Fairless Hills",
    "sg:classifiers":[
        {
            "category":"Government",
            "subcategory":"Post Office",
            "type":"Public Place"
        }
    ],
    "sg:phone":"+1   ",
    "sg:postcode":"19030",
    "sg:province":"PA",
    "wof:name":"Fairless Hills Main Office",
    "wof:placetype":"venue"
},
  "geometry": {"coordinates":[-74.860315,40.175734],"type":"Point"}
}