{
  "type": "Feature",
  "properties": {
    "iso:country":"US",
    "sg:address":"828 Martha Ave",
    "sg:city":"Lancaster",
    "sg:classifiers":[
        {
            "category":"Health Services",
            "subcategory":"Hospital",
            "type":"Services"
        }
    ],
    "sg:phone":"+1 717 291 8208",
    "sg:postcode":"17601",
    "sg:province":"PA",
    "sg:website":"http://www.hma-corp.com",
    "wof:name":"Heart Hospital Of Lancaster",
    "wof:placetype":"venue"
},
  "geometry": {"coordinates":[-76.290948,40.057266],"type":"Point"}
}