{
  "type": "Feature",
  "properties": {
    "iso:country":"US",
    "sg:address":"1144 Old Freeport Rd",
    "sg:city":"Pittsburgh",
    "sg:classifiers":[
        {
            "category":"Professional",
            "subcategory":"Business Services",
            "type":"Services"
        }
    ],
    "sg:phone":"+1   ",
    "sg:postcode":"15238",
    "sg:province":"PA",
    "sg:tags":[
        "interior",
        "decorator"
    ],
    "wof:name":"Upstairs At Merry B",
    "wof:placetype":"venue"
},
  "geometry": {"coordinates":[-79.88293899999999,40.487455],"type":"Point"}
}