{
  "type": "Feature",
  "properties": {
    "iso:country":"US",
    "sg:address":"530 N Cannon Ave",
    "sg:city":"Lansdale",
    "sg:classifiers":[
        {
            "category":"Restaurant",
            "type":"Food & Drink"
        }
    ],
    "sg:phone":"+1 215 855 3785",
    "sg:postcode":"19446",
    "sg:province":"PA",
    "sg:website":"www.molettiere.com",
    "wof:name":"Molettiere's Cafe",
    "wof:placetype":"venue"
},
  "geometry": {"coordinates":[-75.287063,40.249898],"type":"Point"}
}