{
  "type": "Feature",
  "properties": {
    "iso:country":"US",
    "sg:address":"1002 Underwood Rd",
    "sg:city":"Olyphant",
    "sg:classifiers":[
        {
            "category":"Professional",
            "subcategory":"Management & Consulting",
            "type":"Services"
        }
    ],
    "sg:phone":"+1   ",
    "sg:postcode":"18447",
    "sg:province":"PA",
    "wof:name":"Fore of US Inc",
    "wof:placetype":"venue"
},
  "geometry": {"coordinates":[-75.58755499999999,41.453775],"type":"Point"}
}