{
  "type": "Feature",
  "properties": {
    "iso:country":"US",
    "sg:address":"2934 W 26th St",
    "sg:city":"Erie",
    "sg:classifiers":[
        {
            "category":"Autos & Motor Vehicles",
            "subcategory":"Automobile Sales",
            "type":"Retail Goods"
        }
    ],
    "sg:phone":"+1 814 833 1071",
    "sg:postcode":"16506",
    "sg:province":"PA",
    "sg:tags":[
        "used",
        "car",
        "dealers-used",
        "new",
        "cars-wholesale"
    ],
    "wof:name":"Markd Motors, Inc.",
    "wof:placetype":"venue"
},
  "geometry": {"coordinates":[-80.138541,42.087793],"type":"Point"}
}