{
  "type": "Feature",
  "properties": {
    "iso:country":"US",
    "sg:address":"823 Pine Hill Rd",
    "sg:city":"Lititz",
    "sg:classifiers":[
        {
            "category":"Organizations",
            "subcategory":"Religious Organization",
            "type":"Services"
        }
    ],
    "sg:phone":"+1 717 626 8685",
    "sg:postcode":"17543",
    "sg:province":"PA",
    "sg:tags":[
        "clergy"
    ],
    "wof:name":"Mark B Boll",
    "wof:placetype":"venue"
},
  "geometry": {"coordinates":[-76.278013,40.176118],"type":"Point"}
}