{
  "type": "Feature",
  "properties": {
    "iso:country":"US",
    "sg:address":"626 E Street Rd",
    "sg:city":"Southampton",
    "sg:classifiers":[
        {
            "category":"Professional",
            "subcategory":"Accounting & Tax Preparation",
            "type":"Services"
        }
    ],
    "sg:phone":"+1 215 357 4937",
    "sg:postcode":"18966",
    "sg:province":"PA",
    "wof:name":"Norman Braeunle CPA",
    "wof:placetype":"venue"
},
  "geometry": {"coordinates":[-75.044257,40.174682],"type":"Point"}
}