{
  "type": "Feature",
  "properties": {
    "addr:full":"1311 Penn Ave Wyomissing PA 19610",
    "addr:housenumber":"1311",
    "addr:postcode":"19610",
    "addr:street":"Penn Ave",
    "iso:country":"US",
    "sg:address":"1311 Penn Ave",
    "sg:city":"Wyomissing",
    "sg:classifiers":[
        {
            "category":"Retail",
            "subcategory":"Auto Rental",
            "type":"Services"
        }
    ],
    "sg:phone":"+1 610 373 0101",
    "sg:postcode":"19610",
    "sg:province":"PA",
    "sg:tags":[
        "renting",
        "truck",
        "leasing"
    ],
    "wof:name":"Budget Truck Rental",
    "wof:placetype":"venue"
},
  "geometry": {"coordinates":[-75.967699,40.332176],"type":"Point"}
}