{
  "type": "Feature",
  "properties": {
    "addr:full":"1708 Oram St Scranton PA 18504",
    "addr:postcode":"1708;18504",
    "addr:street":"Oram St",
    "iso:country":"US",
    "sg:address":"1708 Oram St",
    "sg:city":"Scranton",
    "sg:classifiers":[
        {
            "category":"Real Estate",
            "subcategory":"Developer",
            "type":"Services"
        }
    ],
    "sg:phone":"+1 570 207 2209",
    "sg:postcode":"18504",
    "sg:province":"PA",
    "sg:tags":[
        "cemetery"
    ],
    "sg:website":"http://www.catholiccemomaha.com",
    "wof:name":"Catholic Cemeteries Inc.",
    "wof:placetype":"venue"
},
  "geometry": {"coordinates":[-75.678281,41.42415],"type":"Point"}
}