{
  "type": "Feature",
  "properties": {
    "iso:country":"US",
    "sg:address":"530 E Broad St",
    "sg:city":"Quakertown",
    "sg:classifiers":[
        {
            "category":"Autos & Motor Vehicles",
            "subcategory":"Fuel & Gas Station",
            "type":"Retail Goods"
        },
        {
            "category":"Utilities",
            "subcategory":"Fuel Oil & Lpg",
            "type":"Services"
        }
    ],
    "sg:phone":"+1 215 538 5375",
    "sg:postcode":"18951",
    "sg:province":"PA",
    "sg:tags":[
        "oils-fuel"
    ],
    "wof:name":"S G Fuel Inc",
    "wof:placetype":"venue"
},
  "geometry": {"coordinates":[-75.326571,40.439919],"type":"Point"}
}