{
  "type": "Feature",
  "properties": {
    "addr:full":"2611 Nicholson Rd Ste 2 Sewickley PA 15143",
    "addr:housenumber":"2611",
    "addr:postcode":"15143",
    "addr:street":"Nicholson Rd Ste 2",
    "iso:country":"US",
    "sg:address":"2611 Nicholson Rd Ste 2",
    "sg:city":"Sewickley",
    "sg:classifiers":[
        {
            "category":"Personal",
            "subcategory":"Nail Salon",
            "type":"Services"
        }
    ],
    "sg:phone":"+1 724 933 3338",
    "sg:postcode":"15143",
    "sg:province":"PA",
    "wof:name":"Pedicure Junction Tips",
    "wof:placetype":"venue"
},
  "geometry": {"coordinates":[-80.099993,40.612237],"type":"Point"}
}