{
  "type": "Feature",
  "properties": {
    "iso:country":"US",
    "sg:address":"19 Brandywine Dr",
    "sg:city":"Glenmoore",
    "sg:classifiers":[
        {
            "category":"Building & Trades",
            "subcategory":"Landscaping Services",
            "type":"Services"
        }
    ],
    "sg:phone":"+1   ",
    "sg:postcode":"19343",
    "sg:province":"PA",
    "wof:name":"Chester Cnty Lawn Ldscp Maint",
    "wof:placetype":"venue"
},
  "geometry": {"coordinates":[-75.822238,40.059467],"type":"Point"}
}