{
  "type": "Feature",
  "properties": {
    "addr:full":"216 S 52nd St Philadelphia PA 19139",
    "addr:housenumber":"216",
    "addr:postcode":"19139",
    "addr:street":"S 52Nd St",
    "iso:country":"US",
    "sg:address":"216 S 52nd St",
    "sg:city":"Philadelphia",
    "sg:classifiers":[
        {
            "category":"Personal",
            "subcategory":"Beauty Salon",
            "type":"Services"
        }
    ],
    "sg:phone":"+1 215 474 3444",
    "sg:postcode":"19139",
    "sg:province":"PA",
    "sg:tags":[
        "hair"
    ],
    "wof:name":"Art of Beauty the",
    "wof:placetype":"venue"
},
  "geometry": {"coordinates":[-75.22585100000001,39.95652],"type":"Point"}
}