{
  "type": "Feature",
  "properties": {
    "iso:country":"US",
    "sg:address":"1407 Bethlehem Pike",
    "sg:city":"Flourtown",
    "sg:classifiers":[
        {
            "category":"Insurance",
            "subcategory":"Insurance Agent",
            "type":"Services"
        }
    ],
    "sg:phone":"+1 610 260 2300",
    "sg:postcode":"19031",
    "sg:province":"PA",
    "wof:name":"Ing Security Life Of Denver",
    "wof:placetype":"venue"
},
  "geometry": {"coordinates":[-75.213255,40.104421],"type":"Point"}
}