{
  "type": "Feature",
  "properties": {
    "addr:full":"987 Wayne Ave Chambersburg PA 17201",
    "addr:housenumber":"987",
    "addr:postcode":"17201",
    "addr:street":"Wayne Ave",
    "iso:country":"US",
    "sg:address":"987 Wayne Ave",
    "sg:city":"Chambersburg",
    "sg:classifiers":[
        {
            "category":"Shopping",
            "subcategory":"Pharmacy",
            "type":"Retail Goods"
        }
    ],
    "sg:phone":"+1   ",
    "sg:postcode":"17201",
    "sg:province":"PA",
    "wof:name":"CVS",
    "wof:placetype":"venue"
},
  "geometry": {"coordinates":[-77.65271799999999,39.91347],"type":"Point"}
}