{
  "type": "Feature",
  "properties": {
    "iso:country":"US",
    "sg:address":"107 W Germantown Pike",
    "sg:city":"Norristown",
    "sg:classifiers":[
        {
            "category":"Restaurant",
            "type":"Food & Drink"
        }
    ],
    "sg:phone":"+1   ",
    "sg:postcode":"19401",
    "sg:province":"PA",
    "sg:tags":[
        "eating"
    ],
    "wof:name":"Charlies Pizza",
    "wof:placetype":"venue"
},
  "geometry": {"coordinates":[-75.321314,40.145945],"type":"Point"}
}