{
  "type": "Feature",
  "properties": {
    "iso:country":"US",
    "sg:address":"756 Mount Rd",
    "sg:city":"Aston",
    "sg:classifiers":[
        {
            "category":"Building & Trades",
            "subcategory":"Construction",
            "type":"Services"
        }
    ],
    "sg:phone":"+1   ",
    "sg:postcode":"19014",
    "sg:province":"PA",
    "sg:tags":[
        "contractor"
    ],
    "wof:name":"Action Seal Coating",
    "wof:placetype":"venue"
},
  "geometry": {"coordinates":[-75.444641,39.884912],"type":"Point"}
}