{
  "type": "Feature",
  "properties": {
    "iso:country":"US",
    "sg:address":"2629 E Cumberland St",
    "sg:city":"Lebanon",
    "sg:classifiers":[
        {
            "category":"Home & Garden",
            "subcategory":"Carpets & Floor Coverings",
            "type":"Retail Goods"
        }
    ],
    "sg:phone":"+1 717 272 0114",
    "sg:postcode":"17042",
    "sg:province":"PA",
    "sg:tags":[
        "dealer",
        "rug"
    ],
    "wof:name":"Keilholz's Flooring",
    "wof:placetype":"venue"
},
  "geometry": {"coordinates":[-76.358198,40.360772],"type":"Point"}
}