{
  "type": "Feature",
  "properties": {
    "addr:full":"1821 Memphis St Philadelphia PA 19125",
    "addr:housenumber":"1821",
    "addr:postcode":"19125",
    "addr:street":"Memphis St",
    "iso:country":"US",
    "sg:address":"1821 Memphis St",
    "sg:city":"Philadelphia",
    "sg:classifiers":[
        {
            "category":"Banks & Credit Unions",
            "subcategory":"Bank",
            "type":"Services"
        }
    ],
    "sg:phone":"+1 215 423 5800",
    "sg:postcode":"19125",
    "sg:province":"PA",
    "sg:tags":[
        "broker",
        "mortgage"
    ],
    "wof:name":"Professional Mortgage Corp",
    "wof:placetype":"venue"
},
  "geometry": {"coordinates":[-75.129501,39.976299],"type":"Point"}
}