{
  "type": "Feature",
  "properties": {
    "iso:country":"US",
    "sg:address":"326 Ridgeway Pl",
    "sg:city":"Philadelphia",
    "sg:classifiers":[
        {
            "category":"Health Services",
            "subcategory":"Clinic",
            "type":"Services"
        }
    ],
    "sg:phone":"+1 215 969 0999",
    "sg:postcode":"19116",
    "sg:province":"PA",
    "sg:tags":[
        "home"
    ],
    "wof:name":"Care 4 You Inc",
    "wof:placetype":"venue"
},
  "geometry": {"coordinates":[-75.033427,40.115201],"type":"Point"}
}