{
  "type": "Feature",
  "properties": {
    "iso:country":"US",
    "sg:address":"308 E Pennsylvania Blvd",
    "sg:city":"Feastervl Trvs",
    "sg:classifiers":[
        {
            "category":"Building & Trades",
            "subcategory":"Electrical",
            "type":"Services"
        }
    ],
    "sg:phone":"+1 215 396 2830",
    "sg:postcode":"19053",
    "sg:province":"PA",
    "sg:tags":[
        "electrical",
        "electric",
        "contractor"
    ],
    "wof:name":"Moeller Electric Inc",
    "wof:placetype":"venue"
},
  "geometry": {"coordinates":[-75.00983600000001,40.151776],"type":"Point"}
}