{
  "type": "Feature",
  "properties": {
    "iso:country":"US",
    "sg:address":"6256 Kellers Church Rd",
    "sg:city":"Pipersville",
    "sg:classifiers":[
        {
            "category":"Professional",
            "type":"Services"
        }
    ],
    "sg:phone":"+1 215 766 1640",
    "sg:postcode":"18947",
    "sg:province":"PA",
    "sg:tags":[
        "establishment"
    ],
    "wof:name":"BMS Technologies Inc",
    "wof:placetype":"venue"
},
  "geometry": {"coordinates":[-75.15425999999999,40.392775],"type":"Point"}
}