{
  "type": "Feature",
  "properties": {
    "addr:full":"2700 Turnpike Industrial Park Middletown PA 17057",
    "addr:housenumber":"2700",
    "addr:postcode":"17057",
    "addr:street":"Turnpike Industrial Park",
    "iso:country":"US",
    "sg:address":"2700 Turnpike Industrial Park",
    "sg:city":"Middletown",
    "sg:classifiers":[
        {
            "category":"Wholesale",
            "subcategory":"Office Equipment",
            "type":"Manufacturing & Wholesale Goods"
        }
    ],
    "sg:phone":"+1 717 939 2700",
    "sg:postcode":"17057",
    "sg:province":"PA",
    "sg:tags":[
        "machine",
        "mailing"
    ],
    "sg:website":"www.prioritysystems.com",
    "wof:name":"Priority Systems Inc",
    "wof:placetype":"venue"
},
  "geometry": {"coordinates":[-76.78424699999999,40.218621],"type":"Point"}
}