{
  "type": "Feature",
  "properties": {
    "iso:country":"US",
    "sg:address":"65 Shady Tree Dr",
    "sg:city":"Mountain Top",
    "sg:classifiers":[
        {
            "category":"Government",
            "subcategory":"Office",
            "type":"Public Place"
        }
    ],
    "sg:phone":"+1 570 000 1111",
    "sg:postcode":"18707",
    "sg:province":"PA",
    "sg:tags":[
        "village"
    ],
    "wof:name":"Fairview Twp Police Dept",
    "wof:placetype":"venue"
},
  "geometry": {"coordinates":[-75.882373,41.153383],"type":"Point"}
}