{
  "type": "Feature",
  "properties": {
    "iso:country":"US",
    "sg:address":"207 House Ave Ste 101",
    "sg:city":"Camp Hill",
    "sg:classifiers":[
        {
            "category":"Health Services",
            "subcategory":"Doctor",
            "type":"Services"
        }
    ],
    "sg:phone":"+1 717 761 8331",
    "sg:postcode":"17011",
    "sg:province":"PA",
    "wof:name":"Conner-Rich Associates",
    "wof:placetype":"venue"
},
  "geometry": {"coordinates":[-76.918198,40.253502],"type":"Point"}
}