{
  "type": "Feature",
  "properties": {
    "iso:country":"US",
    "sg:address":"401 Bingham St",
    "sg:city":"Pittsburgh",
    "sg:classifiers":[
        {
            "category":"Arts & Performance",
            "subcategory":"Art Gallery",
            "type":"Entertainment"
        }
    ],
    "sg:phone":"+1 412 431 5140",
    "sg:postcode":"15203",
    "sg:province":"PA",
    "wof:name":"Berger M Industrial Real Estate Co",
    "wof:placetype":"venue"
},
  "geometry": {"coordinates":[-79.995598,40.429901],"type":"Point"}
}