{
  "type": "Feature",
  "properties": {
    "iso:country":"US",
    "sg:address":"10 Brookline Blvd",
    "sg:city":"Havertown",
    "sg:classifiers":[
        {
            "category":"Food & Beverages",
            "subcategory":"Groceries & Convenience Stores",
            "type":"Retail Goods"
        },
        {
            "category":"Restaurant",
            "type":"Food & Drink"
        }
    ],
    "sg:phone":"+1 610 853 2466",
    "sg:postcode":"19083",
    "sg:province":"PA",
    "sg:tags":[
        "delicatessen"
    ],
    "wof:name":"Centrella's Deli",
    "wof:placetype":"venue"
},
  "geometry": {"coordinates":[-75.30216900000001,39.979682],"type":"Point"}
}