{
  "type": "Feature",
  "properties": {
    "addr:full":"4280 Frankford Ave Philadelphia PA 19124",
    "addr:housenumber":"4280",
    "addr:postcode":"19124",
    "addr:street":"Frankford Ave",
    "iso:country":"US",
    "sg:address":"4280 Frankford Ave",
    "sg:city":"Philadelphia",
    "sg:classifiers":[
        {
            "category":"Building & Trades",
            "subcategory":"Locksmith",
            "type":"Services"
        }
    ],
    "sg:phone":"+1 267 350 9919",
    "sg:postcode":"19124",
    "sg:province":"PA",
    "sg:tags":[
        "key"
    ],
    "wof:name":"A Locksmith Service",
    "wof:placetype":"venue"
},
  "geometry": {"coordinates":[-75.089057,40.010655],"type":"Point"}
}