{
  "type": "Feature",
  "properties": {
    "addr:full":"192 Fulton Rd Oxford PA 19363",
    "addr:housenumber":"192",
    "addr:postcode":"19363",
    "addr:street":"Fulton Rd",
    "iso:country":"US",
    "sg:address":"192 Fulton Rd",
    "sg:city":"Oxford",
    "sg:classifiers":[
        {
            "category":"Farming",
            "subcategory":"Dairy Farm",
            "type":"Manufacturing & Wholesale Goods"
        }
    ],
    "sg:phone":"+1   ",
    "sg:postcode":"19363",
    "sg:province":"PA",
    "wof:name":"Ronald Fulton",
    "wof:placetype":"venue"
},
  "geometry": {"coordinates":[-75.95679199999999,39.779467],"type":"Point"}
}