{
  "type": "Feature",
  "properties": {
    "iso:country":"US",
    "sg:address":"1573 Landvater Rd",
    "sg:city":"Hummelstown",
    "sg:classifiers":[
        {
            "category":"Manufacturing",
            "subcategory":"Printing",
            "type":"Manufacturing & Wholesale Goods"
        }
    ],
    "sg:phone":"+1   ",
    "sg:postcode":"17036",
    "sg:province":"PA",
    "sg:tags":[
        "consulting",
        "book",
        "business"
    ],
    "wof:name":"Buffington Associates",
    "wof:placetype":"venue"
},
  "geometry": {"coordinates":[-76.691042,40.230599],"type":"Point"}
}