{
  "type": "Feature",
  "properties": {
    "iso:country":"US",
    "sg:address":"8 Waterloo Ave",
    "sg:city":"Berwyn",
    "sg:classifiers":[
        {
            "category":"Personal",
            "type":"Services"
        }
    ],
    "sg:phone":"+1 610 296 6300",
    "sg:postcode":"19312",
    "sg:province":"PA",
    "sg:tags":[
        "consultant",
        "consulting",
        "wedding"
    ],
    "sg:website":"www.perfectweddings.tv",
    "wof:name":"Perfect Weddings LLC",
    "wof:placetype":"venue"
},
  "geometry": {"coordinates":[-75.442556,40.046442],"type":"Point"}
}