{
  "type": "Feature",
  "properties": {
    "addr:full":"1074 Old Lancaster Rd Berwyn PA 19312",
    "addr:housenumber":"1074",
    "addr:postcode":"19312",
    "addr:street":"Old Lancaster Rd",
    "iso:country":"US",
    "sg:address":"1074 Old Lancaster Rd",
    "sg:city":"Berwyn",
    "sg:classifiers":[
        {
            "category":"Professional",
            "subcategory":"Management & Consulting",
            "type":"Services"
        }
    ],
    "sg:phone":"+1   ",
    "sg:postcode":"19312",
    "sg:province":"PA",
    "sg:tags":[
        "business"
    ],
    "wof:name":"Garbowski Communication Entps",
    "wof:placetype":"venue"
},
  "geometry": {"coordinates":[-75.45410099999999,40.045254],"type":"Point"}
}