{
  "type": "Feature",
  "properties": {
    "iso:country":"US",
    "sg:address":"2225 N Front St",
    "sg:city":"Philadelphia",
    "sg:classifiers":[
        {
            "category":"Home & Garden",
            "subcategory":"Furniture",
            "type":"Retail Goods"
        }
    ],
    "sg:phone":"+1 215 425 7235",
    "sg:postcode":"19133",
    "sg:province":"PA",
    "sg:tags":[
        "store"
    ],
    "wof:name":"Furniture & Appliance Depot",
    "wof:placetype":"venue"
},
  "geometry": {"coordinates":[-75.13249999999999,39.983898],"type":"Point"}
}