{
  "type": "Feature",
  "properties": {
    "addr:full":"79 Laurel St Wilkes Barre PA 18702",
    "addr:housenumber":"79",
    "addr:postcode":"18702",
    "addr:street":"Laurel St",
    "iso:country":"US",
    "sg:address":"79 Laurel St",
    "sg:city":"Wilkes Barre",
    "sg:classifiers":[
        {
            "category":"Organizations",
            "subcategory":"Religious Organization",
            "type":"Services"
        }
    ],
    "sg:phone":"+1 570 825 9512",
    "sg:postcode":"18702",
    "sg:province":"PA",
    "sg:tags":[
        "church"
    ],
    "wof:name":"East End Primitive Methodist",
    "wof:placetype":"venue"
},
  "geometry": {"coordinates":[-75.86075,41.248644],"type":"Point"}
}