{
  "type": "Feature",
  "properties": {
    "addr:full":"384 Black Rd Cochranton PA 16314",
    "addr:housenumber":"384",
    "addr:postcode":"16314",
    "addr:street":"Black Rd",
    "iso:country":"US",
    "sg:address":"384 Black Rd",
    "sg:city":"Cochranton",
    "sg:classifiers":[
        {
            "category":"Banks & Credit Unions",
            "subcategory":"Financial Services",
            "type":"Services"
        }
    ],
    "sg:phone":"+1   ",
    "sg:postcode":"16314",
    "sg:province":"PA",
    "sg:tags":[
        "trust",
        "management"
    ],
    "wof:name":"Alvin Stoker Trustee",
    "wof:placetype":"venue"
},
  "geometry": {"coordinates":[-80.036182,41.48179],"type":"Point"}
}