{
  "type": "Feature",
  "properties": {
    "addr:full":"1585 E Mountain Rd Hegins PA 17938",
    "addr:housenumber":"1585",
    "addr:postcode":"17938",
    "addr:street":"E Mountain Rd",
    "iso:country":"US",
    "sg:address":"1585 E Mountain Rd",
    "sg:city":"Hegins",
    "sg:classifiers":[
        {
            "category":"Wholesale",
            "subcategory":"Meat",
            "type":"Manufacturing & Wholesale Goods"
        }
    ],
    "sg:phone":"+1 570 682 3449",
    "sg:postcode":"17938",
    "sg:province":"PA",
    "sg:tags":[
        "product"
    ],
    "wof:name":"Bixler's Country Meats",
    "wof:placetype":"venue"
},
  "geometry": {"coordinates":[-76.58210800000001,40.650669],"type":"Point"}
}