{
  "type": "Feature",
  "properties": {
    "addr:full":"927 W Whitehall Rd State College PA 16801",
    "addr:housenumber":"927",
    "addr:postcode":"16801",
    "addr:street":"W Whitehall Rd",
    "iso:country":"US",
    "sg:address":"927 W Whitehall Rd",
    "sg:city":"State College",
    "sg:classifiers":[
        {
            "category":"Education",
            "subcategory":"Special Training",
            "type":"Public Place"
        }
    ],
    "sg:phone":"+1 814 861 0555",
    "sg:postcode":"16801",
    "sg:province":"PA",
    "sg:tags":[
        "program"
    ],
    "wof:name":"Training Resource Group",
    "wof:placetype":"venue"
},
  "geometry": {"coordinates":[-77.86241699999999,40.768844],"type":"Point"}
}