{
  "type": "Feature",
  "properties": {
    "iso:country":"US",
    "sg:address":"26 Ihnat Ln",
    "sg:city":"Avella",
    "sg:classifiers":[
        {
            "category":"Shopping",
            "subcategory":"Bicycles & Sporting Goods",
            "type":"Retail Goods"
        }
    ],
    "sg:phone":"+1   ",
    "sg:postcode":"15312",
    "sg:province":"PA",
    "wof:name":"Worm World",
    "wof:placetype":"venue"
},
  "geometry": {"coordinates":[-80.404662,40.277021],"type":"Point"}
}