{
  "type": "Feature",
  "properties": {
    "iso:country":"US",
    "sg:address":"8013 Revere Pl",
    "sg:city":"Aliquippa",
    "sg:classifiers":[
        {
            "category":"Building & Trades",
            "subcategory":"Construction",
            "type":"Services"
        }
    ],
    "sg:phone":"+1 724 378 9908",
    "sg:postcode":"15001",
    "sg:province":"PA",
    "sg:tags":[
        "excavation",
        "heavy",
        "excavating",
        "contractor"
    ],
    "wof:name":"Bob's Excavating",
    "wof:placetype":"venue"
},
  "geometry": {"coordinates":[-80.278235,40.562251],"type":"Point"}
}