{
  "type": "Feature",
  "properties": {
    "addr:full":"714 Sassafras St Erie PA 16501",
    "addr:housenumber":"714",
    "addr:postcode":"16501",
    "addr:street":"Sassafras St",
    "iso:country":"US",
    "sg:address":"714 Sassafras St",
    "sg:city":"Erie",
    "sg:classifiers":[
        {
            "category":"Real Estate",
            "subcategory":"Real Estate Agent",
            "type":"Services"
        }
    ],
    "sg:phone":"+1 814 456 0757",
    "sg:postcode":"16501",
    "sg:province":"PA",
    "sg:tags":[
        "consultant"
    ],
    "wof:name":"Painter Realty",
    "wof:placetype":"venue"
},
  "geometry": {"coordinates":[-80.087799,42.126191],"type":"Point"}
}