{
  "type": "Feature",
  "properties": {
    "iso:country":"US",
    "sg:address":"970 Gladestry Ln",
    "sg:city":"Ambler",
    "sg:classifiers":[
        {
            "category":"Banks & Credit Unions",
            "subcategory":"Investment Brokerage",
            "type":"Services"
        }
    ],
    "sg:phone":"+1   ",
    "sg:postcode":"19002",
    "sg:province":"PA",
    "sg:tags":[
        "security"
    ],
    "wof:name":"Sally A Gupton DDS",
    "wof:placetype":"venue"
},
  "geometry": {"coordinates":[-75.24553899999999,40.174171],"type":"Point"}
}