{
  "type": "Feature",
  "properties": {
    "iso:country":"US",
    "sg:address":"80 E North St",
    "sg:city":"Wilkes Barre",
    "sg:classifiers":[
        {
            "category":"Retail",
            "subcategory":"Auto Repair",
            "type":"Services"
        }
    ],
    "sg:phone":"+1   ",
    "sg:postcode":"18701",
    "sg:province":"PA",
    "sg:tags":[
        "automotive",
        "general"
    ],
    "wof:name":"Lous Garage Inc",
    "wof:placetype":"venue"
},
  "geometry": {"coordinates":[-75.873299,41.247081],"type":"Point"}
}