{
  "type": "Feature",
  "properties": {
    "iso:country":"US",
    "sg:address":"4500 N 20th St",
    "sg:city":"Philadelphia",
    "sg:classifiers":[
        {
            "category":"Deli",
            "type":"Food & Drink"
        }
    ],
    "sg:phone":"+1 215 324 0777",
    "sg:postcode":"19140",
    "sg:province":"PA",
    "wof:name":"4500 Wll Inc",
    "wof:placetype":"venue"
},
  "geometry": {"coordinates":[-75.157898,40.022999],"type":"Point"}
}