{
  "type": "Feature",
  "properties": {
    "addr:full":"3411 Lil Wolf Dr Orefield PA 18069",
    "addr:housenumber":"3411",
    "addr:postcode":"18069",
    "addr:street":"Lil Wolf Dr Orefield",
    "iso:country":"US",
    "sg:address":"3411 Lil Wolf Dr",
    "sg:city":"Orefield",
    "sg:classifiers":[
        {
            "category":"Real Estate",
            "subcategory":"Real Estate Operator",
            "type":"Services"
        }
    ],
    "sg:phone":"+1   ",
    "sg:postcode":"18069",
    "sg:province":"PA",
    "sg:tags":[
        "mobile",
        "home",
        "site"
    ],
    "wof:name":"Home Town Lil Wolf",
    "wof:placetype":"venue"
},
  "geometry": {"coordinates":[-75.588354,40.647933],"type":"Point"}
}