{
  "type": "Feature",
  "properties": {
    "iso:country":"US",
    "sg:address":"502 Spruce St",
    "sg:city":"Hellertown",
    "sg:classifiers":[
        {
            "category":"Shopping",
            "subcategory":"Hobbies, Toys, & Games",
            "type":"Retail Goods"
        }
    ],
    "sg:phone":"+1   ",
    "sg:postcode":"18055",
    "sg:province":"PA",
    "wof:name":"Rainbow Butterfly Inc",
    "wof:placetype":"venue"
},
  "geometry": {"coordinates":[-75.332993,40.57444],"type":"Point"}
}