{
  "type": "Feature",
  "properties": {
    "iso:country":"US",
    "sg:address":"501 2nd St",
    "sg:city":"Catasauqua",
    "sg:classifiers":[
        {
            "category":"Restaurant",
            "type":"Food & Drink"
        }
    ],
    "sg:phone":"+1 610 266 2599",
    "sg:postcode":"18032",
    "sg:province":"PA",
    "sg:tags":[
        "eating",
        "pizza"
    ],
    "wof:name":"Catty Pizza & Restaurant",
    "wof:placetype":"venue"
},
  "geometry": {"coordinates":[-75.47350299999999,40.654301],"type":"Point"}
}