{
  "type": "Feature",
  "properties": {
    "iso:country":"US",
    "sg:address":"180 W Jamestown Rd",
    "sg:city":"Greenville",
    "sg:classifiers":[
        {
            "category":"Shopping",
            "subcategory":"Computers & Home Electronics",
            "type":"Retail Goods"
        }
    ],
    "sg:phone":"+1 724 588 1340",
    "sg:postcode":"16125",
    "sg:province":"PA",
    "sg:tags":[
        "software"
    ],
    "wof:name":"Lakeland Technical Svc",
    "wof:placetype":"venue"
},
  "geometry": {"coordinates":[-80.39923400000001,41.413627],"type":"Point"}
}