{
  "type": "Feature",
  "properties": {
    "iso:country":"US",
    "sg:address":"24 N Main St",
    "sg:city":"Nazareth",
    "sg:classifiers":[
        {
            "category":"Building & Trades",
            "subcategory":"Landscaping Services",
            "type":"Services"
        }
    ],
    "sg:phone":"+1 610 746 0137",
    "sg:postcode":"18064",
    "sg:province":"PA",
    "sg:tags":[
        "landscape",
        "contractor"
    ],
    "wof:name":"Shafer Landscaping & Lawn Care",
    "wof:placetype":"venue"
},
  "geometry": {"coordinates":[-75.311809,40.743509],"type":"Point"}
}