{
  "type": "Feature",
  "properties": {
    "iso:country":"US",
    "sg:address":"220 N Jackson St",
    "sg:city":"Media",
    "sg:classifiers":[
        {
            "category":"Professional",
            "subcategory":"Lawyer & Legal Services",
            "type":"Services"
        }
    ],
    "sg:phone":"+1 610 627 2300",
    "sg:postcode":"19063",
    "sg:province":"PA",
    "sg:tags":[
        "attorney"
    ],
    "wof:name":"Mutzel & Wesner",
    "wof:placetype":"venue"
},
  "geometry": {"coordinates":[-75.38905099999999,39.919947],"type":"Point"}
}