{
  "type": "Feature",
  "properties": {
    "addr:full":"220 Smith Rd Red Lion PA 17356",
    "addr:housenumber":"220",
    "addr:postcode":"17356",
    "addr:street":"Smith Rd",
    "iso:country":"US",
    "sg:address":"220 Smith Rd",
    "sg:city":"Red Lion",
    "sg:classifiers":[
        {
            "category":"Home & Garden",
            "subcategory":"Hardware",
            "type":"Retail Goods"
        }
    ],
    "sg:phone":"+1 717 244 6170",
    "sg:postcode":"17356",
    "sg:province":"PA",
    "wof:name":"Harry W Smith Co",
    "wof:placetype":"venue"
},
  "geometry": {"coordinates":[-76.58006899999999,39.89959],"type":"Point"}
}