{
  "type": "Feature",
  "properties": {
    "addr:full":"196 Airport Rd Hazleton PA 18202",
    "addr:housenumber":"196",
    "addr:postcode":"18202",
    "addr:street":"Airport Rd",
    "iso:country":"US",
    "sg:address":"196 Airport Rd",
    "sg:city":"Hazleton",
    "sg:classifiers":[
        {
            "category":"Food & Beverages",
            "subcategory":"Candy",
            "type":"Retail Goods"
        }
    ],
    "sg:phone":"+1 570 454 1260",
    "sg:postcode":"18202",
    "sg:province":"PA",
    "sg:tags":[
        "confectionery"
    ],
    "wof:name":"Candy Bouquet",
    "wof:placetype":"venue"
},
  "geometry": {"coordinates":[-75.991467,40.992436],"type":"Point"}
}