{
  "type": "Feature",
  "properties": {
    "iso:country":"US",
    "sg:address":"201 State St",
    "sg:city":"Hamburg",
    "sg:classifiers":[
        {
            "category":"Professional",
            "subcategory":"Computer Services",
            "type":"Services"
        }
    ],
    "sg:phone":"+1   ",
    "sg:postcode":"19526",
    "sg:province":"PA",
    "wof:name":"DJM PC/Repair",
    "wof:placetype":"venue"
},
  "geometry": {"coordinates":[-75.98464199999999,40.554817],"type":"Point"}
}