{
  "type": "Feature",
  "properties": {
    "addr:full":"410 Central Ave Johnstown PA 15902",
    "addr:housenumber":"410",
    "addr:postcode":"15902",
    "addr:street":"Central Ave",
    "iso:country":"US",
    "sg:address":"410 Central Ave",
    "sg:city":"Johnstown",
    "sg:classifiers":[
        {
            "category":"Restaurant",
            "type":"Food & Drink"
        }
    ],
    "sg:menulink":"http://www.allmenus.com/pa/johnstown/67710-foxs-pizza-den/menu/",
    "sg:phone":"+1 814 532 8677",
    "sg:postcode":"15902",
    "sg:province":"PA",
    "sg:tags":[
        "american",
        "pizza"
    ],
    "wof:name":"Fox's Pizza Den",
    "wof:placetype":"venue"
},
  "geometry": {"coordinates":[-78.91130800000001,40.300264],"type":"Point"}
}