{
  "type": "Feature",
  "properties": {
    "iso:country":"US",
    "sg:address":"212 W Broad St",
    "sg:city":"Bethlehem",
    "sg:classifiers":[
        {
            "category":"Professional",
            "subcategory":"Lawyer & Legal Services",
            "type":"Services"
        }
    ],
    "sg:phone":"+1 610 865 6048",
    "sg:postcode":"18018",
    "sg:province":"PA",
    "wof:name":"Barrett Kathryn A Atty",
    "wof:placetype":"venue"
},
  "geometry": {"coordinates":[-75.385902,40.622501],"type":"Point"}
}