{
  "type": "Feature",
  "properties": {
    "iso:country":"US",
    "sg:address":"1100 5th Ave",
    "sg:city":"Duncansville",
    "sg:classifiers":[
        {
            "category":"Real Estate",
            "subcategory":"Real Estate Agent",
            "type":"Services"
        }
    ],
    "sg:phone":"+1   ",
    "sg:postcode":"16635",
    "sg:province":"PA",
    "wof:name":"Green Land Enterprises",
    "wof:placetype":"venue"
},
  "geometry": {"coordinates":[-78.433752,40.425252],"type":"Point"}
}