{
  "type": "Feature",
  "properties": {
    "addr:full":"2200 Greenock Buena Vista Rd Mckeesport PA 15135",
    "addr:housenumber":"2200",
    "addr:postcode":"15135",
    "addr:street":"Greenock Buena Vista Rd",
    "iso:country":"US",
    "sg:address":"2200 Greenock Buena Vista Rd",
    "sg:city":"Mckeesport",
    "sg:classifiers":[
        {
            "category":"Place Of Worship",
            "subcategory":"Church",
            "type":"Public Place"
        },
        {
            "category":"Place Of Worship",
            "type":"Public Place"
        }
    ],
    "sg:phone":"+1 412 751 8479",
    "sg:postcode":"15135",
    "sg:province":"PA",
    "sg:tags":[
        "churches-presbyterian-arp",
        "churches-presbyterian"
    ],
    "sg:website":"http://www.pcwoodbury.com",
    "wof:name":"Mount Vernon Cmnty Presbt Ch",
    "wof:placetype":"venue"
},
  "geometry": {"coordinates":[-79.813507,40.29641],"type":"Point"}
}