{
  "type": "Feature",
  "properties": {
    "iso:country":"US",
    "sg:address":"515 E Main St",
    "sg:city":"Smethport",
    "sg:classifiers":[
        {
            "category":"Autos & Motor Vehicles",
            "subcategory":"Automobile Sales",
            "type":"Retail Goods"
        }
    ],
    "sg:phone":"+1 814 887 5835",
    "sg:postcode":"16749",
    "sg:province":"PA",
    "sg:tags":[
        "car",
        "dealer"
    ],
    "wof:name":"Lundgren Motor Sales",
    "wof:placetype":"venue"
},
  "geometry": {"coordinates":[-78.43605100000001,41.811467],"type":"Point"}
}