{
  "type": "Feature",
  "properties": {
    "addr:full":"19 Pebble Ridge Rd Warrington PA 18976",
    "addr:housenumber":"19",
    "addr:postcode":"18976",
    "addr:street":"Pebble Ridge Rd",
    "iso:country":"US",
    "sg:address":"19 Pebble Ridge Rd",
    "sg:city":"Warrington",
    "sg:classifiers":[
        {
            "category":"Building & Trades",
            "subcategory":"Landscaping Services",
            "type":"Services"
        }
    ],
    "sg:phone":"+1   ",
    "sg:postcode":"18976",
    "sg:province":"PA",
    "sg:tags":[
        "excavating",
        "paving",
        "contractor"
    ],
    "wof:name":"Tulio Landscaping Inc",
    "wof:placetype":"venue"
},
  "geometry": {"coordinates":[-75.143625,40.272113],"type":"Point"}
}