{
  "type": "Feature",
  "properties": {
    "iso:country":"US",
    "sg:address":"2223 5th Ave",
    "sg:city":"Pittsburgh",
    "sg:classifiers":[
        {
            "category":"Wholesale",
            "subcategory":"Medical Equipment & Supplies",
            "type":"Manufacturing & Wholesale Goods"
        },
        {
            "category":"Wholesale",
            "subcategory":"Machinery & Supplies",
            "type":"Manufacturing & Wholesale Goods"
        }
    ],
    "sg:phone":"+1 412 471 2527",
    "sg:postcode":"15219",
    "sg:province":"PA",
    "sg:tags":[
        "instrument",
        "scientific",
        "apparatus",
        "laboratory"
    ],
    "wof:name":"Burrell Scientific, Inc.",
    "wof:placetype":"venue"
},
  "geometry": {"coordinates":[-79.973578,40.437975],"type":"Point"}
}