{
  "type": "Feature",
  "properties": {
    "addr:full":"292 Mingo Rd Royersford PA 19468",
    "addr:housenumber":"292",
    "addr:postcode":"19468",
    "addr:street":"Mingo Rd",
    "iso:country":"US",
    "sg:address":"292 Mingo Rd",
    "sg:city":"Royersford",
    "sg:classifiers":[
        {
            "category":"Recreation",
            "type":"Entertainment"
        }
    ],
    "sg:phone":"+1   ",
    "sg:postcode":"19468",
    "sg:province":"PA",
    "sg:tags":[
        "arts",
        "for",
        "instruction",
        "martial",
        "child",
        "preschool"
    ],
    "wof:name":"Fermlr Inc",
    "wof:placetype":"venue"
},
  "geometry": {"coordinates":[-75.51525100000001,40.177774],"type":"Point"}
}