{
  "type": "Feature",
  "properties": {
    "addr:full":"1711 5th Ave Folsom PA 19033",
    "addr:housenumber":"1711",
    "addr:postcode":"19033",
    "addr:street":"5Th Ave",
    "iso:country":"US",
    "sg:address":"1711 5th Ave",
    "sg:city":"Folsom",
    "sg:classifiers":[
        {
            "category":"Manufacturing",
            "subcategory":"Metals",
            "type":"Manufacturing & Wholesale Goods"
        }
    ],
    "sg:phone":"+1   ",
    "sg:postcode":"19033",
    "sg:province":"PA",
    "sg:tags":[
        "tool",
        "mfg"
    ],
    "wof:name":"Snap-On Tools",
    "wof:placetype":"venue"
},
  "geometry": {"coordinates":[-75.31757899999999,39.898811],"type":"Point"}
}