{
  "type": "Feature",
  "properties": {
    "iso:country":"US",
    "sg:address":"610 Conshohocken State Rd",
    "sg:city":"Gladwyne",
    "sg:classifiers":[
        {
            "category":"Manufacturing",
            "subcategory":"Tools & Machinery",
            "type":"Manufacturing & Wholesale Goods"
        }
    ],
    "sg:phone":"+1 610 642 0310",
    "sg:postcode":"19035",
    "sg:province":"PA",
    "sg:tags":[
        "pumps-wholesale",
        "manufacturer"
    ],
    "wof:name":"The Stockdale Corporation",
    "wof:placetype":"venue"
},
  "geometry": {"coordinates":[-75.286461,40.046051],"type":"Point"}
}