{
  "type": "Feature",
  "properties": {
    "iso:country":"US",
    "sg:address":"500 Pine Hollow Rd",
    "sg:city":"Mc Kees Rocks",
    "sg:classifiers":[
        {
            "category":"Arena",
            "subcategory":"Sports Club",
            "type":"Entertainment"
        }
    ],
    "sg:phone":"+1 412 331 6260",
    "sg:postcode":"15136",
    "sg:province":"PA",
    "sg:tags":[
        "martial art"
    ],
    "wof:name":"Ata Taekwondo Karate For Kids Center",
    "wof:placetype":"venue"
},
  "geometry": {"coordinates":[-80.076853,40.470031],"type":"Point"}
}