{
  "type": "Feature",
  "properties": {
    "iso:country":"US",
    "sg:address":"232 California Dr",
    "sg:city":"Coal Center",
    "sg:classifiers":[
        {
            "category":"Retail",
            "subcategory":"Veterinary Services",
            "type":"Services"
        }
    ],
    "sg:phone":"+1 724 239 5137",
    "sg:postcode":"15423",
    "sg:province":"PA",
    "sg:tags":[
        "veterinarian"
    ],
    "wof:name":"Glenn C Hurley Jr DVM",
    "wof:placetype":"venue"
},
  "geometry": {"coordinates":[-79.97143199999999,40.104019],"type":"Point"}
}