{
  "type": "Feature",
  "properties": {
    "addr:full":"1733 Plum Creek Rd Roaring Spring PA 16673",
    "addr:housenumber":"1733",
    "addr:postcode":"16673",
    "addr:street":"Plum Creek Rd",
    "iso:country":"US",
    "sg:address":"1733 Plum Creek Rd",
    "sg:city":"Roaring Spring",
    "sg:classifiers":[
        {
            "category":"Farming",
            "subcategory":"Dairy Farm",
            "type":"Manufacturing & Wholesale Goods"
        }
    ],
    "sg:phone":"+1   ",
    "sg:postcode":"16673",
    "sg:province":"PA",
    "wof:name":"R Smith",
    "wof:placetype":"venue"
},
  "geometry": {"coordinates":[-78.39232199999999,40.360266],"type":"Point"}
}