{
  "type": "Feature",
  "properties": {
    "addr:full":"76 Lawrence Ave Southampton PA 18966",
    "addr:housenumber":"76",
    "addr:postcode":"18966",
    "addr:street":"Lawrence Ave",
    "iso:country":"US",
    "sg:address":"76 Lawrence Ave",
    "sg:city":"Southampton",
    "sg:classifiers":[
        {
            "category":"Retail",
            "subcategory":"Auto Repair",
            "type":"Services"
        }
    ],
    "sg:phone":"+1   ",
    "sg:postcode":"18966",
    "sg:province":"PA",
    "sg:tags":[
        "transmission"
    ],
    "wof:name":"Northeast Transmissions",
    "wof:placetype":"venue"
},
  "geometry": {"coordinates":[-74.963589,40.193567],"type":"Point"}
}