{
  "type": "Feature",
  "properties": {
    "iso:country":"US",
    "sg:address":"404 Brkich Way",
    "sg:city":"Beaver",
    "sg:classifiers":[
        {
            "category":"Recreation",
            "subcategory":"Marina",
            "type":"Entertainment"
        }
    ],
    "sg:phone":"+1 724 728 2880",
    "sg:postcode":"15009",
    "sg:province":"PA",
    "sg:tags":[
        "operation"
    ],
    "wof:name":"Bridgewater Landings Marina",
    "wof:placetype":"venue"
},
  "geometry": {"coordinates":[-80.292456,40.699883],"type":"Point"}
}