{
  "type": "Feature",
  "properties": {
    "iso:country":"US",
    "sg:address":"1401 S Ringgold St",
    "sg:city":"Philadelphia",
    "sg:classifiers":[
        {
            "category":"Restaurant",
            "type":"Food & Drink"
        }
    ],
    "sg:phone":"+1 215 551 7550",
    "sg:postcode":"19146",
    "sg:province":"PA",
    "wof:name":"1401 Ringold",
    "wof:placetype":"venue"
},
  "geometry": {"coordinates":[-75.18470000000001,39.935001],"type":"Point"}
}