{
  "type": "Feature",
  "properties": {
    "addr:full":"1001 S George St York PA 17403",
    "addr:housenumber":"1001",
    "addr:postcode":"17403",
    "addr:street":"S George St",
    "iso:country":"US",
    "sg:address":"1001 S George St",
    "sg:city":"York",
    "sg:classifiers":[
        {
            "category":"Building & Trades",
            "subcategory":"Construction",
            "type":"Services"
        }
    ],
    "sg:phone":"+1 717 854 1938",
    "sg:postcode":"17403",
    "sg:province":"PA",
    "sg:tags":[
        "company"
    ],
    "wof:name":"Turner Construction Co",
    "wof:placetype":"venue"
},
  "geometry": {"coordinates":[-76.720176,39.946027],"type":"Point"}
}