{
  "type": "Feature",
  "properties": {
    "addr:full":"12 Merwood Dr Upper Darby PA 19082",
    "addr:housenumber":"12",
    "addr:postcode":"19082",
    "addr:street":"Merwood Dr",
    "iso:country":"US",
    "sg:address":"12 Merwood Dr",
    "sg:city":"Upper Darby",
    "sg:classifiers":[
        {
            "category":"Professional",
            "type":"Services"
        }
    ],
    "sg:phone":"+1   ",
    "sg:postcode":"19082",
    "sg:province":"PA",
    "wof:name":"Ether C Sewell",
    "wof:placetype":"venue"
},
  "geometry": {"coordinates":[-75.265765,39.961965],"type":"Point"}
}