{
  "type": "Feature",
  "properties": {
    "addr:full":"105 W Walnut St Allentown PA 18102",
    "addr:housenumber":"105",
    "addr:postcode":"18102",
    "addr:street":"W Walnut St",
    "iso:country":"US",
    "sg:address":"105 W Walnut St",
    "sg:city":"Allentown",
    "sg:classifiers":[
        {
            "category":"Retail",
            "subcategory":"Auto Repair",
            "type":"Services"
        }
    ],
    "sg:phone":"+1 610 432 6830",
    "sg:postcode":"18102",
    "sg:province":"PA",
    "sg:tags":[
        "body",
        "shop"
    ],
    "sg:website":"www.true2form.com",
    "wof:name":"True 2Form Collision Repair Centers",
    "wof:placetype":"venue"
},
  "geometry": {"coordinates":[-75.4571,40.605499],"type":"Point"}
}