{
  "type": "Feature",
  "properties": {
    "iso:country":"US",
    "sg:address":"1452 Woodland Rd",
    "sg:city":"Clearfield",
    "sg:classifiers":[
        {
            "category":"Bars & Pubs",
            "type":"Food & Drink"
        },
        {
            "category":"Restaurant",
            "type":"Food & Drink"
        },
        {
            "category":"Professional",
            "type":"Services"
        }
    ],
    "sg:phone":"+1 814 765 7190",
    "sg:postcode":"16830",
    "sg:province":"PA",
    "sg:tags":[
        "tavern",
        "brew",
        "caterer"
    ],
    "sg:website":"http://dennysbeerbarrelpub.com/",
    "wof:name":"Denny's Beer Barrel Pub",
    "wof:placetype":"venue"
},
  "geometry": {"coordinates":[-78.420925,41.024818],"type":"Point"}
}