{
  "type": "Feature",
  "properties": {
    "iso:country":"US",
    "sg:address":"29 New Commerce Blvd",
    "sg:city":"Hanover Twp",
    "sg:classifiers":[
        {
            "category":"Social Services",
            "type":"Services"
        }
    ],
    "sg:phone":"+1 570 823 7164",
    "sg:postcode":"18706",
    "sg:province":"PA",
    "sg:tags":[
        "organization",
        "welfare"
    ],
    "sg:website":"www.nepagivelife.org",
    "wof:name":"American Red Cross",
    "wof:placetype":"venue"
},
  "geometry": {"coordinates":[-75.932271,41.212282],"type":"Point"}
}