{
  "type": "Feature",
  "properties": {
    "addr:full":"91 Shoemaker St Kingston PA 18704",
    "addr:housenumber":"91",
    "addr:postcode":"18704",
    "addr:street":"Shoemaker St",
    "iso:country":"US",
    "sg:address":"91 Shoemaker St",
    "sg:city":"Kingston",
    "sg:classifiers":[
        {
            "category":"Restaurant",
            "type":"Food & Drink"
        }
    ],
    "sg:phone":"+1   ",
    "sg:postcode":"18704",
    "sg:province":"PA",
    "sg:tags":[
        "eating"
    ],
    "wof:name":"Jamies Snack Bar",
    "wof:placetype":"venue"
},
  "geometry": {"coordinates":[-75.872855,41.287777],"type":"Point"}
}