{
  "type": "Feature",
  "properties": {
    "iso:country":"US",
    "sg:address":"425 Sandy Hill Rd",
    "sg:city":"Valencia",
    "sg:classifiers":[
        {
            "category":"Farming",
            "subcategory":"Farm",
            "type":"Manufacturing & Wholesale Goods"
        }
    ],
    "sg:phone":"+1 724 898 2679",
    "sg:postcode":"16059",
    "sg:province":"PA",
    "wof:name":"Love Farms",
    "wof:placetype":"venue"
},
  "geometry": {"coordinates":[-79.89779,40.702542],"type":"Point"}
}