{
  "type": "Feature",
  "properties": {
    "addr:full":"510 37th St Beaver Falls PA 15010",
    "addr:housenumber":"510",
    "addr:postcode":"15010",
    "addr:street":"37Th St",
    "iso:country":"US",
    "sg:address":"510 37th St",
    "sg:city":"Beaver Falls",
    "sg:classifiers":[
        {
            "category":"Education",
            "subcategory":"School",
            "type":"Public Place"
        }
    ],
    "sg:phone":"+1 724 843 3002",
    "sg:postcode":"15010",
    "sg:province":"PA",
    "wof:name":"Beaver County Christian School",
    "wof:placetype":"venue"
},
  "geometry": {"coordinates":[-80.326419,40.778159],"type":"Point"}
}