{
  "type": "Feature",
  "properties": {
    "iso:country":"US",
    "sg:address":"2707 Primrose Ln",
    "sg:city":"York",
    "sg:classifiers":[
        {
            "category":"Restaurant",
            "type":"Food & Drink"
        }
    ],
    "sg:phone":"+1   ",
    "sg:postcode":"17402",
    "sg:province":"PA",
    "sg:tags":[
        "eating"
    ],
    "wof:name":"West Tork Dairy Queen",
    "wof:placetype":"venue"
},
  "geometry": {"coordinates":[-76.66485,39.938191],"type":"Point"}
}