{
  "type": "Feature",
  "properties": {
    "addr:full":"8 Lackawanna Ave Dallas PA 18612",
    "addr:housenumber":"8",
    "addr:postcode":"18612",
    "addr:street":"Lackawanna Ave",
    "iso:country":"US",
    "sg:address":"8 Lackawanna Ave",
    "sg:city":"Dallas",
    "sg:classifiers":[
        {
            "category":"Organizations",
            "subcategory":"Religious Organization",
            "type":"Services"
        }
    ],
    "sg:phone":"+1 570 675 1987",
    "sg:postcode":"18612",
    "sg:province":"PA",
    "sg:tags":[
        "monastery",
        "convent"
    ],
    "wof:name":"Sisters Of Mercy",
    "wof:placetype":"venue"
},
  "geometry": {"coordinates":[-75.969775,41.337874],"type":"Point"}
}