{
  "type": "Feature",
  "properties": {
    "iso:country":"US",
    "sg:address":"1370 Beulah Rd",
    "sg:city":"Pittsburgh",
    "sg:classifiers":[
        {
            "category":"Professional",
            "subcategory":"Detective & Security Services",
            "type":"Services"
        }
    ],
    "sg:phone":"+1 412 473 6788",
    "sg:postcode":"15235",
    "sg:province":"PA",
    "sg:tags":[
        "telecasting",
        "television",
        "systems-closed",
        "circuit"
    ],
    "wof:name":"Tiex Media",
    "wof:placetype":"venue"
},
  "geometry": {"coordinates":[-79.84780600000001,40.444344],"type":"Point"}
}