{
  "type": "Feature",
  "properties": {
    "iso:country":"US",
    "sg:address":"3119 Spring Garden St",
    "sg:city":"Philadelphia",
    "sg:classifiers":[
        {
            "category":"Health Services",
            "subcategory":"Hospital",
            "type":"Services"
        }
    ],
    "sg:phone":"+1 215 243 0550",
    "sg:postcode":"19104",
    "sg:province":"PA",
    "sg:tags":[
        "mental"
    ],
    "wof:name":"A New Life Consumer Ctr",
    "wof:placetype":"venue"
},
  "geometry": {"coordinates":[-75.187861,39.963395],"type":"Point"}
}