{
  "type": "Feature",
  "properties": {
    "addr:full":"9401 McKnight Rd Pittsburgh PA 15237",
    "addr:housenumber":"9401",
    "addr:postcode":"15237",
    "addr:street":"Mcknight Rd",
    "iso:country":"US",
    "sg:address":"9401 McKnight Rd",
    "sg:city":"Pittsburgh",
    "sg:classifiers":[
        {
            "category":"Health Services",
            "subcategory":"Doctor",
            "type":"Services"
        }
    ],
    "sg:phone":"+1 412 318 0075",
    "sg:postcode":"15237",
    "sg:province":"PA",
    "sg:tags":[
        "physician",
        "surgeon"
    ],
    "wof:name":"Gastroenterology Associates",
    "wof:placetype":"venue"
},
  "geometry": {"coordinates":[-80.028835,40.580791],"type":"Point"}
}