{
  "type": "Feature",
  "properties": {
    "iso:country":"US",
    "sg:address":"6 Export Ln",
    "sg:city":"Archbald",
    "sg:classifiers":[
        {
            "category":"Government",
            "subcategory":"Office",
            "type":"Public Place"
        }
    ],
    "sg:phone":"+1 570 876 4551",
    "sg:postcode":"18403",
    "sg:province":"PA",
    "sg:tags":[
        "village"
    ],
    "wof:name":"Archbald Boro DPW",
    "wof:placetype":"venue"
},
  "geometry": {"coordinates":[-75.547929,41.490364],"type":"Point"}
}