{
  "type": "Feature",
  "properties": {
    "iso:country":"US",
    "sg:address":"2583 Mummasburg Rd",
    "sg:city":"Gettysburg",
    "sg:classifiers":[
        {
            "category":"Shopping",
            "subcategory":"Gifts & Souvenirs",
            "type":"Retail Goods"
        }
    ],
    "sg:phone":"+1 717 677 7887",
    "sg:postcode":"17325",
    "sg:province":"PA",
    "sg:tags":[
        "shop"
    ],
    "wof:name":"An Early Elegance",
    "wof:placetype":"venue"
},
  "geometry": {"coordinates":[-77.290243,39.885885],"type":"Point"}
}