{
  "type": "Feature",
  "properties": {
    "iso:country":"US",
    "sg:address":"1750 Derstine Rd",
    "sg:city":"Souderton",
    "sg:classifiers":[
        {
            "category":"Home & Garden",
            "subcategory":"Home Furnishings",
            "type":"Retail Goods"
        }
    ],
    "sg:phone":"+1   ",
    "sg:postcode":"18964",
    "sg:province":"PA",
    "wof:name":"Crystals Custom Draperies",
    "wof:placetype":"venue"
},
  "geometry": {"coordinates":[-75.31441599999999,40.284624],"type":"Point"}
}