{
  "type": "Feature",
  "properties": {
    "iso:country":"US",
    "sg:address":"142 Gypsy Ln",
    "sg:city":"King Of Prussia",
    "sg:classifiers":[
        {
            "category":"Wholesale",
            "subcategory":"Durable Goods & Equipment",
            "type":"Manufacturing & Wholesale Goods"
        }
    ],
    "sg:phone":"+1 610 668 9191",
    "sg:postcode":"19406",
    "sg:province":"PA",
    "sg:tags":[
        "fire",
        "extinguisher"
    ],
    "wof:name":"Uni-Pro Inc",
    "wof:placetype":"venue"
},
  "geometry": {"coordinates":[-75.34941000000001,40.070271],"type":"Point"}
}