{
  "type": "Feature",
  "properties": {
    "iso:country":"US",
    "sg:address":"553 Main St",
    "sg:city":"Honesdale",
    "sg:classifiers":[
        {
            "category":"Shopping",
            "type":"Retail Goods"
        }
    ],
    "sg:phone":"+1   ",
    "sg:postcode":"18431",
    "sg:province":"PA",
    "sg:tags":[
        "merchandise"
    ],
    "wof:name":"Audible Hearing Care Center",
    "wof:placetype":"venue"
},
  "geometry": {"coordinates":[-75.254381,41.569936],"type":"Point"}
}