{
  "type": "Feature",
  "properties": {
    "iso:country":"US",
    "sg:address":"3380 Spring Garden Ave",
    "sg:city":"Pittsburgh",
    "sg:classifiers":[
        {
            "category":"Building & Trades",
            "subcategory":"Construction",
            "type":"Services"
        }
    ],
    "sg:phone":"+1   ",
    "sg:postcode":"15212",
    "sg:province":"PA",
    "sg:tags":[
        "contractor"
    ],
    "wof:name":"Jay P Grundler Drywall",
    "wof:placetype":"venue"
},
  "geometry": {"coordinates":[-79.99378900000001,40.477287],"type":"Point"}
}