{
  "type": "Feature",
  "properties": {
    "addr:full":"807 W Main St Mount Pleasant PA 15666",
    "addr:housenumber":"807",
    "addr:postcode":"15666",
    "addr:street":"W Main St",
    "iso:country":"US",
    "sg:address":"807 W Main St",
    "sg:city":"Mount Pleasant",
    "sg:classifiers":[
        {
            "category":"Professional",
            "subcategory":"Accounting & Tax Preparation",
            "type":"Services"
        }
    ],
    "sg:phone":"+1   ",
    "sg:postcode":"15666",
    "sg:province":"PA",
    "wof:name":"H&R Block",
    "wof:placetype":"venue"
},
  "geometry": {"coordinates":[-79.547641,40.151554],"type":"Point"}
}