{
  "type": "Feature",
  "properties": {
    "iso:country":"US",
    "sg:address":"20 Maple Ter",
    "sg:city":"Clifton Heights",
    "sg:classifiers":[
        {
            "category":"Building & Trades",
            "subcategory":"Construction",
            "type":"Services"
        }
    ],
    "sg:phone":"+1   ",
    "sg:postcode":"19018",
    "sg:province":"PA",
    "sg:tags":[
        "house"
    ],
    "wof:name":"Olinchak Cabinet Maker",
    "wof:placetype":"venue"
},
  "geometry": {"coordinates":[-75.29586399999999,39.931426],"type":"Point"}
}