{
  "type": "Feature",
  "properties": {
    "iso:country":"US",
    "sg:address":"2533 E Market St",
    "sg:city":"York",
    "sg:classifiers":[
        {
            "category":"Personal",
            "subcategory":"Beauty Salon",
            "type":"Services"
        }
    ],
    "sg:phone":"+1 717 840 4871",
    "sg:postcode":"17402",
    "sg:province":"PA",
    "wof:name":"Holiday Hair",
    "wof:placetype":"venue"
},
  "geometry": {"coordinates":[-76.675799,39.974914],"type":"Point"}
}