{
  "type": "Feature",
  "properties": {
    "iso:country":"US",
    "sg:address":"460 Lapp Rd",
    "sg:city":"Malvern",
    "sg:classifiers":[
        {
            "category":"Wholesale",
            "subcategory":"Auto Parts",
            "type":"Manufacturing & Wholesale Goods"
        }
    ],
    "sg:phone":"+1 610 644 7300",
    "sg:postcode":"19355",
    "sg:province":"PA",
    "sg:tags":[
        "body",
        "automobile",
        "shop"
    ],
    "wof:name":"Akzo Nobel Coatings Inc",
    "wof:placetype":"venue"
},
  "geometry": {"coordinates":[-75.540994,40.058291],"type":"Point"}
}