{
  "type": "Feature",
  "properties": {
    "addr:full":"125 Stokes Ave Stroudsburg PA 18360",
    "addr:housenumber":"125",
    "addr:postcode":"18360",
    "addr:street":"Stokes Ave",
    "iso:country":"US",
    "sg:address":"125 Stokes Ave",
    "sg:city":"Stroudsburg",
    "sg:classifiers":[
        {
            "category":"Professional",
            "subcategory":"Lawyer & Legal Services",
            "type":"Services"
        }
    ],
    "sg:phone":"+1 570 424 9212",
    "sg:postcode":"18360",
    "sg:province":"PA",
    "sg:tags":[
        "attorney",
        "practice"
    ],
    "wof:name":"Tri County Law Offices Ltd",
    "wof:placetype":"venue"
},
  "geometry": {"coordinates":[-75.18695700000001,40.984092],"type":"Point"}
}