{
  "type": "Feature",
  "properties": {
    "addr:full":"2550 Welsh Rd Philadelphia PA 19152",
    "addr:housenumber":"2550",
    "addr:postcode":"19152",
    "addr:street":"Welsh Rd",
    "iso:country":"US",
    "sg:address":"2550 Welsh Rd",
    "sg:city":"Philadelphia",
    "sg:classifiers":[
        {
            "category":"Restaurant",
            "type":"Food & Drink"
        }
    ],
    "sg:menulink":"http://www.allmenus.com/pa/philadelphia/170763-burger-king/menu/",
    "sg:phone":"+1 215 969 0310",
    "sg:postcode":"19152",
    "sg:province":"PA",
    "sg:tags":[
        "burger",
        "american"
    ],
    "wof:name":"Burger King",
    "wof:placetype":"venue"
},
  "geometry": {"coordinates":[-75.03033000000001,40.069008],"type":"Point"}
}