{
  "type": "Feature",
  "properties": {
    "addr:full":"802 Christian St Philadelphia PA 19147",
    "addr:housenumber":"802",
    "addr:postcode":"19147",
    "addr:street":"Christian St",
    "iso:country":"US",
    "sg:address":"802 Christian St",
    "sg:city":"Philadelphia",
    "sg:classifiers":[
        {
            "category":"Restaurant",
            "type":"Food & Drink"
        },
        {
            "category":"Deli",
            "type":"Food & Drink"
        },
        {
            "category":"Food & Beverages",
            "subcategory":"Bakery",
            "type":"Retail Goods"
        }
    ],
    "sg:phone":"+1 215 925 6544",
    "sg:postcode":"19147",
    "sg:province":"PA",
    "sg:tags":[
        "sandwich",
        "vietnamese"
    ],
    "wof:name":"Nhu Y",
    "wof:placetype":"venue"
},
  "geometry": {"coordinates":[-75.156403,39.938702],"type":"Point"}
}