{
  "type": "Feature",
  "properties": {
    "iso:country":"US",
    "sg:address":"1302 Middle Rd",
    "sg:city":"Glenshaw",
    "sg:classifiers":[
        {
            "category":"Building & Trades",
            "subcategory":"Plumbing",
            "type":"Services"
        }
    ],
    "sg:phone":"+1   ",
    "sg:postcode":"15116",
    "sg:province":"PA",
    "sg:tags":[
        "contractor"
    ],
    "wof:name":"Romeas Heating & AC",
    "wof:placetype":"venue"
},
  "geometry": {"coordinates":[-79.942742,40.524325],"type":"Point"}
}