{
  "type": "Feature",
  "properties": {
    "iso:country":"US",
    "sg:address":"2417 E Carson St",
    "sg:city":"Pittsburgh",
    "sg:classifiers":[
        {
            "category":"Professional",
            "type":"Services"
        }
    ],
    "sg:phone":"+1 412 390 0431",
    "sg:postcode":"15203",
    "sg:province":"PA",
    "sg:tags":[
        "establishment"
    ],
    "wof:name":"Thomas Boyle Esquire",
    "wof:placetype":"venue"
},
  "geometry": {"coordinates":[-79.969949,40.427971],"type":"Point"}
}