{
  "type": "Feature",
  "properties": {
    "iso:country":"US",
    "sg:address":"14 Cynthia Rd",
    "sg:city":"Coatesville",
    "sg:classifiers":[
        {
            "category":"Professional",
            "type":"Services"
        }
    ],
    "sg:phone":"+1 610 380 1178",
    "sg:postcode":"19320",
    "sg:province":"PA",
    "sg:tags":[
        "establishment"
    ],
    "wof:name":"Rohjea's",
    "wof:placetype":"venue"
},
  "geometry": {"coordinates":[-75.87702299999999,39.962424],"type":"Point"}
}