{
  "type": "Feature",
  "properties": {
    "iso:country":"US",
    "sg:address":"11824 Pen Mar Rd",
    "sg:city":"Waynesboro",
    "sg:classifiers":[
        {
            "category":"Professional",
            "subcategory":"Lawyer & Legal Services",
            "type":"Services"
        }
    ],
    "sg:phone":"+1 717 762 5785",
    "sg:postcode":"17268",
    "sg:province":"PA",
    "sg:tags":[
        "notary"
    ],
    "wof:name":"Fertenbaugh Clyde J",
    "wof:placetype":"venue"
},
  "geometry": {"coordinates":[-77.525398,39.7351],"type":"Point"}
}