{
  "type": "Feature",
  "properties": {
    "iso:country":"US",
    "sg:address":"2009 Lantern Ln",
    "sg:city":"Oreland",
    "sg:classifiers":[
        {
            "category":"Professional",
            "subcategory":"Management & Consulting",
            "type":"Services"
        }
    ],
    "sg:phone":"+1   ",
    "sg:postcode":"19075",
    "sg:province":"PA",
    "wof:name":"Umt Management Co Inc",
    "wof:placetype":"venue"
},
  "geometry": {"coordinates":[-75.187538,40.104261],"type":"Point"}
}