{
  "type": "Feature",
  "properties": {
    "addr:full":"1321 E Ridge Pike Plymouth Meeting PA 19462",
    "addr:housenumber":"1321",
    "addr:postcode":"19462",
    "addr:street":"E Ridge Pike",
    "iso:country":"US",
    "sg:address":"1321 E Ridge Pike",
    "sg:city":"Plymouth Meeting",
    "sg:classifiers":[
        {
            "category":"Autos & Motor Vehicles",
            "subcategory":"Automobile Sales",
            "type":"Retail Goods"
        }
    ],
    "sg:phone":"+1 610 275 3535",
    "sg:postcode":"19462",
    "sg:province":"PA",
    "sg:tags":[
        "car",
        "dealer"
    ],
    "wof:name":"Louis Auto Sales Inc",
    "wof:placetype":"venue"
},
  "geometry": {"coordinates":[-75.31998,40.107968],"type":"Point"}
}