{
  "type": "Feature",
  "properties": {
    "addr:full":"603 Clayton Ave Waynesboro PA 17268",
    "addr:housenumber":"603",
    "addr:postcode":"17268",
    "addr:street":"Clayton Ave",
    "iso:country":"US",
    "sg:address":"603 Clayton Ave",
    "sg:city":"Waynesboro",
    "sg:classifiers":[
        {
            "category":"Professional",
            "subcategory":"Engineering",
            "type":"Services"
        }
    ],
    "sg:phone":"+1   ",
    "sg:postcode":"17268",
    "sg:province":"PA",
    "sg:tags":[
        "surveying"
    ],
    "wof:name":"Garver Larry Surveyor",
    "wof:placetype":"venue"
},
  "geometry": {"coordinates":[-77.57939399999999,39.745677],"type":"Point"}
}