{
  "type": "Feature",
  "properties": {
    "iso:country":"US",
    "sg:address":"415 Unity Center Rd",
    "sg:city":"Plum",
    "sg:classifiers":[
        {
            "category":"Building & Trades",
            "subcategory":"Construction",
            "type":"Services"
        }
    ],
    "sg:phone":"+1 412 793 4385",
    "sg:postcode":"15239",
    "sg:province":"PA",
    "sg:tags":[
        "product",
        "asphalt"
    ],
    "wof:name":"TPC Asphalt Paving Prods",
    "wof:placetype":"venue"
},
  "geometry": {"coordinates":[-79.77801700000001,40.48937],"type":"Point"}
}