{
  "type": "Feature",
  "properties": {
    "iso:country":"US",
    "sg:address":"4921 Pentridge St",
    "sg:city":"Philadelphia",
    "sg:classifiers":[
        {
            "category":"Home & Garden",
            "subcategory":"Home Furnishings",
            "type":"Retail Goods"
        },
        {
            "category":"Building & Trades",
            "subcategory":"Construction",
            "type":"Services"
        },
        {
            "category":"Manufacturing",
            "subcategory":"Building Materials",
            "type":"Manufacturing & Wholesale Goods"
        }
    ],
    "sg:phone":"+1 215 726 6641",
    "sg:postcode":"19143",
    "sg:province":"PA",
    "sg:tags":[
        "industrial",
        "cabinetmakers-commercial",
        "carpenter",
        "cabinet",
        "refacing",
        "resurfacing",
        "maker",
        "cabinets-refinishing",
        "kitchen"
    ],
    "wof:name":"Tannen Carpentry",
    "wof:placetype":"venue"
},
  "geometry": {"coordinates":[-75.22113899999999,39.947662],"type":"Point"}
}