{
  "type": "Feature",
  "properties": {
    "iso:country":"US",
    "sg:address":"6298 River Dr",
    "sg:city":"York",
    "sg:classifiers":[
        {
            "category":"Building & Trades",
            "subcategory":"Construction",
            "type":"Services"
        }
    ],
    "sg:phone":"+1   ",
    "sg:postcode":"17406",
    "sg:province":"PA",
    "sg:tags":[
        "carpentry",
        "contractor"
    ],
    "wof:name":"Paul A Nevin Fine Carpen",
    "wof:placetype":"venue"
},
  "geometry": {"coordinates":[-76.586077,40.048532],"type":"Point"}
}