{
  "type": "Feature",
  "properties": {
    "iso:country":"US",
    "sg:address":"25 E Spring St",
    "sg:city":"Frackville",
    "sg:classifiers":[
        {
            "category":"Social Services",
            "subcategory":"Child Care",
            "type":"Services"
        }
    ],
    "sg:phone":"+1 570 874 1222",
    "sg:postcode":"17931",
    "sg:province":"PA",
    "sg:tags":[
        "center",
        "learning"
    ],
    "wof:name":"Frackville Learning Center",
    "wof:placetype":"venue"
},
  "geometry": {"coordinates":[-76.231176,40.786858],"type":"Point"}
}