{
  "type": "Feature",
  "properties": {
    "iso:country":"US",
    "sg:address":"911 Gibson Blvd",
    "sg:city":"Harrisburg",
    "sg:classifiers":[
        {
            "category":"Professional",
            "subcategory":"Management & Consulting",
            "type":"Services"
        }
    ],
    "sg:phone":"+1   ",
    "sg:postcode":"17113",
    "sg:province":"PA",
    "sg:tags":[
        "correctional",
        "managed",
        "institution",
        "for",
        "care"
    ],
    "wof:name":"Pihs",
    "wof:placetype":"venue"
},
  "geometry": {"coordinates":[-76.84669,40.245229],"type":"Point"}
}