{
  "type": "Feature",
  "properties": {
    "iso:country":"US",
    "sg:address":"374 Poplar Rd",
    "sg:city":"Honey Brook",
    "sg:classifiers":[
        {
            "category":"Freight",
            "type":"Transportation"
        }
    ],
    "sg:phone":"+1   ",
    "sg:postcode":"19344",
    "sg:province":"PA",
    "sg:tags":[
        "operator",
        "local",
        "trucking"
    ],
    "wof:name":"CM Trucking",
    "wof:placetype":"venue"
},
  "geometry": {"coordinates":[-75.918961,40.107326],"type":"Point"}
}