{
  "type": "Feature",
  "properties": {
    "iso:country":"US",
    "sg:address":"400 Summit Ave",
    "sg:city":"Reading",
    "sg:classifiers":[
        {
            "category":"Education",
            "subcategory":"School",
            "type":"Public Place"
        }
    ],
    "sg:phone":"+1 610 371 5853",
    "sg:postcode":"19611",
    "sg:province":"PA",
    "wof:name":"Millmont Elementary School",
    "wof:placetype":"venue"
},
  "geometry": {"coordinates":[-75.93115400000001,40.318149],"type":"Point"}
}