{
  "type": "Feature",
  "properties": {
    "iso:country":"US",
    "sg:address":"2530 Lebanon Rd",
    "sg:city":"Manheim",
    "sg:classifiers":[
        {
            "category":"Retail",
            "subcategory":"Auto Repair",
            "type":"Services"
        }
    ],
    "sg:phone":"+1 717 664 3992",
    "sg:postcode":"17545",
    "sg:province":"PA",
    "sg:tags":[
        "repairing",
        "automobile"
    ],
    "wof:name":"Mt Hope Svc Ctr",
    "wof:placetype":"venue"
},
  "geometry": {"coordinates":[-76.43228499999999,40.222269],"type":"Point"}
}