{
  "type": "Feature",
  "properties": {
    "addr:full":"374 Morris Rd Harleysville PA 19438",
    "addr:housenumber":"374",
    "addr:postcode":"19438",
    "addr:street":"Morris Rd",
    "iso:country":"US",
    "sg:address":"374 Morris Rd",
    "sg:city":"Harleysville",
    "sg:classifiers":[
        {
            "category":"Real Estate",
            "subcategory":"Architect",
            "type":"Services"
        }
    ],
    "sg:phone":"+1 215 513 0527",
    "sg:postcode":"19438",
    "sg:province":"PA",
    "wof:name":"Ritter Glenn Architect",
    "wof:placetype":"venue"
},
  "geometry": {"coordinates":[-75.39510300000001,40.255901],"type":"Point"}
}