{
  "type": "Feature",
  "properties": {
    "iso:country":"US",
    "sg:address":"277 Upper Gulph Rd",
    "sg:city":"Wayne",
    "sg:classifiers":[
        {
            "category":"Health Services",
            "subcategory":"Doctor",
            "type":"Services"
        }
    ],
    "sg:phone":"+1   ",
    "sg:postcode":"19087",
    "sg:province":"PA",
    "sg:tags":[
        "medical"
    ],
    "wof:name":"Ellen N Herman MD",
    "wof:placetype":"venue"
},
  "geometry": {"coordinates":[-75.412758,40.053028],"type":"Point"}
}