{
  "type": "Feature",
  "properties": {
    "iso:country":"US",
    "sg:address":"1990 Wabank Rd",
    "sg:city":"Lancaster",
    "sg:classifiers":[
        {
            "category":"Education",
            "subcategory":"School",
            "type":"Public Place"
        }
    ],
    "sg:phone":"+1   ",
    "sg:postcode":"17603",
    "sg:province":"PA",
    "wof:name":"Elizabeth Mrtin Elmentary Schl",
    "wof:placetype":"venue"
},
  "geometry": {"coordinates":[-76.336139,40.012133],"type":"Point"}
}