{
  "type": "Feature",
  "properties": {
    "addr:full":"700 Packer Ave Philadelphia PA 19148",
    "addr:housenumber":"700",
    "addr:postcode":"19148",
    "addr:street":"Packer Ave",
    "iso:country":"US",
    "sg:address":"700 Packer Ave",
    "sg:city":"Philadelphia",
    "sg:classifiers":[
        {
            "category":"Government",
            "subcategory":"Office",
            "type":"Public Place"
        }
    ],
    "sg:phone":"+1 215 952 1123",
    "sg:postcode":"19148",
    "sg:province":"PA",
    "sg:tags":[
        "state",
        "taxation"
    ],
    "sg:website":"www.palottery.com",
    "wof:name":"Pennsylvania Lottery",
    "wof:placetype":"venue"
},
  "geometry": {"coordinates":[-75.163398,39.910087],"type":"Point"}
}