{
  "type": "Feature",
  "properties": {
    "iso:country":"US",
    "sg:address":"1527 Federal St",
    "sg:city":"Pittsburgh",
    "sg:classifiers":[
        {
            "category":"Professional",
            "subcategory":"Accounting & Tax Preparation",
            "type":"Services"
        },
        {
            "category":"Professional",
            "subcategory":"Lawyer & Legal Services",
            "type":"Services"
        }
    ],
    "sg:phone":"+1 412 231 4646",
    "sg:postcode":"15212",
    "sg:province":"PA",
    "sg:tags":[
        "notary",
        "accountant"
    ],
    "wof:name":"Payne Rose Marie Notary",
    "wof:placetype":"venue"
},
  "geometry": {"coordinates":[-80.007776,40.458824],"type":"Point"}
}