{
  "type": "Feature",
  "properties": {
    "addr:full":"402 N Mill Rd Kennett Square PA 19348",
    "addr:housenumber":"402",
    "addr:postcode":"19348",
    "addr:street":"N Mill Rd",
    "iso:country":"US",
    "sg:address":"402 N Mill Rd",
    "sg:city":"Kennett Square",
    "sg:classifiers":[
        {
            "category":"Building & Trades",
            "subcategory":"Plumbing",
            "type":"Services"
        }
    ],
    "sg:phone":"+1 610 347 0101",
    "sg:postcode":"19348",
    "sg:province":"PA",
    "wof:name":"Morano Plumbing & Heating",
    "wof:placetype":"venue"
},
  "geometry": {"coordinates":[-75.723602,39.850601],"type":"Point"}
}