{
  "type": "Feature",
  "properties": {
    "addr:full":"263 Pinewood Dr Levittown PA 19054",
    "addr:housenumber":"263",
    "addr:postcode":"19054",
    "addr:street":"Pinewood Dr",
    "iso:country":"US",
    "sg:address":"263 Pinewood Dr",
    "sg:city":"Levittown",
    "sg:classifiers":[
        {
            "category":"Professional",
            "type":"Services"
        }
    ],
    "sg:phone":"+1   ",
    "sg:postcode":"19054",
    "sg:province":"PA",
    "wof:name":"Joseph S Monti",
    "wof:placetype":"venue"
},
  "geometry": {"coordinates":[-74.820104,40.158566],"type":"Point"}
}