{
  "type": "Feature",
  "properties": {
    "iso:country":"US",
    "sg:address":"1894 Saint Peters Rd",
    "sg:city":"Pottstown",
    "sg:classifiers":[
        {
            "category":"Travel",
            "subcategory":"Campground",
            "type":"Entertainment"
        }
    ],
    "sg:phone":"+1 610 970 5480",
    "sg:postcode":"19465",
    "sg:province":"PA",
    "sg:tags":[
        "camp"
    ],
    "wof:name":"Camp Nueva Esperanza",
    "wof:placetype":"venue"
},
  "geometry": {"coordinates":[-75.706219,40.216065],"type":"Point"}
}