{
  "type": "Feature",
  "properties": {
    "iso:country":"US",
    "sg:address":"714 Latonka Dr",
    "sg:city":"Mercer",
    "sg:classifiers":[
        {
            "category":"Professional",
            "type":"Services"
        }
    ],
    "sg:phone":"+1   ",
    "sg:postcode":"16137",
    "sg:province":"PA",
    "wof:name":"J D RE",
    "wof:placetype":"venue"
},
  "geometry": {"coordinates":[-80.18561200000001,41.288878],"type":"Point"}
}