{
  "type": "Feature",
  "properties": {
    "addr:full":"1700 Walnut St Ste 725 Philadelphia PA 19103",
    "addr:housenumber":"1700",
    "addr:postcode":"19103",
    "addr:street":"Walnut St Ste 725",
    "iso:country":"US",
    "sg:address":"1700 Walnut St Ste 725",
    "sg:city":"Philadelphia",
    "sg:classifiers":[
        {
            "category":"Health Services",
            "subcategory":"Doctor",
            "type":"Services"
        },
        {
            "category":"Health Services",
            "subcategory":"Clinic",
            "type":"Services"
        }
    ],
    "sg:phone":"+1 215 735 1243",
    "sg:postcode":"19103",
    "sg:province":"PA",
    "sg:tags":[
        "psychological",
        "psychologist"
    ],
    "wof:name":"Joanne Buzzetta",
    "wof:placetype":"venue"
},
  "geometry": {"coordinates":[-75.169083,39.949951],"type":"Point"}
}