{
  "type": "Feature",
  "properties": {
    "iso:country":"US",
    "sg:address":"1300 Lincoln Hwy",
    "sg:city":"North Versailles",
    "sg:classifiers":[
        {
            "category":"Manufacturing",
            "subcategory":"Printing",
            "type":"Manufacturing & Wholesale Goods"
        }
    ],
    "sg:phone":"+1   ",
    "sg:postcode":"15137",
    "sg:province":"PA",
    "sg:tags":[
        "lithographic",
        "commercial"
    ],
    "wof:name":"OToole Printing Inc",
    "wof:placetype":"venue"
},
  "geometry": {"coordinates":[-79.79912899999999,40.376478],"type":"Point"}
}