{
  "type": "Feature",
  "properties": {
    "iso:country":"US",
    "sg:address":"665 Harleysville Pike",
    "sg:city":"Telford",
    "sg:classifiers":[
        {
            "category":"Professional",
            "subcategory":"Management & Consulting",
            "type":"Services"
        }
    ],
    "sg:phone":"+1 215 723 1100",
    "sg:postcode":"18969",
    "sg:province":"PA",
    "sg:tags":[
        "consultant",
        "business"
    ],
    "wof:name":"Gem-Life Quality",
    "wof:placetype":"venue"
},
  "geometry": {"coordinates":[-75.366462,40.30342],"type":"Point"}
}