{
  "type": "Feature",
  "properties": {
    "addr:full":"423 Railroad St Bridgeville PA 15017",
    "addr:housenumber":"423",
    "addr:postcode":"15017",
    "addr:street":"Railroad St",
    "iso:country":"US",
    "sg:address":"423 Railroad St",
    "sg:city":"Bridgeville",
    "sg:classifiers":[
        {
            "category":"Restaurant",
            "type":"Food & Drink"
        }
    ],
    "sg:phone":"+1   ",
    "sg:postcode":"15017",
    "sg:province":"PA",
    "sg:tags":[
        "eating"
    ],
    "wof:name":"Station Sandwich Shop",
    "wof:placetype":"venue"
},
  "geometry": {"coordinates":[-80.11060999999999,40.357947],"type":"Point"}
}