{
  "type": "Feature",
  "properties": {
    "iso:country":"US",
    "sg:address":"41 Lynbrook Dr S",
    "sg:city":"York",
    "sg:classifiers":[
        {
            "category":"Wholesale",
            "subcategory":"Construction Materials",
            "type":"Manufacturing & Wholesale Goods"
        }
    ],
    "sg:phone":"+1 717 755 8872",
    "sg:postcode":"17402",
    "sg:province":"PA",
    "sg:tags":[
        "lumber"
    ],
    "wof:name":"W K Campbell Wholesale Lumber",
    "wof:placetype":"venue"
},
  "geometry": {"coordinates":[-76.63827999999999,39.980125],"type":"Point"}
}