{
  "type": "Feature",
  "properties": {
    "iso:country":"US",
    "sg:address":"108 Rte 837",
    "sg:city":"Monongahela",
    "sg:classifiers":[
        {
            "category":"Shopping",
            "type":"Retail Goods"
        }
    ],
    "sg:phone":"+1 724 258 8540",
    "sg:postcode":"15063",
    "sg:province":"PA",
    "sg:tags":[
        "monument"
    ],
    "wof:name":"Kurtz Monument Co",
    "wof:placetype":"venue"
},
  "geometry": {"coordinates":[-79.914817,40.171854],"type":"Point"}
}