{
  "type": "Feature",
  "properties": {
    "iso:country":"US",
    "sg:address":"239 N 5th St",
    "sg:city":"Hamburg",
    "sg:classifiers":[
        {
            "category":"Personal",
            "subcategory":"Beauty Salon",
            "type":"Services"
        }
    ],
    "sg:phone":"+1 610 562 3543",
    "sg:postcode":"19526",
    "sg:province":"PA",
    "wof:name":"Personality Discoveries International, Inc. T/A Pdi, Inc.",
    "wof:placetype":"venue"
},
  "geometry": {"coordinates":[-75.981589,40.559795],"type":"Point"}
}