{
  "type": "Feature",
  "properties": {
    "iso:country":"US",
    "sg:address":"2166 Rankintown Rd",
    "sg:city":"Finleyville",
    "sg:classifiers":[
        {
            "category":"Building & Trades",
            "subcategory":"Construction",
            "type":"Services"
        }
    ],
    "sg:phone":"+1   ",
    "sg:postcode":"15332",
    "sg:province":"PA",
    "sg:tags":[
        "floor"
    ],
    "wof:name":"T & K Floor Service",
    "wof:placetype":"venue"
},
  "geometry": {"coordinates":[-80.01056800000001,40.250503],"type":"Point"}
}