{
  "type": "Feature",
  "properties": {
    "iso:country":"US",
    "sg:address":"812 Chestnut St Apt 2",
    "sg:city":"Philadelphia",
    "sg:classifiers":[
        {
            "category":"Real Estate",
            "subcategory":"Architect",
            "type":"Services"
        }
    ],
    "sg:phone":"+1 215 351 0560",
    "sg:postcode":"19107",
    "sg:province":"PA",
    "wof:name":"Lawson John Architect",
    "wof:placetype":"venue"
},
  "geometry": {"coordinates":[-75.154099,39.949699],"type":"Point"}
}