{
  "type": "Feature",
  "properties": {
    "iso:country":"US",
    "sg:address":"1240 W Ritner St",
    "sg:city":"Philadelphia",
    "sg:classifiers":[
        {
            "category":"Health Services",
            "subcategory":"Doctor",
            "type":"Services"
        }
    ],
    "sg:phone":"+1 215 755 4855",
    "sg:postcode":"19148",
    "sg:province":"PA",
    "wof:name":"Villare Anthony W MD",
    "wof:placetype":"venue"
},
  "geometry": {"coordinates":[-75.168297,39.920502],"type":"Point"}
}