{
  "type": "Feature",
  "properties": {
    "iso:country":"US",
    "sg:address":"666 E Township Line Rd",
    "sg:city":"Havertown",
    "sg:classifiers":[
        {
            "category":"Professional",
            "subcategory":"Research",
            "type":"Services"
        }
    ],
    "sg:phone":"+1 610 446 6473",
    "sg:postcode":"19083",
    "sg:province":"PA",
    "sg:tags":[
        "market",
        "analysis"
    ],
    "wof:name":"LHK Partners Inc",
    "wof:placetype":"venue"
},
  "geometry": {"coordinates":[-75.285546,39.972593],"type":"Point"}
}