{
  "type": "Feature",
  "properties": {
    "iso:country":"US",
    "sg:address":"2315 Wylie Ave",
    "sg:city":"Pittsburgh",
    "sg:classifiers":[
        {
            "category":"Organizations",
            "subcategory":"Community Association",
            "type":"Services"
        }
    ],
    "sg:phone":"+1   ",
    "sg:postcode":"15219",
    "sg:province":"PA",
    "wof:name":"Improved Benevolent & Pro",
    "wof:placetype":"venue"
},
  "geometry": {"coordinates":[-79.974034,40.447174],"type":"Point"}
}