{
  "type": "Feature",
  "properties": {
    "iso:country":"US",
    "sg:address":"302 Kathmere Rd",
    "sg:city":"Havertown",
    "sg:classifiers":[
        {
            "category":"Building & Trades",
            "subcategory":"Landscaping Services",
            "type":"Services"
        }
    ],
    "sg:phone":"+1 610 789 5334",
    "sg:postcode":"19083",
    "sg:province":"PA",
    "sg:tags":[
        "tree",
        "landscape",
        "contractor"
    ],
    "wof:name":"Lazar Brian",
    "wof:placetype":"venue"
},
  "geometry": {"coordinates":[-75.298207,39.982417],"type":"Point"}
}