{
  "type": "Feature",
  "properties": {
    "iso:country":"US",
    "sg:address":"620 S Reading Ave",
    "sg:city":"Boyertown",
    "sg:classifiers":[
        {
            "category":"Building & Trades",
            "subcategory":"Construction",
            "type":"Services"
        }
    ],
    "sg:phone":"+1 610 473 3333",
    "sg:postcode":"19512",
    "sg:province":"PA",
    "sg:tags":[
        "home",
        "improvement"
    ],
    "wof:name":"Umbrella Home Maintenance Svc",
    "wof:placetype":"venue"
},
  "geometry": {"coordinates":[-75.64946399999999,40.32589],"type":"Point"}
}