{
  "type": "Feature",
  "properties": {
    "addr:full":"3645 W 12th St Erie PA 16505",
    "addr:housenumber":"3645",
    "addr:postcode":"16505",
    "addr:street":"W 12Th St",
    "iso:country":"US",
    "sg:address":"3645 W 12th St",
    "sg:city":"Erie",
    "sg:classifiers":[
        {
            "category":"Home & Garden",
            "subcategory":"Carpets & Floor Coverings",
            "type":"Retail Goods"
        }
    ],
    "sg:phone":"+1 814 833 1615",
    "sg:postcode":"16505",
    "sg:province":"PA",
    "sg:tags":[
        "dealer",
        "rug"
    ],
    "wof:name":"Joe B's Carpet Connection",
    "wof:placetype":"venue"
},
  "geometry": {"coordinates":[-80.16332,42.093198],"type":"Point"}
}