{
  "type": "Feature",
  "properties": {
    "addr:full":"207 S Main St Greensburg PA 15601",
    "addr:housenumber":"207",
    "addr:postcode":"15601",
    "addr:street":"S Main St",
    "iso:country":"US",
    "sg:address":"207 S Main St",
    "sg:city":"Greensburg",
    "sg:classifiers":[
        {
            "category":"Shopping",
            "subcategory":"Used Merchandise",
            "type":"Retail Goods"
        }
    ],
    "sg:phone":"+1 724 834 4339",
    "sg:postcode":"15601",
    "sg:province":"PA",
    "sg:tags":[
        "shop",
        "thrift"
    ],
    "wof:name":"YWCA Thrift Shop",
    "wof:placetype":"venue"
},
  "geometry": {"coordinates":[-79.543482,40.300392],"type":"Point"}
}