{
  "type": "Feature",
  "properties": {
    "iso:country":"US",
    "sg:address":"1476 Old Swede Rd",
    "sg:city":"Douglassville",
    "sg:classifiers":[
        {
            "category":"Building & Trades",
            "subcategory":"Construction",
            "type":"Services"
        }
    ],
    "sg:phone":"+1   ",
    "sg:postcode":"19518",
    "sg:province":"PA",
    "sg:tags":[
        "house"
    ],
    "wof:name":"Bainbridge Const",
    "wof:placetype":"venue"
},
  "geometry": {"coordinates":[-75.74398600000001,40.310079],"type":"Point"}
}