{
  "type": "Feature",
  "properties": {
    "addr:full":"429 E Main St Somerset PA 15501",
    "addr:housenumber":"429",
    "addr:postcode":"15501",
    "addr:street":"E Main St",
    "iso:country":"US",
    "sg:address":"429 E Main St",
    "sg:city":"Somerset",
    "sg:classifiers":[
        {
            "category":"Retail",
            "subcategory":"Auto Repair",
            "type":"Services"
        }
    ],
    "sg:phone":"+1 814 443 6954",
    "sg:postcode":"15501",
    "sg:province":"PA",
    "sg:tags":[
        "repairing",
        "automobile"
    ],
    "wof:name":"Taylor's Auto",
    "wof:placetype":"venue"
},
  "geometry": {"coordinates":[-79.07132,40.007526],"type":"Point"}
}