{
  "type": "Feature",
  "properties": {
    "iso:country":"US",
    "sg:address":"916 State Rte 113",
    "sg:city":"Sellersville",
    "sg:classifiers":[
        {
            "category":"Wholesale",
            "subcategory":"Machinery & Supplies",
            "type":"Manufacturing & Wholesale Goods"
        }
    ],
    "sg:phone":"+1 215 723 0926",
    "sg:postcode":"18960",
    "sg:province":"PA",
    "sg:tags":[
        "equipment",
        "safety",
        "clothing"
    ],
    "sg:website":"www.coynefirstaid.com",
    "wof:name":"Coyne First Aid Inc",
    "wof:placetype":"venue"
},
  "geometry": {"coordinates":[-75.289557,40.331131],"type":"Point"}
}