{
  "type": "Feature",
  "properties": {
    "iso:country":"US",
    "sg:address":"201 N Front St",
    "sg:city":"Darby",
    "sg:classifiers":[
        {
            "category":"Building & Trades",
            "subcategory":"Electrical",
            "type":"Services"
        }
    ],
    "sg:phone":"+1   ",
    "sg:postcode":"19023",
    "sg:province":"PA",
    "sg:tags":[
        "electrical",
        "contractor"
    ],
    "wof:name":"Hurds Electrical Service",
    "wof:placetype":"venue"
},
  "geometry": {"coordinates":[-75.248113,39.918867],"type":"Point"}
}