{
  "type": "Feature",
  "properties": {
    "iso:country":"US",
    "sg:address":"123 Walnut St",
    "sg:city":"Harrisburg",
    "sg:classifiers":[
        {
            "category":"Government",
            "subcategory":"Police Station",
            "type":"Public Place"
        }
    ],
    "sg:phone":"+1 717 255 3103",
    "sg:postcode":"17101",
    "sg:province":"PA",
    "sg:tags":[
        "department"
    ],
    "wof:name":"Police Chief",
    "wof:placetype":"venue"
},
  "geometry": {"coordinates":[-76.883539,40.260196],"type":"Point"}
}