{
  "type": "Feature",
  "properties": {
    "iso:country":"US",
    "sg:address":"500 Pine Hollow Rd",
    "sg:city":"Mc Kees Rocks",
    "sg:classifiers":[
        {
            "category":"Retail",
            "subcategory":"Auto Repair",
            "type":"Services"
        }
    ],
    "sg:phone":"+1 412 331 9779",
    "sg:postcode":"15136",
    "sg:province":"PA",
    "sg:tags":[
        "automotive",
        "agency"
    ],
    "wof:name":"Jiffy Lube",
    "wof:placetype":"venue"
},
  "geometry": {"coordinates":[-80.076797,40.4701],"type":"Point"}
}