{
  "type": "Feature",
  "properties": {
    "iso:country":"US",
    "sg:address":"5 E 5th St",
    "sg:city":"East Stroudsburg",
    "sg:classifiers":[
        {
            "category":"Shopping",
            "subcategory":"Shoes",
            "type":"Retail Goods"
        }
    ],
    "sg:phone":"+1   ",
    "sg:postcode":"18301",
    "sg:province":"PA",
    "sg:tags":[
        "footwear"
    ],
    "wof:name":"Sneakers Unlimited Inc",
    "wof:placetype":"venue"
},
  "geometry": {"coordinates":[-75.18188000000001,41.014525],"type":"Point"}
}