{
  "type": "Feature",
  "properties": {
    "iso:country":"US",
    "sg:address":"62 W Swamp Rd Ste 9",
    "sg:city":"Doylestown",
    "sg:classifiers":[
        {
            "category":"Wholesale",
            "subcategory":"Computers",
            "type":"Manufacturing & Wholesale Goods"
        }
    ],
    "sg:phone":"+1 215 230 9154",
    "sg:postcode":"18901",
    "sg:province":"PA",
    "wof:name":"Site Link Services",
    "wof:placetype":"venue"
},
  "geometry": {"coordinates":[-75.13110399999999,40.329201],"type":"Point"}
}