{
  "type": "Feature",
  "properties": {
    "iso:country":"US",
    "sg:address":"2237 S Hicks St",
    "sg:city":"Philadelphia",
    "sg:classifiers":[
        {
            "category":"Retail",
            "subcategory":"Auto Rental",
            "type":"Services"
        }
    ],
    "sg:phone":"+1 215 432 6639",
    "sg:postcode":"19145",
    "sg:province":"PA",
    "sg:tags":[
        "car"
    ],
    "wof:name":"Four Seasons Limousine Service Inc.",
    "wof:placetype":"venue"
},
  "geometry": {"coordinates":[-75.172212,39.923336],"type":"Point"}
}