{
  "type": "Feature",
  "properties": {
    "iso:country":"US",
    "sg:address":"8980 Perry Hwy Ste 2",
    "sg:city":"Pittsburgh",
    "sg:classifiers":[
        {
            "category":"Wholesale",
            "subcategory":"Computers",
            "type":"Manufacturing & Wholesale Goods"
        }
    ],
    "sg:phone":"+1 412 367 4772",
    "sg:postcode":"15237",
    "sg:province":"PA",
    "wof:name":"Information Designs Inc",
    "wof:placetype":"venue"
},
  "geometry": {"coordinates":[-80.036903,40.572498],"type":"Point"}
}