{
  "type": "Feature",
  "properties": {
    "addr:full":"1831 Harrison St Philadelphia PA 19124",
    "addr:housenumber":"1831",
    "addr:postcode":"19124",
    "addr:street":"Harrison St",
    "iso:country":"US",
    "sg:address":"1831 Harrison St",
    "sg:city":"Philadelphia",
    "sg:classifiers":[
        {
            "category":"Retail",
            "subcategory":"Self-service Laundry",
            "type":"Services"
        }
    ],
    "sg:phone":"+1   ",
    "sg:postcode":"19124",
    "sg:province":"PA",
    "sg:tags":[
        "coin"
    ],
    "wof:name":"Sinn Sovath",
    "wof:placetype":"venue"
},
  "geometry": {"coordinates":[-75.075839,40.016137],"type":"Point"}
}