{
  "type": "Feature",
  "properties": {
    "iso:country":"US",
    "sg:address":"219 W Main St",
    "sg:city":"Somerset",
    "sg:classifiers":[
        {
            "category":"Professional",
            "subcategory":"Accounting & Tax Preparation",
            "type":"Services"
        }
    ],
    "sg:phone":"+1   ",
    "sg:postcode":"15501",
    "sg:province":"PA",
    "sg:tags":[
        "auditing",
        "bookkeeping"
    ],
    "wof:name":"Sebring Karen A CPA",
    "wof:placetype":"venue"
},
  "geometry": {"coordinates":[-79.08122299999999,40.008391],"type":"Point"}
}