{
  "type": "Feature",
  "properties": {
    "addr:full":"310 S 7th Ave Reading PA 19611",
    "addr:housenumber":"310",
    "addr:postcode":"19611",
    "addr:street":"S 7Th Ave",
    "iso:country":"US",
    "sg:address":"310 S 7th Ave",
    "sg:city":"Reading",
    "sg:classifiers":[
        {
            "category":"Organizations",
            "subcategory":"Membership Organization",
            "type":"Services"
        }
    ],
    "sg:phone":"+1 610 373 0722",
    "sg:postcode":"19611",
    "sg:province":"PA",
    "sg:tags":[
        "club",
        "private"
    ],
    "wof:name":"Scottish Rite Bodies",
    "wof:placetype":"venue"
},
  "geometry": {"coordinates":[-75.952043,40.332132],"type":"Point"}
}