{
  "type": "Feature",
  "properties": {
    "addr:full":"8400 Limekiln Pike Wyncote PA 19095",
    "addr:housenumber":"8400",
    "addr:postcode":"19095",
    "addr:street":"Limekiln Pike",
    "iso:country":"US",
    "sg:address":"8400 Limekiln Pike",
    "sg:city":"Wyncote",
    "sg:classifiers":[
        {
            "category":"Organizations",
            "subcategory":"Community Association",
            "type":"Services"
        }
    ],
    "sg:phone":"+1 215 881 6888",
    "sg:postcode":"19095",
    "sg:province":"PA",
    "sg:tags":[
        "club"
    ],
    "sg:website":"www.cedarbrookhillcc.com",
    "wof:name":"Cedarbrook Hill Country Club",
    "wof:placetype":"venue"
},
  "geometry": {"coordinates":[-75.16128999999999,40.082361],"type":"Point"}
}