{
  "type": "Feature",
  "properties": {
    "addr:full":"9530 Clark St Philadelphia PA 19115",
    "addr:housenumber":"9530",
    "addr:postcode":"19115",
    "addr:street":"Clark St",
    "iso:country":"US",
    "sg:address":"9530 Clark St",
    "sg:city":"Philadelphia",
    "sg:classifiers":[
        {
            "category":"Building & Trades",
            "subcategory":"Construction",
            "type":"Services"
        }
    ],
    "sg:phone":"+1   ",
    "sg:postcode":"19115",
    "sg:province":"PA",
    "sg:tags":[
        "contractor"
    ],
    "wof:name":"Best Gutter Service",
    "wof:placetype":"venue"
},
  "geometry": {"coordinates":[-75.03112299999999,40.083732],"type":"Point"}
}