{
  "type": "Feature",
  "properties": {
    "addr:full":"100 Susquehanna Trl Selinsgrove PA 17870",
    "addr:housenumber":"100",
    "addr:postcode":"17870",
    "addr:street":"Susquehanna Trl",
    "iso:country":"US",
    "sg:address":"100 Susquehanna Trl",
    "sg:city":"Selinsgrove",
    "sg:classifiers":[
        {
            "category":"Restaurant",
            "type":"Food & Drink"
        }
    ],
    "sg:phone":"+1   ",
    "sg:postcode":"17870",
    "sg:province":"PA",
    "sg:tags":[
        "eating"
    ],
    "wof:name":"Long John Silvers",
    "wof:placetype":"venue"
},
  "geometry": {"coordinates":[-76.826218,40.842903],"type":"Point"}
}