{
  "type": "Feature",
  "properties": {
    "addr:full":"5 Riverside Park Blossburg PA 16912",
    "addr:housenumber":"5",
    "addr:postcode":"16912",
    "addr:street":"Riverside Park",
    "iso:country":"US",
    "sg:address":"5 Riverside Park",
    "sg:city":"Blossburg",
    "sg:classifiers":[
        {
            "category":"Sports & Exercise",
            "subcategory":"Gym",
            "type":"Entertainment"
        }
    ],
    "sg:phone":"+1   ",
    "sg:postcode":"16912",
    "sg:province":"PA",
    "sg:tags":[
        "fitness",
        "physical",
        "facility"
    ],
    "wof:name":"Laurel Wellness Centers",
    "wof:placetype":"venue"
},
  "geometry": {"coordinates":[-77.065759,41.678726],"type":"Point"}
}