{
  "type": "Feature",
  "properties": {
    "iso:country":"US",
    "sg:address":"2650 Emerald St ",
    "sg:city":"Philadelphia",
    "sg:classifiers":[
        {
            "category":"Restaurant",
            "type":"Food & Drink"
        }
    ],
    "sg:menulink":"http://www.allmenus.com/pa/philadelphia/290390-eastern-chinese-restaurant/menu/",
    "sg:phone":"+1 215 634 3647",
    "sg:postcode":"19125",
    "sg:province":"PA",
    "sg:tags":[
        "asian",
        "chinese"
    ],
    "wof:name":"Eastern Chinese Restaurant",
    "wof:placetype":"venue"
},
  "geometry": {"coordinates":[-75.124245,39.987575],"type":"Point"}
}