{
  "type": "Feature",
  "properties": {
    "addr:full":"1127 Highwood St Pittsburgh PA 15212",
    "addr:housenumber":"1127",
    "addr:postcode":"15212",
    "addr:street":"Highwood St",
    "iso:country":"US",
    "sg:address":"1127 Highwood St",
    "sg:city":"Pittsburgh",
    "sg:classifiers":[
        {
            "category":"Retail",
            "subcategory":"Laundry & Dry Cleaning",
            "type":"Services"
        }
    ],
    "sg:phone":"+1 412 321 0473",
    "sg:postcode":"15212",
    "sg:province":"PA",
    "sg:tags":[
        "drycleaning",
        "plant",
        "except",
        "rug"
    ],
    "wof:name":"One Price Cleaners",
    "wof:placetype":"venue"
},
  "geometry": {"coordinates":[-80.026842,40.468153],"type":"Point"}
}