{
  "type": "Feature",
  "properties": {
    "addr:full":"109 Diamond St Titusville PA 16354",
    "addr:housenumber":"109",
    "addr:postcode":"16354",
    "addr:street":"Diamond St",
    "iso:country":"US",
    "sg:address":"109 Diamond St",
    "sg:city":"Titusville",
    "sg:classifiers":[
        {
            "category":"Professional",
            "subcategory":"Accounting & Tax Preparation",
            "type":"Services"
        },
        {
            "category":"Banks & Credit Unions",
            "subcategory":"Financial Services",
            "type":"Services"
        }
    ],
    "sg:phone":"+1 814 827 1371",
    "sg:postcode":"16354",
    "sg:province":"PA",
    "sg:tags":[
        "return",
        "preparation-business",
        "taxes-consultants",
        "loan",
        "reporting",
        "representative",
        "alternative",
        "bookkeeping"
    ],
    "sg:website":"http://www.hrblock.com",
    "wof:name":"H&R Block",
    "wof:placetype":"venue"
},
  "geometry": {"coordinates":[-79.67334200000001,41.62644],"type":"Point"}
}