{
  "type": "Feature",
  "properties": {
    "iso:country":"US",
    "sg:address":"353 S Gulph Rd",
    "sg:city":"King Of Prussia",
    "sg:classifiers":[
        {
            "category":"Building & Trades",
            "subcategory":"Landscaping Services",
            "type":"Services"
        }
    ],
    "sg:phone":"+1 610 205 0999",
    "sg:postcode":"19406",
    "sg:province":"PA",
    "sg:tags":[
        "landscape",
        "contractor"
    ],
    "wof:name":"Brendan A Gibbons Co",
    "wof:placetype":"venue"
},
  "geometry": {"coordinates":[-75.370491,40.080059],"type":"Point"}
}