{
  "type": "Feature",
  "properties": {
    "iso:country":"US",
    "sg:address":"1412 Ringneck Loop",
    "sg:city":"Ambler",
    "sg:classifiers":[
        {
            "category":"Professional",
            "type":"Services"
        }
    ],
    "sg:phone":"+1 215 654 1677",
    "sg:postcode":"19025",
    "sg:province":"PA",
    "sg:tags":[
        "establishment"
    ],
    "wof:name":"Graff",
    "wof:placetype":"venue"
},
  "geometry": {"coordinates":[-75.17100000000001,40.145316],"type":"Point"}
}