{
  "type": "Feature",
  "properties": {
    "iso:country":"US",
    "sg:address":"7134 Frankford Ave",
    "sg:city":"Philadelphia",
    "sg:classifiers":[
        {
            "category":"Retail",
            "subcategory":"Laundry & Dry Cleaning",
            "type":"Services"
        }
    ],
    "sg:phone":"+1 215 624 9559",
    "sg:postcode":"19135",
    "sg:province":"PA",
    "sg:tags":[
        "cleaners"
    ],
    "wof:name":"Chin U Cha",
    "wof:placetype":"venue"
},
  "geometry": {"coordinates":[-75.043297,40.035567],"type":"Point"}
}