{
  "type": "Feature",
  "properties": {
    "iso:country":"US",
    "sg:address":"1005 Industrial Hwy",
    "sg:city":"Southampton",
    "sg:classifiers":[
        {
            "category":"Shopping",
            "subcategory":"Used Merchandise",
            "type":"Retail Goods"
        },
        {
            "category":"Professional",
            "subcategory":"Business Services",
            "type":"Services"
        }
    ],
    "sg:phone":"+1 215 322 6182",
    "sg:postcode":"18966",
    "sg:province":"PA",
    "sg:tags":[
        "auctioneer"
    ],
    "sg:website":"www.stephensonsauction.com",
    "wof:name":"Auctions By Stephenson's",
    "wof:placetype":"venue"
},
  "geometry": {"coordinates":[-75.04524000000001,40.16259],"type":"Point"}
}