{
  "type": "Feature",
  "properties": {
    "addr:full":"6080 William Flynn Hwy Gibsonia PA 15044",
    "addr:housenumber":"6080",
    "addr:postcode":"15044",
    "addr:street":"William Flynn Hwy",
    "iso:country":"US",
    "sg:address":"6080 William Flynn Hwy",
    "sg:city":"Gibsonia",
    "sg:classifiers":[
        {
            "category":"Home & Garden",
            "subcategory":"Garden Supply",
            "type":"Retail Goods"
        }
    ],
    "sg:phone":"+1   ",
    "sg:postcode":"15044",
    "sg:province":"PA",
    "sg:tags":[
        "ornamental",
        "nursery"
    ],
    "wof:name":"Zottola Garden Center Inc",
    "wof:placetype":"venue"
},
  "geometry": {"coordinates":[-79.934314,40.663348],"type":"Point"}
}