{
  "type": "Feature",
  "properties": {
    "iso:country":"US",
    "sg:address":"333 Bruce Rd",
    "sg:city":"Airville",
    "sg:classifiers":[
        {
            "category":"Professional",
            "subcategory":"Management & Consulting",
            "type":"Services"
        }
    ],
    "sg:phone":"+1 717 862 0088",
    "sg:postcode":"17302",
    "sg:province":"PA",
    "sg:tags":[
        "consultant",
        "business"
    ],
    "wof:name":"Advanced Management Svc",
    "wof:placetype":"venue"
},
  "geometry": {"coordinates":[-76.445587,39.794935],"type":"Point"}
}