{
  "type": "Feature",
  "properties": {
    "iso:country":"US",
    "sg:address":"140 S Broad St",
    "sg:city":"Lansdale",
    "sg:classifiers":[
        {
            "category":"Professional",
            "subcategory":"Computer Services",
            "type":"Services"
        }
    ],
    "sg:phone":"+1 215 362 8104",
    "sg:postcode":"19446",
    "sg:province":"PA",
    "sg:tags":[
        "repair"
    ],
    "wof:name":"Mobile PC Medic",
    "wof:placetype":"venue"
},
  "geometry": {"coordinates":[-75.28516999999999,40.24026],"type":"Point"}
}