{
  "type": "Feature",
  "properties": {
    "addr:full":"7 W Gay St West Chester PA 19380",
    "addr:housenumber":"7",
    "addr:postcode":"19380",
    "addr:street":"W Gay St",
    "iso:country":"US",
    "sg:address":"7 W Gay St",
    "sg:city":"West Chester",
    "sg:classifiers":[
        {
            "category":"Building & Trades",
            "subcategory":"Construction",
            "type":"Services"
        }
    ],
    "sg:phone":"+1   ",
    "sg:postcode":"19380",
    "sg:province":"PA",
    "sg:tags":[
        "home",
        "speculative",
        "family",
        "custom"
    ],
    "wof:name":"Ashbridge Construction Inc",
    "wof:placetype":"venue"
},
  "geometry": {"coordinates":[-75.606452,39.96004],"type":"Point"}
}