{
  "type": "Feature",
  "properties": {
    "iso:country":"US",
    "sg:address":"1945 Heidlersburg Rd",
    "sg:city":"Aspers",
    "sg:classifiers":[
        {
            "category":"Manufacturing",
            "subcategory":"Tools & Machinery",
            "type":"Manufacturing & Wholesale Goods"
        },
        {
            "category":"Home & Garden",
            "subcategory":"Hardware",
            "type":"Retail Goods"
        }
    ],
    "sg:phone":"+1 717 677 8811",
    "sg:postcode":"17304",
    "sg:province":"PA",
    "sg:tags":[
        "store"
    ],
    "wof:name":"Totally Stainless, Inc.",
    "wof:placetype":"venue"
},
  "geometry": {"coordinates":[-77.180044,39.944883],"type":"Point"}
}