{
  "type": "Feature",
  "properties": {
    "iso:country":"US",
    "sg:address":"1005 Rte 130",
    "sg:city":"Jeannette",
    "sg:classifiers":[
        {
            "category":"Autos & Motor Vehicles",
            "subcategory":"Fuel & Gas Station",
            "type":"Retail Goods"
        }
    ],
    "sg:phone":"+1   ",
    "sg:postcode":"15644",
    "sg:province":"PA",
    "sg:tags":[
        "grocery",
        "gasoline"
    ],
    "wof:name":"Williams Management Corp",
    "wof:placetype":"venue"
},
  "geometry": {"coordinates":[-79.61066099999999,40.335249],"type":"Point"}
}