{
  "type": "Feature",
  "properties": {
    "iso:country":"US",
    "sg:address":"2420 Brownfield Dr",
    "sg:city":"Greensburg",
    "sg:classifiers":[
        {
            "category":"Professional",
            "type":"Services"
        }
    ],
    "sg:phone":"+1   ",
    "sg:postcode":"15601",
    "sg:province":"PA",
    "wof:name":"Kids Kastle Inc",
    "wof:placetype":"venue"
},
  "geometry": {"coordinates":[-79.565944,40.285057],"type":"Point"}
}