{
  "type": "Feature",
  "properties": {
    "iso:country":"US",
    "sg:address":"104 Walnut St",
    "sg:city":"Rices Landing",
    "sg:classifiers":[
        {
            "category":"Personal",
            "subcategory":"Beauty Salon",
            "type":"Services"
        }
    ],
    "sg:phone":"+1 724 592 5545",
    "sg:postcode":"15357",
    "sg:province":"PA",
    "sg:tags":[
        "shop"
    ],
    "wof:name":"Temptations Unlimited",
    "wof:placetype":"venue"
},
  "geometry": {"coordinates":[-80.00353,39.951282],"type":"Point"}
}