{
  "type": "Feature",
  "properties": {
    "iso:country":"US",
    "sg:address":"225 Brownsville Rd",
    "sg:city":"Pittsburgh",
    "sg:classifiers":[
        {
            "category":"Food & Beverages",
            "subcategory":"Bakery",
            "type":"Retail Goods"
        }
    ],
    "sg:phone":"+1 412 431 8407",
    "sg:postcode":"15210",
    "sg:province":"PA",
    "sg:tags":[
        "baker"
    ],
    "wof:name":"Kullman's Bakery",
    "wof:placetype":"venue"
},
  "geometry": {"coordinates":[-79.987602,40.415001],"type":"Point"}
}