{
  "type": "Feature",
  "properties": {
    "iso:country":"US",
    "sg:address":"15 Walnut St",
    "sg:city":"Nicholson",
    "sg:classifiers":[
        {
            "category":"Professional",
            "type":"Services"
        }
    ],
    "sg:phone":"+1 570 942 6868",
    "sg:postcode":"18446",
    "sg:province":"PA",
    "sg:tags":[
        "establishment"
    ],
    "wof:name":"Belvedere Lanes",
    "wof:placetype":"venue"
},
  "geometry": {"coordinates":[-75.781254,41.626879],"type":"Point"}
}