{
  "type": "Feature",
  "properties": {
    "iso:country":"US",
    "sg:address":"1789 Twin House Rd",
    "sg:city":"Oxford",
    "sg:classifiers":[
        {
            "category":"Professional",
            "type":"Services"
        }
    ],
    "sg:phone":"+1   ",
    "sg:postcode":"19363",
    "sg:province":"PA",
    "wof:name":"Life Inc",
    "wof:placetype":"venue"
},
  "geometry": {"coordinates":[-75.997692,39.761622],"type":"Point"}
}