{
  "type": "Feature",
  "properties": {
    "addr:full":"519 Bower Hill Rd Pittsburgh PA 15228",
    "addr:housenumber":"519",
    "addr:postcode":"15228",
    "addr:street":"Bower Hill Rd",
    "iso:country":"US",
    "sg:address":"519 Bower Hill Rd",
    "sg:city":"Pittsburgh",
    "sg:classifiers":[
        {
            "category":"Shopping",
            "subcategory":"Bicycles & Sporting Goods",
            "type":"Retail Goods"
        }
    ],
    "sg:phone":"+1   ",
    "sg:postcode":"15228",
    "sg:province":"PA",
    "wof:name":"Dane B Conwell Sporting E",
    "wof:placetype":"venue"
},
  "geometry": {"coordinates":[-80.053251,40.384904],"type":"Point"}
}