{
  "type": "Feature",
  "properties": {
    "addr:full":"202 Debbie Dr Scranton PA 18505",
    "addr:housenumber":"202",
    "addr:postcode":"18505",
    "addr:street":"Debbie Dr",
    "iso:country":"US",
    "sg:address":"202 Debbie Dr",
    "sg:city":"Scranton",
    "sg:classifiers":[
        {
            "category":"Building & Trades",
            "subcategory":"Construction",
            "type":"Services"
        }
    ],
    "sg:phone":"+1 570 586 5147",
    "sg:postcode":"18505",
    "sg:province":"PA",
    "sg:tags":[
        "general",
        "contractor"
    ],
    "wof:name":"Double M General Contractors",
    "wof:placetype":"venue"
},
  "geometry": {"coordinates":[-75.62464300000001,41.402251],"type":"Point"}
}