{
  "type": "Feature",
  "properties": {
    "iso:country":"US",
    "sg:address":"3144 W Berks St",
    "sg:city":"Philadelphia",
    "sg:classifiers":[
        {
            "category":"Professional",
            "subcategory":"Business Services",
            "type":"Services"
        }
    ],
    "sg:phone":"+1 215 769 1986",
    "sg:postcode":"19121",
    "sg:province":"PA",
    "wof:name":"Cambridge Residents Inc",
    "wof:placetype":"venue"
},
  "geometry": {"coordinates":[-75.18535,39.985266],"type":"Point"}
}