{
  "type": "Feature",
  "properties": {
    "iso:country":"US",
    "sg:address":"3490 Oak St",
    "sg:city":"Lebanon",
    "sg:classifiers":[
        {
            "category":"Autos & Motor Vehicles",
            "subcategory":"Automobile Sales",
            "type":"Retail Goods"
        }
    ],
    "sg:phone":"+1 717 272 8188",
    "sg:postcode":"17042",
    "sg:province":"PA",
    "sg:tags":[
        "dealers-used",
        "car",
        "used",
        "cars-wholesale"
    ],
    "wof:name":"Stan Risser Auto Sales",
    "wof:placetype":"venue"
},
  "geometry": {"coordinates":[-76.475883,40.309711],"type":"Point"}
}