{
  "type": "Feature",
  "properties": {
    "iso:country":"US",
    "sg:address":"2 Meadow Ln",
    "sg:city":"Myerstown",
    "sg:classifiers":[
        {
            "category":"Shopping",
            "subcategory":"Beauty & Cosmetics",
            "type":"Retail Goods"
        }
    ],
    "sg:phone":"+1   ",
    "sg:postcode":"17067",
    "sg:province":"PA",
    "sg:tags":[
        "merchandise"
    ],
    "wof:name":"Landuyt Kandy",
    "wof:placetype":"venue"
},
  "geometry": {"coordinates":[-76.310193,40.385743],"type":"Point"}
}