{
  "type": "Feature",
  "properties": {
    "iso:country":"US",
    "sg:address":"2300 David Dr",
    "sg:city":"Bristol",
    "sg:classifiers":[
        {
            "category":"Building & Trades",
            "subcategory":"Electrical",
            "type":"Services"
        }
    ],
    "sg:phone":"+1 215 788 6306",
    "sg:postcode":"19007",
    "sg:province":"PA",
    "sg:tags":[
        "electrician"
    ],
    "wof:name":"V Services Corporation",
    "wof:placetype":"venue"
},
  "geometry": {"coordinates":[-74.866798,40.1203],"type":"Point"}
}