{
  "type": "Feature",
  "properties": {
    "iso:country":"US",
    "sg:address":"85 Huntsville Rd",
    "sg:city":"Dallas",
    "sg:classifiers":[
        {
            "category":"Health Services",
            "subcategory":"Doctor",
            "type":"Services"
        }
    ],
    "sg:phone":"+1 570 675 4209",
    "sg:postcode":"18612",
    "sg:province":"PA",
    "sg:tags":[
        "physician",
        "surgeon"
    ],
    "wof:name":"Robert L Brown Md",
    "wof:placetype":"venue"
},
  "geometry": {"coordinates":[-75.96296700000001,41.33292],"type":"Point"}
}