{
  "type": "Feature",
  "properties": {
    "iso:country":"US",
    "sg:address":"1706 Washington St",
    "sg:city":"Carnegie",
    "sg:classifiers":[
        {
            "category":"Travel",
            "subcategory":"Travel Agent",
            "type":"Entertainment"
        }
    ],
    "sg:phone":"+1   ",
    "sg:postcode":"15106",
    "sg:province":"PA",
    "sg:tags":[
        "agency"
    ],
    "wof:name":"Global Getaways Inc",
    "wof:placetype":"venue"
},
  "geometry": {"coordinates":[-80.087042,40.390298],"type":"Point"}
}