{
  "type": "Feature",
  "properties": {
    "iso:country":"US",
    "sg:address":"10646 Rte 322",
    "sg:city":"Shippenville",
    "sg:classifiers":[
        {
            "category":"Building & Trades",
            "subcategory":"Construction",
            "type":"Services"
        }
    ],
    "sg:phone":"+1 814 223 9999",
    "sg:postcode":"16254",
    "sg:province":"PA",
    "sg:tags":[
        "mobile",
        "residential",
        "home"
    ],
    "wof:name":"Lake Erie Homes",
    "wof:placetype":"venue"
},
  "geometry": {"coordinates":[-79.420816,41.239085],"type":"Point"}
}