{
  "type": "Feature",
  "properties": {
    "iso:country":"US",
    "sg:address":"63 Pinnacle Dr",
    "sg:city":"Catawissa",
    "sg:classifiers":[
        {
            "category":"Farming",
            "subcategory":"Farm & Veterinary Services",
            "type":"Manufacturing & Wholesale Goods"
        }
    ],
    "sg:phone":"+1   ",
    "sg:postcode":"17820",
    "sg:province":"PA",
    "sg:tags":[
        "livestock",
        "crop",
        "harvesting"
    ],
    "wof:name":"Rolling Hill Farms",
    "wof:placetype":"venue"
},
  "geometry": {"coordinates":[-76.49650200000001,40.925591],"type":"Point"}
}