{
  "type": "Feature",
  "properties": {
    "iso:country":"US",
    "sg:address":"1022 -26 Washington Ave",
    "sg:city":"Philadelphia",
    "sg:classifiers":[
        {
            "category":"Building & Trades",
            "subcategory":"Construction",
            "type":"Services"
        }
    ],
    "sg:phone":"+1 215 468 8300",
    "sg:postcode":"19147",
    "sg:province":"PA",
    "sg:tags":[
        "interior",
        "design"
    ],
    "sg:website":"anviliron.net",
    "wof:name":"Anvil Iron Works",
    "wof:placetype":"venue"
},
  "geometry": {"coordinates":[-75.144434,39.933235],"type":"Point"}
}