{
  "type": "Feature",
  "properties": {
    "iso:country":"US",
    "sg:address":"106 Liberty St",
    "sg:city":"Perryopolis",
    "sg:classifiers":[
        {
            "category":"Shopping",
            "subcategory":"Jewelry",
            "type":"Retail Goods"
        }
    ],
    "sg:phone":"+1 724 736 4367",
    "sg:postcode":"15473",
    "sg:province":"PA",
    "wof:name":"K & B All That Glitters",
    "wof:placetype":"venue"
},
  "geometry": {"coordinates":[-79.75058300000001,40.086937],"type":"Point"}
}