{
  "type": "Feature",
  "properties": {
    "addr:full":"925 York Rd Gettysburg PA 17325",
    "addr:housenumber":"925",
    "addr:postcode":"17325",
    "addr:street":"York Rd",
    "iso:country":"US",
    "sg:address":"925 York Rd",
    "sg:city":"Gettysburg",
    "sg:classifiers":[
        {
            "category":"Retail",
            "subcategory":"Auto Rental",
            "type":"Services"
        }
    ],
    "sg:phone":"+1   ",
    "sg:postcode":"17325",
    "sg:province":"PA",
    "sg:tags":[
        "truck",
        "trailer",
        "utility"
    ],
    "wof:name":"U-Haul",
    "wof:placetype":"venue"
},
  "geometry": {"coordinates":[-77.21114799999999,39.838508],"type":"Point"}
}