{
  "type": "Feature",
  "properties": {
    "iso:country":"US",
    "sg:address":"871 Iris Dr",
    "sg:city":"Irwin",
    "sg:classifiers":[
        {
            "category":"Professional",
            "subcategory":"Engineering",
            "type":"Services"
        }
    ],
    "sg:phone":"+1 724 537 9600",
    "sg:postcode":"15642",
    "sg:province":"PA",
    "sg:tags":[
        "consulting",
        "engineer"
    ],
    "wof:name":"Classic Industries Inc",
    "wof:placetype":"venue"
},
  "geometry": {"coordinates":[-79.721907,40.314697],"type":"Point"}
}