{
  "type": "Feature",
  "properties": {
    "addr:full":"129 Phineyville Rd Ringtown PA 17967",
    "addr:housenumber":"129",
    "addr:postcode":"17967",
    "addr:street":"Phineyville Rd",
    "iso:country":"US",
    "sg:address":"129 Phineyville Rd",
    "sg:city":"Ringtown",
    "sg:classifiers":[
        {
            "category":"Manufacturing",
            "subcategory":"Food",
            "type":"Manufacturing & Wholesale Goods"
        }
    ],
    "sg:phone":"+1 570 889 3783",
    "sg:postcode":"17967",
    "sg:province":"PA",
    "sg:tags":[
        "product"
    ],
    "wof:name":"Edward Austra",
    "wof:placetype":"venue"
},
  "geometry": {"coordinates":[-76.141479,40.881538],"type":"Point"}
}