{
  "type": "Feature",
  "properties": {
    "iso:country":"US",
    "sg:address":"3806 Bensalem Blvd",
    "sg:city":"Bensalem",
    "sg:classifiers":[
        {
            "category":"Real Estate",
            "subcategory":"Real Estate Operator",
            "type":"Services"
        }
    ],
    "sg:phone":"+1 215 638 1115",
    "sg:postcode":"19020",
    "sg:province":"PA",
    "sg:tags":[
        "apartment",
        "complex"
    ],
    "wof:name":"Berkeley Trace Apts",
    "wof:placetype":"venue"
},
  "geometry": {"coordinates":[-74.923698,40.092098],"type":"Point"}
}