{
  "type": "Feature",
  "properties": {
    "iso:country":"US",
    "sg:address":"510 Morse Ave",
    "sg:city":"Simpson",
    "sg:classifiers":[
        {
            "category":"Personal",
            "subcategory":"Beauty Salon",
            "type":"Services"
        }
    ],
    "sg:phone":"+1 570 282 4760",
    "sg:postcode":"18407",
    "sg:province":"PA",
    "wof:name":"Geraldine Romanski Beauty",
    "wof:placetype":"venue"
},
  "geometry": {"coordinates":[-75.479648,41.588087],"type":"Point"}
}