{
  "type": "Feature",
  "properties": {
    "iso:country":"US",
    "sg:address":"1900 West St",
    "sg:city":"Homestead",
    "sg:classifiers":[
        {
            "category":"Government",
            "subcategory":"Office",
            "type":"Public Place"
        }
    ],
    "sg:phone":"+1 412 464 7313",
    "sg:postcode":"15120",
    "sg:province":"PA",
    "sg:tags":[
        "city"
    ],
    "wof:name":"Munhall Boro Mayor",
    "wof:placetype":"venue"
},
  "geometry": {"coordinates":[-79.9042,40.399045],"type":"Point"}
}