{
  "type": "Feature",
  "properties": {
    "addr:full":"367 E Chew Ave Philadelphia PA 19120",
    "addr:housenumber":"367",
    "addr:postcode":"19120",
    "addr:street":"E Chew Ave",
    "iso:country":"US",
    "sg:address":"367 E Chew Ave",
    "sg:city":"Philadelphia",
    "sg:classifiers":[
        {
            "category":"Autos & Motor Vehicles",
            "subcategory":"Auto Supplies",
            "type":"Retail Goods"
        },
        {
            "category":"Retail",
            "subcategory":"Auto Repair",
            "type":"Services"
        }
    ],
    "sg:phone":"+1 215 329 6921",
    "sg:postcode":"19120",
    "sg:province":"PA",
    "sg:tags":[
        "tire"
    ],
    "wof:name":"Veiga Auto",
    "wof:placetype":"venue"
},
  "geometry": {"coordinates":[-75.114968,40.03592],"type":"Point"}
}