{
  "type": "Feature",
  "properties": {
    "iso:country":"US",
    "sg:address":"1147 Grandview Dr",
    "sg:city":"Bethel Park",
    "sg:classifiers":[
        {
            "category":"Building & Trades",
            "subcategory":"Construction",
            "type":"Services"
        }
    ],
    "sg:phone":"+1 412 835 1184",
    "sg:postcode":"15102",
    "sg:province":"PA",
    "sg:tags":[
        "contractor"
    ],
    "wof:name":"Masson Ken Contracting and Design",
    "wof:placetype":"venue"
},
  "geometry": {"coordinates":[-80.038399,40.312],"type":"Point"}
}