{
  "type": "Feature",
  "properties": {
    "iso:country":"US",
    "sg:address":"328 Highlark Dr",
    "sg:city":"Kingston",
    "sg:classifiers":[
        {
            "category":"Building & Trades",
            "subcategory":"Construction",
            "type":"Services"
        }
    ],
    "sg:phone":"+1   ",
    "sg:postcode":"18704",
    "sg:province":"PA",
    "sg:tags":[
        "contractor"
    ],
    "wof:name":"J L Taffera",
    "wof:placetype":"venue"
},
  "geometry": {"coordinates":[-75.91871399999999,41.265523],"type":"Point"}
}