{
  "type": "Feature",
  "properties": {
    "iso:country":"US",
    "sg:address":"10 Swede Hollow Rd",
    "sg:city":"Fairmount City",
    "sg:classifiers":[
        {
            "category":"Government",
            "subcategory":"Office",
            "type":"Public Place"
        }
    ],
    "sg:phone":"+1 814 275 4045",
    "sg:postcode":"16224",
    "sg:province":"PA",
    "sg:tags":[
        "village"
    ],
    "wof:name":"Redbank Twp Maintenance Bldg",
    "wof:placetype":"venue"
},
  "geometry": {"coordinates":[-79.313874,41.011486],"type":"Point"}
}