{
  "type": "Feature",
  "properties": {
    "iso:country":"US",
    "sg:address":"7 Mansion Ave",
    "sg:city":"Marietta",
    "sg:classifiers":[
        {
            "category":"Local Transit",
            "type":"Transportation"
        }
    ],
    "sg:phone":"+1   ",
    "sg:postcode":"17547",
    "sg:province":"PA",
    "sg:tags":[
        "ambulance"
    ],
    "wof:name":"Marietta Area Ambulance Assn",
    "wof:placetype":"venue"
},
  "geometry": {"coordinates":[-76.548597,40.059935],"type":"Point"}
}