{
  "type": "Feature",
  "properties": {
    "addr:full":"2800 S Park Rd Bethel Park PA 15102",
    "addr:housenumber":"2800",
    "addr:postcode":"15102",
    "addr:street":"S Park Rd",
    "iso:country":"US",
    "sg:address":"2800 S Park Rd",
    "sg:city":"Bethel Park",
    "sg:classifiers":[
        {
            "category":"Wholesale",
            "subcategory":"Auto Parts",
            "type":"Manufacturing & Wholesale Goods"
        }
    ],
    "sg:phone":"+1   ",
    "sg:postcode":"15102",
    "sg:province":"PA",
    "wof:name":"NAPA Auto Parts",
    "wof:placetype":"venue"
},
  "geometry": {"coordinates":[-80.036844,40.327905],"type":"Point"}
}