{
  "type": "Feature",
  "properties": {
    "iso:country":"US",
    "sg:address":"821 Capouse Ave",
    "sg:city":"Scranton",
    "sg:classifiers":[
        {
            "category":"Retail",
            "subcategory":"Auto Repair",
            "type":"Services"
        }
    ],
    "sg:phone":"+1 570 343 3195",
    "sg:postcode":"18509",
    "sg:province":"PA",
    "sg:tags":[
        "repairing",
        "automobile"
    ],
    "wof:name":"Len's Garage",
    "wof:placetype":"venue"
},
  "geometry": {"coordinates":[-75.65880300000001,41.417391],"type":"Point"}
}