{
  "type": "Feature",
  "properties": {
    "iso:country":"US",
    "sg:address":"84 Shewell Ave",
    "sg:city":"Doylestown",
    "sg:classifiers":[
        {
            "category":"Professional",
            "type":"Services"
        }
    ],
    "sg:phone":"+1   ",
    "sg:postcode":"18901",
    "sg:province":"PA",
    "wof:name":"Vivid",
    "wof:placetype":"venue"
},
  "geometry": {"coordinates":[-75.13235899999999,40.311762],"type":"Point"}
}