{
  "type": "Feature",
  "properties": {
    "addr:full":"212 S 4th St Philadelphia PA 19106",
    "addr:housenumber":"212",
    "addr:postcode":"19106",
    "addr:street":"S 4Th St",
    "iso:country":"US",
    "sg:address":"212 S 4th St",
    "sg:city":"Philadelphia",
    "sg:classifiers":[
        {
            "category":"Insurance",
            "subcategory":"Hazard Insurance",
            "type":"Services"
        }
    ],
    "sg:phone":"+1   ",
    "sg:postcode":"19106",
    "sg:province":"PA",
    "sg:tags":[
        "installs",
        "underwrites"
    ],
    "wof:name":"Contributionship Companies",
    "wof:placetype":"venue"
},
  "geometry": {"coordinates":[-75.14803999999999,39.947256],"type":"Point"}
}