{
  "type": "Feature",
  "properties": {
    "iso:country":"US",
    "sg:address":"7440 Haverford Ave",
    "sg:city":"Philadelphia",
    "sg:classifiers":[
        {
            "category":"Autos & Motor Vehicles",
            "subcategory":"Fuel & Gas Station",
            "type":"Retail Goods"
        }
    ],
    "sg:phone":"+1   ",
    "sg:postcode":"19151",
    "sg:province":"PA",
    "sg:tags":[
        "station",
        "gasoline"
    ],
    "wof:name":"Coastal Gas Station",
    "wof:placetype":"venue"
},
  "geometry": {"coordinates":[-75.26498599999999,39.97681],"type":"Point"}
}