{
  "type": "Feature",
  "properties": {
    "addr:full":"115 N Main St Mifflintown PA 17059",
    "addr:housenumber":"115",
    "addr:postcode":"17059",
    "addr:street":"N Main St",
    "iso:country":"US",
    "sg:address":"115 N Main St",
    "sg:city":"Mifflintown",
    "sg:classifiers":[
        {
            "category":"Retail",
            "subcategory":"Auto Repair",
            "type":"Services"
        }
    ],
    "sg:phone":"+1 717 436 5883",
    "sg:postcode":"17059",
    "sg:province":"PA",
    "sg:tags":[
        "body",
        "repairing",
        "painting",
        "automobile"
    ],
    "wof:name":"Dave's Auto Body",
    "wof:placetype":"venue"
},
  "geometry": {"coordinates":[-77.39716799999999,40.572013],"type":"Point"}
}