{
  "type": "Feature",
  "properties": {
    "iso:country":"US",
    "sg:address":"400 Lehigh Valley Mall",
    "sg:city":"Whitehall",
    "sg:classifiers":[
        {
            "category":"Shopping",
            "subcategory":"Department Store",
            "type":"Retail Goods"
        }
    ],
    "sg:phone":"+1   ",
    "sg:postcode":"18052",
    "sg:province":"PA",
    "wof:name":"Strawbridges Department Store",
    "wof:placetype":"venue"
},
  "geometry": {"coordinates":[-75.484245,40.62882],"type":"Point"}
}