{
  "type": "Feature",
  "properties": {
    "iso:country":"US",
    "sg:address":"1834 Oregon Pike",
    "sg:city":"Lancaster",
    "sg:classifiers":[
        {
            "category":"Health Services",
            "subcategory":"Doctor",
            "type":"Services"
        }
    ],
    "sg:phone":"+1 717 569 7513",
    "sg:postcode":"17601",
    "sg:province":"PA",
    "sg:tags":[
        "dentist"
    ],
    "wof:name":"Conestoga Oral & Maxillofacial",
    "wof:placetype":"venue"
},
  "geometry": {"coordinates":[-76.296336,40.076776],"type":"Point"}
}