{
  "type": "Feature",
  "properties": {
    "addr:full":"510 Gum Tree Rd Cochranville PA 19330",
    "addr:housenumber":"510",
    "addr:postcode":"19330",
    "addr:street":"Gum Tree Rd",
    "iso:country":"US",
    "sg:address":"510 Gum Tree Rd",
    "sg:city":"Cochranville",
    "sg:classifiers":[
        {
            "category":"Building & Trades",
            "subcategory":"Construction",
            "type":"Services"
        }
    ],
    "sg:phone":"+1   ",
    "sg:postcode":"19330",
    "sg:province":"PA",
    "sg:tags":[
        "nonresidential"
    ],
    "wof:name":"Larry Testa",
    "wof:placetype":"venue"
},
  "geometry": {"coordinates":[-75.893525,39.900165],"type":"Point"}
}