{
  "type": "Feature",
  "properties": {
    "addr:full":"5511 Edsel Rd Harrisburg PA 17109",
    "addr:housenumber":"5511",
    "addr:postcode":"17109",
    "addr:street":"Edsel Rd",
    "iso:country":"US",
    "sg:address":"5511 Edsel Rd",
    "sg:city":"Harrisburg",
    "sg:classifiers":[
        {
            "category":"Shopping",
            "subcategory":"Clothing, Apparel, & Fashions",
            "type":"Retail Goods"
        }
    ],
    "sg:phone":"+1   ",
    "sg:postcode":"17109",
    "sg:province":"PA",
    "sg:tags":[
        "t",
        "shirt"
    ],
    "wof:name":"T Shirts Plus",
    "wof:placetype":"venue"
},
  "geometry": {"coordinates":[-76.792784,40.293917],"type":"Point"}
}