{
  "type": "Feature",
  "properties": {
    "iso:country":"US",
    "sg:address":"1000 Park Ave",
    "sg:city":"Altoona",
    "sg:classifiers":[
        {
            "category":"Recreation",
            "type":"Entertainment"
        }
    ],
    "sg:phone":"+1 814 943 5400",
    "sg:postcode":"16602",
    "sg:province":"PA",
    "sg:tags":[
        "club",
        "baseball"
    ],
    "wof:name":"Altoona Curve Baseball Club",
    "wof:placetype":"venue"
},
  "geometry": {"coordinates":[-78.393624,40.476988],"type":"Point"}
}