{
  "type": "Feature",
  "properties": {
    "addr:full":"1400 Southampton Rd Philadelphia PA 19116",
    "addr:housenumber":"1400",
    "addr:postcode":"19116",
    "addr:street":"Southampton Rd",
    "iso:country":"US",
    "sg:address":"1400 Southampton Rd",
    "sg:city":"Philadelphia",
    "sg:classifiers":[
        {
            "category":"Social Services",
            "type":"Services"
        }
    ],
    "sg:phone":"+1 215 673 5522",
    "sg:postcode":"19116",
    "sg:province":"PA",
    "wof:name":"Somerton Youth Organization",
    "wof:placetype":"venue"
},
  "geometry": {"coordinates":[-74.996859,40.12102],"type":"Point"}
}