{
  "type": "Feature",
  "properties": {
    "iso:country":"US",
    "sg:address":"219 Atlantic Ave",
    "sg:city":"Mc Keesport",
    "sg:classifiers":[
        {
            "category":"Restaurant",
            "type":"Food & Drink"
        }
    ],
    "sg:phone":"+1   ",
    "sg:postcode":"15132",
    "sg:province":"PA",
    "sg:tags":[
        "eating"
    ],
    "wof:name":"Deli Hut",
    "wof:placetype":"venue"
},
  "geometry": {"coordinates":[-79.87352,40.351948],"type":"Point"}
}