{
  "type": "Feature",
  "properties": {
    "iso:country":"US",
    "sg:address":"10 Mooney Rd",
    "sg:city":"Shippensburg",
    "sg:classifiers":[
        {
            "category":"Food & Beverages",
            "subcategory":"Groceries & Convenience Stores",
            "type":"Retail Goods"
        }
    ],
    "sg:phone":"+1 717 477 9339",
    "sg:postcode":"17257",
    "sg:province":"PA",
    "sg:tags":[
        "grocer"
    ],
    "wof:name":"Dutch Country Store",
    "wof:placetype":"venue"
},
  "geometry": {"coordinates":[-77.40244,40.098255],"type":"Point"}
}