{
  "type": "Feature",
  "properties": {
    "iso:country":"US",
    "sg:address":"7347 Elgin St",
    "sg:city":"Philadelphia",
    "sg:classifiers":[
        {
            "category":"Banks & Credit Unions",
            "subcategory":"Bank",
            "type":"Services"
        }
    ],
    "sg:phone":"+1 215 342 7000",
    "sg:postcode":"19111",
    "sg:province":"PA",
    "sg:tags":[
        "mortgage"
    ],
    "wof:name":"L J & P Management Corp",
    "wof:placetype":"venue"
},
  "geometry": {"coordinates":[-75.066666,40.054396],"type":"Point"}
}