{
  "type": "Feature",
  "properties": {
    "iso:country":"US",
    "sg:address":"3505 Arcola Rd",
    "sg:city":"Norristown",
    "sg:classifiers":[
        {
            "category":"Government",
            "subcategory":"Office",
            "type":"Public Place"
        }
    ],
    "sg:phone":"+1 610 489 6822",
    "sg:postcode":"19426",
    "sg:province":"PA",
    "sg:tags":[
        "village"
    ],
    "wof:name":"Lower Providence Twp Office",
    "wof:placetype":"venue"
},
  "geometry": {"coordinates":[-75.449904,40.151682],"type":"Point"}
}