{
  "type": "Feature",
  "properties": {
    "addr:full":"529 E Drinker St Dunmore PA 18512",
    "addr:housenumber":"529",
    "addr:postcode":"18512",
    "addr:street":"E Drinker St",
    "iso:country":"US",
    "sg:address":"529 E Drinker St",
    "sg:city":"Dunmore",
    "sg:classifiers":[
        {
            "category":"Personal",
            "subcategory":"Beauty Salon",
            "type":"Services"
        }
    ],
    "sg:phone":"+1 570 344 8299",
    "sg:postcode":"18512",
    "sg:province":"PA",
    "sg:tags":[
        "shop"
    ],
    "wof:name":"Style At 529",
    "wof:placetype":"venue"
},
  "geometry": {"coordinates":[-75.621852,41.419987],"type":"Point"}
}