{
  "type": "Feature",
  "properties": {
    "addr:full":"2 S High St Selinsgrove PA 17870",
    "addr:housenumber":"2",
    "addr:postcode":"17870",
    "addr:street":"S High St",
    "iso:country":"US",
    "sg:address":"2 S High St",
    "sg:city":"Selinsgrove",
    "sg:classifiers":[
        {
            "category":"Health Services",
            "subcategory":"Podiatrist",
            "type":"Services"
        }
    ],
    "sg:phone":"+1   ",
    "sg:postcode":"17870",
    "sg:province":"PA",
    "wof:name":"Miller DPM Darla R & Assoc",
    "wof:placetype":"venue"
},
  "geometry": {"coordinates":[-76.86333999999999,40.799617],"type":"Point"}
}