{
  "type": "Feature",
  "properties": {
    "iso:country":"US",
    "sg:address":"417 Carlton Ave",
    "sg:city":"Bethlehem",
    "sg:classifiers":[
        {
            "category":"Organizations",
            "subcategory":"Religious Organization",
            "type":"Services"
        }
    ],
    "sg:phone":"+1 610 691 0210",
    "sg:postcode":"18015",
    "sg:province":"PA",
    "sg:tags":[
        "clergy"
    ],
    "wof:name":"A DO Ba",
    "wof:placetype":"venue"
},
  "geometry": {"coordinates":[-75.384019,40.608424],"type":"Point"}
}