{
  "type": "Feature",
  "properties": {
    "addr:full":"60 S Morehall Rd Malvern PA 19355",
    "addr:housenumber":"60",
    "addr:postcode":"19355",
    "addr:street":"S Morehall Rd",
    "iso:country":"US",
    "sg:address":"60 S Morehall Rd",
    "sg:city":"Malvern",
    "sg:classifiers":[
        {
            "category":"Utilities",
            "subcategory":"Telephone",
            "type":"Services"
        }
    ],
    "sg:phone":"+1 610 651 2300",
    "sg:postcode":"19355",
    "sg:province":"PA",
    "sg:tags":[
        "telecommunication"
    ],
    "wof:name":"Verizon Communications",
    "wof:placetype":"venue"
},
  "geometry": {"coordinates":[-75.523398,40.046522],"type":"Point"}
}