{
  "type": "Feature",
  "properties": {
    "iso:country":"US",
    "sg:address":"325 Hays Ave",
    "sg:city":"Pittsburgh",
    "sg:classifiers":[
        {
            "category":"Retail",
            "subcategory":"Event Space",
            "type":"Services"
        }
    ],
    "sg:phone":"+1 412 481 3121",
    "sg:postcode":"15210",
    "sg:province":"PA",
    "sg:tags":[
        "venue"
    ],
    "wof:name":"Casne World",
    "wof:placetype":"venue"
},
  "geometry": {"coordinates":[-79.987629,40.413271],"type":"Point"}
}