{
  "type": "Feature",
  "properties": {
    "iso:country":"US",
    "sg:address":"34 Pennsylvania Ave",
    "sg:city":"York Haven",
    "sg:classifiers":[
        {
            "category":"Organizations",
            "subcategory":"Community Association",
            "type":"Services"
        }
    ],
    "sg:phone":"+1 717 266 6888",
    "sg:postcode":"17370",
    "sg:province":"PA",
    "sg:tags":[
        "educational"
    ],
    "wof:name":"Lincoln Intermediate Unit",
    "wof:placetype":"venue"
},
  "geometry": {"coordinates":[-76.71437,40.110566],"type":"Point"}
}