{
  "type": "Feature",
  "properties": {
    "iso:country":"US",
    "sg:address":"114 N 21st St",
    "sg:city":"Philadelphia",
    "sg:classifiers":[
        {
            "category":"Professional",
            "subcategory":"Business Services",
            "type":"Services"
        }
    ],
    "sg:phone":"+1 215 557 0717",
    "sg:postcode":"19103",
    "sg:province":"PA",
    "sg:tags":[
        "consultant",
        "coach"
    ],
    "wof:name":"Mint Condition",
    "wof:placetype":"venue"
},
  "geometry": {"coordinates":[-75.174522,39.956292],"type":"Point"}
}