{
  "type": "Feature",
  "properties": {
    "iso:country":"US",
    "sg:address":"2864 N Mascher St",
    "sg:city":"Philadelphia",
    "sg:classifiers":[
        {
            "category":"Shopping",
            "subcategory":"Department Store",
            "type":"Retail Goods"
        }
    ],
    "sg:phone":"+1 215 739 0514",
    "sg:postcode":"19133",
    "sg:province":"PA",
    "sg:tags":[
        "shop"
    ],
    "wof:name":"Kang's Discount Store",
    "wof:placetype":"venue"
},
  "geometry": {"coordinates":[-75.132465,39.993257],"type":"Point"}
}