{
  "type": "Feature",
  "properties": {
    "iso:country":"US",
    "sg:address":"103 Delafield Rd",
    "sg:city":"Aspinwall",
    "sg:classifiers":[
        {
            "category":"Food & Beverages",
            "subcategory":"Groceries & Convenience Stores",
            "type":"Retail Goods"
        },
        {
            "category":"Food & Beverages",
            "subcategory":"Fruits & Vegetables",
            "type":"Retail Goods"
        }
    ],
    "sg:phone":"+1 412 781 0125",
    "sg:postcode":"15215",
    "sg:province":"PA",
    "sg:tags":[
        "market"
    ],
    "wof:name":"Patty s Farm Market",
    "wof:placetype":"venue"
},
  "geometry": {"coordinates":[-79.89734900000001,40.489827],"type":"Point"}
}