{
  "type": "Feature",
  "properties": {
    "iso:country":"US",
    "sg:address":"559 Grant St",
    "sg:city":"Pittsburgh",
    "sg:classifiers":[
        {
            "category":"Banks & Credit Unions",
            "subcategory":"Bank",
            "type":"Services"
        }
    ],
    "sg:phone":"+1 412 261 3355",
    "sg:postcode":"15219",
    "sg:province":"PA",
    "wof:name":"Parkvale Bank",
    "wof:placetype":"venue"
},
  "geometry": {"coordinates":[-79.996201,40.440601],"type":"Point"}
}