{
  "type": "Feature",
  "properties": {
    "addr:full":"501 Corporate Dr Ste 200 Canonsburg PA 15317",
    "addr:housenumber":"501",
    "addr:postcode":"15317",
    "addr:street":"Corporate Dr Ste 200",
    "iso:country":"US",
    "sg:address":"501 Corporate Dr Ste 200",
    "sg:city":"Canonsburg",
    "sg:classifiers":[
        {
            "category":"Professional",
            "subcategory":"Lawyer & Legal Services",
            "type":"Services"
        }
    ],
    "sg:phone":"+1 724 873 8660",
    "sg:postcode":"15317",
    "sg:province":"PA",
    "wof:name":"Sinclair Jackson Reinhart & Hayden",
    "wof:placetype":"venue"
},
  "geometry": {"coordinates":[-80.17269899999999,40.297501],"type":"Point"}
}