{
  "type": "Feature",
  "properties": {
    "addr:full":"3 Vernon Ln Boothwyn PA 19061",
    "addr:housenumber":"3",
    "addr:postcode":"19061",
    "addr:street":"Vernon Ln",
    "iso:country":"US",
    "sg:address":"3 Vernon Ln",
    "sg:city":"Boothwyn",
    "sg:classifiers":[
        {
            "category":"Retail",
            "subcategory":"Auto Repair",
            "type":"Services"
        }
    ],
    "sg:phone":"+1 610 358 3748",
    "sg:postcode":"19061",
    "sg:province":"PA",
    "sg:tags":[
        "repairing",
        "automobile"
    ],
    "wof:name":"Chris Greentree Auto Svc",
    "wof:placetype":"venue"
},
  "geometry": {"coordinates":[-75.48259400000001,39.863155],"type":"Point"}
}