{
  "type": "Feature",
  "properties": {
    "iso:country":"US",
    "sg:address":"595 Main St",
    "sg:city":"Bethlehem",
    "sg:classifiers":[
        {
            "category":"Professional",
            "type":"Services"
        }
    ],
    "sg:phone":"+1 610 317 9323",
    "sg:postcode":"18018",
    "sg:province":"PA",
    "sg:tags":[
        "establishment"
    ],
    "wof:name":"Andy's Seconds",
    "wof:placetype":"venue"
},
  "geometry": {"coordinates":[-75.382017,40.62148],"type":"Point"}
}