{
  "type": "Feature",
  "properties": {
    "iso:country":"US",
    "sg:address":"104 W High St",
    "sg:city":"Milford",
    "sg:classifiers":[
        {
            "category":"Professional",
            "subcategory":"Research",
            "type":"Services"
        }
    ],
    "sg:phone":"+1 570 296 0382",
    "sg:postcode":"18337",
    "sg:province":"PA",
    "sg:tags":[
        "environmental",
        "ecological"
    ],
    "wof:name":"C & H Environmental Inc",
    "wof:placetype":"venue"
},
  "geometry": {"coordinates":[-74.800961,41.324644],"type":"Point"}
}