{
  "type": "Feature",
  "properties": {
    "addr:full":"144 Fairville Rd Chadds Ford PA 19317",
    "addr:housenumber":"144",
    "addr:postcode":"19317",
    "addr:street":"Fairville Rd",
    "iso:country":"US",
    "sg:address":"144 Fairville Rd",
    "sg:city":"Chadds Ford",
    "sg:classifiers":[
        {
            "category":"Building & Trades",
            "subcategory":"Construction",
            "type":"Services"
        }
    ],
    "sg:phone":"+1 610 388 3202",
    "sg:postcode":"19317",
    "sg:province":"PA",
    "sg:tags":[
        "painter",
        "contractor"
    ],
    "sg:website":"www.lindsayconstructioninc.com",
    "wof:name":"Lindsay Construction Inc",
    "wof:placetype":"venue"
},
  "geometry": {"coordinates":[-75.59850299999999,39.868],"type":"Point"}
}