{
  "type": "Feature",
  "properties": {
    "iso:country":"US",
    "sg:address":"63 S Main St",
    "sg:city":"Mansfield",
    "sg:classifiers":[
        {
            "category":"Health Services",
            "subcategory":"Doctor",
            "type":"Services"
        }
    ],
    "sg:phone":"+1   ",
    "sg:postcode":"16933",
    "sg:province":"PA",
    "sg:tags":[
        "medical"
    ],
    "wof:name":"Cetton Gregory MD",
    "wof:placetype":"venue"
},
  "geometry": {"coordinates":[-77.07746400000001,41.80573],"type":"Point"}
}