{
  "type": "Feature",
  "properties": {
    "iso:country":"US",
    "sg:address":"7 Nob Hill Rd",
    "sg:city":"Devon",
    "sg:classifiers":[
        {
            "category":"Personal",
            "type":"Services"
        }
    ],
    "sg:phone":"+1 610 688 6286",
    "sg:postcode":"19333",
    "sg:province":"PA",
    "sg:tags":[
        "consultant",
        "program",
        "health",
        "fitness"
    ],
    "wof:name":"Pilates Body Smith",
    "wof:placetype":"venue"
},
  "geometry": {"coordinates":[-75.430611,40.029934],"type":"Point"}
}