{
  "type": "Feature",
  "properties": {
    "iso:country":"US",
    "sg:address":"1801 N. Broad Street",
    "sg:city":"Philadelphia",
    "sg:classifiers":[
        {
            "category":"Education",
            "subcategory":"University",
            "type":"Public Place"
        }
    ],
    "sg:phone":"+1 215 204 7000",
    "sg:postcode":"19102",
    "sg:province":"PA",
    "sg:tags":[
        "college"
    ],
    "sg:website":"www.temple.edu/",
    "wof:name":"Temple University",
    "wof:placetype":"venue"
},
  "geometry": {"coordinates":[-75.156913,39.980243],"type":"Point"}
}