{
  "type": "Feature",
  "properties": {
    "iso:country":"US",
    "sg:address":"482 Portman Rd",
    "sg:city":"Butler",
    "sg:classifiers":[
        {
            "category":"Retail",
            "subcategory":"Laundry & Dry Cleaning",
            "type":"Services"
        },
        {
            "category":"Building & Trades",
            "subcategory":"Cleaning & Sanitation",
            "type":"Services"
        }
    ],
    "sg:phone":"+1 866 263 8430",
    "sg:postcode":"16002",
    "sg:province":"PA",
    "sg:tags":[
        "cleaner",
        "upholstery",
        "rug",
        "carpet"
    ],
    "wof:name":"Surface Restoration Pros",
    "wof:placetype":"venue"
},
  "geometry": {"coordinates":[-79.829812,40.847359],"type":"Point"}
}