{
  "type": "Feature",
  "properties": {
    "addr:full":"2016 Clayton Ave Harrisburg PA 17109",
    "addr:housenumber":"2016",
    "addr:postcode":"17109",
    "addr:street":"Clayton Ave",
    "iso:country":"US",
    "sg:address":"2016 Clayton Ave",
    "sg:city":"Harrisburg",
    "sg:classifiers":[
        {
            "category":"Building & Trades",
            "subcategory":"Construction",
            "type":"Services"
        }
    ],
    "sg:phone":"+1 717 232 4705",
    "sg:postcode":"17109",
    "sg:province":"PA",
    "sg:tags":[
        "home",
        "improvement"
    ],
    "wof:name":"Mc Lamb Done Right Carpentry",
    "wof:placetype":"venue"
},
  "geometry": {"coordinates":[-76.863181,40.284302],"type":"Point"}
}