{
  "type": "Feature",
  "properties": {
    "iso:country":"US",
    "sg:address":"1025 Taneytown Rd",
    "sg:city":"Gettysburg",
    "sg:classifiers":[
        {
            "category":"Personal",
            "type":"Services"
        }
    ],
    "sg:phone":"+1   ",
    "sg:postcode":"17325",
    "sg:province":"PA",
    "wof:name":"Bonham Imit Services Inc",
    "wof:placetype":"venue"
},
  "geometry": {"coordinates":[-77.230644,39.788677],"type":"Point"}
}