{
  "type": "Feature",
  "properties": {
    "addr:full":"7647 Frankstown Ave Pittsburgh PA 15208",
    "addr:housenumber":"7647",
    "addr:postcode":"15208",
    "addr:street":"Frankstown Ave",
    "iso:country":"US",
    "sg:address":"7647 Frankstown Ave",
    "sg:city":"Pittsburgh",
    "sg:classifiers":[
        {
            "category":"Banks & Credit Unions",
            "subcategory":"Bank",
            "type":"Services"
        }
    ],
    "sg:phone":"+1   ",
    "sg:postcode":"15208",
    "sg:province":"PA",
    "sg:tags":[
        "cashing",
        "agency",
        "check"
    ],
    "wof:name":"Money Mart 153",
    "wof:placetype":"venue"
},
  "geometry": {"coordinates":[-79.888155,40.455623],"type":"Point"}
}