{
  "type": "Feature",
  "properties": {
    "addr:full":"208 Mail Route Rd Reading PA 19608",
    "addr:housenumber":"208",
    "addr:postcode":"19608",
    "addr:street":"Mail Route Rd",
    "iso:country":"US",
    "sg:address":"208 Mail Route Rd",
    "sg:city":"Reading",
    "sg:classifiers":[
        {
            "category":"Health Services",
            "subcategory":"Dentist",
            "type":"Services"
        }
    ],
    "sg:phone":"+1 610 775 3607",
    "sg:postcode":"19608",
    "sg:province":"PA",
    "wof:name":"Thomas Orbach",
    "wof:placetype":"venue"
},
  "geometry": {"coordinates":[-76.05183700000001,40.283662],"type":"Point"}
}