{
  "type": "Feature",
  "properties": {
    "iso:country":"US",
    "sg:address":"15 N 6th St",
    "sg:city":"Indiana",
    "sg:classifiers":[
        {
            "category":"Shopping",
            "type":"Retail Goods"
        }
    ],
    "sg:phone":"+1 724 463 6264",
    "sg:postcode":"15701",
    "sg:province":"PA",
    "sg:tags":[
        "trophy",
        "medal",
        "award"
    ],
    "wof:name":"Crooked Creek Creations",
    "wof:placetype":"venue"
},
  "geometry": {"coordinates":[-79.15069699999999,40.623291],"type":"Point"}
}