{
  "type": "Feature",
  "properties": {
    "iso:country":"US",
    "sg:address":"962 Brown Ave",
    "sg:city":"Erie",
    "sg:classifiers":[
        {
            "category":"Restaurant",
            "type":"Food & Drink"
        }
    ],
    "sg:phone":"+1 814 454 7745",
    "sg:postcode":"16502",
    "sg:province":"PA",
    "sg:tags":[
        "delicatessen"
    ],
    "wof:name":"Europa Delicatessen",
    "wof:placetype":"venue"
},
  "geometry": {"coordinates":[-80.095555,42.108686],"type":"Point"}
}