{
  "type": "Feature",
  "properties": {
    "iso:country":"US",
    "sg:address":"501 Howard Ave",
    "sg:city":"Altoona",
    "sg:classifiers":[
        {
            "category":"Professional",
            "subcategory":"Accounting & Tax Preparation",
            "type":"Services"
        }
    ],
    "sg:phone":"+1   ",
    "sg:postcode":"16601",
    "sg:province":"PA",
    "wof:name":"Per-SE Technologies Inc",
    "wof:placetype":"venue"
},
  "geometry": {"coordinates":[-78.397727,40.521537],"type":"Point"}
}