{
  "type": "Feature",
  "properties": {
    "iso:country":"US",
    "sg:address":"551 N Gallatin Ave",
    "sg:city":"Uniontown",
    "sg:classifiers":[
        {
            "category":"Personal",
            "subcategory":"Beauty Salon",
            "type":"Services"
        }
    ],
    "sg:phone":"+1 724 438 3976",
    "sg:postcode":"15401",
    "sg:province":"PA",
    "wof:name":"Carol's Beauty Salon",
    "wof:placetype":"venue"
},
  "geometry": {"coordinates":[-79.71159,39.912069],"type":"Point"}
}