{
  "type": "Feature",
  "properties": {
    "iso:country":"US",
    "sg:address":"1700 E Market St",
    "sg:city":"York",
    "sg:classifiers":[
        {
            "category":"Autos & Motor Vehicles",
            "subcategory":"Fuel & Gas Station",
            "type":"Retail Goods"
        }
    ],
    "sg:phone":"+1 717 846 3492",
    "sg:postcode":"17403",
    "sg:province":"PA",
    "sg:tags":[
        "grocery",
        "station",
        "gasoline"
    ],
    "wof:name":"Sunoco",
    "wof:placetype":"venue"
},
  "geometry": {"coordinates":[-76.694807,39.972915],"type":"Point"}
}