{
  "type": "Feature",
  "properties": {
    "addr:full":"1912 Brownsville Rd Pittsburgh PA 15210",
    "addr:housenumber":"1912",
    "addr:postcode":"15210",
    "addr:street":"Brownsville Rd",
    "iso:country":"US",
    "sg:address":"1912 Brownsville Rd",
    "sg:city":"Pittsburgh",
    "sg:classifiers":[
        {
            "category":"Organizations",
            "subcategory":"Religious Organization",
            "type":"Services"
        }
    ],
    "sg:phone":"+1 412 886 0400",
    "sg:postcode":"15210",
    "sg:province":"PA",
    "sg:tags":[
        "church"
    ],
    "wof:name":"South Pittsburgh Assembly-God",
    "wof:placetype":"venue"
},
  "geometry": {"coordinates":[-79.986881,40.395212],"type":"Point"}
}