{
  "type": "Feature",
  "properties": {
    "addr:full":"241 Swope Rd Bethel PA 19507",
    "addr:housenumber":"241",
    "addr:postcode":"19507",
    "addr:street":"Swope Rd",
    "iso:country":"US",
    "sg:address":"241 Swope Rd",
    "sg:city":"Bethel",
    "sg:classifiers":[
        {
            "category":"Personal",
            "subcategory":"Beauty Salon",
            "type":"Services"
        }
    ],
    "sg:phone":"+1 717 933 5251",
    "sg:postcode":"19507",
    "sg:province":"PA",
    "sg:tags":[
        "shop"
    ],
    "wof:name":"Patricia Bashores Hair Stylist",
    "wof:placetype":"venue"
},
  "geometry": {"coordinates":[-76.33938499999999,40.490988],"type":"Point"}
}