{
  "type": "Feature",
  "properties": {
    "iso:country":"US",
    "sg:address":"510 E Main St",
    "sg:city":"Norristown",
    "sg:classifiers":[
        {
            "category":"Professional",
            "subcategory":"Business Services",
            "type":"Services"
        }
    ],
    "sg:phone":"+1 610 275 3943",
    "sg:postcode":"19401",
    "sg:province":"PA",
    "sg:tags":[
        "license"
    ],
    "wof:name":"Luciani's Title & Tag Svc",
    "wof:placetype":"venue"
},
  "geometry": {"coordinates":[-75.334113,40.110734],"type":"Point"}
}