{
  "type": "Feature",
  "properties": {
    "iso:country":"US",
    "sg:address":"210 W Rittenhouse Sq",
    "sg:city":"Philadelphia",
    "sg:classifiers":[
        {
            "category":"Professional",
            "subcategory":"Management & Consulting",
            "type":"Services"
        }
    ],
    "sg:phone":"+1 215 546 4150",
    "sg:postcode":"19103",
    "sg:province":"PA",
    "sg:tags":[
        "consultant",
        "business"
    ],
    "wof:name":"J P Lerman & Company",
    "wof:placetype":"venue"
},
  "geometry": {"coordinates":[-75.173011,39.949623],"type":"Point"}
}