{
  "type": "Feature",
  "properties": {
    "addr:full":"3621 N 22nd St Philadelphia PA 19140",
    "addr:housenumber":"3621",
    "addr:postcode":"19140",
    "addr:street":"N 22Nd St",
    "iso:country":"US",
    "sg:address":"3621 N 22nd St",
    "sg:city":"Philadelphia",
    "sg:classifiers":[
        {
            "category":"Restaurant",
            "type":"Food & Drink"
        }
    ],
    "sg:phone":"+1 215 226 6654",
    "sg:postcode":"19140",
    "sg:province":"PA",
    "wof:name":"Yang Ying Chun",
    "wof:placetype":"venue"
},
  "geometry": {"coordinates":[-75.164576,40.009336],"type":"Point"}
}