{
  "type": "Feature",
  "properties": {
    "iso:country":"US",
    "sg:address":"4225 Adams Ave",
    "sg:city":"Philadelphia",
    "sg:classifiers":[
        {
            "category":"Building & Trades",
            "subcategory":"Cleaning & Sanitation",
            "type":"Services"
        },
        {
            "category":"Manufacturing",
            "subcategory":"Textiles",
            "type":"Manufacturing & Wholesale Goods"
        },
        {
            "category":"Building & Trades",
            "subcategory":"Construction",
            "type":"Services"
        }
    ],
    "sg:phone":"+1 215 535 0211",
    "sg:postcode":"19124",
    "sg:province":"PA",
    "sg:tags":[
        "refinishing",
        "altering",
        "tile-cleaning",
        "contractor",
        "tile-contractors",
        "tile-wholesale",
        "sealing",
        "manufacturer",
        "remodeling",
        "marble",
        "terrazzo"
    ],
    "wof:name":"Buzzelli Marble and Granite",
    "wof:placetype":"venue"
},
  "geometry": {"coordinates":[-75.09332999999999,40.01186],"type":"Point"}
}