{
  "type": "Feature",
  "properties": {
    "iso:country":"US",
    "sg:address":"901 S Center St",
    "sg:city":"Coal Township",
    "sg:classifiers":[
        {
            "category":"Autos & Motor Vehicles",
            "subcategory":"Auto Supplies",
            "type":"Retail Goods"
        }
    ],
    "sg:phone":"+1   ",
    "sg:postcode":"17866",
    "sg:province":"PA",
    "sg:tags":[
        "automotive",
        "parts"
    ],
    "wof:name":"Advance Auto Parts",
    "wof:placetype":"venue"
},
  "geometry": {"coordinates":[-76.574129,40.804755],"type":"Point"}
}