{
  "type": "Feature",
  "properties": {
    "addr:full":"955 Wertzville Rd Enola PA 17025",
    "addr:housenumber":"955",
    "addr:postcode":"17025",
    "addr:street":"Wertzville Rd",
    "iso:country":"US",
    "sg:address":"955 Wertzville Rd",
    "sg:city":"Enola",
    "sg:classifiers":[
        {
            "category":"Shopping",
            "subcategory":"Luggage & Leather Goods",
            "type":"Retail Goods"
        }
    ],
    "sg:phone":"+1   ",
    "sg:postcode":"17025",
    "sg:province":"PA",
    "wof:name":"Contrad Leather",
    "wof:placetype":"venue"
},
  "geometry": {"coordinates":[-76.957634,40.286918],"type":"Point"}
}