{
  "type": "Feature",
  "properties": {
    "iso:country":"US",
    "sg:address":"273 Waverly Rd",
    "sg:city":"Morton",
    "sg:classifiers":[
        {
            "category":"Building & Trades",
            "subcategory":"Electrical",
            "type":"Services"
        }
    ],
    "sg:phone":"+1 610 544 9730",
    "sg:postcode":"19070",
    "sg:province":"PA",
    "sg:tags":[
        "electrical",
        "contractor"
    ],
    "wof:name":"Natale Electric Inc",
    "wof:placetype":"venue"
},
  "geometry": {"coordinates":[-75.330724,39.91636],"type":"Point"}
}