{
  "type": "Feature",
  "properties": {
    "iso:country":"US",
    "sg:address":"608 N 22nd St",
    "sg:city":"Philadelphia",
    "sg:classifiers":[
        {
            "category":"Organizations",
            "subcategory":"Religious Organization",
            "type":"Services"
        }
    ],
    "sg:phone":"+1 215 232 8393",
    "sg:postcode":"19130",
    "sg:province":"PA",
    "wof:name":"Coalition For Christian Otrch",
    "wof:placetype":"venue"
},
  "geometry": {"coordinates":[-75.17406200000001,39.965827],"type":"Point"}
}