{
  "type": "Feature",
  "properties": {
    "iso:country":"US",
    "sg:address":"56 Banks St",
    "sg:city":"Harrisburg",
    "sg:classifiers":[
        {
            "category":"Organizations",
            "subcategory":"Religious Organization",
            "type":"Services"
        }
    ],
    "sg:phone":"+1 717 236 5275",
    "sg:postcode":"17103",
    "sg:province":"PA",
    "sg:tags":[
        "church"
    ],
    "sg:website":"www.church-of-christ.org",
    "wof:name":"Penbrook United Church of Christ",
    "wof:placetype":"venue"
},
  "geometry": {"coordinates":[-76.84880099999999,40.277401],"type":"Point"}
}