{
  "type": "Feature",
  "properties": {
    "iso:country":"US",
    "sg:address":"1709 Providence Ave",
    "sg:city":"Chester",
    "sg:classifiers":[
        {
            "category":"Social Services",
            "subcategory":"Child Care",
            "type":"Services"
        }
    ],
    "sg:phone":"+1 610 872 5060",
    "sg:postcode":"19013",
    "sg:province":"PA",
    "sg:tags":[
        "guidance",
        "counselor",
        "adolescent"
    ],
    "wof:name":"Center For Self Development",
    "wof:placetype":"venue"
},
  "geometry": {"coordinates":[-75.360294,39.86281],"type":"Point"}
}