{
  "type": "Feature",
  "properties": {
    "iso:country":"US",
    "sg:address":"161 E Main St",
    "sg:city":"Bloomsburg",
    "sg:classifiers":[
        {
            "category":"Restaurant",
            "type":"Food & Drink"
        }
    ],
    "sg:phone":"+1 570 387 9044",
    "sg:postcode":"17815",
    "sg:province":"PA",
    "sg:tags":[
        "eating"
    ],
    "wof:name":"Bloomsburg Diner",
    "wof:placetype":"venue"
},
  "geometry": {"coordinates":[-76.45465299999999,41.004016],"type":"Point"}
}