{
  "type": "Feature",
  "properties": {
    "addr:full":"338 Main St Mc Sherrystown PA 17344",
    "addr:housenumber":"338",
    "addr:postcode":"17344",
    "addr:street":"Main St",
    "iso:country":"US",
    "sg:address":"338 Main St",
    "sg:city":"Mc Sherrystown",
    "sg:classifiers":[
        {
            "category":"Government",
            "subcategory":"Office",
            "type":"Public Place"
        }
    ],
    "sg:phone":"+1   ",
    "sg:postcode":"17344",
    "sg:province":"PA",
    "sg:tags":[
        "borough"
    ],
    "wof:name":"Borough of Mc Sherrystown",
    "wof:placetype":"venue"
},
  "geometry": {"coordinates":[-77.018483,39.804026],"type":"Point"}
}