{
  "type": "Feature",
  "properties": {
    "iso:country":"US",
    "sg:address":"71 Edgewater Dr",
    "sg:city":"Chambersburg",
    "sg:classifiers":[
        {
            "category":"Place Of Worship",
            "type":"Public Place"
        }
    ],
    "sg:phone":"+1 717 369 5285",
    "sg:postcode":"17202",
    "sg:province":"PA",
    "sg:tags":[
        "church"
    ],
    "wof:name":"Hands Of Grace, Inc.",
    "wof:placetype":"venue"
},
  "geometry": {"coordinates":[-77.737908,39.926717],"type":"Point"}
}