{
  "type": "Feature",
  "properties": {
    "addr:full":"111 Pembrooke Cir Phoenixville PA 19460",
    "addr:housenumber":"111",
    "addr:postcode":"19460",
    "addr:street":"Pembrooke Cir",
    "iso:country":"US",
    "sg:address":"111 Pembrooke Cir",
    "sg:city":"Phoenixville",
    "sg:classifiers":[
        {
            "category":"Building & Trades",
            "subcategory":"Construction",
            "type":"Services"
        }
    ],
    "sg:phone":"+1   ",
    "sg:postcode":"19460",
    "sg:province":"PA",
    "sg:tags":[
        "residential"
    ],
    "wof:name":"Toll Brothers Inc",
    "wof:placetype":"venue"
},
  "geometry": {"coordinates":[-75.493815,40.091203],"type":"Point"}
}