{
  "type": "Feature",
  "properties": {
    "iso:country":"US",
    "sg:address":"573 N Main St",
    "sg:city":"Doylestown",
    "sg:classifiers":[
        {
            "category":"Health Services",
            "subcategory":"Doctor",
            "type":"Services"
        }
    ],
    "sg:phone":"+1   ",
    "sg:postcode":"18901",
    "sg:province":"PA",
    "sg:tags":[
        "medical"
    ],
    "wof:name":"Katherine Harris MD",
    "wof:placetype":"venue"
},
  "geometry": {"coordinates":[-75.130341,40.323533],"type":"Point"}
}