{
  "type": "Feature",
  "properties": {
    "addr:full":"626 Galleria Dr Johnstown PA 15904",
    "addr:housenumber":"626",
    "addr:postcode":"15904",
    "addr:street":"Galleria Dr",
    "iso:country":"US",
    "sg:address":"626 Galleria Dr",
    "sg:city":"Johnstown",
    "sg:classifiers":[
        {
            "category":"Shopping",
            "subcategory":"Computers & Home Electronics",
            "type":"Retail Goods"
        }
    ],
    "sg:phone":"+1   ",
    "sg:postcode":"15904",
    "sg:province":"PA",
    "sg:tags":[
        "store"
    ],
    "wof:name":"Circuit City",
    "wof:placetype":"venue"
},
  "geometry": {"coordinates":[-78.832908,40.303602],"type":"Point"}
}