{
  "type": "Feature",
  "properties": {
    "iso:country":"US",
    "sg:address":"696 2nd Street Pike",
    "sg:city":"Richboro",
    "sg:classifiers":[
        {
            "category":"Professional",
            "type":"Services"
        }
    ],
    "sg:phone":"+1   ",
    "sg:postcode":"18954",
    "sg:province":"PA",
    "wof:name":"Innovtive Hlthcare Cncepts LLC",
    "wof:placetype":"venue"
},
  "geometry": {"coordinates":[-75.018086,40.20597],"type":"Point"}
}