{
  "type": "Feature",
  "properties": {
    "iso:country":"US",
    "sg:address":"208 N Main St",
    "sg:city":"Coopersburg",
    "sg:classifiers":[
        {
            "category":"Personal",
            "subcategory":"Beauty Salon",
            "type":"Services"
        }
    ],
    "sg:phone":"+1 610 282 9568",
    "sg:postcode":"18036",
    "sg:province":"PA",
    "wof:name":"Ashley's Main Street Styles",
    "wof:placetype":"venue"
},
  "geometry": {"coordinates":[-75.38981099999999,40.51328],"type":"Point"}
}