{
  "type": "Feature",
  "properties": {
    "addr:full":"20 Conewago Rd New Oxford PA 17350",
    "addr:housenumber":"20",
    "addr:postcode":"17350",
    "addr:street":"Conewago Rd",
    "iso:country":"US",
    "sg:address":"20 Conewago Rd",
    "sg:city":"New Oxford",
    "sg:phone":"+1   ",
    "sg:postcode":"17350",
    "sg:province":"PA",
    "sg:tags":[
        "farm",
        "field",
        "crop"
    ],
    "wof:name":"Gregory Raber",
    "wof:placetype":"venue"
},
  "geometry": {"coordinates":[-77.088487,39.89882],"type":"Point"}
}