{
  "type": "Feature",
  "properties": {
    "iso:country":"US",
    "sg:address":"7325 Frankstown Ave",
    "sg:city":"Pittsburgh",
    "sg:classifiers":[
        {
            "category":"Organizations",
            "subcategory":"Community Association",
            "type":"Services"
        }
    ],
    "sg:phone":"+1 412 247 5908",
    "sg:postcode":"15208",
    "sg:province":"PA",
    "sg:tags":[
        "club"
    ],
    "wof:name":"Wenco Club",
    "wof:placetype":"venue"
},
  "geometry": {"coordinates":[-79.892405,40.45659],"type":"Point"}
}