{
  "type": "Feature",
  "properties": {
    "iso:country":"US",
    "sg:address":"68 Stambaugh Ave",
    "sg:city":"Sharon",
    "sg:classifiers":[
        {
            "category":"Structure",
            "subcategory":"Office Building",
            "type":"Public Place"
        }
    ],
    "sg:phone":"+1 724 979 4850",
    "sg:postcode":"16146",
    "sg:province":"PA",
    "sg:tags":[
        "park"
    ],
    "wof:name":"P J Properties",
    "wof:placetype":"venue"
},
  "geometry": {"coordinates":[-80.493363,41.232432],"type":"Point"}
}