{
  "type": "Feature",
  "properties": {
    "addr:full":"368 Farm Ln North Wales PA 19454",
    "addr:housenumber":"368",
    "addr:postcode":"19454",
    "addr:street":"Farm Ln",
    "iso:country":"US",
    "sg:address":"368 Farm Ln",
    "sg:city":"North Wales",
    "sg:classifiers":[
        {
            "category":"Government",
            "subcategory":"Office",
            "type":"Public Place"
        }
    ],
    "sg:phone":"+1   ",
    "sg:postcode":"19454",
    "sg:province":"PA",
    "sg:tags":[
        "housing",
        "program"
    ],
    "wof:name":"Catrich Inc",
    "wof:placetype":"venue"
},
  "geometry": {"coordinates":[-75.264059,40.215973],"type":"Point"}
}