{
  "type": "Feature",
  "properties": {
    "iso:country":"US",
    "sg:address":"261 Schoolhouse Rd Ste 4",
    "sg:city":"Souderton",
    "sg:classifiers":[
        {
            "category":"Professional",
            "subcategory":"Business Services",
            "type":"Services"
        }
    ],
    "sg:phone":"+1 215 723 1171",
    "sg:postcode":"18964",
    "sg:province":"PA",
    "sg:tags":[
        "holding"
    ],
    "wof:name":"Aldegen Holdings",
    "wof:placetype":"venue"
},
  "geometry": {"coordinates":[-75.352519,40.281222],"type":"Point"}
}