{
  "type": "Feature",
  "properties": {
    "iso:country":"US",
    "sg:address":"111 Lowes Hill Rd",
    "sg:city":"Munson",
    "sg:classifiers":[
        {
            "category":"Organizations",
            "subcategory":"Religious Organization",
            "type":"Services"
        }
    ],
    "sg:phone":"+1 814 342 6427",
    "sg:postcode":"16860",
    "sg:province":"PA",
    "sg:tags":[
        "church"
    ],
    "wof:name":"Jehovah's Witnesses",
    "wof:placetype":"venue"
},
  "geometry": {"coordinates":[-78.184541,40.949086],"type":"Point"}
}