{
  "type": "Feature",
  "properties": {
    "iso:country":"US",
    "sg:address":"600 E Union St",
    "sg:city":"Nanticoke",
    "sg:classifiers":[
        {
            "category":"Education",
            "subcategory":"School",
            "type":"Public Place"
        }
    ],
    "sg:phone":"+1   ",
    "sg:postcode":"18634",
    "sg:province":"PA",
    "wof:name":"Nanticoke Educational Center",
    "wof:placetype":"venue"
},
  "geometry": {"coordinates":[-75.988395,41.202569],"type":"Point"}
}