{
  "type": "Feature",
  "properties": {
    "iso:country":"US",
    "sg:address":"8 Northgate Plz",
    "sg:city":"Harmony",
    "sg:classifiers":[
        {
            "category":"Banks & Credit Unions",
            "subcategory":"Bank",
            "type":"Services"
        }
    ],
    "sg:phone":"+1 724 453 1100",
    "sg:postcode":"16037",
    "sg:province":"PA",
    "sg:tags":[
        "federal"
    ],
    "wof:name":"Freedom United Federal Cr Un",
    "wof:placetype":"venue"
},
  "geometry": {"coordinates":[-80.13566899999999,40.80388],"type":"Point"}
}