{
  "type": "Feature",
  "properties": {
    "iso:country":"US",
    "sg:address":"1043 Robeson St",
    "sg:city":"Reading",
    "sg:classifiers":[
        {
            "category":"Organizations",
            "subcategory":"Religious Organization",
            "type":"Services"
        }
    ],
    "sg:phone":"+1 610 736 0784",
    "sg:postcode":"19604",
    "sg:province":"PA",
    "sg:tags":[
        "church"
    ],
    "wof:name":"New Beginings Community Church",
    "wof:placetype":"venue"
},
  "geometry": {"coordinates":[-75.916704,40.35174],"type":"Point"}
}