{
  "type": "Feature",
  "properties": {
    "iso:country":"US",
    "sg:address":"422 Juniper St",
    "sg:city":"Quakertown",
    "sg:classifiers":[
        {
            "category":"Shopping",
            "type":"Retail Goods"
        }
    ],
    "sg:phone":"+1 215 529 7425",
    "sg:postcode":"18951",
    "sg:province":"PA",
    "sg:tags":[
        "equipment",
        "telephone",
        "supply"
    ],
    "wof:name":"Technical Sales & Svc",
    "wof:placetype":"venue"
},
  "geometry": {"coordinates":[-75.339219,40.439374],"type":"Point"}
}