{
  "type": "Feature",
  "properties": {
    "addr:full":"1520 Locust St Philadelphia PA 19102",
    "addr:housenumber":"1520",
    "addr:postcode":"19102",
    "addr:street":"Locust St",
    "iso:country":"US",
    "sg:address":"1520 Locust St",
    "sg:city":"Philadelphia",
    "sg:classifiers":[
        {
            "category":"Building & Trades",
            "subcategory":"Construction",
            "type":"Services"
        }
    ],
    "sg:phone":"+1 215 772 1203",
    "sg:postcode":"19102",
    "sg:province":"PA",
    "sg:tags":[
        "fire",
        "restoration",
        "damage"
    ],
    "wof:name":"Servpro Of Society Hill",
    "wof:placetype":"venue"
},
  "geometry": {"coordinates":[-75.16775,39.948678],"type":"Point"}
}