{
  "type": "Feature",
  "properties": {
    "addr:full":"21 S 5th St Philadelphia PA 19106",
    "addr:housenumber":"21",
    "addr:postcode":"19106",
    "addr:street":"S 5Th St",
    "iso:country":"US",
    "sg:address":"21 S 5th St",
    "sg:city":"Philadelphia",
    "sg:classifiers":[
        {
            "category":"Professional",
            "subcategory":"Lawyer & Legal Services",
            "type":"Services"
        }
    ],
    "sg:phone":"+1 215 829 1101",
    "sg:postcode":"19106",
    "sg:province":"PA",
    "wof:name":"Nasuti Carmen C Atty",
    "wof:placetype":"venue"
},
  "geometry": {"coordinates":[-75.14919999999999,39.949001],"type":"Point"}
}