{
  "type": "Feature",
  "properties": {
    "iso:country":"US",
    "sg:address":"321 Main St",
    "sg:city":"Pennsburg",
    "sg:classifiers":[
        {
            "category":"Food & Beverages",
            "subcategory":"Meat & Fish",
            "type":"Retail Goods"
        }
    ],
    "sg:phone":"+1 215 541 0577",
    "sg:postcode":"18073",
    "sg:province":"PA",
    "sg:tags":[
        "seafood"
    ],
    "wof:name":"Crababella Seafood",
    "wof:placetype":"venue"
},
  "geometry": {"coordinates":[-75.49695199999999,40.398241],"type":"Point"}
}