{
  "type": "Feature",
  "properties": {
    "addr:full":"3533 Locust Walk Philadelphia PA 19104",
    "addr:housenumber":"3533",
    "addr:postcode":"19104",
    "addr:street":"Locust Walk",
    "iso:country":"US",
    "sg:address":"3533 Locust Walk",
    "sg:city":"Philadelphia",
    "sg:classifiers":[
        {
            "category":"Professional",
            "subcategory":"Management & Consulting",
            "type":"Services"
        }
    ],
    "sg:phone":"+1   ",
    "sg:postcode":"19104",
    "sg:province":"PA",
    "sg:tags":[
        "public",
        "relations"
    ],
    "wof:name":"Alumni Relations",
    "wof:placetype":"venue"
},
  "geometry": {"coordinates":[-75.194581,39.952101],"type":"Point"}
}