{
  "type": "Feature",
  "properties": {
    "addr:full":"1640 N Hermitage Rd Hermitage PA 16148",
    "addr:housenumber":"1640",
    "addr:postcode":"16148",
    "addr:street":"N Hermitage Rd",
    "iso:country":"US",
    "sg:address":"1640 N Hermitage Rd",
    "sg:city":"Hermitage",
    "sg:classifiers":[
        {
            "category":"Recreation",
            "subcategory":"Amusement Park",
            "type":"Entertainment"
        }
    ],
    "sg:phone":"+1 724 962 1155",
    "sg:postcode":"16148",
    "sg:province":"PA",
    "sg:website":"www.recreationstation.net",
    "wof:name":"Recreation Station",
    "wof:placetype":"venue"
},
  "geometry": {"coordinates":[-80.451893,41.25657],"type":"Point"}
}