{
  "type": "Feature",
  "properties": {
    "iso:country":"US",
    "sg:address":"202 State Rte 309",
    "sg:city":"Coopersburg",
    "sg:classifiers":[
        {
            "category":"Health Services",
            "subcategory":"Health Practitioner",
            "type":"Services"
        }
    ],
    "sg:phone":"+1 610 282 2944",
    "sg:postcode":"18036",
    "sg:province":"PA",
    "sg:tags":[
        "psychologist"
    ],
    "sg:website":"www.integratedpsychology.com",
    "wof:name":"Stephen A Shechtman",
    "wof:placetype":"venue"
},
  "geometry": {"coordinates":[-75.385131,40.513074],"type":"Point"}
}