{
  "type": "Feature",
  "properties": {
    "iso:country":"US",
    "sg:address":"2251 Kohn Rd",
    "sg:city":"Harrisburg",
    "sg:classifiers":[
        {
            "category":"Building & Trades",
            "subcategory":"Plumbing",
            "type":"Services"
        }
    ],
    "sg:phone":"+1 717 343 1896",
    "sg:postcode":"17110",
    "sg:province":"PA",
    "sg:tags":[
        "plumbing",
        "contractor"
    ],
    "wof:name":"Wittle's Plumbing",
    "wof:placetype":"venue"
},
  "geometry": {"coordinates":[-76.854,40.30812],"type":"Point"}
}