{
  "type": "Feature",
  "properties": {
    "iso:country":"US",
    "sg:address":"23 W 4th St",
    "sg:city":"Williamsport",
    "sg:classifiers":[
        {
            "category":"Shopping",
            "type":"Retail Goods"
        }
    ],
    "sg:phone":"+1   ",
    "sg:postcode":"17701",
    "sg:province":"PA",
    "sg:tags":[
        "aids",
        "hearing"
    ],
    "wof:name":"Beltone Hring Svc Williamsport",
    "wof:placetype":"venue"
},
  "geometry": {"coordinates":[-77.001997,41.2423],"type":"Point"}
}