{
  "type": "Feature",
  "properties": {
    "addr:full":"10597 Path Valley Rd Fannettsburg PA 17221",
    "addr:housenumber":"10597",
    "addr:postcode":"17221",
    "addr:street":"Path Valley Rd",
    "iso:country":"US",
    "sg:address":"10597 Path Valley Rd",
    "sg:city":"Fannettsburg",
    "sg:classifiers":[
        {
            "category":"Building & Trades",
            "subcategory":"Plumbing",
            "type":"Services"
        }
    ],
    "sg:phone":"+1 717 349 2781",
    "sg:postcode":"17221",
    "sg:province":"PA",
    "sg:tags":[
        "plumbing",
        "contractor"
    ],
    "wof:name":"John P Junkin Plumbing & Htg",
    "wof:placetype":"venue"
},
  "geometry": {"coordinates":[-77.831746,40.062187],"type":"Point"}
}