{
  "type": "Feature",
  "properties": {
    "iso:country":"US",
    "sg:address":"325 E Wyoming Ave",
    "sg:city":"Philadelphia",
    "sg:classifiers":[
        {
            "category":"Communications",
            "type":"Services"
        }
    ],
    "sg:phone":"+1 215 455 1793",
    "sg:postcode":"19120",
    "sg:province":"PA",
    "wof:name":"Germosen Communications Inc",
    "wof:placetype":"venue"
},
  "geometry": {"coordinates":[-75.11965600000001,40.020975],"type":"Point"}
}