{
  "type": "Feature",
  "properties": {
    "iso:country":"US",
    "sg:address":"3428 N 11th St",
    "sg:city":"Philadelphia",
    "sg:classifiers":[
        {
            "category":"Building & Trades",
            "subcategory":"Locksmith",
            "type":"Services"
        }
    ],
    "sg:phone":"+1 267 773 5964",
    "sg:postcode":"19140",
    "sg:province":"PA",
    "sg:tags":[
        "key"
    ],
    "wof:name":"24 Hour A Locksmith",
    "wof:placetype":"venue"
},
  "geometry": {"coordinates":[-75.146843,40.00506],"type":"Point"}
}