{
  "type": "Feature",
  "properties": {
    "addr:full":"842 Gill Hall Rd Clairton PA 15025",
    "addr:housenumber":"842",
    "addr:postcode":"15025",
    "addr:street":"Gill Hall Rd",
    "iso:country":"US",
    "sg:address":"842 Gill Hall Rd",
    "sg:city":"Clairton",
    "sg:classifiers":[
        {
            "category":"Personal",
            "subcategory":"Beauty Salon",
            "type":"Services"
        }
    ],
    "sg:phone":"+1 412 655 3191",
    "sg:postcode":"15025",
    "sg:province":"PA",
    "wof:name":"Joseph's Beauty Shop",
    "wof:placetype":"venue"
},
  "geometry": {"coordinates":[-79.962042,40.300849],"type":"Point"}
}