{
  "type": "Feature",
  "properties": {
    "iso:country":"US",
    "sg:address":"641 Lincoln Hwy",
    "sg:city":"Coatesville",
    "sg:classifiers":[
        {
            "category":"Retail",
            "subcategory":"Laundry & Dry Cleaning",
            "type":"Services"
        }
    ],
    "sg:phone":"+1 610 384 4617",
    "sg:postcode":"19320",
    "sg:province":"PA",
    "sg:tags":[
        "cleaners"
    ],
    "wof:name":"Fluff & Fold",
    "wof:placetype":"venue"
},
  "geometry": {"coordinates":[-75.838313,39.980854],"type":"Point"}
}