{
  "type": "Feature",
  "properties": {
    "iso:country":"US",
    "sg:address":"575 Flora Ln",
    "sg:city":"York",
    "sg:classifiers":[
        {
            "category":"Travel",
            "subcategory":"Travel Agent",
            "type":"Entertainment"
        }
    ],
    "sg:phone":"+1   ",
    "sg:postcode":"17403",
    "sg:province":"PA",
    "sg:tags":[
        "agency"
    ],
    "wof:name":"Travel With Sandy",
    "wof:placetype":"venue"
},
  "geometry": {"coordinates":[-76.670278,39.900466],"type":"Point"}
}