{
  "type": "Feature",
  "properties": {
    "iso:country":"US",
    "sg:address":"54 Holland St",
    "sg:city":"Salunga",
    "sg:classifiers":[
        {
            "category":"Building & Trades",
            "subcategory":"Construction",
            "type":"Services"
        }
    ],
    "sg:phone":"+1 717 898 2321",
    "sg:postcode":"17538",
    "sg:province":"PA",
    "sg:tags":[
        "boring",
        "drilling",
        "contractor"
    ],
    "wof:name":"Myers Brother Drilling Contrs",
    "wof:placetype":"venue"
},
  "geometry": {"coordinates":[-76.42948699999999,40.103487],"type":"Point"}
}