{
  "type": "Feature",
  "properties": {
    "addr:full":"10 Judicial St Pittsburgh PA 15211",
    "addr:housenumber":"10",
    "addr:postcode":"15211",
    "addr:street":"Judicial St",
    "iso:country":"US",
    "sg:address":"10 Judicial St",
    "sg:city":"Pittsburgh",
    "sg:classifiers":[
        {
            "category":"Building & Trades",
            "subcategory":"Construction",
            "type":"Services"
        }
    ],
    "sg:phone":"+1   ",
    "sg:postcode":"15211",
    "sg:province":"PA",
    "sg:tags":[
        "hanging",
        "contractor"
    ],
    "wof:name":"Hanna Painting",
    "wof:placetype":"venue"
},
  "geometry": {"coordinates":[-80.000006,40.42632],"type":"Point"}
}