{
  "type": "Feature",
  "properties": {
    "addr:full":"212 Fairhill St Willow Grove PA 19090",
    "addr:housenumber":"212",
    "addr:postcode":"19090",
    "addr:street":"Fairhill St",
    "iso:country":"US",
    "sg:address":"212 Fairhill St",
    "sg:city":"Willow Grove",
    "sg:classifiers":[
        {
            "category":"Building & Trades",
            "subcategory":"Landscaping Services",
            "type":"Services"
        }
    ],
    "sg:phone":"+1 215 659 4660",
    "sg:postcode":"19090",
    "sg:province":"PA",
    "sg:tags":[
        "landscape",
        "contractor"
    ],
    "wof:name":"Absoloot Organic Lawn Care",
    "wof:placetype":"venue"
},
  "geometry": {"coordinates":[-75.11361599999999,40.151153],"type":"Point"}
}