{
  "type": "Feature",
  "properties": {
    "iso:country":"US",
    "sg:address":"75 Mobile Dr",
    "sg:city":"Thomasville",
    "sg:classifiers":[
        {
            "category":"Building & Trades",
            "subcategory":"Construction",
            "type":"Services"
        }
    ],
    "sg:phone":"+1   ",
    "sg:postcode":"17364",
    "sg:province":"PA",
    "sg:tags":[
        "house"
    ],
    "wof:name":"Paulus Wilmer Builders",
    "wof:placetype":"venue"
},
  "geometry": {"coordinates":[-76.875704,39.924004],"type":"Point"}
}