{
  "type": "Feature",
  "properties": {
    "addr:full":"1400 W 9th St Chester PA 19013",
    "addr:housenumber":"1400",
    "addr:postcode":"19013",
    "addr:street":"W 9Th St",
    "iso:country":"US",
    "sg:address":"1400 W 9th St",
    "sg:city":"Chester",
    "sg:classifiers":[
        {
            "category":"Manufacturing",
            "subcategory":"Glass & Minerals",
            "type":"Manufacturing & Wholesale Goods"
        }
    ],
    "sg:phone":"+1   ",
    "sg:postcode":"19013",
    "sg:province":"PA",
    "sg:tags":[
        "concrete",
        "product",
        "establishment",
        "mfg"
    ],
    "wof:name":"Bradbury Vault",
    "wof:placetype":"venue"
},
  "geometry": {"coordinates":[-75.381422,39.843785],"type":"Point"}
}