{
  "type": "Feature",
  "properties": {
    "addr:full":"602 Poplar St Bangor PA 18013",
    "addr:housenumber":"602",
    "addr:postcode":"18013",
    "addr:street":"Poplar St",
    "iso:country":"US",
    "sg:address":"602 Poplar St",
    "sg:city":"Bangor",
    "sg:classifiers":[
        {
            "category":"Professional",
            "type":"Services"
        }
    ],
    "sg:phone":"+1   ",
    "sg:postcode":"18013",
    "sg:province":"PA",
    "wof:name":"Grand Chapter of Pennsylv",
    "wof:placetype":"venue"
},
  "geometry": {"coordinates":[-75.218941,40.882037],"type":"Point"}
}