{
  "type": "Feature",
  "properties": {
    "iso:country":"US",
    "sg:address":"909 Itaska St",
    "sg:city":"Bethlehem",
    "sg:classifiers":[
        {
            "category":"Organizations",
            "subcategory":"Community Association",
            "type":"Services"
        }
    ],
    "sg:phone":"+1   ",
    "sg:postcode":"18015",
    "sg:province":"PA",
    "wof:name":"Portuguese Continental Un",
    "wof:placetype":"venue"
},
  "geometry": {"coordinates":[-75.390013,40.60394],"type":"Point"}
}