{
  "type": "Feature",
  "properties": {
    "iso:country":"US",
    "sg:address":"15 W State St",
    "sg:city":"Avondale",
    "sg:classifiers":[
        {
            "category":"Professional",
            "subcategory":"Lawyer & Legal Services",
            "type":"Services"
        }
    ],
    "sg:phone":"+1 610 268 3323",
    "sg:postcode":"19311",
    "sg:province":"PA",
    "sg:tags":[
        "attorney",
        "law",
        "family",
        "duo",
        "divorce",
        "criminal",
        "dwi"
    ],
    "wof:name":"Furlong Christopher G Attorney",
    "wof:placetype":"venue"
},
  "geometry": {"coordinates":[-75.78360000000001,39.824501],"type":"Point"}
}