{
  "type": "Feature",
  "properties": {
    "addr:full":"2504 Perkiomen Ave Reading PA 19606",
    "addr:housenumber":"2504",
    "addr:postcode":"19606",
    "addr:street":"Perkiomen Ave",
    "iso:country":"US",
    "sg:address":"2504 Perkiomen Ave",
    "sg:city":"Reading",
    "sg:classifiers":[
        {
            "category":"Health Services",
            "subcategory":"Optometrist",
            "type":"Services"
        }
    ],
    "sg:phone":"+1 610 779 9636",
    "sg:postcode":"19606",
    "sg:province":"PA",
    "wof:name":"Family Eye Care",
    "wof:placetype":"venue"
},
  "geometry": {"coordinates":[-75.88793699999999,40.327723],"type":"Point"}
}