{
  "type": "Feature",
  "properties": {
    "iso:country":"US",
    "sg:address":"2539 N 16th St",
    "sg:city":"Philadelphia",
    "sg:classifiers":[
        {
            "category":"Education",
            "subcategory":"School",
            "type":"Public Place"
        }
    ],
    "sg:phone":"+1 215 227 4434",
    "sg:postcode":"19132",
    "sg:province":"PA",
    "sg:tags":[
        "high",
        "middle",
        "elementary"
    ],
    "wof:name":"Philadelphia School District",
    "wof:placetype":"venue"
},
  "geometry": {"coordinates":[-75.15810500000001,39.992182],"type":"Point"}
}