{
  "type": "Feature",
  "properties": {
    "iso:country":"US",
    "sg:address":"697 River Rd",
    "sg:city":"Lewisburg",
    "sg:classifiers":[
        {
            "category":"Utilities",
            "subcategory":"Sewage",
            "type":"Services"
        }
    ],
    "sg:phone":"+1 570 524 7069",
    "sg:postcode":"17837",
    "sg:province":"PA",
    "sg:tags":[
        "disposal",
        "system"
    ],
    "wof:name":"City Of Lewisburg",
    "wof:placetype":"venue"
},
  "geometry": {"coordinates":[-76.874342,40.946684],"type":"Point"}
}