{
  "type": "Feature",
  "properties": {
    "addr:full":"1207 N 60th St Philadelphia PA 19151",
    "addr:housenumber":"1207",
    "addr:postcode":"19151",
    "addr:street":"N 60Th St",
    "iso:country":"US",
    "sg:address":"1207 N 60th St",
    "sg:city":"Philadelphia",
    "sg:classifiers":[
        {
            "category":"Building & Trades",
            "subcategory":"Locksmith",
            "type":"Services"
        }
    ],
    "sg:phone":"+1 267 299 1208",
    "sg:postcode":"19151",
    "sg:province":"PA",
    "sg:tags":[
        "key"
    ],
    "wof:name":"Locksmith",
    "wof:placetype":"venue"
},
  "geometry": {"coordinates":[-75.23901499999999,39.970417],"type":"Point"}
}