{
  "type": "Feature",
  "properties": {
    "addr:full":"921 Rentzel Rd Biglerville PA 17307",
    "addr:housenumber":"921",
    "addr:postcode":"17307",
    "addr:street":"Rentzel Rd",
    "iso:country":"US",
    "sg:address":"921 Rentzel Rd",
    "sg:city":"Biglerville",
    "sg:classifiers":[
        {
            "category":"Bars & Pubs",
            "type":"Food & Drink"
        }
    ],
    "sg:phone":"+1 717 677 7696",
    "sg:postcode":"17307",
    "sg:province":"PA",
    "sg:tags":[
        "tavern"
    ],
    "wof:name":"Hamilton's Tavern",
    "wof:placetype":"venue"
},
  "geometry": {"coordinates":[-77.205215,39.918572],"type":"Point"}
}