{
  "type": "Feature",
  "properties": {
    "iso:country":"US",
    "sg:address":"135 S 19th St",
    "sg:city":"Philadelphia",
    "sg:classifiers":[
        {
            "category":"Health Services",
            "subcategory":"Hospital",
            "type":"Services"
        }
    ],
    "sg:phone":"+1 215 483 4030",
    "sg:postcode":"19103",
    "sg:province":"PA",
    "sg:tags":[
        "mental"
    ],
    "wof:name":"Robert Schoenholtz",
    "wof:placetype":"venue"
},
  "geometry": {"coordinates":[-75.172164,39.950353],"type":"Point"}
}