{
  "type": "Feature",
  "properties": {
    "addr:full":"361 Sarhelm Rd Harrisburg PA 17112",
    "addr:housenumber":"361",
    "addr:postcode":"17112",
    "addr:street":"Sarhelm Rd",
    "iso:country":"US",
    "sg:address":"361 Sarhelm Rd",
    "sg:city":"Harrisburg",
    "sg:classifiers":[
        {
            "category":"Building & Trades",
            "subcategory":"Construction",
            "type":"Services"
        }
    ],
    "sg:phone":"+1   ",
    "sg:postcode":"17112",
    "sg:province":"PA",
    "sg:tags":[
        "hanging",
        "contractor"
    ],
    "wof:name":"Ken Fultz Painting",
    "wof:placetype":"venue"
},
  "geometry": {"coordinates":[-76.754716,40.322398],"type":"Point"}
}