{
  "type": "Feature",
  "properties": {
    "addr:full":"4 Allison Rd Oreland PA 19075",
    "addr:housenumber":"4",
    "addr:postcode":"19075",
    "addr:street":"Allison Rd",
    "iso:country":"US",
    "sg:address":"4 Allison Rd",
    "sg:city":"Oreland",
    "sg:classifiers":[
        {
            "category":"Restaurant",
            "type":"Food & Drink"
        }
    ],
    "sg:phone":"+1 215 886 2731",
    "sg:postcode":"19075",
    "sg:province":"PA",
    "sg:tags":[
        "eating"
    ],
    "wof:name":"Oreland Pizza",
    "wof:placetype":"venue"
},
  "geometry": {"coordinates":[-75.184426,40.116214],"type":"Point"}
}