{
  "type": "Feature",
  "properties": {
    "iso:country":"US",
    "sg:address":"509 S 7th St",
    "sg:city":"Shamokin",
    "sg:classifiers":[
        {
            "category":"Personal",
            "subcategory":"Beauty Salon",
            "type":"Services"
        }
    ],
    "sg:phone":"+1   ",
    "sg:postcode":"17872",
    "sg:province":"PA",
    "sg:tags":[
        "shop"
    ],
    "wof:name":"Rudies Beauty Shop",
    "wof:placetype":"venue"
},
  "geometry": {"coordinates":[-76.556725,40.78264],"type":"Point"}
}