{
  "type": "Feature",
  "properties": {
    "iso:country":"US",
    "sg:address":"345 Southpointe Blvd",
    "sg:city":"Canonsburg",
    "sg:classifiers":[
        {
            "category":"Professional",
            "type":"Services"
        }
    ],
    "sg:phone":"+1   ",
    "sg:postcode":"15317",
    "sg:province":"PA",
    "wof:name":"Microsignal Corp",
    "wof:placetype":"venue"
},
  "geometry": {"coordinates":[-80.17263800000001,40.296448],"type":"Point"}
}