{
  "type": "Feature",
  "properties": {
    "iso:country":"US",
    "sg:address":"142 Mount Zion Rd",
    "sg:city":"Somerset",
    "sg:classifiers":[
        {
            "category":"Building & Trades",
            "subcategory":"Cleaning & Sanitation",
            "type":"Services"
        }
    ],
    "sg:phone":"+1 814 445 8063",
    "sg:postcode":"15501",
    "sg:province":"PA",
    "sg:tags":[
        "fireplace",
        "chimney"
    ],
    "wof:name":"Fitzgerald Chimney Cleaning",
    "wof:placetype":"venue"
},
  "geometry": {"coordinates":[-79.21715,40.043845],"type":"Point"}
}