{
  "type": "Feature",
  "properties": {
    "iso:country":"US",
    "sg:address":"111 John Roberts Thomas Dr",
    "sg:city":"Exton",
    "sg:classifiers":[
        {
            "category":"Building & Trades",
            "subcategory":"Equipment Rental",
            "type":"Services"
        }
    ],
    "sg:phone":"+1 610 594 0900",
    "sg:postcode":"19341",
    "sg:province":"PA",
    "sg:tags":[
        "leasing"
    ],
    "sg:website":"www.smartbusinesscredit.com",
    "wof:name":"Smart Leasing Inc",
    "wof:placetype":"venue"
},
  "geometry": {"coordinates":[-75.64184899999999,40.027246],"type":"Point"}
}