{
  "type": "Feature",
  "properties": {
    "iso:country":"US",
    "sg:address":"964 Michelle Rd",
    "sg:city":"New Kensington",
    "sg:classifiers":[
        {
            "category":"Wholesale",
            "subcategory":"Chemicals & Plastics",
            "type":"Manufacturing & Wholesale Goods"
        }
    ],
    "sg:phone":"+1   ",
    "sg:postcode":"15068",
    "sg:province":"PA",
    "wof:name":"Tc Sales",
    "wof:placetype":"venue"
},
  "geometry": {"coordinates":[-79.73697199999999,40.548602],"type":"Point"}
}