{
  "type": "Feature",
  "properties": {
    "addr:full":"445 Marpit Dr Broomall PA 19008",
    "addr:housenumber":"445",
    "addr:postcode":"19008",
    "addr:street":"Marpit Dr",
    "iso:country":"US",
    "sg:address":"445 Marpit Dr",
    "sg:city":"Broomall",
    "sg:classifiers":[
        {
            "category":"Utilities",
            "subcategory":"Refuse",
            "type":"Services"
        }
    ],
    "sg:phone":"+1 610 364 2114",
    "sg:postcode":"19008",
    "sg:province":"PA",
    "sg:tags":[
        "system"
    ],
    "wof:name":"Harmon Recycling Inc",
    "wof:placetype":"venue"
},
  "geometry": {"coordinates":[-75.33994300000001,39.956976],"type":"Point"}
}