{
  "type": "Feature",
  "properties": {
    "iso:country":"US",
    "sg:address":"12418 Dunks Ferry Rd",
    "sg:city":"Philadelphia",
    "sg:classifiers":[
        {
            "category":"Building & Trades",
            "subcategory":"Plumbing",
            "type":"Services"
        }
    ],
    "sg:phone":"+1   ",
    "sg:postcode":"19154",
    "sg:province":"PA",
    "sg:tags":[
        "plumbing",
        "heating",
        "contractor"
    ],
    "wof:name":"Howard Gene Plumbing & Heating",
    "wof:placetype":"venue"
},
  "geometry": {"coordinates":[-74.97547900000001,40.100664],"type":"Point"}
}