{
  "type": "Feature",
  "properties": {
    "addr:full":"1723 Northampton St Easton PA 18042",
    "addr:housenumber":"1723",
    "addr:postcode":"18042",
    "addr:street":"Northampton St",
    "iso:country":"US",
    "sg:address":"1723 Northampton St",
    "sg:city":"Easton",
    "sg:classifiers":[
        {
            "category":"Health Services",
            "subcategory":"Doctor",
            "type":"Services"
        }
    ],
    "sg:phone":"+1 610 253 7211",
    "sg:postcode":"18042",
    "sg:province":"PA",
    "sg:tags":[
        "physician",
        "medical",
        "surgeon"
    ],
    "wof:name":"Eric Schoeppner MD PC",
    "wof:placetype":"venue"
},
  "geometry": {"coordinates":[-75.237105,40.689706],"type":"Point"}
}