{
  "type": "Feature",
  "properties": {
    "addr:full":"4804 Delbrook Rd Mechanicsburg PA 17050",
    "addr:housenumber":"4804",
    "addr:postcode":"17050",
    "addr:street":"Delbrook Rd",
    "iso:country":"US",
    "sg:address":"4804 Delbrook Rd",
    "sg:city":"Mechanicsburg",
    "sg:classifiers":[
        {
            "category":"Real Estate",
            "subcategory":"Real Estate Operator",
            "type":"Services"
        }
    ],
    "sg:phone":"+1   ",
    "sg:postcode":"17050",
    "sg:province":"PA",
    "sg:tags":[
        "building",
        "ope",
        "apartment",
        "nonresidential"
    ],
    "wof:name":"William & Robert Schultz",
    "wof:placetype":"venue"
},
  "geometry": {"coordinates":[-76.96796999999999,40.22978],"type":"Point"}
}