{
  "type": "Feature",
  "properties": {
    "iso:country":"US",
    "sg:address":"3405 W Chester Pike",
    "sg:city":"Newtown Square",
    "sg:classifiers":[
        {
            "category":"Real Estate",
            "subcategory":"Real Estate Operator",
            "type":"Services"
        }
    ],
    "sg:phone":"+1 610 356 7583",
    "sg:postcode":"19073",
    "sg:province":"PA",
    "sg:tags":[
        "building",
        "apartment"
    ],
    "wof:name":"Woodbrook House Apartments",
    "wof:placetype":"venue"
},
  "geometry": {"coordinates":[-75.389331,39.984528],"type":"Point"}
}