{
  "type": "Feature",
  "properties": {
    "iso:country":"US",
    "sg:address":"2605 Broad Ave",
    "sg:city":"Altoona",
    "sg:classifiers":[
        {
            "category":"Health Services",
            "subcategory":"Nursing And Care Facility",
            "type":"Services"
        }
    ],
    "sg:phone":"+1   ",
    "sg:postcode":"16601",
    "sg:province":"PA",
    "wof:name":"Skills of Central Pennsylvania",
    "wof:placetype":"venue"
},
  "geometry": {"coordinates":[-78.412873,40.501636],"type":"Point"}
}