{
  "type": "Feature",
  "properties": {
    "iso:country":"US",
    "sg:address":"3987 Monroeville Blvd",
    "sg:city":"Monroeville",
    "sg:classifiers":[
        {
            "category":"Home & Garden",
            "subcategory":"Household Appliances",
            "type":"Retail Goods"
        }
    ],
    "sg:phone":"+1   ",
    "sg:postcode":"15146",
    "sg:province":"PA",
    "wof:name":"Atkinson & Associates",
    "wof:placetype":"venue"
},
  "geometry": {"coordinates":[-79.774913,40.437103],"type":"Point"}
}