{
  "type": "Feature",
  "properties": {
    "iso:country":"US",
    "sg:address":"850 Cambria St",
    "sg:city":"Ebensburg",
    "sg:classifiers":[
        {
            "category":"Retail",
            "subcategory":"Auto Repair",
            "type":"Services"
        }
    ],
    "sg:phone":"+1 814 886 7656",
    "sg:postcode":"15946",
    "sg:province":"PA",
    "sg:tags":[
        "repairing",
        "automobile"
    ],
    "wof:name":"Gregg Brother's Garage",
    "wof:placetype":"venue"
},
  "geometry": {"coordinates":[-78.67425,40.382382],"type":"Point"}
}