{
  "type": "Feature",
  "properties": {
    "iso:country":"US",
    "sg:address":"1110 Fishing Creek Rd",
    "sg:city":"Roulette",
    "sg:classifiers":[
        {
            "category":"Manufacturing",
            "subcategory":"Lumber",
            "type":"Manufacturing & Wholesale Goods"
        }
    ],
    "sg:phone":"+1 814 544 7350",
    "sg:postcode":"16746",
    "sg:province":"PA",
    "sg:tags":[
        "logging"
    ],
    "wof:name":"Cornelius Lumber Logging",
    "wof:placetype":"venue"
},
  "geometry": {"coordinates":[-78.136639,41.80066],"type":"Point"}
}