{
  "type": "Feature",
  "properties": {
    "addr:full":"1435 Easton Rd Riegelsville PA 18077",
    "addr:housenumber":"1435",
    "addr:postcode":"18077",
    "addr:street":"Easton Rd",
    "iso:country":"US",
    "sg:address":"1435 Easton Rd",
    "sg:city":"Riegelsville",
    "sg:classifiers":[
        {
            "category":"Shopping",
            "subcategory":"Used Merchandise",
            "type":"Retail Goods"
        }
    ],
    "sg:phone":"+1 610 749 0230",
    "sg:postcode":"18077",
    "sg:province":"PA",
    "sg:tags":[
        "antique"
    ],
    "wof:name":"Antique Haven",
    "wof:placetype":"venue"
},
  "geometry": {"coordinates":[-75.19689700000001,40.58179],"type":"Point"}
}