{
  "type": "Feature",
  "properties": {
    "addr:full":"204 Wallingford Ave Wallingford PA 19086",
    "addr:housenumber":"204",
    "addr:postcode":"19086",
    "addr:street":"Wallingford Ave",
    "iso:country":"US",
    "sg:address":"204 Wallingford Ave",
    "sg:city":"Wallingford",
    "sg:classifiers":[
        {
            "category":"Professional",
            "type":"Services"
        }
    ],
    "sg:phone":"+1   ",
    "sg:postcode":"19086",
    "sg:province":"PA",
    "wof:name":"Marnic Inc",
    "wof:placetype":"venue"
},
  "geometry": {"coordinates":[-75.38014800000001,39.907561],"type":"Point"}
}