{
  "type": "Feature",
  "properties": {
    "addr:full":"18 W 4th St Williamsport PA 17701",
    "addr:housenumber":"18",
    "addr:postcode":"17701",
    "addr:street":"W 4Th St",
    "iso:country":"US",
    "sg:address":"18 W 4th St",
    "sg:city":"Williamsport",
    "sg:classifiers":[
        {
            "category":"Shopping",
            "subcategory":"Photographic Equipment",
            "type":"Retail Goods"
        }
    ],
    "sg:phone":"+1 570 326 0551",
    "sg:postcode":"17701",
    "sg:province":"PA",
    "sg:tags":[
        "supply"
    ],
    "wof:name":"Hoyer's Photo Supply Inc",
    "wof:placetype":"venue"
},
  "geometry": {"coordinates":[-77.002397,41.242256],"type":"Point"}
}