{
  "type": "Feature",
  "properties": {
    "iso:country":"US",
    "sg:address":"12 E Market St",
    "sg:city":"Bethlehem",
    "sg:classifiers":[
        {
            "category":"Building & Trades",
            "subcategory":"Construction",
            "type":"Services"
        }
    ],
    "sg:phone":"+1 610 868 9680",
    "sg:postcode":"18018",
    "sg:province":"PA",
    "sg:tags":[
        "designer"
    ],
    "wof:name":"Richard H Penske",
    "wof:placetype":"venue"
},
  "geometry": {"coordinates":[-75.37796899999999,40.620626],"type":"Point"}
}