{
  "type": "Feature",
  "properties": {
    "iso:country":"US",
    "sg:address":"2415 W Pike St",
    "sg:city":"Houston",
    "sg:classifiers":[
        {
            "category":"Manufacturing",
            "subcategory":"Metals",
            "type":"Manufacturing & Wholesale Goods"
        }
    ],
    "sg:phone":"+1 724 745 4507",
    "sg:postcode":"15342",
    "sg:province":"PA",
    "sg:tags":[
        "machine",
        "shop",
        "fabrication",
        "structural"
    ],
    "wof:name":"Mc Millen Welding Inc",
    "wof:placetype":"venue"
},
  "geometry": {"coordinates":[-80.217451,40.225652],"type":"Point"}
}