{
  "type": "Feature",
  "properties": {
    "addr:full":"33 Linwood Ave Bradford PA 16701",
    "addr:housenumber":"33",
    "addr:postcode":"16701",
    "addr:street":"Linwood Ave",
    "iso:country":"US",
    "sg:address":"33 Linwood Ave",
    "sg:city":"Bradford",
    "sg:classifiers":[
        {
            "category":"Building & Trades",
            "subcategory":"Construction",
            "type":"Services"
        }
    ],
    "sg:phone":"+1   ",
    "sg:postcode":"16701",
    "sg:province":"PA",
    "sg:tags":[
        "house"
    ],
    "wof:name":"Add On Construction",
    "wof:placetype":"venue"
},
  "geometry": {"coordinates":[-78.626158,41.97024],"type":"Point"}
}