{
  "type": "Feature",
  "properties": {
    "iso:country":"US",
    "sg:address":"270 Bodley Rd",
    "sg:city":"Aston",
    "sg:classifiers":[
        {
            "category":"Building & Trades",
            "subcategory":"Plumbing",
            "type":"Services"
        }
    ],
    "sg:phone":"+1 610 459 7727",
    "sg:postcode":"19014",
    "sg:province":"PA",
    "sg:tags":[
        "contractor"
    ],
    "sg:website":"www.fergusonmccann.com",
    "wof:name":"Ferguson & Mc Cann Contractors",
    "wof:placetype":"venue"
},
  "geometry": {"coordinates":[-75.464883,39.878522],"type":"Point"}
}