{
  "type": "Feature",
  "properties": {
    "addr:full":"105 S Oak St Mt Carmel PA 17851",
    "addr:housenumber":"105",
    "addr:postcode":"17851",
    "addr:street":"S Oak St",
    "iso:country":"US",
    "sg:address":"105 S Oak St",
    "sg:city":"Mt Carmel",
    "sg:classifiers":[
        {
            "category":"Professional",
            "subcategory":"Lawyer & Legal Services",
            "type":"Services"
        }
    ],
    "sg:phone":"+1 570 339 2558",
    "sg:postcode":"17851",
    "sg:province":"PA",
    "sg:tags":[
        "attorney"
    ],
    "wof:name":"Smoker & Gard",
    "wof:placetype":"venue"
},
  "geometry": {"coordinates":[-76.412806,40.795782],"type":"Point"}
}