{
  "type": "Feature",
  "properties": {
    "addr:full":"31 Mulberry Ln Levittown PA 19054",
    "addr:housenumber":"31",
    "addr:postcode":"19054",
    "addr:street":"Mulberry Ln",
    "iso:country":"US",
    "sg:address":"31 Mulberry Ln",
    "sg:city":"Levittown",
    "sg:classifiers":[
        {
            "category":"Building & Trades",
            "subcategory":"Construction",
            "type":"Services"
        }
    ],
    "sg:phone":"+1 215 547 5467",
    "sg:postcode":"19054",
    "sg:province":"PA",
    "sg:tags":[
        "contractor"
    ],
    "wof:name":"William R Leonard",
    "wof:placetype":"venue"
},
  "geometry": {"coordinates":[-74.838953,40.165503],"type":"Point"}
}