{
  "type": "Feature",
  "properties": {
    "iso:country":"US",
    "sg:address":"328 6th St",
    "sg:city":"Mckeesport",
    "sg:classifiers":[
        {
            "category":"Food & Beverages",
            "subcategory":"Meat & Fish",
            "type":"Retail Goods"
        }
    ],
    "sg:phone":"+1 412 672 2496",
    "sg:postcode":"15132",
    "sg:province":"PA",
    "sg:tags":[
        "seafood"
    ],
    "wof:name":"H & H Fish Market",
    "wof:placetype":"venue"
},
  "geometry": {"coordinates":[-79.86306,40.350029],"type":"Point"}
}