{
  "type": "Feature",
  "properties": {
    "iso:country":"US",
    "sg:address":"3331 N Marston St",
    "sg:city":"Philadelphia",
    "sg:classifiers":[
        {
            "category":"Health Services",
            "subcategory":"Health Practitioner",
            "type":"Services"
        },
        {
            "category":"Social Services",
            "subcategory":"Adult Care",
            "type":"Services"
        }
    ],
    "sg:phone":"+1 877 435 0911",
    "sg:postcode":"19129",
    "sg:province":"PA",
    "sg:tags":[
        "addiction",
        "abuse",
        "crisis",
        "drug",
        "intervention"
    ],
    "sg:website":"http://www.NADAI.us",
    "wof:name":"Nadai",
    "wof:placetype":"venue"
},
  "geometry": {"coordinates":[-75.173401,40.006962],"type":"Point"}
}