{
  "type": "Feature",
  "properties": {
    "iso:country":"US",
    "sg:address":"14051 State Rte 993",
    "sg:city":"Trafford",
    "sg:classifiers":[
        {
            "category":"Organizations",
            "subcategory":"Religious Organization",
            "type":"Services"
        }
    ],
    "sg:phone":"+1 412 372 8514",
    "sg:postcode":"15085",
    "sg:province":"PA",
    "sg:tags":[
        "church"
    ],
    "wof:name":"Jehovah's Witnesses Trafford",
    "wof:placetype":"venue"
},
  "geometry": {"coordinates":[-79.74939999999999,40.36978],"type":"Point"}
}