{
  "type": "Feature",
  "properties": {
    "iso:country":"US",
    "sg:address":"209 W Main St",
    "sg:city":"Shiremanstown",
    "sg:classifiers":[
        {
            "category":"Personal",
            "subcategory":"Beauty Salon",
            "type":"Services"
        }
    ],
    "sg:phone":"+1 717 761 5519",
    "sg:postcode":"17011",
    "sg:province":"PA",
    "wof:name":"Hair Care Ctr",
    "wof:placetype":"venue"
},
  "geometry": {"coordinates":[-76.961777,40.221644],"type":"Point"}
}