{
  "type": "Feature",
  "properties": {
    "iso:country":"US",
    "sg:address":"69 Florence Ave",
    "sg:city":"Sharon Hill",
    "sg:classifiers":[
        {
            "category":"Building & Trades",
            "subcategory":"Pest Control",
            "type":"Services"
        }
    ],
    "sg:phone":"+1 610 494 9500",
    "sg:postcode":"19079",
    "sg:province":"PA",
    "wof:name":"Derosa Exterminating Co",
    "wof:placetype":"venue"
},
  "geometry": {"coordinates":[-75.275622,39.908315],"type":"Point"}
}