{
  "type": "Feature",
  "properties": {
    "iso:country":"US",
    "sg:address":"7746 Burkholder Rd",
    "sg:city":"Waynesboro",
    "sg:classifiers":[
        {
            "category":"Building & Trades",
            "subcategory":"Construction",
            "type":"Services"
        }
    ],
    "sg:phone":"+1   ",
    "sg:postcode":"17268",
    "sg:province":"PA",
    "sg:tags":[
        "new",
        "residential"
    ],
    "wof:name":"Roland Hess Building Contr",
    "wof:placetype":"venue"
},
  "geometry": {"coordinates":[-77.59927999999999,39.820941],"type":"Point"}
}