{
  "type": "Feature",
  "properties": {
    "addr:full":"163 S Meadow Ln Hummelstown PA 17036",
    "addr:housenumber":"163",
    "addr:postcode":"17036",
    "addr:street":"S Meadow Ln",
    "iso:country":"US",
    "sg:address":"163 S Meadow Ln",
    "sg:city":"Hummelstown",
    "sg:classifiers":[
        {
            "category":"Manufacturing",
            "subcategory":"Signs",
            "type":"Manufacturing & Wholesale Goods"
        },
        {
            "category":"Professional",
            "subcategory":"Business Services",
            "type":"Services"
        }
    ],
    "sg:phone":"+1 717 469 7716",
    "sg:postcode":"17036",
    "sg:province":"PA",
    "sg:website":"www.stonergraphix.com",
    "wof:name":"Stoner Graphix Inc",
    "wof:placetype":"venue"
},
  "geometry": {"coordinates":[-76.68283599999999,40.351801],"type":"Point"}
}