{
  "type": "Feature",
  "properties": {
    "iso:country":"US",
    "sg:address":"5031 W Ridge Rd",
    "sg:city":"Erie",
    "sg:classifiers":[
        {
            "category":"Organizations",
            "subcategory":"Religious Organization",
            "type":"Services"
        }
    ],
    "sg:phone":"+1 814 838 4100",
    "sg:postcode":"16506",
    "sg:province":"PA",
    "sg:tags":[
        "monastery",
        "convent"
    ],
    "sg:website":"www.ssjerie.org",
    "wof:name":"Sisters Of St Joseph",
    "wof:placetype":"venue"
},
  "geometry": {"coordinates":[-80.19054199999999,42.067194],"type":"Point"}
}