{
  "type": "Feature",
  "properties": {
    "addr:full":"4125 Woerner Ave Levittown PA 19057",
    "addr:housenumber":"4125",
    "addr:postcode":"19057",
    "addr:street":"Woerner Ave",
    "iso:country":"US",
    "sg:address":"4125 Woerner Ave",
    "sg:city":"Levittown",
    "sg:classifiers":[
        {
            "category":"Personal",
            "subcategory":"Barber",
            "type":"Services"
        }
    ],
    "sg:phone":"+1 267 914 0479",
    "sg:postcode":"19057",
    "sg:province":"PA",
    "wof:name":"C Webb's Barbershop",
    "wof:placetype":"venue"
},
  "geometry": {"coordinates":[-74.858615,40.151503],"type":"Point"}
}