{
  "type": "Feature",
  "properties": {
    "iso:country":"US",
    "sg:address":"102 East Montgomery Avenue",
    "sg:city":"Ardmore",
    "sg:classifiers":[
        {
            "category":"Shopping",
            "subcategory":"Clothing, Apparel, & Fashions",
            "type":"Retail Goods"
        }
    ],
    "sg:phone":"+1 610 642 3888",
    "sg:postcode":"19003",
    "sg:province":"PA",
    "sg:tags":[
        "clothing",
        "sale",
        "women's",
        "wear",
        "apparel",
        "rental",
        "store",
        "formal"
    ],
    "sg:website":"http://www.bijoubridal.com",
    "wof:name":"Bijou Bridal & Special Occasion Ardmore",
    "wof:placetype":"venue"
},
  "geometry": {"coordinates":[-75.286631,40.00926],"type":"Point"}
}