{
  "type": "Feature",
  "properties": {
    "iso:country":"US",
    "sg:address":"20006 Rte 19",
    "sg:city":"Cranberry Twp",
    "sg:classifiers":[
        {
            "category":"Autos & Motor Vehicles",
            "subcategory":"Fuel & Gas Station",
            "type":"Retail Goods"
        }
    ],
    "sg:phone":"+1 724 776 7577",
    "sg:postcode":"16066",
    "sg:province":"PA",
    "sg:tags":[
        "oil"
    ],
    "wof:name":"J G Svc Stations-Cranberry",
    "wof:placetype":"venue"
},
  "geometry": {"coordinates":[-80.098637,40.674321],"type":"Point"}
}