{
  "type": "Feature",
  "properties": {
    "addr:full":"149 W Sherwood Dr Oxford PA 19363",
    "addr:housenumber":"149",
    "addr:postcode":"19363",
    "addr:street":"W Sherwood Dr",
    "iso:country":"US",
    "sg:address":"149 W Sherwood Dr",
    "sg:city":"Oxford",
    "sg:classifiers":[
        {
            "category":"Retail",
            "subcategory":"Repair Shop",
            "type":"Services"
        }
    ],
    "sg:phone":"+1 610 932 6715",
    "sg:postcode":"19363",
    "sg:province":"PA",
    "sg:tags":[
        "scooter",
        "motorcycle",
        "motor"
    ],
    "wof:name":"Moto-Man Racing",
    "wof:placetype":"venue"
},
  "geometry": {"coordinates":[-75.974433,39.744919],"type":"Point"}
}