{
  "type": "Feature",
  "properties": {
    "iso:country":"US",
    "sg:address":"416 Hempstead Rd",
    "sg:city":"Newtown Square",
    "sg:classifiers":[
        {
            "category":"Social Services",
            "type":"Services"
        }
    ],
    "sg:phone":"+1 610 325 5231",
    "sg:postcode":"19073",
    "sg:province":"PA",
    "sg:tags":[
        "counselor",
        "marriage",
        "family"
    ],
    "wof:name":"Dorothy Cooper",
    "wof:placetype":"venue"
},
  "geometry": {"coordinates":[-75.41453199999999,39.971945],"type":"Point"}
}