{
  "type": "Feature",
  "properties": {
    "iso:country":"US",
    "sg:address":"100 Windmill Hill",
    "sg:city":"Burnham",
    "sg:classifiers":[
        {
            "category":"Wholesale",
            "subcategory":"Machinery & Supplies",
            "type":"Manufacturing & Wholesale Goods"
        }
    ],
    "sg:phone":"+1 717 248 8876",
    "sg:postcode":"17009",
    "sg:province":"PA",
    "sg:tags":[
        "equipment",
        "material",
        "handling"
    ],
    "wof:name":"Penn Equipment Co",
    "wof:placetype":"venue"
},
  "geometry": {"coordinates":[-77.584307,40.627857],"type":"Point"}
}