{
  "type": "Feature",
  "properties": {
    "iso:country":"US",
    "sg:address":"8239 Carlisle Pike",
    "sg:city":"York Springs",
    "sg:classifiers":[
        {
            "category":"Retail",
            "subcategory":"Animal Services",
            "type":"Services"
        }
    ],
    "sg:phone":"+1   ",
    "sg:postcode":"17372",
    "sg:province":"PA",
    "sg:tags":[
        "breeder",
        "german",
        "training",
        "dog",
        "shepherd"
    ],
    "wof:name":"Atlantic Canine Training Ctr",
    "wof:placetype":"venue"
},
  "geometry": {"coordinates":[-77.103047,39.999648],"type":"Point"}
}