{
  "type": "Feature",
  "properties": {
    "addr:full":"134 Painter St Trafford PA 15085",
    "addr:housenumber":"134",
    "addr:postcode":"15085",
    "addr:street":"Painter St",
    "iso:country":"US",
    "sg:address":"134 Painter St",
    "sg:city":"Trafford",
    "sg:classifiers":[
        {
            "category":"Professional",
            "subcategory":"Business Services",
            "type":"Services"
        },
        {
            "category":"Wholesale",
            "subcategory":"Durable Goods & Equipment",
            "type":"Manufacturing & Wholesale Goods"
        }
    ],
    "sg:phone":"+1 412 374 8880",
    "sg:postcode":"15085",
    "sg:province":"PA",
    "sg:tags":[
        "control",
        "electronic",
        "representative",
        "distributor",
        "sensor",
        "manufacturer"
    ],
    "wof:name":"Advance Technical Sales Inc",
    "wof:placetype":"venue"
},
  "geometry": {"coordinates":[-79.726128,40.396504],"type":"Point"}
}