{
  "type": "Feature",
  "properties": {
    "addr:full":"318 Abbe Pl Delmont PA 15626",
    "addr:housenumber":"318",
    "addr:postcode":"15626",
    "addr:street":"Abbe Pl",
    "iso:country":"US",
    "sg:address":"318 Abbe Pl",
    "sg:city":"Delmont",
    "sg:classifiers":[
        {
            "category":"Building & Trades",
            "subcategory":"Construction",
            "type":"Services"
        }
    ],
    "sg:phone":"+1 724 468 4848",
    "sg:postcode":"15626",
    "sg:province":"PA",
    "sg:tags":[
        "hanging",
        "contractor"
    ],
    "wof:name":"M & S Painting",
    "wof:placetype":"venue"
},
  "geometry": {"coordinates":[-79.572474,40.401919],"type":"Point"}
}