{
  "type": "Feature",
  "properties": {
    "addr:full":"1131 James St Monroeville PA 15146",
    "addr:housenumber":"1131",
    "addr:postcode":"15146",
    "addr:street":"James St",
    "iso:country":"US",
    "sg:address":"1131 James St",
    "sg:city":"Monroeville",
    "sg:classifiers":[
        {
            "category":"Restaurant",
            "type":"Food & Drink"
        }
    ],
    "sg:phone":"+1 412 823 9531",
    "sg:postcode":"15146",
    "sg:province":"PA",
    "sg:tags":[
        "drinking",
        "eating"
    ],
    "wof:name":"Overlook Lounge",
    "wof:placetype":"venue"
},
  "geometry": {"coordinates":[-79.811868,40.419107],"type":"Point"}
}