{
  "type": "Feature",
  "properties": {
    "addr:full":"1256 Plymouth Meeting Mall Plymouth Meeting PA 19462",
    "addr:housenumber":"1256",
    "addr:postcode":"19462",
    "addr:street":"Plymouth;Mall",
    "iso:country":"US",
    "sg:address":"1256 Plymouth Meeting Mall",
    "sg:city":"Plymouth Meeting",
    "sg:classifiers":[
        {
            "category":"Shopping",
            "subcategory":"Books",
            "type":"Retail Goods"
        }
    ],
    "sg:phone":"+1   ",
    "sg:postcode":"19462",
    "sg:province":"PA",
    "wof:name":"Waldenbooks",
    "wof:placetype":"venue"
},
  "geometry": {"coordinates":[-75.28424699999999,40.11726],"type":"Point"}
}