{
  "type": "Feature",
  "properties": {
    "iso:country":"US",
    "sg:address":"2315 Fox Meadow Dr",
    "sg:city":"Allentown",
    "sg:classifiers":[
        {
            "category":"Professional",
            "subcategory":"Management & Consulting",
            "type":"Services"
        }
    ],
    "sg:phone":"+1 610 439 3410",
    "sg:postcode":"18104",
    "sg:province":"PA",
    "sg:tags":[
        "consultant",
        "trademark",
        "agent"
    ],
    "wof:name":"Permissions Place",
    "wof:placetype":"venue"
},
  "geometry": {"coordinates":[-75.500899,40.585091],"type":"Point"}
}