{
  "type": "Feature",
  "properties": {
    "addr:full":"1380 Oakdale Rd Oakdale PA 15071",
    "addr:housenumber":"1380",
    "addr:postcode":"15071",
    "addr:street":"Oakdale Rd",
    "iso:country":"US",
    "sg:address":"1380 Oakdale Rd",
    "sg:city":"Oakdale",
    "sg:classifiers":[
        {
            "category":"Communications",
            "subcategory":"Film & Video Production",
            "type":"Services"
        }
    ],
    "sg:phone":"+1 412 494 6148",
    "sg:postcode":"15071",
    "sg:province":"PA",
    "sg:tags":[
        "taping"
    ],
    "wof:name":"Heart Song",
    "wof:placetype":"venue"
},
  "geometry": {"coordinates":[-80.202701,40.427505],"type":"Point"}
}