{
  "type": "Feature",
  "properties": {
    "iso:country":"US",
    "sg:address":"915 Madison Ave",
    "sg:city":"Scranton",
    "sg:classifiers":[
        {
            "category":"Education",
            "subcategory":"College",
            "type":"Public Place"
        }
    ],
    "sg:phone":"+1 570 343 9550",
    "sg:postcode":"18510",
    "sg:province":"PA",
    "sg:tags":[
        "school",
        "beauty"
    ],
    "wof:name":"Empire Beauty School",
    "wof:placetype":"venue"
},
  "geometry": {"coordinates":[-75.65075,41.414146],"type":"Point"}
}