{
  "type": "Feature",
  "properties": {
    "addr:full":"4901 Grand Ave Neville Island PA 15225",
    "addr:housenumber":"4901",
    "addr:postcode":"15225",
    "addr:street":"Grand Ave Neville",
    "iso:country":"US",
    "sg:address":"4901 Grand Ave",
    "sg:city":"Neville Island",
    "sg:classifiers":[
        {
            "category":"Restaurant",
            "type":"Food & Drink"
        }
    ],
    "sg:phone":"+1 412 264 8265",
    "sg:postcode":"15225",
    "sg:province":"PA",
    "wof:name":"Gino's Restaurant",
    "wof:placetype":"venue"
},
  "geometry": {"coordinates":[-80.131287,40.511974],"type":"Point"}
}