{
  "type": "Feature",
  "properties": {
    "addr:full":"3321 Craftsbury Ct Reading PA 19605",
    "addr:housenumber":"3321",
    "addr:postcode":"19605",
    "addr:street":"Craftsbury Ct",
    "iso:country":"US",
    "sg:address":"3321 Craftsbury Ct",
    "sg:city":"Reading",
    "sg:classifiers":[
        {
            "category":"Building & Trades",
            "subcategory":"Construction",
            "type":"Services"
        }
    ],
    "sg:phone":"+1 610 921 0100",
    "sg:postcode":"19605",
    "sg:province":"PA",
    "sg:tags":[
        "residential",
        "general",
        "family",
        "contractor"
    ],
    "wof:name":"M & S Construction & Repair",
    "wof:placetype":"venue"
},
  "geometry": {"coordinates":[-75.950048,40.386028],"type":"Point"}
}