{
  "type": "Feature",
  "properties": {
    "iso:country":"US",
    "sg:address":"3803 Willow Ave",
    "sg:city":"Pittsburgh",
    "sg:classifiers":[
        {
            "category":"Home & Garden",
            "subcategory":"Carpets & Floor Coverings",
            "type":"Retail Goods"
        }
    ],
    "sg:phone":"+1 412 531 0800",
    "sg:postcode":"15234",
    "sg:province":"PA",
    "sg:tags":[
        "carpeting"
    ],
    "wof:name":"Gallery of Floors",
    "wof:placetype":"venue"
},
  "geometry": {"coordinates":[-80.0261,40.365299],"type":"Point"}
}