{
  "type": "Feature",
  "properties": {
    "iso:country":"US",
    "sg:address":"630 N West End Blvd",
    "sg:city":"Quakertown",
    "sg:classifiers":[
        {
            "category":"Insurance",
            "subcategory":"Hazard Insurance",
            "type":"Services"
        }
    ],
    "sg:phone":"+1 215 536 7482",
    "sg:postcode":"18951",
    "sg:province":"PA",
    "sg:tags":[
        "commercial",
        "business"
    ],
    "sg:website":"http://www.statefarm.com",
    "wof:name":"State Farm Insurance",
    "wof:placetype":"venue"
},
  "geometry": {"coordinates":[-75.367237,40.458142],"type":"Point"}
}