{
  "type": "Feature",
  "properties": {
    "iso:country":"US",
    "sg:address":"Reading Terminal Market 12th St & Filbert St",
    "sg:city":"Philadelphia",
    "sg:classifiers":[
        {
            "category":"Bakery",
            "type":"Food & Drink"
        }
    ],
    "sg:phone":"+1 215 629 1790",
    "sg:postcode":"19107",
    "sg:province":"PA",
    "sg:website":"www.termini.com",
    "wof:name":"Termini Bros Inc",
    "wof:placetype":"venue"
},
  "geometry": {"coordinates":[-75.159682,39.952949],"type":"Point"}
}