{
  "type": "Feature",
  "properties": {
    "iso:country":"US",
    "sg:address":"3 Ways Ln",
    "sg:city":"Kennett Square",
    "sg:classifiers":[
        {
            "category":"Home & Garden",
            "subcategory":"Building Materials",
            "type":"Retail Goods"
        },
        {
            "category":"Building & Trades",
            "subcategory":"Construction",
            "type":"Services"
        }
    ],
    "sg:phone":"+1 610 444 2682",
    "sg:postcode":"19348",
    "sg:province":"PA",
    "sg:tags":[
        "mixed",
        "concrete",
        "contractor"
    ],
    "wof:name":"Deleware Valley Concrete Co",
    "wof:placetype":"venue"
},
  "geometry": {"coordinates":[-75.697864,39.845464],"type":"Point"}
}