{
  "type": "Feature",
  "properties": {
    "addr:full":"417 E Nesquehoning St Easton PA 18042",
    "addr:housenumber":"417",
    "addr:postcode":"18042",
    "addr:street":"E Nesquehoning St",
    "iso:country":"US",
    "sg:address":"417 E Nesquehoning St",
    "sg:city":"Easton",
    "sg:classifiers":[
        {
            "category":"Building & Trades",
            "subcategory":"Landscaping Services",
            "type":"Services"
        }
    ],
    "sg:phone":"+1   ",
    "sg:postcode":"18042",
    "sg:province":"PA",
    "sg:tags":[
        "landscape",
        "maintenance",
        "ground"
    ],
    "wof:name":"C & J Originals Inc",
    "wof:placetype":"venue"
},
  "geometry": {"coordinates":[-75.200439,40.682976],"type":"Point"}
}