{
  "type": "Feature",
  "properties": {
    "iso:country":"US",
    "sg:address":"417 Memorial Hwy",
    "sg:city":"Dallas",
    "sg:classifiers":[
        {
            "category":"Personal",
            "type":"Services"
        }
    ],
    "sg:phone":"+1   ",
    "sg:postcode":"18612",
    "sg:province":"PA",
    "wof:name":"Hollywood Weight Loss",
    "wof:placetype":"venue"
},
  "geometry": {"coordinates":[-75.96110299999999,41.335522],"type":"Point"}
}