{
  "type": "Feature",
  "properties": {
    "iso:country":"US",
    "sg:address":"123 Buford Ave",
    "sg:city":"Gettysburg",
    "sg:classifiers":[
        {
            "category":"Social Services",
            "type":"Services"
        }
    ],
    "sg:phone":"+1 717 338 0300",
    "sg:postcode":"17325",
    "sg:province":"PA",
    "wof:name":"Collaborating For Youth",
    "wof:placetype":"venue"
},
  "geometry": {"coordinates":[-77.238952,39.831993],"type":"Point"}
}