{
  "type": "Feature",
  "properties": {
    "iso:country":"US",
    "sg:address":"941 W 3rd St",
    "sg:city":"Williamsport",
    "sg:classifiers":[
        {
            "category":"Education",
            "subcategory":"Vocational School",
            "type":"Public Place"
        }
    ],
    "sg:phone":"+1   ",
    "sg:postcode":"17701",
    "sg:province":"PA",
    "wof:name":"Mullen Corporation",
    "wof:placetype":"venue"
},
  "geometry": {"coordinates":[-77.021727,41.237579],"type":"Point"}
}