{
  "type": "Feature",
  "properties": {
    "addr:full":"3129 Steele Ave Bristol PA 19007",
    "addr:housenumber":"3129",
    "addr:postcode":"19007",
    "addr:street":"Steele Ave",
    "iso:country":"US",
    "sg:address":"3129 Steele Ave",
    "sg:city":"Bristol",
    "sg:classifiers":[
        {
            "category":"Shopping",
            "subcategory":"Used Merchandise",
            "type":"Retail Goods"
        }
    ],
    "sg:phone":"+1 215 946 8690",
    "sg:postcode":"19007",
    "sg:province":"PA",
    "wof:name":"Crafty Flea Consignment Shop",
    "wof:placetype":"venue"
},
  "geometry": {"coordinates":[-74.88674,40.107725],"type":"Point"}
}