{
  "type": "Feature",
  "properties": {
    "addr:full":"3498 Parrish Rd Glenville PA 17329",
    "addr:housenumber":"3498",
    "addr:postcode":"17329",
    "addr:street":"Parrish Rd",
    "iso:country":"US",
    "sg:address":"3498 Parrish Rd",
    "sg:city":"Glenville",
    "sg:classifiers":[
        {
            "category":"Manufacturing",
            "subcategory":"Paper Products",
            "type":"Manufacturing & Wholesale Goods"
        }
    ],
    "sg:phone":"+1 717 235 3635",
    "sg:postcode":"17329",
    "sg:province":"PA",
    "sg:tags":[
        "bamboo"
    ],
    "wof:name":"Poplar Hollow Farm & Nurseries",
    "wof:placetype":"venue"
},
  "geometry": {"coordinates":[-76.790329,39.78796],"type":"Point"}
}