{
  "type": "Feature",
  "properties": {
    "iso:country":"US",
    "sg:address":"921 Broad St Ext.",
    "sg:city":"Delta",
    "sg:classifiers":[
        {
            "category":"Autos & Motor Vehicles",
            "subcategory":"Motorcycle Sales",
            "type":"Retail Goods"
        },
        {
            "category":"Retail",
            "subcategory":"Auto Repair",
            "type":"Services"
        }
    ],
    "sg:phone":"+1 717 456 5218",
    "sg:postcode":"17314",
    "sg:province":"PA",
    "sg:tags":[
        "scooters-repairing",
        "scooters-parts",
        "supply"
    ],
    "sg:website":"http://www.idiotcycles.com",
    "wof:name":"Idiot Cycles",
    "wof:placetype":"venue"
},
  "geometry": {"coordinates":[-76.32926500000001,39.745323],"type":"Point"}
}