{
  "type": "Feature",
  "properties": {
    "iso:country":"US",
    "sg:address":"305 Mountain Laurel Plz",
    "sg:city":"Latrobe",
    "sg:classifiers":[
        {
            "category":"Shopping",
            "subcategory":"Pharmacy",
            "type":"Retail Goods"
        }
    ],
    "sg:phone":"+1 724 537 4935",
    "sg:postcode":"15650",
    "sg:province":"PA",
    "wof:name":"CVS Pharmacy",
    "wof:placetype":"venue"
},
  "geometry": {"coordinates":[-79.392188,40.283376],"type":"Point"}
}