{
  "type": "Feature",
  "properties": {
    "addr:full":"6 E Main St Bloomsburg PA 17815",
    "addr:housenumber":"6",
    "addr:postcode":"17815",
    "addr:street":"E Main St",
    "iso:country":"US",
    "sg:address":"6 E Main St",
    "sg:city":"Bloomsburg",
    "sg:classifiers":[
        {
            "category":"Shopping",
            "subcategory":"Discount & Variety Stores",
            "type":"Retail Goods"
        }
    ],
    "sg:phone":"+1 570 389 0980",
    "sg:postcode":"17815",
    "sg:province":"PA",
    "wof:name":"Dollar General",
    "wof:placetype":"venue"
},
  "geometry": {"coordinates":[-76.455862,41.003365],"type":"Point"}
}