{
  "type": "Feature",
  "properties": {
    "iso:country":"US",
    "sg:address":"2599 Mayfield Ave",
    "sg:city":"Ambridge",
    "sg:classifiers":[
        {
            "category":"Personal",
            "subcategory":"Beauty Salon",
            "type":"Services"
        }
    ],
    "sg:phone":"+1 724 266 4135",
    "sg:postcode":"15003",
    "sg:province":"PA",
    "wof:name":"Deborah Dishler Beauty Salon",
    "wof:placetype":"venue"
},
  "geometry": {"coordinates":[-80.220249,40.607134],"type":"Point"}
}