{
  "type": "Feature",
  "properties": {
    "iso:country":"US",
    "sg:address":"2826 Frankford Ave",
    "sg:city":"Philadelphia",
    "sg:classifiers":[
        {
            "category":"Building & Trades",
            "subcategory":"Plumbing",
            "type":"Services"
        },
        {
            "category":"Home & Garden",
            "subcategory":"Home Furnishings",
            "type":"Retail Goods"
        }
    ],
    "sg:phone":"+1 215 425 4700",
    "sg:postcode":"19134",
    "sg:province":"PA",
    "sg:tags":[
        "bath",
        "kitchen"
    ],
    "wof:name":"William Betz Plumbing Supplies",
    "wof:placetype":"venue"
},
  "geometry": {"coordinates":[-75.11930099999999,39.989101],"type":"Point"}
}