{
  "type": "Feature",
  "properties": {
    "iso:country":"US",
    "sg:address":"942 S 58th St",
    "sg:city":"Philadelphia",
    "sg:classifiers":[
        {
            "category":"Retail",
            "subcategory":"Self-service Laundry",
            "type":"Services"
        }
    ],
    "sg:phone":"+1 215 472 1700",
    "sg:postcode":"19143",
    "sg:province":"PA",
    "wof:name":"Sun Shine Laundromate",
    "wof:placetype":"venue"
},
  "geometry": {"coordinates":[-75.240116,39.945989],"type":"Point"}
}