{
  "type": "Feature",
  "properties": {
    "addr:full":"2 Revere Rd Carnegie PA 15106",
    "addr:housenumber":"2",
    "addr:postcode":"15106",
    "addr:street":"Revere Rd",
    "iso:country":"US",
    "sg:address":"2 Revere Rd",
    "sg:city":"Carnegie",
    "sg:classifiers":[
        {
            "category":"Banks & Credit Unions",
            "subcategory":"Financial Services",
            "type":"Services"
        }
    ],
    "sg:phone":"+1   ",
    "sg:postcode":"15106",
    "sg:province":"PA",
    "sg:tags":[
        "company",
        "holding"
    ],
    "wof:name":"Pinnacle Properties & Dev",
    "wof:placetype":"venue"
},
  "geometry": {"coordinates":[-80.094635,40.421842],"type":"Point"}
}