{
  "type": "Feature",
  "properties": {
    "iso:country":"US",
    "sg:address":"506 S Bethlehem Pike",
    "sg:city":"Fort Washington",
    "sg:classifiers":[
        {
            "category":"Professional",
            "subcategory":"Advertising",
            "type":"Services"
        }
    ],
    "sg:phone":"+1   ",
    "sg:postcode":"19034",
    "sg:province":"PA",
    "sg:tags":[
        "agency"
    ],
    "wof:name":"Signal Communication Inc",
    "wof:placetype":"venue"
},
  "geometry": {"coordinates":[-75.216769,40.130779],"type":"Point"}
}