{
  "type": "Feature",
  "properties": {
    "iso:country":"US",
    "sg:address":"1080 Saxonburg Blvd",
    "sg:city":"Saxonburg",
    "sg:classifiers":[
        {
            "category":"Personal",
            "type":"Services"
        }
    ],
    "sg:phone":"+1 724 265 1600",
    "sg:postcode":"16056",
    "sg:province":"PA",
    "sg:tags":[
        "therapist",
        "massage"
    ],
    "wof:name":"Therapeutic Muscle Specialists",
    "wof:placetype":"venue"
},
  "geometry": {"coordinates":[-79.831919,40.684985],"type":"Point"}
}