{
  "type": "Feature",
  "properties": {
    "iso:country":"US",
    "sg:address":"4449 Garnet Mine Rd",
    "sg:city":"Marcus Hook",
    "sg:classifiers":[
        {
            "category":"Real Estate",
            "subcategory":"Real Estate Operator",
            "type":"Services"
        }
    ],
    "sg:phone":"+1   ",
    "sg:postcode":"19061",
    "sg:province":"PA",
    "sg:tags":[
        "building",
        "nonresidential"
    ],
    "wof:name":"Shinnen Properties Inc",
    "wof:placetype":"venue"
},
  "geometry": {"coordinates":[-75.462279,39.847995],"type":"Point"}
}