{
  "type": "Feature",
  "properties": {
    "iso:country":"US",
    "sg:address":"129 S Fraser St",
    "sg:city":"State College",
    "sg:classifiers":[
        {
            "category":"Bakery",
            "type":"Food & Drink"
        }
    ],
    "sg:menulink":"http://www.allmenus.com/pa/state-college/260065-insomnia-cookies/menu/",
    "sg:phone":"+1 814 238 3587",
    "sg:postcode":"16801",
    "sg:province":"PA",
    "sg:tags":[
        "american",
        "pastry"
    ],
    "wof:name":"Insomnia Cookies",
    "wof:placetype":"venue"
},
  "geometry": {"coordinates":[-77.861954,40.79316],"type":"Point"}
}