{
  "type": "Feature",
  "properties": {
    "addr:full":"117 S West End Ave Lancaster PA 17603",
    "addr:housenumber":"117",
    "addr:postcode":"17603",
    "addr:street":"S;End Ave",
    "iso:country":"US",
    "sg:address":"117 S West End Ave",
    "sg:city":"Lancaster",
    "sg:classifiers":[
        {
            "category":"Personal",
            "subcategory":"Beauty Salon",
            "type":"Services"
        }
    ],
    "sg:phone":"+1 717 392 5226",
    "sg:postcode":"17603",
    "sg:province":"PA",
    "wof:name":"Noreen Elizabeth's",
    "wof:placetype":"venue"
},
  "geometry": {"coordinates":[-76.32403499999999,40.036802],"type":"Point"}
}