{
  "type": "Feature",
  "properties": {
    "iso:country":"US",
    "sg:address":"4331 Cyril Dr",
    "sg:city":"Pittsburgh",
    "sg:classifiers":[
        {
            "category":"Wholesale",
            "subcategory":"Hardware",
            "type":"Manufacturing & Wholesale Goods"
        }
    ],
    "sg:phone":"+1 412 795 8030",
    "sg:postcode":"15239",
    "sg:province":"PA",
    "sg:tags":[
        "equipment",
        "heating",
        "system"
    ],
    "wof:name":"Bernie's Heating & Air Cond",
    "wof:placetype":"venue"
},
  "geometry": {"coordinates":[-79.75608,40.498446],"type":"Point"}
}