{
  "type": "Feature",
  "properties": {
    "iso:country":"US",
    "sg:address":"1840 Auction Rd",
    "sg:city":"Manheim",
    "sg:classifiers":[
        {
            "category":"Retail",
            "subcategory":"Auto Repair",
            "type":"Services"
        }
    ],
    "sg:phone":"+1 717 653 8600",
    "sg:postcode":"17545",
    "sg:province":"PA",
    "sg:tags":[
        "body",
        "automobile",
        "painting"
    ],
    "wof:name":"Krunch Kritters Spray Shop",
    "wof:placetype":"venue"
},
  "geometry": {"coordinates":[-76.43959099999999,40.113297],"type":"Point"}
}