{
  "type": "Feature",
  "properties": {
    "addr:full":"1377 Mall Rd Muncy PA 17756",
    "addr:housenumber":"1377",
    "addr:postcode":"17756",
    "addr:street":"Mall Rd",
    "iso:country":"US",
    "sg:address":"1377 Mall Rd",
    "sg:city":"Muncy",
    "sg:classifiers":[
        {
            "category":"Shopping",
            "type":"Retail Goods"
        }
    ],
    "sg:phone":"+1 570 433 3054",
    "sg:postcode":"17756",
    "sg:province":"PA",
    "sg:tags":[
        "tropical",
        "fish"
    ],
    "wof:name":"Salt Water Heaven",
    "wof:placetype":"venue"
},
  "geometry": {"coordinates":[-76.832932,41.27605],"type":"Point"}
}