{
  "type": "Feature",
  "properties": {
    "addr:full":"524 E Chestnut St Coatesville PA 19320",
    "addr:housenumber":"524",
    "addr:postcode":"19320",
    "addr:street":"E Chestnut St",
    "iso:country":"US",
    "sg:address":"524 E Chestnut St",
    "sg:city":"Coatesville",
    "sg:classifiers":[
        {
            "category":"Health Services",
            "subcategory":"Nursing And Care Facility",
            "type":"Services"
        }
    ],
    "sg:phone":"+1   ",
    "sg:postcode":"19320",
    "sg:province":"PA",
    "wof:name":"Browns Personal Care",
    "wof:placetype":"venue"
},
  "geometry": {"coordinates":[-75.81626799999999,39.985174],"type":"Point"}
}