{
  "type": "Feature",
  "properties": {
    "addr:full":"322 Warren St Johnstown PA 15905",
    "addr:housenumber":"322",
    "addr:postcode":"15905",
    "addr:street":"Warren St",
    "iso:country":"US",
    "sg:address":"322 Warren St",
    "sg:city":"Johnstown",
    "sg:classifiers":[
        {
            "category":"Health Services",
            "subcategory":"Doctor",
            "type":"Services"
        },
        {
            "category":"Health Services",
            "subcategory":"Podiatrist",
            "type":"Services"
        }
    ],
    "sg:phone":"+1 814 288 4498",
    "sg:postcode":"15905",
    "sg:province":"PA",
    "sg:tags":[
        "physician",
        "family",
        "gynecology",
        "practice",
        "surgeons",
        "obstetrics",
        "medicine",
        "surgeon"
    ],
    "wof:name":"Kastelic Richard M.D. & Associates",
    "wof:placetype":"venue"
},
  "geometry": {"coordinates":[-78.93324200000001,40.294317],"type":"Point"}
}