{
  "type": "Feature",
  "properties": {
    "iso:country":"US",
    "sg:address":"415 Pleasant St",
    "sg:city":"Hanover",
    "sg:classifiers":[
        {
            "category":"Freight",
            "type":"Transportation"
        }
    ],
    "sg:phone":"+1 717 637 3694",
    "sg:postcode":"17331",
    "sg:province":"PA",
    "sg:tags":[
        "commercial",
        "storage"
    ],
    "wof:name":"J & V Self Storage",
    "wof:placetype":"venue"
},
  "geometry": {"coordinates":[-76.973178,39.803767],"type":"Point"}
}