{
  "type": "Feature",
  "properties": {
    "iso:country":"US",
    "sg:address":"2113 Harmony Rd",
    "sg:city":"Susquehanna",
    "sg:classifiers":[
        {
            "category":"Manufacturing",
            "subcategory":"Buildings",
            "type":"Manufacturing & Wholesale Goods"
        },
        {
            "category":"Building & Trades",
            "subcategory":"Construction",
            "type":"Services"
        }
    ],
    "sg:phone":"+1 570 879 4127",
    "sg:postcode":"18847",
    "sg:province":"PA",
    "sg:tags":[
        "home",
        "builder",
        "contractor"
    ],
    "wof:name":"Carlson Construction",
    "wof:placetype":"venue"
},
  "geometry": {"coordinates":[-75.65030299999999,41.953644],"type":"Point"}
}