{
  "type": "Feature",
  "properties": {
    "iso:country":"US",
    "sg:address":"1905 W Allen St",
    "sg:city":"Allentown",
    "sg:classifiers":[
        {
            "category":"Food & Beverages",
            "subcategory":"Groceries & Convenience Stores",
            "type":"Retail Goods"
        }
    ],
    "sg:phone":"+1 610 821 0271",
    "sg:postcode":"18104",
    "sg:province":"PA",
    "sg:tags":[
        "market"
    ],
    "wof:name":"Allen Street Market & Deli",
    "wof:placetype":"venue"
},
  "geometry": {"coordinates":[-75.500595,40.603782],"type":"Point"}
}