{
  "type": "Feature",
  "properties": {
    "addr:full":"530 Galleria Dr Johnstown PA 15904",
    "addr:housenumber":"530",
    "addr:postcode":"15904",
    "addr:street":"Galleria Dr",
    "iso:country":"US",
    "sg:address":"530 Galleria Dr",
    "sg:city":"Johnstown",
    "sg:classifiers":[
        {
            "category":"Restaurant",
            "type":"Food & Drink"
        }
    ],
    "sg:menulink":"http://www.allmenus.com/pa/richland/206125-mcdonalds/menu/",
    "sg:phone":"+1 814 266 7757",
    "sg:postcode":"15904",
    "sg:province":"PA",
    "sg:tags":[
        "burger",
        "american"
    ],
    "wof:name":"McDonald's",
    "wof:placetype":"venue"
},
  "geometry": {"coordinates":[-78.835691,40.297585],"type":"Point"}
}