{
  "type": "Feature",
  "properties": {
    "iso:country":"US",
    "sg:address":"674 Blooming Grove Rd",
    "sg:city":"Hanover",
    "sg:classifiers":[
        {
            "category":"Professional",
            "subcategory":"Computer Services",
            "type":"Services"
        }
    ],
    "sg:phone":"+1 717 630 9021",
    "sg:postcode":"17331",
    "sg:province":"PA",
    "sg:tags":[
        "consultant",
        "designer"
    ],
    "wof:name":"Business Information Systems",
    "wof:placetype":"venue"
},
  "geometry": {"coordinates":[-76.934281,39.793802],"type":"Point"}
}