{
  "type": "Feature",
  "properties": {
    "addr:full":"301 Ohio River Blvd Sewickley PA 15143",
    "addr:housenumber":"301",
    "addr:postcode":"15143",
    "addr:street":"Ohio River Blvd",
    "iso:country":"US",
    "sg:address":"301 Ohio River Blvd",
    "sg:city":"Sewickley",
    "sg:classifiers":[
        {
            "category":"Health Services",
            "subcategory":"Clinic",
            "type":"Services"
        },
        {
            "category":"Health Services",
            "subcategory":"Health Practitioner",
            "type":"Services"
        }
    ],
    "sg:phone":"+1 412 741 9695",
    "sg:postcode":"15143",
    "sg:province":"PA",
    "sg:tags":[
        "therapist",
        "physical",
        "specialty",
        "outpatient"
    ],
    "wof:name":"HealthSouth",
    "wof:placetype":"venue"
},
  "geometry": {"coordinates":[-80.186126,40.537313],"type":"Point"}
}