{
  "type": "Feature",
  "properties": {
    "addr:full":"8 Dire Dr Hickory PA 15340",
    "addr:housenumber":"8",
    "addr:postcode":"15340",
    "addr:street":"Dire Dr",
    "iso:country":"US",
    "sg:address":"8 Dire Dr",
    "sg:city":"Hickory",
    "sg:classifiers":[
        {
            "category":"Retail",
            "subcategory":"Auto Repair",
            "type":"Services"
        }
    ],
    "sg:phone":"+1   ",
    "sg:postcode":"15340",
    "sg:province":"PA",
    "sg:tags":[
        "body"
    ],
    "wof:name":"Gary Fender",
    "wof:placetype":"venue"
},
  "geometry": {"coordinates":[-80.319603,40.296192],"type":"Point"}
}