{
  "type": "Feature",
  "properties": {
    "iso:country":"US",
    "sg:address":"2490 Schoenersville Rd",
    "sg:city":"Allentown",
    "sg:classifiers":[
        {
            "category":"Personal",
            "subcategory":"Day Spa",
            "type":"Services"
        }
    ],
    "sg:phone":"+1 610 266 8080",
    "sg:postcode":"18109",
    "sg:province":"PA",
    "wof:name":"Cameo Health Spa",
    "wof:placetype":"venue"
},
  "geometry": {"coordinates":[-75.420069,40.659037],"type":"Point"}
}