{
  "type": "Feature",
  "properties": {
    "addr:full":"2040 Lehigh St Easton PA 18042",
    "addr:housenumber":"2040",
    "addr:postcode":"18042",
    "addr:street":"Lehigh St",
    "iso:country":"US",
    "sg:address":"2040 Lehigh St",
    "sg:city":"Easton",
    "sg:classifiers":[
        {
            "category":"Social Services",
            "type":"Services"
        }
    ],
    "sg:phone":"+1   ",
    "sg:postcode":"18042",
    "sg:province":"PA",
    "wof:name":"Care For People",
    "wof:placetype":"venue"
},
  "geometry": {"coordinates":[-75.24221199999999,40.686614],"type":"Point"}
}