{
  "type": "Feature",
  "properties": {
    "iso:country":"US",
    "sg:address":"1075 Blair Ave",
    "sg:city":"Scranton",
    "sg:classifiers":[
        {
            "category":"Building & Trades",
            "subcategory":"Plumbing",
            "type":"Services"
        }
    ],
    "sg:phone":"+1   ",
    "sg:postcode":"18508",
    "sg:province":"PA",
    "sg:tags":[
        "contractor"
    ],
    "wof:name":"Goodfield & Goodfield Co Inc",
    "wof:placetype":"venue"
},
  "geometry": {"coordinates":[-75.664463,41.425412],"type":"Point"}
}