{
  "type": "Feature",
  "properties": {
    "iso:country":"US",
    "sg:address":"3400 Aramingo Ave",
    "sg:city":"Philadelphia",
    "sg:classifiers":[
        {
            "category":"Banks & Credit Unions",
            "subcategory":"Bank",
            "type":"Services"
        }
    ],
    "sg:phone":"+1 215 423 4999",
    "sg:postcode":"19134",
    "sg:province":"PA",
    "sg:website":"www.wachovia.com",
    "wof:name":"Wachovia",
    "wof:placetype":"venue"
},
  "geometry": {"coordinates":[-75.101601,39.991001],"type":"Point"}
}