{
  "type": "Feature",
  "properties": {
    "iso:country":"US",
    "sg:address":"1523 Letchworth Dr",
    "sg:city":"Camp Hill",
    "sg:classifiers":[
        {
            "category":"Food & Beverages",
            "subcategory":"Specialty",
            "type":"Retail Goods"
        }
    ],
    "sg:phone":"+1   ",
    "sg:postcode":"17011",
    "sg:province":"PA",
    "wof:name":"Daytons Coffee Tea Confections",
    "wof:placetype":"venue"
},
  "geometry": {"coordinates":[-76.903037,40.232316],"type":"Point"}
}