{
  "type": "Feature",
  "properties": {
    "iso:country":"US",
    "sg:address":"240 Union Station Plz",
    "sg:city":"Bethlehem",
    "sg:classifiers":[
        {
            "category":"Health Services",
            "subcategory":"Doctor",
            "type":"Services"
        },
        {
            "category":"Health Services",
            "subcategory":"Hospital",
            "type":"Services"
        }
    ],
    "sg:phone":"+1 610 954 3060",
    "sg:postcode":"18015",
    "sg:province":"PA",
    "sg:tags":[
        "physician",
        "pediatrics-emergency",
        "pediatrics",
        "surgeons",
        "medicine",
        "surgeon"
    ],
    "wof:name":"St Luke's Pediatric Associates/Kidscare",
    "wof:placetype":"venue"
},
  "geometry": {"coordinates":[-75.38083899999999,40.61392],"type":"Point"}
}