{
  "type": "Feature",
  "properties": {
    "addr:full":"119 S College St Washington PA 15301",
    "addr:housenumber":"119",
    "addr:postcode":"15301",
    "addr:street":"S College St",
    "iso:country":"US",
    "sg:address":"119 S College St",
    "sg:city":"Washington",
    "sg:classifiers":[
        {
            "category":"Professional",
            "subcategory":"Lawyer & Legal Services",
            "type":"Services"
        }
    ],
    "sg:phone":"+1   ",
    "sg:postcode":"15301",
    "sg:province":"PA",
    "wof:name":"Jeffery G Brooks",
    "wof:placetype":"venue"
},
  "geometry": {"coordinates":[-80.24247800000001,40.169481],"type":"Point"}
}