{
  "type": "Feature",
  "properties": {
    "iso:country":"US",
    "sg:address":"6 S Bryn Mawr Ave",
    "sg:city":"Bryn Mawr",
    "sg:classifiers":[
        {
            "category":"Professional",
            "subcategory":"Lawyer & Legal Services",
            "type":"Services"
        }
    ],
    "sg:phone":"+1   ",
    "sg:postcode":"19010",
    "sg:province":"PA",
    "wof:name":"Erica Bazzell",
    "wof:placetype":"venue"
},
  "geometry": {"coordinates":[-75.31889700000001,40.02016],"type":"Point"}
}