{
  "type": "Feature",
  "properties": {
    "addr:full":"109 N Main St Shrewsbury PA 17361",
    "addr:housenumber":"109",
    "addr:postcode":"17361",
    "addr:street":"N Main St",
    "iso:country":"US",
    "sg:address":"109 N Main St",
    "sg:city":"Shrewsbury",
    "sg:classifiers":[
        {
            "category":"Home & Garden",
            "subcategory":"Carpets & Floor Coverings",
            "type":"Retail Goods"
        }
    ],
    "sg:phone":"+1 717 235 7941",
    "sg:postcode":"17361",
    "sg:province":"PA",
    "sg:tags":[
        "installs",
        "rug",
        "dealer"
    ],
    "wof:name":"Bonitz Carpets Inc",
    "wof:placetype":"venue"
},
  "geometry": {"coordinates":[-76.678969,39.76364],"type":"Point"}
}