{
  "type": "Feature",
  "properties": {
    "iso:country":"US",
    "sg:address":"1740 E Passyunk Ave",
    "sg:city":"Philadelphia",
    "sg:classifiers":[
        {
            "category":"Professional",
            "type":"Services"
        }
    ],
    "sg:phone":"+1 215 218 0240",
    "sg:postcode":"19148",
    "sg:province":"PA",
    "sg:tags":[
        "accessory"
    ],
    "wof:name":"Bianca Simone",
    "wof:placetype":"venue"
},
  "geometry": {"coordinates":[-75.16584,39.92813],"type":"Point"}
}