{
  "type": "Feature",
  "properties": {
    "iso:country":"US",
    "sg:address":"629 Elder St",
    "sg:city":"Johnstown",
    "sg:classifiers":[
        {
            "category":"Retail",
            "subcategory":"Repair Shop",
            "type":"Services"
        }
    ],
    "sg:phone":"+1   ",
    "sg:postcode":"15902",
    "sg:province":"PA",
    "sg:tags":[
        "armature",
        "rewinding",
        "merchandise"
    ],
    "wof:name":"Johnstown Electric Mtr Svc LLC",
    "wof:placetype":"venue"
},
  "geometry": {"coordinates":[-78.91328300000001,40.310487],"type":"Point"}
}