{
  "type": "Feature",
  "properties": {
    "iso:country":"US",
    "sg:address":"255 E Ohio St",
    "sg:city":"Pittsburgh",
    "sg:classifiers":[
        {
            "category":"Retail",
            "subcategory":"Auto Repair",
            "type":"Services"
        }
    ],
    "sg:phone":"+1 412 323 0801",
    "sg:postcode":"15212",
    "sg:province":"PA",
    "sg:tags":[
        "repairing",
        "automobile"
    ],
    "wof:name":"ANG Automotive",
    "wof:placetype":"venue"
},
  "geometry": {"coordinates":[-80.00267599999999,40.453059],"type":"Point"}
}