{
  "type": "Feature",
  "properties": {
    "iso:country":"US",
    "sg:address":"5400 Paxton St",
    "sg:city":"Harrisburg",
    "sg:classifiers":[
        {
            "category":"Home & Garden",
            "subcategory":"Building Materials",
            "type":"Retail Goods"
        },
        {
            "category":"Professional",
            "subcategory":"Printing & Photocopies",
            "type":"Services"
        },
        {
            "category":"Manufacturing",
            "subcategory":"Building Materials",
            "type":"Manufacturing & Wholesale Goods"
        },
        {
            "category":"Building & Trades",
            "subcategory":"Locksmith",
            "type":"Services"
        }
    ],
    "sg:phone":"+1 717 232 1033",
    "sg:postcode":"17111",
    "sg:province":"PA",
    "sg:tags":[
        "repair",
        "industrial-sales",
        "door-overhead",
        "doors-commercial",
        "device",
        "door",
        "type",
        "doors-operating"
    ],
    "sg:website":"http://www.csdoors.com",
    "wof:name":"Central State Distributors",
    "wof:placetype":"venue"
},
  "geometry": {"coordinates":[-76.794434,40.25626],"type":"Point"}
}