{
  "type": "Feature",
  "properties": {
    "iso:country":"US",
    "sg:address":"1270 Rte 66",
    "sg:city":"New Bethlehem",
    "sg:classifiers":[
        {
            "category":"Wholesale",
            "subcategory":"Construction Materials",
            "type":"Manufacturing & Wholesale Goods"
        }
    ],
    "sg:phone":"+1 814 275 2420",
    "sg:postcode":"16242",
    "sg:province":"PA",
    "sg:tags":[
        "timberland",
        "company",
        "timber"
    ],
    "wof:name":"Greenland Forestry",
    "wof:placetype":"venue"
},
  "geometry": {"coordinates":[-79.332956,41.016041],"type":"Point"}
}