{
  "type": "Feature",
  "properties": {
    "iso:country":"US",
    "sg:address":"7044 Saint Peters Rd",
    "sg:city":"Macungie",
    "sg:classifiers":[
        {
            "category":"Shopping",
            "subcategory":"Bicycles & Sporting Goods",
            "type":"Retail Goods"
        }
    ],
    "sg:phone":"+1 610 966 4092",
    "sg:postcode":"18062",
    "sg:province":"PA",
    "wof:name":"Tuf Lusy",
    "wof:placetype":"venue"
},
  "geometry": {"coordinates":[-75.55737999999999,40.484463],"type":"Point"}
}