{
  "type": "Feature",
  "properties": {
    "addr:full":"730 Welsh St Kane PA 16735",
    "addr:housenumber":"730",
    "addr:postcode":"16735",
    "addr:street":"Welsh St",
    "iso:country":"US",
    "sg:address":"730 Welsh St",
    "sg:city":"Kane",
    "sg:classifiers":[
        {
            "category":"Shopping",
            "subcategory":"Florist",
            "type":"Retail Goods"
        }
    ],
    "sg:phone":"+1   ",
    "sg:postcode":"16735",
    "sg:province":"PA",
    "wof:name":"Cy Designs",
    "wof:placetype":"venue"
},
  "geometry": {"coordinates":[-78.807911,41.666732],"type":"Point"}
}