{
  "type": "Feature",
  "properties": {
    "addr:full":"127 S Easton Rd Glenside PA 19038",
    "addr:housenumber":"127",
    "addr:postcode":"19038",
    "addr:street":"S Easton Rd",
    "iso:country":"US",
    "sg:address":"127 S Easton Rd",
    "sg:city":"Glenside",
    "sg:classifiers":[
        {
            "category":"Home & Garden",
            "subcategory":"Hardware",
            "type":"Retail Goods"
        }
    ],
    "sg:phone":"+1 215 884 2128",
    "sg:postcode":"19038",
    "sg:province":"PA",
    "wof:name":"Glenside Hardware",
    "wof:placetype":"venue"
},
  "geometry": {"coordinates":[-75.154039,40.100208],"type":"Point"}
}