{
  "type": "Feature",
  "properties": {
    "iso:country":"US",
    "sg:address":"423 Chestnut St",
    "sg:city":"Meadville",
    "sg:classifiers":[
        {
            "category":"Museum",
            "type":"Entertainment"
        }
    ],
    "sg:phone":"+1 814 333 4326",
    "sg:postcode":"16335",
    "sg:province":"PA",
    "wof:name":"Johnson-Shaw Steroscopic",
    "wof:placetype":"venue"
},
  "geometry": {"coordinates":[-80.147155,41.637005],"type":"Point"}
}