{
  "type": "Feature",
  "properties": {
    "iso:country":"US",
    "sg:address":"1015 Penn Ave",
    "sg:city":"Wyomissing",
    "sg:classifiers":[
        {
            "category":"Professional",
            "subcategory":"Accounting & Tax Preparation",
            "type":"Services"
        }
    ],
    "sg:phone":"+1 610 376 1595",
    "sg:postcode":"19610",
    "sg:province":"PA",
    "sg:tags":[
        "accountant"
    ],
    "sg:website":"www.reinsel.com",
    "wof:name":"Reinsel & Co",
    "wof:placetype":"venue"
},
  "geometry": {"coordinates":[-75.959194,40.335203],"type":"Point"}
}