{
  "type": "Feature",
  "properties": {
    "iso:country":"US",
    "sg:address":"1585 Manheim Pike",
    "sg:city":"Lancaster",
    "sg:classifiers":[
        {
            "category":"Ice Cream",
            "type":"Food & Drink"
        }
    ],
    "sg:menulink":"http://www.allmenus.com/pa/manheim/234861-ritas-ice-custard-happiness/menu/",
    "sg:phone":"+1 717 569 5651",
    "sg:postcode":"17601",
    "sg:province":"PA",
    "sg:tags":[
        "american"
    ],
    "wof:name":"Rita's Ice Custard Happiness",
    "wof:placetype":"venue"
},
  "geometry": {"coordinates":[-76.33940200000001,40.080516],"type":"Point"}
}