{
  "type": "Feature",
  "properties": {
    "iso:country":"US",
    "sg:address":"462 North St",
    "sg:city":"Meadville",
    "sg:classifiers":[
        {
            "category":"Retail",
            "subcategory":"Car Wash",
            "type":"Services"
        }
    ],
    "sg:phone":"+1 814 724 4522",
    "sg:postcode":"16335",
    "sg:province":"PA",
    "sg:tags":[
        "polishing",
        "washing"
    ],
    "wof:name":"North Street Shine Care",
    "wof:placetype":"venue"
},
  "geometry": {"coordinates":[-80.14479900000001,41.639715],"type":"Point"}
}