{
  "type": "Feature",
  "properties": {
    "iso:country":"US",
    "sg:address":"4600 Westport Dr",
    "sg:city":"Mechanicsburg",
    "sg:classifiers":[
        {
            "category":"Building & Trades",
            "subcategory":"Construction",
            "type":"Services"
        }
    ],
    "sg:phone":"+1   ",
    "sg:postcode":"17055",
    "sg:province":"PA",
    "sg:tags":[
        "house"
    ],
    "wof:name":"Sears",
    "wof:placetype":"venue"
},
  "geometry": {"coordinates":[-76.95054,40.205551],"type":"Point"}
}