{
  "type": "Feature",
  "properties": {
    "iso:country":"US",
    "sg:address":"330 Grape St",
    "sg:city":"Warminster",
    "sg:classifiers":[
        {
            "category":"Sports & Exercise",
            "subcategory":"Race Track",
            "type":"Entertainment"
        }
    ],
    "sg:phone":"+1   ",
    "sg:postcode":"18974",
    "sg:province":"PA",
    "sg:tags":[
        "operation",
        "racing",
        "or"
    ],
    "wof:name":"Botten Brothers Racing Team",
    "wof:placetype":"venue"
},
  "geometry": {"coordinates":[-75.097837,40.195201],"type":"Point"}
}