{
  "type": "Feature",
  "properties": {
    "addr:full":"140 Easton Rd Warrington PA 18976",
    "addr:housenumber":"140",
    "addr:postcode":"18976",
    "addr:street":"Easton Rd",
    "iso:country":"US",
    "sg:address":"140 Easton Rd",
    "sg:city":"Warrington",
    "sg:phone":"+1 215 918 9090",
    "sg:postcode":"18976",
    "sg:province":"PA",
    "sg:website":"http://www.rubytuesday.com",
    "wof:name":"Ruby Tuesday Restaurant",
    "wof:placetype":"venue"
},
  "geometry": {"coordinates":[-75.13960400000001,40.215976],"type":"Point"}
}