{
  "type": "Feature",
  "properties": {
    "iso:country":"US",
    "sg:address":"21 Little Rd",
    "sg:city":"Perkiomenville",
    "sg:classifiers":[
        {
            "category":"Building & Trades",
            "subcategory":"Construction",
            "type":"Services"
        }
    ],
    "sg:phone":"+1   ",
    "sg:postcode":"19492",
    "sg:province":"PA",
    "sg:tags":[
        "carpentry",
        "contractor"
    ],
    "wof:name":"Naples Carpentry & Contracting",
    "wof:placetype":"venue"
},
  "geometry": {"coordinates":[-75.48520600000001,40.284226],"type":"Point"}
}