{
  "type": "Feature",
  "properties": {
    "iso:country":"US",
    "sg:address":"124 Madison Rd",
    "sg:city":"Willow Grove",
    "sg:classifiers":[
        {
            "category":"Building & Trades",
            "subcategory":"Landscaping Services",
            "type":"Services"
        }
    ],
    "sg:phone":"+1   ",
    "sg:postcode":"19090",
    "sg:province":"PA",
    "sg:tags":[
        "specializing",
        "tree",
        "contractor"
    ],
    "wof:name":"Marks Tree Service",
    "wof:placetype":"venue"
},
  "geometry": {"coordinates":[-75.126777,40.15014],"type":"Point"}
}