{
  "type": "Feature",
  "properties": {
    "iso:country":"US",
    "sg:address":"9220 Marsden St",
    "sg:city":"Philadelphia",
    "sg:classifiers":[
        {
            "category":"Professional",
            "type":"Services"
        }
    ],
    "sg:phone":"+1   ",
    "sg:postcode":"19114",
    "sg:province":"PA",
    "wof:name":"Ronald Perry",
    "wof:placetype":"venue"
},
  "geometry": {"coordinates":[-74.999019,40.051995],"type":"Point"}
}