{
  "type": "Feature",
  "properties": {
    "iso:country":"US",
    "sg:address":"202 Precision Dr",
    "sg:city":"Horsham",
    "sg:classifiers":[
        {
            "category":"Shopping",
            "subcategory":"Catalog Store",
            "type":"Retail Goods"
        }
    ],
    "sg:phone":"+1   ",
    "sg:postcode":"19044",
    "sg:province":"PA",
    "sg:tags":[
        "mail",
        "house"
    ],
    "wof:name":"AARP Pharmacy Services",
    "wof:placetype":"venue"
},
  "geometry": {"coordinates":[-75.156243,40.189332],"type":"Point"}
}