{
  "type": "Feature",
  "properties": {
    "addr:full":"2021 Bridgetown Pike Feasterville Trevose PA 19053",
    "addr:housenumber":"2021",
    "addr:postcode":"19053",
    "addr:street":"Bridgetown Pike",
    "iso:country":"US",
    "sg:address":"2021 Bridgetown Pike",
    "sg:city":"Feasterville Trevose",
    "sg:classifiers":[
        {
            "category":"Freight",
            "type":"Transportation"
        }
    ],
    "sg:phone":"+1   ",
    "sg:postcode":"19053",
    "sg:province":"PA",
    "sg:tags":[
        "storage",
        "facility"
    ],
    "wof:name":"U S Long Life Inc",
    "wof:placetype":"venue"
},
  "geometry": {"coordinates":[-74.982927,40.163633],"type":"Point"}
}