{
  "type": "Feature",
  "properties": {
    "iso:country":"US",
    "sg:address":"3816 Gettysburg Rd",
    "sg:city":"Camp Hill",
    "sg:classifiers":[
        {
            "category":"Personal",
            "subcategory":"Beauty Salon",
            "type":"Services"
        }
    ],
    "sg:phone":"+1 717 761 0228",
    "sg:postcode":"17011",
    "sg:province":"PA",
    "sg:tags":[
        "nail",
        "hair",
        "styling",
        "shop"
    ],
    "sg:website":"www.chichairdesigns.com",
    "wof:name":"Chic Hair Designs Inc",
    "wof:placetype":"venue"
},
  "geometry": {"coordinates":[-76.94259599999999,40.2216],"type":"Point"}
}