{
  "type": "Feature",
  "properties": {
    "iso:country":"US",
    "sg:address":"2342 E Hills Dr",
    "sg:city":"Pittsburgh",
    "sg:classifiers":[
        {
            "category":"Real Estate",
            "subcategory":"Real Estate Agent",
            "type":"Services"
        },
        {
            "category":"Real Estate",
            "subcategory":"Real Estate Operator",
            "type":"Services"
        }
    ],
    "sg:phone":"+1 412 243 8400",
    "sg:postcode":"15221",
    "sg:province":"PA",
    "sg:tags":[
        "apartment"
    ],
    "wof:name":"Second East Hills Apartment",
    "wof:placetype":"venue"
},
  "geometry": {"coordinates":[-79.870936,40.455289],"type":"Point"}
}