{
  "type": "Feature",
  "properties": {
    "iso:country":"US",
    "sg:address":"26 W Baker St",
    "sg:city":"Media",
    "sg:classifiers":[
        {
            "category":"Building & Trades",
            "subcategory":"Construction",
            "type":"Services"
        }
    ],
    "sg:phone":"+1 610 565 5480",
    "sg:postcode":"19063",
    "sg:province":"PA",
    "sg:tags":[
        "dry wall",
        "contractor"
    ],
    "wof:name":"CDS Inc",
    "wof:placetype":"venue"
},
  "geometry": {"coordinates":[-75.39115099999999,39.917561],"type":"Point"}
}