{
  "type": "Feature",
  "properties": {
    "iso:country":"US",
    "sg:address":"704 Donna Ln",
    "sg:city":"Phoenixville",
    "sg:classifiers":[
        {
            "category":"Wholesale",
            "subcategory":"Computers",
            "type":"Manufacturing & Wholesale Goods"
        }
    ],
    "sg:phone":"+1 610 917 8822",
    "sg:postcode":"19460",
    "sg:province":"PA",
    "wof:name":"Teklogix",
    "wof:placetype":"venue"
},
  "geometry": {"coordinates":[-75.54687300000001,40.137866],"type":"Point"}
}