{
  "type": "Feature",
  "properties": {
    "iso:country":"US",
    "sg:address":"1479 E Schuylkill Rd",
    "sg:city":"Pottstown",
    "sg:classifiers":[
        {
            "category":"Restaurant",
            "type":"Food & Drink"
        }
    ],
    "sg:phone":"+1 610 327 2343",
    "sg:postcode":"19465",
    "sg:province":"PA",
    "wof:name":"Coventry Cafe",
    "wof:placetype":"venue"
},
  "geometry": {"coordinates":[-75.62558199999999,40.228898],"type":"Point"}
}