{
  "type": "Feature",
  "properties": {
    "addr:full":"2400 N 16th St Philadelphia PA 19132",
    "addr:housenumber":"2400",
    "addr:postcode":"19132",
    "addr:street":"N 16Th St",
    "iso:country":"US",
    "sg:address":"2400 N 16th St",
    "sg:city":"Philadelphia",
    "sg:classifiers":[
        {
            "category":"Bars & Pubs",
            "type":"Food & Drink"
        }
    ],
    "sg:phone":"+1   ",
    "sg:postcode":"19132",
    "sg:province":"PA",
    "sg:tags":[
        "drinking"
    ],
    "wof:name":"Red Top 2400 Bar Corp",
    "wof:placetype":"venue"
},
  "geometry": {"coordinates":[-75.15848,39.991271],"type":"Point"}
}