{
  "type": "Feature",
  "properties": {
    "iso:country":"US",
    "sg:address":"722 Memory Ln",
    "sg:city":"South Fork",
    "sg:classifiers":[
        {
            "category":"Professional",
            "subcategory":"Detective & Security Services",
            "type":"Services"
        }
    ],
    "sg:phone":"+1 814 495 3167",
    "sg:postcode":"15956",
    "sg:province":"PA",
    "sg:tags":[
        "investigator"
    ],
    "wof:name":"TIA Investigations",
    "wof:placetype":"venue"
},
  "geometry": {"coordinates":[-78.789078,40.370119],"type":"Point"}
}