{
  "type": "Feature",
  "properties": {
    "iso:country":"US",
    "sg:address":"517 W Norris St",
    "sg:city":"Philadelphia",
    "sg:classifiers":[
        {
            "category":"Retail",
            "subcategory":"Auto Repair",
            "type":"Services"
        }
    ],
    "sg:phone":"+1 215 236 9282",
    "sg:postcode":"19122",
    "sg:province":"PA",
    "sg:tags":[
        "repairing",
        "automobile"
    ],
    "wof:name":"A & M Auto Repair Plus",
    "wof:placetype":"venue"
},
  "geometry": {"coordinates":[-75.14339,39.981455],"type":"Point"}
}