{
  "type": "Feature",
  "properties": {
    "iso:country":"US",
    "sg:address":"295 Chicora Rd",
    "sg:city":"Butler",
    "sg:classifiers":[
        {
            "category":"Recreation",
            "type":"Entertainment"
        }
    ],
    "sg:phone":"+1   ",
    "sg:postcode":"16001",
    "sg:province":"PA",
    "wof:name":"Williams Driving Range",
    "wof:placetype":"venue"
},
  "geometry": {"coordinates":[-79.85887,40.888301],"type":"Point"}
}