{
  "type": "Feature",
  "properties": {
    "addr:full":"221 Greenwood Ave Jenkintown PA 19046",
    "addr:housenumber":"221",
    "addr:postcode":"19046",
    "addr:street":"Greenwood Ave",
    "iso:country":"US",
    "sg:address":"221 Greenwood Ave",
    "sg:city":"Jenkintown",
    "sg:classifiers":[
        {
            "category":"Home & Garden",
            "subcategory":"Building Materials",
            "type":"Retail Goods"
        }
    ],
    "sg:phone":"+1 215 517 6834",
    "sg:postcode":"19046",
    "sg:province":"PA",
    "sg:tags":[
        "glass",
        "leaded"
    ],
    "wof:name":"Khaisman Studio Inc",
    "wof:placetype":"venue"
},
  "geometry": {"coordinates":[-75.132546,40.093988],"type":"Point"}
}