{
  "type": "Feature",
  "properties": {
    "iso:country":"US",
    "sg:address":"102 W Hanover St",
    "sg:city":"Spring Grove",
    "sg:classifiers":[
        {
            "category":"Retail",
            "subcategory":"Animal Services",
            "type":"Services"
        }
    ],
    "sg:phone":"+1 717 225 9000",
    "sg:postcode":"17362",
    "sg:province":"PA",
    "wof:name":"Pretty Pup",
    "wof:placetype":"venue"
},
  "geometry": {"coordinates":[-76.867947,39.880978],"type":"Point"}
}