{
  "type": "Feature",
  "properties": {
    "iso:country":"US",
    "sg:address":"910 W 4th St",
    "sg:city":"Lewistown",
    "sg:classifiers":[
        {
            "category":"Food & Beverages",
            "subcategory":"Groceries & Convenience Stores",
            "type":"Retail Goods"
        }
    ],
    "sg:phone":"+1   ",
    "sg:postcode":"17044",
    "sg:province":"PA",
    "wof:name":"Uni-Mart",
    "wof:placetype":"venue"
},
  "geometry": {"coordinates":[-77.595225,40.591198],"type":"Point"}
}