{
  "type": "Feature",
  "properties": {
    "iso:country":"US",
    "sg:address":"201 Weldon St",
    "sg:city":"Latrobe",
    "sg:classifiers":[
        {
            "category":"Organizations",
            "subcategory":"Community Association",
            "type":"Services"
        }
    ],
    "sg:phone":"+1 724 537 7511",
    "sg:postcode":"15650",
    "sg:province":"PA",
    "sg:tags":[
        "membership",
        "cl"
    ],
    "wof:name":"White Eagle Society",
    "wof:placetype":"venue"
},
  "geometry": {"coordinates":[-79.384153,40.315659],"type":"Point"}
}