{
  "type": "Feature",
  "properties": {
    "iso:country":"US",
    "sg:address":"4021 W 12th St",
    "sg:city":"Erie",
    "sg:classifiers":[
        {
            "category":"Banks & Credit Unions",
            "subcategory":"Investment Brokerage",
            "type":"Services"
        },
        {
            "category":"Professional",
            "subcategory":"Management & Consulting",
            "type":"Services"
        }
    ],
    "sg:phone":"+1 814 836 1038",
    "sg:postcode":"16505",
    "sg:province":"PA",
    "sg:tags":[
        "retirement",
        "planning"
    ],
    "wof:name":"Scalise & Associates",
    "wof:placetype":"venue"
},
  "geometry": {"coordinates":[-80.172579,42.089756],"type":"Point"}
}