{
  "type": "Feature",
  "properties": {
    "iso:country":"US",
    "sg:address":"260 S River St",
    "sg:city":"Plains",
    "sg:classifiers":[
        {
            "category":"Autos & Motor Vehicles",
            "subcategory":"Automobile Sales",
            "type":"Retail Goods"
        },
        {
            "category":"Professional",
            "subcategory":"Business Services",
            "type":"Services"
        }
    ],
    "sg:phone":"+1 570 823 8656",
    "sg:postcode":"18705",
    "sg:province":"PA",
    "sg:tags":[
        "used",
        "license"
    ],
    "wof:name":"Global Auto Mart",
    "wof:placetype":"venue"
},
  "geometry": {"coordinates":[-75.862734,41.26864],"type":"Point"}
}