{
  "type": "Feature",
  "properties": {
    "iso:country":"US",
    "sg:address":"132 Wildwood Rd",
    "sg:city":"Midland",
    "sg:classifiers":[
        {
            "category":"Building & Trades",
            "subcategory":"Landscaping Services",
            "type":"Services"
        }
    ],
    "sg:phone":"+1   ",
    "sg:postcode":"15059",
    "sg:province":"PA",
    "wof:name":"Whole Nine Yards Ldscpg Svc",
    "wof:placetype":"venue"
},
  "geometry": {"coordinates":[-80.48878999999999,40.695435],"type":"Point"}
}