{
  "type": "Feature",
  "properties": {
    "iso:country":"US",
    "sg:address":"1704 Locust St",
    "sg:city":"Philadelphia",
    "sg:classifiers":[
        {
            "category":"Education",
            "subcategory":"Vocational School",
            "type":"Public Place"
        }
    ],
    "sg:phone":"+1   ",
    "sg:postcode":"19103",
    "sg:province":"PA",
    "sg:tags":[
        "legal"
    ],
    "wof:name":"Keystone Intelligence Network",
    "wof:placetype":"venue"
},
  "geometry": {"coordinates":[-75.170132,39.948817],"type":"Point"}
}