{
  "type": "Feature",
  "properties": {
    "addr:full":"35 Arbor Ln Wayne PA 19087",
    "addr:housenumber":"35",
    "addr:postcode":"19087",
    "addr:street":"Arbor Ln",
    "iso:country":"US",
    "sg:address":"35 Arbor Ln",
    "sg:city":"Wayne",
    "sg:classifiers":[
        {
            "category":"Building & Trades",
            "subcategory":"Construction",
            "type":"Services"
        }
    ],
    "sg:phone":"+1   ",
    "sg:postcode":"19087",
    "sg:province":"PA",
    "sg:tags":[
        "contractor"
    ],
    "wof:name":"Richard Love Remodeling",
    "wof:placetype":"venue"
},
  "geometry": {"coordinates":[-75.41471900000001,40.063522],"type":"Point"}
}