{
  "type": "Feature",
  "properties": {
    "iso:country":"US",
    "sg:address":"921 E Main St Exd",
    "sg:city":"Grove City",
    "sg:classifiers":[
        {
            "category":"Local Transit",
            "type":"Transportation"
        }
    ],
    "sg:phone":"+1 724 458 6301",
    "sg:postcode":"16127",
    "sg:province":"PA",
    "sg:tags":[
        "ambulance"
    ],
    "wof:name":"Superior Ambulance Svc",
    "wof:placetype":"venue"
},
  "geometry": {"coordinates":[-80.03975800000001,41.140885],"type":"Point"}
}