{
  "type": "Feature",
  "properties": {
    "iso:country":"US",
    "sg:address":"23 E Main St",
    "sg:city":"Lititz",
    "sg:classifiers":[
        {
            "category":"Shopping",
            "subcategory":"Gifts & Souvenirs",
            "type":"Retail Goods"
        }
    ],
    "sg:phone":"+1   ",
    "sg:postcode":"17543",
    "sg:province":"PA",
    "sg:tags":[
        "shop",
        "delivery",
        "balloon",
        "decorating",
        "party"
    ],
    "wof:name":"Absolutely Balloney",
    "wof:placetype":"venue"
},
  "geometry": {"coordinates":[-76.305809,40.157061],"type":"Point"}
}