{
  "type": "Feature",
  "properties": {
    "addr:full":"141 Creek Rd Camp Hill PA 17011",
    "addr:housenumber":"141",
    "addr:postcode":"17011",
    "addr:street":"Creek Rd",
    "iso:country":"US",
    "sg:address":"141 Creek Rd",
    "sg:city":"Camp Hill",
    "sg:classifiers":[
        {
            "category":"Retail",
            "subcategory":"Auto Repair",
            "type":"Services"
        }
    ],
    "sg:phone":"+1 717 737 4880",
    "sg:postcode":"17011",
    "sg:province":"PA",
    "sg:tags":[
        "body",
        "shop"
    ],
    "wof:name":"Auto Body Pros Inc",
    "wof:placetype":"venue"
},
  "geometry": {"coordinates":[-76.906502,40.224499],"type":"Point"}
}