{
  "type": "Feature",
  "properties": {
    "iso:country":"US",
    "sg:address":"1495 Huffs Church Rd",
    "sg:city":"Barto",
    "sg:classifiers":[
        {
            "category":"Organizations",
            "subcategory":"Community Association",
            "type":"Services"
        }
    ],
    "sg:phone":"+1 610 845 9952",
    "sg:postcode":"19504",
    "sg:province":"PA",
    "sg:tags":[
        "club"
    ],
    "wof:name":"Philadelphia Hungarian Sport",
    "wof:placetype":"venue"
},
  "geometry": {"coordinates":[-75.597881,40.436317],"type":"Point"}
}