{
  "type": "Feature",
  "properties": {
    "iso:country":"US",
    "sg:address":"27 W Temple Ave",
    "sg:city":"Sellersville",
    "sg:classifiers":[
        {
            "category":"Health Services",
            "subcategory":"Doctor",
            "type":"Services"
        }
    ],
    "sg:phone":"+1 215 257 8184",
    "sg:postcode":"18960",
    "sg:province":"PA",
    "sg:tags":[
        "dentist"
    ],
    "wof:name":"William V Spear DDS",
    "wof:placetype":"venue"
},
  "geometry": {"coordinates":[-75.31137099999999,40.359627],"type":"Point"}
}