{
  "type": "Feature",
  "properties": {
    "iso:country":"US",
    "sg:address":"1725 E 3rd St",
    "sg:city":"Williamsport",
    "sg:classifiers":[
        {
            "category":"Shopping",
            "subcategory":"Stationery & Office Supplies",
            "type":"Retail Goods"
        }
    ],
    "sg:phone":"+1 570 323 8292",
    "sg:postcode":"17701",
    "sg:province":"PA",
    "sg:tags":[
        "professional",
        "equipment"
    ],
    "wof:name":"Learning Works",
    "wof:placetype":"venue"
},
  "geometry": {"coordinates":[-76.970304,41.250211],"type":"Point"}
}