{
  "type": "Feature",
  "properties": {
    "iso:country":"US",
    "sg:address":"2450 Ionoff Rd",
    "sg:city":"Harrisburg",
    "sg:classifiers":[
        {
            "category":"Real Estate",
            "subcategory":"Real Estate Operator",
            "type":"Services"
        }
    ],
    "sg:phone":"+1 717 652 9938",
    "sg:postcode":"17110",
    "sg:province":"PA",
    "sg:tags":[
        "building",
        "parks"
    ],
    "wof:name":"Paxton Crossing Community Bldg",
    "wof:placetype":"venue"
},
  "geometry": {"coordinates":[-76.856787,40.309596],"type":"Point"}
}