{
  "type": "Feature",
  "properties": {
    "iso:country":"US",
    "sg:address":"200 Cottage Hill Ave",
    "sg:city":"Butler",
    "sg:classifiers":[
        {
            "category":"Manufacturing",
            "subcategory":"Tools & Machinery",
            "type":"Manufacturing & Wholesale Goods"
        },
        {
            "category":"Retail",
            "subcategory":"Repair Shop",
            "type":"Services"
        }
    ],
    "sg:phone":"+1 724 282 0037",
    "sg:postcode":"16001",
    "sg:province":"PA",
    "sg:tags":[
        "machine",
        "machinery-rebuild"
    ],
    "wof:name":"Cooper Machining",
    "wof:placetype":"venue"
},
  "geometry": {"coordinates":[-79.89300900000001,40.850749],"type":"Point"}
}