{
  "type": "Feature",
  "properties": {
    "iso:country":"US",
    "sg:address":"24 Centennial Rd",
    "sg:city":"Telford",
    "sg:classifiers":[
        {
            "category":"Wholesale",
            "subcategory":"Stationery",
            "type":"Manufacturing & Wholesale Goods"
        }
    ],
    "sg:phone":"+1 215 723 4776",
    "sg:postcode":"18969",
    "sg:province":"PA",
    "sg:tags":[
        "form",
        "system",
        "business",
        "supply"
    ],
    "wof:name":"Forms & Systems",
    "wof:placetype":"venue"
},
  "geometry": {"coordinates":[-75.315135,40.327745],"type":"Point"}
}