{
  "type": "Feature",
  "properties": {
    "addr:full":"1302 E Washington St New Castle PA 16101",
    "addr:housenumber":"1302",
    "addr:postcode":"16101",
    "addr:street":"E Washington St",
    "iso:country":"US",
    "sg:address":"1302 E Washington St",
    "sg:city":"New Castle",
    "sg:classifiers":[
        {
            "category":"Organizations",
            "subcategory":"Religious Organization",
            "type":"Services"
        }
    ],
    "sg:phone":"+1 724 658 8009",
    "sg:postcode":"16101",
    "sg:province":"PA",
    "sg:tags":[
        "church"
    ],
    "wof:name":"Christ Lutheran Church",
    "wof:placetype":"venue"
},
  "geometry": {"coordinates":[-80.326992,40.986484],"type":"Point"}
}