{
  "type": "Feature",
  "properties": {
    "iso:country":"US",
    "sg:address":"1643 Bridgeton Hill Rd",
    "sg:city":"Upper Black Eddy",
    "sg:classifiers":[
        {
            "category":"Building & Trades",
            "subcategory":"Construction",
            "type":"Services"
        }
    ],
    "sg:phone":"+1 610 982 5195",
    "sg:postcode":"18972",
    "sg:province":"PA",
    "sg:tags":[
        "concrete",
        "contractor"
    ],
    "wof:name":"Durnan Brothers Inc",
    "wof:placetype":"venue"
},
  "geometry": {"coordinates":[-75.104118,40.565501],"type":"Point"}
}