{
  "type": "Feature",
  "properties": {
    "iso:country":"US",
    "sg:address":"1901 W Tioga St",
    "sg:city":"Philadelphia",
    "sg:classifiers":[
        {
            "category":"Organizations",
            "subcategory":"Religious Organization",
            "type":"Services"
        }
    ],
    "sg:phone":"+1 215 225 5262",
    "sg:postcode":"19140",
    "sg:province":"PA",
    "sg:tags":[
        "church"
    ],
    "wof:name":"Our Lady Of Hope-Tioga",
    "wof:placetype":"venue"
},
  "geometry": {"coordinates":[-75.16125599999999,40.007377],"type":"Point"}
}