{
  "type": "Feature",
  "properties": {
    "iso:country":"US",
    "sg:address":"782 W Pitt St",
    "sg:city":"Bedford",
    "sg:classifiers":[
        {
            "category":"Manufacturing",
            "subcategory":"Signs",
            "type":"Manufacturing & Wholesale Goods"
        },
        {
            "category":"Manufacturing",
            "subcategory":"Motor Vehicles & Parts",
            "type":"Manufacturing & Wholesale Goods"
        }
    ],
    "sg:phone":"+1 814 623 2751",
    "sg:postcode":"15522",
    "sg:province":"PA",
    "sg:tags":[
        "commercial",
        "mfg",
        "design",
        "trimming"
    ],
    "sg:website":"www.huntssigns.com",
    "wof:name":"Hunt's Promotions",
    "wof:placetype":"venue"
},
  "geometry": {"coordinates":[-78.518238,40.024208],"type":"Point"}
}