{
  "type": "Feature",
  "properties": {
    "iso:country":"US",
    "sg:address":"105 Chestnut St",
    "sg:city":"Philadelphia",
    "sg:classifiers":[
        {
            "category":"Personal",
            "type":"Services"
        },
        {
            "category":"Retail",
            "subcategory":"Laundry & Dry Cleaning",
            "type":"Services"
        }
    ],
    "sg:phone":"+1 215 427 2550",
    "sg:postcode":"19106",
    "sg:province":"PA",
    "sg:tags":[
        "sewing",
        "alteration"
    ],
    "wof:name":"Steve's Olde City Cleaners and Tailor",
    "wof:placetype":"venue"
},
  "geometry": {"coordinates":[-75.142805,39.948362],"type":"Point"}
}