{
  "type": "Feature",
  "properties": {
    "iso:country":"US",
    "sg:address":"1432 Unity St",
    "sg:city":"Philadelphia",
    "sg:classifiers":[
        {
            "category":"Building & Trades",
            "subcategory":"Construction",
            "type":"Services"
        }
    ],
    "sg:phone":"+1 215 743 5613",
    "sg:postcode":"19124",
    "sg:province":"PA",
    "sg:tags":[
        "concrete",
        "contractor"
    ],
    "wof:name":"General Contractor Stoica",
    "wof:placetype":"venue"
},
  "geometry": {"coordinates":[-75.08949800000001,40.013601],"type":"Point"}
}