{
  "type": "Feature",
  "properties": {
    "iso:country":"US",
    "sg:address":"4502 Coventry Rd",
    "sg:city":"Harrisburg",
    "sg:classifiers":[
        {
            "category":"Government",
            "subcategory":"Office",
            "type":"Public Place"
        }
    ],
    "sg:phone":"+1   ",
    "sg:postcode":"17109",
    "sg:province":"PA",
    "sg:tags":[
        "administrative",
        "program",
        "economic",
        "general"
    ],
    "wof:name":"Whclist Tax Force",
    "wof:placetype":"venue"
},
  "geometry": {"coordinates":[-76.817875,40.308409],"type":"Point"}
}