{
  "type": "Feature",
  "properties": {
    "iso:country":"US",
    "sg:address":"540 S Main St",
    "sg:city":"Zelienople",
    "sg:classifiers":[
        {
            "category":"Autos & Motor Vehicles",
            "subcategory":"Automobile Sales",
            "type":"Retail Goods"
        }
    ],
    "sg:phone":"+1 724 453 3673",
    "sg:postcode":"16063",
    "sg:province":"PA",
    "sg:tags":[
        "car"
    ],
    "wof:name":"Northland Ford Inc",
    "wof:placetype":"venue"
},
  "geometry": {"coordinates":[-80.135597,40.787899],"type":"Point"}
}