{
  "type": "Feature",
  "properties": {
    "iso:country":"US",
    "sg:address":"6 Butler St",
    "sg:city":"Pittsburgh",
    "sg:classifiers":[
        {
            "category":"Building & Trades",
            "subcategory":"Construction",
            "type":"Services"
        }
    ],
    "sg:phone":"+1   ",
    "sg:postcode":"15209",
    "sg:province":"PA",
    "sg:tags":[
        "floor",
        "laying",
        "contractor"
    ],
    "wof:name":"Young Home Improvements",
    "wof:placetype":"venue"
},
  "geometry": {"coordinates":[-79.972956,40.479745],"type":"Point"}
}