{
  "type": "Feature",
  "properties": {
    "iso:country":"US",
    "sg:address":"397 Pleasant Dr",
    "sg:city":"Warren",
    "sg:classifiers":[
        {
            "category":"Professional",
            "type":"Services"
        }
    ],
    "sg:phone":"+1   ",
    "sg:postcode":"16365",
    "sg:province":"PA",
    "wof:name":"Randall Zinger",
    "wof:placetype":"venue"
},
  "geometry": {"coordinates":[-79.16259700000001,41.830179],"type":"Point"}
}