{
  "type": "Feature",
  "properties": {
    "iso:country":"US",
    "sg:address":"230 S Williamson Rd",
    "sg:city":"Blossburg",
    "sg:classifiers":[
        {
            "category":"Organizations",
            "subcategory":"Community Association",
            "type":"Services"
        }
    ],
    "sg:phone":"+1   ",
    "sg:postcode":"16912",
    "sg:province":"PA",
    "wof:name":"VFW 8730 Blossburg Suprem",
    "wof:placetype":"venue"
},
  "geometry": {"coordinates":[-77.073215,41.668788],"type":"Point"}
}