{
  "type": "Feature",
  "properties": {
    "iso:country":"US",
    "sg:address":"5114 3rd St",
    "sg:city":"Whitehall",
    "sg:classifiers":[
        {
            "category":"Local Transit",
            "type":"Transportation"
        }
    ],
    "sg:phone":"+1 610 262 6484",
    "sg:postcode":"18052",
    "sg:province":"PA",
    "sg:tags":[
        "ambulance"
    ],
    "wof:name":"Cetronia Ambulance Corps",
    "wof:placetype":"venue"
},
  "geometry": {"coordinates":[-75.508768,40.688811],"type":"Point"}
}