{
  "type": "Feature",
  "properties": {
    "iso:country":"US",
    "sg:address":"3431 W 26th St",
    "sg:city":"Erie",
    "sg:classifiers":[
        {
            "category":"Personal",
            "subcategory":"Tanning Parlor",
            "type":"Services"
        },
        {
            "category":"Personal",
            "type":"Services"
        }
    ],
    "sg:phone":"+1 814 836 5887",
    "sg:postcode":"16506",
    "sg:province":"PA",
    "sg:tags":[
        "salon"
    ],
    "wof:name":"Sun Escape Tanning Center",
    "wof:placetype":"venue"
},
  "geometry": {"coordinates":[-80.151837,42.082788],"type":"Point"}
}