{
  "type": "Feature",
  "properties": {
    "addr:full":"117 E Blade Dr Penn Furnace PA 16865",
    "addr:housenumber":"117",
    "addr:postcode":"16865",
    "addr:street":"E Blade Dr",
    "iso:country":"US",
    "sg:address":"117 E Blade Dr",
    "sg:city":"Penn Furnace",
    "sg:classifiers":[
        {
            "category":"Personal",
            "subcategory":"Beauty Salon",
            "type":"Services"
        }
    ],
    "sg:phone":"+1 814 238 1755",
    "sg:postcode":"16865",
    "sg:province":"PA",
    "wof:name":"Noreen's Beauty Salon",
    "wof:placetype":"venue"
},
  "geometry": {"coordinates":[-77.95224899999999,40.719918],"type":"Point"}
}