{
  "type": "Feature",
  "properties": {
    "iso:country":"US",
    "sg:address":"1000 Skiles Blvd",
    "sg:city":"West Chester",
    "sg:classifiers":[
        {
            "category":"Banks & Credit Unions",
            "subcategory":"Bank",
            "type":"Services"
        }
    ],
    "sg:phone":"+1 610 455 3803",
    "sg:postcode":"19382",
    "sg:province":"PA",
    "wof:name":"Malvern Federal Avings Savings Bank",
    "wof:placetype":"venue"
},
  "geometry": {"coordinates":[-75.58317099999999,39.931013],"type":"Point"}
}