{
  "type": "Feature",
  "properties": {
    "iso:country":"US",
    "sg:address":"23 Forest Dr",
    "sg:city":"Doylestown",
    "sg:classifiers":[
        {
            "category":"Professional",
            "subcategory":"Art Services",
            "type":"Services"
        }
    ],
    "sg:phone":"+1 215 340 1004",
    "sg:postcode":"18901",
    "sg:province":"PA",
    "sg:tags":[
        "graphic",
        "designer"
    ],
    "sg:website":"www.pigart.com",
    "wof:name":"Pig Art Graphic Design",
    "wof:placetype":"venue"
},
  "geometry": {"coordinates":[-75.116249,40.314095],"type":"Point"}
}