{
  "type": "Feature",
  "properties": {
    "iso:country":"US",
    "sg:address":"54 E Corydon St",
    "sg:city":"Bradford",
    "sg:classifiers":[
        {
            "category":"Organizations",
            "subcategory":"Religious Organization",
            "type":"Services"
        }
    ],
    "sg:phone":"+1 814 362 5569",
    "sg:postcode":"16701",
    "sg:province":"PA",
    "sg:tags":[
        "church"
    ],
    "wof:name":"First Presbyterian Church",
    "wof:placetype":"venue"
},
  "geometry": {"coordinates":[-78.649126,41.9547],"type":"Point"}
}