{
  "type": "Feature",
  "properties": {
    "addr:full":"129 Laurel Ct Quakertown PA 18951",
    "addr:housenumber":"129",
    "addr:postcode":"18951",
    "addr:street":"Laurel Ct",
    "iso:country":"US",
    "sg:address":"129 Laurel Ct",
    "sg:city":"Quakertown",
    "sg:classifiers":[
        {
            "category":"Wholesale",
            "subcategory":"Machinery & Supplies",
            "type":"Manufacturing & Wholesale Goods"
        }
    ],
    "sg:phone":"+1   ",
    "sg:postcode":"18951",
    "sg:province":"PA",
    "sg:tags":[
        "company",
        "vending"
    ],
    "wof:name":"Seidel Enterprises",
    "wof:placetype":"venue"
},
  "geometry": {"coordinates":[-75.341829,40.424391],"type":"Point"}
}