{
  "type": "Feature",
  "properties": {
    "iso:country":"US",
    "sg:address":"552 Church Rd",
    "sg:city":"Elkins Park",
    "sg:classifiers":[
        {
            "category":"Banks & Credit Unions",
            "subcategory":"Bank",
            "type":"Services"
        }
    ],
    "sg:phone":"+1 215 635 5801",
    "sg:postcode":"19027",
    "sg:province":"PA",
    "sg:tags":[
        "loan"
    ],
    "wof:name":"Royal Financial Svc Corp",
    "wof:placetype":"venue"
},
  "geometry": {"coordinates":[-75.126347,40.075893],"type":"Point"}
}