{
  "type": "Feature",
  "properties": {
    "iso:country":"US",
    "sg:address":"2115 Price St",
    "sg:city":"Scranton",
    "sg:classifiers":[
        {
            "category":"Building & Trades",
            "subcategory":"Construction",
            "type":"Services"
        }
    ],
    "sg:phone":"+1 570 961 2703",
    "sg:postcode":"18504",
    "sg:province":"PA",
    "sg:tags":[
        "roofing",
        "industrial",
        "contractors-commercial",
        "contractor"
    ],
    "wof:name":"Thomas Davis Roofing",
    "wof:placetype":"venue"
},
  "geometry": {"coordinates":[-75.69184199999999,41.419585],"type":"Point"}
}