{
  "type": "Feature",
  "properties": {
    "iso:country":"US",
    "sg:address":"9865 Lincoln Hwy",
    "sg:city":"Bedford",
    "sg:classifiers":[
        {
            "category":"Shopping",
            "subcategory":"Jewelry",
            "type":"Retail Goods"
        },
        {
            "category":"Insurance",
            "subcategory":"Insurance Agent",
            "type":"Services"
        }
    ],
    "sg:phone":"+1 814 623 9084",
    "sg:postcode":"15537",
    "sg:province":"PA",
    "sg:tags":[
        "jeweler"
    ],
    "wof:name":"Warren C Burr & Associates",
    "wof:placetype":"venue"
},
  "geometry": {"coordinates":[-78.47039599999999,40.014511],"type":"Point"}
}