{
  "type": "Feature",
  "properties": {
    "iso:country":"US",
    "sg:address":"285 Bellevue Rd",
    "sg:city":"Pittsburgh",
    "sg:classifiers":[
        {
            "category":"Social Services",
            "subcategory":"Child Care",
            "type":"Services"
        }
    ],
    "sg:phone":"+1 412 931 9761",
    "sg:postcode":"15229",
    "sg:province":"PA",
    "sg:tags":[
        "kindergarten",
        "academic",
        "school"
    ],
    "sg:website":"www.mtnazarethcenter.org",
    "wof:name":"Mt Nazareth Ctr Inc",
    "wof:placetype":"venue"
},
  "geometry": {"coordinates":[-80.03955499999999,40.507095],"type":"Point"}
}