{
  "type": "Feature",
  "properties": {
    "iso:country":"US",
    "sg:address":"342 Monroe St",
    "sg:city":"East Stroudsburg",
    "sg:classifiers":[
        {
            "category":"Building & Trades",
            "subcategory":"Construction",
            "type":"Services"
        }
    ],
    "sg:phone":"+1   ",
    "sg:postcode":"18301",
    "sg:province":"PA",
    "sg:tags":[
        "house"
    ],
    "wof:name":"Graeff Construction",
    "wof:placetype":"venue"
},
  "geometry": {"coordinates":[-75.191801,41.013971],"type":"Point"}
}