{
  "type": "Feature",
  "properties": {
    "iso:country":"US",
    "sg:address":"1103 W 26th St",
    "sg:city":"Erie",
    "sg:classifiers":[
        {
            "category":"Autos & Motor Vehicles",
            "subcategory":"Fuel & Gas Station",
            "type":"Retail Goods"
        }
    ],
    "sg:phone":"+1 814 868 1393",
    "sg:postcode":"16508",
    "sg:province":"PA",
    "sg:tags":[
        "repair",
        "station",
        "general"
    ],
    "wof:name":"Elmwood Auto Sales",
    "wof:placetype":"venue"
},
  "geometry": {"coordinates":[-80.098997,42.102468],"type":"Point"}
}