{
  "type": "Feature",
  "properties": {
    "iso:country":"US",
    "sg:address":"3007 Old Philadelphia Pike",
    "sg:city":"Bird In Hand",
    "sg:classifiers":[
        {
            "category":"Freight",
            "type":"Transportation"
        }
    ],
    "sg:phone":"+1 717 768 3299",
    "sg:postcode":"17505",
    "sg:province":"PA",
    "sg:tags":[
        "carriage"
    ],
    "wof:name":"Weavertown Coach Shop",
    "wof:placetype":"venue"
},
  "geometry": {"coordinates":[-76.145039,40.038768],"type":"Point"}
}