{
  "type": "Feature",
  "properties": {
    "addr:full":"130 Commonwealth Dr Warrendale PA 15086",
    "addr:housenumber":"130",
    "addr:postcode":"15086",
    "addr:street":"Commonwealth Dr",
    "iso:country":"US",
    "sg:address":"130 Commonwealth Dr",
    "sg:city":"Warrendale",
    "sg:classifiers":[
        {
            "category":"Professional",
            "subcategory":"Engineering",
            "type":"Services"
        }
    ],
    "sg:phone":"+1 724 779 5800",
    "sg:postcode":"15086",
    "sg:province":"PA",
    "sg:tags":[
        "engineer"
    ],
    "sg:website":"www.eatonelectrical.com",
    "wof:name":"Cutler Hammer",
    "wof:placetype":"venue"
},
  "geometry": {"coordinates":[-80.102311,40.667625],"type":"Point"}
}