{
  "type": "Feature",
  "properties": {
    "iso:country":"US",
    "sg:address":"635 Toby Rd",
    "sg:city":"Kersey",
    "sg:classifiers":[
        {
            "category":"Utilities",
            "subcategory":"Refuse",
            "type":"Services"
        }
    ],
    "sg:phone":"+1   ",
    "sg:postcode":"15846",
    "sg:province":"PA",
    "sg:tags":[
        "disposal"
    ],
    "wof:name":"Superior Landfill LLC",
    "wof:placetype":"venue"
},
  "geometry": {"coordinates":[-78.66535500000001,41.301126],"type":"Point"}
}