{
  "type": "Feature",
  "properties": {
    "iso:country":"US",
    "sg:address":"2285 Schoenersville Rd",
    "sg:city":"Bethlehem",
    "sg:classifiers":[
        {
            "category":"Education",
            "subcategory":"Vocational School",
            "type":"Public Place"
        }
    ],
    "sg:phone":"+1 610 867 6600",
    "sg:postcode":"18017",
    "sg:province":"PA",
    "sg:tags":[
        "real estate"
    ],
    "wof:name":"Scott-White Real Estate Inst",
    "wof:placetype":"venue"
},
  "geometry": {"coordinates":[-75.400756,40.640667],"type":"Point"}
}