{
  "type": "Feature",
  "properties": {
    "iso:country":"US",
    "sg:address":"801 E Germantown Pike",
    "sg:city":"Plymouth Meeting",
    "sg:classifiers":[
        {
            "category":"Insurance",
            "subcategory":"Insurance Agent",
            "type":"Services"
        }
    ],
    "sg:phone":"+1 610 292 8670",
    "sg:postcode":"19462",
    "sg:province":"PA",
    "wof:name":"Dublin Hall Brokers Inc",
    "wof:placetype":"venue"
},
  "geometry": {"coordinates":[-75.297163,40.127279],"type":"Point"}
}