{
  "type": "Feature",
  "properties": {
    "iso:country":"US",
    "sg:address":"7219 McKnight Rd",
    "sg:city":"Pittsburgh",
    "sg:classifiers":[
        {
            "category":"Banks & Credit Unions",
            "subcategory":"Bank",
            "type":"Services"
        }
    ],
    "sg:phone":"+1 412 367 6225",
    "sg:postcode":"15237",
    "sg:province":"PA",
    "sg:tags":[
        "financing"
    ],
    "wof:name":"Beneficial Consumer Discount",
    "wof:placetype":"venue"
},
  "geometry": {"coordinates":[-80.013846,40.542919],"type":"Point"}
}