{
  "type": "Feature",
  "properties": {
    "iso:country":"US",
    "sg:address":"1721 Chandler St",
    "sg:city":"Philadelphia",
    "sg:classifiers":[
        {
            "category":"Professional",
            "type":"Services"
        }
    ],
    "sg:phone":"+1 215 742 0583",
    "sg:postcode":"19111",
    "sg:province":"PA",
    "wof:name":"Elizabeth Strange Corp",
    "wof:placetype":"venue"
},
  "geometry": {"coordinates":[-75.062951,40.060978],"type":"Point"}
}