{
  "type": "Feature",
  "properties": {
    "iso:country":"US",
    "sg:address":"1518 Manley Rd",
    "sg:city":"West Chester",
    "sg:classifiers":[
        {
            "category":"Real Estate",
            "subcategory":"Real Estate Agent",
            "type":"Services"
        }
    ],
    "sg:phone":"+1 610 696 2231",
    "sg:postcode":"19382",
    "sg:province":"PA",
    "wof:name":"John Larkins Realty",
    "wof:placetype":"venue"
},
  "geometry": {"coordinates":[-75.53006000000001,39.96617],"type":"Point"}
}