{
  "type": "Feature",
  "properties": {
    "iso:country":"US",
    "sg:address":"1524 Locust St",
    "sg:city":"Philadelphia",
    "sg:classifiers":[
        {
            "category":"Professional",
            "subcategory":"Lawyer & Legal Services",
            "type":"Services"
        }
    ],
    "sg:phone":"+1   ",
    "sg:postcode":"19102",
    "sg:province":"PA",
    "sg:tags":[
        "attorney"
    ],
    "wof:name":"Pansini Lssin Attorneys-At-Law",
    "wof:placetype":"venue"
},
  "geometry": {"coordinates":[-75.16771900000001,39.948673],"type":"Point"}
}