{
  "type": "Feature",
  "properties": {
    "iso:country":"US",
    "sg:address":"8351 Hegerman St",
    "sg:city":"Philadelphia",
    "sg:classifiers":[
        {
            "category":"Manufacturing",
            "subcategory":"Buildings",
            "type":"Manufacturing & Wholesale Goods"
        },
        {
            "category":"Structure",
            "subcategory":"Warehouse",
            "type":"Public Place"
        },
        {
            "category":"Building & Trades",
            "subcategory":"Construction",
            "type":"Services"
        }
    ],
    "sg:phone":"+1 215 333 6688",
    "sg:postcode":"19136",
    "sg:province":"PA",
    "sg:tags":[
        "warehouses-merchandise",
        "warehouses-public-commercial",
        "builder",
        "contractor",
        "home",
        "estimate"
    ],
    "wof:name":"Elite MS Construction",
    "wof:placetype":"venue"
},
  "geometry": {"coordinates":[-75.015242,40.038976],"type":"Point"}
}