{
  "type": "Feature",
  "properties": {
    "addr:full":"330 Canal St Leechburg PA 15656",
    "addr:housenumber":"330",
    "addr:postcode":"15656",
    "addr:street":"Canal St",
    "iso:country":"US",
    "sg:address":"330 Canal St",
    "sg:city":"Leechburg",
    "sg:classifiers":[
        {
            "category":"Retail",
            "subcategory":"Auto Repair",
            "type":"Services"
        }
    ],
    "sg:phone":"+1 724 845 5917",
    "sg:postcode":"15656",
    "sg:province":"PA",
    "sg:tags":[
        "repairing",
        "automobile"
    ],
    "wof:name":"Stan's Auto Svc",
    "wof:placetype":"venue"
},
  "geometry": {"coordinates":[-79.598349,40.627547],"type":"Point"}
}