{
  "type": "Feature",
  "properties": {
    "iso:country":"US",
    "sg:address":"712 Reynolds St",
    "sg:city":"Youngwood",
    "sg:classifiers":[
        {
            "category":"Travel",
            "subcategory":"Hotels & Motels",
            "type":"Entertainment"
        }
    ],
    "sg:phone":"+1 724 925 3294",
    "sg:postcode":"15697",
    "sg:province":"PA",
    "wof:name":"Cedar Lounge & Motel",
    "wof:placetype":"venue"
},
  "geometry": {"coordinates":[-79.58679600000001,40.229725],"type":"Point"}
}