{
  "type": "Feature",
  "properties": {
    "iso:country":"US",
    "sg:address":"8 Brunswick Ln",
    "sg:city":"Palmyra",
    "sg:classifiers":[
        {
            "category":"Professional",
            "subcategory":"Accounting & Tax Preparation",
            "type":"Services"
        }
    ],
    "sg:phone":"+1   ",
    "sg:postcode":"17078",
    "sg:province":"PA",
    "wof:name":"Donna Rambler OBlock CPA",
    "wof:placetype":"venue"
},
  "geometry": {"coordinates":[-76.57131099999999,40.316245],"type":"Point"}
}