{
  "type": "Feature",
  "properties": {
    "iso:country":"US",
    "sg:address":"100 Hospital Rd",
    "sg:city":"Brookville",
    "sg:classifiers":[
        {
            "category":"Health Services",
            "subcategory":"Doctor",
            "type":"Services"
        },
        {
            "category":"Health Services",
            "subcategory":"Clinic",
            "type":"Services"
        }
    ],
    "sg:phone":"+1 814 849 1874",
    "sg:postcode":"15825",
    "sg:province":"PA",
    "sg:tags":[
        "physician",
        "surgeon",
        "osteopathic"
    ],
    "wof:name":"Joseph Prusakowski Dr",
    "wof:placetype":"venue"
},
  "geometry": {"coordinates":[-79.093705,41.155613],"type":"Point"}
}