{
  "type": "Feature",
  "properties": {
    "iso:country":"US",
    "sg:address":"1206 Pine Rd",
    "sg:city":"Effort",
    "sg:classifiers":[
        {
            "category":"Professional",
            "type":"Services"
        }
    ],
    "sg:phone":"+1   ",
    "sg:postcode":"18330",
    "sg:province":"PA",
    "wof:name":"Brass Ring Incentives",
    "wof:placetype":"venue"
},
  "geometry": {"coordinates":[-75.46789800000001,40.977798],"type":"Point"}
}