{
  "type": "Feature",
  "properties": {
    "iso:country":"US",
    "sg:address":"1904 E Hazzard St",
    "sg:city":"Philadelphia",
    "sg:classifiers":[
        {
            "category":"Building & Trades",
            "subcategory":"Locksmith",
            "type":"Services"
        }
    ],
    "sg:phone":"+1 267 299 1207",
    "sg:postcode":"19125",
    "sg:province":"PA",
    "sg:tags":[
        "key"
    ],
    "wof:name":"Locksmith",
    "wof:placetype":"venue"
},
  "geometry": {"coordinates":[-75.12710800000001,39.987309],"type":"Point"}
}