{
  "type": "Feature",
  "properties": {
    "addr:full":"1527 Lovi Rd Freedom PA 15042",
    "addr:housenumber":"1527",
    "addr:postcode":"15042",
    "addr:street":"Lovi Rd",
    "iso:country":"US",
    "sg:address":"1527 Lovi Rd",
    "sg:city":"Freedom",
    "sg:classifiers":[
        {
            "category":"Building & Trades",
            "subcategory":"Construction",
            "type":"Services"
        }
    ],
    "sg:phone":"+1   ",
    "sg:postcode":"15042",
    "sg:province":"PA",
    "sg:tags":[
        "contractor"
    ],
    "wof:name":"Jeff Helbig Construction",
    "wof:placetype":"venue"
},
  "geometry": {"coordinates":[-80.218143,40.696546],"type":"Point"}
}