{
  "type": "Feature",
  "properties": {
    "iso:country":"US",
    "sg:address":"147 Weidman St",
    "sg:city":"Lebanon",
    "sg:classifiers":[
        {
            "category":"Food & Beverages",
            "subcategory":"Groceries & Convenience Stores",
            "type":"Retail Goods"
        }
    ],
    "sg:phone":"+1   ",
    "sg:postcode":"17046",
    "sg:province":"PA",
    "wof:name":"B E Mini Mart",
    "wof:placetype":"venue"
},
  "geometry": {"coordinates":[-76.41437999999999,40.345221],"type":"Point"}
}