{
  "type": "Feature",
  "properties": {
    "addr:full":"534 Allegheny Blvd Franklin PA 16323",
    "addr:housenumber":"534",
    "addr:postcode":"16323",
    "addr:street":"Allegheny Blvd",
    "iso:country":"US",
    "sg:address":"534 Allegheny Blvd",
    "sg:city":"Franklin",
    "sg:classifiers":[
        {
            "category":"Professional",
            "type":"Services"
        }
    ],
    "sg:phone":"+1   ",
    "sg:postcode":"16323",
    "sg:province":"PA",
    "wof:name":"Blair Call Center",
    "wof:placetype":"venue"
},
  "geometry": {"coordinates":[-79.810914,41.401402],"type":"Point"}
}