{
  "type": "Feature",
  "properties": {
    "iso:country":"US",
    "sg:address":"8763 Neuburger Rd",
    "sg:city":"Fairview",
    "sg:classifiers":[
        {
            "category":"Farming",
            "subcategory":"Farm",
            "type":"Manufacturing & Wholesale Goods"
        }
    ],
    "sg:phone":"+1   ",
    "sg:postcode":"16415",
    "sg:province":"PA",
    "sg:tags":[
        "crop",
        "general"
    ],
    "wof:name":"Jim Neuberger",
    "wof:placetype":"venue"
},
  "geometry": {"coordinates":[-80.191391,41.995016],"type":"Point"}
}