{
  "type": "Feature",
  "properties": {
    "iso:country":"US",
    "sg:address":"2335 N 7th St",
    "sg:city":"Philadelphia",
    "sg:classifiers":[
        {
            "category":"Manufacturing",
            "subcategory":"Rubber & Plastics",
            "type":"Manufacturing & Wholesale Goods"
        }
    ],
    "sg:phone":"+1 215 763 1000",
    "sg:postcode":"19133",
    "sg:province":"PA",
    "wof:name":"Flora Craft Inc",
    "wof:placetype":"venue"
},
  "geometry": {"coordinates":[-75.14483799999999,39.987452],"type":"Point"}
}