{
  "type": "Feature",
  "properties": {
    "addr:full":"633 W 3rd St Williamsport PA 17701",
    "addr:housenumber":"633",
    "addr:postcode":"17701",
    "addr:street":"W 3Rd St",
    "iso:country":"US",
    "sg:address":"633 W 3rd St",
    "sg:city":"Williamsport",
    "sg:classifiers":[
        {
            "category":"Autos & Motor Vehicles",
            "subcategory":"Automobile Sales",
            "type":"Retail Goods"
        }
    ],
    "sg:phone":"+1 570 326 5127",
    "sg:postcode":"17701",
    "sg:province":"PA",
    "sg:tags":[
        "car",
        "dealer"
    ],
    "wof:name":"Alexander Nissan",
    "wof:placetype":"venue"
},
  "geometry": {"coordinates":[-77.01320699999999,41.237876],"type":"Point"}
}