{
  "type": "Feature",
  "properties": {
    "iso:country":"US",
    "sg:address":"708 E 5th St",
    "sg:city":"Bethlehem",
    "sg:classifiers":[
        {
            "category":"Food & Beverages",
            "subcategory":"Liquor & Beverages",
            "type":"Retail Goods"
        }
    ],
    "sg:phone":"+1   ",
    "sg:postcode":"18015",
    "sg:province":"PA",
    "sg:tags":[
        "alcoholic"
    ],
    "wof:name":"Purity",
    "wof:placetype":"venue"
},
  "geometry": {"coordinates":[-75.367417,40.60945],"type":"Point"}
}