{
  "type": "Feature",
  "properties": {
    "addr:full":"92 Commerce Dr Warminster PA 18974",
    "addr:housenumber":"92",
    "addr:postcode":"18974",
    "addr:street":"Commerce Dr",
    "iso:country":"US",
    "sg:address":"92 Commerce Dr",
    "sg:city":"Warminster",
    "sg:classifiers":[
        {
            "category":"Retail",
            "subcategory":"Auto Repair",
            "type":"Services"
        }
    ],
    "sg:phone":"+1 215 443 7575",
    "sg:postcode":"18974",
    "sg:province":"PA",
    "sg:tags":[
        "truck"
    ],
    "wof:name":"B C Svc",
    "wof:placetype":"venue"
},
  "geometry": {"coordinates":[-75.06344199999999,40.213595],"type":"Point"}
}