{
  "type": "Feature",
  "properties": {
    "iso:country":"US",
    "sg:address":"1845 Old Mill Rd",
    "sg:city":"Bethlehem",
    "sg:classifiers":[
        {
            "category":"Health Services",
            "subcategory":"Doctor",
            "type":"Services"
        }
    ],
    "sg:phone":"+1 610 838 6856",
    "sg:postcode":"18015",
    "sg:province":"PA",
    "wof:name":"McBride Jas G MD",
    "wof:placetype":"venue"
},
  "geometry": {"coordinates":[-75.35169999999999,40.563702],"type":"Point"}
}