{
  "type": "Feature",
  "properties": {
    "addr:full":"3460 N Delaware Ave Philadelphia PA 19134",
    "addr:housenumber":"3460",
    "addr:postcode":"19134",
    "addr:street":"N Delaware Ave",
    "iso:country":"US",
    "sg:address":"3460 N Delaware Ave",
    "sg:city":"Philadelphia",
    "sg:classifiers":[
        {
            "category":"Manufacturing",
            "subcategory":"Food",
            "type":"Manufacturing & Wholesale Goods"
        }
    ],
    "sg:phone":"+1 215 739 5057",
    "sg:postcode":"19134",
    "sg:province":"PA",
    "sg:tags":[
        "product",
        "manufacturer"
    ],
    "sg:website":"www.bocchiamericas.com",
    "wof:name":"Bocchi Americas",
    "wof:placetype":"venue"
},
  "geometry": {"coordinates":[-75.089159,39.980432],"type":"Point"}
}