{
  "type": "Feature",
  "properties": {
    "iso:country":"US",
    "sg:address":"1015 Penn Ave",
    "sg:city":"Reading",
    "sg:classifiers":[
        {
            "category":"Professional",
            "subcategory":"Accounting & Tax Preparation",
            "type":"Services"
        }
    ],
    "sg:phone":"+1   ",
    "sg:postcode":"19610",
    "sg:province":"PA",
    "wof:name":"Alderigi Oliver J",
    "wof:placetype":"venue"
},
  "geometry": {"coordinates":[-75.959194,40.335203],"type":"Point"}
}