{
  "type": "Feature",
  "properties": {
    "addr:full":"535 Smith Ln Pittsburgh PA 15205",
    "addr:housenumber":"535",
    "addr:postcode":"15205",
    "addr:street":"Smith Ln",
    "iso:country":"US",
    "sg:address":"535 Smith Ln",
    "sg:city":"Pittsburgh",
    "sg:classifiers":[
        {
            "category":"Professional",
            "subcategory":"Lawyer & Legal Services",
            "type":"Services"
        }
    ],
    "sg:phone":"+1 412 434 8868",
    "sg:postcode":"15205",
    "sg:province":"PA",
    "sg:tags":[
        "attorney"
    ],
    "wof:name":"Rose Schmidt Hasley & Di Salle",
    "wof:placetype":"venue"
},
  "geometry": {"coordinates":[-80.085649,40.43176],"type":"Point"}
}