{
  "type": "Feature",
  "properties": {
    "addr:full":"152 Morgantown St Uniontown PA 15401",
    "addr:housenumber":"152",
    "addr:postcode":"15401",
    "addr:street":"Morgantown St",
    "iso:country":"US",
    "sg:address":"152 Morgantown St",
    "sg:city":"Uniontown",
    "sg:classifiers":[
        {
            "category":"Shopping",
            "subcategory":"Clothing, Apparel, & Fashions",
            "type":"Retail Goods"
        }
    ],
    "sg:phone":"+1 724 438 4270",
    "sg:postcode":"15401",
    "sg:province":"PA",
    "wof:name":"Big Apple Gear",
    "wof:placetype":"venue"
},
  "geometry": {"coordinates":[-79.729851,39.897152],"type":"Point"}
}