{
  "type": "Feature",
  "properties": {
    "iso:country":"US",
    "sg:address":"1326 Chelsea Ave",
    "sg:city":"Bethlehem",
    "sg:classifiers":[
        {
            "category":"Personal",
            "subcategory":"Nail Salon",
            "type":"Services"
        }
    ],
    "sg:phone":"+1 610 861 0999",
    "sg:postcode":"18018",
    "sg:province":"PA",
    "wof:name":"Paris Salon",
    "wof:placetype":"venue"
},
  "geometry": {"coordinates":[-75.376801,40.631802],"type":"Point"}
}