{
  "type": "Feature",
  "properties": {
    "iso:country":"US",
    "sg:address":"5325 Oxford Ave",
    "sg:city":"Philadelphia",
    "sg:classifiers":[
        {
            "category":"Food & Beverages",
            "subcategory":"Groceries & Convenience Stores",
            "type":"Retail Goods"
        }
    ],
    "sg:phone":"+1   ",
    "sg:postcode":"19124",
    "sg:province":"PA",
    "sg:tags":[
        "deli"
    ],
    "wof:name":"Mattys Market Inc",
    "wof:placetype":"venue"
},
  "geometry": {"coordinates":[-75.085185,40.029046],"type":"Point"}
}