{
  "type": "Feature",
  "properties": {
    "addr:full":"10998 Perry Hwy Ste 107A Meadville PA 16335",
    "addr:housenumber":"10998",
    "addr:postcode":"16335",
    "addr:street":"Perry Hwy Ste 107A",
    "iso:country":"US",
    "sg:address":"10998 Perry Hwy Ste 107A",
    "sg:city":"Meadville",
    "sg:classifiers":[
        {
            "category":"Personal",
            "subcategory":"Beauty Salon",
            "type":"Services"
        }
    ],
    "sg:phone":"+1 814 337 3376",
    "sg:postcode":"16335",
    "sg:province":"PA",
    "wof:name":"Keystone Classic Cuts",
    "wof:placetype":"venue"
},
  "geometry": {"coordinates":[-80.200661,41.61673],"type":"Point"}
}