{
  "type": "Feature",
  "properties": {
    "addr:full":"180 E Center St Shavertown PA 18708",
    "addr:housenumber":"180",
    "addr:postcode":"18708",
    "addr:street":"E Center St",
    "iso:country":"US",
    "sg:address":"180 E Center St",
    "sg:city":"Shavertown",
    "sg:classifiers":[
        {
            "category":"Government",
            "subcategory":"Office",
            "type":"Public Place"
        }
    ],
    "sg:phone":"+1   ",
    "sg:postcode":"18708",
    "sg:province":"PA",
    "sg:tags":[
        "governmental"
    ],
    "wof:name":"Township of Kingston",
    "wof:placetype":"venue"
},
  "geometry": {"coordinates":[-75.928676,41.329578],"type":"Point"}
}