{
  "type": "Feature",
  "properties": {
    "addr:full":"326 W Front St Media PA 19063",
    "addr:housenumber":"326",
    "addr:postcode":"19063",
    "addr:street":"W Front St",
    "iso:country":"US",
    "sg:address":"326 W Front St",
    "sg:city":"Media",
    "sg:classifiers":[
        {
            "category":"Shopping",
            "subcategory":"Gifts & Souvenirs",
            "type":"Retail Goods"
        }
    ],
    "sg:phone":"+1 610 566 4438",
    "sg:postcode":"19063",
    "sg:province":"PA",
    "wof:name":"A Creative Touch",
    "wof:placetype":"venue"
},
  "geometry": {"coordinates":[-75.392905,39.919288],"type":"Point"}
}