{
  "type": "Feature",
  "properties": {
    "addr:full":"5021 Louise Dr Mechanicsburg PA 17055",
    "addr:housenumber":"5021",
    "addr:postcode":"17055",
    "addr:street":"Louise Dr",
    "iso:country":"US",
    "sg:address":"5021 Louise Dr",
    "sg:city":"Mechanicsburg",
    "sg:classifiers":[
        {
            "category":"Education",
            "subcategory":"School",
            "type":"Public Place"
        }
    ],
    "sg:phone":"+1   ",
    "sg:postcode":"17055",
    "sg:province":"PA",
    "sg:tags":[
        "reading",
        "center"
    ],
    "wof:name":"Sylvan Learning Centers",
    "wof:placetype":"venue"
},
  "geometry": {"coordinates":[-76.956554,40.204058],"type":"Point"}
}