{
  "type": "Feature",
  "properties": {
    "addr:full":"1718 N Sydenham St Philadelphia PA 19121",
    "addr:housenumber":"1718",
    "addr:postcode":"19121",
    "addr:street":"N Sydenham St",
    "iso:country":"US",
    "sg:address":"1718 N Sydenham St",
    "sg:city":"Philadelphia",
    "sg:classifiers":[
        {
            "category":"Real Estate",
            "subcategory":"Real Estate Operator",
            "type":"Services"
        }
    ],
    "sg:phone":"+1 215 236 4125",
    "sg:postcode":"19121",
    "sg:province":"PA",
    "sg:tags":[
        "apartment"
    ],
    "sg:website":"www.sydenhamcommons.com",
    "wof:name":"Sydenham Commons Llc",
    "wof:placetype":"venue"
},
  "geometry": {"coordinates":[-75.160454,39.979295],"type":"Point"}
}