{
  "type": "Feature",
  "properties": {
    "iso:country":"US",
    "sg:address":"121 N Main St",
    "sg:city":"Ashley",
    "sg:classifiers":[
        {
            "category":"Restaurant",
            "type":"Food & Drink"
        }
    ],
    "sg:phone":"+1 570 829 9187",
    "sg:postcode":"18706",
    "sg:province":"PA",
    "wof:name":"Kelsey's Pub",
    "wof:placetype":"venue"
},
  "geometry": {"coordinates":[-75.897122,41.217829],"type":"Point"}
}