{
  "type": "Feature",
  "properties": {
    "iso:country":"US",
    "sg:address":"671 E Allen St",
    "sg:city":"Allentown",
    "sg:classifiers":[
        {
            "category":"Personal",
            "type":"Services"
        }
    ],
    "sg:phone":"+1 610 439 3095",
    "sg:postcode":"18109",
    "sg:province":"PA",
    "sg:tags":[
        "wear",
        "formal"
    ],
    "wof:name":"Shapiro's Formal Shop",
    "wof:placetype":"venue"
},
  "geometry": {"coordinates":[-75.446769,40.616927],"type":"Point"}
}