{
  "type": "Feature",
  "properties": {
    "addr:full":"1673 Quarry Rd Yardley PA 19067",
    "addr:housenumber":"1673",
    "addr:postcode":"19067",
    "addr:street":"Quarry Rd",
    "iso:country":"US",
    "sg:address":"1673 Quarry Rd",
    "sg:city":"Yardley",
    "sg:classifiers":[
        {
            "category":"Education",
            "subcategory":"School",
            "type":"Public Place"
        }
    ],
    "sg:phone":"+1 215 321 8540",
    "sg:postcode":"19067",
    "sg:province":"PA",
    "wof:name":"Pennsbury School Dist Afton",
    "wof:placetype":"venue"
},
  "geometry": {"coordinates":[-74.877364,40.245407],"type":"Point"}
}