{
  "type": "Feature",
  "properties": {
    "addr:full":"112 E 2nd St Waynesboro PA 17268",
    "addr:housenumber":"112",
    "addr:postcode":"17268",
    "addr:street":"E 2Nd St",
    "iso:country":"US",
    "sg:address":"112 E 2nd St",
    "sg:city":"Waynesboro",
    "sg:classifiers":[
        {
            "category":"Organizations",
            "subcategory":"Religious Organization",
            "type":"Services"
        }
    ],
    "sg:phone":"+1 717 762 1930",
    "sg:postcode":"17268",
    "sg:province":"PA",
    "sg:tags":[
        "church"
    ],
    "wof:name":"St Mary's Episcopal Church",
    "wof:placetype":"venue"
},
  "geometry": {"coordinates":[-77.575975,39.752374],"type":"Point"}
}