{
  "type": "Feature",
  "properties": {
    "iso:country":"US",
    "sg:address":"7 Maryland Pl",
    "sg:city":"Jeannette",
    "sg:classifiers":[
        {
            "category":"Professional",
            "type":"Services"
        }
    ],
    "sg:phone":"+1   ",
    "sg:postcode":"15644",
    "sg:province":"PA",
    "wof:name":"Anthony M Denunzio",
    "wof:placetype":"venue"
},
  "geometry": {"coordinates":[-79.608687,40.317842],"type":"Point"}
}