{
  "type": "Feature",
  "properties": {
    "iso:country":"US",
    "sg:address":"4244 Old York Rd",
    "sg:city":"Philadelphia",
    "sg:classifiers":[
        {
            "category":"Organizations",
            "subcategory":"Religious Organization",
            "type":"Services"
        }
    ],
    "sg:phone":"+1 215 324 0330",
    "sg:postcode":"19140",
    "sg:province":"PA",
    "sg:tags":[
        "church"
    ],
    "wof:name":"El Shaddai Baptist Church",
    "wof:placetype":"venue"
},
  "geometry": {"coordinates":[-75.147256,40.017497],"type":"Point"}
}