{
  "type": "Feature",
  "properties": {
    "addr:full":"907 Chester Pike Sharon Hill PA 19079",
    "addr:housenumber":"907",
    "addr:postcode":"19079",
    "addr:street":"Chester Pike",
    "iso:country":"US",
    "sg:address":"907 Chester Pike",
    "sg:city":"Sharon Hill",
    "sg:classifiers":[
        {
            "category":"Organizations",
            "subcategory":"Non-profit Organization",
            "type":"Services"
        }
    ],
    "sg:phone":"+1 610 534 2505",
    "sg:postcode":"19079",
    "sg:province":"PA",
    "wof:name":"Aids Care Group",
    "wof:placetype":"venue"
},
  "geometry": {"coordinates":[-75.27118400000001,39.909906],"type":"Point"}
}