{
  "type": "Feature",
  "properties": {
    "addr:full":"190 Jefferson Rd Waynesburg PA 15370",
    "addr:housenumber":"190",
    "addr:postcode":"15370",
    "addr:street":"Jefferson Rd",
    "iso:country":"US",
    "sg:address":"190 Jefferson Rd",
    "sg:city":"Waynesburg",
    "sg:classifiers":[
        {
            "category":"Government",
            "subcategory":"Office",
            "type":"Public Place"
        }
    ],
    "sg:phone":"+1 724 627 6778",
    "sg:postcode":"15370",
    "sg:province":"PA",
    "sg:tags":[
        "county",
        "govt",
        "program"
    ],
    "wof:name":"Greene County Transportation",
    "wof:placetype":"venue"
},
  "geometry": {"coordinates":[-80.15661,39.901329],"type":"Point"}
}