{
  "type": "Feature",
  "properties": {
    "iso:country":"US",
    "sg:address":"9 S 2nd St",
    "sg:city":"Coplay",
    "sg:classifiers":[
        {
            "category":"Manufacturing",
            "subcategory":"Building Materials",
            "type":"Manufacturing & Wholesale Goods"
        }
    ],
    "sg:phone":"+1   ",
    "sg:postcode":"18037",
    "sg:province":"PA",
    "sg:tags":[
        "mfg",
        "wood",
        "kitchen",
        "cabinet"
    ],
    "wof:name":"Stiles Rails",
    "wof:placetype":"venue"
},
  "geometry": {"coordinates":[-75.490731,40.672462],"type":"Point"}
}