{
  "type": "Feature",
  "properties": {
    "iso:country":"US",
    "sg:address":"1001 Rte 940",
    "sg:city":"Mt Pocono",
    "sg:classifiers":[
        {
            "category":"Banks & Credit Unions",
            "subcategory":"Bank",
            "type":"Services"
        }
    ],
    "sg:phone":"+1 570 839 0650",
    "sg:postcode":"18344",
    "sg:province":"PA",
    "sg:tags":[
        "loan",
        "real estate"
    ],
    "wof:name":"Andrew Pizzo Mortgage",
    "wof:placetype":"venue"
},
  "geometry": {"coordinates":[-75.37350499999999,41.122704],"type":"Point"}
}