{
  "type": "Feature",
  "properties": {
    "iso:country":"US",
    "sg:address":"291 Norwood Rd",
    "sg:city":"Downingtown",
    "sg:phone":"+1 610 269 5050",
    "sg:postcode":"19335",
    "sg:province":"PA",
    "wof:name":"Rex Carle Automotive",
    "wof:placetype":"venue"
},
  "geometry": {"coordinates":[-75.704396,40.019592],"type":"Point"}
}