{
  "type": "Feature",
  "properties": {
    "iso:country":"US",
    "sg:address":"211 S Main St",
    "sg:city":"Doylestown",
    "sg:classifiers":[
        {
            "category":"Restaurant",
            "type":"Food & Drink"
        },
        {
            "category":"Bars & Pubs",
            "type":"Food & Drink"
        }
    ],
    "sg:phone":"+1 215 489 7795",
    "sg:postcode":"18901",
    "sg:province":"PA",
    "sg:tags":[
        "bar"
    ],
    "wof:name":"Mugs On Main Street",
    "wof:placetype":"venue"
},
  "geometry": {"coordinates":[-75.128749,40.304135],"type":"Point"}
}