{
  "type": "Feature",
  "properties": {
    "iso:country":"US",
    "sg:address":"111 Smithfield St",
    "sg:city":"Pittsburgh",
    "sg:classifiers":[
        {
            "category":"Restaurant",
            "type":"Food & Drink"
        }
    ],
    "sg:phone":"+1   ",
    "sg:postcode":"15222",
    "sg:province":"PA",
    "sg:tags":[
        "shop",
        "sandwich"
    ],
    "wof:name":"Fads Inc",
    "wof:placetype":"venue"
},
  "geometry": {"coordinates":[-80.000275,40.437756],"type":"Point"}
}