{
  "type": "Feature",
  "properties": {
    "iso:country":"US",
    "sg:address":"2187 Warren Ave",
    "sg:city":"Irwin",
    "sg:classifiers":[
        {
            "category":"Professional",
            "subcategory":"Business Services",
            "type":"Services"
        }
    ],
    "sg:phone":"+1 724 289 0722",
    "sg:postcode":"15642",
    "sg:province":"PA",
    "sg:tags":[
        "consultant",
        "coach"
    ],
    "wof:name":"National Physic Consultan",
    "wof:placetype":"venue"
},
  "geometry": {"coordinates":[-79.737026,40.305059],"type":"Point"}
}