{
  "type": "Feature",
  "properties": {
    "iso:country":"US",
    "sg:address":"203 N Allegheny St",
    "sg:city":"Bellefonte",
    "sg:classifiers":[
        {
            "category":"Health Services",
            "subcategory":"Clinic",
            "type":"Services"
        }
    ],
    "sg:phone":"+1 814 355 1531",
    "sg:postcode":"16823",
    "sg:province":"PA",
    "sg:tags":[
        "organization",
        "medical",
        "surgical"
    ],
    "sg:website":"www.ccfpl.org",
    "wof:name":"Health Line",
    "wof:placetype":"venue"
},
  "geometry": {"coordinates":[-77.77871,40.914029],"type":"Point"}
}