{
  "type": "Feature",
  "properties": {
    "addr:full":"1669 N Atherton St State College PA 16803",
    "addr:housenumber":"1669",
    "addr:postcode":"16803",
    "addr:street":"N Atherton St",
    "iso:country":"US",
    "sg:address":"1669 N Atherton St",
    "sg:city":"State College",
    "sg:classifiers":[
        {
            "category":"Bars & Pubs",
            "type":"Food & Drink"
        }
    ],
    "sg:menulink":"http://www.allmenus.com/pa/patton/273404-fat-jacks-bar-b-que-shack-and-bottle-shop/menu/",
    "sg:phone":"+1 814 238 8066",
    "sg:postcode":"16803",
    "sg:province":"PA",
    "sg:tags":[
        "barbecue",
        "american"
    ],
    "wof:name":"Fat Jack's Bar-B-Que Shack and Bottle Shop",
    "wof:placetype":"venue"
},
  "geometry": {"coordinates":[-77.896916,40.808285],"type":"Point"}
}