{
  "type": "Feature",
  "properties": {
    "addr:full":"297 Bush Hollow Rd Muncy PA 17756",
    "addr:housenumber":"297",
    "addr:postcode":"17756",
    "addr:street":"Bush Hollow Rd",
    "iso:country":"US",
    "sg:address":"297 Bush Hollow Rd",
    "sg:city":"Muncy",
    "sg:classifiers":[
        {
            "category":"Wholesale",
            "subcategory":"Machinery & Supplies",
            "type":"Manufacturing & Wholesale Goods"
        }
    ],
    "sg:phone":"+1   ",
    "sg:postcode":"17756",
    "sg:province":"PA",
    "sg:tags":[
        "equipment",
        "consulting",
        "industrial",
        "management"
    ],
    "wof:name":"Tara Equipment Finance Co",
    "wof:placetype":"venue"
},
  "geometry": {"coordinates":[-76.821612,41.264141],"type":"Point"}
}