{
  "type": "Feature",
  "properties": {
    "addr:full":"7132 Ridge Ave Philadelphia PA 19128",
    "addr:housenumber":"7132",
    "addr:postcode":"19128",
    "addr:street":"Ridge Ave",
    "iso:country":"US",
    "sg:address":"7132 Ridge Ave",
    "sg:city":"Philadelphia",
    "sg:classifiers":[
        {
            "category":"Ice Cream",
            "type":"Food & Drink"
        }
    ],
    "sg:menulink":"http://www.allmenus.com/pa/philadelphia/234939-ritas-ice-custard-happiness/menu/",
    "sg:phone":"+1 215 482 4002",
    "sg:postcode":"19128",
    "sg:province":"PA",
    "sg:tags":[
        "american"
    ],
    "wof:name":"Rita's Ice Custard Happiness",
    "wof:placetype":"venue"
},
  "geometry": {"coordinates":[-75.23133799999999,40.045029],"type":"Point"}
}