{
  "type": "Feature",
  "properties": {
    "iso:country":"US",
    "sg:address":"3900 Jonestown Rd",
    "sg:city":"Harrisburg",
    "sg:classifiers":[
        {
            "category":"Autos & Motor Vehicles",
            "subcategory":"Automobile Sales",
            "type":"Retail Goods"
        }
    ],
    "sg:phone":"+1   ",
    "sg:postcode":"17109",
    "sg:province":"PA",
    "sg:tags":[
        "used"
    ],
    "wof:name":"McKee Motors Inc",
    "wof:placetype":"venue"
},
  "geometry": {"coordinates":[-76.82996,40.293276],"type":"Point"}
}