{
  "type": "Feature",
  "properties": {
    "iso:country":"US",
    "sg:address":"1182 Stone Hill Rd",
    "sg:city":"Conestoga",
    "sg:classifiers":[
        {
            "category":"Personal",
            "subcategory":"Beauty Salon",
            "type":"Services"
        }
    ],
    "sg:phone":"+1 717 872 4733",
    "sg:postcode":"17516",
    "sg:province":"PA",
    "wof:name":"Lefever, Cheryl Beauty Salon",
    "wof:placetype":"venue"
},
  "geometry": {"coordinates":[-76.351956,39.958503],"type":"Point"}
}