{
  "type": "Feature",
  "properties": {
    "iso:country":"US",
    "sg:address":"525 William Penn Pl",
    "sg:city":"Pittsburgh",
    "sg:classifiers":[
        {
            "category":"Professional",
            "subcategory":"Lawyer & Legal Services",
            "type":"Services"
        }
    ],
    "sg:phone":"+1 412 261 3400",
    "sg:postcode":"15219",
    "sg:province":"PA",
    "sg:tags":[
        "attorney"
    ],
    "wof:name":"Dixon J Rich Attorney",
    "wof:placetype":"venue"
},
  "geometry": {"coordinates":[-79.99771699999999,40.43974],"type":"Point"}
}