{
  "type": "Feature",
  "properties": {
    "iso:country":"US",
    "sg:address":"829 E Lancaster Ave",
    "sg:city":"Villanova",
    "sg:phone":"+1 610 527 3606",
    "sg:postcode":"19085",
    "sg:province":"PA",
    "wof:name":"Campus Corner",
    "wof:placetype":"venue"
},
  "geometry": {"coordinates":[-75.345812,40.035336],"type":"Point"}
}