{
  "type": "Feature",
  "properties": {
    "addr:full":"1429 Rte 56 E Apollo PA 15613",
    "addr:housenumber":"1429",
    "addr:postcode":"15613",
    "addr:street":"Rte 56 E Apollo",
    "iso:country":"US",
    "sg:address":"1429 Rte 56 E",
    "sg:city":"Apollo",
    "sg:classifiers":[
        {
            "category":"Retail",
            "subcategory":"Repair Shop",
            "type":"Services"
        }
    ],
    "sg:phone":"+1 724 478 2129",
    "sg:postcode":"15613",
    "sg:province":"PA",
    "sg:tags":[
        "appliance"
    ],
    "wof:name":"Roy's Appliance Repair",
    "wof:placetype":"venue"
},
  "geometry": {"coordinates":[-79.50688100000001,40.600995],"type":"Point"}
}