{
  "type": "Feature",
  "properties": {
    "addr:full":"305 W 6th St Oil City PA 16301",
    "addr:housenumber":"305",
    "addr:postcode":"16301",
    "addr:street":"W 6Th St",
    "iso:country":"US",
    "sg:address":"305 W 6th St",
    "sg:city":"Oil City",
    "sg:classifiers":[
        {
            "category":"Building & Trades",
            "subcategory":"Construction",
            "type":"Services"
        }
    ],
    "sg:phone":"+1 814 677 3514",
    "sg:postcode":"16301",
    "sg:province":"PA",
    "sg:tags":[
        "repair",
        "s",
        "carpentry",
        "contractor"
    ],
    "wof:name":"J & J Construction",
    "wof:placetype":"venue"
},
  "geometry": {"coordinates":[-79.714742,41.421741],"type":"Point"}
}