{
  "type": "Feature",
  "properties": {
    "addr:full":"817 E Baltimore Pike Kennett Square PA 19348",
    "addr:housenumber":"817",
    "addr:postcode":"19348",
    "addr:street":"E Baltimore Pike",
    "iso:country":"US",
    "sg:address":"817 E Baltimore Pike",
    "sg:city":"Kennett Square",
    "sg:classifiers":[
        {
            "category":"Retail",
            "subcategory":"Laundry & Dry Cleaning",
            "type":"Services"
        }
    ],
    "sg:phone":"+1 610 925 3478",
    "sg:postcode":"19348",
    "sg:province":"PA",
    "wof:name":"Kennett Square Cleaners",
    "wof:placetype":"venue"
},
  "geometry": {"coordinates":[-75.6875,39.859699],"type":"Point"}
}