{
  "type": "Feature",
  "properties": {
    "addr:full":"220 Washington Rd Pittsburgh PA 15216",
    "addr:housenumber":"220",
    "addr:postcode":"15216",
    "addr:street":"Washington Rd",
    "iso:country":"US",
    "sg:address":"220 Washington Rd",
    "sg:city":"Pittsburgh",
    "sg:classifiers":[
        {
            "category":"Shopping",
            "subcategory":"Pharmacy",
            "type":"Retail Goods"
        }
    ],
    "sg:phone":"+1 412 343 7323",
    "sg:postcode":"15216",
    "sg:province":"PA",
    "sg:tags":[
        "drug",
        "store"
    ],
    "wof:name":"Eckerd",
    "wof:placetype":"venue"
},
  "geometry": {"coordinates":[-80.04340000000001,40.387879],"type":"Point"}
}