{
  "type": "Feature",
  "properties": {
    "addr:full":"815 W Dekalb Pike King Of Prussia PA 19406",
    "addr:housenumber":"815",
    "addr:postcode":"19406",
    "addr:street":"W Dekalb Pike",
    "iso:country":"US",
    "sg:address":"815 W Dekalb Pike",
    "sg:city":"King Of Prussia",
    "sg:classifiers":[
        {
            "category":"Travel",
            "subcategory":"Hotels & Motels",
            "type":"Entertainment"
        }
    ],
    "sg:phone":"+1 610 265 7200",
    "sg:postcode":"19406",
    "sg:province":"PA",
    "wof:name":"Motel 6",
    "wof:placetype":"venue"
},
  "geometry": {"coordinates":[-75.386955,40.086157],"type":"Point"}
}