{
  "type": "Feature",
  "properties": {
    "iso:country":"US",
    "sg:address":"24 Keystone Ct",
    "sg:city":"Leola",
    "sg:classifiers":[
        {
            "category":"Building & Trades",
            "subcategory":"Construction",
            "type":"Services"
        }
    ],
    "sg:phone":"+1 717 656 4424",
    "sg:postcode":"17540",
    "sg:province":"PA",
    "sg:tags":[
        "dry wall",
        "contractor"
    ],
    "wof:name":"Susquehanna Valley Drywall Inc",
    "wof:placetype":"venue"
},
  "geometry": {"coordinates":[-76.20533500000001,40.084973],"type":"Point"}
}