{
  "type": "Feature",
  "properties": {
    "addr:full":"912 Walnut Rd Warminster PA 18974",
    "addr:housenumber":"912",
    "addr:postcode":"18974",
    "addr:street":"Walnut Rd",
    "iso:country":"US",
    "sg:address":"912 Walnut Rd",
    "sg:city":"Warminster",
    "sg:classifiers":[
        {
            "category":"Retail",
            "subcategory":"Photofinishing",
            "type":"Services"
        }
    ],
    "sg:phone":"+1 215 672 8990",
    "sg:postcode":"18974",
    "sg:province":"PA",
    "sg:tags":[
        "refractory"
    ],
    "sg:website":"http://www.bloomeng.com",
    "wof:name":"Bloom Engineering Co Inc",
    "wof:placetype":"venue"
},
  "geometry": {"coordinates":[-75.11154999999999,40.20423],"type":"Point"}
}