{
  "type": "Feature",
  "properties": {
    "iso:country":"US",
    "sg:address":"546 S Hanover St",
    "sg:city":"Carlisle",
    "sg:classifiers":[
        {
            "category":"Organizations",
            "subcategory":"Religious Organization",
            "type":"Services"
        }
    ],
    "sg:phone":"+1 717 991 8668",
    "sg:postcode":"17013",
    "sg:province":"PA",
    "sg:website":"http://www.marksofchrist.com",
    "wof:name":"Marks Of Christ Publishing",
    "wof:placetype":"venue"
},
  "geometry": {"coordinates":[-77.190243,40.193957],"type":"Point"}
}