{
  "type": "Feature",
  "properties": {
    "addr:full":"1760 S Atherton St State College PA 16801",
    "addr:housenumber":"1760",
    "addr:postcode":"16801",
    "addr:street":"S Atherton St",
    "iso:country":"US",
    "sg:address":"1760 S Atherton St",
    "sg:city":"State College",
    "sg:classifiers":[
        {
            "category":"Health Services",
            "subcategory":"Chiropractor",
            "type":"Services"
        }
    ],
    "sg:phone":"+1 814 272 3555",
    "sg:postcode":"16801",
    "sg:province":"PA",
    "wof:name":"Advanced Chiropractic State",
    "wof:placetype":"venue"
},
  "geometry": {"coordinates":[-77.83400399999999,40.785072],"type":"Point"}
}