{
  "type": "Feature",
  "properties": {
    "iso:country":"US",
    "sg:address":"11 S 12th St",
    "sg:city":"Philadelphia",
    "sg:classifiers":[
        {
            "category":"Food & Beverages",
            "subcategory":"Candy",
            "type":"Retail Goods"
        }
    ],
    "sg:phone":"+1 215 567 6001",
    "sg:postcode":"19107",
    "sg:province":"PA",
    "sg:tags":[
        "confectionery"
    ],
    "wof:name":"Philly's Nuts & Candy",
    "wof:placetype":"venue"
},
  "geometry": {"coordinates":[-75.15988400000001,39.951635],"type":"Point"}
}