{
  "type": "Feature",
  "properties": {
    "addr:full":"1334 Philadelphia St Indiana PA 15701",
    "addr:housenumber":"1334",
    "addr:postcode":"15701",
    "addr:street":"Philadelphia St",
    "iso:country":"US",
    "sg:address":"1334 Philadelphia St",
    "sg:city":"Indiana",
    "sg:classifiers":[
        {
            "category":"Home & Garden",
            "subcategory":"Building Materials",
            "type":"Retail Goods"
        }
    ],
    "sg:phone":"+1   ",
    "sg:postcode":"15701",
    "sg:province":"PA",
    "sg:tags":[
        "garage",
        "door"
    ],
    "wof:name":"Moreau Ted Gar Door Sls Servic",
    "wof:placetype":"venue"
},
  "geometry": {"coordinates":[-79.16627099999999,40.623171],"type":"Point"}
}