{
  "type": "Feature",
  "properties": {
    "addr:full":"220 Church St Moscow PA 18444",
    "addr:housenumber":"220",
    "addr:postcode":"18444",
    "addr:street":"Church St",
    "iso:country":"US",
    "sg:address":"220 Church St",
    "sg:city":"Moscow",
    "sg:classifiers":[
        {
            "category":"Organizations",
            "subcategory":"Religious Organization",
            "type":"Services"
        }
    ],
    "sg:phone":"+1 570 842 4561",
    "sg:postcode":"18444",
    "sg:province":"PA",
    "sg:tags":[
        "church"
    ],
    "wof:name":"St Catherine's Church",
    "wof:placetype":"venue"
},
  "geometry": {"coordinates":[-75.52108200000001,41.336905],"type":"Point"}
}