{
  "type": "Feature",
  "properties": {
    "iso:country":"US",
    "sg:address":"19 Jonathan Dr",
    "sg:city":"Phoenixville",
    "sg:classifiers":[
        {
            "category":"Organizations",
            "subcategory":"Community Association",
            "type":"Services"
        }
    ],
    "sg:phone":"+1   ",
    "sg:postcode":"19460",
    "sg:province":"PA",
    "wof:name":"Penn Delswimming League",
    "wof:placetype":"venue"
},
  "geometry": {"coordinates":[-75.571957,40.119494],"type":"Point"}
}