{
  "type": "Feature",
  "properties": {
    "addr:full":"1800 Memphis St Philadelphia PA 19125",
    "addr:housenumber":"1800",
    "addr:postcode":"19125",
    "addr:street":"Memphis St",
    "iso:country":"US",
    "sg:address":"1800 Memphis St",
    "sg:city":"Philadelphia",
    "sg:classifiers":[
        {
            "category":"Health Services",
            "subcategory":"Doctor",
            "type":"Services"
        }
    ],
    "sg:phone":"+1   ",
    "sg:postcode":"19125",
    "sg:province":"PA",
    "sg:tags":[
        "medical"
    ],
    "wof:name":"Eduardo Munilla MD",
    "wof:placetype":"venue"
},
  "geometry": {"coordinates":[-75.129311,39.976348],"type":"Point"}
}