{
  "type": "Feature",
  "properties": {
    "iso:country":"US",
    "sg:address":"2031 N Broad St Ste 139",
    "sg:city":"Lansdale",
    "sg:classifiers":[
        {
            "category":"Health Services",
            "subcategory":"Doctor",
            "type":"Services"
        }
    ],
    "sg:phone":"+1 215 855 4800",
    "sg:postcode":"19446",
    "sg:province":"PA",
    "wof:name":"Bayard David J MD",
    "wof:placetype":"venue"
},
  "geometry": {"coordinates":[-75.266403,40.257801],"type":"Point"}
}