{
  "type": "Feature",
  "properties": {
    "iso:country":"US",
    "sg:address":"801 Scalp Ave",
    "sg:city":"Johnstown",
    "sg:classifiers":[
        {
            "category":"Retail",
            "subcategory":"Photofinishing",
            "type":"Services"
        }
    ],
    "sg:phone":"+1 814 266 3333",
    "sg:postcode":"15904",
    "sg:province":"PA",
    "sg:tags":[
        "photo",
        "finishing"
    ],
    "wof:name":"Photos & More",
    "wof:placetype":"venue"
},
  "geometry": {"coordinates":[-78.86665000000001,40.288274],"type":"Point"}
}