{
  "type": "Feature",
  "properties": {
    "iso:country":"US",
    "sg:address":"628 S 4th St",
    "sg:city":"Philadelphia",
    "sg:classifiers":[
        {
            "category":"Retail",
            "subcategory":"Laundry & Dry Cleaning",
            "type":"Services"
        }
    ],
    "sg:phone":"+1 215 925 4418",
    "sg:postcode":"19147",
    "sg:province":"PA",
    "sg:tags":[
        "garment",
        "plant",
        "agent",
        "drycleaning"
    ],
    "wof:name":"Society Hill Cleaners",
    "wof:placetype":"venue"
},
  "geometry": {"coordinates":[-75.1493,39.941399],"type":"Point"}
}