{
  "type": "Feature",
  "properties": {
    "iso:country":"US",
    "sg:address":"1955 Lincoln Hwy",
    "sg:city":"North Versailles",
    "sg:classifiers":[
        {
            "category":"Home & Garden",
            "subcategory":"Building Materials",
            "type":"Retail Goods"
        }
    ],
    "sg:phone":"+1 412 829 2584",
    "sg:postcode":"15137",
    "sg:province":"PA",
    "sg:tags":[
        "lumber"
    ],
    "sg:website":"www.84lumber.com",
    "wof:name":"84 Lumber Co",
    "wof:placetype":"venue"
},
  "geometry": {"coordinates":[-79.77681200000001,40.365874],"type":"Point"}
}