{
  "type": "Feature",
  "properties": {
    "iso:country":"US",
    "sg:address":"132 W Chester Rd",
    "sg:city":"West Chester",
    "sg:classifiers":[
        {
            "category":"Personal",
            "subcategory":"Beauty Salon",
            "type":"Services"
        }
    ],
    "sg:phone":"+1 610 701 4355",
    "sg:postcode":"19382",
    "sg:province":"PA",
    "wof:name":"Leisa's Hair & Nails",
    "wof:placetype":"venue"
},
  "geometry": {"coordinates":[-75.544348,39.910636],"type":"Point"}
}