{
  "type": "Feature",
  "properties": {
    "iso:country":"US",
    "sg:address":"4041 Ashland St",
    "sg:city":"Philadelphia",
    "sg:classifiers":[
        {
            "category":"Retail",
            "subcategory":"Auto Repair",
            "type":"Services"
        }
    ],
    "sg:phone":"+1 215 533 8334",
    "sg:postcode":"19124",
    "sg:province":"PA",
    "wof:name":"International Body Works Inc",
    "wof:placetype":"venue"
},
  "geometry": {"coordinates":[-75.08699799999999,40.002998],"type":"Point"}
}