{
  "type": "Feature",
  "properties": {
    "iso:country":"US",
    "sg:address":"28 N Church St",
    "sg:city":"Hazleton",
    "sg:classifiers":[
        {
            "category":"Government",
            "subcategory":"Office",
            "type":"Public Place"
        }
    ],
    "sg:phone":"+1   ",
    "sg:postcode":"18201",
    "sg:province":"PA",
    "sg:tags":[
        "station",
        "recruiting"
    ],
    "wof:name":"Marine Corps Recruiting",
    "wof:placetype":"venue"
},
  "geometry": {"coordinates":[-75.97668,40.955667],"type":"Point"}
}