{
  "type": "Feature",
  "properties": {
    "iso:country":"US",
    "sg:address":"3570 Brighton Rd",
    "sg:city":"Pittsburgh",
    "sg:classifiers":[
        {
            "category":"Health Services",
            "subcategory":"Nursing And Care Facility",
            "type":"Services"
        }
    ],
    "sg:phone":"+1 412 734 5717",
    "sg:postcode":"15212",
    "sg:province":"PA",
    "sg:tags":[
        "intermediate"
    ],
    "wof:name":"Stones Personal Care Home",
    "wof:placetype":"venue"
},
  "geometry": {"coordinates":[-80.03241300000001,40.480908],"type":"Point"}
}