{
  "type": "Feature",
  "properties": {
    "addr:full":"727 N Meadow St Allentown PA 18102",
    "addr:housenumber":"727",
    "addr:postcode":"18102",
    "addr:street":"N Meadow St",
    "iso:country":"US",
    "sg:address":"727 N Meadow St",
    "sg:city":"Allentown",
    "sg:classifiers":[
        {
            "category":"Shopping",
            "subcategory":"Jewelry",
            "type":"Retail Goods"
        }
    ],
    "sg:phone":"+1 610 433 4114",
    "sg:postcode":"18102",
    "sg:province":"PA",
    "sg:tags":[
        "jeweler"
    ],
    "wof:name":"Hyman Companies the",
    "wof:placetype":"venue"
},
  "geometry": {"coordinates":[-75.46820099999999,40.614899],"type":"Point"}
}