{
  "type": "Feature",
  "properties": {
    "iso:country":"US",
    "sg:address":"681 Knight Rd",
    "sg:city":"Harrisburg",
    "sg:classifiers":[
        {
            "category":"Building & Trades",
            "subcategory":"Construction",
            "type":"Services"
        }
    ],
    "sg:phone":"+1 717 652 2230",
    "sg:postcode":"17111",
    "sg:province":"PA",
    "sg:tags":[
        "contractor"
    ],
    "sg:website":"www.massconstruction.com",
    "wof:name":"Mast Construction Group",
    "wof:placetype":"venue"
},
  "geometry": {"coordinates":[-76.747063,40.309701],"type":"Point"}
}