{
  "type": "Feature",
  "properties": {
    "iso:country":"US",
    "sg:address":"3613 N 5th St",
    "sg:city":"Philadelphia",
    "sg:classifiers":[
        {
            "category":"Food & Beverages",
            "subcategory":"Dairy",
            "type":"Retail Goods"
        }
    ],
    "sg:phone":"+1 215 426 8800",
    "sg:postcode":"19140",
    "sg:province":"PA",
    "sg:tags":[
        "egg"
    ],
    "wof:name":"Viva Food Distributors Inc",
    "wof:placetype":"venue"
},
  "geometry": {"coordinates":[-75.137186,40.005995],"type":"Point"}
}