{
  "type": "Feature",
  "properties": {
    "iso:country":"US",
    "sg:address":"4109 Lincoln Hwy",
    "sg:city":"Thorndale",
    "sg:classifiers":[
        {
            "category":"Manufacturing",
            "subcategory":"Motor Vehicles & Parts",
            "type":"Manufacturing & Wholesale Goods"
        }
    ],
    "sg:phone":"+1 610 269 1298",
    "sg:postcode":"19365",
    "sg:province":"PA",
    "sg:tags":[
        "equipment",
        "truck"
    ],
    "sg:website":"www.cohentruckparts.com",
    "wof:name":"William Cohen & Sons Inc",
    "wof:placetype":"venue"
},
  "geometry": {"coordinates":[-75.94356999999999,39.9847],"type":"Point"}
}