{
  "type": "Feature",
  "properties": {
    "iso:country":"US",
    "sg:address":"138 E Winchester Ave",
    "sg:city":"Langhorne",
    "sg:classifiers":[
        {
            "category":"Building & Trades",
            "subcategory":"Construction",
            "type":"Services"
        }
    ],
    "sg:phone":"+1 215 757 0785",
    "sg:postcode":"19047",
    "sg:province":"PA",
    "sg:tags":[
        "house"
    ],
    "wof:name":"Kravitz Construction",
    "wof:placetype":"venue"
},
  "geometry": {"coordinates":[-74.920683,40.181085],"type":"Point"}
}