{
  "type": "Feature",
  "properties": {
    "iso:country":"US",
    "sg:address":"3111 Sycamore St",
    "sg:city":"Harrisburg",
    "sg:classifiers":[
        {
            "category":"Restaurant",
            "type":"Food & Drink"
        }
    ],
    "sg:phone":"+1 717 395 2965",
    "sg:postcode":"17111",
    "sg:province":"PA",
    "sg:tags":[
        "pizza"
    ],
    "wof:name":"Nikos Pizzeria",
    "wof:placetype":"venue"
},
  "geometry": {"coordinates":[-76.836201,40.25659],"type":"Point"}
}