{
  "type": "Feature",
  "properties": {
    "iso:country":"US",
    "sg:address":"185 Arch Ave",
    "sg:city":"Greensburg",
    "sg:classifiers":[
        {
            "category":"Professional",
            "subcategory":"Business Services",
            "type":"Services"
        },
        {
            "category":"Professional",
            "subcategory":"Printing & Photocopies",
            "type":"Services"
        }
    ],
    "sg:phone":"+1 724 837 0530",
    "sg:postcode":"15601",
    "sg:province":"PA",
    "sg:tags":[
        "mail",
        "services-commercial",
        "shipping"
    ],
    "sg:website":"http://www.fotorecord.com",
    "wof:name":"Fotorecord Print Center, Inc.",
    "wof:placetype":"venue"
},
  "geometry": {"coordinates":[-79.539668,40.306263],"type":"Point"}
}