{
  "type": "Feature",
  "properties": {
    "addr:full":"1940 Camp Swatara Rd Myerstown PA 17067",
    "addr:housenumber":"1940",
    "addr:postcode":"17067",
    "addr:street":"Camp Swatara Rd",
    "iso:country":"US",
    "sg:address":"1940 Camp Swatara Rd",
    "sg:city":"Myerstown",
    "sg:classifiers":[
        {
            "category":"Manufacturing",
            "subcategory":"Tools & Machinery",
            "type":"Manufacturing & Wholesale Goods"
        }
    ],
    "sg:phone":"+1 717 933 5566",
    "sg:postcode":"17067",
    "sg:province":"PA",
    "sg:tags":[
        "woodworking",
        "manufacturer"
    ],
    "wof:name":"Eastcoast Cutter Inc",
    "wof:placetype":"venue"
},
  "geometry": {"coordinates":[-76.33478100000001,40.449166],"type":"Point"}
}