{
  "type": "Feature",
  "properties": {
    "iso:country":"US",
    "sg:address":"407 N 40th St",
    "sg:city":"Philadelphia",
    "sg:classifiers":[
        {
            "category":"Autos & Motor Vehicles",
            "subcategory":"Automobile Sales",
            "type":"Retail Goods"
        }
    ],
    "sg:phone":"+1 215 382 6552",
    "sg:postcode":"19104",
    "sg:province":"PA",
    "sg:tags":[
        "car",
        "repair"
    ],
    "wof:name":"West City Select Ltd",
    "wof:placetype":"venue"
},
  "geometry": {"coordinates":[-75.20230100000001,39.960602],"type":"Point"}
}