{
  "type": "Feature",
  "properties": {
    "iso:country":"US",
    "sg:address":"1616 Chichester Ave",
    "sg:city":"Linwood",
    "sg:classifiers":[
        {
            "category":"Personal",
            "subcategory":"Shoe Repair & Shine",
            "type":"Services"
        }
    ],
    "sg:phone":"+1 610 497 8646",
    "sg:postcode":"19061",
    "sg:province":"PA",
    "sg:tags":[
        "repairing",
        "boot"
    ],
    "wof:name":"Freddy's Shoe Repair",
    "wof:placetype":"venue"
},
  "geometry": {"coordinates":[-75.42620700000001,39.826625],"type":"Point"}
}