{
  "type": "Feature",
  "properties": {
    "addr:full":"126 Depot St Clarks Summit PA 18411",
    "addr:housenumber":"126",
    "addr:postcode":"18411",
    "addr:street":"Depot St",
    "iso:country":"US",
    "sg:address":"126 Depot St",
    "sg:city":"Clarks Summit",
    "sg:classifiers":[
        {
            "category":"Shopping",
            "type":"Retail Goods"
        }
    ],
    "sg:phone":"+1 570 587 0381",
    "sg:postcode":"18411",
    "sg:province":"PA",
    "sg:tags":[
        "art",
        "gallery",
        "dealer"
    ],
    "wof:name":"LA Torre's Gallery & Gifts",
    "wof:placetype":"venue"
},
  "geometry": {"coordinates":[-75.70375799999999,41.494265],"type":"Point"}
}