{
  "type": "Feature",
  "properties": {
    "iso:country":"US",
    "sg:address":"1917 Grant Ave",
    "sg:city":"Philadelphia",
    "sg:classifiers":[
        {
            "category":"Insurance",
            "subcategory":"Hazard Insurance",
            "type":"Services"
        },
        {
            "category":"Insurance",
            "subcategory":"Insurance Agent",
            "type":"Services"
        },
        {
            "category":"Insurance",
            "subcategory":"Life Insurance",
            "type":"Services"
        },
        {
            "category":"Insurance",
            "subcategory":"Title Insurance",
            "type":"Services"
        }
    ],
    "sg:phone":"+1 215 969 4663",
    "sg:postcode":"19115",
    "sg:province":"PA",
    "sg:tags":[
        "auto",
        "homeowner"
    ],
    "sg:website":"http://www.nationwide.com/agent/Philadelphia-PENNSYLVANIA-insurance-agent/timothy-reilly/office.html",
    "wof:name":"Timothy P Reilly - Nationwide Insurance",
    "wof:placetype":"venue"
},
  "geometry": {"coordinates":[-75.035105,40.084349],"type":"Point"}
}