{
  "type": "Feature",
  "properties": {
    "addr:full":"22 E State St Quarryville PA 17566",
    "addr:housenumber":"22",
    "addr:postcode":"17566",
    "addr:street":"E State St",
    "iso:country":"US",
    "sg:address":"22 E State St",
    "sg:city":"Quarryville",
    "sg:classifiers":[
        {
            "category":"Manufacturing",
            "subcategory":"Printing",
            "type":"Manufacturing & Wholesale Goods"
        }
    ],
    "sg:phone":"+1 717 786 2992",
    "sg:postcode":"17566",
    "sg:province":"PA",
    "sg:tags":[
        "newspaper"
    ],
    "sg:website":"www.allaroundphilly.com",
    "wof:name":"Ledger Newspapers",
    "wof:placetype":"venue"
},
  "geometry": {"coordinates":[-76.16304,39.897429],"type":"Point"}
}