{
  "type": "Feature",
  "properties": {
    "iso:country":"US",
    "sg:address":"162 Orchard Dr",
    "sg:city":"Pittsburgh",
    "sg:classifiers":[
        {
            "category":"Building & Trades",
            "subcategory":"Plumbing",
            "type":"Services"
        }
    ],
    "sg:phone":"+1   ",
    "sg:postcode":"15235",
    "sg:province":"PA",
    "sg:tags":[
        "contractor"
    ],
    "wof:name":"Hartman Plumbing",
    "wof:placetype":"venue"
},
  "geometry": {"coordinates":[-79.815145,40.47026],"type":"Point"}
}