{
  "type": "Feature",
  "properties": {
    "addr:full":"5807 Lansdowne Ave Philadelphia PA 19131",
    "addr:housenumber":"5807",
    "addr:postcode":"19131",
    "addr:street":"Lansdowne Ave",
    "iso:country":"US",
    "sg:address":"5807 Lansdowne Ave",
    "sg:city":"Philadelphia",
    "sg:classifiers":[
        {
            "category":"Arts & Performance",
            "subcategory":"Theater",
            "type":"Entertainment"
        }
    ],
    "sg:phone":"+1   ",
    "sg:postcode":"19131",
    "sg:province":"PA",
    "sg:tags":[
        "group"
    ],
    "wof:name":"Trauma Entertainment",
    "wof:placetype":"venue"
},
  "geometry": {"coordinates":[-75.237583,39.976292],"type":"Point"}
}