{
  "type": "Feature",
  "properties": {
    "iso:country":"US",
    "sg:address":"49 E 4th St",
    "sg:city":"Williamsport",
    "sg:classifiers":[
        {
            "category":"Building & Trades",
            "subcategory":"Landscaping Services",
            "type":"Services"
        }
    ],
    "sg:phone":"+1   ",
    "sg:postcode":"17701",
    "sg:province":"PA",
    "wof:name":"Pugslys Pet and Lawn Service",
    "wof:placetype":"venue"
},
  "geometry": {"coordinates":[-77.000652,41.243007],"type":"Point"}
}