{
  "type": "Feature",
  "properties": {
    "iso:country":"US",
    "sg:address":"2301 Cherry St",
    "sg:city":"Philadelphia",
    "sg:classifiers":[
        {
            "category":"Professional",
            "type":"Services"
        }
    ],
    "sg:phone":"+1   ",
    "sg:postcode":"19103",
    "sg:province":"PA",
    "wof:name":"Gorgeous Girl",
    "wof:placetype":"venue"
},
  "geometry": {"coordinates":[-75.17828799999999,39.957243],"type":"Point"}
}