{
  "type": "Feature",
  "properties": {
    "iso:country":"US",
    "sg:address":"1517 Hill Rd Apt 2A",
    "sg:city":"Reading",
    "sg:classifiers":[
        {
            "category":"Professional",
            "subcategory":"Printing & Photocopies",
            "type":"Services"
        }
    ],
    "sg:phone":"+1 610 374 7012",
    "sg:postcode":"19602",
    "sg:province":"PA",
    "sg:tags":[
        "lithographer"
    ],
    "wof:name":"Howard Goodman Instant Co",
    "wof:placetype":"venue"
},
  "geometry": {"coordinates":[-75.90716999999999,40.333595],"type":"Point"}
}