{
  "type": "Feature",
  "properties": {
    "iso:country":"US",
    "sg:address":"5940 Baum Blvd",
    "sg:city":"Pittsburgh",
    "sg:classifiers":[
        {
            "category":"Wholesale",
            "subcategory":"Machinery & Supplies",
            "type":"Manufacturing & Wholesale Goods"
        }
    ],
    "sg:phone":"+1   ",
    "sg:postcode":"15206",
    "sg:province":"PA",
    "sg:tags":[
        "equipment",
        "pipeline",
        "maintenance"
    ],
    "wof:name":"Kerr Engineered Sales Company",
    "wof:placetype":"venue"
},
  "geometry": {"coordinates":[-79.926511,40.46044],"type":"Point"}
}