{
  "type": "Feature",
  "properties": {
    "iso:country":"US",
    "sg:address":"223 Atwood St",
    "sg:city":"Pittsburgh",
    "sg:classifiers":[
        {
            "category":"Restaurant",
            "type":"Food & Drink"
        }
    ],
    "sg:phone":"+1   ",
    "sg:postcode":"15213",
    "sg:province":"PA",
    "sg:tags":[
        "eating"
    ],
    "wof:name":"Cumpies Restaurant & Lounge",
    "wof:placetype":"venue"
},
  "geometry": {"coordinates":[-79.957514,40.441097],"type":"Point"}
}