{
  "type": "Feature",
  "properties": {
    "iso:country":"US",
    "sg:address":"815 Suffolk Rd",
    "sg:city":"Jenkintown",
    "sg:classifiers":[
        {
            "category":"Home & Garden",
            "subcategory":"Hardware",
            "type":"Retail Goods"
        }
    ],
    "sg:phone":"+1 215 572 0175",
    "sg:postcode":"19046",
    "sg:province":"PA",
    "sg:tags":[
        "tool",
        "used"
    ],
    "wof:name":"Decision Solutions",
    "wof:placetype":"venue"
},
  "geometry": {"coordinates":[-75.099047,40.093954],"type":"Point"}
}