{
  "type": "Feature",
  "properties": {
    "iso:country":"US",
    "sg:address":"38 N 2nd St",
    "sg:city":"Lewisburg",
    "sg:classifiers":[
        {
            "category":"Health Services",
            "subcategory":"Doctor",
            "type":"Services"
        }
    ],
    "sg:phone":"+1 570 524 4454",
    "sg:postcode":"17837",
    "sg:province":"PA",
    "sg:tags":[
        "dentist"
    ],
    "sg:website":"www.drwinans.com",
    "wof:name":"Lawrence J Winans DDS",
    "wof:placetype":"venue"
},
  "geometry": {"coordinates":[-76.884609,40.966034],"type":"Point"}
}