{
  "type": "Feature",
  "properties": {
    "iso:country":"US",
    "sg:address":"468 Kline Rd",
    "sg:city":"Sligo",
    "sg:classifiers":[
        {
            "category":"Wholesale",
            "subcategory":"Motor Vehicles",
            "type":"Manufacturing & Wholesale Goods"
        }
    ],
    "sg:phone":"+1   ",
    "sg:postcode":"16255",
    "sg:province":"PA",
    "wof:name":"Randy Brown",
    "wof:placetype":"venue"
},
  "geometry": {"coordinates":[-79.44268,41.131944],"type":"Point"}
}