{
  "type": "Feature",
  "properties": {
    "addr:full":"510 Buena Vista Rd Chicora PA 16025",
    "addr:housenumber":"510",
    "addr:postcode":"16025",
    "addr:street":"Buena Vista Rd",
    "iso:country":"US",
    "sg:address":"510 Buena Vista Rd",
    "sg:city":"Chicora",
    "sg:classifiers":[
        {
            "category":"Farming",
            "subcategory":"Farm",
            "type":"Manufacturing & Wholesale Goods"
        }
    ],
    "sg:phone":"+1   ",
    "sg:postcode":"16025",
    "sg:province":"PA",
    "sg:tags":[
        "crop",
        "general"
    ],
    "wof:name":"James Anderson",
    "wof:placetype":"venue"
},
  "geometry": {"coordinates":[-79.756344,40.9978],"type":"Point"}
}