{
  "type": "Feature",
  "properties": {
    "addr:full":"246 Horning Rd Bethel Park PA 15102",
    "addr:housenumber":"246",
    "addr:postcode":"15102",
    "addr:street":"Horning Rd",
    "iso:country":"US",
    "sg:address":"246 Horning Rd",
    "sg:city":"Bethel Park",
    "sg:classifiers":[
        {
            "category":"Real Estate",
            "subcategory":"Real Estate Operator",
            "type":"Services"
        }
    ],
    "sg:phone":"+1 412 854 2001",
    "sg:postcode":"15102",
    "sg:province":"PA",
    "sg:tags":[
        "building",
        "nonresidential"
    ],
    "wof:name":"E School Mall",
    "wof:placetype":"venue"
},
  "geometry": {"coordinates":[-80.02215700000001,40.343933],"type":"Point"}
}