{
  "type": "Feature",
  "properties": {
    "addr:full":"14329 Rte 68 Sligo PA 16255",
    "addr:housenumber":"14329",
    "addr:postcode":"16255",
    "addr:street":"Rte 68",
    "iso:country":"US",
    "sg:address":"14329 Rte 68",
    "sg:city":"Sligo",
    "sg:classifiers":[
        {
            "category":"Freight",
            "type":"Transportation"
        }
    ],
    "sg:phone":"+1 814 745 2392",
    "sg:postcode":"16255",
    "sg:province":"PA",
    "sg:tags":[
        "hauling",
        "trucking"
    ],
    "wof:name":"Burns Farms",
    "wof:placetype":"venue"
},
  "geometry": {"coordinates":[-79.464191,41.110868],"type":"Point"}
}