{
  "type": "Feature",
  "properties": {
    "iso:country":"US",
    "sg:address":"405 Upper Claar Rd",
    "sg:city":"Claysburg",
    "sg:classifiers":[
        {
            "category":"Place Of Worship",
            "subcategory":"Church",
            "type":"Public Place"
        },
        {
            "category":"Place Of Worship",
            "type":"Public Place"
        },
        {
            "category":"Organizations",
            "subcategory":"Religious Organization",
            "type":"Services"
        }
    ],
    "sg:phone":"+1 814 239 5449",
    "sg:postcode":"16625",
    "sg:province":"PA",
    "sg:tags":[
        "churches-brethren",
        "brother",
        "churches-mennonite"
    ],
    "wof:name":"Upper Claar Church Of The Brethren Inc",
    "wof:placetype":"venue"
},
  "geometry": {"coordinates":[-78.515145,40.28656],"type":"Point"}
}