{
  "type": "Feature",
  "properties": {
    "iso:country":"US",
    "sg:address":"375 Main St",
    "sg:city":"Kersey",
    "sg:classifiers":[
        {
            "category":"Manufacturing",
            "subcategory":"Tools & Machinery",
            "type":"Manufacturing & Wholesale Goods"
        },
        {
            "category":"Retail",
            "subcategory":"Repair Shop",
            "type":"Services"
        },
        {
            "category":"Retail",
            "subcategory":"Auto Repair",
            "type":"Services"
        }
    ],
    "sg:phone":"+1 814 885 6744",
    "sg:postcode":"15846",
    "sg:province":"PA",
    "sg:tags":[
        "machine",
        "automobile",
        "machinery-rebuild"
    ],
    "wof:name":"Al's Machining",
    "wof:placetype":"venue"
},
  "geometry": {"coordinates":[-78.603981,41.361935],"type":"Point"}
}