{
  "type": "Feature",
  "properties": {
    "iso:country":"US",
    "sg:address":"1387 Brechbill Rd",
    "sg:city":"Chambersburg",
    "sg:classifiers":[
        {
            "category":"Home & Garden",
            "subcategory":"Building Materials",
            "type":"Retail Goods"
        }
    ],
    "sg:phone":"+1 717 267 7885",
    "sg:postcode":"17202",
    "sg:province":"PA",
    "sg:tags":[
        "wallpaper"
    ],
    "wof:name":"Jessica's Wall Coverings Corp",
    "wof:placetype":"venue"
},
  "geometry": {"coordinates":[-80.243394,40.099516],"type":"Point"}
}