{
  "type": "Feature",
  "properties": {
    "iso:country":"US",
    "sg:address":"907 Scalp Ave",
    "sg:city":"Johnstown",
    "sg:classifiers":[
        {
            "category":"Professional",
            "subcategory":"Computer Services",
            "type":"Services"
        }
    ],
    "sg:phone":"+1 814 262 9693",
    "sg:postcode":"15904",
    "sg:province":"PA",
    "sg:tags":[
        "repair"
    ],
    "wof:name":"Datalan Systems Inc",
    "wof:placetype":"venue"
},
  "geometry": {"coordinates":[-78.865436,40.286178],"type":"Point"}
}