{
  "type": "Feature",
  "properties": {
    "iso:country":"US",
    "sg:address":"810 Carbon St",
    "sg:city":"Jim Thorpe",
    "sg:classifiers":[
        {
            "category":"Education",
            "subcategory":"Special Training",
            "type":"Public Place"
        }
    ],
    "sg:phone":"+1 570 325 9440",
    "sg:postcode":"18229",
    "sg:province":"PA",
    "sg:tags":[
        "g"
    ],
    "wof:name":"Perry Music Studio",
    "wof:placetype":"venue"
},
  "geometry": {"coordinates":[-75.75094,40.863427],"type":"Point"}
}