{
  "type": "Feature",
  "properties": {
    "addr:full":"321 Wyandotte St Bethlehem PA 18015",
    "addr:housenumber":"321",
    "addr:postcode":"18015",
    "addr:street":"Wyandotte St",
    "iso:country":"US",
    "sg:address":"321 Wyandotte St",
    "sg:city":"Bethlehem",
    "sg:classifiers":[
        {
            "category":"Organizations",
            "subcategory":"Religious Organization",
            "type":"Services"
        }
    ],
    "sg:phone":"+1 610 865 0727",
    "sg:postcode":"18015",
    "sg:province":"PA",
    "sg:tags":[
        "church"
    ],
    "sg:website":"www.nativitycathedral.org",
    "wof:name":"Cathedral Church of Nativity",
    "wof:placetype":"venue"
},
  "geometry": {"coordinates":[-75.384396,40.610515],"type":"Point"}
}