{
  "type": "Feature",
  "properties": {
    "iso:country":"US",
    "sg:address":"12 S 4th St",
    "sg:city":"Emmaus",
    "sg:classifiers":[
        {
            "category":"Personal",
            "subcategory":"Tanning Parlor",
            "type":"Services"
        },
        {
            "category":"Personal",
            "subcategory":"Day Spa",
            "type":"Services"
        },
        {
            "category":"Personal",
            "subcategory":"Nail Salon",
            "type":"Services"
        }
    ],
    "sg:phone":"+1 610 965 8444",
    "sg:postcode":"18049",
    "sg:province":"PA",
    "wof:name":"Bodyworks",
    "wof:placetype":"venue"
},
  "geometry": {"coordinates":[-75.491699,40.5345],"type":"Point"}
}