{
  "type": "Feature",
  "properties": {
    "iso:country":"US",
    "sg:address":"62 N Mountain Blvd",
    "sg:city":"Mountain Top",
    "sg:classifiers":[
        {
            "category":"Health Services",
            "subcategory":"Clinic",
            "type":"Services"
        }
    ],
    "sg:phone":"+1 570 474 6925",
    "sg:postcode":"18707",
    "sg:province":"PA",
    "sg:tags":[
        "home"
    ],
    "wof:name":"Omni Home Care",
    "wof:placetype":"venue"
},
  "geometry": {"coordinates":[-75.884985,41.163157],"type":"Point"}
}