{
  "type": "Feature",
  "properties": {
    "iso:country":"US",
    "sg:address":"13437 Worleytown Rd",
    "sg:city":"Greencastle",
    "sg:classifiers":[
        {
            "category":"Government",
            "subcategory":"Office",
            "type":"Public Place"
        }
    ],
    "sg:phone":"+1 717 597 9798",
    "sg:postcode":"17225",
    "sg:province":"PA",
    "sg:tags":[
        "village"
    ],
    "wof:name":"Antrim Twp Sewage Treatment",
    "wof:placetype":"venue"
},
  "geometry": {"coordinates":[-77.779769,39.74635],"type":"Point"}
}