{
  "type": "Feature",
  "properties": {
    "addr:full":"36 S Baltimore St Dillsburg PA 17019",
    "addr:housenumber":"36",
    "addr:postcode":"17019",
    "addr:street":"S Baltimore St",
    "iso:country":"US",
    "sg:address":"36 S Baltimore St",
    "sg:city":"Dillsburg",
    "sg:classifiers":[
        {
            "category":"Food & Beverages",
            "subcategory":"Candy",
            "type":"Retail Goods"
        }
    ],
    "sg:phone":"+1 717 502 8733",
    "sg:postcode":"17019",
    "sg:province":"PA",
    "wof:name":"Cindfullysweet",
    "wof:placetype":"venue"
},
  "geometry": {"coordinates":[-77.03559300000001,40.110389],"type":"Point"}
}