{
  "type": "Feature",
  "properties": {
    "iso:country":"US",
    "sg:address":"6300 Greenway Ave",
    "sg:city":"Philadelphia",
    "sg:classifiers":[
        {
            "category":"Personal",
            "subcategory":"Beauty Salon",
            "type":"Services"
        }
    ],
    "sg:phone":"+1 215 727 6335",
    "sg:postcode":"19142",
    "sg:province":"PA",
    "wof:name":"Hyden's Salon",
    "wof:placetype":"venue"
},
  "geometry": {"coordinates":[-75.234337,39.927526],"type":"Point"}
}