{
  "type": "Feature",
  "properties": {
    "iso:country":"US",
    "sg:address":"1138 N Chester Rd",
    "sg:city":"West Chester",
    "sg:classifiers":[
        {
            "category":"Health Services",
            "subcategory":"Clinic",
            "type":"Services"
        }
    ],
    "sg:phone":"+1   ",
    "sg:postcode":"19380",
    "sg:province":"PA",
    "wof:name":"Accelerated Health Systems",
    "wof:placetype":"venue"
},
  "geometry": {"coordinates":[-75.547495,40.010264],"type":"Point"}
}