{
  "type": "Feature",
  "properties": {
    "iso:country":"US",
    "sg:address":"1660 Broadway Ave",
    "sg:city":"Pittsburgh",
    "sg:classifiers":[
        {
            "category":"Professional",
            "subcategory":"Research",
            "type":"Services"
        }
    ],
    "sg:phone":"+1 412 921 1517",
    "sg:postcode":"15216",
    "sg:province":"PA",
    "sg:tags":[
        "market",
        "analysis"
    ],
    "wof:name":"O'Leary's Interviewing Svc",
    "wof:placetype":"venue"
},
  "geometry": {"coordinates":[-80.024743,40.410194],"type":"Point"}
}