{
  "type": "Feature",
  "properties": {
    "iso:country":"US",
    "sg:address":"1616 Walnut St Ste 806",
    "sg:city":"Philadelphia",
    "sg:classifiers":[
        {
            "category":"Health Services",
            "subcategory":"Doctor",
            "type":"Services"
        },
        {
            "category":"Health Services",
            "subcategory":"Clinic",
            "type":"Services"
        }
    ],
    "sg:phone":"+1 215 546 6670",
    "sg:postcode":"19103",
    "sg:province":"PA",
    "sg:tags":[
        "psychological",
        "psychologist"
    ],
    "wof:name":"Jacqueline Duci Psyd",
    "wof:placetype":"venue"
},
  "geometry": {"coordinates":[-75.168054,39.949812],"type":"Point"}
}