{
  "type": "Feature",
  "properties": {
    "iso:country":"US",
    "sg:address":"78 Tuscarawas Rd",
    "sg:city":"Beaver",
    "sg:classifiers":[
        {
            "category":"Health Services",
            "subcategory":"Doctor",
            "type":"Services"
        }
    ],
    "sg:phone":"+1   ",
    "sg:postcode":"15009",
    "sg:province":"PA",
    "sg:tags":[
        "medical"
    ],
    "wof:name":"Valley Orthopaedic Assoc PC",
    "wof:placetype":"venue"
},
  "geometry": {"coordinates":[-80.31538399999999,40.693342],"type":"Point"}
}