{
  "type": "Feature",
  "properties": {
    "addr:full":"2962 Kings Ln Lancaster PA 17601",
    "addr:housenumber":"2962",
    "addr:postcode":"17601",
    "addr:street":"Kings Ln",
    "iso:country":"US",
    "sg:address":"2962 Kings Ln",
    "sg:city":"Lancaster",
    "sg:classifiers":[
        {
            "category":"Professional",
            "type":"Services"
        },
        {
            "category":"Building & Trades",
            "subcategory":"Construction",
            "type":"Services"
        }
    ],
    "sg:phone":"+1 717 560 5411",
    "sg:postcode":"17601",
    "sg:province":"PA",
    "sg:tags":[
        "new",
        "industrial",
        "commercial",
        "establishment"
    ],
    "wof:name":"Lancaster Design Build",
    "wof:placetype":"venue"
},
  "geometry": {"coordinates":[-76.391516,40.079544],"type":"Point"}
}