{
  "type": "Feature",
  "properties": {
    "addr:full":"1732 State Rte 143 Lenhartsville PA 19534",
    "addr:housenumber":"1732",
    "addr:postcode":"19534",
    "addr:street":"State Rte 143 Lenhartsville",
    "iso:country":"US",
    "sg:address":"1732 State Rte 143",
    "sg:city":"Lenhartsville",
    "sg:classifiers":[
        {
            "category":"Building & Trades",
            "subcategory":"Construction",
            "type":"Services"
        }
    ],
    "sg:phone":"+1 610 756 4199",
    "sg:postcode":"19534",
    "sg:province":"PA",
    "sg:tags":[
        "dry wall",
        "contractor"
    ],
    "wof:name":"HES Drywall",
    "wof:placetype":"venue"
},
  "geometry": {"coordinates":[-75.87383199999999,40.600021],"type":"Point"}
}