{
  "type": "Feature",
  "properties": {
    "addr:full":"108 Zola St Kersey PA 15846",
    "addr:housenumber":"108",
    "addr:postcode":"15846",
    "addr:street":"Zola St",
    "iso:country":"US",
    "sg:address":"108 Zola St",
    "sg:city":"Kersey",
    "sg:classifiers":[
        {
            "category":"Autos & Motor Vehicles",
            "subcategory":"Auto Supplies",
            "type":"Retail Goods"
        },
        {
            "category":"Retail",
            "subcategory":"Auto Repair",
            "type":"Services"
        }
    ],
    "sg:phone":"+1 814 885 8572",
    "sg:postcode":"15846",
    "sg:province":"PA",
    "sg:tags":[
        "body",
        "automobile",
        "truck",
        "painting",
        "repairing"
    ],
    "wof:name":"Kersey Motor Co",
    "wof:placetype":"venue"
},
  "geometry": {"coordinates":[-78.608439,41.346516],"type":"Point"}
}