{
  "type": "Feature",
  "properties": {
    "addr:full":"3826 Liberty St Erie PA 16509",
    "addr:housenumber":"3826",
    "addr:postcode":"16509",
    "addr:street":"Liberty St",
    "iso:country":"US",
    "sg:address":"3826 Liberty St",
    "sg:city":"Erie",
    "sg:classifiers":[
        {
            "category":"Professional",
            "subcategory":"Computer Services",
            "type":"Services"
        }
    ],
    "sg:phone":"+1 814 860 7999",
    "sg:postcode":"16509",
    "sg:province":"PA",
    "sg:tags":[
        "repair"
    ],
    "wof:name":"P C Urgent Care",
    "wof:placetype":"venue"
},
  "geometry": {"coordinates":[-80.08342399999999,42.094655],"type":"Point"}
}