{
  "type": "Feature",
  "properties": {
    "addr:full":"444 Pennsylvania Ave W Warren PA 16365",
    "addr:housenumber":"444",
    "addr:postcode":"16365",
    "addr:street":"Pennsylvania Ave W",
    "iso:country":"US",
    "sg:address":"444 Pennsylvania Ave W",
    "sg:city":"Warren",
    "sg:classifiers":[
        {
            "category":"Organizations",
            "subcategory":"Religious Organization",
            "type":"Services"
        }
    ],
    "sg:phone":"+1   ",
    "sg:postcode":"16365",
    "sg:province":"PA",
    "sg:tags":[
        "church"
    ],
    "wof:name":"Trinity Mem Episcpal Church",
    "wof:placetype":"venue"
},
  "geometry": {"coordinates":[-79.150751,41.845283],"type":"Point"}
}