{
  "type": "Feature",
  "properties": {
    "iso:country":"US",
    "sg:address":"3904 Grant St",
    "sg:city":"Reading",
    "sg:classifiers":[
        {
            "category":"Professional",
            "subcategory":"Art Services",
            "type":"Services"
        }
    ],
    "sg:phone":"+1 610 779 1836",
    "sg:postcode":"19606",
    "sg:province":"PA",
    "sg:tags":[
        "calligrapher"
    ],
    "wof:name":"Calligraphy Creations",
    "wof:placetype":"venue"
},
  "geometry": {"coordinates":[-75.86891799999999,40.31648],"type":"Point"}
}