{
  "type": "Feature",
  "properties": {
    "iso:country":"US",
    "sg:address":"3903 New Texas Rd",
    "sg:city":"Pittsburgh",
    "sg:classifiers":[
        {
            "category":"Building & Trades",
            "subcategory":"Landscaping Services",
            "type":"Services"
        }
    ],
    "sg:phone":"+1   ",
    "sg:postcode":"15239",
    "sg:province":"PA",
    "sg:tags":[
        "tree"
    ],
    "wof:name":"Jj Tree Service and Ldscpg",
    "wof:placetype":"venue"
},
  "geometry": {"coordinates":[-79.73808200000001,40.484258],"type":"Point"}
}