{
  "type": "Feature",
  "properties": {
    "addr:full":"637 Chestnut St Lebanon PA 17042",
    "addr:housenumber":"637",
    "addr:postcode":"17042",
    "addr:street":"Chestnut St",
    "iso:country":"US",
    "sg:address":"637 Chestnut St",
    "sg:city":"Lebanon",
    "sg:classifiers":[
        {
            "category":"Organizations",
            "subcategory":"Religious Organization",
            "type":"Services"
        }
    ],
    "sg:phone":"+1 717 838 1571",
    "sg:postcode":"17042",
    "sg:province":"PA",
    "wof:name":"Child Evangelism Fellowship",
    "wof:placetype":"venue"
},
  "geometry": {"coordinates":[-76.421967,40.338241],"type":"Point"}
}