{
  "type": "Feature",
  "properties": {
    "iso:country":"US",
    "sg:address":"823 Connell Ave",
    "sg:city":"Lansdowne",
    "sg:classifiers":[
        {
            "category":"Building & Trades",
            "subcategory":"Plumbing",
            "type":"Services"
        }
    ],
    "sg:phone":"+1   ",
    "sg:postcode":"19050",
    "sg:province":"PA",
    "sg:tags":[
        "contractor"
    ],
    "wof:name":"Bollers Plumbing Co",
    "wof:placetype":"venue"
},
  "geometry": {"coordinates":[-75.245836,39.930948],"type":"Point"}
}