{
  "type": "Feature",
  "properties": {
    "iso:country":"US",
    "sg:address":"540 Main St",
    "sg:city":"Edwardsville",
    "sg:classifiers":[
        {
            "category":"Organizations",
            "subcategory":"Non-profit Organization",
            "type":"Services"
        }
    ],
    "sg:phone":"+1 570 288 0403",
    "sg:postcode":"18704",
    "sg:province":"PA",
    "sg:tags":[
        "info",
        "addiction",
        "abuse",
        "treatment",
        "drug"
    ],
    "wof:name":"Clem-Mar House Inc",
    "wof:placetype":"venue"
},
  "geometry": {"coordinates":[-75.90733400000001,41.266388],"type":"Point"}
}