{
  "type": "Feature",
  "properties": {
    "iso:country":"US",
    "sg:address":"24 S Main St",
    "sg:city":"Morrisville",
    "sg:classifiers":[
        {
            "category":"Insurance",
            "subcategory":"Insurance Agent",
            "type":"Services"
        }
    ],
    "sg:phone":"+1   ",
    "sg:postcode":"19067",
    "sg:province":"PA",
    "wof:name":"LMS Financial Services",
    "wof:placetype":"venue"
},
  "geometry": {"coordinates":[-74.835863,40.240395],"type":"Point"}
}