{
  "type": "Feature",
  "properties": {
    "iso:country":"US",
    "sg:address":"350 Chestnut St",
    "sg:city":"Mifflinburg",
    "sg:classifiers":[
        {
            "category":"Shopping",
            "subcategory":"Bicycles & Sporting Goods",
            "type":"Retail Goods"
        }
    ],
    "sg:phone":"+1 570 966 0066",
    "sg:postcode":"17844",
    "sg:province":"PA",
    "wof:name":"Buffalo Valley Outdoor",
    "wof:placetype":"venue"
},
  "geometry": {"coordinates":[-77.046828,40.918126],"type":"Point"}
}