{
  "type": "Feature",
  "properties": {
    "addr:full":"505 Pine St Philadelphia PA 19106",
    "addr:housenumber":"505",
    "addr:postcode":"19106",
    "addr:street":"Pine St",
    "iso:country":"US",
    "sg:address":"505 Pine St",
    "sg:city":"Philadelphia",
    "sg:classifiers":[
        {
            "category":"Professional",
            "subcategory":"Lawyer & Legal Services",
            "type":"Services"
        }
    ],
    "sg:phone":"+1 215 546 1110",
    "sg:postcode":"19106",
    "sg:province":"PA",
    "wof:name":"Silverberg Richard J & Associates",
    "wof:placetype":"venue"
},
  "geometry": {"coordinates":[-75.150389,39.943854],"type":"Point"}
}