{
  "type": "Feature",
  "properties": {
    "iso:country":"US",
    "sg:address":"3623 N Hermitage Rd",
    "sg:city":"Transfer",
    "sg:classifiers":[
        {
            "category":"Restaurant",
            "type":"Food & Drink"
        }
    ],
    "sg:phone":"+1 724 646 3663",
    "sg:postcode":"16154",
    "sg:province":"PA",
    "wof:name":"Hughandle",
    "wof:placetype":"venue"
},
  "geometry": {"coordinates":[-80.41266899999999,41.327345],"type":"Point"}
}