{
  "type": "Feature",
  "properties": {
    "iso:country":"US",
    "sg:address":"105 S Queen St",
    "sg:city":"Littlestown",
    "sg:classifiers":[
        {
            "category":"Insurance",
            "subcategory":"Insurance Agent",
            "type":"Services"
        },
        {
            "category":"Insurance",
            "subcategory":"Hazard Insurance",
            "type":"Services"
        },
        {
            "category":"Insurance",
            "subcategory":"Title Insurance",
            "type":"Services"
        },
        {
            "category":"Insurance",
            "subcategory":"Life Insurance",
            "type":"Services"
        }
    ],
    "sg:phone":"+1 717 359 8464",
    "sg:postcode":"17340",
    "sg:province":"PA",
    "sg:tags":[
        "business",
        "auto",
        "commercial",
        "homeowner",
        "motorcycle",
        "renter"
    ],
    "wof:name":"Allstate Insurance Company - William Myer",
    "wof:placetype":"venue"
},
  "geometry": {"coordinates":[-77.08699300000001,39.743465],"type":"Point"}
}