{
  "type": "Feature",
  "properties": {
    "iso:country":"US",
    "sg:address":"322 Hillside Ave",
    "sg:city":"Brookhaven",
    "sg:classifiers":[
        {
            "category":"Wholesale",
            "subcategory":"Groceries",
            "type":"Manufacturing & Wholesale Goods"
        }
    ],
    "sg:phone":"+1   ",
    "sg:postcode":"19015",
    "sg:province":"PA",
    "wof:name":"M D Wright LLC",
    "wof:placetype":"venue"
},
  "geometry": {"coordinates":[-75.387708,39.877676],"type":"Point"}
}