{
  "type": "Feature",
  "properties": {
    "iso:country":"US",
    "sg:address":"801 Walnut St",
    "sg:city":"Easton",
    "sg:classifiers":[
        {
            "category":"Banks & Credit Unions",
            "subcategory":"Investment Brokerage",
            "type":"Services"
        }
    ],
    "sg:phone":"+1 610 252 0455",
    "sg:postcode":"18042",
    "sg:province":"PA",
    "sg:tags":[
        "consultant",
        "planning",
        "financial"
    ],
    "wof:name":"CJM Planning Corp",
    "wof:placetype":"venue"
},
  "geometry": {"coordinates":[-75.21925,40.68781],"type":"Point"}
}