{
  "type": "Feature",
  "properties": {
    "iso:country":"US",
    "sg:address":"102 Micheline Dr",
    "sg:city":"Old Forge",
    "sg:classifiers":[
        {
            "category":"Professional",
            "subcategory":"Printing & Photocopies",
            "type":"Services"
        }
    ],
    "sg:phone":"+1   ",
    "sg:postcode":"18518",
    "sg:province":"PA",
    "sg:tags":[
        "photocopying"
    ],
    "wof:name":"Copier Expert",
    "wof:placetype":"venue"
},
  "geometry": {"coordinates":[-75.74238099999999,41.352888],"type":"Point"}
}