{
  "type": "Feature",
  "properties": {
    "iso:country":"US",
    "sg:address":"7801 Essington Ave",
    "sg:city":"Philadelphia",
    "sg:classifiers":[
        {
            "category":"Government",
            "subcategory":"Office",
            "type":"Public Place"
        }
    ],
    "sg:phone":"+1 215 937 1359",
    "sg:postcode":"19153",
    "sg:province":"PA",
    "wof:name":"Military Shop",
    "wof:placetype":"venue"
},
  "geometry": {"coordinates":[-75.22537199999999,39.901623],"type":"Point"}
}