{
  "type": "Feature",
  "properties": {
    "addr:full":"111 S 11th St Philadelphia PA 19107",
    "addr:housenumber":"111",
    "addr:postcode":"19107",
    "addr:street":"S 11Th St",
    "iso:country":"US",
    "sg:address":"111 S 11th St",
    "sg:city":"Philadelphia",
    "sg:classifiers":[
        {
            "category":"Health Services",
            "subcategory":"Doctor",
            "type":"Services"
        }
    ],
    "sg:phone":"+1 215 955 8706",
    "sg:postcode":"19107",
    "sg:province":"PA",
    "wof:name":"Breecker Steven W MD",
    "wof:placetype":"venue"
},
  "geometry": {"coordinates":[-75.158625,39.949447],"type":"Point"}
}