{
  "type": "Feature",
  "properties": {
    "iso:country":"US",
    "sg:address":"1222 N Wales Rd",
    "sg:city":"North Wales",
    "sg:classifiers":[
        {
            "category":"Retail",
            "subcategory":"Laundry & Dry Cleaning",
            "type":"Services"
        }
    ],
    "sg:phone":"+1 215 393 9228",
    "sg:postcode":"19454",
    "sg:province":"PA",
    "sg:tags":[
        "cleaners"
    ],
    "wof:name":"Bell Run Cleaners",
    "wof:placetype":"venue"
},
  "geometry": {"coordinates":[-75.27225199999999,40.219852],"type":"Point"}
}