{
  "type": "Feature",
  "properties": {
    "iso:country":"US",
    "sg:address":"20267 Route 19",
    "sg:city":"Cranberry Twp",
    "sg:classifiers":[
        {
            "category":"Home & Garden",
            "subcategory":"Furniture",
            "type":"Retail Goods"
        }
    ],
    "sg:phone":"+1 724 779 9880",
    "sg:postcode":"16066",
    "sg:province":"PA",
    "sg:tags":[
        "store"
    ],
    "sg:website":"www.pier1.com",
    "wof:name":"Pier 1 Imports",
    "wof:placetype":"venue"
},
  "geometry": {"coordinates":[-80.10279800000001,40.6894],"type":"Point"}
}