{
  "type": "Feature",
  "properties": {
    "iso:country":"US",
    "sg:address":"2900 Knights Rd",
    "sg:city":"Bensalem",
    "sg:classifiers":[
        {
            "category":"Real Estate",
            "subcategory":"Real Estate Operator",
            "type":"Services"
        }
    ],
    "sg:phone":"+1 215 938 0875",
    "sg:postcode":"19020",
    "sg:province":"PA",
    "sg:tags":[
        "apartment"
    ],
    "wof:name":"Park Place Enterprises",
    "wof:placetype":"venue"
},
  "geometry": {"coordinates":[-74.952338,40.103498],"type":"Point"}
}