{
  "type": "Feature",
  "properties": {
    "iso:country":"US",
    "sg:address":"14389 Roberta Dr",
    "sg:city":"Irwin",
    "sg:classifiers":[
        {
            "category":"Building & Trades",
            "subcategory":"Construction",
            "type":"Services"
        }
    ],
    "sg:phone":"+1   ",
    "sg:postcode":"15642",
    "sg:province":"PA",
    "sg:tags":[
        "contractor"
    ],
    "wof:name":"William Patrick Masonry",
    "wof:placetype":"venue"
},
  "geometry": {"coordinates":[-79.77173000000001,40.332375],"type":"Point"}
}