{
  "type": "Feature",
  "properties": {
    "addr:full":"6324 Stenton Ave Philadelphia PA 19138",
    "addr:housenumber":"6324",
    "addr:postcode":"19138",
    "addr:street":"Stenton Ave",
    "iso:country":"US",
    "sg:address":"6324 Stenton Ave",
    "sg:city":"Philadelphia",
    "sg:classifiers":[
        {
            "category":"Banks & Credit Unions",
            "subcategory":"Bank",
            "type":"Services"
        }
    ],
    "sg:phone":"+1   ",
    "sg:postcode":"19138",
    "sg:province":"PA",
    "sg:tags":[
        "state"
    ],
    "wof:name":"Citizens Bank of Pennsylvania",
    "wof:placetype":"venue"
},
  "geometry": {"coordinates":[-75.165736,40.059601],"type":"Point"}
}