{
  "type": "Feature",
  "properties": {
    "addr:full":"217 Glasgow Rd Pittsburgh PA 15221",
    "addr:housenumber":"217",
    "addr:postcode":"15221",
    "addr:street":"Glasgow Rd",
    "iso:country":"US",
    "sg:address":"217 Glasgow Rd",
    "sg:city":"Pittsburgh",
    "sg:classifiers":[
        {
            "category":"Manufacturing",
            "subcategory":"Printing",
            "type":"Manufacturing & Wholesale Goods"
        }
    ],
    "sg:phone":"+1   ",
    "sg:postcode":"15221",
    "sg:province":"PA",
    "sg:tags":[
        "periodical"
    ],
    "wof:name":"Trader Publishing Company",
    "wof:placetype":"venue"
},
  "geometry": {"coordinates":[-79.857517,40.431802],"type":"Point"}
}