{
  "type": "Feature",
  "properties": {
    "addr:full":"610 Hansen Ave Lyndora PA 16045",
    "addr:housenumber":"610",
    "addr:postcode":"16045",
    "addr:street":"Hansen Ave",
    "iso:country":"US",
    "sg:address":"610 Hansen Ave",
    "sg:city":"Lyndora",
    "sg:classifiers":[
        {
            "category":"Organizations",
            "subcategory":"Religious Organization",
            "type":"Services"
        }
    ],
    "sg:phone":"+1   ",
    "sg:postcode":"16045",
    "sg:province":"PA",
    "wof:name":"Diocese of Parmar",
    "wof:placetype":"venue"
},
  "geometry": {"coordinates":[-79.911776,40.854417],"type":"Point"}
}