{
  "type": "Feature",
  "properties": {
    "iso:country":"US",
    "sg:address":"1380 Old Freeport Rd",
    "sg:city":"Pittsburgh",
    "sg:classifiers":[
        {
            "category":"Professional",
            "subcategory":"Accounting & Tax Preparation",
            "type":"Services"
        }
    ],
    "sg:phone":"+1 412 963 0234",
    "sg:postcode":"15238",
    "sg:province":"PA",
    "sg:tags":[
        "accountant"
    ],
    "wof:name":"Gottschalk & Gottschalk",
    "wof:placetype":"venue"
},
  "geometry": {"coordinates":[-79.871071,40.489479],"type":"Point"}
}