{
  "type": "Feature",
  "properties": {
    "iso:country":"US",
    "sg:address":"611 Bethlehem Pike",
    "sg:city":"Montgomeryville",
    "sg:classifiers":[
        {
            "category":"Professional",
            "subcategory":"Accounting & Tax Preparation",
            "type":"Services"
        }
    ],
    "sg:phone":"+1   ",
    "sg:postcode":"18915",
    "sg:province":"PA",
    "wof:name":"Kugler Pagan & Company PA",
    "wof:placetype":"venue"
},
  "geometry": {"coordinates":[-75.26039,40.277661],"type":"Point"}
}