{
  "type": "Feature",
  "properties": {
    "iso:country":"US",
    "sg:address":"1000 Easton Rd",
    "sg:city":"Wyncote",
    "sg:classifiers":[
        {
            "category":"Home & Garden",
            "subcategory":"Furniture",
            "type":"Retail Goods"
        }
    ],
    "sg:phone":"+1 215 887 0123",
    "sg:postcode":"19001",
    "sg:province":"PA",
    "sg:tags":[
        "store"
    ],
    "wof:name":"Furniture Unlimited  Inc",
    "wof:placetype":"venue"
},
  "geometry": {"coordinates":[-75.134483,40.119948],"type":"Point"}
}