{
  "type": "Feature",
  "properties": {
    "iso:country":"US",
    "sg:address":"3 Timothy Rd",
    "sg:city":"Shavertown",
    "sg:classifiers":[
        {
            "category":"Home & Garden",
            "subcategory":"Building Materials",
            "type":"Retail Goods"
        }
    ],
    "sg:phone":"+1   ",
    "sg:postcode":"18708",
    "sg:province":"PA",
    "wof:name":"AC Auto Glass",
    "wof:placetype":"venue"
},
  "geometry": {"coordinates":[-75.917,41.3286],"type":"Point"}
}