{
  "type": "Feature",
  "properties": {
    "iso:country":"US",
    "sg:address":"340 Kent Rd",
    "sg:city":"Springfield",
    "sg:classifiers":[
        {
            "category":"Professional",
            "subcategory":"Employment Agencies",
            "type":"Services"
        }
    ],
    "sg:phone":"+1   ",
    "sg:postcode":"19064",
    "sg:province":"PA",
    "sg:tags":[
        "help",
        "supply"
    ],
    "wof:name":"Vibe Assist L L C",
    "wof:placetype":"venue"
},
  "geometry": {"coordinates":[-75.321298,39.931684],"type":"Point"}
}