{
  "type": "Feature",
  "properties": {
    "iso:country":"US",
    "sg:address":"1821 Brighton Rd",
    "sg:city":"Pittsburgh",
    "sg:classifiers":[
        {
            "category":"Organizations",
            "subcategory":"Membership Organization",
            "type":"Services"
        }
    ],
    "sg:phone":"+1 412 321 0525",
    "sg:postcode":"15212",
    "sg:province":"PA",
    "wof:name":"Black Men Rising",
    "wof:placetype":"venue"
},
  "geometry": {"coordinates":[-80.017841,40.460023],"type":"Point"}
}