{
  "type": "Feature",
  "properties": {
    "iso:country":"US",
    "sg:address":"117 Langhorne Ave",
    "sg:city":"Johnstown",
    "sg:classifiers":[
        {
            "category":"Bars & Pubs",
            "type":"Food & Drink"
        }
    ],
    "sg:phone":"+1 814 536 9347",
    "sg:postcode":"15905",
    "sg:province":"PA",
    "sg:tags":[
        "bar"
    ],
    "wof:name":"Haven Bar",
    "wof:placetype":"venue"
},
  "geometry": {"coordinates":[-78.92336899999999,40.30381],"type":"Point"}
}