{
  "type": "Feature",
  "properties": {
    "iso:country":"US",
    "sg:address":"1529 Walnut St",
    "sg:city":"Philadelphia",
    "sg:classifiers":[
        {
            "category":"Professional",
            "subcategory":"Lawyer & Legal Services",
            "type":"Services"
        }
    ],
    "sg:phone":"+1   ",
    "sg:postcode":"19102",
    "sg:province":"PA",
    "wof:name":"Joshua B Ladov PC",
    "wof:placetype":"venue"
},
  "geometry": {"coordinates":[-75.167418,39.949804],"type":"Point"}
}