{
  "type": "Feature",
  "properties": {
    "iso:country":"US",
    "sg:address":"85 Oriole Cir N",
    "sg:city":"Lock Haven",
    "sg:classifiers":[
        {
            "category":"Health Services",
            "subcategory":"Doctor",
            "type":"Services"
        }
    ],
    "sg:phone":"+1 570 769 6133",
    "sg:postcode":"17745",
    "sg:province":"PA",
    "sg:tags":[
        "physician",
        "surgeon"
    ],
    "wof:name":"J J Dolan MD",
    "wof:placetype":"venue"
},
  "geometry": {"coordinates":[-77.368917,41.178513],"type":"Point"}
}