{
  "type": "Feature",
  "properties": {
    "iso:country":"US",
    "sg:address":"4984 Glenview St",
    "sg:city":"Schnecksville",
    "sg:classifiers":[
        {
            "category":"Building & Trades",
            "subcategory":"Construction",
            "type":"Services"
        }
    ],
    "sg:phone":"+1 610 799 2376",
    "sg:postcode":"18078",
    "sg:province":"PA",
    "sg:tags":[
        "house"
    ],
    "wof:name":"Bruce C Laub Builder",
    "wof:placetype":"venue"
},
  "geometry": {"coordinates":[-75.626509,40.672917],"type":"Point"}
}