{
  "type": "Feature",
  "properties": {
    "iso:country":"US",
    "sg:address":"201 Rte 940",
    "sg:city":"Mount Pocono",
    "sg:classifiers":[
        {
            "category":"Real Estate",
            "subcategory":"Real Estate Services",
            "type":"Services"
        }
    ],
    "sg:phone":"+1   ",
    "sg:postcode":"18344",
    "sg:province":"PA",
    "sg:tags":[
        "abstract",
        "legal",
        "title"
    ],
    "wof:name":"Homestead Land Services Inc",
    "wof:placetype":"venue"
},
  "geometry": {"coordinates":[-75.363167,41.12581],"type":"Point"}
}