{
  "type": "Feature",
  "properties": {
    "addr:full":"440 Jefferson Ave Pittsburgh PA 15202",
    "addr:housenumber":"440",
    "addr:postcode":"15202",
    "addr:street":"Jefferson Ave",
    "iso:country":"US",
    "sg:address":"440 Jefferson Ave",
    "sg:city":"Pittsburgh",
    "sg:classifiers":[
        {
            "category":"Real Estate",
            "subcategory":"Real Estate Agent",
            "type":"Services"
        }
    ],
    "sg:phone":"+1   ",
    "sg:postcode":"15202",
    "sg:province":"PA",
    "wof:name":"Prudential",
    "wof:placetype":"venue"
},
  "geometry": {"coordinates":[-80.056982,40.493511],"type":"Point"}
}