{
  "type": "Feature",
  "properties": {
    "iso:country":"US",
    "sg:address":"927 Blunston St",
    "sg:city":"Columbia",
    "sg:classifiers":[
        {
            "category":"Manufacturing",
            "subcategory":"Glass & Minerals",
            "type":"Manufacturing & Wholesale Goods"
        }
    ],
    "sg:phone":"+1 717 684 3716",
    "sg:postcode":"17512",
    "sg:province":"PA",
    "sg:tags":[
        "cap",
        "bottle",
        "seal"
    ],
    "wof:name":"Keystone Cap Co, Inc",
    "wof:placetype":"venue"
},
  "geometry": {"coordinates":[-76.491572,40.034634],"type":"Point"}
}