{
  "type": "Feature",
  "properties": {
    "iso:country":"US",
    "sg:address":"204 5th St",
    "sg:city":"Johnstown",
    "sg:classifiers":[
        {
            "category":"Organizations",
            "subcategory":"Community Association",
            "type":"Services"
        }
    ],
    "sg:phone":"+1   ",
    "sg:postcode":"15909",
    "sg:province":"PA",
    "wof:name":"American Fraternal Union",
    "wof:placetype":"venue"
},
  "geometry": {"coordinates":[-78.886184,40.351378],"type":"Point"}
}