{
  "type": "Feature",
  "properties": {
    "addr:full":"839 Bullock Ave Lansdowne PA 19050",
    "addr:housenumber":"839",
    "addr:postcode":"19050",
    "addr:street":"Bullock Ave",
    "iso:country":"US",
    "sg:address":"839 Bullock Ave",
    "sg:city":"Lansdowne",
    "sg:classifiers":[
        {
            "category":"Building & Trades",
            "subcategory":"Electrical",
            "type":"Services"
        }
    ],
    "sg:phone":"+1   ",
    "sg:postcode":"19050",
    "sg:province":"PA",
    "sg:tags":[
        "electrical",
        "contractor"
    ],
    "wof:name":"C R Electric",
    "wof:placetype":"venue"
},
  "geometry": {"coordinates":[-75.24927,39.930859],"type":"Point"}
}