{
  "type": "Feature",
  "properties": {
    "iso:country":"US",
    "sg:address":"235 Pine Tract Rd",
    "sg:city":"Butler",
    "sg:classifiers":[
        {
            "category":"Home & Garden",
            "subcategory":"Home Furnishings",
            "type":"Retail Goods"
        }
    ],
    "sg:phone":"+1 724 282 3031",
    "sg:postcode":"16001",
    "sg:province":"PA",
    "sg:tags":[
        "installs",
        "window",
        "covering"
    ],
    "wof:name":"Custom Window Treatments",
    "wof:placetype":"venue"
},
  "geometry": {"coordinates":[-79.880448,40.928964],"type":"Point"}
}