{
  "type": "Feature",
  "properties": {
    "iso:country":"US",
    "sg:address":"2249 N Broad St",
    "sg:city":"Philadelphia",
    "sg:classifiers":[
        {
            "category":"Personal",
            "type":"Services"
        },
        {
            "category":"Travel",
            "subcategory":"Bed & Breakfast",
            "type":"Entertainment"
        }
    ],
    "sg:phone":"+1 215 763 0159",
    "sg:postcode":"19132",
    "sg:province":"PA",
    "sg:tags":[
        "mover",
        "inn"
    ],
    "sg:website":"http://www.bigbrotherlittlebrothermoving.webs.com",
    "wof:name":"Big Brother Little Brother Enterprises",
    "wof:placetype":"venue"
},
  "geometry": {"coordinates":[-75.15545400000001,39.987555],"type":"Point"}
}