{
  "type": "Feature",
  "properties": {
    "addr:full":"67 W Butler Dr Drums PA 18222",
    "addr:housenumber":"67",
    "addr:postcode":"18222",
    "addr:street":"W Butler Dr",
    "iso:country":"US",
    "sg:address":"67 W Butler Dr",
    "sg:city":"Drums",
    "sg:classifiers":[
        {
            "category":"Professional",
            "subcategory":"Lawyer & Legal Services",
            "type":"Services"
        }
    ],
    "sg:phone":"+1 570 788 2121",
    "sg:postcode":"18222",
    "sg:province":"PA",
    "sg:tags":[
        "plan"
    ],
    "wof:name":"Law Offices George R Hludzik",
    "wof:placetype":"venue"
},
  "geometry": {"coordinates":[-75.970341,41.021723],"type":"Point"}
}