{
  "type": "Feature",
  "properties": {
    "iso:country":"US",
    "sg:address":"110 Robert St",
    "sg:city":"Nanticoke",
    "sg:classifiers":[
        {
            "category":"Food & Beverages",
            "subcategory":"Groceries & Convenience Stores",
            "type":"Retail Goods"
        }
    ],
    "sg:phone":"+1 570 735 7441",
    "sg:postcode":"18634",
    "sg:province":"PA",
    "wof:name":"Pen Fern Mart",
    "wof:placetype":"venue"
},
  "geometry": {"coordinates":[-76.01240900000001,41.187775],"type":"Point"}
}