{
  "type": "Feature",
  "properties": {
    "iso:country":"US",
    "sg:address":"4004 Lyman Dr",
    "sg:city":"Philadelphia",
    "sg:classifiers":[
        {
            "category":"Restaurant",
            "type":"Food & Drink"
        }
    ],
    "sg:phone":"+1 215 612 1879",
    "sg:postcode":"19114",
    "sg:province":"PA",
    "sg:tags":[
        "buffet"
    ],
    "wof:name":"New China Buffet",
    "wof:placetype":"venue"
},
  "geometry": {"coordinates":[-74.98319600000001,40.06433],"type":"Point"}
}