{
  "type": "Feature",
  "properties": {
    "iso:country":"US",
    "sg:address":"141 S 10th St",
    "sg:city":"Reading",
    "sg:classifiers":[
        {
            "category":"Retail",
            "subcategory":"Auto Repair",
            "type":"Services"
        }
    ],
    "sg:phone":"+1 610 374 7887",
    "sg:postcode":"19602",
    "sg:province":"PA",
    "sg:tags":[
        "repairing",
        "automobile"
    ],
    "wof:name":"Larry's Automotive",
    "wof:placetype":"venue"
},
  "geometry": {"coordinates":[-75.91814100000001,40.33264],"type":"Point"}
}