{
  "type": "Feature",
  "properties": {
    "iso:country":"US",
    "sg:address":"600 Freeport Rd",
    "sg:city":"Butler",
    "sg:classifiers":[
        {
            "category":"Social Services",
            "subcategory":"Adult Care",
            "type":"Services"
        }
    ],
    "sg:phone":"+1 724 352 4334",
    "sg:postcode":"16002",
    "sg:province":"PA",
    "sg:tags":[
        "home",
        "residential"
    ],
    "wof:name":"Meadows Manor",
    "wof:placetype":"venue"
},
  "geometry": {"coordinates":[-79.826196,40.802547],"type":"Point"}
}