{
  "type": "Feature",
  "properties": {
    "iso:country":"US",
    "sg:address":"548 Davisville Rd",
    "sg:city":"Willow Grove",
    "sg:classifiers":[
        {
            "category":"Building & Trades",
            "subcategory":"Construction",
            "type":"Services"
        }
    ],
    "sg:phone":"+1   ",
    "sg:postcode":"19090",
    "sg:province":"PA",
    "sg:tags":[
        "residential"
    ],
    "wof:name":"Ivyland Custom Contractors",
    "wof:placetype":"venue"
},
  "geometry": {"coordinates":[-75.106633,40.150713],"type":"Point"}
}