{
  "type": "Feature",
  "properties": {
    "iso:country":"US",
    "sg:address":"196 S Tremont St",
    "sg:city":"Tremont",
    "sg:classifiers":[
        {
            "category":"Manufacturing",
            "subcategory":"Tools & Machinery",
            "type":"Manufacturing & Wholesale Goods"
        }
    ],
    "sg:phone":"+1 570 695 3911",
    "sg:postcode":"17981",
    "sg:province":"PA",
    "sg:tags":[
        "shop",
        "die"
    ],
    "wof:name":"West End Precision",
    "wof:placetype":"venue"
},
  "geometry": {"coordinates":[-76.388479,40.627395],"type":"Point"}
}