{
  "type": "Feature",
  "properties": {
    "iso:country":"US",
    "sg:address":"1949 Lincoln Hwy",
    "sg:city":"North Versailles",
    "sg:classifiers":[
        {
            "category":"Autos & Motor Vehicles",
            "subcategory":"Automobile Sales",
            "type":"Retail Goods"
        }
    ],
    "sg:phone":"+1 412 824 8108",
    "sg:postcode":"15137",
    "sg:province":"PA",
    "sg:tags":[
        "car",
        "used",
        "dealer"
    ],
    "wof:name":"Ace's Auto Sales",
    "wof:placetype":"venue"
},
  "geometry": {"coordinates":[-79.775035,40.364936],"type":"Point"}
}