{
  "type": "Feature",
  "properties": {
    "iso:country":"US",
    "sg:address":"2119 York Rd",
    "sg:city":"Jamison",
    "sg:classifiers":[
        {
            "category":"Retail",
            "subcategory":"Car Wash",
            "type":"Services"
        }
    ],
    "sg:phone":"+1 215 343 2100",
    "sg:postcode":"18929",
    "sg:province":"PA",
    "sg:tags":[
        "polishing",
        "washing"
    ],
    "wof:name":"Carwash Express",
    "wof:placetype":"venue"
},
  "geometry": {"coordinates":[-75.089735,40.251796],"type":"Point"}
}