{
  "type": "Feature",
  "properties": {
    "addr:full":"1 E Crafton Ave Pittsburgh PA 15205",
    "addr:housenumber":"1",
    "addr:postcode":"15205",
    "addr:street":"E Crafton Ave",
    "iso:country":"US",
    "sg:address":"1 E Crafton Ave",
    "sg:city":"Pittsburgh",
    "sg:classifiers":[
        {
            "category":"Wholesale",
            "subcategory":"Groceries",
            "type":"Manufacturing & Wholesale Goods"
        }
    ],
    "sg:phone":"+1 412 922 8866",
    "sg:postcode":"15205",
    "sg:province":"PA",
    "sg:tags":[
        "food",
        "broker"
    ],
    "sg:website":"www.avfs.com",
    "wof:name":"Allegheny Valley Food Service",
    "wof:placetype":"venue"
},
  "geometry": {"coordinates":[-80.06586900000001,40.435676],"type":"Point"}
}