{
  "type": "Feature",
  "properties": {
    "iso:country":"US",
    "sg:address":"958 S Krocks Rd",
    "sg:city":"Allentown",
    "sg:classifiers":[
        {
            "category":"Shopping",
            "subcategory":"Pharmacy",
            "type":"Retail Goods"
        }
    ],
    "sg:phone":"+1   ",
    "sg:postcode":"18106",
    "sg:province":"PA",
    "wof:name":"CVS",
    "wof:placetype":"venue"
},
  "geometry": {"coordinates":[-75.56724699999999,40.559054],"type":"Point"}
}