{
  "type": "Feature",
  "properties": {
    "addr:full":"1471 Jefferson Heights Rd Pittsburgh PA 15235",
    "addr:housenumber":"1471",
    "addr:postcode":"15235",
    "addr:street":"Jefferson Heights Rd",
    "iso:country":"US",
    "sg:address":"1471 Jefferson Heights Rd",
    "sg:city":"Pittsburgh",
    "sg:classifiers":[
        {
            "category":"Professional",
            "subcategory":"Engineering",
            "type":"Services"
        }
    ],
    "sg:phone":"+1 412 829 1250",
    "sg:postcode":"15235",
    "sg:province":"PA",
    "wof:name":"Farris Structural",
    "wof:placetype":"venue"
},
  "geometry": {"coordinates":[-79.816664,40.439012],"type":"Point"}
}