{
  "type": "Feature",
  "properties": {
    "iso:country":"US",
    "sg:address":"25 S 6th St",
    "sg:city":"Indiana",
    "sg:classifiers":[
        {
            "category":"Building & Trades",
            "subcategory":"Plumbing",
            "type":"Services"
        }
    ],
    "sg:phone":"+1   ",
    "sg:postcode":"15701",
    "sg:province":"PA",
    "sg:tags":[
        "contractor"
    ],
    "wof:name":"Schulthesis Brothers",
    "wof:placetype":"venue"
},
  "geometry": {"coordinates":[-79.150719,40.622368],"type":"Point"}
}