{
  "type": "Feature",
  "properties": {
    "addr:full":"1636 York Rd Carlisle PA 17013",
    "addr:housenumber":"1636",
    "addr:postcode":"17013",
    "addr:street":"York Rd",
    "iso:country":"US",
    "sg:address":"1636 York Rd",
    "sg:city":"Carlisle",
    "sg:classifiers":[
        {
            "category":"Retail",
            "subcategory":"Auto Repair",
            "type":"Services"
        }
    ],
    "sg:phone":"+1 717 258 3400",
    "sg:postcode":"17013",
    "sg:province":"PA",
    "wof:name":"Richwine's Garage",
    "wof:placetype":"venue"
},
  "geometry": {"coordinates":[-77.117599,40.171501],"type":"Point"}
}