{
  "type": "Feature",
  "properties": {
    "addr:full":"5750 Centre Ave Pittsburgh PA 15232",
    "addr:housenumber":"5750",
    "addr:postcode":"15232",
    "addr:street":"Centre Ave",
    "iso:country":"US",
    "sg:address":"5750 Centre Ave",
    "sg:city":"Pittsburgh",
    "sg:classifiers":[
        {
            "category":"Health Services",
            "subcategory":"Doctor",
            "type":"Services"
        }
    ],
    "sg:phone":"+1   ",
    "sg:postcode":"15232",
    "sg:province":"PA",
    "sg:tags":[
        "medical"
    ],
    "wof:name":"Jeffrey N Kann MD",
    "wof:placetype":"venue"
},
  "geometry": {"coordinates":[-79.930504,40.458191],"type":"Point"}
}