{
  "type": "Feature",
  "properties": {
    "iso:country":"US",
    "sg:address":"590 S Water St",
    "sg:city":"Kittanning",
    "sg:classifiers":[
        {
            "category":"Sports & Exercise",
            "subcategory":"Bowling",
            "type":"Entertainment"
        }
    ],
    "sg:phone":"+1 724 543 2715",
    "sg:postcode":"16201",
    "sg:province":"PA",
    "wof:name":"King Lanes",
    "wof:placetype":"venue"
},
  "geometry": {"coordinates":[-79.514917,40.80751],"type":"Point"}
}