{
  "type": "Feature",
  "properties": {
    "addr:full":"3901 Market St Philadelphia PA 19104",
    "addr:housenumber":"3901",
    "addr:postcode":"19104",
    "addr:street":"Market St",
    "iso:country":"US",
    "sg:address":"3901 Market St",
    "sg:city":"Philadelphia",
    "sg:classifiers":[
        {
            "category":"Banks & Credit Unions",
            "subcategory":"Bank",
            "type":"Services"
        }
    ],
    "sg:phone":"+1 215 222 2333",
    "sg:postcode":"19104",
    "sg:province":"PA",
    "sg:tags":[
        "saving",
        "commercial"
    ],
    "wof:name":"Citizens Bank",
    "wof:placetype":"venue"
},
  "geometry": {"coordinates":[-75.199608,39.956871],"type":"Point"}
}