{
  "type": "Feature",
  "properties": {
    "iso:country":"US",
    "sg:address":"4001 Galo Dr",
    "sg:city":"Aliquippa",
    "sg:classifiers":[
        {
            "category":"Communications",
            "type":"Services"
        }
    ],
    "sg:phone":"+1 724 378 3577",
    "sg:postcode":"15001",
    "sg:province":"PA",
    "wof:name":"A Communications Advisor Inc",
    "wof:placetype":"venue"
},
  "geometry": {"coordinates":[-80.358852,40.611157],"type":"Point"}
}