{
  "type": "Feature",
  "properties": {
    "iso:country":"US",
    "sg:address":"400 Broad St",
    "sg:city":"Montoursville",
    "sg:classifiers":[
        {
            "category":"Wholesale",
            "subcategory":"Hardware",
            "type":"Manufacturing & Wholesale Goods"
        }
    ],
    "sg:phone":"+1 570 368 2404",
    "sg:postcode":"17754",
    "sg:province":"PA",
    "sg:tags":[
        "plumbing",
        "fixture",
        "supply"
    ],
    "wof:name":"Bi-Lo Supply",
    "wof:placetype":"venue"
},
  "geometry": {"coordinates":[-76.923755,41.249227],"type":"Point"}
}