{
  "type": "Feature",
  "properties": {
    "iso:country":"US",
    "sg:address":"502 Church St",
    "sg:city":"Athens",
    "sg:classifiers":[
        {
            "category":"Real Estate",
            "subcategory":"Real Estate Agent",
            "type":"Services"
        }
    ],
    "sg:phone":"+1 570 888 5772",
    "sg:postcode":"18810",
    "sg:province":"PA",
    "sg:tags":[
        "authorities",
        "housing"
    ],
    "wof:name":"Bradford County Housing Auth",
    "wof:placetype":"venue"
},
  "geometry": {"coordinates":[-76.52061,41.970272],"type":"Point"}
}