{
  "type": "Feature",
  "properties": {
    "addr:full":"9974 Molly Pitcher Hwy Shippensburg PA 17257",
    "addr:housenumber":"9974",
    "addr:postcode":"17257",
    "addr:street":"Molly Pitcher Hwy",
    "iso:country":"US",
    "sg:address":"9974 Molly Pitcher Hwy",
    "sg:city":"Shippensburg",
    "sg:classifiers":[
        {
            "category":"Retail",
            "subcategory":"Auto Repair",
            "type":"Services"
        }
    ],
    "sg:phone":"+1 717 532 5228",
    "sg:postcode":"17257",
    "sg:province":"PA",
    "sg:tags":[
        "repairing",
        "automobile"
    ],
    "wof:name":"Thomas Automotive",
    "wof:placetype":"venue"
},
  "geometry": {"coordinates":[-77.547827,40.034175],"type":"Point"}
}