{
  "type": "Feature",
  "properties": {
    "addr:full":"1002 McKee Rd Oakdale PA 15071",
    "addr:housenumber":"1002",
    "addr:postcode":"15071",
    "addr:street":"Mckee Rd",
    "iso:country":"US",
    "sg:address":"1002 McKee Rd",
    "sg:city":"Oakdale",
    "sg:classifiers":[
        {
            "category":"Professional",
            "subcategory":"Computer Services",
            "type":"Services"
        }
    ],
    "sg:phone":"+1   ",
    "sg:postcode":"15071",
    "sg:province":"PA",
    "sg:tags":[
        "field",
        "instrumentation"
    ],
    "wof:name":"Siemens Energy & Automation",
    "wof:placetype":"venue"
},
  "geometry": {"coordinates":[-80.191323,40.432409],"type":"Point"}
}