{
  "type": "Feature",
  "properties": {
    "iso:country":"US",
    "sg:address":"42 Railroad St",
    "sg:city":"Cresson",
    "sg:classifiers":[
        {
            "category":"Building & Trades",
            "subcategory":"Landscaping Services",
            "type":"Services"
        }
    ],
    "sg:phone":"+1   ",
    "sg:postcode":"16630",
    "sg:province":"PA",
    "wof:name":"Mocks Tree Service",
    "wof:placetype":"venue"
},
  "geometry": {"coordinates":[-78.58238900000001,40.474887],"type":"Point"}
}