{
  "type": "Feature",
  "properties": {
    "addr:full":"225 Hartings Park Rd Denver PA 17517",
    "addr:housenumber":"225",
    "addr:postcode":"17517",
    "addr:street":"Hartings Park Rd",
    "iso:country":"US",
    "sg:address":"225 Hartings Park Rd",
    "sg:city":"Denver",
    "sg:classifiers":[
        {
            "category":"Shopping",
            "subcategory":"Used Merchandise",
            "type":"Retail Goods"
        }
    ],
    "sg:phone":"+1   ",
    "sg:postcode":"17517",
    "sg:province":"PA",
    "wof:name":"Sherrys Year Round Yard Sale",
    "wof:placetype":"venue"
},
  "geometry": {"coordinates":[-76.171914,40.250487],"type":"Point"}
}