{
  "type": "Feature",
  "properties": {
    "addr:full":"3246 Oakland Rd Bethlehem PA 18020",
    "addr:housenumber":"3246",
    "addr:postcode":"18020",
    "addr:street":"Oakland Rd",
    "iso:country":"US",
    "sg:address":"3246 Oakland Rd",
    "sg:city":"Bethlehem",
    "sg:classifiers":[
        {
            "category":"Professional",
            "type":"Services"
        }
    ],
    "sg:phone":"+1   ",
    "sg:postcode":"18020",
    "sg:province":"PA",
    "wof:name":"Lunatech Labs Ltd",
    "wof:placetype":"venue"
},
  "geometry": {"coordinates":[-75.33370600000001,40.66786],"type":"Point"}
}