{
  "type": "Feature",
  "properties": {
    "iso:country":"US",
    "sg:address":"1287 Loop Rd",
    "sg:city":"Lancaster",
    "sg:classifiers":[
        {
            "category":"Wholesale",
            "subcategory":"Vending Machines",
            "type":"Manufacturing & Wholesale Goods"
        },
        {
            "category":"Professional",
            "subcategory":"Management & Consulting",
            "type":"Services"
        }
    ],
    "sg:phone":"+1 717 293 1006",
    "sg:postcode":"17601",
    "sg:province":"PA",
    "sg:tags":[
        "snack",
        "honor",
        "system"
    ],
    "wof:name":"Breakaway Snacks Inc",
    "wof:placetype":"venue"
},
  "geometry": {"coordinates":[-76.32834699999999,40.065884],"type":"Point"}
}