{
  "type": "Feature",
  "properties": {
    "addr:full":"1528 Walnut St Philadelphia PA 19102",
    "addr:housenumber":"1528",
    "addr:postcode":"19102",
    "addr:street":"Walnut St",
    "iso:country":"US",
    "sg:address":"1528 Walnut St",
    "sg:city":"Philadelphia",
    "sg:classifiers":[
        {
            "category":"Professional",
            "subcategory":"Lawyer & Legal Services",
            "type":"Services"
        }
    ],
    "sg:phone":"+1 215 790 9001",
    "sg:postcode":"19102",
    "sg:province":"PA",
    "sg:tags":[
        "attorney"
    ],
    "wof:name":"Zeris Ledva & Meyers",
    "wof:placetype":"venue"
},
  "geometry": {"coordinates":[-75.167427,39.949654],"type":"Point"}
}