{
  "type": "Feature",
  "properties": {
    "iso:country":"US",
    "sg:address":"2761 Oakland Rd",
    "sg:city":"Dover",
    "sg:classifiers":[
        {
            "category":"Real Estate",
            "subcategory":"Real Estate Operator",
            "type":"Services"
        }
    ],
    "sg:phone":"+1   ",
    "sg:postcode":"17315",
    "sg:province":"PA",
    "sg:tags":[
        "property",
        "lessor"
    ],
    "wof:name":"Daughertys",
    "wof:placetype":"venue"
},
  "geometry": {"coordinates":[-76.831092,39.972913],"type":"Point"}
}