{
  "type": "Feature",
  "properties": {
    "iso:country":"US",
    "sg:address":"93 School Ln",
    "sg:city":"Robesonia",
    "sg:classifiers":[
        {
            "category":"Building & Trades",
            "subcategory":"Plumbing",
            "type":"Services"
        }
    ],
    "sg:phone":"+1   ",
    "sg:postcode":"19551",
    "sg:province":"PA",
    "sg:tags":[
        "plumbing",
        "air",
        "heating",
        "conditioning",
        "contractor"
    ],
    "wof:name":"Building Systems Design Inc",
    "wof:placetype":"venue"
},
  "geometry": {"coordinates":[-76.09409599999999,40.389958],"type":"Point"}
}