{
  "type": "Feature",
  "properties": {
    "addr:full":"4415 Carlisle Rd Gardners PA 17324",
    "addr:housenumber":"4415",
    "addr:postcode":"17324",
    "addr:street":"Carlisle Rd",
    "iso:country":"US",
    "sg:address":"4415 Carlisle Rd",
    "sg:city":"Gardners",
    "sg:classifiers":[
        {
            "category":"Building & Trades",
            "subcategory":"Construction",
            "type":"Services"
        }
    ],
    "sg:phone":"+1 717 486 4855",
    "sg:postcode":"17324",
    "sg:province":"PA",
    "sg:tags":[
        "general",
        "contractor"
    ],
    "wof:name":"Cumberland Valley Wood Floor",
    "wof:placetype":"venue"
},
  "geometry": {"coordinates":[-77.19425200000001,40.064618],"type":"Point"}
}