{
  "type": "Feature",
  "properties": {
    "iso:country":"US",
    "sg:address":"1706 5th Ave",
    "sg:city":"Arnold",
    "sg:classifiers":[
        {
            "category":"Education",
            "subcategory":"Vocational School",
            "type":"Public Place"
        }
    ],
    "sg:phone":"+1 724 339 4290",
    "sg:postcode":"15068",
    "sg:province":"PA",
    "sg:tags":[
        "training",
        "computer"
    ],
    "wof:name":"Modern Management Solutions",
    "wof:placetype":"venue"
},
  "geometry": {"coordinates":[-79.767949,40.578785],"type":"Point"}
}