{
  "type": "Feature",
  "properties": {
    "addr:full":"740 Greensburg Rd New Kensington PA 15068",
    "addr:housenumber":"740",
    "addr:postcode":"15068",
    "addr:street":"Greensburg Rd",
    "iso:country":"US",
    "sg:address":"740 Greensburg Rd",
    "sg:city":"New Kensington",
    "sg:classifiers":[
        {
            "category":"Building & Trades",
            "subcategory":"Construction",
            "type":"Services"
        }
    ],
    "sg:phone":"+1 724 339 8900",
    "sg:postcode":"15068",
    "sg:province":"PA",
    "sg:tags":[
        "erectors",
        "machinery"
    ],
    "wof:name":"J V Rigging Inc",
    "wof:placetype":"venue"
},
  "geometry": {"coordinates":[-79.743754,40.550066],"type":"Point"}
}