{
  "type": "Feature",
  "properties": {
    "addr:full":"1401 Chester Pike Sharon Hill PA 19079",
    "addr:housenumber":"1401",
    "addr:postcode":"19079",
    "addr:street":"Chester Pike",
    "iso:country":"US",
    "sg:address":"1401 Chester Pike",
    "sg:city":"Sharon Hill",
    "sg:classifiers":[
        {
            "category":"Food & Beverages",
            "subcategory":"Groceries & Convenience Stores",
            "type":"Retail Goods"
        }
    ],
    "sg:phone":"+1 610 583 6688",
    "sg:postcode":"19079",
    "sg:province":"PA",
    "wof:name":"Plaza Cold Cuts",
    "wof:placetype":"venue"
},
  "geometry": {"coordinates":[-75.279427,39.905483],"type":"Point"}
}