{
  "type": "Feature",
  "properties": {
    "addr:full":"230 Snyder Rd Hermitage PA 16148",
    "addr:housenumber":"230",
    "addr:postcode":"16148",
    "addr:street":"Snyder Rd",
    "iso:country":"US",
    "sg:address":"230 Snyder Rd",
    "sg:city":"Hermitage",
    "sg:classifiers":[
        {
            "category":"Professional",
            "subcategory":"Computer Services",
            "type":"Services"
        }
    ],
    "sg:phone":"+1 724 347 4809",
    "sg:postcode":"16148",
    "sg:province":"PA",
    "sg:tags":[
        "repair"
    ],
    "wof:name":"Penn Ohio Printer Repair",
    "wof:placetype":"venue"
},
  "geometry": {"coordinates":[-80.44161699999999,41.234788],"type":"Point"}
}