{
  "type": "Feature",
  "properties": {
    "addr:full":"304 Poplar St Hanover PA 17331",
    "addr:housenumber":"304",
    "addr:postcode":"17331",
    "addr:street":"Poplar St",
    "iso:country":"US",
    "sg:address":"304 Poplar St",
    "sg:city":"Hanover",
    "sg:classifiers":[
        {
            "category":"Bars & Pubs",
            "type":"Food & Drink"
        },
        {
            "category":"Restaurant",
            "type":"Food & Drink"
        }
    ],
    "sg:menulink":"http://www.allmenus.com/pa/hanover/276974-kclingers-tavern/menu/",
    "sg:phone":"+1 717 633 9197",
    "sg:postcode":"17331",
    "sg:province":"PA",
    "sg:tags":[
        "food",
        "american",
        "pub"
    ],
    "wof:name":"Kclinger's Tavern",
    "wof:placetype":"venue"
},
  "geometry": {"coordinates":[-76.99223600000001,39.798575],"type":"Point"}
}