{
  "type": "Feature",
  "properties": {
    "iso:country":"US",
    "sg:address":"180 E Elizabeth Ln",
    "sg:city":"Richboro",
    "sg:classifiers":[
        {
            "category":"Professional",
            "subcategory":"Employment Agencies",
            "type":"Services"
        }
    ],
    "sg:phone":"+1 215 364 8070",
    "sg:postcode":"18954",
    "sg:province":"PA",
    "sg:tags":[
        "firm",
        "consultant",
        "search",
        "executive",
        "placement"
    ],
    "sg:website":"www.churchillsearch.com",
    "wof:name":"Churchill & Affiliates Inc",
    "wof:placetype":"venue"
},
  "geometry": {"coordinates":[-75.016997,40.210555],"type":"Point"}
}