{
  "type": "Feature",
  "properties": {
    "iso:country":"US",
    "sg:address":"2129 New Danville Pike",
    "sg:city":"Lancaster",
    "sg:classifiers":[
        {
            "category":"Retail",
            "subcategory":"Repair Shop",
            "type":"Services"
        }
    ],
    "sg:phone":"+1 717 872 8537",
    "sg:postcode":"17603",
    "sg:province":"PA",
    "sg:tags":[
        "upholsterer"
    ],
    "wof:name":"Shenks Upholstery",
    "wof:placetype":"venue"
},
  "geometry": {"coordinates":[-76.31652699999999,39.983531],"type":"Point"}
}