{
  "type": "Feature",
  "properties": {
    "iso:country":"US",
    "sg:address":"17 Louisa Ave",
    "sg:city":"Greenville",
    "sg:classifiers":[
        {
            "category":"Insurance",
            "subcategory":"Insurance Agent",
            "type":"Services"
        }
    ],
    "sg:phone":"+1 724 588 3800",
    "sg:postcode":"16125",
    "sg:province":"PA",
    "wof:name":"Hamilton Insurance",
    "wof:placetype":"venue"
},
  "geometry": {"coordinates":[-80.38440300000001,41.406576],"type":"Point"}
}