{
  "type": "Feature",
  "properties": {
    "iso:country":"US",
    "sg:address":"2900 Potshop Ln",
    "sg:city":"Norristown",
    "sg:classifiers":[
        {
            "category":"Shopping",
            "subcategory":"Stationery & Office Supplies",
            "type":"Retail Goods"
        },
        {
            "category":"Home & Garden",
            "subcategory":"Furniture",
            "type":"Retail Goods"
        }
    ],
    "sg:phone":"+1 610 631 5400",
    "sg:postcode":"19403",
    "sg:province":"PA",
    "sg:tags":[
        "equipment",
        "store"
    ],
    "wof:name":"Corporate Interiors Inc",
    "wof:placetype":"venue"
},
  "geometry": {"coordinates":[-75.349403,40.169201],"type":"Point"}
}