{
  "type": "Feature",
  "properties": {
    "addr:full":"3009 N 22nd St Philadelphia PA 19132",
    "addr:housenumber":"3009",
    "addr:postcode":"19132",
    "addr:street":"N 22Nd St",
    "iso:country":"US",
    "sg:address":"3009 N 22nd St",
    "sg:city":"Philadelphia",
    "sg:classifiers":[
        {
            "category":"Restaurant",
            "type":"Food & Drink"
        }
    ],
    "sg:phone":"+1 215 225 2160",
    "sg:postcode":"19132",
    "sg:province":"PA",
    "wof:name":"No Songsu",
    "wof:placetype":"venue"
},
  "geometry": {"coordinates":[-75.166702,40.000301],"type":"Point"}
}