{
  "type": "Feature",
  "properties": {
    "addr:full":"535 Lord St Meadville PA 16335",
    "addr:housenumber":"535",
    "addr:postcode":"16335",
    "addr:street":"Lord St",
    "iso:country":"US",
    "sg:address":"535 Lord St",
    "sg:city":"Meadville",
    "sg:classifiers":[
        {
            "category":"Building & Trades",
            "subcategory":"Construction",
            "type":"Services"
        }
    ],
    "sg:phone":"+1 814 724 1949",
    "sg:postcode":"16335",
    "sg:province":"PA",
    "sg:tags":[
        "house",
        "carpentry",
        "contractor"
    ],
    "wof:name":"Williams Custom Carpentry",
    "wof:placetype":"venue"
},
  "geometry": {"coordinates":[-80.153379,41.649459],"type":"Point"}
}