{
  "type": "Feature",
  "properties": {
    "iso:country":"US",
    "sg:address":"196 Fiske Rd",
    "sg:city":"Fallentimber",
    "sg:classifiers":[
        {
            "category":"Shopping",
            "subcategory":"Hobbies, Toys, & Games",
            "type":"Retail Goods"
        },
        {
            "category":"Shopping",
            "subcategory":"Crafts & Fabrics",
            "type":"Retail Goods"
        }
    ],
    "sg:phone":"+1 814 339 7217",
    "sg:postcode":"16639",
    "sg:province":"PA",
    "sg:tags":[
        "shop",
        "hobby",
        "model",
        "supply"
    ],
    "wof:name":"Nancys Crafts",
    "wof:placetype":"venue"
},
  "geometry": {"coordinates":[-78.50999899999999,40.65545],"type":"Point"}
}