{
  "type": "Feature",
  "properties": {
    "iso:country":"US",
    "sg:address":"3700 Horizon Dr",
    "sg:city":"King Of Prussia",
    "sg:classifiers":[
        {
            "category":"Manufacturing",
            "subcategory":"Chemicals & Compounds",
            "type":"Manufacturing & Wholesale Goods"
        },
        {
            "category":"Manufacturing",
            "subcategory":"Tools & Machinery",
            "type":"Manufacturing & Wholesale Goods"
        }
    ],
    "sg:phone":"+1 610 239 0300",
    "sg:postcode":"19406",
    "sg:province":"PA",
    "sg:tags":[
        "physician",
        "product",
        "mfg",
        "preparation",
        "biological",
        "surgeon"
    ],
    "wof:name":"Bachem Bio-Science",
    "wof:placetype":"venue"
},
  "geometry": {"coordinates":[-75.339918,40.08782],"type":"Point"}
}