{
  "type": "Feature",
  "properties": {
    "iso:country":"US",
    "sg:address":"487 Strayer St",
    "sg:city":"Johnstown",
    "sg:classifiers":[
        {
            "category":"Building & Trades",
            "subcategory":"Construction",
            "type":"Services"
        }
    ],
    "sg:phone":"+1   ",
    "sg:postcode":"15906",
    "sg:province":"PA",
    "sg:tags":[
        "contractor",
        "co",
        "hanging"
    ],
    "wof:name":"Mainhart Construction",
    "wof:placetype":"venue"
},
  "geometry": {"coordinates":[-78.949439,40.355338],"type":"Point"}
}