{
  "type": "Feature",
  "properties": {
    "iso:country":"US",
    "sg:address":"3 Mariner Ct",
    "sg:city":"Pittsburgh",
    "sg:classifiers":[
        {
            "category":"Health Services",
            "subcategory":"Doctor",
            "type":"Services"
        }
    ],
    "sg:phone":"+1 412 369 5690",
    "sg:postcode":"15238",
    "sg:province":"PA",
    "sg:tags":[
        "medical"
    ],
    "wof:name":"Aurapin Sukanich MD",
    "wof:placetype":"venue"
},
  "geometry": {"coordinates":[-79.83965499999999,40.537992],"type":"Point"}
}