{
  "type": "Feature",
  "properties": {
    "iso:country":"US",
    "sg:address":"250 W 7th St",
    "sg:city":"Erie",
    "sg:classifiers":[
        {
            "category":"Organizations",
            "subcategory":"Religious Organization",
            "type":"Services"
        }
    ],
    "sg:phone":"+1   ",
    "sg:postcode":"16501",
    "sg:province":"PA",
    "sg:tags":[
        "presbyterian",
        "church"
    ],
    "wof:name":"Covenant Preschool",
    "wof:placetype":"venue"
},
  "geometry": {"coordinates":[-80.089624,42.126689],"type":"Point"}
}