{
  "type": "Feature",
  "properties": {
    "iso:country":"US",
    "sg:address":"58 Woodchip Ln",
    "sg:city":"East Stroudsburg",
    "sg:classifiers":[
        {
            "category":"Professional",
            "subcategory":"Computer Services",
            "type":"Services"
        }
    ],
    "sg:phone":"+1 570 476 6222",
    "sg:postcode":"18301",
    "sg:province":"PA",
    "sg:tags":[
        "website",
        "design"
    ],
    "sg:website":"www.greenforest.com",
    "wof:name":"Green Forest",
    "wof:placetype":"venue"
},
  "geometry": {"coordinates":[-75.235786,41.038546],"type":"Point"}
}