{
  "type": "Feature",
  "properties": {
    "iso:country":"US",
    "sg:address":"902 Grandview Ave",
    "sg:city":"Pittsburgh",
    "sg:classifiers":[
        {
            "category":"Professional",
            "subcategory":"Accounting & Tax Preparation",
            "type":"Services"
        }
    ],
    "sg:phone":"+1 412 481 6003",
    "sg:postcode":"15211",
    "sg:province":"PA",
    "sg:tags":[
        "accountant"
    ],
    "wof:name":"McCrory Kenneth C CPA",
    "wof:placetype":"venue"
},
  "geometry": {"coordinates":[-80.016098,40.436798],"type":"Point"}
}