{
  "type": "Feature",
  "properties": {
    "iso:country":"US",
    "sg:address":"500 Commerce Dr",
    "sg:city":"Coraopolis",
    "sg:classifiers":[
        {
            "category":"Insurance",
            "subcategory":"Insurance Agent",
            "type":"Services"
        }
    ],
    "sg:phone":"+1 412 893 2500",
    "sg:postcode":"15108",
    "sg:province":"PA",
    "sg:website":"www.hicksheimmustio.com",
    "wof:name":"Hicks Heim Mustio",
    "wof:placetype":"venue"
},
  "geometry": {"coordinates":[-80.209721,40.503507],"type":"Point"}
}