{
  "type": "Feature",
  "properties": {
    "addr:full":"2467 Creek View Dr Lancaster PA 17602",
    "addr:housenumber":"2467",
    "addr:postcode":"17602",
    "addr:street":"Creek View Dr",
    "iso:country":"US",
    "sg:address":"2467 Creek View Dr",
    "sg:city":"Lancaster",
    "sg:classifiers":[
        {
            "category":"Building & Trades",
            "subcategory":"Construction",
            "type":"Services"
        }
    ],
    "sg:phone":"+1   ",
    "sg:postcode":"17602",
    "sg:province":"PA",
    "sg:tags":[
        "hanging",
        "contractor"
    ],
    "wof:name":"Strubel Kenneth E",
    "wof:placetype":"venue"
},
  "geometry": {"coordinates":[-76.19778700000001,40.028922],"type":"Point"}
}