{
  "type": "Feature",
  "properties": {
    "addr:full":"422 Main St Towanda PA 18848",
    "addr:housenumber":"422",
    "addr:postcode":"18848",
    "addr:street":"Main St",
    "iso:country":"US",
    "sg:address":"422 Main St",
    "sg:city":"Towanda",
    "sg:classifiers":[
        {
            "category":"Building & Trades",
            "subcategory":"Equipment Rental",
            "type":"Services"
        },
        {
            "category":"Shopping",
            "subcategory":"Musical Instruments",
            "type":"Retail Goods"
        }
    ],
    "sg:phone":"+1 570 265 4616",
    "sg:postcode":"18848",
    "sg:province":"PA",
    "wof:name":"River City Music",
    "wof:placetype":"venue"
},
  "geometry": {"coordinates":[-76.44318,41.766154],"type":"Point"}
}