{
  "type": "Feature",
  "properties": {
    "iso:country":"US",
    "sg:address":"2962 Skippack Pike",
    "sg:city":"Lansdale",
    "sg:classifiers":[
        {
            "category":"Insurance",
            "subcategory":"Insurance Agent",
            "type":"Services"
        }
    ],
    "sg:phone":"+1   ",
    "sg:postcode":"19446",
    "sg:province":"PA",
    "wof:name":"Young Bair Agency",
    "wof:placetype":"venue"
},
  "geometry": {"coordinates":[-75.339859,40.19736],"type":"Point"}
}