{
  "type": "Feature",
  "properties": {
    "iso:country":"US",
    "sg:address":"1701 Art School Rd",
    "sg:city":"Chester Springs",
    "sg:classifiers":[
        {
            "category":"Restaurant",
            "type":"Food & Drink"
        }
    ],
    "sg:phone":"+1   ",
    "sg:postcode":"19425",
    "sg:province":"PA",
    "wof:name":"Bellewood Golf Club",
    "wof:placetype":"venue"
},
  "geometry": {"coordinates":[-75.62665699999999,40.100812],"type":"Point"}
}