{
  "type": "Feature",
  "properties": {
    "addr:full":"10 Kerns Ave Chalfont PA 18914",
    "addr:housenumber":"10",
    "addr:postcode":"18914",
    "addr:street":"Kerns Ave",
    "iso:country":"US",
    "sg:address":"10 Kerns Ave",
    "sg:city":"Chalfont",
    "sg:classifiers":[
        {
            "category":"Building & Trades",
            "subcategory":"Plumbing",
            "type":"Services"
        }
    ],
    "sg:phone":"+1 215 822 0515",
    "sg:postcode":"18914",
    "sg:province":"PA",
    "sg:tags":[
        "system",
        "specialty",
        "heating",
        "contractor",
        "air conditioning"
    ],
    "sg:website":"www.bi-countyfuels.com",
    "wof:name":"Bi-County Fuels Inc",
    "wof:placetype":"venue"
},
  "geometry": {"coordinates":[-75.20700100000001,40.286701],"type":"Point"}
}