{
  "type": "Feature",
  "properties": {
    "iso:country":"US",
    "sg:address":"132 23rd St",
    "sg:city":"Pittsburgh",
    "sg:classifiers":[
        {
            "category":"Wholesale",
            "subcategory":"Machinery & Supplies",
            "type":"Manufacturing & Wholesale Goods"
        }
    ],
    "sg:phone":"+1 412 782 5606",
    "sg:postcode":"15215",
    "sg:province":"PA",
    "sg:tags":[
        "equipment",
        "ride",
        "park",
        "amusement"
    ],
    "wof:name":"Sonny's Sales & Svc",
    "wof:placetype":"venue"
},
  "geometry": {"coordinates":[-79.914057,40.494338],"type":"Point"}
}