{
  "type": "Feature",
  "properties": {
    "iso:country":"US",
    "sg:address":"323 Hunting Creek Rd",
    "sg:city":"Canonsburg",
    "sg:classifiers":[
        {
            "category":"Manufacturing",
            "subcategory":"Retail Goods",
            "type":"Manufacturing & Wholesale Goods"
        }
    ],
    "sg:phone":"+1   ",
    "sg:postcode":"15317",
    "sg:province":"PA",
    "sg:tags":[
        "product",
        "mfg"
    ],
    "wof:name":"Remarkable Manufacturing Co",
    "wof:placetype":"venue"
},
  "geometry": {"coordinates":[-80.14427000000001,40.259715],"type":"Point"}
}