{
  "type": "Feature",
  "properties": {
    "addr:full":"2275 Swallow Hill Rd Ste 500 Pittsburgh PA 15220",
    "addr:housenumber":"2275",
    "addr:postcode":"15220",
    "addr:street":"Swallow Hill Rd Ste 500",
    "iso:country":"US",
    "sg:address":"2275 Swallow Hill Rd Ste 500",
    "sg:city":"Pittsburgh",
    "sg:classifiers":[
        {
            "category":"Health Services",
            "subcategory":"Dentist",
            "type":"Services"
        }
    ],
    "sg:phone":"+1 412 279 9400",
    "sg:postcode":"15220",
    "sg:province":"PA",
    "sg:website":"www.southhillsdentist.com",
    "wof:name":"English J Alan DMD",
    "wof:placetype":"venue"
},
  "geometry": {"coordinates":[-80.073044,40.38836],"type":"Point"}
}