{
  "type": "Feature",
  "properties": {
    "addr:full":"714 Fairview Rd North Washington PA 16050",
    "addr:housenumber":"714",
    "addr:postcode":"16050",
    "addr:street":"Fairview Rd North",
    "iso:country":"US",
    "sg:address":"714 Fairview Rd",
    "sg:city":"North Washington",
    "sg:classifiers":[
        {
            "category":"Organizations",
            "subcategory":"Religious Organization",
            "type":"Services"
        }
    ],
    "sg:phone":"+1 724 894 2976",
    "sg:postcode":"16050",
    "sg:province":"PA",
    "sg:tags":[
        "church"
    ],
    "wof:name":"North Washington United Presby",
    "wof:placetype":"venue"
},
  "geometry": {"coordinates":[-79.80946900000001,41.047888],"type":"Point"}
}