{
  "type": "Feature",
  "properties": {
    "addr:full":"20 N Prince St Shippensburg PA 17257",
    "addr:housenumber":"20",
    "addr:postcode":"17257",
    "addr:street":"N Prince St",
    "iso:country":"US",
    "sg:address":"20 N Prince St",
    "sg:city":"Shippensburg",
    "sg:classifiers":[
        {
            "category":"Organizations",
            "subcategory":"Religious Organization",
            "type":"Services"
        }
    ],
    "sg:phone":"+1 717 532 8404",
    "sg:postcode":"17257",
    "sg:province":"PA",
    "sg:tags":[
        "church"
    ],
    "wof:name":"Prince St UNITED Brethren Chr",
    "wof:placetype":"venue"
},
  "geometry": {"coordinates":[-77.517771,40.053225],"type":"Point"}
}