{
  "type": "Feature",
  "properties": {
    "iso:country":"US",
    "sg:address":"700 S Potomac St",
    "sg:city":"Waynesboro",
    "sg:classifiers":[
        {
            "category":"Health Services",
            "subcategory":"Chiropractor",
            "type":"Services"
        }
    ],
    "sg:phone":"+1 717 762 1773",
    "sg:postcode":"17268",
    "sg:province":"PA",
    "wof:name":"Herman Larry Chiroprctr",
    "wof:placetype":"venue"
},
  "geometry": {"coordinates":[-77.589996,39.745399],"type":"Point"}
}