{
  "type": "Feature",
  "properties": {
    "iso:country":"US",
    "sg:address":"412 E Basin St",
    "sg:city":"Norristown",
    "sg:classifiers":[
        {
            "category":"Social Services",
            "subcategory":"Child Care",
            "type":"Services"
        }
    ],
    "sg:phone":"+1   ",
    "sg:postcode":"19401",
    "sg:province":"PA",
    "sg:tags":[
        "day"
    ],
    "wof:name":"Learn Through Play Childcare",
    "wof:placetype":"venue"
},
  "geometry": {"coordinates":[-75.332519,40.118898],"type":"Point"}
}