{
  "type": "Feature",
  "properties": {
    "iso:country":"US",
    "sg:address":"10 Allegheny Center",
    "sg:city":"Pittsburgh",
    "sg:classifiers":[
        {
            "category":"Real Estate",
            "subcategory":"Real Estate Operator",
            "type":"Services"
        }
    ],
    "sg:phone":"+1 412 231 3400",
    "sg:postcode":"15212",
    "sg:province":"PA",
    "sg:tags":[
        "building",
        "automobile",
        "op",
        "apt",
        "parking"
    ],
    "sg:website":"www.alleghenycenter.com",
    "wof:name":"Allegheny Center",
    "wof:placetype":"venue"
},
  "geometry": {"coordinates":[-80.006833,40.451398],"type":"Point"}
}