{
  "type": "Feature",
  "properties": {
    "iso:country":"US",
    "sg:address":"2301 Wharton St",
    "sg:city":"Philadelphia",
    "sg:classifiers":[
        {
            "category":"Social Services",
            "subcategory":"Child Care",
            "type":"Services"
        },
        {
            "category":"Organizations",
            "subcategory":"Religious Organization",
            "type":"Services"
        }
    ],
    "sg:phone":"+1 215 336 2262",
    "sg:postcode":"19146",
    "sg:province":"PA",
    "sg:tags":[
        "day",
        "church"
    ],
    "wof:name":"New Gethsemane Baptist Church",
    "wof:placetype":"venue"
},
  "geometry": {"coordinates":[-75.182856,39.936115],"type":"Point"}
}