{
  "type": "Feature",
  "properties": {
    "iso:country":"US",
    "sg:address":"217 Von Steuben Dr",
    "sg:city":"Collegeville",
    "sg:classifiers":[
        {
            "category":"Manufacturing",
            "subcategory":"Wood Products",
            "type":"Manufacturing & Wholesale Goods"
        }
    ],
    "sg:phone":"+1 610 650 8400",
    "sg:postcode":"19426",
    "sg:province":"PA",
    "sg:tags":[
        "pallet",
        "skid",
        "mfg"
    ],
    "wof:name":"Quality Penn Products, Inc.",
    "wof:placetype":"venue"
},
  "geometry": {"coordinates":[-75.451111,40.148708],"type":"Point"}
}