{
  "type": "Feature",
  "properties": {
    "iso:country":"US",
    "sg:address":"3001 Sussex Ave",
    "sg:city":"Pittsburgh",
    "sg:classifiers":[
        {
            "category":"Social Services",
            "subcategory":"Child Care",
            "type":"Services"
        }
    ],
    "sg:phone":"+1 412 343 8866",
    "sg:postcode":"15226",
    "sg:province":"PA",
    "sg:tags":[
        "elementary",
        "kindergarten",
        "school",
        "academic"
    ],
    "wof:name":"Munchkin University Child Care Center",
    "wof:placetype":"venue"
},
  "geometry": {"coordinates":[-80.0158,40.384399],"type":"Point"}
}