{
  "type": "Feature",
  "properties": {
    "iso:country":"US",
    "sg:address":"1301 Tyler Way",
    "sg:city":"Lansdale",
    "sg:classifiers":[
        {
            "category":"Professional",
            "subcategory":"Management & Consulting",
            "type":"Services"
        }
    ],
    "sg:phone":"+1   ",
    "sg:postcode":"19446",
    "sg:province":"PA",
    "wof:name":"Page and Mooney Intnl",
    "wof:placetype":"venue"
},
  "geometry": {"coordinates":[-75.328429,40.242284],"type":"Point"}
}