{
  "type": "Feature",
  "properties": {
    "iso:country":"US",
    "sg:address":"675 Williams Grove Rd Ste 4",
    "sg:city":"Mechanicsburg",
    "sg:classifiers":[
        {
            "category":"Shopping",
            "subcategory":"Crafts & Fabrics",
            "type":"Retail Goods"
        }
    ],
    "sg:phone":"+1 717 691 1466",
    "sg:postcode":"17055",
    "sg:province":"PA",
    "sg:tags":[
        "art",
        "supply"
    ],
    "wof:name":"Williams Grove Hobbies",
    "wof:placetype":"venue"
},
  "geometry": {"coordinates":[-77.017212,40.198085],"type":"Point"}
}