{
  "type": "Feature",
  "properties": {
    "iso:country":"US",
    "sg:address":"770 Rill Dr",
    "sg:city":"Lebanon",
    "sg:classifiers":[
        {
            "category":"Retail",
            "subcategory":"Veterinary Services",
            "type":"Services"
        }
    ],
    "sg:phone":"+1 717 867 4481",
    "sg:postcode":"17042",
    "sg:province":"PA",
    "sg:tags":[
        "specialty"
    ],
    "wof:name":"Annville Veterinary Hospital",
    "wof:placetype":"venue"
},
  "geometry": {"coordinates":[-76.489853,40.295363],"type":"Point"}
}