{
  "type": "Feature",
  "properties": {
    "addr:full":"225 W Mahoning St Punxsutawney PA 15767",
    "addr:housenumber":"225",
    "addr:postcode":"15767",
    "addr:street":"W Mahoning St",
    "iso:country":"US",
    "sg:address":"225 W Mahoning St",
    "sg:city":"Punxsutawney",
    "sg:classifiers":[
        {
            "category":"Organizations",
            "subcategory":"Community Association",
            "type":"Services"
        }
    ],
    "sg:phone":"+1   ",
    "sg:postcode":"15767",
    "sg:province":"PA",
    "sg:tags":[
        "membership",
        "cl"
    ],
    "wof:name":"Masonic Temple",
    "wof:placetype":"venue"
},
  "geometry": {"coordinates":[-78.97297399999999,40.943149],"type":"Point"}
}