{
  "type": "Feature",
  "properties": {
    "addr:full":"5323 Lincoln Hwy Gap PA 17527",
    "addr:housenumber":"5323",
    "addr:postcode":"17527",
    "addr:street":"Lincoln Hwy",
    "iso:country":"US",
    "sg:address":"5323 Lincoln Hwy",
    "sg:city":"Gap",
    "sg:classifiers":[
        {
            "category":"Restaurant",
            "type":"Food & Drink"
        }
    ],
    "sg:menulink":"http://www.allmenus.com/pa/salisbury/133561-subway/menu/",
    "sg:phone":"+1 717 442 4903",
    "sg:postcode":"17527",
    "sg:province":"PA",
    "sg:tags":[
        "american",
        "sandwich"
    ],
    "wof:name":"Subway",
    "wof:placetype":"venue"
},
  "geometry": {"coordinates":[-76.021224,39.992186],"type":"Point"}
}