{
  "type": "Feature",
  "properties": {
    "addr:full":"111 S Garner St State College PA 16801",
    "addr:housenumber":"111",
    "addr:postcode":"16801",
    "addr:street":"S Garner St",
    "iso:country":"US",
    "sg:address":"111 S Garner St",
    "sg:city":"State College",
    "sg:classifiers":[
        {
            "category":"Shopping",
            "subcategory":"Gifts & Souvenirs",
            "type":"Retail Goods"
        }
    ],
    "sg:phone":"+1 814 234 7071",
    "sg:postcode":"16801",
    "sg:province":"PA",
    "sg:tags":[
        "shop"
    ],
    "sg:website":"www.pennstateroom.com",
    "wof:name":"Mc Lanahan Penn State Room",
    "wof:placetype":"venue"
},
  "geometry": {"coordinates":[-77.85578099999999,40.796841],"type":"Point"}
}