{
  "type": "Feature",
  "properties": {
    "addr:full":"404 Old Hershberger Rd Hollsopple PA 15935",
    "addr:housenumber":"404",
    "addr:postcode":"15935",
    "addr:street":"Old Hershberger Rd",
    "iso:country":"US",
    "sg:address":"404 Old Hershberger Rd",
    "sg:city":"Hollsopple",
    "sg:classifiers":[
        {
            "category":"Building & Trades",
            "subcategory":"Electrical",
            "type":"Services"
        }
    ],
    "sg:phone":"+1 814 479 4346",
    "sg:postcode":"15935",
    "sg:province":"PA",
    "sg:tags":[
        "electrical",
        "electric",
        "contractor"
    ],
    "wof:name":"Shroyer Electric Inc",
    "wof:placetype":"venue"
},
  "geometry": {"coordinates":[-78.964645,40.207117],"type":"Point"}
}