{
  "type": "Feature",
  "properties": {
    "iso:country":"US",
    "sg:address":"2215 Biglerville Rd",
    "sg:city":"Gettysburg",
    "sg:classifiers":[
        {
            "category":"Building & Trades",
            "subcategory":"Plumbing",
            "type":"Services"
        }
    ],
    "sg:phone":"+1 717 752 0239",
    "sg:postcode":"17325",
    "sg:province":"PA",
    "sg:tags":[
        "plumbing",
        "contractor"
    ],
    "wof:name":"Battlefield Plumbing",
    "wof:placetype":"venue"
},
  "geometry": {"coordinates":[-77.245738,39.890495],"type":"Point"}
}