{
  "type": "Feature",
  "properties": {
    "addr:full":"225 Grandview Ave Camp Hill PA 17011",
    "addr:housenumber":"225",
    "addr:postcode":"17011",
    "addr:street":"Grandview Ave",
    "iso:country":"US",
    "sg:address":"225 Grandview Ave",
    "sg:city":"Camp Hill",
    "sg:classifiers":[
        {
            "category":"Professional",
            "subcategory":"Computer Services",
            "type":"Services"
        }
    ],
    "sg:phone":"+1 717 763 6000",
    "sg:postcode":"17011",
    "sg:province":"PA",
    "sg:website":"www.eds.com",
    "wof:name":"EDS Corp",
    "wof:placetype":"venue"
},
  "geometry": {"coordinates":[-76.922265,40.257968],"type":"Point"}
}