{
  "type": "Feature",
  "properties": {
    "addr:full":"708 Mercer-New Wilmington Rd Mercer PA 16137",
    "addr:housenumber":"708",
    "addr:postcode":"16137",
    "addr:street":"Mercer-New Wilmington Rd",
    "iso:country":"US",
    "sg:address":"708 Mercer-New Wilmington Rd",
    "sg:city":"Mercer",
    "sg:classifiers":[
        {
            "category":"Professional",
            "subcategory":"Business Services",
            "type":"Services"
        }
    ],
    "sg:phone":"+1 724 662 2663",
    "sg:postcode":"16137",
    "sg:province":"PA",
    "sg:tags":[
        "notary"
    ],
    "wof:name":"Leydic Notary Svc",
    "wof:placetype":"venue"
},
  "geometry": {"coordinates":[-80.254729,41.201743],"type":"Point"}
}