{
  "type": "Feature",
  "properties": {
    "iso:country":"US",
    "sg:address":"2546 Library Rd",
    "sg:city":"Pittsburgh",
    "sg:classifiers":[
        {
            "category":"Professional",
            "subcategory":"Employment Agencies",
            "type":"Services"
        }
    ],
    "sg:phone":"+1   ",
    "sg:postcode":"15234",
    "sg:province":"PA",
    "wof:name":"Wild Thingz Inc",
    "wof:placetype":"venue"
},
  "geometry": {"coordinates":[-79.998097,40.381578],"type":"Point"}
}