{
  "type": "Feature",
  "properties": {
    "iso:country":"US",
    "sg:address":"503 N 21st St",
    "sg:city":"Camp Hill",
    "sg:classifiers":[
        {
            "category":"Health Services",
            "subcategory":"Health Practitioner",
            "type":"Services"
        }
    ],
    "sg:phone":"+1 717 972 4545",
    "sg:postcode":"17011",
    "sg:province":"PA",
    "sg:tags":[
        "therapist",
        "physical"
    ],
    "wof:name":"Holy Spirit Hospital Rehab Svc",
    "wof:placetype":"venue"
},
  "geometry": {"coordinates":[-76.925817,40.2549],"type":"Point"}
}