{
  "type": "Feature",
  "properties": {
    "iso:country":"US",
    "sg:address":"959 Wayne Ave",
    "sg:city":"Chambersburg",
    "sg:classifiers":[
        {
            "category":"Retail",
            "subcategory":"Laundry & Dry Cleaning",
            "type":"Services"
        }
    ],
    "sg:phone":"+1 717 261 0126",
    "sg:postcode":"17201",
    "sg:province":"PA",
    "sg:tags":[
        "power"
    ],
    "wof:name":"Laundry Quarters",
    "wof:placetype":"venue"
},
  "geometry": {"coordinates":[-77.652963,39.913718],"type":"Point"}
}