{
  "type": "Feature",
  "properties": {
    "addr:full":"9 Old Lincoln Hwy Malvern PA 19355",
    "addr:housenumber":"9",
    "addr:postcode":"19355",
    "addr:street":"Old Lincoln Hwy",
    "iso:country":"US",
    "sg:address":"9 Old Lincoln Hwy",
    "sg:city":"Malvern",
    "sg:classifiers":[
        {
            "category":"Organizations",
            "subcategory":"Membership Organization",
            "type":"Services"
        },
        {
            "category":"Organizations",
            "subcategory":"Professional Association",
            "type":"Services"
        }
    ],
    "sg:phone":"+1 610 408 0612",
    "sg:postcode":"19355",
    "sg:province":"PA",
    "wof:name":"Whiteland Woods Association",
    "wof:placetype":"venue"
},
  "geometry": {"coordinates":[-75.518891,40.043712],"type":"Point"}
}