{
  "type": "Feature",
  "properties": {
    "iso:country":"US",
    "sg:address":"6810 Yocum St",
    "sg:city":"Philadelphia",
    "sg:classifiers":[
        {
            "category":"Organizations",
            "subcategory":"Religious Organization",
            "type":"Services"
        }
    ],
    "sg:phone":"+1 215 724 4347",
    "sg:postcode":"19142",
    "sg:province":"PA",
    "wof:name":"Discipleship Ministries of Jesus Christ Inc",
    "wof:placetype":"venue"
},
  "geometry": {"coordinates":[-75.239034,39.923135],"type":"Point"}
}