{
  "type": "Feature",
  "properties": {
    "addr:full":"300 W Trenton Ave Morrisville PA 19067",
    "addr:housenumber":"300",
    "addr:postcode":"19067",
    "addr:street":"W Trenton Ave",
    "iso:country":"US",
    "sg:address":"300 W Trenton Ave",
    "sg:city":"Morrisville",
    "sg:classifiers":[
        {
            "category":"Real Estate",
            "subcategory":"Real Estate Services",
            "type":"Services"
        }
    ],
    "sg:phone":"+1 215 295 7800",
    "sg:postcode":"19067",
    "sg:province":"PA",
    "sg:tags":[
        "company",
        "title"
    ],
    "wof:name":"Stewart Title Guaranty Co",
    "wof:placetype":"venue"
},
  "geometry": {"coordinates":[-74.79260499999999,40.212025],"type":"Point"}
}