{
  "type": "Feature",
  "properties": {
    "addr:full":"300 W Broadway Jim Thorpe PA 18229",
    "addr:housenumber":"300",
    "addr:postcode":"18229",
    "addr:street":"W Broadway",
    "iso:country":"US",
    "sg:address":"300 W Broadway",
    "sg:city":"Jim Thorpe",
    "sg:classifiers":[
        {
            "category":"Professional",
            "type":"Services"
        }
    ],
    "sg:phone":"+1 570 325 2710",
    "sg:postcode":"18229",
    "sg:province":"PA",
    "sg:tags":[
        "establishment"
    ],
    "wof:name":"Hoban Corp",
    "wof:placetype":"venue"
},
  "geometry": {"coordinates":[-75.752726,40.861549],"type":"Point"}
}