{
  "type": "Feature",
  "properties": {
    "iso:country":"US",
    "sg:address":"223 W Penn St",
    "sg:city":"Bedford",
    "sg:classifiers":[
        {
            "category":"Banks & Credit Unions",
            "subcategory":"Bank",
            "type":"Services"
        }
    ],
    "sg:phone":"+1 814 624 0233",
    "sg:postcode":"15522",
    "sg:province":"PA",
    "sg:tags":[
        "loan",
        "real estate"
    ],
    "wof:name":"Atlas Funding Co Inc",
    "wof:placetype":"venue"
},
  "geometry": {"coordinates":[-78.506382,40.017213],"type":"Point"}
}