{
  "type": "Feature",
  "properties": {
    "addr:full":"2016 S 15th St Philadelphia PA 19145",
    "addr:housenumber":"2016",
    "addr:postcode":"19145",
    "addr:street":"S 15Th St",
    "iso:country":"US",
    "sg:address":"2016 S 15th St",
    "sg:city":"Philadelphia",
    "sg:classifiers":[
        {
            "category":"Communications",
            "subcategory":"Newspaper",
            "type":"Services"
        }
    ],
    "sg:phone":"+1 215 465 1143",
    "sg:postcode":"19145",
    "sg:province":"PA",
    "sg:tags":[
        "magazine"
    ],
    "wof:name":"Ramaji Newstand",
    "wof:placetype":"venue"
},
  "geometry": {"coordinates":[-75.17138199999999,39.92528],"type":"Point"}
}