{
  "type": "Feature",
  "properties": {
    "addr:full":"128 Wallace Ave Downingtown PA 19335",
    "addr:housenumber":"128",
    "addr:postcode":"19335",
    "addr:street":"Wallace Ave",
    "iso:country":"US",
    "sg:address":"128 Wallace Ave",
    "sg:city":"Downingtown",
    "sg:classifiers":[
        {
            "category":"Restaurant",
            "type":"Food & Drink"
        }
    ],
    "sg:phone":"+1   ",
    "sg:postcode":"19335",
    "sg:province":"PA",
    "sg:tags":[
        "eating"
    ],
    "wof:name":"Dominos Pizza",
    "wof:placetype":"venue"
},
  "geometry": {"coordinates":[-75.704167,40.012596],"type":"Point"}
}