{
  "type": "Feature",
  "properties": {
    "iso:country":"US",
    "sg:address":"1101 Pittsburgh St",
    "sg:city":"Springdale",
    "sg:classifiers":[
        {
            "category":"Bars & Pubs",
            "type":"Food & Drink"
        }
    ],
    "sg:phone":"+1   ",
    "sg:postcode":"15144",
    "sg:province":"PA",
    "sg:tags":[
        "drinking"
    ],
    "wof:name":"Valentines Bar & Grill",
    "wof:placetype":"venue"
},
  "geometry": {"coordinates":[-79.772097,40.543265],"type":"Point"}
}