{
  "type": "Feature",
  "properties": {
    "addr:full":"462 Chestnut St Columbia PA 17512",
    "addr:housenumber":"462",
    "addr:postcode":"17512",
    "addr:street":"Chestnut St",
    "iso:country":"US",
    "sg:address":"462 Chestnut St",
    "sg:city":"Columbia",
    "sg:classifiers":[
        {
            "category":"Manufacturing",
            "subcategory":"Printing",
            "type":"Manufacturing & Wholesale Goods"
        }
    ],
    "sg:phone":"+1   ",
    "sg:postcode":"17512",
    "sg:province":"PA",
    "sg:tags":[
        "publishing"
    ],
    "wof:name":"Bonasa Press",
    "wof:placetype":"venue"
},
  "geometry": {"coordinates":[-76.502394,40.035404],"type":"Point"}
}