{
  "type": "Feature",
  "properties": {
    "iso:country":"US",
    "sg:address":"402 Chestnut St",
    "sg:city":"Kulpmont",
    "sg:classifiers":[
        {
            "category":"Shopping",
            "type":"Retail Goods"
        }
    ],
    "sg:phone":"+1 570 373 3741",
    "sg:postcode":"17834",
    "sg:province":"PA",
    "sg:tags":[
        "merchandise"
    ],
    "wof:name":"Molesevich Monuments",
    "wof:placetype":"venue"
},
  "geometry": {"coordinates":[-76.46270199999999,40.794778],"type":"Point"}
}