{
  "type": "Feature",
  "properties": {
    "addr:full":"1552 W 45th St Erie PA 16509",
    "addr:housenumber":"1552",
    "addr:postcode":"16509",
    "addr:street":"W 45Th St",
    "iso:country":"US",
    "sg:address":"1552 W 45th St",
    "sg:city":"Erie",
    "sg:classifiers":[
        {
            "category":"Building & Trades",
            "subcategory":"Cleaning & Sanitation",
            "type":"Services"
        }
    ],
    "sg:phone":"+1 814 864 8100",
    "sg:postcode":"16509",
    "sg:province":"PA",
    "sg:tags":[
        "polishing",
        "waxing",
        "floor"
    ],
    "wof:name":"Just Floors",
    "wof:placetype":"venue"
},
  "geometry": {"coordinates":[-80.095303,42.08468],"type":"Point"}
}