{
  "type": "Feature",
  "properties": {
    "iso:country":"US",
    "sg:address":"81 Misty Mdw",
    "sg:city":"Perkasie",
    "sg:classifiers":[
        {
            "category":"Professional",
            "type":"Services"
        }
    ],
    "sg:phone":"+1   ",
    "sg:postcode":"18944",
    "sg:province":"PA",
    "wof:name":"Browns Sports",
    "wof:placetype":"venue"
},
  "geometry": {"coordinates":[-75.276972,40.358689],"type":"Point"}
}