{
  "type": "Feature",
  "properties": {
    "iso:country":"US",
    "sg:address":"24 S 10th St",
    "sg:city":"Lebanon",
    "sg:classifiers":[
        {
            "category":"Arts & Performance",
            "subcategory":"Theater",
            "type":"Entertainment"
        }
    ],
    "sg:phone":"+1 717 273 7070",
    "sg:postcode":"17042",
    "sg:province":"PA",
    "sg:tags":[
        "live",
        "music"
    ],
    "wof:name":"Elect Services",
    "wof:placetype":"venue"
},
  "geometry": {"coordinates":[-76.42788299999999,40.33837],"type":"Point"}
}