{
  "type": "Feature",
  "properties": {
    "iso:country":"US",
    "sg:address":"419 Bedminster Rd",
    "sg:city":"Perkasie",
    "sg:classifiers":[
        {
            "category":"Personal",
            "subcategory":"Beauty Salon",
            "type":"Services"
        }
    ],
    "sg:phone":"+1 215 257 0758",
    "sg:postcode":"18944",
    "sg:province":"PA",
    "wof:name":"Doris Bartls Beauty Salon",
    "wof:placetype":"venue"
},
  "geometry": {"coordinates":[-75.249308,40.380739],"type":"Point"}
}