{
  "type": "Feature",
  "properties": {
    "iso:country":"US",
    "sg:address":"5416 6th Ave",
    "sg:city":"Altoona",
    "sg:classifiers":[
        {
            "category":"Wholesale",
            "subcategory":"Machinery & Supplies",
            "type":"Manufacturing & Wholesale Goods"
        }
    ],
    "sg:phone":"+1   ",
    "sg:postcode":"16602",
    "sg:province":"PA",
    "sg:tags":[
        "construction",
        "fastener",
        "industrial",
        "suppl",
        "threaded"
    ],
    "wof:name":"Fastenal Company",
    "wof:placetype":"venue"
},
  "geometry": {"coordinates":[-78.422939,40.475109],"type":"Point"}
}