{
  "type": "Feature",
  "properties": {
    "iso:country":"US",
    "sg:address":"456 W 6th St",
    "sg:city":"Erie",
    "sg:classifiers":[
        {
            "category":"Professional",
            "subcategory":"Lawyer & Legal Services",
            "type":"Services"
        }
    ],
    "sg:phone":"+1 814 456 5318",
    "sg:postcode":"16507",
    "sg:province":"PA",
    "sg:tags":[
        "attorney"
    ],
    "sg:website":"www.tmgattys.com",
    "wof:name":"Mc Donald Group",
    "wof:placetype":"venue"
},
  "geometry": {"coordinates":[-80.095142,42.126],"type":"Point"}
}