{
  "type": "Feature",
  "properties": {
    "addr:full":"428 6th Ave Folsom PA 19033",
    "addr:housenumber":"428",
    "addr:postcode":"19033",
    "addr:street":"6Th Ave",
    "iso:country":"US",
    "sg:address":"428 6th Ave",
    "sg:city":"Folsom",
    "sg:classifiers":[
        {
            "category":"Organizations",
            "subcategory":"Religious Organization",
            "type":"Services"
        }
    ],
    "sg:phone":"+1 610 461 8398",
    "sg:postcode":"19033",
    "sg:province":"PA",
    "sg:tags":[
        "clergy"
    ],
    "wof:name":"Amos Glass",
    "wof:placetype":"venue"
},
  "geometry": {"coordinates":[-75.329532,39.893104],"type":"Point"}
}