{
  "type": "Feature",
  "properties": {
    "iso:country":"US",
    "sg:address":"211 N State St",
    "sg:city":"Clarks Summit",
    "sg:classifiers":[
        {
            "category":"Health Services",
            "subcategory":"Doctor",
            "type":"Services"
        }
    ],
    "sg:phone":"+1 570 586 3300",
    "sg:postcode":"18411",
    "sg:province":"PA",
    "sg:tags":[
        "physician",
        "surgeon"
    ],
    "wof:name":"Summit Family Care",
    "wof:placetype":"venue"
},
  "geometry": {"coordinates":[-75.70674099999999,41.498084],"type":"Point"}
}