{
  "type": "Feature",
  "properties": {
    "addr:full":"5729 McMahon St Philadelphia PA 19144",
    "addr:housenumber":"5729",
    "addr:postcode":"19144",
    "addr:street":"Mcmahon St",
    "iso:country":"US",
    "sg:address":"5729 McMahon St",
    "sg:city":"Philadelphia",
    "sg:classifiers":[
        {
            "category":"Freight",
            "type":"Transportation"
        }
    ],
    "sg:phone":"+1   ",
    "sg:postcode":"19144",
    "sg:province":"PA",
    "sg:tags":[
        "moving",
        "storage"
    ],
    "wof:name":"Jah Movers",
    "wof:placetype":"venue"
},
  "geometry": {"coordinates":[-75.166991,40.044839],"type":"Point"}
}