{
  "type": "Feature",
  "properties": {
    "iso:country":"US",
    "sg:address":"3000 B St",
    "sg:city":"Philadelphia",
    "sg:classifiers":[
        {
            "category":"Building & Trades",
            "subcategory":"Locksmith",
            "type":"Services"
        }
    ],
    "sg:phone":"+1 267 519 4153",
    "sg:postcode":"19134",
    "sg:province":"PA",
    "sg:tags":[
        "key"
    ],
    "wof:name":"24 Hour Available Locksmith",
    "wof:placetype":"venue"
},
  "geometry": {"coordinates":[-75.126255,39.994978],"type":"Point"}
}