{
  "type": "Feature",
  "properties": {
    "iso:country":"US",
    "sg:address":"4880 Buchanan Trl E",
    "sg:city":"Waynesboro",
    "sg:classifiers":[
        {
            "category":"Recreation",
            "type":"Entertainment"
        }
    ],
    "sg:phone":"+1 717 762 3922",
    "sg:postcode":"17268",
    "sg:province":"PA",
    "sg:tags":[
        "tennis",
        "court"
    ],
    "wof:name":"Tennis Club",
    "wof:placetype":"venue"
},
  "geometry": {"coordinates":[-77.62737199999999,39.769308],"type":"Point"}
}