{
  "type": "Feature",
  "properties": {
    "addr:full":"4259 Old William Penn Hwy Murrysville PA 15668",
    "addr:housenumber":"4259",
    "addr:postcode":"15668",
    "addr:street":"Old William Penn Hwy",
    "iso:country":"US",
    "sg:address":"4259 Old William Penn Hwy",
    "sg:city":"Murrysville",
    "sg:classifiers":[
        {
            "category":"Professional",
            "subcategory":"Accounting & Tax Preparation",
            "type":"Services"
        }
    ],
    "sg:phone":"+1 724 325 2476",
    "sg:postcode":"15668",
    "sg:province":"PA",
    "sg:tags":[
        "accountant"
    ],
    "wof:name":"Mark P Mc Hail CPA",
    "wof:placetype":"venue"
},
  "geometry": {"coordinates":[-79.689324,40.428013],"type":"Point"}
}