{
  "type": "Feature",
  "properties": {
    "iso:country":"US",
    "sg:address":"140 W Mattson Hollow Rd",
    "sg:city":"Coatesville",
    "sg:classifiers":[
        {
            "category":"Farming",
            "subcategory":"Farm & Veterinary Services",
            "type":"Manufacturing & Wholesale Goods"
        }
    ],
    "sg:phone":"+1 610 857 2917",
    "sg:postcode":"19320",
    "sg:province":"PA",
    "sg:tags":[
        "breeder",
        "livestock"
    ],
    "wof:name":"Ultragen LLC",
    "wof:placetype":"venue"
},
  "geometry": {"coordinates":[-75.89372,39.991012],"type":"Point"}
}