{
  "type": "Feature",
  "properties": {
    "addr:full":"5561 Baynton St Philadelphia PA 19144",
    "addr:postcode":"5561;19144",
    "addr:street":"Baynton St",
    "iso:country":"US",
    "sg:address":"5561 Baynton St",
    "sg:city":"Philadelphia",
    "sg:classifiers":[
        {
            "category":"Retail",
            "subcategory":"Auto Repair",
            "type":"Services"
        }
    ],
    "sg:phone":"+1 215 844 6029",
    "sg:postcode":"19144",
    "sg:province":"PA",
    "sg:tags":[
        "repairing",
        "automobile"
    ],
    "wof:name":"Dick Cohen Auto Repair",
    "wof:placetype":"venue"
},
  "geometry": {"coordinates":[-75.16991,40.037561],"type":"Point"}
}