{
  "type": "Feature",
  "properties": {
    "iso:country":"US",
    "sg:address":"1564 Village Dr",
    "sg:city":"Pittsburgh",
    "sg:classifiers":[
        {
            "category":"Manufacturing",
            "subcategory":"Tools & Machinery",
            "type":"Manufacturing & Wholesale Goods"
        }
    ],
    "sg:phone":"+1   ",
    "sg:postcode":"15237",
    "sg:province":"PA",
    "sg:tags":[
        "environmental",
        "consulting",
        "industrial",
        "fan",
        "mfg"
    ],
    "wof:name":"Vh Enterprises Inc",
    "wof:placetype":"venue"
},
  "geometry": {"coordinates":[-80.075773,40.58025],"type":"Point"}
}