{
  "type": "Feature",
  "properties": {
    "iso:country":"US",
    "sg:address":"Broadway & Clewell",
    "sg:city":"Bethlehem",
    "sg:classifiers":[
        {
            "category":"Autos & Motor Vehicles",
            "subcategory":"Fuel & Gas Station",
            "type":"Retail Goods"
        }
    ],
    "sg:phone":"+1 610 868 8382",
    "sg:postcode":"18015",
    "sg:province":"PA",
    "wof:name":"Friedman's Svc Sta",
    "wof:placetype":"venue"
},
  "geometry": {"coordinates":[-75.38069900000001,40.595501],"type":"Point"}
}