{
  "type": "Feature",
  "properties": {
    "iso:country":"US",
    "sg:address":"32 Hawthorne Rd",
    "sg:city":"Bradford",
    "sg:classifiers":[
        {
            "category":"Building & Trades",
            "subcategory":"Landscaping Services",
            "type":"Services"
        }
    ],
    "sg:phone":"+1   ",
    "sg:postcode":"16701",
    "sg:province":"PA",
    "wof:name":"Always Green Landscaping Svc",
    "wof:placetype":"venue"
},
  "geometry": {"coordinates":[-78.620722,41.969258],"type":"Point"}
}