{
  "type": "Feature",
  "properties": {
    "iso:country":"US",
    "sg:address":"211 Airport Rd",
    "sg:city":"Corry",
    "sg:classifiers":[
        {
            "category":"Building & Trades",
            "subcategory":"Construction",
            "type":"Services"
        }
    ],
    "sg:phone":"+1 814 664 5714",
    "sg:postcode":"16407",
    "sg:province":"PA",
    "sg:tags":[
        "general",
        "contractor"
    ],
    "wof:name":"Dyne Asty Construction",
    "wof:placetype":"venue"
},
  "geometry": {"coordinates":[-79.640593,41.910675],"type":"Point"}
}