{
  "type": "Feature",
  "properties": {
    "iso:country":"US",
    "sg:address":"1209 1st Ave",
    "sg:city":"Conway",
    "sg:classifiers":[
        {
            "category":"Travel",
            "subcategory":"Hotels & Motels",
            "type":"Entertainment"
        }
    ],
    "sg:phone":"+1 724 869 8131",
    "sg:postcode":"15027",
    "sg:province":"PA",
    "sg:tags":[
        "operation"
    ],
    "wof:name":"James Motel",
    "wof:placetype":"venue"
},
  "geometry": {"coordinates":[-80.23999000000001,40.661198],"type":"Point"}
}