{
  "type": "Feature",
  "properties": {
    "iso:country":"US",
    "sg:address":"130 Main St",
    "sg:city":"Harleysville",
    "sg:classifiers":[
        {
            "category":"Real Estate",
            "subcategory":"Real Estate Agent",
            "type":"Services"
        }
    ],
    "sg:phone":"+1   ",
    "sg:postcode":"19438",
    "sg:province":"PA",
    "wof:name":"Coldwell Banker Realty Corp",
    "wof:placetype":"venue"
},
  "geometry": {"coordinates":[-75.365527,40.25985],"type":"Point"}
}