{
  "type": "Feature",
  "properties": {
    "iso:country":"US",
    "sg:address":"175 E King St",
    "sg:city":"Ephrata",
    "sg:classifiers":[
        {
            "category":"Manufacturing",
            "subcategory":"Metals",
            "type":"Manufacturing & Wholesale Goods"
        }
    ],
    "sg:phone":"+1   ",
    "sg:postcode":"17522",
    "sg:province":"PA",
    "wof:name":"Precision Coating Tech & Mfg",
    "wof:placetype":"venue"
},
  "geometry": {"coordinates":[-76.184122,40.175866],"type":"Point"}
}