{
  "type": "Feature",
  "properties": {
    "iso:country":"US",
    "sg:address":"1800 N Howard St",
    "sg:city":"Philadelphia",
    "sg:classifiers":[
        {
            "category":"Government",
            "subcategory":"Office",
            "type":"Public Place"
        }
    ],
    "sg:phone":"+1 215 685 9892",
    "sg:postcode":"19122",
    "sg:province":"PA",
    "sg:tags":[
        "village"
    ],
    "wof:name":"Towey Playground",
    "wof:placetype":"venue"
},
  "geometry": {"coordinates":[-75.134767,39.977854],"type":"Point"}
}