{
  "type": "Feature",
  "properties": {
    "iso:country":"US",
    "sg:address":"19 W Houston Ave",
    "sg:city":"Montgomery",
    "sg:classifiers":[
        {
            "category":"Organizations",
            "subcategory":"Religious Organization",
            "type":"Services"
        }
    ],
    "sg:phone":"+1 570 547 1474",
    "sg:postcode":"17752",
    "sg:province":"PA",
    "sg:tags":[
        "church"
    ],
    "wof:name":"Clinton Baptist Church",
    "wof:placetype":"venue"
},
  "geometry": {"coordinates":[-76.877646,41.170109],"type":"Point"}
}