{
  "type": "Feature",
  "properties": {
    "addr:full":"52 S. Second St. Emmaus PA 18099",
    "addr:housenumber":"52",
    "addr:postcode":"18099",
    "addr:street":"S. Second St.",
    "iso:country":"US",
    "sg:address":"52 S. Second St.",
    "sg:city":"Emmaus",
    "sg:classifiers":[
        {
            "category":"Shopping",
            "subcategory":"Books",
            "type":"Retail Goods"
        }
    ],
    "sg:postcode":"18099",
    "sg:province":"PA",
    "sg:tags":[
        "bookstore"
    ],
    "wof:name":"Delaware River Books",
    "wof:placetype":"venue"
},
  "geometry": {"coordinates":[-75.487099,40.536037],"type":"Point"}
}