{
  "type": "Feature",
  "properties": {
    "iso:country":"US",
    "sg:address":"114 W Line St",
    "sg:city":"Olyphant",
    "sg:classifiers":[
        {
            "category":"Building & Trades",
            "subcategory":"Cleaning & Sanitation",
            "type":"Services"
        }
    ],
    "sg:phone":"+1 570 383 1244",
    "sg:postcode":"18447",
    "sg:province":"PA",
    "sg:tags":[
        "janitor"
    ],
    "wof:name":"A2Z Cleaning Co",
    "wof:placetype":"venue"
},
  "geometry": {"coordinates":[-75.605992,41.459611],"type":"Point"}
}