{
  "type": "Feature",
  "properties": {
    "iso:country":"US",
    "sg:address":"2893 Grays Ferry Ave",
    "sg:city":"Philadelphia",
    "sg:classifiers":[
        {
            "category":"Shopping",
            "type":"Retail Goods"
        }
    ],
    "sg:phone":"+1   ",
    "sg:postcode":"19146",
    "sg:province":"PA",
    "sg:tags":[
        "merchandise"
    ],
    "wof:name":"Ranbow Shops",
    "wof:placetype":"venue"
},
  "geometry": {"coordinates":[-75.190157,39.939154],"type":"Point"}
}