{
  "type": "Feature",
  "properties": {
    "iso:country":"US",
    "sg:address":"908 Hickory Dr",
    "sg:city":"Irwin",
    "sg:classifiers":[
        {
            "category":"Wholesale",
            "subcategory":"Sporting Goods",
            "type":"Manufacturing & Wholesale Goods"
        }
    ],
    "sg:phone":"+1   ",
    "sg:postcode":"15642",
    "sg:province":"PA",
    "wof:name":"Arts Bowl Connection & Pro Sp",
    "wof:placetype":"venue"
},
  "geometry": {"coordinates":[-79.753052,40.325178],"type":"Point"}
}