{
  "type": "Feature",
  "properties": {
    "iso:country":"US",
    "sg:address":"314 S Water St",
    "sg:city":"Kittanning",
    "sg:classifiers":[
        {
            "category":"Professional",
            "subcategory":"Engineering",
            "type":"Services"
        }
    ],
    "sg:phone":"+1 724 548 1561",
    "sg:postcode":"16201",
    "sg:province":"PA",
    "sg:tags":[
        "engineer"
    ],
    "wof:name":"R B Shannon & Assoc Inc",
    "wof:placetype":"venue"
},
  "geometry": {"coordinates":[-79.518023,40.81067],"type":"Point"}
}