{
  "type": "Feature",
  "properties": {
    "iso:country":"US",
    "sg:address":"318 N 13th St",
    "sg:city":"Allentown",
    "sg:classifiers":[
        {
            "category":"Health Services",
            "subcategory":"Hospital",
            "type":"Services"
        }
    ],
    "sg:phone":"+1 610 434 3691",
    "sg:postcode":"18102",
    "sg:province":"PA",
    "sg:tags":[
        "sleep",
        "treatment",
        "disorders-information"
    ],
    "wof:name":"Listett M Lazor",
    "wof:placetype":"venue"
},
  "geometry": {"coordinates":[-75.48607800000001,40.603637],"type":"Point"}
}