{
  "type": "Feature",
  "properties": {
    "iso:country":"US",
    "sg:address":"540 US Hwy 209",
    "sg:city":"Milford",
    "sg:classifiers":[
        {
            "category":"Banks & Credit Unions",
            "subcategory":"Investment Brokerage",
            "type":"Services"
        }
    ],
    "sg:phone":"+1   ",
    "sg:postcode":"18337",
    "sg:province":"PA",
    "sg:tags":[
        "security"
    ],
    "wof:name":"Citigroup Global Markets Inc",
    "wof:placetype":"venue"
},
  "geometry": {"coordinates":[-74.71711500000001,41.355246],"type":"Point"}
}