{
  "type": "Feature",
  "properties": {
    "iso:country":"US",
    "sg:address":"10 W Chocolate Ave",
    "sg:city":"Hershey",
    "sg:classifiers":[
        {
            "category":"Restaurant",
            "type":"Food & Drink"
        }
    ],
    "sg:phone":"+1 717 534 1660",
    "sg:postcode":"17033",
    "sg:province":"PA",
    "sg:tags":[
        "pizza"
    ],
    "wof:name":"Sorrento's Mr Pizza Sub & Pasta House",
    "wof:placetype":"venue"
},
  "geometry": {"coordinates":[-76.6502,40.285702],"type":"Point"}
}