{
  "type": "Feature",
  "properties": {
    "iso:country":"US",
    "sg:address":"200 S Progress Ave",
    "sg:city":"Harrisburg",
    "sg:classifiers":[
        {
            "category":"Professional",
            "type":"Services"
        }
    ],
    "sg:phone":"+1 717 652 8878",
    "sg:postcode":"17109",
    "sg:province":"PA",
    "sg:tags":[
        "establishment"
    ],
    "wof:name":"International Academy-Sports",
    "wof:placetype":"venue"
},
  "geometry": {"coordinates":[-76.839894,40.283264],"type":"Point"}
}