{
  "type": "Feature",
  "properties": {
    "iso:country":"US",
    "sg:address":"9125 Marshall Rd",
    "sg:city":"Cranberry Township",
    "sg:classifiers":[
        {
            "category":"Health Services",
            "subcategory":"Chiropractor",
            "type":"Services"
        }
    ],
    "sg:phone":"+1 724 741 6080",
    "sg:postcode":"16066",
    "sg:province":"PA",
    "wof:name":"Jordan Family Chiropractic",
    "wof:placetype":"venue"
},
  "geometry": {"coordinates":[-80.100377,40.716265],"type":"Point"}
}