{
  "type": "Feature",
  "properties": {
    "addr:full":"21 Kugler Rd Royersford PA 19468",
    "addr:housenumber":"21",
    "addr:postcode":"19468",
    "addr:street":"Kugler Rd",
    "iso:country":"US",
    "sg:address":"21 Kugler Rd",
    "sg:city":"Royersford",
    "sg:classifiers":[
        {
            "category":"Restaurant",
            "type":"Food & Drink"
        }
    ],
    "sg:menulink":"http://www.allmenus.com/pa/limerick/288357-bravo-pizza/menu/",
    "sg:phone":"+1 610 495 8242",
    "sg:postcode":"19468",
    "sg:province":"PA",
    "sg:tags":[
        "american",
        "pizza"
    ],
    "wof:name":"Bravo Pizza",
    "wof:placetype":"venue"
},
  "geometry": {"coordinates":[-75.535644,40.237577],"type":"Point"}
}