{
  "type": "Feature",
  "properties": {
    "iso:country":"US",
    "sg:address":"43 Snyder Ave",
    "sg:city":"Philadelphia",
    "sg:classifiers":[
        {
            "category":"Restaurant",
            "type":"Food & Drink"
        }
    ],
    "sg:phone":"+1   ",
    "sg:postcode":"19148",
    "sg:province":"PA",
    "sg:tags":[
        "eating"
    ],
    "wof:name":"Dynasty Inn Inc",
    "wof:placetype":"venue"
},
  "geometry": {"coordinates":[-75.1467,39.921462],"type":"Point"}
}