{
  "type": "Feature",
  "properties": {
    "addr:full":"138 W Main St Ridgway PA 15853",
    "addr:housenumber":"138",
    "addr:postcode":"15853",
    "addr:street":"W Main St",
    "iso:country":"US",
    "sg:address":"138 W Main St",
    "sg:city":"Ridgway",
    "sg:classifiers":[
        {
            "category":"Retail",
            "subcategory":"Auto Repair",
            "type":"Services"
        }
    ],
    "sg:phone":"+1 814 776 1523",
    "sg:postcode":"15853",
    "sg:province":"PA",
    "sg:tags":[
        "repairing",
        "automobile"
    ],
    "wof:name":"Piccirillo's Auto Svc",
    "wof:placetype":"venue"
},
  "geometry": {"coordinates":[-78.739096,41.420916],"type":"Point"}
}