{
  "type": "Feature",
  "properties": {
    "addr:full":"1230 Win Dr Bethlehem PA 18017",
    "addr:housenumber":"1230",
    "addr:postcode":"18017",
    "addr:street":"Win Dr",
    "iso:country":"US",
    "sg:address":"1230 Win Dr",
    "sg:city":"Bethlehem",
    "sg:classifiers":[
        {
            "category":"Retail",
            "subcategory":"Repair Shop",
            "type":"Services"
        }
    ],
    "sg:phone":"+1   ",
    "sg:postcode":"18017",
    "sg:province":"PA",
    "wof:name":"Pan-Glo",
    "wof:placetype":"venue"
},
  "geometry": {"coordinates":[-75.352675,40.62585],"type":"Point"}
}