{
  "type": "Feature",
  "properties": {
    "iso:country":"US",
    "sg:address":"1415 6th Ave",
    "sg:city":"Beaver Falls",
    "sg:classifiers":[
        {
            "category":"Health Services",
            "subcategory":"Health Practitioner",
            "type":"Services"
        }
    ],
    "sg:phone":"+1 724 843 7930",
    "sg:postcode":"15010",
    "sg:province":"PA",
    "sg:tags":[
        "therapist",
        "physical"
    ],
    "wof:name":"Centers For Rehab Svc",
    "wof:placetype":"venue"
},
  "geometry": {"coordinates":[-80.317983,40.755795],"type":"Point"}
}