{
  "type": "Feature",
  "properties": {
    "addr:full":"13 Ave B Leetsdale PA 15056",
    "addr:postcode":"15056",
    "addr:street":"13 Ave B",
    "iso:country":"US",
    "sg:address":"13 Ave B",
    "sg:city":"Leetsdale",
    "sg:classifiers":[
        {
            "category":"Wholesale",
            "subcategory":"Chemicals & Plastics",
            "type":"Manufacturing & Wholesale Goods"
        }
    ],
    "sg:phone":"+1 412 741 2600",
    "sg:postcode":"15056",
    "sg:province":"PA",
    "sg:tags":[
        "cleaning",
        "compound"
    ],
    "wof:name":"Zep Manufacturing Co",
    "wof:placetype":"venue"
},
  "geometry": {"coordinates":[-80.208449,40.558605],"type":"Point"}
}