{
  "type": "Feature",
  "properties": {
    "iso:country":"US",
    "sg:address":"719 Morgantown Rd",
    "sg:city":"Uniontown",
    "sg:classifiers":[
        {
            "category":"Building & Trades",
            "subcategory":"Construction",
            "type":"Services"
        }
    ],
    "sg:phone":"+1   ",
    "sg:postcode":"15401",
    "sg:province":"PA",
    "wof:name":"Corodi Paving Company",
    "wof:placetype":"venue"
},
  "geometry": {"coordinates":[-79.741178,39.87327],"type":"Point"}
}