{
  "type": "Feature",
  "properties": {
    "iso:country":"US",
    "sg:address":"3650 Kings Hwy",
    "sg:city":"Downingtown",
    "sg:classifiers":[
        {
            "category":"Building & Trades",
            "subcategory":"Landscaping Services",
            "type":"Services"
        },
        {
            "category":"Manufacturing",
            "subcategory":"Wood Products",
            "type":"Manufacturing & Wholesale Goods"
        },
        {
            "category":"Building & Trades",
            "subcategory":"Construction",
            "type":"Services"
        }
    ],
    "sg:phone":"+1 610 269 8484",
    "sg:postcode":"19335",
    "sg:province":"PA",
    "sg:tags":[
        "excavation",
        "firewood",
        "tree",
        "contractor"
    ],
    "wof:name":"Love Dave Tree Care",
    "wof:placetype":"venue"
},
  "geometry": {"coordinates":[-75.75302600000001,40.01225],"type":"Point"}
}