{
  "type": "Feature",
  "properties": {
    "addr:full":"68 S 69th St Upper Darby PA 19082",
    "addr:housenumber":"68",
    "addr:postcode":"19082",
    "addr:street":"S 69Th St",
    "iso:country":"US",
    "sg:address":"68 S 69th St",
    "sg:city":"Upper Darby",
    "sg:classifiers":[
        {
            "category":"Education",
            "subcategory":"Special Training",
            "type":"Public Place"
        }
    ],
    "sg:phone":"+1 610 352 2362",
    "sg:postcode":"19082",
    "sg:province":"PA",
    "sg:tags":[
        "tutoring"
    ],
    "wof:name":"Score Learning Ctr",
    "wof:placetype":"venue"
},
  "geometry": {"coordinates":[-75.258695,39.96023],"type":"Point"}
}