{
  "type": "Feature",
  "properties": {
    "iso:country":"US",
    "sg:address":"6710 Greenway Ave",
    "sg:city":"Philadelphia",
    "sg:classifiers":[
        {
            "category":"Retail",
            "subcategory":"Auto Repair",
            "type":"Services"
        }
    ],
    "sg:phone":"+1 215 727 5880",
    "sg:postcode":"19142",
    "sg:province":"PA",
    "sg:tags":[
        "body",
        "shop"
    ],
    "wof:name":"Tim's Auto Body",
    "wof:placetype":"venue"
},
  "geometry": {"coordinates":[-75.23840300000001,39.9249],"type":"Point"}
}