{
  "type": "Feature",
  "properties": {
    "iso:country":"US",
    "sg:address":"3341 Imlertown Rd",
    "sg:city":"Bedford",
    "sg:classifiers":[
        {
            "category":"Retail",
            "subcategory":"Auto Repair",
            "type":"Services"
        }
    ],
    "sg:phone":"+1 814 623 1352",
    "sg:postcode":"15522",
    "sg:province":"PA",
    "sg:tags":[
        "carburetor"
    ],
    "wof:name":"Burtnette's Engine Tuning",
    "wof:placetype":"venue"
},
  "geometry": {"coordinates":[-78.45523300000001,40.098045],"type":"Point"}
}