{
  "type": "Feature",
  "properties": {
    "iso:country":"US",
    "sg:address":"10 York St",
    "sg:city":"Hanover",
    "sg:classifiers":[
        {
            "category":"Shopping",
            "subcategory":"Hobbies, Toys, & Games",
            "type":"Retail Goods"
        }
    ],
    "sg:phone":"+1 717 637 6025",
    "sg:postcode":"17331",
    "sg:province":"PA",
    "sg:tags":[
        "model",
        "supply"
    ],
    "wof:name":"Groft's Sportscards",
    "wof:placetype":"venue"
},
  "geometry": {"coordinates":[-76.98273,39.801056],"type":"Point"}
}