{
  "type": "Feature",
  "properties": {
    "addr:full":"194 Castle Shannon Blvd Pittsburgh PA 15228",
    "addr:housenumber":"194",
    "addr:postcode":"15228",
    "addr:street":"Castle Shannon Blvd",
    "iso:country":"US",
    "sg:address":"194 Castle Shannon Blvd",
    "sg:city":"Pittsburgh",
    "sg:classifiers":[
        {
            "category":"Restaurant",
            "type":"Food & Drink"
        }
    ],
    "sg:phone":"+1 412 344 0633",
    "sg:postcode":"15228",
    "sg:province":"PA",
    "wof:name":"Cuckoo's Nest Cafe",
    "wof:placetype":"venue"
},
  "geometry": {"coordinates":[-80.040414,40.377589],"type":"Point"}
}