{
  "type": "Feature",
  "properties": {
    "addr:full":"4110 Lancaster Ave Philadelphia PA 19104",
    "addr:housenumber":"4110",
    "addr:postcode":"19104",
    "addr:street":"Lancaster Ave",
    "iso:country":"US",
    "sg:address":"4110 Lancaster Ave",
    "sg:city":"Philadelphia",
    "sg:classifiers":[
        {
            "category":"Retail",
            "subcategory":"Laundry & Dry Cleaning",
            "type":"Services"
        }
    ],
    "sg:phone":"+1 215 386 7778",
    "sg:postcode":"19104",
    "sg:province":"PA",
    "wof:name":"Lancaster Cleaners",
    "wof:placetype":"venue"
},
  "geometry": {"coordinates":[-75.20582400000001,39.965143],"type":"Point"}
}