{
  "type": "Feature",
  "properties": {
    "iso:country":"US",
    "sg:address":"92 N Morgantown St",
    "sg:city":"Fairchance",
    "sg:phone":"+1 724 564 1700",
    "sg:postcode":"15436",
    "sg:province":"PA",
    "wof:name":"Valentine Pharmacy",
    "wof:placetype":"venue"
},
  "geometry": {"coordinates":[-79.753418,39.826241],"type":"Point"}
}