{
  "type": "Feature",
  "properties": {
    "addr:full":"312 E Ross St Lancaster PA 17602",
    "addr:housenumber":"312",
    "addr:postcode":"17602",
    "addr:street":"E Ross St",
    "iso:country":"US",
    "sg:address":"312 E Ross St",
    "sg:city":"Lancaster",
    "sg:classifiers":[
        {
            "category":"Organizations",
            "subcategory":"Religious Organization",
            "type":"Services"
        }
    ],
    "sg:phone":"+1   ",
    "sg:postcode":"17602",
    "sg:province":"PA",
    "wof:name":"Ross St Untd Methdst Church",
    "wof:placetype":"venue"
},
  "geometry": {"coordinates":[-76.299657,40.051811],"type":"Point"}
}