{
  "type": "Feature",
  "properties": {
    "iso:country":"US",
    "sg:address":"307 Broad St",
    "sg:city":"Waverly",
    "sg:classifiers":[
        {
            "category":"Health Services",
            "subcategory":"Health Practitioner",
            "type":"Services"
        }
    ],
    "sg:phone":"+1 607 565 9292",
    "sg:postcode":"14892",
    "sg:province":"PA",
    "sg:tags":[
        "therapist",
        "physical"
    ],
    "wof:name":"Valley Procare Physical T",
    "wof:placetype":"venue"
},
  "geometry": {"coordinates":[-76.540273,42.001097],"type":"Point"}
}