{
  "type": "Feature",
  "properties": {
    "iso:country":"US",
    "sg:address":"3 Cedar Green Ctr",
    "sg:city":"Mifflinburg",
    "sg:classifiers":[
        {
            "category":"Coffee & Tea",
            "type":"Food & Drink"
        }
    ],
    "sg:phone":"+1 570 966 3300",
    "sg:postcode":"17844",
    "sg:province":"PA",
    "sg:website":"http://www.thedecoratingcenter.net",
    "wof:name":"The Decorating Center",
    "wof:placetype":"venue"
},
  "geometry": {"coordinates":[-77.021702,40.926174],"type":"Point"}
}