{
  "type": "Feature",
  "properties": {
    "iso:country":"US",
    "sg:address":"1355 Cordova Rd",
    "sg:city":"Pittsburgh",
    "sg:classifiers":[
        {
            "category":"Retail",
            "subcategory":"Repair Shop",
            "type":"Services"
        }
    ],
    "sg:phone":"+1 412 781 1655",
    "sg:postcode":"15206",
    "sg:province":"PA",
    "sg:tags":[
        "repairing",
        "organs"
    ],
    "wof:name":"Luley & Assoc Inc",
    "wof:placetype":"venue"
},
  "geometry": {"coordinates":[-79.92659399999999,40.479344],"type":"Point"}
}