{
  "type": "Feature",
  "properties": {
    "addr:full":"357 N Main St Sellersville PA 18960",
    "addr:housenumber":"357",
    "addr:postcode":"18960",
    "addr:street":"N Main St",
    "iso:country":"US",
    "sg:address":"357 N Main St",
    "sg:city":"Sellersville",
    "sg:classifiers":[
        {
            "category":"Shopping",
            "subcategory":"Shoes",
            "type":"Retail Goods"
        }
    ],
    "sg:phone":"+1 215 453 7452",
    "sg:postcode":"18960",
    "sg:province":"PA",
    "wof:name":"Specialty Footwear",
    "wof:placetype":"venue"
},
  "geometry": {"coordinates":[-75.312246,40.363259],"type":"Point"}
}