{
  "type": "Feature",
  "properties": {
    "iso:country":"US",
    "sg:address":"413 9th St",
    "sg:city":"Ford City",
    "sg:classifiers":[
        {
            "category":"Insurance",
            "subcategory":"Insurance Agent",
            "type":"Services"
        }
    ],
    "sg:phone":"+1 724 763 1761",
    "sg:postcode":"16226",
    "sg:province":"PA",
    "wof:name":"Nationwide Insurance",
    "wof:placetype":"venue"
},
  "geometry": {"coordinates":[-79.531796,40.76998],"type":"Point"}
}