{
  "type": "Feature",
  "properties": {
    "iso:country":"US",
    "sg:address":"60 N Industrial Park Rd",
    "sg:city":"Milton",
    "sg:classifiers":[
        {
            "category":"Wholesale",
            "subcategory":"Meat",
            "type":"Manufacturing & Wholesale Goods"
        }
    ],
    "sg:phone":"+1   ",
    "sg:postcode":"17847",
    "sg:province":"PA",
    "sg:tags":[
        "dry",
        "pork",
        "beef",
        "packer",
        "grocery",
        "prepared",
        "po"
    ],
    "wof:name":"Conagra Foods Inc",
    "wof:placetype":"venue"
},
  "geometry": {"coordinates":[-76.85601200000001,40.994958],"type":"Point"}
}