{
  "type": "Feature",
  "properties": {
    "iso:country":"US",
    "sg:address":"213 Bellevue Rd",
    "sg:city":"Red Lion",
    "sg:classifiers":[
        {
            "category":"Professional",
            "subcategory":"Research",
            "type":"Services"
        }
    ],
    "sg:phone":"+1   ",
    "sg:postcode":"17356",
    "sg:province":"PA",
    "sg:tags":[
        "commercial",
        "physical"
    ],
    "wof:name":"Digital Elec SEC Systems",
    "wof:placetype":"venue"
},
  "geometry": {"coordinates":[-76.61094900000001,39.890958],"type":"Point"}
}