{
  "type": "Feature",
  "properties": {
    "addr:full":"514 N Highland Ave Pittsburgh PA 15206",
    "addr:housenumber":"514",
    "addr:postcode":"15206",
    "addr:street":"N Highland Ave",
    "iso:country":"US",
    "sg:address":"514 N Highland Ave",
    "sg:city":"Pittsburgh",
    "sg:classifiers":[
        {
            "category":"Food & Beverages",
            "subcategory":"Groceries & Convenience Stores",
            "type":"Retail Goods"
        }
    ],
    "sg:phone":"+1 412 441 1067",
    "sg:postcode":"15206",
    "sg:province":"PA",
    "wof:name":"A Plus Mini Market",
    "wof:placetype":"venue"
},
  "geometry": {"coordinates":[-79.921359,40.468742],"type":"Point"}
}