{
  "type": "Feature",
  "properties": {
    "iso:country":"US",
    "sg:address":"500 Chesterbrook Blvd",
    "sg:city":"Wayne",
    "sg:classifiers":[
        {
            "category":"Shopping",
            "subcategory":"Gifts & Souvenirs",
            "type":"Retail Goods"
        }
    ],
    "sg:phone":"+1   ",
    "sg:postcode":"19087",
    "sg:province":"PA",
    "sg:tags":[
        "collectible",
        "confectionery",
        "jewelry",
        "chocolate"
    ],
    "wof:name":"Chesterbrook Boutique & Flower",
    "wof:placetype":"venue"
},
  "geometry": {"coordinates":[-75.45879499999999,40.073519],"type":"Point"}
}