{
  "type": "Feature",
  "properties": {
    "iso:country":"US",
    "sg:address":"22 Triplett Ct",
    "sg:city":"Dillsburg",
    "sg:classifiers":[
        {
            "category":"Organizations",
            "subcategory":"Professional Association",
            "type":"Services"
        }
    ],
    "sg:phone":"+1 717 432 0090",
    "sg:postcode":"17019",
    "sg:province":"PA",
    "wof:name":"National Apple Month Program",
    "wof:placetype":"venue"
},
  "geometry": {"coordinates":[-77.045776,40.114045],"type":"Point"}
}