{
  "type": "Feature",
  "properties": {
    "iso:country":"US",
    "sg:address":"22 N Cameron St",
    "sg:city":"Harrisburg",
    "sg:classifiers":[
        {
            "category":"Bars & Pubs",
            "subcategory":"Champagne Bar",
            "type":"Food & Drink"
        },
        {
            "category":"Home & Garden",
            "subcategory":"Kitchen Supply",
            "type":"Retail Goods"
        },
        {
            "category":"Building & Trades",
            "subcategory":"Equipment Rental",
            "type":"Services"
        },
        {
            "category":"Wholesale",
            "subcategory":"Home Furnishings",
            "type":"Manufacturing & Wholesale Goods"
        }
    ],
    "sg:phone":"+1 717 236 5006",
    "sg:postcode":"17101",
    "sg:province":"PA",
    "sg:tags":[
        "restaurant",
        "equipment-wholesale",
        "fixture",
        "cabinet",
        "equipment-repair",
        "manufacturer"
    ],
    "sg:website":"http://www.ccfse.com",
    "wof:name":"Chef's Choice Foodservice Equipment INC",
    "wof:placetype":"venue"
},
  "geometry": {"coordinates":[-76.874809,40.265079],"type":"Point"}
}