{
  "type": "Feature",
  "properties": {
    "iso:country":"US",
    "sg:address":"107 Wickshire Cir",
    "sg:city":"Lititz",
    "sg:classifiers":[
        {
            "category":"Professional",
            "type":"Services"
        }
    ],
    "sg:phone":"+1   ",
    "sg:postcode":"17543",
    "sg:province":"PA",
    "wof:name":"Phill Mann Inc",
    "wof:placetype":"venue"
},
  "geometry": {"coordinates":[-76.308548,40.135838],"type":"Point"}
}