{
  "type": "Feature",
  "properties": {
    "addr:full":"108 E South St New Castle PA 16101",
    "addr:housenumber":"108 e",
    "addr:postcode":"16101",
    "addr:street":"South St",
    "iso:country":"US",
    "sg:address":"108 E South St",
    "sg:city":"New Castle",
    "sg:classifiers":[
        {
            "category":"Government",
            "subcategory":"Office",
            "type":"Public Place"
        }
    ],
    "sg:phone":"+1 724 656 3041",
    "sg:postcode":"16101",
    "sg:province":"PA",
    "sg:tags":[
        "state",
        "resource"
    ],
    "wof:name":"Public Welfare Dept",
    "wof:placetype":"venue"
},
  "geometry": {"coordinates":[-80.345535,40.99867],"type":"Point"}
}