{
  "type": "Feature",
  "properties": {
    "addr:full":"2914 Raspberry St Erie PA 16508",
    "addr:housenumber":"2914",
    "addr:postcode":"16508",
    "addr:street":"Raspberry St",
    "iso:country":"US",
    "sg:address":"2914 Raspberry St",
    "sg:city":"Erie",
    "sg:classifiers":[
        {
            "category":"Real Estate",
            "subcategory":"Real Estate Agent",
            "type":"Services"
        }
    ],
    "sg:phone":"+1   ",
    "sg:postcode":"16508",
    "sg:province":"PA",
    "wof:name":"Mook Kocher Real Estate",
    "wof:placetype":"venue"
},
  "geometry": {"coordinates":[-80.09464699999999,42.100254],"type":"Point"}
}