{
  "type": "Feature",
  "properties": {
    "iso:country":"US",
    "sg:address":"1511 Walnut St",
    "sg:city":"Philadelphia",
    "sg:classifiers":[
        {
            "category":"Real Estate",
            "subcategory":"Real Estate Agent",
            "type":"Services"
        }
    ],
    "sg:phone":"+1   ",
    "sg:postcode":"19102",
    "sg:province":"PA",
    "wof:name":"Icis Investment LP",
    "wof:placetype":"venue"
},
  "geometry": {"coordinates":[-75.16618699999999,39.949488],"type":"Point"}
}