{
  "type": "Feature",
  "properties": {
    "iso:country":"US",
    "sg:address":"24465 State St",
    "sg:city":"Meadville",
    "sg:classifiers":[
        {
            "category":"Government",
            "subcategory":"Office",
            "type":"Public Place"
        }
    ],
    "sg:phone":"+1 814 724 4727",
    "sg:postcode":"16335",
    "sg:province":"PA",
    "sg:tags":[
        "village"
    ],
    "wof:name":"Blooming Valley Council Pres",
    "wof:placetype":"venue"
},
  "geometry": {"coordinates":[-80.058027,41.674222],"type":"Point"}
}