{
  "type": "Feature",
  "properties": {
    "iso:country":"US",
    "sg:address":"609 Park Ln",
    "sg:city":"Wyncote",
    "sg:classifiers":[
        {
            "category":"Professional",
            "subcategory":"Management & Consulting",
            "type":"Services"
        }
    ],
    "sg:phone":"+1   ",
    "sg:postcode":"19095",
    "sg:province":"PA",
    "wof:name":"Ford Building Co",
    "wof:placetype":"venue"
},
  "geometry": {"coordinates":[-75.14253600000001,40.094627],"type":"Point"}
}