{
  "type": "Feature",
  "properties": {
    "iso:country":"US",
    "sg:address":"281 N 1st St",
    "sg:city":"Lehighton",
    "sg:classifiers":[
        {
            "category":"Health Services",
            "subcategory":"Doctor",
            "type":"Services"
        }
    ],
    "sg:phone":"+1   ",
    "sg:postcode":"18235",
    "sg:province":"PA",
    "sg:tags":[
        "medical"
    ],
    "wof:name":"Mark T Vandenberg MD",
    "wof:placetype":"venue"
},
  "geometry": {"coordinates":[-75.708838,40.835626],"type":"Point"}
}