{
  "type": "Feature",
  "properties": {
    "addr:full":"4909 Louise Dr Mechanicsburg PA 17055",
    "addr:housenumber":"4909",
    "addr:postcode":"17055",
    "addr:street":"Louise Dr",
    "iso:country":"US",
    "sg:address":"4909 Louise Dr",
    "sg:city":"Mechanicsburg",
    "sg:classifiers":[
        {
            "category":"Organizations",
            "subcategory":"Non-profit Organization",
            "type":"Services"
        },
        {
            "category":"Professional",
            "subcategory":"Lawyer & Legal Services",
            "type":"Services"
        }
    ],
    "sg:phone":"+1 717 691 7503",
    "sg:postcode":"17055",
    "sg:province":"PA",
    "sg:website":"www.palawfund.com",
    "wof:name":"For Pennsylvania Lawyers Fund",
    "wof:placetype":"venue"
},
  "geometry": {"coordinates":[-76.95634699999999,40.204082],"type":"Point"}
}