{
  "type": "Feature",
  "properties": {
    "addr:full":"3036 W 12th St Erie PA 16505",
    "addr:housenumber":"3036",
    "addr:postcode":"16505",
    "addr:street":"W 12Th St",
    "iso:country":"US",
    "sg:address":"3036 W 12th St",
    "sg:city":"Erie",
    "sg:classifiers":[
        {
            "category":"Health Services",
            "subcategory":"Hospital",
            "type":"Services"
        }
    ],
    "sg:phone":"+1   ",
    "sg:postcode":"16505",
    "sg:province":"PA",
    "sg:tags":[
        "specialty"
    ],
    "wof:name":"Cove Forge Luteran Center",
    "wof:placetype":"venue"
},
  "geometry": {"coordinates":[-80.15087,42.097924],"type":"Point"}
}