{
  "type": "Feature",
  "properties": {
    "iso:country":"US",
    "sg:address":"1817 Tyris Dr",
    "sg:city":"Pittsburgh",
    "sg:classifiers":[
        {
            "category":"Professional",
            "subcategory":"Business Services",
            "type":"Services"
        },
        {
            "category":"Professional",
            "subcategory":"Management & Consulting",
            "type":"Services"
        }
    ],
    "sg:phone":"+1 412 221 3933",
    "sg:postcode":"15241",
    "sg:province":"PA",
    "sg:tags":[
        "consultant"
    ],
    "wof:name":"Interface Management Intl",
    "wof:placetype":"venue"
},
  "geometry": {"coordinates":[-80.078534,40.351758],"type":"Point"}
}