{
  "type": "Feature",
  "properties": {
    "addr:full":"334 W Broad St Quakertown PA 18951",
    "addr:housenumber":"334",
    "addr:postcode":"18951",
    "addr:street":"W Broad St",
    "iso:country":"US",
    "sg:address":"334 W Broad St",
    "sg:city":"Quakertown",
    "sg:classifiers":[
        {
            "category":"Health Services",
            "subcategory":"Chiropractor",
            "type":"Services"
        }
    ],
    "sg:phone":"+1 215 536 4002",
    "sg:postcode":"18951",
    "sg:province":"PA",
    "wof:name":"Discover Chiropractic Center",
    "wof:placetype":"venue"
},
  "geometry": {"coordinates":[-75.339495,40.441416],"type":"Point"}
}