{
  "type": "Feature",
  "properties": {
    "addr:full":"870 W Lancaster Ave Bryn Mawr PA 19010",
    "addr:housenumber":"870",
    "addr:postcode":"19010",
    "addr:street":"W Lancaster Ave",
    "iso:country":"US",
    "sg:address":"870 W Lancaster Ave",
    "sg:city":"Bryn Mawr",
    "sg:classifiers":[
        {
            "category":"Food & Beverages",
            "subcategory":"Groceries & Convenience Stores",
            "type":"Retail Goods"
        },
        {
            "category":"Restaurant",
            "type":"Food & Drink"
        }
    ],
    "sg:phone":"+1 610 520 4414",
    "sg:postcode":"19010",
    "sg:province":"PA",
    "sg:tags":[
        "delicatessen"
    ],
    "wof:name":"Gibo's Inc",
    "wof:placetype":"venue"
},
  "geometry": {"coordinates":[-75.320866,40.022729],"type":"Point"}
}