{
  "type": "Feature",
  "properties": {
    "addr:full":"20411 Rte 19 Cranberry Twp PA 16066",
    "addr:postcode":"20411;16066",
    "addr:street":"Rte 19",
    "iso:country":"US",
    "sg:address":"20411 Rte 19",
    "sg:city":"Cranberry Twp",
    "sg:classifiers":[
        {
            "category":"Utilities",
            "subcategory":"Mobile Phone",
            "type":"Services"
        }
    ],
    "sg:phone":"+1 724 776 3939",
    "sg:postcode":"16066",
    "sg:province":"PA",
    "sg:tags":[
        "telephone",
        "cellular"
    ],
    "wof:name":"Millennium Digital",
    "wof:placetype":"venue"
},
  "geometry": {"coordinates":[-80.104417,40.699517],"type":"Point"}
}