{
  "type": "Feature",
  "properties": {
    "iso:country":"US",
    "sg:address":"1201 E Erie Ave",
    "sg:city":"Philadelphia",
    "sg:classifiers":[
        {
            "category":"Retail",
            "subcategory":"Car Wash",
            "type":"Services"
        }
    ],
    "sg:phone":"+1   ",
    "sg:postcode":"19140",
    "sg:province":"PA",
    "sg:tags":[
        "carwash"
    ],
    "wof:name":"Barbara Wash & Dry Inc",
    "wof:placetype":"venue"
},
  "geometry": {"coordinates":[-75.148466,40.008885],"type":"Point"}
}