{
  "type": "Feature",
  "properties": {
    "iso:country":"US",
    "sg:address":"152 Academy Ln",
    "sg:city":"Upper Darby",
    "sg:classifiers":[
        {
            "category":"Wholesale",
            "subcategory":"Metals & Minerals",
            "type":"Manufacturing & Wholesale Goods"
        }
    ],
    "sg:phone":"+1   ",
    "sg:postcode":"19082",
    "sg:province":"PA",
    "sg:tags":[
        "process",
        "steel"
    ],
    "wof:name":"C B A Steel Corp",
    "wof:placetype":"venue"
},
  "geometry": {"coordinates":[-75.279726,39.968003],"type":"Point"}
}