{
  "type": "Feature",
  "properties": {
    "addr:full":"124 Lori Ln Broomall PA 19008",
    "addr:housenumber":"124",
    "addr:postcode":"19008",
    "addr:street":"Lori Ln",
    "iso:country":"US",
    "sg:address":"124 Lori Ln",
    "sg:city":"Broomall",
    "sg:classifiers":[
        {
            "category":"Wholesale",
            "subcategory":"Durable Goods & Equipment",
            "type":"Manufacturing & Wholesale Goods"
        }
    ],
    "sg:phone":"+1 610 353 9440",
    "sg:postcode":"19008",
    "sg:province":"PA",
    "sg:tags":[
        "representative",
        "manufacturer"
    ],
    "wof:name":"John Motley Assoc",
    "wof:placetype":"venue"
},
  "geometry": {"coordinates":[-75.346842,39.987247],"type":"Point"}
}