{
  "type": "Feature",
  "properties": {
    "addr:full":"936 N Providence Rd Media PA 19063",
    "addr:housenumber":"936",
    "addr:postcode":"19063",
    "addr:street":"N Providence Rd",
    "iso:country":"US",
    "sg:address":"936 N Providence Rd",
    "sg:city":"Media",
    "sg:classifiers":[
        {
            "category":"Retail",
            "subcategory":"Repair Shop",
            "type":"Services"
        }
    ],
    "sg:phone":"+1 610 565 9900",
    "sg:postcode":"19063",
    "sg:province":"PA",
    "sg:tags":[
        "organization",
        "religious"
    ],
    "wof:name":"South Penn Lock & Safe Co",
    "wof:placetype":"venue"
},
  "geometry": {"coordinates":[-75.38806599999999,39.930978],"type":"Point"}
}