{
  "type": "Feature",
  "properties": {
    "iso:country":"US",
    "sg:address":"203 E State St",
    "sg:city":"Kennett Square",
    "sg:classifiers":[
        {
            "category":"Wholesale",
            "subcategory":"Electrical",
            "type":"Manufacturing & Wholesale Goods"
        }
    ],
    "sg:phone":"+1 610 444 5898",
    "sg:postcode":"19348",
    "sg:province":"PA",
    "sg:tags":[
        "electronic"
    ],
    "wof:name":"Tera Acoustics",
    "wof:placetype":"venue"
},
  "geometry": {"coordinates":[-75.709884,39.847275],"type":"Point"}
}