{
  "type": "Feature",
  "properties": {
    "iso:country":"US",
    "sg:address":"2200 Lebanon Valley Mall",
    "sg:city":"Lebanon",
    "sg:classifiers":[
        {
            "category":"Ice Cream",
            "type":"Food & Drink"
        }
    ],
    "sg:menulink":"http://www.allmenus.com/pa/north-lebanon/227920-dippin-dots/menu/",
    "sg:phone":"0",
    "sg:postcode":"17042",
    "sg:province":"PA",
    "sg:tags":[
        "american"
    ],
    "wof:name":"Dippin' Dots",
    "wof:placetype":"venue"
},
  "geometry": {"coordinates":[-76.453368,40.339402],"type":"Point"}
}