{
  "type": "Feature",
  "properties": {
    "iso:country":"US",
    "sg:address":"2364 Robert Fulton Hwy",
    "sg:city":"Peach Bottom",
    "sg:classifiers":[
        {
            "category":"Professional",
            "subcategory":"Research",
            "type":"Services"
        }
    ],
    "sg:phone":"+1   ",
    "sg:postcode":"17563",
    "sg:province":"PA",
    "sg:tags":[
        "commercial",
        "physical"
    ],
    "wof:name":"Ppie LLC",
    "wof:placetype":"venue"
},
  "geometry": {"coordinates":[-76.178023,39.76287],"type":"Point"}
}