{
  "type": "Feature",
  "properties": {
    "iso:country":"US",
    "sg:address":"901 Sleepy Hollow Ln",
    "sg:city":"Mechanicsburg",
    "sg:classifiers":[
        {
            "category":"Building & Trades",
            "subcategory":"Equipment Rental",
            "type":"Services"
        }
    ],
    "sg:phone":"+1 717 612 5101",
    "sg:postcode":"17050",
    "sg:province":"PA",
    "sg:tags":[
        "consultant",
        "valuation",
        "business"
    ],
    "wof:name":"Sleepy Hollow Enterprises",
    "wof:placetype":"venue"
},
  "geometry": {"coordinates":[-76.977089,40.264019],"type":"Point"}
}