{
  "type": "Feature",
  "properties": {
    "iso:country":"US",
    "sg:address":"108 E Cherry St",
    "sg:city":"Clearfield",
    "sg:classifiers":[
        {
            "category":"Government",
            "subcategory":"Fire Station",
            "type":"Public Place"
        }
    ],
    "sg:phone":"+1 814 765 4861",
    "sg:postcode":"16830",
    "sg:province":"PA",
    "sg:tags":[
        "department"
    ],
    "wof:name":"Clearfield Fire Co 1",
    "wof:placetype":"venue"
},
  "geometry": {"coordinates":[-78.439723,41.020839],"type":"Point"}
}