{
  "type": "Feature",
  "properties": {
    "iso:country":"US",
    "sg:address":"734 Kohn St",
    "sg:city":"Norristown",
    "sg:classifiers":[
        {
            "category":"Professional",
            "type":"Services"
        }
    ],
    "sg:phone":"+1   ",
    "sg:postcode":"19401",
    "sg:province":"PA",
    "wof:name":"Lim Sim Boy",
    "wof:placetype":"venue"
},
  "geometry": {"coordinates":[-75.348118,40.123413],"type":"Point"}
}