{
  "type": "Feature",
  "properties": {
    "iso:country":"US",
    "sg:address":"413 S Michael St",
    "sg:city":"St Marys",
    "sg:classifiers":[
        {
            "category":"Banks & Credit Unions",
            "subcategory":"Bank",
            "type":"Services"
        }
    ],
    "sg:phone":"+1 814 834 9518",
    "sg:postcode":"15857",
    "sg:province":"PA",
    "sg:tags":[
        "federally",
        "chartered"
    ],
    "sg:website":"www.smafcu.com",
    "wof:name":"St Marys Area Federal Cu",
    "wof:placetype":"venue"
},
  "geometry": {"coordinates":[-78.55645800000001,41.426037],"type":"Point"}
}