{
  "type": "Feature",
  "properties": {
    "addr:full":"13 Chisel Creek Dr Landenberg PA 19350",
    "addr:housenumber":"13",
    "addr:postcode":"19350",
    "addr:street":"Chisel Creek Dr",
    "iso:country":"US",
    "sg:address":"13 Chisel Creek Dr",
    "sg:city":"Landenberg",
    "sg:classifiers":[
        {
            "category":"Sports & Exercise",
            "subcategory":"Golf",
            "type":"Entertainment"
        }
    ],
    "sg:phone":"+1 610 255 3961",
    "sg:postcode":"19350",
    "sg:province":"PA",
    "sg:tags":[
        "course",
        "public"
    ],
    "sg:website":"www.chiselcreekgolf.com",
    "wof:name":"Chisel Creek Golf Club LLC",
    "wof:placetype":"venue"
},
  "geometry": {"coordinates":[-75.817499,39.73987],"type":"Point"}
}