{
  "type": "Feature",
  "properties": {
    "iso:country":"US",
    "sg:address":"416 9th St",
    "sg:city":"Huntingdon",
    "sg:classifiers":[
        {
            "category":"Food & Beverages",
            "subcategory":"Groceries & Convenience Stores",
            "type":"Retail Goods"
        }
    ],
    "sg:phone":"+1 814 641 7241",
    "sg:postcode":"16652",
    "sg:province":"PA",
    "wof:name":"Ninth Street Market & Deli",
    "wof:placetype":"venue"
},
  "geometry": {"coordinates":[-78.015413,40.488669],"type":"Point"}
}