{
  "type": "Feature",
  "properties": {
    "iso:country":"US",
    "sg:address":"606 N Chester Rd",
    "sg:city":"West Chester",
    "sg:classifiers":[
        {
            "category":"Health Services",
            "subcategory":"Doctor",
            "type":"Services"
        }
    ],
    "sg:phone":"+1 610 431 3032",
    "sg:postcode":"19380",
    "sg:province":"PA",
    "sg:tags":[
        "physician",
        "medical",
        "surgeon"
    ],
    "wof:name":"Alan M Gardner MD",
    "wof:placetype":"venue"
},
  "geometry": {"coordinates":[-75.539362,39.980911],"type":"Point"}
}