{
  "type": "Feature",
  "properties": {
    "iso:country":"US",
    "sg:address":"401 E Murphy Ave",
    "sg:city":"Connellsville",
    "sg:classifiers":[
        {
            "category":"Health Services",
            "subcategory":"Doctor",
            "type":"Services"
        }
    ],
    "sg:phone":"+1 724 628 5221",
    "sg:postcode":"15425",
    "sg:province":"PA",
    "sg:tags":[
        "psychiatry",
        "physician",
        "surgeon",
        "surgeons"
    ],
    "wof:name":"Robert G Bowman Md",
    "wof:placetype":"venue"
},
  "geometry": {"coordinates":[-79.585968,40.023392],"type":"Point"}
}