{
  "type": "Feature",
  "properties": {
    "iso:country":"US",
    "sg:address":"8634 Germantown Ave",
    "sg:city":"Philadelphia",
    "sg:classifiers":[
        {
            "category":"Bars & Pubs",
            "type":"Food & Drink"
        },
        {
            "category":"Restaurant",
            "type":"Food & Drink"
        }
    ],
    "sg:phone":"+1 215 247 9736",
    "sg:postcode":"19118",
    "sg:province":"PA",
    "sg:tags":[
        "grill",
        "brew",
        "tavern"
    ],
    "sg:website":"http://mcnallystavern.com",
    "wof:name":"Mc Nally's Tavern",
    "wof:placetype":"venue"
},
  "geometry": {"coordinates":[-75.208319,40.077084],"type":"Point"}
}