{
  "type": "Feature",
  "properties": {
    "iso:country":"US",
    "sg:address":"4 E Athens Ave",
    "sg:city":"Ardmore",
    "sg:classifiers":[
        {
            "category":"Manufacturing",
            "subcategory":"Furniture",
            "type":"Manufacturing & Wholesale Goods"
        }
    ],
    "sg:phone":"+1   ",
    "sg:postcode":"19003",
    "sg:province":"PA",
    "sg:tags":[
        "repair",
        "household",
        "mfg"
    ],
    "wof:name":"Rigo Julius",
    "wof:placetype":"venue"
},
  "geometry": {"coordinates":[-75.29278100000001,40.006531],"type":"Point"}
}