{
  "type": "Feature",
  "properties": {
    "iso:country":"US",
    "sg:address":"615 W Highland Ave",
    "sg:city":"Ebensburg",
    "sg:classifiers":[
        {
            "category":"Professional",
            "subcategory":"Engineering",
            "type":"Services"
        }
    ],
    "sg:phone":"+1 814 472 7700",
    "sg:postcode":"15931",
    "sg:province":"PA",
    "sg:tags":[
        "engineer"
    ],
    "sg:website":"www.lrkimball.com",
    "wof:name":"L Robert Kimball & Assoc",
    "wof:placetype":"venue"
},
  "geometry": {"coordinates":[-78.73089899999999,40.490016],"type":"Point"}
}