{
  "type": "Feature",
  "properties": {
    "addr:full":"5070 Parkside Ave Unit 75 Philadelphia PA 19131",
    "addr:housenumber":"5070;75",
    "addr:postcode":"19131",
    "addr:street":"Parkside Ave Unit",
    "iso:country":"US",
    "sg:address":"5070 Parkside Ave Unit 75",
    "sg:city":"Philadelphia",
    "sg:classifiers":[
        {
            "category":"Education",
            "subcategory":"School",
            "type":"Public Place"
        }
    ],
    "sg:phone":"+1 215 879 8182",
    "sg:postcode":"19131",
    "sg:province":"PA",
    "sg:tags":[
        "high",
        "middle",
        "elementary"
    ],
    "sg:website":"www.discoverycharterschool.com",
    "wof:name":"Discovery Charter School",
    "wof:placetype":"venue"
},
  "geometry": {"coordinates":[-75.22089800000001,39.980393],"type":"Point"}
}