{
  "type": "Feature",
  "properties": {
    "iso:country":"US",
    "sg:address":"1604 Shepard Dr",
    "sg:city":"Ambler",
    "sg:classifiers":[
        {
            "category":"Professional",
            "type":"Services"
        }
    ],
    "sg:phone":"+1   ",
    "sg:postcode":"19002",
    "sg:province":"PA",
    "wof:name":"Box 37 Inc",
    "wof:placetype":"venue"
},
  "geometry": {"coordinates":[-75.180939,40.167639],"type":"Point"}
}