{
  "type": "Feature",
  "properties": {
    "iso:country":"US",
    "sg:address":"2987 Babcock Blvd",
    "sg:city":"Pittsburgh",
    "sg:classifiers":[
        {
            "category":"Manufacturing",
            "subcategory":"Retail Goods",
            "type":"Manufacturing & Wholesale Goods"
        }
    ],
    "sg:phone":"+1   ",
    "sg:postcode":"15237",
    "sg:province":"PA",
    "sg:tags":[
        "coated",
        "for",
        "mfg",
        "computer",
        "film",
        "ribbon"
    ],
    "wof:name":"Imtech",
    "wof:placetype":"venue"
},
  "geometry": {"coordinates":[-80.006863,40.514372],"type":"Point"}
}