{
  "type": "Feature",
  "properties": {
    "iso:country":"US",
    "sg:address":"27 N Water Ave",
    "sg:city":"Sharon",
    "sg:classifiers":[
        {
            "category":"Shopping",
            "subcategory":"Clothing, Apparel, & Fashions",
            "type":"Retail Goods"
        }
    ],
    "sg:phone":"+1 724 347 0333",
    "sg:postcode":"16146",
    "sg:province":"PA",
    "sg:tags":[
        "tailor"
    ],
    "wof:name":"Tuxedos & More, Inc.",
    "wof:placetype":"venue"
},
  "geometry": {"coordinates":[-80.51123800000001,41.233376],"type":"Point"}
}