{
  "type": "Feature",
  "properties": {
    "iso:country":"US",
    "sg:address":"3420 4th Ave",
    "sg:city":"Beaver Falls",
    "sg:classifiers":[
        {
            "category":"Personal",
            "subcategory":"Tanning Parlor",
            "type":"Services"
        }
    ],
    "sg:phone":"+1 724 846 6100",
    "sg:postcode":"15010",
    "sg:province":"PA",
    "sg:tags":[
        "salon"
    ],
    "wof:name":"Thumm's Nail & Tanning",
    "wof:placetype":"venue"
},
  "geometry": {"coordinates":[-80.324056,40.775999],"type":"Point"}
}