{
  "type": "Feature",
  "properties": {
    "iso:country":"US",
    "sg:address":"154 W Main St",
    "sg:city":"Kutztown",
    "sg:classifiers":[
        {
            "category":"Professional",
            "subcategory":"Accounting & Tax Preparation",
            "type":"Services"
        }
    ],
    "sg:phone":"+1 610 683 6542",
    "sg:postcode":"19530",
    "sg:province":"PA",
    "sg:tags":[
        "return",
        "filing"
    ],
    "wof:name":"H & R Block Tax Svc",
    "wof:placetype":"venue"
},
  "geometry": {"coordinates":[-75.776719,40.518],"type":"Point"}
}