{
  "type": "Feature",
  "properties": {
    "iso:country":"US",
    "sg:address":"788 Avalon Rd",
    "sg:city":"Altoona",
    "sg:classifiers":[
        {
            "category":"Home & Garden",
            "subcategory":"Carpets & Floor Coverings",
            "type":"Retail Goods"
        }
    ],
    "sg:phone":"+1 814 944 6096",
    "sg:postcode":"16601",
    "sg:province":"PA",
    "sg:tags":[
        "installation"
    ],
    "wof:name":"Weston's Floor Covering",
    "wof:placetype":"venue"
},
  "geometry": {"coordinates":[-78.444462,40.54134],"type":"Point"}
}