{
  "type": "Feature",
  "properties": {
    "iso:country":"US",
    "sg:address":"645 Clark Ave",
    "sg:city":"King Of Prussia",
    "sg:classifiers":[
        {
            "category":"Health Services",
            "subcategory":"Chiropractor",
            "type":"Services"
        }
    ],
    "sg:phone":"+1 610 265 2522",
    "sg:postcode":"19406",
    "sg:province":"PA",
    "wof:name":"Chiropractic & Holistic Welnes",
    "wof:placetype":"venue"
},
  "geometry": {"coordinates":[-75.40231,40.097127],"type":"Point"}
}