{
  "type": "Feature",
  "properties": {
    "iso:country":"US",
    "sg:address":"1248 W Hamilton St",
    "sg:city":"Allentown",
    "sg:classifiers":[
        {
            "category":"Professional",
            "subcategory":"Lawyer & Legal Services",
            "type":"Services"
        }
    ],
    "sg:phone":"+1 610 432 2300",
    "sg:postcode":"18102",
    "sg:province":"PA",
    "wof:name":"Blanco Theresa Atty At Law",
    "wof:placetype":"venue"
},
  "geometry": {"coordinates":[-75.48303900000001,40.598939],"type":"Point"}
}