{
  "type": "Feature",
  "properties": {
    "iso:country":"US",
    "sg:address":"1444 Linden St",
    "sg:city":"Bethlehem",
    "sg:classifiers":[
        {
            "category":"Food & Beverages",
            "subcategory":"Bakery",
            "type":"Retail Goods"
        },
        {
            "category":"Wholesale",
            "subcategory":"Groceries",
            "type":"Manufacturing & Wholesale Goods"
        }
    ],
    "sg:phone":"+1 610 867 9959",
    "sg:postcode":"18018",
    "sg:province":"PA",
    "sg:tags":[
        "cooky",
        "crackers-wholesale",
        "bakers-wholesale",
        "manufacturer"
    ],
    "wof:name":"Uncle Ernie's Cookie Co Inc",
    "wof:placetype":"venue"
},
  "geometry": {"coordinates":[-75.369096,40.633439],"type":"Point"}
}