{
  "type": "Feature",
  "properties": {
    "addr:full":"928 Jaymor Rd Southampton PA 18966",
    "addr:housenumber":"928",
    "addr:postcode":"18966",
    "addr:street":"Jaymor Rd",
    "iso:country":"US",
    "sg:address":"928 Jaymor Rd",
    "sg:city":"Southampton",
    "sg:classifiers":[
        {
            "category":"Shopping",
            "subcategory":"Music",
            "type":"Retail Goods"
        }
    ],
    "sg:phone":"+1   ",
    "sg:postcode":"18966",
    "sg:province":"PA",
    "sg:tags":[
        "store"
    ],
    "wof:name":"West Coast Video",
    "wof:placetype":"venue"
},
  "geometry": {"coordinates":[-75.047616,40.164211],"type":"Point"}
}