{
  "type": "Feature",
  "properties": {
    "iso:country":"US",
    "sg:address":"400 Swatara Rd",
    "sg:city":"Frackville",
    "sg:phone":"+1 570 462 4483",
    "sg:postcode":"17976",
    "sg:province":"PA",
    "sg:tags":[
        "oil"
    ],
    "wof:name":"Kosar Coal & Oil",
    "wof:placetype":"venue"
},
  "geometry": {"coordinates":[-76.209419,40.831178],"type":"Point"}
}