{
  "type": "Feature",
  "properties": {
    "iso:country":"US",
    "sg:address":"1249 Troupe Rd",
    "sg:city":"Harborcreek",
    "sg:classifiers":[
        {
            "category":"Social Services",
            "subcategory":"Child Care",
            "type":"Services"
        }
    ],
    "sg:phone":"+1   ",
    "sg:postcode":"16421",
    "sg:province":"PA",
    "sg:tags":[
        "membership",
        "day"
    ],
    "wof:name":"Bob Learn Enterprises Inc",
    "wof:placetype":"venue"
},
  "geometry": {"coordinates":[-79.96833100000001,42.170123],"type":"Point"}
}