{
  "type": "Feature",
  "properties": {
    "iso:country":"US",
    "sg:address":"726 Fairview Ave",
    "sg:city":"Irwin",
    "sg:classifiers":[
        {
            "category":"Building & Trades",
            "subcategory":"Construction",
            "type":"Services"
        }
    ],
    "sg:phone":"+1 724 864 2222",
    "sg:postcode":"15642",
    "sg:province":"PA",
    "sg:tags":[
        "excavating",
        "contractor"
    ],
    "wof:name":"Lou Botti Construction",
    "wof:placetype":"venue"
},
  "geometry": {"coordinates":[-79.70083,40.329579],"type":"Point"}
}