{
  "type": "Feature",
  "properties": {
    "iso:country":"US",
    "sg:address":"229 Bustleton Pike",
    "sg:city":"Feasterville Trevose",
    "sg:classifiers":[
        {
            "category":"Professional",
            "subcategory":"Lawyer & Legal Services",
            "type":"Services"
        }
    ],
    "sg:phone":"+1   ",
    "sg:postcode":"19053",
    "sg:province":"PA",
    "wof:name":"Michael B Lerner Esq",
    "wof:placetype":"venue"
},
  "geometry": {"coordinates":[-75.00603099999999,40.141486],"type":"Point"}
}