{
  "type": "Feature",
  "properties": {
    "iso:country":"US",
    "sg:address":"237 Northampton St",
    "sg:city":"Easton",
    "sg:classifiers":[
        {
            "category":"Restaurant",
            "type":"Food & Drink"
        }
    ],
    "sg:phone":"+1 610 250 0198",
    "sg:postcode":"18042",
    "sg:province":"PA",
    "wof:name":"Sogo",
    "wof:placetype":"venue"
},
  "geometry": {"coordinates":[-75.208061,40.69125],"type":"Point"}
}