{
  "type": "Feature",
  "properties": {
    "iso:country":"US",
    "sg:address":"3501 6th Ave",
    "sg:city":"Altoona",
    "sg:classifiers":[
        {
            "category":"Real Estate",
            "subcategory":"Real Estate Agent",
            "type":"Services"
        }
    ],
    "sg:phone":"+1   ",
    "sg:postcode":"16602",
    "sg:province":"PA",
    "wof:name":"Hudson & Assoc Appraisal Svcs",
    "wof:placetype":"venue"
},
  "geometry": {"coordinates":[-78.413546,40.490131],"type":"Point"}
}