{
  "type": "Feature",
  "properties": {
    "addr:full":"1290 W Portersville Rd Portersville PA 16051",
    "addr:housenumber":"1290",
    "addr:postcode":"16051",
    "addr:street":"W Portersville Rd",
    "iso:country":"US",
    "sg:address":"1290 W Portersville Rd",
    "sg:city":"Portersville",
    "sg:classifiers":[
        {
            "category":"Farming",
            "subcategory":"Farm",
            "type":"Manufacturing & Wholesale Goods"
        }
    ],
    "sg:phone":"+1   ",
    "sg:postcode":"16051",
    "sg:province":"PA",
    "sg:tags":[
        "crop",
        "general"
    ],
    "wof:name":"Aiken Farms",
    "wof:placetype":"venue"
},
  "geometry": {"coordinates":[-80.159981,40.920401],"type":"Point"}
}