{
  "type": "Feature",
  "properties": {
    "addr:full":"2213 Shenango Valley Fwy Hermitage PA 16148",
    "addr:housenumber":"2213",
    "addr:postcode":"16148",
    "addr:street":"Shenango Valley Fwy",
    "iso:country":"US",
    "sg:address":"2213 Shenango Valley Fwy",
    "sg:city":"Hermitage",
    "sg:classifiers":[
        {
            "category":"Government",
            "subcategory":"Court House",
            "type":"Public Place"
        }
    ],
    "sg:phone":"+1 724 347 7037",
    "sg:postcode":"16148",
    "sg:province":"PA",
    "sg:tags":[
        "legislator"
    ],
    "sg:website":"http://www.pa4life.org",
    "wof:name":"House Of Representatives, Pennsylvania",
    "wof:placetype":"venue"
},
  "geometry": {"coordinates":[-80.467687,41.226913],"type":"Point"}
}