{
  "type": "Feature",
  "properties": {
    "iso:country":"US",
    "sg:address":"75 Logan St",
    "sg:city":"Lewistown",
    "sg:classifiers":[
        {
            "category":"Retail",
            "subcategory":"Funeral Services",
            "type":"Services"
        }
    ],
    "sg:phone":"+1 717 248 7823",
    "sg:postcode":"17044",
    "sg:province":"PA",
    "sg:tags":[
        "director",
        "home"
    ],
    "wof:name":"Hoenstine Funeral Home Inc",
    "wof:placetype":"venue"
},
  "geometry": {"coordinates":[-77.56968999999999,40.600918],"type":"Point"}
}