{
  "type": "Feature",
  "properties": {
    "iso:country":"US",
    "sg:address":"2208 Ben Franklin Dr",
    "sg:city":"Pittsburgh",
    "sg:classifiers":[
        {
            "category":"Shopping",
            "subcategory":"Hobbies, Toys, & Games",
            "type":"Retail Goods"
        }
    ],
    "sg:phone":"+1 412 366 4541",
    "sg:postcode":"15237",
    "sg:province":"PA",
    "sg:tags":[
        "craft",
        "supply"
    ],
    "wof:name":"Your Memory Page",
    "wof:placetype":"venue"
},
  "geometry": {"coordinates":[-80.068377,40.569097],"type":"Point"}
}