{
  "type": "Feature",
  "properties": {
    "iso:country":"US",
    "sg:address":"1441 Baltimore St",
    "sg:city":"Hanover",
    "sg:classifiers":[
        {
            "category":"Health Services",
            "subcategory":"Nursing And Care Facility",
            "type":"Services"
        }
    ],
    "sg:phone":"+1 717 633 7001",
    "sg:postcode":"17331",
    "sg:province":"PA",
    "sg:tags":[
        "residential",
        "retirement",
        "intermediate",
        "community",
        "home"
    ],
    "wof:name":"Wonder's Personal Care",
    "wof:placetype":"venue"
},
  "geometry": {"coordinates":[-76.96059200000001,39.770854],"type":"Point"}
}