{
  "type": "Feature",
  "properties": {
    "iso:country":"US",
    "sg:address":"308 Woodbine Ave",
    "sg:city":"Narberth",
    "sg:classifiers":[
        {
            "category":"Building & Trades",
            "subcategory":"Electrical",
            "type":"Services"
        }
    ],
    "sg:phone":"+1 610 667 5299",
    "sg:postcode":"19072",
    "sg:province":"PA",
    "sg:tags":[
        "electric",
        "industrial",
        "contractors-commercial",
        "contractor"
    ],
    "wof:name":"Chelsvig Electric",
    "wof:placetype":"venue"
},
  "geometry": {"coordinates":[-75.25862100000001,40.009888],"type":"Point"}
}