{
  "type": "Feature",
  "properties": {
    "iso:country":"US",
    "sg:address":"10431 Perry Hwy",
    "sg:city":"Wexford",
    "sg:classifiers":[
        {
            "category":"Insurance",
            "subcategory":"Insurance Agent",
            "type":"Services"
        }
    ],
    "sg:phone":"+1 724 940 5588",
    "sg:postcode":"15090",
    "sg:province":"PA",
    "wof:name":"Services Primerica Financial",
    "wof:placetype":"venue"
},
  "geometry": {"coordinates":[-80.054852,40.61409],"type":"Point"}
}