{
  "type": "Feature",
  "properties": {
    "iso:country":"US",
    "sg:address":"601 Cedar Ave",
    "sg:city":"Scranton",
    "sg:classifiers":[
        {
            "category":"Retail",
            "subcategory":"Repair Shop",
            "type":"Services"
        }
    ],
    "sg:phone":"+1 570 343 1121",
    "sg:postcode":"18505",
    "sg:province":"PA",
    "sg:tags":[
        "cleaners",
        "parts",
        "vacuum"
    ],
    "wof:name":"Vac-Way Appliance & Svc",
    "wof:placetype":"venue"
},
  "geometry": {"coordinates":[-75.66779699999999,41.399501],"type":"Point"}
}