{
  "type": "Feature",
  "properties": {
    "addr:full":"2252 Butler St Easton PA 18042",
    "addr:housenumber":"2252",
    "addr:postcode":"18042",
    "addr:street":"Butler St",
    "iso:country":"US",
    "sg:address":"2252 Butler St",
    "sg:city":"Easton",
    "sg:classifiers":[
        {
            "category":"Home & Garden",
            "subcategory":"Hardware",
            "type":"Retail Goods"
        }
    ],
    "sg:phone":"+1   ",
    "sg:postcode":"18042",
    "sg:province":"PA",
    "wof:name":"True Value",
    "wof:placetype":"venue"
},
  "geometry": {"coordinates":[-75.243835,40.683508],"type":"Point"}
}