{
  "type": "Feature",
  "properties": {
    "iso:country":"US",
    "sg:address":"526 Ohio Ave",
    "sg:city":"Midland",
    "sg:classifiers":[
        {
            "category":"Insurance",
            "subcategory":"Insurance Agent",
            "type":"Services"
        }
    ],
    "sg:phone":"+1   ",
    "sg:postcode":"15059",
    "sg:province":"PA",
    "wof:name":"Mutual of New York Inc",
    "wof:placetype":"venue"
},
  "geometry": {"coordinates":[-80.454093,40.641146],"type":"Point"}
}