{
  "type": "Feature",
  "properties": {
    "addr:full":"147 Merion Ln Reading PA 19607",
    "addr:housenumber":"147",
    "addr:postcode":"19607",
    "addr:street":"Merion Ln",
    "iso:country":"US",
    "sg:address":"147 Merion Ln",
    "sg:city":"Reading",
    "sg:classifiers":[
        {
            "category":"Banks & Credit Unions",
            "subcategory":"Bank",
            "type":"Services"
        }
    ],
    "sg:phone":"+1 610 775 4720",
    "sg:postcode":"19607",
    "sg:province":"PA",
    "sg:tags":[
        "financing"
    ],
    "wof:name":"Atlantis Funding Concepts",
    "wof:placetype":"venue"
},
  "geometry": {"coordinates":[-75.91360400000001,40.279877],"type":"Point"}
}