{
  "type": "Feature",
  "properties": {
    "addr:city":"Bethlehem",
    "addr:full":"556 Main St #2 Bethlehem, Pa 18018",
    "addr:house_number":"556",
    "addr:housenumber":"556",
    "addr:phone":"+1 484-821-0809",
    "addr:postcode":"18018",
    "addr:road":"Main St",
    "addr:state":"PA",
    "addr:street":"Main St",
    "addr:unit":"#2",
    "iso:country":"US",
    "sg:address":"556 Main St",
    "sg:city":"Bethlehem",
    "sg:classifiers":[
        {
            "category":"Museum",
            "type":"Entertainment"
        },
        {
            "category":"Organizations",
            "subcategory":"Membership Organization",
            "type":"Services"
        }
    ],
    "sg:phone":"+1 610 866 1758",
    "sg:postcode":"18018",
    "sg:province":"PA",
    "sg:tags":[
        "operator",
        "commercial",
        "historical"
    ],
    "wof:airports":[
        102529131
    ],
    "wof:name":"Sun Inn Preservation Association",
    "wof:placetype":"venue"
},
  "geometry": {"coordinates":[-75.38185,40.62167],"type":"Point"}
}