{
  "type": "Feature",
  "properties": {
    "iso:country":"US",
    "sg:address":"556 Main St",
    "sg:city":"Bethlehem",
    "sg:classifiers":[
        {
            "category":"Museum",
            "type":"Entertainment"
        },
        {
            "category":"Organizations",
            "subcategory":"Membership Organization",
            "type":"Services"
        }
    ],
    "sg:phone":"+1 610 866 1758",
    "sg:postcode":"18018",
    "sg:province":"PA",
    "sg:tags":[
        "operator",
        "commercial",
        "historical"
    ],
    "wof:name":"Sun Inn Preservation Association",
    "wof:placetype":"venue"
},
  "geometry": {"coordinates":[-75.38200399999999,40.621601],"type":"Point"}
}