{
  "type": "Feature",
  "properties": {
    "iso:country":"US",
    "sg:address":"320 Brownsville Rd",
    "sg:city":"Pittsburgh",
    "sg:classifiers":[
        {
            "category":"Social Services",
            "type":"Services"
        }
    ],
    "sg:phone":"+1 412 381 6925",
    "sg:postcode":"15210",
    "sg:province":"PA",
    "sg:tags":[
        "organization",
        "welfare"
    ],
    "wof:name":"Nazareth Housing Svc",
    "wof:placetype":"venue"
},
  "geometry": {"coordinates":[-79.988727,40.413522],"type":"Point"}
}