{
  "type": "Feature",
  "properties": {
    "iso:country":"US",
    "sg:address":"2341 N 7th St",
    "sg:city":"Philadelphia",
    "sg:classifiers":[
        {
            "category":"Manufacturing",
            "subcategory":"Rubber & Plastics",
            "type":"Manufacturing & Wholesale Goods"
        }
    ],
    "sg:phone":"+1   ",
    "sg:postcode":"19133",
    "sg:province":"PA",
    "sg:tags":[
        "unsupported",
        "mfg"
    ],
    "wof:name":"Floracraft Corp",
    "wof:placetype":"venue"
},
  "geometry": {"coordinates":[-75.144854,39.98736],"type":"Point"}
}