{
  "type": "Feature",
  "properties": {
    "iso:country":"US",
    "sg:address":"355 N Main St",
    "sg:city":"Jersey Shore",
    "sg:classifiers":[
        {
            "category":"Retail",
            "subcategory":"Auto Repair",
            "type":"Services"
        }
    ],
    "sg:phone":"+1 570 398 7577",
    "sg:postcode":"17740",
    "sg:province":"PA",
    "sg:tags":[
        "repairing",
        "automobile",
        "general"
    ],
    "wof:name":"Stout's Pro Auto",
    "wof:placetype":"venue"
},
  "geometry": {"coordinates":[-77.250259,41.209731],"type":"Point"}
}