{
  "type": "Feature",
  "properties": {
    "addr:full":"220 Woodward Ave Lock Haven PA 17745",
    "addr:housenumber":"220",
    "addr:postcode":"17745",
    "addr:street":"Woodward Ave",
    "iso:country":"US",
    "sg:address":"220 Woodward Ave",
    "sg:city":"Lock Haven",
    "sg:classifiers":[
        {
            "category":"Banks & Credit Unions",
            "subcategory":"Bank",
            "type":"Services"
        }
    ],
    "sg:phone":"+1 570 748 5558",
    "sg:postcode":"17745",
    "sg:province":"PA",
    "sg:tags":[
        "loan",
        "real estate"
    ],
    "wof:name":"Mc Ginness Mortgage",
    "wof:placetype":"venue"
},
  "geometry": {"coordinates":[-77.423782,41.143649],"type":"Point"}
}