{
  "type": "Feature",
  "properties": {
    "iso:country":"US",
    "sg:address":"100 Marland Dr",
    "sg:city":"Mars",
    "sg:classifiers":[
        {
            "category":"Freight",
            "type":"Transportation"
        }
    ],
    "sg:phone":"+1   ",
    "sg:postcode":"16046",
    "sg:province":"PA",
    "sg:tags":[
        "operator",
        "trucking"
    ],
    "wof:name":"USFreightways",
    "wof:placetype":"venue"
},
  "geometry": {"coordinates":[-80.001296,40.688152],"type":"Point"}
}