{
  "type": "Feature",
  "properties": {
    "iso:country":"US",
    "sg:address":"442 Renfrew Ave",
    "sg:city":"Ambler",
    "sg:classifiers":[
        {
            "category":"Professional",
            "subcategory":"Management & Consulting",
            "type":"Services"
        }
    ],
    "sg:phone":"+1   ",
    "sg:postcode":"19002",
    "sg:province":"PA",
    "sg:tags":[
        "business"
    ],
    "wof:name":"Shearspire Inc",
    "wof:placetype":"venue"
},
  "geometry": {"coordinates":[-75.21467800000001,40.149877],"type":"Point"}
}