{
  "type": "Feature",
  "properties": {
    "iso:country":"US",
    "sg:address":"5428 Turner Rd",
    "sg:city":"Gibsonia",
    "sg:classifiers":[
        {
            "category":"Building & Trades",
            "subcategory":"Construction",
            "type":"Services"
        }
    ],
    "sg:phone":"+1   ",
    "sg:postcode":"15044",
    "sg:province":"PA",
    "sg:tags":[
        "housing"
    ],
    "wof:name":"Cityscape Construction Co Inc",
    "wof:placetype":"venue"
},
  "geometry": {"coordinates":[-79.92953199999999,40.618961],"type":"Point"}
}