{
  "type": "Feature",
  "properties": {
    "iso:country":"US",
    "sg:address":"800 Wood St",
    "sg:city":"Harrisburg",
    "sg:classifiers":[
        {
            "category":"Retail",
            "subcategory":"Repair Shop",
            "type":"Services"
        }
    ],
    "sg:phone":"+1   ",
    "sg:postcode":"17109",
    "sg:province":"PA",
    "sg:tags":[
        "sporting"
    ],
    "wof:name":"Dennis R Pletz Enterprises",
    "wof:placetype":"venue"
},
  "geometry": {"coordinates":[-76.834788,40.279212],"type":"Point"}
}