{
  "type": "Feature",
  "properties": {
    "iso:country":"US",
    "sg:address":"301 E Main St",
    "sg:city":"Palmyra",
    "sg:classifiers":[
        {
            "category":"Travel",
            "subcategory":"Bed & Breakfast",
            "type":"Entertainment"
        }
    ],
    "sg:phone":"+1 717 838 7400",
    "sg:postcode":"17078",
    "sg:province":"PA",
    "sg:tags":[
        "house"
    ],
    "wof:name":"Main Street Inn",
    "wof:placetype":"venue"
},
  "geometry": {"coordinates":[-76.59099399999999,40.309891],"type":"Point"}
}