{
  "type": "Feature",
  "properties": {
    "iso:country":"US",
    "sg:address":"1137 Moosic St",
    "sg:city":"Scranton",
    "sg:classifiers":[
        {
            "category":"Wholesale",
            "subcategory":"Medical Equipment & Supplies",
            "type":"Manufacturing & Wholesale Goods"
        }
    ],
    "sg:phone":"+1 570 346 2511",
    "sg:postcode":"18505",
    "sg:province":"PA",
    "wof:name":"East Orient Trading Co",
    "wof:placetype":"venue"
},
  "geometry": {"coordinates":[-75.64835100000001,41.396225],"type":"Point"}
}