{
  "type": "Feature",
  "properties": {
    "iso:country":"US",
    "sg:address":"345 Pierce St",
    "sg:city":"Kingston",
    "sg:classifiers":[
        {
            "category":"Professional",
            "subcategory":"Lawyer & Legal Services",
            "type":"Services"
        }
    ],
    "sg:phone":"+1   ",
    "sg:postcode":"18704",
    "sg:province":"PA",
    "wof:name":"Sherwood Grabiec",
    "wof:placetype":"venue"
},
  "geometry": {"coordinates":[-75.88658700000001,41.260791],"type":"Point"}
}