{
  "type": "Feature",
  "properties": {
    "addr:full":"1103 Main St Warrington PA 18976",
    "addr:housenumber":"1103",
    "addr:postcode":"18976",
    "addr:street":"Main St",
    "iso:country":"US",
    "sg:address":"1103 Main St",
    "sg:city":"Warrington",
    "sg:classifiers":[
        {
            "category":"Restaurant",
            "type":"Food & Drink"
        }
    ],
    "sg:menulink":"http://www.allmenus.com/pa/warrington/292126-roma-pizza--italian-eatery/menu/",
    "sg:phone":"+1 215 343 5599",
    "sg:postcode":"18976",
    "sg:province":"PA",
    "sg:tags":[
        "pizza"
    ],
    "wof:name":"Roma Pizza & Italian Eatery",
    "wof:placetype":"venue"
},
  "geometry": {"coordinates":[-75.13188599999999,40.229643],"type":"Point"}
}