{
  "type": "Feature",
  "properties": {
    "iso:country":"US",
    "sg:address":"305 Orchard Ave",
    "sg:city":"Ellwood City",
    "sg:classifiers":[
        {
            "category":"Health Services",
            "subcategory":"Clinic",
            "type":"Services"
        }
    ],
    "sg:phone":"+1   ",
    "sg:postcode":"16117",
    "sg:province":"PA",
    "wof:name":"Pro Health Services",
    "wof:placetype":"venue"
},
  "geometry": {"coordinates":[-80.282742,40.869117],"type":"Point"}
}