{
  "type": "Feature",
  "properties": {
    "iso:country":"US",
    "sg:address":"356 Ridgway Rd",
    "sg:city":"St Marys",
    "sg:classifiers":[
        {
            "category":"Shopping",
            "subcategory":"Used Merchandise",
            "type":"Retail Goods"
        }
    ],
    "sg:phone":"+1 814 834 6774",
    "sg:postcode":"15857",
    "sg:province":"PA",
    "sg:tags":[
        "antique"
    ],
    "wof:name":"Shadows Of The Past",
    "wof:placetype":"venue"
},
  "geometry": {"coordinates":[-78.639398,41.420828],"type":"Point"}
}