{
  "type": "Feature",
  "properties": {
    "addr:full":"3342 Carlisle Pike New Oxford PA 17350",
    "addr:housenumber":"3342",
    "addr:postcode":"17350",
    "addr:street":"Carlisle Pike",
    "iso:country":"US",
    "sg:address":"3342 Carlisle Pike",
    "sg:city":"New Oxford",
    "sg:classifiers":[
        {
            "category":"Home & Garden",
            "subcategory":"Garden Supply",
            "type":"Retail Goods"
        }
    ],
    "sg:phone":"+1 717 624 4802",
    "sg:postcode":"17350",
    "sg:province":"PA",
    "sg:tags":[
        "center"
    ],
    "wof:name":"Dellinger Horticulture",
    "wof:placetype":"venue"
},
  "geometry": {"coordinates":[-77.02962100000001,39.874527],"type":"Point"}
}