{
  "type": "Feature",
  "properties": {
    "iso:country":"US",
    "sg:address":"121 N Main St Ste 102",
    "sg:city":"Greensburg",
    "sg:classifiers":[
        {
            "category":"Professional",
            "subcategory":"Lawyer & Legal Services",
            "type":"Services"
        }
    ],
    "sg:phone":"+1 724 830 9700",
    "sg:postcode":"15601",
    "sg:province":"PA",
    "sg:tags":[
        "attorney",
        "practice"
    ],
    "wof:name":"Law Office Of Kevin Feigel",
    "wof:placetype":"venue"
},
  "geometry": {"coordinates":[-79.544756,40.303884],"type":"Point"}
}