{
  "type": "Feature",
  "properties": {
    "iso:country":"US",
    "sg:address":"1739 State Rte 654",
    "sg:city":"Williamsport",
    "sg:classifiers":[
        {
            "category":"Retail",
            "subcategory":"Auto Repair",
            "type":"Services"
        }
    ],
    "sg:phone":"+1 570 326 0496",
    "sg:postcode":"17702",
    "sg:province":"PA",
    "sg:tags":[
        "automobile",
        "inspection"
    ],
    "wof:name":"B & J Automotive",
    "wof:placetype":"venue"
},
  "geometry": {"coordinates":[-77.086174,41.216361],"type":"Point"}
}