{
  "type": "Feature",
  "properties": {
    "iso:country":"US",
    "sg:address":"123 Chestnut St",
    "sg:city":"Philadelphia",
    "sg:classifiers":[
        {
            "category":"Real Estate",
            "subcategory":"Real Estate Agent",
            "type":"Services"
        }
    ],
    "sg:phone":"+1 215 625 9253",
    "sg:postcode":"19106",
    "sg:province":"PA",
    "sg:tags":[
        "management",
        "property"
    ],
    "wof:name":"P & A Assocs",
    "wof:placetype":"venue"
},
  "geometry": {"coordinates":[-75.143303,39.948299],"type":"Point"}
}