{
  "type": "Feature",
  "properties": {
    "addr:full":"534 Centre Ave Reading PA 19601",
    "addr:housenumber":"534",
    "addr:postcode":"19601",
    "addr:street":"Centre Ave",
    "iso:country":"US",
    "sg:address":"534 Centre Ave",
    "sg:city":"Reading",
    "sg:classifiers":[
        {
            "category":"Social Services",
            "type":"Services"
        }
    ],
    "sg:phone":"+1   ",
    "sg:postcode":"19601",
    "sg:province":"PA",
    "wof:name":"Northwester Human Services",
    "wof:placetype":"venue"
},
  "geometry": {"coordinates":[-75.929059,40.344215],"type":"Point"}
}