{
  "type": "Feature",
  "properties": {
    "iso:country":"US",
    "sg:address":"2505 Trenton Rd",
    "sg:city":"Levittown",
    "sg:classifiers":[
        {
            "category":"Organizations",
            "subcategory":"Religious Organization",
            "type":"Services"
        }
    ],
    "sg:phone":"+1 215 945 6116",
    "sg:postcode":"19056",
    "sg:province":"PA",
    "sg:tags":[
        "monastery",
        "convent"
    ],
    "wof:name":"Queen Of The Universe Convent",
    "wof:placetype":"venue"
},
  "geometry": {"coordinates":[-74.87672499999999,40.167788],"type":"Point"}
}