{
  "type": "Feature",
  "properties": {
    "addr:full":"706 Monroe St Stroudsburg PA 18360",
    "addr:housenumber":"706",
    "addr:postcode":"18360",
    "addr:street":"Monroe St",
    "iso:country":"US",
    "sg:address":"706 Monroe St",
    "sg:city":"Stroudsburg",
    "sg:classifiers":[
        {
            "category":"Professional",
            "subcategory":"Research",
            "type":"Services"
        },
        {
            "category":"Government",
            "subcategory":"Office",
            "type":"Public Place"
        }
    ],
    "sg:phone":"+1 570 424 9932",
    "sg:postcode":"18360",
    "sg:province":"PA",
    "sg:tags":[
        "environmental",
        "ecological",
        "management"
    ],
    "wof:name":"Alternative Resources Inc",
    "wof:placetype":"venue"
},
  "geometry": {"coordinates":[-75.195263,40.98644],"type":"Point"}
}