{
  "type": "Feature",
  "properties": {
    "iso:country":"US",
    "sg:address":"536 S Oxford Valley Rd",
    "sg:city":"Fairless Hills",
    "sg:classifiers":[
        {
            "category":"Home & Garden",
            "subcategory":"Furniture",
            "type":"Retail Goods"
        }
    ],
    "sg:phone":"+1 215 547 7787",
    "sg:postcode":"19030",
    "sg:province":"PA",
    "wof:name":"Quality Furniture Outlet Inc",
    "wof:placetype":"venue"
},
  "geometry": {"coordinates":[-74.847837,40.167832],"type":"Point"}
}