{
  "type": "Feature",
  "properties": {
    "addr:full":"2219 S Broad St Philadelphia PA 19148",
    "addr:housenumber":"2219",
    "addr:postcode":"19148",
    "addr:street":"S Broad St",
    "iso:country":"US",
    "sg:address":"2219 S Broad St",
    "sg:city":"Philadelphia",
    "sg:classifiers":[
        {
            "category":"Community Center",
            "type":"Public Place"
        }
    ],
    "sg:phone":"+1 800 639 6773",
    "sg:postcode":"19148",
    "sg:province":"PA",
    "sg:tags":[
        "medical"
    ],
    "sg:website":"www.localstdtesting.com/15",
    "wof:name":"Philadelphia Local HIV / STD Testing",
    "wof:placetype":"venue"
},
  "geometry": {"coordinates":[-75.169695,39.922385],"type":"Point"}
}