{
  "type": "Feature",
  "properties": {
    "addr:full":"904 E Gowen Ave Philadelphia PA 19150",
    "addr:housenumber":"904",
    "addr:postcode":"19150",
    "addr:street":"E Gowen Ave",
    "iso:country":"US",
    "sg:address":"904 E Gowen Ave",
    "sg:city":"Philadelphia",
    "sg:classifiers":[
        {
            "category":"Organizations",
            "subcategory":"Religious Organization",
            "type":"Services"
        }
    ],
    "sg:phone":"+1 215 753 9333",
    "sg:postcode":"19150",
    "sg:province":"PA",
    "sg:tags":[
        "clergy"
    ],
    "wof:name":"James Moore",
    "wof:placetype":"venue"
},
  "geometry": {"coordinates":[-75.18325900000001,40.071872],"type":"Point"}
}