{
  "type": "Feature",
  "properties": {
    "iso:country":"US",
    "sg:address":"3445 N Sugan Rd",
    "sg:city":"New Hope",
    "sg:classifiers":[
        {
            "category":"Manufacturing",
            "subcategory":"Jewelry",
            "type":"Manufacturing & Wholesale Goods"
        }
    ],
    "sg:phone":"+1   ",
    "sg:postcode":"18938",
    "sg:province":"PA",
    "sg:tags":[
        "design"
    ],
    "wof:name":"Dakota Moon Designs",
    "wof:placetype":"venue"
},
  "geometry": {"coordinates":[-75.03093200000001,40.388507],"type":"Point"}
}