{
  "type": "Feature",
  "properties": {
    "addr:full":"324 S Saint Marys St St Marys PA 15857",
    "addr:housenumber":"324",
    "addr:postcode":"15857",
    "addr:street":"S;Marys St",
    "iso:country":"US",
    "sg:address":"324 S Saint Marys St",
    "sg:city":"St Marys",
    "sg:classifiers":[
        {
            "category":"Insurance",
            "subcategory":"Insurance Agent",
            "type":"Services"
        }
    ],
    "sg:phone":"+1 814 834 2897",
    "sg:postcode":"15857",
    "sg:province":"PA",
    "wof:name":"St Marys Insurance Inc",
    "wof:placetype":"venue"
},
  "geometry": {"coordinates":[-78.56112899999999,41.425024],"type":"Point"}
}