{
  "type": "Feature",
  "properties": {
    "iso:country":"US",
    "sg:address":"1401 Wilmington Rd",
    "sg:city":"New Castle",
    "sg:classifiers":[
        {
            "category":"Health Services",
            "subcategory":"Doctor",
            "type":"Services"
        }
    ],
    "sg:phone":"+1 724 658 7790",
    "sg:postcode":"16105",
    "sg:province":"PA",
    "sg:tags":[
        "physician",
        "surgeon"
    ],
    "wof:name":"Urologic Associates",
    "wof:placetype":"venue"
},
  "geometry": {"coordinates":[-80.352198,41.015315],"type":"Point"}
}