{
  "type": "Feature",
  "properties": {
    "addr:full":"715 Harvard Ave Swarthmore PA 19081",
    "addr:housenumber":"715",
    "addr:postcode":"19081",
    "addr:street":"Harvard Ave",
    "iso:country":"US",
    "sg:address":"715 Harvard Ave",
    "sg:city":"Swarthmore",
    "sg:classifiers":[
        {
            "category":"Professional",
            "subcategory":"Research",
            "type":"Services"
        }
    ],
    "sg:phone":"+1   ",
    "sg:postcode":"19081",
    "sg:province":"PA",
    "sg:tags":[
        "cell",
        "protein",
        "line",
        "biomedical",
        "for"
    ],
    "wof:name":"Impact Biologicals Inc",
    "wof:placetype":"venue"
},
  "geometry": {"coordinates":[-75.35394599999999,39.897111],"type":"Point"}
}