{
  "type": "Feature",
  "properties": {
    "iso:country":"US",
    "sg:address":"327 Dogwood Dr",
    "sg:city":"Alburtis",
    "sg:classifiers":[
        {
            "category":"Building & Trades",
            "subcategory":"Construction",
            "type":"Services"
        }
    ],
    "sg:phone":"+1 610 845 8581",
    "sg:postcode":"18011",
    "sg:province":"PA",
    "sg:tags":[
        "excavation",
        "contractor"
    ],
    "wof:name":"Hopko Excavating",
    "wof:placetype":"venue"
},
  "geometry": {"coordinates":[-75.644393,40.466989],"type":"Point"}
}