{
  "type": "Feature",
  "properties": {
    "addr:full":"51 Main St Lawrenceville PA 16901",
    "addr:housenumber":"51",
    "addr:postcode":"16901",
    "addr:street":"Main St",
    "iso:country":"US",
    "sg:address":"51 Main St",
    "sg:city":"Lawrenceville",
    "sg:classifiers":[
        {
            "category":"Banks & Credit Unions",
            "subcategory":"Bank",
            "type":"Services"
        }
    ],
    "sg:phone":"+1 570 827 2525",
    "sg:postcode":"16901",
    "sg:province":"PA",
    "sg:tags":[
        "loan",
        "real estate"
    ],
    "wof:name":"Territory Mortgage Co",
    "wof:placetype":"venue"
},
  "geometry": {"coordinates":[-77.3006,41.748381],"type":"Point"}
}