{
  "type": "Feature",
  "properties": {
    "iso:country":"US",
    "sg:address":"12967 Sipes Mill Rd",
    "sg:city":"Harrisonville",
    "sg:classifiers":[
        {
            "category":"Manufacturing",
            "subcategory":"Food",
            "type":"Manufacturing & Wholesale Goods"
        },
        {
            "category":"Farming",
            "subcategory":"Livestock Farm",
            "type":"Manufacturing & Wholesale Goods"
        },
        {
            "category":"Farming",
            "subcategory":"Farm",
            "type":"Manufacturing & Wholesale Goods"
        }
    ],
    "sg:phone":"+1 717 485 4458",
    "sg:postcode":"17228",
    "sg:province":"PA",
    "sg:tags":[
        "corn",
        "ranch",
        "product"
    ],
    "wof:name":"Franklin Reel Farms",
    "wof:placetype":"venue"
},
  "geometry": {"coordinates":[-78.111502,39.982777],"type":"Point"}
}