{
  "type": "Feature",
  "properties": {
    "addr:full":"50 Herring Aly Kutztown PA 19530",
    "addr:housenumber":"50",
    "addr:postcode":"19530",
    "addr:street":"Herring Aly",
    "iso:country":"US",
    "sg:address":"50 Herring Aly",
    "sg:city":"Kutztown",
    "sg:classifiers":[
        {
            "category":"Organizations",
            "subcategory":"Religious Organization",
            "type":"Services"
        }
    ],
    "sg:phone":"+1 610 683 7707",
    "sg:postcode":"19530",
    "sg:province":"PA",
    "sg:tags":[
        "church"
    ],
    "wof:name":"Adam 2 Ctr",
    "wof:placetype":"venue"
},
  "geometry": {"coordinates":[-75.77663,40.515567],"type":"Point"}
}