{
  "type": "Feature",
  "properties": {
    "iso:country":"US",
    "sg:address":"830 Montgomery Ave",
    "sg:city":"Narberth",
    "sg:classifiers":[
        {
            "category":"Real Estate",
            "subcategory":"Real Estate Operator",
            "type":"Services"
        }
    ],
    "sg:phone":"+1 610 667 1122",
    "sg:postcode":"19072",
    "sg:province":"PA",
    "sg:tags":[
        "condominium"
    ],
    "wof:name":"Benjamin Cobrin & Co",
    "wof:placetype":"venue"
},
  "geometry": {"coordinates":[-75.257757,40.010359],"type":"Point"}
}