{
  "type": "Feature",
  "properties": {
    "addr:full":"223 Plymouth St Pittsburgh PA 15211",
    "addr:housenumber":"223",
    "addr:postcode":"15211",
    "addr:street":"Plymouth St",
    "iso:country":"US",
    "sg:address":"223 Plymouth St",
    "sg:city":"Pittsburgh",
    "sg:classifiers":[
        {
            "category":"Organizations",
            "subcategory":"Religious Organization",
            "type":"Services"
        }
    ],
    "sg:phone":"+1   ",
    "sg:postcode":"15211",
    "sg:province":"PA",
    "wof:name":"Belle Bridge Wesleyan",
    "wof:placetype":"venue"
},
  "geometry": {"coordinates":[-80.021536,40.434031],"type":"Point"}
}