{
  "type": "Feature",
  "properties": {
    "iso:country":"US",
    "sg:address":"4006 Market St",
    "sg:city":"Philadelphia",
    "sg:classifiers":[
        {
            "category":"Restaurant",
            "type":"Food & Drink"
        }
    ],
    "sg:phone":"+1 215 382 8888",
    "sg:postcode":"19104",
    "sg:province":"PA",
    "wof:name":"Bo Sing",
    "wof:placetype":"venue"
},
  "geometry": {"coordinates":[-75.2024,39.957298],"type":"Point"}
}