{
  "type": "Feature",
  "properties": {
    "addr:full":"223 Ellery St Reading PA 19611",
    "addr:housenumber":"223",
    "addr:postcode":"19611",
    "addr:street":"Ellery St",
    "iso:country":"US",
    "sg:address":"223 Ellery St",
    "sg:city":"Reading",
    "sg:classifiers":[
        {
            "category":"Building & Trades",
            "subcategory":"Construction",
            "type":"Services"
        }
    ],
    "sg:phone":"+1 610 378 9515",
    "sg:postcode":"19611",
    "sg:province":"PA",
    "sg:tags":[
        "resurfacing",
        "laying",
        "refinishing",
        "floor"
    ],
    "wof:name":"Sebastian Hardwood Floors",
    "wof:placetype":"venue"
},
  "geometry": {"coordinates":[-75.93249,40.319093],"type":"Point"}
}