{
  "type": "Feature",
  "properties": {
    "addr:full":"325 Nicholson Rd Ridley Park PA 19078",
    "addr:housenumber":"325",
    "addr:postcode":"19078",
    "addr:street":"Nicholson Rd;Park",
    "iso:country":"US",
    "sg:address":"325 Nicholson Rd",
    "sg:city":"Ridley Park",
    "sg:classifiers":[
        {
            "category":"Shopping",
            "subcategory":"Catalog Store",
            "type":"Retail Goods"
        }
    ],
    "sg:phone":"+1   ",
    "sg:postcode":"19078",
    "sg:province":"PA",
    "sg:tags":[
        "mail",
        "group",
        "house"
    ],
    "wof:name":"Poolside Murder Mysteries",
    "wof:placetype":"venue"
},
  "geometry": {"coordinates":[-75.334446,39.874861],"type":"Point"}
}