{
  "type": "Feature",
  "properties": {
    "iso:country":"US",
    "sg:address":"44 N Christian St",
    "sg:city":"Lancaster",
    "sg:classifiers":[
        {
            "category":"Health Services",
            "subcategory":"Doctor",
            "type":"Services"
        },
        {
            "category":"Health Services",
            "subcategory":"Clinic",
            "type":"Services"
        }
    ],
    "sg:phone":"+1 717 393 9388",
    "sg:postcode":"17602",
    "sg:province":"PA",
    "sg:tags":[
        "physician",
        "psychologist",
        "surgeon",
        "mental"
    ],
    "wof:name":"Cannon Jean S Psy D",
    "wof:placetype":"venue"
},
  "geometry": {"coordinates":[-76.304852,40.039046],"type":"Point"}
}