{
  "type": "Feature",
  "properties": {
    "iso:country":"US",
    "sg:address":"57 E High St",
    "sg:city":"Elizabethtown",
    "sg:classifiers":[
        {
            "category":"Shopping",
            "type":"Retail Goods"
        }
    ],
    "sg:phone":"+1 717 361 7611",
    "sg:postcode":"17022",
    "sg:province":"PA",
    "sg:tags":[
        "art",
        "gallery",
        "dealer"
    ],
    "wof:name":"E-Town Art Gallery",
    "wof:placetype":"venue"
},
  "geometry": {"coordinates":[-76.60369900000001,40.152449],"type":"Point"}
}