{
  "type": "Feature",
  "properties": {
    "iso:country":"US",
    "sg:address":"123 E Wyoming Ave",
    "sg:city":"Philadelphia",
    "sg:classifiers":[
        {
            "category":"Organizations",
            "subcategory":"Religious Organization",
            "type":"Services"
        }
    ],
    "sg:phone":"+1   ",
    "sg:postcode":"19120",
    "sg:province":"PA",
    "wof:name":"Wyoming AV Baptist Church",
    "wof:placetype":"venue"
},
  "geometry": {"coordinates":[-75.122743,40.021441],"type":"Point"}
}