{
  "type": "Feature",
  "properties": {
    "iso:country":"US",
    "sg:address":"1319 Derry St",
    "sg:city":"Harrisburg",
    "sg:classifiers":[
        {
            "category":"Shopping",
            "subcategory":"Used Merchandise",
            "type":"Retail Goods"
        }
    ],
    "sg:phone":"+1 717 234 6657",
    "sg:postcode":"17104",
    "sg:province":"PA",
    "wof:name":"Brethren Community Thrift Shop",
    "wof:placetype":"venue"
},
  "geometry": {"coordinates":[-76.867451,40.262819],"type":"Point"}
}