{
  "type": "Feature",
  "properties": {
    "iso:country":"US",
    "sg:address":"421 Broad St",
    "sg:city":"Sewickley",
    "sg:classifiers":[
        {
            "category":"Professional",
            "type":"Services"
        }
    ],
    "sg:phone":"+1 412 741 0616",
    "sg:postcode":"15143",
    "sg:province":"PA",
    "sg:tags":[
        "establishment"
    ],
    "wof:name":"Gebhardt Assocs",
    "wof:placetype":"venue"
},
  "geometry": {"coordinates":[-80.181172,40.539639],"type":"Point"}
}