{
  "type": "Feature",
  "properties": {
    "iso:country":"US",
    "sg:address":"210 W Rittenhouse Sq # 405",
    "sg:city":"Philadelphia",
    "sg:classifiers":[
        {
            "category":"Health Services",
            "subcategory":"Dentist",
            "type":"Services"
        }
    ],
    "sg:phone":"+1 215 985 9030",
    "sg:postcode":"19103",
    "sg:province":"PA",
    "wof:name":"Orhan Tuncay Dr",
    "wof:placetype":"venue"
},
  "geometry": {"coordinates":[-75.172871,39.949825],"type":"Point"}
}