{
  "type": "Feature",
  "properties": {
    "addr:full":"554 Wildflower Dr Wilkes Barre PA 18702",
    "addr:housenumber":"554",
    "addr:postcode":"18702",
    "addr:street":"Wildflower Dr",
    "iso:country":"US",
    "sg:address":"554 Wildflower Dr",
    "sg:city":"Wilkes Barre",
    "sg:classifiers":[
        {
            "category":"Organizations",
            "subcategory":"Membership Organization",
            "type":"Services"
        }
    ],
    "sg:phone":"+1   ",
    "sg:postcode":"18702",
    "sg:province":"PA",
    "wof:name":"Hospital & Health Sys Assn PA",
    "wof:placetype":"venue"
},
  "geometry": {"coordinates":[-75.815304,41.251992],"type":"Point"}
}