{
  "type": "Feature",
  "properties": {
    "iso:country":"US",
    "sg:address":"495 Eisenhower Dr",
    "sg:city":"Hanover",
    "sg:classifiers":[
        {
            "category":"Personal",
            "subcategory":"Beauty Salon",
            "type":"Services"
        }
    ],
    "sg:phone":"+1 717 633 9106",
    "sg:postcode":"17331",
    "sg:province":"PA",
    "wof:name":"Smart Style Family Hair Salon",
    "wof:placetype":"venue"
},
  "geometry": {"coordinates":[-76.972915,39.825133],"type":"Point"}
}