{
  "type": "Feature",
  "properties": {
    "addr:full":"66 N Park Ests East Stroudsburg PA 18301",
    "addr:housenumber":"66",
    "addr:postcode":"18301",
    "addr:street":"N Park Ests",
    "iso:country":"US",
    "sg:address":"66 N Park Ests",
    "sg:city":"East Stroudsburg",
    "sg:classifiers":[
        {
            "category":"Personal",
            "subcategory":"Beauty Salon",
            "type":"Services"
        }
    ],
    "sg:phone":"+1   ",
    "sg:postcode":"18301",
    "sg:province":"PA",
    "sg:tags":[
        "shop"
    ],
    "wof:name":"Jean Pierre Bellini",
    "wof:placetype":"venue"
},
  "geometry": {"coordinates":[-75.050731,41.061126],"type":"Point"}
}