{
  "type": "Feature",
  "properties": {
    "iso:country":"US",
    "sg:address":"795 Pine Valley Dr",
    "sg:city":"Pittsburgh",
    "sg:classifiers":[
        {
            "category":"Wholesale",
            "subcategory":"Electrical",
            "type":"Manufacturing & Wholesale Goods"
        }
    ],
    "sg:phone":"+1 724 387 1479",
    "sg:postcode":"15239",
    "sg:province":"PA",
    "sg:tags":[
        "equipment",
        "electric",
        "motor"
    ],
    "wof:name":"Electramec Automation",
    "wof:placetype":"venue"
},
  "geometry": {"coordinates":[-79.71171,40.455429],"type":"Point"}
}