{
  "type": "Feature",
  "properties": {
    "addr:full":"118 Arden Dr Glenshaw PA 15116",
    "addr:housenumber":"118",
    "addr:postcode":"15116",
    "addr:street":"Arden Dr",
    "iso:country":"US",
    "sg:address":"118 Arden Dr",
    "sg:city":"Glenshaw",
    "sg:classifiers":[
        {
            "category":"Real Estate",
            "subcategory":"Real Estate Agent",
            "type":"Services"
        }
    ],
    "sg:phone":"+1   ",
    "sg:postcode":"15116",
    "sg:province":"PA",
    "wof:name":"Wo Smith & Assoc",
    "wof:placetype":"venue"
},
  "geometry": {"coordinates":[-79.974525,40.540303],"type":"Point"}
}