{
  "type": "Feature",
  "properties": {
    "iso:country":"US",
    "sg:address":"425 Delaware Dr",
    "sg:city":"Fort Washington",
    "sg:classifiers":[
        {
            "category":"Building & Trades",
            "subcategory":"Construction",
            "type":"Services"
        },
        {
            "category":"Building & Trades",
            "subcategory":"Plumbing",
            "type":"Services"
        }
    ],
    "sg:phone":"+1 215 283 9910",
    "sg:postcode":"19034",
    "sg:province":"PA",
    "sg:tags":[
        "air",
        "conditioning",
        "industrial",
        "system",
        "contractor"
    ],
    "wof:name":"Boa Construction Inc",
    "wof:placetype":"venue"
},
  "geometry": {"coordinates":[-75.195778,40.136642],"type":"Point"}
}