{
  "type": "Feature",
  "properties": {
    "addr:full":"50 W 3rd Ave Collegeville PA 19426",
    "addr:housenumber":"50",
    "addr:postcode":"19426",
    "addr:street":"W 3Rd Ave",
    "iso:country":"US",
    "sg:address":"50 W 3rd Ave",
    "sg:city":"Collegeville",
    "sg:classifiers":[
        {
            "category":"Restaurant",
            "type":"Food & Drink"
        }
    ],
    "sg:phone":"+1 610 489 7022",
    "sg:postcode":"19426",
    "sg:province":"PA",
    "wof:name":"Bunjung Japanese Restaurant",
    "wof:placetype":"venue"
},
  "geometry": {"coordinates":[-75.471401,40.196167],"type":"Point"}
}