{
  "type": "Feature",
  "properties": {
    "addr:full":"242 Lehigh Valley Mall Whitehall PA 18052",
    "addr:housenumber":"242",
    "addr:postcode":"18052",
    "addr:street":"Lehigh Valley Mall",
    "iso:country":"US",
    "sg:address":"242 Lehigh Valley Mall",
    "sg:city":"Whitehall",
    "sg:classifiers":[
        {
            "category":"Shopping",
            "subcategory":"Computers & Home Electronics",
            "type":"Retail Goods"
        }
    ],
    "sg:phone":"+1   ",
    "sg:postcode":"18052",
    "sg:province":"PA",
    "sg:tags":[
        "game",
        "video",
        "software"
    ],
    "wof:name":"Electronics Boutique",
    "wof:placetype":"venue"
},
  "geometry": {"coordinates":[-75.484245,40.62882],"type":"Point"}
}