{
  "type": "Feature",
  "properties": {
    "iso:country":"US",
    "sg:address":"601 Wayne Ave",
    "sg:city":"Chambersburg",
    "sg:classifiers":[
        {
            "category":"Health Services",
            "subcategory":"Doctor",
            "type":"Services"
        }
    ],
    "sg:phone":"+1 717 267 2255",
    "sg:postcode":"17201",
    "sg:province":"PA",
    "sg:tags":[
        "podiatrist",
        "medical",
        "surgeons",
        "physician"
    ],
    "wof:name":"Kirk W Davis Dpm",
    "wof:placetype":"venue"
},
  "geometry": {"coordinates":[-77.65776099999999,39.919441],"type":"Point"}
}