{
  "type": "Feature",
  "properties": {
    "iso:country":"US",
    "sg:address":"322 Main St",
    "sg:city":"Latrobe",
    "sg:classifiers":[
        {
            "category":"Banks & Credit Unions",
            "subcategory":"Bank",
            "type":"Services"
        }
    ],
    "sg:phone":"+1 724 539 9755",
    "sg:postcode":"15650",
    "sg:province":"PA",
    "sg:tags":[
        "savings",
        "loan",
        "association"
    ],
    "wof:name":"Westmoreland Federal Savings",
    "wof:placetype":"venue"
},
  "geometry": {"coordinates":[-79.383054,40.317583],"type":"Point"}
}