{
  "type": "Feature",
  "properties": {
    "iso:country":"US",
    "sg:address":"211 Huff Ave",
    "sg:city":"Greensburg",
    "sg:classifiers":[
        {
            "category":"Freight",
            "type":"Transportation"
        },
        {
            "category":"Wholesale",
            "subcategory":"Groceries",
            "type":"Manufacturing & Wholesale Goods"
        }
    ],
    "sg:phone":"+1 724 850 9001",
    "sg:postcode":"15601",
    "sg:province":"PA",
    "sg:tags":[
        "warehouse",
        "general"
    ],
    "wof:name":"Catch-Up Logistics",
    "wof:placetype":"venue"
},
  "geometry": {"coordinates":[-79.54694600000001,40.280973],"type":"Point"}
}