{
  "type": "Feature",
  "properties": {
    "addr:full":"920 E Main St Pen Argyl PA 18072",
    "addr:housenumber":"920",
    "addr:postcode":"18072",
    "addr:street":"E Main St",
    "iso:country":"US",
    "sg:address":"920 E Main St",
    "sg:city":"Pen Argyl",
    "sg:classifiers":[
        {
            "category":"Food & Beverages",
            "subcategory":"Liquor & Beverages",
            "type":"Retail Goods"
        },
        {
            "category":"Wholesale",
            "subcategory":"Beer",
            "type":"Manufacturing & Wholesale Goods"
        }
    ],
    "sg:phone":"+1 610 863 5990",
    "sg:postcode":"18072",
    "sg:province":"PA",
    "sg:tags":[
        "ale",
        "ice",
        "soda"
    ],
    "wof:name":"Cascario's Ice",
    "wof:placetype":"venue"
},
  "geometry": {"coordinates":[-75.24583199999999,40.872944],"type":"Point"}
}