{
  "type": "Feature",
  "properties": {
    "iso:country":"US",
    "sg:address":"910 Penn St",
    "sg:city":"Reading",
    "sg:classifiers":[
        {
            "category":"Travel",
            "subcategory":"Travel Agent",
            "type":"Entertainment"
        }
    ],
    "sg:phone":"+1 610 372 9352",
    "sg:postcode":"19602",
    "sg:province":"PA",
    "sg:tags":[
        "agency",
        "bureau"
    ],
    "wof:name":"Hoy Travel Multe Services",
    "wof:placetype":"venue"
},
  "geometry": {"coordinates":[-75.91829199999999,40.335101],"type":"Point"}
}