{
  "type": "Feature",
  "properties": {
    "iso:country":"US",
    "sg:address":"535 N Perry Hwy",
    "sg:city":"Mercer",
    "sg:classifiers":[
        {
            "category":"Professional",
            "subcategory":"Business Services",
            "type":"Services"
        }
    ],
    "sg:phone":"+1 724 662 2322",
    "sg:postcode":"16137",
    "sg:province":"PA",
    "sg:tags":[
        "auctioneer"
    ],
    "wof:name":"Mc Knight Auction",
    "wof:placetype":"venue"
},
  "geometry": {"coordinates":[-80.238772,41.257277],"type":"Point"}
}