{
  "type": "Feature",
  "properties": {
    "addr:full":"105 Highland Ave New Stanton PA 15672",
    "addr:housenumber":"105",
    "addr:postcode":"15672",
    "addr:street":"Highland Ave",
    "iso:country":"US",
    "sg:address":"105 Highland Ave",
    "sg:city":"New Stanton",
    "sg:classifiers":[
        {
            "category":"Restaurant",
            "type":"Food & Drink"
        }
    ],
    "sg:menulink":"http://www.allmenus.com/pa/new-stanton/72034-pizza-hut/menu/",
    "sg:phone":"+1 724 925 8166",
    "sg:postcode":"15672",
    "sg:province":"PA",
    "sg:tags":[
        "american",
        "pizza"
    ],
    "wof:name":"Pizza Hut",
    "wof:placetype":"venue"
},
  "geometry": {"coordinates":[-79.610265,40.219933],"type":"Point"}
}