{
  "type": "Feature",
  "properties": {
    "addr:full":"924 Colonial Ave York PA 17403",
    "addr:housenumber":"924",
    "addr:postcode":"17403",
    "addr:street":"Colonial Ave",
    "iso:country":"US",
    "sg:address":"924 Colonial Ave",
    "sg:city":"York",
    "sg:classifiers":[
        {
            "category":"Health Services",
            "subcategory":"Chiropractor",
            "type":"Services"
        }
    ],
    "sg:phone":"+1 717 848 8859",
    "sg:postcode":"17403",
    "sg:province":"PA",
    "wof:name":"Spring Garden Chiropractic Ctr",
    "wof:placetype":"venue"
},
  "geometry": {"coordinates":[-76.74078299999999,39.941909],"type":"Point"}
}