{
  "type": "Feature",
  "properties": {
    "iso:country":"US",
    "sg:address":"240 S 8th St",
    "sg:city":"Lebanon",
    "sg:classifiers":[
        {
            "category":"Professional",
            "subcategory":"Research",
            "type":"Services"
        },
        {
            "category":"Social Services",
            "type":"Services"
        }
    ],
    "sg:phone":"+1 717 277 7178",
    "sg:postcode":"17042",
    "sg:province":"PA",
    "sg:tags":[
        "organization",
        "instruction",
        "health",
        "noncommercial",
        "care"
    ],
    "wof:name":"Health Care Data Inc",
    "wof:placetype":"venue"
},
  "geometry": {"coordinates":[-76.424048,40.335453],"type":"Point"}
}