{
  "type": "Feature",
  "properties": {
    "iso:country":"US",
    "sg:address":"1486 Standard Ave",
    "sg:city":"Masury",
    "sg:classifiers":[
        {
            "category":"Building & Trades",
            "subcategory":"Electrical",
            "type":"Services"
        }
    ],
    "sg:phone":"+1 330 448 6368",
    "sg:postcode":"44438",
    "sg:province":"PA",
    "sg:tags":[
        "electrical",
        "contractor"
    ],
    "wof:name":"Shaffer Electric",
    "wof:placetype":"venue"
},
  "geometry": {"coordinates":[-80.533984,41.206966],"type":"Point"}
}