{
  "type": "Feature",
  "properties": {
    "iso:country":"US",
    "sg:address":"406 Juniper St",
    "sg:city":"Mckeesport",
    "sg:classifiers":[
        {
            "category":"Personal",
            "subcategory":"Beauty Salon",
            "type":"Services"
        }
    ],
    "sg:phone":"+1 412 751 3324",
    "sg:postcode":"15132",
    "sg:province":"PA",
    "wof:name":"Debbie Maizer's Hair Salon",
    "wof:placetype":"venue"
},
  "geometry": {"coordinates":[-79.83359400000001,40.319504],"type":"Point"}
}