{
  "type": "Feature",
  "properties": {
    "iso:country":"US",
    "sg:address":"3929 W Chew St",
    "sg:city":"Allentown",
    "sg:classifiers":[
        {
            "category":"Building & Trades",
            "subcategory":"Construction",
            "type":"Services"
        }
    ],
    "sg:phone":"+1 610 398 2331",
    "sg:postcode":"18104",
    "sg:province":"PA",
    "sg:tags":[
        "contractor"
    ],
    "wof:name":"Elliott R J Genl Contrctr",
    "wof:placetype":"venue"
},
  "geometry": {"coordinates":[-75.541496,40.587601],"type":"Point"}
}