{
  "type": "Feature",
  "properties": {
    "addr:full":"117 E Main St Youngsville PA 16371",
    "addr:housenumber":"117",
    "addr:postcode":"16371",
    "addr:street":"E Main St",
    "iso:country":"US",
    "sg:address":"117 E Main St",
    "sg:city":"Youngsville",
    "sg:classifiers":[
        {
            "category":"Banks & Credit Unions",
            "subcategory":"Bank",
            "type":"Services"
        }
    ],
    "sg:phone":"+1 814 563 4666",
    "sg:postcode":"16371",
    "sg:province":"PA",
    "sg:website":"http://www.pnc.com",
    "wof:name":"PNC",
    "wof:placetype":"venue"
},
  "geometry": {"coordinates":[-79.317059,41.851805],"type":"Point"}
}