{
  "type": "Feature",
  "properties": {
    "iso:country":"US",
    "sg:address":"2343 Haverford Rd ",
    "sg:city":"Ardmore",
    "sg:classifiers":[
        {
            "category":"Restaurant",
            "type":"Food & Drink"
        }
    ],
    "sg:menulink":"http://www.allmenus.com/pa/haverford/278727-original-eagle-pizza/menu/",
    "sg:phone":"+1 610 896 6140",
    "sg:postcode":"19003",
    "sg:province":"PA",
    "sg:tags":[
        "sandwich",
        "salad",
        "gyro",
        "seafood",
        "pasta",
        "calzones",
        "american",
        "wrap",
        "chicken",
        "hoagy",
        "pizza"
    ],
    "wof:name":"Original Eagle Pizza",
    "wof:placetype":"venue"
},
  "geometry": {"coordinates":[-75.29740700000001,39.993296],"type":"Point"}
}