{
  "type": "Feature",
  "properties": {
    "iso:country":"US",
    "sg:address":"2395 S Market St",
    "sg:city":"Elizabethtown",
    "sg:classifiers":[
        {
            "category":"Food & Beverages",
            "subcategory":"Groceries & Convenience Stores",
            "type":"Retail Goods"
        }
    ],
    "sg:phone":"+1 717 367 4139",
    "sg:postcode":"17022",
    "sg:province":"PA",
    "wof:name":"Turkey Hill Minit Market",
    "wof:placetype":"venue"
},
  "geometry": {"coordinates":[-76.56831699999999,40.132901],"type":"Point"}
}