{
  "type": "Feature",
  "properties": {
    "addr:full":"206 Church Ln Sewickley PA 15143",
    "addr:housenumber":"206",
    "addr:postcode":"15143",
    "addr:street":"Church Ln",
    "iso:country":"US",
    "sg:address":"206 Church Ln",
    "sg:city":"Sewickley",
    "sg:classifiers":[
        {
            "category":"Banks & Credit Unions",
            "subcategory":"Investment Brokerage",
            "type":"Services"
        }
    ],
    "sg:phone":"+1 412 749 9256",
    "sg:postcode":"15143",
    "sg:province":"PA",
    "sg:tags":[
        "advisory",
        "financial"
    ],
    "wof:name":"Schenley Capital Inc",
    "wof:placetype":"venue"
},
  "geometry": {"coordinates":[-80.199831,40.554282],"type":"Point"}
}