{
  "type": "Feature",
  "properties": {
    "iso:country":"US",
    "sg:address":"5760 Susquehanna Trl",
    "sg:city":"Manchester",
    "sg:classifiers":[
        {
            "category":"Professional",
            "subcategory":"Business Services",
            "type":"Services"
        }
    ],
    "sg:phone":"+1 717 266 9183",
    "sg:postcode":"17345",
    "sg:province":"PA",
    "sg:tags":[
        "consultant",
        "coach"
    ],
    "sg:website":"http://www.old-trail.com",
    "wof:name":"Old Trail Consulting",
    "wof:placetype":"venue"
},
  "geometry": {"coordinates":[-76.76135499999999,40.092492],"type":"Point"}
}