{
  "type": "Feature",
  "properties": {
    "addr:full":"240 The Mall At Steamtown Scranton PA 18503",
    "addr:housenumber":"240",
    "addr:postcode":"18503",
    "addr:street":"The",
    "iso:country":"US",
    "sg:address":"240 The Mall At Steamtown",
    "sg:city":"Scranton",
    "sg:classifiers":[
        {
            "category":"Shopping",
            "subcategory":"Clothing, Apparel, & Fashions",
            "type":"Retail Goods"
        }
    ],
    "sg:phone":"+1 570 343 8832",
    "sg:postcode":"18503",
    "sg:province":"PA",
    "sg:tags":[
        "men's",
        "uniform",
        "apparel",
        "women's",
        "clothing",
        "store"
    ],
    "sg:website":"http://www.aeropostale.com",
    "wof:name":"Aeropostale",
    "wof:placetype":"venue"
},
  "geometry": {"coordinates":[-75.669031,41.408739],"type":"Point"}
}