{
  "type": "Feature",
  "properties": {
    "iso:country":"US",
    "sg:address":"2783 Leechburg Rd",
    "sg:city":"New Kensington",
    "sg:classifiers":[
        {
            "category":"Wholesale",
            "subcategory":"Construction Materials",
            "type":"Manufacturing & Wholesale Goods"
        }
    ],
    "sg:phone":"+1   ",
    "sg:postcode":"15068",
    "sg:province":"PA",
    "sg:tags":[
        "hardware"
    ],
    "wof:name":"Len Friedman Associates Inc",
    "wof:placetype":"venue"
},
  "geometry": {"coordinates":[-79.732674,40.591725],"type":"Point"}
}