{
  "type": "Feature",
  "properties": {
    "addr:full":"5 Raab Dr Morrisville PA 19067",
    "addr:housenumber":"5",
    "addr:postcode":"19067",
    "addr:street":"Raab Dr",
    "iso:country":"US",
    "sg:address":"5 Raab Dr",
    "sg:city":"Morrisville",
    "sg:classifiers":[
        {
            "category":"Professional",
            "type":"Services"
        }
    ],
    "sg:phone":"+1   ",
    "sg:postcode":"19067",
    "sg:province":"PA",
    "wof:name":"Boattique",
    "wof:placetype":"venue"
},
  "geometry": {"coordinates":[-74.85843,40.245925],"type":"Point"}
}