{
  "type": "Feature",
  "properties": {
    "iso:country":"US",
    "sg:address":"3301 Market St",
    "sg:city":"Camp Hill",
    "sg:classifiers":[
        {
            "category":"Banks & Credit Unions",
            "subcategory":"Investment Brokerage",
            "type":"Services"
        }
    ],
    "sg:phone":"+1   ",
    "sg:postcode":"17011",
    "sg:province":"PA",
    "sg:tags":[
        "security"
    ],
    "wof:name":"Access Mortgage Consultants",
    "wof:placetype":"venue"
},
  "geometry": {"coordinates":[-76.93668599999999,40.239647],"type":"Point"}
}