{
  "type": "Feature",
  "properties": {
    "iso:country":"US",
    "sg:address":"1405 Bridgewater Rd",
    "sg:city":"Bensalem",
    "sg:classifiers":[
        {
            "category":"Professional",
            "subcategory":"Accounting & Tax Preparation",
            "type":"Services"
        }
    ],
    "sg:phone":"+1 215 244 2010",
    "sg:postcode":"19020",
    "sg:province":"PA",
    "sg:tags":[
        "return",
        "filing"
    ],
    "wof:name":"Neshaminy Brick & Block Inc",
    "wof:placetype":"venue"
},
  "geometry": {"coordinates":[-74.92965599999999,40.108808],"type":"Point"}
}