{
  "type": "Feature",
  "properties": {
    "addr:full":"671 Noble St Kutztown PA 19530",
    "addr:housenumber":"671",
    "addr:postcode":"19530",
    "addr:street":"Noble St",
    "iso:country":"US",
    "sg:address":"671 Noble St",
    "sg:city":"Kutztown",
    "sg:classifiers":[
        {
            "category":"Organizations",
            "subcategory":"Religious Organization",
            "type":"Services"
        }
    ],
    "sg:phone":"+1 610 683 8634",
    "sg:postcode":"19530",
    "sg:province":"PA",
    "sg:tags":[
        "place",
        "worship",
        "church"
    ],
    "sg:website":"http://www.watchtower.org",
    "wof:name":"Jehovah's Witnesses",
    "wof:placetype":"venue"
},
  "geometry": {"coordinates":[-75.76882999999999,40.504671],"type":"Point"}
}