{
  "type": "Feature",
  "properties": {
    "addr:full":"20 Country Ln Muncy PA 17756",
    "addr:housenumber":"20",
    "addr:postcode":"17756",
    "addr:street":"Country Ln",
    "iso:country":"US",
    "sg:address":"20 Country Ln",
    "sg:city":"Muncy",
    "sg:classifiers":[
        {
            "category":"Professional",
            "subcategory":"Employment Agencies",
            "type":"Services"
        }
    ],
    "sg:phone":"+1 570 584 3945",
    "sg:postcode":"17756",
    "sg:province":"PA",
    "sg:tags":[
        "driver",
        "leasing",
        "truck",
        "help",
        "supply"
    ],
    "wof:name":"Terry L Walter",
    "wof:placetype":"venue"
},
  "geometry": {"coordinates":[-76.717249,41.220133],"type":"Point"}
}