{
  "type": "Feature",
  "properties": {
    "addr:full":"4401 N Philip St Philadelphia PA 19140",
    "addr:housenumber":"4401",
    "addr:postcode":"19140",
    "addr:street":"N Philip St",
    "iso:country":"US",
    "sg:address":"4401 N Philip St",
    "sg:city":"Philadelphia",
    "sg:classifiers":[
        {
            "category":"Manufacturing",
            "subcategory":"Tools & Machinery",
            "type":"Manufacturing & Wholesale Goods"
        }
    ],
    "sg:phone":"+1 215 324 0410",
    "sg:postcode":"19140",
    "sg:province":"PA",
    "sg:tags":[
        "industrial",
        "mfg"
    ],
    "wof:name":"Brown Machine Works",
    "wof:placetype":"venue"
},
  "geometry": {"coordinates":[-75.12955599999999,40.019028],"type":"Point"}
}