{
  "type": "Feature",
  "properties": {
    "addr:full":"480 Indian Creek Rd Telford PA 18969",
    "addr:housenumber":"480",
    "addr:postcode":"18969",
    "addr:street":"Indian Creek Rd",
    "iso:country":"US",
    "sg:address":"480 Indian Creek Rd",
    "sg:city":"Telford",
    "sg:classifiers":[
        {
            "category":"Government",
            "subcategory":"Office",
            "type":"Public Place"
        }
    ],
    "sg:phone":"+1 215 723 1153",
    "sg:postcode":"18969",
    "sg:province":"PA",
    "sg:tags":[
        "village"
    ],
    "wof:name":"Maintenance Building",
    "wof:placetype":"venue"
},
  "geometry": {"coordinates":[-75.367805,40.315846],"type":"Point"}
}