{
  "type": "Feature",
  "properties": {
    "addr:full":"4520 Chester Ave Philadelphia PA 19143",
    "addr:housenumber":"4520",
    "addr:postcode":"19143",
    "addr:street":"Chester Ave",
    "iso:country":"US",
    "sg:address":"4520 Chester Ave",
    "sg:city":"Philadelphia",
    "sg:classifiers":[
        {
            "category":"Travel",
            "subcategory":"Hotels & Motels",
            "type":"Entertainment"
        }
    ],
    "sg:phone":"+1 215 662 1918",
    "sg:postcode":"19143",
    "sg:province":"PA",
    "sg:tags":[
        "operation",
        "lodging"
    ],
    "sg:website":"www.gablesbb.com",
    "wof:name":"Gables Bed & Breakfast",
    "wof:placetype":"venue"
},
  "geometry": {"coordinates":[-75.2127,39.947102],"type":"Point"}
}