{
  "type": "Feature",
  "properties": {
    "iso:country":"US",
    "sg:address":"1378 4th St",
    "sg:city":"Monongahela",
    "sg:classifiers":[
        {
            "category":"Health Services",
            "subcategory":"Nursing And Care Facility",
            "type":"Services"
        },
        {
            "category":"Social Services",
            "subcategory":"Retirement Home",
            "type":"Services"
        },
        {
            "category":"Social Services",
            "subcategory":"Adult Care",
            "type":"Services"
        }
    ],
    "sg:phone":"+1 724 997 8122",
    "sg:postcode":"15063",
    "sg:province":"PA",
    "sg:tags":[
        "living",
        "people",
        "personal",
        "assisted",
        "elder",
        "homes-elderly"
    ],
    "sg:website":"http://www.fouroaksmonvalley.com",
    "wof:name":"Four Oaks Personal Care Home",
    "wof:placetype":"venue"
},
  "geometry": {"coordinates":[-79.936169,40.20047],"type":"Point"}
}