{
  "type": "Feature",
  "properties": {
    "addr:full":"3330 Tillman Dr Bensalem PA 19020",
    "addr:housenumber":"3330",
    "addr:postcode":"19020",
    "addr:street":"Tillman Dr",
    "iso:country":"US",
    "sg:address":"3330 Tillman Dr",
    "sg:city":"Bensalem",
    "sg:classifiers":[
        {
            "category":"Education",
            "subcategory":"Special Training",
            "type":"Public Place"
        },
        {
            "category":"Education",
            "subcategory":"Vocational School",
            "type":"Public Place"
        },
        {
            "category":"Education",
            "subcategory":"University",
            "type":"Public Place"
        },
        {
            "category":"Education",
            "subcategory":"School",
            "type":"Public Place"
        }
    ],
    "sg:phone":"+1 888 578 5676",
    "sg:postcode":"19020",
    "sg:province":"PA",
    "sg:tags":[
        "educational",
        "industrial",
        "business",
        "technical",
        "trade",
        "college"
    ],
    "sg:website":"http://philadelphia.citysearch.com/profile/external/36440314/bensalem_pa/itt_technical_institute.html?publisher=yellowpages&reference_id=1&placement=ypwebsitemip",
    "wof:name":"ITT TECHNICAL INSTITUTE",
    "wof:placetype":"venue"
},
  "geometry": {"coordinates":[-74.96150900000001,40.11775],"type":"Point"}
}