{
  "type": "Feature",
  "properties": {
    "iso:country":"US",
    "sg:address":"245 Division St",
    "sg:city":"Harrisburg",
    "sg:classifiers":[
        {
            "category":"Organizations",
            "subcategory":"Religious Organization",
            "type":"Services"
        }
    ],
    "sg:phone":"+1 717 232 7566",
    "sg:postcode":"17110",
    "sg:province":"PA",
    "sg:tags":[
        "church"
    ],
    "wof:name":"Lakeside Lutheran Church",
    "wof:placetype":"venue"
},
  "geometry": {"coordinates":[-76.90289799999999,40.29117],"type":"Point"}
}