{
  "type": "Feature",
  "properties": {
    "iso:country":"US",
    "sg:address":"667 Conestoga Rd",
    "sg:city":"Villanova",
    "sg:classifiers":[
        {
            "category":"Shopping",
            "subcategory":"Computers & Home Electronics",
            "type":"Retail Goods"
        }
    ],
    "sg:phone":"+1 610 519 1700",
    "sg:postcode":"19085",
    "sg:province":"PA",
    "sg:tags":[
        "software"
    ],
    "wof:name":"Medical Data Systems",
    "wof:placetype":"venue"
},
  "geometry": {"coordinates":[-75.35775599999999,40.028696],"type":"Point"}
}