{
  "type": "Feature",
  "properties": {
    "addr:full":"405 W Elm St Norristown PA 19401",
    "addr:housenumber":"405",
    "addr:postcode":"19401",
    "addr:street":"W Elm St",
    "iso:country":"US",
    "sg:address":"405 W Elm St",
    "sg:city":"Norristown",
    "sg:classifiers":[
        {
            "category":"Manufacturing",
            "subcategory":"Metals",
            "type":"Manufacturing & Wholesale Goods"
        }
    ],
    "sg:phone":"+1   ",
    "sg:postcode":"19401",
    "sg:province":"PA",
    "sg:tags":[
        "steel",
        "door",
        "cellar",
        "steps",
        "mfg"
    ],
    "wof:name":"Steelway Custom Cellar Doors",
    "wof:placetype":"venue"
},
  "geometry": {"coordinates":[-75.345473,40.12277],"type":"Point"}
}