{
  "type": "Feature",
  "properties": {
    "addr:full":"619 S Carlisle Ln Altoona PA 16602",
    "addr:housenumber":"619",
    "addr:postcode":"16602",
    "addr:street":"S Carlisle Ln",
    "iso:country":"US",
    "sg:address":"619 S Carlisle Ln",
    "sg:city":"Altoona",
    "sg:classifiers":[
        {
            "category":"Retail",
            "subcategory":"Repair Shop",
            "type":"Services"
        }
    ],
    "sg:phone":"+1   ",
    "sg:postcode":"16602",
    "sg:province":"PA",
    "wof:name":"Jims Wood Finshg & Seat Repr",
    "wof:placetype":"venue"
},
  "geometry": {"coordinates":[-78.35075000000001,40.541308],"type":"Point"}
}