{
  "type": "Feature",
  "properties": {
    "iso:country":"US",
    "sg:address":"427 N Lawrence St",
    "sg:city":"Middletown",
    "sg:classifiers":[
        {
            "category":"Communications",
            "subcategory":"Radio Station",
            "type":"Services"
        }
    ],
    "sg:phone":"+1   ",
    "sg:postcode":"17057",
    "sg:province":"PA",
    "sg:tags":[
        "broadcast"
    ],
    "wof:name":"Pennsylvnia Hgher Educatn Assn",
    "wof:placetype":"venue"
},
  "geometry": {"coordinates":[-76.738923,40.197796],"type":"Point"}
}