{
  "type": "Feature",
  "properties": {
    "addr:full":"455 Pennsylvania Ave Fort Washington PA 19034",
    "addr:housenumber":"455",
    "addr:postcode":"19034",
    "addr:street":"Pennsylvania Ave",
    "iso:country":"US",
    "sg:address":"455 Pennsylvania Ave",
    "sg:city":"Fort Washington",
    "sg:classifiers":[
        {
            "category":"Professional",
            "subcategory":"Accounting & Tax Preparation",
            "type":"Services"
        }
    ],
    "sg:phone":"+1   ",
    "sg:postcode":"19034",
    "sg:province":"PA",
    "wof:name":"Cahan Smerman Spewak Lipschutz",
    "wof:placetype":"venue"
},
  "geometry": {"coordinates":[-75.208524,40.135814],"type":"Point"}
}