{
  "type": "Feature",
  "properties": {
    "iso:country":"US",
    "sg:address":"3301 Main St",
    "sg:city":"Homestead",
    "sg:classifiers":[
        {
            "category":"Restaurant",
            "type":"Food & Drink"
        },
        {
            "category":"Bars & Pubs",
            "type":"Food & Drink"
        }
    ],
    "sg:phone":"+1 412 461 9411",
    "sg:postcode":"15120",
    "sg:province":"PA",
    "sg:tags":[
        "drinking",
        "eating"
    ],
    "wof:name":"Cuzzins Cafe Inc",
    "wof:placetype":"venue"
},
  "geometry": {"coordinates":[-79.902669,40.386551],"type":"Point"}
}