{
  "type": "Feature",
  "properties": {
    "addr:full":"60 E Main St Leola PA 17540",
    "addr:housenumber":"60",
    "addr:postcode":"17540",
    "addr:street":"E Main St",
    "iso:country":"US",
    "sg:address":"60 E Main St",
    "sg:city":"Leola",
    "sg:classifiers":[
        {
            "category":"Manufacturing",
            "subcategory":"Rubber & Plastics",
            "type":"Manufacturing & Wholesale Goods"
        }
    ],
    "sg:phone":"+1 717 656 2236",
    "sg:postcode":"17540",
    "sg:province":"PA",
    "sg:tags":[
        "product"
    ],
    "sg:website":"www.dartcontainer.com",
    "wof:name":"Dart Container Corp",
    "wof:placetype":"venue"
},
  "geometry": {"coordinates":[-76.17728099999999,40.089475],"type":"Point"}
}