{
  "type": "Feature",
  "properties": {
    "addr:full":"178 County Line Rd Bridgeville PA 15017",
    "addr:housenumber":"178",
    "addr:postcode":"15017",
    "addr:street":"County Line Rd",
    "iso:country":"US",
    "sg:address":"178 County Line Rd",
    "sg:city":"Bridgeville",
    "sg:classifiers":[
        {
            "category":"Professional",
            "subcategory":"Business Services",
            "type":"Services"
        }
    ],
    "sg:phone":"+1   ",
    "sg:postcode":"15017",
    "sg:province":"PA",
    "sg:tags":[
        "interior",
        "design"
    ],
    "wof:name":"E D I",
    "wof:placetype":"venue"
},
  "geometry": {"coordinates":[-80.146143,40.322618],"type":"Point"}
}