{
  "type": "Feature",
  "properties": {
    "iso:country":"US",
    "sg:address":"1452 Schuylkill Ave",
    "sg:city":"Reading",
    "sg:classifiers":[
        {
            "category":"Personal",
            "subcategory":"Beauty Salon",
            "type":"Services"
        }
    ],
    "sg:phone":"+1 610 396 0878",
    "sg:postcode":"19601",
    "sg:province":"PA",
    "sg:tags":[
        "shop"
    ],
    "wof:name":"Queen Nail Salon",
    "wof:placetype":"venue"
},
  "geometry": {"coordinates":[-75.949595,40.356613],"type":"Point"}
}