{
  "type": "Feature",
  "properties": {
    "iso:country":"US",
    "sg:address":"139 N Pioneer Ave",
    "sg:city":"Shavertown",
    "sg:classifiers":[
        {
            "category":"Building & Trades",
            "subcategory":"Plumbing",
            "type":"Services"
        }
    ],
    "sg:phone":"+1 570 675 7335",
    "sg:postcode":"18708",
    "sg:province":"PA",
    "sg:tags":[
        "contractor"
    ],
    "wof:name":"Pro HVAC Inc",
    "wof:placetype":"venue"
},
  "geometry": {"coordinates":[-75.945556,41.319879],"type":"Point"}
}