{
  "type": "Feature",
  "properties": {
    "iso:country":"US",
    "sg:address":"17 Burnett St",
    "sg:city":"Hunlock Creek",
    "sg:classifiers":[
        {
            "category":"Building & Trades",
            "subcategory":"Construction",
            "type":"Services"
        }
    ],
    "sg:phone":"+1   ",
    "sg:postcode":"18634",
    "sg:province":"PA",
    "sg:tags":[
        "general",
        "contractor"
    ],
    "wof:name":"F B Construction",
    "wof:placetype":"venue"
},
  "geometry": {"coordinates":[-76.026212,41.189592],"type":"Point"}
}