{
  "type": "Feature",
  "properties": {
    "iso:country":"US",
    "sg:address":"242 Little Deer Creek Rd",
    "sg:city":"Cheswick",
    "sg:classifiers":[
        {
            "category":"Building & Trades",
            "subcategory":"Plumbing",
            "type":"Services"
        }
    ],
    "sg:phone":"+1   ",
    "sg:postcode":"15024",
    "sg:province":"PA",
    "sg:tags":[
        "plumbing",
        "air",
        "heating",
        "conditioning",
        "contractor"
    ],
    "wof:name":"Roth George Plbg & Htg Inc",
    "wof:placetype":"venue"
},
  "geometry": {"coordinates":[-79.829581,40.595958],"type":"Point"}
}