{
  "type": "Feature",
  "properties": {
    "iso:country":"US",
    "sg:address":"619 S 4th St Apt 1",
    "sg:city":"Philadelphia",
    "sg:phone":"+1 215 627 3777",
    "sg:postcode":"19147",
    "sg:province":"PA",
    "wof:name":"Amanda Stevenson Photography",
    "wof:placetype":"venue"
},
  "geometry": {"coordinates":[-75.149255,39.941177],"type":"Point"}
}