{
  "type": "Feature",
  "properties": {
    "iso:country":"US",
    "sg:address":"1654 Washington Ave",
    "sg:city":"Ambler",
    "sg:classifiers":[
        {
            "category":"Building & Trades",
            "subcategory":"Construction",
            "type":"Services"
        }
    ],
    "sg:phone":"+1   ",
    "sg:postcode":"19013",
    "sg:province":"PA",
    "sg:tags":[
        "house"
    ],
    "wof:name":"Top Gun Construction Inc",
    "wof:placetype":"venue"
},
  "geometry": {"coordinates":[-75.353407,39.864241],"type":"Point"}
}