{
  "type": "Feature",
  "properties": {
    "iso:country":"US",
    "sg:address":"606 N Chester Rd",
    "sg:city":"West Chester",
    "sg:classifiers":[
        {
            "category":"Professional",
            "subcategory":"Research",
            "type":"Services"
        }
    ],
    "sg:phone":"+1 610 696 8210",
    "sg:postcode":"19380",
    "sg:province":"PA",
    "sg:tags":[
        "analytical",
        "consulting",
        "chemistry",
        "testing"
    ],
    "wof:name":"M-Scan Inc",
    "wof:placetype":"venue"
},
  "geometry": {"coordinates":[-75.539362,39.980911],"type":"Point"}
}