{
  "type": "Feature",
  "properties": {
    "addr:full":"2438 Bristol Rd Bensalem PA 19020",
    "addr:housenumber":"2438",
    "addr:postcode":"19020",
    "addr:street":"Bristol Rd",
    "iso:country":"US",
    "sg:address":"2438 Bristol Rd",
    "sg:city":"Bensalem",
    "sg:classifiers":[
        {
            "category":"Banks & Credit Unions",
            "subcategory":"Financial Services",
            "type":"Services"
        }
    ],
    "sg:phone":"+1 215 741 1007",
    "sg:postcode":"19020",
    "sg:province":"PA",
    "sg:tags":[
        "broker",
        "mortgage"
    ],
    "wof:name":"Advantage One Mortgage Corp",
    "wof:placetype":"venue"
},
  "geometry": {"coordinates":[-74.929604,40.133099],"type":"Point"}
}