{
  "type": "Feature",
  "properties": {
    "addr:full":"2955 Franks Rd Huntingdon Vly PA 19006",
    "addr:housenumber":"2955",
    "addr:postcode":"19006",
    "addr:street":"Franks Rd",
    "iso:country":"US",
    "sg:address":"2955 Franks Rd",
    "sg:city":"Huntingdon Vly",
    "sg:classifiers":[
        {
            "category":"Manufacturing",
            "subcategory":"Metals",
            "type":"Manufacturing & Wholesale Goods"
        }
    ],
    "sg:phone":"+1 215 947 1867",
    "sg:postcode":"19006",
    "sg:province":"PA",
    "sg:tags":[
        "product",
        "iron",
        "mfg"
    ],
    "wof:name":"Northern Iron Works Inc",
    "wof:placetype":"venue"
},
  "geometry": {"coordinates":[-75.03736000000001,40.122229],"type":"Point"}
}