{
  "type": "Feature",
  "properties": {
    "iso:country":"US",
    "sg:address":"420 Springwood Dr",
    "sg:city":"Verona",
    "sg:classifiers":[
        {
            "category":"Manufacturing",
            "subcategory":"Printing",
            "type":"Manufacturing & Wholesale Goods"
        }
    ],
    "sg:phone":"+1   ",
    "sg:postcode":"15147",
    "sg:province":"PA",
    "sg:tags":[
        "lithographic",
        "commercial"
    ],
    "wof:name":"A G Halldin Publishing Company",
    "wof:placetype":"venue"
},
  "geometry": {"coordinates":[-79.82241399999999,40.504989],"type":"Point"}
}