{
  "type": "Feature",
  "properties": {
    "addr:full":"800 Westerly Pkwy State College PA 16801",
    "addr:housenumber":"800",
    "addr:postcode":"16801",
    "addr:street":"Westerly Pkwy",
    "iso:country":"US",
    "sg:address":"800 Westerly Pkwy",
    "sg:city":"State College",
    "sg:classifiers":[
        {
            "category":"Organizations",
            "subcategory":"Religious Organization",
            "type":"Services"
        }
    ],
    "sg:phone":"+1   ",
    "sg:postcode":"16801",
    "sg:province":"PA",
    "sg:tags":[
        "school"
    ],
    "wof:name":"Our Lady of Victory Church",
    "wof:placetype":"venue"
},
  "geometry": {"coordinates":[-77.86472500000001,40.781909],"type":"Point"}
}