{
  "type": "Feature",
  "properties": {
    "addr:full":"5110 Allentown Pike Temple PA 19560",
    "addr:housenumber":"5110",
    "addr:postcode":"19560",
    "addr:street":"Allentown Pike",
    "iso:country":"US",
    "sg:address":"5110 Allentown Pike",
    "sg:city":"Temple",
    "sg:classifiers":[
        {
            "category":"Insurance",
            "subcategory":"Insurance Agent",
            "type":"Services"
        }
    ],
    "sg:phone":"+1 610 921 2118",
    "sg:postcode":"19560",
    "sg:province":"PA",
    "wof:name":"State Farm Insurance",
    "wof:placetype":"venue"
},
  "geometry": {"coordinates":[-75.9277,40.409277],"type":"Point"}
}