{
  "type": "Feature",
  "properties": {
    "addr:full":"3005 Veterans Hwy Bristol PA 19007",
    "addr:housenumber":"3005",
    "addr:postcode":"19007",
    "addr:street":"Veterans Hwy",
    "iso:country":"US",
    "sg:address":"3005 Veterans Hwy",
    "sg:city":"Bristol",
    "sg:phone":"+1 215 547 4364",
    "sg:postcode":"19007",
    "sg:province":"PA",
    "sg:website":"http://www.difabiobrothers.com",
    "wof:name":"Difabio Brothers Inc",
    "wof:placetype":"venue"
},
  "geometry": {"coordinates":[-74.881494,40.122036],"type":"Point"}
}