{
  "type": "Feature",
  "properties": {
    "addr:full":"105 Sunset Dr Edinboro PA 16412",
    "addr:housenumber":"105",
    "addr:postcode":"16412",
    "addr:street":"Sunset Dr",
    "iso:country":"US",
    "sg:address":"105 Sunset Dr",
    "sg:city":"Edinboro",
    "sg:classifiers":[
        {
            "category":"Building & Trades",
            "subcategory":"Construction",
            "type":"Services"
        }
    ],
    "sg:phone":"+1 814 734 1622",
    "sg:postcode":"16412",
    "sg:province":"PA",
    "sg:tags":[
        "roof",
        "deck"
    ],
    "wof:name":"Mike Argue Trex Co",
    "wof:placetype":"venue"
},
  "geometry": {"coordinates":[-80.13728399999999,41.876585],"type":"Point"}
}