{
  "type": "Feature",
  "properties": {
    "iso:country":"US",
    "sg:address":"200 Newburn Ave",
    "sg:city":"Pittsburgh",
    "sg:classifiers":[
        {
            "category":"Building & Trades",
            "subcategory":"Construction",
            "type":"Services"
        }
    ],
    "sg:phone":"+1 412 885 1133",
    "sg:postcode":"15227",
    "sg:province":"PA",
    "sg:tags":[
        "home",
        "general",
        "family",
        "contractor"
    ],
    "wof:name":"Vernon Building Inspection",
    "wof:placetype":"venue"
},
  "geometry": {"coordinates":[-79.98433799999999,40.37976],"type":"Point"}
}