{
  "type": "Feature",
  "properties": {
    "iso:country":"US",
    "sg:address":"301 Fulling Mill Rd",
    "sg:city":"Middletown",
    "sg:classifiers":[
        {
            "category":"Airline",
            "type":"Transportation"
        }
    ],
    "sg:phone":"+1   ",
    "sg:postcode":"17057",
    "sg:province":"PA",
    "sg:tags":[
        "courier",
        "air"
    ],
    "wof:name":"D H L Worldwide Express",
    "wof:placetype":"venue"
},
  "geometry": {"coordinates":[-76.73434,40.230176],"type":"Point"}
}