{
  "type": "Feature",
  "properties": {
    "iso:country":"US",
    "sg:address":"18 Pine Springs Blvd",
    "sg:city":"York",
    "sg:classifiers":[
        {
            "category":"Home & Garden",
            "subcategory":"Home Furnishings",
            "type":"Retail Goods"
        },
        {
            "category":"Community Center",
            "type":"Public Place"
        }
    ],
    "sg:phone":"+1 717 309 3035",
    "sg:postcode":"17408",
    "sg:province":"PA",
    "sg:tags":[
        "basket",
        "house"
    ],
    "sg:website":"http://WWW.MYLONGABERGER.COM/ROBINGREER",
    "wof:name":"ROBIN GREER - LONGABERGER SALES ASSOCIATE",
    "wof:placetype":"venue"
},
  "geometry": {"coordinates":[-76.838956,39.911893],"type":"Point"}
}