{
  "type": "Feature",
  "properties": {
    "iso:country":"US",
    "sg:address":"4190 City Ave",
    "sg:city":"Philadelphia",
    "sg:classifiers":[
        {
            "category":"Social Services",
            "type":"Services"
        }
    ],
    "sg:phone":"+1 215 871 1948",
    "sg:postcode":"19131",
    "sg:province":"PA",
    "sg:tags":[
        "organization",
        "welfare"
    ],
    "wof:name":"WIC Program Admin General",
    "wof:placetype":"venue"
},
  "geometry": {"coordinates":[-75.214039,40.007008],"type":"Point"}
}