{
  "type": "Feature",
  "properties": {
    "addr:full":"640 Astor St Norristown PA 19401",
    "addr:housenumber":"640",
    "addr:postcode":"19401",
    "addr:street":"Astor St",
    "iso:country":"US",
    "sg:address":"640 Astor St",
    "sg:city":"Norristown",
    "sg:classifiers":[
        {
            "category":"Building & Trades",
            "subcategory":"Construction",
            "type":"Services"
        }
    ],
    "sg:phone":"+1   ",
    "sg:postcode":"19401",
    "sg:province":"PA",
    "sg:tags":[
        "home",
        "general",
        "family",
        "contractor"
    ],
    "wof:name":"Enrico J Gioquindo Jr Cnstr",
    "wof:placetype":"venue"
},
  "geometry": {"coordinates":[-75.34705700000001,40.120708],"type":"Point"}
}