{
  "type": "Feature",
  "properties": {
    "iso:country":"US",
    "sg:address":"54 Clinton St",
    "sg:city":"Greenville",
    "sg:classifiers":[
        {
            "category":"Banks & Credit Unions",
            "subcategory":"Bank",
            "type":"Services"
        }
    ],
    "sg:phone":"+1 724 588 7375",
    "sg:postcode":"16125",
    "sg:province":"PA",
    "sg:tags":[
        "loan",
        "real estate"
    ],
    "wof:name":"First Universal Mortgage Svc",
    "wof:placetype":"venue"
},
  "geometry": {"coordinates":[-80.387303,41.404737],"type":"Point"}
}