{
  "type": "Feature",
  "properties": {
    "iso:country":"US",
    "sg:address":"1445 City Ave",
    "sg:city":"Wynnewood",
    "sg:classifiers":[
        {
            "category":"Education",
            "subcategory":"Special Training",
            "type":"Public Place"
        }
    ],
    "sg:phone":"+1 610 642 1202",
    "sg:postcode":"19096",
    "sg:province":"PA",
    "sg:tags":[
        "school",
        "language"
    ],
    "wof:name":"Japanese Language School Phila",
    "wof:placetype":"venue"
},
  "geometry": {"coordinates":[-75.270083,39.980065],"type":"Point"}
}