{
  "type": "Feature",
  "properties": {
    "addr:full":"518 W High St Ebensburg PA 15931",
    "addr:housenumber":"518",
    "addr:postcode":"15931",
    "addr:street":"W High St",
    "iso:country":"US",
    "sg:address":"518 W High St",
    "sg:city":"Ebensburg",
    "sg:classifiers":[
        {
            "category":"Professional",
            "type":"Services"
        }
    ],
    "sg:phone":"+1 814 472 6424",
    "sg:postcode":"15931",
    "sg:province":"PA",
    "sg:tags":[
        "inventor"
    ],
    "wof:name":"MIDEA Inc",
    "wof:placetype":"venue"
},
  "geometry": {"coordinates":[-78.730188,40.48514],"type":"Point"}
}