{
  "type": "Feature",
  "properties": {
    "iso:country":"US",
    "sg:address":"9601 Germantown Ave",
    "sg:city":"Philadelphia",
    "sg:classifiers":[
        {
            "category":"Education",
            "subcategory":"College",
            "type":"Public Place"
        },
        {
            "category":"Shopping",
            "subcategory":"Books",
            "type":"Retail Goods"
        }
    ],
    "sg:phone":"+1 215 248 7000",
    "sg:postcode":"19118",
    "sg:province":"PA",
    "sg:tags":[
        "textbook"
    ],
    "wof:name":"Chestnut Hill College Bkstr",
    "wof:placetype":"venue"
},
  "geometry": {"coordinates":[-75.22642999999999,40.084414],"type":"Point"}
}