{
  "type": "Feature",
  "properties": {
    "iso:country":"US",
    "sg:address":"2 E Linden St",
    "sg:city":"Richland",
    "sg:classifiers":[
        {
            "category":"Building & Trades",
            "subcategory":"Construction",
            "type":"Services"
        }
    ],
    "sg:phone":"+1   ",
    "sg:postcode":"17087",
    "sg:province":"PA",
    "sg:tags":[
        "excavating",
        "contractor"
    ],
    "wof:name":"Harlan Nolt Excavating",
    "wof:placetype":"venue"
},
  "geometry": {"coordinates":[-76.26205,40.354828],"type":"Point"}
}