{
  "type": "Feature",
  "properties": {
    "iso:country":"US",
    "sg:address":"4321 Tower St",
    "sg:city":"Philadelphia",
    "sg:classifiers":[
        {
            "category":"Organizations",
            "subcategory":"Religious Organization",
            "type":"Services"
        }
    ],
    "sg:phone":"+1   ",
    "sg:postcode":"19127",
    "sg:province":"PA",
    "wof:name":"Heard Josie D African Mthdst",
    "wof:placetype":"venue"
},
  "geometry": {"coordinates":[-75.220642,40.026997],"type":"Point"}
}