{
  "type": "Feature",
  "properties": {
    "iso:country":"US",
    "sg:address":"1219 S Broad St",
    "sg:city":"Philadelphia",
    "sg:classifiers":[
        {
            "category":"Recreation",
            "type":"Entertainment"
        }
    ],
    "sg:phone":"+1 215 551 6344",
    "sg:postcode":"19147",
    "sg:province":"PA",
    "sg:tags":[
        "center"
    ],
    "wof:name":"Tolentine Community Center",
    "wof:placetype":"venue"
},
  "geometry": {"coordinates":[-75.16734099999999,39.934632],"type":"Point"}
}