{
  "type": "Feature",
  "properties": {
    "addr:full":"3420 Versailles Ave Mckeesport PA 15132",
    "addr:housenumber":"3420",
    "addr:postcode":"15132",
    "addr:street":"Versailles Ave",
    "iso:country":"US",
    "sg:address":"3420 Versailles Ave",
    "sg:city":"Mckeesport",
    "sg:classifiers":[
        {
            "category":"Retail",
            "subcategory":"Auto Repair",
            "type":"Services"
        }
    ],
    "sg:phone":"+1 412 678 7367",
    "sg:postcode":"15132",
    "sg:province":"PA",
    "sg:tags":[
        "wheel",
        "electric",
        "automobile",
        "servicing-automotive",
        "axle",
        "alignment-frame"
    ],
    "wof:name":"Bobs Garage",
    "wof:placetype":"venue"
},
  "geometry": {"coordinates":[-79.83739199999999,40.344918],"type":"Point"}
}