{
  "type": "Feature",
  "properties": {
    "iso:country":"US",
    "sg:address":"3425 Markleton School Rd",
    "sg:city":"Rockwood",
    "sg:classifiers":[
        {
            "category":"Building & Trades",
            "subcategory":"Construction",
            "type":"Services"
        }
    ],
    "sg:phone":"+1 814 926 2906",
    "sg:postcode":"15557",
    "sg:province":"PA",
    "sg:tags":[
        "handyman"
    ],
    "wof:name":"Ohlers Repair",
    "wof:placetype":"venue"
},
  "geometry": {"coordinates":[-79.161547,39.907164],"type":"Point"}
}