{
  "type": "Feature",
  "properties": {
    "addr:full":"31 King Charles Ln Newtown PA 18940",
    "addr:housenumber":"31",
    "addr:postcode":"18940",
    "addr:street":"King Charles Ln",
    "iso:country":"US",
    "sg:address":"31 King Charles Ln",
    "sg:city":"Newtown",
    "sg:classifiers":[
        {
            "category":"Shopping",
            "subcategory":"Shoes",
            "type":"Retail Goods"
        }
    ],
    "sg:phone":"+1   ",
    "sg:postcode":"18940",
    "sg:province":"PA",
    "wof:name":"AR Foods",
    "wof:placetype":"venue"
},
  "geometry": {"coordinates":[-74.95460799999999,40.216671],"type":"Point"}
}