{
  "type": "Feature",
  "properties": {
    "iso:country":"US",
    "sg:address":"411 N River St",
    "sg:city":"Wilkes Barre",
    "sg:classifiers":[
        {
            "category":"Home & Garden",
            "subcategory":"Furniture",
            "type":"Retail Goods"
        }
    ],
    "sg:phone":"+1   ",
    "sg:postcode":"18702",
    "sg:province":"PA",
    "wof:name":"Nachlis Clearance Ctr & B",
    "wof:placetype":"venue"
},
  "geometry": {"coordinates":[-75.871056,41.255339],"type":"Point"}
}