{
  "type": "Feature",
  "properties": {
    "iso:country":"US",
    "sg:address":"137 Glo Min Dr",
    "sg:city":"Pittsburgh",
    "sg:classifiers":[
        {
            "category":"Health Services",
            "subcategory":"Doctor",
            "type":"Services"
        }
    ],
    "sg:phone":"+1   ",
    "sg:postcode":"15241",
    "sg:province":"PA",
    "sg:tags":[
        "medical"
    ],
    "wof:name":"Mercys Hospital",
    "wof:placetype":"venue"
},
  "geometry": {"coordinates":[-80.065164,40.352483],"type":"Point"}
}