{
  "type": "Feature",
  "properties": {
    "iso:country":"US",
    "sg:address":"2040 Lucon Rd",
    "sg:city":"Schwenksville",
    "sg:classifiers":[
        {
            "category":"Retail",
            "subcategory":"Auto Repair",
            "type":"Services"
        }
    ],
    "sg:phone":"+1 215 513 4100",
    "sg:postcode":"19473",
    "sg:province":"PA",
    "sg:tags":[
        "wrecker"
    ],
    "wof:name":"Harleysville Vehicle Recovery",
    "wof:placetype":"venue"
},
  "geometry": {"coordinates":[-75.41233200000001,40.238172],"type":"Point"}
}