{
  "type": "Feature",
  "properties": {
    "iso:country":"US",
    "sg:address":"120 S York Rd",
    "sg:city":"Hatboro",
    "sg:classifiers":[
        {
            "category":"Professional",
            "type":"Services"
        }
    ],
    "sg:phone":"+1 215 675 0744",
    "sg:postcode":"19040",
    "sg:province":"PA",
    "sg:tags":[
        "establishment"
    ],
    "wof:name":"Hoover's Healing Hands",
    "wof:placetype":"venue"
},
  "geometry": {"coordinates":[-75.106892,40.174819],"type":"Point"}
}