{
  "type": "Feature",
  "properties": {
    "addr:full":"2776 Oxford Rd New Oxford PA 17350",
    "addr:housenumber":"2776",
    "addr:postcode":"17350",
    "addr:street":"Oxford Rd",
    "iso:country":"US",
    "sg:address":"2776 Oxford Rd",
    "sg:city":"New Oxford",
    "sg:classifiers":[
        {
            "category":"Manufacturing",
            "subcategory":"Tools & Machinery",
            "type":"Manufacturing & Wholesale Goods"
        }
    ],
    "sg:phone":"+1   ",
    "sg:postcode":"17350",
    "sg:province":"PA",
    "sg:tags":[
        "machine",
        "work",
        "mfg"
    ],
    "wof:name":"Gardner Associate Enterprises",
    "wof:placetype":"venue"
},
  "geometry": {"coordinates":[-77.121191,39.918604],"type":"Point"}
}