{
  "type": "Feature",
  "properties": {
    "iso:country":"US",
    "sg:address":"6450 Lincoln Way W",
    "sg:city":"St Thomas",
    "sg:classifiers":[
        {
            "category":"Building & Trades",
            "subcategory":"Construction",
            "type":"Services"
        }
    ],
    "sg:phone":"+1 717 369 3411",
    "sg:postcode":"17252",
    "sg:province":"PA",
    "sg:tags":[
        "excavating",
        "contractor"
    ],
    "wof:name":"Charles E Brake Co Inc",
    "wof:placetype":"venue"
},
  "geometry": {"coordinates":[-77.812124,39.913523],"type":"Point"}
}