{
  "type": "Feature",
  "properties": {
    "addr:full":"106 Rochester Rd Pittsburgh PA 15229",
    "addr:housenumber":"106",
    "addr:postcode":"15229",
    "addr:street":"Rochester Rd",
    "iso:country":"US",
    "sg:address":"106 Rochester Rd",
    "sg:city":"Pittsburgh",
    "sg:classifiers":[
        {
            "category":"Manufacturing",
            "subcategory":"Tools & Machinery",
            "type":"Manufacturing & Wholesale Goods"
        }
    ],
    "sg:phone":"+1 412 931 8250",
    "sg:postcode":"15229",
    "sg:province":"PA",
    "sg:tags":[
        "equipment",
        "engineering",
        "electric",
        "mfg"
    ],
    "wof:name":"Elcon Technologies Inc",
    "wof:placetype":"venue"
},
  "geometry": {"coordinates":[-80.022972,40.520701],"type":"Point"}
}