{
  "type": "Feature",
  "properties": {
    "iso:country":"US",
    "sg:address":"4820 Cumberland St",
    "sg:city":"Harrisburg",
    "sg:classifiers":[
        {
            "category":"Building & Trades",
            "subcategory":"Construction",
            "type":"Services"
        }
    ],
    "sg:phone":"+1 717 564 6871",
    "sg:postcode":"17111",
    "sg:province":"PA",
    "sg:tags":[
        "excavating",
        "contractor"
    ],
    "wof:name":"Arney Brothers Inc",
    "wof:placetype":"venue"
},
  "geometry": {"coordinates":[-76.80278800000001,40.26196],"type":"Point"}
}