{
  "type": "Feature",
  "properties": {
    "iso:country":"US",
    "sg:address":"27 W Seminary St",
    "sg:city":"Mercersburg",
    "sg:classifiers":[
        {
            "category":"Professional",
            "subcategory":"Business Services",
            "type":"Services"
        }
    ],
    "sg:phone":"+1 717 328 5239",
    "sg:postcode":"17236",
    "sg:province":"PA",
    "sg:tags":[
        "notary"
    ],
    "wof:name":"Chris' Title & Tags",
    "wof:placetype":"venue"
},
  "geometry": {"coordinates":[-77.90516599999999,39.82821],"type":"Point"}
}