{
  "type": "Feature",
  "properties": {
    "iso:country":"US",
    "sg:address":"1860 Centre Ave",
    "sg:city":"Pittsburgh",
    "sg:classifiers":[
        {
            "category":"Organizations",
            "subcategory":"Professional Association",
            "type":"Services"
        }
    ],
    "sg:phone":"+1 412 281 5774",
    "sg:postcode":"15219",
    "sg:province":"PA",
    "wof:name":"Allegheny Union Baptist Assn",
    "wof:placetype":"venue"
},
  "geometry": {"coordinates":[-79.98156,40.442795],"type":"Point"}
}