{
  "type": "Feature",
  "properties": {
    "iso:country":"US",
    "sg:address":"813 Raccoon St",
    "sg:city":"Aliquippa",
    "sg:classifiers":[
        {
            "category":"Insurance",
            "subcategory":"Insurance Agent",
            "type":"Services"
        }
    ],
    "sg:phone":"+1   ",
    "sg:postcode":"15001",
    "sg:province":"PA",
    "wof:name":"Rob Jones",
    "wof:placetype":"venue"
},
  "geometry": {"coordinates":[-80.28574399999999,40.606651],"type":"Point"}
}