{
  "type": "Feature",
  "properties": {
    "iso:country":"US",
    "sg:address":"300 W Presqueisle St",
    "sg:city":"Philipsburg",
    "sg:classifiers":[
        {
            "category":"Bars & Pubs",
            "type":"Food & Drink"
        }
    ],
    "sg:phone":"+1 814 342 9119",
    "sg:postcode":"16866",
    "sg:province":"PA",
    "sg:tags":[
        "tavern",
        "drinking"
    ],
    "wof:name":"Kelce's Tavern",
    "wof:placetype":"venue"
},
  "geometry": {"coordinates":[-78.22657,40.893551],"type":"Point"}
}