{
  "type": "Feature",
  "properties": {
    "addr:full":"311 Bunker Hill Dr Canonsburg PA 15317",
    "addr:housenumber":"311",
    "addr:postcode":"15317",
    "addr:street":"Bunker Hill Dr",
    "iso:country":"US",
    "sg:address":"311 Bunker Hill Dr",
    "sg:city":"Canonsburg",
    "sg:classifiers":[
        {
            "category":"Professional",
            "subcategory":"Management & Consulting",
            "type":"Services"
        }
    ],
    "sg:phone":"+1   ",
    "sg:postcode":"15317",
    "sg:province":"PA",
    "sg:tags":[
        "development",
        "technology",
        "research"
    ],
    "wof:name":"Composite Semiconductor Tech",
    "wof:placetype":"venue"
},
  "geometry": {"coordinates":[-80.07602900000001,40.27421],"type":"Point"}
}