{
  "type": "Feature",
  "properties": {
    "iso:country":"US",
    "sg:address":"816 Herman Rd",
    "sg:city":"Butler",
    "sg:classifiers":[
        {
            "category":"Restaurant",
            "type":"Food & Drink"
        }
    ],
    "sg:phone":"+1 724 285 6117",
    "sg:postcode":"16002",
    "sg:province":"PA",
    "wof:name":"Herman Mini Mart",
    "wof:placetype":"venue"
},
  "geometry": {"coordinates":[-79.809907,40.829977],"type":"Point"}
}