{
  "type": "Feature",
  "properties": {
    "iso:country":"US",
    "sg:address":"2636 Heidlersburg Rd",
    "sg:city":"Gettysburg",
    "sg:classifiers":[
        {
            "category":"Farming",
            "subcategory":"Dairy Farm",
            "type":"Manufacturing & Wholesale Goods"
        }
    ],
    "sg:phone":"+1   ",
    "sg:postcode":"17325",
    "sg:province":"PA",
    "wof:name":"Louis Baral",
    "wof:placetype":"venue"
},
  "geometry": {"coordinates":[-77.15558299999999,39.948839],"type":"Point"}
}