{
  "type": "Feature",
  "properties": {
    "addr:full":"3313 B St Philadelphia PA 19134",
    "addr:housenumber":"3313",
    "addr:postcode":"19134",
    "addr:street":"B St",
    "iso:country":"US",
    "sg:address":"3313 B St",
    "sg:city":"Philadelphia",
    "sg:classifiers":[
        {
            "category":"Food & Beverages",
            "subcategory":"Groceries & Convenience Stores",
            "type":"Retail Goods"
        }
    ],
    "sg:phone":"+1 215 427 9510",
    "sg:postcode":"19134",
    "sg:province":"PA",
    "sg:tags":[
        "grocer"
    ],
    "wof:name":"Jose's Grocery",
    "wof:placetype":"venue"
},
  "geometry": {"coordinates":[-75.124793,39.999983],"type":"Point"}
}