{
  "type": "Feature",
  "properties": {
    "iso:country":"US",
    "sg:address":"2613 Street Rd",
    "sg:city":"Bensalem",
    "sg:classifiers":[
        {
            "category":"Banks & Credit Unions",
            "subcategory":"Financial Services",
            "type":"Services"
        }
    ],
    "sg:phone":"+1 215 639 6170",
    "sg:postcode":"19020",
    "sg:province":"PA",
    "sg:tags":[
        "broker",
        "mortgage"
    ],
    "sg:website":"financial.wellsfargo.com",
    "wof:name":"Wells Fargo Financial",
    "wof:placetype":"venue"
},
  "geometry": {"coordinates":[-74.953003,40.109798],"type":"Point"}
}