{
  "type": "Feature",
  "properties": {
    "iso:country":"US",
    "sg:address":"701 W 5th St",
    "sg:city":"Williamstown",
    "sg:classifiers":[
        {
            "category":"Building & Trades",
            "subcategory":"Construction",
            "type":"Services"
        }
    ],
    "sg:phone":"+1 717 647 9533",
    "sg:postcode":"17098",
    "sg:province":"PA",
    "sg:tags":[
        "excavation",
        "excavating",
        "contractor"
    ],
    "wof:name":"Drum's Excavating",
    "wof:placetype":"venue"
},
  "geometry": {"coordinates":[-76.628879,40.583091],"type":"Point"}
}