{
  "type": "Feature",
  "properties": {
    "iso:country":"US",
    "sg:address":"141 Adam Dr",
    "sg:city":"New Oxford",
    "sg:classifiers":[
        {
            "category":"Building & Trades",
            "subcategory":"Construction",
            "type":"Services"
        }
    ],
    "sg:phone":"+1 717 624 4633",
    "sg:postcode":"17350",
    "sg:province":"PA",
    "sg:tags":[
        "hanging",
        "marking",
        "parking",
        "maintenance",
        "contractor"
    ],
    "wof:name":"B & E Parking Space Control",
    "wof:placetype":"venue"
},
  "geometry": {"coordinates":[-77.07778500000001,39.842906],"type":"Point"}
}