{
  "type": "Feature",
  "properties": {
    "addr:full":"1616 S Franklin St Philadelphia PA 19148",
    "addr:housenumber":"1616",
    "addr:postcode":"19148",
    "addr:street":"S Franklin St",
    "iso:country":"US",
    "sg:address":"1616 S Franklin St",
    "sg:city":"Philadelphia",
    "sg:classifiers":[
        {
            "category":"Wholesale",
            "subcategory":"Toys & Hobbies",
            "type":"Manufacturing & Wholesale Goods"
        }
    ],
    "sg:phone":"+1 215 467 2493",
    "sg:postcode":"19148",
    "sg:province":"PA",
    "sg:tags":[
        "model",
        "supplies-wholesale",
        "manufacturer"
    ],
    "wof:name":"Arttista Accessories",
    "wof:placetype":"venue"
},
  "geometry": {"coordinates":[-75.157859,39.928955],"type":"Point"}
}