{
  "type": "Feature",
  "properties": {
    "iso:country":"US",
    "sg:address":"1631 S Atherton St",
    "sg:city":"State College",
    "sg:classifiers":[
        {
            "category":"Professional",
            "type":"Services"
        }
    ],
    "sg:phone":"+1 814 689 2000",
    "sg:postcode":"16801",
    "sg:province":"PA",
    "sg:tags":[
        "establishment"
    ],
    "wof:name":"Medical Alliance Partners",
    "wof:placetype":"venue"
},
  "geometry": {"coordinates":[-77.83650799999999,40.785393],"type":"Point"}
}