{
  "type": "Feature",
  "properties": {
    "iso:country":"US",
    "sg:address":"213 E Penn Ave",
    "sg:city":"Cleona",
    "sg:classifiers":[
        {
            "category":"Restaurant",
            "type":"Food & Drink"
        }
    ],
    "sg:phone":"+1 717 274 9942",
    "sg:postcode":"17042",
    "sg:province":"PA",
    "wof:name":"Schwalm's Restaurant",
    "wof:placetype":"venue"
},
  "geometry": {"coordinates":[-76.471676,40.337922],"type":"Point"}
}