{
  "type": "Feature",
  "properties": {
    "addr:full":"107 Forrest Ave Narberth PA 19072",
    "addr:housenumber":"107",
    "addr:postcode":"19072",
    "addr:street":"Forrest Ave",
    "iso:country":"US",
    "sg:address":"107 Forrest Ave",
    "sg:city":"Narberth",
    "sg:classifiers":[
        {
            "category":"Professional",
            "subcategory":"Lawyer & Legal Services",
            "type":"Services"
        }
    ],
    "sg:phone":"+1 610 668 0702",
    "sg:postcode":"19072",
    "sg:province":"PA",
    "wof:name":"Law Offices of Jeffrey M Lindy",
    "wof:placetype":"venue"
},
  "geometry": {"coordinates":[-75.260966,40.005584],"type":"Point"}
}