{
  "type": "Feature",
  "properties": {
    "addr:full":"4949 Kutztown Rd Temple PA 19560",
    "addr:housenumber":"4949",
    "addr:postcode":"19560",
    "addr:street":"Kutztown Rd",
    "iso:country":"US",
    "sg:address":"4949 Kutztown Rd",
    "sg:city":"Temple",
    "sg:classifiers":[
        {
            "category":"Food & Beverages",
            "subcategory":"Candy",
            "type":"Retail Goods"
        }
    ],
    "sg:phone":"+1   ",
    "sg:postcode":"19560",
    "sg:province":"PA",
    "wof:name":"Billys Candies",
    "wof:placetype":"venue"
},
  "geometry": {"coordinates":[-75.920276,40.409976],"type":"Point"}
}