{
  "type": "Feature",
  "properties": {
    "addr:full":"811 Raystown Rd Everett PA 15537",
    "addr:housenumber":"811",
    "addr:postcode":"15537",
    "addr:street":"Raystown Rd",
    "iso:country":"US",
    "sg:address":"811 Raystown Rd",
    "sg:city":"Everett",
    "sg:classifiers":[
        {
            "category":"Home & Garden",
            "subcategory":"Garden Supply",
            "type":"Retail Goods"
        }
    ],
    "sg:phone":"+1 814 652 6101",
    "sg:postcode":"15537",
    "sg:province":"PA",
    "sg:tags":[
        "lawn"
    ],
    "wof:name":"Morris International Inc",
    "wof:placetype":"venue"
},
  "geometry": {"coordinates":[-78.36219199999999,40.048677],"type":"Point"}
}