{
  "type": "Feature",
  "properties": {
    "iso:country":"US",
    "sg:address":"908 Packer St",
    "sg:city":"Easton",
    "sg:classifiers":[
        {
            "category":"Local Transit",
            "type":"Transportation"
        }
    ],
    "sg:phone":"+1 610 258 2866",
    "sg:postcode":"18042",
    "sg:province":"PA",
    "sg:tags":[
        "passenger"
    ],
    "wof:name":"Easton Emergency Squad",
    "wof:placetype":"venue"
},
  "geometry": {"coordinates":[-75.22767899999999,40.672994],"type":"Point"}
}