{
  "type": "Feature",
  "properties": {
    "addr:full":"203 W Tioga St Tunkhannock PA 18657",
    "addr:housenumber":"203",
    "addr:postcode":"18657",
    "addr:street":"W Tioga St",
    "iso:country":"US",
    "sg:address":"203 W Tioga St",
    "sg:city":"Tunkhannock",
    "sg:classifiers":[
        {
            "category":"Utilities",
            "subcategory":"Water",
            "type":"Services"
        },
        {
            "category":"Government",
            "subcategory":"Office",
            "type":"Public Place"
        }
    ],
    "sg:phone":"+1 570 836 3493",
    "sg:postcode":"18657",
    "sg:province":"PA",
    "sg:tags":[
        "company-utility",
        "township",
        "government-city",
        "village"
    ],
    "wof:name":"Water & Sewer Office",
    "wof:placetype":"venue"
},
  "geometry": {"coordinates":[-75.963786,41.544696],"type":"Point"}
}