{
  "type": "Feature",
  "properties": {
    "iso:country":"US",
    "sg:address":"1528 Sansom St",
    "sg:city":"Philadelphia",
    "sg:classifiers":[
        {
            "category":"Restaurant",
            "type":"Food & Drink"
        }
    ],
    "sg:phone":"+1 215 561 6442",
    "sg:postcode":"19103",
    "sg:province":"PA",
    "wof:name":"Royal Gourmet Inc",
    "wof:placetype":"venue"
},
  "geometry": {"coordinates":[-75.165773,39.950317],"type":"Point"}
}