{
  "type": "Feature",
  "properties": {
    "addr:full":"151 Terrace Dr Olyphant PA 18447",
    "addr:housenumber":"151",
    "addr:postcode":"18447",
    "addr:street":"Terrace Dr",
    "iso:country":"US",
    "sg:address":"151 Terrace Dr",
    "sg:city":"Olyphant",
    "sg:classifiers":[
        {
            "category":"Sports & Exercise",
            "subcategory":"Gym",
            "type":"Entertainment"
        }
    ],
    "sg:phone":"+1 570 383 3223",
    "sg:postcode":"18447",
    "sg:province":"PA",
    "sg:tags":[
        "club",
        "health",
        "studio",
        "gymnasium"
    ],
    "wof:name":"Spectrum Health & Racquet Club",
    "wof:placetype":"venue"
},
  "geometry": {"coordinates":[-75.587903,41.491094],"type":"Point"}
}