{
  "type": "Feature",
  "properties": {
    "iso:country":"US",
    "sg:address":"139 N Main St",
    "sg:city":"Manheim",
    "sg:classifiers":[
        {
            "category":"Autos & Motor Vehicles",
            "subcategory":"Automobile Sales",
            "type":"Retail Goods"
        }
    ],
    "sg:phone":"+1 717 665 6777",
    "sg:postcode":"17545",
    "sg:province":"PA",
    "sg:tags":[
        "car",
        "dealer"
    ],
    "wof:name":"Manheim Pre-Owned Auto Sales",
    "wof:placetype":"venue"
},
  "geometry": {"coordinates":[-76.397879,40.166664],"type":"Point"}
}