{
  "type": "Feature",
  "properties": {
    "iso:country":"US",
    "sg:address":"1061 Willowbrook Ln",
    "sg:city":"Media",
    "sg:classifiers":[
        {
            "category":"Professional",
            "subcategory":"Employment Agencies",
            "type":"Services"
        }
    ],
    "sg:phone":"+1   ",
    "sg:postcode":"19063",
    "sg:province":"PA",
    "sg:tags":[
        "help",
        "supply"
    ],
    "wof:name":"K C Cleaning Service",
    "wof:placetype":"venue"
},
  "geometry": {"coordinates":[-75.395698,39.929938],"type":"Point"}
}