{
  "type": "Feature",
  "properties": {
    "iso:country":"US",
    "sg:address":"5249 Pleasant View Rd",
    "sg:city":"Red Lion",
    "sg:classifiers":[
        {
            "category":"Banks & Credit Unions",
            "subcategory":"Bank",
            "type":"Services"
        }
    ],
    "sg:phone":"+1   ",
    "sg:postcode":"17356",
    "sg:province":"PA",
    "sg:tags":[
        "loan",
        "broker"
    ],
    "wof:name":"All About Mortgages",
    "wof:placetype":"venue"
},
  "geometry": {"coordinates":[-76.609021,39.862246],"type":"Point"}
}