{
  "type": "Feature",
  "properties": {
    "iso:country":"US",
    "sg:address":"327 N McKean St",
    "sg:city":"Kittanning",
    "sg:classifiers":[
        {
            "category":"Social Services",
            "subcategory":"Child Care",
            "type":"Services"
        }
    ],
    "sg:phone":"+1 724 543 2135",
    "sg:postcode":"16201",
    "sg:province":"PA",
    "sg:tags":[
        "day"
    ],
    "wof:name":"Happy Hearts Home Day Care",
    "wof:placetype":"venue"
},
  "geometry": {"coordinates":[-79.521625,40.81772],"type":"Point"}
}