{
  "type": "Feature",
  "properties": {
    "iso:country":"US",
    "sg:address":"1216 11th Ave",
    "sg:city":"Altoona",
    "sg:classifiers":[
        {
            "category":"Professional",
            "subcategory":"Lawyer & Legal Services",
            "type":"Services"
        }
    ],
    "sg:phone":"+1   ",
    "sg:postcode":"16601",
    "sg:province":"PA",
    "wof:name":"John C Peters Jr",
    "wof:placetype":"venue"
},
  "geometry": {"coordinates":[-78.401994,40.515155],"type":"Point"}
}