{
  "type": "Feature",
  "properties": {
    "iso:country":"US",
    "sg:address":"2330 S 9th St",
    "sg:city":"Philadelphia",
    "sg:classifiers":[
        {
            "category":"Personal",
            "subcategory":"Beauty Salon",
            "type":"Services"
        }
    ],
    "sg:phone":"+1 215 467 4902",
    "sg:postcode":"19148",
    "sg:province":"PA",
    "sg:tags":[
        "shop"
    ],
    "wof:name":"Janet's Hair Salon",
    "wof:placetype":"venue"
},
  "geometry": {"coordinates":[-75.16184199999999,39.920811],"type":"Point"}
}