{
  "type": "Feature",
  "properties": {
    "iso:country":"US",
    "sg:address":"2275 Warren Rd",
    "sg:city":"Indiana",
    "sg:classifiers":[
        {
            "category":"Manufacturing",
            "subcategory":"Signs",
            "type":"Manufacturing & Wholesale Goods"
        }
    ],
    "sg:phone":"+1 724 465 2990",
    "sg:postcode":"15701",
    "sg:province":"PA",
    "sg:tags":[
        "advertising",
        "specialty"
    ],
    "wof:name":"Ben Satterlee Signs",
    "wof:placetype":"venue"
},
  "geometry": {"coordinates":[-79.185619,40.610423],"type":"Point"}
}