{
  "type": "Feature",
  "properties": {
    "iso:country":"US",
    "sg:address":"635 Monongahela Ave",
    "sg:city":"Glassport",
    "sg:classifiers":[
        {
            "category":"Building & Trades",
            "subcategory":"Construction",
            "type":"Services"
        }
    ],
    "sg:phone":"+1 412 896 0031",
    "sg:postcode":"15045",
    "sg:province":"PA",
    "sg:tags":[
        "landscaping",
        "excavating",
        "paving",
        "contractor"
    ],
    "wof:name":"Murin Paving & Excavating",
    "wof:placetype":"venue"
},
  "geometry": {"coordinates":[-79.89238899999999,40.32492],"type":"Point"}
}