{
  "type": "Feature",
  "properties": {
    "iso:country":"US",
    "sg:address":"370 Woodlands Rd",
    "sg:city":"Evans City",
    "sg:classifiers":[
        {
            "category":"Wholesale",
            "subcategory":"Medical Equipment & Supplies",
            "type":"Manufacturing & Wholesale Goods"
        }
    ],
    "sg:phone":"+1   ",
    "sg:postcode":"16033",
    "sg:province":"PA",
    "wof:name":"Well Enterprises Inc",
    "wof:placetype":"venue"
},
  "geometry": {"coordinates":[-80.04232500000001,40.844237],"type":"Point"}
}