{
  "type": "Feature",
  "properties": {
    "addr:full":"451 Colonial Dr Monroeville PA 15146",
    "addr:housenumber":"451",
    "addr:postcode":"15146",
    "addr:street":"Colonial Dr",
    "iso:country":"US",
    "sg:address":"451 Colonial Dr",
    "sg:city":"Monroeville",
    "sg:classifiers":[
        {
            "category":"Farming",
            "subcategory":"Livestock Farm",
            "type":"Manufacturing & Wholesale Goods"
        }
    ],
    "sg:phone":"+1   ",
    "sg:postcode":"15146",
    "sg:province":"PA",
    "sg:tags":[
        "animal",
        "general"
    ],
    "wof:name":"4 D Ranch & Stable Inc",
    "wof:placetype":"venue"
},
  "geometry": {"coordinates":[-79.764332,40.454555],"type":"Point"}
}