{
  "type": "Feature",
  "properties": {
    "iso:country":"US",
    "sg:address":"76 Main Blvd",
    "sg:city":"Ringtown",
    "sg:classifiers":[
        {
            "category":"Manufacturing",
            "subcategory":"Tools & Machinery",
            "type":"Manufacturing & Wholesale Goods"
        }
    ],
    "sg:phone":"+1 570 889 5650",
    "sg:postcode":"17967",
    "sg:province":"PA",
    "sg:tags":[
        "machine",
        "die",
        "specialty",
        "shop"
    ],
    "wof:name":"Nordic Tool & Die Co",
    "wof:placetype":"venue"
},
  "geometry": {"coordinates":[-76.166701,40.861839],"type":"Point"}
}