{
  "type": "Feature",
  "properties": {
    "iso:country":"US",
    "sg:address":"6831 Ruppsville Rd",
    "sg:city":"Allentown",
    "sg:classifiers":[
        {
            "category":"Manufacturing",
            "subcategory":"Rubber & Plastics",
            "type":"Manufacturing & Wholesale Goods"
        }
    ],
    "sg:phone":"+1 610 481 0655",
    "sg:postcode":"18106",
    "sg:province":"PA",
    "sg:tags":[
        "bottle",
        "mfg"
    ],
    "wof:name":"Consolidated Container Co",
    "wof:placetype":"venue"
},
  "geometry": {"coordinates":[-75.59898800000001,40.575476],"type":"Point"}
}