{
  "type": "Feature",
  "properties": {
    "iso:country":"US",
    "sg:address":"2390 Lincoln Hwy E",
    "sg:city":"Lancaster",
    "sg:classifiers":[
        {
            "category":"Travel",
            "subcategory":"Hotels & Motels",
            "type":"Entertainment"
        }
    ],
    "sg:phone":"+1 717 397 6531",
    "sg:postcode":"17602",
    "sg:province":"PA",
    "wof:name":"Canadiana Motel",
    "wof:placetype":"venue"
},
  "geometry": {"coordinates":[-76.203909,40.024667],"type":"Point"}
}