{
  "type": "Feature",
  "properties": {
    "addr:full":"147 Municipal Bldg Rd Melcroft PA 15490",
    "addr:housenumber":"147",
    "addr:postcode":"15490",
    "addr:street":"Municipal Bldg Rd",
    "iso:country":"US",
    "sg:address":"147 Municipal Bldg Rd",
    "sg:city":"Melcroft",
    "sg:classifiers":[
        {
            "category":"Government",
            "subcategory":"Office",
            "type":"Public Place"
        }
    ],
    "sg:phone":"+1 724 455 2866",
    "sg:postcode":"15490",
    "sg:province":"PA",
    "sg:tags":[
        "village"
    ],
    "wof:name":"Saltlick Township Municipal",
    "wof:placetype":"venue"
},
  "geometry": {"coordinates":[-79.38802,40.052589],"type":"Point"}
}