{
  "type": "Feature",
  "properties": {
    "iso:country":"US",
    "sg:address":"920 Beck Mill Rd",
    "sg:city":"Hanover",
    "sg:classifiers":[
        {
            "category":"Organizations",
            "subcategory":"Religious Organization",
            "type":"Services"
        },
        {
            "category":"Education",
            "subcategory":"School",
            "type":"Public Place"
        }
    ],
    "sg:phone":"+1 717 632 3590",
    "sg:postcode":"17331",
    "sg:province":"PA",
    "sg:tags":[
        "church"
    ],
    "wof:name":"Missionary Bible Bapt Academy",
    "wof:placetype":"venue"
},
  "geometry": {"coordinates":[-76.98161,39.775254],"type":"Point"}
}