{
  "type": "Feature",
  "properties": {
    "iso:country":"US",
    "sg:address":"1 Freedom Valley Dr",
    "sg:city":"Oaks",
    "sg:classifiers":[
        {
            "category":"Banks & Credit Unions",
            "subcategory":"Investment Brokerage",
            "type":"Services"
        }
    ],
    "sg:phone":"+1 800 610 1114",
    "sg:postcode":"19456",
    "sg:province":"PA",
    "sg:tags":[
        "trust"
    ],
    "wof:name":"Krantz Family Foundation",
    "wof:placetype":"venue"
},
  "geometry": {"coordinates":[-75.448502,40.140179],"type":"Point"}
}