{
  "type": "Feature",
  "properties": {
    "addr:full":"846 Cross St Pottstown PA 19464",
    "addr:housenumber":"846",
    "addr:postcode":"19464",
    "addr:street":"Cross St",
    "iso:country":"US",
    "sg:address":"846 Cross St",
    "sg:city":"Pottstown",
    "sg:classifiers":[
        {
            "category":"Building & Trades",
            "subcategory":"Construction",
            "type":"Services"
        }
    ],
    "sg:phone":"+1 610 970 4214",
    "sg:postcode":"19464",
    "sg:province":"PA",
    "sg:tags":[
        "masonry",
        "contractor"
    ],
    "wof:name":"Thompson Masonry Contracting",
    "wof:placetype":"venue"
},
  "geometry": {"coordinates":[-75.632972,40.240649],"type":"Point"}
}