{
  "type": "Feature",
  "properties": {
    "iso:country":"US",
    "sg:address":"3245 Hamilton Blvd",
    "sg:city":"Allentown",
    "sg:classifiers":[
        {
            "category":"Restaurant",
            "type":"Food & Drink"
        }
    ],
    "sg:phone":"+1 610 432 1800",
    "sg:postcode":"18103",
    "sg:province":"PA",
    "wof:name":"Foo Joy",
    "wof:placetype":"venue"
},
  "geometry": {"coordinates":[-75.522797,40.5793],"type":"Point"}
}