{
  "type": "Feature",
  "properties": {
    "iso:country":"US",
    "sg:address":"1808 Diamond Dr",
    "sg:city":"Newtown",
    "sg:classifiers":[
        {
            "category":"Building & Trades",
            "subcategory":"Construction",
            "type":"Services"
        }
    ],
    "sg:phone":"+1 215 504 9427",
    "sg:postcode":"18940",
    "sg:province":"PA",
    "sg:tags":[
        "hanging",
        "contractor"
    ],
    "wof:name":"Dillon Painting Concepts",
    "wof:placetype":"venue"
},
  "geometry": {"coordinates":[-74.944688,40.216248],"type":"Point"}
}