{
  "type": "Feature",
  "properties": {
    "addr:full":"116 S Market St Nanticoke PA 18634",
    "addr:housenumber":"116",
    "addr:postcode":"18634",
    "addr:street":"S Market St",
    "iso:country":"US",
    "sg:address":"116 S Market St",
    "sg:city":"Nanticoke",
    "sg:classifiers":[
        {
            "category":"Personal",
            "subcategory":"Beauty Salon",
            "type":"Services"
        }
    ],
    "sg:phone":"+1 570 735 3725",
    "sg:postcode":"18634",
    "sg:province":"PA",
    "sg:tags":[
        "shop"
    ],
    "wof:name":"Jan Lor Roz Styling Salon",
    "wof:placetype":"venue"
},
  "geometry": {"coordinates":[-76.003615,41.202762],"type":"Point"}
}