{
  "type": "Feature",
  "properties": {
    "addr:full":"794 Mt Bethel Hwy Mt Bethel PA 18343",
    "addr:housenumber":"794",
    "addr:postcode":"18343",
    "addr:street":"Mt Bethel Hwy Mt",
    "iso:country":"US",
    "sg:address":"794 Mt Bethel Hwy",
    "sg:city":"Mt Bethel",
    "sg:classifiers":[
        {
            "category":"Restaurant",
            "type":"Food & Drink"
        }
    ],
    "sg:phone":"+1 570 897 6969",
    "sg:postcode":"18343",
    "sg:province":"PA",
    "wof:name":"Valley View Inn & Restaurant",
    "wof:placetype":"venue"
},
  "geometry": {"coordinates":[-75.153513,40.888039],"type":"Point"}
}