{
  "type": "Feature",
  "properties": {
    "iso:country":"US",
    "sg:address":"120 Upper Pine Creek Rd",
    "sg:city":"Chester Springs",
    "sg:classifiers":[
        {
            "category":"Wholesale",
            "subcategory":"Medical Equipment & Supplies",
            "type":"Manufacturing & Wholesale Goods"
        }
    ],
    "sg:phone":"+1   ",
    "sg:postcode":"19425",
    "sg:province":"PA",
    "sg:tags":[
        "fire",
        "rep",
        "sales",
        "emergency",
        "for"
    ],
    "wof:name":"Manion Associates",
    "wof:placetype":"venue"
},
  "geometry": {"coordinates":[-75.62696800000001,40.062315],"type":"Point"}
}