{
  "type": "Feature",
  "properties": {
    "iso:country":"US",
    "sg:address":"68 E Main St",
    "sg:city":"Reinholds",
    "sg:classifiers":[
        {
            "category":"Home & Garden",
            "subcategory":"Carpets & Floor Coverings",
            "type":"Retail Goods"
        }
    ],
    "sg:phone":"+1 717 336 5322",
    "sg:postcode":"17569",
    "sg:province":"PA",
    "sg:tags":[
        "dealer",
        "rug"
    ],
    "wof:name":"Sweigart's Floor Covering Co",
    "wof:placetype":"venue"
},
  "geometry": {"coordinates":[-76.114147,40.266584],"type":"Point"}
}