{
  "type": "Feature",
  "properties": {
    "iso:country":"US",
    "sg:address":"1750 5th Ave",
    "sg:city":"York",
    "sg:classifiers":[
        {
            "category":"Health Services",
            "subcategory":"Doctor",
            "type":"Services"
        }
    ],
    "sg:phone":"+1 717 846 1337",
    "sg:postcode":"17403",
    "sg:province":"PA",
    "sg:tags":[
        "physician",
        "surgeon"
    ],
    "wof:name":"Carl A Frankel MD",
    "wof:placetype":"venue"
},
  "geometry": {"coordinates":[-76.69194299999999,39.9665],"type":"Point"}
}