{
  "type": "Feature",
  "properties": {
    "iso:country":"US",
    "sg:address":"27 N Johnson Rd",
    "sg:city":"Houston",
    "sg:classifiers":[
        {
            "category":"Real Estate",
            "subcategory":"Architect",
            "type":"Services"
        }
    ],
    "sg:phone":"+1 724 745 3685",
    "sg:postcode":"15342",
    "sg:province":"PA",
    "wof:name":"R N Mc Carthy",
    "wof:placetype":"venue"
},
  "geometry": {"coordinates":[-80.21382699999999,40.239737],"type":"Point"}
}