{
  "type": "Feature",
  "properties": {
    "addr:full":"129 Allendale Way Camp Hill PA 17011",
    "addr:housenumber":"129",
    "addr:postcode":"17011",
    "addr:street":"Allendale Way",
    "iso:country":"US",
    "sg:address":"129 Allendale Way",
    "sg:city":"Camp Hill",
    "sg:classifiers":[
        {
            "category":"Banks & Credit Unions",
            "subcategory":"Bank",
            "type":"Services"
        }
    ],
    "sg:phone":"+1 717 232 2797",
    "sg:postcode":"17011",
    "sg:province":"PA",
    "sg:tags":[
        "broker",
        "mortgage"
    ],
    "wof:name":"Assurance Mortgage Co",
    "wof:placetype":"venue"
},
  "geometry": {"coordinates":[-76.887753,40.217638],"type":"Point"}
}