{
  "type": "Feature",
  "properties": {
    "iso:country":"US",
    "sg:address":"1099 Bower Hill Rd",
    "sg:city":"Pittsburgh",
    "sg:classifiers":[
        {
            "category":"Government",
            "subcategory":"Office",
            "type":"Public Place"
        }
    ],
    "sg:phone":"+1 412 923 1904",
    "sg:postcode":"15243",
    "sg:province":"PA",
    "sg:tags":[
        "federal",
        "program"
    ],
    "wof:name":"US Food Safety Inspection Svc",
    "wof:placetype":"venue"
},
  "geometry": {"coordinates":[-80.067965,40.376149],"type":"Point"}
}