{
  "type": "Feature",
  "properties": {
    "addr:full":"135 N 3rd St Sunbury PA 17801",
    "addr:housenumber":"135",
    "addr:postcode":"17801",
    "addr:street":"N 3Rd St",
    "iso:country":"US",
    "sg:address":"135 N 3rd St",
    "sg:city":"Sunbury",
    "sg:classifiers":[
        {
            "category":"Government",
            "subcategory":"Post Office",
            "type":"Public Place"
        }
    ],
    "sg:phone":"+1 570 286 7176",
    "sg:postcode":"17801",
    "sg:province":"PA",
    "sg:tags":[
        "postal",
        "us"
    ],
    "wof:name":"US Post Office",
    "wof:placetype":"venue"
},
  "geometry": {"coordinates":[-76.791541,40.864485],"type":"Point"}
}