{
  "type": "Feature",
  "properties": {
    "iso:country":"US",
    "sg:address":"3804 Forbes Ave",
    "sg:city":"Pittsburgh",
    "sg:classifiers":[
        {
            "category":"Shopping",
            "subcategory":"Computers & Home Electronics",
            "type":"Retail Goods"
        }
    ],
    "sg:phone":"+1 412 681 0125",
    "sg:postcode":"15213",
    "sg:province":"PA",
    "sg:tags":[
        "television",
        "radio"
    ],
    "wof:name":"Direct Access TV",
    "wof:placetype":"venue"
},
  "geometry": {"coordinates":[-79.956453,40.44183],"type":"Point"}
}