{
  "type": "Feature",
  "properties": {
    "addr:full":"236 Tyrone St Greencastle PA 17225",
    "addr:housenumber":"236",
    "addr:postcode":"17225",
    "addr:street":"Tyrone St",
    "iso:country":"US",
    "sg:address":"236 Tyrone St",
    "sg:city":"Greencastle",
    "sg:classifiers":[
        {
            "category":"Organizations",
            "subcategory":"Religious Organization",
            "type":"Services"
        }
    ],
    "sg:phone":"+1   ",
    "sg:postcode":"17225",
    "sg:province":"PA",
    "wof:name":"Greencstle Frsqare Gspl Church",
    "wof:placetype":"venue"
},
  "geometry": {"coordinates":[-77.72161199999999,39.793081],"type":"Point"}
}