{
  "type": "Feature",
  "properties": {
    "iso:country":"US",
    "sg:address":"681 N 52nd St",
    "sg:city":"Philadelphia",
    "sg:classifiers":[
        {
            "category":"Retail",
            "subcategory":"Repair Shop",
            "type":"Services"
        }
    ],
    "sg:phone":"+1 215 473 0677",
    "sg:postcode":"19131",
    "sg:province":"PA",
    "sg:tags":[
        "reupholstery",
        "upholsterer",
        "furniture"
    ],
    "wof:name":"Morlaye Upholstery Plus",
    "wof:placetype":"venue"
},
  "geometry": {"coordinates":[-75.225998,39.971298],"type":"Point"}
}