{
  "type": "Feature",
  "properties": {
    "addr:full":"1501 N Broad St Philadelphia PA 19122",
    "addr:housenumber":"1501",
    "addr:postcode":"19122",
    "addr:street":"N Broad St",
    "iso:country":"US",
    "sg:address":"1501 N Broad St",
    "sg:city":"Philadelphia",
    "sg:classifiers":[
        {
            "category":"Banks & Credit Unions",
            "subcategory":"Bank",
            "type":"Services"
        }
    ],
    "sg:phone":"+1 215 978 4400",
    "sg:postcode":"19122",
    "sg:province":"PA",
    "wof:name":"United Bank Of Philadelphia",
    "wof:placetype":"venue"
},
  "geometry": {"coordinates":[-75.15823899999999,39.97728],"type":"Point"}
}