{
  "type": "Feature",
  "properties": {
    "addr:full":"100 W Wood St Mc Connellsburg PA 17233",
    "addr:housenumber":"100",
    "addr:postcode":"17233",
    "addr:street":"W Wood St",
    "iso:country":"US",
    "sg:address":"100 W Wood St",
    "sg:city":"Mc Connellsburg",
    "sg:classifiers":[
        {
            "category":"Real Estate",
            "subcategory":"Real Estate Operator",
            "type":"Services"
        }
    ],
    "sg:phone":"+1   ",
    "sg:postcode":"17233",
    "sg:province":"PA",
    "sg:tags":[
        "property",
        "lessor"
    ],
    "wof:name":"McGarvey Rental Properties",
    "wof:placetype":"venue"
},
  "geometry": {"coordinates":[-77.98663999999999,39.937692],"type":"Point"}
}