{
  "type": "Feature",
  "properties": {
    "iso:country":"US",
    "sg:address":"196 Red Hill Rd",
    "sg:city":"Ottsville",
    "sg:classifiers":[
        {
            "category":"Health Services",
            "subcategory":"Doctor",
            "type":"Services"
        }
    ],
    "sg:phone":"+1 610 847 5472",
    "sg:postcode":"18942",
    "sg:province":"PA",
    "sg:tags":[
        "psychoanalyst"
    ],
    "wof:name":"Paul Wieand",
    "wof:placetype":"venue"
},
  "geometry": {"coordinates":[-75.13051,40.464729],"type":"Point"}
}