{
  "type": "Feature",
  "properties": {
    "iso:country":"US",
    "sg:address":"646 Skippack Pike",
    "sg:city":"Blue Bell",
    "sg:classifiers":[
        {
            "category":"Autos & Motor Vehicles",
            "subcategory":"Fuel & Gas Station",
            "type":"Retail Goods"
        }
    ],
    "sg:phone":"+1 215 643 9664",
    "sg:postcode":"19422",
    "sg:province":"PA",
    "wof:name":"Pei of PA Inc",
    "wof:placetype":"venue"
},
  "geometry": {"coordinates":[-75.26781800000001,40.1532],"type":"Point"}
}