{
  "type": "Feature",
  "properties": {
    "iso:country":"US",
    "sg:address":"210 N Main St",
    "sg:city":"Souderton",
    "sg:classifiers":[
        {
            "category":"Building & Trades",
            "subcategory":"Construction",
            "type":"Services"
        }
    ],
    "sg:phone":"+1   ",
    "sg:postcode":"18964",
    "sg:province":"PA",
    "sg:tags":[
        "merchandise",
        "contractor"
    ],
    "wof:name":"C J Miller Vacuflo",
    "wof:placetype":"venue"
},
  "geometry": {"coordinates":[-75.325248,40.311997],"type":"Point"}
}