{
  "type": "Feature",
  "properties": {
    "iso:country":"US",
    "sg:address":"516 Orchard Dr",
    "sg:city":"Harrisburg",
    "sg:classifiers":[
        {
            "category":"Shopping",
            "subcategory":"Clothing, Apparel, & Fashions",
            "type":"Retail Goods"
        }
    ],
    "sg:phone":"+1 717 379 2233",
    "sg:postcode":"17113",
    "sg:province":"PA",
    "sg:tags":[
        "apparel",
        "women's"
    ],
    "wof:name":"Premier Designs High Fashion Jewelry",
    "wof:placetype":"venue"
},
  "geometry": {"coordinates":[-76.834561,40.237293],"type":"Point"}
}