{
  "type": "Feature",
  "properties": {
    "addr:full":"1001 Pattison Ave Philadelphia PA 19148",
    "addr:housenumber":"1001",
    "addr:postcode":"19148",
    "addr:street":"Pattison Ave",
    "iso:country":"US",
    "sg:address":"1001 Pattison Ave",
    "sg:city":"Philadelphia",
    "sg:classifiers":[
        {
            "category":"Sports & Exercise",
            "subcategory":"Sports Center",
            "type":"Entertainment"
        }
    ],
    "sg:phone":"+1 267 570 2960",
    "sg:postcode":"19148",
    "sg:province":"PA",
    "sg:tags":[
        "athletic"
    ],
    "wof:name":"Phillies Baseball Club",
    "wof:placetype":"venue"
},
  "geometry": {"coordinates":[-75.16677799999999,39.904525],"type":"Point"}
}