{
  "type": "Feature",
  "properties": {
    "iso:country":"US",
    "sg:address":"164 Maynard St",
    "sg:city":"Williamsport",
    "sg:classifiers":[
        {
            "category":"Manufacturing",
            "subcategory":"Metals",
            "type":"Manufacturing & Wholesale Goods"
        }
    ],
    "sg:phone":"+1 570 323 6216",
    "sg:postcode":"17701",
    "sg:province":"PA",
    "sg:tags":[
        "copper",
        "foundry",
        "iron",
        "aluminum"
    ],
    "wof:name":"Williamsport Foundry Co Inc",
    "wof:placetype":"venue"
},
  "geometry": {"coordinates":[-77.01971500000001,41.235539],"type":"Point"}
}