{
  "type": "Feature",
  "properties": {
    "iso:country":"US",
    "sg:address":"702 18th St",
    "sg:city":"Altoona",
    "sg:classifiers":[
        {
            "category":"Real Estate",
            "subcategory":"Real Estate Agent",
            "type":"Services"
        }
    ],
    "sg:phone":"+1   ",
    "sg:postcode":"16602",
    "sg:province":"PA",
    "sg:tags":[
        "insurance"
    ],
    "wof:name":"Consiglio David J Ins",
    "wof:placetype":"venue"
},
  "geometry": {"coordinates":[-78.402376,40.508483],"type":"Point"}
}