{
  "type": "Feature",
  "properties": {
    "iso:country":"US",
    "sg:address":"1080 3rd St",
    "sg:city":"North Versailles",
    "sg:classifiers":[
        {
            "category":"Retail",
            "subcategory":"Laundry & Dry Cleaning",
            "type":"Services"
        }
    ],
    "sg:phone":"+1 412 824 2629",
    "sg:postcode":"15137",
    "sg:province":"PA",
    "sg:tags":[
        "cleaners",
        "rug",
        "carpet"
    ],
    "wof:name":"Cory Cleaning Svc",
    "wof:placetype":"venue"
},
  "geometry": {"coordinates":[-79.807659,40.376719],"type":"Point"}
}