{
  "type": "Feature",
  "properties": {
    "iso:country":"US",
    "sg:address":"1150 State Rte 136",
    "sg:city":"Belle Vernon",
    "sg:classifiers":[
        {
            "category":"Wholesale",
            "subcategory":"Auto Parts",
            "type":"Manufacturing & Wholesale Goods"
        }
    ],
    "sg:phone":"+1 724 872 9909",
    "sg:postcode":"15012",
    "sg:province":"PA",
    "sg:tags":[
        "automobile",
        "rebuilt"
    ],
    "wof:name":"Starr Auto Svc",
    "wof:placetype":"venue"
},
  "geometry": {"coordinates":[-79.790655,40.211457],"type":"Point"}
}