{
  "type": "Feature",
  "properties": {
    "iso:country":"US",
    "sg:address":"10 Union Hill Rd",
    "sg:city":"W Conshohocken",
    "sg:classifiers":[
        {
            "category":"Professional",
            "type":"Services"
        }
    ],
    "sg:phone":"+1 484 530 0500",
    "sg:postcode":"19428",
    "sg:province":"PA",
    "sg:tags":[
        "establishment"
    ],
    "wof:name":"Grand American Corp",
    "wof:placetype":"venue"
},
  "geometry": {"coordinates":[-75.32577499999999,40.068711],"type":"Point"}
}