{
  "type": "Feature",
  "properties": {
    "addr:full":"433 Yellow Creek Dr Hopewell PA 16650",
    "addr:housenumber":"433",
    "addr:postcode":"16650",
    "addr:street":"Yellow Creek Dr",
    "iso:country":"US",
    "sg:address":"433 Yellow Creek Dr",
    "sg:city":"Hopewell",
    "sg:classifiers":[
        {
            "category":"Transit Center",
            "subcategory":"Freight",
            "type":"Transportation"
        },
        {
            "category":"Freight",
            "type":"Transportation"
        }
    ],
    "sg:phone":"+1 814 928 3172",
    "sg:postcode":"16650",
    "sg:province":"PA",
    "sg:tags":[
        "local",
        "trucking-motor",
        "trucking"
    ],
    "wof:name":"Jeffrey A Best",
    "wof:placetype":"venue"
},
  "geometry": {"coordinates":[-78.329729,40.136252],"type":"Point"}
}