{
  "type": "Feature",
  "properties": {
    "addr:full":"147 Hartline Dr Reading PA 19606",
    "addr:housenumber":"147",
    "addr:postcode":"19606",
    "addr:street":"Hartline Dr",
    "iso:country":"US",
    "sg:address":"147 Hartline Dr",
    "sg:city":"Reading",
    "sg:classifiers":[
        {
            "category":"Professional",
            "subcategory":"Detective & Security Services",
            "type":"Services"
        }
    ],
    "sg:phone":"+1 610 582 7332",
    "sg:postcode":"19606",
    "sg:province":"PA",
    "sg:tags":[
        "guard",
        "patrol"
    ],
    "wof:name":"Katzaman Detective Agency",
    "wof:placetype":"venue"
},
  "geometry": {"coordinates":[-75.83663199999999,40.297908],"type":"Point"}
}