{
  "type": "Feature",
  "properties": {
    "iso:country":"US",
    "sg:address":"2421 Aspen Way",
    "sg:city":"Harrisburg",
    "sg:classifiers":[
        {
            "category":"Building & Trades",
            "subcategory":"Electrical",
            "type":"Services"
        }
    ],
    "sg:phone":"+1   ",
    "sg:postcode":"17110",
    "sg:province":"PA",
    "sg:tags":[
        "electrical",
        "contractor"
    ],
    "wof:name":"Landon Electrical Services",
    "wof:placetype":"venue"
},
  "geometry": {"coordinates":[-76.86067799999999,40.303982],"type":"Point"}
}