{
  "type": "Feature",
  "properties": {
    "iso:country":"US",
    "sg:address":"126 Baker Hollow",
    "sg:city":"Coudersport",
    "sg:classifiers":[
        {
            "category":"Retail",
            "subcategory":"Repair Shop",
            "type":"Services"
        },
        {
            "category":"Shopping",
            "subcategory":"Bicycles & Sporting Goods",
            "type":"Retail Goods"
        }
    ],
    "sg:phone":"+1 814 274 0315",
    "sg:postcode":"16915",
    "sg:province":"PA",
    "sg:tags":[
        "taxidermist"
    ],
    "wof:name":"Ken's Taxidermy",
    "wof:placetype":"venue"
},
  "geometry": {"coordinates":[-77.982859,41.843482],"type":"Point"}
}