{
  "type": "Feature",
  "properties": {
    "iso:country":"US",
    "sg:address":"2215 Rosstown Rd",
    "sg:city":"Wellsville",
    "sg:classifiers":[
        {
            "category":"Shopping",
            "subcategory":"Bicycles & Sporting Goods",
            "type":"Retail Goods"
        }
    ],
    "sg:phone":"+1   ",
    "sg:postcode":"17365",
    "sg:province":"PA",
    "sg:tags":[
        "fishing",
        "gear"
    ],
    "wof:name":"Hawg Head Baits  Inc",
    "wof:placetype":"venue"
},
  "geometry": {"coordinates":[-76.888884,40.086781],"type":"Point"}
}