{
  "type": "Feature",
  "properties": {
    "iso:country":"US",
    "sg:address":"138 Stone Quarry Rd",
    "sg:city":"Aliquippa",
    "sg:classifiers":[
        {
            "category":"Recreation",
            "type":"Entertainment"
        }
    ],
    "sg:phone":"+1   ",
    "sg:postcode":"15001",
    "sg:province":"PA",
    "sg:tags":[
        "club",
        "membership"
    ],
    "wof:name":"Hopewell Twp VFW",
    "wof:placetype":"venue"
},
  "geometry": {"coordinates":[-80.282954,40.557804],"type":"Point"}
}