{
  "type": "Feature",
  "properties": {
    "addr:full":"506 Stump Rd Montgomeryville PA 18914",
    "addr:housenumber":"506",
    "addr:postcode":"18914",
    "addr:street":"Stump Rd",
    "iso:country":"US",
    "sg:address":"506 Stump Rd",
    "sg:city":"Montgomeryville",
    "sg:classifiers":[
        {
            "category":"Professional",
            "subcategory":"Engineering",
            "type":"Services"
        }
    ],
    "sg:phone":"+1 215 362 5340",
    "sg:postcode":"18914",
    "sg:province":"PA",
    "sg:tags":[
        "engineer"
    ],
    "wof:name":"Apantec LLC",
    "wof:placetype":"venue"
},
  "geometry": {"coordinates":[-75.20415800000001,40.255103],"type":"Point"}
}