{
  "type": "Feature",
  "properties": {
    "iso:country":"US",
    "sg:address":"1703 Chestnut St",
    "sg:city":"Philadelphia",
    "sg:classifiers":[
        {
            "category":"Shopping",
            "subcategory":"Department Store",
            "type":"Retail Goods"
        }
    ],
    "sg:phone":"+1 215 977 9480",
    "sg:postcode":"19103",
    "sg:province":"PA",
    "sg:tags":[
        "variety"
    ],
    "wof:name":"B & J Variety Store",
    "wof:placetype":"venue"
},
  "geometry": {"coordinates":[-75.168802,39.951473],"type":"Point"}
}