{
  "type": "Feature",
  "properties": {
    "iso:country":"US",
    "sg:address":"220 Bennett St",
    "sg:city":"Luzerne",
    "sg:classifiers":[
        {
            "category":"Retail",
            "subcategory":"Auto Repair",
            "type":"Services"
        }
    ],
    "sg:phone":"+1   ",
    "sg:postcode":"18709",
    "sg:province":"PA",
    "sg:tags":[
        "general"
    ],
    "wof:name":"Matties Inspection & Tire Sls",
    "wof:placetype":"venue"
},
  "geometry": {"coordinates":[-75.887489,41.278667],"type":"Point"}
}