{
  "type": "Feature",
  "properties": {
    "iso:country":"US",
    "sg:address":"4905 W Tilghman St",
    "sg:city":"Allentown",
    "sg:classifiers":[
        {
            "category":"Banks & Credit Unions",
            "subcategory":"Bank",
            "type":"Services"
        }
    ],
    "sg:phone":"+1 610 366 0110",
    "sg:postcode":"18104",
    "sg:province":"PA",
    "sg:tags":[
        "loan",
        "mortgage",
        "real estate"
    ],
    "sg:website":"www.fhhlc.com",
    "wof:name":"First Horizon Home Loans Corp",
    "wof:placetype":"venue"
},
  "geometry": {"coordinates":[-75.56853099999999,40.59114],"type":"Point"}
}