{
  "type": "Feature",
  "properties": {
    "iso:country":"US",
    "sg:address":"3461 Market St",
    "sg:city":"Camp Hill",
    "sg:classifiers":[
        {
            "category":"Banks & Credit Unions",
            "subcategory":"Financial Services",
            "type":"Services"
        }
    ],
    "sg:phone":"+1 717 731 9109",
    "sg:postcode":"17011",
    "sg:province":"PA",
    "sg:tags":[
        "broker",
        "mortgage"
    ],
    "wof:name":"Nationwide Mortgage Services",
    "wof:placetype":"venue"
},
  "geometry": {"coordinates":[-76.940662,40.239178],"type":"Point"}
}