{
  "type": "Feature",
  "properties": {
    "iso:country":"US",
    "sg:address":"413 Avenue Of The States",
    "sg:city":"Chester",
    "sg:classifiers":[
        {
            "category":"Personal",
            "type":"Services"
        }
    ],
    "sg:phone":"+1 610 876 1200",
    "sg:postcode":"19013",
    "sg:province":"PA",
    "sg:tags":[
        "assistant"
    ],
    "wof:name":"Delaware County Today Almanac",
    "wof:placetype":"venue"
},
  "geometry": {"coordinates":[-75.35958100000001,39.84758],"type":"Point"}
}