{
  "type": "Feature",
  "properties": {
    "iso:country":"US",
    "sg:address":"2330 Clinton St",
    "sg:city":"Homestead",
    "sg:classifiers":[
        {
            "category":"Building & Trades",
            "subcategory":"Construction",
            "type":"Services"
        }
    ],
    "sg:phone":"+1 412 464 4726",
    "sg:postcode":"15120",
    "sg:province":"PA",
    "sg:tags":[
        "roofing",
        "contractor"
    ],
    "wof:name":"Mathews Construction",
    "wof:placetype":"venue"
},
  "geometry": {"coordinates":[-79.896765,40.394924],"type":"Point"}
}