{
  "type": "Feature",
  "properties": {
    "iso:country":"US",
    "sg:address":"4268 Verona Rd",
    "sg:city":"Verona",
    "sg:classifiers":[
        {
            "category":"Restaurant",
            "type":"Food & Drink"
        }
    ],
    "sg:phone":"+1 412 242 8114",
    "sg:postcode":"15147",
    "sg:province":"PA",
    "wof:name":"Heart & Soul Restaurant",
    "wof:placetype":"venue"
},
  "geometry": {"coordinates":[-79.86347600000001,40.467078],"type":"Point"}
}