{
  "type": "Feature",
  "properties": {
    "iso:country":"US",
    "sg:address":"50 S 15th St",
    "sg:city":"Pittsburgh",
    "sg:classifiers":[
        {
            "category":"Freight",
            "type":"Transportation"
        }
    ],
    "sg:phone":"+1 412 488 7000",
    "sg:postcode":"15203",
    "sg:province":"PA",
    "wof:name":"Gasper Transportation Group",
    "wof:placetype":"venue"
},
  "geometry": {"coordinates":[-79.983424,40.428815],"type":"Point"}
}