{
  "type": "Feature",
  "properties": {
    "addr:full":"212 Welsh Rd Huntingdon Valley PA 19006",
    "addr:housenumber":"212",
    "addr:postcode":"19006",
    "addr:street":"Welsh Rd",
    "iso:country":"US",
    "sg:address":"212 Welsh Rd",
    "sg:city":"Huntingdon Valley",
    "sg:classifiers":[
        {
            "category":"Organizations",
            "subcategory":"Religious Organization",
            "type":"Services"
        }
    ],
    "sg:phone":"+1   ",
    "sg:postcode":"19006",
    "sg:province":"PA",
    "wof:name":"St Albert Church",
    "wof:placetype":"venue"
},
  "geometry": {"coordinates":[-75.059854,40.113978],"type":"Point"}
}