{
  "type": "Feature",
  "properties": {
    "iso:country":"US",
    "sg:address":"719 Ohio Ave",
    "sg:city":"Glassport",
    "sg:classifiers":[
        {
            "category":"Professional",
            "type":"Services"
        }
    ],
    "sg:phone":"+1   ",
    "sg:postcode":"15045",
    "sg:province":"PA",
    "wof:name":"Jh 825 Inc",
    "wof:placetype":"venue"
},
  "geometry": {"coordinates":[-79.891306,40.323013],"type":"Point"}
}