{
  "type": "Feature",
  "properties": {
    "addr:full":"1282 Lititz Pike Lancaster PA 17601",
    "addr:housenumber":"1282",
    "addr:postcode":"17601",
    "addr:street":"Lititz Pike",
    "iso:country":"US",
    "sg:address":"1282 Lititz Pike",
    "sg:city":"Lancaster",
    "sg:classifiers":[
        {
            "category":"Professional",
            "type":"Services"
        }
    ],
    "sg:phone":"+1 717 390 8688",
    "sg:postcode":"17601",
    "sg:province":"PA",
    "sg:tags":[
        "establishment"
    ],
    "wof:name":"L A Weight Loss Ctr Inc",
    "wof:placetype":"venue"
},
  "geometry": {"coordinates":[-76.306287,40.060474],"type":"Point"}
}