{
  "type": "Feature",
  "properties": {
    "iso:country":"US",
    "sg:address":"490 E Main St",
    "sg:city":"Leola",
    "sg:classifiers":[
        {
            "category":"Communications",
            "subcategory":"Film & Video Production",
            "type":"Services"
        },
        {
            "category":"Shopping",
            "subcategory":"Computers & Home Electronics",
            "type":"Retail Goods"
        }
    ],
    "sg:phone":"+1 717 656 8686",
    "sg:postcode":"17540",
    "sg:province":"PA",
    "sg:tags":[
        "taping"
    ],
    "wof:name":"Snader & Weaver Computer Svc",
    "wof:placetype":"venue"
},
  "geometry": {"coordinates":[-76.136808,40.092059],"type":"Point"}
}