{
  "type": "Feature",
  "properties": {
    "iso:country":"US",
    "sg:address":"2511 Bedford St",
    "sg:city":"Johnstown",
    "sg:classifiers":[
        {
            "category":"Home & Garden",
            "subcategory":"Carpets & Floor Coverings",
            "type":"Retail Goods"
        }
    ],
    "sg:phone":"+1   ",
    "sg:postcode":"15904",
    "sg:province":"PA",
    "wof:name":"Bobs Custom Carpets Inc",
    "wof:placetype":"venue"
},
  "geometry": {"coordinates":[-78.866142,40.294129],"type":"Point"}
}