{
  "type": "Feature",
  "properties": {
    "iso:country":"US",
    "sg:address":"765 Swamp Rd",
    "sg:city":"Newtown",
    "sg:classifiers":[
        {
            "category":"Manufacturing",
            "subcategory":"Food",
            "type":"Manufacturing & Wholesale Goods"
        }
    ],
    "sg:phone":"+1   ",
    "sg:postcode":"18940",
    "sg:province":"PA",
    "sg:tags":[
        "preparation",
        "grocery",
        "mfg"
    ],
    "wof:name":"CCS Pastosa Ravioli Inc",
    "wof:placetype":"venue"
},
  "geometry": {"coordinates":[-75.00460099999999,40.254172],"type":"Point"}
}