{
  "type": "Feature",
  "properties": {
    "iso:country":"US",
    "sg:address":"151 Southmont Blvd",
    "sg:city":"Johnstown",
    "sg:classifiers":[
        {
            "category":"Shopping",
            "subcategory":"Discount & Variety Stores",
            "type":"Retail Goods"
        }
    ],
    "sg:phone":"+1 814 535 3266",
    "sg:postcode":"15905",
    "sg:province":"PA",
    "wof:name":"Dollar General",
    "wof:placetype":"venue"
},
  "geometry": {"coordinates":[-78.92348,40.303409],"type":"Point"}
}