{
  "type": "Feature",
  "properties": {
    "iso:country":"US",
    "sg:address":"1275 Stonegate Rd",
    "sg:city":"Lansdale",
    "sg:classifiers":[
        {
            "category":"Shopping",
            "subcategory":"Hobbies, Toys, & Games",
            "type":"Retail Goods"
        },
        {
            "category":"Shopping",
            "subcategory":"Crafts & Fabrics",
            "type":"Retail Goods"
        }
    ],
    "sg:phone":"+1 215 287 8236",
    "sg:postcode":"19446",
    "sg:province":"PA",
    "sg:tags":[
        "shop",
        "hobby",
        "model",
        "supply"
    ],
    "wof:name":"Ethnic India",
    "wof:placetype":"venue"
},
  "geometry": {"coordinates":[-75.30578199999999,40.231337],"type":"Point"}
}