{
  "type": "Feature",
  "properties": {
    "addr:full":"298 California Rd Westfield PA 16950",
    "addr:housenumber":"298",
    "addr:postcode":"16950",
    "addr:street":"California Rd",
    "iso:country":"US",
    "sg:address":"298 California Rd",
    "sg:city":"Westfield",
    "sg:classifiers":[
        {
            "category":"Manufacturing",
            "subcategory":"Pet Food",
            "type":"Manufacturing & Wholesale Goods"
        },
        {
            "category":"Farming",
            "subcategory":"Farm",
            "type":"Manufacturing & Wholesale Goods"
        }
    ],
    "sg:phone":"+1 814 367 5594",
    "sg:postcode":"16950",
    "sg:province":"PA",
    "sg:tags":[
        "hay"
    ],
    "wof:name":"George Alles",
    "wof:placetype":"venue"
},
  "geometry": {"coordinates":[-77.52574300000001,41.931228],"type":"Point"}
}