{
  "type": "Feature",
  "properties": {
    "iso:country":"US",
    "sg:address":"3008 Hauck Rd",
    "sg:city":"Green Lane",
    "sg:classifiers":[
        {
            "category":"Farming",
            "subcategory":"Livestock Farm",
            "type":"Manufacturing & Wholesale Goods"
        }
    ],
    "sg:phone":"+1   ",
    "sg:postcode":"18054",
    "sg:province":"PA",
    "sg:tags":[
        "general"
    ],
    "wof:name":"Highview Estates Stock Farm",
    "wof:placetype":"venue"
},
  "geometry": {"coordinates":[-75.50051499999999,40.319344],"type":"Point"}
}