{
  "type": "Feature",
  "properties": {
    "iso:country":"US",
    "sg:address":"810 Penn Green Rd",
    "sg:city":"Landenberg",
    "sg:classifiers":[
        {
            "category":"Wholesale",
            "subcategory":"Fruits & Vegetables",
            "type":"Manufacturing & Wholesale Goods"
        }
    ],
    "sg:phone":"+1   ",
    "sg:postcode":"19350",
    "sg:province":"PA",
    "sg:tags":[
        "mushroom"
    ],
    "wof:name":"Leone Pizzini and Son Inc",
    "wof:placetype":"venue"
},
  "geometry": {"coordinates":[-75.76779500000001,39.815585],"type":"Point"}
}