{
  "type": "Feature",
  "properties": {
    "addr:full":"702 Fordham Rd Bala Cynwyd PA 19004",
    "addr:housenumber":"702",
    "addr:postcode":"19004",
    "addr:street":"Fordham Rd",
    "iso:country":"US",
    "sg:address":"702 Fordham Rd",
    "sg:city":"Bala Cynwyd",
    "sg:classifiers":[
        {
            "category":"Autos & Motor Vehicles",
            "subcategory":"Auto Supplies",
            "type":"Retail Goods"
        },
        {
            "category":"Wholesale",
            "subcategory":"Auto Parts",
            "type":"Manufacturing & Wholesale Goods"
        }
    ],
    "sg:phone":"+1 610 668 1123",
    "sg:postcode":"19004",
    "sg:province":"PA",
    "sg:tags":[
        "automobile"
    ],
    "wof:name":"Karamatic Automotive Inc",
    "wof:placetype":"venue"
},
  "geometry": {"coordinates":[-75.233222,40.020238],"type":"Point"}
}