{
  "type": "Feature",
  "properties": {
    "iso:country":"US",
    "sg:address":"826 Biddle St",
    "sg:city":"Ardmore",
    "sg:classifiers":[
        {
            "category":"Building & Trades",
            "subcategory":"Construction",
            "type":"Services"
        }
    ],
    "sg:phone":"+1   ",
    "sg:postcode":"19003",
    "sg:province":"PA",
    "sg:tags":[
        "contractor"
    ],
    "wof:name":"McGarvey & Sons",
    "wof:placetype":"venue"
},
  "geometry": {"coordinates":[-75.297702,40.001643],"type":"Point"}
}