{
  "type": "Feature",
  "properties": {
    "iso:country":"US",
    "sg:address":"402 Ridge Ave",
    "sg:city":"Springdale",
    "sg:classifiers":[
        {
            "category":"Building & Trades",
            "subcategory":"Electrical",
            "type":"Services"
        }
    ],
    "sg:phone":"+1 724 275 6614",
    "sg:postcode":"15144",
    "sg:province":"PA",
    "sg:tags":[
        "electric",
        "contractor"
    ],
    "wof:name":"Overly's Electrical Svc",
    "wof:placetype":"venue"
},
  "geometry": {"coordinates":[-79.788771,40.546847],"type":"Point"}
}