{
  "type": "Feature",
  "properties": {
    "iso:country":"US",
    "sg:address":"330 Government Pl",
    "sg:city":"Williamsport",
    "sg:classifiers":[
        {
            "category":"Manufacturing",
            "subcategory":"Printing",
            "type":"Manufacturing & Wholesale Goods"
        }
    ],
    "sg:phone":"+1   ",
    "sg:postcode":"17701",
    "sg:province":"PA",
    "sg:tags":[
        "digital"
    ],
    "wof:name":"HI-Rez Output",
    "wof:placetype":"venue"
},
  "geometry": {"coordinates":[-77.005723,41.240318],"type":"Point"}
}