{
  "type": "Feature",
  "properties": {
    "iso:country":"US",
    "sg:address":"241 Windsor Way",
    "sg:city":"Doylestown",
    "sg:classifiers":[
        {
            "category":"Real Estate",
            "subcategory":"Real Estate Agent",
            "type":"Services"
        }
    ],
    "sg:phone":"+1 215 340 5060",
    "sg:postcode":"18901",
    "sg:province":"PA",
    "wof:name":"Land & Buildings Group",
    "wof:placetype":"venue"
},
  "geometry": {"coordinates":[-75.15071,40.282842],"type":"Point"}
}