{
  "type": "Feature",
  "properties": {
    "iso:country":"US",
    "sg:address":"100 N Londonderry Sq",
    "sg:city":"Palmyra",
    "sg:classifiers":[
        {
            "category":"Personal",
            "subcategory":"Barber",
            "type":"Services"
        }
    ],
    "sg:phone":"+1 717 832 3464",
    "sg:postcode":"17078",
    "sg:province":"PA",
    "sg:website":"www.smartstyle.com",
    "wof:name":"Smartstyle",
    "wof:placetype":"venue"
},
  "geometry": {"coordinates":[-76.5672,40.319801],"type":"Point"}
}