{
  "type": "Feature",
  "properties": {
    "iso:country":"US",
    "sg:address":"46 Church St",
    "sg:city":"Montrose",
    "sg:classifiers":[
        {
            "category":"Professional",
            "subcategory":"Lawyer & Legal Services",
            "type":"Services"
        }
    ],
    "sg:phone":"+1 570 278 4075",
    "sg:postcode":"18801",
    "sg:province":"PA",
    "wof:name":"Sam W Lewis",
    "wof:placetype":"venue"
},
  "geometry": {"coordinates":[-75.87786699999999,41.832507],"type":"Point"}
}