{
  "type": "Feature",
  "properties": {
    "iso:country":"US",
    "sg:address":"408 S State St",
    "sg:city":"Newtown",
    "sg:classifiers":[
        {
            "category":"Professional",
            "subcategory":"Lawyer & Legal Services",
            "type":"Services"
        }
    ],
    "sg:phone":"+1   ",
    "sg:postcode":"18940",
    "sg:province":"PA",
    "wof:name":"Reilly & Michael",
    "wof:placetype":"venue"
},
  "geometry": {"coordinates":[-74.934799,40.222223],"type":"Point"}
}