{
  "type": "Feature",
  "properties": {
    "iso:country":"US",
    "sg:address":"140 E High St",
    "sg:city":"Manheim",
    "sg:classifiers":[
        {
            "category":"Building & Trades",
            "subcategory":"Construction",
            "type":"Services"
        }
    ],
    "sg:phone":"+1 717 665 7885",
    "sg:postcode":"17545",
    "sg:province":"PA",
    "sg:tags":[
        "painter"
    ],
    "wof:name":"Mc Geehan Painting",
    "wof:placetype":"venue"
},
  "geometry": {"coordinates":[-76.393531,40.16477],"type":"Point"}
}