{
  "type": "Feature",
  "properties": {
    "iso:country":"US",
    "sg:address":"939 N Delaware Ave",
    "sg:city":"Philadelphia",
    "sg:classifiers":[
        {
            "category":"Restaurant",
            "type":"Food & Drink"
        }
    ],
    "sg:phone":"+1 215 928 9979",
    "sg:postcode":"19123",
    "sg:province":"PA",
    "sg:tags":[
        "american",
        "seafood"
    ],
    "wof:name":"Baja Beach Club",
    "wof:placetype":"venue"
},
  "geometry": {"coordinates":[-75.135406,39.963581],"type":"Point"}
}