{
  "type": "Feature",
  "properties": {
    "addr:full":"430 Lehigh St Allentown PA 18103",
    "addr:housenumber":"430",
    "addr:postcode":"18103",
    "addr:street":"Lehigh St",
    "iso:country":"US",
    "sg:address":"430 Lehigh St",
    "sg:city":"Allentown",
    "sg:classifiers":[
        {
            "category":"Home & Garden",
            "subcategory":"Building Materials",
            "type":"Retail Goods"
        }
    ],
    "sg:phone":"+1 610 439 0738",
    "sg:postcode":"18103",
    "sg:province":"PA",
    "sg:tags":[
        "stone"
    ],
    "wof:name":"Schuylkill Stone Inc",
    "wof:placetype":"venue"
},
  "geometry": {"coordinates":[-75.467196,40.59728],"type":"Point"}
}