{
  "type": "Feature",
  "properties": {
    "iso:country":"US",
    "sg:address":"1519 Marr Rd",
    "sg:city":"Pulaski",
    "sg:classifiers":[
        {
            "category":"Professional",
            "subcategory":"Engineering",
            "type":"Services"
        }
    ],
    "sg:phone":"+1 724 964 1808",
    "sg:postcode":"16143",
    "sg:province":"PA",
    "sg:tags":[
        "system",
        "engineer"
    ],
    "wof:name":"Pulaski Engineering Co",
    "wof:placetype":"venue"
},
  "geometry": {"coordinates":[-80.482116,41.0913],"type":"Point"}
}