{
  "type": "Feature",
  "properties": {
    "addr:full":"4043 William Penn Hwy Monroeville PA 15146",
    "addr:housenumber":"4043",
    "addr:postcode":"15146",
    "addr:street":"William Penn Hwy",
    "iso:country":"US",
    "sg:address":"4043 William Penn Hwy",
    "sg:city":"Monroeville",
    "sg:classifiers":[
        {
            "category":"Home & Garden",
            "subcategory":"Home Furnishings",
            "type":"Retail Goods"
        }
    ],
    "sg:phone":"+1 412 373 2110",
    "sg:postcode":"15146",
    "sg:province":"PA",
    "sg:tags":[
        "linen"
    ],
    "wof:name":"Luxury Linens",
    "wof:placetype":"venue"
},
  "geometry": {"coordinates":[-79.769032,40.438816],"type":"Point"}
}