{
  "type": "Feature",
  "properties": {
    "iso:country":"US",
    "sg:address":"772 Pine Valley Dr",
    "sg:city":"Plum",
    "sg:classifiers":[
        {
            "category":"Wholesale",
            "subcategory":"Machinery & Supplies",
            "type":"Manufacturing & Wholesale Goods"
        }
    ],
    "sg:phone":"+1 724 327 1250",
    "sg:postcode":"15239",
    "sg:province":"PA",
    "sg:tags":[
        "equipment",
        "industrial"
    ],
    "wof:name":"Johnson Diversey Inc",
    "wof:placetype":"venue"
},
  "geometry": {"coordinates":[-79.711174,40.455077],"type":"Point"}
}