{
  "type": "Feature",
  "properties": {
    "addr:full":"205 Prospect Rd Columbia PA 17512",
    "addr:housenumber":"205",
    "addr:postcode":"17512",
    "addr:street":"Prospect Rd",
    "iso:country":"US",
    "sg:address":"205 Prospect Rd",
    "sg:city":"Columbia",
    "sg:classifiers":[
        {
            "category":"Building & Trades",
            "subcategory":"Construction",
            "type":"Services"
        }
    ],
    "sg:phone":"+1 717 684 3173",
    "sg:postcode":"17512",
    "sg:province":"PA",
    "sg:tags":[
        "excavation",
        "contractor"
    ],
    "wof:name":"G & H Excavating",
    "wof:placetype":"venue"
},
  "geometry": {"coordinates":[-76.45529399999999,40.0423],"type":"Point"}
}