{
  "type": "Feature",
  "properties": {
    "iso:country":"US",
    "sg:address":"138 S 25th St",
    "sg:city":"Pittsburgh",
    "sg:classifiers":[
        {
            "category":"Manufacturing",
            "subcategory":"Wood Products",
            "type":"Manufacturing & Wholesale Goods"
        }
    ],
    "sg:phone":"+1 412 381 7700",
    "sg:postcode":"15203",
    "sg:province":"PA",
    "sg:tags":[
        "wall",
        "fiber",
        "plaque",
        "mfg"
    ],
    "wof:name":"Soroka Sales Inc",
    "wof:placetype":"venue"
},
  "geometry": {"coordinates":[-79.971019,40.425336],"type":"Point"}
}