{
  "type": "Feature",
  "properties": {
    "iso:country":"US",
    "sg:address":"606 Continental Blvd",
    "sg:city":"Danville",
    "sg:classifiers":[
        {
            "category":"Cinema",
            "subcategory":"Movie Rental",
            "type":"Entertainment"
        }
    ],
    "sg:phone":"+1 570 271 1042",
    "sg:postcode":"17821",
    "sg:province":"PA",
    "sg:tags":[
        "leasing",
        "video",
        "disc",
        "tape"
    ],
    "wof:name":"Movie Gallery",
    "wof:placetype":"venue"
},
  "geometry": {"coordinates":[-76.61774200000001,40.964225],"type":"Point"}
}