{
  "type": "Feature",
  "properties": {
    "iso:country":"US",
    "sg:address":"157 Deep Run Rd",
    "sg:city":"Perkasie",
    "sg:classifiers":[
        {
            "category":"Home & Garden",
            "subcategory":"Building Materials",
            "type":"Retail Goods"
        },
        {
            "category":"Manufacturing",
            "subcategory":"Building Materials",
            "type":"Manufacturing & Wholesale Goods"
        }
    ],
    "sg:phone":"+1 215 322 8669",
    "sg:postcode":"18944",
    "sg:province":"PA",
    "sg:tags":[
        "door",
        "accessory",
        "garage",
        "opener",
        "doors",
        "frames"
    ],
    "sg:website":"http://www.nrgenterprises.com",
    "wof:name":"Academy Plus Over Head Door",
    "wof:placetype":"venue"
},
  "geometry": {"coordinates":[-75.1994,40.377244],"type":"Point"}
}