{
  "type": "Feature",
  "properties": {
    "addr:full":"1422 Callowhill St Philadelphia PA 19130",
    "addr:housenumber":"1422",
    "addr:postcode":"19130",
    "addr:street":"Callowhill St",
    "iso:country":"US",
    "sg:address":"1422 Callowhill St",
    "sg:city":"Philadelphia",
    "sg:classifiers":[
        {
            "category":"Manufacturing",
            "subcategory":"Printing",
            "type":"Manufacturing & Wholesale Goods"
        }
    ],
    "sg:phone":"+1   ",
    "sg:postcode":"19130",
    "sg:province":"PA",
    "sg:tags":[
        "mfg"
    ],
    "wof:name":"Looseleaf Binder Company",
    "wof:placetype":"venue"
},
  "geometry": {"coordinates":[-75.163443,39.959694],"type":"Point"}
}