{
  "type": "Feature",
  "properties": {
    "iso:country":"US",
    "sg:address":"202 E Plane St",
    "sg:city":"Gordon",
    "sg:classifiers":[
        {
            "category":"Manufacturing",
            "subcategory":"Furniture",
            "type":"Manufacturing & Wholesale Goods"
        }
    ],
    "sg:phone":"+1 570 875 3790",
    "sg:postcode":"17936",
    "sg:province":"PA",
    "sg:tags":[
        "upholstered",
        "wood"
    ],
    "wof:name":"Wolfgang's Woodcraft",
    "wof:placetype":"venue"
},
  "geometry": {"coordinates":[-76.34056200000001,40.748407],"type":"Point"}
}