{
  "type": "Feature",
  "properties": {
    "iso:country":"US",
    "sg:address":"23 Andover Dr",
    "sg:city":"Exton",
    "sg:classifiers":[
        {
            "category":"Building & Trades",
            "subcategory":"Construction",
            "type":"Services"
        }
    ],
    "sg:phone":"+1 610 363 0635",
    "sg:postcode":"19341",
    "sg:province":"PA",
    "sg:tags":[
        "equipment",
        "supply",
        "drywall",
        "contractor"
    ],
    "wof:name":"Eagle House Contractors Inc",
    "wof:placetype":"venue"
},
  "geometry": {"coordinates":[-75.649472,40.052704],"type":"Point"}
}