{
  "type": "Feature",
  "properties": {
    "iso:country":"US",
    "sg:address":"619 Canal Rd",
    "sg:city":"Womelsdorf",
    "sg:classifiers":[
        {
            "category":"Retail",
            "subcategory":"Auto Repair",
            "type":"Services"
        }
    ],
    "sg:phone":"+1   ",
    "sg:postcode":"19567",
    "sg:province":"PA",
    "sg:tags":[
        "general"
    ],
    "wof:name":"Hermans Auto Reconditioning",
    "wof:placetype":"venue"
},
  "geometry": {"coordinates":[-76.207015,40.375018],"type":"Point"}
}