{
  "type": "Feature",
  "properties": {
    "addr:full":"210 Gulph Creek Rd Radnor PA 19087",
    "addr:housenumber":"210",
    "addr:postcode":"19087",
    "addr:street":"Gulph Creek Rd",
    "iso:country":"US",
    "sg:address":"210 Gulph Creek Rd",
    "sg:city":"Radnor",
    "sg:classifiers":[
        {
            "category":"Banks & Credit Unions",
            "subcategory":"Investment Brokerage",
            "type":"Services"
        }
    ],
    "sg:phone":"+1 610 687 9178",
    "sg:postcode":"19087",
    "sg:province":"PA",
    "sg:tags":[
        "advisory",
        "financial"
    ],
    "wof:name":"Somers Asset Management Inc",
    "wof:placetype":"venue"
},
  "geometry": {"coordinates":[-75.36236100000001,40.052743],"type":"Point"}
}