{
  "type": "Feature",
  "properties": {
    "iso:country":"US",
    "sg:address":"154 Snyder Ave",
    "sg:city":"Butler",
    "sg:classifiers":[
        {
            "category":"Food & Beverages",
            "subcategory":"Candy",
            "type":"Retail Goods"
        }
    ],
    "sg:phone":"+1 724 282 3006",
    "sg:postcode":"16001",
    "sg:province":"PA",
    "sg:tags":[
        "confectionery"
    ],
    "wof:name":"Barkus Chocolates",
    "wof:placetype":"venue"
},
  "geometry": {"coordinates":[-79.904642,40.862515],"type":"Point"}
}