{
  "type": "Feature",
  "properties": {
    "iso:country":"US",
    "sg:address":"3401 W Chester Pike",
    "sg:city":"Newtown Square",
    "sg:classifiers":[
        {
            "category":"Professional",
            "subcategory":"Lawyer & Legal Services",
            "type":"Services"
        }
    ],
    "sg:phone":"+1 610 353 6530",
    "sg:postcode":"19073",
    "sg:province":"PA",
    "sg:tags":[
        "attorney"
    ],
    "wof:name":"Christina M Kane",
    "wof:placetype":"venue"
},
  "geometry": {"coordinates":[-75.386349,39.984277],"type":"Point"}
}