{
  "type": "Feature",
  "properties": {
    "iso:country":"US",
    "sg:address":"8840 Peffer Rd",
    "sg:city":"Fairview",
    "sg:classifiers":[
        {
            "category":"Retail",
            "subcategory":"Repair Shop",
            "type":"Services"
        }
    ],
    "sg:phone":"+1 814 474 2744",
    "sg:postcode":"16415",
    "sg:province":"PA",
    "sg:tags":[
        "welding"
    ],
    "wof:name":"Inchco",
    "wof:placetype":"venue"
},
  "geometry": {"coordinates":[-80.20159700000001,41.98686],"type":"Point"}
}