{
  "type": "Feature",
  "properties": {
    "iso:country":"US",
    "sg:address":"440 Cloverleaf Rd",
    "sg:city":"Elizabethtown",
    "sg:classifiers":[
        {
            "category":"Organizations",
            "subcategory":"Religious Organization",
            "type":"Services"
        }
    ],
    "sg:phone":"+1 717 367 6148",
    "sg:postcode":"17022",
    "sg:province":"PA",
    "sg:tags":[
        "church"
    ],
    "wof:name":"Brethren In Christ Church-Atln",
    "wof:placetype":"venue"
},
  "geometry": {"coordinates":[-76.56332,40.133945],"type":"Point"}
}