{
  "type": "Feature",
  "properties": {
    "iso:country":"US",
    "sg:address":"131 Clover Ln",
    "sg:city":"Palmyra",
    "sg:classifiers":[
        {
            "category":"Professional",
            "subcategory":"Art Services",
            "type":"Services"
        }
    ],
    "sg:phone":"+1 717 838 5251",
    "sg:postcode":"17078",
    "sg:province":"PA",
    "sg:tags":[
        "graphic",
        "designer"
    ],
    "wof:name":"Todd Krick Graphic Design",
    "wof:placetype":"venue"
},
  "geometry": {"coordinates":[-76.601229,40.295004],"type":"Point"}
}