{
  "type": "Feature",
  "properties": {
    "addr:full":"414 Harvard Ave Broomall PA 19008",
    "addr:housenumber":"414",
    "addr:postcode":"19008",
    "addr:street":"Harvard Ave",
    "iso:country":"US",
    "sg:address":"414 Harvard Ave",
    "sg:city":"Broomall",
    "sg:classifiers":[
        {
            "category":"Manufacturing",
            "subcategory":"Tools & Machinery",
            "type":"Manufacturing & Wholesale Goods"
        }
    ],
    "sg:phone":"+1   ",
    "sg:postcode":"19008",
    "sg:province":"PA",
    "sg:tags":[
        "mfg"
    ],
    "wof:name":"A Pour Die Co Inc",
    "wof:placetype":"venue"
},
  "geometry": {"coordinates":[-75.35816800000001,39.970134],"type":"Point"}
}