{
  "type": "Feature",
  "properties": {
    "iso:country":"US",
    "sg:address":"1932 S 4th St",
    "sg:city":"Allentown",
    "sg:classifiers":[
        {
            "category":"Shopping",
            "type":"Retail Goods"
        }
    ],
    "sg:phone":"+1 610 797 7000",
    "sg:postcode":"18103",
    "sg:province":"PA",
    "sg:tags":[
        "burglar",
        "installs",
        "alarm",
        "system",
        "fire",
        "protection"
    ],
    "sg:website":"http://www.protectalarms.com",
    "wof:name":"Protect Alarms",
    "wof:placetype":"venue"
},
  "geometry": {"coordinates":[-75.455279,40.579312],"type":"Point"}
}