{
  "type": "Feature",
  "properties": {
    "iso:country":"US",
    "sg:address":"43 N Delaware Dr",
    "sg:city":"Easton",
    "sg:classifiers":[
        {
            "category":"Professional",
            "subcategory":"Management & Consulting",
            "type":"Services"
        }
    ],
    "sg:phone":"+1 610 923 6699",
    "sg:postcode":"18042",
    "sg:province":"PA",
    "sg:tags":[
        "consultant",
        "automation"
    ],
    "wof:name":"United Automation Inc",
    "wof:placetype":"venue"
},
  "geometry": {"coordinates":[-75.204556,40.696734],"type":"Point"}
}