{
  "type": "Feature",
  "properties": {
    "addr:full":"105 S Front St Souderton PA 18964",
    "addr:housenumber":"105",
    "addr:postcode":"18964",
    "addr:street":"S Front St",
    "iso:country":"US",
    "sg:address":"105 S Front St",
    "sg:city":"Souderton",
    "sg:classifiers":[
        {
            "category":"Building & Trades",
            "subcategory":"Electrical",
            "type":"Services"
        }
    ],
    "sg:phone":"+1 215 721 7183",
    "sg:postcode":"18964",
    "sg:province":"PA",
    "sg:tags":[
        "electrician",
        "contractor"
    ],
    "wof:name":"Ron Beck Electric",
    "wof:placetype":"venue"
},
  "geometry": {"coordinates":[-75.318912,40.308416],"type":"Point"}
}