{
  "type": "Feature",
  "properties": {
    "addr:full":"2746 Plank Rd Altoona PA 16650",
    "addr:housenumber":"2746",
    "addr:postcode":"16650",
    "addr:street":"Plank Rd",
    "iso:country":"US",
    "sg:address":"2746 Plank Rd",
    "sg:city":"Altoona",
    "sg:classifiers":[
        {
            "category":"Shopping",
            "subcategory":"Discount & Variety Stores",
            "type":"Retail Goods"
        }
    ],
    "sg:phone":"+1   ",
    "sg:postcode":"16650",
    "sg:province":"PA",
    "wof:name":"Dollar Tree",
    "wof:placetype":"venue"
},
  "geometry": {"coordinates":[-78.313954,40.110156],"type":"Point"}
}