{
  "type": "Feature",
  "properties": {
    "addr:full":"4444 Marywood Dr Monroeville PA 15146",
    "addr:housenumber":"4444",
    "addr:postcode":"15146",
    "addr:street":"Marywood Dr",
    "iso:country":"US",
    "sg:address":"4444 Marywood Dr",
    "sg:city":"Monroeville",
    "sg:classifiers":[
        {
            "category":"Building & Trades",
            "subcategory":"Construction",
            "type":"Services"
        }
    ],
    "sg:phone":"+1   ",
    "sg:postcode":"15146",
    "sg:province":"PA",
    "sg:tags":[
        "concrete",
        "contractor"
    ],
    "wof:name":"John Varrati Cement Contg Co",
    "wof:placetype":"venue"
},
  "geometry": {"coordinates":[-79.75653,40.452174],"type":"Point"}
}