{
  "type": "Feature",
  "properties": {
    "iso:country":"US",
    "sg:address":"221 Trailing Pine Rd",
    "sg:city":"Shickshinny",
    "sg:classifiers":[
        {
            "category":"Autos & Motor Vehicles",
            "subcategory":"Auto Supplies",
            "type":"Retail Goods"
        }
    ],
    "sg:phone":"+1   ",
    "sg:postcode":"18655",
    "sg:province":"PA",
    "sg:tags":[
        "automotive",
        "repair"
    ],
    "wof:name":"ZS Tire & Auto Service",
    "wof:placetype":"venue"
},
  "geometry": {"coordinates":[-76.153593,41.177316],"type":"Point"}
}