{
  "type": "Feature",
  "properties": {
    "iso:country":"US",
    "sg:address":"2744 W Washington St",
    "sg:city":"Allentown",
    "sg:classifiers":[
        {
            "category":"Professional",
            "subcategory":"Management & Consulting",
            "type":"Services"
        }
    ],
    "sg:phone":"+1 610 821 7777",
    "sg:postcode":"18104",
    "sg:province":"PA",
    "sg:tags":[
        "consultant",
        "business"
    ],
    "sg:website":"www.inforum.org",
    "wof:name":"Executive Technology Assoc",
    "wof:placetype":"venue"
},
  "geometry": {"coordinates":[-75.52040100000001,40.601435],"type":"Point"}
}