{
  "type": "Feature",
  "properties": {
    "addr:full":"138 S 2nd St Bangor PA 18013",
    "addr:housenumber":"138",
    "addr:postcode":"18013",
    "addr:street":"S 2Nd St",
    "iso:country":"US",
    "sg:address":"138 S 2nd St",
    "sg:city":"Bangor",
    "sg:classifiers":[
        {
            "category":"Personal",
            "subcategory":"Beauty Salon",
            "type":"Services"
        }
    ],
    "sg:phone":"+1   ",
    "sg:postcode":"18013",
    "sg:province":"PA",
    "sg:tags":[
        "shop"
    ],
    "wof:name":"Family Salon",
    "wof:placetype":"venue"
},
  "geometry": {"coordinates":[-75.20752899999999,40.865529],"type":"Point"}
}