{
  "type": "Feature",
  "properties": {
    "iso:country":"US",
    "sg:address":"1800 Mearns Rd",
    "sg:city":"Warminster",
    "sg:classifiers":[
        {
            "category":"Manufacturing",
            "subcategory":"Metals",
            "type":"Manufacturing & Wholesale Goods"
        }
    ],
    "sg:phone":"+1 215 441 8210",
    "sg:postcode":"18974",
    "sg:province":"PA",
    "sg:tags":[
        "stamping"
    ],
    "wof:name":"RMC Inc",
    "wof:placetype":"venue"
},
  "geometry": {"coordinates":[-75.067837,40.227266],"type":"Point"}
}