{
  "type": "Feature",
  "properties": {
    "iso:country":"US",
    "sg:address":"2080 Newville Rd",
    "sg:city":"Plainfield",
    "sg:classifiers":[
        {
            "category":"Retail",
            "subcategory":"Auto Rental",
            "type":"Services"
        }
    ],
    "sg:phone":"+1 717 243 4940",
    "sg:postcode":"17081",
    "sg:province":"PA",
    "sg:tags":[
        "renting",
        "truck",
        "leasing"
    ],
    "wof:name":"GET Inc",
    "wof:placetype":"venue"
},
  "geometry": {"coordinates":[-77.288335,40.20306],"type":"Point"}
}