{
  "type": "Feature",
  "properties": {
    "iso:country":"US",
    "sg:address":"7619 Vincent Rd",
    "sg:city":"Cochranton",
    "sg:classifiers":[
        {
            "category":"Local Transit",
            "type":"Transportation"
        }
    ],
    "sg:phone":"+1 814 425 3603",
    "sg:postcode":"16314",
    "sg:province":"PA",
    "sg:tags":[
        "bus",
        "line"
    ],
    "wof:name":"Girardat Transportation",
    "wof:placetype":"venue"
},
  "geometry": {"coordinates":[-79.99293,41.581265],"type":"Point"}
}