{
  "type": "Feature",
  "properties": {
    "addr:full":"1410 N 5th St Stroudsburg PA 18360",
    "addr:housenumber":"1410",
    "addr:postcode":"18360",
    "addr:street":"N 5Th St",
    "iso:country":"US",
    "sg:address":"1410 N 5th St",
    "sg:city":"Stroudsburg",
    "sg:classifiers":[
        {
            "category":"Retail",
            "subcategory":"Auto Repair",
            "type":"Services"
        }
    ],
    "sg:phone":"+1 570 421 3329",
    "sg:postcode":"18360",
    "sg:province":"PA",
    "sg:tags":[
        "towing"
    ],
    "wof:name":"Treible's Wrecker Svc & Auto",
    "wof:placetype":"venue"
},
  "geometry": {"coordinates":[-75.19962,41.003275],"type":"Point"}
}