{
  "type": "Feature",
  "properties": {
    "addr:full":"2489 Curwensville Grampian Rd Grampian PA 16838",
    "addr:housenumber":"2489",
    "addr:postcode":"16838",
    "addr:street":"Grampian Rd",
    "iso:country":"US",
    "sg:address":"2489 Curwensville Grampian Rd",
    "sg:city":"Grampian",
    "sg:classifiers":[
        {
            "category":"Bars & Pubs",
            "type":"Food & Drink"
        }
    ],
    "sg:phone":"+1 814 236 0167",
    "sg:postcode":"16838",
    "sg:province":"PA",
    "wof:name":"Wildwood Tavern Inc",
    "wof:placetype":"venue"
},
  "geometry": {"coordinates":[-78.57453599999999,40.971359],"type":"Point"}
}