{
  "type": "Feature",
  "properties": {
    "addr:full":"131 Washington Ln Wyncote PA 19095",
    "addr:housenumber":"131",
    "addr:postcode":"19095",
    "addr:street":"Washington Ln",
    "iso:country":"US",
    "sg:address":"131 Washington Ln",
    "sg:city":"Wyncote",
    "sg:classifiers":[
        {
            "category":"Building & Trades",
            "subcategory":"Landscaping Services",
            "type":"Services"
        }
    ],
    "sg:phone":"+1 215 884 4978",
    "sg:postcode":"19095",
    "sg:province":"PA",
    "sg:tags":[
        "landscape"
    ],
    "wof:name":"Baker Creative Inc",
    "wof:placetype":"venue"
},
  "geometry": {"coordinates":[-75.139218,40.08647],"type":"Point"}
}