{
  "type": "Feature",
  "properties": {
    "iso:country":"US",
    "sg:address":"5022 Delta Rd",
    "sg:city":"Delta",
    "sg:classifiers":[
        {
            "category":"Social Services",
            "subcategory":"Child Care",
            "type":"Services"
        }
    ],
    "sg:phone":"+1   ",
    "sg:postcode":"17314",
    "sg:province":"PA",
    "sg:tags":[
        "day"
    ],
    "wof:name":"Salem Community Nursery School",
    "wof:placetype":"venue"
},
  "geometry": {"coordinates":[-76.359864,39.789474],"type":"Point"}
}