{
  "type": "Feature",
  "properties": {
    "iso:country":"US",
    "sg:address":"208 Saint David Ct",
    "sg:city":"Wayne",
    "sg:classifiers":[
        {
            "category":"Professional",
            "type":"Services"
        }
    ],
    "sg:phone":"+1   ",
    "sg:postcode":"19087",
    "sg:province":"PA",
    "wof:name":"Mark V Pauly",
    "wof:placetype":"venue"
},
  "geometry": {"coordinates":[-75.37441699999999,40.04014],"type":"Point"}
}