{
  "type": "Feature",
  "properties": {
    "iso:country":"US",
    "sg:address":"300 E Louther St",
    "sg:city":"Carlisle",
    "sg:classifiers":[
        {
            "category":"Shopping",
            "subcategory":"Bicycles & Sporting Goods",
            "type":"Retail Goods"
        }
    ],
    "sg:phone":"+1   ",
    "sg:postcode":"17013",
    "sg:province":"PA",
    "sg:tags":[
        "repair"
    ],
    "wof:name":"Morrows Pro Shop",
    "wof:placetype":"venue"
},
  "geometry": {"coordinates":[-77.182281,40.202483],"type":"Point"}
}