{
  "type": "Feature",
  "properties": {
    "iso:country":"US",
    "sg:address":"1029 Country Club Rd",
    "sg:city":"Monongahela",
    "sg:classifiers":[
        {
            "category":"Health Services",
            "subcategory":"Doctor",
            "type":"Services"
        }
    ],
    "sg:phone":"+1 724 258 9680",
    "sg:postcode":"15063",
    "sg:province":"PA",
    "wof:name":"Mathur Ajay MD",
    "wof:placetype":"venue"
},
  "geometry": {"coordinates":[-79.918701,40.190201],"type":"Point"}
}