{
  "type": "Feature",
  "properties": {
    "iso:country":"US",
    "sg:address":"82 Quarry Rd",
    "sg:city":"Downingtown",
    "sg:classifiers":[
        {
            "category":"Banks & Credit Unions",
            "subcategory":"Bank",
            "type":"Services"
        }
    ],
    "sg:phone":"+1   ",
    "sg:postcode":"19335",
    "sg:province":"PA",
    "sg:tags":[
        "savings",
        "institution"
    ],
    "wof:name":"Brandywine Square Office",
    "wof:placetype":"venue"
},
  "geometry": {"coordinates":[-75.675363,40.018568],"type":"Point"}
}