{
  "type": "Feature",
  "properties": {
    "iso:country":"US",
    "sg:address":"316 Main St",
    "sg:city":"Emmaus",
    "sg:classifiers":[
        {
            "category":"Organizations",
            "subcategory":"Community Association",
            "type":"Services"
        }
    ],
    "sg:phone":"+1 610 965 6590",
    "sg:postcode":"18049",
    "sg:province":"PA",
    "sg:tags":[
        "center",
        "facility",
        "hall",
        "nightlife",
        "reception",
        "bowling",
        "drinking",
        "banquet"
    ],
    "wof:name":"Emmaus Nest of Owls",
    "wof:placetype":"venue"
},
  "geometry": {"coordinates":[-75.490799,40.5355],"type":"Point"}
}