{
  "type": "Feature",
  "properties": {
    "iso:country":"US",
    "sg:address":"713 N 10th St",
    "sg:city":"Philadelphia",
    "sg:classifiers":[
        {
            "category":"Wholesale",
            "subcategory":"Groceries",
            "type":"Manufacturing & Wholesale Goods"
        }
    ],
    "sg:phone":"+1 215 765 3289",
    "sg:postcode":"19123",
    "sg:province":"PA",
    "sg:tags":[
        "health",
        "market"
    ],
    "sg:website":"www.naturesoyonline.com",
    "wof:name":"Nature Soy Inc",
    "wof:placetype":"venue"
},
  "geometry": {"coordinates":[-75.153702,39.9659],"type":"Point"}
}