{
  "type": "Feature",
  "properties": {
    "iso:country":"US",
    "sg:address":"1407 Dwight Dr",
    "sg:city":"Johnstown",
    "sg:classifiers":[
        {
            "category":"Food & Beverages",
            "subcategory":"Groceries & Convenience Stores",
            "type":"Retail Goods"
        }
    ],
    "sg:phone":"+1 814 266 5311",
    "sg:postcode":"15904",
    "sg:province":"PA",
    "sg:tags":[
        "grocer"
    ],
    "wof:name":"Market Basket Inc",
    "wof:placetype":"venue"
},
  "geometry": {"coordinates":[-78.861699,40.267795],"type":"Point"}
}