{
  "type": "Feature",
  "properties": {
    "iso:country":"US",
    "sg:address":"13078 Old Plank Rd",
    "sg:city":"Waterford",
    "sg:classifiers":[
        {
            "category":"Professional",
            "subcategory":"Engineering",
            "type":"Services"
        }
    ],
    "sg:phone":"+1 814 796 3297",
    "sg:postcode":"16441",
    "sg:province":"PA",
    "wof:name":"Trusted Building & Remodeling",
    "wof:placetype":"venue"
},
  "geometry": {"coordinates":[-80.034604,41.893923],"type":"Point"}
}