{
  "type": "Feature",
  "properties": {
    "addr:full":"15 S Main St Mansfield PA 16933",
    "addr:housenumber":"15",
    "addr:postcode":"16933",
    "addr:street":"S Main St",
    "iso:country":"US",
    "sg:address":"15 S Main St",
    "sg:city":"Mansfield",
    "sg:classifiers":[
        {
            "category":"Banks & Credit Unions",
            "subcategory":"Bank",
            "type":"Services"
        }
    ],
    "sg:phone":"+1   ",
    "sg:postcode":"16933",
    "sg:province":"PA",
    "sg:tags":[
        "national"
    ],
    "wof:name":"Citizens Financial Services",
    "wof:placetype":"venue"
},
  "geometry": {"coordinates":[-77.077867,41.806743],"type":"Point"}
}