{
  "type": "Feature",
  "properties": {
    "iso:country":"US",
    "sg:address":"828 W Main St",
    "sg:city":"Mount Pleasant",
    "sg:classifiers":[
        {
            "category":"Health Services",
            "subcategory":"Doctor",
            "type":"Services"
        }
    ],
    "sg:phone":"+1   ",
    "sg:postcode":"15666",
    "sg:province":"PA",
    "wof:name":"Habiba Health Services Inc",
    "wof:placetype":"venue"
},
  "geometry": {"coordinates":[-79.54821,40.152007],"type":"Point"}
}