{
  "type": "Feature",
  "properties": {
    "iso:country":"US",
    "sg:address":"918 Ridge Rd",
    "sg:city":"Bridgeville",
    "sg:classifiers":[
        {
            "category":"Building & Trades",
            "subcategory":"Construction",
            "type":"Services"
        }
    ],
    "sg:phone":"+1   ",
    "sg:postcode":"15017",
    "sg:province":"PA",
    "sg:tags":[
        "hanging",
        "contractor"
    ],
    "wof:name":"Lakus Painting",
    "wof:placetype":"venue"
},
  "geometry": {"coordinates":[-80.101857,40.355591],"type":"Point"}
}