{
  "type": "Feature",
  "properties": {
    "addr:full":"1438 Margaret Ct Jamison PA 18929",
    "addr:housenumber":"1438",
    "addr:postcode":"18929",
    "addr:street":"Margaret Ct",
    "iso:country":"US",
    "sg:address":"1438 Margaret Ct",
    "sg:city":"Jamison",
    "sg:classifiers":[
        {
            "category":"Insurance",
            "subcategory":"Insurance Agent",
            "type":"Services"
        }
    ],
    "sg:phone":"+1 215 918 0404",
    "sg:postcode":"18929",
    "sg:province":"PA",
    "wof:name":"Prudential Insurance Co",
    "wof:placetype":"venue"
},
  "geometry": {"coordinates":[-75.084329,40.262288],"type":"Point"}
}