{
  "type": "Feature",
  "properties": {
    "iso:country":"US",
    "sg:address":"2012 Spruce St",
    "sg:city":"Philadelphia",
    "sg:classifiers":[
        {
            "category":"Health Services",
            "subcategory":"Doctor",
            "type":"Services"
        }
    ],
    "sg:phone":"+1 215 546 1454",
    "sg:postcode":"19103",
    "sg:province":"PA",
    "sg:tags":[
        "physician",
        "surgeon"
    ],
    "wof:name":"L J Bird Md",
    "wof:placetype":"venue"
},
  "geometry": {"coordinates":[-75.17455200000001,39.948211],"type":"Point"}
}