{
  "type": "Feature",
  "properties": {
    "addr:full":"990 Broad St Greensburg PA 15601",
    "addr:housenumber":"990",
    "addr:postcode":"15601",
    "addr:street":"Broad St",
    "iso:country":"US",
    "sg:address":"990 Broad St",
    "sg:city":"Greensburg",
    "sg:classifiers":[
        {
            "category":"Wholesale",
            "subcategory":"Hardware",
            "type":"Manufacturing & Wholesale Goods"
        }
    ],
    "sg:phone":"+1 724 836 6319",
    "sg:postcode":"15601",
    "sg:province":"PA",
    "sg:tags":[
        "plumbing",
        "p",
        "merchandise"
    ],
    "wof:name":"Robertson Heating Supply Co",
    "wof:placetype":"venue"
},
  "geometry": {"coordinates":[-79.54486900000001,40.285697],"type":"Point"}
}