{
  "type": "Feature",
  "properties": {
    "addr:full":"63 Hampshire Rd Reading PA 19608",
    "addr:housenumber":"63",
    "addr:postcode":"19608",
    "addr:street":"Hampshire Rd",
    "iso:country":"US",
    "sg:address":"63 Hampshire Rd",
    "sg:city":"Reading",
    "sg:classifiers":[
        {
            "category":"Wholesale",
            "subcategory":"Machinery & Supplies",
            "type":"Manufacturing & Wholesale Goods"
        }
    ],
    "sg:phone":"+1   ",
    "sg:postcode":"19608",
    "sg:province":"PA",
    "sg:tags":[
        "steel",
        "pipe",
        "fitting",
        "valve",
        "tubing"
    ],
    "wof:name":"Duffeys",
    "wof:placetype":"venue"
},
  "geometry": {"coordinates":[-76.00675699999999,40.275362],"type":"Point"}
}