{
  "type": "Feature",
  "properties": {
    "addr:full":"1138 N Main St Butler PA 16001",
    "addr:housenumber":"1138",
    "addr:postcode":"16001",
    "addr:street":"N Main St",
    "iso:country":"US",
    "sg:address":"1138 N Main St",
    "sg:city":"Butler",
    "sg:classifiers":[
        {
            "category":"Shopping",
            "subcategory":"Bicycles & Sporting Goods",
            "type":"Retail Goods"
        }
    ],
    "sg:phone":"+1 724 283 5898",
    "sg:postcode":"16001",
    "sg:province":"PA",
    "sg:tags":[
        "equipment",
        "golf",
        "accessory"
    ],
    "wof:name":"Golf Etc",
    "wof:placetype":"venue"
},
  "geometry": {"coordinates":[-79.902113,40.885996],"type":"Point"}
}