{
  "type": "Feature",
  "properties": {
    "addr:full":"5123 Penn Ave Pittsburgh PA 15224",
    "addr:housenumber":"5123",
    "addr:postcode":"15224",
    "addr:street":"Penn Ave",
    "iso:country":"US",
    "sg:address":"5123 Penn Ave",
    "sg:city":"Pittsburgh",
    "sg:classifiers":[
        {
            "category":"Shopping",
            "subcategory":"Used Merchandise",
            "type":"Retail Goods"
        }
    ],
    "sg:phone":"+1 412 361 6010",
    "sg:postcode":"15224",
    "sg:province":"PA",
    "wof:name":"East End Community Thrift",
    "wof:placetype":"venue"
},
  "geometry": {"coordinates":[-79.94183200000001,40.464925],"type":"Point"}
}