{
  "type": "Feature",
  "properties": {
    "addr:full":"330 4th St Blawnox PA 15238",
    "addr:housenumber":"330",
    "addr:postcode":"15238",
    "addr:street":"4Th St",
    "iso:country":"US",
    "sg:address":"330 4th St",
    "sg:city":"Blawnox",
    "sg:classifiers":[
        {
            "category":"Organizations",
            "subcategory":"Religious Organization",
            "type":"Services"
        }
    ],
    "sg:phone":"+1 412 271 0303",
    "sg:postcode":"15238",
    "sg:province":"PA",
    "sg:tags":[
        "church"
    ],
    "wof:name":"Mt Olive Baptist Church",
    "wof:placetype":"venue"
},
  "geometry": {"coordinates":[-79.862359,40.490104],"type":"Point"}
}