{
  "type": "Feature",
  "properties": {
    "addr:full":"360 Main Rd Pitman PA 17964",
    "addr:housenumber":"360",
    "addr:postcode":"17964",
    "addr:street":"Main Rd",
    "iso:country":"US",
    "sg:address":"360 Main Rd",
    "sg:city":"Pitman",
    "sg:classifiers":[
        {
            "category":"Building & Trades",
            "subcategory":"Construction",
            "type":"Services"
        }
    ],
    "sg:phone":"+1   ",
    "sg:postcode":"17964",
    "sg:province":"PA",
    "sg:tags":[
        "house"
    ],
    "wof:name":"John A Heim General Contg",
    "wof:placetype":"venue"
},
  "geometry": {"coordinates":[-76.543576,40.712792],"type":"Point"}
}