{
  "type": "Feature",
  "properties": {
    "iso:country":"US",
    "sg:address":"99 Duquesne Blvd",
    "sg:city":"Duquesne",
    "sg:classifiers":[
        {
            "category":"Retail",
            "subcategory":"Auto Repair",
            "type":"Services"
        }
    ],
    "sg:phone":"+1   ",
    "sg:postcode":"15110",
    "sg:province":"PA",
    "sg:tags":[
        "automotive",
        "station",
        "gasoline"
    ],
    "wof:name":"Leos Service Center",
    "wof:placetype":"venue"
},
  "geometry": {"coordinates":[-79.845342,40.374225],"type":"Point"}
}