{
  "type": "Feature",
  "properties": {
    "iso:country":"US",
    "sg:address":"446 McCombs Rd",
    "sg:city":"Venetia",
    "sg:classifiers":[
        {
            "category":"Arts & Performance",
            "subcategory":"Theater",
            "type":"Entertainment"
        }
    ],
    "sg:phone":"+1   ",
    "sg:postcode":"15367",
    "sg:province":"PA",
    "sg:tags":[
        "group"
    ],
    "wof:name":"Daniel Lutes",
    "wof:placetype":"venue"
},
  "geometry": {"coordinates":[-80.05620999999999,40.257553],"type":"Point"}
}