{
  "type": "Feature",
  "properties": {
    "iso:country":"US",
    "sg:address":"1153 W High St",
    "sg:city":"Ebensburg",
    "sg:classifiers":[
        {
            "category":"Food & Beverages",
            "subcategory":"Specialty",
            "type":"Retail Goods"
        },
        {
            "category":"Health Services",
            "subcategory":"Health Practitioner",
            "type":"Services"
        }
    ],
    "sg:phone":"+1 814 471 9588",
    "sg:postcode":"15931",
    "sg:province":"PA",
    "sg:tags":[
        "diet"
    ],
    "wof:name":"A Healing Touch",
    "wof:placetype":"venue"
},
  "geometry": {"coordinates":[-78.738544,40.479438],"type":"Point"}
}