{
  "type": "Feature",
  "properties": {
    "iso:country":"US",
    "sg:address":"311 Mattson Rd",
    "sg:city":"Boothwyn",
    "sg:classifiers":[
        {
            "category":"Education",
            "subcategory":"Special Training",
            "type":"Public Place"
        }
    ],
    "sg:phone":"+1 610 358 5577",
    "sg:postcode":"19061",
    "sg:province":"PA",
    "sg:tags":[
        "instruction",
        "driving"
    ],
    "wof:name":"A & B Driving School",
    "wof:placetype":"venue"
},
  "geometry": {"coordinates":[-75.483502,39.870712],"type":"Point"}
}