{
  "type": "Feature",
  "properties": {
    "iso:country":"US",
    "sg:address":"449 E 9th St",
    "sg:city":"Erie",
    "sg:classifiers":[
        {
            "category":"Retail",
            "subcategory":"Funeral Services",
            "type":"Services"
        }
    ],
    "sg:phone":"+1 814 454 7151",
    "sg:postcode":"16503",
    "sg:province":"PA",
    "sg:tags":[
        "plan"
    ],
    "sg:website":"www.bruggerfuneralhomes.com",
    "wof:name":"A Brugger & Sons LLP",
    "wof:placetype":"venue"
},
  "geometry": {"coordinates":[-80.07319,42.130041],"type":"Point"}
}