{
  "type": "Feature",
  "properties": {
    "iso:country":"US",
    "sg:address":"1218 Chestnut St Ste 409",
    "sg:city":"Philadelphia",
    "sg:classifiers":[
        {
            "category":"Health Services",
            "subcategory":"Doctor",
            "type":"Services"
        }
    ],
    "sg:phone":"+1 215 592 8720",
    "sg:postcode":"19107",
    "sg:province":"PA",
    "sg:tags":[
        "physician",
        "surgeon",
        "psychologist"
    ],
    "wof:name":"Romano, Mary Ann T Phd",
    "wof:placetype":"venue"
},
  "geometry": {"coordinates":[-75.160488,39.950419],"type":"Point"}
}