{
  "type": "Feature",
  "properties": {
    "iso:country":"US",
    "sg:address":"651 Germantown Pike",
    "sg:city":"Lafayette Hill",
    "sg:classifiers":[
        {
            "category":"Retail",
            "subcategory":"Portrait Studio",
            "type":"Services"
        }
    ],
    "sg:phone":"+1 610 828 1142",
    "sg:postcode":"19444",
    "sg:province":"PA",
    "sg:tags":[
        "photographer"
    ],
    "sg:website":"www.lafayette.com",
    "wof:name":"Lafayette Hill Studios",
    "wof:placetype":"venue"
},
  "geometry": {"coordinates":[-75.249886,40.084286],"type":"Point"}
}