{
  "type": "Feature",
  "properties": {
    "iso:country":"US",
    "sg:address":"575 Morgantown Rd",
    "sg:city":"Uniontown",
    "sg:classifiers":[
        {
            "category":"Cinema",
            "subcategory":"Movie Rental",
            "type":"Entertainment"
        }
    ],
    "sg:phone":"+1 724 439 9151",
    "sg:postcode":"15401",
    "sg:province":"PA",
    "sg:tags":[
        "leasing",
        "video",
        "disc",
        "tape"
    ],
    "wof:name":"Movie Gallery",
    "wof:placetype":"venue"
},
  "geometry": {"coordinates":[-79.73519400000001,39.883706],"type":"Point"}
}