{
  "type": "Feature",
  "properties": {
    "addr:full":"4706 W Penn Ave Reading PA 19608",
    "addr:housenumber":"4706",
    "addr:postcode":"19608",
    "addr:street":"W Penn Ave",
    "iso:country":"US",
    "sg:address":"4706 W Penn Ave",
    "sg:city":"Reading",
    "sg:classifiers":[
        {
            "category":"Autos & Motor Vehicles",
            "subcategory":"Auto Supplies",
            "type":"Retail Goods"
        },
        {
            "category":"Wholesale",
            "subcategory":"Auto Parts",
            "type":"Manufacturing & Wholesale Goods"
        }
    ],
    "sg:phone":"+1 610 678 4555",
    "sg:postcode":"19608",
    "sg:province":"PA",
    "sg:tags":[
        "automobile"
    ],
    "wof:name":"Carquest Auto Parts",
    "wof:placetype":"venue"
},
  "geometry": {"coordinates":[-76.03969499999999,40.326601],"type":"Point"}
}