{
  "type": "Feature",
  "properties": {
    "iso:country":"US",
    "sg:address":"200 Park Manor Dr",
    "sg:city":"Pittsburgh",
    "sg:classifiers":[
        {
            "category":"Restaurant",
            "type":"Food & Drink"
        }
    ],
    "sg:phone":"+1   ",
    "sg:postcode":"15205",
    "sg:province":"PA",
    "sg:tags":[
        "eating"
    ],
    "wof:name":"Dingbats",
    "wof:placetype":"venue"
},
  "geometry": {"coordinates":[-80.162592,40.448149],"type":"Point"}
}