{
  "type": "Feature",
  "properties": {
    "iso:country":"US",
    "sg:address":"10 E Main St",
    "sg:city":"Everett",
    "sg:classifiers":[
        {
            "category":"Shopping",
            "type":"Retail Goods"
        }
    ],
    "sg:phone":"+1   ",
    "sg:postcode":"15537",
    "sg:province":"PA",
    "sg:tags":[
        "merchandise"
    ],
    "wof:name":"Barbers Cstm Frmng & Art Sups",
    "wof:placetype":"venue"
},
  "geometry": {"coordinates":[-78.372716,40.011344],"type":"Point"}
}