{
  "type": "Feature",
  "properties": {
    "iso:country":"US",
    "sg:address":"1199 Buck Hollow Rd",
    "sg:city":"Mohnton",
    "sg:classifiers":[
        {
            "category":"Professional",
            "type":"Services"
        }
    ],
    "sg:phone":"+1   ",
    "sg:postcode":"19540",
    "sg:province":"PA",
    "wof:name":"Joe Reimeis",
    "wof:placetype":"venue"
},
  "geometry": {"coordinates":[-75.901802,40.218064],"type":"Point"}
}