{
  "type": "Feature",
  "properties": {
    "addr:full":"329 W Washington St Bradford PA 16701",
    "addr:housenumber":"329",
    "addr:postcode":"16701",
    "addr:street":"W Washington St",
    "iso:country":"US",
    "sg:address":"329 W Washington St",
    "sg:city":"Bradford",
    "sg:classifiers":[
        {
            "category":"Freight",
            "type":"Transportation"
        }
    ],
    "sg:phone":"+1 814 362 2911",
    "sg:postcode":"16701",
    "sg:province":"PA",
    "sg:tags":[
        "operator",
        "local",
        "trucking"
    ],
    "wof:name":"Paul C Smith & Son",
    "wof:placetype":"venue"
},
  "geometry": {"coordinates":[-78.667633,41.955101],"type":"Point"}
}