{
  "type": "Feature",
  "properties": {
    "iso:country":"US",
    "sg:address":"300 Heinz St. Suite C-115",
    "sg:city":"Pittsburgh",
    "sg:classifiers":[
        {
            "category":"Personal",
            "subcategory":"Massage",
            "type":"Services"
        }
    ],
    "sg:phone":"+1 888 473 5883",
    "sg:postcode":"15212",
    "sg:province":"PA",
    "sg:tags":[
        "therapist"
    ],
    "sg:website":"http://www.urbanescapepgh.com",
    "wof:name":"Urban Escape/Customized Massage Therapy",
    "wof:placetype":"venue"
},
  "geometry": {"coordinates":[-79.991402,40.45417],"type":"Point"}
}