{
  "type": "Feature",
  "properties": {
    "addr:full":"316 Finley Rd Belle Vernon PA 15012",
    "addr:housenumber":"316",
    "addr:postcode":"15012",
    "addr:street":"Finley Rd",
    "iso:country":"US",
    "sg:address":"316 Finley Rd",
    "sg:city":"Belle Vernon",
    "sg:classifiers":[
        {
            "category":"Freight",
            "type":"Transportation"
        }
    ],
    "sg:phone":"+1   ",
    "sg:postcode":"15012",
    "sg:province":"PA",
    "sg:tags":[
        "distance",
        "moving",
        "storage",
        "hauling",
        "long"
    ],
    "wof:name":"Vesesly Bros United Van Lines",
    "wof:placetype":"venue"
},
  "geometry": {"coordinates":[-79.82191,40.14076],"type":"Point"}
}