{
  "type": "Feature",
  "properties": {
    "iso:country":"US",
    "sg:address":"57 E Market St",
    "sg:city":"York",
    "sg:classifiers":[
        {
            "category":"Building & Trades",
            "subcategory":"Equipment Rental",
            "type":"Services"
        }
    ],
    "sg:phone":"+1   ",
    "sg:postcode":"17401",
    "sg:province":"PA",
    "wof:name":"Austin Law Firm",
    "wof:placetype":"venue"
},
  "geometry": {"coordinates":[-76.726749,39.962793],"type":"Point"}
}