{
  "type": "Feature",
  "properties": {
    "iso:country":"US",
    "sg:address":"329 Rider Ave",
    "sg:city":"Lancaster",
    "sg:classifiers":[
        {
            "category":"Freight",
            "type":"Transportation"
        }
    ],
    "sg:phone":"+1   ",
    "sg:postcode":"17603",
    "sg:province":"PA",
    "sg:tags":[
        "operator",
        "local",
        "trucking"
    ],
    "wof:name":"Kenneth C Kinard Jr",
    "wof:placetype":"venue"
},
  "geometry": {"coordinates":[-76.325948,40.035208],"type":"Point"}
}