{
  "type": "Feature",
  "properties": {
    "iso:country":"US",
    "sg:address":"2743 Jenkintown Rd",
    "sg:city":"Glenside",
    "sg:classifiers":[
        {
            "category":"Personal",
            "type":"Services"
        }
    ],
    "sg:phone":"+1 215 885 8087",
    "sg:postcode":"19038",
    "sg:province":"PA",
    "sg:tags":[
        "therapist",
        "massage"
    ],
    "wof:name":"Body Basics Massage",
    "wof:placetype":"venue"
},
  "geometry": {"coordinates":[-75.157453,40.116471],"type":"Point"}
}