{
  "type": "Feature",
  "properties": {
    "iso:country":"US",
    "sg:address":"1575 River Rd",
    "sg:city":"Pittston",
    "sg:classifiers":[
        {
            "category":"Bars & Pubs",
            "type":"Food & Drink"
        },
        {
            "category":"Bars & Pubs",
            "subcategory":"Lounge",
            "type":"Food & Drink"
        }
    ],
    "sg:phone":"+1 570 654 3223",
    "sg:postcode":"18640",
    "sg:province":"PA",
    "sg:tags":[
        "cocktail"
    ],
    "wof:name":"River Street Ale House",
    "wof:placetype":"venue"
},
  "geometry": {"coordinates":[-75.82659099999999,41.304808],"type":"Point"}
}