{
  "type": "Feature",
  "properties": {
    "addr:full":"247 Main St Mill Hall PA 17751",
    "addr:housenumber":"247",
    "addr:postcode":"17751",
    "addr:street":"Main St",
    "iso:country":"US",
    "sg:address":"247 Main St",
    "sg:city":"Mill Hall",
    "sg:classifiers":[
        {
            "category":"Bars & Pubs",
            "type":"Food & Drink"
        }
    ],
    "sg:phone":"+1 570 726 7505",
    "sg:postcode":"17751",
    "sg:province":"PA",
    "wof:name":"Abbey's Inn",
    "wof:placetype":"venue"
},
  "geometry": {"coordinates":[-77.484972,41.10388],"type":"Point"}
}