{
  "type": "Feature",
  "properties": {
    "iso:country":"US",
    "sg:address":"3027 Swanson St",
    "sg:city":"Palmer",
    "sg:classifiers":[
        {
            "category":"Retail",
            "subcategory":"Car Wash",
            "type":"Services"
        }
    ],
    "sg:phone":"+1 610 253 4640",
    "sg:postcode":"18045",
    "sg:province":"PA",
    "sg:tags":[
        "automobile",
        "detail",
        "clean"
    ],
    "wof:name":"Fix-A-Chip",
    "wof:placetype":"venue"
},
  "geometry": {"coordinates":[-75.272497,40.696933],"type":"Point"}
}