{
  "type": "Feature",
  "properties": {
    "iso:country":"US",
    "sg:address":"301 5th Ave",
    "sg:city":"Mckeesport",
    "sg:classifiers":[
        {
            "category":"Social Services",
            "type":"Services"
        }
    ],
    "sg:phone":"+1 412 664 9390",
    "sg:postcode":"15132",
    "sg:province":"PA",
    "sg:tags":[
        "organization",
        "welfare"
    ],
    "wof:name":"Pittsburgh American Indian Ctr",
    "wof:placetype":"venue"
},
  "geometry": {"coordinates":[-79.864271,40.351071],"type":"Point"}
}