{
  "type": "Feature",
  "properties": {
    "addr:full":"1 Thomas Ln Pittsburgh PA 15235",
    "addr:housenumber":"1",
    "addr:postcode":"15235",
    "addr:street":"Thomas Ln",
    "iso:country":"US",
    "sg:address":"1 Thomas Ln",
    "sg:city":"Pittsburgh",
    "sg:classifiers":[
        {
            "category":"Wholesale",
            "subcategory":"Electrical",
            "type":"Manufacturing & Wholesale Goods"
        }
    ],
    "sg:phone":"+1 412 823 0451",
    "sg:postcode":"15235",
    "sg:province":"PA",
    "sg:tags":[
        "equipment",
        "electric",
        "supply"
    ],
    "wof:name":"Power Superconductor",
    "wof:placetype":"venue"
},
  "geometry": {"coordinates":[-79.82583099999999,40.429802],"type":"Point"}
}