{
  "type": "Feature",
  "properties": {
    "addr:full":"2790 W College Ave State College PA 16801",
    "addr:housenumber":"2790",
    "addr:postcode":"16801",
    "addr:street":"W College Ave",
    "iso:country":"US",
    "sg:address":"2790 W College Ave",
    "sg:city":"State College",
    "sg:classifiers":[
        {
            "category":"Banks & Credit Unions",
            "subcategory":"Bank",
            "type":"Services"
        }
    ],
    "sg:phone":"+1 814 231 4003",
    "sg:postcode":"16801",
    "sg:province":"PA",
    "wof:name":"Sovereign Bank",
    "wof:placetype":"venue"
},
  "geometry": {"coordinates":[-77.87974800000001,40.761798],"type":"Point"}
}