{
  "type": "Feature",
  "properties": {
    "iso:country":"US",
    "sg:address":"1104 Chestnut St",
    "sg:city":"Philadelphia",
    "sg:classifiers":[
        {
            "category":"Shopping",
            "subcategory":"Jewelry",
            "type":"Retail Goods"
        }
    ],
    "sg:phone":"+1 215 629 2979",
    "sg:postcode":"19107",
    "sg:province":"PA",
    "sg:tags":[
        "jeweler"
    ],
    "wof:name":"Unique Accessories",
    "wof:placetype":"venue"
},
  "geometry": {"coordinates":[-75.160172,39.950313],"type":"Point"}
}