{
  "type": "Feature",
  "properties": {
    "iso:country":"US",
    "sg:address":"1309 Unruh Ave",
    "sg:city":"Philadelphia",
    "sg:classifiers":[
        {
            "category":"Shopping",
            "subcategory":"Gifts & Souvenirs",
            "type":"Retail Goods"
        }
    ],
    "sg:phone":"+1 215 728 0328",
    "sg:postcode":"19111",
    "sg:province":"PA",
    "sg:tags":[
        "announcement",
        "invitation"
    ],
    "wof:name":"Unique Invitations",
    "wof:placetype":"venue"
},
  "geometry": {"coordinates":[-75.07547700000001,40.044179],"type":"Point"}
}