{
  "type": "Feature",
  "properties": {
    "addr:full":"7501 Church Ave Pittsburgh PA 15202",
    "addr:housenumber":"7501",
    "addr:postcode":"15202",
    "addr:street":"Church Ave",
    "iso:country":"US",
    "sg:address":"7501 Church Ave",
    "sg:city":"Pittsburgh",
    "sg:classifiers":[
        {
            "category":"Organizations",
            "subcategory":"Religious Organization",
            "type":"Services"
        }
    ],
    "sg:phone":"+1   ",
    "sg:postcode":"15202",
    "sg:province":"PA",
    "wof:name":"Community Prsbt Church Ben Avo",
    "wof:placetype":"venue"
},
  "geometry": {"coordinates":[-80.087503,40.510611],"type":"Point"}
}