{
  "type": "Feature",
  "properties": {
    "iso:country":"US",
    "sg:address":"600 Old Lancaster Rd",
    "sg:city":"Bryn Mawr",
    "sg:classifiers":[
        {
            "category":"Professional",
            "type":"Services"
        }
    ],
    "sg:phone":"+1 610 520 4416",
    "sg:postcode":"19010",
    "sg:province":"PA",
    "sg:tags":[
        "establishment"
    ],
    "wof:name":"Enwrapture The Body Wrapping",
    "wof:placetype":"venue"
},
  "geometry": {"coordinates":[-75.31421400000001,40.018686],"type":"Point"}
}