{
  "type": "Feature",
  "properties": {
    "addr:full":"501 Chestnut St Emmaus PA 18049",
    "addr:housenumber":"501",
    "addr:postcode":"18049",
    "addr:street":"Chestnut St",
    "iso:country":"US",
    "sg:address":"501 Chestnut St",
    "sg:city":"Emmaus",
    "sg:classifiers":[
        {
            "category":"Organizations",
            "subcategory":"Religious Organization",
            "type":"Services"
        }
    ],
    "sg:phone":"+1 610 965 9885",
    "sg:postcode":"18049",
    "sg:province":"PA",
    "sg:tags":[
        "church"
    ],
    "wof:name":"St John's Lutheran Church",
    "wof:placetype":"venue"
},
  "geometry": {"coordinates":[-75.493599,40.534199],"type":"Point"}
}