{
  "type": "Feature",
  "properties": {
    "iso:country":"US",
    "sg:address":"628 Chelten Hills Dr",
    "sg:city":"Elkins Park",
    "sg:classifiers":[
        {
            "category":"Health Services",
            "subcategory":"Doctor",
            "type":"Services"
        }
    ],
    "sg:phone":"+1   ",
    "sg:postcode":"19027",
    "sg:province":"PA",
    "sg:tags":[
        "medical"
    ],
    "wof:name":"Irwin L Stoloff MD",
    "wof:placetype":"venue"
},
  "geometry": {"coordinates":[-75.130582,40.076928],"type":"Point"}
}