{
  "type": "Feature",
  "properties": {
    "iso:country":"US",
    "sg:address":"2599 Wexford Run Rd",
    "sg:city":"Wexford",
    "sg:classifiers":[
        {
            "category":"Health Services",
            "subcategory":"Clinic",
            "type":"Services"
        },
        {
            "category":"Community Center",
            "type":"Public Place"
        },
        {
            "category":"Health Services",
            "subcategory":"Hospital",
            "type":"Services"
        }
    ],
    "sg:phone":"+1 724 933 3600",
    "sg:postcode":"15090",
    "sg:province":"PA",
    "sg:tags":[
        "children's",
        "medical"
    ],
    "wof:name":"Childrens Hospital of Pittsburgh Outpatient Services Neighborhood",
    "wof:placetype":"venue"
},
  "geometry": {"coordinates":[-80.077011,40.61276],"type":"Point"}
}