{
  "type": "Feature",
  "properties": {
    "iso:country":"US",
    "sg:address":"512 E Penn Ave",
    "sg:city":"Lebanon",
    "sg:classifiers":[
        {
            "category":"Autos & Motor Vehicles",
            "subcategory":"Automobile Sales",
            "type":"Retail Goods"
        }
    ],
    "sg:phone":"+1   ",
    "sg:postcode":"17042",
    "sg:province":"PA",
    "sg:tags":[
        "used"
    ],
    "wof:name":"Cortrights Auto Sales Inc",
    "wof:placetype":"venue"
},
  "geometry": {"coordinates":[-76.46722699999999,40.33867],"type":"Point"}
}