{
  "type": "Feature",
  "properties": {
    "iso:country":"US",
    "sg:address":"6404 Woodland Ave",
    "sg:city":"Philadelphia",
    "sg:classifiers":[
        {
            "category":"Shopping",
            "type":"Retail Goods"
        }
    ],
    "sg:phone":"+1 215 724 4404",
    "sg:postcode":"19142",
    "sg:province":"PA",
    "sg:tags":[
        "merchandise"
    ],
    "wof:name":"African House Enterprise",
    "wof:placetype":"venue"
},
  "geometry": {"coordinates":[-75.23361800000001,39.926002],"type":"Point"}
}