{
  "type": "Feature",
  "properties": {
    "addr:full":"1200 E King St Lancaster PA 17602",
    "addr:housenumber":"1200",
    "addr:postcode":"17602",
    "addr:street":"E King St",
    "iso:country":"US",
    "sg:address":"1200 E King St",
    "sg:city":"Lancaster",
    "sg:classifiers":[
        {
            "category":"Organizations",
            "subcategory":"Religious Organization",
            "type":"Services"
        }
    ],
    "sg:phone":"+1 717 295 1157",
    "sg:postcode":"17602",
    "sg:province":"PA",
    "sg:tags":[
        "church"
    ],
    "wof:name":"Church Of Jesus Christ Of Lds",
    "wof:placetype":"venue"
},
  "geometry": {"coordinates":[-76.27870299999999,40.038725],"type":"Point"}
}