{
  "type": "Feature",
  "properties": {
    "iso:country":"US",
    "sg:address":"100 S Keyser Ave",
    "sg:city":"Old Forge",
    "sg:classifiers":[
        {
            "category":"Retail",
            "subcategory":"Auto Repair",
            "type":"Services"
        }
    ],
    "sg:phone":"+1 570 457 9017",
    "sg:postcode":"18518",
    "sg:province":"PA",
    "sg:tags":[
        "automotive",
        "general"
    ],
    "wof:name":"Old Forge Gulf",
    "wof:placetype":"venue"
},
  "geometry": {"coordinates":[-75.74100300000001,41.38435],"type":"Point"}
}