{
  "type": "Feature",
  "properties": {
    "addr:full":"1123 Centre St Ashland PA 17921",
    "addr:housenumber":"1123",
    "addr:postcode":"17921",
    "addr:street":"Centre St",
    "iso:country":"US",
    "sg:address":"1123 Centre St",
    "sg:city":"Ashland",
    "sg:classifiers":[
        {
            "category":"Personal",
            "subcategory":"Beauty Salon",
            "type":"Services"
        }
    ],
    "sg:phone":"+1 570 875 4450",
    "sg:postcode":"17921",
    "sg:province":"PA",
    "wof:name":"Christopher Roberts Hair Design",
    "wof:placetype":"venue"
},
  "geometry": {"coordinates":[-76.345116,40.781976],"type":"Point"}
}