{
  "type": "Feature",
  "properties": {
    "iso:country":"US",
    "sg:address":"170 Schoolhouse Ln",
    "sg:city":"York",
    "sg:classifiers":[
        {
            "category":"Health Services",
            "subcategory":"Health Practitioner",
            "type":"Services"
        }
    ],
    "sg:phone":"+1   ",
    "sg:postcode":"17406",
    "sg:province":"PA",
    "wof:name":"Spring Grdn Psychlogical Assoc",
    "wof:placetype":"venue"
},
  "geometry": {"coordinates":[-76.605183,40.000986],"type":"Point"}
}