{
  "type": "Feature",
  "properties": {
    "addr:full":"127 E Wyoming Ave Philadelphia PA 19120",
    "addr:housenumber":"127",
    "addr:postcode":"19120",
    "addr:street":"E Wyoming Ave",
    "iso:country":"US",
    "sg:address":"127 E Wyoming Ave",
    "sg:city":"Philadelphia",
    "sg:classifiers":[
        {
            "category":"Organizations",
            "subcategory":"Religious Organization",
            "type":"Services"
        }
    ],
    "sg:phone":"+1 215 329 8295",
    "sg:postcode":"19120",
    "sg:province":"PA",
    "sg:tags":[
        "church"
    ],
    "wof:name":"Wyoming Avenue Baptist Church",
    "wof:placetype":"venue"
},
  "geometry": {"coordinates":[-75.122803,40.021451],"type":"Point"}
}