{
  "type": "Feature",
  "properties": {
    "addr:full":"321 Run Rd Carlisle PA 17015",
    "addr:housenumber":"321",
    "addr:postcode":"17015",
    "addr:street":"Run Rd",
    "iso:country":"US",
    "sg:address":"321 Run Rd",
    "sg:city":"Carlisle",
    "sg:classifiers":[
        {
            "category":"Retail",
            "subcategory":"Auto Repair",
            "type":"Services"
        }
    ],
    "sg:phone":"+1 717 249 4952",
    "sg:postcode":"17015",
    "sg:province":"PA",
    "wof:name":"Sipe G Enterprise",
    "wof:placetype":"venue"
},
  "geometry": {"coordinates":[-77.258247,40.213547],"type":"Point"}
}