{
  "type": "Feature",
  "properties": {
    "addr:full":"1037 Trout Run Rd St Marys PA 15857",
    "addr:housenumber":"1037",
    "addr:postcode":"15857",
    "addr:street":"Trout Run Rd",
    "iso:country":"US",
    "sg:address":"1037 Trout Run Rd",
    "sg:city":"St Marys",
    "sg:classifiers":[
        {
            "category":"Manufacturing",
            "subcategory":"Food",
            "type":"Manufacturing & Wholesale Goods"
        }
    ],
    "sg:phone":"+1 814 781 1447",
    "sg:postcode":"15857",
    "sg:province":"PA",
    "sg:tags":[
        "preparation",
        "whole",
        "tortilla",
        "wheat",
        "mfg"
    ],
    "sg:website":"www.mexamericafoods.com",
    "wof:name":"Mex America Foods Inc",
    "wof:placetype":"venue"
},
  "geometry": {"coordinates":[-78.52178499999999,41.422672],"type":"Point"}
}