{
  "type": "Feature",
  "properties": {
    "iso:country":"US",
    "sg:address":"1463 Westgate Dr",
    "sg:city":"Bethlehem",
    "sg:classifiers":[
        {
            "category":"Professional",
            "subcategory":"Detective & Security Services",
            "type":"Services"
        }
    ],
    "sg:phone":"+1   ",
    "sg:postcode":"18017",
    "sg:province":"PA",
    "sg:tags":[
        "system"
    ],
    "wof:name":"N V T",
    "wof:placetype":"venue"
},
  "geometry": {"coordinates":[-75.403514,40.644743],"type":"Point"}
}