{
  "type": "Feature",
  "properties": {
    "addr:full":"15392 Rte 322 Clarion PA 16214",
    "addr:housenumber":"15392",
    "addr:postcode":"16214",
    "addr:street":"Rte 322",
    "iso:country":"US",
    "sg:address":"15392 Rte 322",
    "sg:city":"Clarion",
    "sg:classifiers":[
        {
            "category":"Personal",
            "type":"Services"
        }
    ],
    "sg:phone":"+1 814 764 3548",
    "sg:postcode":"16214",
    "sg:province":"PA",
    "sg:tags":[
        "therapist",
        "massage"
    ],
    "wof:name":"Sapphire Moon",
    "wof:placetype":"venue"
},
  "geometry": {"coordinates":[-79.353827,41.202884],"type":"Point"}
}