{
  "type": "Feature",
  "properties": {
    "addr:full":"13600 Wolfe Rd New Freedom PA 17349",
    "addr:housenumber":"13600",
    "addr:postcode":"17349",
    "addr:street":"Wolfe Rd",
    "iso:country":"US",
    "sg:address":"13600 Wolfe Rd",
    "sg:city":"New Freedom",
    "sg:classifiers":[
        {
            "category":"Bars & Pubs",
            "type":"Food & Drink"
        }
    ],
    "sg:menulink":"http://www.allmenus.com/pa/hopewell/35283-cracker-barrel-old-country-store/menu/",
    "sg:phone":"+1 717 235 4040",
    "sg:postcode":"17349",
    "sg:province":"PA",
    "sg:tags":[
        "american",
        "southern"
    ],
    "wof:name":"Cracker Barrel Old Country Store",
    "wof:placetype":"venue"
},
  "geometry": {"coordinates":[-76.66369,39.773221],"type":"Point"}
}