{
  "type": "Feature",
  "properties": {
    "iso:country":"US",
    "sg:address":"233 S 6th St",
    "sg:city":"Philadelphia",
    "sg:classifiers":[
        {
            "category":"Professional",
            "subcategory":"Management & Consulting",
            "type":"Services"
        }
    ],
    "sg:phone":"+1   ",
    "sg:postcode":"19106",
    "sg:province":"PA",
    "wof:name":"Salkowitz Assoc LLC",
    "wof:placetype":"venue"
},
  "geometry": {"coordinates":[-75.151443,39.946104],"type":"Point"}
}