{
  "type": "Feature",
  "properties": {
    "addr:full":"8968 Main St Mc Kean PA 16426",
    "addr:housenumber":"8968",
    "addr:postcode":"16426",
    "addr:street":"Main St Mc",
    "iso:country":"US",
    "sg:address":"8968 Main St",
    "sg:city":"Mc Kean",
    "sg:classifiers":[
        {
            "category":"Bars & Pubs",
            "type":"Food & Drink"
        }
    ],
    "sg:phone":"+1 814 476 1195",
    "sg:postcode":"16426",
    "sg:province":"PA",
    "wof:name":"Mc KEAN Tavern",
    "wof:placetype":"venue"
},
  "geometry": {"coordinates":[-80.142951,41.997713],"type":"Point"}
}