{
  "type": "Feature",
  "properties": {
    "iso:country":"US",
    "sg:address":"710 S York Rd",
    "sg:city":"Dillsburg",
    "sg:classifiers":[
        {
            "category":"Building & Trades",
            "subcategory":"Construction",
            "type":"Services"
        }
    ],
    "sg:phone":"+1   ",
    "sg:postcode":"17019",
    "sg:province":"PA",
    "sg:tags":[
        "floor",
        "laying",
        "contractor"
    ],
    "wof:name":"K & L Flooring",
    "wof:placetype":"venue"
},
  "geometry": {"coordinates":[-76.957544,40.117775],"type":"Point"}
}