{
  "type": "Feature",
  "properties": {
    "addr:full":"3309 Stone Ridge Rd York PA 17402",
    "addr:housenumber":"3309",
    "addr:postcode":"17402",
    "addr:street":"Stone Ridge Rd",
    "iso:country":"US",
    "sg:address":"3309 Stone Ridge Rd",
    "sg:city":"York",
    "sg:phone":"+1   ",
    "sg:postcode":"17402",
    "sg:province":"PA",
    "sg:tags":[
        "beef",
        "farm",
        "cash",
        "grain",
        "cattle",
        "feedlot"
    ],
    "wof:name":"Clair Heidlebaugh",
    "wof:placetype":"venue"
},
  "geometry": {"coordinates":[-76.65390600000001,39.97684],"type":"Point"}
}