{
  "type": "Feature",
  "properties": {
    "addr:full":"2000 N 18th St Philadelphia PA 19121",
    "addr:housenumber":"2000",
    "addr:postcode":"19121",
    "addr:street":"N 18Th St",
    "iso:country":"US",
    "sg:address":"2000 N 18th St",
    "sg:city":"Philadelphia",
    "sg:classifiers":[
        {
            "category":"Place Of Worship",
            "type":"Public Place"
        },
        {
            "category":"Organizations",
            "subcategory":"Religious Organization",
            "type":"Services"
        }
    ],
    "sg:phone":"+1 215 787 0700",
    "sg:postcode":"19121",
    "sg:province":"PA",
    "sg:tags":[
        "church"
    ],
    "wof:name":"Deliverance Revival Temple Inc",
    "wof:placetype":"venue"
},
  "geometry": {"coordinates":[-75.16327699999999,39.98399],"type":"Point"}
}