{
  "type": "Feature",
  "properties": {
    "addr:full":"1301 Lancaster Ave Ste 3 Berwyn PA 19312",
    "addr:housenumber":"1301",
    "addr:postcode":"19312",
    "addr:street":"Lancaster Ave Ste 3",
    "iso:country":"US",
    "sg:address":"1301 Lancaster Ave Ste 3",
    "sg:city":"Berwyn",
    "sg:classifiers":[
        {
            "category":"Real Estate",
            "subcategory":"Real Estate Services",
            "type":"Services"
        },
        {
            "category":"Real Estate",
            "subcategory":"Real Estate Agent",
            "type":"Services"
        }
    ],
    "sg:phone":"+1 610 640 4711",
    "sg:postcode":"19312",
    "sg:province":"PA",
    "sg:tags":[
        "buyer",
        "broker"
    ],
    "wof:name":"Signature Communities Ltd",
    "wof:placetype":"venue"
},
  "geometry": {"coordinates":[-75.457578,40.042812],"type":"Point"}
}