{
  "type": "Feature",
  "properties": {
    "iso:country":"US",
    "sg:address":"1417 W Allegheny Ave",
    "sg:city":"Philadelphia",
    "sg:classifiers":[
        {
            "category":"Health Services",
            "subcategory":"Podiatrist",
            "type":"Services"
        }
    ],
    "sg:phone":"+1 215 226 2808",
    "sg:postcode":"19132",
    "sg:province":"PA",
    "wof:name":"Dickinson Joseph DPM",
    "wof:placetype":"venue"
},
  "geometry": {"coordinates":[-75.153603,40.001598],"type":"Point"}
}