{
  "type": "Feature",
  "properties": {
    "iso:country":"US",
    "sg:address":"1025 Hay St",
    "sg:city":"Wilkinsburg",
    "sg:classifiers":[
        {
            "category":"Government",
            "subcategory":"Post Office",
            "type":"Public Place"
        }
    ],
    "sg:phone":"+1 412 241 0205",
    "sg:postcode":"15221",
    "sg:province":"PA",
    "wof:name":"US Post Office",
    "wof:placetype":"venue"
},
  "geometry": {"coordinates":[-79.885598,40.444689],"type":"Point"}
}