{
  "type": "Feature",
  "properties": {
    "addr:full":"221 W Washington St Rochester PA 15074",
    "addr:housenumber":"221",
    "addr:postcode":"15074",
    "addr:street":"W Washington St",
    "iso:country":"US",
    "sg:address":"221 W Washington St",
    "sg:city":"Rochester",
    "sg:classifiers":[
        {
            "category":"Social Services",
            "type":"Services"
        }
    ],
    "sg:phone":"+1 724 774 8335",
    "sg:postcode":"15074",
    "sg:province":"PA",
    "sg:tags":[
        "organization",
        "welfare"
    ],
    "wof:name":"Salvation Army",
    "wof:placetype":"venue"
},
  "geometry": {"coordinates":[-80.284738,40.700566],"type":"Point"}
}