{
  "type": "Feature",
  "properties": {
    "iso:country":"US",
    "sg:address":"304 Church St",
    "sg:city":"Media",
    "sg:classifiers":[
        {
            "category":"Professional",
            "subcategory":"Business Services",
            "type":"Services"
        }
    ],
    "sg:phone":"+1 610 565 3938",
    "sg:postcode":"19063",
    "sg:province":"PA",
    "sg:tags":[
        "interior",
        "consultant",
        "design",
        "decorator"
    ],
    "wof:name":"Planned Interior Environments",
    "wof:placetype":"venue"
},
  "geometry": {"coordinates":[-75.38923200000001,39.915299],"type":"Point"}
}