{
  "type": "Feature",
  "properties": {
    "iso:country":"US",
    "sg:address":"527 Pine Rd",
    "sg:city":"Palmyra",
    "sg:classifiers":[
        {
            "category":"Building & Trades",
            "subcategory":"Construction",
            "type":"Services"
        }
    ],
    "sg:phone":"+1   ",
    "sg:postcode":"17078",
    "sg:province":"PA",
    "sg:tags":[
        "house"
    ],
    "wof:name":"Warren Moeller Enterprises",
    "wof:placetype":"venue"
},
  "geometry": {"coordinates":[-76.62903799999999,40.340356],"type":"Point"}
}