{
  "type": "Feature",
  "properties": {
    "iso:country":"US",
    "sg:address":"492 Stephenson St",
    "sg:city":"Duryea",
    "sg:classifiers":[
        {
            "category":"Organizations",
            "subcategory":"Community Association",
            "type":"Services"
        }
    ],
    "sg:phone":"+1   ",
    "sg:postcode":"18642",
    "sg:province":"PA",
    "wof:name":"Veterans Fgn Wars Post 1227",
    "wof:placetype":"venue"
},
  "geometry": {"coordinates":[-75.760239,41.350049],"type":"Point"}
}