{
  "type": "Feature",
  "properties": {
    "iso:country":"US",
    "sg:address":"373 Woodland Ave",
    "sg:city":"Oakmont",
    "sg:classifiers":[
        {
            "category":"Autos & Motor Vehicles",
            "subcategory":"Automobile Sales",
            "type":"Retail Goods"
        }
    ],
    "sg:phone":"+1   ",
    "sg:postcode":"15139",
    "sg:province":"PA",
    "wof:name":"Buzz Taylor Sales Rep",
    "wof:placetype":"venue"
},
  "geometry": {"coordinates":[-79.83905300000001,40.52643],"type":"Point"}
}