{
  "type": "Feature",
  "properties": {
    "addr:full":"269 Great Valley Pkwy Malvern PA 19355",
    "addr:housenumber":"269",
    "addr:postcode":"19355",
    "addr:street":"Great Valley Pkwy",
    "iso:country":"US",
    "sg:address":"269 Great Valley Pkwy",
    "sg:city":"Malvern",
    "sg:classifiers":[
        {
            "category":"Professional",
            "subcategory":"Research",
            "type":"Services"
        }
    ],
    "sg:phone":"+1 610 722 9050",
    "sg:postcode":"19355",
    "sg:province":"PA",
    "sg:tags":[
        "environmental",
        "ecological"
    ],
    "sg:website":"www.apex.com",
    "wof:name":"Apex Environmental Inc",
    "wof:placetype":"venue"
},
  "geometry": {"coordinates":[-75.540114,40.064082],"type":"Point"}
}