{
  "type": "Feature",
  "properties": {
    "iso:country":"US",
    "sg:address":"3308 Nicole Ct",
    "sg:city":"Dover",
    "sg:classifiers":[
        {
            "category":"Building & Trades",
            "subcategory":"Plumbing",
            "type":"Services"
        }
    ],
    "sg:phone":"+1 717 292 1229",
    "sg:postcode":"17315",
    "sg:province":"PA",
    "sg:tags":[
        "contractor"
    ],
    "wof:name":"Irvine Plumbing",
    "wof:placetype":"venue"
},
  "geometry": {"coordinates":[-76.830716,39.97834],"type":"Point"}
}