{
  "type": "Feature",
  "properties": {
    "iso:country":"US",
    "sg:address":"214 E College Ave",
    "sg:city":"State College",
    "sg:classifiers":[
        {
            "category":"Professional",
            "type":"Services"
        }
    ],
    "sg:phone":"+1 814 235 6927",
    "sg:postcode":"16801",
    "sg:province":"PA",
    "wof:name":"Five Twenty Seven",
    "wof:placetype":"venue"
},
  "geometry": {"coordinates":[-77.859489,40.79591],"type":"Point"}
}