{
  "type": "Feature",
  "properties": {
    "iso:country":"US",
    "sg:address":"32 S Chestnut St",
    "sg:city":"Elverson",
    "sg:classifiers":[
        {
            "category":"Building & Trades",
            "subcategory":"Plumbing",
            "type":"Services"
        }
    ],
    "sg:phone":"+1 610 286 6763",
    "sg:postcode":"19520",
    "sg:province":"PA",
    "sg:tags":[
        "plumbing",
        "contractor"
    ],
    "wof:name":"Onushko Plumbing & Heating",
    "wof:placetype":"venue"
},
  "geometry": {"coordinates":[-75.83284999999999,40.155209],"type":"Point"}
}