{
  "type": "Feature",
  "properties": {
    "iso:country":"US",
    "sg:address":"51 Beaver Dr",
    "sg:city":"Du Bois",
    "sg:classifiers":[
        {
            "category":"Professional",
            "type":"Services"
        }
    ],
    "sg:phone":"+1 814 371 4071",
    "sg:postcode":"15801",
    "sg:province":"PA",
    "sg:tags":[
        "establishment"
    ],
    "wof:name":"Vancheri & Vancheri Orthdntsts",
    "wof:placetype":"venue"
},
  "geometry": {"coordinates":[-78.754085,41.123794],"type":"Point"}
}