{
  "type": "Feature",
  "properties": {
    "iso:country":"US",
    "sg:address":"255 S 17th St",
    "sg:city":"Philadelphia",
    "sg:classifiers":[
        {
            "category":"Health Services",
            "subcategory":"Podiatrist",
            "type":"Services"
        }
    ],
    "sg:phone":"+1 877 896 0256",
    "sg:postcode":"19103",
    "sg:province":"PA",
    "sg:tags":[
        "physician",
        "surgeons"
    ],
    "sg:website":"http://local.ingenio.com/Listings/Details.aspx?NUM=a%3a9825521%3a13%3a4859924%3a14%3a0%3a7",
    "wof:name":"Center City FootCare Center",
    "wof:placetype":"venue"
},
  "geometry": {"coordinates":[-75.169479,39.948181],"type":"Point"}
}