{
  "type": "Feature",
  "properties": {
    "addr:full":"4511 Jonestown Rd Harrisburg PA 17109",
    "addr:housenumber":"4511",
    "addr:postcode":"17109",
    "addr:street":"Jonestown Rd",
    "iso:country":"US",
    "sg:address":"4511 Jonestown Rd",
    "sg:city":"Harrisburg",
    "sg:classifiers":[
        {
            "category":"Food & Beverages",
            "subcategory":"Liquor & Beverages",
            "type":"Retail Goods"
        }
    ],
    "sg:phone":"+1 717 545 9590",
    "sg:postcode":"17109",
    "sg:province":"PA",
    "sg:tags":[
        "beer",
        "spirit",
        "wine"
    ],
    "wof:name":"Case-O'- Beer",
    "wof:placetype":"venue"
},
  "geometry": {"coordinates":[-76.81759599999999,40.300098],"type":"Point"}
}