{
  "type": "Feature",
  "properties": {
    "addr:full":"1600 Market St Philadelphia PA 19103",
    "addr:housenumber":"1600",
    "addr:postcode":"19103",
    "addr:street":"Market St",
    "iso:country":"US",
    "sg:address":"1600 Market St",
    "sg:city":"Philadelphia",
    "sg:classifiers":[
        {
            "category":"Professional",
            "subcategory":"Lawyer & Legal Services",
            "type":"Services"
        }
    ],
    "sg:phone":"+1   ",
    "sg:postcode":"19103",
    "sg:province":"PA",
    "wof:name":"Palmer K Schreiber",
    "wof:placetype":"venue"
},
  "geometry": {"coordinates":[-75.16844399999999,39.952974],"type":"Point"}
}