{
  "type": "Feature",
  "properties": {
    "iso:country":"US",
    "sg:address":"717 Market St Ste 112",
    "sg:city":"Lemoyne",
    "sg:classifiers":[
        {
            "category":"Health Services",
            "subcategory":"Optometrist",
            "type":"Services"
        }
    ],
    "sg:phone":"+1 717 774 7718",
    "sg:postcode":"17043",
    "sg:province":"PA",
    "sg:tags":[
        "ophthalmologist"
    ],
    "wof:name":"Herbst James D Optometry",
    "wof:placetype":"venue"
},
  "geometry": {"coordinates":[-76.9002,40.244499],"type":"Point"}
}