{
  "type": "Feature",
  "properties": {
    "iso:country":"US",
    "sg:address":"521 Baldtop Rd",
    "sg:city":"Danville",
    "sg:classifiers":[
        {
            "category":"Building & Trades",
            "subcategory":"Plumbing",
            "type":"Services"
        }
    ],
    "sg:phone":"+1   ",
    "sg:postcode":"17821",
    "sg:province":"PA",
    "sg:tags":[
        "contractor"
    ],
    "wof:name":"Penn Heating & Cooling Inc",
    "wof:placetype":"venue"
},
  "geometry": {"coordinates":[-76.66179099999999,40.974526],"type":"Point"}
}