{
  "type": "Feature",
  "properties": {
    "iso:country":"US",
    "sg:address":"8525 Summerdale Ave",
    "sg:city":"Philadelphia",
    "sg:classifiers":[
        {
            "category":"Building & Trades",
            "subcategory":"Construction",
            "type":"Services"
        }
    ],
    "sg:phone":"+1 215 745 0634",
    "sg:postcode":"19152",
    "sg:province":"PA",
    "sg:tags":[
        "contractor"
    ],
    "wof:name":"Kolb Roofing",
    "wof:placetype":"venue"
},
  "geometry": {"coordinates":[-75.05195000000001,40.074191],"type":"Point"}
}