{
  "type": "Feature",
  "properties": {
    "iso:country":"US",
    "sg:address":"1040 Lincoln Ave",
    "sg:city":"Prospect Park",
    "sg:classifiers":[
        {
            "category":"Shopping",
            "subcategory":"Bicycles & Sporting Goods",
            "type":"Retail Goods"
        }
    ],
    "sg:phone":"+1 610 583 5525",
    "sg:postcode":"19076",
    "sg:province":"PA",
    "sg:tags":[
        "gun",
        "gunsmith"
    ],
    "wof:name":"Old Odd & Otherwise",
    "wof:placetype":"venue"
},
  "geometry": {"coordinates":[-75.30928400000001,39.886599],"type":"Point"}
}