{
  "type": "Feature",
  "properties": {
    "iso:country":"US",
    "sg:address":"327 Noll Rd",
    "sg:city":"Loretto",
    "sg:classifiers":[
        {
            "category":"Building & Trades",
            "subcategory":"Construction",
            "type":"Services"
        }
    ],
    "sg:phone":"+1   ",
    "sg:postcode":"15940",
    "sg:province":"PA",
    "sg:tags":[
        "house"
    ],
    "wof:name":"McCloskey Home Const",
    "wof:placetype":"venue"
},
  "geometry": {"coordinates":[-78.61785999999999,40.514263],"type":"Point"}
}