{
  "type": "Feature",
  "properties": {
    "iso:country":"US",
    "sg:address":"4192 Viola St",
    "sg:city":"Philadelphia",
    "sg:classifiers":[
        {
            "category":"Food & Beverages",
            "subcategory":"Meat & Fish",
            "type":"Retail Goods"
        }
    ],
    "sg:phone":"+1 215 473 7065",
    "sg:postcode":"19104",
    "sg:province":"PA",
    "sg:tags":[
        "shop"
    ],
    "wof:name":"Sheinman Provn Co",
    "wof:placetype":"venue"
},
  "geometry": {"coordinates":[-75.209503,39.975601],"type":"Point"}
}