{
  "type": "Feature",
  "properties": {
    "addr:full":"243 Blosser Hill Rd Lake Lynn PA 15451",
    "addr:housenumber":"243",
    "addr:postcode":"15451",
    "addr:street":"Blosser Hill Rd",
    "iso:country":"US",
    "sg:address":"243 Blosser Hill Rd",
    "sg:city":"Lake Lynn",
    "sg:classifiers":[
        {
            "category":"Wholesale",
            "subcategory":"Computers",
            "type":"Manufacturing & Wholesale Goods"
        }
    ],
    "sg:phone":"+1   ",
    "sg:postcode":"15451",
    "sg:province":"PA",
    "sg:tags":[
        "repair",
        "retail"
    ],
    "wof:name":"Chaos Horizon",
    "wof:placetype":"venue"
},
  "geometry": {"coordinates":[-79.89743,39.744029],"type":"Point"}
}