{
  "type": "Feature",
  "properties": {
    "addr:full":"10 N State St Ephrata PA 17522",
    "addr:housenumber":"10",
    "addr:postcode":"17522",
    "addr:street":"N State St",
    "iso:country":"US",
    "sg:address":"10 N State St",
    "sg:city":"Ephrata",
    "sg:classifiers":[
        {
            "category":"Wholesale",
            "subcategory":"Durable Goods & Equipment",
            "type":"Manufacturing & Wholesale Goods"
        }
    ],
    "sg:phone":"+1   ",
    "sg:postcode":"17522",
    "sg:province":"PA",
    "wof:name":"Rays Coolers & Supplies",
    "wof:placetype":"venue"
},
  "geometry": {"coordinates":[-76.177043,40.179091],"type":"Point"}
}