{
  "type": "Feature",
  "properties": {
    "iso:country":"US",
    "sg:address":"424 W Cambria St",
    "sg:city":"Philadelphia",
    "sg:classifiers":[
        {
            "category":"Food & Beverages",
            "subcategory":"Groceries & Convenience Stores",
            "type":"Retail Goods"
        }
    ],
    "sg:phone":"+1 215 426 2786",
    "sg:postcode":"19133",
    "sg:province":"PA",
    "sg:tags":[
        "grocer"
    ],
    "wof:name":"Julie's Market",
    "wof:placetype":"venue"
},
  "geometry": {"coordinates":[-75.138603,39.994999],"type":"Point"}
}