{
  "type": "Feature",
  "properties": {
    "iso:country":"US",
    "sg:address":"126 Barnes Rd",
    "sg:city":"Perryopolis",
    "sg:classifiers":[
        {
            "category":"Manufacturing",
            "subcategory":"Furniture",
            "type":"Manufacturing & Wholesale Goods"
        }
    ],
    "sg:phone":"+1   ",
    "sg:postcode":"15445",
    "sg:province":"PA",
    "sg:tags":[
        "drapery",
        "mfg"
    ],
    "wof:name":"Vertical Access Services Lec",
    "wof:placetype":"venue"
},
  "geometry": {"coordinates":[-79.693957,39.873049],"type":"Point"}
}