{
  "type": "Feature",
  "properties": {
    "iso:country":"US",
    "sg:address":"6024 Linglestown Rd",
    "sg:city":"Harrisburg",
    "sg:classifiers":[
        {
            "category":"Personal",
            "subcategory":"Beauty Salon",
            "type":"Services"
        }
    ],
    "sg:phone":"+1 717 545 7988",
    "sg:postcode":"17112",
    "sg:province":"PA",
    "sg:tags":[
        "hair",
        "stylist"
    ],
    "wof:name":"Todays Hair Designs",
    "wof:placetype":"venue"
},
  "geometry": {"coordinates":[-76.790717,40.343642],"type":"Point"}
}