{
  "type": "Feature",
  "properties": {
    "iso:country":"US",
    "sg:address":"103 Kathleen Dr",
    "sg:city":"Coatesville",
    "sg:classifiers":[
        {
            "category":"Home & Garden",
            "subcategory":"Home Furnishings",
            "type":"Retail Goods"
        }
    ],
    "sg:phone":"+1 610 384 6442",
    "sg:postcode":"19320",
    "sg:province":"PA",
    "sg:tags":[
        "house"
    ],
    "wof:name":"Passion Parties by Her \"Toys\"",
    "wof:placetype":"venue"
},
  "geometry": {"coordinates":[-75.860694,39.947455],"type":"Point"}
}