{
  "type": "Feature",
  "properties": {
    "iso:country":"US",
    "sg:address":"312 N Montgomery St",
    "sg:city":"Hollidaysburg",
    "sg:classifiers":[
        {
            "category":"Building & Trades",
            "subcategory":"Plumbing",
            "type":"Services"
        }
    ],
    "sg:phone":"+1 814 695 2541",
    "sg:postcode":"16648",
    "sg:province":"PA",
    "sg:tags":[
        "sheet",
        "work",
        "metal",
        "contractor"
    ],
    "wof:name":"Diehl's Sheet Metal",
    "wof:placetype":"venue"
},
  "geometry": {"coordinates":[-78.394004,40.428439],"type":"Point"}
}