{
  "type": "Feature",
  "properties": {
    "iso:country":"US",
    "sg:address":"RR 1",
    "sg:city":"Henryville",
    "sg:classifiers":[
        {
            "category":"Building & Trades",
            "subcategory":"Cleaning & Sanitation",
            "type":"Services"
        }
    ],
    "sg:phone":"+1 570 424 1539",
    "sg:postcode":"18332",
    "sg:province":"PA",
    "sg:tags":[
        "supply",
        "septic",
        "tanks-treatment"
    ],
    "wof:name":"Ronald E Treible Rooter Service",
    "wof:placetype":"venue"
},
  "geometry": {"coordinates":[-75.233299,41.083624],"type":"Point"}
}