{
  "type": "Feature",
  "properties": {
    "iso:country":"US",
    "sg:address":"1420 Locust St Ste 310",
    "sg:city":"Philadelphia",
    "sg:classifiers":[
        {
            "category":"Building & Trades",
            "subcategory":"Construction",
            "type":"Services"
        }
    ],
    "sg:phone":"+1 215 732 1652",
    "sg:postcode":"19102",
    "sg:province":"PA",
    "sg:tags":[
        "interior",
        "design"
    ],
    "sg:website":"www.flossbarber.com",
    "wof:name":"Floss Barber Inc",
    "wof:placetype":"venue"
},
  "geometry": {"coordinates":[-75.164888,39.948104],"type":"Point"}
}