{
  "type": "Feature",
  "properties": {
    "addr:full":"260 Hershey Heights Rd Hanover PA 17331",
    "addr:housenumber":"260",
    "addr:postcode":"17331",
    "addr:street":"Hershey Heights Rd",
    "iso:country":"US",
    "sg:address":"260 Hershey Heights Rd",
    "sg:city":"Hanover",
    "sg:classifiers":[
        {
            "category":"Farming",
            "subcategory":"Farm",
            "type":"Manufacturing & Wholesale Goods"
        }
    ],
    "sg:phone":"+1   ",
    "sg:postcode":"17331",
    "sg:province":"PA",
    "sg:tags":[
        "crop",
        "general"
    ],
    "wof:name":"Jacob Shank",
    "wof:placetype":"venue"
},
  "geometry": {"coordinates":[-76.990786,39.834528],"type":"Point"}
}