{
  "type": "Feature",
  "properties": {
    "addr:full":"211 E Center St Nazareth PA 18064",
    "addr:housenumber":"211",
    "addr:postcode":"18064",
    "addr:street":"E Center St",
    "iso:country":"US",
    "sg:address":"211 E Center St",
    "sg:city":"Nazareth",
    "sg:classifiers":[
        {
            "category":"Retail",
            "subcategory":"Funeral Services",
            "type":"Services"
        }
    ],
    "sg:phone":"+1   ",
    "sg:postcode":"18064",
    "sg:province":"PA",
    "wof:name":"Bartholomew-Schisler Fnrl HM",
    "wof:placetype":"venue"
},
  "geometry": {"coordinates":[-75.307261,40.74256],"type":"Point"}
}