{
  "type": "Feature",
  "properties": {
    "iso:country":"US",
    "sg:address":"3229 Elmwood Dr",
    "sg:city":"Harrisburg",
    "sg:classifiers":[
        {
            "category":"Retail",
            "subcategory":"Repair Shop",
            "type":"Services"
        }
    ],
    "sg:phone":"+1 717 652 2957",
    "sg:postcode":"17110",
    "sg:province":"PA",
    "sg:tags":[
        "upholsterer"
    ],
    "wof:name":"HIS Upholstery",
    "wof:placetype":"venue"
},
  "geometry": {"coordinates":[-76.84982599999999,40.317384],"type":"Point"}
}