{
  "type": "Feature",
  "properties": {
    "addr:full":"900 Old York Rd Jenkintown PA 19046",
    "addr:housenumber":"900",
    "addr:postcode":"19046",
    "addr:street":"Old York Rd",
    "iso:country":"US",
    "sg:address":"900 Old York Rd",
    "sg:city":"Jenkintown",
    "sg:classifiers":[
        {
            "category":"Autos & Motor Vehicles",
            "subcategory":"Automobile Sales",
            "type":"Retail Goods"
        }
    ],
    "sg:phone":"+1 215 887 8870",
    "sg:postcode":"19046",
    "sg:province":"PA",
    "sg:tags":[
        "car",
        "dealer"
    ],
    "sg:website":"www.brandowgroup.com",
    "wof:name":"Brandow's Fairway Chrysler",
    "wof:placetype":"venue"
},
  "geometry": {"coordinates":[-75.12335,40.111789],"type":"Point"}
}