{
  "type": "Feature",
  "properties": {
    "iso:country":"US",
    "sg:address":"Hampden Ctr",
    "sg:city":"Mechanicsburg",
    "sg:classifiers":[
        {
            "category":"Sports & Exercise",
            "subcategory":"Gym",
            "type":"Entertainment"
        },
        {
            "category":"Arena",
            "subcategory":"Sports Club",
            "type":"Entertainment"
        }
    ],
    "sg:phone":"+1 717 975 2111",
    "sg:postcode":"17050",
    "sg:province":"PA",
    "sg:tags":[
        "trainer",
        "martial art"
    ],
    "wof:name":"Villari's Self Defense Center of Mechanicsburg",
    "wof:placetype":"venue"
},
  "geometry": {"coordinates":[-76.99659699999999,40.244801],"type":"Point"}
}