{
  "type": "Feature",
  "properties": {
    "iso:country":"US",
    "sg:address":"15 S 8th St",
    "sg:city":"Lebanon",
    "sg:classifiers":[
        {
            "category":"Wholesale",
            "subcategory":"Machinery & Supplies",
            "type":"Manufacturing & Wholesale Goods"
        }
    ],
    "sg:phone":"+1 717 270 1060",
    "sg:postcode":"17042",
    "sg:province":"PA",
    "sg:tags":[
        "equipment",
        "establishment"
    ],
    "wof:name":"Studio 15",
    "wof:placetype":"venue"
},
  "geometry": {"coordinates":[-76.424578,40.339004],"type":"Point"}
}