{
  "type": "Feature",
  "properties": {
    "iso:country":"US",
    "sg:address":"602 S State St",
    "sg:city":"Clarks Summit",
    "sg:classifiers":[
        {
            "category":"Shopping",
            "subcategory":"Optical Goods",
            "type":"Retail Goods"
        }
    ],
    "sg:phone":"+1 570 586 2020",
    "sg:postcode":"18411",
    "sg:province":"PA",
    "sg:tags":[
        "optician"
    ],
    "wof:name":"O'Hora Eye Care Ctr",
    "wof:placetype":"venue"
},
  "geometry": {"coordinates":[-75.699322,41.49278],"type":"Point"}
}