{
  "type": "Feature",
  "properties": {
    "iso:country":"US",
    "sg:address":"22 S 18th St",
    "sg:city":"Philadelphia",
    "sg:classifiers":[
        {
            "category":"Professional",
            "subcategory":"Lawyer & Legal Services",
            "type":"Services"
        }
    ],
    "sg:phone":"+1 215 557 7600",
    "sg:postcode":"19103",
    "sg:province":"PA",
    "wof:name":"Gelinas Robert A Atty",
    "wof:placetype":"venue"
},
  "geometry": {"coordinates":[-75.170284,39.952463],"type":"Point"}
}