{
  "type": "Feature",
  "properties": {
    "iso:country":"US",
    "sg:address":"128 Springs Rd",
    "sg:city":"Carlisle",
    "sg:classifiers":[
        {
            "category":"Farming",
            "subcategory":"Dairy Farm",
            "type":"Manufacturing & Wholesale Goods"
        }
    ],
    "sg:phone":"+1   ",
    "sg:postcode":"17013",
    "sg:province":"PA",
    "wof:name":"Mark R Diller",
    "wof:placetype":"venue"
},
  "geometry": {"coordinates":[-77.18729399999999,40.208728],"type":"Point"}
}