{
  "type": "Feature",
  "properties": {
    "iso:country":"US",
    "sg:address":"1226 Perry Hwy",
    "sg:city":"Mercer",
    "sg:classifiers":[
        {
            "category":"Restaurant",
            "type":"Food & Drink"
        }
    ],
    "sg:phone":"+1 724 962 1775",
    "sg:postcode":"16137",
    "sg:province":"PA",
    "sg:tags":[
        "grill",
        "bar"
    ],
    "wof:name":"Hickory Bar And Grille",
    "wof:placetype":"venue"
},
  "geometry": {"coordinates":[-80.23120400000001,41.172331],"type":"Point"}
}