{
  "type": "Feature",
  "properties": {
    "addr:full":"9 Tracy Ter Bryn Mawr PA 19010",
    "addr:housenumber":"9",
    "addr:postcode":"19010",
    "addr:street":"Tracy Ter",
    "iso:country":"US",
    "sg:address":"9 Tracy Ter",
    "sg:city":"Bryn Mawr",
    "sg:classifiers":[
        {
            "category":"Building & Trades",
            "subcategory":"Construction",
            "type":"Services"
        }
    ],
    "sg:phone":"+1   ",
    "sg:postcode":"19010",
    "sg:province":"PA",
    "sg:tags":[
        "contractor"
    ],
    "wof:name":"Ceramic Tile World",
    "wof:placetype":"venue"
},
  "geometry": {"coordinates":[-75.331912,40.006002],"type":"Point"}
}