{
  "type": "Feature",
  "properties": {
    "addr:full":"355 Country Club Rd Phoenixville PA 19460",
    "addr:housenumber":"355",
    "addr:postcode":"19460",
    "addr:street":"Country Club Rd",
    "iso:country":"US",
    "sg:address":"355 Country Club Rd",
    "sg:city":"Phoenixville",
    "sg:classifiers":[
        {
            "category":"Organizations",
            "subcategory":"Community Association",
            "type":"Services"
        }
    ],
    "sg:phone":"+1 610 933 3727",
    "sg:postcode":"19460",
    "sg:province":"PA",
    "sg:tags":[
        "club"
    ],
    "sg:website":"www.phoenixvillecc.com",
    "wof:name":"Phoenixville Country Club",
    "wof:placetype":"venue"
},
  "geometry": {"coordinates":[-75.485868,40.102308],"type":"Point"}
}