{
  "type": "Feature",
  "properties": {
    "iso:country":"US",
    "sg:address":"3 Nicholson Dr",
    "sg:city":"Cuddy",
    "sg:classifiers":[
        {
            "category":"Banks & Credit Unions",
            "subcategory":"Financial Services",
            "type":"Services"
        }
    ],
    "sg:phone":"+1 412 348 1091",
    "sg:postcode":"15031",
    "sg:province":"PA",
    "sg:tags":[
        "broker",
        "mortgage"
    ],
    "wof:name":"Lender Pro Mortgage Services",
    "wof:placetype":"venue"
},
  "geometry": {"coordinates":[-80.16638500000001,40.347244],"type":"Point"}
}