{
  "type": "Feature",
  "properties": {
    "addr:full":"34 S 4th St Pittsburgh PA 15219",
    "addr:housenumber":"34",
    "addr:postcode":"15219",
    "addr:street":"S 4Th St",
    "iso:country":"US",
    "sg:address":"34 S 4th St",
    "sg:city":"Pittsburgh",
    "sg:classifiers":[
        {
            "category":"Building & Trades",
            "subcategory":"Construction",
            "type":"Services"
        }
    ],
    "sg:phone":"+1 412 781 3415",
    "sg:postcode":"15219",
    "sg:province":"PA",
    "sg:tags":[
        "contractor"
    ],
    "wof:name":"Keefer Joel",
    "wof:placetype":"venue"
},
  "geometry": {"coordinates":[-79.996061,40.42962],"type":"Point"}
}