{
  "type": "Feature",
  "properties": {
    "iso:country":"US",
    "sg:address":"395 S 3rd St",
    "sg:city":"Steelton",
    "sg:classifiers":[
        {
            "category":"Health Services",
            "subcategory":"Dentist",
            "type":"Services"
        }
    ],
    "sg:phone":"+1 717 939 6220",
    "sg:postcode":"17113",
    "sg:province":"PA",
    "wof:name":"Keating Brian F DMD",
    "wof:placetype":"venue"
},
  "geometry": {"coordinates":[-76.83200100000001,40.230701],"type":"Point"}
}