{
  "type": "Feature",
  "properties": {
    "iso:country":"US",
    "sg:address":"41 Deerpath Rd",
    "sg:city":"Southampton",
    "sg:classifiers":[
        {
            "category":"Building & Trades",
            "subcategory":"Plumbing",
            "type":"Services"
        },
        {
            "category":"Building & Trades",
            "subcategory":"Construction",
            "type":"Services"
        }
    ],
    "sg:phone":"+1 215 322 6257",
    "sg:postcode":"18966",
    "sg:province":"PA",
    "sg:tags":[
        "plumber",
        "industrial",
        "system",
        "specialty",
        "heating",
        "contractors-commercial",
        "contractor",
        "air conditioning"
    ],
    "wof:name":"S C Witty Plumbing & Heating",
    "wof:placetype":"venue"
},
  "geometry": {"coordinates":[-75.038786,40.199674],"type":"Point"}
}