{
  "type": "Feature",
  "properties": {
    "addr:full":"108 Boyd Rd Freeport PA 16229",
    "addr:housenumber":"108",
    "addr:postcode":"16229",
    "addr:street":"Boyd Rd",
    "iso:country":"US",
    "sg:address":"108 Boyd Rd",
    "sg:city":"Freeport",
    "sg:classifiers":[
        {
            "category":"Professional",
            "type":"Services"
        }
    ],
    "sg:phone":"+1   ",
    "sg:postcode":"16229",
    "sg:province":"PA",
    "wof:name":"L Jack Claypool",
    "wof:placetype":"venue"
},
  "geometry": {"coordinates":[-79.633488,40.754729],"type":"Point"}
}