{
  "type": "Feature",
  "properties": {
    "addr:full":"553 Lindley Ave Philadelphia PA 19120",
    "addr:housenumber":"553",
    "addr:postcode":"19120",
    "addr:street":"Lindley Ave",
    "iso:country":"US",
    "sg:address":"553 Lindley Ave",
    "sg:city":"Philadelphia",
    "sg:classifiers":[
        {
            "category":"Organizations",
            "subcategory":"Religious Organization",
            "type":"Services"
        }
    ],
    "sg:phone":"+1 215 457 6831",
    "sg:postcode":"19120",
    "sg:province":"PA",
    "sg:tags":[
        "clergy"
    ],
    "wof:name":"William Dunn",
    "wof:placetype":"venue"
},
  "geometry": {"coordinates":[-75.133898,40.029074],"type":"Point"}
}