{
  "type": "Feature",
  "properties": {
    "addr:full":"208 N 3rd St Ste 210 Harrisburg PA 17101",
    "addr:housenumber":"208",
    "addr:postcode":"17101",
    "addr:street":"N 3Rd St Ste 210",
    "iso:country":"US",
    "sg:address":"208 N 3rd St Ste 210",
    "sg:city":"Harrisburg",
    "sg:classifiers":[
        {
            "category":"Education",
            "subcategory":"School",
            "type":"Public Place"
        }
    ],
    "sg:phone":"+1 717 233 1791",
    "sg:postcode":"17101",
    "sg:province":"PA",
    "wof:name":"Pennsylvania Nutrition Education Network",
    "wof:placetype":"venue"
},
  "geometry": {"coordinates":[-76.883089,40.262068],"type":"Point"}
}