{
  "type": "Feature",
  "properties": {
    "addr:full":"1021 N 4th St Sunbury PA 17801",
    "addr:housenumber":"1021",
    "addr:postcode":"17801",
    "addr:street":"N 4Th St",
    "iso:country":"US",
    "sg:address":"1021 N 4th St",
    "sg:city":"Sunbury",
    "sg:classifiers":[
        {
            "category":"Banks & Credit Unions",
            "subcategory":"Bank",
            "type":"Services"
        },
        {
            "category":"Banks & Credit Unions",
            "subcategory":"Financial Services",
            "type":"Services"
        }
    ],
    "sg:phone":"+1 570 286 7136",
    "sg:postcode":"17801",
    "sg:province":"PA",
    "sg:tags":[
        "saving",
        "loan",
        "commercial"
    ],
    "sg:website":"http://www.mandtbank.com",
    "wof:name":"M&T Bank",
    "wof:placetype":"venue"
},
  "geometry": {"coordinates":[-76.78508100000001,40.872519],"type":"Point"}
}