{
  "type": "Feature",
  "properties": {
    "addr:full":"2116 Highland Dr Butler PA 16002",
    "addr:housenumber":"2116",
    "addr:postcode":"16002",
    "addr:street":"Highland Dr",
    "iso:country":"US",
    "sg:address":"2116 Highland Dr",
    "sg:city":"Butler",
    "sg:classifiers":[
        {
            "category":"Retail",
            "subcategory":"Animal Services",
            "type":"Services"
        }
    ],
    "sg:phone":"+1 724 283 1208",
    "sg:postcode":"16002",
    "sg:province":"PA",
    "sg:tags":[
        "pet",
        "boarding",
        "sitting"
    ],
    "wof:name":"Tender Loving Kare",
    "wof:placetype":"venue"
},
  "geometry": {"coordinates":[-79.813818,40.885392],"type":"Point"}
}