{
  "type": "Feature",
  "properties": {
    "addr:full":"2497 Aramingo Ave Philadelphia PA 19125",
    "addr:housenumber":"2497",
    "addr:postcode":"19125",
    "addr:street":"Aramingo Ave",
    "iso:country":"US",
    "sg:address":"2497 Aramingo Ave",
    "sg:city":"Philadelphia",
    "sg:classifiers":[
        {
            "category":"Food & Beverages",
            "subcategory":"Groceries & Convenience Stores",
            "type":"Retail Goods"
        }
    ],
    "sg:phone":"+1 215 425 5690",
    "sg:postcode":"19125",
    "sg:province":"PA",
    "sg:tags":[
        "grocer",
        "super",
        "supermarket"
    ],
    "wof:name":"Port Richmond Thriftway Market",
    "wof:placetype":"venue"
},
  "geometry": {"coordinates":[-75.120003,39.9762],"type":"Point"}
}