{
  "type": "Feature",
  "properties": {
    "addr:full":"114 Brunner Dr Pittsburgh PA 15214",
    "addr:housenumber":"114",
    "addr:postcode":"15214",
    "addr:street":"Brunner Dr",
    "iso:country":"US",
    "sg:address":"114 Brunner Dr",
    "sg:city":"Pittsburgh",
    "sg:classifiers":[
        {
            "category":"Organizations",
            "subcategory":"Non-profit Organization",
            "type":"Services"
        }
    ],
    "sg:phone":"+1 412 931 4567",
    "sg:postcode":"15214",
    "sg:province":"PA",
    "wof:name":"Rivertree Christian Ministries",
    "wof:placetype":"venue"
},
  "geometry": {"coordinates":[-80.029819,40.498244],"type":"Point"}
}