{
  "type": "Feature",
  "properties": {
    "iso:country":"US",
    "sg:address":"121 Jay Dr",
    "sg:city":"Verona",
    "sg:classifiers":[
        {
            "category":"Professional",
            "subcategory":"Management & Consulting",
            "type":"Services"
        }
    ],
    "sg:phone":"+1   ",
    "sg:postcode":"15147",
    "sg:province":"PA",
    "sg:tags":[
        "computer",
        "custom"
    ],
    "wof:name":"Business Info Systems Inc",
    "wof:placetype":"venue"
},
  "geometry": {"coordinates":[-79.810211,40.500815],"type":"Point"}
}