{
  "type": "Feature",
  "properties": {
    "addr:full":"539 Boggs Ave Pittsburgh PA 15211",
    "addr:housenumber":"539",
    "addr:postcode":"15211",
    "addr:street":"Boggs Ave",
    "iso:country":"US",
    "sg:address":"539 Boggs Ave",
    "sg:city":"Pittsburgh",
    "sg:classifiers":[
        {
            "category":"Organizations",
            "subcategory":"Religious Organization",
            "type":"Services"
        }
    ],
    "sg:phone":"+1 412 381 9878",
    "sg:postcode":"15211",
    "sg:province":"PA",
    "sg:tags":[
        "church"
    ],
    "wof:name":"St Justin Church",
    "wof:placetype":"venue"
},
  "geometry": {"coordinates":[-80.010184,40.422024],"type":"Point"}
}