{
  "type": "Feature",
  "properties": {
    "iso:country":"US",
    "sg:address":"2815 Penn Ave",
    "sg:city":"Pittsburgh",
    "sg:classifiers":[
        {
            "category":"Shopping",
            "subcategory":"Crafts & Fabrics",
            "type":"Retail Goods"
        }
    ],
    "sg:phone":"+1 412 560 1196",
    "sg:postcode":"15222",
    "sg:province":"PA",
    "sg:tags":[
        "florist",
        "supplies-wholesale",
        "manufacturer",
        "florists'",
        "supply"
    ],
    "wof:name":"Keystone Keystone Floral Supply Inc",
    "wof:placetype":"venue"
},
  "geometry": {"coordinates":[-79.975407,40.457],"type":"Point"}
}