{
  "type": "Feature",
  "properties": {
    "iso:country":"US",
    "sg:address":"709 Sansom St Ste 202",
    "sg:city":"Philadelphia",
    "sg:classifiers":[
        {
            "category":"Shopping",
            "subcategory":"Jewelry",
            "type":"Retail Goods"
        },
        {
            "category":"Manufacturing",
            "subcategory":"Jewelry",
            "type":"Manufacturing & Wholesale Goods"
        }
    ],
    "sg:phone":"+1 215 625 0504",
    "sg:postcode":"19106",
    "sg:province":"PA",
    "sg:tags":[
        "stone",
        "semi-precious",
        "precious",
        "jewelers-wholesale",
        "manufacturer"
    ],
    "wof:name":"Alvini J Strott",
    "wof:placetype":"venue"
},
  "geometry": {"coordinates":[-75.15252,39.948649],"type":"Point"}
}