{
  "type": "Feature",
  "properties": {
    "iso:country":"US",
    "sg:address":"5160 Elliott Rd",
    "sg:city":"Butler",
    "sg:classifiers":[
        {
            "category":"Home & Garden",
            "subcategory":"Building Materials",
            "type":"Retail Goods"
        }
    ],
    "sg:phone":"+1 724 283 8673",
    "sg:postcode":"16001",
    "sg:province":"PA",
    "sg:tags":[
        "lumber"
    ],
    "wof:name":"Fry Brothers Trim & Molding",
    "wof:placetype":"venue"
},
  "geometry": {"coordinates":[-79.920384,40.930889],"type":"Point"}
}