{
  "type": "Feature",
  "properties": {
    "iso:country":"US",
    "sg:address":"1106 Wheatfield Dr",
    "sg:city":"Davidsville",
    "sg:classifiers":[
        {
            "category":"Retail",
            "subcategory":"Auto Repair",
            "type":"Services"
        }
    ],
    "sg:phone":"+1   ",
    "sg:postcode":"15928",
    "sg:province":"PA",
    "sg:tags":[
        "tire"
    ],
    "wof:name":"403 Tire Service & Dist",
    "wof:placetype":"venue"
},
  "geometry": {"coordinates":[-78.910071,40.251326],"type":"Point"}
}