{
  "type": "Feature",
  "properties": {
    "iso:country":"US",
    "sg:address":"165 Brandon Rd",
    "sg:city":"Slippery Rock",
    "sg:classifiers":[
        {
            "category":"Farming",
            "subcategory":"Farm",
            "type":"Manufacturing & Wholesale Goods"
        }
    ],
    "sg:phone":"+1   ",
    "sg:postcode":"16057",
    "sg:province":"PA",
    "sg:tags":[
        "crop",
        "general"
    ],
    "wof:name":"Stone Ridge Farms",
    "wof:placetype":"venue"
},
  "geometry": {"coordinates":[-80.12184499999999,41.02634],"type":"Point"}
}