{
  "type": "Feature",
  "properties": {
    "addr:full":"46 S Main St Muncy PA 17756",
    "addr:housenumber":"46",
    "addr:postcode":"17756",
    "addr:street":"S Main St",
    "iso:country":"US",
    "sg:address":"46 S Main St",
    "sg:city":"Muncy",
    "sg:classifiers":[
        {
            "category":"Education",
            "subcategory":"School",
            "type":"Public Place"
        }
    ],
    "sg:phone":"+1 570 546 3125",
    "sg:postcode":"17756",
    "sg:province":"PA",
    "sg:tags":[
        "educational",
        "administrative"
    ],
    "wof:name":"Muncy School District Office",
    "wof:placetype":"venue"
},
  "geometry": {"coordinates":[-76.786203,41.204046],"type":"Point"}
}