{
  "type": "Feature",
  "properties": {
    "iso:country":"US",
    "sg:address":"7289 Airport Rd",
    "sg:city":"Bath",
    "sg:classifiers":[
        {
            "category":"Real Estate",
            "subcategory":"Real Estate Operator",
            "type":"Services"
        }
    ],
    "sg:phone":"+1   ",
    "sg:postcode":"18014",
    "sg:province":"PA",
    "sg:tags":[
        "warehouse",
        "building",
        "apartment",
        "operates",
        "lease"
    ],
    "wof:name":"Banko & Fassman",
    "wof:placetype":"venue"
},
  "geometry": {"coordinates":[-75.41803299999999,40.703283],"type":"Point"}
}