{
  "type": "Feature",
  "properties": {
    "iso:country":"US",
    "sg:address":"420 Rutter Ave",
    "sg:city":"Kingston",
    "sg:classifiers":[
        {
            "category":"Professional",
            "subcategory":"Management & Consulting",
            "type":"Services"
        }
    ],
    "sg:phone":"+1 570 714 8339",
    "sg:postcode":"18704",
    "sg:province":"PA",
    "wof:name":"Encore Marketing",
    "wof:placetype":"venue"
},
  "geometry": {"coordinates":[-75.889881,41.264791],"type":"Point"}
}