{
  "type": "Feature",
  "properties": {
    "iso:country":"US",
    "sg:address":"713 Route 113",
    "sg:city":"Perkasie",
    "sg:classifiers":[
        {
            "category":"Health Services",
            "subcategory":"Health Practitioner",
            "type":"Services"
        }
    ],
    "sg:phone":"+1 215 721 8828",
    "sg:postcode":"18944",
    "sg:province":"PA",
    "sg:tags":[
        "nutritionist"
    ],
    "sg:website":"www.queenshealthcenter.com",
    "wof:name":"Queen's Health Center",
    "wof:placetype":"venue"
},
  "geometry": {"coordinates":[-75.275901,40.343114],"type":"Point"}
}