{
  "type": "Feature",
  "properties": {
    "addr:full":"4610 Pleasant View Dr Coopersburg PA 18036",
    "addr:housenumber":"4610",
    "addr:postcode":"18036",
    "addr:street":"Pleasant View Dr",
    "iso:country":"US",
    "sg:address":"4610 Pleasant View Dr",
    "sg:city":"Coopersburg",
    "sg:classifiers":[
        {
            "category":"Personal",
            "type":"Services"
        },
        {
            "category":"Building & Trades",
            "subcategory":"Electrical",
            "type":"Services"
        }
    ],
    "sg:phone":"+1 610 791 4458",
    "sg:postcode":"18036",
    "sg:province":"PA",
    "sg:tags":[
        "home",
        "electronics",
        "system",
        "automation"
    ],
    "sg:website":"www.currentconceptshas.com",
    "wof:name":"Current Concepts",
    "wof:placetype":"venue"
},
  "geometry": {"coordinates":[-75.44945,40.555877],"type":"Point"}
}