{
  "type": "Feature",
  "properties": {
    "iso:country":"US",
    "sg:address":"374 Shurs Ln",
    "sg:city":"Philadelphia",
    "sg:classifiers":[
        {
            "category":"Health Services",
            "subcategory":"Clinic",
            "type":"Services"
        },
        {
            "category":"Professional",
            "subcategory":"Employment Agencies",
            "type":"Services"
        }
    ],
    "sg:phone":"+1 215 487 3790",
    "sg:postcode":"19128",
    "sg:province":"PA",
    "sg:tags":[
        "home",
        "physical",
        "therapy",
        "care"
    ],
    "wof:name":"Roxborough's Home Care Nursing",
    "wof:placetype":"venue"
},
  "geometry": {"coordinates":[-75.213233,40.025143],"type":"Point"}
}