{
  "type": "Feature",
  "properties": {
    "iso:country":"US",
    "sg:address":"47 N 2nd St",
    "sg:city":"Philadelphia",
    "sg:classifiers":[
        {
            "category":"Shopping",
            "type":"Retail Goods"
        }
    ],
    "sg:phone":"+1 215 922 0935",
    "sg:postcode":"19106",
    "sg:province":"PA",
    "sg:tags":[
        "art",
        "gallery",
        "dealer"
    ],
    "wof:name":"Cristinzio Pichardo Pvt Art",
    "wof:placetype":"venue"
},
  "geometry": {"coordinates":[-75.143399,39.951056],"type":"Point"}
}