{
  "type": "Feature",
  "properties": {
    "iso:country":"US",
    "sg:address":"567 W Brady St",
    "sg:city":"Butler",
    "sg:classifiers":[
        {
            "category":"Personal",
            "subcategory":"Beauty Salon",
            "type":"Services"
        }
    ],
    "sg:phone":"+1   ",
    "sg:postcode":"16001",
    "sg:province":"PA",
    "sg:tags":[
        "shop"
    ],
    "wof:name":"Styles By Bonnie",
    "wof:placetype":"venue"
},
  "geometry": {"coordinates":[-79.90489700000001,40.863257],"type":"Point"}
}