{
  "type": "Feature",
  "properties": {
    "addr:full":"946 8th Ave Brackenridge PA 15014",
    "addr:housenumber":"946",
    "addr:postcode":"15014",
    "addr:street":"8Th Ave",
    "iso:country":"US",
    "sg:address":"946 8th Ave",
    "sg:city":"Brackenridge",
    "sg:classifiers":[
        {
            "category":"Shopping",
            "subcategory":"Hobbies, Toys, & Games",
            "type":"Retail Goods"
        }
    ],
    "sg:phone":"+1   ",
    "sg:postcode":"15014",
    "sg:province":"PA",
    "wof:name":"Jims Trains",
    "wof:placetype":"venue"
},
  "geometry": {"coordinates":[-79.742741,40.608425],"type":"Point"}
}