{
  "type": "Feature",
  "properties": {
    "addr:full":"1111 Lysle Blvd Mckeesport PA 15132",
    "addr:housenumber":"1111",
    "addr:postcode":"15132",
    "addr:street":"Lysle Blvd",
    "iso:country":"US",
    "sg:address":"1111 Lysle Blvd",
    "sg:city":"Mckeesport",
    "sg:classifiers":[
        {
            "category":"Autos & Motor Vehicles",
            "subcategory":"Automobile Sales",
            "type":"Retail Goods"
        }
    ],
    "sg:phone":"+1 412 678 8500",
    "sg:postcode":"15132",
    "sg:province":"PA",
    "sg:tags":[
        "car",
        "dealer"
    ],
    "wof:name":"Target Motors",
    "wof:placetype":"venue"
},
  "geometry": {"coordinates":[-79.855526,40.352376],"type":"Point"}
}