{
  "type": "Feature",
  "properties": {
    "iso:country":"US",
    "sg:address":"2222 Old Welsh Rd",
    "sg:city":"Willow Grove",
    "sg:classifiers":[
        {
            "category":"Real Estate",
            "subcategory":"Real Estate Operator",
            "type":"Services"
        }
    ],
    "sg:phone":"+1   ",
    "sg:postcode":"19090",
    "sg:province":"PA",
    "sg:tags":[
        "building",
        "apartment"
    ],
    "wof:name":"Jane Washington",
    "wof:placetype":"venue"
},
  "geometry": {"coordinates":[-75.11718,40.135785],"type":"Point"}
}