{
  "type": "Feature",
  "properties": {
    "addr:full":"115 Lloyd Ave Latrobe PA 15650",
    "addr:housenumber":"115",
    "addr:postcode":"15650",
    "addr:street":"Lloyd Ave",
    "iso:country":"US",
    "sg:address":"115 Lloyd Ave",
    "sg:city":"Latrobe",
    "sg:classifiers":[
        {
            "category":"Retail",
            "subcategory":"Laundry & Dry Cleaning",
            "type":"Services"
        }
    ],
    "sg:phone":"+1 724 537 7271",
    "sg:postcode":"15650",
    "sg:province":"PA",
    "sg:tags":[
        "cleaners"
    ],
    "wof:name":"Westgate Cleaning Village",
    "wof:placetype":"venue"
},
  "geometry": {"coordinates":[-79.389242,40.31329],"type":"Point"}
}