{
  "type": "Feature",
  "properties": {
    "iso:country":"US",
    "sg:address":"123 S State Rd",
    "sg:city":"Upper Darby",
    "sg:classifiers":[
        {
            "category":"Personal",
            "subcategory":"Beauty Salon",
            "type":"Services"
        }
    ],
    "sg:phone":"+1 610 352 9172",
    "sg:postcode":"19082",
    "sg:province":"PA",
    "wof:name":"Rick's Place",
    "wof:placetype":"venue"
},
  "geometry": {"coordinates":[-75.27718299999999,39.9612],"type":"Point"}
}