{
  "type": "Feature",
  "properties": {
    "iso:country":"US",
    "sg:address":"17370 Susquehanna Trl S",
    "sg:city":"New Freedom",
    "sg:classifiers":[
        {
            "category":"Building & Trades",
            "subcategory":"Construction",
            "type":"Services"
        }
    ],
    "sg:phone":"+1 717 227 4945",
    "sg:postcode":"17349",
    "sg:province":"PA",
    "sg:tags":[
        "resurfacing",
        "laying",
        "refinishing",
        "floor"
    ],
    "wof:name":"D C Flooring",
    "wof:placetype":"venue"
},
  "geometry": {"coordinates":[-76.667259,39.729731],"type":"Point"}
}