{
  "type": "Feature",
  "properties": {
    "iso:country":"US",
    "sg:address":"3165 Estate Dr",
    "sg:city":"Oakdale",
    "sg:classifiers":[
        {
            "category":"Professional",
            "subcategory":"Computer Services",
            "type":"Services"
        }
    ],
    "sg:phone":"+1 412 920 9303",
    "sg:postcode":"15071",
    "sg:province":"PA",
    "sg:tags":[
        "internet"
    ],
    "sg:website":"www.returncentral.com",
    "wof:name":"RETURNCENTRAL.COM",
    "wof:placetype":"venue"
},
  "geometry": {"coordinates":[-80.20705700000001,40.447722],"type":"Point"}
}