{
  "type": "Feature",
  "properties": {
    "iso:country":"US",
    "sg:address":"207 Mansfield Blvd",
    "sg:city":"Carnegie",
    "sg:classifiers":[
        {
            "category":"Autos & Motor Vehicles",
            "subcategory":"Auto Supplies",
            "type":"Retail Goods"
        }
    ],
    "sg:phone":"+1 412 276 2345",
    "sg:postcode":"15106",
    "sg:province":"PA",
    "sg:tags":[
        "tire"
    ],
    "wof:name":"West Pitt Tire Co",
    "wof:placetype":"venue"
},
  "geometry": {"coordinates":[-80.085098,40.409901],"type":"Point"}
}