{
  "type": "Feature",
  "properties": {
    "iso:country":"US",
    "sg:address":"18201 Conneaut Lake Rd",
    "sg:city":"Meadville",
    "sg:classifiers":[
        {
            "category":"Health Services",
            "subcategory":"Doctor",
            "type":"Services"
        }
    ],
    "sg:phone":"+1 814 333 5060",
    "sg:postcode":"16335",
    "sg:province":"PA",
    "sg:tags":[
        "physician",
        "surgeon"
    ],
    "wof:name":"Mind Body Wellness Ctr",
    "wof:placetype":"venue"
},
  "geometry": {"coordinates":[-80.179509,41.622194],"type":"Point"}
}