{
  "type": "Feature",
  "properties": {
    "iso:country":"US",
    "sg:address":"410 W Oak Ln",
    "sg:city":"Glenolden",
    "sg:classifiers":[
        {
            "category":"Professional",
            "subcategory":"Advertising",
            "type":"Services"
        },
        {
            "category":"Professional",
            "subcategory":"Printing & Photocopies",
            "type":"Services"
        },
        {
            "category":"Manufacturing",
            "subcategory":"Signs",
            "type":"Manufacturing & Wholesale Goods"
        }
    ],
    "sg:phone":"+1 610 461 2274",
    "sg:postcode":"19036",
    "sg:province":"PA",
    "sg:tags":[
        "banners",
        "flag",
        "specialty",
        "pennant"
    ],
    "sg:website":"http://www.95signs.com",
    "wof:name":"95 Signs",
    "wof:placetype":"venue"
},
  "geometry": {"coordinates":[-75.287758,39.908741],"type":"Point"}
}