{
  "type": "Feature",
  "properties": {
    "iso:country":"US",
    "sg:address":"9251 Loghouse Rd",
    "sg:city":"Kempton",
    "sg:phone":"+1   ",
    "sg:postcode":"19529",
    "sg:province":"PA",
    "sg:tags":[
        "farm",
        "grain",
        "cash"
    ],
    "wof:name":"William Hildeheitel",
    "wof:placetype":"venue"
},
  "geometry": {"coordinates":[-75.73899299999999,40.609336],"type":"Point"}
}