{
  "type": "Feature",
  "properties": {
    "addr:full":"617 Washington Ave Mifflintown PA 17059",
    "addr:housenumber":"617",
    "addr:postcode":"17059",
    "addr:street":"Washington Ave",
    "iso:country":"US",
    "sg:address":"617 Washington Ave",
    "sg:city":"Mifflintown",
    "sg:classifiers":[
        {
            "category":"Travel",
            "subcategory":"Hotels & Motels",
            "type":"Entertainment"
        }
    ],
    "sg:phone":"+1 717 436 6605",
    "sg:postcode":"17059",
    "sg:province":"PA",
    "sg:tags":[
        "breakfast",
        "operation",
        "bed",
        "accommodation"
    ],
    "wof:name":"Rose House Bed & Breakfast",
    "wof:placetype":"venue"
},
  "geometry": {"coordinates":[-77.390632,40.572669],"type":"Point"}
}