{
  "type": "Feature",
  "properties": {
    "addr:full":"620 Chestnut St Philadelphia PA 19106",
    "addr:housenumber":"620",
    "addr:postcode":"19106",
    "addr:street":"Chestnut St",
    "iso:country":"US",
    "sg:address":"620 Chestnut St",
    "sg:city":"Philadelphia",
    "sg:classifiers":[
        {
            "category":"Professional",
            "subcategory":"Lawyer & Legal Services",
            "type":"Services"
        }
    ],
    "sg:phone":"+1 215 440 8000",
    "sg:postcode":"19106",
    "sg:province":"PA",
    "wof:name":"Zevnik Horton Llp",
    "wof:placetype":"venue"
},
  "geometry": {"coordinates":[-75.1511,39.949299],"type":"Point"}
}