{
  "type": "Feature",
  "properties": {
    "iso:country":"US",
    "sg:address":"1100 1st Ave",
    "sg:city":"King Of Prussia",
    "sg:classifiers":[
        {
            "category":"Professional",
            "subcategory":"Lawyer & Legal Services",
            "type":"Services"
        }
    ],
    "sg:phone":"+1   ",
    "sg:postcode":"19406",
    "sg:province":"PA",
    "wof:name":"Gelan D Hawk",
    "wof:placetype":"venue"
},
  "geometry": {"coordinates":[-75.41502199999999,40.095064],"type":"Point"}
}