{
  "type": "Feature",
  "properties": {
    "iso:country":"US",
    "sg:address":"222 E Durham St",
    "sg:city":"Philadelphia",
    "sg:classifiers":[
        {
            "category":"Education",
            "subcategory":"School",
            "type":"Public Place"
        }
    ],
    "sg:phone":"+1   ",
    "sg:postcode":"19119",
    "sg:province":"PA",
    "wof:name":"Islamic Day School of Phila",
    "wof:placetype":"venue"
},
  "geometry": {"coordinates":[-75.185768,40.062681],"type":"Point"}
}