{
  "type": "Feature",
  "properties": {
    "iso:country":"US",
    "sg:address":"2667 Egypt Rd",
    "sg:city":"Norristown",
    "sg:classifiers":[
        {
            "category":"Wholesale",
            "subcategory":"Farm Supplies",
            "type":"Manufacturing & Wholesale Goods"
        }
    ],
    "sg:phone":"+1 610 666 0725",
    "sg:postcode":"19403",
    "sg:province":"PA",
    "sg:tags":[
        "livestock"
    ],
    "wof:name":"Frank A Fillippo Inc",
    "wof:placetype":"venue"
},
  "geometry": {"coordinates":[-75.41269699999999,40.130069],"type":"Point"}
}