{
  "type": "Feature",
  "properties": {
    "iso:country":"US",
    "sg:address":"22 Pocono Rd",
    "sg:city":"Mt Pocono",
    "sg:classifiers":[
        {
            "category":"Building & Trades",
            "subcategory":"Construction",
            "type":"Services"
        }
    ],
    "sg:phone":"+1 570 894 2005",
    "sg:postcode":"18344",
    "sg:province":"PA",
    "sg:tags":[
        "general",
        "contractor"
    ],
    "wof:name":"Acinom Custom Walls",
    "wof:placetype":"venue"
},
  "geometry": {"coordinates":[-75.35862899999999,41.121103],"type":"Point"}
}