{
  "type": "Feature",
  "properties": {
    "iso:country":"US",
    "sg:address":"96 Zechman Dr",
    "sg:city":"Lewisburg",
    "sg:classifiers":[
        {
            "category":"Professional",
            "type":"Services"
        }
    ],
    "sg:phone":"+1   ",
    "sg:postcode":"17870",
    "sg:province":"PA",
    "wof:name":"Jerry L Bergenstock",
    "wof:placetype":"venue"
},
  "geometry": {"coordinates":[-76.90466000000001,40.804796],"type":"Point"}
}