{
  "type": "Feature",
  "properties": {
    "addr:full":"16A E Glenside Ave Glenside PA 19038",
    "addr:postcode":"19038",
    "addr:street":"Glenside Ave",
    "iso:country":"US",
    "sg:address":"16A E Glenside Ave",
    "sg:city":"Glenside",
    "sg:classifiers":[
        {
            "category":"Personal",
            "subcategory":"Beauty Salon",
            "type":"Services"
        }
    ],
    "sg:phone":"+1 215 885 8025",
    "sg:postcode":"19038",
    "sg:province":"PA",
    "wof:name":"Image Architechs",
    "wof:placetype":"venue"
},
  "geometry": {"coordinates":[-75.153339,40.100479],"type":"Point"}
}