{
  "type": "Feature",
  "properties": {
    "addr:full":"318 Roaring Spring Cmn Roaring Spring PA 16673",
    "addr:housenumber":"318",
    "addr:postcode":"16673",
    "addr:street":"Roaring",
    "iso:country":"US",
    "sg:address":"318 Roaring Spring Cmn",
    "sg:city":"Roaring Spring",
    "sg:classifiers":[
        {
            "category":"Professional",
            "subcategory":"Printing & Photocopies",
            "type":"Services"
        }
    ],
    "sg:phone":"+1 814 224 1300",
    "sg:postcode":"16673",
    "sg:province":"PA",
    "sg:tags":[
        "duplicating",
        "copying"
    ],
    "wof:name":"Copy-Rite Roaring Spring",
    "wof:placetype":"venue"
},
  "geometry": {"coordinates":[-78.389633,40.331515],"type":"Point"}
}