{
  "type": "Feature",
  "properties": {
    "iso:country":"US",
    "sg:address":"809 Lakeview Dr",
    "sg:city":"Mohnton",
    "sg:classifiers":[
        {
            "category":"Building & Trades",
            "subcategory":"Electrical",
            "type":"Services"
        }
    ],
    "sg:phone":"+1   ",
    "sg:postcode":"19540",
    "sg:province":"PA",
    "sg:tags":[
        "repair",
        "electrical",
        "contractor"
    ],
    "wof:name":"Bob Lineaweaver Electric",
    "wof:placetype":"venue"
},
  "geometry": {"coordinates":[-75.97717799999999,40.288197],"type":"Point"}
}