{
  "type": "Feature",
  "properties": {
    "addr:full":"60 N Market St Millerstown PA 17062",
    "addr:housenumber":"60",
    "addr:postcode":"17062",
    "addr:street":"N Market St",
    "iso:country":"US",
    "sg:address":"60 N Market St",
    "sg:city":"Millerstown",
    "sg:phone":"+1 717 589 3211",
    "sg:postcode":"17062",
    "sg:province":"PA",
    "sg:tags":[
        "oil"
    ],
    "wof:name":"J P Russell & Son Inc",
    "wof:placetype":"venue"
},
  "geometry": {"coordinates":[-77.15747500000001,40.553077],"type":"Point"}
}