{
  "type": "Feature",
  "properties": {
    "iso:country":"US",
    "sg:address":"4150 Parkside Ave",
    "sg:city":"Philadelphia",
    "sg:classifiers":[
        {
            "category":"Health Services",
            "subcategory":"Hospital",
            "type":"Services"
        }
    ],
    "sg:phone":"+1   ",
    "sg:postcode":"19104",
    "sg:province":"PA",
    "sg:tags":[
        "specialty"
    ],
    "wof:name":"Interim House West Phmc",
    "wof:placetype":"venue"
},
  "geometry": {"coordinates":[-75.20927500000001,39.976144],"type":"Point"}
}