{
  "type": "Feature",
  "properties": {
    "iso:country":"US",
    "sg:address":"721 Emily Ave",
    "sg:city":"Croydon",
    "sg:classifiers":[
        {
            "category":"Education",
            "subcategory":"School",
            "type":"Public Place"
        }
    ],
    "sg:phone":"+1 215 785 2120",
    "sg:postcode":"19021",
    "sg:province":"PA",
    "sg:tags":[
        "academic",
        "special"
    ],
    "wof:name":"Friendship Circle Early Chldhd",
    "wof:placetype":"venue"
},
  "geometry": {"coordinates":[-74.898149,40.090186],"type":"Point"}
}