{
  "type": "Feature",
  "properties": {
    "addr:full":"348 S Highland Ave Pittsburgh PA 15206",
    "addr:housenumber":"348",
    "addr:postcode":"15206",
    "addr:street":"S Highland Ave",
    "iso:country":"US",
    "sg:address":"348 S Highland Ave",
    "sg:city":"Pittsburgh",
    "sg:classifiers":[
        {
            "category":"Utilities",
            "subcategory":"Telephone",
            "type":"Services"
        }
    ],
    "sg:phone":"+1   ",
    "sg:postcode":"15206",
    "sg:province":"PA",
    "sg:tags":[
        "internet",
        "provider"
    ],
    "wof:name":"Hosting24-7com",
    "wof:placetype":"venue"
},
  "geometry": {"coordinates":[-79.92533299999999,40.456456],"type":"Point"}
}