{
  "type": "Feature",
  "properties": {
    "addr:full":"437 Jefferson Ave Washington PA 15301",
    "addr:housenumber":"437",
    "addr:postcode":"15301",
    "addr:street":"Jefferson Ave",
    "iso:country":"US",
    "sg:address":"437 Jefferson Ave",
    "sg:city":"Washington",
    "sg:classifiers":[
        {
            "category":"Wholesale",
            "subcategory":"Machinery & Supplies",
            "type":"Manufacturing & Wholesale Goods"
        },
        {
            "category":"Wholesale",
            "subcategory":"Electrical",
            "type":"Manufacturing & Wholesale Goods"
        }
    ],
    "sg:phone":"+1 724 223 2200",
    "sg:postcode":"15301",
    "sg:province":"PA",
    "sg:tags":[
        "equipment",
        "industrial",
        "electric"
    ],
    "sg:website":"www.fairmontsupply.com",
    "wof:name":"Fairmont Supply Company",
    "wof:placetype":"venue"
},
  "geometry": {"coordinates":[-80.255995,40.175396],"type":"Point"}
}