{
  "type": "Feature",
  "properties": {
    "iso:country":"US",
    "sg:address":"1409 Somerset Ave",
    "sg:city":"Windber",
    "sg:classifiers":[
        {
            "category":"Banks & Credit Unions",
            "subcategory":"Bank",
            "type":"Services"
        }
    ],
    "sg:phone":"+1   ",
    "sg:postcode":"15963",
    "sg:province":"PA",
    "sg:tags":[
        "state",
        "executive"
    ],
    "wof:name":"Cambria-Somerset Cog Credit Un",
    "wof:placetype":"venue"
},
  "geometry": {"coordinates":[-78.82996799999999,40.236156],"type":"Point"}
}