{
  "type": "Feature",
  "properties": {
    "iso:country":"US",
    "sg:address":"360 Southpointe Blvd",
    "sg:city":"Canonsburg",
    "sg:classifiers":[
        {
            "category":"Recreation",
            "type":"Entertainment"
        }
    ],
    "sg:phone":"+1 724 746 2950",
    "sg:postcode":"15317",
    "sg:province":"PA",
    "sg:tags":[
        "club",
        "course",
        "membership",
        "golf",
        "public"
    ],
    "wof:name":"Southpointe Golf Club Inc",
    "wof:placetype":"venue"
},
  "geometry": {"coordinates":[-80.172513,40.296068],"type":"Point"}
}