{
  "type": "Feature",
  "properties": {
    "iso:country":"US",
    "sg:address":"122 Vine St",
    "sg:city":"Homestead",
    "sg:classifiers":[
        {
            "category":"Professional",
            "subcategory":"Management & Consulting",
            "type":"Services"
        }
    ],
    "sg:phone":"+1   ",
    "sg:postcode":"15120",
    "sg:province":"PA",
    "sg:tags":[
        "retail",
        "direct",
        "sales"
    ],
    "wof:name":"Balloons n Favors",
    "wof:placetype":"venue"
},
  "geometry": {"coordinates":[-79.891702,40.403705],"type":"Point"}
}