{
  "type": "Feature",
  "properties": {
    "iso:country":"US",
    "sg:address":"610 Bailey Ln",
    "sg:city":"Boalsburg",
    "sg:classifiers":[
        {
            "category":"Farming",
            "subcategory":"Nursery",
            "type":"Manufacturing & Wholesale Goods"
        }
    ],
    "sg:phone":"+1 814 466 7546",
    "sg:postcode":"16827",
    "sg:province":"PA",
    "sg:tags":[
        "greenhouse"
    ],
    "wof:name":"Hillside Gardens",
    "wof:placetype":"venue"
},
  "geometry": {"coordinates":[-77.803595,40.76593],"type":"Point"}
}