{
  "type": "Feature",
  "properties": {
    "iso:country":"US",
    "sg:address":"4101 Nantucket Dr",
    "sg:city":"Mechanicsburg",
    "sg:classifiers":[
        {
            "category":"Professional",
            "subcategory":"Management & Consulting",
            "type":"Services"
        }
    ],
    "sg:phone":"+1   ",
    "sg:postcode":"17050",
    "sg:province":"PA",
    "sg:tags":[
        "consultant"
    ],
    "wof:name":"Martin & Associates",
    "wof:placetype":"venue"
},
  "geometry": {"coordinates":[-76.970612,40.27034],"type":"Point"}
}