{
  "type": "Feature",
  "properties": {
    "iso:country":"US",
    "sg:address":"300 E Philadelphia Ave",
    "sg:city":"Boyertown",
    "sg:classifiers":[
        {
            "category":"Professional",
            "subcategory":"Accounting & Tax Preparation",
            "type":"Services"
        }
    ],
    "sg:phone":"+1 610 369 3773",
    "sg:postcode":"19512",
    "sg:province":"PA",
    "sg:tags":[
        "accountant"
    ],
    "wof:name":"Larry E Hoffa & Co",
    "wof:placetype":"venue"
},
  "geometry": {"coordinates":[-75.632638,40.330448],"type":"Point"}
}