{
  "type": "Feature",
  "properties": {
    "addr:full":"1500 Sterling St Altoona PA 16602",
    "addr:housenumber":"1500",
    "addr:postcode":"16602",
    "addr:street":"Sterling St",
    "iso:country":"US",
    "sg:address":"1500 Sterling St",
    "sg:city":"Altoona",
    "sg:classifiers":[
        {
            "category":"Travel",
            "subcategory":"Hotels & Motels",
            "type":"Entertainment"
        }
    ],
    "sg:phone":"+1 814 946 7603",
    "sg:postcode":"16602",
    "sg:province":"PA",
    "wof:name":"Howard Johnson",
    "wof:placetype":"venue"
},
  "geometry": {"coordinates":[-78.403014,40.467169],"type":"Point"}
}