{
  "type": "Feature",
  "properties": {
    "iso:country":"US",
    "sg:address":"89 School St",
    "sg:city":"Kane",
    "sg:classifiers":[
        {
            "category":"Food & Beverages",
            "subcategory":"Specialty",
            "type":"Retail Goods"
        },
        {
            "category":"Food & Beverages",
            "subcategory":"Fruits & Vegetables",
            "type":"Retail Goods"
        }
    ],
    "sg:phone":"+1 814 837 7704",
    "sg:postcode":"16735",
    "sg:province":"PA",
    "sg:tags":[
        "herb",
        "spice"
    ],
    "wof:name":"Herbs Edgewood",
    "wof:placetype":"venue"
},
  "geometry": {"coordinates":[-78.813119,41.656785],"type":"Point"}
}