{
  "type": "Feature",
  "properties": {
    "iso:country":"US",
    "sg:address":"1812 Signal Hill Dr",
    "sg:city":"Mechanicsburg",
    "sg:classifiers":[
        {
            "category":"Building & Trades",
            "subcategory":"Equipment Rental",
            "type":"Services"
        }
    ],
    "sg:phone":"+1 717 732 0581",
    "sg:postcode":"17050",
    "sg:province":"PA",
    "sg:tags":[
        "crane"
    ],
    "wof:name":"Crane Christoph",
    "wof:placetype":"venue"
},
  "geometry": {"coordinates":[-76.99957999999999,40.27886],"type":"Point"}
}