{
  "type": "Feature",
  "properties": {
    "iso:country":"US",
    "sg:address":"10063 Sandmeyer Ln",
    "sg:city":"Philadelphia",
    "sg:classifiers":[
        {
            "category":"Building & Trades",
            "subcategory":"Plumbing",
            "type":"Services"
        }
    ],
    "sg:phone":"+1   ",
    "sg:postcode":"19116",
    "sg:province":"PA",
    "sg:tags":[
        "air",
        "heating",
        "conditioning",
        "contractor"
    ],
    "wof:name":"D J Tracy Mechanical LLC",
    "wof:placetype":"venue"
},
  "geometry": {"coordinates":[-75.03715200000001,40.114803],"type":"Point"}
}