{
  "type": "Feature",
  "properties": {
    "iso:country":"US",
    "sg:address":"1950 W Rockland St",
    "sg:city":"Philadelphia",
    "sg:classifiers":[
        {
            "category":"Professional",
            "type":"Services"
        }
    ],
    "sg:phone":"+1   ",
    "sg:postcode":"19141",
    "sg:province":"PA",
    "wof:name":"Diverified Sourcing",
    "wof:placetype":"venue"
},
  "geometry": {"coordinates":[-75.156741,40.028876],"type":"Point"}
}