{
  "type": "Feature",
  "properties": {
    "addr:full":"1741 Prospect Rd Washington Boro PA 17582",
    "addr:housenumber":"1741",
    "addr:postcode":"17582",
    "addr:street":"Prospect Rd",
    "iso:country":"US",
    "sg:address":"1741 Prospect Rd",
    "sg:city":"Washington Boro",
    "sg:classifiers":[
        {
            "category":"Farming",
            "subcategory":"Dairy Farm",
            "type":"Manufacturing & Wholesale Goods"
        }
    ],
    "sg:phone":"+1   ",
    "sg:postcode":"17582",
    "sg:province":"PA",
    "wof:name":"Burkholder John",
    "wof:placetype":"venue"
},
  "geometry": {"coordinates":[-76.455178,40.013772],"type":"Point"}
}