{
  "type": "Feature",
  "properties": {
    "iso:country":"US",
    "sg:address":"315 S 2nd Ave",
    "sg:city":"Lebanon",
    "sg:classifiers":[
        {
            "category":"Organizations",
            "subcategory":"Religious Organization",
            "type":"Services"
        }
    ],
    "sg:phone":"+1 717 273 6477",
    "sg:postcode":"17042",
    "sg:province":"PA",
    "sg:tags":[
        "clergy"
    ],
    "wof:name":"Mark R Kutz",
    "wof:placetype":"venue"
},
  "geometry": {"coordinates":[-76.407884,40.336132],"type":"Point"}
}