{
  "type": "Feature",
  "properties": {
    "iso:country":"US",
    "sg:address":"3013 Greenridge Dr",
    "sg:city":"Verona",
    "sg:classifiers":[
        {
            "category":"Professional",
            "subcategory":"Computer Services",
            "type":"Services"
        }
    ],
    "sg:phone":"+1 412 793 1878",
    "sg:postcode":"15147",
    "sg:province":"PA",
    "wof:name":"JAT Computer Solutions Inc",
    "wof:placetype":"venue"
},
  "geometry": {"coordinates":[-79.812395,40.511171],"type":"Point"}
}