{
  "type": "Feature",
  "properties": {
    "iso:country":"US",
    "sg:address":"7747 New Falls Rd",
    "sg:city":"Levittown",
    "sg:classifiers":[
        {
            "category":"Banks & Credit Unions",
            "subcategory":"Bank",
            "type":"Services"
        }
    ],
    "sg:phone":"+1   ",
    "sg:postcode":"19055",
    "sg:province":"PA",
    "sg:tags":[
        "personal",
        "institution"
    ],
    "wof:name":"Windsor Consumer Discount Co",
    "wof:placetype":"venue"
},
  "geometry": {"coordinates":[-74.845502,40.162557],"type":"Point"}
}