{
  "type": "Feature",
  "properties": {
    "iso:country":"US",
    "sg:address":"764 Kennedy St",
    "sg:city":"Meadville",
    "sg:classifiers":[
        {
            "category":"Health Services",
            "subcategory":"Doctor",
            "type":"Services"
        }
    ],
    "sg:phone":"+1 814 373 2195",
    "sg:postcode":"16335",
    "sg:province":"PA",
    "sg:tags":[
        "physician",
        "surgeon",
        "surgeons",
        "infectious",
        "disease"
    ],
    "wof:name":"Carol F Encarnacion Md",
    "wof:placetype":"venue"
},
  "geometry": {"coordinates":[-80.144914,41.641014],"type":"Point"}
}