{
  "type": "Feature",
  "properties": {
    "iso:country":"US",
    "sg:address":"408 Sheeley Ln",
    "sg:city":"Mechanicsburg",
    "sg:classifiers":[
        {
            "category":"Wholesale",
            "subcategory":"Motor Vehicles",
            "type":"Manufacturing & Wholesale Goods"
        }
    ],
    "sg:phone":"+1 717 766 7651",
    "sg:postcode":"17050",
    "sg:province":"PA",
    "sg:tags":[
        "body",
        "equipment",
        "truck"
    ],
    "sg:website":"www.nhtbco.com",
    "wof:name":"New Harrisburg Truck Body Co",
    "wof:placetype":"venue"
},
  "geometry": {"coordinates":[-76.980225,40.219981],"type":"Point"}
}