{
  "type": "Feature",
  "properties": {
    "iso:country":"US",
    "sg:address":"30 Rabbit Run Rd",
    "sg:city":"Malvern",
    "sg:classifiers":[
        {
            "category":"Professional",
            "type":"Services"
        }
    ],
    "sg:phone":"+1   ",
    "sg:postcode":"19355",
    "sg:province":"PA",
    "wof:name":"AV Cancelmo Fund Raising Div",
    "wof:placetype":"venue"
},
  "geometry": {"coordinates":[-75.467061,40.004512],"type":"Point"}
}