{
  "type": "Feature",
  "properties": {
    "iso:country":"US",
    "sg:address":"330 Burmont Rd",
    "sg:city":"Drexel Hill",
    "sg:classifiers":[
        {
            "category":"Shopping",
            "subcategory":"Catalog Store",
            "type":"Retail Goods"
        }
    ],
    "sg:phone":"+1   ",
    "sg:postcode":"19026",
    "sg:province":"PA",
    "sg:tags":[
        "house",
        "mail"
    ],
    "wof:name":"Jomar Enterprises",
    "wof:placetype":"venue"
},
  "geometry": {"coordinates":[-75.295694,39.942457],"type":"Point"}
}