{
  "type": "Feature",
  "properties": {
    "iso:country":"US",
    "sg:address":"252 S Jefferson St",
    "sg:city":"Kittanning",
    "sg:classifiers":[
        {
            "category":"Health Services",
            "subcategory":"Doctor",
            "type":"Services"
        }
    ],
    "sg:phone":"+1 724 543 3313",
    "sg:postcode":"16201",
    "sg:province":"PA",
    "wof:name":"Steven R Bono DDS",
    "wof:placetype":"venue"
},
  "geometry": {"coordinates":[-79.51676999999999,40.81132],"type":"Point"}
}