{
  "type": "Feature",
  "properties": {
    "iso:country":"US",
    "sg:address":"105 S 12th St",
    "sg:city":"Philadelphia",
    "sg:classifiers":[
        {
            "category":"Professional",
            "subcategory":"Lawyer & Legal Services",
            "type":"Services"
        }
    ],
    "sg:phone":"+1 215 625 9070",
    "sg:postcode":"19107",
    "sg:province":"PA",
    "wof:name":"Furman Jerome E Atty",
    "wof:placetype":"venue"
},
  "geometry": {"coordinates":[-75.160141,39.949939],"type":"Point"}
}