{
  "type": "Feature",
  "properties": {
    "iso:country":"US",
    "sg:address":"101 Logan Valley Mall",
    "sg:city":"Altoona",
    "sg:classifiers":[
        {
            "category":"Shopping",
            "subcategory":"Department Store",
            "type":"Retail Goods"
        }
    ],
    "sg:phone":"+1   ",
    "sg:postcode":"16602",
    "sg:province":"PA",
    "wof:name":"JC Penney",
    "wof:placetype":"venue"
},
  "geometry": {"coordinates":[-78.406322,40.472191],"type":"Point"}
}