{
  "type": "Feature",
  "properties": {
    "iso:country":"US",
    "sg:address":"417 E Roy Furman Hwy",
    "sg:city":"Waynesburg",
    "sg:classifiers":[
        {
            "category":"Restaurant",
            "type":"Food & Drink"
        }
    ],
    "sg:phone":"+1 724 627 8207",
    "sg:postcode":"15370",
    "sg:province":"PA",
    "wof:name":"Airport Restaurant",
    "wof:placetype":"venue"
},
  "geometry": {"coordinates":[-80.15701199999999,39.897745],"type":"Point"}
}