{
  "type": "Feature",
  "properties": {
    "iso:country":"US",
    "sg:address":"201 Laurel Dr",
    "sg:city":"Dalton",
    "sg:classifiers":[
        {
            "category":"Building & Trades",
            "subcategory":"Landscaping Services",
            "type":"Services"
        }
    ],
    "sg:phone":"+1   ",
    "sg:postcode":"18414",
    "sg:province":"PA",
    "wof:name":"Bk Evergreen Lawn Service",
    "wof:placetype":"venue"
},
  "geometry": {"coordinates":[-75.718677,41.516716],"type":"Point"}
}