{
  "type": "Feature",
  "properties": {
    "addr:full":"6110 Old Berwick Rd Bloomsburg PA 17815",
    "addr:housenumber":"6110",
    "addr:postcode":"17815",
    "addr:street":"Old Berwick Rd",
    "iso:country":"US",
    "sg:address":"6110 Old Berwick Rd",
    "sg:city":"Bloomsburg",
    "sg:classifiers":[
        {
            "category":"Health Services",
            "subcategory":"Doctor",
            "type":"Services"
        },
        {
            "category":"Health Services",
            "subcategory":"Dentist",
            "type":"Services"
        }
    ],
    "sg:phone":"+1 570 784 5054",
    "sg:postcode":"17815",
    "sg:province":"PA",
    "sg:tags":[
        "dentists-oral",
        "physician",
        "maxillofacial",
        "surgeons",
        "surgery",
        "oral"
    ],
    "wof:name":"Gronka Joseph P DMD",
    "wof:placetype":"venue"
},
  "geometry": {"coordinates":[-76.386875,41.01285],"type":"Point"}
}