{
  "type": "Feature",
  "properties": {
    "addr:full":"13710 Doolittle Rd Wattsburg PA 16442",
    "addr:housenumber":"13710",
    "addr:postcode":"16442",
    "addr:street":"Doolittle Rd",
    "iso:country":"US",
    "sg:address":"13710 Doolittle Rd",
    "sg:city":"Wattsburg",
    "sg:classifiers":[
        {
            "category":"Building & Trades",
            "subcategory":"Construction",
            "type":"Services"
        }
    ],
    "sg:phone":"+1   ",
    "sg:postcode":"16442",
    "sg:province":"PA",
    "sg:tags":[
        "housing"
    ],
    "wof:name":"Phillips Contracting",
    "wof:placetype":"venue"
},
  "geometry": {"coordinates":[-79.83247900000001,42.009783],"type":"Point"}
}