{
  "type": "Feature",
  "properties": {
    "addr:full":"3094 York Rd Gettysburg PA 17325",
    "addr:housenumber":"3094",
    "addr:postcode":"17325",
    "addr:street":"York Rd",
    "iso:country":"US",
    "sg:address":"3094 York Rd",
    "sg:city":"Gettysburg",
    "sg:classifiers":[
        {
            "category":"Home & Garden",
            "subcategory":"Furniture",
            "type":"Retail Goods"
        }
    ],
    "sg:phone":"+1 717 334 9564",
    "sg:postcode":"17325",
    "sg:province":"PA",
    "sg:tags":[
        "new",
        "household",
        "used",
        "television"
    ],
    "wof:name":"Hartlaubs New & Used Furniture",
    "wof:placetype":"venue"
},
  "geometry": {"coordinates":[-77.136081,39.859517],"type":"Point"}
}