{
  "type": "Feature",
  "properties": {
    "iso:country":"US",
    "sg:address":"14675 State Rte 36",
    "sg:city":"Punxsutawney",
    "sg:classifiers":[
        {
            "category":"Autos & Motor Vehicles",
            "subcategory":"Automobile Sales",
            "type":"Retail Goods"
        }
    ],
    "sg:phone":"+1 814 938 9395",
    "sg:postcode":"15767",
    "sg:province":"PA",
    "sg:tags":[
        "car",
        "dealer"
    ],
    "wof:name":"Route 36 Auto Sales",
    "wof:placetype":"venue"
},
  "geometry": {"coordinates":[-79.10048999999999,41.11741],"type":"Point"}
}