{
  "type": "Feature",
  "properties": {
    "addr:full":"521 Greenfield Rd Lancaster PA 17601",
    "addr:housenumber":"521",
    "addr:postcode":"17601",
    "addr:street":"Greenfield Rd",
    "iso:country":"US",
    "sg:address":"521 Greenfield Rd",
    "sg:city":"Lancaster",
    "sg:classifiers":[
        {
            "category":"Restaurant",
            "type":"Food & Drink"
        }
    ],
    "sg:phone":"+1 717 397 0220",
    "sg:postcode":"17601",
    "sg:province":"PA",
    "sg:tags":[
        "cafe"
    ],
    "wof:name":"Cafe Sandalwood",
    "wof:placetype":"venue"
},
  "geometry": {"coordinates":[-76.25310399999999,40.053593],"type":"Point"}
}