{
  "type": "Feature",
  "properties": {
    "iso:country":"US",
    "sg:address":"985 Old Eagle School Rd",
    "sg:city":"Wayne",
    "sg:classifiers":[
        {
            "category":"Insurance",
            "subcategory":"Insurance Agent",
            "type":"Services"
        }
    ],
    "sg:phone":"+1 610 687 3869",
    "sg:postcode":"19087",
    "sg:province":"PA",
    "sg:tags":[
        "consultant"
    ],
    "sg:website":"www.consolidatedriskservices.com",
    "wof:name":"Consolidated Risk Svc Inc",
    "wof:placetype":"venue"
},
  "geometry": {"coordinates":[-75.410695,40.076273],"type":"Point"}
}