{
  "type": "Feature",
  "properties": {
    "iso:country":"US",
    "sg:address":"3075 Washington Rd",
    "sg:city":"Canonsburg",
    "sg:classifiers":[
        {
            "category":"Sports & Exercise",
            "subcategory":"Gym",
            "type":"Entertainment"
        }
    ],
    "sg:phone":"+1 724 942 3870",
    "sg:postcode":"15317",
    "sg:province":"PA",
    "sg:tags":[
        "trainer"
    ],
    "wof:name":"Fitness Performance",
    "wof:placetype":"venue"
},
  "geometry": {"coordinates":[-80.105698,40.291599],"type":"Point"}
}