{
  "type": "Feature",
  "properties": {
    "addr:full":"34 Edward Rd Hatboro PA 19040",
    "addr:housenumber":"34",
    "addr:postcode":"19040",
    "addr:street":"Edward Rd",
    "iso:country":"US",
    "sg:address":"34 Edward Rd",
    "sg:city":"Hatboro",
    "sg:classifiers":[
        {
            "category":"Manufacturing",
            "subcategory":"Motor Vehicles & Parts",
            "type":"Manufacturing & Wholesale Goods"
        }
    ],
    "sg:phone":"+1   ",
    "sg:postcode":"19040",
    "sg:province":"PA",
    "sg:tags":[
        "cylinder",
        "head"
    ],
    "wof:name":"Rogers Performance",
    "wof:placetype":"venue"
},
  "geometry": {"coordinates":[-75.107501,40.191651],"type":"Point"}
}