{
  "type": "Feature",
  "properties": {
    "iso:country":"US",
    "sg:address":"103 Belmont S Ste 2",
    "sg:city":"Kittanning",
    "sg:classifiers":[
        {
            "category":"Shopping",
            "subcategory":"Department Store",
            "type":"Retail Goods"
        },
        {
            "category":"Shopping",
            "subcategory":"Clothing, Apparel, & Fashions",
            "type":"Retail Goods"
        },
        {
            "category":"Shopping",
            "subcategory":"Discount & Variety Stores",
            "type":"Retail Goods"
        },
        {
            "category":"Shopping",
            "type":"Retail Goods"
        }
    ],
    "sg:phone":"+1 724 543 2023",
    "sg:postcode":"16201",
    "sg:province":"PA",
    "sg:tags":[
        "clothing",
        "merchandise"
    ],
    "sg:website":"http://www.walmart.com",
    "wof:name":"Wal-Mart",
    "wof:placetype":"venue"
},
  "geometry": {"coordinates":[-79.535667,40.812851],"type":"Point"}
}