{
  "type": "Feature",
  "properties": {
    "iso:country":"US",
    "sg:address":"2157 S Queen St",
    "sg:city":"York",
    "sg:classifiers":[
        {
            "category":"Autos & Motor Vehicles",
            "subcategory":"Automobile Sales",
            "type":"Retail Goods"
        }
    ],
    "sg:phone":"+1   ",
    "sg:postcode":"17402",
    "sg:province":"PA",
    "sg:tags":[
        "passenger",
        "used"
    ],
    "wof:name":"Vision Lincoln Mercury",
    "wof:placetype":"venue"
},
  "geometry": {"coordinates":[-76.686882,39.929215],"type":"Point"}
}