{
  "type": "Feature",
  "properties": {
    "addr:full":"320 Commons Dr Parkesburg PA 19365",
    "addr:housenumber":"320",
    "addr:postcode":"19365",
    "addr:street":"Commons Dr",
    "iso:country":"US",
    "sg:address":"320 Commons Dr",
    "sg:city":"Parkesburg",
    "sg:classifiers":[
        {
            "category":"Wholesale",
            "subcategory":"Machinery & Supplies",
            "type":"Manufacturing & Wholesale Goods"
        }
    ],
    "sg:phone":"+1 610 857 1998",
    "sg:postcode":"19365",
    "sg:province":"PA",
    "sg:tags":[
        "salon",
        "beauty"
    ],
    "wof:name":"Sally Beauty Supply",
    "wof:placetype":"venue"
},
  "geometry": {"coordinates":[-75.934332,39.981573],"type":"Point"}
}