{
  "type": "Feature",
  "properties": {
    "addr:full":"11 Franklin Village Mall Kittanning PA 16201",
    "addr:housenumber":"11",
    "addr:postcode":"16201",
    "addr:street":"Franklin Village Mall",
    "iso:country":"US",
    "sg:address":"11 Franklin Village Mall",
    "sg:city":"Kittanning",
    "sg:classifiers":[
        {
            "category":"Organizations",
            "subcategory":"Membership Organization",
            "type":"Services"
        }
    ],
    "sg:phone":"+1   ",
    "sg:postcode":"16201",
    "sg:province":"PA",
    "wof:name":"AAA",
    "wof:placetype":"venue"
},
  "geometry": {"coordinates":[-79.54858299999999,40.81228],"type":"Point"}
}