{
  "type": "Feature",
  "properties": {
    "addr:full":"1001 Washington Pike Bridgeville PA 15017",
    "addr:housenumber":"1001",
    "addr:postcode":"15017",
    "addr:street":"Washington Pike",
    "iso:country":"US",
    "sg:address":"1001 Washington Pike",
    "sg:city":"Bridgeville",
    "sg:classifiers":[
        {
            "category":"Food & Beverages",
            "subcategory":"Groceries & Convenience Stores",
            "type":"Retail Goods"
        }
    ],
    "sg:phone":"+1 412 220 0356",
    "sg:postcode":"15017",
    "sg:province":"PA",
    "wof:name":"Atlantic Refining & Marketing",
    "wof:placetype":"venue"
},
  "geometry": {"coordinates":[-80.10906199999999,40.364808],"type":"Point"}
}