{
  "type": "Feature",
  "properties": {
    "iso:country":"US",
    "sg:address":"201 Erie St",
    "sg:city":"Grove City",
    "sg:classifiers":[
        {
            "category":"Health Services",
            "subcategory":"Clinic",
            "type":"Services"
        },
        {
            "category":"Health Services",
            "subcategory":"Health Practitioner",
            "type":"Services"
        }
    ],
    "sg:phone":"+1 724 458 5850",
    "sg:postcode":"16127",
    "sg:province":"PA",
    "sg:tags":[
        "therapist",
        "specialty",
        "outpatient",
        "physical"
    ],
    "sg:website":"www.tmspt.com",
    "wof:name":"Tms Physical Therapy",
    "wof:placetype":"venue"
},
  "geometry": {"coordinates":[-80.08807299999999,41.161834],"type":"Point"}
}