{
  "type": "Feature",
  "properties": {
    "addr:full":"1649 Lititz Pike Lancaster PA 17601",
    "addr:housenumber":"1649",
    "addr:postcode":"17601",
    "addr:street":"Lititz Pike",
    "iso:country":"US",
    "sg:address":"1649 Lititz Pike",
    "sg:city":"Lancaster",
    "sg:classifiers":[
        {
            "category":"Education",
            "subcategory":"Special Training",
            "type":"Public Place"
        }
    ],
    "sg:phone":"+1 717 291 1140",
    "sg:postcode":"17601",
    "sg:province":"PA",
    "sg:tags":[
        "craft"
    ],
    "wof:name":"A C Moore",
    "wof:placetype":"venue"
},
  "geometry": {"coordinates":[-76.307546,40.0689],"type":"Point"}
}