{
  "type": "Feature",
  "properties": {
    "addr:full":"724 Coventry Pointe Ln Pottstown PA 19465",
    "addr:housenumber":"724",
    "addr:postcode":"19465",
    "addr:street":"Coventry Pointe Ln",
    "iso:country":"US",
    "sg:address":"724 Coventry Pointe Ln",
    "sg:city":"Pottstown",
    "sg:classifiers":[
        {
            "category":"Shopping",
            "subcategory":"Clothing, Apparel, & Fashions",
            "type":"Retail Goods"
        }
    ],
    "sg:phone":"+1   ",
    "sg:postcode":"19465",
    "sg:province":"PA",
    "sg:tags":[
        "family"
    ],
    "wof:name":"Gap",
    "wof:placetype":"venue"
},
  "geometry": {"coordinates":[-75.662088,40.229172],"type":"Point"}
}