{
  "type": "Feature",
  "properties": {
    "addr:full":"646 N Lancaster St Jonestown PA 17038",
    "addr:housenumber":"646",
    "addr:postcode":"17038",
    "addr:street":"N Lancaster St",
    "iso:country":"US",
    "sg:address":"646 N Lancaster St",
    "sg:city":"Jonestown",
    "sg:classifiers":[
        {
            "category":"Farming",
            "subcategory":"Dairy Farm",
            "type":"Manufacturing & Wholesale Goods"
        }
    ],
    "sg:phone":"+1   ",
    "sg:postcode":"17038",
    "sg:province":"PA",
    "wof:name":"Mar Ree Farms",
    "wof:placetype":"venue"
},
  "geometry": {"coordinates":[-76.478905,40.42791],"type":"Point"}
}