{
  "type": "Feature",
  "properties": {
    "iso:country":"US",
    "sg:address":"1014 Stonehedge Dr",
    "sg:city":"Coraopolis",
    "sg:classifiers":[
        {
            "category":"Professional",
            "subcategory":"Business Services",
            "type":"Services"
        }
    ],
    "sg:phone":"+1   ",
    "sg:postcode":"15108",
    "sg:province":"PA",
    "sg:tags":[
        "franchise"
    ],
    "wof:name":"Vavco Hospitality Inc",
    "wof:placetype":"venue"
},
  "geometry": {"coordinates":[-80.114893,40.488963],"type":"Point"}
}