{
  "type": "Feature",
  "properties": {
    "iso:country":"US",
    "sg:address":"1306 Valley Glen Rd",
    "sg:city":"Elkins Park",
    "sg:classifiers":[
        {
            "category":"Professional",
            "subcategory":"Advertising",
            "type":"Services"
        }
    ],
    "sg:phone":"+1   ",
    "sg:postcode":"19027",
    "sg:province":"PA",
    "sg:tags":[
        "steel",
        "product",
        "mfg"
    ],
    "wof:name":"FMI Display Services Inc",
    "wof:placetype":"venue"
},
  "geometry": {"coordinates":[-75.101615,40.080018],"type":"Point"}
}