{
  "type": "Feature",
  "properties": {
    "iso:country":"US",
    "sg:address":"226 Fairfield Ave",
    "sg:city":"Johnstown",
    "sg:classifiers":[
        {
            "category":"Health Services",
            "subcategory":"Health Practitioner",
            "type":"Services"
        }
    ],
    "sg:phone":"+1   ",
    "sg:postcode":"15906",
    "sg:province":"PA",
    "sg:tags":[
        "osteopathic"
    ],
    "wof:name":"Kowtoniuk Walter V Dr",
    "wof:placetype":"venue"
},
  "geometry": {"coordinates":[-78.94728499999999,40.34457],"type":"Point"}
}