{
  "type": "Feature",
  "properties": {
    "iso:country":"US",
    "sg:address":"1015 S 13th St",
    "sg:city":"Altoona",
    "sg:classifiers":[
        {
            "category":"Health Services",
            "subcategory":"Doctor",
            "type":"Services"
        }
    ],
    "sg:phone":"+1   ",
    "sg:postcode":"16602",
    "sg:province":"PA",
    "wof:name":"Gerald Osmolinski DDS",
    "wof:placetype":"venue"
},
  "geometry": {"coordinates":[-78.384135,40.504498],"type":"Point"}
}