{
  "type": "Feature",
  "properties": {
    "iso:country":"US",
    "sg:address":"1041 Maple St",
    "sg:city":"Lebanon",
    "sg:classifiers":[
        {
            "category":"Food & Beverages",
            "subcategory":"Groceries & Convenience Stores",
            "type":"Retail Goods"
        }
    ],
    "sg:phone":"+1 717 272 0125",
    "sg:postcode":"17046",
    "sg:province":"PA",
    "sg:tags":[
        "grocer"
    ],
    "wof:name":"Hutter Stores Inc",
    "wof:placetype":"venue"
},
  "geometry": {"coordinates":[-76.43059599999999,40.34976],"type":"Point"}
}