{
  "type": "Feature",
  "properties": {
    "iso:country":"US",
    "sg:address":"142 Jordan St",
    "sg:city":"South Heights",
    "sg:classifiers":[
        {
            "category":"Health Services",
            "subcategory":"Chiropractor",
            "type":"Services"
        }
    ],
    "sg:phone":"+1 724 375 5534",
    "sg:postcode":"15081",
    "sg:province":"PA",
    "wof:name":"Tejan Chiropractic Inc",
    "wof:placetype":"venue"
},
  "geometry": {"coordinates":[-80.235649,40.574867],"type":"Point"}
}