{
  "type": "Feature",
  "properties": {
    "iso:country":"US",
    "sg:address":"300 1st Ave",
    "sg:city":"Red Lion",
    "sg:classifiers":[
        {
            "category":"Communications",
            "type":"Services"
        }
    ],
    "sg:phone":"+1 717 244 9661",
    "sg:postcode":"17356",
    "sg:province":"PA",
    "wof:name":"Apa Communications",
    "wof:placetype":"venue"
},
  "geometry": {"coordinates":[-76.61210199999999,39.897199],"type":"Point"}
}