{
  "type": "Feature",
  "properties": {
    "iso:country":"US",
    "sg:address":"414 Jefferson Ave",
    "sg:city":"Cheltenham",
    "sg:classifiers":[
        {
            "category":"Insurance",
            "subcategory":"Insurance Agent",
            "type":"Services"
        }
    ],
    "sg:phone":"+1 215 379 2400",
    "sg:postcode":"19012",
    "sg:province":"PA",
    "wof:name":"Francis Martino Insurance",
    "wof:placetype":"venue"
},
  "geometry": {"coordinates":[-75.093903,40.065997],"type":"Point"}
}