{
  "type": "Feature",
  "properties": {
    "iso:country":"US",
    "sg:address":"222 Cameron Dr",
    "sg:city":"Slippery Rock",
    "sg:classifiers":[
        {
            "category":"Professional",
            "type":"Services"
        }
    ],
    "sg:phone":"+1 724 738 0230",
    "sg:postcode":"16057",
    "sg:province":"PA",
    "sg:tags":[
        "establishment"
    ],
    "wof:name":"Capital Asset Protection Inc",
    "wof:placetype":"venue"
},
  "geometry": {"coordinates":[-80.037054,41.056619],"type":"Point"}
}