{
  "type": "Feature",
  "properties": {
    "addr:full":"18 E Market St Bethlehem PA 18018",
    "addr:housenumber":"18",
    "addr:postcode":"18018",
    "addr:street":"E Market St",
    "iso:country":"US",
    "sg:address":"18 E Market St",
    "sg:city":"Bethlehem",
    "sg:classifiers":[
        {
            "category":"Professional",
            "subcategory":"Lawyer & Legal Services",
            "type":"Services"
        }
    ],
    "sg:phone":"+1 610 868 8543",
    "sg:postcode":"18018",
    "sg:province":"PA",
    "sg:tags":[
        "attorney"
    ],
    "wof:name":"Riskin & Riskin",
    "wof:placetype":"venue"
},
  "geometry": {"coordinates":[-75.377701,40.620701],"type":"Point"}
}