{
  "type": "Feature",
  "properties": {
    "iso:country":"US",
    "sg:address":"437 Grant St",
    "sg:city":"Pittsburgh",
    "sg:classifiers":[
        {
            "category":"Professional",
            "subcategory":"Lawyer & Legal Services",
            "type":"Services"
        }
    ],
    "sg:phone":"+1 412 434 7500",
    "sg:postcode":"15219",
    "sg:province":"PA",
    "wof:name":"Rogers Peter M ESQ",
    "wof:placetype":"venue"
},
  "geometry": {"coordinates":[-79.9972,40.438801],"type":"Point"}
}