{
  "type": "Feature",
  "properties": {
    "iso:country":"US",
    "sg:address":"78 S 69th St",
    "sg:city":"Upper Darby",
    "sg:classifiers":[
        {
            "category":"Shopping",
            "subcategory":"Bicycles & Sporting Goods",
            "type":"Retail Goods"
        }
    ],
    "sg:phone":"+1 610 352 9503",
    "sg:postcode":"19082",
    "sg:province":"PA",
    "sg:website":"www.modells.com",
    "wof:name":"Modell's Sporting Goods",
    "wof:placetype":"venue"
},
  "geometry": {"coordinates":[-75.25859800000001,39.959301],"type":"Point"}
}