{
  "type": "Feature",
  "properties": {
    "iso:country":"US",
    "sg:address":"425 Broad St",
    "sg:city":"Tatamy",
    "sg:classifiers":[
        {
            "category":"Government",
            "subcategory":"Police Station",
            "type":"Public Place"
        }
    ],
    "sg:phone":"+1 610 252 2260",
    "sg:postcode":"18085",
    "sg:province":"PA",
    "sg:tags":[
        "department"
    ],
    "wof:name":"Tatamy Borouth Police Dept",
    "wof:placetype":"venue"
},
  "geometry": {"coordinates":[-75.25287899999999,40.74042],"type":"Point"}
}