{
  "type": "Feature",
  "properties": {
    "iso:country":"US",
    "sg:address":"728 W Main St",
    "sg:city":"Lansdale",
    "sg:classifiers":[
        {
            "category":"Personal",
            "subcategory":"Barber",
            "type":"Services"
        }
    ],
    "sg:phone":"+1 215 855 7155",
    "sg:postcode":"19446",
    "sg:province":"PA",
    "wof:name":"Kristy Salon",
    "wof:placetype":"venue"
},
  "geometry": {"coordinates":[-75.292198,40.246799],"type":"Point"}
}