{
  "type": "Feature",
  "properties": {
    "iso:country":"US",
    "sg:address":"542 Wesley Rd",
    "sg:city":"Springfield",
    "sg:classifiers":[
        {
            "category":"Organizations",
            "subcategory":"Religious Organization",
            "type":"Services"
        }
    ],
    "sg:phone":"+1 610 449 7799",
    "sg:postcode":"19064",
    "sg:province":"PA",
    "sg:tags":[
        "church"
    ],
    "wof:name":"Broomall Korean Presbyterian",
    "wof:placetype":"venue"
},
  "geometry": {"coordinates":[-75.352761,39.931182],"type":"Point"}
}