{
  "type": "Feature",
  "properties": {
    "addr:full":"3727 Birney Ave Moosic PA 18507",
    "addr:housenumber":"3727",
    "addr:postcode":"18507",
    "addr:street":"Birney Ave",
    "iso:country":"US",
    "sg:address":"3727 Birney Ave",
    "sg:city":"Moosic",
    "sg:classifiers":[
        {
            "category":"Government",
            "subcategory":"Fire Station",
            "type":"Public Place"
        }
    ],
    "sg:phone":"+1 570 961 9454",
    "sg:postcode":"18507",
    "sg:province":"PA",
    "sg:tags":[
        "department",
        "company",
        "volunteer"
    ],
    "wof:name":"Greenwood Hose Co",
    "wof:placetype":"venue"
},
  "geometry": {"coordinates":[-75.707004,41.371464],"type":"Point"}
}