{
  "type": "Feature",
  "properties": {
    "addr:full":"32 Central Ave Berwyn PA 19312",
    "addr:housenumber":"32",
    "addr:postcode":"19312",
    "addr:street":"Central Ave",
    "iso:country":"US",
    "sg:address":"32 Central Ave",
    "sg:city":"Berwyn",
    "sg:classifiers":[
        {
            "category":"Building & Trades",
            "subcategory":"Plumbing",
            "type":"Services"
        }
    ],
    "sg:phone":"+1   ",
    "sg:postcode":"19312",
    "sg:province":"PA",
    "sg:tags":[
        "contractor"
    ],
    "wof:name":"Rek Krohn Plumbing and Heating",
    "wof:placetype":"venue"
},
  "geometry": {"coordinates":[-75.445701,40.045782],"type":"Point"}
}