{
  "type": "Feature",
  "properties": {
    "addr:full":"459A W Ellet St Philadelphia PA 19119",
    "addr:housenumber":"459a",
    "addr:postcode":"19119",
    "addr:street":"W Ellet St",
    "iso:country":"US",
    "sg:address":"459A W Ellet St",
    "sg:city":"Philadelphia",
    "sg:classifiers":[
        {
            "category":"Professional",
            "subcategory":"Detective & Security Services",
            "type":"Services"
        }
    ],
    "sg:phone":"+1 215 906 9409",
    "sg:postcode":"19119",
    "sg:province":"PA",
    "sg:tags":[
        "car",
        "armored",
        "private",
        "investigator"
    ],
    "wof:name":"Vigiles Corp.",
    "wof:placetype":"venue"
},
  "geometry": {"coordinates":[-75.19579400000001,40.050002],"type":"Point"}
}