{
  "type": "Feature",
  "properties": {
    "iso:country":"US",
    "sg:address":"1006 Perry Hwy",
    "sg:city":"Harmony",
    "sg:classifiers":[
        {
            "category":"Autos & Motor Vehicles",
            "subcategory":"Boat Sales",
            "type":"Retail Goods"
        },
        {
            "category":"Personal",
            "subcategory":"Beauty Salon",
            "type":"Services"
        }
    ],
    "sg:phone":"+1 724 368 9400",
    "sg:postcode":"16037",
    "sg:province":"PA",
    "sg:tags":[
        "equipment",
        "marine"
    ],
    "wof:name":"Nautical Design Inc",
    "wof:placetype":"venue"
},
  "geometry": {"coordinates":[-80.139757,40.902051],"type":"Point"}
}