{
  "type": "Feature",
  "properties": {
    "addr:full":"489 Salem Dr Pittsburgh PA 15243",
    "addr:housenumber":"489",
    "addr:postcode":"15243",
    "addr:street":"Salem Dr",
    "iso:country":"US",
    "sg:address":"489 Salem Dr",
    "sg:city":"Pittsburgh",
    "sg:classifiers":[
        {
            "category":"Banks & Credit Unions",
            "subcategory":"Bank",
            "type":"Services"
        }
    ],
    "sg:phone":"+1 412 343 7754",
    "sg:postcode":"15243",
    "sg:province":"PA",
    "sg:tags":[
        "loan",
        "real estate"
    ],
    "wof:name":"PHH Mortgage Svc Inc",
    "wof:placetype":"venue"
},
  "geometry": {"coordinates":[-80.05744,40.380215],"type":"Point"}
}