{
  "type": "Feature",
  "properties": {
    "iso:country":"US",
    "sg:address":"1905 Village Rd",
    "sg:city":"Orwigsburg",
    "sg:classifiers":[
        {
            "category":"Organizations",
            "subcategory":"Community Association",
            "type":"Services"
        }
    ],
    "sg:phone":"+1 570 366 1000",
    "sg:postcode":"17961",
    "sg:province":"PA",
    "wof:name":"Pinebrook Homeowners Association (19)",
    "wof:placetype":"venue"
},
  "geometry": {"coordinates":[-76.077887,40.642931],"type":"Point"}
}