{
  "type": "Feature",
  "properties": {
    "addr:full":"1211 3rd Ave Duncansville PA 16635",
    "addr:housenumber":"1211",
    "addr:postcode":"16635",
    "addr:street":"3Rd Ave",
    "iso:country":"US",
    "sg:address":"1211 3rd Ave",
    "sg:city":"Duncansville",
    "sg:classifiers":[
        {
            "category":"Social Services",
            "type":"Services"
        }
    ],
    "sg:phone":"+1 814 695 0203",
    "sg:postcode":"16635",
    "sg:province":"PA",
    "sg:tags":[
        "organization",
        "welfare"
    ],
    "wof:name":"Duncansville Senior Ctr",
    "wof:placetype":"venue"
},
  "geometry": {"coordinates":[-78.43302199999999,40.423435],"type":"Point"}
}