{
  "type": "Feature",
  "properties": {
    "addr:full":"1210 Fox Den Rd Chambersburg PA 17202",
    "addr:housenumber":"1210",
    "addr:postcode":"17202",
    "addr:street":"Fox Den Rd",
    "iso:country":"US",
    "sg:address":"1210 Fox Den Rd",
    "sg:city":"Chambersburg",
    "sg:classifiers":[
        {
            "category":"Personal",
            "subcategory":"Beauty Salon",
            "type":"Services"
        }
    ],
    "sg:phone":"+1 717 264 3402",
    "sg:postcode":"17202",
    "sg:province":"PA",
    "wof:name":"Hair Racquet",
    "wof:placetype":"venue"
},
  "geometry": {"coordinates":[-80.19882200000001,40.18358],"type":"Point"}
}