{
  "type": "Feature",
  "properties": {
    "addr:full":"5025 Drummond Cir Center Valley PA 18034",
    "addr:housenumber":"5025",
    "addr:postcode":"18034",
    "addr:street":"Drummond Cir",
    "iso:country":"US",
    "sg:address":"5025 Drummond Cir",
    "sg:city":"Center Valley",
    "sg:classifiers":[
        {
            "category":"Professional",
            "type":"Services"
        }
    ],
    "sg:phone":"+1   ",
    "sg:postcode":"18034",
    "sg:province":"PA",
    "wof:name":"Jorge R Tapies",
    "wof:placetype":"venue"
},
  "geometry": {"coordinates":[-75.404083,40.546916],"type":"Point"}
}