{
  "type": "Feature",
  "properties": {
    "iso:country":"US",
    "sg:address":"602 W Walnut Ln",
    "sg:city":"Philadelphia",
    "sg:classifiers":[
        {
            "category":"Banks & Credit Unions",
            "subcategory":"Bank",
            "type":"Services"
        }
    ],
    "sg:phone":"+1   ",
    "sg:postcode":"19128",
    "sg:province":"PA",
    "sg:tags":[
        "company",
        "mortgage"
    ],
    "wof:name":"Open",
    "wof:placetype":"venue"
},
  "geometry": {"coordinates":[-75.205679,40.028711],"type":"Point"}
}