{
  "type": "Feature",
  "properties": {
    "iso:country":"US",
    "sg:address":"3458 Pennell Rd",
    "sg:city":"Aston",
    "sg:classifiers":[
        {
            "category":"Restaurant",
            "type":"Food & Drink"
        }
    ],
    "sg:phone":"+1 610 494 8062",
    "sg:postcode":"19014",
    "sg:province":"PA",
    "sg:tags":[
        "grill",
        "bar"
    ],
    "wof:name":"Memories Grill",
    "wof:placetype":"venue"
},
  "geometry": {"coordinates":[-75.427868,39.86445],"type":"Point"}
}