{
  "type": "Feature",
  "properties": {
    "iso:country":"US",
    "sg:address":"615 Carverton Rd",
    "sg:city":"Wyoming",
    "sg:classifiers":[
        {
            "category":"Shopping",
            "subcategory":"Gifts & Souvenirs",
            "type":"Retail Goods"
        }
    ],
    "sg:phone":"+1   ",
    "sg:postcode":"18644",
    "sg:province":"PA",
    "wof:name":"Beagle & Co",
    "wof:placetype":"venue"
},
  "geometry": {"coordinates":[-75.875466,41.335099],"type":"Point"}
}