{
  "type": "Feature",
  "properties": {
    "iso:country":"US",
    "sg:address":"3000 Meetinghouse Rd",
    "sg:city":"Philadelphia",
    "sg:classifiers":[
        {
            "category":"Food & Beverages",
            "subcategory":"Liquor & Beverages",
            "type":"Retail Goods"
        },
        {
            "category":"Wholesale",
            "subcategory":"Wine & Distilled Alcoholic Beverages",
            "type":"Manufacturing & Wholesale Goods"
        }
    ],
    "sg:phone":"+1 215 698 9500",
    "sg:postcode":"19154",
    "sg:province":"PA",
    "sg:tags":[
        "liquors-wholesale",
        "beer",
        "ale"
    ],
    "sg:website":"http://www.origlio.com",
    "wof:name":"Antonio Origlio, Inc.",
    "wof:placetype":"venue"
},
  "geometry": {"coordinates":[-74.968979,40.112881],"type":"Point"}
}