{
  "type": "Feature",
  "properties": {
    "iso:country":"US",
    "sg:address":"326 Centre St",
    "sg:city":"Freeland",
    "sg:classifiers":[
        {
            "category":"Personal",
            "subcategory":"Beauty Salon",
            "type":"Services"
        }
    ],
    "sg:phone":"+1   ",
    "sg:postcode":"18224",
    "sg:province":"PA",
    "sg:tags":[
        "shop",
        "fitness",
        "physical",
        "facility"
    ],
    "wof:name":"Segon Mary Beth Beauty Salon",
    "wof:placetype":"venue"
},
  "geometry": {"coordinates":[-75.897437,41.014878],"type":"Point"}
}