{
  "type": "Feature",
  "properties": {
    "addr:full":"184 Niantic Rd Barto PA 19504",
    "addr:housenumber":"184",
    "addr:postcode":"19504",
    "addr:street":"Niantic Rd",
    "iso:country":"US",
    "sg:address":"184 Niantic Rd",
    "sg:city":"Barto",
    "sg:classifiers":[
        {
            "category":"Building & Trades",
            "subcategory":"Construction",
            "type":"Services"
        }
    ],
    "sg:phone":"+1   ",
    "sg:postcode":"19504",
    "sg:province":"PA",
    "sg:tags":[
        "home",
        "speculative",
        "builder"
    ],
    "wof:name":"Trim Development Co",
    "wof:placetype":"venue"
},
  "geometry": {"coordinates":[-75.56723,40.375736],"type":"Point"}
}