{
  "type": "Feature",
  "properties": {
    "addr:full":"4841 Bulltown Rd Murrysville PA 15668",
    "addr:housenumber":"4841",
    "addr:postcode":"15668",
    "addr:street":"Bulltown Rd",
    "iso:country":"US",
    "sg:address":"4841 Bulltown Rd",
    "sg:city":"Murrysville",
    "sg:classifiers":[
        {
            "category":"Building & Trades",
            "subcategory":"Landscaping Services",
            "type":"Services"
        }
    ],
    "sg:phone":"+1   ",
    "sg:postcode":"15668",
    "sg:province":"PA",
    "wof:name":"A Caldwell",
    "wof:placetype":"venue"
},
  "geometry": {"coordinates":[-79.68573600000001,40.474686],"type":"Point"}
}