{
  "type": "Feature",
  "properties": {
    "iso:country":"US",
    "sg:address":"284 N Hanover St",
    "sg:city":"Pottstown",
    "sg:classifiers":[
        {
            "category":"Manufacturing",
            "subcategory":"Apparel",
            "type":"Manufacturing & Wholesale Goods"
        }
    ],
    "sg:phone":"+1 610 327 2884",
    "sg:postcode":"19464",
    "sg:province":"PA",
    "sg:tags":[
        "sportswear"
    ],
    "wof:name":"Lifewear",
    "wof:placetype":"venue"
},
  "geometry": {"coordinates":[-75.64879500000001,40.250604],"type":"Point"}
}