{
  "type": "Feature",
  "properties": {
    "addr:full":"3801 Nazareth Pike Bethlehem PA 18020",
    "addr:housenumber":"3801",
    "addr:postcode":"18020",
    "addr:street":"Nazareth Pike",
    "iso:country":"US",
    "sg:address":"3801 Nazareth Pike",
    "sg:city":"Bethlehem",
    "sg:classifiers":[
        {
            "category":"Wholesale",
            "subcategory":"Sporting Goods",
            "type":"Manufacturing & Wholesale Goods"
        }
    ],
    "sg:phone":"+1 610 882 5757",
    "sg:postcode":"18020",
    "sg:province":"PA",
    "sg:tags":[
        "equipment",
        "pool",
        "swimming"
    ],
    "wof:name":"Leslie's Swimming Pool Supply",
    "wof:placetype":"venue"
},
  "geometry": {"coordinates":[-75.342738,40.678117],"type":"Point"}
}