{
  "type": "Feature",
  "properties": {
    "iso:country":"US",
    "sg:address":"1476 N Center Ave",
    "sg:city":"Somerset",
    "sg:classifiers":[
        {
            "category":"Organizations",
            "subcategory":"Non-profit Organization",
            "type":"Services"
        }
    ],
    "sg:phone":"+1 814 443 1637",
    "sg:postcode":"15501",
    "sg:province":"PA",
    "wof:name":"Children's Aid Home",
    "wof:placetype":"venue"
},
  "geometry": {"coordinates":[-79.075292,40.03268],"type":"Point"}
}