{
  "type": "Feature",
  "properties": {
    "addr:full":"856 Milmar Rd Newtown Square PA 19073",
    "addr:housenumber":"856",
    "addr:postcode":"19073",
    "addr:street":"Milmar Rd",
    "iso:country":"US",
    "sg:address":"856 Milmar Rd",
    "sg:city":"Newtown Square",
    "sg:classifiers":[
        {
            "category":"Shopping",
            "subcategory":"Used Merchandise",
            "type":"Retail Goods"
        }
    ],
    "sg:phone":"+1   ",
    "sg:postcode":"19073",
    "sg:province":"PA",
    "wof:name":"S Bishop Antiques",
    "wof:placetype":"venue"
},
  "geometry": {"coordinates":[-75.377965,39.996833],"type":"Point"}
}