{
  "type": "Feature",
  "properties": {
    "iso:country":"US",
    "sg:address":"332 Broad St",
    "sg:city":"Nescopeck",
    "sg:classifiers":[
        {
            "category":"Personal",
            "subcategory":"Beauty Salon",
            "type":"Services"
        }
    ],
    "sg:phone":"+1 570 759 2604",
    "sg:postcode":"18635",
    "sg:province":"PA",
    "wof:name":"Carolyn Lamon's Salon & Spa",
    "wof:placetype":"venue"
},
  "geometry": {"coordinates":[-76.220697,41.051737],"type":"Point"}
}