{
  "type": "Feature",
  "properties": {
    "iso:country":"US",
    "sg:address":"4221 Highgrove Rd",
    "sg:city":"Pittsburgh",
    "sg:classifiers":[
        {
            "category":"Shopping",
            "subcategory":"Gifts & Souvenirs",
            "type":"Retail Goods"
        }
    ],
    "sg:phone":"+1   ",
    "sg:postcode":"15236",
    "sg:province":"PA",
    "wof:name":"Laibach Gifts",
    "wof:placetype":"venue"
},
  "geometry": {"coordinates":[-80.01178299999999,40.354045],"type":"Point"}
}