{
  "type": "Feature",
  "properties": {
    "iso:country":"US",
    "sg:address":"3532 W Chester Pike",
    "sg:city":"Newtown Square",
    "sg:classifiers":[
        {
            "category":"Utilities",
            "subcategory":"Mobile Phone",
            "type":"Services"
        }
    ],
    "sg:phone":"+1   ",
    "sg:postcode":"19073",
    "sg:province":"PA",
    "sg:tags":[
        "communication",
        "radiotelephone"
    ],
    "wof:name":"National Communications",
    "wof:placetype":"venue"
},
  "geometry": {"coordinates":[-75.394756,39.985427],"type":"Point"}
}