{
  "type": "Feature",
  "properties": {
    "addr:full":"100 Ben Franklin Rd S Indiana PA 15701",
    "addr:housenumber":"100",
    "addr:postcode":"15701",
    "addr:street":"Ben Franklin Rd",
    "iso:country":"US",
    "sg:address":"100 Ben Franklin Rd S",
    "sg:city":"Indiana",
    "sg:classifiers":[
        {
            "category":"Organizations",
            "subcategory":"Religious Organization",
            "type":"Services"
        }
    ],
    "sg:phone":"+1   ",
    "sg:postcode":"15701",
    "sg:province":"PA",
    "sg:tags":[
        "church"
    ],
    "wof:name":"Calvary Evang Free Church",
    "wof:placetype":"venue"
},
  "geometry": {"coordinates":[-79.193198,40.618209],"type":"Point"}
}