{
  "type": "Feature",
  "properties": {
    "iso:country":"US",
    "sg:address":"1 Park Ave",
    "sg:city":"Coatesville",
    "sg:classifiers":[
        {
            "category":"Recreation",
            "type":"Entertainment"
        }
    ],
    "sg:phone":"+1 610 383 3812",
    "sg:postcode":"19320",
    "sg:province":"PA",
    "sg:tags":[
        "parks"
    ],
    "sg:website":"www.chesco.org",
    "wof:name":"Hibernia County Park",
    "wof:placetype":"venue"
},
  "geometry": {"coordinates":[-75.858952,39.945491],"type":"Point"}
}