{
  "type": "Feature",
  "properties": {
    "iso:country":"US",
    "sg:address":"1 Limekiln Pike",
    "sg:city":"Glenside",
    "sg:classifiers":[
        {
            "category":"Manufacturing",
            "subcategory":"Metals",
            "type":"Manufacturing & Wholesale Goods"
        }
    ],
    "sg:phone":"+1   ",
    "sg:postcode":"19038",
    "sg:province":"PA",
    "sg:tags":[
        "small",
        "sporting",
        "arms",
        "mfg"
    ],
    "wof:name":"Popperts Gunsmithing",
    "wof:placetype":"venue"
},
  "geometry": {"coordinates":[-75.16366499999999,40.107645],"type":"Point"}
}