{
  "type": "Feature",
  "properties": {
    "iso:country":"US",
    "sg:address":"2323 Carlisle Rd",
    "sg:city":"York",
    "sg:classifiers":[
        {
            "category":"Retail",
            "subcategory":"Laundry & Dry Cleaning",
            "type":"Services"
        }
    ],
    "sg:phone":"+1 717 764 2867",
    "sg:postcode":"17408",
    "sg:province":"PA",
    "sg:tags":[
        "cleaners"
    ],
    "wof:name":"Snow White Cleaners",
    "wof:placetype":"venue"
},
  "geometry": {"coordinates":[-76.802131,39.979524],"type":"Point"}
}