{
  "type": "Feature",
  "properties": {
    "iso:country":"US",
    "sg:address":"191 View Ave",
    "sg:city":"Strabane",
    "sg:classifiers":[
        {
            "category":"Organizations",
            "subcategory":"Membership Organization",
            "type":"Services"
        }
    ],
    "sg:phone":"+1 724 745 0561",
    "sg:postcode":"15363",
    "sg:province":"PA",
    "sg:tags":[
        "fraternal"
    ],
    "wof:name":"Strabane Memorial Post 553",
    "wof:placetype":"venue"
},
  "geometry": {"coordinates":[-80.198271,40.249777],"type":"Point"}
}