{
  "type": "Feature",
  "properties": {
    "addr:full":"2000 Campus Ln Norristown PA 19403",
    "addr:housenumber":"2000",
    "addr:postcode":"19403",
    "addr:street":"Campus Ln",
    "iso:country":"US",
    "sg:address":"2000 Campus Ln",
    "sg:city":"Norristown",
    "sg:classifiers":[
        {
            "category":"Autos & Motor Vehicles",
            "subcategory":"Auto Supplies",
            "type":"Retail Goods"
        }
    ],
    "sg:phone":"+1 610 615 8000",
    "sg:postcode":"19403",
    "sg:province":"PA",
    "sg:tags":[
        "tire"
    ],
    "wof:name":"Sumitomo Tire",
    "wof:placetype":"venue"
},
  "geometry": {"coordinates":[-75.363083,40.154369],"type":"Point"}
}