{
  "type": "Feature",
  "properties": {
    "addr:full":"1019 Tanney St Bellefonte PA 16823",
    "addr:housenumber":"1019",
    "addr:postcode":"16823",
    "addr:street":"Tanney St",
    "iso:country":"US",
    "sg:address":"1019 Tanney St",
    "sg:city":"Bellefonte",
    "sg:classifiers":[
        {
            "category":"Banks & Credit Unions",
            "subcategory":"Investment Brokerage",
            "type":"Services"
        }
    ],
    "sg:phone":"+1   ",
    "sg:postcode":"16823",
    "sg:province":"PA",
    "sg:tags":[
        "advisory"
    ],
    "wof:name":"Wdl Financial Co Inc",
    "wof:placetype":"venue"
},
  "geometry": {"coordinates":[-77.75737700000001,40.917105],"type":"Point"}
}