{
  "type": "Feature",
  "properties": {
    "addr:full":"240 Barker Rd Cheltenham PA 19095",
    "addr:housenumber":"240",
    "addr:postcode":"19095",
    "addr:street":"Barker Rd",
    "iso:country":"US",
    "sg:address":"240 Barker Rd",
    "sg:city":"Cheltenham",
    "sg:classifiers":[
        {
            "category":"Social Services",
            "subcategory":"Adult Care",
            "type":"Services"
        }
    ],
    "sg:phone":"+1 215 517 8200",
    "sg:postcode":"19095",
    "sg:province":"PA",
    "sg:tags":[
        "home",
        "residential"
    ],
    "wof:name":"Oak Assisted Living Community",
    "wof:placetype":"venue"
},
  "geometry": {"coordinates":[-75.151568,40.090039],"type":"Point"}
}