{
  "type": "Feature",
  "properties": {
    "iso:country":"US",
    "sg:address":"12270 Frankstown Rd",
    "sg:city":"Penn Hills",
    "sg:classifiers":[
        {
            "category":"Home & Garden",
            "subcategory":"Household Appliances",
            "type":"Retail Goods"
        },
        {
            "category":"Retail",
            "subcategory":"Repair Shop",
            "type":"Services"
        }
    ],
    "sg:phone":"+1 412 793 7799",
    "sg:postcode":"15235",
    "sg:province":"PA",
    "sg:tags":[
        "elect"
    ],
    "wof:name":"Penn Hills Appliance Parts Co",
    "wof:placetype":"venue"
},
  "geometry": {"coordinates":[-79.81952200000001,40.471741],"type":"Point"}
}