{
  "type": "Feature",
  "properties": {
    "addr:full":"162 W Main St Millheim PA 16854",
    "addr:housenumber":"162",
    "addr:postcode":"16854",
    "addr:street":"W Main St",
    "iso:country":"US",
    "sg:address":"162 W Main St",
    "sg:city":"Millheim",
    "sg:classifiers":[
        {
            "category":"Organizations",
            "subcategory":"Community Association",
            "type":"Services"
        }
    ],
    "sg:phone":"+1 814 349 8367",
    "sg:postcode":"16854",
    "sg:province":"PA",
    "sg:tags":[
        "military"
    ],
    "wof:name":"American Legion",
    "wof:placetype":"venue"
},
  "geometry": {"coordinates":[-77.477182,40.890907],"type":"Point"}
}