{
  "type": "Feature",
  "properties": {
    "addr:full":"31 Beverly Dr Kintnersville PA 18930",
    "addr:housenumber":"31",
    "addr:postcode":"18930",
    "addr:street":"Beverly Dr Kintnersville",
    "iso:country":"US",
    "sg:address":"31 Beverly Dr",
    "sg:city":"Kintnersville",
    "sg:classifiers":[
        {
            "category":"Wholesale",
            "subcategory":"Furniture",
            "type":"Manufacturing & Wholesale Goods"
        }
    ],
    "sg:phone":"+1   ",
    "sg:postcode":"18930",
    "sg:province":"PA",
    "sg:tags":[
        "industry",
        "representative",
        "for",
        "mfg"
    ],
    "wof:name":"Str",
    "wof:placetype":"venue"
},
  "geometry": {"coordinates":[-75.188031,40.530867],"type":"Point"}
}