{
  "type": "Feature",
  "properties": {
    "iso:country":"US",
    "sg:address":"2200 Washington Pike",
    "sg:city":"Carnegie",
    "sg:classifiers":[
        {
            "category":"Shopping",
            "subcategory":"Department Store",
            "type":"Retail Goods"
        },
        {
            "category":"Shopping",
            "subcategory":"Mobile Phones",
            "type":"Retail Goods"
        },
        {
            "category":"Food & Beverages",
            "subcategory":"Groceries & Convenience Stores",
            "type":"Retail Goods"
        }
    ],
    "sg:phone":"+1 412 429 1285",
    "sg:postcode":"15106",
    "sg:province":"PA",
    "sg:website":"www.walmart.com/",
    "wof:name":"Walmart",
    "wof:placetype":"venue"
},
  "geometry": {"coordinates":[-80.089234,40.385884],"type":"Point"}
}