{
  "type": "Feature",
  "properties": {
    "iso:country":"US",
    "sg:address":"7919 Jenkintown Rd",
    "sg:city":"Cheltenham",
    "sg:classifiers":[
        {
            "category":"Communications",
            "subcategory":"Film & Video Production",
            "type":"Services"
        }
    ],
    "sg:phone":"+1 215 379 3800",
    "sg:postcode":"19012",
    "sg:province":"PA",
    "sg:tags":[
        "taping"
    ],
    "wof:name":"Images In Motion",
    "wof:placetype":"venue"
},
  "geometry": {"coordinates":[-75.10499900000001,40.063567],"type":"Point"}
}