{
  "type": "Feature",
  "properties": {
    "iso:country":"US",
    "sg:address":"809 Society Pl",
    "sg:city":"Newtown",
    "sg:classifiers":[
        {
            "category":"Real Estate",
            "subcategory":"Real Estate Services",
            "type":"Services"
        },
        {
            "category":"Building & Trades",
            "subcategory":"Cleaning & Sanitation",
            "type":"Services"
        }
    ],
    "sg:phone":"+1 215 579 8241",
    "sg:postcode":"18940",
    "sg:province":"PA",
    "sg:tags":[
        "maintenance",
        "cleaners-interior"
    ],
    "wof:name":"Checchia, Thomast/A Excel Asphalt Maintenance",
    "wof:placetype":"venue"
},
  "geometry": {"coordinates":[-74.96274099999999,40.259548],"type":"Point"}
}