{
  "type": "Feature",
  "properties": {
    "addr:full":"933 Ave of the States Chester PA 19013",
    "addr:housenumber":"933",
    "addr:postcode":"19013",
    "addr:street":"Ave Of The",
    "iso:country":"US",
    "sg:address":"933 Ave of the States",
    "sg:city":"Chester",
    "sg:classifiers":[
        {
            "category":"Real Estate",
            "subcategory":"Real Estate Agent",
            "type":"Services"
        }
    ],
    "sg:phone":"+1 610 874 8484",
    "sg:postcode":"19013",
    "sg:province":"PA",
    "wof:name":"Alfred V Stiscia Real Estate",
    "wof:placetype":"venue"
},
  "geometry": {"coordinates":[-75.360631,39.853572],"type":"Point"}
}