{
  "type": "Feature",
  "properties": {
    "iso:country":"US",
    "sg:address":"1539 Carlene Ct",
    "sg:city":"Langhorne",
    "sg:classifiers":[
        {
            "category":"Professional",
            "subcategory":"Computer Services",
            "type":"Services"
        }
    ],
    "sg:phone":"+1 215 860 5283",
    "sg:postcode":"19047",
    "sg:province":"PA",
    "sg:tags":[
        "consultant",
        "designer"
    ],
    "wof:name":"Digital Data Systems Inc",
    "wof:placetype":"venue"
},
  "geometry": {"coordinates":[-74.917005,40.216807],"type":"Point"}
}