{
  "type": "Feature",
  "properties": {
    "addr:full":"1720 Brittany Dr Ambler PA 19002",
    "addr:housenumber":"1720",
    "addr:postcode":"19002",
    "addr:street":"Brittany Dr",
    "iso:country":"US",
    "sg:address":"1720 Brittany Dr",
    "sg:city":"Ambler",
    "sg:classifiers":[
        {
            "category":"Building & Trades",
            "subcategory":"Construction",
            "type":"Services"
        }
    ],
    "sg:phone":"+1   ",
    "sg:postcode":"19002",
    "sg:province":"PA",
    "sg:tags":[
        "hanging",
        "contractor"
    ],
    "wof:name":"Aacorn Painting Inc",
    "wof:placetype":"venue"
},
  "geometry": {"coordinates":[-75.16077900000001,40.164256],"type":"Point"}
}