{
  "type": "Feature",
  "properties": {
    "iso:country":"US",
    "sg:address":"247 S Oakland Ave",
    "sg:city":"Sharon",
    "sg:classifiers":[
        {
            "category":"Social Services",
            "type":"Services"
        }
    ],
    "sg:phone":"+1 724 981 3205",
    "sg:postcode":"16146",
    "sg:province":"PA",
    "sg:tags":[
        "organization",
        "welfare"
    ],
    "wof:name":"American Red Cross",
    "wof:placetype":"venue"
},
  "geometry": {"coordinates":[-80.49944499999999,41.228267],"type":"Point"}
}