{
  "type": "Feature",
  "properties": {
    "addr:full":"1520 Locust Street 2nd Floor 2nd Floor Philadelphia PA 19102",
    "addr:housenumber":"1520;2nd floor",
    "addr:postcode":"19102",
    "addr:street":"Locust Street 2Nd Floor",
    "iso:country":"US",
    "sg:address":"1520 Locust Street 2nd Floor 2nd Floor",
    "sg:city":"Philadelphia",
    "sg:classifiers":[
        {
            "category":"Organizations",
            "subcategory":"Non-profit Organization",
            "type":"Services"
        }
    ],
    "sg:phone":"+1 800 533 7806",
    "sg:postcode":"19102",
    "sg:province":"PA",
    "sg:tags":[
        "service/non-profit",
        "community"
    ],
    "sg:website":"www.varietyphila.org",
    "wof:name":"Variety, The Children's Charity - Tent 13",
    "wof:placetype":"venue"
},
  "geometry": {"coordinates":[-75.167112,39.948516],"type":"Point"}
}