{
  "type": "Feature",
  "properties": {
    "addr:full":"3330 W 26th St Erie PA 16506",
    "addr:housenumber":"3330",
    "addr:postcode":"16506",
    "addr:street":"W 26Th St",
    "iso:country":"US",
    "sg:address":"3330 W 26th St",
    "sg:city":"Erie",
    "sg:classifiers":[
        {
            "category":"Shopping",
            "subcategory":"Department Store",
            "type":"Retail Goods"
        },
        {
            "category":"Shopping",
            "subcategory":"Clothing, Apparel, & Fashions",
            "type":"Retail Goods"
        }
    ],
    "sg:phone":"+1 814 833 1800",
    "sg:postcode":"16506",
    "sg:province":"PA",
    "sg:website":"www.talbots.com",
    "wof:name":"Talbots",
    "wof:placetype":"venue"
},
  "geometry": {"coordinates":[-80.148107,42.08428],"type":"Point"}
}