{
  "type": "Feature",
  "properties": {
    "iso:country":"US",
    "sg:address":"2524 State Rd",
    "sg:city":"Bensalem",
    "sg:classifiers":[
        {
            "category":"Building & Trades",
            "subcategory":"Construction",
            "type":"Services"
        }
    ],
    "sg:phone":"+1   ",
    "sg:postcode":"19020",
    "sg:province":"PA",
    "sg:tags":[
        "hanging",
        "contractor"
    ],
    "wof:name":"R J B Painting",
    "wof:placetype":"venue"
},
  "geometry": {"coordinates":[-74.934557,40.073468],"type":"Point"}
}