{
  "type": "Feature",
  "properties": {
    "addr:full":"1121 Bridgeton Hill Rd Upper Black Eddy PA 18972",
    "addr:housenumber":"1121",
    "addr:postcode":"18972",
    "addr:street":"Bridgeton Hill Rd",
    "iso:country":"US",
    "sg:address":"1121 Bridgeton Hill Rd",
    "sg:city":"Upper Black Eddy",
    "sg:classifiers":[
        {
            "category":"Home & Garden",
            "subcategory":"Garden Supply",
            "type":"Retail Goods"
        }
    ],
    "sg:phone":"+1 610 982 9634",
    "sg:postcode":"18972",
    "sg:province":"PA",
    "sg:tags":[
        "center"
    ],
    "wof:name":"Bridgeton Craft & Garden Ctr",
    "wof:placetype":"venue"
},
  "geometry": {"coordinates":[-75.133438,40.548993],"type":"Point"}
}