{
  "type": "Feature",
  "properties": {
    "iso:country":"US",
    "sg:address":"100 Tarentum Bridge Rd",
    "sg:city":"New Kensington",
    "sg:classifiers":[
        {
            "category":"Restaurant",
            "type":"Food & Drink"
        }
    ],
    "sg:phone":"+1 724 335 5383",
    "sg:postcode":"15068",
    "sg:province":"PA",
    "wof:name":"East Lake",
    "wof:placetype":"venue"
},
  "geometry": {"coordinates":[-79.74939999999999,40.58689],"type":"Point"}
}