{
  "type": "Feature",
  "properties": {
    "iso:country":"US",
    "sg:address":"2080 Snyder Rd",
    "sg:city":"Indiana",
    "sg:classifiers":[
        {
            "category":"Health Services",
            "subcategory":"Nursing And Care Facility",
            "type":"Services"
        }
    ],
    "sg:phone":"+1 724 479 2485",
    "sg:postcode":"15701",
    "sg:province":"PA",
    "sg:tags":[
        "home",
        "retirement",
        "community"
    ],
    "wof:name":"Zele's Boarding Home",
    "wof:placetype":"venue"
},
  "geometry": {"coordinates":[-79.074625,40.550158],"type":"Point"}
}