{
  "type": "Feature",
  "properties": {
    "iso:country":"US",
    "sg:address":"101 Bellevue Rd",
    "sg:city":"Pittsburgh",
    "sg:classifiers":[
        {
            "category":"Insurance",
            "subcategory":"Insurance Agent",
            "type":"Services"
        }
    ],
    "sg:phone":"+1 412 931 6070",
    "sg:postcode":"15229",
    "sg:province":"PA",
    "wof:name":"J S Smith Insurance Agency",
    "wof:placetype":"venue"
},
  "geometry": {"coordinates":[-80.03124699999999,40.513829],"type":"Point"}
}