{
  "type": "Feature",
  "properties": {
    "addr:full":"2577 Interplex Dr Feasterville Trevose PA 19053",
    "addr:housenumber":"2577",
    "addr:postcode":"19053",
    "addr:street":"Interplex Dr",
    "iso:country":"US",
    "sg:address":"2577 Interplex Dr",
    "sg:city":"Feasterville Trevose",
    "sg:classifiers":[
        {
            "category":"Wholesale",
            "subcategory":"Computers",
            "type":"Manufacturing & Wholesale Goods"
        }
    ],
    "sg:phone":"+1   ",
    "sg:postcode":"19053",
    "sg:province":"PA",
    "sg:tags":[
        "end",
        "system",
        "to",
        "s",
        "user",
        "provides",
        "software"
    ],
    "wof:name":"The Software Company",
    "wof:placetype":"venue"
},
  "geometry": {"coordinates":[-74.979828,40.125088],"type":"Point"}
}