{
  "type": "Feature",
  "properties": {
    "addr:full":"82 N Penn St Windsor PA 17366",
    "addr:housenumber":"82",
    "addr:postcode":"17366",
    "addr:street":"N Penn St",
    "iso:country":"US",
    "sg:address":"82 N Penn St",
    "sg:city":"Windsor",
    "sg:classifiers":[
        {
            "category":"Building & Trades",
            "subcategory":"Electrical",
            "type":"Services"
        }
    ],
    "sg:phone":"+1 717 246 0682",
    "sg:postcode":"17366",
    "sg:province":"PA",
    "sg:tags":[
        "electric",
        "industrial",
        "contractors-commercial",
        "contractor"
    ],
    "wof:name":"Milts Repair Service",
    "wof:placetype":"venue"
},
  "geometry": {"coordinates":[-76.580788,39.91885],"type":"Point"}
}