{
  "type": "Feature",
  "properties": {
    "addr:full":"203 Karch Rd Burgettstown PA 15021",
    "addr:housenumber":"203",
    "addr:postcode":"15021",
    "addr:street":"Karch Rd",
    "iso:country":"US",
    "sg:address":"203 Karch Rd",
    "sg:city":"Burgettstown",
    "sg:classifiers":[
        {
            "category":"Insurance",
            "subcategory":"Hazard Insurance",
            "type":"Services"
        }
    ],
    "sg:phone":"+1 724 947 3515",
    "sg:postcode":"15021",
    "sg:province":"PA",
    "wof:name":"James Thompson Sr",
    "wof:placetype":"venue"
},
  "geometry": {"coordinates":[-80.46221300000001,40.347523],"type":"Point"}
}