{
  "type": "Feature",
  "properties": {
    "iso:country":"US",
    "sg:address":"240 W Bridge St",
    "sg:city":"Morrisville",
    "sg:classifiers":[
        {
            "category":"Personal",
            "subcategory":"Beauty Salon",
            "type":"Services"
        }
    ],
    "sg:phone":"+1 215 428 1331",
    "sg:postcode":"19067",
    "sg:province":"PA",
    "sg:tags":[
        "shop",
        "barber"
    ],
    "wof:name":"Colonial Haircutting",
    "wof:placetype":"venue"
},
  "geometry": {"coordinates":[-74.77916399999999,40.206322],"type":"Point"}
}