{
  "type": "Feature",
  "properties": {
    "iso:country":"US",
    "sg:address":"1828 Roosevelt Rd",
    "sg:city":"Sewickley",
    "sg:classifiers":[
        {
            "category":"Place Of Worship",
            "subcategory":"Church",
            "type":"Public Place"
        },
        {
            "category":"Place Of Worship",
            "type":"Public Place"
        }
    ],
    "sg:phone":"+1 412 741 6880",
    "sg:postcode":"15143",
    "sg:province":"PA",
    "sg:tags":[
        "churches-presbyterian-arp",
        "churches-presbyterian"
    ],
    "wof:name":"Mount Nebo United Presbyterian Church",
    "wof:placetype":"venue"
},
  "geometry": {"coordinates":[-80.102525,40.55274],"type":"Point"}
}