{
  "type": "Feature",
  "properties": {
    "iso:country":"US",
    "sg:address":"111 W Drinker St",
    "sg:city":"Dunmore",
    "sg:classifiers":[
        {
            "category":"Real Estate",
            "subcategory":"Real Estate Agent",
            "type":"Services"
        }
    ],
    "sg:phone":"+1 570 344 6724",
    "sg:postcode":"18512",
    "sg:province":"PA",
    "sg:website":"www.jruddy.com",
    "wof:name":"John A Ruddy Appraisal Svc",
    "wof:placetype":"venue"
},
  "geometry": {"coordinates":[-75.631184,41.422325],"type":"Point"}
}