{
  "type": "Feature",
  "properties": {
    "iso:country":"US",
    "sg:address":"156 Prospect Ave",
    "sg:city":"Lansdale",
    "sg:classifiers":[
        {
            "category":"Wholesale",
            "subcategory":"Machinery & Supplies",
            "type":"Manufacturing & Wholesale Goods"
        }
    ],
    "sg:phone":"+1 215 393 7290",
    "sg:postcode":"19446",
    "sg:province":"PA",
    "sg:tags":[
        "control",
        "equipment",
        "rep",
        "static",
        "mfg"
    ],
    "wof:name":"Kerstat Inc",
    "wof:placetype":"venue"
},
  "geometry": {"coordinates":[-75.28238,40.236965],"type":"Point"}
}