{
  "type": "Feature",
  "properties": {
    "iso:country":"US",
    "sg:address":"192 Glenview Dr",
    "sg:city":"New Kensington",
    "sg:classifiers":[
        {
            "category":"Shopping",
            "subcategory":"Gifts & Souvenirs",
            "type":"Retail Goods"
        }
    ],
    "sg:phone":"+1   ",
    "sg:postcode":"15068",
    "sg:province":"PA",
    "wof:name":"Amanda Lynn Gifts",
    "wof:placetype":"venue"
},
  "geometry": {"coordinates":[-79.745121,40.582166],"type":"Point"}
}