{
  "type": "Feature",
  "properties": {
    "addr:full":"107 W Euclid Ave New Castle PA 16105",
    "addr:housenumber":"107",
    "addr:postcode":"16105",
    "addr:street":"W Euclid Ave",
    "iso:country":"US",
    "sg:address":"107 W Euclid Ave",
    "sg:city":"New Castle",
    "sg:classifiers":[
        {
            "category":"Building & Trades",
            "subcategory":"Landscaping Services",
            "type":"Services"
        }
    ],
    "sg:phone":"+1   ",
    "sg:postcode":"16105",
    "sg:province":"PA",
    "wof:name":"Finley Tom Tree Service",
    "wof:placetype":"venue"
},
  "geometry": {"coordinates":[-80.348401,41.01607],"type":"Point"}
}