{
  "type": "Feature",
  "properties": {
    "iso:country":"US",
    "sg:address":"195 Green Ln",
    "sg:city":"Philadelphia",
    "sg:classifiers":[
        {
            "category":"Organizations",
            "subcategory":"Religious Organization",
            "type":"Services"
        }
    ],
    "sg:phone":"+1 215 483 3920",
    "sg:postcode":"19127",
    "sg:province":"PA",
    "sg:tags":[
        "church"
    ],
    "wof:name":"First Baptist Church-Manayunk",
    "wof:placetype":"venue"
},
  "geometry": {"coordinates":[-75.223692,40.029156],"type":"Point"}
}