{
  "type": "Feature",
  "properties": {
    "iso:country":"US",
    "sg:address":"2030 W Tilghman St",
    "sg:city":"Allentown",
    "sg:classifiers":[
        {
            "category":"Professional",
            "subcategory":"Lawyer & Legal Services",
            "type":"Services"
        }
    ],
    "sg:phone":"+1 610 432 1590",
    "sg:postcode":"18104",
    "sg:province":"PA",
    "sg:tags":[
        "attorney"
    ],
    "wof:name":"Joseph J Plunkett PC",
    "wof:placetype":"venue"
},
  "geometry": {"coordinates":[-75.503086,40.604464],"type":"Point"}
}