{
  "type": "Feature",
  "properties": {
    "addr:full":"1381 Columbia Blvd Bloomsburg PA 17815",
    "addr:housenumber":"1381",
    "addr:postcode":"17815",
    "addr:street":"Columbia Blvd",
    "iso:country":"US",
    "sg:address":"1381 Columbia Blvd",
    "sg:city":"Bloomsburg",
    "sg:classifiers":[
        {
            "category":"Shopping",
            "subcategory":"Discount & Variety Stores",
            "type":"Retail Goods"
        }
    ],
    "sg:phone":"+1 570 387 9616",
    "sg:postcode":"17815",
    "sg:province":"PA",
    "wof:name":"Dollar Tree",
    "wof:placetype":"venue"
},
  "geometry": {"coordinates":[-76.434663,41.005287],"type":"Point"}
}