{
  "type": "Feature",
  "properties": {
    "iso:country":"US",
    "sg:address":"660 Fisher Hill St",
    "sg:city":"Sharon",
    "sg:classifiers":[
        {
            "category":"Organizations",
            "subcategory":"Non-profit Organization",
            "type":"Services"
        }
    ],
    "sg:phone":"+1 724 983 8737",
    "sg:postcode":"16146",
    "sg:province":"PA",
    "sg:tags":[
        "human"
    ],
    "wof:name":"UPMC Horizon Medical Equipment",
    "wof:placetype":"venue"
},
  "geometry": {"coordinates":[-80.495873,41.245896],"type":"Point"}
}