{
  "type": "Feature",
  "properties": {
    "iso:country":"US",
    "sg:address":"711 Saginaw Rd",
    "sg:city":"Oxford",
    "sg:classifiers":[
        {
            "category":"Health Services",
            "subcategory":"Health Practitioner",
            "type":"Services"
        }
    ],
    "sg:phone":"+1 610 998 0267",
    "sg:postcode":"19363",
    "sg:province":"PA",
    "sg:tags":[
        "nurse",
        "registry"
    ],
    "wof:name":"M P Mc Garvey",
    "wof:placetype":"venue"
},
  "geometry": {"coordinates":[-75.910691,39.767301],"type":"Point"}
}