{
  "type": "Feature",
  "properties": {
    "addr:full":"123 S Broad St Philadelphia PA 19109",
    "addr:housenumber":"123",
    "addr:postcode":"19109",
    "addr:street":"S Broad St",
    "iso:country":"US",
    "sg:address":"123 S Broad St",
    "sg:city":"Philadelphia",
    "sg:classifiers":[
        {
            "category":"Professional",
            "subcategory":"Lawyer & Legal Services",
            "type":"Services"
        }
    ],
    "sg:phone":"+1 215 772 7539",
    "sg:postcode":"19109",
    "sg:province":"PA",
    "wof:name":"Caruso John E Attorney",
    "wof:placetype":"venue"
},
  "geometry": {"coordinates":[-75.164101,39.950001],"type":"Point"}
}