{
  "type": "Feature",
  "properties": {
    "addr:full":"10 Smithfield St Pittsburgh PA 15222",
    "addr:housenumber":"10",
    "addr:postcode":"15222",
    "addr:street":"Smithfield St",
    "iso:country":"US",
    "sg:address":"10 Smithfield St",
    "sg:city":"Pittsburgh",
    "sg:classifiers":[
        {
            "category":"Building & Trades",
            "subcategory":"Locksmith",
            "type":"Services"
        }
    ],
    "sg:phone":"+1 412 323 8164",
    "sg:postcode":"15222",
    "sg:province":"PA",
    "sg:tags":[
        "key"
    ],
    "wof:name":"3-Rivers Locksmith & Supply",
    "wof:placetype":"venue"
},
  "geometry": {"coordinates":[-80.000603,40.436901],"type":"Point"}
}