{
  "type": "Feature",
  "properties": {
    "addr:full":"959 E Main St Birdsboro PA 19508",
    "addr:housenumber":"959",
    "addr:postcode":"19508",
    "addr:street":"E Main St",
    "iso:country":"US",
    "sg:address":"959 E Main St",
    "sg:city":"Birdsboro",
    "sg:classifiers":[
        {
            "category":"Recreation",
            "type":"Entertainment"
        }
    ],
    "sg:phone":"+1   ",
    "sg:postcode":"19508",
    "sg:province":"PA",
    "wof:name":"Shady Hollow Assisted Riding",
    "wof:placetype":"venue"
},
  "geometry": {"coordinates":[-75.793154,40.262882],"type":"Point"}
}