{
  "type": "Feature",
  "properties": {
    "iso:country":"US",
    "sg:address":"2104 Murray Ave",
    "sg:city":"Pittsburgh",
    "sg:classifiers":[
        {
            "category":"Restaurant",
            "type":"Food & Drink"
        }
    ],
    "sg:menulink":"http://www.allmenus.com/pa/pittsburgh/275132-chaya-japanese-cuisine/menu/",
    "sg:phone":"+1 412 422 2082",
    "sg:postcode":"15217",
    "sg:province":"PA",
    "sg:tags":[
        "japanese",
        "asian"
    ],
    "wof:name":"Chaya Japanese Cuisine",
    "wof:placetype":"venue"
},
  "geometry": {"coordinates":[-79.92301,40.433469],"type":"Point"}
}