{
  "type": "Feature",
  "properties": {
    "iso:country":"US",
    "sg:address":"44 W Highland Ave",
    "sg:city":"Philadelphia",
    "sg:classifiers":[
        {
            "category":"Health Services",
            "subcategory":"Doctor",
            "type":"Services"
        }
    ],
    "sg:phone":"+1 215 247 3272",
    "sg:postcode":"19118",
    "sg:province":"PA",
    "sg:tags":[
        "physician",
        "surgeon"
    ],
    "wof:name":"Thomas W Clark MD",
    "wof:placetype":"venue"
},
  "geometry": {"coordinates":[-75.207246,40.075206],"type":"Point"}
}