{
  "type": "Feature",
  "properties": {
    "addr:full":"264 Susquehanna Trl Allentown PA 18104",
    "addr:housenumber":"264",
    "addr:postcode":"18104",
    "addr:street":"Susquehanna Trl",
    "iso:country":"US",
    "sg:address":"264 Susquehanna Trl",
    "sg:city":"Allentown",
    "sg:classifiers":[
        {
            "category":"Professional",
            "type":"Services"
        }
    ],
    "sg:phone":"+1   ",
    "sg:postcode":"18104",
    "sg:province":"PA",
    "wof:name":"Robert J Gowell",
    "wof:placetype":"venue"
},
  "geometry": {"coordinates":[-75.596014,40.573908],"type":"Point"}
}