{
  "type": "Feature",
  "properties": {
    "iso:country":"US",
    "sg:address":"560 Willow Rd",
    "sg:city":"Lancaster",
    "sg:classifiers":[
        {
            "category":"Shopping",
            "type":"Retail Goods"
        }
    ],
    "sg:phone":"+1 717 391 7808",
    "sg:postcode":"17601",
    "sg:province":"PA",
    "sg:tags":[
        "baling",
        "supply",
        "merchandise",
        "equipment"
    ],
    "sg:website":"http://www.eberlybarns.net",
    "wof:name":"Eberly Barns Inc",
    "wof:placetype":"venue"
},
  "geometry": {"coordinates":[-76.24340599999999,40.062203],"type":"Point"}
}