{
  "type": "Feature",
  "properties": {
    "iso:country":"US",
    "sg:address":"219 Bullens Ln",
    "sg:city":"Woodlyn",
    "sg:classifiers":[
        {
            "category":"Professional",
            "subcategory":"Detective & Security Services",
            "type":"Services"
        }
    ],
    "sg:phone":"+1   ",
    "sg:postcode":"19094",
    "sg:province":"PA",
    "sg:tags":[
        "installs",
        "system"
    ],
    "wof:name":"ADT Security Services Inc",
    "wof:placetype":"venue"
},
  "geometry": {"coordinates":[-75.353657,39.870916],"type":"Point"}
}