{
  "type": "Feature",
  "properties": {
    "iso:country":"US",
    "sg:address":"2100 S 61st St",
    "sg:city":"Philadelphia",
    "sg:classifiers":[
        {
            "category":"Retail",
            "subcategory":"Auto Repair",
            "type":"Services"
        }
    ],
    "sg:phone":"+1 215 727 9998",
    "sg:postcode":"19142",
    "sg:province":"PA",
    "sg:tags":[
        "automobile",
        "inspection"
    ],
    "wof:name":"Freddies Auto Parts",
    "wof:placetype":"venue"
},
  "geometry": {"coordinates":[-75.230484,39.929915],"type":"Point"}
}