{
  "type": "Feature",
  "properties": {
    "addr:full":"1441 Pittsburgh Rd Valencia PA 16059",
    "addr:housenumber":"1441",
    "addr:postcode":"16059",
    "addr:street":"Pittsburgh Rd",
    "iso:country":"US",
    "sg:address":"1441 Pittsburgh Rd",
    "sg:city":"Valencia",
    "sg:classifiers":[
        {
            "category":"Restaurant",
            "type":"Food & Drink"
        }
    ],
    "sg:phone":"+1 724 443 2010",
    "sg:postcode":"16059",
    "sg:province":"PA",
    "sg:tags":[
        "eating"
    ],
    "wof:name":"Hoover's Restaurant",
    "wof:placetype":"venue"
},
  "geometry": {"coordinates":[-79.93262900000001,40.673459],"type":"Point"}
}