{
  "type": "Feature",
  "properties": {
    "addr:full":"121 Witmer Rd Horsham PA 19044",
    "addr:housenumber":"121",
    "addr:postcode":"19044",
    "addr:street":"Witmer Rd",
    "iso:country":"US",
    "sg:address":"121 Witmer Rd",
    "sg:city":"Horsham",
    "sg:classifiers":[
        {
            "category":"Professional",
            "subcategory":"Engineering",
            "type":"Services"
        },
        {
            "category":"Professional",
            "subcategory":"Management & Consulting",
            "type":"Services"
        }
    ],
    "sg:phone":"+1 215 675 1700",
    "sg:postcode":"19044",
    "sg:province":"PA",
    "sg:tags":[
        "business",
        "engineer"
    ],
    "sg:website":"www.edaonline.com",
    "wof:name":"Electronic Display Application",
    "wof:placetype":"venue"
},
  "geometry": {"coordinates":[-75.137989,40.167572],"type":"Point"}
}