{
  "type": "Feature",
  "properties": {
    "addr:full":"3503 Peach St Erie PA 16508",
    "addr:housenumber":"3503",
    "addr:postcode":"16508",
    "addr:street":"Peach St",
    "iso:country":"US",
    "sg:address":"3503 Peach St",
    "sg:city":"Erie",
    "sg:classifiers":[
        {
            "category":"Education",
            "subcategory":"School",
            "type":"Public Place"
        }
    ],
    "sg:phone":"+1 814 874 6570",
    "sg:postcode":"16508",
    "sg:province":"PA",
    "sg:tags":[
        "elementary"
    ],
    "wof:name":"Glenwood Elementary School",
    "wof:placetype":"venue"
},
  "geometry": {"coordinates":[-80.07991800000001,42.10024],"type":"Point"}
}