{
  "type": "Feature",
  "properties": {
    "iso:country":"US",
    "sg:address":"3520 Plow Rd",
    "sg:city":"Mohnton",
    "sg:classifiers":[
        {
            "category":"Organizations",
            "subcategory":"Religious Organization",
            "type":"Services"
        }
    ],
    "sg:phone":"+1 610 856 7242",
    "sg:postcode":"19540",
    "sg:province":"PA",
    "sg:tags":[
        "church"
    ],
    "sg:website":"www.robesonlutheranchurch.org",
    "wof:name":"Robeson Evangelical Lutheran",
    "wof:placetype":"venue"
},
  "geometry": {"coordinates":[-75.896018,40.223598],"type":"Point"}
}