{
  "type": "Feature",
  "properties": {
    "addr:full":"2435 Aramingo Ave Philadelphia PA 19125",
    "addr:housenumber":"2435",
    "addr:postcode":"19125",
    "addr:street":"Aramingo Ave",
    "iso:country":"US",
    "sg:address":"2435 Aramingo Ave",
    "sg:city":"Philadelphia",
    "sg:classifiers":[
        {
            "category":"Retail",
            "subcategory":"Laundry & Dry Cleaning",
            "type":"Services"
        }
    ],
    "sg:phone":"+1 215 739 8432",
    "sg:postcode":"19125",
    "sg:province":"PA",
    "sg:tags":[
        "cleaner"
    ],
    "wof:name":"Save Cleaners",
    "wof:placetype":"venue"
},
  "geometry": {"coordinates":[-75.12069700000001,39.9757],"type":"Point"}
}