{
  "type": "Feature",
  "properties": {
    "iso:country":"US",
    "sg:address":"118 N Main St",
    "sg:city":"Davidsville",
    "sg:classifiers":[
        {
            "category":"Shopping",
            "subcategory":"Pharmacy",
            "type":"Retail Goods"
        }
    ],
    "sg:phone":"+1 814 479 2588",
    "sg:postcode":"15928",
    "sg:province":"PA",
    "wof:name":"Township Pharmacy Davidsville",
    "wof:placetype":"venue"
},
  "geometry": {"coordinates":[-78.935018,40.229179],"type":"Point"}
}