{
  "type": "Feature",
  "properties": {
    "addr:full":"1610 Bedford St Johnstown PA 15902",
    "addr:housenumber":"1610",
    "addr:postcode":"15902",
    "addr:street":"Bedford St",
    "iso:country":"US",
    "sg:address":"1610 Bedford St",
    "sg:city":"Johnstown",
    "sg:classifiers":[
        {
            "category":"Government",
            "subcategory":"Office",
            "type":"Public Place"
        }
    ],
    "sg:phone":"+1 814 266 3111",
    "sg:postcode":"15902",
    "sg:province":"PA",
    "sg:tags":[
        "village"
    ],
    "wof:name":"Stoneycreek Twp Municipal Bldg",
    "wof:placetype":"venue"
},
  "geometry": {"coordinates":[-78.89049,40.303545],"type":"Point"}
}