{
  "type": "Feature",
  "properties": {
    "addr:full":"555 Walnut St Harrisburg PA 17101",
    "addr:housenumber":"555",
    "addr:postcode":"17101",
    "addr:street":"Walnut St",
    "iso:country":"US",
    "sg:address":"555 Walnut St",
    "sg:city":"Harrisburg",
    "sg:classifiers":[
        {
            "category":"Social Services",
            "type":"Services"
        }
    ],
    "sg:phone":"+1 717 783 7247",
    "sg:postcode":"17101",
    "sg:province":"PA",
    "sg:tags":[
        "organization",
        "welfare"
    ],
    "wof:name":"Regional Ombudsman Volunteer",
    "wof:placetype":"venue"
},
  "geometry": {"coordinates":[-76.88005800000001,40.263922],"type":"Point"}
}