{
  "type": "Feature",
  "properties": {
    "addr:full":"39 N 9th St Rear Akron PA 17501",
    "addr:housenumber":"39",
    "addr:postcode":"17501",
    "addr:street":"N 9Th St",
    "iso:country":"US",
    "sg:address":"39 N 9th St Rear",
    "sg:city":"Akron",
    "sg:classifiers":[
        {
            "category":"Building & Trades",
            "subcategory":"Plumbing",
            "type":"Services"
        }
    ],
    "sg:phone":"+1 717 859 1816",
    "sg:postcode":"17501",
    "sg:province":"PA",
    "sg:tags":[
        "plumber",
        "industrial",
        "contractors-commercial"
    ],
    "wof:name":"Cammauf Carl C Plumbing & Htg",
    "wof:placetype":"venue"
},
  "geometry": {"coordinates":[-76.202308,40.157573],"type":"Point"}
}