{
  "type": "Feature",
  "properties": {
    "addr:full":"1022 S Main Ave Scranton PA 18504",
    "addr:housenumber":"1022",
    "addr:postcode":"18504",
    "addr:street":"S Main Ave",
    "iso:country":"US",
    "sg:address":"1022 S Main Ave",
    "sg:city":"Scranton",
    "sg:classifiers":[
        {
            "category":"Shopping",
            "subcategory":"Clothing, Apparel, & Fashions",
            "type":"Retail Goods"
        }
    ],
    "sg:phone":"+1   ",
    "sg:postcode":"18504",
    "sg:province":"PA",
    "sg:tags":[
        "wear",
        "formal"
    ],
    "wof:name":"Weddings By Denise",
    "wof:placetype":"venue"
},
  "geometry": {"coordinates":[-75.686975,41.401998],"type":"Point"}
}