{
  "type": "Feature",
  "properties": {
    "addr:full":"1719 South St Philadelphia PA 19146",
    "addr:housenumber":"1719",
    "addr:postcode":"19146",
    "addr:street":"South St",
    "iso:country":"US",
    "sg:address":"1719 South St",
    "sg:city":"Philadelphia",
    "sg:classifiers":[
        {
            "category":"Home & Garden",
            "subcategory":"Household Appliances",
            "type":"Retail Goods"
        },
        {
            "category":"Personal",
            "type":"Services"
        }
    ],
    "sg:phone":"+1 215 545 2505",
    "sg:postcode":"19146",
    "sg:province":"PA",
    "sg:website":"www.hearthandstove.com",
    "wof:name":"Hearth and Stove",
    "wof:placetype":"venue"
},
  "geometry": {"coordinates":[-75.170981,39.944449],"type":"Point"}
}