{
  "type": "Feature",
  "properties": {
    "iso:country":"US",
    "sg:address":"115 N Monroe St",
    "sg:city":"Media",
    "sg:classifiers":[
        {
            "category":"Professional",
            "subcategory":"Lawyer & Legal Services",
            "type":"Services"
        }
    ],
    "sg:phone":"+1 610 565 6700",
    "sg:postcode":"19063",
    "sg:province":"PA",
    "sg:tags":[
        "attorney"
    ],
    "wof:name":"Andrew J D'Amico Law Offices",
    "wof:placetype":"venue"
},
  "geometry": {"coordinates":[-75.387162,39.919343],"type":"Point"}
}