{
  "type": "Feature",
  "properties": {
    "iso:country":"US",
    "sg:address":"3660 S Lawrence St",
    "sg:city":"Philadelphia",
    "sg:classifiers":[
        {
            "category":"Wholesale",
            "subcategory":"Fruits & Vegetables",
            "type":"Manufacturing & Wholesale Goods"
        }
    ],
    "sg:phone":"+1 215 467 1400",
    "sg:postcode":"19148",
    "sg:province":"PA",
    "sg:tags":[
        "veggie"
    ],
    "wof:name":"Novick Brothers Corp",
    "wof:placetype":"venue"
},
  "geometry": {"coordinates":[-75.158997,39.901699],"type":"Point"}
}