{
  "type": "Feature",
  "properties": {
    "iso:country":"US",
    "sg:address":"1350 Sportsman Rd",
    "sg:city":"Leechburg",
    "sg:classifiers":[
        {
            "category":"Professional",
            "subcategory":"Business Services",
            "type":"Services"
        }
    ],
    "sg:phone":"+1 724 295 4281",
    "sg:postcode":"15656",
    "sg:province":"PA",
    "sg:tags":[
        "appraiser"
    ],
    "wof:name":"Fred J Brient & Assoc",
    "wof:placetype":"venue"
},
  "geometry": {"coordinates":[-79.65692300000001,40.685318],"type":"Point"}
}