{
  "type": "Feature",
  "properties": {
    "addr:full":"2017 Raleigh Rd Hummelstown PA 17036",
    "addr:housenumber":"2017",
    "addr:postcode":"17036",
    "addr:street":"Raleigh Rd",
    "iso:country":"US",
    "sg:address":"2017 Raleigh Rd",
    "sg:city":"Hummelstown",
    "sg:classifiers":[
        {
            "category":"Wholesale",
            "subcategory":"Non-durable Goods",
            "type":"Manufacturing & Wholesale Goods"
        }
    ],
    "sg:phone":"+1   ",
    "sg:postcode":"17036",
    "sg:province":"PA",
    "sg:tags":[
        "promotional",
        "advertising",
        "specialty",
        "sales"
    ],
    "wof:name":"Richard Fink & Associates",
    "wof:placetype":"venue"
},
  "geometry": {"coordinates":[-76.711297,40.24144],"type":"Point"}
}