{
  "type": "Feature",
  "properties": {
    "iso:country":"US",
    "sg:address":"30 Lakeview Dr",
    "sg:city":"Elizabethtown",
    "sg:classifiers":[
        {
            "category":"Building & Trades",
            "subcategory":"Construction",
            "type":"Services"
        }
    ],
    "sg:phone":"+1   ",
    "sg:postcode":"17022",
    "sg:province":"PA",
    "sg:tags":[
        "hanging",
        "contractor"
    ],
    "wof:name":"Jjs Painting & Wallcovering",
    "wof:placetype":"venue"
},
  "geometry": {"coordinates":[-76.61439799999999,40.164529],"type":"Point"}
}