{
  "type": "Feature",
  "properties": {
    "addr:full":"167 Airport Dr Middletown PA 17057",
    "addr:housenumber":"167",
    "addr:postcode":"17057",
    "addr:street":"Airport Dr",
    "iso:country":"US",
    "sg:address":"167 Airport Dr",
    "sg:city":"Middletown",
    "sg:classifiers":[
        {
            "category":"Retail",
            "subcategory":"Auto Rental",
            "type":"Services"
        }
    ],
    "sg:phone":"+1   ",
    "sg:postcode":"17057",
    "sg:province":"PA",
    "sg:tags":[
        "passenger",
        "truck",
        "car"
    ],
    "wof:name":"Hertz",
    "wof:placetype":"venue"
},
  "geometry": {"coordinates":[-76.74282100000001,40.195634],"type":"Point"}
}