{
  "type": "Feature",
  "properties": {
    "iso:country":"US",
    "sg:address":"6328 Howe St",
    "sg:city":"Pittsburgh",
    "sg:classifiers":[
        {
            "category":"Sports & Exercise",
            "subcategory":"Gym",
            "type":"Entertainment"
        }
    ],
    "sg:phone":"+1   ",
    "sg:postcode":"15206",
    "sg:province":"PA",
    "sg:tags":[
        "fitness",
        "physical",
        "facility"
    ],
    "wof:name":"X Factor Training",
    "wof:placetype":"venue"
},
  "geometry": {"coordinates":[-79.919955,40.454677],"type":"Point"}
}