{
  "type": "Feature",
  "properties": {
    "iso:country":"US",
    "sg:address":"7227 Reynolds St",
    "sg:city":"Pittsburgh",
    "sg:classifiers":[
        {
            "category":"Arts & Performance",
            "subcategory":"Art Gallery",
            "type":"Entertainment"
        },
        {
            "category":"Museum",
            "type":"Entertainment"
        }
    ],
    "sg:phone":"+1 412 371 0600",
    "sg:postcode":"15208",
    "sg:province":"PA",
    "sg:tags":[
        "consultant",
        "galleries"
    ],
    "sg:website":"http://www.frickart.org",
    "wof:name":"Frick Art & Historical Ctr",
    "wof:placetype":"venue"
},
  "geometry": {"coordinates":[-79.90265599999999,40.446273],"type":"Point"}
}