{
  "type": "Feature",
  "properties": {
    "addr:city":"Pittsburgh",
    "addr:full":"7227 Reynolds St Pittsburgh, Pa 15208-2919",
    "addr:house_number":"7227",
    "addr:housenumber":"7227",
    "addr:phone":"+1 412-371-0600",
    "addr:postcode":"15208-2919",
    "addr:road":"Reynolds St",
    "addr:state":"PA",
    "addr:street":"Reynolds St",
    "iso:country":"US",
    "sg:address":"7227 Reynolds St",
    "sg:city":"Pittsburgh",
    "sg:classifiers":[
        {
            "category":"Arts & Performance",
            "subcategory":"Art Gallery",
            "type":"Entertainment"
        },
        {
            "category":"Museum",
            "type":"Entertainment"
        }
    ],
    "sg:phone":"+1 412 371 0600",
    "sg:postcode":"15208",
    "sg:province":"PA",
    "sg:tags":[
        "consultant",
        "galleries"
    ],
    "sg:website":"http://www.frickart.org",
    "wof:name":"Frick Art & Historical Center",
    "wof:placetype":"venue"
},
  "geometry": {"coordinates":[-79.90228999999999,40.44659],"type":"Point"}
}