{
  "type": "Feature",
  "properties": {
    "addr:full":"5 Center Ave Collegeville PA 19426",
    "addr:housenumber":"5",
    "addr:postcode":"19426",
    "addr:street":"Center Ave",
    "iso:country":"US",
    "sg:address":"5 Center Ave",
    "sg:city":"Collegeville",
    "sg:classifiers":[
        {
            "category":"Professional",
            "subcategory":"Lawyer & Legal Services",
            "type":"Services"
        }
    ],
    "sg:phone":"+1 610 454 7978",
    "sg:postcode":"19426",
    "sg:province":"PA",
    "wof:name":"Fliegelman Elderlaw",
    "wof:placetype":"venue"
},
  "geometry": {"coordinates":[-75.464316,40.193959],"type":"Point"}
}