{
  "type": "Feature",
  "properties": {
    "iso:country":"US",
    "sg:address":"226 E Liberty St",
    "sg:city":"Lowellville",
    "sg:classifiers":[
        {
            "category":"Shopping",
            "subcategory":"Florist",
            "type":"Retail Goods"
        }
    ],
    "sg:phone":"+1 330 536 6495",
    "sg:postcode":"44436",
    "sg:province":"PA",
    "wof:name":"Christinas Floral Art & Gift",
    "wof:placetype":"venue"
},
  "geometry": {"coordinates":[-80.53372400000001,41.036527],"type":"Point"}
}