{
  "type": "Feature",
  "properties": {
    "iso:country":"US",
    "sg:address":"3035 Lehigh St",
    "sg:city":"Allentown",
    "sg:classifiers":[
        {
            "category":"Manufacturing",
            "subcategory":"Printing",
            "type":"Manufacturing & Wholesale Goods"
        }
    ],
    "sg:phone":"+1 610 797 0650",
    "sg:postcode":"18103",
    "sg:province":"PA",
    "sg:tags":[
        "commercial",
        "letterpress"
    ],
    "wof:name":"Rebco Kwik-Print",
    "wof:placetype":"venue"
},
  "geometry": {"coordinates":[-75.487297,40.5592],"type":"Point"}
}