{
  "type": "Feature",
  "properties": {
    "iso:country":"US",
    "sg:address":"300 Valley Heights Dr",
    "sg:city":"Williamsport",
    "sg:classifiers":[
        {
            "category":"Real Estate",
            "subcategory":"Real Estate Operator",
            "type":"Services"
        }
    ],
    "sg:phone":"+1 570 326 0557",
    "sg:postcode":"17701",
    "sg:province":"PA",
    "sg:tags":[
        "apartment"
    ],
    "sg:website":"www.themanorgroup.com",
    "wof:name":"Grampian Hills Manor Apts",
    "wof:placetype":"venue"
},
  "geometry": {"coordinates":[-76.97648599999999,41.263067],"type":"Point"}
}