{
  "type": "Feature",
  "properties": {
    "iso:country":"US",
    "sg:address":"89 Highland Dr",
    "sg:city":"Lancaster",
    "sg:classifiers":[
        {
            "category":"Building & Trades",
            "subcategory":"Construction",
            "type":"Services"
        }
    ],
    "sg:phone":"+1   ",
    "sg:postcode":"17602",
    "sg:province":"PA",
    "sg:tags":[
        "contractor"
    ],
    "wof:name":"K Thomas Buchen",
    "wof:placetype":"venue"
},
  "geometry": {"coordinates":[-76.248831,40.038457],"type":"Point"}
}