{
  "type": "Feature",
  "properties": {
    "addr:full":"3700 Raystown Rd Hopewell PA 16650",
    "addr:postcode":"3700;16650",
    "addr:street":"Raystown Rd",
    "iso:country":"US",
    "sg:address":"3700 Raystown Rd",
    "sg:city":"Hopewell",
    "sg:classifiers":[
        {
            "category":"Professional",
            "type":"Services"
        }
    ],
    "sg:phone":"+1   ",
    "sg:postcode":"16650",
    "sg:province":"PA",
    "wof:name":"Trevor T Alexander",
    "wof:placetype":"venue"
},
  "geometry": {"coordinates":[-78.34705599999999,40.129305],"type":"Point"}
}