{
  "type": "Feature",
  "properties": {
    "addr:full":"2050 Columbia Ave Lancaster PA 17603",
    "addr:housenumber":"2050",
    "addr:postcode":"17603",
    "addr:street":"Columbia Ave",
    "iso:country":"US",
    "sg:address":"2050 Columbia Ave",
    "sg:city":"Lancaster",
    "sg:classifiers":[
        {
            "category":"Health Services",
            "subcategory":"Medical Lab",
            "type":"Services"
        }
    ],
    "sg:phone":"+1 717 394 7218",
    "sg:postcode":"17603",
    "sg:province":"PA",
    "sg:tags":[
        "laboratory",
        "dental"
    ],
    "wof:name":"Family Dentist",
    "wof:placetype":"venue"
},
  "geometry": {"coordinates":[-76.358817,40.038745],"type":"Point"}
}