{
  "type": "Feature",
  "properties": {
    "iso:country":"US",
    "sg:address":"1275 York Rd",
    "sg:city":"Gettysburg",
    "sg:classifiers":[
        {
            "category":"Shopping",
            "subcategory":"Pharmacy",
            "type":"Retail Goods"
        }
    ],
    "sg:phone":"+1   ",
    "sg:postcode":"17325",
    "sg:province":"PA",
    "sg:tags":[
        "drug",
        "store"
    ],
    "wof:name":"CVS",
    "wof:placetype":"venue"
},
  "geometry": {"coordinates":[-77.20689900000001,39.840919],"type":"Point"}
}