{
  "type": "Feature",
  "properties": {
    "iso:country":"US",
    "sg:address":"63 Erie Ave",
    "sg:city":"St Marys",
    "sg:classifiers":[
        {
            "category":"Shopping",
            "subcategory":"Gifts & Souvenirs",
            "type":"Retail Goods"
        }
    ],
    "sg:phone":"+1 814 781 1778",
    "sg:postcode":"15857",
    "sg:province":"PA",
    "sg:tags":[
        "shop"
    ],
    "wof:name":"Sweet Scentations",
    "wof:placetype":"venue"
},
  "geometry": {"coordinates":[-78.558336,41.429539],"type":"Point"}
}