{
  "type": "Feature",
  "properties": {
    "iso:country":"US",
    "sg:address":"216 S Queen St",
    "sg:city":"Littlestown",
    "sg:classifiers":[
        {
            "category":"Autos & Motor Vehicles",
            "subcategory":"Auto Supplies",
            "type":"Retail Goods"
        }
    ],
    "sg:phone":"+1 717 359 7388",
    "sg:postcode":"17340",
    "sg:province":"PA",
    "sg:tags":[
        "automobile",
        "parts"
    ],
    "wof:name":"Towne Auto Parts",
    "wof:placetype":"venue"
},
  "geometry": {"coordinates":[-77.086444,39.743156],"type":"Point"}
}