{
  "type": "Feature",
  "properties": {
    "iso:country":"US",
    "sg:address":"198 S Main St",
    "sg:city":"Carrolltown",
    "sg:classifiers":[
        {
            "category":"Manufacturing",
            "subcategory":"Petroleum Products",
            "type":"Manufacturing & Wholesale Goods"
        }
    ],
    "sg:phone":"+1 814 344 9911",
    "sg:postcode":"15722",
    "sg:province":"PA",
    "sg:tags":[
        "coal"
    ],
    "wof:name":"E P Bender Coal Co Inc",
    "wof:placetype":"venue"
},
  "geometry": {"coordinates":[-78.70984,40.598836],"type":"Point"}
}