{
  "type": "Feature",
  "properties": {
    "iso:country":"US",
    "sg:address":"70 W Main St",
    "sg:city":"Waynesboro",
    "sg:classifiers":[
        {
            "category":"Professional",
            "subcategory":"Management & Consulting",
            "type":"Services"
        }
    ],
    "sg:phone":"+1   ",
    "sg:postcode":"17268",
    "sg:province":"PA",
    "sg:tags":[
        "retail",
        "direct",
        "sales"
    ],
    "wof:name":"Mas Country Crafts & Flea Mkt",
    "wof:placetype":"venue"
},
  "geometry": {"coordinates":[-77.578846,39.756233],"type":"Point"}
}