{
  "type": "Feature",
  "properties": {
    "iso:country":"US",
    "sg:address":"114 Perry Hwy",
    "sg:city":"Harmony",
    "sg:classifiers":[
        {
            "category":"Real Estate",
            "subcategory":"Real Estate Agent",
            "type":"Services"
        }
    ],
    "sg:phone":"+1 724 452 4488",
    "sg:postcode":"16037",
    "sg:province":"PA",
    "wof:name":"Keystone Properties Inc",
    "wof:placetype":"venue"
},
  "geometry": {"coordinates":[-80.136774,40.804004],"type":"Point"}
}