{
  "type": "Feature",
  "properties": {
    "iso:country":"US",
    "sg:address":"1425 Beaver Ave",
    "sg:city":"Pittsburgh",
    "sg:classifiers":[
        {
            "category":"Health Services",
            "subcategory":"Clinic",
            "type":"Services"
        }
    ],
    "sg:phone":"+1   ",
    "sg:postcode":"15233",
    "sg:province":"PA",
    "sg:tags":[
        "rehabilitation",
        "drug"
    ],
    "wof:name":"Second Step The",
    "wof:placetype":"venue"
},
  "geometry": {"coordinates":[-80.029487,40.454489],"type":"Point"}
}