{
  "type": "Feature",
  "properties": {
    "addr:full":"3542 Meridian St Philadelphia PA 19136",
    "addr:housenumber":"3542",
    "addr:postcode":"19136",
    "addr:street":"Meridian St",
    "iso:country":"US",
    "sg:address":"3542 Meridian St",
    "sg:city":"Philadelphia",
    "sg:classifiers":[
        {
            "category":"Building & Trades",
            "subcategory":"Construction",
            "type":"Services"
        }
    ],
    "sg:phone":"+1 215 332 8890",
    "sg:postcode":"19136",
    "sg:province":"PA",
    "sg:tags":[
        "contractor"
    ],
    "wof:name":"Tom Charles & Sons Roofing",
    "wof:placetype":"venue"
},
  "geometry": {"coordinates":[-75.03366800000001,40.041026],"type":"Point"}
}