{
  "type": "Feature",
  "properties": {
    "addr:full":"430 N 64th St Philadelphia PA 19151",
    "addr:housenumber":"430",
    "addr:postcode":"19151",
    "addr:street":"N 64Th St",
    "iso:country":"US",
    "sg:address":"430 N 64th St",
    "sg:city":"Philadelphia",
    "sg:classifiers":[
        {
            "category":"Building & Trades",
            "subcategory":"Locksmith",
            "type":"Services"
        }
    ],
    "sg:phone":"+1 267 295 2412",
    "sg:postcode":"19151",
    "sg:province":"PA",
    "sg:tags":[
        "key"
    ],
    "wof:name":"Always Available Emergency Locksmith",
    "wof:placetype":"venue"
},
  "geometry": {"coordinates":[-75.247607,39.969591],"type":"Point"}
}