{
  "type": "Feature",
  "properties": {
    "iso:country":"US",
    "sg:address":"3006 Foxx Ln",
    "sg:city":"Philadelphia",
    "sg:classifiers":[
        {
            "category":"Building & Trades",
            "subcategory":"Landscaping Services",
            "type":"Services"
        }
    ],
    "sg:phone":"+1 215 843 3058",
    "sg:postcode":"19144",
    "sg:province":"PA",
    "sg:tags":[
        "consultant",
        "designer",
        "landscape"
    ],
    "wof:name":"Kjk Associates",
    "wof:placetype":"venue"
},
  "geometry": {"coordinates":[-75.18452499999999,40.024693],"type":"Point"}
}