{
  "type": "Feature",
  "properties": {
    "iso:country":"US",
    "sg:address":"233 W Mulberry St",
    "sg:city":"Shamokin",
    "sg:classifiers":[
        {
            "category":"Personal",
            "type":"Services"
        }
    ],
    "sg:phone":"+1 570 648 3969",
    "sg:postcode":"17872",
    "sg:province":"PA",
    "sg:tags":[
        "therapist",
        "massage"
    ],
    "wof:name":"Audrey's Pro Massage",
    "wof:placetype":"venue"
},
  "geometry": {"coordinates":[-76.559579,40.7844],"type":"Point"}
}