{
  "type": "Feature",
  "properties": {
    "addr:full":"154 Orlan Rd New Holland PA 17557",
    "addr:housenumber":"154",
    "addr:postcode":"17557",
    "addr:street":"Orlan Rd",
    "iso:country":"US",
    "sg:address":"154 Orlan Rd",
    "sg:city":"New Holland",
    "sg:classifiers":[
        {
            "category":"Freight",
            "type":"Transportation"
        }
    ],
    "sg:phone":"+1 717 355 5294",
    "sg:postcode":"17557",
    "sg:province":"PA",
    "sg:tags":[
        "trucking"
    ],
    "wof:name":"Orlan Transport",
    "wof:placetype":"venue"
},
  "geometry": {"coordinates":[-76.093197,40.092118],"type":"Point"}
}