{
  "type": "Feature",
  "properties": {
    "iso:country":"US",
    "sg:address":"5336 Diamond St",
    "sg:city":"Philadelphia",
    "sg:classifiers":[
        {
            "category":"Organizations",
            "subcategory":"Religious Organization",
            "type":"Services"
        }
    ],
    "sg:phone":"+1   ",
    "sg:postcode":"19131",
    "sg:province":"PA",
    "wof:name":"Sisters of Blessed Sacrament",
    "wof:placetype":"venue"
},
  "geometry": {"coordinates":[-75.23267,39.988155],"type":"Point"}
}