{
  "type": "Feature",
  "properties": {
    "iso:country":"US",
    "sg:address":"2925 W Emmaus Ave",
    "sg:city":"Allentown",
    "sg:classifiers":[
        {
            "category":"Home & Garden",
            "subcategory":"Hardware",
            "type":"Retail Goods"
        }
    ],
    "sg:phone":"+1 610 797 6161",
    "sg:postcode":"18103",
    "sg:province":"PA",
    "sg:tags":[
        "store"
    ],
    "wof:name":"Blue Star Hardware",
    "wof:placetype":"venue"
},
  "geometry": {"coordinates":[-75.48110200000001,40.557899],"type":"Point"}
}