{
  "type": "Feature",
  "properties": {
    "iso:country":"US",
    "sg:address":"2800 W Dauphin St",
    "sg:city":"Philadelphia",
    "sg:classifiers":[
        {
            "category":"Health Services",
            "subcategory":"Optometrist",
            "type":"Services"
        }
    ],
    "sg:phone":"+1   ",
    "sg:postcode":"19132",
    "sg:province":"PA",
    "wof:name":"Eye Inst Strwbry Mansion",
    "wof:placetype":"venue"
},
  "geometry": {"coordinates":[-75.179895,39.990978],"type":"Point"}
}