{
  "type": "Feature",
  "properties": {
    "iso:country":"US",
    "sg:address":"150 Blakely Rd",
    "sg:city":"Butler",
    "sg:classifiers":[
        {
            "category":"Retail",
            "subcategory":"Self-service Laundry",
            "type":"Services"
        }
    ],
    "sg:phone":"+1   ",
    "sg:postcode":"16002",
    "sg:province":"PA",
    "sg:tags":[
        "coin"
    ],
    "wof:name":"Galbreaths Laundrymat Dry Clg",
    "wof:placetype":"venue"
},
  "geometry": {"coordinates":[-79.85713199999999,40.800493],"type":"Point"}
}