{
  "type": "Feature",
  "properties": {
    "iso:country":"US",
    "sg:address":"3705 Saw Mill Run Blvd",
    "sg:city":"Pittsburgh",
    "sg:classifiers":[
        {
            "category":"Shopping",
            "subcategory":"Mobile Phones",
            "type":"Retail Goods"
        }
    ],
    "sg:phone":"+1 800 274 2538",
    "sg:postcode":"15227",
    "sg:province":"PA",
    "wof:name":"Cricket",
    "wof:placetype":"venue"
},
  "geometry": {"coordinates":[-79.981898,40.37141],"type":"Point"}
}