{
  "type": "Feature",
  "properties": {
    "iso:country":"US",
    "sg:address":"98 Pine Meadow Rd",
    "sg:city":"Lebanon",
    "sg:classifiers":[
        {
            "category":"Building & Trades",
            "subcategory":"Construction",
            "type":"Services"
        }
    ],
    "sg:phone":"+1   ",
    "sg:postcode":"17046",
    "sg:province":"PA",
    "sg:tags":[
        "residential",
        "contractor"
    ],
    "wof:name":"S E Gensler",
    "wof:placetype":"venue"
},
  "geometry": {"coordinates":[-76.437573,40.409688],"type":"Point"}
}