{
  "type": "Feature",
  "properties": {
    "addr:full":"471 Jacksonville Rd Hatboro PA 19040",
    "addr:housenumber":"471",
    "addr:postcode":"19040",
    "addr:street":"Jacksonville Rd",
    "iso:country":"US",
    "sg:address":"471 Jacksonville Rd",
    "sg:city":"Hatboro",
    "sg:classifiers":[
        {
            "category":"Retail",
            "subcategory":"Repair Shop",
            "type":"Services"
        }
    ],
    "sg:phone":"+1 215 355 1211",
    "sg:postcode":"19040",
    "sg:province":"PA",
    "sg:tags":[
        "lock",
        "locksmith"
    ],
    "wof:name":"S K H Locksmiths",
    "wof:placetype":"venue"
},
  "geometry": {"coordinates":[-75.09465400000001,40.185038],"type":"Point"}
}