{
  "type": "Feature",
  "properties": {
    "addr:full":"2380 Maryland Rd Willow Grove PA 19090",
    "addr:housenumber":"2380",
    "addr:postcode":"19090",
    "addr:street":"Maryland Rd",
    "iso:country":"US",
    "sg:address":"2380 Maryland Rd",
    "sg:city":"Willow Grove",
    "sg:classifiers":[
        {
            "category":"Autos & Motor Vehicles",
            "subcategory":"Auto Supplies",
            "type":"Retail Goods"
        },
        {
            "category":"Wholesale",
            "subcategory":"Auto Parts",
            "type":"Manufacturing & Wholesale Goods"
        }
    ],
    "sg:phone":"+1 215 784 0410",
    "sg:postcode":"19090",
    "sg:province":"PA",
    "sg:tags":[
        "automobile",
        "automotive"
    ],
    "wof:name":"Gordon Group",
    "wof:placetype":"venue"
},
  "geometry": {"coordinates":[-75.13422300000001,40.162253],"type":"Point"}
}