{
  "type": "Feature",
  "properties": {
    "iso:country":"US",
    "sg:address":"501 S 69th St",
    "sg:city":"Upper Darby",
    "sg:classifiers":[
        {
            "category":"Restaurant",
            "type":"Food & Drink"
        }
    ],
    "sg:phone":"+1 610 352 8353",
    "sg:postcode":"19082",
    "sg:province":"PA",
    "sg:website":"www.crownfriedchicken.com",
    "wof:name":"Royal Crown Fried Chicken",
    "wof:placetype":"venue"
},
  "geometry": {"coordinates":[-75.256401,39.952202],"type":"Point"}
}