{
  "type": "Feature",
  "properties": {
    "addr:full":"246 Noblestown Rd Carnegie PA 15106",
    "addr:housenumber":"246",
    "addr:postcode":"15106",
    "addr:street":"Noblestown Rd",
    "iso:country":"US",
    "sg:address":"246 Noblestown Rd",
    "sg:city":"Carnegie",
    "sg:classifiers":[
        {
            "category":"Home & Garden",
            "subcategory":"Building Materials",
            "type":"Retail Goods"
        }
    ],
    "sg:phone":"+1 412 276 8280",
    "sg:postcode":"15106",
    "sg:province":"PA",
    "sg:tags":[
        "glass",
        "window",
        "plate"
    ],
    "wof:name":"Auto Glass Svc",
    "wof:placetype":"venue"
},
  "geometry": {"coordinates":[-80.077417,40.413358],"type":"Point"}
}