{
  "type": "Feature",
  "properties": {
    "iso:country":"US",
    "sg:address":"720 N Main Ave",
    "sg:city":"Scranton",
    "sg:classifiers":[
        {
            "category":"Building & Trades",
            "subcategory":"Equipment Rental",
            "type":"Services"
        }
    ],
    "sg:phone":"+1   ",
    "sg:postcode":"18504",
    "sg:province":"PA",
    "wof:name":"C & A Vending Inc",
    "wof:placetype":"venue"
},
  "geometry": {"coordinates":[-75.673649,41.420819],"type":"Point"}
}