{
  "type": "Feature",
  "properties": {
    "iso:country":"US",
    "sg:address":"8300 Bear Creek Blvd",
    "sg:city":"Bear Creek Twp",
    "sg:classifiers":[
        {
            "category":"Organizations",
            "subcategory":"Religious Organization",
            "type":"Services"
        }
    ],
    "sg:phone":"+1 570 474 9575",
    "sg:postcode":"18702",
    "sg:province":"PA",
    "sg:tags":[
        "church"
    ],
    "wof:name":"New Life Community Church",
    "wof:placetype":"venue"
},
  "geometry": {"coordinates":[-75.712678,41.181997],"type":"Point"}
}