{
  "type": "Feature",
  "properties": {
    "iso:country":"US",
    "sg:address":"134 N Tyson Ave",
    "sg:city":"Glenside",
    "sg:classifiers":[
        {
            "category":"Social Services",
            "type":"Services"
        }
    ],
    "sg:phone":"+1   ",
    "sg:postcode":"19038",
    "sg:province":"PA",
    "wof:name":"Summit Settlement",
    "wof:placetype":"venue"
},
  "geometry": {"coordinates":[-75.158041,40.106687],"type":"Point"}
}