{
  "type": "Feature",
  "properties": {
    "iso:country":"US",
    "sg:address":"600 King St",
    "sg:city":"Pottstown",
    "sg:classifiers":[
        {
            "category":"Shopping",
            "type":"Retail Goods"
        }
    ],
    "sg:phone":"+1   ",
    "sg:postcode":"19464",
    "sg:province":"PA",
    "sg:tags":[
        "merchandise"
    ],
    "wof:name":"Scentual Accnts Crative Design",
    "wof:placetype":"venue"
},
  "geometry": {"coordinates":[-75.638403,40.245242],"type":"Point"}
}