{
  "type": "Feature",
  "properties": {
    "iso:country":"US",
    "sg:address":"2318 Bellevue Rd",
    "sg:city":"Harrisburg",
    "sg:classifiers":[
        {
            "category":"Professional",
            "subcategory":"Lawyer & Legal Services",
            "type":"Services"
        }
    ],
    "sg:phone":"+1 717 236 7214",
    "sg:postcode":"17104",
    "sg:province":"PA",
    "sg:tags":[
        "attorney"
    ],
    "wof:name":"Michael Kerrigan",
    "wof:placetype":"venue"
},
  "geometry": {"coordinates":[-76.850404,40.269308],"type":"Point"}
}