{
  "type": "Feature",
  "properties": {
    "iso:country":"US",
    "sg:address":"10560 Sampson Rd",
    "sg:city":"Waterford",
    "sg:classifiers":[
        {
            "category":"Building & Trades",
            "subcategory":"Construction",
            "type":"Services"
        }
    ],
    "sg:phone":"+1   ",
    "sg:postcode":"16441",
    "sg:province":"PA",
    "sg:tags":[
        "house",
        "nonresidential"
    ],
    "wof:name":"Konkol Construction & Rmdlg",
    "wof:placetype":"venue"
},
  "geometry": {"coordinates":[-79.98909999999999,42.011494],"type":"Point"}
}