{
  "type": "Feature",
  "properties": {
    "addr:full":"5825 Lindbergh Blvd Philadelphia PA 19143",
    "addr:housenumber":"5825",
    "addr:postcode":"19143",
    "addr:street":"Lindbergh Blvd",
    "iso:country":"US",
    "sg:address":"5825 Lindbergh Blvd",
    "sg:city":"Philadelphia",
    "sg:classifiers":[
        {
            "category":"Social Services",
            "subcategory":"Adult Care",
            "type":"Services"
        }
    ],
    "sg:phone":"+1   ",
    "sg:postcode":"19143",
    "sg:province":"PA",
    "sg:tags":[
        "handicapped",
        "residential",
        "mentally",
        "for",
        "child"
    ],
    "wof:name":"Allegheny Valley School",
    "wof:placetype":"venue"
},
  "geometry": {"coordinates":[-75.220326,39.926759],"type":"Point"}
}