{
  "type": "Feature",
  "properties": {
    "addr:full":"76 Cowan Rd Mc Kees Rocks PA 15136",
    "addr:housenumber":"76",
    "addr:postcode":"15136",
    "addr:street":"Cowan Rd;Kees Rocks",
    "iso:country":"US",
    "sg:address":"76 Cowan Rd",
    "sg:city":"Mc Kees Rocks",
    "sg:classifiers":[
        {
            "category":"Health Services",
            "subcategory":"Dentist",
            "type":"Services"
        }
    ],
    "sg:phone":"+1 412 787 9677",
    "sg:postcode":"15136",
    "sg:province":"PA",
    "wof:name":"Skoff David M DMD",
    "wof:placetype":"venue"
},
  "geometry": {"coordinates":[-80.077003,40.4729],"type":"Point"}
}