{
  "type": "Feature",
  "properties": {
    "iso:country":"US",
    "sg:address":"121 Bridge St",
    "sg:city":"Homestead",
    "sg:classifiers":[
        {
            "category":"Building & Trades",
            "subcategory":"Construction",
            "type":"Services"
        }
    ],
    "sg:phone":"+1 412 462 9524",
    "sg:postcode":"15148",
    "sg:province":"PA",
    "sg:tags":[
        "contractor"
    ],
    "wof:name":"Montgomery Development",
    "wof:placetype":"venue"
},
  "geometry": {"coordinates":[-79.798011,40.393699],"type":"Point"}
}