{
  "type": "Feature",
  "properties": {
    "iso:country":"US",
    "sg:address":"1624 Lincoln Hwy E",
    "sg:city":"Lancaster",
    "sg:classifiers":[
        {
            "category":"Restaurant",
            "type":"Food & Drink"
        }
    ],
    "sg:phone":"+1 717 509 7600",
    "sg:postcode":"17602",
    "sg:province":"PA",
    "sg:website":"www.subway.com",
    "wof:name":"Subway Sandwiches & Salads",
    "wof:placetype":"venue"
},
  "geometry": {"coordinates":[-76.271846,40.037696],"type":"Point"}
}