{
  "type": "Feature",
  "properties": {
    "addr:full":"502 S Center Ave Somerset PA 15501",
    "addr:housenumber":"502",
    "addr:postcode":"15501",
    "addr:street":"S Center Ave",
    "iso:country":"US",
    "sg:address":"502 S Center Ave",
    "sg:city":"Somerset",
    "sg:classifiers":[
        {
            "category":"Freight",
            "type":"Transportation"
        }
    ],
    "sg:phone":"+1   ",
    "sg:postcode":"15501",
    "sg:province":"PA",
    "sg:tags":[
        "operator",
        "local",
        "trucking"
    ],
    "wof:name":"Somerset Movers",
    "wof:placetype":"venue"
},
  "geometry": {"coordinates":[-79.078676,40.00468],"type":"Point"}
}