{
  "type": "Feature",
  "properties": {
    "addr:full":"9424 State Hwy 430 Sherman NY 14781",
    "addr:housenumber":"9424",
    "addr:postcode":"14781",
    "addr:street":"State Hwy 430",
    "iso:country":"US",
    "sg:address":"9424 State Hwy 430",
    "sg:city":"Sherman",
    "sg:classifiers":[
        {
            "category":"Farming",
            "subcategory":"Dairy Farm",
            "type":"Manufacturing & Wholesale Goods"
        }
    ],
    "sg:phone":"+1 716 761 6806",
    "sg:postcode":"14781",
    "sg:province":"NY",
    "wof:name":"Burgess Dairy",
    "wof:placetype":"venue"
},
  "geometry": {"coordinates":[-79.672425,42.138485],"type":"Point"}
}