{
  "type": "Feature",
  "properties": {
    "iso:country":"US",
    "sg:address":"2618 Cynwyd Ave",
    "sg:city":"Broomall",
    "sg:classifiers":[
        {
            "category":"Building & Trades",
            "subcategory":"Construction",
            "type":"Services"
        }
    ],
    "sg:phone":"+1 610 325 3234",
    "sg:postcode":"19008",
    "sg:province":"PA",
    "sg:tags":[
        "fence",
        "contractor"
    ],
    "wof:name":"Joseph A Deangelis Inc",
    "wof:placetype":"venue"
},
  "geometry": {"coordinates":[-75.36498899999999,39.984811],"type":"Point"}
}