{
  "type": "Feature",
  "properties": {
    "iso:country":"US",
    "sg:address":"201 E Arch St",
    "sg:city":"Fleetwood",
    "sg:classifiers":[
        {
            "category":"Professional",
            "type":"Services"
        }
    ],
    "sg:phone":"+1 610 944 8393",
    "sg:postcode":"19522",
    "sg:province":"PA",
    "sg:tags":[
        "establishment"
    ],
    "wof:name":"Parson P V",
    "wof:placetype":"venue"
},
  "geometry": {"coordinates":[-75.81711799999999,40.45744],"type":"Point"}
}