{
  "type": "Feature",
  "properties": {
    "addr:full":"1027 State Rte 100 Trexlertown PA 18087",
    "addr:housenumber":"1027",
    "addr:postcode":"18087",
    "addr:street":"State Rte 100",
    "iso:country":"US",
    "sg:address":"1027 State Rte 100",
    "sg:city":"Trexlertown",
    "sg:classifiers":[
        {
            "category":"Professional",
            "subcategory":"Management & Consulting",
            "type":"Services"
        }
    ],
    "sg:phone":"+1 610 530 7000",
    "sg:postcode":"18087",
    "sg:province":"PA",
    "sg:tags":[
        "personnel",
        "consultant"
    ],
    "wof:name":"Allied Personnel Svc",
    "wof:placetype":"venue"
},
  "geometry": {"coordinates":[-75.60757,40.553613],"type":"Point"}
}