{
  "type": "Feature",
  "properties": {
    "iso:country":"US",
    "sg:address":"4220 Steubenville Pike",
    "sg:city":"Pittsburgh",
    "sg:classifiers":[
        {
            "category":"Retail",
            "subcategory":"Auto Repair",
            "type":"Services"
        }
    ],
    "sg:phone":"+1 412 921 6093",
    "sg:postcode":"15205",
    "sg:province":"PA",
    "sg:tags":[
        "towing",
        "truck"
    ],
    "wof:name":"Route 60 Auto & Truck Repair",
    "wof:placetype":"venue"
},
  "geometry": {"coordinates":[-80.089428,40.440002],"type":"Point"}
}