{
  "type": "Feature",
  "properties": {
    "addr:full":"1445 Market St Beaver PA 15009",
    "addr:housenumber":"1445",
    "addr:postcode":"15009",
    "addr:street":"Market St",
    "iso:country":"US",
    "sg:address":"1445 Market St",
    "sg:city":"Beaver",
    "sg:classifiers":[
        {
            "category":"Building & Trades",
            "subcategory":"Cleaning & Sanitation",
            "type":"Services"
        }
    ],
    "sg:phone":"+1 724 775 9665",
    "sg:postcode":"15009",
    "sg:province":"PA",
    "sg:tags":[
        "house",
        "maid"
    ],
    "wof:name":"Merry Maids",
    "wof:placetype":"venue"
},
  "geometry": {"coordinates":[-80.30010799999999,40.710308],"type":"Point"}
}