{
  "type": "Feature",
  "properties": {
    "addr:full":"2949 Maple Ln Bloomsburg PA 17815",
    "addr:housenumber":"2949",
    "addr:postcode":"17815",
    "addr:street":"Maple Ln",
    "iso:country":"US",
    "sg:address":"2949 Maple Ln",
    "sg:city":"Bloomsburg",
    "sg:classifiers":[
        {
            "category":"Wholesale",
            "subcategory":"Auto Parts",
            "type":"Manufacturing & Wholesale Goods"
        }
    ],
    "sg:phone":"+1 570 784 1000",
    "sg:postcode":"17815",
    "sg:province":"PA",
    "wof:name":"Orelli Supply Inc",
    "wof:placetype":"venue"
},
  "geometry": {"coordinates":[-76.40289799999999,41.013533],"type":"Point"}
}