{
  "type": "Feature",
  "properties": {
    "addr:full":"8 Runyon Rd Hummelstown PA 17036",
    "addr:housenumber":"8",
    "addr:postcode":"17036",
    "addr:street":"Runyon Rd",
    "iso:country":"US",
    "sg:address":"8 Runyon Rd",
    "sg:city":"Hummelstown",
    "sg:classifiers":[
        {
            "category":"Professional",
            "type":"Services"
        }
    ],
    "sg:phone":"+1 717 583 1842",
    "sg:postcode":"17036",
    "sg:province":"PA",
    "sg:tags":[
        "establishment"
    ],
    "wof:name":"Macelwee & Assoc",
    "wof:placetype":"venue"
},
  "geometry": {"coordinates":[-76.71731800000001,40.261123],"type":"Point"}
}