{
  "type": "Feature",
  "properties": {
    "addr:full":"142 Elder Ln Bedford PA 15522",
    "addr:housenumber":"142",
    "addr:postcode":"15522",
    "addr:street":"Elder Ln",
    "iso:country":"US",
    "sg:address":"142 Elder Ln",
    "sg:city":"Bedford",
    "sg:phone":"+1   ",
    "sg:postcode":"15522",
    "sg:province":"PA",
    "sg:tags":[
        "farm"
    ],
    "wof:name":"Pentacreek Farm",
    "wof:placetype":"venue"
},
  "geometry": {"coordinates":[-78.63132899999999,39.833573],"type":"Point"}
}