{
  "type": "Feature",
  "properties": {
    "iso:country":"US",
    "sg:address":"700 Chestnut St",
    "sg:city":"Philadelphia",
    "sg:classifiers":[
        {
            "category":"Personal",
            "subcategory":"Adult",
            "type":"Services"
        }
    ],
    "sg:phone":"+1   ",
    "sg:postcode":"19106",
    "sg:province":"PA",
    "sg:tags":[
        "agency",
        "advertising"
    ],
    "wof:name":"Compudate USA",
    "wof:placetype":"venue"
},
  "geometry": {"coordinates":[-75.15391700000001,39.949615],"type":"Point"}
}