{
  "type": "Feature",
  "properties": {
    "addr:full":"4214 Brownsville Rd Pittsburgh PA 15227",
    "addr:housenumber":"4214",
    "addr:postcode":"15227",
    "addr:street":"Brownsville Rd",
    "iso:country":"US",
    "sg:address":"4214 Brownsville Rd",
    "sg:city":"Pittsburgh",
    "sg:classifiers":[
        {
            "category":"Restaurant",
            "type":"Food & Drink"
        }
    ],
    "sg:phone":"+1 412 881 2075",
    "sg:postcode":"15227",
    "sg:province":"PA",
    "wof:name":"McDonald's Hamburgers",
    "wof:placetype":"venue"
},
  "geometry": {"coordinates":[-79.98380299999999,40.3643],"type":"Point"}
}