{
  "type": "Feature",
  "properties": {
    "iso:country":"US",
    "sg:address":"1286 Brandt Rd",
    "sg:city":"Mechanicsburg",
    "sg:classifiers":[
        {
            "category":"Retail",
            "subcategory":"Repair Shop",
            "type":"Services"
        }
    ],
    "sg:phone":"+1   ",
    "sg:postcode":"17055",
    "sg:province":"PA",
    "sg:tags":[
        "trade",
        "welding",
        "contractor"
    ],
    "wof:name":"Nester Enterprises",
    "wof:placetype":"venue"
},
  "geometry": {"coordinates":[-77.080281,40.162457],"type":"Point"}
}