{
  "type": "Feature",
  "properties": {
    "iso:country":"US",
    "sg:address":"245 Old Zion Rd",
    "sg:city":"North East",
    "sg:classifiers":[
        {
            "category":"Organizations",
            "subcategory":"Religious Organization",
            "type":"Services"
        }
    ],
    "sg:phone":"+1 410 658 5767",
    "sg:postcode":"21901",
    "sg:province":"MD",
    "sg:tags":[
        "church"
    ],
    "sg:website":"www.gracebiblechapel.org",
    "wof:name":"Grace Bible Chapel",
    "wof:placetype":"venue"
},
  "geometry": {"coordinates":[-75.96839,39.681238],"type":"Point"}
}