{
  "type": "Feature",
  "properties": {
    "addr:full":"680 Andersen Dr Pittsburgh PA 15220",
    "addr:housenumber":"680",
    "addr:postcode":"15220",
    "addr:street":"Andersen Dr",
    "iso:country":"US",
    "sg:address":"680 Andersen Dr",
    "sg:city":"Pittsburgh",
    "sg:classifiers":[
        {
            "category":"Banks & Credit Unions",
            "subcategory":"Bank",
            "type":"Services"
        }
    ],
    "sg:phone":"+1 412 919 0500",
    "sg:postcode":"15220",
    "sg:province":"PA",
    "sg:tags":[
        "mortgage",
        "loan",
        "broker",
        "real estate"
    ],
    "wof:name":"Mortgage One Financial Group Inc",
    "wof:placetype":"venue"
},
  "geometry": {"coordinates":[-80.06199599999999,40.421398],"type":"Point"}
}