{
  "type": "Feature",
  "properties": {
    "iso:country":"US",
    "sg:address":"64 Forest Grove Rd",
    "sg:city":"Coraopolis",
    "sg:classifiers":[
        {
            "category":"Professional",
            "type":"Services"
        },
        {
            "category":"Food & Beverages",
            "subcategory":"Groceries & Convenience Stores",
            "type":"Retail Goods"
        }
    ],
    "sg:phone":"+1 412 859 3333",
    "sg:postcode":"15108",
    "sg:province":"PA",
    "sg:tags":[
        "caterer"
    ],
    "wof:name":"Rossi's Market",
    "wof:placetype":"venue"
},
  "geometry": {"coordinates":[-80.127403,40.4818],"type":"Point"}
}