{
  "type": "Feature",
  "properties": {
    "iso:country":"US",
    "sg:address":"550 California Rd",
    "sg:city":"Quakertown",
    "sg:classifiers":[
        {
            "category":"Professional",
            "subcategory":"Engineering",
            "type":"Services"
        }
    ],
    "sg:phone":"+1   ",
    "sg:postcode":"18951",
    "sg:province":"PA",
    "wof:name":"Alpha Watch",
    "wof:placetype":"venue"
},
  "geometry": {"coordinates":[-75.35504,40.458628],"type":"Point"}
}