{
  "type": "Feature",
  "properties": {
    "addr:full":"4805 Rawle St Philadelphia PA 19135",
    "addr:housenumber":"4805",
    "addr:postcode":"19135",
    "addr:street":"Rawle St",
    "iso:country":"US",
    "sg:address":"4805 Rawle St",
    "sg:city":"Philadelphia",
    "sg:classifiers":[
        {
            "category":"Building & Trades",
            "subcategory":"Plumbing",
            "type":"Services"
        }
    ],
    "sg:phone":"+1 215 332 1500",
    "sg:postcode":"19135",
    "sg:province":"PA",
    "sg:tags":[
        "conditioning",
        "air",
        "system",
        "contractor"
    ],
    "wof:name":"S Bonaccori",
    "wof:placetype":"venue"
},
  "geometry": {"coordinates":[-75.043846,40.022765],"type":"Point"}
}