{
  "type": "Feature",
  "properties": {
    "iso:country":"US",
    "sg:address":"14 Rambling Ln",
    "sg:city":"Malvern",
    "sg:classifiers":[
        {
            "category":"Autos & Motor Vehicles",
            "subcategory":"Automobile Sales",
            "type":"Retail Goods"
        }
    ],
    "sg:phone":"+1 610 415 1320",
    "sg:postcode":"19355",
    "sg:province":"PA",
    "sg:tags":[
        "distributor",
        "manufacturer"
    ],
    "wof:name":"Luckys Race Cars & Fabricatio",
    "wof:placetype":"venue"
},
  "geometry": {"coordinates":[-75.4967,40.028031],"type":"Point"}
}