{
  "type": "Feature",
  "properties": {
    "addr:full":"504 McNeilly Rd Pittsburgh PA 15226",
    "addr:housenumber":"504",
    "addr:postcode":"15226",
    "addr:street":"Mcneilly Rd",
    "iso:country":"US",
    "sg:address":"504 McNeilly Rd",
    "sg:city":"Pittsburgh",
    "sg:classifiers":[
        {
            "category":"Wholesale",
            "subcategory":"Hardware",
            "type":"Manufacturing & Wholesale Goods"
        }
    ],
    "sg:phone":"+1 412 563 2658",
    "sg:postcode":"15226",
    "sg:province":"PA",
    "sg:tags":[
        "fastener"
    ],
    "sg:website":"www.ajfastener.com",
    "wof:name":"A & J Fastener",
    "wof:placetype":"venue"
},
  "geometry": {"coordinates":[-80.010216,40.382913],"type":"Point"}
}