{
  "type": "Feature",
  "properties": {
    "iso:country":"US",
    "sg:address":"46 Public Sq",
    "sg:city":"Wilkes Barre",
    "sg:classifiers":[
        {
            "category":"Professional",
            "subcategory":"Accounting & Tax Preparation",
            "type":"Services"
        }
    ],
    "sg:phone":"+1   ",
    "sg:postcode":"18701",
    "sg:province":"PA",
    "wof:name":"Eugene A Korjeski",
    "wof:placetype":"venue"
},
  "geometry": {"coordinates":[-75.88118,41.245521],"type":"Point"}
}