{
  "type": "Feature",
  "properties": {
    "iso:country":"US",
    "sg:address":"106 Chestnut St",
    "sg:city":"Centerport",
    "sg:classifiers":[
        {
            "category":"Government",
            "subcategory":"Post Office",
            "type":"Public Place"
        }
    ],
    "sg:phone":"+1   ",
    "sg:postcode":"19516",
    "sg:province":"PA",
    "sg:tags":[
        "postal",
        "us"
    ],
    "wof:name":"Centerport Post Office",
    "wof:placetype":"venue"
},
  "geometry": {"coordinates":[-76.00639099999999,40.486502],"type":"Point"}
}