{
  "type": "Feature",
  "properties": {
    "iso:country":"US",
    "sg:address":"88 Woodchoppertown Rd",
    "sg:city":"Boyertown",
    "sg:classifiers":[
        {
            "category":"Organizations",
            "subcategory":"Religious Organization",
            "type":"Services"
        }
    ],
    "sg:phone":"+1 610 689 5862",
    "sg:postcode":"19512",
    "sg:province":"PA",
    "sg:tags":[
        "church"
    ],
    "sg:website":"www.forministry.com/abc19512",
    "wof:name":"Ark Bible Chapel",
    "wof:placetype":"venue"
},
  "geometry": {"coordinates":[-75.71974899999999,40.349171],"type":"Point"}
}