{
  "type": "Feature",
  "properties": {
    "addr:full":"1256 Welsh Rd North Wales PA 19454",
    "addr:housenumber":"1256",
    "addr:postcode":"19454",
    "addr:street":"Welsh Rd",
    "iso:country":"US",
    "sg:address":"1256 Welsh Rd",
    "sg:city":"North Wales",
    "sg:classifiers":[
        {
            "category":"Autos & Motor Vehicles",
            "subcategory":"Automobile Sales",
            "type":"Retail Goods"
        },
        {
            "category":"Airline",
            "type":"Transportation"
        }
    ],
    "sg:phone":"+1 215 616 5370",
    "sg:postcode":"19454",
    "sg:province":"PA",
    "sg:tags":[
        "shuttle",
        "airport",
        "limo"
    ],
    "sg:website":"www.tropianotransportation.com",
    "wof:name":"Tropiano Transportation",
    "wof:placetype":"venue"
},
  "geometry": {"coordinates":[-75.244202,40.2309],"type":"Point"}
}