{
  "type": "Feature",
  "properties": {
    "iso:country":"US",
    "sg:address":"134A Veterans Ln",
    "sg:city":"Doylestown",
    "sg:classifiers":[
        {
            "category":"Personal",
            "subcategory":"Beauty Salon",
            "type":"Services"
        },
        {
            "category":"Personal",
            "subcategory":"Barber",
            "type":"Services"
        },
        {
            "category":"Personal",
            "subcategory":"Tanning Parlor",
            "type":"Services"
        }
    ],
    "sg:phone":"+1 267 880 0521",
    "sg:postcode":"18901",
    "sg:province":"PA",
    "sg:tags":[
        "hair",
        "stylist"
    ],
    "wof:name":"Doylestown Haircutters",
    "wof:placetype":"venue"
},
  "geometry": {"coordinates":[-75.131765,40.319378],"type":"Point"}
}