{
  "type": "Feature",
  "properties": {
    "addr:full":"902 Peach Tree Dr Mechanicsburg PA 17055",
    "addr:housenumber":"902",
    "addr:postcode":"17055",
    "addr:street":"Peach Tree Dr",
    "iso:country":"US",
    "sg:address":"902 Peach Tree Dr",
    "sg:city":"Mechanicsburg",
    "sg:classifiers":[
        {
            "category":"Professional",
            "type":"Services"
        }
    ],
    "sg:phone":"+1   ",
    "sg:postcode":"17055",
    "sg:province":"PA",
    "wof:name":"Mybil Inc",
    "wof:placetype":"venue"
},
  "geometry": {"coordinates":[-77.01715900000001,40.199217],"type":"Point"}
}