{
  "type": "Feature",
  "properties": {
    "iso:country":"US",
    "sg:address":"504 Glade St",
    "sg:city":"Ellwood City",
    "sg:classifiers":[
        {
            "category":"Building & Trades",
            "subcategory":"Cleaning & Sanitation",
            "type":"Services"
        }
    ],
    "sg:phone":"+1 724 758 6255",
    "sg:postcode":"16117",
    "sg:province":"PA",
    "sg:tags":[
        "window"
    ],
    "wof:name":"Bob Steffler Window Cleaning",
    "wof:placetype":"venue"
},
  "geometry": {"coordinates":[-80.254628,40.854068],"type":"Point"}
}