{
  "type": "Feature",
  "properties": {
    "addr:full":"406 Oak St Old Forge PA 18518",
    "addr:housenumber":"406",
    "addr:postcode":"18518",
    "addr:street":"Oak St",
    "iso:country":"US",
    "sg:address":"406 Oak St",
    "sg:city":"Old Forge",
    "sg:classifiers":[
        {
            "category":"Personal",
            "subcategory":"Beauty Salon",
            "type":"Services"
        }
    ],
    "sg:phone":"+1 570 457 8819",
    "sg:postcode":"18518",
    "sg:province":"PA",
    "wof:name":"Dolores Beauty Shop",
    "wof:placetype":"venue"
},
  "geometry": {"coordinates":[-75.738224,41.373468],"type":"Point"}
}