{
  "type": "Feature",
  "properties": {
    "iso:country":"US",
    "sg:address":"1241 Blakeslee Boulevard Dr E",
    "sg:city":"Lehighton",
    "sg:classifiers":[
        {
            "category":"Shopping",
            "subcategory":"Musical Instruments",
            "type":"Retail Goods"
        }
    ],
    "sg:phone":"+1 570 386 2452",
    "sg:postcode":"18235",
    "sg:province":"PA",
    "sg:tags":[
        "music",
        "dealer"
    ],
    "wof:name":"Soundcheck Records Inc",
    "wof:placetype":"venue"
},
  "geometry": {"coordinates":[-75.72771400000001,40.818106],"type":"Point"}
}