{
  "type": "Feature",
  "properties": {
    "iso:country":"US",
    "sg:address":"1755 Oregon Pike",
    "sg:city":"Lancaster",
    "sg:classifiers":[
        {
            "category":"Health Services",
            "subcategory":"Health Practitioner",
            "type":"Services"
        }
    ],
    "sg:phone":"+1   ",
    "sg:postcode":"17601",
    "sg:province":"PA",
    "wof:name":"Heather Laird Beaudry PHD",
    "wof:placetype":"venue"
},
  "geometry": {"coordinates":[-76.30030600000001,40.071414],"type":"Point"}
}