{
  "type": "Feature",
  "properties": {
    "iso:country":"US",
    "sg:address":"142 Park City Center",
    "sg:city":"Lancaster",
    "sg:classifiers":[
        {
            "category":"Professional",
            "subcategory":"Management & Consulting",
            "type":"Services"
        }
    ],
    "sg:phone":"+1 717 290 6917",
    "sg:postcode":"17601",
    "sg:province":"PA",
    "sg:tags":[
        "consultant"
    ],
    "wof:name":"Weathervane Retail Store",
    "wof:placetype":"venue"
},
  "geometry": {"coordinates":[-76.340878,40.064696],"type":"Point"}
}