{
  "type": "Feature",
  "properties": {
    "iso:country":"US",
    "sg:address":"315 2nd Ave",
    "sg:city":"Warren",
    "sg:classifiers":[
        {
            "category":"Coffee & Tea",
            "type":"Food & Drink"
        },
        {
            "category":"Restaurant",
            "type":"Food & Drink"
        }
    ],
    "sg:phone":"+1 814 726 1863",
    "sg:postcode":"16365",
    "sg:province":"PA",
    "sg:tags":[
        "shop",
        "espresso"
    ],
    "wof:name":"The Point",
    "wof:placetype":"venue"
},
  "geometry": {"coordinates":[-79.14804100000001,41.844818],"type":"Point"}
}