{
  "type": "Feature",
  "properties": {
    "iso:country":"US",
    "sg:address":"1227 Tasker St",
    "sg:city":"Philadelphia",
    "sg:classifiers":[
        {
            "category":"Personal",
            "subcategory":"Beauty Salon",
            "type":"Services"
        }
    ],
    "sg:phone":"+1 215 463 3666",
    "sg:postcode":"19148",
    "sg:province":"PA",
    "wof:name":"Exquisite Cuts",
    "wof:placetype":"venue"
},
  "geometry": {"coordinates":[-75.166246,39.930206],"type":"Point"}
}