{
  "type": "Feature",
  "properties": {
    "iso:country":"US",
    "sg:address":"1229 Spruce St",
    "sg:city":"Philadelphia",
    "sg:classifiers":[
        {
            "category":"Restaurant",
            "type":"Food & Drink"
        }
    ],
    "sg:phone":"+1 215 790 9494",
    "sg:postcode":"19107",
    "sg:province":"PA",
    "sg:tags":[
        "american",
        "latin",
        "eating"
    ],
    "sg:website":"www.valanni.com",
    "wof:name":"Valanni Restaurant",
    "wof:placetype":"venue"
},
  "geometry": {"coordinates":[-75.16219100000001,39.946892],"type":"Point"}
}