{
  "type": "Feature",
  "properties": {
    "iso:country":"US",
    "sg:address":"633 Napoleon St",
    "sg:city":"Johnstown",
    "sg:classifiers":[
        {
            "category":"Science Facility",
            "type":"Public Place"
        }
    ],
    "sg:phone":"+1 814 262 7331",
    "sg:postcode":"15901",
    "sg:province":"PA",
    "sg:tags":[
        "development",
        "laboratories-research"
    ],
    "wof:name":"Itsi-Biosciences",
    "wof:placetype":"venue"
},
  "geometry": {"coordinates":[-78.918212,40.318484],"type":"Point"}
}