{
  "type": "Feature",
  "properties": {
    "addr:full":"18 College Park Apartment Shippensburg PA 17257",
    "addr:housenumber":"18",
    "addr:postcode":"17257",
    "addr:street":"College Park",
    "iso:country":"US",
    "sg:address":"18 College Park Apartment",
    "sg:city":"Shippensburg",
    "sg:classifiers":[
        {
            "category":"Real Estate",
            "subcategory":"Real Estate Operator",
            "type":"Services"
        }
    ],
    "sg:phone":"+1   ",
    "sg:postcode":"17257",
    "sg:province":"PA",
    "sg:tags":[
        "building",
        "apartment"
    ],
    "wof:name":"College Park Apartments",
    "wof:placetype":"venue"
},
  "geometry": {"coordinates":[-77.526534,40.062646],"type":"Point"}
}