{
  "type": "Feature",
  "properties": {
    "iso:country":"US",
    "sg:address":"14 Rosemont Ave",
    "sg:city":"Pittsburgh",
    "sg:classifiers":[
        {
            "category":"Shopping",
            "subcategory":"Used Merchandise",
            "type":"Retail Goods"
        }
    ],
    "sg:phone":"+1   ",
    "sg:postcode":"15228",
    "sg:province":"PA",
    "wof:name":"H & H Antiques",
    "wof:placetype":"venue"
},
  "geometry": {"coordinates":[-80.035636,40.38219],"type":"Point"}
}