{
  "type": "Feature",
  "properties": {
    "iso:country":"US",
    "sg:address":"221 Rogers Ln",
    "sg:city":"Wallingford",
    "sg:classifiers":[
        {
            "category":"Building & Trades",
            "subcategory":"Plumbing",
            "type":"Services"
        }
    ],
    "sg:phone":"+1 610 566 7600",
    "sg:postcode":"19086",
    "sg:province":"PA",
    "sg:tags":[
        "conditioning",
        "air",
        "system",
        "contractor"
    ],
    "sg:website":"www.wilsonoil.com",
    "wof:name":"Wilson Heating & Air Cond",
    "wof:placetype":"venue"
},
  "geometry": {"coordinates":[-75.367262,39.903628],"type":"Point"}
}