{
  "type": "Feature",
  "properties": {
    "addr:full":"1240 Scalp Ave Johnstown PA 15904",
    "addr:housenumber":"1240",
    "addr:postcode":"15904",
    "addr:street":"Scalp Ave",
    "iso:country":"US",
    "sg:address":"1240 Scalp Ave",
    "sg:city":"Johnstown",
    "sg:classifiers":[
        {
            "category":"Building & Trades",
            "subcategory":"Construction",
            "type":"Services"
        }
    ],
    "sg:phone":"+1   ",
    "sg:postcode":"15904",
    "sg:province":"PA",
    "sg:tags":[
        "contractor"
    ],
    "wof:name":"Merry Go Round Stain Glass Ctr",
    "wof:placetype":"venue"
},
  "geometry": {"coordinates":[-78.860923,40.277084],"type":"Point"}
}