{
  "type": "Feature",
  "properties": {
    "iso:country":"US",
    "sg:address":"442 Lincoln St",
    "sg:city":"York",
    "sg:classifiers":[
        {
            "category":"Real Estate",
            "subcategory":"Real Estate Services",
            "type":"Services"
        },
        {
            "category":"Building & Trades",
            "subcategory":"Cleaning & Sanitation",
            "type":"Services"
        }
    ],
    "sg:phone":"+1 717 845 9207",
    "sg:postcode":"17401",
    "sg:province":"PA",
    "sg:tags":[
        "maintenance",
        "cleaners-interior"
    ],
    "wof:name":"Mark Guillispee Efficient Contracting",
    "wof:placetype":"venue"
},
  "geometry": {"coordinates":[-76.742064,39.964193],"type":"Point"}
}