{
  "type": "Feature",
  "properties": {
    "iso:country":"US",
    "sg:address":"9 Llanberris Rd",
    "sg:city":"Bala Cynwyd",
    "sg:classifiers":[
        {
            "category":"Professional",
            "type":"Services"
        }
    ],
    "sg:phone":"+1   ",
    "sg:postcode":"19004",
    "sg:province":"PA",
    "wof:name":"Malenux Inc",
    "wof:placetype":"venue"
},
  "geometry": {"coordinates":[-75.22574299999999,40.00571],"type":"Point"}
}