{
  "type": "Feature",
  "properties": {
    "iso:country":"US",
    "sg:address":"551 Old Rte 68",
    "sg:city":"Evans City",
    "sg:classifiers":[
        {
            "category":"Retail",
            "subcategory":"Auto Repair",
            "type":"Services"
        }
    ],
    "sg:phone":"+1 724 789 7750",
    "sg:postcode":"16033",
    "sg:province":"PA",
    "sg:tags":[
        "repairing",
        "automobile"
    ],
    "wof:name":"Jeff's Auto Svc",
    "wof:placetype":"venue"
},
  "geometry": {"coordinates":[-80.018486,40.800247],"type":"Point"}
}