{
  "type": "Feature",
  "properties": {
    "iso:country":"US",
    "sg:address":"257 Center Ave",
    "sg:city":"Uniontown",
    "sg:classifiers":[
        {
            "category":"Professional",
            "type":"Services"
        }
    ],
    "sg:phone":"+1   ",
    "sg:postcode":"15401",
    "sg:province":"PA",
    "wof:name":"Lifetime Memory Makers",
    "wof:placetype":"venue"
},
  "geometry": {"coordinates":[-79.704217,39.916833],"type":"Point"}
}