{
  "type": "Feature",
  "properties": {
    "iso:country":"US",
    "sg:address":"6028 Penn Cir S",
    "sg:city":"Pittsburgh",
    "sg:classifiers":[
        {
            "category":"Building & Trades",
            "subcategory":"Cleaning & Sanitation",
            "type":"Services"
        }
    ],
    "sg:phone":"+1 412 441 8890",
    "sg:postcode":"15206",
    "sg:province":"PA",
    "sg:tags":[
        "janitor",
        "maintenance"
    ],
    "wof:name":"L R Custom Cleaning Services",
    "wof:placetype":"venue"
},
  "geometry": {"coordinates":[-79.924657,40.459969],"type":"Point"}
}