{
  "type": "Feature",
  "properties": {
    "iso:country":"US",
    "sg:address":"611 N Swarthmore Ave",
    "sg:city":"Ridley Park",
    "sg:classifiers":[
        {
            "category":"Retail",
            "subcategory":"Auto Repair",
            "type":"Services"
        }
    ],
    "sg:phone":"+1 610 521 3190",
    "sg:postcode":"19078",
    "sg:province":"PA",
    "sg:tags":[
        "body",
        "automotive",
        "work",
        "painting",
        "automobile"
    ],
    "wof:name":"Verone's Collision Inc",
    "wof:placetype":"venue"
},
  "geometry": {"coordinates":[-75.328436,39.88306],"type":"Point"}
}