{
  "type": "Feature",
  "properties": {
    "iso:country":"US",
    "sg:address":"27014 State Rte 77",
    "sg:city":"Guys Mills",
    "sg:classifiers":[
        {
            "category":"Manufacturing",
            "subcategory":"Tools & Machinery",
            "type":"Manufacturing & Wholesale Goods"
        }
    ],
    "sg:phone":"+1 814 967 3064",
    "sg:postcode":"16327",
    "sg:province":"PA",
    "sg:tags":[
        "die",
        "maker",
        "manufacturer"
    ],
    "wof:name":"Whitehead Tool & Design Inc",
    "wof:placetype":"venue"
},
  "geometry": {"coordinates":[-80.00718500000001,41.695845],"type":"Point"}
}