{
  "type": "Feature",
  "properties": {
    "iso:country":"US",
    "sg:address":"2030 Swamp Pike",
    "sg:city":"Gilbertsville",
    "sg:classifiers":[
        {
            "category":"Home & Garden",
            "subcategory":"Furniture",
            "type":"Retail Goods"
        }
    ],
    "sg:phone":"+1 484 945 0720",
    "sg:postcode":"19525",
    "sg:province":"PA",
    "wof:name":"Creative Home Furnishings Inc",
    "wof:placetype":"venue"
},
  "geometry": {"coordinates":[-75.584998,40.299272],"type":"Point"}
}