{
  "type": "Feature",
  "properties": {
    "addr:full":"1975 Trumbauersville Rd Quakertown PA 18951",
    "addr:housenumber":"1975",
    "addr:postcode":"18951",
    "addr:street":"Trumbauersville Rd",
    "iso:country":"US",
    "sg:address":"1975 Trumbauersville Rd",
    "sg:city":"Quakertown",
    "sg:classifiers":[
        {
            "category":"Wholesale",
            "subcategory":"Machinery & Supplies",
            "type":"Manufacturing & Wholesale Goods"
        }
    ],
    "sg:phone":"+1   ",
    "sg:postcode":"18951",
    "sg:province":"PA",
    "sg:tags":[
        "farm",
        "equipment"
    ],
    "wof:name":"Wonsidler C J Realtors",
    "wof:placetype":"venue"
},
  "geometry": {"coordinates":[-75.403504,40.40085],"type":"Point"}
}