{
  "type": "Feature",
  "properties": {
    "iso:country":"US",
    "sg:address":"103 Filbert St",
    "sg:city":"Curwensville",
    "sg:classifiers":[
        {
            "category":"Building & Trades",
            "subcategory":"Construction",
            "type":"Services"
        }
    ],
    "sg:phone":"+1 814 236 2244",
    "sg:postcode":"16833",
    "sg:province":"PA",
    "sg:tags":[
        "painter"
    ],
    "wof:name":"Curwensville Painters",
    "wof:placetype":"venue"
},
  "geometry": {"coordinates":[-78.526973,40.97284],"type":"Point"}
}