{
  "type": "Feature",
  "properties": {
    "iso:country":"US",
    "sg:address":"700 E Butler Ave",
    "sg:city":"Doylestown",
    "sg:classifiers":[
        {
            "category":"Education",
            "subcategory":"Special Training",
            "type":"Public Place"
        }
    ],
    "sg:phone":"+1 215 489 5359",
    "sg:postcode":"18901",
    "sg:province":"PA",
    "sg:tags":[
        "center"
    ],
    "wof:name":"Philadelphia Health Edu Corp",
    "wof:placetype":"venue"
},
  "geometry": {"coordinates":[-75.15697299999999,40.299517],"type":"Point"}
}