{
  "type": "Feature",
  "properties": {
    "addr:full":"208 E King St Malvern PA 19355",
    "addr:housenumber":"208",
    "addr:postcode":"19355",
    "addr:street":"E King St",
    "iso:country":"US",
    "sg:address":"208 E King St",
    "sg:city":"Malvern",
    "sg:classifiers":[
        {
            "category":"Home & Garden",
            "subcategory":"Building Materials",
            "type":"Retail Goods"
        },
        {
            "category":"Building & Trades",
            "subcategory":"Construction",
            "type":"Services"
        }
    ],
    "sg:phone":"+1 610 644 1334",
    "sg:postcode":"19355",
    "sg:province":"PA",
    "sg:tags":[
        "fence-sales",
        "contractor"
    ],
    "sg:website":"http://www.staydog.invisiblefence.com",
    "wof:name":"Stay Dog Invisible Fence",
    "wof:placetype":"venue"
},
  "geometry": {"coordinates":[-75.511915,40.036921],"type":"Point"}
}