{
  "type": "Feature",
  "properties": {
    "addr:full":"88 Sylvan Heights Dr Hollidaysburg PA 16648",
    "addr:housenumber":"88",
    "addr:postcode":"16648",
    "addr:street":"Sylvan Heights Dr",
    "iso:country":"US",
    "sg:address":"88 Sylvan Heights Dr",
    "sg:city":"Hollidaysburg",
    "sg:classifiers":[
        {
            "category":"Food & Beverages",
            "subcategory":"Liquor & Beverages",
            "type":"Retail Goods"
        }
    ],
    "sg:phone":"+1   ",
    "sg:postcode":"16648",
    "sg:province":"PA",
    "sg:tags":[
        "alcoholic"
    ],
    "wof:name":"JD Beer Store Inc",
    "wof:placetype":"venue"
},
  "geometry": {"coordinates":[-78.382419,40.453369],"type":"Point"}
}