{
  "type": "Feature",
  "properties": {
    "addr:full":"1760 Pine Hollow Rd Mc Kees Rocks PA 15136",
    "addr:housenumber":"1760",
    "addr:postcode":"15136",
    "addr:street":"Pine Hollow Rd;Kees Rocks",
    "iso:country":"US",
    "sg:address":"1760 Pine Hollow Rd",
    "sg:city":"Mc Kees Rocks",
    "sg:classifiers":[
        {
            "category":"Organizations",
            "subcategory":"Religious Organization",
            "type":"Services"
        }
    ],
    "sg:phone":"+1 412 331 2863",
    "sg:postcode":"15136",
    "sg:province":"PA",
    "sg:tags":[
        "church"
    ],
    "wof:name":"Ken Mawr United Presbyterian",
    "wof:placetype":"venue"
},
  "geometry": {"coordinates":[-80.100835,40.476296],"type":"Point"}
}