{
  "type": "Feature",
  "properties": {
    "iso:country":"US",
    "sg:address":"1721 Weavertown Rd",
    "sg:city":"Lebanon",
    "sg:classifiers":[
        {
            "category":"Building & Trades",
            "subcategory":"Construction",
            "type":"Services"
        }
    ],
    "sg:phone":"+1   ",
    "sg:postcode":"17046",
    "sg:province":"PA",
    "sg:tags":[
        "house"
    ],
    "wof:name":"J M Construction",
    "wof:placetype":"venue"
},
  "geometry": {"coordinates":[-76.391637,40.356811],"type":"Point"}
}