{
  "type": "Feature",
  "properties": {
    "addr:full":"1020 Blakeslee Boulevard Dr E Lehighton PA 18235",
    "addr:housenumber":"1020",
    "addr:postcode":"18235",
    "addr:street":"Blakeslee Boulevard Dr E",
    "iso:country":"US",
    "sg:address":"1020 Blakeslee Boulevard Dr E",
    "sg:city":"Lehighton",
    "sg:classifiers":[
        {
            "category":"Utilities",
            "subcategory":"Mobile Phone",
            "type":"Services"
        }
    ],
    "sg:phone":"+1 610 377 4535",
    "sg:postcode":"18235",
    "sg:province":"PA",
    "sg:tags":[
        "telephone",
        "cellular"
    ],
    "wof:name":"Cingular Wireless",
    "wof:placetype":"venue"
},
  "geometry": {"coordinates":[-75.728374,40.81788],"type":"Point"}
}