{
  "type": "Feature",
  "properties": {
    "iso:country":"US",
    "sg:address":"14 Market Pl",
    "sg:city":"New Hope",
    "sg:classifiers":[
        {
            "category":"Health Services",
            "subcategory":"Chiropractor",
            "type":"Services"
        }
    ],
    "sg:phone":"+1 215 862 1400",
    "sg:postcode":"18938",
    "sg:province":"PA",
    "wof:name":"Wolf Janet DC",
    "wof:placetype":"venue"
},
  "geometry": {"coordinates":[-74.976601,40.3582],"type":"Point"}
}