{
  "type": "Feature",
  "properties": {
    "addr:full":"2070 Bennet Ave Lancaster PA 17601",
    "addr:postcode":"2070;17601",
    "addr:street":"Bennet Ave",
    "iso:country":"US",
    "sg:address":"2070 Bennet Ave",
    "sg:city":"Lancaster",
    "sg:classifiers":[
        {
            "category":"Building & Trades",
            "subcategory":"Construction",
            "type":"Services"
        }
    ],
    "sg:phone":"+1   ",
    "sg:postcode":"17601",
    "sg:province":"PA",
    "sg:tags":[
        "house"
    ],
    "wof:name":"Yorktown Kitchens",
    "wof:placetype":"venue"
},
  "geometry": {"coordinates":[-76.357615,40.059848],"type":"Point"}
}