{
  "type": "Feature",
  "properties": {
    "addr:full":"1332 Delta Rd Red Lion PA 17356",
    "addr:housenumber":"1332",
    "addr:postcode":"17356",
    "addr:street":"Delta Rd",
    "iso:country":"US",
    "sg:address":"1332 Delta Rd",
    "sg:city":"Red Lion",
    "sg:classifiers":[
        {
            "category":"Building & Trades",
            "subcategory":"Construction",
            "type":"Services"
        }
    ],
    "sg:phone":"+1 717 244 2855",
    "sg:postcode":"17356",
    "sg:province":"PA",
    "sg:tags":[
        "painting",
        "contractor"
    ],
    "wof:name":"Red Lion Spray Inc",
    "wof:placetype":"venue"
},
  "geometry": {"coordinates":[-76.54428,39.884939],"type":"Point"}
}