{
  "type": "Feature",
  "properties": {
    "iso:country":"US",
    "sg:address":"150 Brooklyn St",
    "sg:city":"Carbondale",
    "sg:classifiers":[
        {
            "category":"Health Services",
            "subcategory":"Doctor",
            "type":"Services"
        }
    ],
    "sg:phone":"+1   ",
    "sg:postcode":"18407",
    "sg:province":"PA",
    "sg:tags":[
        "osteopathic"
    ],
    "wof:name":"Dzielak Edward J Do",
    "wof:placetype":"venue"
},
  "geometry": {"coordinates":[-75.51760400000001,41.565409],"type":"Point"}
}