{
  "type": "Feature",
  "properties": {
    "addr:full":"103 S Spring St Bellefonte PA 16823",
    "addr:housenumber":"103",
    "addr:postcode":"16823",
    "addr:street":"S Spring St",
    "iso:country":"US",
    "sg:address":"103 S Spring St",
    "sg:city":"Bellefonte",
    "sg:classifiers":[
        {
            "category":"Social Services",
            "type":"Services"
        }
    ],
    "sg:phone":"+1   ",
    "sg:postcode":"16823",
    "sg:province":"PA",
    "wof:name":"Spaw Counseling Services",
    "wof:placetype":"venue"
},
  "geometry": {"coordinates":[-77.779657,40.911588],"type":"Point"}
}