{
  "type": "Feature",
  "properties": {
    "iso:country":"US",
    "sg:address":"232 Broad St",
    "sg:city":"New Bethlehem",
    "sg:classifiers":[
        {
            "category":"Real Estate",
            "subcategory":"Real Estate Agent",
            "type":"Services"
        }
    ],
    "sg:phone":"+1 814 275 2497",
    "sg:postcode":"16242",
    "sg:province":"PA",
    "wof:name":"Pat Merwin Realty",
    "wof:placetype":"venue"
},
  "geometry": {"coordinates":[-79.339945,41.000077],"type":"Point"}
}