{
  "type": "Feature",
  "properties": {
    "iso:country":"US",
    "sg:address":"662 N Main St",
    "sg:city":"Greensburg",
    "sg:classifiers":[
        {
            "category":"Wholesale",
            "subcategory":"Non-durable Goods",
            "type":"Manufacturing & Wholesale Goods"
        }
    ],
    "sg:phone":"+1   ",
    "sg:postcode":"15601",
    "sg:province":"PA",
    "sg:tags":[
        "advertising",
        "specialty"
    ],
    "wof:name":"Premier Promotional Solutions",
    "wof:placetype":"venue"
},
  "geometry": {"coordinates":[-79.548374,40.314765],"type":"Point"}
}