{
  "type": "Feature",
  "properties": {
    "addr:full":"4870 McKnight Rd Pittsburgh PA 15237",
    "addr:housenumber":"4870",
    "addr:postcode":"15237",
    "addr:street":"Mcknight Rd",
    "iso:country":"US",
    "sg:address":"4870 McKnight Rd",
    "sg:city":"Pittsburgh",
    "sg:classifiers":[
        {
            "category":"Shopping",
            "subcategory":"Pharmacy",
            "type":"Retail Goods"
        }
    ],
    "sg:phone":"+1 412 364 8100",
    "sg:postcode":"15237",
    "sg:province":"PA",
    "sg:tags":[
        "drug",
        "store"
    ],
    "wof:name":"Berkeley Hills Pharmacy",
    "wof:placetype":"venue"
},
  "geometry": {"coordinates":[-80.005442,40.525433],"type":"Point"}
}