{
  "type": "Feature",
  "properties": {
    "addr:full":"8 Atkinson Dr Doylestown PA 18901",
    "addr:housenumber":"8",
    "addr:postcode":"18901",
    "addr:street":"Atkinson Dr",
    "iso:country":"US",
    "sg:address":"8 Atkinson Dr",
    "sg:city":"Doylestown",
    "sg:classifiers":[
        {
            "category":"Government",
            "subcategory":"Post Office",
            "type":"Public Place"
        }
    ],
    "sg:phone":"+1 267 880 3918",
    "sg:postcode":"18901",
    "sg:province":"PA",
    "wof:name":"US Post Office",
    "wof:placetype":"venue"
},
  "geometry": {"coordinates":[-75.131816,40.31907],"type":"Point"}
}