{
  "type": "Feature",
  "properties": {
    "addr:full":"345 High Rock Rd W Hanover PA 17331",
    "addr:housenumber":"345",
    "addr:postcode":"17331",
    "addr:street":"High Rock Rd W",
    "iso:country":"US",
    "sg:address":"345 High Rock Rd W",
    "sg:city":"Hanover",
    "sg:classifiers":[
        {
            "category":"Building & Trades",
            "subcategory":"Equipment Rental",
            "type":"Services"
        }
    ],
    "sg:phone":"+1 717 633 6444",
    "sg:postcode":"17331",
    "sg:province":"PA",
    "sg:tags":[
        "crane"
    ],
    "wof:name":"Boomin Inc",
    "wof:placetype":"venue"
},
  "geometry": {"coordinates":[-76.95473699999999,39.859839],"type":"Point"}
}