{
  "type": "Feature",
  "properties": {
    "iso:country":"US",
    "sg:address":"1545 Wayne Ave",
    "sg:city":"Indiana",
    "sg:classifiers":[
        {
            "category":"Travel",
            "subcategory":"Hotels & Motels",
            "type":"Entertainment"
        }
    ],
    "sg:phone":"+1 724 349 9620",
    "sg:postcode":"15701",
    "sg:province":"PA",
    "wof:name":"Best Western Inn",
    "wof:placetype":"venue"
},
  "geometry": {"coordinates":[-79.16153199999999,40.589017],"type":"Point"}
}