{
  "type": "Feature",
  "properties": {
    "iso:country":"US",
    "sg:address":"110 N Main St",
    "sg:city":"Greenville",
    "sg:classifiers":[
        {
            "category":"Health Services",
            "subcategory":"Health Practitioner",
            "type":"Services"
        }
    ],
    "sg:phone":"+1   ",
    "sg:postcode":"16125",
    "sg:province":"PA",
    "wof:name":"Occupational Medicine",
    "wof:placetype":"venue"
},
  "geometry": {"coordinates":[-80.372056,41.411231],"type":"Point"}
}