{
  "type": "Feature",
  "properties": {
    "addr:full":"222 Northern Blvd Clarks Summit PA 18411",
    "addr:housenumber":"222",
    "addr:postcode":"18411",
    "addr:street":"Northern Blvd",
    "iso:country":"US",
    "sg:address":"222 Northern Blvd",
    "sg:city":"Clarks Summit",
    "sg:classifiers":[
        {
            "category":"Shopping",
            "subcategory":"Jewelry",
            "type":"Retail Goods"
        }
    ],
    "sg:phone":"+1   ",
    "sg:postcode":"18411",
    "sg:province":"PA",
    "wof:name":"Tokens",
    "wof:placetype":"venue"
},
  "geometry": {"coordinates":[-75.668634,41.466557],"type":"Point"}
}