{
  "type": "Feature",
  "properties": {
    "iso:country":"US",
    "sg:address":"347 Village Walk Dr",
    "sg:city":"Macungie",
    "sg:classifiers":[
        {
            "category":"Professional",
            "type":"Services"
        }
    ],
    "sg:phone":"+1   ",
    "sg:postcode":"18062",
    "sg:province":"PA",
    "wof:name":"Stephen T Mould",
    "wof:placetype":"venue"
},
  "geometry": {"coordinates":[-75.558291,40.519208],"type":"Point"}
}