{
  "type": "Feature",
  "properties": {
    "iso:country":"US",
    "sg:address":"15795 Cumberland Hwy",
    "sg:city":"Newburg",
    "sg:classifiers":[
        {
            "category":"Building & Trades",
            "subcategory":"Construction",
            "type":"Services"
        }
    ],
    "sg:phone":"+1   ",
    "sg:postcode":"17240",
    "sg:province":"PA",
    "sg:tags":[
        "house"
    ],
    "wof:name":"Harold L Bard",
    "wof:placetype":"venue"
},
  "geometry": {"coordinates":[-77.65724899999999,40.114862],"type":"Point"}
}