{
  "type": "Feature",
  "properties": {
    "addr:full":"2600 Philmont Ave Huntingdon Vly PA 19006",
    "addr:housenumber":"2600",
    "addr:postcode":"19006",
    "addr:street":"Philmont Ave",
    "iso:country":"US",
    "sg:address":"2600 Philmont Ave",
    "sg:city":"Huntingdon Vly",
    "sg:classifiers":[
        {
            "category":"Professional",
            "subcategory":"Engineering",
            "type":"Services"
        },
        {
            "category":"Manufacturing",
            "subcategory":"Metals",
            "type":"Manufacturing & Wholesale Goods"
        }
    ],
    "sg:phone":"+1 215 938 7748",
    "sg:postcode":"19006",
    "sg:province":"PA",
    "sg:tags":[
        "refractory",
        "mfg",
        "heating",
        "equipment",
        "clay",
        "engineer"
    ],
    "wof:name":"Bloom Engineering Company Inc",
    "wof:placetype":"venue"
},
  "geometry": {"coordinates":[-75.05150399999999,40.121964],"type":"Point"}
}