{
  "type": "Feature",
  "properties": {
    "iso:country":"US",
    "sg:address":"106 Maple Ave",
    "sg:city":"Marysville",
    "sg:classifiers":[
        {
            "category":"Organizations",
            "subcategory":"Religious Organization",
            "type":"Services"
        }
    ],
    "sg:phone":"+1 717 957 2730",
    "sg:postcode":"17053",
    "sg:province":"PA",
    "sg:tags":[
        "church"
    ],
    "wof:name":"Marysville Church Of God",
    "wof:placetype":"venue"
},
  "geometry": {"coordinates":[-76.931501,40.344015],"type":"Point"}
}