{
  "type": "Feature",
  "properties": {
    "iso:country":"US",
    "sg:address":"4711 Kutztown Rd",
    "sg:city":"Temple",
    "sg:classifiers":[
        {
            "category":"Building & Trades",
            "subcategory":"Plumbing",
            "type":"Services"
        }
    ],
    "sg:phone":"+1 610 929 8666",
    "sg:postcode":"19560",
    "sg:province":"PA",
    "sg:tags":[
        "boiler",
        "cleaning"
    ],
    "sg:website":"www.harjanmechanical.com",
    "wof:name":"Har-Jan Mechanical",
    "wof:placetype":"venue"
},
  "geometry": {"coordinates":[-75.920029,40.406498],"type":"Point"}
}