{
  "type": "Feature",
  "properties": {
    "addr:full":"1202 Elk St Franklin PA 16323",
    "addr:housenumber":"1202",
    "addr:postcode":"16323",
    "addr:street":"Elk St",
    "iso:country":"US",
    "sg:address":"1202 Elk St",
    "sg:city":"Franklin",
    "sg:classifiers":[
        {
            "category":"Government",
            "subcategory":"Post Office",
            "type":"Public Place"
        }
    ],
    "sg:phone":"+1 814 432 4018",
    "sg:postcode":"16323",
    "sg:province":"PA",
    "sg:tags":[
        "postal",
        "us"
    ],
    "wof:name":"US Post Office",
    "wof:placetype":"venue"
},
  "geometry": {"coordinates":[-79.82897800000001,41.398729],"type":"Point"}
}