{
  "type": "Feature",
  "properties": {
    "addr:full":"518 Waldron Park Dr Haverford PA 19041",
    "addr:housenumber":"518",
    "addr:postcode":"19041",
    "addr:street":"Waldron Park Dr",
    "iso:country":"US",
    "sg:address":"518 Waldron Park Dr",
    "sg:city":"Haverford",
    "sg:classifiers":[
        {
            "category":"Professional",
            "subcategory":"Management & Consulting",
            "type":"Services"
        }
    ],
    "sg:phone":"+1   ",
    "sg:postcode":"19041",
    "sg:province":"PA",
    "sg:tags":[
        "marketing"
    ],
    "wof:name":"Gross Stan Associates Inc",
    "wof:placetype":"venue"
},
  "geometry": {"coordinates":[-75.287888,40.022647],"type":"Point"}
}