{
  "type": "Feature",
  "properties": {
    "iso:country":"US",
    "sg:address":"5 Nottingham Ln",
    "sg:city":"Horsham",
    "sg:classifiers":[
        {
            "category":"Professional",
            "type":"Services"
        }
    ],
    "sg:phone":"+1   ",
    "sg:postcode":"19044",
    "sg:province":"PA",
    "wof:name":"Little Legue Baseball Inc",
    "wof:placetype":"venue"
},
  "geometry": {"coordinates":[-75.175389,40.183748],"type":"Point"}
}