{
  "type": "Feature",
  "properties": {
    "iso:country":"US",
    "sg:address":"3908 Kensington Ave",
    "sg:city":"Philadelphia",
    "sg:classifiers":[
        {
            "category":"Cinema",
            "subcategory":"Movie Rental",
            "type":"Entertainment"
        },
        {
            "category":"Banks & Credit Unions",
            "subcategory":"Investment Brokerage",
            "type":"Services"
        }
    ],
    "sg:phone":"+1 215 533 5266",
    "sg:postcode":"19124",
    "sg:province":"PA",
    "sg:tags":[
        "leasing",
        "sale",
        "dvds-rental",
        "tape",
        "video",
        "games-renting"
    ],
    "wof:name":"Blockbuster",
    "wof:placetype":"venue"
},
  "geometry": {"coordinates":[-75.09623000000001,40.005926],"type":"Point"}
}