{
  "type": "Feature",
  "properties": {
    "iso:country":"US",
    "sg:address":"23 Turner Ln",
    "sg:city":"West Chester",
    "sg:classifiers":[
        {
            "category":"Professional",
            "type":"Services"
        }
    ],
    "sg:phone":"+1   ",
    "sg:postcode":"19380",
    "sg:province":"PA",
    "wof:name":"Bechtle & Ryan",
    "wof:placetype":"venue"
},
  "geometry": {"coordinates":[-75.587322,39.968082],"type":"Point"}
}