{
  "type": "Feature",
  "properties": {
    "iso:country":"US",
    "sg:address":"1831 Chestnut St Ste 100",
    "sg:city":"Philadelphia",
    "sg:classifiers":[
        {
            "category":"Health Services",
            "subcategory":"Dentist",
            "type":"Services"
        }
    ],
    "sg:phone":"+1 215 557 9889",
    "sg:postcode":"19103",
    "sg:province":"PA",
    "sg:tags":[
        "clinic",
        "dental"
    ],
    "wof:name":"Ford Helen Dds",
    "wof:placetype":"venue"
},
  "geometry": {"coordinates":[-75.170833,39.951721],"type":"Point"}
}