{
  "type": "Feature",
  "properties": {
    "addr:full":"537 Sumner Ct Allentown PA 18102",
    "addr:housenumber":"537",
    "addr:postcode":"18102",
    "addr:street":"Sumner Ct",
    "iso:country":"US",
    "sg:address":"537 Sumner Ct",
    "sg:city":"Allentown",
    "sg:classifiers":[
        {
            "category":"Building & Trades",
            "subcategory":"Construction",
            "type":"Services"
        }
    ],
    "sg:phone":"+1 610 433 2876",
    "sg:postcode":"18102",
    "sg:province":"PA",
    "sg:tags":[
        "painter"
    ],
    "sg:website":"www.parkwaypainting.com",
    "wof:name":"Parkway Painting Inc",
    "wof:placetype":"venue"
},
  "geometry": {"coordinates":[-75.47564199999999,40.617197],"type":"Point"}
}