{
  "type": "Feature",
  "properties": {
    "addr:full":"1701 Albert St New Castle PA 16105",
    "addr:housenumber":"1701",
    "addr:postcode":"16105",
    "addr:street":"Albert St",
    "iso:country":"US",
    "sg:address":"1701 Albert St",
    "sg:city":"New Castle",
    "sg:classifiers":[
        {
            "category":"Education",
            "subcategory":"School",
            "type":"Public Place"
        }
    ],
    "sg:phone":"+1 724 658 5858",
    "sg:postcode":"16105",
    "sg:province":"PA",
    "wof:name":"New Castle Christian Academy",
    "wof:placetype":"venue"
},
  "geometry": {"coordinates":[-80.340424,41.019556],"type":"Point"}
}