{
  "type": "Feature",
  "properties": {
    "iso:country":"US",
    "sg:address":"69 W End Blvd",
    "sg:city":"Quakertown",
    "sg:classifiers":[
        {
            "category":"Restaurant",
            "type":"Food & Drink"
        }
    ],
    "sg:phone":"+1 215 529 7111",
    "sg:postcode":"18951",
    "sg:province":"PA",
    "sg:tags":[
        "eating"
    ],
    "sg:website":"www.bostonmarket.com",
    "wof:name":"Boston Market",
    "wof:placetype":"venue"
},
  "geometry": {"coordinates":[-75.351698,40.431471],"type":"Point"}
}