{
  "type": "Feature",
  "properties": {
    "addr:full":"2242 Sanatoga Station Rd Pottstown PA 19464",
    "addr:housenumber":"2242",
    "addr:postcode":"19464",
    "addr:street":"Sanatoga Station Rd",
    "iso:country":"US",
    "sg:address":"2242 Sanatoga Station Rd",
    "sg:city":"Pottstown",
    "sg:classifiers":[
        {
            "category":"Real Estate",
            "subcategory":"Real Estate Agent",
            "type":"Services"
        }
    ],
    "sg:phone":"+1 610 323 4500",
    "sg:postcode":"19464",
    "sg:province":"PA",
    "wof:name":"Mahr Realty",
    "wof:placetype":"venue"
},
  "geometry": {"coordinates":[-75.60874200000001,40.238628],"type":"Point"}
}