{
  "type": "Feature",
  "properties": {
    "addr:full":"16046 Mountain Green Rd Spring Run PA 17262",
    "addr:housenumber":"16046",
    "addr:postcode":"17262",
    "addr:street":"Mountain Green Rd",
    "iso:country":"US",
    "sg:address":"16046 Mountain Green Rd",
    "sg:city":"Spring Run",
    "sg:classifiers":[
        {
            "category":"Professional",
            "subcategory":"Accounting & Tax Preparation",
            "type":"Services"
        }
    ],
    "sg:phone":"+1 717 349 2191",
    "sg:postcode":"17262",
    "sg:province":"PA",
    "sg:tags":[
        "consultant"
    ],
    "wof:name":"Mts Tax",
    "wof:placetype":"venue"
},
  "geometry": {"coordinates":[-77.78811899999999,40.135123],"type":"Point"}
}