{
  "type": "Feature",
  "properties": {
    "addr:full":"352 Farnum Rd Media PA 19063",
    "addr:housenumber":"352",
    "addr:postcode":"19063",
    "addr:street":"Farnum Rd",
    "iso:country":"US",
    "sg:address":"352 Farnum Rd",
    "sg:city":"Media",
    "sg:classifiers":[
        {
            "category":"Banks & Credit Unions",
            "subcategory":"Financial Services",
            "type":"Services"
        }
    ],
    "sg:phone":"+1 610 627 1774",
    "sg:postcode":"19063",
    "sg:province":"PA",
    "sg:tags":[
        "investment",
        "closed"
    ],
    "wof:name":"Farnum Trading Group",
    "wof:placetype":"venue"
},
  "geometry": {"coordinates":[-75.38164399999999,39.92249],"type":"Point"}
}