{
  "type": "Feature",
  "properties": {
    "iso:country":"US",
    "sg:address":"1211 Bridge St",
    "sg:city":"Rockwood",
    "sg:classifiers":[
        {
            "category":"Bars & Pubs",
            "type":"Food & Drink"
        }
    ],
    "sg:phone":"+1 814 926 3380",
    "sg:postcode":"15557",
    "sg:province":"PA",
    "wof:name":"Tin's Tavern",
    "wof:placetype":"venue"
},
  "geometry": {"coordinates":[-79.159925,39.911885],"type":"Point"}
}