{
  "type": "Feature",
  "properties": {
    "iso:country":"US",
    "sg:address":"200 Barton St",
    "sg:city":"Bloomsburg",
    "sg:classifiers":[
        {
            "category":"Social Services",
            "subcategory":"Child Care",
            "type":"Services"
        }
    ],
    "sg:phone":"+1 570 784 9282",
    "sg:postcode":"17815",
    "sg:province":"PA",
    "sg:tags":[
        "school",
        "day"
    ],
    "wof:name":"Magic Carpet Pre-School",
    "wof:placetype":"venue"
},
  "geometry": {"coordinates":[-76.467162,40.998463],"type":"Point"}
}