{
  "type": "Feature",
  "properties": {
    "iso:country":"US",
    "sg:address":"201 Shadeland Ave",
    "sg:city":"Lansdowne",
    "sg:classifiers":[
        {
            "category":"Food & Beverages",
            "subcategory":"Bakery",
            "type":"Retail Goods"
        }
    ],
    "sg:phone":"+1 610 259 4000",
    "sg:postcode":"19050",
    "sg:province":"PA",
    "wof:name":"My Old Place Bakery",
    "wof:placetype":"venue"
},
  "geometry": {"coordinates":[-75.28845,39.940839],"type":"Point"}
}