{
  "type": "Feature",
  "properties": {
    "addr:full":"220 New Castle Rd Butler PA 16001",
    "addr:housenumber":"220",
    "addr:postcode":"16001",
    "addr:street":"New Castle Rd",
    "iso:country":"US",
    "sg:address":"220 New Castle Rd",
    "sg:city":"Butler",
    "sg:classifiers":[
        {
            "category":"Organizations",
            "subcategory":"Religious Organization",
            "type":"Services"
        }
    ],
    "sg:phone":"+1 724 285 8641",
    "sg:postcode":"16001",
    "sg:province":"PA",
    "sg:tags":[
        "church"
    ],
    "wof:name":"Grace Lutheran Church",
    "wof:placetype":"venue"
},
  "geometry": {"coordinates":[-79.931748,40.870618],"type":"Point"}
}