{
  "type": "Feature",
  "properties": {
    "addr:full":"2502 S Broad St Philadelphia PA 19145",
    "addr:housenumber":"2502",
    "addr:postcode":"19145",
    "addr:street":"S Broad St",
    "iso:country":"US",
    "sg:address":"2502 S Broad St",
    "sg:city":"Philadelphia",
    "sg:classifiers":[
        {
            "category":"Personal",
            "subcategory":"Nail Salon",
            "type":"Services"
        }
    ],
    "sg:phone":"+1 215 271 9831",
    "sg:postcode":"19145",
    "sg:province":"PA",
    "wof:name":"Philly's Nail Salon",
    "wof:placetype":"venue"
},
  "geometry": {"coordinates":[-75.170799,39.919399],"type":"Point"}
}