{
  "type": "Feature",
  "properties": {
    "addr:full":"102 W Bridge St Morrisville PA 19067",
    "addr:housenumber":"102",
    "addr:postcode":"19067",
    "addr:street":"W Bridge St",
    "iso:country":"US",
    "sg:address":"102 W Bridge St",
    "sg:city":"Morrisville",
    "sg:classifiers":[
        {
            "category":"Wholesale",
            "subcategory":"Vending Machines",
            "type":"Manufacturing & Wholesale Goods"
        }
    ],
    "sg:phone":"+1 215 295 1285",
    "sg:postcode":"19067",
    "sg:province":"PA",
    "wof:name":"Borden's Home Amusements",
    "wof:placetype":"venue"
},
  "geometry": {"coordinates":[-74.778049,40.206911],"type":"Point"}
}