{
  "type": "Feature",
  "properties": {
    "iso:country":"US",
    "sg:address":"916 Egypt Rd",
    "sg:city":"Woodland",
    "sg:classifiers":[
        {
            "category":"Building & Trades",
            "subcategory":"Construction",
            "type":"Services"
        }
    ],
    "sg:phone":"+1 814 857 7905",
    "sg:postcode":"16881",
    "sg:province":"PA",
    "sg:tags":[
        "contractor"
    ],
    "wof:name":"Quality Masonry",
    "wof:placetype":"venue"
},
  "geometry": {"coordinates":[-78.329324,41.037196],"type":"Point"}
}