{
  "type": "Feature",
  "properties": {
    "iso:country":"US",
    "sg:address":"682 Northampton St",
    "sg:city":"Easton",
    "sg:classifiers":[
        {
            "category":"Organizations",
            "subcategory":"Membership Organization",
            "type":"Services"
        }
    ],
    "sg:phone":"+1   ",
    "sg:postcode":"18042",
    "sg:province":"PA",
    "wof:name":"Amvets World War II Post 17",
    "wof:placetype":"venue"
},
  "geometry": {"coordinates":[-75.217474,40.690768],"type":"Point"}
}