{
  "type": "Feature",
  "properties": {
    "iso:country":"US",
    "sg:address":"30 Euclid Ave",
    "sg:city":"Uniontown",
    "sg:classifiers":[
        {
            "category":"Organizations",
            "subcategory":"Religious Organization",
            "type":"Services"
        }
    ],
    "sg:phone":"+1   ",
    "sg:postcode":"15401",
    "sg:province":"PA",
    "wof:name":"James Methodist Church",
    "wof:placetype":"venue"
},
  "geometry": {"coordinates":[-79.71118,39.900727],"type":"Point"}
}