{
  "type": "Feature",
  "properties": {
    "addr:full":"111 Westinghouse Ave Wilmerding PA 15148",
    "addr:housenumber":"111",
    "addr:postcode":"15148",
    "addr:street":"Westinghouse Ave",
    "iso:country":"US",
    "sg:address":"111 Westinghouse Ave",
    "sg:city":"Wilmerding",
    "sg:classifiers":[
        {
            "category":"Banks & Credit Unions",
            "subcategory":"Bank",
            "type":"Services"
        }
    ],
    "sg:phone":"+1 412 824 1070",
    "sg:postcode":"15148",
    "sg:province":"PA",
    "sg:tags":[
        "commercial",
        "saving"
    ],
    "sg:website":"www.compassfederal.com",
    "wof:name":"Compass Savings Bank",
    "wof:placetype":"venue"
},
  "geometry": {"coordinates":[-79.809701,40.393211],"type":"Point"}
}