{
  "type": "Feature",
  "properties": {
    "iso:country":"US",
    "sg:address":"177 Mc Connell Dr",
    "sg:city":"Portersville",
    "sg:classifiers":[
        {
            "category":"Retail",
            "subcategory":"Veterinary Services",
            "type":"Services"
        }
    ],
    "sg:phone":"+1   ",
    "sg:postcode":"16001",
    "sg:province":"PA",
    "wof:name":"Silver Spring Equine",
    "wof:placetype":"venue"
},
  "geometry": {"coordinates":[-79.994291,40.88728],"type":"Point"}
}