{
  "type": "Feature",
  "properties": {
    "iso:country":"US",
    "sg:address":"530 S 60th St",
    "sg:city":"Philadelphia",
    "sg:classifiers":[
        {
            "category":"Food & Beverages",
            "subcategory":"Groceries & Convenience Stores",
            "type":"Retail Goods"
        }
    ],
    "sg:phone":"+1 215 748 0178",
    "sg:postcode":"19143",
    "sg:province":"PA",
    "sg:tags":[
        "grocer"
    ],
    "wof:name":"Family Grocery",
    "wof:placetype":"venue"
},
  "geometry": {"coordinates":[-75.24256099999999,39.953858],"type":"Point"}
}