{
  "type": "Feature",
  "properties": {
    "addr:full":"830 Norman Dr Lebanon PA 17042",
    "addr:housenumber":"830",
    "addr:postcode":"17042",
    "addr:street":"Norman Dr",
    "iso:country":"US",
    "sg:address":"830 Norman Dr",
    "sg:city":"Lebanon",
    "sg:classifiers":[
        {
            "category":"Banks & Credit Unions",
            "subcategory":"Bank",
            "type":"Services"
        }
    ],
    "sg:phone":"+1 717 675 2100",
    "sg:postcode":"17042",
    "sg:province":"PA",
    "wof:name":"Bank Of Lebanon County",
    "wof:placetype":"venue"
},
  "geometry": {"coordinates":[-76.416048,40.31342],"type":"Point"}
}