{
  "type": "Feature",
  "properties": {
    "iso:country":"US",
    "sg:address":"106 Sarah Dr",
    "sg:city":"Altoona",
    "sg:classifiers":[
        {
            "category":"Restaurant",
            "type":"Food & Drink"
        }
    ],
    "sg:phone":"+1 814 941 4502",
    "sg:postcode":"16601",
    "sg:province":"PA",
    "sg:tags":[
        "eating"
    ],
    "wof:name":"Ruby Tuesday",
    "wof:placetype":"venue"
},
  "geometry": {"coordinates":[-78.34335799999999,40.571074],"type":"Point"}
}