{
  "type": "Feature",
  "properties": {
    "iso:country":"US",
    "sg:address":"348 Market St",
    "sg:city":"Williamsport",
    "sg:classifiers":[
        {
            "category":"Organizations",
            "subcategory":"Community Association",
            "type":"Services"
        }
    ],
    "sg:phone":"+1 570 323 6194",
    "sg:postcode":"17701",
    "sg:province":"PA",
    "sg:tags":[
        "fraternal"
    ],
    "wof:name":"Williamsport Scottish Rite",
    "wof:placetype":"venue"
},
  "geometry": {"coordinates":[-77.00184400000001,41.242198],"type":"Point"}
}