{
  "type": "Feature",
  "properties": {
    "iso:country":"US",
    "sg:address":"6139 Germantown Ave",
    "sg:city":"Philadelphia",
    "sg:classifiers":[
        {
            "category":"Social Services",
            "type":"Services"
        }
    ],
    "sg:phone":"+1 215 843 2115",
    "sg:postcode":"19144",
    "sg:province":"PA",
    "sg:tags":[
        "individual",
        "crisis",
        "family",
        "intervention"
    ],
    "wof:name":"Center For Arson Research",
    "wof:placetype":"venue"
},
  "geometry": {"coordinates":[-75.17966,40.041705],"type":"Point"}
}