{
  "type": "Feature",
  "properties": {
    "iso:country":"US",
    "sg:address":"2654 S Jessup St",
    "sg:city":"Philadelphia",
    "sg:classifiers":[
        {
            "category":"Personal",
            "subcategory":"Beauty Salon",
            "type":"Services"
        }
    ],
    "sg:phone":"+1 215 389 0100",
    "sg:postcode":"19148",
    "sg:province":"PA",
    "sg:tags":[
        "nail"
    ],
    "wof:name":"Violets Salon",
    "wof:placetype":"venue"
},
  "geometry": {"coordinates":[-75.166663,39.916872],"type":"Point"}
}