{
  "type": "Feature",
  "properties": {
    "iso:country":"US",
    "sg:address":"3533 Old Philadelphia Pike",
    "sg:city":"Bethlehem",
    "sg:classifiers":[
        {
            "category":"Food & Beverages",
            "subcategory":"Liquor & Beverages",
            "type":"Retail Goods"
        }
    ],
    "sg:phone":"+1 610 861 4830",
    "sg:postcode":"18015",
    "sg:province":"PA",
    "sg:tags":[
        "bottler",
        "beverages-distributors"
    ],
    "wof:name":"Team Drinks",
    "wof:placetype":"venue"
},
  "geometry": {"coordinates":[-75.390877,40.57658],"type":"Point"}
}