{
  "type": "Feature",
  "properties": {
    "addr:full":"221 S Broad St Grove City PA 16127",
    "addr:housenumber":"221",
    "addr:postcode":"16127",
    "addr:street":"S Broad St",
    "iso:country":"US",
    "sg:address":"221 S Broad St",
    "sg:city":"Grove City",
    "sg:classifiers":[
        {
            "category":"Shopping",
            "subcategory":"Florist",
            "type":"Retail Goods"
        }
    ],
    "sg:phone":"+1 724 458 9570",
    "sg:postcode":"16127",
    "sg:province":"PA",
    "sg:website":"www.nelsonsflowershop.com",
    "wof:name":"Nelson's Flower Shop",
    "wof:placetype":"venue"
},
  "geometry": {"coordinates":[-80.086656,41.159328],"type":"Point"}
}