{
  "type": "Feature",
  "properties": {
    "addr:full":"8398 Easton Rd Ottsville PA 18942",
    "addr:housenumber":"8398",
    "addr:postcode":"18942",
    "addr:street":"Easton Rd",
    "iso:country":"US",
    "sg:address":"8398 Easton Rd",
    "sg:city":"Ottsville",
    "sg:classifiers":[
        {
            "category":"Retail",
            "subcategory":"Veterinary Services",
            "type":"Services"
        }
    ],
    "sg:phone":"+1   ",
    "sg:postcode":"18942",
    "sg:province":"PA",
    "wof:name":"Durham Valley Vets",
    "wof:placetype":"venue"
},
  "geometry": {"coordinates":[-75.17449999999999,40.499694],"type":"Point"}
}