{
  "type": "Feature",
  "properties": {
    "iso:country":"US",
    "sg:address":"1001 Ardmore Blvd",
    "sg:city":"Pittsburgh",
    "sg:classifiers":[
        {
            "category":"Insurance",
            "subcategory":"Insurance Agent",
            "type":"Services"
        }
    ],
    "sg:phone":"+1 412 247 8070",
    "sg:postcode":"15221",
    "sg:province":"PA",
    "wof:name":"Prudential Insurance Co",
    "wof:placetype":"venue"
},
  "geometry": {"coordinates":[-79.86682999999999,40.433551],"type":"Point"}
}