{
  "type": "Feature",
  "properties": {
    "iso:country":"US",
    "sg:address":"40 Canton St",
    "sg:city":"Troy",
    "sg:classifiers":[
        {
            "category":"Farming",
            "subcategory":"Farm",
            "type":"Manufacturing & Wholesale Goods"
        }
    ],
    "sg:phone":"+1 570 297 0420",
    "sg:postcode":"16947",
    "sg:province":"PA",
    "wof:name":"Country View Family Farms",
    "wof:placetype":"venue"
},
  "geometry": {"coordinates":[-76.788089,41.785514],"type":"Point"}
}