{
  "type": "Feature",
  "properties": {
    "iso:country":"US",
    "sg:address":"471 Robison Rd W",
    "sg:city":"Erie",
    "sg:classifiers":[
        {
            "category":"Communications",
            "subcategory":"Radio Station",
            "type":"Services"
        }
    ],
    "sg:phone":"+1 814 868 5355",
    "sg:postcode":"16509",
    "sg:province":"PA",
    "sg:tags":[
        "company",
        "broadcasting"
    ],
    "wof:name":"WRIE",
    "wof:placetype":"venue"
},
  "geometry": {"coordinates":[-80.033855,42.058965],"type":"Point"}
}