{
  "type": "Feature",
  "properties": {
    "addr:full":"140 Henderson Ave Norwood PA 19074",
    "addr:housenumber":"140",
    "addr:postcode":"19074",
    "addr:street":"Henderson Ave",
    "iso:country":"US",
    "sg:address":"140 Henderson Ave",
    "sg:city":"Norwood",
    "sg:classifiers":[
        {
            "category":"Building & Trades",
            "subcategory":"Construction",
            "type":"Services"
        }
    ],
    "sg:phone":"+1   ",
    "sg:postcode":"19074",
    "sg:province":"PA",
    "sg:tags":[
        "residential"
    ],
    "wof:name":"C M S Construction",
    "wof:placetype":"venue"
},
  "geometry": {"coordinates":[-75.29284,39.887858],"type":"Point"}
}