{
  "type": "Feature",
  "properties": {
    "addr:full":"500 E Pumping Station Rd Quakertown PA 18951",
    "addr:housenumber":"500",
    "addr:postcode":"18951",
    "addr:street":"Station Rd",
    "iso:country":"US",
    "sg:address":"500 E Pumping Station Rd",
    "sg:city":"Quakertown",
    "sg:classifiers":[
        {
            "category":"Wholesale",
            "subcategory":"Farm Supplies",
            "type":"Manufacturing & Wholesale Goods"
        },
        {
            "category":"Wholesale",
            "subcategory":"Non-durable Goods",
            "type":"Manufacturing & Wholesale Goods"
        }
    ],
    "sg:phone":"+1 215 538 2330",
    "sg:postcode":"18951",
    "sg:province":"PA",
    "sg:tags":[
        "mulch",
        "mill"
    ],
    "sg:website":"www.jollygardener.com",
    "wof:name":"Frontier Wood Products Inc",
    "wof:placetype":"venue"
},
  "geometry": {"coordinates":[-75.341491,40.463483],"type":"Point"}
}