{
  "type": "Feature",
  "properties": {
    "iso:country":"US",
    "sg:address":"316 Evergreen Rd",
    "sg:city":"Horsham",
    "sg:classifiers":[
        {
            "category":"Building & Trades",
            "subcategory":"Construction",
            "type":"Services"
        }
    ],
    "sg:phone":"+1   ",
    "sg:postcode":"19044",
    "sg:province":"PA",
    "sg:tags":[
        "hanging",
        "contractor"
    ],
    "wof:name":"Nikander Painting Co",
    "wof:placetype":"venue"
},
  "geometry": {"coordinates":[-75.169349,40.203042],"type":"Point"}
}