{
  "type": "Feature",
  "properties": {
    "iso:country":"US",
    "sg:address":"117 Culvert St",
    "sg:city":"Orbisonia",
    "sg:classifiers":[
        {
            "category":"Personal",
            "subcategory":"Beauty Salon",
            "type":"Services"
        }
    ],
    "sg:phone":"+1 814 447 3352",
    "sg:postcode":"17249",
    "sg:province":"PA",
    "wof:name":"Creative Corner Hair Salon",
    "wof:placetype":"venue"
},
  "geometry": {"coordinates":[-77.900885,40.242508],"type":"Point"}
}