{
  "type": "Feature",
  "properties": {
    "iso:country":"US",
    "sg:address":"201 Spring Garden St",
    "sg:city":"Philadelphia",
    "sg:classifiers":[
        {
            "category":"Banks & Credit Unions",
            "subcategory":"Financial Services",
            "type":"Services"
        }
    ],
    "sg:phone":"+1   ",
    "sg:postcode":"19123",
    "sg:province":"PA",
    "sg:tags":[
        "investor"
    ],
    "wof:name":"Battaglia Investments LP",
    "wof:placetype":"venue"
},
  "geometry": {"coordinates":[-75.14197,39.96076],"type":"Point"}
}