{
  "type": "Feature",
  "properties": {
    "addr:full":"3209 Brodhead Rd Aliquippa PA 15001",
    "addr:postcode":"3209;15001",
    "addr:street":"Brodhead Rd",
    "iso:country":"US",
    "sg:address":"3209 Brodhead Rd",
    "sg:city":"Aliquippa",
    "sg:classifiers":[
        {
            "category":"Health Services",
            "subcategory":"Clinic",
            "type":"Services"
        }
    ],
    "sg:phone":"+1 724 375 1710",
    "sg:postcode":"15001",
    "sg:province":"PA",
    "sg:tags":[
        "home"
    ],
    "wof:name":"Heartland Home Healthcare",
    "wof:placetype":"venue"
},
  "geometry": {"coordinates":[-80.25533299999999,40.575503],"type":"Point"}
}