{
  "type": "Feature",
  "properties": {
    "iso:country":"US",
    "sg:address":"605 S Central Ave",
    "sg:city":"Canonsburg",
    "sg:classifiers":[
        {
            "category":"Building & Trades",
            "subcategory":"Construction",
            "type":"Services"
        }
    ],
    "sg:phone":"+1 724 873 8745",
    "sg:postcode":"15317",
    "sg:province":"PA",
    "sg:tags":[
        "painter"
    ],
    "wof:name":"Williams Industrial Painters",
    "wof:placetype":"venue"
},
  "geometry": {"coordinates":[-80.185021,40.25026],"type":"Point"}
}