{
  "type": "Feature",
  "properties": {
    "iso:country":"US",
    "sg:address":"7353 State Rd",
    "sg:city":"Philadelphia",
    "sg:classifiers":[
        {
            "category":"Wholesale",
            "subcategory":"Scrap",
            "type":"Manufacturing & Wholesale Goods"
        }
    ],
    "sg:phone":"+1 215 333 3610",
    "sg:postcode":"19136",
    "sg:province":"PA",
    "sg:tags":[
        "recycling",
        "center"
    ],
    "wof:name":"Planet Earth Recycling Inc",
    "wof:placetype":"venue"
},
  "geometry": {"coordinates":[-75.029916,40.026397],"type":"Point"}
}