{
  "type": "Feature",
  "properties": {
    "addr:full":"41 Lincoln St Pittston PA 18643",
    "addr:housenumber":"41",
    "addr:postcode":"18643",
    "addr:street":"Lincoln St",
    "iso:country":"US",
    "sg:address":"41 Lincoln St",
    "sg:city":"Pittston",
    "sg:classifiers":[
        {
            "category":"Social Services",
            "subcategory":"Child Care",
            "type":"Services"
        }
    ],
    "sg:phone":"+1   ",
    "sg:postcode":"18643",
    "sg:province":"PA",
    "sg:tags":[
        "day"
    ],
    "wof:name":"Magic Yrs Child Care Lrng Cntr",
    "wof:placetype":"venue"
},
  "geometry": {"coordinates":[-75.814046,41.320861],"type":"Point"}
}