{
  "type": "Feature",
  "properties": {
    "iso:country":"US",
    "sg:address":"204 Sewickley Ave",
    "sg:city":"Herminie",
    "sg:classifiers":[
        {
            "category":"Restaurant",
            "type":"Food & Drink"
        }
    ],
    "sg:phone":"+1 724 446 0540",
    "sg:postcode":"15637",
    "sg:province":"PA",
    "sg:tags":[
        "style",
        "family"
    ],
    "wof:name":"Palace Lunch",
    "wof:placetype":"venue"
},
  "geometry": {"coordinates":[-79.71637800000001,40.263542],"type":"Point"}
}