{
  "type": "Feature",
  "properties": {
    "iso:country":"US",
    "sg:address":"858 N 3rd St",
    "sg:city":"Philadelphia",
    "sg:classifiers":[
        {
            "category":"Shopping",
            "subcategory":"Pets & Pet Supplies",
            "type":"Retail Goods"
        },
        {
            "category":"Retail",
            "subcategory":"Pet Boarding",
            "type":"Services"
        }
    ],
    "sg:phone":"+1 215 238 7200",
    "sg:postcode":"19123",
    "sg:province":"PA",
    "sg:tags":[
        "training",
        "boarding/pet",
        "sitting"
    ],
    "sg:website":"www.doggieworld.net",
    "wof:name":"Doggie World Daycare Inc",
    "wof:placetype":"venue"
},
  "geometry": {"coordinates":[-75.142658,39.964475],"type":"Point"}
}