{
  "type": "Feature",
  "properties": {
    "iso:country":"US",
    "sg:address":"58 S 2nd St",
    "sg:city":"Cressona",
    "sg:classifiers":[
        {
            "category":"Building & Trades",
            "subcategory":"Construction",
            "type":"Services"
        }
    ],
    "sg:phone":"+1   ",
    "sg:postcode":"17929",
    "sg:province":"PA",
    "sg:tags":[
        "contractor"
    ],
    "wof:name":"Hiltop Meadow Products",
    "wof:placetype":"venue"
},
  "geometry": {"coordinates":[-76.19502300000001,40.628234],"type":"Point"}
}