{
  "type": "Feature",
  "properties": {
    "iso:country":"US",
    "sg:address":"222 Sugartown Rd",
    "sg:city":"Wayne",
    "sg:classifiers":[
        {
            "category":"Restaurant",
            "type":"Food & Drink"
        }
    ],
    "sg:phone":"+1   ",
    "sg:postcode":"19087",
    "sg:province":"PA",
    "sg:tags":[
        "eating"
    ],
    "wof:name":"Johnny Cabos",
    "wof:placetype":"venue"
},
  "geometry": {"coordinates":[-75.40633800000001,40.044774],"type":"Point"}
}