{
  "type": "Feature",
  "properties": {
    "addr:full":"3011 Walnut Ave Altoona PA 16601",
    "addr:housenumber":"3011",
    "addr:postcode":"16601",
    "addr:street":"Walnut Ave",
    "iso:country":"US",
    "sg:address":"3011 Walnut Ave",
    "sg:city":"Altoona",
    "sg:classifiers":[
        {
            "category":"Retail",
            "subcategory":"Laundry & Dry Cleaning",
            "type":"Services"
        }
    ],
    "sg:phone":"+1 814 943 6098",
    "sg:postcode":"16601",
    "sg:province":"PA",
    "sg:tags":[
        "cleaners",
        "laundromat",
        "coin"
    ],
    "wof:name":"Dale's Cleaning Village",
    "wof:placetype":"venue"
},
  "geometry": {"coordinates":[-78.42025,40.499756],"type":"Point"}
}