{
  "type": "Feature",
  "properties": {
    "iso:country":"US",
    "sg:address":"3101 Bristol Rd",
    "sg:city":"Bensalem",
    "sg:classifiers":[
        {
            "category":"Communications",
            "type":"Services"
        }
    ],
    "sg:phone":"+1 215 584 7888",
    "sg:postcode":"19020",
    "sg:province":"PA",
    "sg:tags":[
        "web",
        "design"
    ],
    "sg:website":"www.nextdayonline.com",
    "wof:name":"NextDayOnline",
    "wof:placetype":"venue"
},
  "geometry": {"coordinates":[-74.93568999999999,40.133991],"type":"Point"}
}