{
  "type": "Feature",
  "properties": {
    "iso:country":"US",
    "sg:address":"412 W Main St",
    "sg:city":"Ringtown",
    "sg:classifiers":[
        {
            "category":"Retail",
            "subcategory":"Funeral Services",
            "type":"Services"
        }
    ],
    "sg:phone":"+1   ",
    "sg:postcode":"17967",
    "sg:province":"PA",
    "wof:name":"Stauffer Funeral Home",
    "wof:placetype":"venue"
},
  "geometry": {"coordinates":[-76.240134,40.856837],"type":"Point"}
}