{
  "type": "Feature",
  "properties": {
    "addr:full":"502 2nd Street Pike Southampton PA 18966",
    "addr:housenumber":"502",
    "addr:postcode":"18966",
    "addr:street":"2Nd Street Pike",
    "iso:country":"US",
    "sg:address":"502 2nd Street Pike",
    "sg:city":"Southampton",
    "sg:classifiers":[
        {
            "category":"Food & Beverages",
            "subcategory":"Specialty",
            "type":"Retail Goods"
        }
    ],
    "sg:phone":"+1   ",
    "sg:postcode":"18966",
    "sg:province":"PA",
    "wof:name":"Vitamins Specialties",
    "wof:placetype":"venue"
},
  "geometry": {"coordinates":[-75.045147,40.169977],"type":"Point"}
}