{
  "type": "Feature",
  "properties": {
    "iso:country":"US",
    "sg:address":"19038 Cochranton Rd",
    "sg:city":"Meadville",
    "sg:classifiers":[
        {
            "category":"Autos & Motor Vehicles",
            "subcategory":"Automobile Sales",
            "type":"Retail Goods"
        }
    ],
    "sg:phone":"+1 814 337 0116",
    "sg:postcode":"16335",
    "sg:province":"PA",
    "sg:tags":[
        "body",
        "used",
        "general"
    ],
    "wof:name":"Smock Auto Sales",
    "wof:placetype":"venue"
},
  "geometry": {"coordinates":[-80.14094299999999,41.592704],"type":"Point"}
}