{
  "type": "Feature",
  "properties": {
    "iso:country":"US",
    "sg:address":"2117 Sturbridge Cmn",
    "sg:city":"Southampton",
    "sg:classifiers":[
        {
            "category":"Building & Trades",
            "subcategory":"Construction",
            "type":"Services"
        }
    ],
    "sg:phone":"+1   ",
    "sg:postcode":"18966",
    "sg:province":"PA",
    "sg:tags":[
        "contractor"
    ],
    "wof:name":"A C and S Inc",
    "wof:placetype":"venue"
},
  "geometry": {"coordinates":[-74.945277,40.209621],"type":"Point"}
}