{
  "type": "Feature",
  "properties": {
    "addr:full":"55 N Broad St Philadelphia PA 19107",
    "addr:housenumber":"55",
    "addr:postcode":"19107",
    "addr:street":"N Broad St",
    "iso:country":"US",
    "sg:address":"55 N Broad St",
    "sg:city":"Philadelphia",
    "sg:classifiers":[
        {
            "category":"Place Of Worship",
            "subcategory":"Church",
            "type":"Public Place"
        },
        {
            "category":"Place Of Worship",
            "type":"Public Place"
        }
    ],
    "sg:phone":"+1 215 568 6250",
    "sg:postcode":"19107",
    "sg:province":"PA",
    "sg:tags":[
        "churches-interdenominational",
        "denomination",
        "churches-various",
        "churches-methodist"
    ],
    "wof:name":"Arch Street United Methodist Church",
    "wof:placetype":"venue"
},
  "geometry": {"coordinates":[-75.163228,39.954086],"type":"Point"}
}