{
  "type": "Feature",
  "properties": {
    "addr:full":"529 W Penn Ave Cleona PA 17042",
    "addr:housenumber":"529",
    "addr:postcode":"17042",
    "addr:street":"W Penn Ave",
    "iso:country":"US",
    "sg:address":"529 W Penn Ave",
    "sg:city":"Cleona",
    "sg:classifiers":[
        {
            "category":"Organizations",
            "subcategory":"Religious Organization",
            "type":"Services"
        }
    ],
    "sg:phone":"+1 717 272 4276",
    "sg:postcode":"17042",
    "sg:province":"PA",
    "sg:tags":[
        "churches-brethren"
    ],
    "sg:website":"www.nbn.net",
    "wof:name":"Fairland Brethren In Christ Church",
    "wof:placetype":"venue"
},
  "geometry": {"coordinates":[-76.485412,40.335636],"type":"Point"}
}