{
  "type": "Feature",
  "properties": {
    "addr:full":"122 Cidar Ln Canonsburg PA 15317",
    "addr:housenumber":"122",
    "addr:postcode":"15317",
    "addr:street":"Cidar Ln",
    "iso:country":"US",
    "sg:address":"122 Cidar Ln",
    "sg:city":"Canonsburg",
    "sg:classifiers":[
        {
            "category":"Real Estate",
            "subcategory":"Developer",
            "type":"Services"
        }
    ],
    "sg:phone":"+1   ",
    "sg:postcode":"15317",
    "sg:province":"PA",
    "wof:name":"Briwood Inc",
    "wof:placetype":"venue"
},
  "geometry": {"coordinates":[-80.08156,40.284878],"type":"Point"}
}