{
  "type": "Feature",
  "properties": {
    "iso:country":"US",
    "sg:address":"19 Green Ridge St",
    "sg:city":"Scranton",
    "sg:classifiers":[
        {
            "category":"Home & Garden",
            "subcategory":"Building Materials",
            "type":"Retail Goods"
        }
    ],
    "sg:phone":"+1 570 969 2544",
    "sg:postcode":"18509",
    "sg:province":"PA",
    "sg:tags":[
        "remodeling",
        "contractor"
    ],
    "wof:name":"DOORS Windows & More",
    "wof:placetype":"venue"
},
  "geometry": {"coordinates":[-75.658889,41.432647],"type":"Point"}
}