{
  "type": "Feature",
  "properties": {
    "iso:country":"US",
    "sg:address":"811 Dekalb Pike",
    "sg:city":"Blue Bell",
    "sg:classifiers":[
        {
            "category":"Autos & Motor Vehicles",
            "subcategory":"Automobile Sales",
            "type":"Retail Goods"
        }
    ],
    "sg:phone":"+1   ",
    "sg:postcode":"19422",
    "sg:province":"PA",
    "sg:tags":[
        "used"
    ],
    "wof:name":"Auto Sales",
    "wof:placetype":"venue"
},
  "geometry": {"coordinates":[-75.28578400000001,40.171566],"type":"Point"}
}