{
  "type": "Feature",
  "properties": {
    "addr:full":"1328 Rehobeth Rd Strattanville PA 16258",
    "addr:housenumber":"1328",
    "addr:postcode":"16258",
    "addr:street":"Rehobeth Rd",
    "iso:country":"US",
    "sg:address":"1328 Rehobeth Rd",
    "sg:city":"Strattanville",
    "sg:classifiers":[
        {
            "category":"Building & Trades",
            "subcategory":"Cleaning & Sanitation",
            "type":"Services"
        }
    ],
    "sg:phone":"+1 814 371 0454",
    "sg:postcode":"16258",
    "sg:province":"PA",
    "wof:name":"Service Master",
    "wof:placetype":"venue"
},
  "geometry": {"coordinates":[-79.30459500000001,41.18378],"type":"Point"}
}