{
  "type": "Feature",
  "properties": {
    "iso:country":"US",
    "sg:address":"282 Bears Rd",
    "sg:city":"Hastings",
    "sg:classifiers":[
        {
            "category":"Retail",
            "subcategory":"Repair Shop",
            "type":"Services"
        }
    ],
    "sg:phone":"+1   ",
    "sg:postcode":"16646",
    "sg:province":"PA",
    "wof:name":"Bearers Custom Gunsmithing",
    "wof:placetype":"venue"
},
  "geometry": {"coordinates":[-78.72952100000001,40.644094],"type":"Point"}
}