{
  "type": "Feature",
  "properties": {
    "iso:country":"US",
    "sg:address":"500 Reinholds Rd",
    "sg:city":"Denver",
    "sg:classifiers":[
        {
            "category":"Building & Trades",
            "subcategory":"Construction",
            "type":"Services"
        }
    ],
    "sg:phone":"+1   ",
    "sg:postcode":"17517",
    "sg:province":"PA",
    "sg:tags":[
        "carpentry",
        "contractor"
    ],
    "wof:name":"Frontierwoodcraftsmn",
    "wof:placetype":"venue"
},
  "geometry": {"coordinates":[-76.120543,40.247017],"type":"Point"}
}