{
  "type": "Feature",
  "properties": {
    "addr:full":"125 Sherman Ave Ridgway PA 15853",
    "addr:housenumber":"125",
    "addr:postcode":"15853",
    "addr:street":"Sherman Ave",
    "iso:country":"US",
    "sg:address":"125 Sherman Ave",
    "sg:city":"Ridgway",
    "sg:classifiers":[
        {
            "category":"Place Of Worship",
            "subcategory":"Church",
            "type":"Public Place"
        },
        {
            "category":"Place Of Worship",
            "type":"Public Place"
        }
    ],
    "sg:phone":"+1 814 772 0302",
    "sg:postcode":"15853",
    "sg:province":"PA",
    "sg:tags":[
        "churches-interdenominational",
        "churches-various",
        "denomination"
    ],
    "wof:name":"Faith Baha'i",
    "wof:placetype":"venue"
},
  "geometry": {"coordinates":[-78.72524300000001,41.423989],"type":"Point"}
}