{
  "type": "Feature",
  "properties": {
    "addr:full":"122 S 4th St Connellsville PA 15425",
    "addr:housenumber":"122",
    "addr:postcode":"15425",
    "addr:street":"S 4Th St",
    "iso:country":"US",
    "sg:address":"122 S 4th St",
    "sg:city":"Connellsville",
    "sg:classifiers":[
        {
            "category":"Social Services",
            "type":"Services"
        }
    ],
    "sg:phone":"+1 724 626 8006",
    "sg:postcode":"15425",
    "sg:province":"PA",
    "sg:tags":[
        "counselor",
        "marriage",
        "family"
    ],
    "wof:name":"Bonnie A Nara PHD",
    "wof:placetype":"venue"
},
  "geometry": {"coordinates":[-79.59683800000001,40.016433],"type":"Point"}
}