{
  "type": "Feature",
  "properties": {
    "iso:country":"US",
    "sg:address":"25 Ferry St",
    "sg:city":"Leetsdale",
    "sg:classifiers":[
        {
            "category":"Home & Garden",
            "subcategory":"Building Materials",
            "type":"Retail Goods"
        }
    ],
    "sg:phone":"+1 724 266 4474",
    "sg:postcode":"15056",
    "sg:province":"PA",
    "wof:name":"Sewickley Stained Glass",
    "wof:placetype":"venue"
},
  "geometry": {"coordinates":[-80.207155,40.563885],"type":"Point"}
}