{
  "type": "Feature",
  "properties": {
    "iso:country":"US",
    "sg:address":"848 April Hill Way",
    "sg:city":"Harleysville",
    "sg:classifiers":[
        {
            "category":"Building & Trades",
            "subcategory":"Construction",
            "type":"Services"
        }
    ],
    "sg:phone":"+1   ",
    "sg:postcode":"19438",
    "sg:province":"PA",
    "sg:tags":[
        "house"
    ],
    "wof:name":"Berc Associates Inc",
    "wof:placetype":"venue"
},
  "geometry": {"coordinates":[-75.389267,40.240968],"type":"Point"}
}