{
  "type": "Feature",
  "properties": {
    "iso:country":"US",
    "sg:address":"738 E Penn St",
    "sg:city":"Philadelphia",
    "sg:classifiers":[
        {
            "category":"Organizations",
            "subcategory":"Religious Organization",
            "type":"Services"
        }
    ],
    "sg:phone":"+1 215 438 5001",
    "sg:postcode":"19144",
    "sg:province":"PA",
    "sg:tags":[
        "church"
    ],
    "wof:name":"Church Of The Redeemer",
    "wof:placetype":"venue"
},
  "geometry": {"coordinates":[-75.158473,40.041728],"type":"Point"}
}