{
  "type": "Feature",
  "properties": {
    "iso:country":"US",
    "sg:address":"917 Chartiers Ave",
    "sg:city":"Pittsburgh",
    "sg:classifiers":[
        {
            "category":"Shopping",
            "subcategory":"Used Merchandise",
            "type":"Retail Goods"
        }
    ],
    "sg:phone":"+1 412 921 6883",
    "sg:postcode":"15220",
    "sg:province":"PA",
    "sg:tags":[
        "shop",
        "thrift"
    ],
    "wof:name":"Dorothy Chilson",
    "wof:placetype":"venue"
},
  "geometry": {"coordinates":[-80.040612,40.443837],"type":"Point"}
}