{
  "type": "Feature",
  "properties": {
    "addr:full":"492 Woodlawn Ave Mountain Top PA 18707",
    "addr:housenumber":"492",
    "addr:postcode":"18707",
    "addr:street":"Woodlawn Ave",
    "iso:country":"US",
    "sg:address":"492 Woodlawn Ave",
    "sg:city":"Mountain Top",
    "sg:classifiers":[
        {
            "category":"Professional",
            "type":"Services"
        }
    ],
    "sg:phone":"+1   ",
    "sg:postcode":"18707",
    "sg:province":"PA",
    "wof:name":"George Steinson",
    "wof:placetype":"venue"
},
  "geometry": {"coordinates":[-75.867053,41.144053],"type":"Point"}
}