{
  "type": "Feature",
  "properties": {
    "iso:country":"US",
    "sg:address":"1195 Kingsley Rd",
    "sg:city":"Camp Hill",
    "sg:classifiers":[
        {
            "category":"Professional",
            "subcategory":"Management & Consulting",
            "type":"Services"
        }
    ],
    "sg:phone":"+1   ",
    "sg:postcode":"17011",
    "sg:province":"PA",
    "sg:tags":[
        "retail",
        "direct",
        "sales"
    ],
    "wof:name":"Susan C Brewer",
    "wof:placetype":"venue"
},
  "geometry": {"coordinates":[-76.893761,40.233784],"type":"Point"}
}