{
  "type": "Feature",
  "properties": {
    "addr:full":"1078 Hunters Path Lancaster PA 17601",
    "addr:housenumber":"1078",
    "addr:postcode":"17601",
    "addr:street":"Hunters Path",
    "iso:country":"US",
    "sg:address":"1078 Hunters Path",
    "sg:city":"Lancaster",
    "sg:classifiers":[
        {
            "category":"Shopping",
            "subcategory":"Discount & Variety Stores",
            "type":"Retail Goods"
        }
    ],
    "sg:phone":"+1   ",
    "sg:postcode":"17601",
    "sg:province":"PA",
    "sg:tags":[
        "merchandise",
        "general"
    ],
    "wof:name":"B&E Group Inc",
    "wof:placetype":"venue"
},
  "geometry": {"coordinates":[-76.386422,40.076848],"type":"Point"}
}