{
  "type": "Feature",
  "properties": {
    "addr:full":"347 East Ave Erie PA 16507",
    "addr:housenumber":"347",
    "addr:postcode":"16507",
    "addr:street":"East Ave",
    "iso:country":"US",
    "sg:address":"347 East Ave",
    "sg:city":"Erie",
    "sg:classifiers":[
        {
            "category":"Shopping",
            "type":"Retail Goods"
        }
    ],
    "sg:phone":"+1   ",
    "sg:postcode":"16507",
    "sg:province":"PA",
    "sg:tags":[
        "merchandise"
    ],
    "wof:name":"Country Fair Store",
    "wof:placetype":"venue"
},
  "geometry": {"coordinates":[-80.06469800000001,42.140263],"type":"Point"}
}