{
  "type": "Feature",
  "properties": {
    "iso:country":"US",
    "sg:address":"189 Applegate Way",
    "sg:city":"New Castle",
    "sg:classifiers":[
        {
            "category":"Home & Garden",
            "subcategory":"Building Materials",
            "type":"Retail Goods"
        },
        {
            "category":"Manufacturing",
            "subcategory":"Furniture",
            "type":"Manufacturing & Wholesale Goods"
        }
    ],
    "sg:phone":"+1 724 652 8711",
    "sg:postcode":"16101",
    "sg:province":"PA",
    "sg:tags":[
        "custom",
        "wood",
        "made",
        "cabinet"
    ],
    "wof:name":"L Applegate Cabinets & Supply",
    "wof:placetype":"venue"
},
  "geometry": {"coordinates":[-80.388616,41.008458],"type":"Point"}
}