{
  "type": "Feature",
  "properties": {
    "iso:country":"US",
    "sg:address":"210 E 4th Ave",
    "sg:city":"Tarentum",
    "sg:classifiers":[
        {
            "category":"Manufacturing",
            "subcategory":"Printing",
            "type":"Manufacturing & Wholesale Goods"
        }
    ],
    "sg:phone":"+1 724 226 7776",
    "sg:postcode":"15084",
    "sg:province":"PA",
    "sg:tags":[
        "newspaper"
    ],
    "wof:name":"Western Pennsylvania Printing",
    "wof:placetype":"venue"
},
  "geometry": {"coordinates":[-79.754965,40.601143],"type":"Point"}
}