{
  "type": "Feature",
  "properties": {
    "iso:country":"US",
    "sg:address":"5212 Cedar Ave",
    "sg:city":"Philadelphia",
    "sg:classifiers":[
        {
            "category":"Health Services",
            "subcategory":"Podiatrist",
            "type":"Services"
        }
    ],
    "sg:phone":"+1 215 474 9775",
    "sg:postcode":"19143",
    "sg:province":"PA",
    "wof:name":"Cedar Medical",
    "wof:placetype":"venue"
},
  "geometry": {"coordinates":[-75.22867100000001,39.950601],"type":"Point"}
}