{
  "type": "Feature",
  "properties": {
    "iso:country":"US",
    "sg:address":"3030 Carnegie Dr",
    "sg:city":"State College",
    "sg:classifiers":[
        {
            "category":"Organizations",
            "subcategory":"Religious Organization",
            "type":"Services"
        }
    ],
    "sg:phone":"+1 814 234 1900",
    "sg:postcode":"16803",
    "sg:province":"PA",
    "sg:tags":[
        "church"
    ],
    "sg:website":"www.parkforestbaptist.org",
    "wof:name":"Forest Park Baptist Church",
    "wof:placetype":"venue"
},
  "geometry": {"coordinates":[-77.929284,40.811437],"type":"Point"}
}