{
  "type": "Feature",
  "properties": {
    "iso:country":"US",
    "sg:address":"318 Munson Ave",
    "sg:city":"Mc Kees Rocks",
    "sg:classifiers":[
        {
            "category":"Organizations",
            "subcategory":"Religious Organization",
            "type":"Services"
        }
    ],
    "sg:phone":"+1 412 331 1053",
    "sg:postcode":"15136",
    "sg:province":"PA",
    "sg:tags":[
        "church"
    ],
    "wof:name":"St Nicholas Russian Orthodox",
    "wof:placetype":"venue"
},
  "geometry": {"coordinates":[-80.059179,40.474798],"type":"Point"}
}