{
  "type": "Feature",
  "properties": {
    "addr:full":"6 Landings Dr Pittsburgh PA 15238",
    "addr:housenumber":"6",
    "addr:postcode":"15238",
    "addr:street":"Landings Dr",
    "iso:country":"US",
    "sg:address":"6 Landings Dr",
    "sg:city":"Pittsburgh",
    "sg:classifiers":[
        {
            "category":"Building & Trades",
            "subcategory":"Landscaping Services",
            "type":"Services"
        }
    ],
    "sg:phone":"+1   ",
    "sg:postcode":"15238",
    "sg:province":"PA",
    "sg:tags":[
        "landscape"
    ],
    "wof:name":"All American Lawns Inc",
    "wof:placetype":"venue"
},
  "geometry": {"coordinates":[-79.82661299999999,40.540693],"type":"Point"}
}