{
  "type": "Feature",
  "properties": {
    "iso:country":"US",
    "sg:address":"208 Division Ln",
    "sg:city":"Beaver",
    "sg:classifiers":[
        {
            "category":"Wholesale",
            "subcategory":"Electrical",
            "type":"Manufacturing & Wholesale Goods"
        },
        {
            "category":"Shopping",
            "subcategory":"Computers & Home Electronics",
            "type":"Retail Goods"
        }
    ],
    "sg:phone":"+1 724 775 1779",
    "sg:postcode":"15009",
    "sg:province":"PA",
    "sg:tags":[
        "equipment",
        "satellite",
        "electronic",
        "system"
    ],
    "wof:name":"Roushs Electronics",
    "wof:placetype":"venue"
},
  "geometry": {"coordinates":[-80.328126,40.690287],"type":"Point"}
}