{
  "type": "Feature",
  "properties": {
    "addr:full":"1149 Wyoming Ave Kingston PA 18704",
    "addr:housenumber":"1149",
    "addr:postcode":"18704",
    "addr:street":"Wyoming Ave",
    "iso:country":"US",
    "sg:address":"1149 Wyoming Ave",
    "sg:city":"Kingston",
    "sg:classifiers":[
        {
            "category":"Real Estate",
            "subcategory":"Real Estate Agent",
            "type":"Services"
        }
    ],
    "sg:phone":"+1   ",
    "sg:postcode":"18704",
    "sg:province":"PA",
    "wof:name":"Prudential",
    "wof:placetype":"venue"
},
  "geometry": {"coordinates":[-75.87612799999999,41.281662],"type":"Point"}
}