{
  "type": "Feature",
  "properties": {
    "iso:country":"US",
    "sg:address":"3759 US Hwy 220",
    "sg:city":"Bedford",
    "sg:classifiers":[
        {
            "category":"Manufacturing",
            "subcategory":"Printing",
            "type":"Manufacturing & Wholesale Goods"
        }
    ],
    "sg:phone":"+1 814 623 2477",
    "sg:postcode":"15522",
    "sg:province":"PA",
    "sg:tags":[
        "commercial"
    ],
    "wof:name":"Gary James Designs",
    "wof:placetype":"venue"
},
  "geometry": {"coordinates":[-78.66151499999999,39.81579],"type":"Point"}
}