{
  "type": "Feature",
  "properties": {
    "iso:country":"US",
    "sg:address":"169 Overland Ave",
    "sg:city":"Duquesne",
    "sg:classifiers":[
        {
            "category":"Arena",
            "subcategory":"Sports Club",
            "type":"Entertainment"
        }
    ],
    "sg:phone":"+1   ",
    "sg:postcode":"15110",
    "sg:province":"PA",
    "wof:name":"Duquesne School District Footb",
    "wof:placetype":"venue"
},
  "geometry": {"coordinates":[-79.85976700000001,40.381506],"type":"Point"}
}