{
  "type": "Feature",
  "properties": {
    "addr:full":"2727 W 21st St Erie PA 16506",
    "addr:housenumber":"2727",
    "addr:postcode":"16506",
    "addr:street":"W 21St St",
    "iso:country":"US",
    "sg:address":"2727 W 21st St",
    "sg:city":"Erie",
    "sg:classifiers":[
        {
            "category":"Professional",
            "type":"Services"
        },
        {
            "category":"Shopping",
            "subcategory":"Pharmacy",
            "type":"Retail Goods"
        }
    ],
    "sg:phone":"+1 814 836 0207",
    "sg:postcode":"16506",
    "sg:province":"PA",
    "sg:tags":[
        "establishment"
    ],
    "wof:name":"Lakeshore Isotopes Inc",
    "wof:placetype":"venue"
},
  "geometry": {"coordinates":[-80.137519,42.093423],"type":"Point"}
}