{
  "type": "Feature",
  "properties": {
    "iso:country":"US",
    "sg:address":"301 Airport Dr",
    "sg:city":"Smoketown",
    "sg:classifiers":[
        {
            "category":"Personal",
            "subcategory":"Beauty Salon",
            "type":"Services"
        }
    ],
    "sg:phone":"+1 717 394 7386",
    "sg:postcode":"17576",
    "sg:province":"PA",
    "wof:name":"Inspirations Hair Care Ctr",
    "wof:placetype":"venue"
},
  "geometry": {"coordinates":[-76.204893,40.039466],"type":"Point"}
}