{
  "type": "Feature",
  "properties": {
    "iso:country":"US",
    "sg:address":"15 N Chester Rd",
    "sg:city":"West Chester",
    "sg:classifiers":[
        {
            "category":"Education",
            "subcategory":"Library",
            "type":"Public Place"
        }
    ],
    "sg:phone":"+1 610 344 6166",
    "sg:postcode":"19380",
    "sg:province":"PA",
    "sg:tags":[
        "special",
        "interest"
    ],
    "sg:website":"www.chesco.org",
    "wof:name":"Chester County Law Library",
    "wof:placetype":"venue"
},
  "geometry": {"coordinates":[-75.52378400000001,39.967086],"type":"Point"}
}