{
  "type": "Feature",
  "properties": {
    "addr:full":"6962 Lincoln Way W St Thomas PA 17252",
    "addr:housenumber":"6962",
    "addr:postcode":"17252",
    "addr:street":"Lincoln Way W St",
    "iso:country":"US",
    "sg:address":"6962 Lincoln Way W",
    "sg:city":"St Thomas",
    "sg:classifiers":[
        {
            "category":"Banks & Credit Unions",
            "subcategory":"Bank",
            "type":"Services"
        }
    ],
    "sg:phone":"+1 717 369 3240",
    "sg:postcode":"17252",
    "sg:province":"PA",
    "wof:name":"Fulton County National Bank",
    "wof:placetype":"venue"
},
  "geometry": {"coordinates":[-77.84096599999999,39.906139],"type":"Point"}
}