{
  "type": "Feature",
  "properties": {
    "iso:country":"US",
    "sg:address":"2516 E Lehigh Ave",
    "sg:city":"Philadelphia",
    "sg:classifiers":[
        {
            "category":"Health Services",
            "subcategory":"Doctor",
            "type":"Services"
        }
    ],
    "sg:phone":"+1   ",
    "sg:postcode":"19125",
    "sg:province":"PA",
    "sg:tags":[
        "medical"
    ],
    "wof:name":"Thachet Cyriac MD",
    "wof:placetype":"venue"
},
  "geometry": {"coordinates":[-75.116146,39.980111],"type":"Point"}
}