{
  "type": "Feature",
  "properties": {
    "iso:country":"US",
    "sg:address":"157 Henry St",
    "sg:city":"Smithton",
    "sg:classifiers":[
        {
            "category":"Organizations",
            "subcategory":"Religious Organization",
            "type":"Services"
        }
    ],
    "sg:phone":"+1 724 872 5058",
    "sg:postcode":"15425",
    "sg:province":"PA",
    "sg:tags":[
        "church"
    ],
    "wof:name":"Smithton Church-Nazarene",
    "wof:placetype":"venue"
},
  "geometry": {"coordinates":[-79.544392,40.042787],"type":"Point"}
}