{
  "type": "Feature",
  "properties": {
    "iso:country":"US",
    "sg:address":"264 W Queen Ln",
    "sg:city":"Philadelphia",
    "sg:classifiers":[
        {
            "category":"Retail",
            "subcategory":"Laundry & Dry Cleaning",
            "type":"Services"
        }
    ],
    "sg:phone":"+1 215 848 2677",
    "sg:postcode":"19144",
    "sg:province":"PA",
    "sg:tags":[
        "cleaners"
    ],
    "wof:name":"Neighborhood Dry Cleaning",
    "wof:placetype":"venue"
},
  "geometry": {"coordinates":[-75.173894,40.026653],"type":"Point"}
}