{
  "type": "Feature",
  "properties": {
    "iso:country":"US",
    "sg:address":"207 Pine Grove Ct",
    "sg:city":"Baden",
    "sg:classifiers":[
        {
            "category":"Farming",
            "subcategory":"Livestock Farm",
            "type":"Manufacturing & Wholesale Goods"
        }
    ],
    "sg:phone":"+1   ",
    "sg:postcode":"15005",
    "sg:province":"PA",
    "sg:tags":[
        "beef",
        "feedlot",
        "cattle"
    ],
    "wof:name":"K Flying Cattle Company",
    "wof:placetype":"venue"
},
  "geometry": {"coordinates":[-80.117965,40.647264],"type":"Point"}
}