{
  "type": "Feature",
  "properties": {
    "iso:country":"US",
    "sg:address":"2950 Turnpike Dr",
    "sg:city":"Hatboro",
    "sg:classifiers":[
        {
            "category":"Professional",
            "subcategory":"Management & Consulting",
            "type":"Services"
        }
    ],
    "sg:phone":"+1 215 957 2338",
    "sg:postcode":"19040",
    "sg:province":"PA",
    "sg:tags":[
        "fuel"
    ],
    "wof:name":"Hankin Management",
    "wof:placetype":"venue"
},
  "geometry": {"coordinates":[-75.092911,40.16264],"type":"Point"}
}