{
  "type": "Feature",
  "properties": {
    "iso:country":"US",
    "sg:address":"532 Lancaster Ave",
    "sg:city":"Haverford",
    "sg:classifiers":[
        {
            "category":"Shopping",
            "type":"Retail Goods"
        }
    ],
    "sg:phone":"+1   ",
    "sg:postcode":"19041",
    "sg:province":"PA",
    "sg:tags":[
        "pet",
        "food",
        "supply"
    ],
    "wof:name":"Petco",
    "wof:placetype":"venue"
},
  "geometry": {"coordinates":[-75.307984,40.016287],"type":"Point"}
}