{
  "type": "Feature",
  "properties": {
    "iso:country":"US",
    "sg:address":"300 Commons Dr",
    "sg:city":"Parkesburg",
    "sg:classifiers":[
        {
            "category":"Shopping",
            "subcategory":"Shoes",
            "type":"Retail Goods"
        }
    ],
    "sg:phone":"+1 610 857 4902",
    "sg:postcode":"19365",
    "sg:province":"PA",
    "wof:name":"Shoe Department",
    "wof:placetype":"venue"
},
  "geometry": {"coordinates":[-75.934377,39.981571],"type":"Point"}
}