{
  "type": "Feature",
  "properties": {
    "iso:country":"US",
    "sg:address":"8 Woodland Ave",
    "sg:city":"Greensburg",
    "sg:classifiers":[
        {
            "category":"Restaurant",
            "type":"Food & Drink"
        }
    ],
    "sg:menulink":"http://www.allmenus.com/pa/greensburg/237765-rax/menu/",
    "sg:phone":"+1 724 836 2690",
    "sg:postcode":"15601",
    "sg:province":"PA",
    "sg:tags":[
        "wrap",
        "american",
        "sandwich"
    ],
    "wof:name":"Rax",
    "wof:placetype":"venue"
},
  "geometry": {"coordinates":[-79.538208,40.315989],"type":"Point"}
}