{
  "type": "Feature",
  "properties": {
    "addr:full":"117 Charlwood Dr Freeland PA 18224",
    "addr:housenumber":"117",
    "addr:postcode":"18224",
    "addr:street":"Charlwood Dr",
    "iso:country":"US",
    "sg:address":"117 Charlwood Dr",
    "sg:city":"Freeland",
    "sg:classifiers":[
        {
            "category":"Building & Trades",
            "subcategory":"Construction",
            "type":"Services"
        }
    ],
    "sg:phone":"+1 570 636 1896",
    "sg:postcode":"18224",
    "sg:province":"PA",
    "sg:tags":[
        "painter"
    ],
    "wof:name":"Legge's Painting & Paperhangng",
    "wof:placetype":"venue"
},
  "geometry": {"coordinates":[-75.912761,41.02075],"type":"Point"}
}