{
  "type": "Feature",
  "properties": {
    "addr:full":"120 E Main St Grove City PA 16127",
    "addr:housenumber":"120",
    "addr:postcode":"16127",
    "addr:street":"E Main St",
    "iso:country":"US",
    "sg:address":"120 E Main St",
    "sg:city":"Grove City",
    "sg:classifiers":[
        {
            "category":"Organizations",
            "subcategory":"Religious Organization",
            "type":"Services"
        }
    ],
    "sg:phone":"+1 724 458 8270",
    "sg:postcode":"16127",
    "sg:province":"PA",
    "sg:website":"www.eastmainpc.org",
    "wof:name":"East Main Presbyterian Church",
    "wof:placetype":"venue"
},
  "geometry": {"coordinates":[-80.08654199999999,41.156568],"type":"Point"}
}