{
  "type": "Feature",
  "properties": {
    "iso:country":"US",
    "sg:address":"2835 W 23rd St",
    "sg:city":"Erie",
    "sg:classifiers":[
        {
            "category":"Home & Garden",
            "subcategory":"Building Materials",
            "type":"Retail Goods"
        },
        {
            "category":"Manufacturing",
            "subcategory":"Building Materials",
            "type":"Manufacturing & Wholesale Goods"
        }
    ],
    "sg:phone":"+1 814 835 6677",
    "sg:postcode":"16506",
    "sg:province":"PA",
    "sg:tags":[
        "door",
        "accessory",
        "garage",
        "opener",
        "doors",
        "frames"
    ],
    "sg:website":"http://www.miljackinc.com",
    "wof:name":"Overhead Door Co-Greater Erie",
    "wof:placetype":"venue"
},
  "geometry": {"coordinates":[-80.137727,42.091388],"type":"Point"}
}