{
  "type": "Feature",
  "properties": {
    "iso:country":"US",
    "sg:address":"140 E Wyoming Ave",
    "sg:city":"Philadelphia",
    "sg:classifiers":[
        {
            "category":"Food & Beverages",
            "subcategory":"Groceries & Convenience Stores",
            "type":"Retail Goods"
        }
    ],
    "sg:phone":"+1 215 455 3297",
    "sg:postcode":"19120",
    "sg:province":"PA",
    "wof:name":"Paulino Grocery",
    "wof:placetype":"venue"
},
  "geometry": {"coordinates":[-75.12357,40.021316],"type":"Point"}
}