{
  "type": "Feature",
  "properties": {
    "iso:country":"US",
    "sg:address":"1407 Bethlehem Pike",
    "sg:city":"Flourtown",
    "sg:classifiers":[
        {
            "category":"Wholesale",
            "subcategory":"Medical Equipment & Supplies",
            "type":"Manufacturing & Wholesale Goods"
        }
    ],
    "sg:phone":"+1   ",
    "sg:postcode":"19031",
    "sg:province":"PA",
    "wof:name":"Medeast Post-Op & Surgical",
    "wof:placetype":"venue"
},
  "geometry": {"coordinates":[-75.213255,40.104421],"type":"Point"}
}