{
  "type": "Feature",
  "properties": {
    "addr:full":"180 Hickory Rd Carlisle PA 17015",
    "addr:housenumber":"180",
    "addr:postcode":"17015",
    "addr:street":"Hickory Rd",
    "iso:country":"US",
    "sg:address":"180 Hickory Rd",
    "sg:city":"Carlisle",
    "sg:classifiers":[
        {
            "category":"Retail",
            "subcategory":"Veterinary Services",
            "type":"Services"
        }
    ],
    "sg:phone":"+1 717 245 0885",
    "sg:postcode":"17015",
    "sg:province":"PA",
    "sg:tags":[
        "specialty"
    ],
    "wof:name":"Bowers Ralph Jr Dvm",
    "wof:placetype":"venue"
},
  "geometry": {"coordinates":[-77.106251,40.200484],"type":"Point"}
}