{
  "type": "Feature",
  "properties": {
    "addr:full":"211 E Harford St Milford PA 18337",
    "addr:housenumber":"211 e",
    "addr:postcode":"18337",
    "addr:street":"Harford St",
    "iso:country":"US",
    "sg:address":"211 E Harford St",
    "sg:city":"Milford",
    "sg:classifiers":[
        {
            "category":"Health Services",
            "subcategory":"Doctor",
            "type":"Services"
        }
    ],
    "sg:phone":"+1 570 296 2390",
    "sg:postcode":"18337",
    "sg:province":"PA",
    "sg:tags":[
        "dentist"
    ],
    "wof:name":"Harry G Boyle DMD",
    "wof:placetype":"venue"
},
  "geometry": {"coordinates":[-74.801333,41.320463],"type":"Point"}
}