{
  "type": "Feature",
  "properties": {
    "iso:country":"US",
    "sg:address":"800 Norman Rd",
    "sg:city":"York",
    "sg:classifiers":[
        {
            "category":"Professional",
            "subcategory":"Business Services",
            "type":"Services"
        },
        {
            "category":"Wholesale",
            "subcategory":"Motor Vehicles",
            "type":"Manufacturing & Wholesale Goods"
        }
    ],
    "sg:phone":"+1 717 843 2679",
    "sg:postcode":"17406",
    "sg:province":"PA",
    "sg:tags":[
        "auctioneer"
    ],
    "wof:name":"Nevin D Rentzel Auctioneer",
    "wof:placetype":"venue"
},
  "geometry": {"coordinates":[-76.724525,40.004256],"type":"Point"}
}