{
  "type": "Feature",
  "properties": {
    "addr:full":"711 E Walnut St Lewistown PA 17044",
    "addr:housenumber":"711",
    "addr:postcode":"17044",
    "addr:street":"E Walnut St",
    "iso:country":"US",
    "sg:address":"711 E Walnut St",
    "sg:city":"Lewistown",
    "sg:classifiers":[
        {
            "category":"Autos & Motor Vehicles",
            "subcategory":"Fuel & Gas Station",
            "type":"Retail Goods"
        }
    ],
    "sg:phone":"+1 717 248 1806",
    "sg:postcode":"17044",
    "sg:province":"PA",
    "sg:tags":[
        "oil"
    ],
    "wof:name":"Snedeker Oil Co",
    "wof:placetype":"venue"
},
  "geometry": {"coordinates":[-77.558391,40.611319],"type":"Point"}
}