{
  "type": "Feature",
  "properties": {
    "addr:full":"866 Troxel Rd Lansdale PA 19446",
    "addr:housenumber":"866",
    "addr:postcode":"19446",
    "addr:street":"Troxel Rd",
    "iso:country":"US",
    "sg:address":"866 Troxel Rd",
    "sg:city":"Lansdale",
    "sg:classifiers":[
        {
            "category":"Building & Trades",
            "subcategory":"Construction",
            "type":"Services"
        }
    ],
    "sg:phone":"+1 215 361 1008",
    "sg:postcode":"19446",
    "sg:province":"PA",
    "sg:tags":[
        "contractor",
        "painter",
        "hanging"
    ],
    "wof:name":"Rb Painting",
    "wof:placetype":"venue"
},
  "geometry": {"coordinates":[-75.315399,40.248299],"type":"Point"}
}