{
  "type": "Feature",
  "properties": {
    "iso:country":"US",
    "sg:address":"6 Hampshire Dr",
    "sg:city":"New Oxford",
    "sg:classifiers":[
        {
            "category":"Professional",
            "type":"Services"
        }
    ],
    "sg:phone":"+1   ",
    "sg:postcode":"17350",
    "sg:province":"PA",
    "wof:name":"Jim Houck - Dis",
    "wof:placetype":"venue"
},
  "geometry": {"coordinates":[-77.048908,39.871411],"type":"Point"}
}