{
  "type": "Feature",
  "properties": {
    "addr:full":"6401 Penn Ave Pittsburgh PA 15206",
    "addr:housenumber":"6401",
    "addr:postcode":"15206",
    "addr:street":"Penn Ave",
    "iso:country":"US",
    "sg:address":"6401 Penn Ave",
    "sg:city":"Pittsburgh",
    "sg:classifiers":[
        {
            "category":"Personal",
            "subcategory":"Beauty Salon",
            "type":"Services"
        }
    ],
    "sg:phone":"+1 412 362 2119",
    "sg:postcode":"15206",
    "sg:province":"PA",
    "sg:tags":[
        "nail",
        "manicuring"
    ],
    "wof:name":"Ultimate Nail Spa",
    "wof:placetype":"venue"
},
  "geometry": {"coordinates":[-79.91764000000001,40.457634],"type":"Point"}
}