{
  "type": "Feature",
  "properties": {
    "iso:country":"US",
    "sg:address":"544 Chester Pike",
    "sg:city":"Norwood",
    "sg:classifiers":[
        {
            "category":"Professional",
            "subcategory":"Accounting & Tax Preparation",
            "type":"Services"
        }
    ],
    "sg:phone":"+1   ",
    "sg:postcode":"19074",
    "sg:province":"PA",
    "wof:name":"Campbell & Associates",
    "wof:placetype":"venue"
},
  "geometry": {"coordinates":[-75.29949499999999,39.88882],"type":"Point"}
}