{
  "type": "Feature",
  "properties": {
    "iso:country":"US",
    "sg:address":"2500 N 33rd St",
    "sg:city":"Philadelphia",
    "sg:classifiers":[
        {
            "category":"Bars & Pubs",
            "type":"Food & Drink"
        }
    ],
    "sg:phone":"+1   ",
    "sg:postcode":"19132",
    "sg:province":"PA",
    "sg:tags":[
        "drinking"
    ],
    "wof:name":"Mann-Zi Bar",
    "wof:placetype":"venue"
},
  "geometry": {"coordinates":[-75.185457,39.995889],"type":"Point"}
}