{
  "type": "Feature",
  "properties": {
    "iso:country":"US",
    "sg:address":"268 Freeport Rd",
    "sg:city":"Pittsburgh",
    "sg:classifiers":[
        {
            "category":"Professional",
            "subcategory":"Management & Consulting",
            "type":"Services"
        }
    ],
    "sg:phone":"+1   ",
    "sg:postcode":"15238",
    "sg:province":"PA",
    "wof:name":"Allen Selig",
    "wof:placetype":"venue"
},
  "geometry": {"coordinates":[-79.862469,40.493048],"type":"Point"}
}