{
  "type": "Feature",
  "properties": {
    "iso:country":"US",
    "sg:address":"2342 S Mole St",
    "sg:city":"Philadelphia",
    "sg:classifiers":[
        {
            "category":"Arts & Performance",
            "subcategory":"Theater",
            "type":"Entertainment"
        }
    ],
    "sg:phone":"+1 215 462 6603",
    "sg:postcode":"19145",
    "sg:province":"PA",
    "sg:tags":[
        "group",
        "radiators-heating",
        "supply",
        "mo",
        "sales",
        "merchandise"
    ],
    "wof:name":"Adonis Band",
    "wof:placetype":"venue"
},
  "geometry": {"coordinates":[-75.173035,39.921705],"type":"Point"}
}