{
  "type": "Feature",
  "properties": {
    "iso:country":"US",
    "sg:address":"23 N 4th St",
    "sg:city":"Steelton",
    "sg:classifiers":[
        {
            "category":"Building & Trades",
            "subcategory":"Construction",
            "type":"Services"
        }
    ],
    "sg:phone":"+1 717 939 1028",
    "sg:postcode":"17113",
    "sg:province":"PA",
    "sg:tags":[
        "general",
        "contractor"
    ],
    "wof:name":"Selveys General Contracting",
    "wof:placetype":"venue"
},
  "geometry": {"coordinates":[-76.838576,40.236479],"type":"Point"}
}