{
  "type": "Feature",
  "properties": {
    "iso:country":"US",
    "sg:address":"19 Golf Course Rd",
    "sg:city":"Dillsburg",
    "sg:classifiers":[
        {
            "category":"Building & Trades",
            "subcategory":"Construction",
            "type":"Services"
        }
    ],
    "sg:phone":"+1 717 432 8833",
    "sg:postcode":"17019",
    "sg:province":"PA",
    "sg:tags":[
        "contractor"
    ],
    "wof:name":"Aspen Contracting Group",
    "wof:placetype":"venue"
},
  "geometry": {"coordinates":[-77.03094299999999,40.098251],"type":"Point"}
}