{
  "type": "Feature",
  "properties": {
    "iso:country":"US",
    "sg:address":"1730 Hidden Ln",
    "sg:city":"Lancaster",
    "sg:classifiers":[
        {
            "category":"Real Estate",
            "subcategory":"Architect",
            "type":"Services"
        }
    ],
    "sg:phone":"+1   ",
    "sg:postcode":"17603",
    "sg:province":"PA",
    "sg:tags":[
        "architectural"
    ],
    "wof:name":"Bradley Associates Inc",
    "wof:placetype":"venue"
},
  "geometry": {"coordinates":[-76.34467100000001,40.050521],"type":"Point"}
}