{
  "type": "Feature",
  "properties": {
    "iso:country":"US",
    "sg:address":"154 Deep Well Rd",
    "sg:city":"Schellsburg",
    "sg:classifiers":[
        {
            "category":"Professional",
            "subcategory":"Detective & Security Services",
            "type":"Services"
        }
    ],
    "sg:phone":"+1 814 733 4348",
    "sg:postcode":"15559",
    "sg:province":"PA",
    "sg:tags":[
        "information",
        "bureau"
    ],
    "wof:name":"D & D Services",
    "wof:placetype":"venue"
},
  "geometry": {"coordinates":[-78.6437,40.064147],"type":"Point"}
}