{
  "type": "Feature",
  "properties": {
    "iso:country":"US",
    "sg:address":"3421 Paxton St",
    "sg:city":"Harrisburg",
    "sg:classifiers":[
        {
            "category":"Shopping",
            "subcategory":"Shoes",
            "type":"Retail Goods"
        }
    ],
    "sg:phone":"+1   ",
    "sg:postcode":"17111",
    "sg:province":"PA",
    "wof:name":"Payless Shoesource 3498",
    "wof:placetype":"venue"
},
  "geometry": {"coordinates":[-76.83098099999999,40.254092],"type":"Point"}
}