{
  "type": "Feature",
  "properties": {
    "iso:country":"US",
    "sg:address":"528 N New St Unit 3",
    "sg:city":"Bethlehem",
    "sg:classifiers":[
        {
            "category":"Real Estate",
            "subcategory":"Real Estate Services",
            "type":"Services"
        },
        {
            "category":"Insurance",
            "subcategory":"Hazard Insurance",
            "type":"Services"
        },
        {
            "category":"Banks & Credit Unions",
            "subcategory":"Financial Services",
            "type":"Services"
        }
    ],
    "sg:phone":"+1 610 332 0601",
    "sg:postcode":"18018",
    "sg:province":"PA",
    "sg:tags":[
        "loan",
        "broker",
        "mortgage"
    ],
    "wof:name":"Wf & K Mortgage",
    "wof:placetype":"venue"
},
  "geometry": {"coordinates":[-75.378502,40.6213],"type":"Point"}
}