{
  "type": "Feature",
  "properties": {
    "iso:country":"US",
    "sg:address":"126 N Hanover St",
    "sg:city":"Carlisle",
    "sg:classifiers":[
        {
            "category":"Real Estate",
            "subcategory":"Real Estate Agent",
            "type":"Services"
        }
    ],
    "sg:phone":"+1 717 243 6646",
    "sg:postcode":"17013",
    "sg:province":"PA",
    "sg:tags":[
        "appraiser"
    ],
    "sg:website":"www.swbarrett.com",
    "wof:name":"Steven W Barrett Real Estate",
    "wof:placetype":"venue"
},
  "geometry": {"coordinates":[-77.18892200000001,40.203131],"type":"Point"}
}