{
  "type": "Feature",
  "properties": {
    "iso:country":"US",
    "sg:address":"181 W Beau St",
    "sg:city":"Washington",
    "sg:classifiers":[
        {
            "category":"Health Services",
            "subcategory":"Doctor",
            "type":"Services"
        }
    ],
    "sg:phone":"+1 724 223 1067",
    "sg:postcode":"15301",
    "sg:province":"PA",
    "sg:tags":[
        "physician",
        "surgeon"
    ],
    "wof:name":"Centerville Clinic",
    "wof:placetype":"venue"
},
  "geometry": {"coordinates":[-80.250344,40.170152],"type":"Point"}
}