{
  "type": "Feature",
  "properties": {
    "addr:full":"60 Chestnut Ave Devon PA 19333",
    "addr:housenumber":"60",
    "addr:postcode":"19333",
    "addr:street":"Chestnut Ave",
    "iso:country":"US",
    "sg:address":"60 Chestnut Ave",
    "sg:city":"Devon",
    "sg:classifiers":[
        {
            "category":"Professional",
            "type":"Services"
        }
    ],
    "sg:phone":"+1   ",
    "sg:postcode":"19333",
    "sg:province":"PA",
    "wof:name":"Nova",
    "wof:placetype":"venue"
},
  "geometry": {"coordinates":[-75.416641,40.047317],"type":"Point"}
}