{
  "type": "Feature",
  "properties": {
    "iso:country":"US",
    "sg:address":"1900 Market St",
    "sg:city":"Philadelphia",
    "sg:classifiers":[
        {
            "category":"Professional",
            "subcategory":"Lawyer & Legal Services",
            "type":"Services"
        }
    ],
    "sg:phone":"+1 215 665 3716",
    "sg:postcode":"19103",
    "sg:province":"PA",
    "wof:name":"Doret David Atty",
    "wof:placetype":"venue"
},
  "geometry": {"coordinates":[-75.171572,39.953244],"type":"Point"}
}