{
  "type": "Feature",
  "properties": {
    "addr:full":"2480 Frankford Ave Philadelphia PA 19125",
    "addr:housenumber":"2480",
    "addr:postcode":"19125",
    "addr:street":"Frankford Ave",
    "iso:country":"US",
    "sg:address":"2480 Frankford Ave",
    "sg:city":"Philadelphia",
    "sg:classifiers":[
        {
            "category":"Food & Beverages",
            "subcategory":"Groceries & Convenience Stores",
            "type":"Retail Goods"
        }
    ],
    "sg:phone":"+1 215 634 4344",
    "sg:postcode":"19125",
    "sg:province":"PA",
    "wof:name":"Angies Deli",
    "wof:placetype":"venue"
},
  "geometry": {"coordinates":[-75.126023,39.983126],"type":"Point"}
}