{
  "type": "Feature",
  "properties": {
    "iso:country":"US",
    "sg:address":"24 Rocherty Rd",
    "sg:city":"Lebanon",
    "sg:classifiers":[
        {
            "category":"Retail",
            "subcategory":"Auto Repair",
            "type":"Services"
        }
    ],
    "sg:phone":"+1 717 273 6511",
    "sg:postcode":"17042",
    "sg:province":"PA",
    "sg:tags":[
        "repairing",
        "automobile"
    ],
    "wof:name":"Eagle Brothers Used Cars",
    "wof:placetype":"venue"
},
  "geometry": {"coordinates":[-76.410617,40.305768],"type":"Point"}
}