{
  "type": "Feature",
  "properties": {
    "iso:country":"US",
    "sg:address":"340 Glen Gary Dr",
    "sg:city":"Havertown",
    "sg:classifiers":[
        {
            "category":"Building & Trades",
            "subcategory":"Construction",
            "type":"Services"
        }
    ],
    "sg:phone":"+1 610 853 3888",
    "sg:postcode":"19083",
    "sg:province":"PA",
    "sg:tags":[
        "brick-fire",
        "brick-clay-common",
        "face"
    ],
    "wof:name":"Everyone Wins",
    "wof:placetype":"venue"
},
  "geometry": {"coordinates":[-75.331799,39.972709],"type":"Point"}
}