{
  "type": "Feature",
  "properties": {
    "iso:country":"US",
    "sg:address":"2023 Bethel Rd",
    "sg:city":"Worcester",
    "sg:classifiers":[
        {
            "category":"Building & Trades",
            "subcategory":"Construction",
            "type":"Services"
        }
    ],
    "sg:phone":"+1 610 222 4932",
    "sg:postcode":"19490",
    "sg:province":"PA",
    "sg:tags":[
        "contractor"
    ],
    "wof:name":"Knock On Wood",
    "wof:placetype":"venue"
},
  "geometry": {"coordinates":[-75.34050000000001,40.205799],"type":"Point"}
}