{
  "type": "Feature",
  "properties": {
    "addr:full":"6115 Sullivan Trl Nazareth PA 18064",
    "addr:housenumber":"6115",
    "addr:postcode":"18064",
    "addr:street":"Sullivan Trl",
    "iso:country":"US",
    "sg:address":"6115 Sullivan Trl",
    "sg:city":"Nazareth",
    "sg:classifiers":[
        {
            "category":"Building & Trades",
            "subcategory":"Construction",
            "type":"Services"
        }
    ],
    "sg:phone":"+1   ",
    "sg:postcode":"18064",
    "sg:province":"PA",
    "sg:tags":[
        "house"
    ],
    "wof:name":"Bates Construction",
    "wof:placetype":"venue"
},
  "geometry": {"coordinates":[-75.284767,40.794953],"type":"Point"}
}