{
  "type": "Feature",
  "properties": {
    "iso:country":"US",
    "sg:address":"232 Strawberry Cir",
    "sg:city":"Langhorne",
    "sg:classifiers":[
        {
            "category":"Manufacturing",
            "subcategory":"Tools & Machinery",
            "type":"Manufacturing & Wholesale Goods"
        }
    ],
    "sg:phone":"+1   ",
    "sg:postcode":"19047",
    "sg:province":"PA",
    "sg:tags":[
        "equipment",
        "mfg"
    ],
    "wof:name":"Daves Lawn Cutting",
    "wof:placetype":"venue"
},
  "geometry": {"coordinates":[-74.909679,40.192226],"type":"Point"}
}