{
  "type": "Feature",
  "properties": {
    "addr:full":"306 Latrobe Derry Rd Loyalhanna PA 15661",
    "addr:housenumber":"306",
    "addr:postcode":"15661",
    "addr:street":"Latrobe Derry Rd",
    "iso:country":"US",
    "sg:address":"306 Latrobe Derry Rd",
    "sg:city":"Loyalhanna",
    "sg:classifiers":[
        {
            "category":"Building & Trades",
            "subcategory":"Construction",
            "type":"Services"
        }
    ],
    "sg:phone":"+1 724 537 3335",
    "sg:postcode":"15661",
    "sg:province":"PA",
    "sg:tags":[
        "painter"
    ],
    "wof:name":"Latrobe Industrial Mntnc Inc",
    "wof:placetype":"venue"
},
  "geometry": {"coordinates":[-79.35639999999999,40.322302],"type":"Point"}
}