{
  "type": "Feature",
  "properties": {
    "iso:country":"US",
    "sg:address":"3002 N Front St",
    "sg:city":"Whitehall",
    "sg:classifiers":[
        {
            "category":"Insurance",
            "subcategory":"Insurance Agent",
            "type":"Services"
        }
    ],
    "sg:phone":"+1   ",
    "sg:postcode":"18052",
    "sg:province":"PA",
    "wof:name":"West G O Jr",
    "wof:placetype":"venue"
},
  "geometry": {"coordinates":[-75.48814,40.66222],"type":"Point"}
}