{
  "type": "Feature",
  "properties": {
    "iso:country":"US",
    "sg:address":"180 4th St",
    "sg:city":"Houtzdale",
    "sg:classifiers":[
        {
            "category":"Organizations",
            "subcategory":"Religious Organization",
            "type":"Services"
        }
    ],
    "sg:phone":"+1 814 378 5150",
    "sg:postcode":"16651",
    "sg:province":"PA",
    "sg:tags":[
        "church"
    ],
    "wof:name":"New Hope Christian Fellowship",
    "wof:placetype":"venue"
},
  "geometry": {"coordinates":[-78.36787099999999,40.828382],"type":"Point"}
}