{
  "type": "Feature",
  "properties": {
    "addr:full":"2375 Woodward St Philadelphia PA 19115",
    "addr:housenumber":"2375",
    "addr:postcode":"19115",
    "addr:street":"Woodward St",
    "iso:country":"US",
    "sg:address":"2375 Woodward St",
    "sg:city":"Philadelphia",
    "sg:classifiers":[
        {
            "category":"Health Services",
            "subcategory":"Doctor",
            "type":"Services"
        }
    ],
    "sg:phone":"+1 215 673 6696",
    "sg:postcode":"19115",
    "sg:province":"PA",
    "sg:tags":[
        "physician",
        "surgeon"
    ],
    "wof:name":"Abraham Perlman MD",
    "wof:placetype":"venue"
},
  "geometry": {"coordinates":[-75.03917199999999,40.071757],"type":"Point"}
}