{
  "type": "Feature",
  "properties": {
    "iso:country":"US",
    "sg:address":"960 Old York Rd Ste 203",
    "sg:city":"Abington",
    "sg:classifiers":[
        {
            "category":"Building & Trades",
            "subcategory":"Construction",
            "type":"Services"
        }
    ],
    "sg:phone":"+1 215 947 6140",
    "sg:postcode":"19001",
    "sg:province":"PA",
    "sg:tags":[
        "system",
        "specialty",
        "heating",
        "contractor",
        "air conditioning"
    ],
    "wof:name":"Rite Temp Inc Heating & Air Conditioning, Inc",
    "wof:placetype":"venue"
},
  "geometry": {"coordinates":[-75.123186,40.108788],"type":"Point"}
}