{
  "type": "Feature",
  "properties": {
    "addr:full":"118 W Main St Fleetwood PA 19522",
    "addr:housenumber":"118",
    "addr:postcode":"19522",
    "addr:street":"W Main St",
    "iso:country":"US",
    "sg:address":"118 W Main St",
    "sg:city":"Fleetwood",
    "sg:classifiers":[
        {
            "category":"Manufacturing",
            "subcategory":"Pet Food",
            "type":"Manufacturing & Wholesale Goods"
        }
    ],
    "sg:phone":"+1 610 944 7654",
    "sg:postcode":"19522",
    "sg:province":"PA",
    "sg:tags":[
        "flour"
    ],
    "wof:name":"F M Brown Sons Inc",
    "wof:placetype":"venue"
},
  "geometry": {"coordinates":[-75.82209400000001,40.452337],"type":"Point"}
}