{
  "type": "Feature",
  "properties": {
    "iso:country":"US",
    "sg:address":"599 Old Berwick Rd",
    "sg:city":"Bloomsburg",
    "sg:classifiers":[
        {
            "category":"Professional",
            "subcategory":"Business Services",
            "type":"Services"
        },
        {
            "category":"Health Services",
            "subcategory":"Doctor",
            "type":"Services"
        }
    ],
    "sg:phone":"+1 570 784 8460",
    "sg:postcode":"17815",
    "sg:province":"PA",
    "sg:tags":[
        "dentist",
        "medical"
    ],
    "wof:name":"Stephen T Fleetwood DDS",
    "wof:placetype":"venue"
},
  "geometry": {"coordinates":[-76.442446,41.001522],"type":"Point"}
}