{
  "type": "Feature",
  "properties": {
    "iso:country":"US",
    "sg:address":"881 Hex Hwy",
    "sg:city":"Hamburg",
    "sg:classifiers":[
        {
            "category":"Building & Trades",
            "subcategory":"Plumbing",
            "type":"Services"
        }
    ],
    "sg:phone":"+1 610 562 9325",
    "sg:postcode":"19526",
    "sg:province":"PA",
    "sg:tags":[
        "control",
        "air",
        "pollution"
    ],
    "wof:name":"SGF Consulting Svc",
    "wof:placetype":"venue"
},
  "geometry": {"coordinates":[-76.020436,40.537577],"type":"Point"}
}