{
  "type": "Feature",
  "properties": {
    "iso:country":"US",
    "sg:address":"1200 N 7th St",
    "sg:city":"Harrisburg",
    "sg:classifiers":[
        {
            "category":"Home & Garden",
            "subcategory":"Hardware",
            "type":"Retail Goods"
        }
    ],
    "sg:phone":"+1 717 260 5295",
    "sg:postcode":"17102",
    "sg:province":"PA",
    "sg:tags":[
        "store"
    ],
    "wof:name":"A Fscme Local 1224",
    "wof:placetype":"venue"
},
  "geometry": {"coordinates":[-76.883752,40.271624],"type":"Point"}
}