{
  "type": "Feature",
  "properties": {
    "iso:country":"US",
    "sg:address":"45 Greenhill Rd",
    "sg:city":"Coatesville",
    "sg:classifiers":[
        {
            "category":"Manufacturing",
            "subcategory":"Chemicals & Compounds",
            "type":"Manufacturing & Wholesale Goods"
        }
    ],
    "sg:phone":"+1   ",
    "sg:postcode":"19320",
    "sg:province":"PA",
    "sg:tags":[
        "active",
        "surface",
        "agent",
        "mfg"
    ],
    "wof:name":"Geofence",
    "wof:placetype":"venue"
},
  "geometry": {"coordinates":[-75.798579,40.019831],"type":"Point"}
}