{
  "type": "Feature",
  "properties": {
    "iso:country":"US",
    "sg:address":"343 Forest Grove Rd Ste 1",
    "sg:city":"Coraopolis",
    "sg:classifiers":[
        {
            "category":"Organizations",
            "subcategory":"Religious Organization",
            "type":"Services"
        }
    ],
    "sg:phone":"+1 412 771 0848",
    "sg:postcode":"15108",
    "sg:province":"PA",
    "wof:name":"St Malachy Church",
    "wof:placetype":"venue"
},
  "geometry": {"coordinates":[-80.107201,40.4814],"type":"Point"}
}