{
  "type": "Feature",
  "properties": {
    "iso:country":"US",
    "sg:address":"1650 Limekiln Pike",
    "sg:city":"Dresher",
    "sg:classifiers":[
        {
            "category":"Shopping",
            "type":"Retail Goods"
        }
    ],
    "sg:phone":"+1 215 628 0544",
    "sg:postcode":"19025",
    "sg:province":"PA",
    "sg:tags":[
        "merchandise"
    ],
    "wof:name":"Dresher Pet Shop",
    "wof:placetype":"venue"
},
  "geometry": {"coordinates":[-75.169434,40.147343],"type":"Point"}
}