{
  "type": "Feature",
  "properties": {
    "addr:full":"818 S Railroad St Myerstown PA 17067",
    "addr:housenumber":"818",
    "addr:postcode":"17067",
    "addr:street":"S Railroad St",
    "iso:country":"US",
    "sg:address":"818 S Railroad St",
    "sg:city":"Myerstown",
    "sg:classifiers":[
        {
            "category":"Utilities",
            "subcategory":"Fuel Oil & Lpg",
            "type":"Services"
        }
    ],
    "sg:phone":"+1 717 866 7412",
    "sg:postcode":"17067",
    "sg:province":"PA",
    "sg:tags":[
        "coal"
    ],
    "wof:name":"Neuman Oil & Coal",
    "wof:placetype":"venue"
},
  "geometry": {"coordinates":[-76.30240999999999,40.365592],"type":"Point"}
}