{
  "type": "Feature",
  "properties": {
    "iso:country":"US",
    "sg:address":"7116 Sladek Rd",
    "sg:city":"Plumsteadville",
    "sg:classifiers":[
        {
            "category":"Health Services",
            "subcategory":"Health Practitioner",
            "type":"Services"
        }
    ],
    "sg:phone":"+1   ",
    "sg:postcode":"18938",
    "sg:province":"PA",
    "wof:name":"Andrea Kollath Dr",
    "wof:placetype":"venue"
},
  "geometry": {"coordinates":[-75.064902,40.406865],"type":"Point"}
}