{
  "type": "Feature",
  "properties": {
    "iso:country":"US",
    "sg:address":"120 Earland Dr",
    "sg:city":"New Holland",
    "sg:classifiers":[
        {
            "category":"Professional",
            "type":"Services"
        }
    ],
    "sg:phone":"+1 717 355 0571",
    "sg:postcode":"17557",
    "sg:province":"PA",
    "sg:tags":[
        "purchasing"
    ],
    "wof:name":"Good's Stores Distribution Ctr",
    "wof:placetype":"venue"
},
  "geometry": {"coordinates":[-76.05847799999999,40.113516],"type":"Point"}
}