{
  "type": "Feature",
  "properties": {
    "iso:country":"US",
    "sg:address":"2069 W Harrisburg Pike",
    "sg:city":"Middletown",
    "sg:classifiers":[
        {
            "category":"Autos & Motor Vehicles",
            "subcategory":"Automobile Sales",
            "type":"Retail Goods"
        }
    ],
    "sg:phone":"+1   ",
    "sg:postcode":"17057",
    "sg:province":"PA",
    "sg:tags":[
        "used"
    ],
    "wof:name":"Steven Seagal Auto Leasing",
    "wof:placetype":"venue"
},
  "geometry": {"coordinates":[-76.766296,40.200528],"type":"Point"}
}