{
  "type": "Feature",
  "properties": {
    "iso:country":"US",
    "sg:address":"635 W Emmaus Ave",
    "sg:city":"Allentown",
    "sg:classifiers":[
        {
            "category":"Health Services",
            "subcategory":"Dentist",
            "type":"Services"
        }
    ],
    "sg:phone":"+1 610 797 1420",
    "sg:postcode":"18103",
    "sg:province":"PA",
    "wof:name":"Dillon Thos M Dntst",
    "wof:placetype":"venue"
},
  "geometry": {"coordinates":[-75.459999,40.5751],"type":"Point"}
}