{
  "type": "Feature",
  "properties": {
    "addr:full":"130 Almshouse Rd Ste 404A Richboro PA 18954",
    "addr:housenumber":"130",
    "addr:postcode":"18954",
    "addr:street":"Almshouse Rd Ste 404A",
    "iso:country":"US",
    "sg:address":"130 Almshouse Rd Ste 404A",
    "sg:city":"Richboro",
    "sg:classifiers":[
        {
            "category":"Personal",
            "subcategory":"Beauty Salon",
            "type":"Services"
        }
    ],
    "sg:phone":"+1 215 953 9977",
    "sg:postcode":"18954",
    "sg:province":"PA",
    "wof:name":"Monet Hair Artistry",
    "wof:placetype":"venue"
},
  "geometry": {"coordinates":[-75.01486199999999,40.21639],"type":"Point"}
}