{
  "type": "Feature",
  "properties": {
    "iso:country":"US",
    "sg:address":"134 Market St",
    "sg:city":"Kittanning",
    "sg:classifiers":[
        {
            "category":"Shopping",
            "subcategory":"Computers & Home Electronics",
            "type":"Retail Goods"
        }
    ],
    "sg:phone":"+1 724 543 3582",
    "sg:postcode":"16201",
    "sg:province":"PA",
    "wof:name":"Delta Computers",
    "wof:placetype":"venue"
},
  "geometry": {"coordinates":[-79.51981499999999,40.814046],"type":"Point"}
}