{
  "type": "Feature",
  "properties": {
    "addr:full":"912 E Highland St Allentown PA 18109",
    "addr:housenumber":"912",
    "addr:postcode":"18109",
    "addr:street":"E Highland St",
    "iso:country":"US",
    "sg:address":"912 E Highland St",
    "sg:city":"Allentown",
    "sg:classifiers":[
        {
            "category":"Retail",
            "subcategory":"Car Wash",
            "type":"Services"
        }
    ],
    "sg:phone":"+1 610 439 2884",
    "sg:postcode":"18109",
    "sg:province":"PA",
    "sg:tags":[
        "automobile",
        "detail",
        "clean"
    ],
    "wof:name":"Detailers Plus Car & Boat Care",
    "wof:placetype":"venue"
},
  "geometry": {"coordinates":[-75.443254,40.626534],"type":"Point"}
}