{
  "type": "Feature",
  "properties": {
    "addr:full":"1060 Baltimore St Hanover PA 17331",
    "addr:housenumber":"1060",
    "addr:postcode":"17331",
    "addr:street":"Baltimore St",
    "iso:country":"US",
    "sg:address":"1060 Baltimore St",
    "sg:city":"Hanover",
    "sg:classifiers":[
        {
            "category":"Real Estate",
            "subcategory":"Real Estate Agent",
            "type":"Services"
        }
    ],
    "sg:phone":"+1 717 633 9598",
    "sg:postcode":"17331",
    "sg:province":"PA",
    "wof:name":"Realty Executives",
    "wof:placetype":"venue"
},
  "geometry": {"coordinates":[-76.963252,39.781134],"type":"Point"}
}