{
  "type": "Feature",
  "properties": {
    "addr:full":"281 Staff Rd Slippery Rock PA 16057",
    "addr:housenumber":"281",
    "addr:postcode":"16057",
    "addr:street":"Staff Rd",
    "iso:country":"US",
    "sg:address":"281 Staff Rd",
    "sg:city":"Slippery Rock",
    "sg:classifiers":[
        {
            "category":"Recreation",
            "type":"Entertainment"
        }
    ],
    "sg:phone":"+1 724 794 6242",
    "sg:postcode":"16057",
    "sg:province":"PA",
    "sg:tags":[
        "campground",
        "membership",
        "association"
    ],
    "wof:name":"Moraine Camplands",
    "wof:placetype":"venue"
},
  "geometry": {"coordinates":[-79.99004100000001,40.993921],"type":"Point"}
}