{
  "type": "Feature",
  "properties": {
    "addr:full":"122 Union St Catasauqua PA 18032",
    "addr:housenumber":"122",
    "addr:postcode":"18032",
    "addr:street":"Union St",
    "iso:country":"US",
    "sg:address":"122 Union St",
    "sg:city":"Catasauqua",
    "sg:classifiers":[
        {
            "category":"Social Services",
            "type":"Services"
        }
    ],
    "sg:phone":"+1 610 264 8366",
    "sg:postcode":"18032",
    "sg:province":"PA",
    "sg:tags":[
        "organization",
        "welfare"
    ],
    "wof:name":"Catasaqua Ministerium Food Bnk",
    "wof:placetype":"venue"
},
  "geometry": {"coordinates":[-75.46837600000001,40.650664],"type":"Point"}
}