{
  "type": "Feature",
  "properties": {
    "addr:full":"12402 Main St Titusville PA 16354",
    "addr:housenumber":"12402",
    "addr:postcode":"16354",
    "addr:street":"Main St",
    "iso:country":"US",
    "sg:address":"12402 Main St",
    "sg:city":"Titusville",
    "sg:classifiers":[
        {
            "category":"Bars & Pubs",
            "type":"Food & Drink"
        }
    ],
    "sg:phone":"+1 814 827 9921",
    "sg:postcode":"16354",
    "sg:province":"PA",
    "wof:name":"Oaks",
    "wof:placetype":"venue"
},
  "geometry": {"coordinates":[-79.72031699999999,41.648482],"type":"Point"}
}