{
  "type": "Feature",
  "properties": {
    "iso:country":"US",
    "sg:address":"920 Settlers Ridge Rd",
    "sg:city":"Pittsburgh",
    "sg:classifiers":[
        {
            "category":"Building & Trades",
            "subcategory":"Construction",
            "type":"Services"
        }
    ],
    "sg:phone":"+1 412 968 0190",
    "sg:postcode":"15238",
    "sg:province":"PA",
    "sg:tags":[
        "home",
        "builder"
    ],
    "wof:name":"Mitrakos Homes Inc",
    "wof:placetype":"venue"
},
  "geometry": {"coordinates":[-79.909387,40.538135],"type":"Point"}
}