{
  "type": "Feature",
  "properties": {
    "addr:full":"Arrott Building Pittsburgh PA 15222",
    "addr:postcode":"15222",
    "iso:country":"US",
    "sg:address":"Arrott Building",
    "sg:city":"Pittsburgh",
    "sg:classifiers":[
        {
            "category":"Professional",
            "subcategory":"Lawyer & Legal Services",
            "type":"Services"
        }
    ],
    "sg:phone":"+1 412 765 1338",
    "sg:postcode":"15222",
    "sg:province":"PA",
    "wof:name":"Hightower Janet R Attorney",
    "wof:placetype":"venue"
},
  "geometry": {"coordinates":[-80.00129699999999,40.4394],"type":"Point"}
}