{
  "type": "Feature",
  "properties": {
    "iso:country":"US",
    "sg:address":"2 S Bacton Hill Rd",
    "sg:city":"Malvern",
    "sg:classifiers":[
        {
            "category":"Manufacturing",
            "subcategory":"Furniture",
            "type":"Manufacturing & Wholesale Goods"
        }
    ],
    "sg:phone":"+1   ",
    "sg:postcode":"19355",
    "sg:province":"PA",
    "sg:tags":[
        "household",
        "wood",
        "mfg"
    ],
    "wof:name":"Contract Solutions",
    "wof:placetype":"venue"
},
  "geometry": {"coordinates":[-75.57902199999999,40.042091],"type":"Point"}
}