{
  "type": "Feature",
  "properties": {
    "iso:country":"US",
    "sg:address":"718 Arch St",
    "sg:city":"Philadelphia",
    "sg:classifiers":[
        {
            "category":"Professional",
            "subcategory":"Business Services",
            "type":"Services"
        }
    ],
    "sg:phone":"+1 215 627 6700",
    "sg:postcode":"19106",
    "sg:province":"PA",
    "sg:tags":[
        "delivery",
        "courier"
    ],
    "wof:name":"Phila Express Courier",
    "wof:placetype":"venue"
},
  "geometry": {"coordinates":[-75.151802,39.9529],"type":"Point"}
}