{
  "type": "Feature",
  "properties": {
    "iso:country":"US",
    "sg:address":"318 W Union Blvd",
    "sg:city":"Bethlehem",
    "sg:classifiers":[
        {
            "category":"Retail",
            "subcategory":"Auto Repair",
            "type":"Services"
        }
    ],
    "sg:phone":"+1 610 867 8841",
    "sg:postcode":"18018",
    "sg:province":"PA",
    "sg:tags":[
        "repairing",
        "automobile"
    ],
    "wof:name":"Dave & Wayne's Auto Center",
    "wof:placetype":"venue"
},
  "geometry": {"coordinates":[-75.387199,40.625301],"type":"Point"}
}