{
  "type": "Feature",
  "properties": {
    "iso:country":"US",
    "sg:address":"570 Dunksferry Rd",
    "sg:city":"Bensalem",
    "sg:classifiers":[
        {
            "category":"Professional",
            "subcategory":"Business Services",
            "type":"Services"
        }
    ],
    "sg:phone":"+1 215 245 1760",
    "sg:postcode":"19020",
    "sg:province":"PA",
    "sg:tags":[
        "water",
        "treatment"
    ],
    "wof:name":"Water Management Svc",
    "wof:placetype":"venue"
},
  "geometry": {"coordinates":[-74.926845,40.081478],"type":"Point"}
}