{
  "type": "Feature",
  "properties": {
    "iso:country":"US",
    "sg:address":"995 Linden St",
    "sg:city":"Sharon",
    "sg:classifiers":[
        {
            "category":"Social Services",
            "type":"Services"
        },
        {
            "category":"Personal",
            "type":"Services"
        }
    ],
    "sg:phone":"+1 814 676 8263",
    "sg:postcode":"16146",
    "sg:province":"PA",
    "sg:tags":[
        "family",
        "professional",
        "counselors-licensed",
        "individual",
        "marriage",
        "child",
        "counseling",
        "counselor"
    ],
    "sg:website":"http://www.catholiccharitiesusa.org",
    "wof:name":"Catholic Charities Counseling And Adoption Services Inc",
    "wof:placetype":"venue"
},
  "geometry": {"coordinates":[-80.490832,41.234679],"type":"Point"}
}