{
  "type": "Feature",
  "properties": {
    "iso:country":"US",
    "sg:address":"1007 S 2nd St",
    "sg:city":"Clearfield",
    "sg:classifiers":[
        {
            "category":"Restaurant",
            "type":"Food & Drink"
        }
    ],
    "sg:menulink":"http://www.allmenus.com/pa/lawrence/205987-mcdonalds/menu/",
    "sg:phone":"+1 814 765 5985",
    "sg:postcode":"16830",
    "sg:province":"PA",
    "sg:tags":[
        "burger",
        "american"
    ],
    "wof:name":"McDonald's",
    "wof:placetype":"venue"
},
  "geometry": {"coordinates":[-78.44905199999999,41.010777],"type":"Point"}
}