{
  "type": "Feature",
  "properties": {
    "iso:country":"US",
    "sg:address":"2051 Dublin Rd",
    "sg:city":"Waterford",
    "sg:classifiers":[
        {
            "category":"Retail",
            "subcategory":"Auto Repair",
            "type":"Services"
        }
    ],
    "sg:phone":"+1 814 796 3527",
    "sg:postcode":"16441",
    "sg:province":"PA",
    "sg:tags":[
        "body",
        "painting",
        "repairing",
        "automobile"
    ],
    "wof:name":"Tom Weary's Auto Body",
    "wof:placetype":"venue"
},
  "geometry": {"coordinates":[-79.939177,41.962861],"type":"Point"}
}