{
  "type": "Feature",
  "properties": {
    "iso:country":"US",
    "sg:address":"2913 Pittsburgh Ave",
    "sg:city":"Erie",
    "sg:classifiers":[
        {
            "category":"Home & Garden",
            "subcategory":"Building Materials",
            "type":"Retail Goods"
        },
        {
            "category":"Building & Trades",
            "subcategory":"Construction",
            "type":"Services"
        },
        {
            "category":"Building & Trades",
            "subcategory":"Electrical",
            "type":"Services"
        }
    ],
    "sg:phone":"+1 814 866 0939",
    "sg:postcode":"16508",
    "sg:province":"PA",
    "sg:tags":[
        "repair",
        "electrician",
        "maintenance",
        "improvement"
    ],
    "wof:name":"ZEWE Electric Inc",
    "wof:placetype":"venue"
},
  "geometry": {"coordinates":[-80.12137199999999,42.091189],"type":"Point"}
}