{
  "type": "Feature",
  "properties": {
    "addr:full":"1489 Ridge Rd Apollo PA 15686",
    "addr:housenumber":"1489",
    "addr:postcode":"15686",
    "addr:street":"Ridge Rd",
    "iso:country":"US",
    "sg:address":"1489 Ridge Rd",
    "sg:city":"Apollo",
    "sg:classifiers":[
        {
            "category":"Manufacturing",
            "subcategory":"Tools & Machinery",
            "type":"Manufacturing & Wholesale Goods"
        }
    ],
    "sg:phone":"+1 724 478 1414",
    "sg:postcode":"15686",
    "sg:province":"PA",
    "sg:tags":[
        "die",
        "maker"
    ],
    "sg:website":"www.rearicktooling.com",
    "wof:name":"JIT Enterprises",
    "wof:placetype":"venue"
},
  "geometry": {"coordinates":[-79.476134,40.623163],"type":"Point"}
}