{
  "type": "Feature",
  "properties": {
    "iso:country":"US",
    "sg:address":"1003 Church St",
    "sg:city":"Jessup",
    "sg:classifiers":[
        {
            "category":"Retail",
            "subcategory":"Funeral Services",
            "type":"Services"
        }
    ],
    "sg:phone":"+1 570 489 1152",
    "sg:postcode":"18434",
    "sg:province":"PA",
    "sg:tags":[
        "director"
    ],
    "wof:name":"Arthur A Albini Funeral Home",
    "wof:placetype":"venue"
},
  "geometry": {"coordinates":[-75.56234600000001,41.468866],"type":"Point"}
}