{
  "type": "Feature",
  "properties": {
    "addr:full":"220 Hazel Ave Folsom PA 19033",
    "addr:housenumber":"220",
    "addr:postcode":"19033",
    "addr:street":"Hazel Ave",
    "iso:country":"US",
    "sg:address":"220 Hazel Ave",
    "sg:city":"Folsom",
    "sg:classifiers":[
        {
            "category":"Building & Trades",
            "subcategory":"Construction",
            "type":"Services"
        }
    ],
    "sg:phone":"+1   ",
    "sg:postcode":"19033",
    "sg:province":"PA",
    "sg:tags":[
        "home",
        "family",
        "contractor"
    ],
    "wof:name":"Leonard Builders",
    "wof:placetype":"venue"
},
  "geometry": {"coordinates":[-75.324471,39.890102],"type":"Point"}
}