{
  "type": "Feature",
  "properties": {
    "iso:country":"US",
    "sg:address":"630 Cherry Tree Ln",
    "sg:city":"Uniontown",
    "sg:classifiers":[
        {
            "category":"Health Services",
            "subcategory":"Doctor",
            "type":"Services"
        }
    ],
    "sg:phone":"+1 724 437 6000",
    "sg:postcode":"15401",
    "sg:province":"PA",
    "sg:tags":[
        "physician",
        "surgeon"
    ],
    "sg:website":"www.martinelli-eye.com",
    "wof:name":"Uniontown Medical Eye Clinic",
    "wof:placetype":"venue"
},
  "geometry": {"coordinates":[-79.754481,39.900188],"type":"Point"}
}