{
  "type": "Feature",
  "properties": {
    "iso:country":"US",
    "sg:address":"201 Churchill Rd",
    "sg:city":"Turtle Creek",
    "sg:classifiers":[
        {
            "category":"Retail",
            "subcategory":"Animal Services",
            "type":"Services"
        }
    ],
    "sg:phone":"+1   ",
    "sg:postcode":"15145",
    "sg:province":"PA",
    "wof:name":"Roses Groom Room",
    "wof:placetype":"venue"
},
  "geometry": {"coordinates":[-79.82709800000001,40.422823],"type":"Point"}
}