{
  "type": "Feature",
  "properties": {
    "iso:country":"US",
    "sg:address":"412 Paxinosa Rd E",
    "sg:city":"Easton",
    "sg:classifiers":[
        {
            "category":"Education",
            "subcategory":"Music School",
            "type":"Public Place"
        },
        {
            "category":"Education",
            "subcategory":"School",
            "type":"Public Place"
        }
    ],
    "sg:phone":"+1 610 252 4292",
    "sg:postcode":"18040",
    "sg:province":"PA",
    "wof:name":"George A Gollub",
    "wof:placetype":"venue"
},
  "geometry": {"coordinates":[-75.20354500000001,40.713971],"type":"Point"}
}