{
  "type": "Feature",
  "properties": {
    "addr:full":"1312 N 3rd St Harrisburg PA 17102",
    "addr:housenumber":"1312",
    "addr:postcode":"17102",
    "addr:street":"N 3Rd St",
    "iso:country":"US",
    "sg:address":"1312 N 3rd St",
    "sg:city":"Harrisburg",
    "sg:classifiers":[
        {
            "category":"Professional",
            "subcategory":"Accounting & Tax Preparation",
            "type":"Services"
        }
    ],
    "sg:phone":"+1 717 233 4188",
    "sg:postcode":"17102",
    "sg:province":"PA",
    "sg:tags":[
        "accountant"
    ],
    "wof:name":"Jackson Hewitt Tax Svc",
    "wof:placetype":"venue"
},
  "geometry": {"coordinates":[-76.88924900000001,40.269937],"type":"Point"}
}