{
  "type": "Feature",
  "properties": {
    "iso:country":"US",
    "sg:address":"177 W Creek Rd",
    "sg:city":"Saint Marys",
    "sg:classifiers":[
        {
            "category":"Government",
            "subcategory":"Court House",
            "type":"Public Place"
        }
    ],
    "sg:phone":"+1   ",
    "sg:postcode":"15857",
    "sg:province":"PA",
    "sg:tags":[
        "state"
    ],
    "wof:name":"Magisterial District 59-3-03",
    "wof:placetype":"venue"
},
  "geometry": {"coordinates":[-78.552488,41.453075],"type":"Point"}
}