{
  "type": "Feature",
  "properties": {
    "iso:country":"US",
    "sg:address":"114 N Grant Rd",
    "sg:city":"Thomasville",
    "sg:classifiers":[
        {
            "category":"Professional",
            "type":"Services"
        }
    ],
    "sg:phone":"+1   ",
    "sg:postcode":"17364",
    "sg:province":"PA",
    "wof:name":"Sterility Assurance Labotories",
    "wof:placetype":"venue"
},
  "geometry": {"coordinates":[-76.871218,39.930306],"type":"Point"}
}