{
  "type": "Feature",
  "properties": {
    "iso:country":"US",
    "sg:address":"1069 Methodist Rd",
    "sg:city":"Greenville",
    "sg:classifiers":[
        {
            "category":"Freight",
            "type":"Transportation"
        }
    ],
    "sg:phone":"+1   ",
    "sg:postcode":"16125",
    "sg:province":"PA",
    "sg:tags":[
        "distance",
        "local",
        "long",
        "trucking"
    ],
    "wof:name":"K P Trucking",
    "wof:placetype":"venue"
},
  "geometry": {"coordinates":[-80.329576,41.439954],"type":"Point"}
}