{
  "type": "Feature",
  "properties": {
    "iso:country":"US",
    "sg:address":"17 Bishop Hollow Rd",
    "sg:city":"Newtown Square",
    "sg:classifiers":[
        {
            "category":"Building & Trades",
            "subcategory":"Construction",
            "type":"Services"
        }
    ],
    "sg:phone":"+1 610 353 3110",
    "sg:postcode":"19073",
    "sg:province":"PA",
    "sg:tags":[
        "general",
        "contractor"
    ],
    "wof:name":"Addax Construction Co Inc",
    "wof:placetype":"venue"
},
  "geometry": {"coordinates":[-75.402681,39.985534],"type":"Point"}
}