{
  "type": "Feature",
  "properties": {
    "iso:country":"US",
    "sg:address":"926 Stonebridge Dr",
    "sg:city":"Lancaster",
    "sg:classifiers":[
        {
            "category":"Sports & Exercise",
            "subcategory":"Gym",
            "type":"Entertainment"
        }
    ],
    "sg:phone":"+1   ",
    "sg:postcode":"17601",
    "sg:province":"PA",
    "sg:tags":[
        "fitness",
        "physical",
        "facility"
    ],
    "wof:name":"Silhouettes Total Fitness",
    "wof:placetype":"venue"
},
  "geometry": {"coordinates":[-76.390378,40.069949],"type":"Point"}
}