{
  "type": "Feature",
  "properties": {
    "iso:country":"US",
    "sg:address":"303 S 32nd St",
    "sg:city":"Camp Hill",
    "sg:classifiers":[
        {
            "category":"Health Services",
            "subcategory":"Chiropractor",
            "type":"Services"
        }
    ],
    "sg:phone":"+1 717 761 2273",
    "sg:postcode":"17011",
    "sg:province":"PA",
    "wof:name":"Gerhart Family Chiropractic",
    "wof:placetype":"venue"
},
  "geometry": {"coordinates":[-76.93319700000001,40.2351],"type":"Point"}
}