{
  "type": "Feature",
  "properties": {
    "iso:country":"US",
    "sg:address":"451 Hill Rd",
    "sg:city":"Denver",
    "sg:classifiers":[
        {
            "category":"Building & Trades",
            "subcategory":"Landscaping Services",
            "type":"Services"
        }
    ],
    "sg:phone":"+1 717 336 7811",
    "sg:postcode":"17517",
    "sg:province":"PA",
    "wof:name":"Green Lawn Mowing",
    "wof:placetype":"venue"
},
  "geometry": {"coordinates":[-76.10133999999999,40.238997],"type":"Point"}
}