{
  "type": "Feature",
  "properties": {
    "addr:full":"3401 Neshaminy Blvd Bensalem PA 19020",
    "addr:housenumber":"3401",
    "addr:postcode":"19020",
    "addr:street":"Neshaminy Blvd",
    "iso:country":"US",
    "sg:address":"3401 Neshaminy Blvd",
    "sg:city":"Bensalem",
    "sg:classifiers":[
        {
            "category":"Government",
            "subcategory":"Police Station",
            "type":"Public Place"
        }
    ],
    "sg:phone":"+1 215 000 1111",
    "sg:postcode":"19020",
    "sg:province":"PA",
    "sg:tags":[
        "state"
    ],
    "wof:name":"State Police",
    "wof:placetype":"venue"
},
  "geometry": {"coordinates":[-74.934107,40.14533],"type":"Point"}
}