{
  "type": "Feature",
  "properties": {
    "iso:country":"US",
    "sg:address":"115 Clearfield Ave",
    "sg:city":"Norristown",
    "sg:classifiers":[
        {
            "category":"Building & Trades",
            "subcategory":"Construction",
            "type":"Services"
        },
        {
            "category":"Building & Trades",
            "subcategory":"Landscaping Services",
            "type":"Services"
        }
    ],
    "sg:phone":"+1 610 630 3330",
    "sg:postcode":"19403",
    "sg:province":"PA",
    "sg:tags":[
        "commercial",
        "contractor"
    ],
    "wof:name":"Cotteta Landscaping Inc",
    "wof:placetype":"venue"
},
  "geometry": {"coordinates":[-75.395426,40.140785],"type":"Point"}
}