{
  "type": "Feature",
  "properties": {
    "iso:country":"US",
    "sg:address":"422 N Front St",
    "sg:city":"Philipsburg",
    "sg:classifiers":[
        {
            "category":"Professional",
            "type":"Services"
        }
    ],
    "sg:phone":"+1 814 342 5699",
    "sg:postcode":"16866",
    "sg:province":"PA",
    "sg:tags":[
        "establishment"
    ],
    "wof:name":"Prime Star",
    "wof:placetype":"venue"
},
  "geometry": {"coordinates":[-78.225454,40.899359],"type":"Point"}
}