{
  "type": "Feature",
  "properties": {
    "addr:full":"1560 Temple Dr Ambler PA 19002",
    "addr:housenumber":"1560",
    "addr:postcode":"19002",
    "addr:street":"Temple Dr",
    "iso:country":"US",
    "sg:address":"1560 Temple Dr",
    "sg:city":"Ambler",
    "sg:classifiers":[
        {
            "category":"Real Estate",
            "subcategory":"Real Estate Agent",
            "type":"Services"
        }
    ],
    "sg:phone":"+1   ",
    "sg:postcode":"19002",
    "sg:province":"PA",
    "wof:name":"Vantage Realty Group",
    "wof:placetype":"venue"
},
  "geometry": {"coordinates":[-75.192007,40.170565],"type":"Point"}
}