{
  "type": "Feature",
  "properties": {
    "addr:full":"1819 Blacks Bridge Rd Annville PA 17003",
    "addr:housenumber":"1819",
    "addr:postcode":"17003",
    "addr:street":"Blacks Bridge Rd",
    "iso:country":"US",
    "sg:address":"1819 Blacks Bridge Rd",
    "sg:city":"Annville",
    "sg:classifiers":[
        {
            "category":"Professional",
            "subcategory":"Engineering",
            "type":"Services"
        }
    ],
    "sg:phone":"+1 717 867 0992",
    "sg:postcode":"17003",
    "sg:province":"PA",
    "sg:tags":[
        "engineer"
    ],
    "wof:name":"Maurer Engineering Assoc",
    "wof:placetype":"venue"
},
  "geometry": {"coordinates":[-76.57442399999999,40.376872],"type":"Point"}
}