{
  "type": "Feature",
  "properties": {
    "addr:full":"1500 Yardley Rd Morrisville PA 19067",
    "addr:housenumber":"1500",
    "addr:postcode":"19067",
    "addr:street":"Yardley Rd",
    "iso:country":"US",
    "sg:address":"1500 Yardley Rd",
    "sg:city":"Morrisville",
    "sg:classifiers":[
        {
            "category":"Recreation",
            "type":"Entertainment"
        }
    ],
    "sg:phone":"+1   ",
    "sg:postcode":"19067",
    "sg:province":"PA",
    "sg:tags":[
        "club",
        "membership"
    ],
    "wof:name":"Crossroads Investment Club",
    "wof:placetype":"venue"
},
  "geometry": {"coordinates":[-74.81126399999999,40.220185],"type":"Point"}
}