{
  "type": "Feature",
  "properties": {
    "iso:country":"US",
    "sg:address":"233 Lauriston St",
    "sg:city":"Philadelphia",
    "sg:classifiers":[
        {
            "category":"Building & Trades",
            "subcategory":"Cleaning & Sanitation",
            "type":"Services"
        }
    ],
    "sg:phone":"+1 215 482 1372",
    "sg:postcode":"19128",
    "sg:province":"PA",
    "wof:name":"Service Master Co",
    "wof:placetype":"venue"
},
  "geometry": {"coordinates":[-75.205471,40.020861],"type":"Point"}
}