{
  "type": "Feature",
  "properties": {
    "addr:full":"255 S 17th St Philadelphia PA 19103",
    "addr:housenumber":"255",
    "addr:postcode":"19103",
    "addr:street":"S 17Th St",
    "iso:country":"US",
    "sg:address":"255 S 17th St",
    "sg:city":"Philadelphia",
    "sg:classifiers":[
        {
            "category":"Health Services",
            "subcategory":"Doctor",
            "type":"Services"
        }
    ],
    "sg:phone":"+1 215 735 0180",
    "sg:postcode":"19103",
    "sg:province":"PA",
    "sg:tags":[
        "dentist"
    ],
    "wof:name":"Joseph Salkowitz DMD PC",
    "wof:placetype":"venue"
},
  "geometry": {"coordinates":[-75.169439,39.948338],"type":"Point"}
}