{
  "type": "Feature",
  "properties": {
    "addr:full":"808 Sumter Dr Morrisville PA 19067",
    "addr:housenumber":"808",
    "addr:postcode":"19067",
    "addr:street":"Sumter Dr",
    "iso:country":"US",
    "sg:address":"808 Sumter Dr",
    "sg:city":"Morrisville",
    "sg:classifiers":[
        {
            "category":"Banks & Credit Unions",
            "subcategory":"Investment Brokerage",
            "type":"Services"
        }
    ],
    "sg:phone":"+1   ",
    "sg:postcode":"19067",
    "sg:province":"PA",
    "sg:tags":[
        "security"
    ],
    "wof:name":"RE Assurance Management Inc",
    "wof:placetype":"venue"
},
  "geometry": {"coordinates":[-74.861396,40.22852],"type":"Point"}
}