{
  "type": "Feature",
  "properties": {
    "addr:full":"325 E Street Rd Warminster PA 18974",
    "addr:housenumber":"325",
    "addr:postcode":"18974",
    "addr:street":"E Street Rd",
    "iso:country":"US",
    "sg:address":"325 E Street Rd",
    "sg:city":"Warminster",
    "sg:classifiers":[
        {
            "category":"Professional",
            "type":"Services"
        }
    ],
    "sg:phone":"+1 215 441 9826",
    "sg:postcode":"18974",
    "sg:province":"PA",
    "sg:tags":[
        "establishment"
    ],
    "wof:name":"Centennial Station Activity Ct",
    "wof:placetype":"venue"
},
  "geometry": {"coordinates":[-75.090699,40.201488],"type":"Point"}
}