{
  "type": "Feature",
  "properties": {
    "iso:country":"US",
    "sg:address":"2520 W 26th St",
    "sg:city":"Erie",
    "sg:classifiers":[
        {
            "category":"Banks & Credit Unions",
            "subcategory":"Bank",
            "type":"Services"
        }
    ],
    "sg:phone":"+1 814 871 1186",
    "sg:postcode":"16506",
    "sg:province":"PA",
    "sg:tags":[
        "state",
        "commercial"
    ],
    "sg:website":"www.nationalcity.com",
    "wof:name":"National City Bank",
    "wof:placetype":"venue"
},
  "geometry": {"coordinates":[-80.13055,42.090767],"type":"Point"}
}