{
  "type": "Feature",
  "properties": {
    "iso:country":"US",
    "sg:address":"2329 Rose Dr",
    "sg:city":"Glenshaw",
    "sg:classifiers":[
        {
            "category":"Building & Trades",
            "subcategory":"Cleaning & Sanitation",
            "type":"Services"
        }
    ],
    "sg:phone":"+1 412 492 0160",
    "sg:postcode":"15116",
    "sg:province":"PA",
    "sg:tags":[
        "maintenance"
    ],
    "wof:name":"Sittig Home & Building Svc",
    "wof:placetype":"venue"
},
  "geometry": {"coordinates":[-79.938096,40.539553],"type":"Point"}
}