{
  "type": "Feature",
  "properties": {
    "addr:full":"566 Franklin Blvd Freedom PA 15042",
    "addr:housenumber":"566",
    "addr:postcode":"15042",
    "addr:street":"Franklin Blvd",
    "iso:country":"US",
    "sg:address":"566 Franklin Blvd",
    "sg:city":"Freedom",
    "sg:classifiers":[
        {
            "category":"Professional",
            "type":"Services"
        }
    ],
    "sg:phone":"+1   ",
    "sg:postcode":"15042",
    "sg:province":"PA",
    "wof:name":"Grubb Michael New Sewickley",
    "wof:placetype":"venue"
},
  "geometry": {"coordinates":[-80.158,40.684574],"type":"Point"}
}