{
  "type": "Feature",
  "properties": {
    "iso:country":"US",
    "sg:address":"249 Planebrook Rd",
    "sg:city":"Malvern",
    "sg:classifiers":[
        {
            "category":"Professional",
            "subcategory":"Management & Consulting",
            "type":"Services"
        }
    ],
    "sg:phone":"+1   ",
    "sg:postcode":"19355",
    "sg:province":"PA",
    "sg:tags":[
        "promotion"
    ],
    "wof:name":"Dynamic Fndrsing Prmotions LLC",
    "wof:placetype":"venue"
},
  "geometry": {"coordinates":[-75.575598,40.04065],"type":"Point"}
}