{
  "type": "Feature",
  "properties": {
    "iso:country":"US",
    "sg:address":"9 W Market St",
    "sg:city":"Middleburg",
    "sg:classifiers":[
        {
            "category":"Government",
            "subcategory":"Office",
            "type":"Public Place"
        }
    ],
    "sg:phone":"+1 570 837 4226",
    "sg:postcode":"17842",
    "sg:province":"PA",
    "wof:name":"Snyder County Register-Wills",
    "wof:placetype":"venue"
},
  "geometry": {"coordinates":[-77.046128,40.791961],"type":"Point"}
}