{
  "type": "Feature",
  "properties": {
    "iso:country":"US",
    "sg:address":"1216 11th Ave",
    "sg:city":"Altoona",
    "sg:classifiers":[
        {
            "category":"Professional",
            "subcategory":"Employment Agencies",
            "type":"Services"
        }
    ],
    "sg:phone":"+1 814 944 8976",
    "sg:postcode":"16601",
    "sg:province":"PA",
    "sg:tags":[
        "help",
        "contractor"
    ],
    "wof:name":"Manpower Temporary Svc",
    "wof:placetype":"venue"
},
  "geometry": {"coordinates":[-78.401994,40.515155],"type":"Point"}
}