{
  "type": "Feature",
  "properties": {
    "iso:country":"US",
    "sg:address":"1143 Vivjon Dr",
    "sg:city":"Homestead",
    "sg:classifiers":[
        {
            "category":"Farming",
            "subcategory":"Farm",
            "type":"Manufacturing & Wholesale Goods"
        }
    ],
    "sg:phone":"+1 412 461 6226",
    "sg:postcode":"15120",
    "sg:province":"PA",
    "wof:name":"Stoney Hills Farm",
    "wof:placetype":"venue"
},
  "geometry": {"coordinates":[-79.90979,40.395184],"type":"Point"}
}