{
  "type": "Feature",
  "properties": {
    "iso:country":"US",
    "sg:address":"300 Domino Ln",
    "sg:city":"Philadelphia",
    "sg:classifiers":[
        {
            "category":"Communications",
            "subcategory":"Television Station",
            "type":"Services"
        }
    ],
    "sg:phone":"+1 215 483 4550",
    "sg:postcode":"19128",
    "sg:province":"PA",
    "sg:tags":[
        "broadcasting",
        "co"
    ],
    "wof:name":"Penna Pay TV",
    "wof:placetype":"venue"
},
  "geometry": {"coordinates":[-75.23846899999999,40.040542],"type":"Point"}
}