{
  "type": "Feature",
  "properties": {
    "iso:country":"US",
    "sg:address":"719 Sansom St",
    "sg:city":"Philadelphia",
    "sg:phone":"+1 215 238 9373",
    "sg:postcode":"19106",
    "sg:province":"PA",
    "wof:name":"Tampopo Japanese Restaurant 2",
    "wof:placetype":"venue"
},
  "geometry": {"coordinates":[-75.152531,39.948647],"type":"Point"}
}