{
  "type": "Feature",
  "properties": {
    "iso:country":"US",
    "sg:address":"715 Campbell St",
    "sg:city":"Williamsport",
    "sg:classifiers":[
        {
            "category":"Shopping",
            "type":"Retail Goods"
        }
    ],
    "sg:phone":"+1 570 322 4156",
    "sg:postcode":"17701",
    "sg:province":"PA",
    "sg:tags":[
        "merchandise"
    ],
    "wof:name":"Memories By Glenda",
    "wof:placetype":"venue"
},
  "geometry": {"coordinates":[-77.01763099999999,41.246377],"type":"Point"}
}