{
  "type": "Feature",
  "properties": {
    "addr:full":"306 4th Ave Pittsburgh PA 15222",
    "addr:housenumber":"306",
    "addr:postcode":"15222",
    "addr:street":"4Th Ave",
    "iso:country":"US",
    "sg:address":"306 4th Ave",
    "sg:city":"Pittsburgh",
    "sg:classifiers":[
        {
            "category":"Professional",
            "subcategory":"Lawyer & Legal Services",
            "type":"Services"
        }
    ],
    "sg:phone":"+1 412 281 4333",
    "sg:postcode":"15222",
    "sg:province":"PA",
    "sg:tags":[
        "attorney"
    ],
    "wof:name":"Mc Grath & Assoc",
    "wof:placetype":"venue"
},
  "geometry": {"coordinates":[-79.99965899999999,40.438697],"type":"Point"}
}