{
  "type": "Feature",
  "properties": {
    "iso:country":"US",
    "sg:address":"1817 John F Kennedy Blvd",
    "sg:city":"Philadelphia",
    "sg:classifiers":[
        {
            "category":"Personal",
            "type":"Services"
        },
        {
            "category":"Professional",
            "subcategory":"Art Services",
            "type":"Services"
        }
    ],
    "sg:phone":"+1 215 232 4444",
    "sg:postcode":"19103",
    "sg:province":"PA",
    "sg:tags":[
        "photography",
        "videography",
        "photographers-portrait",
        "wedding"
    ],
    "sg:website":"http://www.CrossPhotograph.com",
    "wof:name":"David P Cross Photography",
    "wof:placetype":"venue"
},
  "geometry": {"coordinates":[-75.17000299999999,39.954216],"type":"Point"}
}