{
  "type": "Feature",
  "properties": {
    "iso:country":"US",
    "sg:address":"100 E King St",
    "sg:city":"Lancaster",
    "sg:classifiers":[
        {
            "category":"Banks & Credit Unions",
            "subcategory":"Investment Brokerage",
            "type":"Services"
        }
    ],
    "sg:phone":"+1 717 397 5515",
    "sg:postcode":"17602",
    "sg:province":"PA",
    "sg:tags":[
        "security"
    ],
    "wof:name":"Burt Hazlett & Watson Inc",
    "wof:placetype":"venue"
},
  "geometry": {"coordinates":[-76.30134099999999,40.03843],"type":"Point"}
}