{
  "type": "Feature",
  "properties": {
    "iso:country":"US",
    "sg:address":"4701 Clairton Blvd",
    "sg:city":"Pittsburgh",
    "sg:classifiers":[
        {
            "category":"Retail",
            "subcategory":"Veterinary Services",
            "type":"Services"
        }
    ],
    "sg:phone":"+1 412 882 3070",
    "sg:postcode":"15236",
    "sg:province":"PA",
    "sg:tags":[
        "clinic",
        "hospital",
        "specialty"
    ],
    "wof:name":"Always Compassionate Veterinary",
    "wof:placetype":"venue"
},
  "geometry": {"coordinates":[-79.97873,40.354185],"type":"Point"}
}