{
  "type": "Feature",
  "properties": {
    "iso:country":"US",
    "sg:address":"5248 Lycoming Mall Dr",
    "sg:city":"Montoursville",
    "sg:classifiers":[
        {
            "category":"Real Estate",
            "subcategory":"Real Estate Agent",
            "type":"Services"
        }
    ],
    "sg:phone":"+1 570 368 1003",
    "sg:postcode":"17754",
    "sg:province":"PA",
    "wof:name":"Realty World Broker Network",
    "wof:placetype":"venue"
},
  "geometry": {"coordinates":[-76.896479,41.245789],"type":"Point"}
}