{
  "type": "Feature",
  "properties": {
    "iso:country":"US",
    "sg:address":"501 Parkway Blvd",
    "sg:city":"York",
    "sg:classifiers":[
        {
            "category":"Utilities",
            "subcategory":"Electric",
            "type":"Services"
        }
    ],
    "sg:phone":"+1   ",
    "sg:postcode":"17404",
    "sg:province":"PA",
    "sg:tags":[
        "power",
        "facility"
    ],
    "wof:name":"Met-Ed",
    "wof:placetype":"venue"
},
  "geometry": {"coordinates":[-76.741587,39.969642],"type":"Point"}
}