{
  "type": "Feature",
  "properties": {
    "addr:full":"1037 Ford St Bridgeport PA 19405",
    "addr:housenumber":"1037",
    "addr:postcode":"19405",
    "addr:street":"Ford St",
    "iso:country":"US",
    "sg:address":"1037 Ford St",
    "sg:city":"Bridgeport",
    "sg:classifiers":[
        {
            "category":"Personal",
            "subcategory":"Beauty Salon",
            "type":"Services"
        }
    ],
    "sg:phone":"+1 610 239 7011",
    "sg:postcode":"19405",
    "sg:province":"PA",
    "sg:tags":[
        "shop"
    ],
    "wof:name":"Lori's Hair Designs",
    "wof:placetype":"venue"
},
  "geometry": {"coordinates":[-75.351069,40.099679],"type":"Point"}
}