{
  "type": "Feature",
  "properties": {
    "iso:country":"US",
    "sg:address":"46 Red Rowan Ln",
    "sg:city":"Plymouth Meeting",
    "sg:classifiers":[
        {
            "category":"Health Services",
            "subcategory":"Health Practitioner",
            "type":"Services"
        }
    ],
    "sg:phone":"+1   ",
    "sg:postcode":"19462",
    "sg:province":"PA",
    "wof:name":"Dr Phillip Friedman Foud W Bin",
    "wof:placetype":"venue"
},
  "geometry": {"coordinates":[-75.293909,40.116047],"type":"Point"}
}