{
  "type": "Feature",
  "properties": {
    "addr:full":"372 Styer Rd Glenmoore PA 19343",
    "addr:housenumber":"372",
    "addr:postcode":"19343",
    "addr:street":"Styer Rd",
    "iso:country":"US",
    "sg:address":"372 Styer Rd",
    "sg:city":"Glenmoore",
    "sg:classifiers":[
        {
            "category":"Building & Trades",
            "subcategory":"Construction",
            "type":"Services"
        }
    ],
    "sg:phone":"+1   ",
    "sg:postcode":"19343",
    "sg:province":"PA",
    "sg:tags":[
        "house"
    ],
    "wof:name":"Timothy Spillane Inc",
    "wof:placetype":"venue"
},
  "geometry": {"coordinates":[-75.718675,40.098204],"type":"Point"}
}