{
  "type": "Feature",
  "properties": {
    "addr:full":"801 Montour Blvd Danville PA 17821",
    "addr:housenumber":"801",
    "addr:postcode":"17821",
    "addr:street":"Montour Blvd",
    "iso:country":"US",
    "sg:address":"801 Montour Blvd",
    "sg:city":"Danville",
    "sg:classifiers":[
        {
            "category":"Building & Trades",
            "subcategory":"Construction",
            "type":"Services"
        }
    ],
    "sg:phone":"+1 570 275 0821",
    "sg:postcode":"17821",
    "sg:province":"PA",
    "sg:tags":[
        "home",
        "builder",
        "general",
        "contractor"
    ],
    "wof:name":"Pinebrook Homes Inc",
    "wof:placetype":"venue"
},
  "geometry": {"coordinates":[-76.58528800000001,40.959878],"type":"Point"}
}