{
  "type": "Feature",
  "properties": {
    "addr:full":"338 Christmas Village Rd Womelsdorf PA 19567",
    "addr:housenumber":"338",
    "addr:postcode":"19567",
    "addr:street":"Christmas Village Rd",
    "iso:country":"US",
    "sg:address":"338 Christmas Village Rd",
    "sg:city":"Womelsdorf",
    "sg:classifiers":[
        {
            "category":"Professional",
            "subcategory":"Business Services",
            "type":"Services"
        }
    ],
    "sg:phone":"+1 610 488 9990",
    "sg:postcode":"19567",
    "sg:province":"PA",
    "sg:tags":[
        "auctioneer"
    ],
    "wof:name":"Heidelberg Auction Svc",
    "wof:placetype":"venue"
},
  "geometry": {"coordinates":[-76.172489,40.412321],"type":"Point"}
}