{
  "type": "Feature",
  "properties": {
    "addr:full":"4525 McKnight Rd Pittsburgh PA 15237",
    "addr:housenumber":"4525",
    "addr:postcode":"15237",
    "addr:street":"Mcknight Rd",
    "iso:country":"US",
    "sg:address":"4525 McKnight Rd",
    "sg:city":"Pittsburgh",
    "sg:classifiers":[
        {
            "category":"Building & Trades",
            "subcategory":"Plumbing",
            "type":"Services"
        }
    ],
    "sg:phone":"+1 412 366 2525",
    "sg:postcode":"15237",
    "sg:province":"PA",
    "sg:tags":[
        "as",
        "contractor",
        "heating",
        "conditioning",
        "air"
    ],
    "wof:name":"Beverly Heating & Cooling Inc",
    "wof:placetype":"venue"
},
  "geometry": {"coordinates":[-80.01296000000001,40.499127],"type":"Point"}
}