{
  "type": "Feature",
  "properties": {
    "iso:country":"US",
    "sg:address":"10 Margaret St",
    "sg:city":"New Castle",
    "sg:classifiers":[
        {
            "category":"Government",
            "subcategory":"Fire Station",
            "type":"Public Place"
        }
    ],
    "sg:phone":"+1 724 656 3566",
    "sg:postcode":"16101",
    "sg:province":"PA",
    "sg:tags":[
        "department"
    ],
    "wof:name":"New Castle Fire Dept",
    "wof:placetype":"venue"
},
  "geometry": {"coordinates":[-80.348893,40.99485],"type":"Point"}
}