{
  "type": "Feature",
  "properties": {
    "iso:country":"US",
    "sg:address":"1201 S Church St",
    "sg:city":"Hazleton",
    "sg:classifiers":[
        {
            "category":"Wholesale",
            "subcategory":"Auto Parts",
            "type":"Manufacturing & Wholesale Goods"
        }
    ],
    "sg:phone":"+1   ",
    "sg:postcode":"18201",
    "sg:province":"PA",
    "sg:tags":[
        "supply"
    ],
    "wof:name":"Kittys Auto Parts Inc",
    "wof:placetype":"venue"
},
  "geometry": {"coordinates":[-75.99379399999999,40.92958],"type":"Point"}
}