{
  "type": "Feature",
  "properties": {
    "addr:full":"339 Mansfield Ave Pittsburgh PA 15220",
    "addr:housenumber":"339",
    "addr:postcode":"15220",
    "addr:street":"Mansfield Ave",
    "iso:country":"US",
    "sg:address":"339 Mansfield Ave",
    "sg:city":"Pittsburgh",
    "sg:classifiers":[
        {
            "category":"Building & Trades",
            "subcategory":"Electrical",
            "type":"Services"
        }
    ],
    "sg:phone":"+1 412 921 7284",
    "sg:postcode":"15220",
    "sg:province":"PA",
    "sg:tags":[
        "electrician"
    ],
    "wof:name":"Malacane Refrigeration & Electric Service",
    "wof:placetype":"venue"
},
  "geometry": {"coordinates":[-80.05120100000001,40.4216],"type":"Point"}
}