{
  "type": "Feature",
  "properties": {
    "addr:full":"3401 Walnut St Philadelphia PA 19104",
    "addr:housenumber":"3401",
    "addr:postcode":"19104",
    "addr:street":"Walnut St",
    "iso:country":"US",
    "sg:address":"3401 Walnut St",
    "sg:city":"Philadelphia",
    "sg:classifiers":[
        {
            "category":"Building & Trades",
            "subcategory":"Locksmith",
            "type":"Services"
        }
    ],
    "sg:phone":"+1 215 525 6708",
    "sg:postcode":"19104",
    "sg:province":"PA",
    "sg:tags":[
        "key"
    ],
    "wof:name":"Locksmith",
    "wof:placetype":"venue"
},
  "geometry": {"coordinates":[-75.19206,39.952946],"type":"Point"}
}