{
  "type": "Feature",
  "properties": {
    "iso:country":"US",
    "sg:address":"45 N 8th St",
    "sg:city":"Philadelphia",
    "sg:classifiers":[
        {
            "category":"Retail",
            "subcategory":"Laundry & Dry Cleaning",
            "type":"Services"
        }
    ],
    "sg:phone":"+1 215 592 4788",
    "sg:postcode":"19106",
    "sg:province":"PA",
    "wof:name":"Arch Cleaners",
    "wof:placetype":"venue"
},
  "geometry": {"coordinates":[-75.153194,39.952064],"type":"Point"}
}