{
  "type": "Feature",
  "properties": {
    "iso:country":"US",
    "sg:address":"40 Farm Ln",
    "sg:city":"Manchester",
    "sg:classifiers":[
        {
            "category":"Restaurant",
            "type":"Food & Drink"
        }
    ],
    "sg:phone":"+1 717 266 0613",
    "sg:postcode":"17345",
    "sg:province":"PA",
    "wof:name":"Michaels Pizza",
    "wof:placetype":"venue"
},
  "geometry": {"coordinates":[-76.720506,40.070596],"type":"Point"}
}