{
  "type": "Feature",
  "properties": {
    "iso:country":"US",
    "sg:address":"4937 Frankford Ave",
    "sg:city":"Philadelphia",
    "sg:classifiers":[
        {
            "category":"Personal",
            "subcategory":"Beauty Salon",
            "type":"Services"
        }
    ],
    "sg:phone":"+1 215 288 6011",
    "sg:postcode":"19124",
    "sg:province":"PA",
    "sg:tags":[
        "shop"
    ],
    "wof:name":"Bintou African Hair Braiding",
    "wof:placetype":"venue"
},
  "geometry": {"coordinates":[-75.080417,40.020184],"type":"Point"}
}