{
  "type": "Feature",
  "properties": {
    "iso:country":"US",
    "sg:address":"1109 Grand Ave",
    "sg:city":"Pittsburgh",
    "sg:classifiers":[
        {
            "category":"Professional",
            "subcategory":"Lawyer & Legal Services",
            "type":"Services"
        }
    ],
    "sg:phone":"+1 412 255 6500",
    "sg:postcode":"15212",
    "sg:province":"PA",
    "wof:name":"Milnes Gary Atty",
    "wof:placetype":"venue"
},
  "geometry": {"coordinates":[-80.027702,40.4748],"type":"Point"}
}