{
  "type": "Feature",
  "properties": {
    "addr:full":"419 May St Jermyn PA 18433",
    "addr:housenumber":"419",
    "addr:postcode":"18433",
    "addr:street":"May St",
    "iso:country":"US",
    "sg:address":"419 May St",
    "sg:city":"Jermyn",
    "sg:classifiers":[
        {
            "category":"Building & Trades",
            "subcategory":"Construction",
            "type":"Services"
        }
    ],
    "sg:phone":"+1   ",
    "sg:postcode":"18433",
    "sg:province":"PA",
    "sg:tags":[
        "house"
    ],
    "wof:name":"Beyond Builders",
    "wof:placetype":"venue"
},
  "geometry": {"coordinates":[-75.53734,41.534975],"type":"Point"}
}