{
  "type": "Feature",
  "properties": {
    "iso:country":"US",
    "sg:address":"723 Lehman St",
    "sg:city":"Lebanon",
    "sg:classifiers":[
        {
            "category":"Organizations",
            "subcategory":"Religious Organization",
            "type":"Services"
        }
    ],
    "sg:phone":"+1 717 273 8567",
    "sg:postcode":"17046",
    "sg:province":"PA",
    "sg:tags":[
        "churches-lutheran"
    ],
    "wof:name":"Holy Trinity Lutheran Church",
    "wof:placetype":"venue"
},
  "geometry": {"coordinates":[-76.423416,40.345791],"type":"Point"}
}