{
  "type": "Feature",
  "properties": {
    "addr:full":"1455 S 28th St Philadelphia PA 19146",
    "addr:housenumber":"1455",
    "addr:postcode":"19146",
    "addr:street":"S 28Th St",
    "iso:country":"US",
    "sg:address":"1455 S 28th St",
    "sg:city":"Philadelphia",
    "sg:classifiers":[
        {
            "category":"Organizations",
            "subcategory":"Membership Organization",
            "type":"Services"
        }
    ],
    "sg:phone":"+1 215 336 3916",
    "sg:postcode":"19146",
    "sg:province":"PA",
    "sg:tags":[
        "athletic"
    ],
    "wof:name":"Arcadia Athletic Assoc",
    "wof:placetype":"venue"
},
  "geometry": {"coordinates":[-75.19081,39.935311],"type":"Point"}
}