{
  "type": "Feature",
  "properties": {
    "iso:country":"US",
    "sg:address":"108 Erickson Ave Ste E",
    "sg:city":"Essington",
    "sg:classifiers":[
        {
            "category":"Wholesale",
            "subcategory":"Groceries",
            "type":"Manufacturing & Wholesale Goods"
        },
        {
            "category":"Food & Beverages",
            "subcategory":"Supermarket",
            "type":"Retail Goods"
        }
    ],
    "sg:phone":"+1 484 494 9191",
    "sg:postcode":"19029",
    "sg:province":"PA",
    "sg:tags":[
        "grocers-wholesale",
        "super",
        "products-wholesale",
        "store"
    ],
    "wof:name":"Bell Export Foods Group",
    "wof:placetype":"venue"
},
  "geometry": {"coordinates":[-75.29415,39.860614],"type":"Point"}
}