{
  "type": "Feature",
  "properties": {
    "iso:country":"US",
    "sg:address":"732 Negley Ave",
    "sg:city":"Turtle Creek",
    "sg:classifiers":[
        {
            "category":"Restaurant",
            "type":"Food & Drink"
        }
    ],
    "sg:phone":"+1   ",
    "sg:postcode":"15145",
    "sg:province":"PA",
    "sg:tags":[
        "eating"
    ],
    "wof:name":"Lunch Box",
    "wof:placetype":"venue"
},
  "geometry": {"coordinates":[-79.82675500000001,40.416518],"type":"Point"}
}