{
  "type": "Feature",
  "properties": {
    "iso:country":"US",
    "sg:address":"3358 W 26th St",
    "sg:city":"Erie",
    "sg:classifiers":[
        {
            "category":"Shopping",
            "subcategory":"Gifts & Souvenirs",
            "type":"Retail Goods"
        }
    ],
    "sg:phone":"+1 814 833 2895",
    "sg:postcode":"16506",
    "sg:province":"PA",
    "sg:tags":[
        "shop",
        "collectible",
        "fine"
    ],
    "wof:name":"Emporium Collectibles Gallery",
    "wof:placetype":"venue"
},
  "geometry": {"coordinates":[-80.14966800000001,42.083606],"type":"Point"}
}