{
  "type": "Feature",
  "properties": {
    "iso:country":"US",
    "sg:address":"100 Newport Ave",
    "sg:city":"Nazareth",
    "sg:classifiers":[
        {
            "category":"Government",
            "subcategory":"Office",
            "type":"Public Place"
        },
        {
            "category":"Government",
            "subcategory":"Police Station",
            "type":"Public Place"
        }
    ],
    "sg:phone":"+1 610 759 7050",
    "sg:postcode":"18064",
    "sg:province":"PA",
    "sg:tags":[
        "department",
        "executive"
    ],
    "wof:name":"Upper Nazareth Township Police",
    "wof:placetype":"venue"
},
  "geometry": {"coordinates":[-75.29809299999999,40.751293],"type":"Point"}
}