{
  "type": "Feature",
  "properties": {
    "iso:country":"US",
    "sg:address":"5323 Frankford Ave",
    "sg:city":"Philadelphia",
    "sg:classifiers":[
        {
            "category":"Professional",
            "subcategory":"Accounting & Tax Preparation",
            "type":"Services"
        }
    ],
    "sg:phone":"+1   ",
    "sg:postcode":"19124",
    "sg:province":"PA",
    "sg:tags":[
        "return"
    ],
    "wof:name":"Delaware Valley Tax Service",
    "wof:placetype":"venue"
},
  "geometry": {"coordinates":[-75.075622,40.024074],"type":"Point"}
}