{
  "type": "Feature",
  "properties": {
    "iso:country":"US",
    "sg:address":"603 S Main St",
    "sg:city":"Ulysses",
    "sg:classifiers":[
        {
            "category":"Organizations",
            "subcategory":"Religious Organization",
            "type":"Services"
        }
    ],
    "sg:phone":"+1 814 848 9878",
    "sg:postcode":"16948",
    "sg:province":"PA",
    "sg:tags":[
        "church"
    ],
    "wof:name":"First Baptist Church",
    "wof:placetype":"venue"
},
  "geometry": {"coordinates":[-77.762294,41.901009],"type":"Point"}
}