{
  "type": "Feature",
  "properties": {
    "addr:full":"1128 7th Ave Beaver Falls PA 15010",
    "addr:housenumber":"1128",
    "addr:postcode":"15010",
    "addr:street":"7Th Ave",
    "iso:country":"US",
    "sg:address":"1128 7th Ave",
    "sg:city":"Beaver Falls",
    "sg:classifiers":[
        {
            "category":"Restaurant",
            "type":"Food & Drink"
        }
    ],
    "sg:phone":"+1 724 846 6700",
    "sg:postcode":"15010",
    "sg:province":"PA",
    "sg:tags":[
        "eating"
    ],
    "wof:name":"China Wok",
    "wof:placetype":"venue"
},
  "geometry": {"coordinates":[-80.319428,40.752689],"type":"Point"}
}