{
  "type": "Feature",
  "properties": {
    "iso:country":"US",
    "sg:address":"2100 Arch St",
    "sg:city":"Philadelphia",
    "sg:classifiers":[
        {
            "category":"Professional",
            "type":"Services"
        }
    ],
    "sg:phone":"+1   ",
    "sg:postcode":"19103",
    "sg:province":"PA",
    "wof:name":"Board of Rabbis Philadelphia",
    "wof:placetype":"venue"
},
  "geometry": {"coordinates":[-75.17575600000001,39.955968],"type":"Point"}
}