{
  "type": "Feature",
  "properties": {
    "addr:full":"590 W Oregon Ave Philadelphia PA 19148",
    "addr:housenumber":"590",
    "addr:postcode":"19148",
    "addr:street":"W Oregon Ave",
    "iso:country":"US",
    "sg:address":"590 W Oregon Ave",
    "sg:city":"Philadelphia",
    "sg:classifiers":[
        {
            "category":"Health Services",
            "subcategory":"Optometrist",
            "type":"Services"
        }
    ],
    "sg:phone":"+1 215 334 2424",
    "sg:postcode":"19148",
    "sg:province":"PA",
    "wof:name":"Whitman Family Eye Care",
    "wof:placetype":"venue"
},
  "geometry": {"coordinates":[-75.158096,39.915199],"type":"Point"}
}