{
  "type": "Feature",
  "properties": {
    "addr:full":"14500 Bustleton Ave Philadelphia PA 19116",
    "addr:postcode":"14500;19116",
    "addr:street":"Bustleton Ave",
    "iso:country":"US",
    "sg:address":"14500 Bustleton Ave",
    "sg:city":"Philadelphia",
    "sg:classifiers":[
        {
            "category":"Health Services",
            "subcategory":"Health Practitioner",
            "type":"Services"
        }
    ],
    "sg:phone":"+1   ",
    "sg:postcode":"19116",
    "sg:province":"PA",
    "wof:name":"Richard Sadowsky PHD",
    "wof:placetype":"venue"
},
  "geometry": {"coordinates":[-75.012124,40.13201],"type":"Point"}
}