{
  "type": "Feature",
  "properties": {
    "iso:country":"US",
    "sg:address":"4415 N Front St",
    "sg:city":"Harrisburg",
    "sg:classifiers":[
        {
            "category":"Professional",
            "subcategory":"Lawyer & Legal Services",
            "type":"Services"
        }
    ],
    "sg:phone":"+1 717 671 1955",
    "sg:postcode":"17110",
    "sg:province":"PA",
    "sg:tags":[
        "attorney",
        "accident",
        "personal",
        "worker",
        "disability",
        "damage",
        "benefit",
        "social",
        "employee",
        "injury",
        "security",
        "property",
        "compensation",
        "law"
    ],
    "sg:website":"http://injurylawyer.com",
    "wof:name":"Freeburn & Hamilton Attys",
    "wof:placetype":"venue"
},
  "geometry": {"coordinates":[-76.899045,40.324732],"type":"Point"}
}