{
  "type": "Feature",
  "properties": {
    "iso:country":"US",
    "sg:address":"524 Washington Blvd",
    "sg:city":"Williamsport",
    "sg:classifiers":[
        {
            "category":"Food & Beverages",
            "subcategory":"Bakery",
            "type":"Retail Goods"
        }
    ],
    "sg:phone":"+1 570 323 4920",
    "sg:postcode":"17701",
    "sg:province":"PA",
    "sg:tags":[
        "baker"
    ],
    "wof:name":"Roys Bakery",
    "wof:placetype":"venue"
},
  "geometry": {"coordinates":[-76.993813,41.247494],"type":"Point"}
}