{
  "type": "Feature",
  "properties": {
    "iso:country":"US",
    "sg:address":"505 Penn St",
    "sg:city":"Reading",
    "sg:classifiers":[
        {
            "category":"Professional",
            "type":"Services"
        }
    ],
    "sg:phone":"+1 610 685 4940",
    "sg:postcode":"19601",
    "sg:province":"PA",
    "sg:tags":[
        "establishment"
    ],
    "wof:name":"Community First Fund",
    "wof:placetype":"venue"
},
  "geometry": {"coordinates":[-75.927813,40.335389],"type":"Point"}
}