{
  "type": "Feature",
  "properties": {
    "iso:country":"US",
    "sg:address":"475 Rosewood Dr",
    "sg:city":"Northampton",
    "sg:classifiers":[
        {
            "category":"Real Estate",
            "subcategory":"Real Estate Operator",
            "type":"Services"
        }
    ],
    "sg:phone":"+1 610 760 9325",
    "sg:postcode":"18067",
    "sg:province":"PA",
    "sg:tags":[
        "building",
        "apartment"
    ],
    "wof:name":"Crown Suites At Trexler Park",
    "wof:placetype":"venue"
},
  "geometry": {"coordinates":[-75.529169,40.746417],"type":"Point"}
}