{
  "type": "Feature",
  "properties": {
    "addr:full":"4450 Richmond Rd Easton PA 18040",
    "addr:housenumber":"4450",
    "addr:postcode":"18040",
    "addr:street":"Richmond Rd",
    "iso:country":"US",
    "sg:address":"4450 Richmond Rd",
    "sg:city":"Easton",
    "sg:classifiers":[
        {
            "category":"Farming",
            "subcategory":"Farm",
            "type":"Manufacturing & Wholesale Goods"
        }
    ],
    "sg:phone":"+1   ",
    "sg:postcode":"18040",
    "sg:province":"PA",
    "sg:tags":[
        "crop",
        "general"
    ],
    "wof:name":"Russell Reeder",
    "wof:placetype":"venue"
},
  "geometry": {"coordinates":[-75.210362,40.75479],"type":"Point"}
}