{
  "type": "Feature",
  "properties": {
    "iso:country":"US",
    "sg:address":"19219 Hwy 198",
    "sg:city":"Saegertown",
    "sg:classifiers":[
        {
            "category":"Health Services",
            "subcategory":"Optometrist",
            "type":"Services"
        }
    ],
    "sg:phone":"+1 814 763 5220",
    "sg:postcode":"16433",
    "sg:province":"PA",
    "wof:name":"Lori F Merritt OD",
    "wof:placetype":"venue"
},
  "geometry": {"coordinates":[-80.172713,41.739476],"type":"Point"}
}