{
  "type": "Feature",
  "properties": {
    "iso:country":"US",
    "sg:address":"5551 Louise St",
    "sg:city":"Erie",
    "sg:classifiers":[
        {
            "category":"Retail",
            "subcategory":"Portrait Studio",
            "type":"Services"
        }
    ],
    "sg:phone":"+1 814 899 1161",
    "sg:postcode":"16510",
    "sg:province":"PA",
    "sg:tags":[
        "photographer"
    ],
    "wof:name":"Bruce Bennett Photography",
    "wof:placetype":"venue"
},
  "geometry": {"coordinates":[-79.97357599999999,42.132804],"type":"Point"}
}