{
  "type": "Feature",
  "properties": {
    "iso:country":"US",
    "sg:address":"1927 E Saw Mill Rd",
    "sg:city":"Quakertown",
    "sg:classifiers":[
        {
            "category":"Professional",
            "type":"Services"
        }
    ],
    "sg:phone":"+1 215 538 5278",
    "sg:postcode":"18951",
    "sg:province":"PA",
    "sg:tags":[
        "establishment"
    ],
    "wof:name":"Edward Kehs Jr Mountainside Dg",
    "wof:placetype":"venue"
},
  "geometry": {"coordinates":[-75.22676300000001,40.475865],"type":"Point"}
}