{
  "type": "Feature",
  "properties": {
    "addr:full":"158 W Hutchinson Ave Swissvale PA 15218",
    "addr:housenumber":"158",
    "addr:postcode":"15218",
    "addr:street":"W Hutchinson Ave",
    "iso:country":"US",
    "sg:address":"158 W Hutchinson Ave",
    "sg:city":"Swissvale",
    "sg:classifiers":[
        {
            "category":"Professional",
            "subcategory":"Lawyer & Legal Services",
            "type":"Services"
        }
    ],
    "sg:phone":"+1 412 731 1000",
    "sg:postcode":"15218",
    "sg:province":"PA",
    "sg:tags":[
        "attorney"
    ],
    "wof:name":"Sweeney & Assoc",
    "wof:placetype":"venue"
},
  "geometry": {"coordinates":[-79.885768,40.435671],"type":"Point"}
}