{
  "type": "Feature",
  "properties": {
    "iso:country":"US",
    "sg:address":"51 N 3rd St",
    "sg:city":"Philadelphia",
    "sg:classifiers":[
        {
            "category":"Building & Trades",
            "subcategory":"Cleaning & Sanitation",
            "type":"Services"
        }
    ],
    "sg:phone":"+1 267 671 2339",
    "sg:postcode":"19106",
    "sg:province":"PA",
    "sg:tags":[
        "window"
    ],
    "wof:name":"Wissahickon Window Washing",
    "wof:placetype":"venue"
},
  "geometry": {"coordinates":[-75.145399,39.951434],"type":"Point"}
}