{
  "type": "Feature",
  "properties": {
    "iso:country":"US",
    "sg:address":"311 Mahoning Ave",
    "sg:city":"New Castle",
    "sg:classifiers":[
        {
            "category":"Local Transit",
            "type":"Transportation"
        }
    ],
    "sg:phone":"+1 724 654 3130",
    "sg:postcode":"16102",
    "sg:province":"PA",
    "sg:tags":[
        "line"
    ],
    "sg:website":"www.newcastletransit.org",
    "wof:name":"New Castle Area Transit",
    "wof:placetype":"venue"
},
  "geometry": {"coordinates":[-80.356658,40.981922],"type":"Point"}
}