{
  "type": "Feature",
  "properties": {
    "iso:country":"US",
    "sg:address":"171 W North St",
    "sg:city":"Carlisle",
    "sg:classifiers":[
        {
            "category":"Manufacturing",
            "subcategory":"Buildings",
            "type":"Manufacturing & Wholesale Goods"
        },
        {
            "category":"Building & Trades",
            "subcategory":"Construction",
            "type":"Services"
        }
    ],
    "sg:phone":"+1 717 254 6290",
    "sg:postcode":"17013",
    "sg:province":"PA",
    "sg:tags":[
        "home",
        "builder",
        "contractor"
    ],
    "wof:name":"Home Wreckers Construction And Remodelin",
    "wof:placetype":"venue"
},
  "geometry": {"coordinates":[-77.192858,40.204872],"type":"Point"}
}