{
  "type": "Feature",
  "properties": {
    "addr:full":"1650 Arch St Philadelphia PA 19103",
    "addr:housenumber":"1650",
    "addr:postcode":"19103",
    "addr:street":"Arch St",
    "iso:country":"US",
    "sg:address":"1650 Arch St",
    "sg:city":"Philadelphia",
    "sg:classifiers":[
        {
            "category":"Juice Bar",
            "subcategory":"None",
            "type":"Food & Drink"
        },
        {
            "category":"Food & Beverages",
            "subcategory":"Bakery",
            "type":"Retail Goods"
        }
    ],
    "sg:phone":"+1 215 569 3666",
    "sg:postcode":"19103",
    "sg:province":"PA",
    "sg:tags":[
        "smoothy",
        "sandwich"
    ],
    "wof:name":"Raindrop Cafe",
    "wof:placetype":"venue"
},
  "geometry": {"coordinates":[-75.16720599999999,39.954891],"type":"Point"}
}