{
  "type": "Feature",
  "properties": {
    "iso:country":"US",
    "sg:address":"1432 Easton Rd",
    "sg:city":"Warrington",
    "sg:classifiers":[
        {
            "category":"Professional",
            "subcategory":"Advertising",
            "type":"Services"
        }
    ],
    "sg:phone":"+1 215 491 6272",
    "sg:postcode":"18976",
    "sg:province":"PA",
    "wof:name":"Kendig Corp",
    "wof:placetype":"venue"
},
  "geometry": {"coordinates":[-75.13317000000001,40.25255],"type":"Point"}
}