{
  "type": "Feature",
  "properties": {
    "iso:country":"US",
    "sg:address":"1905 Spring Garden St",
    "sg:city":"Philadelphia",
    "sg:classifiers":[
        {
            "category":"Professional",
            "subcategory":"Lawyer & Legal Services",
            "type":"Services"
        }
    ],
    "sg:phone":"+1 215 751 2766",
    "sg:postcode":"19130",
    "sg:province":"PA",
    "wof:name":"Brotman Sidney S Atty",
    "wof:placetype":"venue"
},
  "geometry": {"coordinates":[-75.16950199999999,39.963501],"type":"Point"}
}