{
  "type": "Feature",
  "properties": {
    "addr:full":"104 Oakdale Dr Zelienople PA 16063",
    "addr:housenumber":"104",
    "addr:postcode":"16063",
    "addr:street":"Oakdale Dr Zelienople",
    "iso:country":"US",
    "sg:address":"104 Oakdale Dr",
    "sg:city":"Zelienople",
    "sg:classifiers":[
        {
            "category":"Manufacturing",
            "subcategory":"Metals",
            "type":"Manufacturing & Wholesale Goods"
        }
    ],
    "sg:phone":"+1   ",
    "sg:postcode":"16063",
    "sg:province":"PA",
    "sg:tags":[
        "blast",
        "furnace",
        "works"
    ],
    "wof:name":"Material Search Co",
    "wof:placetype":"venue"
},
  "geometry": {"coordinates":[-80.142325,40.783692],"type":"Point"}
}