{
  "type": "Feature",
  "properties": {
    "iso:country":"US",
    "sg:address":"3701 Market St",
    "sg:city":"Philadelphia",
    "sg:classifiers":[
        {
            "category":"Education",
            "subcategory":"University",
            "type":"Public Place"
        }
    ],
    "sg:phone":"+1 215 966 6000",
    "sg:postcode":"19104",
    "sg:province":"PA",
    "sg:tags":[
        "college"
    ],
    "wof:name":"Philadelphia Biotechnology And Life Sciences Inst",
    "wof:placetype":"venue"
},
  "geometry": {"coordinates":[-75.19609800000001,39.956421],"type":"Point"}
}