{
  "type": "Feature",
  "properties": {
    "iso:country":"US",
    "sg:address":"265 Southview Rd",
    "sg:city":"Mc Donald",
    "sg:classifiers":[
        {
            "category":"Food & Beverages",
            "subcategory":"Fruits & Vegetables",
            "type":"Retail Goods"
        }
    ],
    "sg:phone":"+1 724 356 7960",
    "sg:postcode":"15057",
    "sg:province":"PA",
    "sg:tags":[
        "produce"
    ],
    "wof:name":"Brown's Orchard",
    "wof:placetype":"venue"
},
  "geometry": {"coordinates":[-80.273692,40.316895],"type":"Point"}
}