{
  "type": "Feature",
  "properties": {
    "iso:country":"US",
    "sg:address":"223 Siebert Rd",
    "sg:city":"Pittsburgh",
    "sg:classifiers":[
        {
            "category":"Retail",
            "subcategory":"Veterinary Services",
            "type":"Services"
        },
        {
            "category":"Retail",
            "subcategory":"Animal Services",
            "type":"Services"
        }
    ],
    "sg:phone":"+1 412 364 5353",
    "sg:postcode":"15237",
    "sg:province":"PA",
    "sg:tags":[
        "pet",
        "hospital",
        "specialty",
        "clinic",
        "veterinarian",
        "grooming"
    ],
    "sg:website":"http://www.northviewvethospsystem.com",
    "wof:name":"Northview Veterinary Hospital System",
    "wof:placetype":"venue"
},
  "geometry": {"coordinates":[-80.00572200000001,40.530087],"type":"Point"}
}