{
  "type": "Feature",
  "properties": {
    "addr:full":"1800 Byberry Rd Huntingdon Valley PA 19006",
    "addr:housenumber":"1800",
    "addr:postcode":"19006",
    "addr:street":"Byberry Rd",
    "iso:country":"US",
    "sg:address":"1800 Byberry Rd",
    "sg:city":"Huntingdon Valley",
    "sg:classifiers":[
        {
            "category":"Freight",
            "type":"Transportation"
        }
    ],
    "sg:phone":"+1   ",
    "sg:postcode":"19006",
    "sg:province":"PA",
    "sg:tags":[
        "scheduled",
        "domestic",
        "transport",
        "air"
    ],
    "wof:name":"Rock-It Cargo USA Inc",
    "wof:placetype":"venue"
},
  "geometry": {"coordinates":[-75.074574,40.158812],"type":"Point"}
}