{
  "type": "Feature",
  "properties": {
    "iso:country":"US",
    "sg:address":"413 S George St",
    "sg:city":"York",
    "sg:classifiers":[
        {
            "category":"Personal",
            "subcategory":"Beauty Salon",
            "type":"Services"
        }
    ],
    "sg:phone":"+1 717 880 3268",
    "sg:postcode":"17403",
    "sg:province":"PA",
    "wof:name":"Portraits Of Beaute",
    "wof:placetype":"venue"
},
  "geometry": {"coordinates":[-76.72452800000001,39.956567],"type":"Point"}
}