{
  "type": "Feature",
  "properties": {
    "iso:country":"US",
    "sg:address":"1251 Eckert Ave",
    "sg:city":"Reading",
    "sg:classifiers":[
        {
            "category":"Health Services",
            "subcategory":"Health Practitioner",
            "type":"Services"
        }
    ],
    "sg:phone":"+1 610 372 0885",
    "sg:postcode":"19602",
    "sg:province":"PA",
    "sg:tags":[
        "psychologist"
    ],
    "wof:name":"Gilbert M Foley",
    "wof:placetype":"venue"
},
  "geometry": {"coordinates":[-75.91163299999999,40.333339],"type":"Point"}
}