{
  "type": "Feature",
  "properties": {
    "iso:country":"US",
    "sg:address":"259 E Main St",
    "sg:city":"Norristown",
    "sg:classifiers":[
        {
            "category":"Home & Garden",
            "subcategory":"Hardware",
            "type":"Retail Goods"
        }
    ],
    "sg:phone":"+1 610 275 3137",
    "sg:postcode":"19401",
    "sg:province":"PA",
    "wof:name":"Joseph J Zummo Hardware Inc",
    "wof:placetype":"venue"
},
  "geometry": {"coordinates":[-75.33963,40.112849],"type":"Point"}
}