{
  "type": "Feature",
  "properties": {
    "iso:country":"US",
    "sg:address":"2012 W 16th St",
    "sg:city":"Erie",
    "sg:classifiers":[
        {
            "category":"Professional",
            "subcategory":"Business Services",
            "type":"Services"
        }
    ],
    "sg:phone":"+1   ",
    "sg:postcode":"16505",
    "sg:province":"PA",
    "wof:name":"Tpi Solutions",
    "wof:placetype":"venue"
},
  "geometry": {"coordinates":[-80.122394,42.104275],"type":"Point"}
}