{
  "type": "Feature",
  "properties": {
    "iso:country":"US",
    "sg:address":"2110 Bressler Dr",
    "sg:city":"Wyomissing",
    "sg:classifiers":[
        {
            "category":"Building & Trades",
            "subcategory":"Construction",
            "type":"Services"
        }
    ],
    "sg:phone":"+1 610 678 6104",
    "sg:postcode":"19610",
    "sg:province":"PA",
    "sg:tags":[
        "roofing",
        "contractor"
    ],
    "wof:name":"P Glenn Shaub",
    "wof:placetype":"venue"
},
  "geometry": {"coordinates":[-75.99974899999999,40.342132],"type":"Point"}
}