{
  "type": "Feature",
  "properties": {
    "iso:country":"US",
    "sg:address":"2500 W Chester Pike",
    "sg:city":"Broomall",
    "sg:classifiers":[
        {
            "category":"Restaurant",
            "type":"Food & Drink"
        }
    ],
    "sg:menulink":"http://www.allmenus.com/pa/marple/123095-quiznos-sub/menu/",
    "sg:phone":"+1 610 353 3344",
    "sg:postcode":"19008",
    "sg:province":"PA",
    "sg:tags":[
        "wrap",
        "american",
        "sandwich"
    ],
    "wof:name":"Quiznos Sub",
    "wof:placetype":"venue"
},
  "geometry": {"coordinates":[-75.356891,39.981163],"type":"Point"}
}