{
  "type": "Feature",
  "properties": {
    "iso:country":"US",
    "sg:address":"220 Powell Ave",
    "sg:city":"Cresson",
    "sg:classifiers":[
        {
            "category":"Education",
            "subcategory":"School",
            "type":"Public Place"
        }
    ],
    "sg:phone":"+1 814 886 7942",
    "sg:postcode":"16630",
    "sg:province":"PA",
    "wof:name":"All Saints Catholic School",
    "wof:placetype":"venue"
},
  "geometry": {"coordinates":[-78.587176,40.464795],"type":"Point"}
}