{
  "type": "Feature",
  "properties": {
    "addr:full":"1928 W Walnut St Allentown PA 18104",
    "addr:housenumber":"1928",
    "addr:postcode":"18104",
    "addr:street":"W Walnut St",
    "iso:country":"US",
    "sg:address":"1928 W Walnut St",
    "sg:city":"Allentown",
    "sg:classifiers":[
        {
            "category":"Social Services",
            "type":"Services"
        }
    ],
    "sg:phone":"+1   ",
    "sg:postcode":"18104",
    "sg:province":"PA",
    "wof:name":"Senior Fest",
    "wof:placetype":"venue"
},
  "geometry": {"coordinates":[-75.496865,40.593996],"type":"Point"}
}