{
  "type": "Feature",
  "properties": {
    "iso:country":"US",
    "sg:address":"4650 Ramona Ave",
    "sg:city":"Philadelphia",
    "sg:classifiers":[
        {
            "category":"Home & Garden",
            "subcategory":"Building Materials",
            "type":"Retail Goods"
        }
    ],
    "sg:phone":"+1 215 289 6400",
    "sg:postcode":"19124",
    "sg:province":"PA",
    "wof:name":"Oakland Greenhouse",
    "wof:placetype":"venue"
},
  "geometry": {"coordinates":[-75.09745599999999,40.022887],"type":"Point"}
}