{
  "type": "Feature",
  "properties": {
    "iso:country":"US",
    "sg:address":"3102 Drexel Rd",
    "sg:city":"Bensalem",
    "sg:classifiers":[
        {
            "category":"Building & Trades",
            "subcategory":"Construction",
            "type":"Services"
        }
    ],
    "sg:phone":"+1   ",
    "sg:postcode":"19020",
    "sg:province":"PA",
    "sg:tags":[
        "hanging",
        "contractor"
    ],
    "wof:name":"Walling Daughters",
    "wof:placetype":"venue"
},
  "geometry": {"coordinates":[-74.93345600000001,40.138864],"type":"Point"}
}