{
  "type": "Feature",
  "properties": {
    "iso:country":"US",
    "sg:address":"2700 Brownsville Rd",
    "sg:city":"South Park",
    "sg:classifiers":[
        {
            "category":"Building & Trades",
            "subcategory":"Locksmith",
            "type":"Services"
        }
    ],
    "sg:phone":"+1 724 292 7333",
    "sg:postcode":"15129",
    "sg:province":"PA",
    "sg:tags":[
        "key"
    ],
    "wof:name":"Locksmith & Locks-24 7 Emergency",
    "wof:placetype":"venue"
},
  "geometry": {"coordinates":[-80.003417,40.287538],"type":"Point"}
}