{
  "type": "Feature",
  "properties": {
    "addr:full":"275 W Moreland Rd Willow Grove PA 19090",
    "addr:housenumber":"275",
    "addr:postcode":"19090",
    "addr:street":"W Moreland Rd",
    "iso:country":"US",
    "sg:address":"275 W Moreland Rd",
    "sg:city":"Willow Grove",
    "sg:classifiers":[
        {
            "category":"Banks & Credit Unions",
            "subcategory":"Bank",
            "type":"Services"
        }
    ],
    "sg:phone":"+1 215 659 2100",
    "sg:postcode":"19090",
    "sg:province":"PA",
    "wof:name":"Abington Bank",
    "wof:placetype":"venue"
},
  "geometry": {"coordinates":[-75.120098,40.143349],"type":"Point"}
}