{
  "type": "Feature",
  "properties": {
    "addr:full":"412 S Main St Wilkes Barre PA 18701",
    "addr:housenumber":"412",
    "addr:postcode":"18701",
    "addr:street":"S Main St",
    "iso:country":"US",
    "sg:address":"412 S Main St",
    "sg:city":"Wilkes Barre",
    "sg:classifiers":[
        {
            "category":"Autos & Motor Vehicles",
            "subcategory":"Fuel & Gas Station",
            "type":"Retail Goods"
        }
    ],
    "sg:phone":"+1   ",
    "sg:postcode":"18701",
    "sg:province":"PA",
    "sg:tags":[
        "station",
        "gasoline"
    ],
    "wof:name":"Petroleum Service Company",
    "wof:placetype":"venue"
},
  "geometry": {"coordinates":[-75.893574,41.239452],"type":"Point"}
}