{
  "type": "Feature",
  "properties": {
    "iso:country":"US",
    "sg:address":"1528 Salaway Ct",
    "sg:city":"Ambler",
    "sg:classifiers":[
        {
            "category":"Professional",
            "subcategory":"Engineering",
            "type":"Services"
        }
    ],
    "sg:phone":"+1   ",
    "sg:postcode":"19002",
    "sg:province":"PA",
    "wof:name":"Bridge Machinery Inc",
    "wof:placetype":"venue"
},
  "geometry": {"coordinates":[-75.162375,40.165327],"type":"Point"}
}