{
  "type": "Feature",
  "properties": {
    "addr:full":"729 S Saint Marys Rd St Marys PA 15857",
    "addr:housenumber":"729",
    "addr:postcode":"15857",
    "addr:street":"S;Marys Rd",
    "iso:country":"US",
    "sg:address":"729 S Saint Marys Rd",
    "sg:city":"St Marys",
    "sg:classifiers":[
        {
            "category":"Autos & Motor Vehicles",
            "subcategory":"Automobile Sales",
            "type":"Retail Goods"
        }
    ],
    "sg:phone":"+1 814 781 3545",
    "sg:postcode":"15857",
    "sg:province":"PA",
    "sg:tags":[
        "car",
        "dealer"
    ],
    "wof:name":"Pistner Brothers Cars & Trucks",
    "wof:placetype":"venue"
},
  "geometry": {"coordinates":[-78.560754,41.413811],"type":"Point"}
}