{
  "type": "Feature",
  "properties": {
    "iso:country":"US",
    "sg:address":"101 S 25th St",
    "sg:city":"Harrisburg",
    "sg:classifiers":[
        {
            "category":"Restaurant",
            "type":"Food & Drink"
        }
    ],
    "sg:phone":"+1 717 232 9941",
    "sg:postcode":"17104",
    "sg:province":"PA",
    "wof:name":"Tropic Chicken",
    "wof:placetype":"venue"
},
  "geometry": {"coordinates":[-76.84504699999999,40.271559],"type":"Point"}
}