{
  "type": "Feature",
  "properties": {
    "iso:country":"US",
    "sg:address":"116 W Chestnut St",
    "sg:city":"Ephrata",
    "sg:classifiers":[
        {
            "category":"Home & Garden",
            "subcategory":"Furniture",
            "type":"Retail Goods"
        }
    ],
    "sg:phone":"+1   ",
    "sg:postcode":"17522",
    "sg:province":"PA",
    "wof:name":"George Robert Platt",
    "wof:placetype":"venue"
},
  "geometry": {"coordinates":[-76.17370699999999,40.18214],"type":"Point"}
}