{
  "type": "Feature",
  "properties": {
    "iso:country":"US",
    "sg:address":"12041 Perry Hwy",
    "sg:city":"Wexford",
    "sg:classifiers":[
        {
            "category":"Personal",
            "subcategory":"Hair Removal",
            "type":"Services"
        },
        {
            "category":"Personal",
            "subcategory":"Nail Salon",
            "type":"Services"
        }
    ],
    "sg:phone":"+1 724 934 0211",
    "sg:postcode":"15090",
    "sg:province":"PA",
    "wof:name":"Jockel Greg Hair Dezigners Inc",
    "wof:placetype":"venue"
},
  "geometry": {"coordinates":[-80.0597,40.633202],"type":"Point"}
}