{
  "type": "Feature",
  "properties": {
    "addr:full":"153 S Market St Nanticoke PA 18634",
    "addr:housenumber":"153",
    "addr:postcode":"18634",
    "addr:street":"S Market St",
    "iso:country":"US",
    "sg:address":"153 S Market St",
    "sg:city":"Nanticoke",
    "sg:classifiers":[
        {
            "category":"Insurance",
            "subcategory":"Insurance Agent",
            "type":"Services"
        }
    ],
    "sg:phone":"+1 570 735 3800",
    "sg:postcode":"18634",
    "sg:province":"PA",
    "wof:name":"Lewis Insurance",
    "wof:placetype":"venue"
},
  "geometry": {"coordinates":[-76.003861,41.20343],"type":"Point"}
}