{
  "type": "Feature",
  "properties": {
    "addr:full":"30 S Valley Rd Paoli PA 19301",
    "addr:housenumber":"30",
    "addr:postcode":"19301",
    "addr:street":"S Valley Rd",
    "iso:country":"US",
    "sg:address":"30 S Valley Rd",
    "sg:city":"Paoli",
    "sg:classifiers":[
        {
            "category":"Professional",
            "subcategory":"Business Services",
            "type":"Services"
        }
    ],
    "sg:phone":"+1 610 296 4777",
    "sg:postcode":"19301",
    "sg:province":"PA",
    "sg:tags":[
        "paging",
        "answering"
    ],
    "wof:name":"Chester County Telephone Svc",
    "wof:placetype":"venue"
},
  "geometry": {"coordinates":[-75.48342,40.040101],"type":"Point"}
}