{
  "type": "Feature",
  "properties": {
    "iso:country":"US",
    "sg:address":"6 Corbett Rd",
    "sg:city":"Galeton",
    "sg:classifiers":[
        {
            "category":"Farming",
            "subcategory":"Livestock Farm",
            "type":"Manufacturing & Wholesale Goods"
        }
    ],
    "sg:phone":"+1   ",
    "sg:postcode":"16922",
    "sg:province":"PA",
    "sg:tags":[
        "beef",
        "feedlot",
        "cattle"
    ],
    "wof:name":"Alan Matz",
    "wof:placetype":"venue"
},
  "geometry": {"coordinates":[-77.77546100000001,41.682423],"type":"Point"}
}