{
  "type": "Feature",
  "properties": {
    "iso:country":"US",
    "sg:address":"1002 Newton Rd",
    "sg:city":"Clarks Summit",
    "sg:classifiers":[
        {
            "category":"Building & Trades",
            "subcategory":"Construction",
            "type":"Services"
        }
    ],
    "sg:phone":"+1 570 457 5230",
    "sg:postcode":"18411",
    "sg:province":"PA",
    "sg:tags":[
        "residential",
        "general",
        "commercial",
        "contractor"
    ],
    "wof:name":"Raymond Orchard Construction",
    "wof:placetype":"venue"
},
  "geometry": {"coordinates":[-75.715377,41.453025],"type":"Point"}
}