{
  "type": "Feature",
  "properties": {
    "iso:country":"US",
    "sg:address":"1093 Noble Rd",
    "sg:city":"Christiana",
    "sg:classifiers":[
        {
            "category":"Building & Trades",
            "subcategory":"Electrical",
            "type":"Services"
        }
    ],
    "sg:phone":"+1   ",
    "sg:postcode":"17509",
    "sg:province":"PA",
    "sg:tags":[
        "electrical",
        "contractor"
    ],
    "wof:name":"Kane Services",
    "wof:placetype":"venue"
},
  "geometry": {"coordinates":[-76.058871,39.901176],"type":"Point"}
}