{
  "type": "Feature",
  "properties": {
    "iso:country":"US",
    "sg:address":"923 Monroe St",
    "sg:city":"Berwick",
    "sg:classifiers":[
        {
            "category":"Food & Beverages",
            "subcategory":"Groceries & Convenience Stores",
            "type":"Retail Goods"
        }
    ],
    "sg:phone":"+1   ",
    "sg:postcode":"18603",
    "sg:province":"PA",
    "wof:name":"Andersons Food Service",
    "wof:placetype":"venue"
},
  "geometry": {"coordinates":[-76.25047499999999,41.058751],"type":"Point"}
}