{
  "type": "Feature",
  "properties": {
    "iso:country":"US",
    "sg:address":"18 W 3rd St",
    "sg:city":"Bethlehem",
    "sg:classifiers":[
        {
            "category":"Retail",
            "subcategory":"Repair Shop",
            "type":"Services"
        }
    ],
    "sg:phone":"+1 610 867 3313",
    "sg:postcode":"18015",
    "sg:province":"PA",
    "sg:tags":[
        "antique"
    ],
    "wof:name":"Burlesque Repair Service",
    "wof:placetype":"venue"
},
  "geometry": {"coordinates":[-75.379097,40.612],"type":"Point"}
}