{
  "type": "Feature",
  "properties": {
    "addr:full":"545 York Rd Warminster PA 18974",
    "addr:housenumber":"545",
    "addr:postcode":"18974",
    "addr:street":"York Rd",
    "iso:country":"US",
    "sg:address":"545 York Rd",
    "sg:city":"Warminster",
    "sg:classifiers":[
        {
            "category":"Personal",
            "subcategory":"Beauty Salon",
            "type":"Services"
        }
    ],
    "sg:phone":"+1 215 675 1055",
    "sg:postcode":"18974",
    "sg:province":"PA",
    "sg:tags":[
        "shop"
    ],
    "wof:name":"Trends Hair Salon",
    "wof:placetype":"venue"
},
  "geometry": {"coordinates":[-75.10018700000001,40.204243],"type":"Point"}
}