{
  "type": "Feature",
  "properties": {
    "iso:country":"US",
    "sg:address":"56 Woodland Dr",
    "sg:city":"Pittsburgh",
    "sg:classifiers":[
        {
            "category":"Health Services",
            "subcategory":"Doctor",
            "type":"Services"
        }
    ],
    "sg:phone":"+1 412 341 4994",
    "sg:postcode":"15228",
    "sg:province":"PA",
    "wof:name":"Hagen Tanya MD",
    "wof:placetype":"venue"
},
  "geometry": {"coordinates":[-80.04289300000001,40.360897],"type":"Point"}
}