{
  "type": "Feature",
  "properties": {
    "iso:country":"US",
    "sg:address":"664 Tire Hill Rd",
    "sg:city":"Johnstown",
    "sg:classifiers":[
        {
            "category":"Real Estate",
            "subcategory":"Real Estate Operator",
            "type":"Services"
        }
    ],
    "sg:phone":"+1   ",
    "sg:postcode":"15905",
    "sg:province":"PA",
    "sg:tags":[
        "building",
        "business",
        "nonresidential"
    ],
    "wof:name":"API Commercial Properties",
    "wof:placetype":"venue"
},
  "geometry": {"coordinates":[-78.915953,40.268772],"type":"Point"}
}