{
  "type": "Feature",
  "properties": {
    "iso:country":"US",
    "sg:address":"1550 Pond Rd",
    "sg:city":"Allentown",
    "sg:classifiers":[
        {
            "category":"Banks & Credit Unions",
            "subcategory":"Investment Brokerage",
            "type":"Services"
        }
    ],
    "sg:phone":"+1 610 973 2550",
    "sg:postcode":"18104",
    "sg:province":"PA",
    "sg:tags":[
        "consultant",
        "planning",
        "financial"
    ],
    "wof:name":"Oakwood Financial",
    "wof:placetype":"venue"
},
  "geometry": {"coordinates":[-75.538718,40.613728],"type":"Point"}
}