{
  "type": "Feature",
  "properties": {
    "iso:country":"US",
    "sg:address":"2345 Morton Rd",
    "sg:city":"Pittsburgh",
    "sg:classifiers":[
        {
            "category":"Building & Trades",
            "subcategory":"Construction",
            "type":"Services"
        }
    ],
    "sg:phone":"+1 412 287 1550",
    "sg:postcode":"15241",
    "sg:province":"PA",
    "sg:tags":[
        "brick-fire",
        "brick-clay-common",
        "face"
    ],
    "wof:name":"Admixture Products Inc.",
    "wof:placetype":"venue"
},
  "geometry": {"coordinates":[-80.09539100000001,40.333056],"type":"Point"}
}