{
  "type": "Feature",
  "properties": {
    "iso:country":"US",
    "sg:address":"1410 72nd Ave",
    "sg:city":"Philadelphia",
    "sg:classifiers":[
        {
            "category":"Shopping",
            "subcategory":"Clothing, Apparel, & Fashions",
            "type":"Retail Goods"
        }
    ],
    "sg:phone":"+1 215 866 7561",
    "sg:postcode":"19126",
    "sg:province":"PA",
    "sg:tags":[
        "apparel",
        "women's"
    ],
    "wof:name":"Adohr Apparels",
    "wof:placetype":"venue"
},
  "geometry": {"coordinates":[-75.139652,40.06283],"type":"Point"}
}