{
  "type": "Feature",
  "properties": {
    "iso:country":"US",
    "sg:address":"7401 State Rd",
    "sg:city":"Philadelphia",
    "sg:classifiers":[
        {
            "category":"Freight",
            "type":"Transportation"
        }
    ],
    "sg:phone":"+1 215 331 9398",
    "sg:postcode":"19136",
    "sg:province":"PA",
    "sg:tags":[
        "commercial",
        "storage"
    ],
    "wof:name":"E Z Storage",
    "wof:placetype":"venue"
},
  "geometry": {"coordinates":[-75.02741399999999,40.028118],"type":"Point"}
}