{
  "type": "Feature",
  "properties": {
    "iso:country":"US",
    "sg:address":"240 E Miller Ave",
    "sg:city":"Homestead",
    "sg:classifiers":[
        {
            "category":"Professional",
            "subcategory":"Detective & Security Services",
            "type":"Services"
        }
    ],
    "sg:phone":"+1   ",
    "sg:postcode":"15120",
    "sg:province":"PA",
    "sg:tags":[
        "system"
    ],
    "wof:name":"Protection Plus Inc",
    "wof:placetype":"venue"
},
  "geometry": {"coordinates":[-79.89846,40.38622],"type":"Point"}
}