{
  "type": "Feature",
  "properties": {
    "iso:country":"US",
    "sg:address":"23 E High St",
    "sg:city":"Topton",
    "sg:classifiers":[
        {
            "category":"Food & Beverages",
            "subcategory":"Meat & Fish",
            "type":"Retail Goods"
        }
    ],
    "sg:phone":"+1   ",
    "sg:postcode":"19562",
    "sg:province":"PA",
    "wof:name":"Gehris Quality Meats",
    "wof:placetype":"venue"
},
  "geometry": {"coordinates":[-75.701671,40.505189],"type":"Point"}
}