{
  "type": "Feature",
  "properties": {
    "addr:full":"29 N River St Plains PA 18705",
    "addr:housenumber":"29",
    "addr:postcode":"18705",
    "addr:street":"N River St",
    "iso:country":"US",
    "sg:address":"29 N River St",
    "sg:city":"Plains",
    "sg:classifiers":[
        {
            "category":"Government",
            "subcategory":"Post Office",
            "type":"Public Place"
        }
    ],
    "sg:phone":"+1 570 822 2597",
    "sg:postcode":"18705",
    "sg:province":"PA",
    "wof:name":"US Post Office",
    "wof:placetype":"venue"
},
  "geometry": {"coordinates":[-75.856719,41.278144],"type":"Point"}
}