{
  "type": "Feature",
  "properties": {
    "addr:full":"20 E Church St Lock Haven PA 17745",
    "addr:housenumber":"20",
    "addr:postcode":"17745",
    "addr:street":"E Church St",
    "iso:country":"US",
    "sg:address":"20 E Church St",
    "sg:city":"Lock Haven",
    "sg:classifiers":[
        {
            "category":"Government",
            "subcategory":"Police Station",
            "type":"Public Place"
        }
    ],
    "sg:phone":"+1   ",
    "sg:postcode":"17745",
    "sg:province":"PA",
    "sg:tags":[
        "protection"
    ],
    "wof:name":"Police Department",
    "wof:placetype":"venue"
},
  "geometry": {"coordinates":[-77.44706600000001,41.136113],"type":"Point"}
}