{
  "type": "Feature",
  "properties": {
    "iso:country":"US",
    "sg:address":"69 N Mountain Blvd",
    "sg:city":"Mountain Top",
    "sg:classifiers":[
        {
            "category":"Real Estate",
            "subcategory":"Real Estate Agent",
            "type":"Services"
        }
    ],
    "sg:phone":"+1 570 788 1047",
    "sg:postcode":"18707",
    "sg:province":"PA",
    "wof:name":"Century 21",
    "wof:placetype":"venue"
},
  "geometry": {"coordinates":[-75.879544,41.169295],"type":"Point"}
}