{
  "type": "Feature",
  "properties": {
    "iso:country":"US",
    "sg:address":"Rd",
    "sg:city":"Centre Hall",
    "sg:classifiers":[
        {
            "category":"Shopping",
            "subcategory":"Antiques",
            "type":"Retail Goods"
        },
        {
            "category":"Retail",
            "subcategory":"Auto Repair",
            "type":"Services"
        }
    ],
    "sg:phone":"+1 814 364 9585",
    "sg:postcode":"16828",
    "sg:province":"PA",
    "sg:tags":[
        "body",
        "shop"
    ],
    "wof:name":"Stan's Auto Body",
    "wof:placetype":"venue"
},
  "geometry": {"coordinates":[-77.685402,40.798901],"type":"Point"}
}