{
  "type": "Feature",
  "properties": {
    "iso:country":"US",
    "sg:address":"5313 Campbells Run Rd",
    "sg:city":"Pittsburgh",
    "sg:classifiers":[
        {
            "category":"Wholesale",
            "subcategory":"Office Equipment",
            "type":"Manufacturing & Wholesale Goods"
        }
    ],
    "sg:phone":"+1 412 788 1695",
    "sg:postcode":"15205",
    "sg:province":"PA",
    "sg:tags":[
        "machine",
        "duplicating",
        "copying"
    ],
    "wof:name":"Xerox Corp",
    "wof:placetype":"venue"
},
  "geometry": {"coordinates":[-80.15898199999999,40.444223],"type":"Point"}
}