{
  "type": "Feature",
  "properties": {
    "addr:full":"131 Center St Sayre PA 18840",
    "addr:housenumber":"131",
    "addr:postcode":"18840",
    "addr:street":"Center St",
    "iso:country":"US",
    "sg:address":"131 Center St",
    "sg:city":"Sayre",
    "sg:classifiers":[
        {
            "category":"Social Services",
            "subcategory":"Child Care",
            "type":"Services"
        }
    ],
    "sg:phone":"+1 570 888 2928",
    "sg:postcode":"18840",
    "sg:province":"PA",
    "sg:tags":[
        "day"
    ],
    "wof:name":"Little Lambs Daycare Center O",
    "wof:placetype":"venue"
},
  "geometry": {"coordinates":[-76.52905699999999,41.980185],"type":"Point"}
}