{
  "type": "Feature",
  "properties": {
    "iso:country":"US",
    "sg:address":"1601 Market St Ste 1700",
    "sg:city":"Philadelphia",
    "sg:classifiers":[
        {
            "category":"Organizations",
            "subcategory":"Labor Organization",
            "type":"Services"
        }
    ],
    "sg:phone":"+1 215 597 9960",
    "sg:postcode":"19103",
    "sg:province":"PA",
    "sg:tags":[
        "consultant",
        "relation"
    ],
    "wof:name":"Mspb N E Regional Office",
    "wof:placetype":"venue"
},
  "geometry": {"coordinates":[-75.16681699999999,39.952782],"type":"Point"}
}