{
  "type": "Feature",
  "properties": {
    "iso:country":"US",
    "sg:address":"30 Hunter Ln",
    "sg:city":"Camp Hill",
    "sg:classifiers":[
        {
            "category":"Banks & Credit Unions",
            "subcategory":"Bank",
            "type":"Services"
        }
    ],
    "sg:phone":"+1 717 975 5858",
    "sg:postcode":"17011",
    "sg:province":"PA",
    "wof:name":"Rae Credit Union",
    "wof:placetype":"venue"
},
  "geometry": {"coordinates":[-76.915381,40.25791],"type":"Point"}
}