{
  "type": "Feature",
  "properties": {
    "iso:country":"US",
    "sg:address":"205 Grandview Ave",
    "sg:city":"Camp Hill",
    "sg:classifiers":[
        {
            "category":"Health Services",
            "subcategory":"Doctor",
            "type":"Services"
        }
    ],
    "sg:phone":"+1 717 972 2821",
    "sg:postcode":"17011",
    "sg:province":"PA",
    "wof:name":"Patel Kaushal R MD",
    "wof:placetype":"venue"
},
  "geometry": {"coordinates":[-76.921774,40.257402],"type":"Point"}
}