{
  "type": "Feature",
  "properties": {
    "iso:country":"US",
    "sg:address":"14 Chestnut St",
    "sg:city":"Cressona",
    "sg:classifiers":[
        {
            "category":"Freight",
            "type":"Transportation"
        }
    ],
    "sg:phone":"+1   ",
    "sg:postcode":"17929",
    "sg:province":"PA",
    "sg:tags":[
        "operator",
        "trucking"
    ],
    "wof:name":"Aj Barger",
    "wof:placetype":"venue"
},
  "geometry": {"coordinates":[-76.195787,40.629819],"type":"Point"}
}