{
  "type": "Feature",
  "properties": {
    "iso:country":"US",
    "sg:address":"2225 Saw Mill Run Blvd",
    "sg:city":"Pittsburgh",
    "sg:classifiers":[
        {
            "category":"Autos & Motor Vehicles",
            "subcategory":"Recreational Vehicle Sales",
            "type":"Retail Goods"
        }
    ],
    "sg:phone":"+1   ",
    "sg:postcode":"15210",
    "sg:province":"PA",
    "sg:tags":[
        "parts",
        "trailer",
        "hitch"
    ],
    "wof:name":"American Rent-A-Trailer Co",
    "wof:placetype":"venue"
},
  "geometry": {"coordinates":[-79.996798,40.388874],"type":"Point"}
}