{
  "type": "Feature",
  "properties": {
    "iso:country":"US",
    "sg:address":"121 Fayette St",
    "sg:city":"Conshohocken",
    "sg:classifiers":[
        {
            "category":"Banks & Credit Unions",
            "subcategory":"Bank",
            "type":"Services"
        }
    ],
    "sg:phone":"+1 610 828 1331",
    "sg:postcode":"19428",
    "sg:province":"PA",
    "wof:name":"Reliance Federal Credit Union",
    "wof:placetype":"venue"
},
  "geometry": {"coordinates":[-75.30554600000001,40.0745],"type":"Point"}
}