{
  "type": "Feature",
  "properties": {
    "addr:full":"14233 Kutztown Rd Fleetwood PA 19522",
    "addr:housenumber":"14233",
    "addr:postcode":"19522",
    "addr:street":"Kutztown Rd",
    "iso:country":"US",
    "sg:address":"14233 Kutztown Rd",
    "sg:city":"Fleetwood",
    "sg:classifiers":[
        {
            "category":"Restaurant",
            "type":"Food & Drink"
        }
    ],
    "sg:phone":"+1 610 944 1384",
    "sg:postcode":"19522",
    "sg:province":"PA",
    "sg:tags":[
        "pizza"
    ],
    "wof:name":"Godfather's Pizza",
    "wof:placetype":"venue"
},
  "geometry": {"coordinates":[-75.841589,40.484488],"type":"Point"}
}