{
  "type": "Feature",
  "properties": {
    "iso:country":"US",
    "sg:address":"2618 Rhawn St",
    "sg:city":"Philadelphia",
    "sg:classifiers":[
        {
            "category":"Food & Beverages",
            "subcategory":"Groceries & Convenience Stores",
            "type":"Retail Goods"
        }
    ],
    "sg:phone":"+1 215 331 3238",
    "sg:postcode":"19152",
    "sg:province":"PA",
    "sg:tags":[
        "independent"
    ],
    "wof:name":"Super Farms Mini Market",
    "wof:placetype":"venue"
},
  "geometry": {"coordinates":[-75.04546999999999,40.055926],"type":"Point"}
}