{
  "type": "Feature",
  "properties": {
    "iso:country":"US",
    "sg:address":"201 S 14th St",
    "sg:city":"Allentown",
    "sg:classifiers":[
        {
            "category":"Restaurant",
            "type":"Food & Drink"
        },
        {
            "category":"Food & Beverages",
            "subcategory":"Groceries & Convenience Stores",
            "type":"Retail Goods"
        }
    ],
    "sg:phone":"+1 610 435 4224",
    "sg:postcode":"18102",
    "sg:province":"PA",
    "sg:tags":[
        "delicatessen",
        "sandwich"
    ],
    "wof:name":"Kocher's Deli",
    "wof:placetype":"venue"
},
  "geometry": {"coordinates":[-75.484703,40.595699],"type":"Point"}
}