{
  "type": "Feature",
  "properties": {
    "iso:country":"US",
    "sg:address":"471 Wigard Ave",
    "sg:city":"Philadelphia",
    "sg:classifiers":[
        {
            "category":"Communications",
            "subcategory":"Film & Video Production",
            "type":"Services"
        }
    ],
    "sg:phone":"+1 215 482 7998",
    "sg:postcode":"19128",
    "sg:province":"PA",
    "sg:tags":[
        "dvd",
        "cassette",
        "duplicating",
        "cd"
    ],
    "wof:name":"Moon Light & Sound",
    "wof:placetype":"venue"
},
  "geometry": {"coordinates":[-75.236749,40.048174],"type":"Point"}
}