{
  "type": "Feature",
  "properties": {
    "addr:full":"74 W High St Waynesburg PA 15370",
    "addr:housenumber":"74",
    "addr:postcode":"15370",
    "addr:street":"W High St",
    "iso:country":"US",
    "sg:address":"74 W High St",
    "sg:city":"Waynesburg",
    "sg:classifiers":[
        {
            "category":"Health Services",
            "subcategory":"Optometrist",
            "type":"Services"
        }
    ],
    "sg:phone":"+1 724 852 2200",
    "sg:postcode":"15370",
    "sg:province":"PA",
    "sg:tags":[
        "optical",
        "good"
    ],
    "wof:name":"Cathleen A Lizza Dr",
    "wof:placetype":"venue"
},
  "geometry": {"coordinates":[-80.188174,39.896422],"type":"Point"}
}