{
  "type": "Feature",
  "properties": {
    "addr:full":"825 Main St Boothwyn PA 19061",
    "addr:postcode":"825;19061",
    "addr:street":"Main St",
    "iso:country":"US",
    "sg:address":"825 Main St",
    "sg:city":"Boothwyn",
    "sg:classifiers":[
        {
            "category":"Retail",
            "subcategory":"Funeral Services",
            "type":"Services"
        }
    ],
    "sg:phone":"+1 610 494 0505",
    "sg:postcode":"19061",
    "sg:province":"PA",
    "sg:tags":[
        "director"
    ],
    "wof:name":"Moreland-Pagano Funeral Home",
    "wof:placetype":"venue"
},
  "geometry": {"coordinates":[-75.40740099999999,39.829479],"type":"Point"}
}