{
  "type": "Feature",
  "properties": {
    "addr:full":"1331 Saxonburg Blvd Glenshaw PA 15116",
    "addr:housenumber":"1331",
    "addr:postcode":"15116",
    "addr:street":"Saxonburg Blvd",
    "iso:country":"US",
    "sg:address":"1331 Saxonburg Blvd",
    "sg:city":"Glenshaw",
    "sg:classifiers":[
        {
            "category":"Restaurant",
            "type":"Food & Drink"
        }
    ],
    "sg:phone":"+1 412 767 9993",
    "sg:postcode":"15116",
    "sg:province":"PA",
    "wof:name":"Saxonburg Restaurant Inc",
    "wof:placetype":"venue"
},
  "geometry": {"coordinates":[-79.92006600000001,40.537523],"type":"Point"}
}