{
  "type": "Feature",
  "properties": {
    "iso:country":"US",
    "sg:address":"38 Sunrise Dr",
    "sg:city":"Pittsburgh",
    "sg:classifiers":[
        {
            "category":"Building & Trades",
            "subcategory":"Construction",
            "type":"Services"
        }
    ],
    "sg:phone":"+1   ",
    "sg:postcode":"15236",
    "sg:province":"PA",
    "sg:tags":[
        "house"
    ],
    "wof:name":"Jpj Construction",
    "wof:placetype":"venue"
},
  "geometry": {"coordinates":[-79.96082,40.340068],"type":"Point"}
}