{
  "type": "Feature",
  "properties": {
    "addr:full":"110 Bala Ave Bala Cynwyd PA 19004",
    "addr:housenumber":"110",
    "addr:postcode":"19004",
    "addr:street":"Bala Ave",
    "iso:country":"US",
    "sg:address":"110 Bala Ave",
    "sg:city":"Bala Cynwyd",
    "sg:classifiers":[
        {
            "category":"Banks & Credit Unions",
            "subcategory":"Investment Brokerage",
            "type":"Services"
        }
    ],
    "sg:phone":"+1 610 668 7670",
    "sg:postcode":"19004",
    "sg:province":"PA",
    "sg:tags":[
        "consultant",
        "financing"
    ],
    "wof:name":"Richmond Financial Svc Inc",
    "wof:placetype":"venue"
},
  "geometry": {"coordinates":[-75.232139,40.004982],"type":"Point"}
}