{
  "type": "Feature",
  "properties": {
    "iso:country":"US",
    "sg:address":"1033 Sumner Ave",
    "sg:city":"Allentown",
    "sg:classifiers":[
        {
            "category":"Home & Garden",
            "subcategory":"Home Furnishings",
            "type":"Retail Goods"
        }
    ],
    "sg:phone":"+1 610 435 9691",
    "sg:postcode":"18052",
    "sg:province":"PA",
    "sg:tags":[
        "lighting",
        "fixture"
    ],
    "wof:name":"Lighting Fixture & Supply Co",
    "wof:placetype":"venue"
},
  "geometry": {"coordinates":[-75.485907,40.612839],"type":"Point"}
}