{
  "type": "Feature",
  "properties": {
    "addr:full":"228 E Chestnut St Hanover PA 17331",
    "addr:housenumber":"228",
    "addr:postcode":"17331",
    "addr:street":"E Chestnut St",
    "iso:country":"US",
    "sg:address":"228 E Chestnut St",
    "sg:city":"Hanover",
    "sg:classifiers":[
        {
            "category":"Home & Garden",
            "subcategory":"Furniture",
            "type":"Retail Goods"
        }
    ],
    "sg:phone":"+1 717 633 5400",
    "sg:postcode":"17331",
    "sg:province":"PA",
    "wof:name":"Toomey's Furniture",
    "wof:placetype":"venue"
},
  "geometry": {"coordinates":[-76.98070300000001,39.804879],"type":"Point"}
}