{
  "type": "Feature",
  "properties": {
    "iso:country":"US",
    "sg:address":"761 Easton Rd",
    "sg:city":"Warrington",
    "sg:classifiers":[
        {
            "category":"Shopping",
            "subcategory":"Shoes",
            "type":"Retail Goods"
        }
    ],
    "sg:phone":"+1 215 343 6358",
    "sg:postcode":"18976",
    "sg:province":"PA",
    "sg:tags":[
        "store"
    ],
    "wof:name":"Dsw Inc",
    "wof:placetype":"venue"
},
  "geometry": {"coordinates":[-75.13709799999999,40.233691],"type":"Point"}
}