{
  "type": "Feature",
  "properties": {
    "iso:country":"US",
    "sg:address":"2809 Ritner Hwy",
    "sg:city":"Carlisle",
    "sg:classifiers":[
        {
            "category":"Manufacturing",
            "subcategory":"Petroleum Products",
            "type":"Manufacturing & Wholesale Goods"
        }
    ],
    "sg:phone":"+1 717 776 6030",
    "sg:postcode":"17015",
    "sg:province":"PA",
    "sg:tags":[
        "contract"
    ],
    "wof:name":"Denise Agar",
    "wof:placetype":"venue"
},
  "geometry": {"coordinates":[-77.31877,40.160379],"type":"Point"}
}