{
  "type": "Feature",
  "properties": {
    "addr:full":"968 Prescott Ave Scranton PA 18510",
    "addr:housenumber":"968",
    "addr:postcode":"18510",
    "addr:street":"Prescott Ave",
    "iso:country":"US",
    "sg:address":"968 Prescott Ave",
    "sg:city":"Scranton",
    "sg:classifiers":[
        {
            "category":"Banks & Credit Unions",
            "subcategory":"Bank",
            "type":"Services"
        }
    ],
    "sg:phone":"+1 570 342 9101",
    "sg:postcode":"18510",
    "sg:province":"PA",
    "sg:tags":[
        "state",
        "commercial"
    ],
    "wof:name":"Penn Security Bank & Trust Co",
    "wof:placetype":"venue"
},
  "geometry": {"coordinates":[-75.642577,41.409554],"type":"Point"}
}