{
  "type": "Feature",
  "properties": {
    "iso:country":"US",
    "sg:address":"821 W Main St",
    "sg:city":"Carnegie",
    "sg:classifiers":[
        {
            "category":"Shopping",
            "type":"Retail Goods"
        }
    ],
    "sg:phone":"+1   ",
    "sg:postcode":"15106",
    "sg:province":"PA",
    "sg:tags":[
        "merchandise"
    ],
    "wof:name":"Our Shop",
    "wof:placetype":"venue"
},
  "geometry": {"coordinates":[-80.09818799999999,40.399992],"type":"Point"}
}