{
  "type": "Feature",
  "properties": {
    "addr:full":"231 McClellan St Philadelphia PA 19148",
    "addr:housenumber":"231",
    "addr:postcode":"19148",
    "addr:street":"Mcclellan St",
    "iso:country":"US",
    "sg:address":"231 McClellan St",
    "sg:city":"Philadelphia",
    "sg:classifiers":[
        {
            "category":"Deli",
            "type":"Food & Drink"
        },
        {
            "category":"Food & Beverages",
            "subcategory":"Bakery",
            "type":"Retail Goods"
        }
    ],
    "sg:phone":"+1 215 334 7668",
    "sg:postcode":"19148",
    "sg:province":"PA",
    "sg:tags":[
        "sandwich"
    ],
    "wof:name":"Gooey Looie's",
    "wof:placetype":"venue"
},
  "geometry": {"coordinates":[-75.15055700000001,39.925206],"type":"Point"}
}