{
  "type": "Feature",
  "properties": {
    "iso:country":"US",
    "sg:address":"123 Glade Run Rd",
    "sg:city":"Mars",
    "sg:classifiers":[
        {
            "category":"Health Services",
            "subcategory":"Doctor",
            "type":"Services"
        }
    ],
    "sg:phone":"+1 724 625 3171",
    "sg:postcode":"16046",
    "sg:province":"PA",
    "sg:tags":[
        "medicine",
        "internal"
    ],
    "wof:name":"Rubio Wilfredo V MD",
    "wof:placetype":"venue"
},
  "geometry": {"coordinates":[-79.973408,40.71803],"type":"Point"}
}