{
  "type": "Feature",
  "properties": {
    "addr:full":"420 Mountain Ave Tamaqua PA 18252",
    "addr:housenumber":"420",
    "addr:postcode":"18252",
    "addr:street":"Mountain Ave",
    "iso:country":"US",
    "sg:address":"420 Mountain Ave",
    "sg:city":"Tamaqua",
    "sg:classifiers":[
        {
            "category":"Retail",
            "subcategory":"Auto Repair",
            "type":"Services"
        }
    ],
    "sg:phone":"+1   ",
    "sg:postcode":"18252",
    "sg:province":"PA",
    "sg:tags":[
        "body",
        "good",
        "sporting",
        "t",
        "motor",
        "boat"
    ],
    "wof:name":"Toms Autobody and Marine",
    "wof:placetype":"venue"
},
  "geometry": {"coordinates":[-75.959923,40.796343],"type":"Point"}
}