{
  "type": "Feature",
  "properties": {
    "iso:country":"US",
    "sg:address":"8 E State St",
    "sg:city":"Media",
    "sg:classifiers":[
        {
            "category":"Food & Beverages",
            "subcategory":"Liquor & Beverages",
            "type":"Retail Goods"
        }
    ],
    "sg:phone":"+1   ",
    "sg:postcode":"19063",
    "sg:province":"PA",
    "sg:tags":[
        "alcoholic"
    ],
    "wof:name":"Wine & Spirits Shoppe 2305",
    "wof:placetype":"venue"
},
  "geometry": {"coordinates":[-75.388841,39.917767],"type":"Point"}
}