{
  "type": "Feature",
  "properties": {
    "addr:full":"1915 Yorktown N Norristown PA 19403",
    "addr:housenumber":"1915",
    "addr:postcode":"19403",
    "addr:street":"Yorktown N",
    "iso:country":"US",
    "sg:address":"1915 Yorktown N",
    "sg:city":"Norristown",
    "sg:classifiers":[
        {
            "category":"Shopping",
            "subcategory":"Computers & Home Electronics",
            "type":"Retail Goods"
        }
    ],
    "sg:phone":"+1   ",
    "sg:postcode":"19403",
    "sg:province":"PA",
    "wof:name":"Computer Co Asci",
    "wof:placetype":"venue"
},
  "geometry": {"coordinates":[-75.38503799999999,40.121255],"type":"Point"}
}