{
  "type": "Feature",
  "properties": {
    "iso:country":"US",
    "sg:address":"4421 Market St",
    "sg:city":"Philadelphia",
    "sg:classifiers":[
        {
            "category":"Food & Beverages",
            "subcategory":"Groceries & Convenience Stores",
            "type":"Retail Goods"
        }
    ],
    "sg:phone":"+1 215 000 1111",
    "sg:postcode":"19104",
    "sg:province":"PA",
    "sg:tags":[
        "grocer"
    ],
    "wof:name":"Aldi",
    "wof:placetype":"venue"
},
  "geometry": {"coordinates":[-75.21080000000001,39.958313],"type":"Point"}
}