{
  "type": "Feature",
  "properties": {
    "addr:full":"36 S Main St Chambersburg PA 17201",
    "addr:housenumber":"36",
    "addr:postcode":"17201",
    "addr:street":"S Main St",
    "iso:country":"US",
    "sg:address":"36 S Main St",
    "sg:city":"Chambersburg",
    "sg:classifiers":[
        {
            "category":"Shopping",
            "subcategory":"Discount & Variety Stores",
            "type":"Retail Goods"
        }
    ],
    "sg:phone":"+1 717 267 3025",
    "sg:postcode":"17201",
    "sg:province":"PA",
    "wof:name":"Money Saver Discount",
    "wof:placetype":"venue"
},
  "geometry": {"coordinates":[-77.661421,39.936818],"type":"Point"}
}