{
  "type": "Feature",
  "properties": {
    "iso:country":"US",
    "sg:address":"227 Marwood Rd",
    "sg:city":"Cabot",
    "sg:classifiers":[
        {
            "category":"Insurance",
            "subcategory":"Insurance Agent",
            "type":"Services"
        }
    ],
    "sg:phone":"+1   ",
    "sg:postcode":"16023",
    "sg:province":"PA",
    "wof:name":"Mr Brant L Dempster",
    "wof:placetype":"venue"
},
  "geometry": {"coordinates":[-79.776008,40.778475],"type":"Point"}
}