{
  "type": "Feature",
  "properties": {
    "iso:country":"US",
    "sg:address":"1 Middleland Ave",
    "sg:city":"Charleroi",
    "sg:classifiers":[
        {
            "category":"Real Estate",
            "subcategory":"Real Estate Operator",
            "type":"Services"
        }
    ],
    "sg:phone":"+1   ",
    "sg:postcode":"15022",
    "sg:province":"PA",
    "sg:tags":[
        "building",
        "apartment",
        "executive"
    ],
    "wof:name":"Washington County Housing Auth",
    "wof:placetype":"venue"
},
  "geometry": {"coordinates":[-79.91000699999999,40.147019],"type":"Point"}
}