{
  "type": "Feature",
  "properties": {
    "addr:full":"6 N 3rd St Emmaus PA 18049",
    "addr:housenumber":"6",
    "addr:postcode":"18049",
    "addr:street":"N 3Rd St",
    "iso:country":"US",
    "sg:address":"6 N 3rd St",
    "sg:city":"Emmaus",
    "sg:classifiers":[
        {
            "category":"Wholesale",
            "subcategory":"Electrical",
            "type":"Manufacturing & Wholesale Goods"
        }
    ],
    "sg:phone":"+1   ",
    "sg:postcode":"18049",
    "sg:province":"PA",
    "sg:tags":[
        "s",
        "electronic"
    ],
    "wof:name":"Kistler Apartments",
    "wof:placetype":"venue"
},
  "geometry": {"coordinates":[-75.491084,40.536364],"type":"Point"}
}