{
  "type": "Feature",
  "properties": {
    "iso:country":"US",
    "sg:address":"654 Lincoln Ave",
    "sg:city":"Pittsburgh",
    "sg:classifiers":[
        {
            "category":"Personal",
            "subcategory":"Beauty Salon",
            "type":"Services"
        }
    ],
    "sg:phone":"+1 412 761 4512",
    "sg:postcode":"15202",
    "sg:province":"PA",
    "wof:name":"Cost Cutters Family Hair Care",
    "wof:placetype":"venue"
},
  "geometry": {"coordinates":[-80.059645,40.497613],"type":"Point"}
}