{
  "type": "Feature",
  "properties": {
    "iso:country":"US",
    "sg:address":"18 W Main St",
    "sg:city":"Schuylkill Haven",
    "sg:classifiers":[
        {
            "category":"Restaurant",
            "type":"Food & Drink"
        }
    ],
    "sg:phone":"+1   ",
    "sg:postcode":"17972",
    "sg:province":"PA",
    "sg:tags":[
        "eating"
    ],
    "wof:name":"Cullys Subs",
    "wof:placetype":"venue"
},
  "geometry": {"coordinates":[-76.173343,40.628506],"type":"Point"}
}