{
  "type": "Feature",
  "properties": {
    "iso:country":"US",
    "sg:address":"103 N Wales Rd",
    "sg:city":"North Wales",
    "sg:classifiers":[
        {
            "category":"Real Estate",
            "subcategory":"Real Estate Agent",
            "type":"Services"
        }
    ],
    "sg:phone":"+1 215 997 0595",
    "sg:postcode":"19454",
    "sg:province":"PA",
    "sg:tags":[
        "appraiser"
    ],
    "wof:name":"Mc Carthy Appaisals",
    "wof:placetype":"venue"
},
  "geometry": {"coordinates":[-75.259213,40.231311],"type":"Point"}
}