{
  "type": "Feature",
  "properties": {
    "iso:country":"US",
    "sg:address":"460 S 7th St",
    "sg:city":"Lehighton",
    "sg:classifiers":[
        {
            "category":"Organizations",
            "subcategory":"Religious Organization",
            "type":"Services"
        }
    ],
    "sg:phone":"+1 610 377 2450",
    "sg:postcode":"18235",
    "sg:province":"PA",
    "sg:tags":[
        "church"
    ],
    "wof:name":"Lehighton Congregation",
    "wof:placetype":"venue"
},
  "geometry": {"coordinates":[-75.71773399999999,40.825674],"type":"Point"}
}