{
  "type": "Feature",
  "properties": {
    "iso:country":"US",
    "sg:address":"1710 Stout Dr",
    "sg:city":"Warminster",
    "sg:classifiers":[
        {
            "category":"Building & Trades",
            "subcategory":"Cleaning & Sanitation",
            "type":"Services"
        }
    ],
    "sg:phone":"+1   ",
    "sg:postcode":"18974",
    "sg:province":"PA",
    "sg:tags":[
        "restoration"
    ],
    "wof:name":"A-1 Yates Services Grp Inc",
    "wof:placetype":"venue"
},
  "geometry": {"coordinates":[-75.075046,40.22564],"type":"Point"}
}