{
  "type": "Feature",
  "properties": {
    "addr:full":"70 N Main St Carbondale PA 18407",
    "addr:housenumber":"70",
    "addr:postcode":"18407",
    "addr:street":"N Main St",
    "iso:country":"US",
    "sg:address":"70 N Main St",
    "sg:city":"Carbondale",
    "sg:classifiers":[
        {
            "category":"Autos & Motor Vehicles",
            "subcategory":"Fuel & Gas Station",
            "type":"Retail Goods"
        }
    ],
    "sg:phone":"+1 570 281 9001",
    "sg:postcode":"18407",
    "sg:province":"PA",
    "sg:tags":[
        "oil"
    ],
    "wof:name":"Main Street Sunoco",
    "wof:placetype":"venue"
},
  "geometry": {"coordinates":[-75.499144,41.574937],"type":"Point"}
}