{
  "type": "Feature",
  "properties": {
    "iso:country":"US",
    "sg:address":"200 South St",
    "sg:city":"Ridgway",
    "sg:classifiers":[
        {
            "category":"Health Services",
            "subcategory":"Doctor",
            "type":"Services"
        }
    ],
    "sg:phone":"+1   ",
    "sg:postcode":"15853",
    "sg:province":"PA",
    "wof:name":"Paul Z Rees DMD",
    "wof:placetype":"venue"
},
  "geometry": {"coordinates":[-78.72976199999999,41.419436],"type":"Point"}
}