{
  "type": "Feature",
  "properties": {
    "iso:country":"US",
    "sg:address":"253 Sunset Dr",
    "sg:city":"Butler",
    "sg:classifiers":[
        {
            "category":"Retail",
            "subcategory":"Auto Repair",
            "type":"Services"
        }
    ],
    "sg:phone":"+1 724 287 2737",
    "sg:postcode":"16001",
    "sg:province":"PA",
    "sg:tags":[
        "body",
        "automotive"
    ],
    "wof:name":"Joe Pierrel Auto Inc",
    "wof:placetype":"venue"
},
  "geometry": {"coordinates":[-79.914526,40.90438],"type":"Point"}
}