{
  "type": "Feature",
  "properties": {
    "addr:full":"476 Hugart St Confluence PA 15424",
    "addr:housenumber":"476",
    "addr:postcode":"15424",
    "addr:street":"Hugart St",
    "iso:country":"US",
    "sg:address":"476 Hugart St",
    "sg:city":"Confluence",
    "sg:classifiers":[
        {
            "category":"Professional",
            "subcategory":"Lawyer & Legal Services",
            "type":"Services"
        }
    ],
    "sg:phone":"+1 814 395 5788",
    "sg:postcode":"15424",
    "sg:province":"PA",
    "sg:tags":[
        "attorney"
    ],
    "wof:name":"Ogle Policicchio & Frantz",
    "wof:placetype":"venue"
},
  "geometry": {"coordinates":[-79.359876,39.81254],"type":"Point"}
}