{
  "type": "Feature",
  "properties": {
    "addr:full":"1103 Edann Rd Oreland PA 19075",
    "addr:housenumber":"1103",
    "addr:postcode":"19075",
    "addr:street":"Edann Rd",
    "iso:country":"US",
    "sg:address":"1103 Edann Rd",
    "sg:city":"Oreland",
    "sg:classifiers":[
        {
            "category":"Building & Trades",
            "subcategory":"Plumbing",
            "type":"Services"
        }
    ],
    "sg:phone":"+1 215 233 5586",
    "sg:postcode":"19075",
    "sg:province":"PA",
    "sg:tags":[
        "plumbing",
        "contractor"
    ],
    "wof:name":"Manson-Parkes Co",
    "wof:placetype":"venue"
},
  "geometry": {"coordinates":[-75.185802,40.109385],"type":"Point"}
}