{
  "type": "Feature",
  "properties": {
    "iso:country":"US",
    "sg:address":"601 Hampton Rd",
    "sg:city":"Clarks Summit",
    "sg:classifiers":[
        {
            "category":"Insurance",
            "subcategory":"Insurance Agent",
            "type":"Services"
        }
    ],
    "sg:phone":"+1   ",
    "sg:postcode":"18411",
    "sg:province":"PA",
    "wof:name":"James Cammerota",
    "wof:placetype":"venue"
},
  "geometry": {"coordinates":[-75.685856,41.508331],"type":"Point"}
}