{
  "type": "Feature",
  "properties": {
    "iso:country":"US",
    "sg:address":"409 Front St",
    "sg:city":"Catasauqua",
    "sg:classifiers":[
        {
            "category":"Professional",
            "subcategory":"Computer Services",
            "type":"Services"
        }
    ],
    "sg:phone":"+1 610 266 5885",
    "sg:postcode":"18032",
    "sg:province":"PA",
    "sg:tags":[
        "repair"
    ],
    "wof:name":"Total PC Solutions",
    "wof:placetype":"venue"
},
  "geometry": {"coordinates":[-75.47399900000001,40.652802],"type":"Point"}
}