{
  "type": "Feature",
  "properties": {
    "addr:full":"3340 Concord Rd York PA 17402",
    "addr:housenumber":"3340",
    "addr:postcode":"17402",
    "addr:street":"Concord Rd",
    "iso:country":"US",
    "sg:address":"3340 Concord Rd",
    "sg:city":"York",
    "sg:classifiers":[
        {
            "category":"Wholesale",
            "subcategory":"Scrap",
            "type":"Manufacturing & Wholesale Goods"
        }
    ],
    "sg:phone":"+1 717 840 1844",
    "sg:postcode":"17402",
    "sg:province":"PA",
    "sg:tags":[
        "recycling",
        "center"
    ],
    "sg:website":"www.ncbcommodities.com",
    "wof:name":"Ncb Commodities",
    "wof:placetype":"venue"
},
  "geometry": {"coordinates":[-76.660596,39.988203],"type":"Point"}
}