{
  "type": "Feature",
  "properties": {
    "iso:country":"US",
    "sg:address":"172 Jacksonville Rd",
    "sg:city":"Bellefonte",
    "sg:classifiers":[
        {
            "category":"Retail",
            "subcategory":"Laundry & Dry Cleaning",
            "type":"Services"
        }
    ],
    "sg:phone":"+1 814 353 1880",
    "sg:postcode":"16823",
    "sg:province":"PA",
    "sg:tags":[
        "cleaners",
        "rug",
        "carpet"
    ],
    "wof:name":"Central Penn Steamway Carpet",
    "wof:placetype":"venue"
},
  "geometry": {"coordinates":[-77.74677699999999,40.931052],"type":"Point"}
}