{
  "type": "Feature",
  "properties": {
    "iso:country":"US",
    "sg:address":"147 Klever Rd",
    "sg:city":"West Sunbury",
    "sg:classifiers":[
        {
            "category":"Building & Trades",
            "subcategory":"Construction",
            "type":"Services"
        }
    ],
    "sg:phone":"+1 724 637 2522",
    "sg:postcode":"16061",
    "sg:province":"PA",
    "sg:tags":[
        "general",
        "contractor"
    ],
    "wof:name":"P B & B Construction Co",
    "wof:placetype":"venue"
},
  "geometry": {"coordinates":[-79.867845,40.978875],"type":"Point"}
}