{
  "type": "Feature",
  "properties": {
    "iso:country":"US",
    "sg:address":"681 Bethlehem Pike",
    "sg:city":"Montgomeryvle",
    "sg:classifiers":[
        {
            "category":"Autos & Motor Vehicles",
            "subcategory":"Automobile Sales",
            "type":"Retail Goods"
        }
    ],
    "sg:phone":"+1 215 361 0117",
    "sg:postcode":"18936",
    "sg:province":"PA",
    "sg:tags":[
        "car"
    ],
    "wof:name":"Keystone Motors Isuzu",
    "wof:placetype":"venue"
},
  "geometry": {"coordinates":[-75.23809799999999,40.232101],"type":"Point"}
}