{
  "type": "Feature",
  "properties": {
    "addr:full":"290 Harrison Ave Morrisville PA 19067",
    "addr:housenumber":"290",
    "addr:postcode":"19067",
    "addr:street":"Harrison Ave",
    "iso:country":"US",
    "sg:address":"290 Harrison Ave",
    "sg:city":"Morrisville",
    "sg:classifiers":[
        {
            "category":"Professional",
            "subcategory":"Business Services",
            "type":"Services"
        }
    ],
    "sg:phone":"+1   ",
    "sg:postcode":"19067",
    "sg:province":"PA",
    "sg:tags":[
        "automotive",
        "towing",
        "repossession"
    ],
    "wof:name":"Daves Towing",
    "wof:placetype":"venue"
},
  "geometry": {"coordinates":[-74.775414,40.199421],"type":"Point"}
}