{
  "type": "Feature",
  "properties": {
    "iso:country":"US",
    "sg:address":"16 Highview Dr",
    "sg:city":"Sewickley",
    "sg:classifiers":[
        {
            "category":"Banks & Credit Unions",
            "subcategory":"Investment Brokerage",
            "type":"Services"
        }
    ],
    "sg:phone":"+1   ",
    "sg:postcode":"15143",
    "sg:province":"PA",
    "sg:tags":[
        "advisory"
    ],
    "wof:name":"Ibex Financial Resources Inc",
    "wof:placetype":"venue"
},
  "geometry": {"coordinates":[-80.17833299999999,40.58938],"type":"Point"}
}