{
  "type": "Feature",
  "properties": {
    "iso:country":"US",
    "sg:address":"4068 Mount Royal Blvd",
    "sg:city":"Allison Park",
    "sg:classifiers":[
        {
            "category":"Organizations",
            "subcategory":"Non-profit Organization",
            "type":"Services"
        }
    ],
    "sg:phone":"+1 412 487 6851",
    "sg:postcode":"15101",
    "sg:province":"PA",
    "sg:tags":[
        "human"
    ],
    "wof:name":"National Alliance-Autism Rsrch",
    "wof:placetype":"venue"
},
  "geometry": {"coordinates":[-79.965476,40.566865],"type":"Point"}
}