{
  "type": "Feature",
  "properties": {
    "addr:full":"330 Larry Holmes Dr Easton PA 18042",
    "addr:housenumber":"330",
    "addr:postcode":"18042",
    "addr:street":"Larry Holmes Dr",
    "iso:country":"US",
    "sg:address":"330 Larry Holmes Dr",
    "sg:city":"Easton",
    "sg:classifiers":[
        {
            "category":"Restaurant",
            "type":"Food & Drink"
        }
    ],
    "sg:menulink":"http://www.allmenus.com/pa/easton/66281-dominos-pizza/menu/",
    "sg:phone":"+1 610 258 7100",
    "sg:postcode":"18042",
    "sg:province":"PA",
    "sg:tags":[
        "american",
        "wing",
        "pizza"
    ],
    "wof:name":"Domino's Pizza",
    "wof:placetype":"venue"
},
  "geometry": {"coordinates":[-75.20789600000001,40.688099],"type":"Point"}
}