{
  "type": "Feature",
  "properties": {
    "iso:country":"US",
    "sg:address":"2009 Woodside Rd",
    "sg:city":"Glenshaw",
    "sg:classifiers":[
        {
            "category":"Real Estate",
            "subcategory":"Real Estate Operator",
            "type":"Services"
        }
    ],
    "sg:phone":"+1   ",
    "sg:postcode":"15116",
    "sg:province":"PA",
    "sg:tags":[
        "building",
        "industrial",
        "commercial",
        "sales"
    ],
    "wof:name":"Innovative Bldg Solutions LLC",
    "wof:placetype":"venue"
},
  "geometry": {"coordinates":[-79.97003599999999,40.533198],"type":"Point"}
}