{
  "type": "Feature",
  "properties": {
    "iso:country":"US",
    "sg:address":"4208 Ridge Ave",
    "sg:city":"Philadelphia",
    "sg:classifiers":[
        {
            "category":"Government",
            "subcategory":"Fire Station",
            "type":"Public Place"
        }
    ],
    "sg:phone":"+1   ",
    "sg:postcode":"19129",
    "sg:province":"PA",
    "sg:tags":[
        "protection"
    ],
    "wof:name":"Fire Dept",
    "wof:placetype":"venue"
},
  "geometry": {"coordinates":[-75.194524,40.009026],"type":"Point"}
}