{
  "type": "Feature",
  "properties": {
    "addr:full":"420 S 45th St Apt 3F Philadelphia PA 19104",
    "addr:housenumber":"420;3f",
    "addr:postcode":"19104",
    "addr:street":"S 45Th St Apt",
    "iso:country":"US",
    "sg:address":"420 S 45th St Apt 3F",
    "sg:city":"Philadelphia",
    "sg:classifiers":[
        {
            "category":"Building & Trades",
            "subcategory":"Construction",
            "type":"Services"
        }
    ],
    "sg:phone":"+1 215 243 0161",
    "sg:postcode":"19104",
    "sg:province":"PA",
    "sg:tags":[
        "wallcoverings-installation",
        "wallpaper",
        "painting",
        "contractor"
    ],
    "wof:name":"Fine Art Paintings",
    "wof:placetype":"venue"
},
  "geometry": {"coordinates":[-75.21255499999999,39.951042],"type":"Point"}
}