{
  "type": "Feature",
  "properties": {
    "iso:country":"US",
    "sg:address":"107 Parkhurst St",
    "sg:city":"Elkland",
    "sg:classifiers":[
        {
            "category":"Real Estate",
            "subcategory":"Real Estate Agent",
            "type":"Services"
        }
    ],
    "sg:phone":"+1 814 258 5668",
    "sg:postcode":"16920",
    "sg:province":"NY",
    "wof:name":"R & S Properties",
    "wof:placetype":"venue"
},
  "geometry": {"coordinates":[-77.313304,41.987957],"type":"Point"}
}