{
  "type": "Feature",
  "properties": {
    "addr:full":"2791 E Winter Rd Loganton PA 17747",
    "addr:housenumber":"2791",
    "addr:postcode":"17747",
    "addr:street":"E Winter Rd",
    "iso:country":"US",
    "sg:address":"2791 E Winter Rd",
    "sg:city":"Loganton",
    "sg:classifiers":[
        {
            "category":"Manufacturing",
            "subcategory":"Petroleum Products",
            "type":"Manufacturing & Wholesale Goods"
        }
    ],
    "sg:phone":"+1 570 725 3050",
    "sg:postcode":"17747",
    "sg:province":"PA",
    "sg:tags":[
        "lubricating",
        "oil",
        "grease"
    ],
    "wof:name":"Walizer's Sales & Svc",
    "wof:placetype":"venue"
},
  "geometry": {"coordinates":[-77.21542700000001,41.046621],"type":"Point"}
}