{
  "type": "Feature",
  "properties": {
    "iso:country":"US",
    "sg:address":"502 Jason Dr",
    "sg:city":"Southampton",
    "sg:classifiers":[
        {
            "category":"Building & Trades",
            "subcategory":"Construction",
            "type":"Services"
        }
    ],
    "sg:phone":"+1   ",
    "sg:postcode":"18966",
    "sg:province":"PA",
    "sg:tags":[
        "house",
        "general",
        "family",
        "contractor"
    ],
    "wof:name":"Keystone Select Builders",
    "wof:placetype":"venue"
},
  "geometry": {"coordinates":[-75.025808,40.159568],"type":"Point"}
}