{
  "type": "Feature",
  "properties": {
    "addr:full":"576 E Lancaster Ave Berwyn PA 19312",
    "addr:housenumber":"576",
    "addr:postcode":"19312",
    "addr:street":"E Lancaster Ave",
    "iso:country":"US",
    "sg:address":"576 E Lancaster Ave",
    "sg:city":"Berwyn",
    "sg:classifiers":[
        {
            "category":"Retail",
            "subcategory":"Auto Repair",
            "type":"Services"
        }
    ],
    "sg:phone":"+1   ",
    "sg:postcode":"19312",
    "sg:province":"PA",
    "sg:tags":[
        "automobile"
    ],
    "wof:name":"Jims Berwyn Auto Repair Ctr",
    "wof:placetype":"venue"
},
  "geometry": {"coordinates":[-75.441366,40.047869],"type":"Point"}
}