{
  "type": "Feature",
  "properties": {
    "iso:country":"US",
    "sg:address":"1672 Summit Lake Rd",
    "sg:city":"Clarks Summit",
    "sg:classifiers":[
        {
            "category":"Professional",
            "subcategory":"Lawyer & Legal Services",
            "type":"Services"
        }
    ],
    "sg:phone":"+1   ",
    "sg:postcode":"18411",
    "sg:province":"PA",
    "wof:name":"Randle John Brooks",
    "wof:placetype":"venue"
},
  "geometry": {"coordinates":[-75.726786,41.461668],"type":"Point"}
}