{
  "type": "Feature",
  "properties": {
    "addr:full":"246 Reifsnyder Rd Lititz PA 17543",
    "addr:housenumber":"246",
    "addr:postcode":"17543",
    "addr:street":"Reifsnyder Rd",
    "iso:country":"US",
    "sg:address":"246 Reifsnyder Rd",
    "sg:city":"Lititz",
    "sg:classifiers":[
        {
            "category":"Professional",
            "type":"Services"
        }
    ],
    "sg:phone":"+1   ",
    "sg:postcode":"17543",
    "sg:province":"PA",
    "wof:name":"Promised Land AG",
    "wof:placetype":"venue"
},
  "geometry": {"coordinates":[-76.289632,40.216256],"type":"Point"}
}