{
  "type": "Feature",
  "properties": {
    "iso:country":"US",
    "sg:address":"1014 Hagys Ford Rd",
    "sg:city":"Narberth",
    "sg:classifiers":[
        {
            "category":"Health Services",
            "subcategory":"Doctor",
            "type":"Services"
        }
    ],
    "sg:phone":"+1 610 664 8964",
    "sg:postcode":"19072",
    "sg:province":"PA",
    "wof:name":"Katz M Richard MD",
    "wof:placetype":"venue"
},
  "geometry": {"coordinates":[-75.258301,40.025002],"type":"Point"}
}