{
  "type": "Feature",
  "properties": {
    "addr:full":"506 S Franklin Ave Somerset PA 15501",
    "addr:housenumber":"506",
    "addr:postcode":"15501",
    "addr:street":"S Franklin Ave",
    "iso:country":"US",
    "sg:address":"506 S Franklin Ave",
    "sg:city":"Somerset",
    "sg:classifiers":[
        {
            "category":"Building & Trades",
            "subcategory":"Construction",
            "type":"Services"
        }
    ],
    "sg:phone":"+1   ",
    "sg:postcode":"15501",
    "sg:province":"PA",
    "sg:tags":[
        "house"
    ],
    "wof:name":"Jason S Ankeny",
    "wof:placetype":"venue"
},
  "geometry": {"coordinates":[-79.08911999999999,40.004705],"type":"Point"}
}