{
  "type": "Feature",
  "properties": {
    "iso:country":"US",
    "sg:address":"1040 Boot Rd",
    "sg:city":"Downingtown",
    "sg:classifiers":[
        {
            "category":"Retail",
            "subcategory":"Auto Repair",
            "type":"Services"
        }
    ],
    "sg:phone":"+1 610 269 6444",
    "sg:postcode":"19335",
    "sg:province":"PA",
    "sg:tags":[
        "repairing",
        "automobile",
        "transmission"
    ],
    "wof:name":"Transplant Transmission Spec",
    "wof:placetype":"venue"
},
  "geometry": {"coordinates":[-75.66973900000001,40.006556],"type":"Point"}
}