{
  "type": "Feature",
  "properties": {
    "addr:full":"112 Confer Vista Dr Uniontown PA 15401",
    "addr:housenumber":"112",
    "addr:postcode":"15401",
    "addr:street":"Confer Vista Dr",
    "iso:country":"US",
    "sg:address":"112 Confer Vista Dr",
    "sg:city":"Uniontown",
    "sg:classifiers":[
        {
            "category":"Professional",
            "subcategory":"Lawyer & Legal Services",
            "type":"Services"
        }
    ],
    "sg:phone":"+1 724 438 3638",
    "sg:postcode":"15401",
    "sg:province":"PA",
    "sg:tags":[
        "plan"
    ],
    "wof:name":"Woomer Law Group",
    "wof:placetype":"venue"
},
  "geometry": {"coordinates":[-79.731334,39.923783],"type":"Point"}
}