{
  "type": "Feature",
  "properties": {
    "iso:country":"US",
    "sg:address":"1350 Locust St Ste 220",
    "sg:city":"Pittsburgh",
    "sg:classifiers":[
        {
            "category":"Health Services",
            "subcategory":"Doctor",
            "type":"Services"
        }
    ],
    "sg:phone":"+1 412 232 5800",
    "sg:postcode":"15219",
    "sg:province":"PA",
    "sg:tags":[
        "orthopedist"
    ],
    "wof:name":"Habib Gregory F DO",
    "wof:placetype":"venue"
},
  "geometry": {"coordinates":[-79.988683,40.436741],"type":"Point"}
}