{
  "type": "Feature",
  "properties": {
    "iso:country":"US",
    "sg:address":"216 Forge Hill Rd",
    "sg:city":"Wrightsville",
    "sg:classifiers":[
        {
            "category":"Professional",
            "subcategory":"Business Services",
            "type":"Services"
        }
    ],
    "sg:phone":"+1   ",
    "sg:postcode":"17368",
    "sg:province":"PA",
    "wof:name":"Gilbert Brian L",
    "wof:placetype":"venue"
},
  "geometry": {"coordinates":[-76.51144600000001,39.960224],"type":"Point"}
}