{
  "type": "Feature",
  "properties": {
    "iso:country":"US",
    "sg:address":"1075 Virginia Dr",
    "sg:city":"Fort Washington",
    "sg:classifiers":[
        {
            "category":"Wholesale",
            "subcategory":"Metals & Minerals",
            "type":"Manufacturing & Wholesale Goods"
        }
    ],
    "sg:phone":"+1   ",
    "sg:postcode":"19034",
    "sg:province":"PA",
    "sg:tags":[
        "center"
    ],
    "wof:name":"Carpenter Specialty Alloys",
    "wof:placetype":"venue"
},
  "geometry": {"coordinates":[-75.180013,40.136321],"type":"Point"}
}