{
  "type": "Feature",
  "properties": {
    "addr:full":"1120 Snyder Corner Rd Red Lion PA 17356",
    "addr:housenumber":"1120",
    "addr:postcode":"17356",
    "addr:street":"Snyder Corner Rd",
    "iso:country":"US",
    "sg:address":"1120 Snyder Corner Rd",
    "sg:city":"Red Lion",
    "sg:classifiers":[
        {
            "category":"Farming",
            "subcategory":"Livestock Farm",
            "type":"Manufacturing & Wholesale Goods"
        }
    ],
    "sg:phone":"+1   ",
    "sg:postcode":"17356",
    "sg:province":"PA",
    "sg:tags":[
        "wheat",
        "beef",
        "cash",
        "grain",
        "cattle",
        "feedlot"
    ],
    "wof:name":"Donald Rexroth",
    "wof:placetype":"venue"
},
  "geometry": {"coordinates":[-76.53506299999999,39.907796],"type":"Point"}
}