{
  "type": "Feature",
  "properties": {
    "iso:country":"US",
    "sg:address":"29 York St",
    "sg:city":"Gettysburg",
    "sg:classifiers":[
        {
            "category":"Personal",
            "subcategory":"Beauty Salon",
            "type":"Services"
        }
    ],
    "sg:phone":"+1 717 398 2064",
    "sg:postcode":"17325",
    "sg:province":"PA",
    "wof:name":"Grace Kelly Salon",
    "wof:placetype":"venue"
},
  "geometry": {"coordinates":[-77.230309,39.830923],"type":"Point"}
}