{
  "type": "Feature",
  "properties": {
    "iso:country":"US",
    "sg:address":"1852 Delmar Dr",
    "sg:city":"Folcroft",
    "sg:classifiers":[
        {
            "category":"Shopping",
            "subcategory":"Bicycles & Sporting Goods",
            "type":"Retail Goods"
        }
    ],
    "sg:phone":"+1 610 583 1614",
    "sg:postcode":"19032",
    "sg:province":"PA",
    "wof:name":"South East Archery & Sports",
    "wof:placetype":"venue"
},
  "geometry": {"coordinates":[-75.283424,39.89156],"type":"Point"}
}