{
  "type": "Feature",
  "properties": {
    "addr:full":"1815 Robison Rd W Erie PA 16509",
    "addr:housenumber":"1815",
    "addr:postcode":"16509",
    "addr:street":"Robison Rd W",
    "iso:country":"US",
    "sg:address":"1815 Robison Rd W",
    "sg:city":"Erie",
    "sg:classifiers":[
        {
            "category":"Organizations",
            "subcategory":"Community Association",
            "type":"Services"
        }
    ],
    "sg:phone":"+1   ",
    "sg:postcode":"16509",
    "sg:province":"PA",
    "sg:tags":[
        "religious"
    ],
    "wof:name":"Boy Scout Council",
    "wof:placetype":"venue"
},
  "geometry": {"coordinates":[-80.075068,42.044392],"type":"Point"}
}