{
  "type": "Feature",
  "properties": {
    "iso:country":"US",
    "sg:address":"501 N 17th St",
    "sg:city":"Allentown",
    "sg:classifiers":[
        {
            "category":"Health Services",
            "subcategory":"Doctor",
            "type":"Services"
        }
    ],
    "sg:phone":"+1 610 435 9000",
    "sg:postcode":"18104",
    "sg:province":"PA",
    "sg:tags":[
        "dermatologist"
    ],
    "wof:name":"Meyer Pamela L PC",
    "wof:placetype":"venue"
},
  "geometry": {"coordinates":[-75.495499,40.6035],"type":"Point"}
}