{
  "type": "Feature",
  "properties": {
    "iso:country":"US",
    "sg:address":"RR 309",
    "sg:city":"Colmar",
    "sg:classifiers":[
        {
            "category":"Restaurant",
            "type":"Food & Drink"
        }
    ],
    "sg:phone":"+1 215 822 6610",
    "sg:postcode":"18915",
    "sg:province":"PA",
    "wof:name":"Inn Flight Steak & Seafood Grille",
    "wof:placetype":"venue"
},
  "geometry": {"coordinates":[-75.25700399999999,40.2714],"type":"Point"}
}