{
  "type": "Feature",
  "properties": {
    "addr:full":"1207 Brickell Ave Jeannette PA 15644",
    "addr:housenumber":"1207",
    "addr:postcode":"15644",
    "addr:street":"Brickell Ave",
    "iso:country":"US",
    "sg:address":"1207 Brickell Ave",
    "sg:city":"Jeannette",
    "sg:classifiers":[
        {
            "category":"Manufacturing",
            "subcategory":"Pottery",
            "type":"Manufacturing & Wholesale Goods"
        }
    ],
    "sg:phone":"+1 724 523 4798",
    "sg:postcode":"15644",
    "sg:province":"PA",
    "sg:tags":[
        "pottery-wholesale",
        "manufacturer"
    ],
    "wof:name":"Saving Grace Pottery",
    "wof:placetype":"venue"
},
  "geometry": {"coordinates":[-79.613998,40.336128],"type":"Point"}
}