{
  "type": "Feature",
  "properties": {
    "iso:country":"US",
    "sg:address":"111 Stoney Run Rd",
    "sg:city":"Dillsburg",
    "sg:classifiers":[
        {
            "category":"Retail",
            "subcategory":"Repair Shop",
            "type":"Services"
        }
    ],
    "sg:phone":"+1 717 432 1589",
    "sg:postcode":"17019",
    "sg:province":"PA",
    "sg:tags":[
        "repairing",
        "lawn",
        "mower"
    ],
    "wof:name":"Seifert's Repair Svc",
    "wof:placetype":"venue"
},
  "geometry": {"coordinates":[-77.018055,40.091075],"type":"Point"}
}