{
  "type": "Feature",
  "properties": {
    "iso:country":"US",
    "sg:address":"308 Hummingbird Cir",
    "sg:city":"Cranberry Twp",
    "sg:classifiers":[
        {
            "category":"Building & Trades",
            "subcategory":"Construction",
            "type":"Services"
        }
    ],
    "sg:phone":"+1 724 776 3251",
    "sg:postcode":"16066",
    "sg:province":"PA",
    "sg:tags":[
        "contractor"
    ],
    "wof:name":"Washington Homes Incorporated",
    "wof:placetype":"venue"
},
  "geometry": {"coordinates":[-80.132877,40.675671],"type":"Point"}
}