{
  "type": "Feature",
  "properties": {
    "iso:country":"US",
    "sg:address":"4224 Market St",
    "sg:city":"Philadelphia",
    "sg:classifiers":[
        {
            "category":"Wholesale",
            "subcategory":"Machinery & Supplies",
            "type":"Manufacturing & Wholesale Goods"
        }
    ],
    "sg:phone":"+1   ",
    "sg:postcode":"19104",
    "sg:province":"PA",
    "sg:tags":[
        "construction",
        "equipment",
        "ha",
        "industrial"
    ],
    "wof:name":"Atlantic Tool & Supply",
    "wof:placetype":"venue"
},
  "geometry": {"coordinates":[-75.20655600000001,39.957628],"type":"Point"}
}