{
  "type": "Feature",
  "properties": {
    "iso:country":"US",
    "sg:address":"2329 Cottman Ave",
    "sg:city":"Philadelphia",
    "sg:classifiers":[
        {
            "category":"Personal",
            "subcategory":"Beauty Salon",
            "type":"Services"
        }
    ],
    "sg:phone":"+1 215 331 4511",
    "sg:postcode":"19149",
    "sg:province":"PA",
    "sg:tags":[
        "manicuring"
    ],
    "wof:name":"Nail Glamour",
    "wof:placetype":"venue"
},
  "geometry": {"coordinates":[-75.060205,40.048049],"type":"Point"}
}