{
  "type": "Feature",
  "properties": {
    "iso:country":"US",
    "sg:address":"237 Buford Ave",
    "sg:city":"Gettysburg",
    "sg:classifiers":[
        {
            "category":"Restaurant",
            "type":"Food & Drink"
        }
    ],
    "sg:menulink":"http://www.allmenus.com/pa/gettysburg/71988-pizza-hut/menu/",
    "sg:phone":"+1 717 334 2165",
    "sg:postcode":"17325",
    "sg:province":"PA",
    "sg:tags":[
        "american",
        "pizza"
    ],
    "wof:name":"Pizza Hut",
    "wof:placetype":"venue"
},
  "geometry": {"coordinates":[-77.240302,39.832614],"type":"Point"}
}