{
  "type": "Feature",
  "properties": {
    "addr:full":"2334 Oakland Ave Indiana PA 15701",
    "addr:housenumber":"2334",
    "addr:postcode":"15701",
    "addr:street":"Oakland Ave",
    "iso:country":"US",
    "sg:address":"2334 Oakland Ave",
    "sg:city":"Indiana",
    "sg:classifiers":[
        {
            "category":"Shopping",
            "subcategory":"Clothing, Apparel, & Fashions",
            "type":"Retail Goods"
        }
    ],
    "sg:phone":"+1 724 357 8310",
    "sg:postcode":"15701",
    "sg:province":"PA",
    "sg:tags":[
        "clot",
        "ready",
        "wear",
        "casual"
    ],
    "wof:name":"Maurice's",
    "wof:placetype":"venue"
},
  "geometry": {"coordinates":[-79.181495,40.607071],"type":"Point"}
}