{
  "type": "Feature",
  "properties": {
    "addr:full":"290 Big Sewickley Creek Rd Sewickley PA 15143",
    "addr:housenumber":"290",
    "addr:postcode":"15143",
    "addr:street":"Big Sewickley Creek Rd",
    "iso:country":"US",
    "sg:address":"290 Big Sewickley Creek Rd",
    "sg:city":"Sewickley",
    "sg:classifiers":[
        {
            "category":"Building & Trades",
            "subcategory":"Plumbing",
            "type":"Services"
        }
    ],
    "sg:phone":"+1 724 266 8070",
    "sg:postcode":"15143",
    "sg:province":"PA",
    "sg:tags":[
        "conditioning",
        "air",
        "system",
        "contractor"
    ],
    "wof:name":"Breezewood Air Cond Inc",
    "wof:placetype":"venue"
},
  "geometry": {"coordinates":[-80.177346,40.608106],"type":"Point"}
}