{
  "type": "Feature",
  "properties": {
    "iso:country":"US",
    "sg:address":"550 Homestead Rd",
    "sg:city":"Hershey",
    "sg:classifiers":[
        {
            "category":"Professional",
            "type":"Services"
        }
    ],
    "sg:phone":"+1 717 534 2509",
    "sg:postcode":"17033",
    "sg:province":"PA",
    "sg:tags":[
        "elementary",
        "school"
    ],
    "wof:name":"Derry Township Elementary",
    "wof:placetype":"venue"
},
  "geometry": {"coordinates":[-76.64009900000001,40.279999],"type":"Point"}
}