{
  "type": "Feature",
  "properties": {
    "iso:country":"US",
    "sg:address":"1021 Park Ave",
    "sg:city":"Quakertown",
    "sg:classifiers":[
        {
            "category":"Health Services",
            "subcategory":"Health Practitioner",
            "type":"Services"
        }
    ],
    "sg:phone":"+1 215 538 4621",
    "sg:postcode":"18951",
    "sg:province":"PA",
    "sg:tags":[
        "nutritionist"
    ],
    "wof:name":"St Luke's Quakertown Nutrition",
    "wof:placetype":"venue"
},
  "geometry": {"coordinates":[-75.34836900000001,40.437873],"type":"Point"}
}