{
  "type": "Feature",
  "properties": {
    "addr:full":"29 W 4th St Williamsport PA 17701",
    "addr:housenumber":"29",
    "addr:postcode":"17701",
    "addr:street":"W 4Th St",
    "iso:country":"US",
    "sg:address":"29 W 4th St",
    "sg:city":"Williamsport",
    "sg:classifiers":[
        {
            "category":"Professional",
            "type":"Services"
        }
    ],
    "sg:phone":"+1   ",
    "sg:postcode":"17701",
    "sg:province":"PA",
    "wof:name":"Super Skeet",
    "wof:placetype":"venue"
},
  "geometry": {"coordinates":[-77.00306500000001,41.241699],"type":"Point"}
}