{
  "type": "Feature",
  "properties": {
    "addr:full":"1627 Chestnut Ridge Dr Pittsburgh PA 15205",
    "addr:housenumber":"1627",
    "addr:postcode":"15205",
    "addr:street":"Chestnut Ridge Dr",
    "iso:country":"US",
    "sg:address":"1627 Chestnut Ridge Dr",
    "sg:city":"Pittsburgh",
    "sg:classifiers":[
        {
            "category":"Professional",
            "subcategory":"Detective & Security Services",
            "type":"Services"
        }
    ],
    "sg:phone":"+1 412 787 0761",
    "sg:postcode":"15205",
    "sg:province":"PA",
    "sg:tags":[
        "investigator"
    ],
    "wof:name":"Audits & Investigations LLC",
    "wof:placetype":"venue"
},
  "geometry": {"coordinates":[-80.150268,40.436244],"type":"Point"}
}