{
  "type": "Feature",
  "properties": {
    "addr:full":"700 E Parker St Scranton PA 18509",
    "addr:housenumber":"700",
    "addr:postcode":"18509",
    "addr:street":"E Parker St",
    "iso:country":"US",
    "sg:address":"700 E Parker St",
    "sg:city":"Scranton",
    "sg:classifiers":[
        {
            "category":"Manufacturing",
            "subcategory":"Textiles",
            "type":"Manufacturing & Wholesale Goods"
        }
    ],
    "sg:phone":"+1 570 207 7000",
    "sg:postcode":"18509",
    "sg:province":"PA",
    "sg:tags":[
        "mills"
    ],
    "sg:website":"www.jauntytextile.com",
    "wof:name":"Jaunty Textiles",
    "wof:placetype":"venue"
},
  "geometry": {"coordinates":[-75.639064,41.440028],"type":"Point"}
}