{
  "type": "Feature",
  "properties": {
    "iso:country":"US",
    "sg:address":"6036 Limeport Pike",
    "sg:city":"Coopersburg",
    "sg:classifiers":[
        {
            "category":"Building & Trades",
            "subcategory":"Construction",
            "type":"Services"
        }
    ],
    "sg:phone":"+1   ",
    "sg:postcode":"18036",
    "sg:province":"PA",
    "sg:tags":[
        "house"
    ],
    "wof:name":"Willard H Gerhardt & Son Inc",
    "wof:placetype":"venue"
},
  "geometry": {"coordinates":[-75.449307,40.520848],"type":"Point"}
}