{
  "type": "Feature",
  "properties": {
    "iso:country":"US",
    "sg:address":"47 E High St",
    "sg:city":"New Freedom",
    "sg:classifiers":[
        {
            "category":"Government",
            "subcategory":"Police Station",
            "type":"Public Place"
        }
    ],
    "sg:phone":"+1 717 235 3944",
    "sg:postcode":"17349",
    "sg:province":"PA",
    "sg:tags":[
        "department",
        "protection"
    ],
    "wof:name":"Southern Freedom Police Dept",
    "wof:placetype":"venue"
},
  "geometry": {"coordinates":[-76.702191,39.735186],"type":"Point"}
}