{
  "type": "Feature",
  "properties": {
    "iso:country":"US",
    "sg:address":"1742 S Atherton St",
    "sg:city":"State College",
    "sg:classifiers":[
        {
            "category":"Shopping",
            "subcategory":"Gifts & Souvenirs",
            "type":"Retail Goods"
        }
    ],
    "sg:phone":"+1 814 272 7883",
    "sg:postcode":"16801",
    "sg:province":"PA",
    "sg:tags":[
        "shop"
    ],
    "sg:website":"www.stuffingtown.com",
    "wof:name":"Stuffing Town LLC",
    "wof:placetype":"venue"
},
  "geometry": {"coordinates":[-77.83389099999999,40.785059],"type":"Point"}
}