{
  "type": "Feature",
  "properties": {
    "addr:full":"28 Bridge Ave Berwyn PA 19312",
    "addr:housenumber":"28",
    "addr:postcode":"19312",
    "addr:street":"Bridge Ave",
    "iso:country":"US",
    "sg:address":"28 Bridge Ave",
    "sg:city":"Berwyn",
    "sg:classifiers":[
        {
            "category":"Social Services",
            "type":"Services"
        }
    ],
    "sg:phone":"+1 610 647 9840",
    "sg:postcode":"19312",
    "sg:province":"PA",
    "sg:website":"http://surreyservices.org",
    "wof:name":"Surrey Services for Seniors",
    "wof:placetype":"venue"
},
  "geometry": {"coordinates":[-75.44440299999999,40.045353],"type":"Point"}
}