{
  "type": "Feature",
  "properties": {
    "iso:country":"US",
    "sg:address":"122 Stoney Battery Rd",
    "sg:city":"Landisville",
    "sg:classifiers":[
        {
            "category":"Autos & Motor Vehicles",
            "subcategory":"Automobile Sales",
            "type":"Retail Goods"
        }
    ],
    "sg:phone":"+1   ",
    "sg:postcode":"17538",
    "sg:province":"PA",
    "sg:tags":[
        "used"
    ],
    "wof:name":"Haldemans Auto Body",
    "wof:placetype":"venue"
},
  "geometry": {"coordinates":[-76.42584100000001,40.098767],"type":"Point"}
}