{
  "type": "Feature",
  "properties": {
    "iso:country":"US",
    "sg:address":"520 W Walnut St",
    "sg:city":"Perkasie",
    "sg:classifiers":[
        {
            "category":"Manufacturing",
            "subcategory":"Signs",
            "type":"Manufacturing & Wholesale Goods"
        }
    ],
    "sg:phone":"+1 215 453 1917",
    "sg:postcode":"18944",
    "sg:province":"PA",
    "wof:name":"Impact Signs",
    "wof:placetype":"venue"
},
  "geometry": {"coordinates":[-75.29723,40.372699],"type":"Point"}
}