{
  "type": "Feature",
  "properties": {
    "iso:country":"US",
    "sg:address":"2121 Abington Rd",
    "sg:city":"Bethlehem",
    "sg:classifiers":[
        {
            "category":"Education",
            "subcategory":"School",
            "type":"Public Place"
        }
    ],
    "sg:phone":"+1 610 868 5994",
    "sg:postcode":"18018",
    "sg:province":"PA",
    "wof:name":"Bethlehem Area School District Clearview",
    "wof:placetype":"venue"
},
  "geometry": {"coordinates":[-75.4188,40.637901],"type":"Point"}
}