{
  "type": "Feature",
  "properties": {
    "iso:country":"US",
    "sg:address":"2334 Brown St",
    "sg:city":"Philadelphia",
    "sg:classifiers":[
        {
            "category":"Personal",
            "subcategory":"Psychics & Astrologers",
            "type":"Services"
        }
    ],
    "sg:phone":"+1 267 506 1131",
    "sg:postcode":"19130",
    "sg:province":"PA",
    "sg:website":"readingsbynicole.webs.com",
    "wof:name":"Psychic Readings By Nicole",
    "wof:placetype":"venue"
},
  "geometry": {"coordinates":[-75.176053,39.969843],"type":"Point"}
}