{
  "type": "Feature",
  "properties": {
    "iso:country":"US",
    "sg:address":"38 Dixon Blvd",
    "sg:city":"Uniontown",
    "sg:classifiers":[
        {
            "category":"Building & Trades",
            "subcategory":"Construction",
            "type":"Services"
        }
    ],
    "sg:phone":"+1 724 439 1333",
    "sg:postcode":"15401",
    "sg:province":"PA",
    "sg:tags":[
        "home",
        "builder"
    ],
    "wof:name":"Foxchase Custom Homes",
    "wof:placetype":"venue"
},
  "geometry": {"coordinates":[-79.742287,39.894394],"type":"Point"}
}