{
  "type": "Feature",
  "properties": {
    "iso:country":"US",
    "sg:address":"3805 W 12th St",
    "sg:city":"Erie",
    "sg:classifiers":[
        {
            "category":"Building & Trades",
            "subcategory":"Plumbing",
            "type":"Services"
        }
    ],
    "sg:phone":"+1 814 835 9078",
    "sg:postcode":"16505",
    "sg:province":"PA",
    "sg:tags":[
        "plumbing",
        "contractor"
    ],
    "wof:name":"Pinnacle Plumbing",
    "wof:placetype":"venue"
},
  "geometry": {"coordinates":[-80.168729,42.091157],"type":"Point"}
}