{
  "type": "Feature",
  "properties": {
    "iso:country":"US",
    "sg:address":"625 S Chester Rd",
    "sg:city":"Swarthmore",
    "sg:classifiers":[
        {
            "category":"Local Transit",
            "type":"Transportation"
        },
        {
            "category":"Professional",
            "subcategory":"Accounting & Tax Preparation",
            "type":"Services"
        }
    ],
    "sg:phone":"+1 610 541 6610",
    "sg:postcode":"19081",
    "sg:province":"PA",
    "sg:tags":[
        "department",
        "billing",
        "ambulance"
    ],
    "wof:name":"Keystone Quality Transport Co",
    "wof:placetype":"venue"
},
  "geometry": {"coordinates":[-75.35356,39.890611],"type":"Point"}
}