{
  "type": "Feature",
  "properties": {
    "addr:full":"623 E Hamilton St Allentown PA 18109",
    "addr:housenumber":"623",
    "addr:postcode":"18109",
    "addr:street":"E Hamilton St",
    "iso:country":"US",
    "sg:address":"623 E Hamilton St",
    "sg:city":"Allentown",
    "sg:classifiers":[
        {
            "category":"Building & Trades",
            "subcategory":"Electrical",
            "type":"Services"
        }
    ],
    "sg:phone":"+1 610 434 9399",
    "sg:postcode":"18109",
    "sg:province":"PA",
    "sg:tags":[
        "electrician",
        "electric",
        "contractor"
    ],
    "wof:name":"East Side Electric",
    "wof:placetype":"venue"
},
  "geometry": {"coordinates":[-75.44470200000001,40.611],"type":"Point"}
}