{
  "type": "Feature",
  "properties": {
    "iso:country":"US",
    "sg:address":"2204 Murray Ave",
    "sg:city":"Pittsburgh",
    "sg:classifiers":[
        {
            "category":"Health Services",
            "subcategory":"Doctor",
            "type":"Services"
        }
    ],
    "sg:phone":"+1 412 421 9100",
    "sg:postcode":"15217",
    "sg:province":"PA",
    "sg:tags":[
        "physician",
        "surgeon",
        "medical"
    ],
    "wof:name":"Sheldon Widlan MD PC",
    "wof:placetype":"venue"
},
  "geometry": {"coordinates":[-79.92329599999999,40.431788],"type":"Point"}
}