{
  "type": "Feature",
  "properties": {
    "iso:country":"US",
    "sg:address":"45 N Market St",
    "sg:city":"Lancaster",
    "sg:classifiers":[
        {
            "category":"Professional",
            "subcategory":"Management & Consulting",
            "type":"Services"
        }
    ],
    "sg:phone":"+1   ",
    "sg:postcode":"17603",
    "sg:province":"PA",
    "wof:name":"Schoolhouse Catering",
    "wof:placetype":"venue"
},
  "geometry": {"coordinates":[-76.306641,40.037889],"type":"Point"}
}