{
  "type": "Feature",
  "properties": {
    "addr:full":"2469 Napfle St Fl 1 Philadelphia PA 19152",
    "addr:housenumber":"2469;1",
    "addr:postcode":"19152",
    "addr:street":"Napfle St",
    "iso:country":"US",
    "sg:address":"2469 Napfle St Fl 1",
    "sg:city":"Philadelphia",
    "sg:classifiers":[
        {
            "category":"Health Services",
            "subcategory":"Hospital",
            "type":"Services"
        }
    ],
    "sg:phone":"+1 215 624 0466",
    "sg:postcode":"19152",
    "sg:province":"PA",
    "sg:tags":[
        "ambulance"
    ],
    "wof:name":"A&V Global Services Inc",
    "wof:placetype":"venue"
},
  "geometry": {"coordinates":[-75.052044,40.052267],"type":"Point"}
}