{
  "type": "Feature",
  "properties": {
    "iso:country":"US",
    "sg:address":"468 Union St",
    "sg:city":"Luzerne",
    "sg:classifiers":[
        {
            "category":"Food & Beverages",
            "subcategory":"Liquor & Beverages",
            "type":"Retail Goods"
        }
    ],
    "sg:phone":"+1 570 331 6702",
    "sg:postcode":"18709",
    "sg:province":"PA",
    "sg:tags":[
        "consultant",
        "regulation",
        "commercial",
        "sect",
        "alcoholic"
    ],
    "wof:name":"Wine & Spirits Shoppe 4006",
    "wof:placetype":"venue"
},
  "geometry": {"coordinates":[-75.895685,41.281852],"type":"Point"}
}