{
  "type": "Feature",
  "properties": {
    "iso:country":"US",
    "sg:address":"225 S 45th St",
    "sg:city":"Philadelphia",
    "sg:classifiers":[
        {
            "category":"Professional",
            "type":"Services"
        }
    ],
    "sg:phone":"+1 215 222 0239",
    "sg:postcode":"19104",
    "sg:province":"PA",
    "sg:tags":[
        "establishment"
    ],
    "wof:name":"Island International Sprmrkt",
    "wof:placetype":"venue"
},
  "geometry": {"coordinates":[-75.211685,39.955065],"type":"Point"}
}