{
  "type": "Feature",
  "properties": {
    "iso:country":"US",
    "sg:address":"5195 Admire Rd",
    "sg:city":"Thomasville",
    "sg:classifiers":[
        {
            "category":"Farming",
            "subcategory":"Farm",
            "type":"Manufacturing & Wholesale Goods"
        }
    ],
    "sg:phone":"+1   ",
    "sg:postcode":"17364",
    "sg:province":"PA",
    "sg:tags":[
        "crop",
        "general"
    ],
    "wof:name":"Glenn Reynolds",
    "wof:placetype":"venue"
},
  "geometry": {"coordinates":[-76.91568599999999,39.951486],"type":"Point"}
}