{
  "type": "Feature",
  "properties": {
    "addr:full":"522 N Jennersville Rd Cochranville PA 19330",
    "addr:housenumber":"522",
    "addr:postcode":"19330",
    "addr:street":"N Jennersville Rd",
    "iso:country":"US",
    "sg:address":"522 N Jennersville Rd",
    "sg:city":"Cochranville",
    "sg:classifiers":[
        {
            "category":"Farming",
            "subcategory":"Nursery",
            "type":"Manufacturing & Wholesale Goods"
        }
    ],
    "sg:phone":"+1 610 869 7300",
    "sg:postcode":"19330",
    "sg:province":"PA",
    "sg:tags":[
        "ornamental",
        "greenhouse"
    ],
    "wof:name":"Londonderry Greenhouses LLC",
    "wof:placetype":"venue"
},
  "geometry": {"coordinates":[-75.877996,39.860388],"type":"Point"}
}