{
  "type": "Feature",
  "properties": {
    "iso:country":"US",
    "sg:address":"327 Steelstown Rd",
    "sg:city":"Newville",
    "sg:classifiers":[
        {
            "category":"Personal",
            "subcategory":"Beauty Salon",
            "type":"Services"
        }
    ],
    "sg:phone":"+1 717 776 3839",
    "sg:postcode":"17241",
    "sg:province":"PA",
    "wof:name":"Bonnie Leachs Styling Salon",
    "wof:placetype":"venue"
},
  "geometry": {"coordinates":[-77.427891,40.173918],"type":"Point"}
}