{
  "type": "Feature",
  "properties": {
    "addr:full":"2 N Main St Greensburg PA 15601",
    "addr:housenumber":"2",
    "addr:postcode":"15601",
    "addr:street":"N Main St",
    "iso:country":"US",
    "sg:address":"2 N Main St",
    "sg:city":"Greensburg",
    "sg:classifiers":[
        {
            "category":"Government",
            "subcategory":"Court House",
            "type":"Public Place"
        }
    ],
    "sg:phone":"+1 724 830 3757",
    "sg:postcode":"15601",
    "sg:province":"PA",
    "sg:tags":[
        "county"
    ],
    "sg:website":"www.co.westmoreland.pa.us",
    "wof:name":"Court Administrator's Office",
    "wof:placetype":"venue"
},
  "geometry": {"coordinates":[-79.544617,40.303494],"type":"Point"}
}