{
  "type": "Feature",
  "properties": {
    "iso:country":"US",
    "sg:address":"837 Sharon New Castle Rd",
    "sg:city":"Farrell",
    "sg:classifiers":[
        {
            "category":"Food & Beverages",
            "subcategory":"Liquor & Beverages",
            "type":"Retail Goods"
        }
    ],
    "sg:phone":"+1 724 983 5201",
    "sg:postcode":"16121",
    "sg:province":"PA",
    "wof:name":"Pennsylvania Liquor Store",
    "wof:placetype":"venue"
},
  "geometry": {"coordinates":[-80.48313899999999,41.214172],"type":"Point"}
}