{
  "type": "Feature",
  "properties": {
    "iso:country":"US",
    "sg:address":"602 Bellefonte Ave",
    "sg:city":"Lock Haven",
    "sg:classifiers":[
        {
            "category":"Travel",
            "subcategory":"Hotels & Motels",
            "type":"Entertainment"
        }
    ],
    "sg:phone":"+1   ",
    "sg:postcode":"17745",
    "sg:province":"PA",
    "sg:tags":[
        "membership",
        "lodging"
    ],
    "wof:name":"Kappa Delta RHO",
    "wof:placetype":"venue"
},
  "geometry": {"coordinates":[-77.454655,41.134122],"type":"Point"}
}