{
  "type": "Feature",
  "properties": {
    "iso:country":"US",
    "sg:address":"42 E Maiden St",
    "sg:city":"Washington",
    "sg:classifiers":[
        {
            "category":"Government",
            "subcategory":"Fire Station",
            "type":"Public Place"
        },
        {
            "category":"Building & Trades",
            "subcategory":"Cleaning & Sanitation",
            "type":"Services"
        }
    ],
    "sg:phone":"+1 724 222 9007",
    "sg:postcode":"15301",
    "sg:province":"PA",
    "sg:tags":[
        "recovery",
        "damage",
        "water",
        "restoration",
        "relief",
        "disaster"
    ],
    "wof:name":"Tri State Restoration Service Inc",
    "wof:placetype":"venue"
},
  "geometry": {"coordinates":[-80.243622,40.16798],"type":"Point"}
}