{
  "type": "Feature",
  "properties": {
    "addr:full":"1250 Washington Rd Washington PA 15301",
    "addr:housenumber":"1250",
    "addr:postcode":"15301",
    "addr:street":"Washington Rd",
    "iso:country":"US",
    "sg:address":"1250 Washington Rd",
    "sg:city":"Washington",
    "sg:classifiers":[
        {
            "category":"Manufacturing",
            "subcategory":"Printing",
            "type":"Manufacturing & Wholesale Goods"
        }
    ],
    "sg:phone":"+1 724 222 8304",
    "sg:postcode":"15301",
    "sg:province":"PA",
    "sg:tags":[
        "commercial"
    ],
    "wof:name":"Creative Printing",
    "wof:placetype":"venue"
},
  "geometry": {"coordinates":[-80.194526,40.213886],"type":"Point"}
}