{
  "type": "Feature",
  "properties": {
    "iso:country":"US",
    "sg:address":"288 Dahl Rd",
    "sg:city":"Bloomsburg",
    "sg:classifiers":[
        {
            "category":"Social Services",
            "subcategory":"Job Training",
            "type":"Services"
        }
    ],
    "sg:phone":"+1 570 784 5445",
    "sg:postcode":"17815",
    "sg:province":"PA",
    "sg:tags":[
        "rehabilitation"
    ],
    "wof:name":"Eos Therapuetic Riding Ctr",
    "wof:placetype":"venue"
},
  "geometry": {"coordinates":[-76.554018,41.028398],"type":"Point"}
}