{
  "type": "Feature",
  "properties": {
    "iso:country":"US",
    "sg:address":"701 Prospect Rd",
    "sg:city":"Columbia",
    "sg:classifiers":[
        {
            "category":"Building & Trades",
            "subcategory":"Electrical",
            "type":"Services"
        }
    ],
    "sg:phone":"+1 717 674 4723",
    "sg:postcode":"17512",
    "sg:province":"PA",
    "sg:tags":[
        "industrial",
        "electrician",
        "contractors-commercial",
        "electric"
    ],
    "sg:website":"http://www.wilcoelectric.com",
    "wof:name":"Wilco Electric Inc",
    "wof:placetype":"venue"
},
  "geometry": {"coordinates":[-76.46302,40.059059],"type":"Point"}
}