{
  "type": "Feature",
  "properties": {
    "iso:country":"US",
    "sg:address":"302 N Chester Rd",
    "sg:city":"West Chester",
    "sg:classifiers":[
        {
            "category":"Professional",
            "type":"Services"
        }
    ],
    "sg:phone":"+1   ",
    "sg:postcode":"19380",
    "sg:province":"PA",
    "wof:name":"Chester County Aids Consortium",
    "wof:placetype":"venue"
},
  "geometry": {"coordinates":[-75.533935,39.973907],"type":"Point"}
}