{
  "type": "Feature",
  "properties": {
    "iso:country":"US",
    "sg:address":"102 Jamestown St",
    "sg:city":"Philadelphia",
    "sg:classifiers":[
        {
            "category":"Building & Trades",
            "subcategory":"Construction",
            "type":"Services"
        }
    ],
    "sg:phone":"+1   ",
    "sg:postcode":"19127",
    "sg:province":"PA",
    "sg:tags":[
        "carpentry",
        "contractor"
    ],
    "wof:name":"Jeffrey K Maier",
    "wof:placetype":"venue"
},
  "geometry": {"coordinates":[-75.21919,40.023123],"type":"Point"}
}