{
  "type": "Feature",
  "properties": {
    "iso:country":"US",
    "sg:address":"1264 Maple Valley Rd",
    "sg:city":"Meyersdale",
    "sg:classifiers":[
        {
            "category":"Building & Trades",
            "subcategory":"Equipment Rental",
            "type":"Services"
        }
    ],
    "sg:phone":"+1 814 634 5242",
    "sg:postcode":"15552",
    "sg:province":"PA",
    "sg:tags":[
        "contractors'"
    ],
    "wof:name":"Penn Woods Rental",
    "wof:placetype":"venue"
},
  "geometry": {"coordinates":[-78.98782199999999,39.843201],"type":"Point"}
}