{
  "type": "Feature",
  "properties": {
    "iso:country":"US",
    "sg:address":"209 S 20th St",
    "sg:city":"Philadelphia",
    "sg:classifiers":[
        {
            "category":"Restaurant",
            "type":"Food & Drink"
        }
    ],
    "sg:phone":"+1 215 545 2388",
    "sg:postcode":"19103",
    "sg:province":"PA",
    "sg:tags":[
        "seafood",
        "sushi",
        "bar"
    ],
    "wof:name":"Yamaki Sushi Bar",
    "wof:placetype":"venue"
},
  "geometry": {"coordinates":[-75.173861,39.950239],"type":"Point"}
}