{
  "type": "Feature",
  "properties": {
    "addr:full":"15 Franklin Mills Blvd Philadelphia PA 19154",
    "addr:housenumber":"15",
    "addr:postcode":"19154",
    "addr:street":"Franklin Mills Blvd",
    "iso:country":"US",
    "sg:address":"15 Franklin Mills Blvd",
    "sg:city":"Philadelphia",
    "sg:classifiers":[
        {
            "category":"Personal",
            "subcategory":"Nail Salon",
            "type":"Services"
        }
    ],
    "sg:phone":"+1 215 612 8334",
    "sg:postcode":"19154",
    "sg:province":"PA",
    "wof:name":"Liberty Nail",
    "wof:placetype":"venue"
},
  "geometry": {"coordinates":[-74.966003,40.083],"type":"Point"}
}