{
  "type": "Feature",
  "properties": {
    "iso:country":"US",
    "sg:address":"1060 Howertown Rd",
    "sg:city":"Catasauqua",
    "sg:classifiers":[
        {
            "category":"Wholesale",
            "subcategory":"Hardware",
            "type":"Manufacturing & Wholesale Goods"
        }
    ],
    "sg:phone":"+1   ",
    "sg:postcode":"18032",
    "sg:province":"PA",
    "sg:tags":[
        "control",
        "industrial",
        "pollution"
    ],
    "wof:name":"Air and Noise Products Inc",
    "wof:placetype":"venue"
},
  "geometry": {"coordinates":[-75.471907,40.661564],"type":"Point"}
}