{
  "type": "Feature",
  "properties": {
    "addr:full":"200 Humane Ave Pottsville PA 17901",
    "addr:postcode":"17901",
    "addr:street":"Humane Ave",
    "iso:country":"US",
    "sg:address":"200 Humane Ave",
    "sg:city":"Pottsville",
    "sg:classifiers":[
        {
            "category":"Organizations",
            "subcategory":"Membership Organization",
            "type":"Services"
        }
    ],
    "sg:phone":"+1   ",
    "sg:postcode":"17901",
    "sg:province":"PA",
    "wof:name":"Fire Department",
    "wof:placetype":"venue"
},
  "geometry": {"coordinates":[-76.197863,40.686374],"type":"Point"}
}