{
  "type": "Feature",
  "properties": {
    "addr:full":"117 W Ridge St Centre Hall PA 16828",
    "addr:housenumber":"117",
    "addr:postcode":"16828",
    "addr:street":"W Ridge St",
    "iso:country":"US",
    "sg:address":"117 W Ridge St",
    "sg:city":"Centre Hall",
    "sg:classifiers":[
        {
            "category":"Real Estate",
            "subcategory":"Real Estate Agent",
            "type":"Services"
        }
    ],
    "sg:phone":"+1 814 364 2549",
    "sg:postcode":"16828",
    "sg:province":"PA",
    "sg:tags":[
        "inspection"
    ],
    "wof:name":"All Systems Inspections LLC",
    "wof:placetype":"venue"
},
  "geometry": {"coordinates":[-77.685363,40.843318],"type":"Point"}
}