{
  "type": "Feature",
  "properties": {
    "addr:full":"109 N Findley St Punxsutawney PA 15767",
    "addr:housenumber":"109",
    "addr:postcode":"15767",
    "addr:street":"N Findley St",
    "iso:country":"US",
    "sg:address":"109 N Findley St",
    "sg:city":"Punxsutawney",
    "sg:classifiers":[
        {
            "category":"Banks & Credit Unions",
            "subcategory":"Bank",
            "type":"Services"
        },
        {
            "category":"Shopping",
            "subcategory":"Used Merchandise",
            "type":"Retail Goods"
        }
    ],
    "sg:phone":"+1 814 938 4849",
    "sg:postcode":"15767",
    "sg:province":"PA",
    "sg:tags":[
        "shop",
        "second",
        "resale",
        "hand"
    ],
    "wof:name":"Wanda S New Used Items",
    "wof:placetype":"venue"
},
  "geometry": {"coordinates":[-78.97138200000001,40.944038],"type":"Point"}
}