{
  "type": "Feature",
  "properties": {
    "iso:country":"US",
    "sg:address":"3535 Market St",
    "sg:city":"Philadelphia",
    "sg:classifiers":[
        {
            "category":"Professional",
            "subcategory":"Management & Consulting",
            "type":"Services"
        }
    ],
    "sg:phone":"+1 215 386 7252",
    "sg:postcode":"19104",
    "sg:province":"PA",
    "sg:tags":[
        "break",
        "tea",
        "coffee",
        "supply"
    ],
    "wof:name":"Cafe Soleil",
    "wof:placetype":"venue"
},
  "geometry": {"coordinates":[-75.193298,39.9561],"type":"Point"}
}