{
  "type": "Feature",
  "properties": {
    "iso:country":"US",
    "sg:address":"6020 Overbrook Ave",
    "sg:city":"Philadelphia",
    "sg:classifiers":[
        {
            "category":"Education",
            "subcategory":"School",
            "type":"Public Place"
        }
    ],
    "sg:phone":"+1 215 473 0384",
    "sg:postcode":"19131",
    "sg:province":"PA",
    "wof:name":"Torah Academy Of Greater Phila",
    "wof:placetype":"venue"
},
  "geometry": {"coordinates":[-75.247839,39.990697],"type":"Point"}
}