{
  "type": "Feature",
  "properties": {
    "iso:country":"US",
    "sg:address":"4715 N 5th St",
    "sg:city":"Philadelphia",
    "sg:classifiers":[
        {
            "category":"Real Estate",
            "subcategory":"Real Estate Agent",
            "type":"Services"
        }
    ],
    "sg:phone":"+1 215 455 8510",
    "sg:postcode":"19120",
    "sg:province":"PA",
    "sg:tags":[
        "management",
        "property"
    ],
    "wof:name":"Bricks Management Inc",
    "wof:placetype":"venue"
},
  "geometry": {"coordinates":[-75.13359800000001,40.023102],"type":"Point"}
}