{
  "type": "Feature",
  "properties": {
    "iso:country":"US",
    "sg:address":"209 Brinton Ave ",
    "sg:city":"Trafford",
    "sg:classifiers":[
        {
            "category":"Restaurant",
            "type":"Food & Drink"
        }
    ],
    "sg:menulink":"http://www.allmenus.com/pa/trafford/287668-keith-heinritz-katering/menu/",
    "sg:phone":"+1 412 373 6788",
    "sg:postcode":"15085",
    "sg:province":"PA",
    "sg:tags":[
        "american",
        "sandwich",
        "seafood",
        "hoagy"
    ],
    "wof:name":"Keith Heinritz Katering",
    "wof:placetype":"venue"
},
  "geometry": {"coordinates":[-79.762456,40.382658],"type":"Point"}
}