{
  "type": "Feature",
  "properties": {
    "addr:full":"1500 Hayden Blvd Elizabeth PA 15037",
    "addr:housenumber":"1500",
    "addr:postcode":"15037",
    "addr:street":"Hayden Blvd",
    "iso:country":"US",
    "sg:address":"1500 Hayden Blvd",
    "sg:city":"Elizabeth",
    "sg:classifiers":[
        {
            "category":"Wholesale",
            "subcategory":"Scrap",
            "type":"Manufacturing & Wholesale Goods"
        }
    ],
    "sg:phone":"+1 412 384 7569",
    "sg:postcode":"15037",
    "sg:province":"PA",
    "sg:tags":[
        "waste"
    ],
    "wof:name":"Kelly Run Sanitation Inc",
    "wof:placetype":"venue"
},
  "geometry": {"coordinates":[-79.878353,40.253],"type":"Point"}
}