{
  "type": "Feature",
  "properties": {
    "iso:country":"US",
    "sg:address":"34 N Main St",
    "sg:city":"Shenandoah",
    "sg:classifiers":[
        {
            "category":"Food & Beverages",
            "subcategory":"Bakery",
            "type":"Retail Goods"
        }
    ],
    "sg:phone":"+1 570 462 3577",
    "sg:postcode":"17976",
    "sg:province":"PA",
    "sg:tags":[
        "doughnut"
    ],
    "wof:name":"King Kruller Donut Shoppe",
    "wof:placetype":"venue"
},
  "geometry": {"coordinates":[-76.201452,40.821141],"type":"Point"}
}