{
  "type": "Feature",
  "properties": {
    "addr:full":"233 W Parkside Dr New Castle PA 16105",
    "addr:housenumber":"233",
    "addr:postcode":"16105",
    "addr:street":"W Parkside Dr",
    "iso:country":"US",
    "sg:address":"233 W Parkside Dr",
    "sg:city":"New Castle",
    "sg:classifiers":[
        {
            "category":"Real Estate",
            "subcategory":"Real Estate Agent",
            "type":"Services"
        }
    ],
    "sg:phone":"+1   ",
    "sg:postcode":"16105",
    "sg:province":"PA",
    "wof:name":"Golba Realty Group Inc",
    "wof:placetype":"venue"
},
  "geometry": {"coordinates":[-80.351409,41.060381],"type":"Point"}
}