{
  "type": "Feature",
  "properties": {
    "iso:country":"US",
    "sg:address":"3816 Morrell Ave",
    "sg:city":"Philadelphia",
    "sg:classifiers":[
        {
            "category":"Professional",
            "subcategory":"Business Services",
            "type":"Services"
        }
    ],
    "sg:phone":"+1 215 637 8098",
    "sg:postcode":"19114",
    "sg:province":"PA",
    "sg:tags":[
        "license"
    ],
    "wof:name":"Morrell Park Auto Tags",
    "wof:placetype":"venue"
},
  "geometry": {"coordinates":[-74.985851,40.063647],"type":"Point"}
}