{
  "type": "Feature",
  "properties": {
    "iso:country":"US",
    "sg:address":"929 Rose St",
    "sg:city":"Baden",
    "sg:classifiers":[
        {
            "category":"Professional",
            "subcategory":"Art Services",
            "type":"Services"
        }
    ],
    "sg:phone":"+1 724 622 7021",
    "sg:postcode":"15005",
    "sg:province":"PA",
    "sg:tags":[
        "designer",
        "display",
        "producer"
    ],
    "wof:name":"Premier Designs",
    "wof:placetype":"venue"
},
  "geometry": {"coordinates":[-80.227017,40.648001],"type":"Point"}
}