{
  "type": "Feature",
  "properties": {
    "iso:country":"US",
    "sg:address":"157 N Westview Dr",
    "sg:city":"Gordonville",
    "sg:classifiers":[
        {
            "category":"Building & Trades",
            "subcategory":"Construction",
            "type":"Services"
        }
    ],
    "sg:phone":"+1   ",
    "sg:postcode":"17529",
    "sg:province":"PA",
    "sg:tags":[
        "gen"
    ],
    "wof:name":"Sunny Slope Construction LLC",
    "wof:placetype":"venue"
},
  "geometry": {"coordinates":[-76.093076,40.05059],"type":"Point"}
}