{
  "type": "Feature",
  "properties": {
    "addr:full":"2101 Longshore Ave Philadelphia PA 19149",
    "addr:housenumber":"2101",
    "addr:postcode":"19149",
    "addr:street":"Longshore Ave",
    "iso:country":"US",
    "sg:address":"2101 Longshore Ave",
    "sg:city":"Philadelphia",
    "sg:classifiers":[
        {
            "category":"Personal",
            "subcategory":"Beauty Salon",
            "type":"Services"
        }
    ],
    "sg:phone":"+1 215 338 2727",
    "sg:postcode":"19149",
    "sg:province":"PA",
    "wof:name":"Hairstyling By Patricia",
    "wof:placetype":"venue"
},
  "geometry": {"coordinates":[-75.06225499999999,40.040524],"type":"Point"}
}