{
  "type": "Feature",
  "properties": {
    "iso:country":"US",
    "sg:address":"68 Clearview Rd",
    "sg:city":"Ronks",
    "sg:classifiers":[
        {
            "category":"Retail",
            "subcategory":"Animal Services",
            "type":"Services"
        }
    ],
    "sg:phone":"+1 717 768 0045",
    "sg:postcode":"17572",
    "sg:province":"PA",
    "sg:tags":[
        "pet",
        "boarding",
        "sitting"
    ],
    "wof:name":"Clearview Kennels",
    "wof:placetype":"venue"
},
  "geometry": {"coordinates":[-76.117305,40.033142],"type":"Point"}
}