{
  "type": "Feature",
  "properties": {
    "addr:full":"413 Howell Rd Exton PA 19341",
    "addr:housenumber":"413",
    "addr:postcode":"19341",
    "addr:street":"Howell Rd",
    "iso:country":"US",
    "sg:address":"413 Howell Rd",
    "sg:city":"Exton",
    "sg:classifiers":[
        {
            "category":"Social Services",
            "subcategory":"Child Care",
            "type":"Services"
        }
    ],
    "sg:phone":"+1 610 363 9546",
    "sg:postcode":"19341",
    "sg:province":"PA",
    "sg:tags":[
        "nursery",
        "day"
    ],
    "wof:name":"Ferdinand N Latch Inc",
    "wof:placetype":"venue"
},
  "geometry": {"coordinates":[-75.650305,40.039558],"type":"Point"}
}