{
  "type": "Feature",
  "properties": {
    "addr:full":"838 Montgomery Ave Narberth PA 19072",
    "addr:housenumber":"838",
    "addr:postcode":"19072",
    "addr:street":"Montgomery Ave",
    "iso:country":"US",
    "sg:address":"838 Montgomery Ave",
    "sg:city":"Narberth",
    "sg:classifiers":[
        {
            "category":"Restaurant",
            "type":"Food & Drink"
        }
    ],
    "sg:phone":"+1 610 667 0500",
    "sg:postcode":"19072",
    "sg:province":"PA",
    "sg:tags":[
        "pizza"
    ],
    "wof:name":"Sun Valley Pizza",
    "wof:placetype":"venue"
},
  "geometry": {"coordinates":[-75.25859800000001,40.011002],"type":"Point"}
}