{
  "type": "Feature",
  "properties": {
    "addr:full":"6235 Passyunk Ave Philadelphia PA 19153",
    "addr:postcode":"6235;19153",
    "addr:street":"Passyunk Ave",
    "iso:country":"US",
    "sg:address":"6235 Passyunk Ave",
    "sg:city":"Philadelphia",
    "sg:classifiers":[
        {
            "category":"Autos & Motor Vehicles",
            "subcategory":"Auto Supplies",
            "type":"Retail Goods"
        }
    ],
    "sg:phone":"+1 215 729 4573",
    "sg:postcode":"19153",
    "sg:province":"PA",
    "sg:tags":[
        "automobile",
        "parts"
    ],
    "wof:name":"Auto Parts Drive Line",
    "wof:placetype":"venue"
},
  "geometry": {"coordinates":[-75.212144,39.917937],"type":"Point"}
}