{
  "type": "Feature",
  "properties": {
    "iso:country":"US",
    "sg:address":"16 Copperleaf Dr",
    "sg:city":"Newtown",
    "sg:classifiers":[
        {
            "category":"Manufacturing",
            "subcategory":"Tools & Machinery",
            "type":"Manufacturing & Wholesale Goods"
        }
    ],
    "sg:phone":"+1   ",
    "sg:postcode":"18940",
    "sg:province":"PA",
    "sg:tags":[
        "instrument",
        "mfg"
    ],
    "wof:name":"Power Scan Inc",
    "wof:placetype":"venue"
},
  "geometry": {"coordinates":[-74.91132,40.24048],"type":"Point"}
}