{
  "type": "Feature",
  "properties": {
    "addr:full":"101 Park City Center Lancaster PA 17601",
    "addr:housenumber":"101",
    "addr:postcode":"17601",
    "addr:street":"Park",
    "iso:country":"US",
    "sg:address":"101 Park City Center",
    "sg:city":"Lancaster",
    "sg:classifiers":[
        {
            "category":"Retail",
            "subcategory":"Repair Shop",
            "type":"Services"
        }
    ],
    "sg:phone":"+1 717 299 2275",
    "sg:postcode":"17601",
    "sg:province":"PA",
    "sg:tags":[
        "watch"
    ],
    "wof:name":"Cooper's Watchworks",
    "wof:placetype":"venue"
},
  "geometry": {"coordinates":[-76.340878,40.064696],"type":"Point"}
}