{
  "type": "Feature",
  "properties": {
    "iso:country":"US",
    "sg:address":"433 Northampton St",
    "sg:city":"Easton",
    "sg:classifiers":[
        {
            "category":"Personal",
            "subcategory":"Barber",
            "type":"Services"
        }
    ],
    "sg:phone":"+1   ",
    "sg:postcode":"18042",
    "sg:province":"PA",
    "sg:tags":[
        "salon",
        "beauty"
    ],
    "wof:name":"Creations Boutique",
    "wof:placetype":"venue"
},
  "geometry": {"coordinates":[-75.212588,40.691153],"type":"Point"}
}