{
  "type": "Feature",
  "properties": {
    "iso:country":"US",
    "sg:address":"65 Hellers Church Rd",
    "sg:city":"Leola",
    "sg:classifiers":[
        {
            "category":"Building & Trades",
            "subcategory":"Construction",
            "type":"Services"
        }
    ],
    "sg:phone":"+1 717 656 8644",
    "sg:postcode":"17540",
    "sg:province":"PA",
    "sg:tags":[
        "painter"
    ],
    "wof:name":"Groff Painting",
    "wof:placetype":"venue"
},
  "geometry": {"coordinates":[-76.206248,40.078883],"type":"Point"}
}