{
  "type": "Feature",
  "properties": {
    "addr:full":"201 State St Erie PA 16501",
    "addr:housenumber":"201",
    "addr:postcode":"16501",
    "addr:street":"State St",
    "iso:country":"US",
    "sg:address":"201 State St",
    "sg:city":"Erie",
    "sg:classifiers":[
        {
            "category":"Health Services",
            "subcategory":"Hospital",
            "type":"Services"
        }
    ],
    "sg:phone":"+1 814 877 2774",
    "sg:postcode":"16501",
    "sg:province":"PA",
    "sg:website":"www.selectmedicalcorp.com",
    "wof:name":"Select Specialty Hospital",
    "wof:placetype":"venue"
},
  "geometry": {"coordinates":[-80.087176,42.132346],"type":"Point"}
}