{
  "type": "Feature",
  "properties": {
    "iso:country":"US",
    "sg:address":"610 Quail Ave",
    "sg:city":"Altoona",
    "sg:classifiers":[
        {
            "category":"Health Services",
            "subcategory":"Doctor",
            "type":"Services"
        }
    ],
    "sg:phone":"+1 814 944 2051",
    "sg:postcode":"16602",
    "sg:province":"PA",
    "sg:tags":[
        "dentist"
    ],
    "wof:name":"William B Zumovitch DMD",
    "wof:placetype":"venue"
},
  "geometry": {"coordinates":[-78.404747,40.475933],"type":"Point"}
}