{
  "type": "Feature",
  "properties": {
    "addr:full":"914 Elizabeth Ave Reading PA 19605",
    "addr:housenumber":"914",
    "addr:postcode":"19605",
    "addr:street":"Elizabeth Ave",
    "iso:country":"US",
    "sg:address":"914 Elizabeth Ave",
    "sg:city":"Reading",
    "sg:classifiers":[
        {
            "category":"Personal",
            "subcategory":"Beauty Salon",
            "type":"Services"
        }
    ],
    "sg:phone":"+1 610 939 0166",
    "sg:postcode":"19605",
    "sg:province":"PA",
    "wof:name":"Hair Designs By Mike",
    "wof:placetype":"venue"
},
  "geometry": {"coordinates":[-75.919628,40.38752],"type":"Point"}
}