{
  "type": "Feature",
  "properties": {
    "iso:country":"US",
    "sg:address":"5021 Haverford Ave",
    "sg:city":"Philadelphia",
    "sg:classifiers":[
        {
            "category":"Shopping",
            "type":"Retail Goods"
        }
    ],
    "sg:phone":"+1   ",
    "sg:postcode":"19139",
    "sg:province":"PA",
    "sg:tags":[
        "equipment",
        "cleaning",
        "supply"
    ],
    "wof:name":"Enviro-San",
    "wof:placetype":"venue"
},
  "geometry": {"coordinates":[-75.22030599999999,39.963911],"type":"Point"}
}