{
  "type": "Feature",
  "properties": {
    "iso:country":"US",
    "sg:address":"100 N 17th St",
    "sg:city":"Philadelphia",
    "sg:classifiers":[
        {
            "category":"Professional",
            "subcategory":"Business Services",
            "type":"Services"
        }
    ],
    "sg:phone":"+1 215 864 2500",
    "sg:postcode":"19103",
    "sg:province":"PA",
    "sg:tags":[
        "consultant",
        "coach"
    ],
    "wof:name":"Sugarman & Associates",
    "wof:placetype":"venue"
},
  "geometry": {"coordinates":[-75.168037,39.954979],"type":"Point"}
}