{
  "type": "Feature",
  "properties": {
    "iso:country":"US",
    "sg:address":"114 Harrison Ave",
    "sg:city":"Glenside",
    "sg:classifiers":[
        {
            "category":"Manufacturing",
            "subcategory":"Tools & Machinery",
            "type":"Manufacturing & Wholesale Goods"
        }
    ],
    "sg:phone":"+1   ",
    "sg:postcode":"19038",
    "sg:province":"PA",
    "sg:tags":[
        "industrial",
        "mfg"
    ],
    "wof:name":"Remington Tool Co",
    "wof:placetype":"venue"
},
  "geometry": {"coordinates":[-75.156628,40.099351],"type":"Point"}
}