{
  "type": "Feature",
  "properties": {
    "addr:full":"9122 Frankford Ave Philadelphia PA 19114",
    "addr:housenumber":"9122",
    "addr:postcode":"19114",
    "addr:street":"Frankford Ave",
    "iso:country":"US",
    "sg:address":"9122 Frankford Ave",
    "sg:city":"Philadelphia",
    "sg:classifiers":[
        {
            "category":"Health Services",
            "subcategory":"Doctor",
            "type":"Services"
        }
    ],
    "sg:phone":"+1 215 331 1400",
    "sg:postcode":"19114",
    "sg:province":"PA",
    "sg:tags":[
        "physician",
        "family",
        "practice",
        "surgeons",
        "medicine",
        "surgeon"
    ],
    "wof:name":"Frankford North Medical Ctr",
    "wof:placetype":"venue"
},
  "geometry": {"coordinates":[-75.007121,40.052981],"type":"Point"}
}