{
  "type": "Feature",
  "properties": {
    "addr:full":"536 E Main St Norristown PA 19401",
    "addr:housenumber":"536",
    "addr:postcode":"19401",
    "addr:street":"E Main St",
    "iso:country":"US",
    "sg:address":"536 E Main St",
    "sg:city":"Norristown",
    "sg:classifiers":[
        {
            "category":"Building & Trades",
            "subcategory":"Landscaping Services",
            "type":"Services"
        }
    ],
    "sg:phone":"+1   ",
    "sg:postcode":"19401",
    "sg:province":"PA",
    "wof:name":"Michael Dippolito",
    "wof:placetype":"venue"
},
  "geometry": {"coordinates":[-75.334822,40.111028],"type":"Point"}
}