{
  "type": "Feature",
  "properties": {
    "iso:country":"US",
    "sg:address":"2000 Market St Ste 1805",
    "sg:city":"Philadelphia",
    "sg:classifiers":[
        {
            "category":"Professional",
            "subcategory":"Lawyer & Legal Services",
            "type":"Services"
        }
    ],
    "sg:phone":"+1 215 972 7200",
    "sg:postcode":"19103",
    "sg:province":"PA",
    "sg:tags":[
        "plan"
    ],
    "wof:name":"Schafle & Cotter",
    "wof:placetype":"venue"
},
  "geometry": {"coordinates":[-75.17318,39.953571],"type":"Point"}
}