{
  "type": "Feature",
  "properties": {
    "addr:full":"16 S 6th St Allentown PA 18101",
    "addr:housenumber":"16",
    "addr:postcode":"18101",
    "addr:street":"S 6Th St",
    "iso:country":"US",
    "sg:address":"16 S 6th St",
    "sg:city":"Allentown",
    "sg:classifiers":[
        {
            "category":"Personal",
            "subcategory":"Beauty Salon",
            "type":"Services"
        }
    ],
    "sg:phone":"+1 610 435 0888",
    "sg:postcode":"18101",
    "sg:province":"PA",
    "wof:name":"Creative Styles",
    "wof:placetype":"venue"
},
  "geometry": {"coordinates":[-75.469598,40.602167],"type":"Point"}
}