{
  "type": "Feature",
  "properties": {
    "iso:country":"US",
    "sg:address":"2805 Egypt Rd",
    "sg:city":"Norristown",
    "sg:classifiers":[
        {
            "category":"Personal",
            "subcategory":"Beauty Salon",
            "type":"Services"
        }
    ],
    "sg:phone":"+1   ",
    "sg:postcode":"19403",
    "sg:province":"PA",
    "sg:tags":[
        "shop"
    ],
    "wof:name":"Nail Cottage",
    "wof:placetype":"venue"
},
  "geometry": {"coordinates":[-75.43521200000001,40.129588],"type":"Point"}
}