{
  "type": "Feature",
  "properties": {
    "iso:country":"US",
    "sg:address":"2000 N 6th St",
    "sg:city":"Harrisburg",
    "sg:classifiers":[
        {
            "category":"Shopping",
            "subcategory":"Beauty & Cosmetics",
            "type":"Retail Goods"
        }
    ],
    "sg:phone":"+1 717 233 2199",
    "sg:postcode":"17102",
    "sg:province":"PA",
    "sg:tags":[
        "supply"
    ],
    "wof:name":"A Bc Discount Store",
    "wof:placetype":"venue"
},
  "geometry": {"coordinates":[-76.889999,40.279598],"type":"Point"}
}