{
  "type": "Feature",
  "properties": {
    "addr:full":"530 Heath Rd Merion Station PA 19066",
    "addr:housenumber":"530",
    "addr:postcode":"19066",
    "addr:street":"Heath Rd Merion Station",
    "iso:country":"US",
    "sg:address":"530 Heath Rd",
    "sg:city":"Merion Station",
    "sg:classifiers":[
        {
            "category":"Recreation",
            "type":"Entertainment"
        }
    ],
    "sg:phone":"+1 610 664 0440",
    "sg:postcode":"19066",
    "sg:province":"PA",
    "wof:name":"Kramer Associates",
    "wof:placetype":"venue"
},
  "geometry": {"coordinates":[-75.254587,40.000127],"type":"Point"}
}