{
  "type": "Feature",
  "properties": {
    "iso:country":"US",
    "sg:address":"73 Old Dublin Pike",
    "sg:city":"Doylestown",
    "sg:classifiers":[
        {
            "category":"Shopping",
            "subcategory":"Gifts & Souvenirs",
            "type":"Retail Goods"
        }
    ],
    "sg:phone":"+1 215 862 4252",
    "sg:postcode":"18901",
    "sg:province":"PA",
    "sg:tags":[
        "shop"
    ],
    "wof:name":"Cellar",
    "wof:placetype":"venue"
},
  "geometry": {"coordinates":[-75.134586,40.324479],"type":"Point"}
}