{
  "type": "Feature",
  "properties": {
    "iso:country":"US",
    "sg:address":"581 Abbott Dr",
    "sg:city":"Broomall",
    "sg:classifiers":[
        {
            "category":"Real Estate",
            "subcategory":"Real Estate Agent",
            "type":"Services"
        }
    ],
    "sg:phone":"+1   ",
    "sg:postcode":"19008",
    "sg:province":"PA",
    "wof:name":"Lawrence Park Industrial Estat",
    "wof:placetype":"venue"
},
  "geometry": {"coordinates":[-75.33728600000001,39.960004],"type":"Point"}
}