{
  "type": "Feature",
  "properties": {
    "iso:country":"US",
    "sg:address":"2651 Carolean Dr",
    "sg:city":"State College",
    "sg:classifiers":[
        {
            "category":"Manufacturing",
            "subcategory":"Furniture",
            "type":"Manufacturing & Wholesale Goods"
        }
    ],
    "sg:phone":"+1   ",
    "sg:postcode":"16801",
    "sg:province":"PA",
    "sg:tags":[
        "mfg",
        "product",
        "wood",
        "furn"
    ],
    "wof:name":"Chase Collection The",
    "wof:placetype":"venue"
},
  "geometry": {"coordinates":[-77.80112,40.826778],"type":"Point"}
}