{
  "type": "Feature",
  "properties": {
    "addr:full":"510 Bryn Mawr Ave Bala Cynwyd PA 19004",
    "addr:housenumber":"510",
    "addr:postcode":"19004",
    "addr:street":"Bryn Mawr Ave",
    "iso:country":"US",
    "sg:address":"510 Bryn Mawr Ave",
    "sg:city":"Bala Cynwyd",
    "sg:classifiers":[
        {
            "category":"Education",
            "subcategory":"School",
            "type":"Public Place"
        }
    ],
    "sg:phone":"+1 610 645 1480",
    "sg:postcode":"19004",
    "sg:province":"PA",
    "sg:tags":[
        "high",
        "middle",
        "elementary"
    ],
    "wof:name":"Bala Cynwyd Middle School",
    "wof:placetype":"venue"
},
  "geometry": {"coordinates":[-75.241096,40.012199],"type":"Point"}
}