{
  "type": "Feature",
  "properties": {
    "addr:full":"1233 Cherry St Brockway PA 15824",
    "addr:housenumber":"1233",
    "addr:postcode":"15824",
    "addr:street":"Cherry St",
    "iso:country":"US",
    "sg:address":"1233 Cherry St",
    "sg:city":"Brockway",
    "sg:classifiers":[
        {
            "category":"Retail",
            "subcategory":"Car Wash",
            "type":"Services"
        }
    ],
    "sg:phone":"+1 814 265 8400",
    "sg:postcode":"15824",
    "sg:province":"PA",
    "sg:tags":[
        "polishing",
        "salon",
        "washing",
        "beauty"
    ],
    "wof:name":"All Washed Up Auto Spa",
    "wof:placetype":"venue"
},
  "geometry": {"coordinates":[-78.786517,41.24301],"type":"Point"}
}