{
  "type": "Feature",
  "properties": {
    "iso:country":"US",
    "sg:address":"224 W Mahoning St",
    "sg:city":"Punxsutawney",
    "sg:classifiers":[
        {
            "category":"Professional",
            "subcategory":"Accounting & Tax Preparation",
            "type":"Services"
        }
    ],
    "sg:phone":"+1 814 938 6040",
    "sg:postcode":"15767",
    "sg:province":"PA",
    "sg:tags":[
        "accountant"
    ],
    "wof:name":"Michael A Stello CPA",
    "wof:placetype":"venue"
},
  "geometry": {"coordinates":[-78.97297399999999,40.943149],"type":"Point"}
}