{
  "type": "Feature",
  "properties": {
    "iso:country":"US",
    "sg:address":"5411 Butler St",
    "sg:city":"Pittsburgh",
    "sg:classifiers":[
        {
            "category":"Manufacturing",
            "subcategory":"Metals",
            "type":"Manufacturing & Wholesale Goods"
        }
    ],
    "sg:phone":"+1   ",
    "sg:postcode":"15201",
    "sg:province":"PA",
    "sg:tags":[
        "spring",
        "product",
        "wire",
        "fabricated",
        "mfg"
    ],
    "wof:name":"Spring Distributors",
    "wof:placetype":"venue"
},
  "geometry": {"coordinates":[-79.950074,40.483568],"type":"Point"}
}