{
  "type": "Feature",
  "properties": {
    "iso:country":"US",
    "sg:address":"34 N George St",
    "sg:city":"York",
    "sg:classifiers":[
        {
            "category":"Real Estate",
            "subcategory":"Real Estate Operator",
            "type":"Services"
        }
    ],
    "sg:phone":"+1   ",
    "sg:postcode":"17401",
    "sg:province":"PA",
    "sg:tags":[
        "building"
    ],
    "wof:name":"J & B Associates",
    "wof:placetype":"venue"
},
  "geometry": {"coordinates":[-76.72783699999999,39.962515],"type":"Point"}
}