{
  "type": "Feature",
  "properties": {
    "iso:country":"US",
    "sg:address":"2926 Conestoga Rd",
    "sg:city":"Glenmoore",
    "sg:classifiers":[
        {
            "category":"Home & Garden",
            "subcategory":"Home Furnishings",
            "type":"Retail Goods"
        }
    ],
    "sg:phone":"+1 610 458 8964",
    "sg:postcode":"19343",
    "sg:province":"PA",
    "sg:tags":[
        "lighting",
        "fixture"
    ],
    "wof:name":"Eagle Lantern",
    "wof:placetype":"venue"
},
  "geometry": {"coordinates":[-75.694615,40.115825],"type":"Point"}
}