{
  "type": "Feature",
  "properties": {
    "addr:full":"Cross Keys Plaza Rt 313 & 611 Doylestown PA 18901",
    "addr:postcode":"18901",
    "addr:street":"Plaza Rt 313 & 611",
    "iso:country":"US",
    "sg:address":"Cross Keys Plaza Rt 313 & 611",
    "sg:city":"Doylestown",
    "sg:classifiers":[
        {
            "category":"Restaurant",
            "type":"Food & Drink"
        }
    ],
    "sg:menulink":"http://www.allmenus.com/pa/doylestown/91395-pinas-iii/menu/",
    "sg:phone":"+1 215 348 8945",
    "sg:postcode":"18901",
    "sg:province":"PA",
    "sg:tags":[
        "american",
        "pizza"
    ],
    "wof:name":"Pina's Iii",
    "wof:placetype":"venue"
},
  "geometry": {"coordinates":[-75.12762499999999,40.275723],"type":"Point"}
}