{
  "type": "Feature",
  "properties": {
    "iso:country":"US",
    "sg:address":"750 Chestnut St",
    "sg:city":"Reading",
    "sg:classifiers":[
        {
            "category":"Wholesale",
            "subcategory":"Office Equipment",
            "type":"Manufacturing & Wholesale Goods"
        }
    ],
    "sg:phone":"+1 610 372 4444",
    "sg:postcode":"19602",
    "sg:province":"PA",
    "sg:tags":[
        "register",
        "cash",
        "supply"
    ],
    "sg:website":"www.sharpequipment.com",
    "wof:name":"Sharp Equipment Co",
    "wof:placetype":"venue"
},
  "geometry": {"coordinates":[-75.92238399999999,40.332024],"type":"Point"}
}