{
  "type": "Feature",
  "properties": {
    "iso:country":"US",
    "sg:address":"344 E Walnut Ln",
    "sg:city":"Philadelphia",
    "sg:classifiers":[
        {
            "category":"Real Estate",
            "subcategory":"Real Estate Agent",
            "type":"Services"
        }
    ],
    "sg:phone":"+1 215 848 6710",
    "sg:postcode":"19144",
    "sg:province":"PA",
    "sg:tags":[
        "cooperative"
    ],
    "wof:name":"Weavers Way Co Op Warehouse",
    "wof:placetype":"venue"
},
  "geometry": {"coordinates":[-75.173734,40.045619],"type":"Point"}
}