{
  "type": "Feature",
  "properties": {
    "addr:full":"213 Lindenwold Ave Ambler PA 19002",
    "addr:housenumber":"213",
    "addr:postcode":"19002",
    "addr:street":"Lindenwold Ave",
    "iso:country":"US",
    "sg:address":"213 Lindenwold Ave",
    "sg:city":"Ambler",
    "sg:classifiers":[
        {
            "category":"Professional",
            "subcategory":"Art Services",
            "type":"Services"
        }
    ],
    "sg:phone":"+1 215 653 7000",
    "sg:postcode":"19002",
    "sg:province":"PA",
    "sg:tags":[
        "graphics",
        "design",
        "package"
    ],
    "wof:name":"Marcolina Design Inc",
    "wof:placetype":"venue"
},
  "geometry": {"coordinates":[-75.21720500000001,40.155683],"type":"Point"}
}