{
  "type": "Feature",
  "properties": {
    "iso:country":"US",
    "sg:address":"168 Walnut St",
    "sg:city":"Carmichaels",
    "sg:classifiers":[
        {
            "category":"Real Estate",
            "subcategory":"Real Estate Agent",
            "type":"Services"
        }
    ],
    "sg:phone":"+1   ",
    "sg:postcode":"15320",
    "sg:province":"PA",
    "wof:name":"Brother Rentals",
    "wof:placetype":"venue"
},
  "geometry": {"coordinates":[-79.983485,39.889291],"type":"Point"}
}