{
  "type": "Feature",
  "properties": {
    "addr:full":"301 Dautrich Rd Reading PA 19606",
    "addr:housenumber":"301",
    "addr:postcode":"19606",
    "addr:street":"Dautrich Rd",
    "iso:country":"US",
    "sg:address":"301 Dautrich Rd",
    "sg:city":"Reading",
    "sg:classifiers":[
        {
            "category":"Social Services",
            "type":"Services"
        },
        {
            "category":"Professional",
            "subcategory":"Employment Agencies",
            "type":"Services"
        },
        {
            "category":"Sports & Exercise",
            "subcategory":"Sports Center",
            "type":"Entertainment"
        },
        {
            "category":"Arena",
            "subcategory":"Sports Club",
            "type":"Entertainment"
        }
    ],
    "sg:phone":"+1 610 779 2090",
    "sg:postcode":"19606",
    "sg:province":"PA",
    "sg:tags":[
        "workers'",
        "placement",
        "volunteer"
    ],
    "sg:website":"http://www.danielboonerodandgun.com",
    "wof:name":"Boone, Daniel Rod & Gun Club",
    "wof:placetype":"venue"
},
  "geometry": {"coordinates":[-75.84944900000001,40.34763],"type":"Point"}
}