{
  "type": "Feature",
  "properties": {
    "iso:country":"US",
    "sg:address":"289 Town Center Blvd Suite 212",
    "sg:city":"Easton",
    "sg:classifiers":[
        {
            "category":"Professional",
            "subcategory":"Accounting & Tax Preparation",
            "type":"Services"
        }
    ],
    "sg:phone":"+1 610 365 7878",
    "sg:postcode":"18040",
    "sg:province":"PA",
    "sg:tags":[
        "bookkeeping",
        "return",
        "public",
        "accountants-certified"
    ],
    "wof:name":"Diane L. Wallo, CPA",
    "wof:placetype":"venue"
},
  "geometry": {"coordinates":[-75.22036199999999,40.712792],"type":"Point"}
}