{
  "type": "Feature",
  "properties": {
    "iso:country":"US",
    "sg:address":"275 W Market St",
    "sg:city":"York",
    "sg:classifiers":[
        {
            "category":"Organizations",
            "subcategory":"Professional Association",
            "type":"Services"
        }
    ],
    "sg:phone":"+1 717 845 2475",
    "sg:postcode":"17401",
    "sg:province":"PA",
    "wof:name":"Democratic Party-York County",
    "wof:placetype":"venue"
},
  "geometry": {"coordinates":[-76.73423099999999,39.96057],"type":"Point"}
}