{
  "type": "Feature",
  "properties": {
    "addr:full":"500 N Front St Lemoyne PA 17043",
    "addr:housenumber":"500",
    "addr:postcode":"17043",
    "addr:street":"N Front St",
    "iso:country":"US",
    "sg:address":"500 N Front St",
    "sg:city":"Lemoyne",
    "sg:classifiers":[
        {
            "category":"Professional",
            "subcategory":"Engineering",
            "type":"Services"
        }
    ],
    "sg:phone":"+1 717 737 1559",
    "sg:postcode":"17043",
    "sg:province":"PA",
    "sg:tags":[
        "contractor",
        "engineer"
    ],
    "wof:name":"Bruce Ensor Structural Engineer",
    "wof:placetype":"venue"
},
  "geometry": {"coordinates":[-76.905098,40.261002],"type":"Point"}
}