{
  "type": "Feature",
  "properties": {
    "iso:country":"US",
    "sg:address":"1265 Drummers Ln",
    "sg:city":"Wayne",
    "sg:classifiers":[
        {
            "category":"Banks & Credit Unions",
            "subcategory":"Investment Brokerage",
            "type":"Services"
        }
    ],
    "sg:phone":"+1   ",
    "sg:postcode":"19087",
    "sg:province":"PA",
    "sg:tags":[
        "security"
    ],
    "wof:name":"Dean Witter",
    "wof:placetype":"venue"
},
  "geometry": {"coordinates":[-75.41359199999999,40.084866],"type":"Point"}
}