{
  "type": "Feature",
  "properties": {
    "iso:country":"US",
    "sg:address":"528 Sanderson St",
    "sg:city":"Throop",
    "sg:classifiers":[
        {
            "category":"Bars & Pubs",
            "type":"Food & Drink"
        }
    ],
    "sg:phone":"+1 570 489 4510",
    "sg:postcode":"18512",
    "sg:province":"PA",
    "sg:tags":[
        "drinking",
        "restaurant"
    ],
    "wof:name":"Puzzles Pub",
    "wof:placetype":"venue"
},
  "geometry": {"coordinates":[-75.619181,41.445478],"type":"Point"}
}