{
  "type": "Feature",
  "properties": {
    "iso:country":"US",
    "sg:address":"2526 Mosside Blvd",
    "sg:city":"Monroeville",
    "sg:classifiers":[
        {
            "category":"Personal",
            "subcategory":"Beauty Salon",
            "type":"Services"
        }
    ],
    "sg:phone":"+1 412 373 5060",
    "sg:postcode":"15146",
    "sg:province":"PA",
    "wof:name":"Parlor Salon & Spa",
    "wof:placetype":"venue"
},
  "geometry": {"coordinates":[-79.754474,40.424487],"type":"Point"}
}