{
  "type": "Feature",
  "properties": {
    "iso:country":"US",
    "sg:address":"25 West Ave",
    "sg:city":"Wayne",
    "sg:classifiers":[
        {
            "category":"Retail",
            "subcategory":"Laundry & Dry Cleaning",
            "type":"Services"
        }
    ],
    "sg:phone":"+1   ",
    "sg:postcode":"19087",
    "sg:province":"PA",
    "sg:tags":[
        "garment",
        "agent"
    ],
    "wof:name":"Montgomery Cleaning Services",
    "wof:placetype":"venue"
},
  "geometry": {"coordinates":[-75.390873,40.046031],"type":"Point"}
}