{
  "type": "Feature",
  "properties": {
    "addr:full":"42 Main St Hellertown PA 18055",
    "addr:housenumber":"42",
    "addr:postcode":"18055",
    "addr:street":"Main St",
    "iso:country":"US",
    "sg:address":"42 Main St",
    "sg:city":"Hellertown",
    "sg:classifiers":[
        {
            "category":"Banks & Credit Unions",
            "subcategory":"Financial Services",
            "type":"Services"
        }
    ],
    "sg:phone":"+1 610 838 5433",
    "sg:postcode":"18055",
    "sg:province":"PA",
    "sg:tags":[
        "broker",
        "mortgage"
    ],
    "wof:name":"Wharton Financial",
    "wof:placetype":"venue"
},
  "geometry": {"coordinates":[-75.340366,40.568191],"type":"Point"}
}