{
  "type": "Feature",
  "properties": {
    "addr:full":"2121 Willow Park Rd Bethlehem PA 18020",
    "addr:housenumber":"2121",
    "addr:postcode":"18020",
    "addr:street":"Willow Park Rd",
    "iso:country":"US",
    "sg:address":"2121 Willow Park Rd",
    "sg:city":"Bethlehem",
    "sg:classifiers":[
        {
            "category":"Wholesale",
            "subcategory":"Construction Materials",
            "type":"Manufacturing & Wholesale Goods"
        }
    ],
    "sg:phone":"+1   ",
    "sg:postcode":"18020",
    "sg:province":"PA",
    "sg:tags":[
        "industrial",
        "supply"
    ],
    "wof:name":"Pallet Pro",
    "wof:placetype":"venue"
},
  "geometry": {"coordinates":[-75.33314900000001,40.647775],"type":"Point"}
}