{
  "type": "Feature",
  "properties": {
    "addr:full":"226 Schoolhouse Rd Palmyra PA 17078",
    "addr:housenumber":"226",
    "addr:postcode":"17078",
    "addr:street":"Schoolhouse Rd",
    "iso:country":"US",
    "sg:address":"226 Schoolhouse Rd",
    "sg:city":"Palmyra",
    "sg:phone":"+1 717 838 9780",
    "sg:postcode":"17078",
    "sg:province":"PA",
    "wof:name":"Yeany Educational Products",
    "wof:placetype":"venue"
},
  "geometry": {"coordinates":[-76.588584,40.262454],"type":"Point"}
}