{
  "type": "Feature",
  "properties": {
    "iso:country":"US",
    "sg:address":"1026 Prospect Ave",
    "sg:city":"Langhorne",
    "sg:classifiers":[
        {
            "category":"Building & Trades",
            "subcategory":"Landscaping Services",
            "type":"Services"
        }
    ],
    "sg:phone":"+1 215 757 0186",
    "sg:postcode":"19047",
    "sg:province":"PA",
    "sg:tags":[
        "landscape",
        "contractor"
    ],
    "wof:name":"Cravener & Sons Landscaping",
    "wof:placetype":"venue"
},
  "geometry": {"coordinates":[-74.931361,40.157883],"type":"Point"}
}