{
  "type": "Feature",
  "properties": {
    "iso:country":"US",
    "sg:address":"270 Yost Blvd ",
    "sg:city":"Pittsburgh",
    "sg:classifiers":[
        {
            "category":"Deli",
            "type":"Food & Drink"
        }
    ],
    "sg:menulink":"http://www.allmenus.com/pa/braddock-hills/287517-rudys-submarines/menu/",
    "sg:phone":"+1 412 271 9557",
    "sg:postcode":"15221",
    "sg:province":"PA",
    "sg:tags":[
        "american"
    ],
    "wof:name":"Rudy's Submarines",
    "wof:placetype":"venue"
},
  "geometry": {"coordinates":[-79.85456600000001,40.413505],"type":"Point"}
}