{
  "type": "Feature",
  "properties": {
    "iso:country":"US",
    "sg:address":"217 Bridge St",
    "sg:city":"Clearfield",
    "sg:classifiers":[
        {
            "category":"Professional",
            "type":"Services"
        }
    ],
    "sg:phone":"+1 814 768 7388",
    "sg:postcode":"16830",
    "sg:province":"PA",
    "wof:name":"Jack & Jill Scrapbooking",
    "wof:placetype":"venue"
},
  "geometry": {"coordinates":[-78.43789599999999,41.026417],"type":"Point"}
}