{
  "type": "Feature",
  "properties": {
    "iso:country":"US",
    "sg:address":"720 Saint Thomas St",
    "sg:city":"Gallitzin",
    "sg:classifiers":[
        {
            "category":"Building & Trades",
            "subcategory":"Construction",
            "type":"Services"
        }
    ],
    "sg:phone":"+1   ",
    "sg:postcode":"16641",
    "sg:province":"PA",
    "wof:name":"Egers Construction",
    "wof:placetype":"venue"
},
  "geometry": {"coordinates":[-78.547545,40.482617],"type":"Point"}
}