{
  "type": "Feature",
  "properties": {
    "iso:country":"US",
    "sg:address":"11 W Maiden St",
    "sg:city":"Washington",
    "sg:classifiers":[
        {
            "category":"Shopping",
            "type":"Retail Goods"
        }
    ],
    "sg:phone":"+1 724 250 9140",
    "sg:postcode":"15301",
    "sg:province":"PA",
    "sg:tags":[
        "merchandise"
    ],
    "wof:name":"Miracle-Ear",
    "wof:placetype":"venue"
},
  "geometry": {"coordinates":[-80.244868,40.167845],"type":"Point"}
}