{
  "type": "Feature",
  "properties": {
    "iso:country":"US",
    "sg:address":"917 Evergreen Ave",
    "sg:city":"Millvale",
    "sg:classifiers":[
        {
            "category":"Social Services",
            "subcategory":"Adult Care",
            "type":"Services"
        }
    ],
    "sg:phone":"+1 412 821 1257",
    "sg:postcode":"15209",
    "sg:province":"PA",
    "sg:tags":[
        "organization",
        "senior",
        "citizen"
    ],
    "wof:name":"Northern Area Multi-Svc Ctr",
    "wof:placetype":"venue"
},
  "geometry": {"coordinates":[-79.97188,40.49016],"type":"Point"}
}