{
  "type": "Feature",
  "properties": {
    "addr:full":"1779 Winters Rd Windsor PA 17366",
    "addr:housenumber":"1779",
    "addr:postcode":"17366",
    "addr:street":"Winters Rd",
    "iso:country":"US",
    "sg:address":"1779 Winters Rd",
    "sg:city":"Windsor",
    "sg:phone":"+1 717 244 4419",
    "sg:postcode":"17366",
    "sg:province":"PA",
    "sg:tags":[
        "oil"
    ],
    "wof:name":"Robbie's Oil Svc",
    "wof:placetype":"venue"
},
  "geometry": {"coordinates":[-76.56446099999999,39.936186],"type":"Point"}
}