{
  "type": "Feature",
  "properties": {
    "iso:country":"US",
    "sg:address":"5125 Jonestown Rd",
    "sg:city":"Harrisburg",
    "sg:classifiers":[
        {
            "category":"Shopping",
            "subcategory":"Clothing, Apparel, & Fashions",
            "type":"Retail Goods"
        }
    ],
    "sg:phone":"+1 717 526 2024",
    "sg:postcode":"17112",
    "sg:province":"PA",
    "sg:tags":[
        "store"
    ],
    "wof:name":"Dress Barn",
    "wof:placetype":"venue"
},
  "geometry": {"coordinates":[-76.800453,40.31226],"type":"Point"}
}