{
  "type": "Feature",
  "properties": {
    "iso:country":"US",
    "sg:address":"143 N Flowers Mill Rd",
    "sg:city":"Langhorne",
    "sg:classifiers":[
        {
            "category":"Restaurant",
            "type":"Food & Drink"
        }
    ],
    "sg:phone":"+1 215 752 4743",
    "sg:postcode":"19047",
    "sg:province":"PA",
    "sg:tags":[
        "eating",
        "pizza"
    ],
    "wof:name":"Peppi's Pizza",
    "wof:placetype":"venue"
},
  "geometry": {"coordinates":[-74.907546,40.179773],"type":"Point"}
}