{
  "type": "Feature",
  "properties": {
    "iso:country":"US",
    "sg:address":"450 Gibner Rd",
    "sg:city":"Carlisle",
    "sg:classifiers":[
        {
            "category":"Health Services",
            "subcategory":"Hospital",
            "type":"Services"
        },
        {
            "category":"Health Services",
            "subcategory":"Doctor",
            "type":"Services"
        }
    ],
    "sg:phone":"+1 717 245 3301",
    "sg:postcode":"17013",
    "sg:province":"PA",
    "sg:tags":[
        "physician",
        "surgeon",
        "general"
    ],
    "wof:name":"Dunham US Army Health Clinic",
    "wof:placetype":"venue"
},
  "geometry": {"coordinates":[-77.17483799999999,40.208234],"type":"Point"}
}