{
  "type": "Feature",
  "properties": {
    "iso:country":"US",
    "sg:address":"1002 New Hope St",
    "sg:city":"Norristown",
    "sg:classifiers":[
        {
            "category":"Food & Beverages",
            "subcategory":"Bakery",
            "type":"Retail Goods"
        }
    ],
    "sg:phone":"+1   ",
    "sg:postcode":"19401",
    "sg:province":"PA",
    "wof:name":"Espresso Plus Inc",
    "wof:placetype":"venue"
},
  "geometry": {"coordinates":[-75.324335,40.116658],"type":"Point"}
}