{
  "type": "Feature",
  "properties": {
    "addr:full":"8636 Germantown Ave Philadelphia PA 19118",
    "addr:housenumber":"8636",
    "addr:postcode":"19118",
    "addr:street":"Germantown Ave",
    "iso:country":"US",
    "sg:address":"8636 Germantown Ave",
    "sg:city":"Philadelphia",
    "sg:classifiers":[
        {
            "category":"Bars & Pubs",
            "type":"Food & Drink"
        },
        {
            "category":"Restaurant",
            "type":"Food & Drink"
        },
        {
            "category":"Bars & Pubs",
            "subcategory":"Lounge",
            "type":"Food & Drink"
        }
    ],
    "sg:phone":"+1 215 247 9948",
    "sg:postcode":"19118",
    "sg:province":"PA",
    "sg:tags":[
        "grill",
        "tavern",
        "brew",
        "cocktail"
    ],
    "wof:name":"Tavern On The Hill",
    "wof:placetype":"venue"
},
  "geometry": {"coordinates":[-75.208327,40.077087],"type":"Point"}
}