{
  "type": "Feature",
  "properties": {
    "iso:country":"US",
    "sg:address":"930 Willshire Dr",
    "sg:city":"Mechanicsburg",
    "sg:classifiers":[
        {
            "category":"Professional",
            "type":"Services"
        }
    ],
    "sg:phone":"+1   ",
    "sg:postcode":"17050",
    "sg:province":"PA",
    "wof:name":"Hempfield Associates",
    "wof:placetype":"venue"
},
  "geometry": {"coordinates":[-76.967664,40.264514],"type":"Point"}
}