{
  "type": "Feature",
  "properties": {
    "iso:country":"US",
    "sg:address":"77 Towpath Rd",
    "sg:city":"Fairless Hills",
    "sg:classifiers":[
        {
            "category":"Building & Trades",
            "subcategory":"Equipment Rental",
            "type":"Services"
        }
    ],
    "sg:phone":"+1   ",
    "sg:postcode":"19030",
    "sg:province":"PA",
    "wof:name":"Safety-Kleen",
    "wof:placetype":"venue"
},
  "geometry": {"coordinates":[-74.790846,40.184422],"type":"Point"}
}