{
  "type": "Feature",
  "properties": {
    "iso:country":"US",
    "sg:address":"288 Evansville Rd",
    "sg:city":"Fleetwood",
    "sg:classifiers":[
        {
            "category":"Farming",
            "subcategory":"Livestock Farm",
            "type":"Manufacturing & Wholesale Goods"
        }
    ],
    "sg:phone":"+1   ",
    "sg:postcode":"19522",
    "sg:province":"PA",
    "sg:tags":[
        "beef",
        "feedlot",
        "cattle"
    ],
    "wof:name":"Robert J Heffner",
    "wof:placetype":"venue"
},
  "geometry": {"coordinates":[-75.88439,40.470316],"type":"Point"}
}