{
  "type": "Feature",
  "properties": {
    "iso:country":"US",
    "sg:address":"1001 Forrest St",
    "sg:city":"Conshohocken",
    "sg:classifiers":[
        {
            "category":"Manufacturing",
            "subcategory":"Printing",
            "type":"Manufacturing & Wholesale Goods"
        }
    ],
    "sg:phone":"+1   ",
    "sg:postcode":"19428",
    "sg:province":"PA",
    "sg:tags":[
        "newspaper",
        "eating"
    ],
    "wof:name":"Cafe Fiore Inc",
    "wof:placetype":"venue"
},
  "geometry": {"coordinates":[-75.299228,40.082215],"type":"Point"}
}