{
  "type": "Feature",
  "properties": {
    "iso:country":"US",
    "sg:address":"2570 Boyce Plaza Rd",
    "sg:city":"Pittsburgh",
    "sg:classifiers":[
        {
            "category":"Real Estate",
            "subcategory":"Architect",
            "type":"Services"
        }
    ],
    "sg:phone":"+1 412 269 7677",
    "sg:postcode":"15241",
    "sg:province":"PA",
    "wof:name":"Richard Hamil",
    "wof:placetype":"venue"
},
  "geometry": {"coordinates":[-80.114155,40.320888],"type":"Point"}
}