{
  "type": "Feature",
  "properties": {
    "iso:country":"US",
    "sg:address":"1400 Liberty Ridge Dr",
    "sg:city":"Chesterbrook",
    "sg:classifiers":[
        {
            "category":"Professional",
            "type":"Services"
        }
    ],
    "sg:phone":"+1 610 408 3700",
    "sg:postcode":"19087",
    "sg:province":"PA",
    "sg:tags":[
        "establishment"
    ],
    "sg:website":"www.investorforce.com",
    "wof:name":"INVESTORFORCE.COM",
    "wof:placetype":"venue"
},
  "geometry": {"coordinates":[-75.464693,40.069136],"type":"Point"}
}