{
  "type": "Feature",
  "properties": {
    "iso:country":"US",
    "sg:address":"2544 Brandt School Rd",
    "sg:city":"Wexford",
    "sg:classifiers":[
        {
            "category":"Building & Trades",
            "subcategory":"Construction",
            "type":"Services"
        }
    ],
    "sg:phone":"+1 724 934 8134",
    "sg:postcode":"15090",
    "sg:province":"PA",
    "sg:tags":[
        "roofing",
        "contractor"
    ],
    "wof:name":"Baileys Roofing",
    "wof:placetype":"venue"
},
  "geometry": {"coordinates":[-80.087486,40.606392],"type":"Point"}
}