{
  "type": "Feature",
  "properties": {
    "iso:country":"US",
    "sg:address":"2001 Ehrman Rd Ste 100",
    "sg:city":"Cranberry Twp",
    "sg:classifiers":[
        {
            "category":"Community Center",
            "type":"Public Place"
        }
    ],
    "sg:phone":"+1 724 631 0053",
    "sg:postcode":"16066",
    "sg:province":"PA",
    "sg:tags":[
        "medical"
    ],
    "sg:website":"www.bhswholehealth.org",
    "wof:name":"Bhs Wholehealth",
    "wof:placetype":"venue"
},
  "geometry": {"coordinates":[-80.109736,40.734747],"type":"Point"}
}