{
  "type": "Feature",
  "properties": {
    "addr:full":"5 S Oak Ave Clifton Heights PA 19018",
    "addr:housenumber":"5",
    "addr:postcode":"19018",
    "addr:street":"S Oak Ave",
    "iso:country":"US",
    "sg:address":"5 S Oak Ave",
    "sg:city":"Clifton Heights",
    "sg:classifiers":[
        {
            "category":"Autos & Motor Vehicles",
            "subcategory":"Fuel & Gas Station",
            "type":"Retail Goods"
        }
    ],
    "sg:phone":"+1 610 622 8226",
    "sg:postcode":"19018",
    "sg:province":"PA",
    "sg:tags":[
        "oil"
    ],
    "wof:name":"Aldan Getty",
    "wof:placetype":"venue"
},
  "geometry": {"coordinates":[-75.302108,39.926654],"type":"Point"}
}