{
  "type": "Feature",
  "properties": {
    "iso:country":"US",
    "sg:address":"1199 Greenhill Ln",
    "sg:city":"Somerset",
    "sg:classifiers":[
        {
            "category":"Home & Garden",
            "subcategory":"Garden Supply",
            "type":"Retail Goods"
        },
        {
            "category":"Utilities",
            "type":"Services"
        }
    ],
    "sg:phone":"+1 814 442 6653",
    "sg:postcode":"15501",
    "sg:province":"PA",
    "sg:tags":[
        "sanitary",
        "nurseryman"
    ],
    "wof:name":"Marteeny Lawn & Garden Center",
    "wof:placetype":"venue"
},
  "geometry": {"coordinates":[-79.1039,39.999278],"type":"Point"}
}