{
  "type": "Feature",
  "properties": {
    "iso:country":"US",
    "sg:address":"276 Ashler Manor Dr",
    "sg:city":"Muncy",
    "sg:classifiers":[
        {
            "category":"Health Services",
            "subcategory":"Clinic",
            "type":"Services"
        }
    ],
    "sg:phone":"+1 570 546 8797",
    "sg:postcode":"17756",
    "sg:province":"PA",
    "sg:tags":[
        "welfare"
    ],
    "wof:name":"Ashler Manor",
    "wof:placetype":"venue"
},
  "geometry": {"coordinates":[-76.808776,41.225778],"type":"Point"}
}