{
  "type": "Feature",
  "properties": {
    "iso:country":"US",
    "sg:address":"325 W Main St",
    "sg:city":"Collegeville",
    "sg:classifiers":[
        {
            "category":"Wholesale",
            "subcategory":"Beer",
            "type":"Manufacturing & Wholesale Goods"
        },
        {
            "category":"Food & Beverages",
            "subcategory":"Liquor & Beverages",
            "type":"Retail Goods"
        }
    ],
    "sg:phone":"+1 610 489 2070",
    "sg:postcode":"19426",
    "sg:province":"PA",
    "sg:tags":[
        "ale",
        "ale-wholesale",
        "manufacturer"
    ],
    "wof:name":"Trappe Beer & Soda",
    "wof:placetype":"venue"
},
  "geometry": {"coordinates":[-75.471903,40.197022],"type":"Point"}
}