{
  "type": "Feature",
  "properties": {
    "iso:country":"US",
    "sg:address":"6403 Lexington Dr",
    "sg:city":"Mechanicsburg",
    "sg:classifiers":[
        {
            "category":"Social Services",
            "type":"Services"
        }
    ],
    "sg:phone":"+1   ",
    "sg:postcode":"17050",
    "sg:province":"PA",
    "wof:name":"Small Frys Family Day Care",
    "wof:placetype":"venue"
},
  "geometry": {"coordinates":[-77.008466,40.260382],"type":"Point"}
}