{
  "type": "Feature",
  "properties": {
    "iso:country":"US",
    "sg:address":"1551 Devers Rd",
    "sg:city":"York",
    "sg:classifiers":[
        {
            "category":"Health Services",
            "subcategory":"Doctor",
            "type":"Services"
        }
    ],
    "sg:phone":"+1   ",
    "sg:postcode":"17404",
    "sg:province":"PA",
    "sg:tags":[
        "medical"
    ],
    "wof:name":"Winifred L Dawson",
    "wof:placetype":"venue"
},
  "geometry": {"coordinates":[-76.750112,39.980641],"type":"Point"}
}