{
  "type": "Feature",
  "properties": {
    "iso:country":"US",
    "sg:address":"3901 Market St",
    "sg:city":"Philadelphia",
    "sg:classifiers":[
        {
            "category":"Restaurant",
            "type":"Food & Drink"
        }
    ],
    "sg:menulink":"http://www.allmenus.com/pa/philadelphia/292906-mothers-garden-organic-restaurant/menu/",
    "sg:phone":"+1 866 491 5603",
    "sg:postcode":"19104",
    "sg:province":"PA",
    "sg:tags":[
        "american"
    ],
    "wof:name":"Mother's Garden Organic Restaurant",
    "wof:placetype":"venue"
},
  "geometry": {"coordinates":[-75.199642,39.956897],"type":"Point"}
}