{
  "type": "Feature",
  "properties": {
    "addr:full":"681 Andersen Dr Pittsburgh PA 15220",
    "addr:housenumber":"681",
    "addr:postcode":"15220",
    "addr:street":"Andersen Dr",
    "iso:country":"US",
    "sg:address":"681 Andersen Dr",
    "sg:city":"Pittsburgh",
    "sg:classifiers":[
        {
            "category":"Insurance",
            "subcategory":"Insurance Agent",
            "type":"Services"
        }
    ],
    "sg:phone":"+1 412 921 4666",
    "sg:postcode":"15220",
    "sg:province":"PA",
    "wof:name":"Pacific Life Insurance Co",
    "wof:placetype":"venue"
},
  "geometry": {"coordinates":[-80.064363,40.42011],"type":"Point"}
}