{
  "type": "Feature",
  "properties": {
    "iso:country":"US",
    "sg:address":"25 W Germantown Pike",
    "sg:city":"Norristown",
    "sg:classifiers":[
        {
            "category":"Restaurant",
            "type":"Food & Drink"
        }
    ],
    "sg:phone":"+1 610 278 2993",
    "sg:postcode":"19401",
    "sg:province":"PA",
    "sg:tags":[
        "pizza"
    ],
    "wof:name":"Genuardi's Family Markets Pizza",
    "wof:placetype":"venue"
},
  "geometry": {"coordinates":[-75.31390399999999,40.142502],"type":"Point"}
}