{
  "type": "Feature",
  "properties": {
    "iso:country":"US",
    "sg:address":"717 Church Ln",
    "sg:city":"Yeadon",
    "sg:classifiers":[
        {
            "category":"Restaurant",
            "type":"Food & Drink"
        }
    ],
    "sg:phone":"+1 610 622 6600",
    "sg:postcode":"19050",
    "sg:province":"PA",
    "sg:tags":[
        "southern",
        "eating"
    ],
    "wof:name":"Cafe Harlem",
    "wof:placetype":"venue"
},
  "geometry": {"coordinates":[-75.25045900000001,39.933792],"type":"Point"}
}