{
  "type": "Feature",
  "properties": {
    "addr:full":"530 E Walton Ave Altoona PA 16602",
    "addr:housenumber":"530",
    "addr:postcode":"16602",
    "addr:street":"E Walton Ave",
    "iso:country":"US",
    "sg:address":"530 E Walton Ave",
    "sg:city":"Altoona",
    "sg:classifiers":[
        {
            "category":"Health Services",
            "subcategory":"Doctor",
            "type":"Services"
        }
    ],
    "sg:phone":"+1   ",
    "sg:postcode":"16602",
    "sg:province":"PA",
    "wof:name":"Ralph Marasco",
    "wof:placetype":"venue"
},
  "geometry": {"coordinates":[-78.3755,40.523737],"type":"Point"}
}