{
  "type": "Feature",
  "properties": {
    "iso:country":"US",
    "sg:address":"1800 Rose Valley Way",
    "sg:city":"Ambler",
    "sg:classifiers":[
        {
            "category":"Professional",
            "subcategory":"Management & Consulting",
            "type":"Services"
        }
    ],
    "sg:phone":"+1   ",
    "sg:postcode":"19002",
    "sg:province":"PA",
    "wof:name":"Gsa Consulting Group Inc",
    "wof:placetype":"venue"
},
  "geometry": {"coordinates":[-75.215017,40.166351],"type":"Point"}
}