{
  "type": "Feature",
  "properties": {
    "iso:country":"US",
    "sg:address":"313 Chemung St",
    "sg:city":"Sayre",
    "sg:classifiers":[
        {
            "category":"Building & Trades",
            "subcategory":"Plumbing",
            "type":"Services"
        }
    ],
    "sg:phone":"+1 570 882 9170",
    "sg:postcode":"18840",
    "sg:province":"PA",
    "sg:tags":[
        "plumbing",
        "contractor"
    ],
    "wof:name":"A Affordable Plumbing Heating",
    "wof:placetype":"venue"
},
  "geometry": {"coordinates":[-76.522183,41.978071],"type":"Point"}
}