{
  "type": "Feature",
  "properties": {
    "iso:country":"US",
    "sg:address":"1031 S Broad St",
    "sg:city":"Lansdale",
    "sg:classifiers":[
        {
            "category":"Professional",
            "subcategory":"Management & Consulting",
            "type":"Services"
        }
    ],
    "sg:phone":"+1 215 361 5020",
    "sg:postcode":"19446",
    "sg:province":"PA",
    "sg:tags":[
        "consultant"
    ],
    "wof:name":"Cardiology Consultants",
    "wof:placetype":"venue"
},
  "geometry": {"coordinates":[-75.299173,40.225716],"type":"Point"}
}