{
  "type": "Feature",
  "properties": {
    "iso:country":"US",
    "sg:address":"6 Marian Rd",
    "sg:city":"Phoenixville",
    "sg:classifiers":[
        {
            "category":"Government",
            "subcategory":"Office",
            "type":"Public Place"
        }
    ],
    "sg:phone":"+1   ",
    "sg:postcode":"19460",
    "sg:province":"PA",
    "sg:tags":[
        "executive"
    ],
    "wof:name":"Charlestown Township Tax",
    "wof:placetype":"venue"
},
  "geometry": {"coordinates":[-75.552408,40.113331],"type":"Point"}
}