{
  "type": "Feature",
  "properties": {
    "iso:country":"US",
    "sg:address":"8203 Westminster Rd",
    "sg:city":"Elkins Park",
    "sg:classifiers":[
        {
            "category":"Cinema",
            "subcategory":"Movie Rental",
            "type":"Entertainment"
        }
    ],
    "sg:phone":"+1   ",
    "sg:postcode":"19027",
    "sg:province":"PA",
    "sg:tags":[
        "video",
        "tape"
    ],
    "wof:name":"On Air Video Inc",
    "wof:placetype":"venue"
},
  "geometry": {"coordinates":[-75.12868,40.082486],"type":"Point"}
}