{
  "type": "Feature",
  "properties": {
    "addr:full":"719 Pensacola Rd Ebensburg PA 15931",
    "addr:housenumber":"719",
    "addr:postcode":"15931",
    "addr:street":"Pensacola Rd",
    "iso:country":"US",
    "sg:address":"719 Pensacola Rd",
    "sg:city":"Ebensburg",
    "sg:classifiers":[
        {
            "category":"Shopping",
            "subcategory":"Computers & Home Electronics",
            "type":"Retail Goods"
        }
    ],
    "sg:phone":"+1 814 472 5540",
    "sg:postcode":"15931",
    "sg:province":"PA",
    "sg:tags":[
        "antenna"
    ],
    "wof:name":"Propagation Systems Inc",
    "wof:placetype":"venue"
},
  "geometry": {"coordinates":[-78.765502,40.45656],"type":"Point"}
}