{
  "type": "Feature",
  "properties": {
    "iso:country":"US",
    "sg:address":"1211 Marshallton Thorndale Rd",
    "sg:city":"Downingtown",
    "sg:classifiers":[
        {
            "category":"Building & Trades",
            "subcategory":"Construction",
            "type":"Services"
        }
    ],
    "sg:phone":"+1   ",
    "sg:postcode":"19335",
    "sg:province":"PA",
    "sg:tags":[
        "house"
    ],
    "wof:name":"Wilber & Bortree Bldg & Rmdlg",
    "wof:placetype":"venue"
},
  "geometry": {"coordinates":[-75.711541,39.968052],"type":"Point"}
}