{
  "type": "Feature",
  "properties": {
    "iso:country":"US",
    "sg:address":"325 S 12th St",
    "sg:city":"Reading",
    "sg:classifiers":[
        {
            "category":"Organizations",
            "subcategory":"Non-profit Organization",
            "type":"Services"
        },
        {
            "category":"Social Services",
            "type":"Services"
        }
    ],
    "sg:phone":"+1 610 376 1973",
    "sg:postcode":"19602",
    "sg:province":"PA",
    "sg:tags":[
        "alternative",
        "abortion"
    ],
    "sg:website":"www.marysshelter.com",
    "wof:name":"Mary's Shelter",
    "wof:placetype":"venue"
},
  "geometry": {"coordinates":[-75.914338,40.330362],"type":"Point"}
}