{
  "type": "Feature",
  "properties": {
    "iso:country":"US",
    "sg:address":"31 Williams Rd",
    "sg:city":"Punxsutawney",
    "sg:classifiers":[
        {
            "category":"Autos & Motor Vehicles",
            "subcategory":"Automobile Sales",
            "type":"Retail Goods"
        }
    ],
    "sg:phone":"+1 814 938 6299",
    "sg:postcode":"15767",
    "sg:province":"PA",
    "sg:tags":[
        "car",
        "dealer"
    ],
    "wof:name":"Shell's Auto Sales",
    "wof:placetype":"venue"
},
  "geometry": {"coordinates":[-78.932052,40.937497],"type":"Point"}
}