{
  "type": "Feature",
  "properties": {
    "addr:full":"3220 Tillman Dr Bensalem PA 19020",
    "addr:housenumber":"3220",
    "addr:postcode":"19020",
    "addr:street":"Tillman Dr",
    "iso:country":"US",
    "sg:address":"3220 Tillman Dr",
    "sg:city":"Bensalem",
    "sg:classifiers":[
        {
            "category":"Utilities",
            "subcategory":"Mobile Phone",
            "type":"Services"
        }
    ],
    "sg:phone":"+1   ",
    "sg:postcode":"19020",
    "sg:province":"PA",
    "sg:tags":[
        "messaging",
        "telephone",
        "cellular"
    ],
    "wof:name":"AT&T",
    "wof:placetype":"venue"
},
  "geometry": {"coordinates":[-74.96182399999999,40.114834],"type":"Point"}
}