{
  "type": "Feature",
  "properties": {
    "addr:full":"134 Washington Towne Blvd N Edinboro PA 16412",
    "addr:housenumber":"134",
    "addr:postcode":"16412",
    "addr:street":"Washington Towne Blvd N",
    "iso:country":"US",
    "sg:address":"134 Washington Towne Blvd N",
    "sg:city":"Edinboro",
    "sg:classifiers":[
        {
            "category":"Restaurant",
            "type":"Food & Drink"
        }
    ],
    "sg:menulink":"http://www.allmenus.com/pa/washington/133437-subway/menu/",
    "sg:phone":"+1 814 734 9444",
    "sg:postcode":"16412",
    "sg:province":"PA",
    "sg:tags":[
        "american",
        "sandwich"
    ],
    "wof:name":"Subway",
    "wof:placetype":"venue"
},
  "geometry": {"coordinates":[-80.172819,41.87763],"type":"Point"}
}