{
  "type": "Feature",
  "properties": {
    "addr:full":"716 Barnesville Dr Barnesville PA 18214",
    "addr:housenumber":"716",
    "addr:postcode":"18214",
    "addr:street":"Barnesville Dr",
    "iso:country":"US",
    "sg:address":"716 Barnesville Dr",
    "sg:city":"Barnesville",
    "sg:classifiers":[
        {
            "category":"Food & Beverages",
            "subcategory":"Liquor & Beverages",
            "type":"Retail Goods"
        }
    ],
    "sg:phone":"+1 570 467 0017",
    "sg:postcode":"18214",
    "sg:province":"PA",
    "wof:name":"Lake Side Park Beverage",
    "wof:placetype":"venue"
},
  "geometry": {"coordinates":[-76.04387699999999,40.812481],"type":"Point"}
}