{
  "type": "Feature",
  "properties": {
    "iso:country":"US",
    "sg:address":"3272 W Newport Rd",
    "sg:city":"Ronks",
    "sg:classifiers":[
        {
            "category":"Shopping",
            "subcategory":"Used Merchandise",
            "type":"Retail Goods"
        }
    ],
    "sg:phone":"+1 717 768 3067",
    "sg:postcode":"17572",
    "sg:province":"PA",
    "sg:website":"www.dutchbarnantiques.com",
    "wof:name":"Dutch Barn Antiques",
    "wof:placetype":"venue"
},
  "geometry": {"coordinates":[-76.135008,40.057508],"type":"Point"}
}