{
  "type": "Feature",
  "properties": {
    "addr:full":"663 Carson St Hazleton PA 18201",
    "addr:housenumber":"663",
    "addr:postcode":"18201",
    "addr:street":"Carson St",
    "iso:country":"US",
    "sg:address":"663 Carson St",
    "sg:city":"Hazleton",
    "sg:classifiers":[
        {
            "category":"Social Services",
            "subcategory":"Child Care",
            "type":"Services"
        }
    ],
    "sg:phone":"+1   ",
    "sg:postcode":"18201",
    "sg:province":"PA",
    "sg:tags":[
        "day"
    ],
    "wof:name":"Luzerne County Head Start",
    "wof:placetype":"venue"
},
  "geometry": {"coordinates":[-75.97062699999999,40.965673],"type":"Point"}
}