{
  "type": "Feature",
  "properties": {
    "addr:full":"144 W Chester Rd West Chester PA 19382",
    "addr:housenumber":"144",
    "addr:postcode":"19382",
    "addr:street":"W Chester Rd",
    "iso:country":"US",
    "sg:address":"144 W Chester Rd",
    "sg:city":"West Chester",
    "sg:classifiers":[
        {
            "category":"Building & Trades",
            "subcategory":"Electrical",
            "type":"Services"
        }
    ],
    "sg:phone":"+1 610 793 0152",
    "sg:postcode":"19382",
    "sg:province":"PA",
    "sg:tags":[
        "lighting",
        "landscape"
    ],
    "wof:name":"Wolff Lighting Systems",
    "wof:placetype":"venue"
},
  "geometry": {"coordinates":[-75.54437,39.910644],"type":"Point"}
}