{
  "type": "Feature",
  "properties": {
    "iso:country":"US",
    "sg:address":"10990 Decatur Rd",
    "sg:city":"Philadelphia",
    "sg:classifiers":[
        {
            "category":"Recreation",
            "type":"Entertainment"
        }
    ],
    "sg:phone":"+1 215 618 0050",
    "sg:postcode":"19154",
    "sg:province":"PA",
    "sg:tags":[
        "skating",
        "rink"
    ],
    "wof:name":"Flyers Skate Zone",
    "wof:placetype":"venue"
},
  "geometry": {"coordinates":[-74.992307,40.091463],"type":"Point"}
}