{
  "type": "Feature",
  "properties": {
    "iso:country":"US",
    "sg:address":"389 Wells Ter",
    "sg:city":"West Chester",
    "sg:classifiers":[
        {
            "category":"Manufacturing",
            "subcategory":"Furniture",
            "type":"Manufacturing & Wholesale Goods"
        }
    ],
    "sg:phone":"+1   ",
    "sg:postcode":"19380",
    "sg:province":"PA",
    "sg:tags":[
        "drapery",
        "mfg"
    ],
    "wof:name":"Curtain Lady",
    "wof:placetype":"venue"
},
  "geometry": {"coordinates":[-75.62391,40.013089],"type":"Point"}
}