{
  "type": "Feature",
  "properties": {
    "iso:country":"US",
    "sg:address":"206 Noel Rd",
    "sg:city":"Titusville",
    "sg:classifiers":[
        {
            "category":"Professional",
            "type":"Services"
        }
    ],
    "sg:phone":"+1 814 827 1514",
    "sg:postcode":"16354",
    "sg:province":"PA",
    "sg:tags":[
        "establishment"
    ],
    "wof:name":"Chapmanville Volunteer Fire",
    "wof:placetype":"venue"
},
  "geometry": {"coordinates":[-79.82650099999999,41.616407],"type":"Point"}
}