{
  "type": "Feature",
  "properties": {
    "addr:full":"1931 N Charlotte St Pottstown PA 19464",
    "addr:housenumber":"1931",
    "addr:postcode":"19464",
    "addr:street":"N Charlotte St",
    "iso:country":"US",
    "sg:address":"1931 N Charlotte St",
    "sg:city":"Pottstown",
    "sg:classifiers":[
        {
            "category":"Personal",
            "subcategory":"Beauty Salon",
            "type":"Services"
        }
    ],
    "sg:phone":"+1 610 323 3010",
    "sg:postcode":"19464",
    "sg:province":"PA",
    "wof:name":"Jenn's Stylig Salon",
    "wof:placetype":"venue"
},
  "geometry": {"coordinates":[-75.61156699999999,40.272987],"type":"Point"}
}