{
  "type": "Feature",
  "properties": {
    "iso:country":"US",
    "sg:address":"426 Beaver St",
    "sg:city":"Sewickley",
    "sg:classifiers":[
        {
            "category":"Restaurant",
            "type":"Food & Drink"
        }
    ],
    "sg:phone":"+1 412 741 1744",
    "sg:postcode":"15143",
    "sg:province":"PA",
    "sg:tags":[
        "drinking",
        "eating"
    ],
    "wof:name":"Pizza Roma",
    "wof:placetype":"venue"
},
  "geometry": {"coordinates":[-80.180981,40.540662],"type":"Point"}
}