{
  "type": "Feature",
  "properties": {
    "iso:country":"US",
    "sg:address":"2824 Fiddlers Green Rd",
    "sg:city":"Lancaster",
    "sg:classifiers":[
        {
            "category":"Professional",
            "subcategory":"Management & Consulting",
            "type":"Services"
        }
    ],
    "sg:phone":"+1   ",
    "sg:postcode":"17601",
    "sg:province":"PA",
    "wof:name":"L & D Marketing Inc",
    "wof:placetype":"venue"
},
  "geometry": {"coordinates":[-76.28832800000001,40.096045],"type":"Point"}
}