{
  "type": "Feature",
  "properties": {
    "iso:country":"US",
    "sg:address":"170 Amsite Rd",
    "sg:city":"South Fork",
    "sg:classifiers":[
        {
            "category":"Personal",
            "subcategory":"Beauty Salon",
            "type":"Services"
        }
    ],
    "sg:phone":"+1 814 495 9554",
    "sg:postcode":"15956",
    "sg:province":"PA",
    "wof:name":"Paula Oswalt's Unique Hair",
    "wof:placetype":"venue"
},
  "geometry": {"coordinates":[-78.782645,40.347765],"type":"Point"}
}