{
  "type": "Feature",
  "properties": {
    "addr:full":"1243 S Cedar Crest Blvd Allentown PA 18103",
    "addr:housenumber":"1243",
    "addr:postcode":"18103",
    "addr:street":"S Cedar Crest Blvd",
    "iso:country":"US",
    "sg:address":"1243 S Cedar Crest Blvd",
    "sg:city":"Allentown",
    "sg:classifiers":[
        {
            "category":"Health Services",
            "subcategory":"Doctor",
            "type":"Services"
        }
    ],
    "sg:phone":"+1 610 402 9200",
    "sg:postcode":"18103",
    "sg:province":"PA",
    "sg:tags":[
        "physician",
        "surgeon"
    ],
    "wof:name":"Healthworks",
    "wof:placetype":"venue"
},
  "geometry": {"coordinates":[-75.51860600000001,40.567255],"type":"Point"}
}