{
  "type": "Feature",
  "properties": {
    "iso:country":"US",
    "sg:address":"1940 5th Ave",
    "sg:city":"Pittsburgh",
    "sg:classifiers":[
        {
            "category":"Professional",
            "subcategory":"Art Services",
            "type":"Services"
        }
    ],
    "sg:phone":"+1 412 471 2323",
    "sg:postcode":"15219",
    "sg:province":"PA",
    "sg:tags":[
        "design",
        "creative"
    ],
    "sg:website":"www.sohoinvention.com",
    "wof:name":"Soho Invention Inc",
    "wof:placetype":"venue"
},
  "geometry": {"coordinates":[-79.978404,40.43819],"type":"Point"}
}