{
  "type": "Feature",
  "properties": {
    "addr:full":"820 S Market St Elizabethtown PA 17022",
    "addr:housenumber":"820",
    "addr:postcode":"17022",
    "addr:street":"S Market St",
    "iso:country":"US",
    "sg:address":"820 S Market St",
    "sg:city":"Elizabethtown",
    "sg:classifiers":[
        {
            "category":"Banks & Credit Unions",
            "subcategory":"Bank",
            "type":"Services"
        }
    ],
    "sg:phone":"+1 717 367 8973",
    "sg:postcode":"17022",
    "sg:province":"PA",
    "sg:tags":[
        "commercial",
        "saving"
    ],
    "sg:website":"http://www.sovereignbank.com",
    "wof:name":"Sovereign Bank",
    "wof:placetype":"venue"
},
  "geometry": {"coordinates":[-76.598381,40.143991],"type":"Point"}
}