{
  "type": "Feature",
  "properties": {
    "addr:full":"346 Meadowview Dr Collegeville PA 19426",
    "addr:housenumber":"346",
    "addr:postcode":"19426",
    "addr:street":"Meadowview Dr",
    "iso:country":"US",
    "sg:address":"346 Meadowview Dr",
    "sg:city":"Collegeville",
    "sg:classifiers":[
        {
            "category":"Professional",
            "subcategory":"Management & Consulting",
            "type":"Services"
        }
    ],
    "sg:phone":"+1 610 409 9081",
    "sg:postcode":"19426",
    "sg:province":"PA",
    "sg:tags":[
        "consultant",
        "publishing"
    ],
    "wof:name":"Wagner Publishing",
    "wof:placetype":"venue"
},
  "geometry": {"coordinates":[-75.49383400000001,40.198026],"type":"Point"}
}