{
  "type": "Feature",
  "properties": {
    "iso:country":"US",
    "sg:address":"408 N Allison St",
    "sg:city":"Greencastle",
    "sg:classifiers":[
        {
            "category":"Organizations",
            "subcategory":"Membership Organization",
            "type":"Services"
        }
    ],
    "sg:phone":"+1   ",
    "sg:postcode":"17225",
    "sg:province":"PA",
    "wof:name":"Greencastle Area Arts Council",
    "wof:placetype":"venue"
},
  "geometry": {"coordinates":[-77.721937,39.793888],"type":"Point"}
}