{
  "type": "Feature",
  "properties": {
    "iso:country":"US",
    "sg:address":"2447 N 54th St",
    "sg:city":"Philadelphia",
    "sg:classifiers":[
        {
            "category":"Professional",
            "subcategory":"Management & Consulting",
            "type":"Services"
        }
    ],
    "sg:phone":"+1 215 397 4176",
    "sg:postcode":"19131",
    "sg:province":"PA",
    "sg:tags":[
        "science",
        "consultant",
        "academic"
    ],
    "wof:name":"Cdc Consulting Philadelphia",
    "wof:placetype":"venue"
},
  "geometry": {"coordinates":[-75.23401800000001,39.994869],"type":"Point"}
}