{
  "type": "Feature",
  "properties": {
    "addr:full":"4375 Druck Valley Rd York PA 17406",
    "addr:postcode":"4375;17406",
    "addr:street":"Druck Valley Rd",
    "iso:country":"US",
    "sg:address":"4375 Druck Valley Rd",
    "sg:city":"York",
    "sg:classifiers":[
        {
            "category":"Building & Trades",
            "subcategory":"Construction",
            "type":"Services"
        }
    ],
    "sg:phone":"+1   ",
    "sg:postcode":"17406",
    "sg:province":"PA",
    "sg:tags":[
        "residential"
    ],
    "wof:name":"D & R Builders",
    "wof:placetype":"venue"
},
  "geometry": {"coordinates":[-76.64605299999999,40.020472],"type":"Point"}
}