{
  "type": "Feature",
  "properties": {
    "iso:country":"US",
    "sg:address":"5313 W Thompson St",
    "sg:city":"Philadelphia",
    "sg:classifiers":[
        {
            "category":"Personal",
            "subcategory":"Beauty Salon",
            "type":"Services"
        }
    ],
    "sg:phone":"+1 215 877 9667",
    "sg:postcode":"19131",
    "sg:province":"PA",
    "sg:tags":[
        "shop"
    ],
    "wof:name":"Blessed Hairtage Beauty Center",
    "wof:placetype":"venue"
},
  "geometry": {"coordinates":[-75.22889499999999,39.972738],"type":"Point"}
}