{
  "type": "Feature",
  "properties": {
    "iso:country":"US",
    "sg:address":"203 N Broad St",
    "sg:city":"Ridgway",
    "sg:classifiers":[
        {
            "category":"Autos & Motor Vehicles",
            "subcategory":"Fuel & Gas Station",
            "type":"Retail Goods"
        }
    ],
    "sg:phone":"+1   ",
    "sg:postcode":"15853",
    "sg:province":"PA",
    "sg:tags":[
        "station",
        "gasoline"
    ],
    "wof:name":"Barnetts Auto Service",
    "wof:placetype":"venue"
},
  "geometry": {"coordinates":[-78.73205900000001,41.425606],"type":"Point"}
}