{
  "type": "Feature",
  "properties": {
    "iso:country":"US",
    "sg:address":"2915 Whiteford Rd",
    "sg:city":"York",
    "sg:classifiers":[
        {
            "category":"Home & Garden",
            "subcategory":"Furniture",
            "type":"Retail Goods"
        }
    ],
    "sg:phone":"+1 717 757 3818",
    "sg:postcode":"17402",
    "sg:province":"PA",
    "sg:tags":[
        "mattress"
    ],
    "wof:name":"Mattress Warehouse",
    "wof:placetype":"venue"
},
  "geometry": {"coordinates":[-76.675566,39.98744],"type":"Point"}
}