{
  "type": "Feature",
  "properties": {
    "iso:country":"US",
    "sg:address":"262 Allegheny St",
    "sg:city":"Jersey Shore",
    "sg:classifiers":[
        {
            "category":"Insurance",
            "subcategory":"Insurance Agent",
            "type":"Services"
        }
    ],
    "sg:phone":"+1 570 398 1411",
    "sg:postcode":"17740",
    "sg:province":"PA",
    "wof:name":"Richard R Motter Agency",
    "wof:placetype":"venue"
},
  "geometry": {"coordinates":[-77.255878,41.202926],"type":"Point"}
}