{
  "type": "Feature",
  "properties": {
    "addr:full":"1 Maple Hollow Rd Duncansville PA 16635",
    "addr:housenumber":"1",
    "addr:postcode":"16635",
    "addr:street":"Maple Hollow Rd",
    "iso:country":"US",
    "sg:address":"1 Maple Hollow Rd",
    "sg:city":"Duncansville",
    "sg:classifiers":[
        {
            "category":"Real Estate",
            "subcategory":"Real Estate Operator",
            "type":"Services"
        }
    ],
    "sg:phone":"+1 814 695 6601",
    "sg:postcode":"16635",
    "sg:province":"PA",
    "sg:tags":[
        "apartment"
    ],
    "wof:name":"Maple Hollow Townhouses",
    "wof:placetype":"venue"
},
  "geometry": {"coordinates":[-78.45744500000001,40.431582],"type":"Point"}
}