{
  "type": "Feature",
  "properties": {
    "iso:country":"US",
    "sg:address":"1689 Fillmore St",
    "sg:city":"Philadelphia",
    "sg:classifiers":[
        {
            "category":"Autos & Motor Vehicles",
            "subcategory":"Automobile Sales",
            "type":"Retail Goods"
        }
    ],
    "sg:phone":"+1 215 743 2700",
    "sg:postcode":"19124",
    "sg:province":"PA",
    "sg:tags":[
        "limo"
    ],
    "wof:name":"Frankford Limousineservice",
    "wof:placetype":"venue"
},
  "geometry": {"coordinates":[-75.079399,40.0173],"type":"Point"}
}