{
  "type": "Feature",
  "properties": {
    "iso:country":"US",
    "sg:address":"538 E Market St",
    "sg:city":"York",
    "sg:classifiers":[
        {
            "category":"Retail",
            "subcategory":"Auto Repair",
            "type":"Services"
        }
    ],
    "sg:phone":"+1 717 848 5007",
    "sg:postcode":"17403",
    "sg:province":"PA",
    "sg:tags":[
        "repairing",
        "automobile",
        "radiator"
    ],
    "wof:name":"K & W Auto Radiator",
    "wof:placetype":"venue"
},
  "geometry": {"coordinates":[-76.71601099999999,39.966204],"type":"Point"}
}