{
  "type": "Feature",
  "properties": {
    "addr:full":"1619 E Passyunk Ave Philadelphia PA 19148",
    "addr:housenumber":"1619",
    "addr:postcode":"19148",
    "addr:street":"E Passyunk Ave",
    "iso:country":"US",
    "sg:address":"1619 E Passyunk Ave",
    "sg:city":"Philadelphia",
    "sg:classifiers":[
        {
            "category":"Shopping",
            "subcategory":"Music",
            "type":"Retail Goods"
        }
    ],
    "sg:phone":"+1 215 467 0401",
    "sg:postcode":"19148",
    "sg:province":"PA",
    "sg:tags":[
        "record",
        "vinyl",
        "dvd's"
    ],
    "wof:name":"Beautiful World Syndicate",
    "wof:placetype":"venue"
},
  "geometry": {"coordinates":[-75.163774,39.929643],"type":"Point"}
}