{
  "type": "Feature",
  "properties": {
    "iso:country":"US",
    "sg:address":"213 Market St",
    "sg:city":"Harrisburg",
    "sg:classifiers":[
        {
            "category":"Professional",
            "subcategory":"Lawyer & Legal Services",
            "type":"Services"
        }
    ],
    "sg:phone":"+1 717 237 6091",
    "sg:postcode":"17101",
    "sg:province":"PA",
    "sg:tags":[
        "attorney"
    ],
    "wof:name":"Ursula R Siverling",
    "wof:placetype":"venue"
},
  "geometry": {"coordinates":[-76.88073199999999,40.260844],"type":"Point"}
}