{
  "type": "Feature",
  "properties": {
    "addr:full":"389 Brush Creek Rd Rochester PA 15086",
    "addr:housenumber":"389",
    "addr:postcode":"15086",
    "addr:street":"Brush Creek Rd",
    "iso:country":"US",
    "sg:address":"389 Brush Creek Rd",
    "sg:city":"Rochester",
    "sg:classifiers":[
        {
            "category":"Wholesale",
            "subcategory":"Auto Parts",
            "type":"Manufacturing & Wholesale Goods"
        }
    ],
    "sg:phone":"+1   ",
    "sg:postcode":"15086",
    "sg:province":"PA",
    "sg:tags":[
        "used"
    ],
    "wof:name":"Novak Auto Parts",
    "wof:placetype":"venue"
},
  "geometry": {"coordinates":[-80.11417299999999,40.672854],"type":"Point"}
}