{
  "type": "Feature",
  "properties": {
    "addr:full":"401 N 52nd St Philadelphia PA 19139",
    "addr:housenumber":"401",
    "addr:postcode":"19139",
    "addr:street":"N 52Nd St",
    "iso:country":"US",
    "sg:address":"401 N 52nd St",
    "sg:city":"Philadelphia",
    "sg:classifiers":[
        {
            "category":"Place Of Worship",
            "subcategory":"Church",
            "type":"Public Place"
        },
        {
            "category":"Place Of Worship",
            "type":"Public Place"
        }
    ],
    "sg:phone":"+1 215 477 4412",
    "sg:postcode":"19139",
    "sg:province":"PA",
    "sg:tags":[
        "churches-pentecostal-independent",
        "churches-pentecostal"
    ],
    "sg:website":"http://www.odmtlc.org",
    "wof:name":"Gates Of Heaven",
    "wof:placetype":"venue"
},
  "geometry": {"coordinates":[-75.22492200000001,39.966648],"type":"Point"}
}