{
  "type": "Feature",
  "properties": {
    "addr:full":"2030 Lehigh St Easton PA 18042",
    "addr:housenumber":"2030",
    "addr:postcode":"18042",
    "addr:street":"Lehigh St",
    "iso:country":"US",
    "sg:address":"2030 Lehigh St",
    "sg:city":"Easton",
    "sg:classifiers":[
        {
            "category":"Real Estate",
            "subcategory":"Real Estate Operator",
            "type":"Services"
        }
    ],
    "sg:phone":"+1 610 253 7119",
    "sg:postcode":"18042",
    "sg:province":"PA",
    "sg:tags":[
        "apartment"
    ],
    "wof:name":"Lafayette Towers Apartments",
    "wof:placetype":"venue"
},
  "geometry": {"coordinates":[-75.24237599999999,40.686603],"type":"Point"}
}