{
  "type": "Feature",
  "properties": {
    "iso:country":"US",
    "sg:address":"3440 Lehigh St",
    "sg:city":"Allentown",
    "sg:classifiers":[
        {
            "category":"Professional",
            "subcategory":"Lawyer & Legal Services",
            "type":"Services"
        },
        {
            "category":"Professional",
            "subcategory":"Printing & Photocopies",
            "type":"Services"
        }
    ],
    "sg:phone":"+1 610 966 4255",
    "sg:postcode":"18103",
    "sg:province":"PA",
    "sg:tags":[
        "notary"
    ],
    "sg:website":"www.mbe.com",
    "wof:name":"Mail Boxes Et Cetera",
    "wof:placetype":"venue"
},
  "geometry": {"coordinates":[-75.491501,40.551498],"type":"Point"}
}