{
  "type": "Feature",
  "properties": {
    "iso:country":"US",
    "sg:address":"64 Camp Horne Rd",
    "sg:city":"Pittsburgh",
    "sg:classifiers":[
        {
            "category":"Autos & Motor Vehicles",
            "subcategory":"Automobile Sales",
            "type":"Retail Goods"
        }
    ],
    "sg:phone":"+1 412 613 7129",
    "sg:postcode":"15202",
    "sg:province":"PA",
    "sg:tags":[
        "car",
        "dealer"
    ],
    "wof:name":"Craig North Auto Sales Inc",
    "wof:placetype":"venue"
},
  "geometry": {"coordinates":[-80.094021,40.511538],"type":"Point"}
}