{
  "type": "Feature",
  "properties": {
    "addr:full":"6064 Ogontz Ave Philadelphia PA 19141",
    "addr:housenumber":"6064",
    "addr:postcode":"19141",
    "addr:street":"Ogontz Ave",
    "iso:country":"US",
    "sg:address":"6064 Ogontz Ave",
    "sg:city":"Philadelphia",
    "sg:classifiers":[
        {
            "category":"Health Services",
            "subcategory":"Chiropractor",
            "type":"Services"
        }
    ],
    "sg:phone":"+1 215 751 9650",
    "sg:postcode":"19141",
    "sg:province":"PA",
    "wof:name":"Thomas G Lee DC",
    "wof:placetype":"venue"
},
  "geometry": {"coordinates":[-75.15099499999999,40.04808],"type":"Point"}
}