{
  "type": "Feature",
  "properties": {
    "iso:country":"US",
    "sg:address":"315 W High St",
    "sg:city":"Bellefonte",
    "sg:classifiers":[
        {
            "category":"Restaurant",
            "type":"Food & Drink"
        }
    ],
    "sg:phone":"+1 814 355 4230",
    "sg:postcode":"16823",
    "sg:province":"PA",
    "sg:tags":[
        "drinking",
        "eating"
    ],
    "wof:name":"Schnitzels Tavern",
    "wof:placetype":"venue"
},
  "geometry": {"coordinates":[-77.780643,40.911484],"type":"Point"}
}