{
  "type": "Feature",
  "properties": {
    "iso:country":"US",
    "sg:address":"1515 Kathryn St",
    "sg:city":"New Cumberland",
    "sg:classifiers":[
        {
            "category":"Manufacturing",
            "subcategory":"Printing",
            "type":"Manufacturing & Wholesale Goods"
        }
    ],
    "sg:phone":"+1 717 774 7152",
    "sg:postcode":"17070",
    "sg:province":"PA",
    "sg:tags":[
        "commercial"
    ],
    "wof:name":"Kirsch's Printing Inc",
    "wof:placetype":"venue"
},
  "geometry": {"coordinates":[-76.874583,40.237759],"type":"Point"}
}