{
  "type": "Feature",
  "properties": {
    "iso:country":"US",
    "sg:address":"4575 W Tilghman St",
    "sg:city":"Allentown",
    "sg:classifiers":[
        {
            "category":"Education",
            "subcategory":"Dance Studio",
            "type":"Public Place"
        }
    ],
    "sg:phone":"+1 610 395 6060",
    "sg:postcode":"18104",
    "sg:province":"PA",
    "sg:tags":[
        "performing",
        "art"
    ],
    "wof:name":"Accent School of Dance",
    "wof:placetype":"venue"
},
  "geometry": {"coordinates":[-75.557301,40.589551],"type":"Point"}
}