{
  "type": "Feature",
  "properties": {
    "iso:country":"US",
    "sg:address":"790 Tree Ln",
    "sg:city":"West Chester",
    "sg:classifiers":[
        {
            "category":"Professional",
            "subcategory":"Lawyer & Legal Services",
            "type":"Services"
        }
    ],
    "sg:phone":"+1 610 431 9467",
    "sg:postcode":"19380",
    "sg:province":"PA",
    "sg:tags":[
        "attorney"
    ],
    "wof:name":"John J Breen Law Offices",
    "wof:placetype":"venue"
},
  "geometry": {"coordinates":[-75.638819,39.973663],"type":"Point"}
}