{
  "type": "Feature",
  "properties": {
    "iso:country":"US",
    "sg:address":"297 Long Ln",
    "sg:city":"Oley",
    "sg:classifiers":[
        {
            "category":"Retail",
            "subcategory":"Repair Shop",
            "type":"Services"
        }
    ],
    "sg:phone":"+1 610 987 3838",
    "sg:postcode":"19547",
    "sg:province":"PA",
    "sg:tags":[
        "taxidermist"
    ],
    "wof:name":"Moyer's Taxidermy",
    "wof:placetype":"venue"
},
  "geometry": {"coordinates":[-75.693832,40.429899],"type":"Point"}
}