{
  "type": "Feature",
  "properties": {
    "iso:country":"US",
    "sg:address":"253 Pike St",
    "sg:city":"Carbondale",
    "sg:classifiers":[
        {
            "category":"Organizations",
            "subcategory":"Membership Organization",
            "type":"Services"
        }
    ],
    "sg:phone":"+1   ",
    "sg:postcode":"18407",
    "sg:province":"PA",
    "wof:name":"Northeast Chld Fishing Derby",
    "wof:placetype":"venue"
},
  "geometry": {"coordinates":[-75.516942,41.563666],"type":"Point"}
}