{
  "type": "Feature",
  "properties": {
    "addr:full":"33 Hood St Chambersburg PA 17201",
    "addr:housenumber":"33",
    "addr:postcode":"17201",
    "addr:street":"Hood St",
    "iso:country":"US",
    "sg:address":"33 Hood St",
    "sg:city":"Chambersburg",
    "sg:classifiers":[
        {
            "category":"Home & Garden",
            "subcategory":"Building Materials",
            "type":"Retail Goods"
        }
    ],
    "sg:phone":"+1 717 264 0733",
    "sg:postcode":"17201",
    "sg:province":"PA",
    "wof:name":"Fogal Glassworks",
    "wof:placetype":"venue"
},
  "geometry": {"coordinates":[-77.66383500000001,39.938129],"type":"Point"}
}