{
  "type": "Feature",
  "properties": {
    "addr:full":"2846 N Front St Philadelphia PA 19133",
    "addr:housenumber":"2846",
    "addr:postcode":"19133",
    "addr:street":"N Front St",
    "iso:country":"US",
    "sg:address":"2846 N Front St",
    "sg:city":"Philadelphia",
    "sg:classifiers":[
        {
            "category":"Professional",
            "type":"Services"
        }
    ],
    "sg:phone":"+1 215 423 2060",
    "sg:postcode":"19133",
    "sg:province":"PA",
    "sg:tags":[
        "establishment"
    ],
    "wof:name":"Express Autotags",
    "wof:placetype":"venue"
},
  "geometry": {"coordinates":[-75.13043500000001,39.993278],"type":"Point"}
}