{
  "type": "Feature",
  "properties": {
    "iso:country":"US",
    "sg:address":"305 E Northampton St",
    "sg:city":"Wilkes Barre",
    "sg:classifiers":[
        {
            "category":"Professional",
            "type":"Services"
        }
    ],
    "sg:phone":"+1   ",
    "sg:postcode":"18702",
    "sg:province":"PA",
    "wof:name":"Recoverable Assets Inc",
    "wof:placetype":"venue"
},
  "geometry": {"coordinates":[-75.877906,41.237087],"type":"Point"}
}