{
  "type": "Feature",
  "properties": {
    "iso:country":"US",
    "sg:address":"1012 Wood St",
    "sg:city":"Bristol",
    "sg:classifiers":[
        {
            "category":"Utilities",
            "subcategory":"Refuse",
            "type":"Services"
        },
        {
            "category":"Building & Trades",
            "subcategory":"Plumbing",
            "type":"Services"
        }
    ],
    "sg:phone":"+1 215 788 7451",
    "sg:postcode":"19007",
    "sg:province":"PA",
    "sg:tags":[
        "tank",
        "installation",
        "system"
    ],
    "wof:name":"Midouhas Arthur Tank & Oil",
    "wof:placetype":"venue"
},
  "geometry": {"coordinates":[-74.847478,40.101175],"type":"Point"}
}