{
  "type": "Feature",
  "properties": {
    "iso:country":"US",
    "sg:address":"690 Kohler Rd",
    "sg:city":"Kutztown",
    "sg:classifiers":[
        {
            "category":"Shopping",
            "subcategory":"Bicycles & Sporting Goods",
            "type":"Retail Goods"
        }
    ],
    "sg:phone":"+1 610 682 2760",
    "sg:postcode":"19530",
    "sg:province":"PA",
    "sg:tags":[
        "saddlery",
        "equestrian",
        "farm",
        "equipment",
        "harness",
        "dairy",
        "shoes"
    ],
    "wof:name":"Leid Shoes and Saddlery",
    "wof:placetype":"venue"
},
  "geometry": {"coordinates":[-75.733498,40.502136],"type":"Point"}
}