{
  "type": "Feature",
  "properties": {
    "iso:country":"US",
    "sg:address":"7239 Ogontz Ave",
    "sg:city":"Philadelphia",
    "sg:classifiers":[
        {
            "category":"Personal",
            "subcategory":"Beauty Salon",
            "type":"Services"
        }
    ],
    "sg:phone":"+1 215 424 7690",
    "sg:postcode":"19138",
    "sg:province":"PA",
    "wof:name":"Lucille's Beauty Salon",
    "wof:placetype":"venue"
},
  "geometry": {"coordinates":[-75.15400200000001,40.064503],"type":"Point"}
}