{
  "type": "Feature",
  "properties": {
    "iso:country":"US",
    "sg:address":"201 Hickory St",
    "sg:city":"Warren",
    "sg:classifiers":[
        {
            "category":"Autos & Motor Vehicles",
            "subcategory":"Fuel & Gas Station",
            "type":"Retail Goods"
        }
    ],
    "sg:phone":"+1 814 726 1652",
    "sg:postcode":"16365",
    "sg:province":"PA",
    "sg:tags":[
        "grocery",
        "gasoline"
    ],
    "wof:name":"Kwik - Fill",
    "wof:placetype":"venue"
},
  "geometry": {"coordinates":[-79.149545,41.845721],"type":"Point"}
}