{
  "type": "Feature",
  "properties": {
    "addr:full":"400 S 4th St Philipsburg PA 16866",
    "addr:housenumber":"400",
    "addr:postcode":"16866",
    "addr:street":"S 4Th St",
    "iso:country":"US",
    "sg:address":"400 S 4th St",
    "sg:city":"Philipsburg",
    "sg:classifiers":[
        {
            "category":"Organizations",
            "subcategory":"Religious Organization",
            "type":"Services"
        }
    ],
    "sg:phone":"+1 814 342 1700",
    "sg:postcode":"16866",
    "sg:province":"PA",
    "sg:tags":[
        "church"
    ],
    "wof:name":"St Peter & Paul Catholic Chrch",
    "wof:placetype":"venue"
},
  "geometry": {"coordinates":[-78.216686,40.893466],"type":"Point"}
}