{
  "type": "Feature",
  "properties": {
    "iso:country":"US",
    "sg:address":"2730 N 5th St",
    "sg:city":"Philadelphia",
    "sg:classifiers":[
        {
            "category":"Shopping",
            "subcategory":"Jewelry",
            "type":"Retail Goods"
        }
    ],
    "sg:phone":"+1   ",
    "sg:postcode":"19133",
    "sg:province":"PA",
    "wof:name":"Johns Jeweller",
    "wof:placetype":"venue"
},
  "geometry": {"coordinates":[-75.140006,39.993199],"type":"Point"}
}