{
  "type": "Feature",
  "properties": {
    "addr:full":"69 Romeo Ln Uniontown PA 15401",
    "addr:housenumber":"69",
    "addr:postcode":"15401",
    "addr:street":"Romeo Ln",
    "iso:country":"US",
    "sg:address":"69 Romeo Ln",
    "sg:city":"Uniontown",
    "sg:classifiers":[
        {
            "category":"Autos & Motor Vehicles",
            "subcategory":"Motorcycle Sales",
            "type":"Retail Goods"
        }
    ],
    "sg:phone":"+1 724 439 8888",
    "sg:postcode":"15401",
    "sg:province":"PA",
    "sg:tags":[
        "scooter"
    ],
    "wof:name":"Cerini's National Rd Harley",
    "wof:placetype":"venue"
},
  "geometry": {"coordinates":[-79.72483,39.915395],"type":"Point"}
}