{
  "type": "Feature",
  "properties": {
    "iso:country":"US",
    "sg:address":"1500 N George St",
    "sg:city":"York",
    "sg:classifiers":[
        {
            "category":"Food & Beverages",
            "subcategory":"Groceries & Convenience Stores",
            "type":"Retail Goods"
        }
    ],
    "sg:phone":"+1 717 848 6060",
    "sg:postcode":"17404",
    "sg:province":"PA",
    "sg:tags":[
        "super",
        "supermarket"
    ],
    "sg:website":"http://www.weis.com",
    "wof:name":"Weis Markets",
    "wof:placetype":"venue"
},
  "geometry": {"coordinates":[-76.734489,39.98233],"type":"Point"}
}