{
  "type": "Feature",
  "properties": {
    "iso:country":"US",
    "sg:address":"680 Pont Reading Rd",
    "sg:city":"Ardmore",
    "sg:classifiers":[
        {
            "category":"Retail",
            "subcategory":"Repair Shop",
            "type":"Services"
        }
    ],
    "sg:phone":"+1 610 642 2594",
    "sg:postcode":"19003",
    "sg:province":"PA",
    "sg:tags":[
        "lock",
        "locksmith"
    ],
    "wof:name":"Main Line Master Locksmith",
    "wof:placetype":"venue"
},
  "geometry": {"coordinates":[-75.300687,39.998779],"type":"Point"}
}