{
  "type": "Feature",
  "properties": {
    "iso:country":"US",
    "sg:address":"34 Holmgren Ln",
    "sg:city":"Windsor",
    "sg:classifiers":[
        {
            "category":"Professional",
            "subcategory":"Research",
            "type":"Services"
        }
    ],
    "sg:phone":"+1 717 246 4480",
    "sg:postcode":"17366",
    "sg:province":"PA",
    "sg:tags":[
        "analysis",
        "market"
    ],
    "wof:name":"Davis M",
    "wof:placetype":"venue"
},
  "geometry": {"coordinates":[-76.537292,39.928735],"type":"Point"}
}