{
  "type": "Feature",
  "properties": {
    "iso:country":"US",
    "sg:address":"114 Smithfield St",
    "sg:city":"Pittsburgh",
    "sg:classifiers":[
        {
            "category":"Professional",
            "subcategory":"Business Services",
            "type":"Services"
        }
    ],
    "sg:phone":"+1 412 434 0610",
    "sg:postcode":"15222",
    "sg:province":"PA",
    "sg:tags":[
        "legal"
    ],
    "wof:name":"Linda A Cobb",
    "wof:placetype":"venue"
},
  "geometry": {"coordinates":[-80.000152,40.437667],"type":"Point"}
}