{
  "type": "Feature",
  "properties": {
    "addr:full":"685 Knapp Ave Hermitage PA 16148",
    "addr:housenumber":"685",
    "addr:postcode":"16148",
    "addr:street":"Knapp Ave",
    "iso:country":"US",
    "sg:address":"685 Knapp Ave",
    "sg:city":"Hermitage",
    "sg:classifiers":[
        {
            "category":"Building & Trades",
            "subcategory":"Plumbing",
            "type":"Services"
        }
    ],
    "sg:phone":"+1   ",
    "sg:postcode":"16148",
    "sg:province":"PA",
    "sg:tags":[
        "cooling",
        "heating",
        "contractor"
    ],
    "wof:name":"Banjak Heating & Cooling Inc",
    "wof:placetype":"venue"
},
  "geometry": {"coordinates":[-80.48067,41.221289],"type":"Point"}
}