{
  "type": "Feature",
  "properties": {
    "addr:full":"391 Lincoln Hwy W Jeannette PA 15644",
    "addr:housenumber":"391",
    "addr:postcode":"15644",
    "addr:street":"Lincoln Hwy W Jeannette",
    "iso:country":"US",
    "sg:address":"391 Lincoln Hwy W",
    "sg:city":"Jeannette",
    "sg:classifiers":[
        {
            "category":"Personal",
            "type":"Services"
        }
    ],
    "sg:phone":"+1   ",
    "sg:postcode":"15644",
    "sg:province":"PA",
    "wof:name":"Route 30 Health Spa",
    "wof:placetype":"venue"
},
  "geometry": {"coordinates":[-79.65643300000001,40.310244],"type":"Point"}
}