{
  "type": "Feature",
  "properties": {
    "iso:country":"US",
    "sg:address":"17 S Main St",
    "sg:city":"Manheim",
    "sg:classifiers":[
        {
            "category":"Real Estate",
            "subcategory":"Real Estate Agent",
            "type":"Services"
        }
    ],
    "sg:phone":"+1 717 665 3333",
    "sg:postcode":"17545",
    "sg:province":"PA",
    "wof:name":"Robert R Swayne Jr",
    "wof:placetype":"venue"
},
  "geometry": {"coordinates":[-76.394133,40.162956],"type":"Point"}
}