{
  "type": "Feature",
  "properties": {
    "iso:country":"US",
    "sg:address":"1507 Lane Rd",
    "sg:city":"Waterford",
    "sg:classifiers":[
        {
            "category":"Building & Trades",
            "subcategory":"Landscaping Services",
            "type":"Services"
        }
    ],
    "sg:phone":"+1   ",
    "sg:postcode":"16441",
    "sg:province":"PA",
    "wof:name":"Jefferson Tree Service",
    "wof:placetype":"venue"
},
  "geometry": {"coordinates":[-80.029849,41.978753],"type":"Point"}
}