{
  "type": "Feature",
  "properties": {
    "iso:country":"US",
    "sg:address":"265 46th St",
    "sg:city":"Pittsburgh",
    "sg:classifiers":[
        {
            "category":"Real Estate",
            "subcategory":"Real Estate Operator",
            "type":"Services"
        }
    ],
    "sg:phone":"+1   ",
    "sg:postcode":"15201",
    "sg:province":"PA",
    "sg:tags":[
        "building",
        "apartment"
    ],
    "wof:name":"Davison Square Apartments",
    "wof:placetype":"venue"
},
  "geometry": {"coordinates":[-79.95880699999999,40.472818],"type":"Point"}
}