{
  "type": "Feature",
  "properties": {
    "addr:full":"110 Bell Dr Canonsburg PA 15317",
    "addr:housenumber":"110",
    "addr:postcode":"15317",
    "addr:street":"Bell Dr",
    "iso:country":"US",
    "sg:address":"110 Bell Dr",
    "sg:city":"Canonsburg",
    "sg:classifiers":[
        {
            "category":"Education",
            "subcategory":"School",
            "type":"Public Place"
        }
    ],
    "sg:phone":"+1 724 941 8981",
    "sg:postcode":"15317",
    "sg:province":"PA",
    "sg:tags":[
        "high",
        "middle",
        "elementary"
    ],
    "wof:name":"Peters Twp School Dist",
    "wof:placetype":"venue"
},
  "geometry": {"coordinates":[-80.08000800000001,40.282171],"type":"Point"}
}