{
  "type": "Feature",
  "properties": {
    "iso:country":"US",
    "sg:address":"124 Wilmar Dr",
    "sg:city":"Pittsburgh",
    "sg:classifiers":[
        {
            "category":"Health Services",
            "subcategory":"Doctor",
            "type":"Services"
        }
    ],
    "sg:phone":"+1 412 680 3450",
    "sg:postcode":"15238",
    "sg:province":"PA",
    "sg:tags":[
        "physician",
        "surgeon"
    ],
    "wof:name":"Reddy Medical Assoc",
    "wof:placetype":"venue"
},
  "geometry": {"coordinates":[-79.89759100000001,40.539069],"type":"Point"}
}