{
  "type": "Feature",
  "properties": {
    "iso:country":"US",
    "sg:address":"218 N Broad St",
    "sg:city":"Grove City",
    "sg:classifiers":[
        {
            "category":"Arts & Performance",
            "subcategory":"Theater",
            "type":"Entertainment"
        }
    ],
    "sg:phone":"+1 724 458 0132",
    "sg:postcode":"16127",
    "sg:province":"PA",
    "sg:tags":[
        "entertainer"
    ],
    "wof:name":"Amazing Magic By Devin",
    "wof:placetype":"venue"
},
  "geometry": {"coordinates":[-80.083822,41.163636],"type":"Point"}
}