{
  "type": "Feature",
  "properties": {
    "iso:country":"US",
    "sg:address":"602 Summit Ave",
    "sg:city":"Jenkintown",
    "sg:classifiers":[
        {
            "category":"Building & Trades",
            "subcategory":"Construction",
            "type":"Services"
        }
    ],
    "sg:phone":"+1   ",
    "sg:postcode":"19046",
    "sg:province":"PA",
    "sg:tags":[
        "contractor"
    ],
    "wof:name":"McCool Gutter Service",
    "wof:placetype":"venue"
},
  "geometry": {"coordinates":[-75.126741,40.094238],"type":"Point"}
}