{
  "type": "Feature",
  "properties": {
    "iso:country":"US",
    "sg:address":"114 E Washington St",
    "sg:city":"Fleetwood",
    "sg:classifiers":[
        {
            "category":"Professional",
            "type":"Services"
        }
    ],
    "sg:phone":"+1   ",
    "sg:postcode":"19522",
    "sg:province":"PA",
    "wof:name":"Geschwindt Gregg Fleetwood",
    "wof:placetype":"venue"
},
  "geometry": {"coordinates":[-75.81654,40.456174],"type":"Point"}
}