{
  "type": "Feature",
  "properties": {
    "iso:country":"US",
    "sg:address":"1890 Woodhaven Rd",
    "sg:city":"Philadelphia",
    "sg:classifiers":[
        {
            "category":"Professional",
            "type":"Services"
        }
    ],
    "sg:phone":"+1   ",
    "sg:postcode":"19116",
    "sg:province":"PA",
    "wof:name":"Jash & Yash Inc",
    "wof:placetype":"venue"
},
  "geometry": {"coordinates":[-75.00198899999999,40.112323],"type":"Point"}
}