{
  "type": "Feature",
  "properties": {
    "iso:country":"US",
    "sg:address":"355 5th Ave",
    "sg:city":"Pittsburgh",
    "sg:classifiers":[
        {
            "category":"Health Services",
            "subcategory":"Clinic",
            "type":"Services"
        }
    ],
    "sg:phone":"+1 412 721 1430",
    "sg:postcode":"15222",
    "sg:province":"PA",
    "sg:tags":[
        "medical"
    ],
    "sg:website":"http://www.liceremovalcenter.com",
    "wof:name":"Lice Removal Clinic",
    "wof:placetype":"venue"
},
  "geometry": {"coordinates":[-79.99941800000001,40.440367],"type":"Point"}
}