{
  "type": "Feature",
  "properties": {
    "iso:country":"US",
    "sg:address":"811 3rd Ave",
    "sg:city":"New Brighton",
    "sg:classifiers":[
        {
            "category":"Personal",
            "type":"Services"
        }
    ],
    "sg:phone":"+1 724 847 9455",
    "sg:postcode":"15066",
    "sg:province":"PA",
    "sg:tags":[
        "salon",
        "tanning"
    ],
    "wof:name":"Caribbean Cruz Tanning Salon",
    "wof:placetype":"venue"
},
  "geometry": {"coordinates":[-80.314104,40.735065],"type":"Point"}
}