{
  "type": "Feature",
  "properties": {
    "iso:country":"US",
    "sg:address":"241 W Pine St",
    "sg:city":"Grove City",
    "sg:classifiers":[
        {
            "category":"Health Services",
            "subcategory":"Doctor",
            "type":"Services"
        }
    ],
    "sg:phone":"+1 724 458 8770",
    "sg:postcode":"16127",
    "sg:province":"PA",
    "sg:tags":[
        "dentist"
    ],
    "wof:name":"Eugene D Campagna Jr DDS",
    "wof:placetype":"venue"
},
  "geometry": {"coordinates":[-80.089214,41.159676],"type":"Point"}
}