{
  "type": "Feature",
  "properties": {
    "iso:country":"US",
    "sg:address":"6053 Allentown Blvd",
    "sg:city":"Harrisburg",
    "sg:classifiers":[
        {
            "category":"Restaurant",
            "type":"Food & Drink"
        }
    ],
    "sg:menulink":"http://www.allmenus.com/pa/lower-paxton/28062-great-wall-chinese-restaurant/menu/",
    "sg:phone":"+1 717 540 1100",
    "sg:postcode":"17112",
    "sg:province":"PA",
    "sg:tags":[
        "asian",
        "chinese"
    ],
    "wof:name":"Great Wall Chinese Restaurant",
    "wof:placetype":"venue"
},
  "geometry": {"coordinates":[-76.78828300000001,40.32255],"type":"Point"}
}