{
  "type": "Feature",
  "properties": {
    "addr:full":"785 Ave B Reading PA 19601",
    "addr:housenumber":"785",
    "addr:postcode":"19601",
    "addr:street":"Ave B",
    "iso:country":"US",
    "sg:address":"785 Ave B",
    "sg:city":"Reading",
    "sg:classifiers":[
        {
            "category":"Real Estate",
            "subcategory":"Real Estate Operator",
            "type":"Services"
        }
    ],
    "sg:phone":"+1 610 374 6500",
    "sg:postcode":"19601",
    "sg:province":"PA",
    "sg:tags":[
        "apartment"
    ],
    "wof:name":"Court Street Commons Apartment",
    "wof:placetype":"venue"
},
  "geometry": {"coordinates":[-75.944174,40.355381],"type":"Point"}
}