{
  "type": "Feature",
  "properties": {
    "iso:country":"US",
    "sg:address":"4900 Brown Ln",
    "sg:city":"Hellam",
    "sg:classifiers":[
        {
            "category":"Farming",
            "subcategory":"Farm",
            "type":"Manufacturing & Wholesale Goods"
        }
    ],
    "sg:phone":"+1 717 840 7878",
    "sg:postcode":"17406",
    "sg:province":"PA",
    "wof:name":"Dave Adcock",
    "wof:placetype":"venue"
},
  "geometry": {"coordinates":[-76.614113,40.019741],"type":"Point"}
}