{
  "type": "Feature",
  "properties": {
    "iso:country":"US",
    "sg:address":"2003 W Norris St",
    "sg:city":"Philadelphia",
    "sg:classifiers":[
        {
            "category":"Organizations",
            "subcategory":"Religious Organization",
            "type":"Services"
        }
    ],
    "sg:phone":"+1 215 763 8806",
    "sg:postcode":"19121",
    "sg:province":"PA",
    "wof:name":"New Jerusamlem Now",
    "wof:placetype":"venue"
},
  "geometry": {"coordinates":[-75.16656,39.984429],"type":"Point"}
}