{
  "type": "Feature",
  "properties": {
    "iso:country":"US",
    "sg:address":"160 US Hwy 209",
    "sg:city":"Matamoras",
    "sg:classifiers":[
        {
            "category":"Utilities",
            "subcategory":"Natural Gas",
            "type":"Services"
        }
    ],
    "sg:phone":"+1 570 491 0065",
    "sg:postcode":"18336",
    "sg:province":"PA",
    "sg:tags":[
        "company"
    ],
    "wof:name":"Tri State Gas Inc",
    "wof:placetype":"venue"
},
  "geometry": {"coordinates":[-74.69892400000001,41.369813],"type":"Point"}
}