{
  "type": "Feature",
  "properties": {
    "iso:country":"US",
    "sg:address":"4615 Lorigan St",
    "sg:city":"Pittsburgh",
    "sg:classifiers":[
        {
            "category":"Restaurant",
            "type":"Food & Drink"
        }
    ],
    "sg:phone":"+1   ",
    "sg:postcode":"15224",
    "sg:province":"PA",
    "sg:tags":[
        "eating"
    ],
    "wof:name":"Bloomfield Italian Ind CLB",
    "wof:placetype":"venue"
},
  "geometry": {"coordinates":[-79.95229399999999,40.459092],"type":"Point"}
}