{
  "type": "Feature",
  "properties": {
    "iso:country":"US",
    "sg:address":"480 S. Broad Street",
    "sg:city":"Philadelphia",
    "sg:classifiers":[
        {
            "category":"Arts & Performance",
            "subcategory":"Arts Center",
            "type":"Entertainment"
        },
        {
            "category":"Cinema",
            "subcategory":"Movie Theater",
            "type":"Entertainment"
        },
        {
            "category":"Arts & Performance",
            "subcategory":"Theater",
            "type":"Entertainment"
        }
    ],
    "sg:phone":"+1 215 985 0420",
    "sg:postcode":"19146",
    "sg:province":"PA",
    "sg:tags":[
        "theatres-concert",
        "performing",
        "venue",
        "hall",
        "theatre"
    ],
    "sg:website":"www.philadelphiatheatrecompany.org/",
    "wof:name":"Philadelphia Theatre Company",
    "wof:placetype":"venue"
},
  "geometry": {"coordinates":[-75.16524,39.944841],"type":"Point"}
}