{
  "type": "Feature",
  "properties": {
    "iso:country":"US",
    "sg:address":"210 Grant St",
    "sg:city":"Pittsburgh",
    "sg:classifiers":[
        {
            "category":"Professional",
            "subcategory":"Lawyer & Legal Services",
            "type":"Services"
        }
    ],
    "sg:phone":"+1 724 225 5543",
    "sg:postcode":"15219",
    "sg:province":"PA",
    "sg:tags":[
        "attorney"
    ],
    "wof:name":"Joyce & Bittner",
    "wof:placetype":"venue"
},
  "geometry": {"coordinates":[-79.998497,40.437099],"type":"Point"}
}