{
  "type": "Feature",
  "properties": {
    "iso:country":"US",
    "sg:address":"3166 Hulmeville Rd",
    "sg:city":"Bensalem",
    "sg:classifiers":[
        {
            "category":"Personal",
            "subcategory":"Barber",
            "type":"Services"
        }
    ],
    "sg:phone":"+1 215 639 3840",
    "sg:postcode":"19020",
    "sg:province":"PA",
    "wof:name":"Chets Barber Stylist",
    "wof:placetype":"venue"
},
  "geometry": {"coordinates":[-74.94430199999999,40.09687],"type":"Point"}
}