{
  "type": "Feature",
  "properties": {
    "iso:country":"US",
    "sg:address":"1199 Jacks Run Rd",
    "sg:city":"North Versailles",
    "sg:classifiers":[
        {
            "category":"Retail",
            "subcategory":"Car Wash",
            "type":"Services"
        }
    ],
    "sg:phone":"+1 412 829 9969",
    "sg:postcode":"15137",
    "sg:province":"PA",
    "sg:tags":[
        "automobile",
        "detail",
        "clean"
    ],
    "wof:name":"Detail Shop",
    "wof:placetype":"venue"
},
  "geometry": {"coordinates":[-79.785015,40.363007],"type":"Point"}
}