{
  "type": "Feature",
  "properties": {
    "iso:country":"US",
    "sg:address":"100 Bayer Rd",
    "sg:city":"Pittsburgh",
    "sg:classifiers":[
        {
            "category":"Government",
            "subcategory":"Office",
            "type":"Public Place"
        }
    ],
    "sg:phone":"+1 412 787 3078",
    "sg:postcode":"15205",
    "sg:province":"PA",
    "sg:tags":[
        "federal",
        "affairs"
    ],
    "wof:name":"Nicaraguan General Consul",
    "wof:placetype":"venue"
},
  "geometry": {"coordinates":[-80.165452,40.443252],"type":"Point"}
}