{
  "type": "Feature",
  "properties": {
    "addr:full":"810 Bristol Pike Bristol PA 19007",
    "addr:housenumber":"810",
    "addr:postcode":"19007",
    "addr:street":"Bristol Pike",
    "iso:country":"US",
    "sg:address":"810 Bristol Pike",
    "sg:city":"Bristol",
    "sg:classifiers":[
        {
            "category":"Bars & Pubs",
            "type":"Food & Drink"
        }
    ],
    "sg:phone":"+1 215 785 1111",
    "sg:postcode":"19007",
    "sg:province":"PA",
    "sg:tags":[
        "tavern"
    ],
    "wof:name":"Three Monkeys",
    "wof:placetype":"venue"
},
  "geometry": {"coordinates":[-74.87194100000001,40.099041],"type":"Point"}
}