{
  "type": "Feature",
  "properties": {
    "addr:full":"2613 Brodhead Rd Aliquippa PA 15001",
    "addr:postcode":"2613;15001",
    "addr:street":"Brodhead Rd",
    "iso:country":"US",
    "sg:address":"2613 Brodhead Rd",
    "sg:city":"Aliquippa",
    "sg:classifiers":[
        {
            "category":"Autos & Motor Vehicles",
            "subcategory":"Auto Supplies",
            "type":"Retail Goods"
        }
    ],
    "sg:phone":"+1 724 375 3005",
    "sg:postcode":"15001",
    "sg:province":"PA",
    "wof:name":"Carquest Auto Parts",
    "wof:placetype":"venue"
},
  "geometry": {"coordinates":[-80.257948,40.581424],"type":"Point"}
}