{
  "type": "Feature",
  "properties": {
    "iso:country":"US",
    "sg:address":"2390 River Rd",
    "sg:city":"Ellwood City",
    "sg:classifiers":[
        {
            "category":"Social Services",
            "subcategory":"Child Care",
            "type":"Services"
        }
    ],
    "sg:phone":"+1 724 752 0430",
    "sg:postcode":"16117",
    "sg:province":"PA",
    "wof:name":"Christina L Hoffmeier",
    "wof:placetype":"venue"
},
  "geometry": {"coordinates":[-80.312839,40.844743],"type":"Point"}
}