{
  "type": "Feature",
  "properties": {
    "addr:full":"4365 Molly Pitcher Hwy Chambersburg PA 17201",
    "addr:housenumber":"4365",
    "addr:postcode":"17201",
    "addr:street":"Molly Pitcher Hwy",
    "iso:country":"US",
    "sg:address":"4365 Molly Pitcher Hwy",
    "sg:city":"Chambersburg",
    "sg:classifiers":[
        {
            "category":"Social Services",
            "subcategory":"Child Care",
            "type":"Services"
        }
    ],
    "sg:phone":"+1 717 375 2214",
    "sg:postcode":"17201",
    "sg:province":"PA",
    "sg:tags":[
        "kindergarten",
        "academic",
        "school"
    ],
    "wof:name":"Growing Tree",
    "wof:placetype":"venue"
},
  "geometry": {"coordinates":[-77.688924,39.87216],"type":"Point"}
}