{
  "type": "Feature",
  "properties": {
    "addr:full":"490 N Trooper Rd Norristown PA 19403",
    "addr:housenumber":"490",
    "addr:postcode":"19403",
    "addr:street":"N Trooper Rd",
    "iso:country":"US",
    "sg:address":"490 N Trooper Rd",
    "sg:city":"Norristown",
    "sg:classifiers":[
        {
            "category":"Social Services",
            "subcategory":"Child Care",
            "type":"Services"
        },
        {
            "category":"Education",
            "subcategory":"Preschool",
            "type":"Public Place"
        },
        {
            "category":"Education",
            "subcategory":"School",
            "type":"Public Place"
        }
    ],
    "sg:phone":"+1 610 635 1700",
    "sg:postcode":"19403",
    "sg:province":"PA",
    "sg:tags":[
        "elementary",
        "day"
    ],
    "sg:website":"www.malvernschool.com",
    "wof:name":"Malvern School the",
    "wof:placetype":"venue"
},
  "geometry": {"coordinates":[-75.378998,40.152699],"type":"Point"}
}