{
  "type": "Feature",
  "properties": {
    "iso:country":"US",
    "sg:address":"1533 Ridge Ave",
    "sg:city":"Philadelphia",
    "sg:classifiers":[
        {
            "category":"Arts & Performance",
            "subcategory":"Art Gallery",
            "type":"Entertainment"
        },
        {
            "category":"Arts & Performance",
            "subcategory":"Music",
            "type":"Entertainment"
        }
    ],
    "sg:phone":"+1 215 765 2702",
    "sg:postcode":"19130",
    "sg:province":"PA",
    "sg:tags":[
        "venue"
    ],
    "sg:website":"www.theartsgarage.com/",
    "wof:name":"The Arts Garage",
    "wof:placetype":"venue"
},
  "geometry": {"coordinates":[-75.16252799999999,39.968845],"type":"Point"}
}