{
  "type": "Feature",
  "properties": {
    "iso:country":"US",
    "sg:address":"400 Jefferson Ave",
    "sg:city":"Washington",
    "sg:classifiers":[
        {
            "category":"Health Services",
            "subcategory":"Doctor",
            "type":"Services"
        }
    ],
    "sg:phone":"+1 724 228 7400",
    "sg:postcode":"15301",
    "sg:province":"PA",
    "sg:tags":[
        "physician",
        "surgeon"
    ],
    "wof:name":"Pediatric Associates-Wshngtn",
    "wof:placetype":"venue"
},
  "geometry": {"coordinates":[-80.255544,40.175084],"type":"Point"}
}