{
  "type": "Feature",
  "properties": {
    "addr:full":"1100 3rd Ave New Brighton PA 15066",
    "addr:housenumber":"1100",
    "addr:postcode":"15066",
    "addr:street":"3Rd Ave",
    "iso:country":"US",
    "sg:address":"1100 3rd Ave",
    "sg:city":"New Brighton",
    "sg:classifiers":[
        {
            "category":"Home & Garden",
            "subcategory":"Carpets & Floor Coverings",
            "type":"Retail Goods"
        }
    ],
    "sg:phone":"+1 724 843 1456",
    "sg:postcode":"15066",
    "sg:province":"PA",
    "wof:name":"Floors Galore",
    "wof:placetype":"venue"
},
  "geometry": {"coordinates":[-80.31059999999999,40.731286],"type":"Point"}
}