{
  "type": "Feature",
  "properties": {
    "iso:country":"US",
    "sg:address":"507 S Main St",
    "sg:city":"Perkasie",
    "sg:classifiers":[
        {
            "category":"Building & Trades",
            "subcategory":"Plumbing",
            "type":"Services"
        }
    ],
    "sg:phone":"+1 215 257 3248",
    "sg:postcode":"18944",
    "sg:province":"PA",
    "sg:tags":[
        "heating",
        "contractor"
    ],
    "wof:name":"William S Seachrist",
    "wof:placetype":"venue"
},
  "geometry": {"coordinates":[-75.291358,40.358747],"type":"Point"}
}