{
  "type": "Feature",
  "properties": {
    "iso:country":"US",
    "sg:address":"211 Lefever Rd",
    "sg:city":"Newville",
    "sg:classifiers":[
        {
            "category":"Professional",
            "type":"Services"
        }
    ],
    "sg:phone":"+1   ",
    "sg:postcode":"17241",
    "sg:province":"PA",
    "wof:name":"Gregory J Young",
    "wof:placetype":"venue"
},
  "geometry": {"coordinates":[-77.37067500000001,40.177103],"type":"Point"}
}