{
  "type": "Feature",
  "properties": {
    "iso:country":"US",
    "sg:address":"1100 Lincoln Ave",
    "sg:city":"Prospect Park",
    "sg:classifiers":[
        {
            "category":"Shopping",
            "subcategory":"Used Merchandise",
            "type":"Retail Goods"
        }
    ],
    "sg:phone":"+1 610 237 0746",
    "sg:postcode":"19076",
    "sg:province":"PA",
    "wof:name":"Tri State Antiques",
    "wof:placetype":"venue"
},
  "geometry": {"coordinates":[-75.30983999999999,39.887508],"type":"Point"}
}