{
  "type": "Feature",
  "properties": {
    "iso:country":"US",
    "sg:address":"223 S Warren St",
    "sg:city":"Berwick",
    "sg:classifiers":[
        {
            "category":"Wholesale",
            "subcategory":"Vending Machines",
            "type":"Manufacturing & Wholesale Goods"
        }
    ],
    "sg:phone":"+1 570 759 9449",
    "sg:postcode":"18603",
    "sg:province":"PA",
    "sg:tags":[
        "operator"
    ],
    "wof:name":"Vending Ideal Products Company",
    "wof:placetype":"venue"
},
  "geometry": {"coordinates":[-76.25207399999999,41.048152],"type":"Point"}
}