{
  "type": "Feature",
  "properties": {
    "iso:country":"US",
    "sg:address":"1180 Main St",
    "sg:city":"Bloomsburg",
    "sg:classifiers":[
        {
            "category":"Manufacturing",
            "subcategory":"Printing",
            "type":"Manufacturing & Wholesale Goods"
        }
    ],
    "sg:phone":"+1   ",
    "sg:postcode":"17815",
    "sg:province":"PA",
    "sg:tags":[
        "commercial"
    ],
    "wof:name":"Gemco",
    "wof:placetype":"venue"
},
  "geometry": {"coordinates":[-76.42393,41.030134],"type":"Point"}
}