{
  "type": "Feature",
  "properties": {
    "addr:full":"1128 Race St Connellsville PA 15425",
    "addr:housenumber":"1128",
    "addr:postcode":"15425",
    "addr:street":"Race St",
    "iso:country":"US",
    "sg:address":"1128 Race St",
    "sg:city":"Connellsville",
    "sg:classifiers":[
        {
            "category":"Education",
            "subcategory":"School",
            "type":"Public Place"
        }
    ],
    "sg:phone":"+1   ",
    "sg:postcode":"15425",
    "sg:province":"PA",
    "wof:name":"Josh Garlick",
    "wof:placetype":"venue"
},
  "geometry": {"coordinates":[-79.587838,40.007917],"type":"Point"}
}