{
  "type": "Feature",
  "properties": {
    "iso:country":"US",
    "sg:address":"360 Middletown Blvd",
    "sg:city":"Langhorne",
    "sg:classifiers":[
        {
            "category":"Health Services",
            "subcategory":"Doctor",
            "type":"Services"
        }
    ],
    "sg:phone":"+1   ",
    "sg:postcode":"19047",
    "sg:province":"PA",
    "sg:tags":[
        "medical"
    ],
    "wof:name":"Aesthepic Laser Center",
    "wof:placetype":"venue"
},
  "geometry": {"coordinates":[-74.881325,40.18657],"type":"Point"}
}