{
  "type": "Feature",
  "properties": {
    "addr:full":"4500 Melwood Rd Leechburg PA 15656",
    "addr:housenumber":"4500",
    "addr:postcode":"15656",
    "addr:street":"Melwood Rd",
    "iso:country":"US",
    "sg:address":"4500 Melwood Rd",
    "sg:city":"Leechburg",
    "sg:classifiers":[
        {
            "category":"Professional",
            "subcategory":"Management & Consulting",
            "type":"Services"
        }
    ],
    "sg:phone":"+1   ",
    "sg:postcode":"15656",
    "sg:province":"PA",
    "sg:tags":[
        "food"
    ],
    "wof:name":"Five Starr Services",
    "wof:placetype":"venue"
},
  "geometry": {"coordinates":[-79.61775299999999,40.593661],"type":"Point"}
}