{
  "type": "Feature",
  "properties": {
    "iso:country":"US",
    "sg:address":"1017 E Pleasant Valley Blvd",
    "sg:city":"Altoona",
    "sg:classifiers":[
        {
            "category":"Building & Trades",
            "subcategory":"Construction",
            "type":"Services"
        }
    ],
    "sg:phone":"+1 814 943 6345",
    "sg:postcode":"16602",
    "sg:province":"PA",
    "sg:tags":[
        "house",
        "general",
        "ma",
        "contractor"
    ],
    "wof:name":"Altoona Builders & Remodelers",
    "wof:placetype":"venue"
},
  "geometry": {"coordinates":[-78.364722,40.525903],"type":"Point"}
}