{
  "type": "Feature",
  "properties": {
    "iso:country":"US",
    "sg:address":"1480 Blakeslee Boulevard Dr W",
    "sg:city":"Lehighton",
    "sg:classifiers":[
        {
            "category":"Manufacturing",
            "subcategory":"Glass & Minerals",
            "type":"Manufacturing & Wholesale Goods"
        }
    ],
    "sg:phone":"+1 570 386 4700",
    "sg:postcode":"18235",
    "sg:province":"PA",
    "sg:tags":[
        "plate",
        "shape",
        "glass-wholesale",
        "window",
        "special",
        "circle",
        "glass-auto",
        "manufacturer"
    ],
    "wof:name":"Mahoning Valley Glass Co",
    "wof:placetype":"venue"
},
  "geometry": {"coordinates":[-75.79537000000001,40.790379],"type":"Point"}
}