{
  "type": "Feature",
  "properties": {
    "iso:country":"US",
    "sg:address":"70 Mine Rd",
    "sg:city":"Quakertown",
    "sg:classifiers":[
        {
            "category":"Retail",
            "subcategory":"Auto Repair",
            "type":"Services"
        }
    ],
    "sg:phone":"+1 215 258 1030",
    "sg:postcode":"18951",
    "sg:province":"PA",
    "sg:tags":[
        "repairing",
        "automobile"
    ],
    "wof:name":"Wieand's Automotive & Truck",
    "wof:placetype":"venue"
},
  "geometry": {"coordinates":[-75.362858,40.474595],"type":"Point"}
}