{
  "type": "Feature",
  "properties": {
    "addr:full":"12 S 3rd St Clearfield PA 16830",
    "addr:housenumber":"12",
    "addr:postcode":"16830",
    "addr:street":"S 3Rd St",
    "iso:country":"US",
    "sg:address":"12 S 3rd St",
    "sg:city":"Clearfield",
    "sg:classifiers":[
        {
            "category":"Insurance",
            "subcategory":"Insurance Agent",
            "type":"Services"
        }
    ],
    "sg:phone":"+1 814 236 2650",
    "sg:postcode":"16830",
    "sg:province":"PA",
    "sg:website":"www.hsinsurance.net",
    "wof:name":"Bellmore Insurance Inc",
    "wof:placetype":"venue"
},
  "geometry": {"coordinates":[-78.43624199999999,41.02195],"type":"Point"}
}