{
  "type": "Feature",
  "properties": {
    "iso:country":"US",
    "sg:address":"1230 E Mermaid Ln",
    "sg:city":"Glenside",
    "sg:classifiers":[
        {
            "category":"Utilities",
            "subcategory":"Mobile Phone",
            "type":"Services"
        },
        {
            "category":"Utilities",
            "subcategory":"Telephone",
            "type":"Services"
        },
        {
            "category":"Communications",
            "type":"Services"
        }
    ],
    "sg:phone":"+1 215 233 0455",
    "sg:postcode":"19038",
    "sg:province":"PA",
    "sg:tags":[
        "equipment",
        "data",
        "system",
        "cellular"
    ],
    "wof:name":"Mobile Communications Inc",
    "wof:placetype":"venue"
},
  "geometry": {"coordinates":[-75.182545,40.082783],"type":"Point"}
}