{
  "type": "Feature",
  "properties": {
    "addr:full":"100 Robinson Center Dr Pittsburgh PA 15205",
    "addr:housenumber":"100",
    "addr:postcode":"15205",
    "addr:street":"Robinson Center Dr",
    "iso:country":"US",
    "sg:address":"100 Robinson Center Dr",
    "sg:city":"Pittsburgh",
    "sg:classifiers":[
        {
            "category":"Shopping",
            "subcategory":"Optician",
            "type":"Retail Goods"
        }
    ],
    "sg:phone":"+1 412 490 7464",
    "sg:postcode":"15205",
    "sg:province":"PA",
    "sg:tags":[
        "eyewear"
    ],
    "wof:name":"Sunglass Hut International",
    "wof:placetype":"venue"
},
  "geometry": {"coordinates":[-80.157709,40.454458],"type":"Point"}
}