{
  "type": "Feature",
  "properties": {
    "addr:full":"918 W 3rd St Lansdale PA 19446",
    "addr:housenumber":"918",
    "addr:postcode":"19446",
    "addr:street":"W 3Rd St",
    "iso:country":"US",
    "sg:address":"918 W 3rd St",
    "sg:city":"Lansdale",
    "sg:classifiers":[
        {
            "category":"Manufacturing",
            "subcategory":"Tools & Machinery",
            "type":"Manufacturing & Wholesale Goods"
        }
    ],
    "sg:phone":"+1   ",
    "sg:postcode":"19446",
    "sg:province":"PA",
    "sg:tags":[
        "industry",
        "mfg"
    ],
    "wof:name":"Performnce McHining Rebuilding",
    "wof:placetype":"venue"
},
  "geometry": {"coordinates":[-75.294481,40.250509],"type":"Point"}
}