{
  "type": "Feature",
  "properties": {
    "addr:full":"1709 N 52nd St Philadelphia PA 19131",
    "addr:housenumber":"1709",
    "addr:postcode":"19131",
    "addr:street":"N 52Nd St",
    "iso:country":"US",
    "sg:address":"1709 N 52nd St",
    "sg:city":"Philadelphia",
    "sg:classifiers":[
        {
            "category":"Organizations",
            "subcategory":"Religious Organization",
            "type":"Services"
        }
    ],
    "sg:phone":"+1 215 877 2749",
    "sg:postcode":"19131",
    "sg:province":"PA",
    "sg:tags":[
        "church"
    ],
    "wof:name":"Macedonia Pentecostal Church",
    "wof:placetype":"venue"
},
  "geometry": {"coordinates":[-75.224417,39.980766],"type":"Point"}
}