{
  "type": "Feature",
  "properties": {
    "iso:country":"US",
    "sg:address":"128 W Beil Ave",
    "sg:city":"Nazareth",
    "sg:classifiers":[
        {
            "category":"Retail",
            "subcategory":"Auto Repair",
            "type":"Services"
        }
    ],
    "sg:phone":"+1 610 759 6121",
    "sg:postcode":"18064",
    "sg:province":"PA",
    "sg:tags":[
        "repairing",
        "automobile",
        "body"
    ],
    "wof:name":"Louis Murante Auto Body Repair",
    "wof:placetype":"venue"
},
  "geometry": {"coordinates":[-75.31921,40.754655],"type":"Point"}
}