{
  "type": "Feature",
  "properties": {
    "iso:country":"US",
    "sg:address":"1283 Liberty St",
    "sg:city":"Franklin",
    "sg:classifiers":[
        {
            "category":"Government",
            "subcategory":"Office",
            "type":"Public Place"
        }
    ],
    "sg:phone":"+1 814 432 9753",
    "sg:postcode":"16323",
    "sg:province":"PA",
    "sg:tags":[
        "county",
        "program",
        "health"
    ],
    "wof:name":"Mental Health-Mental Rtrdtn",
    "wof:placetype":"venue"
},
  "geometry": {"coordinates":[-79.830634,41.397734],"type":"Point"}
}