{
  "type": "Feature",
  "properties": {
    "iso:country":"US",
    "sg:address":"594 Galleria Dr",
    "sg:city":"Johnstown",
    "sg:classifiers":[
        {
            "category":"Shopping",
            "subcategory":"Bicycles & Sporting Goods",
            "type":"Retail Goods"
        }
    ],
    "sg:phone":"+1   ",
    "sg:postcode":"15904",
    "sg:province":"PA",
    "wof:name":"Dunhams 041",
    "wof:placetype":"venue"
},
  "geometry": {"coordinates":[-78.83275,40.304031],"type":"Point"}
}