{
  "type": "Feature",
  "properties": {
    "iso:country":"US",
    "sg:address":"345 Mulberry St",
    "sg:city":"Williamsport",
    "sg:classifiers":[
        {
            "category":"Building & Trades",
            "subcategory":"Construction",
            "type":"Services"
        }
    ],
    "sg:phone":"+1 570 323 3346",
    "sg:postcode":"17701",
    "sg:province":"PA",
    "sg:tags":[
        "hanging",
        "general",
        "contractor"
    ],
    "wof:name":"Marguerite P Bierman",
    "wof:placetype":"venue"
},
  "geometry": {"coordinates":[-77.000468,41.242933],"type":"Point"}
}