{
  "type": "Feature",
  "properties": {
    "iso:country":"US",
    "sg:address":"1500 Walnut St",
    "sg:city":"Philadelphia",
    "sg:classifiers":[
        {
            "category":"Professional",
            "subcategory":"Lawyer & Legal Services",
            "type":"Services"
        }
    ],
    "sg:phone":"+1 215 893 0100",
    "sg:postcode":"19102",
    "sg:province":"PA",
    "wof:name":"Greatrex George C Jr Atty",
    "wof:placetype":"venue"
},
  "geometry": {"coordinates":[-75.166901,39.949501],"type":"Point"}
}