{
  "type": "Feature",
  "properties": {
    "iso:country":"US",
    "sg:address":"2021 Birchwood Dr",
    "sg:city":"Norristown",
    "sg:classifiers":[
        {
            "category":"Freight",
            "type":"Transportation"
        }
    ],
    "sg:phone":"+1   ",
    "sg:postcode":"19401",
    "sg:province":"PA",
    "sg:tags":[
        "delivery",
        "vehicular",
        "parcel"
    ],
    "wof:name":"Assoc Parcel Service",
    "wof:placetype":"venue"
},
  "geometry": {"coordinates":[-75.317898,40.13057],"type":"Point"}
}