{
  "type": "Feature",
  "properties": {
    "addr:full":"580 W Germantown Pike Plymouth Meeting PA 19462",
    "addr:housenumber":"580",
    "addr:postcode":"19462",
    "addr:street":"W Germantown Pike",
    "iso:country":"US",
    "sg:address":"580 W Germantown Pike",
    "sg:city":"Plymouth Meeting",
    "sg:classifiers":[
        {
            "category":"Banks & Credit Unions",
            "subcategory":"Investment Brokerage",
            "type":"Services"
        }
    ],
    "sg:phone":"+1 610 825 6405",
    "sg:postcode":"19462",
    "sg:province":"PA",
    "sg:tags":[
        "consultant",
        "planning",
        "financial"
    ],
    "wof:name":"Dudycha Retirement Svc",
    "wof:placetype":"venue"
},
  "geometry": {"coordinates":[-75.285698,40.116372],"type":"Point"}
}