{
  "type": "Feature",
  "properties": {
    "iso:country":"US",
    "sg:address":"41 Silver Swallow Rd",
    "sg:city":"Reading",
    "sg:classifiers":[
        {
            "category":"Building & Trades",
            "subcategory":"Construction",
            "type":"Services"
        }
    ],
    "sg:phone":"+1 610 779 9191",
    "sg:postcode":"19606",
    "sg:province":"PA",
    "sg:tags":[
        "general",
        "contractor"
    ],
    "wof:name":"AGM Assoc Inc",
    "wof:placetype":"venue"
},
  "geometry": {"coordinates":[-75.835943,40.365826],"type":"Point"}
}