{
  "type": "Feature",
  "properties": {
    "addr:full":"3 Flora Rd Pittsburgh PA 15227",
    "addr:housenumber":"3",
    "addr:postcode":"15227",
    "addr:street":"Flora Rd",
    "iso:country":"US",
    "sg:address":"3 Flora Rd",
    "sg:city":"Pittsburgh",
    "sg:classifiers":[
        {
            "category":"Personal",
            "subcategory":"Beauty Salon",
            "type":"Services"
        }
    ],
    "sg:phone":"+1 412 881 1110",
    "sg:postcode":"15227",
    "sg:province":"PA",
    "wof:name":"Marcy Schugg Family Hair Salon",
    "wof:placetype":"venue"
},
  "geometry": {"coordinates":[-79.951482,40.386823],"type":"Point"}
}