{
  "type": "Feature",
  "properties": {
    "addr:full":"441 Friendship Rd Harrisburg PA 17111",
    "addr:housenumber":"441",
    "addr:postcode":"17111",
    "addr:street":"Friendship Rd",
    "iso:country":"US",
    "sg:address":"441 Friendship Rd",
    "sg:city":"Harrisburg",
    "sg:classifiers":[
        {
            "category":"Government",
            "subcategory":"Office",
            "type":"Public Place"
        }
    ],
    "sg:phone":"+1   ",
    "sg:postcode":"17111",
    "sg:province":"PA",
    "sg:tags":[
        "development",
        "economic"
    ],
    "wof:name":"Regional Econ Dev District Ini",
    "wof:placetype":"venue"
},
  "geometry": {"coordinates":[-76.82727199999999,40.250424],"type":"Point"}
}