{
  "type": "Feature",
  "properties": {
    "addr:full":"142 Knollwood Ct Aston PA 19014",
    "addr:housenumber":"142",
    "addr:postcode":"19014",
    "addr:street":"Knollwood Ct Aston",
    "iso:country":"US",
    "sg:address":"142 Knollwood Ct",
    "sg:city":"Aston",
    "sg:classifiers":[
        {
            "category":"Wholesale",
            "subcategory":"Stationery",
            "type":"Manufacturing & Wholesale Goods"
        }
    ],
    "sg:phone":"+1   ",
    "sg:postcode":"19014",
    "sg:province":"PA",
    "sg:tags":[
        "paper"
    ],
    "wof:name":"Diva U S A Inc",
    "wof:placetype":"venue"
},
  "geometry": {"coordinates":[-75.43471,39.882525],"type":"Point"}
}