{
  "type": "Feature",
  "properties": {
    "iso:country":"US",
    "sg:address":"328 Beaver Dam Rd",
    "sg:city":"Butler",
    "sg:classifiers":[
        {
            "category":"Personal",
            "type":"Services"
        },
        {
            "category":"Retail",
            "subcategory":"Auto Repair",
            "type":"Services"
        }
    ],
    "sg:phone":"+1 724 637 2301",
    "sg:postcode":"16001",
    "sg:province":"PA",
    "sg:tags":[
        "towing"
    ],
    "wof:name":"Pry Towing & Garage",
    "wof:placetype":"venue"
},
  "geometry": {"coordinates":[-79.93853,40.981695],"type":"Point"}
}