{
  "type": "Feature",
  "properties": {
    "iso:country":"US",
    "sg:address":"26 W Maplewood Mall",
    "sg:city":"Philadelphia",
    "sg:classifiers":[
        {
            "category":"Organizations",
            "subcategory":"Religious Organization",
            "type":"Services"
        }
    ],
    "sg:phone":"+1 215 849 0900",
    "sg:postcode":"19144",
    "sg:province":"PA",
    "wof:name":"Freshfire Ministries",
    "wof:placetype":"venue"
},
  "geometry": {"coordinates":[-75.175633,40.034107],"type":"Point"}
}