{
  "type": "Feature",
  "properties": {
    "iso:country":"US",
    "sg:address":"1727 Scalp Ave",
    "sg:city":"Johnstown",
    "sg:classifiers":[
        {
            "category":"Autos & Motor Vehicles",
            "subcategory":"Auto Supplies",
            "type":"Retail Goods"
        },
        {
            "category":"Retail",
            "subcategory":"Auto Repair",
            "type":"Services"
        }
    ],
    "sg:phone":"+1 814 467 4056",
    "sg:postcode":"15904",
    "sg:province":"PA",
    "sg:tags":[
        "automotive",
        "parts",
        "automobile",
        "general"
    ],
    "wof:name":"Petros NAPA Auto Care Center",
    "wof:placetype":"venue"
},
  "geometry": {"coordinates":[-78.84987,40.260199],"type":"Point"}
}