{
  "type": "Feature",
  "properties": {
    "iso:country":"US",
    "sg:address":"7 E Main St",
    "sg:city":"Nanticoke",
    "sg:classifiers":[
        {
            "category":"Retail",
            "subcategory":"Auto Repair",
            "type":"Services"
        }
    ],
    "sg:phone":"+1 570 736 6260",
    "sg:postcode":"18634",
    "sg:province":"PA",
    "sg:tags":[
        "automobile",
        "inspection"
    ],
    "wof:name":"A Two Z Auto Ctr",
    "wof:placetype":"venue"
},
  "geometry": {"coordinates":[-76.004356,41.205209],"type":"Point"}
}