{
  "type": "Feature",
  "properties": {
    "addr:full":"4916 Larchwood Ave Philadelphia PA 19143",
    "addr:housenumber":"4916",
    "addr:postcode":"19143",
    "addr:street":"Larchwood Ave",
    "iso:country":"US",
    "sg:address":"4916 Larchwood Ave",
    "sg:city":"Philadelphia",
    "sg:classifiers":[
        {
            "category":"Building & Trades",
            "subcategory":"Construction",
            "type":"Services"
        }
    ],
    "sg:phone":"+1 215 747 8331",
    "sg:postcode":"19143",
    "sg:province":"PA",
    "sg:tags":[
        "contractor"
    ],
    "wof:name":"Alexander Gillett",
    "wof:placetype":"venue"
},
  "geometry": {"coordinates":[-75.222354,39.951405],"type":"Point"}
}