{
  "type": "Feature",
  "properties": {
    "addr:full":"40 Knob Hill Shavertown PA 18708",
    "addr:housenumber":"40",
    "addr:postcode":"18708",
    "addr:street":"Knob Hill",
    "iso:country":"US",
    "sg:address":"40 Knob Hill",
    "sg:city":"Shavertown",
    "sg:classifiers":[
        {
            "category":"Social Services",
            "subcategory":"Child Care",
            "type":"Services"
        }
    ],
    "sg:phone":"+1 570 696 3899",
    "sg:postcode":"18708",
    "sg:province":"PA",
    "sg:tags":[
        "kindergarten",
        "academic",
        "school",
        "day"
    ],
    "wof:name":"Trucksville Nursery School",
    "wof:placetype":"venue"
},
  "geometry": {"coordinates":[-75.92771500000001,41.301303],"type":"Point"}
}