{
  "type": "Feature",
  "properties": {
    "iso:country":"US",
    "sg:address":"515 W 8th St",
    "sg:city":"Hazleton",
    "sg:classifiers":[
        {
            "category":"Freight",
            "type":"Transportation"
        }
    ],
    "sg:phone":"+1 570 450 6914",
    "sg:postcode":"18201",
    "sg:province":"PA",
    "sg:tags":[
        "operator",
        "trucking"
    ],
    "wof:name":"Walden Transportation LLC",
    "wof:placetype":"venue"
},
  "geometry": {"coordinates":[-75.980879,40.963601],"type":"Point"}
}