{
  "type": "Feature",
  "properties": {
    "iso:country":"US",
    "sg:address":"213 Reeceville Rd",
    "sg:city":"Coatesville",
    "sg:classifiers":[
        {
            "category":"Health Services",
            "subcategory":"Doctor",
            "type":"Services"
        }
    ],
    "sg:phone":"+1   ",
    "sg:postcode":"19320",
    "sg:province":"PA",
    "sg:tags":[
        "medical"
    ],
    "wof:name":"Arthur P Schless MD",
    "wof:placetype":"venue"
},
  "geometry": {"coordinates":[-75.79071999999999,40.013307],"type":"Point"}
}