{
  "type": "Feature",
  "properties": {
    "iso:country":"US",
    "sg:address":"358 Montgomery Ave",
    "sg:city":"Merion Station",
    "sg:classifiers":[
        {
            "category":"Shopping",
            "subcategory":"Clothing, Apparel, & Fashions",
            "type":"Retail Goods"
        }
    ],
    "sg:phone":"+1 610 664 2583",
    "sg:postcode":"19066",
    "sg:province":"PA",
    "sg:tags":[
        "sportswear",
        "accessory"
    ],
    "wof:name":"Funda & Marc",
    "wof:placetype":"venue"
},
  "geometry": {"coordinates":[-75.244202,40.006001],"type":"Point"}
}