{
  "type": "Feature",
  "properties": {
    "addr:full":"621 Swede St Norristown PA 19401",
    "addr:housenumber":"621",
    "addr:postcode":"19401",
    "addr:street":"Swede St",
    "iso:country":"US",
    "sg:address":"621 Swede St",
    "sg:city":"Norristown",
    "sg:classifiers":[
        {
            "category":"Professional",
            "subcategory":"Lawyer & Legal Services",
            "type":"Services"
        }
    ],
    "sg:phone":"+1   ",
    "sg:postcode":"19401",
    "sg:province":"PA",
    "wof:name":"Thomas C Egan III",
    "wof:placetype":"venue"
},
  "geometry": {"coordinates":[-75.342507,40.118139],"type":"Point"}
}