{
  "type": "Feature",
  "properties": {
    "iso:country":"US",
    "sg:address":"126 Foxshire Dr",
    "sg:city":"Lancaster",
    "sg:classifiers":[
        {
            "category":"Real Estate",
            "subcategory":"Real Estate Services",
            "type":"Services"
        }
    ],
    "sg:phone":"+1 717 581 5810",
    "sg:postcode":"17601",
    "sg:province":"PA",
    "sg:tags":[
        "company",
        "abstract",
        "title"
    ],
    "sg:website":"www.premiersettlements.com",
    "wof:name":"Premier Settlements Inc",
    "wof:placetype":"venue"
},
  "geometry": {"coordinates":[-76.32284300000001,40.076129],"type":"Point"}
}