{
  "type": "Feature",
  "properties": {
    "addr:full":"501 Columbia Hill Rd Danville PA 17821",
    "addr:housenumber":"501",
    "addr:postcode":"17821",
    "addr:street":"Columbia Hill Rd",
    "iso:country":"US",
    "sg:address":"501 Columbia Hill Rd",
    "sg:city":"Danville",
    "sg:classifiers":[
        {
            "category":"Professional",
            "type":"Services"
        }
    ],
    "sg:phone":"+1   ",
    "sg:postcode":"17821",
    "sg:province":"PA",
    "wof:name":"Joseph Hettinger",
    "wof:placetype":"venue"
},
  "geometry": {"coordinates":[-76.58624399999999,41.007645],"type":"Point"}
}