{
  "type": "Feature",
  "properties": {
    "iso:country":"US",
    "sg:address":"230 Bilmar Dr",
    "sg:city":"Pittsburgh",
    "sg:classifiers":[
        {
            "category":"Utilities",
            "subcategory":"Telephone",
            "type":"Services"
        }
    ],
    "sg:phone":"+1 412 920 6100",
    "sg:postcode":"15205",
    "sg:province":"PA",
    "sg:tags":[
        "communications",
        "merchandise"
    ],
    "wof:name":"Greyfox Systems Inc",
    "wof:placetype":"venue"
},
  "geometry": {"coordinates":[-80.10575,40.451713],"type":"Point"}
}