{
  "type": "Feature",
  "properties": {
    "iso:country":"US",
    "sg:address":"610 Sunbury St",
    "sg:city":"Minersville",
    "sg:classifiers":[
        {
            "category":"Autos & Motor Vehicles",
            "subcategory":"Automobile Sales",
            "type":"Retail Goods"
        }
    ],
    "sg:phone":"+1 570 544 2037",
    "sg:postcode":"17954",
    "sg:province":"PA",
    "sg:tags":[
        "used"
    ],
    "wof:name":"Kozura Motor Co Inc",
    "wof:placetype":"venue"
},
  "geometry": {"coordinates":[-76.266312,40.692267],"type":"Point"}
}