{
  "type": "Feature",
  "properties": {
    "addr:full":"107 N Main St Mansfield PA 16933",
    "addr:housenumber":"107",
    "addr:postcode":"16933",
    "addr:street":"N Main St",
    "iso:country":"US",
    "sg:address":"107 N Main St",
    "sg:city":"Mansfield",
    "sg:classifiers":[
        {
            "category":"Sports & Exercise",
            "subcategory":"Gym",
            "type":"Entertainment"
        }
    ],
    "sg:phone":"+1 570 513 0836",
    "sg:postcode":"16933",
    "sg:province":"PA",
    "sg:tags":[
        "club",
        "health",
        "studio",
        "gymnasium"
    ],
    "wof:name":"Club Optima Private Health Clb",
    "wof:placetype":"venue"
},
  "geometry": {"coordinates":[-77.078902,41.808974],"type":"Point"}
}