{
  "type": "Feature",
  "properties": {
    "iso:country":"US",
    "sg:address":"2622 N 28th St",
    "sg:city":"Philadelphia",
    "sg:classifiers":[
        {
            "category":"Professional",
            "type":"Services"
        }
    ],
    "sg:phone":"+1   ",
    "sg:postcode":"19132",
    "sg:province":"PA",
    "wof:name":"Hafsah Inc",
    "wof:placetype":"venue"
},
  "geometry": {"coordinates":[-75.177244,39.995821],"type":"Point"}
}