{
  "type": "Feature",
  "properties": {
    "addr:full":"257 Concord Rd Aston PA 19014",
    "addr:housenumber":"257",
    "addr:postcode":"19014",
    "addr:street":"Concord Rd",
    "iso:country":"US",
    "sg:address":"257 Concord Rd",
    "sg:city":"Aston",
    "sg:classifiers":[
        {
            "category":"Recreation",
            "type":"Entertainment"
        }
    ],
    "sg:phone":"+1 610 497 1255",
    "sg:postcode":"19014",
    "sg:province":"PA",
    "sg:tags":[
        "hall",
        "auditorium"
    ],
    "wof:name":"Aston Community Ctr",
    "wof:placetype":"venue"
},
  "geometry": {"coordinates":[-75.425096,39.867135],"type":"Point"}
}