{
  "type": "Feature",
  "properties": {
    "iso:country":"US",
    "sg:address":"306 W George St",
    "sg:city":"Carmichaels",
    "sg:classifiers":[
        {
            "category":"Professional",
            "type":"Services"
        }
    ],
    "sg:phone":"+1   ",
    "sg:postcode":"15320",
    "sg:province":"PA",
    "wof:name":"Bo Dudleys",
    "wof:placetype":"venue"
},
  "geometry": {"coordinates":[-79.978308,39.895206],"type":"Point"}
}