{
  "type": "Feature",
  "properties": {
    "addr:full":"256 Baldy Hill Rd Alburtis PA 18011",
    "addr:housenumber":"256",
    "addr:postcode":"18011",
    "addr:street":"Baldy Hill Rd",
    "iso:country":"US",
    "sg:address":"256 Baldy Hill Rd",
    "sg:city":"Alburtis",
    "sg:classifiers":[
        {
            "category":"Professional",
            "subcategory":"Detective & Security Services",
            "type":"Services"
        }
    ],
    "sg:phone":"+1 610 845 2593",
    "sg:postcode":"18011",
    "sg:province":"PA",
    "sg:tags":[
        "system"
    ],
    "wof:name":"Valucom Services",
    "wof:placetype":"venue"
},
  "geometry": {"coordinates":[-75.66976200000001,40.439371],"type":"Point"}
}