{
  "type": "Feature",
  "properties": {
    "addr:full":"30 Fox Run Dr York PA 17403",
    "addr:housenumber":"30",
    "addr:postcode":"17403",
    "addr:street":"Fox Run Dr",
    "iso:country":"US",
    "sg:address":"30 Fox Run Dr",
    "sg:city":"York",
    "sg:classifiers":[
        {
            "category":"Freight",
            "type":"Transportation"
        }
    ],
    "sg:phone":"+1 717 747 5660",
    "sg:postcode":"17403",
    "sg:province":"PA",
    "sg:tags":[
        "trucking"
    ],
    "wof:name":"Central Refrigerated Svc",
    "wof:placetype":"venue"
},
  "geometry": {"coordinates":[-76.698999,39.924492],"type":"Point"}
}