{
  "type": "Feature",
  "properties": {
    "iso:country":"US",
    "sg:address":"2429 Saratoga Dr",
    "sg:city":"Sharpsville",
    "sg:classifiers":[
        {
            "category":"Personal",
            "subcategory":"Beauty Salon",
            "type":"Services"
        }
    ],
    "sg:phone":"+1   ",
    "sg:postcode":"16148",
    "sg:province":"PA",
    "sg:tags":[
        "shop"
    ],
    "wof:name":"Edna Gibsons Beauty Salon",
    "wof:placetype":"venue"
},
  "geometry": {"coordinates":[-80.464736,41.255592],"type":"Point"}
}