{
  "type": "Feature",
  "properties": {
    "addr:full":"1000 Washington Blvd Williamsport PA 17701",
    "addr:housenumber":"1000",
    "addr:postcode":"17701",
    "addr:street":"Washington Blvd",
    "iso:country":"US",
    "sg:address":"1000 Washington Blvd",
    "sg:city":"Williamsport",
    "sg:classifiers":[
        {
            "category":"Banks & Credit Unions",
            "subcategory":"Bank",
            "type":"Services"
        }
    ],
    "sg:phone":"+1   ",
    "sg:postcode":"17701",
    "sg:province":"PA",
    "sg:tags":[
        "mortgage"
    ],
    "wof:name":"Wells Fargo",
    "wof:placetype":"venue"
},
  "geometry": {"coordinates":[-76.98481099999999,41.249092],"type":"Point"}
}