{
  "type": "Feature",
  "properties": {
    "addr:full":"419 Loder St Waverly PA 14892",
    "addr:housenumber":"419",
    "addr:postcode":"14892",
    "addr:street":"Loder St",
    "iso:country":"US",
    "sg:address":"419 Loder St",
    "sg:city":"Waverly",
    "sg:classifiers":[
        {
            "category":"Personal",
            "subcategory":"Beauty Salon",
            "type":"Services"
        }
    ],
    "sg:phone":"+1 607 565 9321",
    "sg:postcode":"14892",
    "sg:province":"PA",
    "wof:name":"Originales By Russ Hair & Skin",
    "wof:placetype":"venue"
},
  "geometry": {"coordinates":[-76.543803,42.001942],"type":"Point"}
}