{
  "type": "Feature",
  "properties": {
    "iso:country":"US",
    "sg:address":"3801 William Penn Hwy",
    "sg:city":"Monroeville",
    "sg:classifiers":[
        {
            "category":"Shopping",
            "subcategory":"Used Merchandise",
            "type":"Retail Goods"
        }
    ],
    "sg:phone":"+1   ",
    "sg:postcode":"15146",
    "sg:province":"PA",
    "sg:tags":[
        "shop",
        "thrift"
    ],
    "wof:name":"Goodwill Industries Pittsburgh",
    "wof:placetype":"venue"
},
  "geometry": {"coordinates":[-79.779918,40.437149],"type":"Point"}
}