{
  "type": "Feature",
  "properties": {
    "iso:country":"US",
    "sg:address":"58 Four Leaf Rd",
    "sg:city":"Levittown",
    "sg:classifiers":[
        {
            "category":"Building & Trades",
            "subcategory":"Construction",
            "type":"Services"
        }
    ],
    "sg:phone":"+1 215 946 3619",
    "sg:postcode":"19056",
    "sg:province":"PA",
    "sg:tags":[
        "residential",
        "siding",
        "contractor"
    ],
    "wof:name":"Mc Govern & Sons Home Imprvmts",
    "wof:placetype":"venue"
},
  "geometry": {"coordinates":[-74.88407599999999,40.161812],"type":"Point"}
}