{
  "type": "Feature",
  "properties": {
    "addr:full":"515 Brown Rd Fawn Grove PA 17321",
    "addr:housenumber":"515",
    "addr:postcode":"17321",
    "addr:street":"Brown Rd",
    "iso:country":"US",
    "sg:address":"515 Brown Rd",
    "sg:city":"Fawn Grove",
    "sg:classifiers":[
        {
            "category":"Farming",
            "subcategory":"Farm & Veterinary Services",
            "type":"Manufacturing & Wholesale Goods"
        }
    ],
    "sg:phone":"+1   ",
    "sg:postcode":"17321",
    "sg:province":"PA",
    "sg:tags":[
        "management"
    ],
    "wof:name":"Brown Croft Farm",
    "wof:placetype":"venue"
},
  "geometry": {"coordinates":[-76.474079,39.745107],"type":"Point"}
}