{
  "type": "Feature",
  "properties": {
    "iso:country":"US",
    "sg:address":"3827 Janice St",
    "sg:city":"Philadelphia",
    "sg:classifiers":[
        {
            "category":"Arts & Performance",
            "subcategory":"Theater",
            "type":"Entertainment"
        }
    ],
    "sg:phone":"+1   ",
    "sg:postcode":"19114",
    "sg:province":"PA",
    "sg:tags":[
        "group"
    ],
    "wof:name":"Tappin Music Ltd",
    "wof:placetype":"venue"
},
  "geometry": {"coordinates":[-75.002904,40.057812],"type":"Point"}
}