{
  "type": "Feature",
  "properties": {
    "addr:full":"10902 Nandina Ln Philadelphia PA 19116",
    "addr:housenumber":"10902",
    "addr:postcode":"19116",
    "addr:street":"Nandina Ln",
    "iso:country":"US",
    "sg:address":"10902 Nandina Ln",
    "sg:city":"Philadelphia",
    "sg:classifiers":[
        {
            "category":"Professional",
            "subcategory":"Art Services",
            "type":"Services"
        }
    ],
    "sg:phone":"+1 215 969 5527",
    "sg:postcode":"19116",
    "sg:province":"PA",
    "sg:tags":[
        "photographer"
    ],
    "wof:name":"Progress Photography",
    "wof:placetype":"venue"
},
  "geometry": {"coordinates":[-75.034834,40.118424],"type":"Point"}
}