{
  "type": "Feature",
  "properties": {
    "addr:full":"685 Green Grove Rd Spring Mills PA 16875",
    "addr:housenumber":"685",
    "addr:postcode":"16875",
    "addr:street":"Green Grove Rd",
    "iso:country":"US",
    "sg:address":"685 Green Grove Rd",
    "sg:city":"Spring Mills",
    "sg:classifiers":[
        {
            "category":"Retail",
            "subcategory":"Auto Repair",
            "type":"Services"
        }
    ],
    "sg:phone":"+1 814 422 8546",
    "sg:postcode":"16875",
    "sg:province":"PA",
    "sg:tags":[
        "repairing",
        "automobile"
    ],
    "wof:name":"F C Stover Garage",
    "wof:placetype":"venue"
},
  "geometry": {"coordinates":[-77.572986,40.876204],"type":"Point"}
}