{
  "type": "Feature",
  "properties": {
    "iso:country":"US",
    "sg:address":"1790 Yardley Langhorne Rd",
    "sg:city":"Morrisville",
    "sg:classifiers":[
        {
            "category":"Home & Garden",
            "subcategory":"Household Appliances",
            "type":"Retail Goods"
        },
        {
            "category":"Home & Garden",
            "subcategory":"Furniture",
            "type":"Retail Goods"
        }
    ],
    "sg:phone":"+1 215 493 8600",
    "sg:postcode":"19067",
    "sg:province":"PA",
    "sg:tags":[
        "equipment",
        "cabinet",
        "kitchen",
        "bath"
    ],
    "wof:name":"Cranmer's Kitchens By Design",
    "wof:placetype":"venue"
},
  "geometry": {"coordinates":[-74.87259899999999,40.22518],"type":"Point"}
}