{
  "type": "Feature",
  "properties": {
    "iso:country":"US",
    "sg:address":"247 Quarry Rd",
    "sg:city":"Gap",
    "sg:classifiers":[
        {
            "category":"Building & Trades",
            "subcategory":"Construction",
            "type":"Services"
        }
    ],
    "sg:phone":"+1   ",
    "sg:postcode":"17527",
    "sg:province":"PA",
    "sg:tags":[
        "general"
    ],
    "wof:name":"Riehl Brothers Cnstr LLC",
    "wof:placetype":"venue"
},
  "geometry": {"coordinates":[-75.941132,40.007142],"type":"Point"}
}