{
  "type": "Feature",
  "properties": {
    "iso:country":"US",
    "sg:address":"4290 W Market St",
    "sg:city":"York",
    "sg:classifiers":[
        {
            "category":"Wholesale",
            "subcategory":"Hardware",
            "type":"Manufacturing & Wholesale Goods"
        },
        {
            "category":"Home & Garden",
            "subcategory":"Garden Supply",
            "type":"Retail Goods"
        },
        {
            "category":"Retail",
            "subcategory":"Repair Shop",
            "type":"Services"
        }
    ],
    "sg:phone":"+1 717 792 0071",
    "sg:postcode":"17408",
    "sg:province":"PA",
    "sg:tags":[
        "renting",
        "lawn",
        "outdoor",
        "power",
        "landscaping",
        "equipment-sales",
        "equipment",
        "saw"
    ],
    "sg:website":"http://www.stihldealer.net/default-dealer-044072.aspx",
    "wof:name":"Southern York Turf and Tractor Inc",
    "wof:placetype":"venue"
},
  "geometry": {"coordinates":[-76.814683,39.930684],"type":"Point"}
}