{
  "type": "Feature",
  "properties": {
    "iso:country":"US",
    "sg:address":"415 S Dartmouth Ln",
    "sg:city":"Altoona",
    "sg:classifiers":[
        {
            "category":"Building & Trades",
            "subcategory":"Plumbing",
            "type":"Services"
        },
        {
            "category":"Building & Trades",
            "subcategory":"Construction",
            "type":"Services"
        }
    ],
    "sg:phone":"+1 814 942 8529",
    "sg:postcode":"16602",
    "sg:province":"PA",
    "sg:tags":[
        "plumber",
        "specialty",
        "excavation",
        "heating",
        "system",
        "contractor",
        "air conditioning"
    ],
    "sg:website":"http://www.kimmenplumbing.com",
    "wof:name":"Kimmen Plumbing & Heating Inc",
    "wof:placetype":"venue"
},
  "geometry": {"coordinates":[-78.36422,40.546594],"type":"Point"}
}