{
  "type": "Feature",
  "properties": {
    "addr:full":"106 Penn St Newtown PA 18940",
    "addr:housenumber":"106",
    "addr:postcode":"18940",
    "addr:street":"Penn St",
    "iso:country":"US",
    "sg:address":"106 Penn St",
    "sg:city":"Newtown",
    "sg:classifiers":[
        {
            "category":"Education",
            "subcategory":"University",
            "type":"Public Place"
        }
    ],
    "sg:phone":"+1 215 497 8363",
    "sg:postcode":"18940",
    "sg:province":"PA",
    "sg:tags":[
        "college"
    ],
    "wof:name":"The Pennsylvania Anti Car",
    "wof:placetype":"venue"
},
  "geometry": {"coordinates":[-74.935124,40.226538],"type":"Point"}
}