{
  "type": "Feature",
  "properties": {
    "iso:country":"US",
    "sg:address":"2808 State St",
    "sg:city":"Erie",
    "sg:classifiers":[
        {
            "category":"Health Services",
            "subcategory":"Hospital",
            "type":"Services"
        }
    ],
    "sg:phone":"+1 814 456 2457",
    "sg:postcode":"16508",
    "sg:province":"PA",
    "sg:tags":[
        "mental"
    ],
    "sg:website":"www.dbhn.com",
    "wof:name":"Deerfield Management Group",
    "wof:placetype":"venue"
},
  "geometry": {"coordinates":[-80.072382,42.110174],"type":"Point"}
}