{
  "type": "Feature",
  "properties": {
    "addr:full":"1628 Roseytown Rd Greensburg PA 15601",
    "addr:housenumber":"1628",
    "addr:postcode":"15601",
    "addr:street":"Roseytown Rd",
    "iso:country":"US",
    "sg:address":"1628 Roseytown Rd",
    "sg:city":"Greensburg",
    "sg:classifiers":[
        {
            "category":"Home & Garden",
            "subcategory":"Building Materials",
            "type":"Retail Goods"
        },
        {
            "category":"Building & Trades",
            "subcategory":"Construction",
            "type":"Services"
        }
    ],
    "sg:phone":"+1 724 834 5170",
    "sg:postcode":"15601",
    "sg:province":"PA",
    "sg:tags":[
        "insulation",
        "product",
        "conservation",
        "energy",
        "contractor"
    ],
    "wof:name":"East Coast Insulation",
    "wof:placetype":"venue"
},
  "geometry": {"coordinates":[-79.515691,40.309578],"type":"Point"}
}