{
  "type": "Feature",
  "properties": {
    "iso:country":"US",
    "sg:address":"2967 W School House Ln Apt 1210",
    "sg:city":"Philadelphia",
    "sg:classifiers":[
        {
            "category":"Professional",
            "subcategory":"Lawyer & Legal Services",
            "type":"Services"
        }
    ],
    "sg:phone":"+1 215 849 4400",
    "sg:postcode":"19144",
    "sg:province":"PA",
    "wof:name":"Commons & Commons Llp",
    "wof:placetype":"venue"
},
  "geometry": {"coordinates":[-75.184303,40.0247],"type":"Point"}
}