{
  "type": "Feature",
  "properties": {
    "iso:country":"US",
    "sg:address":"900 N 66th St",
    "sg:city":"Philadelphia",
    "sg:classifiers":[
        {
            "category":"Bars & Pubs",
            "type":"Food & Drink"
        }
    ],
    "sg:phone":"+1 215 796 9703",
    "sg:postcode":"19151",
    "sg:province":"PA",
    "sg:tags":[
        "tavern"
    ],
    "wof:name":"Johnny's Place",
    "wof:placetype":"venue"
},
  "geometry": {"coordinates":[-75.252319,39.97683],"type":"Point"}
}