{
  "type": "Feature",
  "properties": {
    "iso:country":"US",
    "sg:address":"1562 Maytown Rd",
    "sg:city":"Elizabethtown",
    "sg:classifiers":[
        {
            "category":"Manufacturing",
            "subcategory":"Rubber & Plastics",
            "type":"Manufacturing & Wholesale Goods"
        },
        {
            "category":"Autos & Motor Vehicles",
            "subcategory":"Auto Supplies",
            "type":"Retail Goods"
        },
        {
            "category":"Retail",
            "subcategory":"Auto Repair",
            "type":"Services"
        }
    ],
    "sg:phone":"+1 717 367 7361",
    "sg:postcode":"17022",
    "sg:province":"PA",
    "sg:tags":[
        "tires-wholesale",
        "tire",
        "retread",
        "recap",
        "manufacturer"
    ],
    "sg:website":"http://www.coopertire.com/html/",
    "wof:name":"Keener Tire Service",
    "wof:placetype":"venue"
},
  "geometry": {"coordinates":[-76.591506,40.111589],"type":"Point"}
}