{
  "type": "Feature",
  "properties": {
    "iso:country":"US",
    "sg:address":"246 Gibbons Rd",
    "sg:city":"Springfield",
    "sg:classifiers":[
        {
            "category":"Real Estate",
            "subcategory":"Real Estate Services",
            "type":"Services"
        },
        {
            "category":"Real Estate",
            "subcategory":"Real Estate Agent",
            "type":"Services"
        }
    ],
    "sg:phone":"+1 610 544 2728",
    "sg:postcode":"19064",
    "sg:province":"PA",
    "sg:tags":[
        "buyer",
        "broker"
    ],
    "wof:name":"Decesaris Domenic F Real Estate Inc",
    "wof:placetype":"venue"
},
  "geometry": {"coordinates":[-75.34784399999999,39.918028],"type":"Point"}
}