{
  "type": "Feature",
  "properties": {
    "iso:country":"US",
    "sg:address":"498 Main St",
    "sg:city":"Archbald",
    "sg:classifiers":[
        {
            "category":"Manufacturing",
            "subcategory":"Food",
            "type":"Manufacturing & Wholesale Goods"
        }
    ],
    "sg:phone":"+1   ",
    "sg:postcode":"18403",
    "sg:province":"PA",
    "sg:tags":[
        "popcorn",
        "mfg"
    ],
    "wof:name":"Aunt Mollys Popcorn Inc",
    "wof:placetype":"venue"
},
  "geometry": {"coordinates":[-75.573376,41.496753],"type":"Point"}
}