{
  "type": "Feature",
  "properties": {
    "iso:country":"US",
    "sg:address":"811 Merchant St",
    "sg:city":"Ambridge",
    "sg:classifiers":[
        {
            "category":"Home & Garden",
            "subcategory":"Household Appliances",
            "type":"Retail Goods"
        },
        {
            "category":"Retail",
            "subcategory":"Repair Shop",
            "type":"Services"
        }
    ],
    "sg:phone":"+1 724 266 3140",
    "sg:postcode":"15003",
    "sg:province":"PA",
    "sg:tags":[
        "electrical"
    ],
    "wof:name":"Mikush Maytag Home Appliance",
    "wof:placetype":"venue"
},
  "geometry": {"coordinates":[-80.229659,40.590134],"type":"Point"}
}