{
  "type": "Feature",
  "properties": {
    "addr:full":"113 Grace St Ruffs Dale PA 15613",
    "addr:housenumber":"113",
    "addr:postcode":"15613",
    "addr:street":"Grace St;Dale",
    "iso:country":"US",
    "sg:address":"113 Grace St",
    "sg:city":"Ruffs Dale",
    "sg:classifiers":[
        {
            "category":"Organizations",
            "subcategory":"Religious Organization",
            "type":"Services"
        }
    ],
    "sg:phone":"+1 724 446 0843",
    "sg:postcode":"15613",
    "sg:province":"PA",
    "sg:tags":[
        "clergy"
    ],
    "wof:name":"Wesley Johnson",
    "wof:placetype":"venue"
},
  "geometry": {"coordinates":[-79.56920599999999,40.582533],"type":"Point"}
}