{
  "type": "Feature",
  "properties": {
    "iso:country":"US",
    "sg:address":"945 William Pitt Way",
    "sg:city":"Pittsburgh",
    "sg:classifiers":[
        {
            "category":"Building & Trades",
            "subcategory":"Plumbing",
            "type":"Services"
        }
    ],
    "sg:phone":"+1 412 826 5185",
    "sg:postcode":"15238",
    "sg:province":"PA",
    "sg:tags":[
        "contractor"
    ],
    "wof:name":"Engineered Air",
    "wof:placetype":"venue"
},
  "geometry": {"coordinates":[-79.834304,40.542837],"type":"Point"}
}