{
  "type": "Feature",
  "properties": {
    "iso:country":"US",
    "sg:address":"104 Edwin Ln",
    "sg:city":"Stroudsburg",
    "sg:classifiers":[
        {
            "category":"Professional",
            "subcategory":"Art Services",
            "type":"Services"
        }
    ],
    "sg:phone":"+1 570 402 2004",
    "sg:postcode":"18360",
    "sg:province":"PA",
    "sg:tags":[
        "graphic",
        "designer"
    ],
    "wof:name":"Thornton Creative",
    "wof:placetype":"venue"
},
  "geometry": {"coordinates":[-75.316813,40.970665],"type":"Point"}
}