{
  "type": "Feature",
  "properties": {
    "iso:country":"US",
    "sg:address":"4623 State Rte 30",
    "sg:city":"Greensburg",
    "sg:classifiers":[
        {
            "category":"Shopping",
            "subcategory":"Clothing, Apparel, & Fashions",
            "type":"Retail Goods"
        }
    ],
    "sg:phone":"+1 724 539 0494",
    "sg:postcode":"15601",
    "sg:province":"PA",
    "sg:tags":[
        "accessory"
    ],
    "sg:website":"www.murrayautoelectric.com",
    "wof:name":"Murray Automotive Electric Inc",
    "wof:placetype":"venue"
},
  "geometry": {"coordinates":[-79.44994199999999,40.287522],"type":"Point"}
}