{
  "type": "Feature",
  "properties": {
    "addr:full":"2261 N 51st St Philadelphia PA 19131",
    "addr:housenumber":"2261",
    "addr:postcode":"19131",
    "addr:street":"N 51St St",
    "iso:country":"US",
    "sg:address":"2261 N 51st St",
    "sg:city":"Philadelphia",
    "sg:classifiers":[
        {
            "category":"Banks & Credit Unions",
            "subcategory":"Bank",
            "type":"Services"
        }
    ],
    "sg:phone":"+1 215 879 4050",
    "sg:postcode":"19131",
    "sg:province":"PA",
    "sg:tags":[
        "loan",
        "real estate"
    ],
    "wof:name":"Valor Mortgage",
    "wof:placetype":"venue"
},
  "geometry": {"coordinates":[-75.228387,39.993466],"type":"Point"}
}