{
  "type": "Feature",
  "properties": {
    "iso:country":"US",
    "sg:address":"1341 N Delaware Ave Ste 405",
    "sg:city":"Philadelphia",
    "sg:classifiers":[
        {
            "category":"Communications",
            "subcategory":"Radio Station",
            "type":"Services"
        }
    ],
    "sg:phone":"+1 215 739 9886",
    "sg:postcode":"19125",
    "sg:province":"PA",
    "wof:name":"Multi-Cultural Radio Broadcasting Inc",
    "wof:placetype":"venue"
},
  "geometry": {"coordinates":[-75.12830099999999,39.967782],"type":"Point"}
}