{
  "type": "Feature",
  "properties": {
    "iso:country":"US",
    "sg:address":"19 Bala Ave",
    "sg:city":"Bala Cynwyd",
    "sg:classifiers":[
        {
            "category":"Health Services",
            "subcategory":"Health Practitioner",
            "type":"Services"
        }
    ],
    "sg:phone":"+1 610 664 4488",
    "sg:postcode":"19004",
    "sg:province":"PA",
    "sg:tags":[
        "acupuncture"
    ],
    "wof:name":"Debevoise Mark Dipl Ac & Ch",
    "wof:placetype":"venue"
},
  "geometry": {"coordinates":[-75.229202,40.000702],"type":"Point"}
}