{
  "type": "Feature",
  "properties": {
    "addr:full":"399 Pittsburgh Rd Butler PA 16002",
    "addr:housenumber":"399",
    "addr:postcode":"16002",
    "addr:street":"Pittsburgh Rd",
    "iso:country":"US",
    "sg:address":"399 Pittsburgh Rd",
    "sg:city":"Butler",
    "sg:classifiers":[
        {
            "category":"Banks & Credit Unions",
            "subcategory":"Investment Brokerage",
            "type":"Services"
        }
    ],
    "sg:phone":"+1 724 586 9099",
    "sg:postcode":"16002",
    "sg:province":"PA",
    "sg:tags":[
        "consultant",
        "planning",
        "financial"
    ],
    "wof:name":"Mc Kinney Financial Advisors",
    "wof:placetype":"venue"
},
  "geometry": {"coordinates":[-79.929907,40.78026],"type":"Point"}
}