{
  "type": "Feature",
  "properties": {
    "iso:country":"US",
    "sg:address":"8670 Peebles Rd",
    "sg:city":"Pittsburgh",
    "sg:classifiers":[
        {
            "category":"Health Services",
            "subcategory":"Chiropractor",
            "type":"Services"
        }
    ],
    "sg:phone":"+1 412 366 5474",
    "sg:postcode":"15237",
    "sg:province":"PA",
    "wof:name":"Results Family Chiropractic",
    "wof:placetype":"venue"
},
  "geometry": {"coordinates":[-80.007976,40.566009],"type":"Point"}
}