{
  "type": "Feature",
  "properties": {
    "iso:country":"US",
    "sg:address":"110 S Franklin St",
    "sg:city":"Titusville",
    "sg:classifiers":[
        {
            "category":"Health Services",
            "subcategory":"Doctor",
            "type":"Services"
        }
    ],
    "sg:phone":"+1 814 827 6293",
    "sg:postcode":"16354",
    "sg:province":"PA",
    "sg:tags":[
        "physician",
        "surgeon"
    ],
    "wof:name":"Medical Assistance Trnsprtn",
    "wof:placetype":"venue"
},
  "geometry": {"coordinates":[-79.67324499999999,41.624435],"type":"Point"}
}