{
  "type": "Feature",
  "properties": {
    "addr:full":"435 Baylor Rd Muncy PA 17756",
    "addr:housenumber":"435",
    "addr:postcode":"17756",
    "addr:street":"Baylor Rd",
    "iso:country":"US",
    "sg:address":"435 Baylor Rd",
    "sg:city":"Muncy",
    "sg:classifiers":[
        {
            "category":"Retail",
            "subcategory":"Repair Shop",
            "type":"Services"
        }
    ],
    "sg:phone":"+1 570 546 2690",
    "sg:postcode":"17756",
    "sg:province":"PA",
    "sg:tags":[
        "welding"
    ],
    "wof:name":"Mull's Metal",
    "wof:placetype":"venue"
},
  "geometry": {"coordinates":[-76.622635,41.172427],"type":"Point"}
}