{
  "type": "Feature",
  "properties": {
    "iso:country":"US",
    "sg:address":"5915 Beacon St",
    "sg:city":"Pittsburgh",
    "sg:classifiers":[
        {
            "category":"Shopping",
            "type":"Retail Goods"
        }
    ],
    "sg:phone":"+1   ",
    "sg:postcode":"15217",
    "sg:province":"PA",
    "sg:tags":[
        "merchandise"
    ],
    "wof:name":"Sisterhood",
    "wof:placetype":"venue"
},
  "geometry": {"coordinates":[-79.92086399999999,40.435062],"type":"Point"}
}