{
  "type": "Feature",
  "properties": {
    "iso:country":"US",
    "sg:address":"178 High St",
    "sg:city":"Wilkes Barre",
    "sg:classifiers":[
        {
            "category":"Shopping",
            "subcategory":"Computers & Home Electronics",
            "type":"Retail Goods"
        }
    ],
    "sg:phone":"+1 570 830 4044",
    "sg:postcode":"18702",
    "sg:province":"PA",
    "sg:tags":[
        "equipment",
        "dealer"
    ],
    "wof:name":"Comptoys Computers",
    "wof:placetype":"venue"
},
  "geometry": {"coordinates":[-75.89700000000001,41.235216],"type":"Point"}
}