{
  "type": "Feature",
  "properties": {
    "addr:full":"203 Salem Church Rd Midland PA 15059",
    "addr:housenumber":"203",
    "addr:postcode":"15059",
    "addr:street":"Salem Church Rd",
    "iso:country":"US",
    "sg:address":"203 Salem Church Rd",
    "sg:city":"Midland",
    "sg:classifiers":[
        {
            "category":"Building & Trades",
            "subcategory":"Construction",
            "type":"Services"
        }
    ],
    "sg:phone":"+1   ",
    "sg:postcode":"15059",
    "sg:province":"PA",
    "sg:tags":[
        "house"
    ],
    "wof:name":"Thumms Construction",
    "wof:placetype":"venue"
},
  "geometry": {"coordinates":[-80.48178,40.697392],"type":"Point"}
}