{
  "type": "Feature",
  "properties": {
    "iso:country":"US",
    "sg:address":"1211 Inverness St",
    "sg:city":"Pittsburgh",
    "sg:classifiers":[
        {
            "category":"Real Estate",
            "subcategory":"Real Estate Agent",
            "type":"Services"
        }
    ],
    "sg:phone":"+1   ",
    "sg:postcode":"15217",
    "sg:province":"PA",
    "wof:name":"Warren J Shapera",
    "wof:placetype":"venue"
},
  "geometry": {"coordinates":[-79.93175599999999,40.443577],"type":"Point"}
}