{
  "type": "Feature",
  "properties": {
    "addr:full":"920 Berkshire Ave Pittsburgh PA 15226",
    "addr:housenumber":"920",
    "addr:postcode":"15226",
    "addr:street":"Berkshire Ave",
    "iso:country":"US",
    "sg:address":"920 Berkshire Ave",
    "sg:city":"Pittsburgh",
    "sg:classifiers":[
        {
            "category":"Education",
            "subcategory":"Special Training",
            "type":"Public Place"
        }
    ],
    "sg:phone":"+1 412 341 6912",
    "sg:postcode":"15226",
    "sg:province":"PA",
    "sg:tags":[
        "instruction",
        "music"
    ],
    "wof:name":"Anthony's Guitars",
    "wof:placetype":"venue"
},
  "geometry": {"coordinates":[-80.018276,40.3912],"type":"Point"}
}