{
  "type": "Feature",
  "properties": {
    "iso:country":"US",
    "sg:address":"3200 Trindle Rd",
    "sg:city":"Camp Hill",
    "sg:classifiers":[
        {
            "category":"Shopping",
            "subcategory":"Mobile Phones",
            "type":"Retail Goods"
        }
    ],
    "sg:phone":"+1 717 761 2515",
    "sg:postcode":"17011",
    "sg:province":"PA",
    "sg:website":"sprint.com",
    "wof:name":"Sprint",
    "wof:placetype":"venue"
},
  "geometry": {"coordinates":[-76.934425,40.238695],"type":"Point"}
}