{
  "type": "Feature",
  "properties": {
    "addr:full":"525 Church St New Ringgold PA 17960",
    "addr:housenumber":"525",
    "addr:postcode":"17960",
    "addr:street":"Church St",
    "iso:country":"US",
    "sg:address":"525 Church St",
    "sg:city":"New Ringgold",
    "sg:classifiers":[
        {
            "category":"Organizations",
            "subcategory":"Religious Organization",
            "type":"Services"
        }
    ],
    "sg:phone":"+1 570 943 2007",
    "sg:postcode":"17960",
    "sg:province":"PA",
    "sg:tags":[
        "church"
    ],
    "wof:name":"Freidens Lutheran Church",
    "wof:placetype":"venue"
},
  "geometry": {"coordinates":[-76.008712,40.688395],"type":"Point"}
}