{
  "type": "Feature",
  "properties": {
    "addr:full":"99 Miller St Braddock PA 15104",
    "addr:housenumber":"99",
    "addr:postcode":"15104",
    "addr:street":"Miller St",
    "iso:country":"US",
    "sg:address":"99 Miller St",
    "sg:city":"Braddock",
    "sg:classifiers":[
        {
            "category":"Building & Trades",
            "subcategory":"Equipment Rental",
            "type":"Services"
        }
    ],
    "sg:phone":"+1   ",
    "sg:postcode":"15104",
    "sg:province":"PA",
    "sg:tags":[
        "product",
        "retail",
        "safety"
    ],
    "wof:name":"Fei Safety & Supply Inc",
    "wof:placetype":"venue"
},
  "geometry": {"coordinates":[-79.884855,40.415958],"type":"Point"}
}