{
  "type": "Feature",
  "properties": {
    "iso:country":"US",
    "sg:address":"1123 Crestwood Dr",
    "sg:city":"Pottstown",
    "sg:classifiers":[
        {
            "category":"Building & Trades",
            "subcategory":"Construction",
            "type":"Services"
        }
    ],
    "sg:phone":"+1 610 970 1476",
    "sg:postcode":"19464",
    "sg:province":"PA",
    "sg:tags":[
        "tile",
        "dealer"
    ],
    "wof:name":"Mac Farland Restoration Svc",
    "wof:placetype":"venue"
},
  "geometry": {"coordinates":[-75.614046,40.257684],"type":"Point"}
}