{
  "type": "Feature",
  "properties": {
    "iso:country":"US",
    "sg:address":"27 N Front St",
    "sg:city":"Harrisburg",
    "sg:classifiers":[
        {
            "category":"Organizations",
            "subcategory":"Non-profit Organization",
            "type":"Services"
        }
    ],
    "sg:phone":"+1   ",
    "sg:postcode":"17101",
    "sg:province":"PA",
    "sg:tags":[
        "association",
        "social"
    ],
    "wof:name":"Casey For Treasurer Committee",
    "wof:placetype":"venue"
},
  "geometry": {"coordinates":[-76.88422199999999,40.259348],"type":"Point"}
}