{
  "type": "Feature",
  "properties": {
    "iso:country":"US",
    "sg:address":"50 W Stoever Ave",
    "sg:city":"Myerstown",
    "sg:classifiers":[
        {
            "category":"Home & Garden",
            "subcategory":"Building Materials",
            "type":"Retail Goods"
        }
    ],
    "sg:phone":"+1 717 866 2167",
    "sg:postcode":"17067",
    "sg:province":"PA",
    "sg:tags":[
        "lumber"
    ],
    "sg:website":"www.stockbuildingsupply.com",
    "wof:name":"Stock Building Supply",
    "wof:placetype":"venue"
},
  "geometry": {"coordinates":[-76.304582,40.365888],"type":"Point"}
}