{
  "type": "Feature",
  "properties": {
    "addr:full":"62 W Green St Nanticoke PA 18634",
    "addr:housenumber":"62",
    "addr:postcode":"18634",
    "addr:street":"W Green St",
    "iso:country":"US",
    "sg:address":"62 W Green St",
    "sg:city":"Nanticoke",
    "sg:classifiers":[
        {
            "category":"Restaurant",
            "type":"Food & Drink"
        }
    ],
    "sg:phone":"+1 570 735 3533",
    "sg:postcode":"18634",
    "sg:province":"PA",
    "wof:name":"Green Street's Restaurant",
    "wof:placetype":"venue"
},
  "geometry": {"coordinates":[-76.004738,41.201111],"type":"Point"}
}