{
  "type": "Feature",
  "properties": {
    "iso:country":"US",
    "sg:address":"1672 Fairway Dr",
    "sg:city":"Jamison",
    "sg:classifiers":[
        {
            "category":"Health Services",
            "subcategory":"Doctor",
            "type":"Services"
        }
    ],
    "sg:phone":"+1 215 343 0900",
    "sg:postcode":"18929",
    "sg:province":"PA",
    "sg:tags":[
        "dentist"
    ],
    "wof:name":"Susan S Plotnich DDS",
    "wof:placetype":"venue"
},
  "geometry": {"coordinates":[-75.09200199999999,40.261034],"type":"Point"}
}