{
  "type": "Feature",
  "properties": {
    "addr:full":"28 Susquehanna Trl Selinsgrove PA 17870",
    "addr:housenumber":"28",
    "addr:postcode":"17870",
    "addr:street":"Susquehanna Trl",
    "iso:country":"US",
    "sg:address":"28 Susquehanna Trl",
    "sg:city":"Selinsgrove",
    "sg:classifiers":[
        {
            "category":"Restaurant",
            "type":"Food & Drink"
        }
    ],
    "sg:menulink":"http://www.allmenus.com/pa/monroe/170798-burger-king/menu/",
    "sg:phone":"+1 570 743 7617",
    "sg:postcode":"17870",
    "sg:province":"PA",
    "sg:tags":[
        "burger",
        "american"
    ],
    "wof:name":"Burger King",
    "wof:placetype":"venue"
},
  "geometry": {"coordinates":[-76.835426,40.83522],"type":"Point"}
}