{
  "type": "Feature",
  "properties": {
    "iso:country":"US",
    "sg:address":"500 W Rosedale Ave",
    "sg:city":"West Chester",
    "sg:classifiers":[
        {
            "category":"Real Estate",
            "subcategory":"Real Estate Operator",
            "type":"Services"
        }
    ],
    "sg:phone":"+1 610 696 5140",
    "sg:postcode":"19382",
    "sg:province":"PA",
    "sg:tags":[
        "apartment"
    ],
    "wof:name":"Cambridge Hall Apartments",
    "wof:placetype":"venue"
},
  "geometry": {"coordinates":[-75.606499,39.9464],"type":"Point"}
}