{
  "type": "Feature",
  "properties": {
    "iso:country":"US",
    "sg:address":"1422 Valley View Blvd",
    "sg:city":"Altoona",
    "sg:classifiers":[
        {
            "category":"Autos & Motor Vehicles",
            "subcategory":"Automobile Sales",
            "type":"Retail Goods"
        }
    ],
    "sg:phone":"+1 814 940 1216",
    "sg:postcode":"16602",
    "sg:province":"PA",
    "sg:tags":[
        "used"
    ],
    "wof:name":"Mountain Motors",
    "wof:placetype":"venue"
},
  "geometry": {"coordinates":[-78.386083,40.502965],"type":"Point"}
}