{
  "type": "Feature",
  "properties": {
    "iso:country":"US",
    "sg:address":"273 Old Mill Rd",
    "sg:city":"Apollo",
    "sg:classifiers":[
        {
            "category":"Freight",
            "type":"Transportation"
        }
    ],
    "sg:phone":"+1   ",
    "sg:postcode":"15613",
    "sg:province":"PA",
    "sg:tags":[
        "general"
    ],
    "wof:name":"Storage Place",
    "wof:placetype":"venue"
},
  "geometry": {"coordinates":[-79.575282,40.569345],"type":"Point"}
}