{
  "type": "Feature",
  "properties": {
    "iso:country":"US",
    "sg:address":"1260 W Philadelphia Ave",
    "sg:city":"Boyertown",
    "sg:classifiers":[
        {
            "category":"Banks & Credit Unions",
            "subcategory":"Financial Services",
            "type":"Services"
        }
    ],
    "sg:phone":"+1   ",
    "sg:postcode":"19512",
    "sg:province":"PA",
    "sg:tags":[
        "investor"
    ],
    "wof:name":"Ardie M Ruth",
    "wof:placetype":"venue"
},
  "geometry": {"coordinates":[-75.66597400000001,40.35898],"type":"Point"}
}