{
  "type": "Feature",
  "properties": {
    "addr:full":"1066 Clamtown Rd Tamaqua PA 18252",
    "addr:housenumber":"1066",
    "addr:postcode":"18252",
    "addr:street":"Clamtown Rd",
    "iso:country":"US",
    "sg:address":"1066 Clamtown Rd",
    "sg:city":"Tamaqua",
    "sg:classifiers":[
        {
            "category":"Retail",
            "subcategory":"Auto Repair",
            "type":"Services"
        }
    ],
    "sg:phone":"+1 570 386 8288",
    "sg:postcode":"18252",
    "sg:province":"PA",
    "sg:tags":[
        "repairing",
        "automobile"
    ],
    "wof:name":"Nothstein Auto Repair",
    "wof:placetype":"venue"
},
  "geometry": {"coordinates":[-75.959575,40.748908],"type":"Point"}
}