{
  "type": "Feature",
  "properties": {
    "iso:country":"US",
    "sg:address":"637 N Center St",
    "sg:city":"Corry",
    "sg:classifiers":[
        {
            "category":"Manufacturing",
            "subcategory":"Paper Products",
            "type":"Manufacturing & Wholesale Goods"
        }
    ],
    "sg:phone":"+1 814 664 4433",
    "sg:postcode":"16407",
    "sg:province":"PA",
    "sg:tags":[
        "label"
    ],
    "sg:website":"www.thermallabelwarehouse.com",
    "wof:name":"Thermal Label Warehouse Inc",
    "wof:placetype":"venue"
},
  "geometry": {"coordinates":[-79.641462,41.927336],"type":"Point"}
}