{
  "type": "Feature",
  "properties": {
    "addr:full":"21 Church Rd Scenery Hill PA 15360",
    "addr:housenumber":"21",
    "addr:postcode":"15360",
    "addr:street":"Church Rd",
    "iso:country":"US",
    "sg:address":"21 Church Rd",
    "sg:city":"Scenery Hill",
    "sg:classifiers":[
        {
            "category":"Organizations",
            "subcategory":"Religious Organization",
            "type":"Services"
        }
    ],
    "sg:phone":"+1 724 945 5198",
    "sg:postcode":"15360",
    "sg:province":"PA",
    "wof:name":"Bethlehem Lutheran Church",
    "wof:placetype":"venue"
},
  "geometry": {"coordinates":[-80.133965,40.113979],"type":"Point"}
}