{
  "type": "Feature",
  "properties": {
    "addr:full":"1016 South St Philadelphia PA 19147",
    "addr:housenumber":"1016",
    "addr:postcode":"19147",
    "addr:street":"South St",
    "iso:country":"US",
    "sg:address":"1016 South St",
    "sg:city":"Philadelphia",
    "sg:classifiers":[
        {
            "category":"Social Services",
            "type":"Services"
        }
    ],
    "sg:phone":"+1 215 922 1217",
    "sg:postcode":"19147",
    "sg:province":"PA",
    "sg:tags":[
        "youth",
        "organization",
        "center"
    ],
    "wof:name":"Reach To Your Youth Mentor",
    "wof:placetype":"venue"
},
  "geometry": {"coordinates":[-75.15977599999999,39.942945],"type":"Point"}
}