{
  "type": "Feature",
  "properties": {
    "iso:country":"US",
    "sg:address":"2022 Golfway Dr",
    "sg:city":"Aliquippa",
    "sg:classifiers":[
        {
            "category":"Building & Trades",
            "subcategory":"Plumbing",
            "type":"Services"
        }
    ],
    "sg:phone":"+1 724 375 9394",
    "sg:postcode":"15001",
    "sg:province":"PA",
    "sg:tags":[
        "plumber",
        "industrial",
        "contractors-commercial"
    ],
    "wof:name":"Clark Plumbing",
    "wof:placetype":"venue"
},
  "geometry": {"coordinates":[-80.293668,40.614507],"type":"Point"}
}