{
  "type": "Feature",
  "properties": {
    "iso:country":"US",
    "sg:address":"22 Lincoln Ave",
    "sg:city":"Jeannette",
    "sg:classifiers":[
        {
            "category":"Freight",
            "type":"Transportation"
        }
    ],
    "sg:phone":"+1   ",
    "sg:postcode":"15644",
    "sg:province":"PA",
    "sg:tags":[
        "courier"
    ],
    "wof:name":"M L D Courier",
    "wof:placetype":"venue"
},
  "geometry": {"coordinates":[-79.617434,40.307604],"type":"Point"}
}