{
  "type": "Feature",
  "properties": {
    "iso:country":"US",
    "sg:address":"25 Breckenridge Dr",
    "sg:city":"Warminster",
    "sg:classifiers":[
        {
            "category":"Professional",
            "subcategory":"Accounting & Tax Preparation",
            "type":"Services"
        }
    ],
    "sg:phone":"+1   ",
    "sg:postcode":"18974",
    "sg:province":"PA",
    "wof:name":"Facer Mee & Associates CPA",
    "wof:placetype":"venue"
},
  "geometry": {"coordinates":[-75.04093899999999,40.232455],"type":"Point"}
}