{
  "type": "Feature",
  "properties": {
    "iso:country":"US",
    "sg:address":"1270 Township Line Rd",
    "sg:city":"Drexel Hill",
    "sg:classifiers":[
        {
            "category":"Banks & Credit Unions",
            "subcategory":"Bank",
            "type":"Services"
        }
    ],
    "sg:phone":"+1   ",
    "sg:postcode":"19026",
    "sg:province":"PA",
    "sg:tags":[
        "national",
        "commercial"
    ],
    "wof:name":"Township Line Office",
    "wof:placetype":"venue"
},
  "geometry": {"coordinates":[-75.29577999999999,39.967839],"type":"Point"}
}