{
  "type": "Feature",
  "properties": {
    "iso:country":"US",
    "sg:address":"6907 Rising Sun Ave",
    "sg:city":"Philadelphia",
    "sg:classifiers":[
        {
            "category":"Recreation",
            "type":"Entertainment"
        }
    ],
    "sg:phone":"+1 215 728 9380",
    "sg:postcode":"19111",
    "sg:province":"PA",
    "sg:tags":[
        "karate",
        "judo",
        "instr"
    ],
    "wof:name":"Pennsylvania Ki-Aikido",
    "wof:placetype":"venue"
},
  "geometry": {"coordinates":[-75.088381,40.056851],"type":"Point"}
}