{
  "type": "Feature",
  "properties": {
    "iso:country":"US",
    "sg:address":"914 E Clair St",
    "sg:city":"Allentown",
    "sg:classifiers":[
        {
            "category":"Autos & Motor Vehicles",
            "subcategory":"Automobile Sales",
            "type":"Retail Goods"
        }
    ],
    "sg:phone":"+1 610 435 1900",
    "sg:postcode":"18109",
    "sg:province":"PA",
    "sg:tags":[
        "used"
    ],
    "wof:name":"John Sam Motors",
    "wof:placetype":"venue"
},
  "geometry": {"coordinates":[-75.441487,40.616386],"type":"Point"}
}