{
  "type": "Feature",
  "properties": {
    "addr:full":"235 Moyers Station Rd Schuylkill Haven PA 17972",
    "addr:housenumber":"235",
    "addr:postcode":"17972",
    "addr:street":"Moyers Station Rd",
    "iso:country":"US",
    "sg:address":"235 Moyers Station Rd",
    "sg:city":"Schuylkill Haven",
    "sg:classifiers":[
        {
            "category":"Building & Trades",
            "subcategory":"Construction",
            "type":"Services"
        }
    ],
    "sg:phone":"+1   ",
    "sg:postcode":"17972",
    "sg:province":"PA",
    "wof:name":"Ulsh S Stake House",
    "wof:placetype":"venue"
},
  "geometry": {"coordinates":[-76.281291,40.540682],"type":"Point"}
}