{
  "type": "Feature",
  "properties": {
    "addr:full":"3325 Wahoo Dr Williamsport PA 17701",
    "addr:housenumber":"3325",
    "addr:postcode":"17701",
    "addr:street":"Wahoo Dr",
    "iso:country":"US",
    "sg:address":"3325 Wahoo Dr",
    "sg:city":"Williamsport",
    "sg:classifiers":[
        {
            "category":"Manufacturing",
            "subcategory":"Paper Products",
            "type":"Manufacturing & Wholesale Goods"
        }
    ],
    "sg:phone":"+1 570 326 1244",
    "sg:postcode":"17701",
    "sg:province":"PA",
    "sg:tags":[
        "print",
        "lithographic",
        "mfg"
    ],
    "wof:name":"Labels By Pulizzi Inc",
    "wof:placetype":"venue"
},
  "geometry": {"coordinates":[-77.079542,41.233434],"type":"Point"}
}