{
  "type": "Feature",
  "properties": {
    "iso:country":"US",
    "sg:address":"204 Gale Ln",
    "sg:city":"Kennett Square",
    "sg:classifiers":[
        {
            "category":"Manufacturing",
            "subcategory":"Electronics",
            "type":"Manufacturing & Wholesale Goods"
        }
    ],
    "sg:phone":"+1 610 444 1000",
    "sg:postcode":"19348",
    "sg:province":"PA",
    "sg:tags":[
        "communications",
        "equipment"
    ],
    "sg:website":"www.tri-mgroup.com",
    "wof:name":"Tri-M Eletrical Constr LLC",
    "wof:placetype":"venue"
},
  "geometry": {"coordinates":[-75.703631,39.852231],"type":"Point"}
}