{
  "type": "Feature",
  "properties": {
    "iso:country":"US",
    "sg:address":"900 Vine Rd",
    "sg:city":"Saint Marys",
    "sg:classifiers":[
        {
            "category":"Wholesale",
            "subcategory":"Electrical",
            "type":"Manufacturing & Wholesale Goods"
        }
    ],
    "sg:phone":"+1   ",
    "sg:postcode":"15857",
    "sg:province":"PA",
    "sg:tags":[
        "disposal",
        "trash"
    ],
    "wof:name":"A James Groll Container Svc",
    "wof:placetype":"venue"
},
  "geometry": {"coordinates":[-78.543899,41.411697],"type":"Point"}
}