{
  "type": "Feature",
  "properties": {
    "iso:country":"US",
    "sg:address":"807 Goucher St",
    "sg:city":"Johnstown",
    "sg:classifiers":[
        {
            "category":"Social Services",
            "subcategory":"Child Care",
            "type":"Services"
        }
    ],
    "sg:phone":"+1   ",
    "sg:postcode":"15905",
    "sg:province":"PA",
    "sg:tags":[
        "day"
    ],
    "wof:name":"Adult Day Activities Program",
    "wof:placetype":"venue"
},
  "geometry": {"coordinates":[-78.949085,40.306978],"type":"Point"}
}