{
  "type": "Feature",
  "properties": {
    "iso:country":"US",
    "sg:address":"1028 School St",
    "sg:city":"Sharon Hill",
    "sg:classifiers":[
        {
            "category":"Organizations",
            "subcategory":"Religious Organization",
            "type":"Services"
        }
    ],
    "sg:phone":"+1   ",
    "sg:postcode":"19079",
    "sg:province":"PA",
    "wof:name":"Holy Spirit Parish",
    "wof:placetype":"venue"
},
  "geometry": {"coordinates":[-75.271148,39.906401],"type":"Point"}
}