{
  "type": "Feature",
  "properties": {
    "addr:full":"201 Park Ave Windber PA 15963",
    "addr:housenumber":"201",
    "addr:postcode":"15963",
    "addr:street":"Park Ave",
    "iso:country":"US",
    "sg:address":"201 Park Ave",
    "sg:city":"Windber",
    "sg:classifiers":[
        {
            "category":"Retail",
            "subcategory":"Portrait Studio",
            "type":"Services"
        }
    ],
    "sg:phone":"+1 814 467 5634",
    "sg:postcode":"15963",
    "sg:province":"PA",
    "sg:tags":[
        "photographer"
    ],
    "wof:name":"David Grush Photography",
    "wof:placetype":"venue"
},
  "geometry": {"coordinates":[-78.838734,40.245533],"type":"Point"}
}