{
  "type": "Feature",
  "properties": {
    "iso:country":"US",
    "sg:address":"3100 Robinson Ln",
    "sg:city":"Pittsburgh",
    "sg:classifiers":[
        {
            "category":"Personal",
            "type":"Services"
        }
    ],
    "sg:phone":"+1 412 787 2480",
    "sg:postcode":"15201",
    "sg:province":"PA",
    "sg:tags":[
        "party",
        "planning",
        "event"
    ],
    "wof:name":"Masquerade",
    "wof:placetype":"venue"
},
  "geometry": {"coordinates":[-80.16497099999999,40.452737],"type":"Point"}
}