{
  "type": "Feature",
  "properties": {
    "iso:country":"US",
    "sg:address":"24 Diana Cir",
    "sg:city":"Nottingham",
    "sg:classifiers":[
        {
            "category":"Building & Trades",
            "subcategory":"Construction",
            "type":"Services"
        }
    ],
    "sg:phone":"+1   ",
    "sg:postcode":"19362",
    "sg:province":"PA",
    "sg:tags":[
        "hanging",
        "contractor"
    ],
    "wof:name":"James Moore Painting Inc",
    "wof:placetype":"venue"
},
  "geometry": {"coordinates":[-76.04472699999999,39.762966],"type":"Point"}
}