{
  "type": "Feature",
  "properties": {
    "addr:full":"1525 Locust St Philadelphia PA 19102",
    "addr:housenumber":"1525",
    "addr:postcode":"19102",
    "addr:street":"Locust St",
    "iso:country":"US",
    "sg:address":"1525 Locust St",
    "sg:city":"Philadelphia",
    "sg:classifiers":[
        {
            "category":"Health Services",
            "subcategory":"Doctor",
            "type":"Services"
        }
    ],
    "sg:phone":"+1 215 735 6104",
    "sg:postcode":"19102",
    "sg:province":"PA",
    "sg:tags":[
        "physician",
        "surgeon"
    ],
    "wof:name":"Ronald B Greene MD",
    "wof:placetype":"venue"
},
  "geometry": {"coordinates":[-75.16771199999999,39.948672],"type":"Point"}
}