{
  "type": "Feature",
  "properties": {
    "iso:country":"US",
    "sg:address":"205 Shepard Ln",
    "sg:city":"Chalfont",
    "sg:classifiers":[
        {
            "category":"Travel",
            "subcategory":"Travel Agent",
            "type":"Entertainment"
        }
    ],
    "sg:phone":"+1   ",
    "sg:postcode":"18914",
    "sg:province":"PA",
    "sg:tags":[
        "agency"
    ],
    "wof:name":"Cirrus Travel",
    "wof:placetype":"venue"
},
  "geometry": {"coordinates":[-75.192153,40.260058],"type":"Point"}
}