{
  "type": "Feature",
  "properties": {
    "iso:country":"US",
    "sg:address":"161 Modena Rd",
    "sg:city":"Coatesville",
    "sg:classifiers":[
        {
            "category":"Manufacturing",
            "subcategory":"Chemicals & Compounds",
            "type":"Manufacturing & Wholesale Goods"
        }
    ],
    "sg:phone":"+1 610 384 8105",
    "sg:postcode":"19320",
    "sg:province":"PA",
    "sg:tags":[
        "gas"
    ],
    "wof:name":"Air Liquide America Corp",
    "wof:placetype":"venue"
},
  "geometry": {"coordinates":[-75.803495,39.967417],"type":"Point"}
}