{
  "type": "Feature",
  "properties": {
    "iso:country":"US",
    "sg:address":"1355 Orchard Dr",
    "sg:city":"Chambersburg",
    "sg:classifiers":[
        {
            "category":"Banks & Credit Unions",
            "subcategory":"Bank",
            "type":"Services"
        }
    ],
    "sg:phone":"+1 717 532 6114",
    "sg:postcode":"17201",
    "sg:province":"PA",
    "wof:name":"Orrstown Bank",
    "wof:placetype":"venue"
},
  "geometry": {"coordinates":[-77.659509,39.91362],"type":"Point"}
}