{
  "type": "Feature",
  "properties": {
    "addr:full":"450 Mill Ln Muncy PA 17756",
    "addr:housenumber":"450",
    "addr:postcode":"17756",
    "addr:street":"Mill Ln",
    "iso:country":"US",
    "sg:address":"450 Mill Ln",
    "sg:city":"Muncy",
    "sg:classifiers":[
        {
            "category":"Building & Trades",
            "subcategory":"Construction",
            "type":"Services"
        }
    ],
    "sg:phone":"+1   ",
    "sg:postcode":"17756",
    "sg:province":"PA",
    "sg:tags":[
        "excavation",
        "contractor"
    ],
    "wof:name":"Terrys Excavating",
    "wof:placetype":"venue"
},
  "geometry": {"coordinates":[-76.60915,41.228671],"type":"Point"}
}