{
  "type": "Feature",
  "properties": {
    "iso:country":"US",
    "sg:address":"2381 State Route 66 ",
    "sg:city":"Delmont",
    "sg:classifiers":[
        {
            "category":"Restaurant",
            "type":"Food & Drink"
        }
    ],
    "sg:menulink":"http://www.allmenus.com/pa/delmont/286886-premiere-pizza/menu/",
    "sg:phone":"+1 724 468 6776",
    "sg:postcode":"15626",
    "sg:province":"PA",
    "sg:tags":[
        "american",
        "pizza"
    ],
    "wof:name":"Premiere Pizza",
    "wof:placetype":"venue"
},
  "geometry": {"coordinates":[-79.572419,40.409278],"type":"Point"}
}