{
  "type": "Feature",
  "properties": {
    "iso:country":"US",
    "sg:address":"21382 N Norrisville Rd",
    "sg:city":"Conneautville",
    "sg:classifiers":[
        {
            "category":"Building & Trades",
            "subcategory":"Construction",
            "type":"Services"
        }
    ],
    "sg:phone":"+1 814 587 3653",
    "sg:postcode":"16406",
    "sg:province":"PA",
    "sg:tags":[
        "contractor"
    ],
    "wof:name":"Foltz Construction",
    "wof:placetype":"venue"
},
  "geometry": {"coordinates":[-80.269046,41.755934],"type":"Point"}
}