{
  "type": "Feature",
  "properties": {
    "addr:full":"4 Amherst Ave Pittsburgh PA 15229",
    "addr:housenumber":"4",
    "addr:postcode":"15229",
    "addr:street":"Amherst Ave",
    "iso:country":"US",
    "sg:address":"4 Amherst Ave",
    "sg:city":"Pittsburgh",
    "sg:classifiers":[
        {
            "category":"Building & Trades",
            "subcategory":"Construction",
            "type":"Services"
        }
    ],
    "sg:phone":"+1   ",
    "sg:postcode":"15229",
    "sg:province":"PA",
    "sg:tags":[
        "hanging",
        "contractor"
    ],
    "wof:name":"Schmidt Painting",
    "wof:placetype":"venue"
},
  "geometry": {"coordinates":[-80.044631,40.519394],"type":"Point"}
}