{
  "type": "Feature",
  "properties": {
    "addr:full":"26 W Broadway Jim Thorpe PA 18229",
    "addr:housenumber":"26",
    "addr:postcode":"18229",
    "addr:street":"W Broadway",
    "iso:country":"US",
    "sg:address":"26 W Broadway",
    "sg:city":"Jim Thorpe",
    "sg:classifiers":[
        {
            "category":"Professional",
            "subcategory":"Lawyer & Legal Services",
            "type":"Services"
        }
    ],
    "sg:phone":"+1 570 325 3300",
    "sg:postcode":"18229",
    "sg:province":"PA",
    "sg:tags":[
        "attorney"
    ],
    "wof:name":"Michael Muffley",
    "wof:placetype":"venue"
},
  "geometry": {"coordinates":[-75.746921,40.863646],"type":"Point"}
}