{
  "type": "Feature",
  "properties": {
    "iso:country":"US",
    "sg:address":"295 Buck Rd",
    "sg:city":"Southampton",
    "sg:classifiers":[
        {
            "category":"Health Services",
            "subcategory":"Doctor",
            "type":"Services"
        }
    ],
    "sg:phone":"+1   ",
    "sg:postcode":"18966",
    "sg:province":"PA",
    "sg:tags":[
        "medical"
    ],
    "wof:name":"Sharma Meena MD",
    "wof:placetype":"venue"
},
  "geometry": {"coordinates":[-74.98654999999999,40.17376],"type":"Point"}
}