{
  "type": "Feature",
  "properties": {
    "addr:full":"111 Berkshire Ln Avondale PA 19311",
    "addr:housenumber":"111",
    "addr:postcode":"19311",
    "addr:street":"Berkshire Ln",
    "iso:country":"US",
    "sg:address":"111 Berkshire Ln",
    "sg:city":"Avondale",
    "sg:classifiers":[
        {
            "category":"Recreation",
            "type":"Entertainment"
        }
    ],
    "sg:phone":"+1 610 268 8538",
    "sg:postcode":"19311",
    "sg:province":"PA",
    "sg:tags":[
        "trainer",
        "club",
        "membership"
    ],
    "wof:name":"Hartefeld Swim & Fitness Club",
    "wof:placetype":"venue"
},
  "geometry": {"coordinates":[-75.72729699999999,39.804131],"type":"Point"}
}