{
  "type": "Feature",
  "properties": {
    "addr:full":"5523 Sprague St Philadelphia PA 19138",
    "addr:postcode":"5523;19138",
    "addr:street":"Sprague St",
    "iso:country":"US",
    "sg:address":"5523 Sprague St",
    "sg:city":"Philadelphia",
    "sg:classifiers":[
        {
            "category":"Organizations",
            "subcategory":"Community Association",
            "type":"Services"
        }
    ],
    "sg:phone":"+1   ",
    "sg:postcode":"19138",
    "sg:province":"PA",
    "wof:name":"Henry Hopkins American Legion",
    "wof:placetype":"venue"
},
  "geometry": {"coordinates":[-75.159227,40.047126],"type":"Point"}
}