{
  "type": "Feature",
  "properties": {
    "addr:full":"518 Georgian Pl Somerset PA 15501",
    "addr:housenumber":"518",
    "addr:postcode":"15501",
    "addr:street":"Georgian Pl",
    "iso:country":"US",
    "sg:address":"518 Georgian Pl",
    "sg:city":"Somerset",
    "sg:classifiers":[
        {
            "category":"Banks & Credit Unions",
            "subcategory":"Bank",
            "type":"Services"
        }
    ],
    "sg:phone":"+1 814 445 3574",
    "sg:postcode":"15501",
    "sg:province":"PA",
    "sg:tags":[
        "financing"
    ],
    "wof:name":"American General Consumer Disc",
    "wof:placetype":"venue"
},
  "geometry": {"coordinates":[-79.073213,40.022685],"type":"Point"}
}