{
  "type": "Feature",
  "properties": {
    "iso:country":"US",
    "sg:address":"854 Conestoga Rd",
    "sg:city":"Bryn Mawr",
    "sg:classifiers":[
        {
            "category":"Retail",
            "subcategory":"Auto Repair",
            "type":"Services"
        }
    ],
    "sg:phone":"+1 610 527 2673",
    "sg:postcode":"19010",
    "sg:province":"PA",
    "sg:tags":[
        "repairing",
        "automobile"
    ],
    "wof:name":"Garrett Hill Auto Svc",
    "wof:placetype":"venue"
},
  "geometry": {"coordinates":[-75.33761199999999,40.02555],"type":"Point"}
}