{
  "type": "Feature",
  "properties": {
    "addr:full":"1017 Highland Ave Bethlehem PA 18018",
    "addr:housenumber":"1017",
    "addr:postcode":"18018",
    "addr:street":"Highland Ave",
    "iso:country":"US",
    "sg:address":"1017 Highland Ave",
    "sg:city":"Bethlehem",
    "sg:classifiers":[
        {
            "category":"Building & Trades",
            "subcategory":"Construction",
            "type":"Services"
        }
    ],
    "sg:phone":"+1 610 882 9657",
    "sg:postcode":"18018",
    "sg:province":"PA",
    "sg:tags":[
        "handyman"
    ],
    "wof:name":"EJS Enterprises",
    "wof:placetype":"venue"
},
  "geometry": {"coordinates":[-75.409026,40.629214],"type":"Point"}
}