{
  "type": "Feature",
  "properties": {
    "addr:full":"20 York St Hanover PA 17331",
    "addr:housenumber":"20",
    "addr:postcode":"17331",
    "addr:street":"York St",
    "iso:country":"US",
    "sg:address":"20 York St",
    "sg:city":"Hanover",
    "sg:classifiers":[
        {
            "category":"Arts & Performance",
            "subcategory":"Theater",
            "type":"Entertainment"
        }
    ],
    "sg:phone":"+1 717 632 6313",
    "sg:postcode":"17331",
    "sg:province":"PA",
    "sg:tags":[
        "band",
        "orchestra"
    ],
    "wof:name":"Lyric Band",
    "wof:placetype":"venue"
},
  "geometry": {"coordinates":[-76.98256499999999,39.801025],"type":"Point"}
}