{
  "type": "Feature",
  "properties": {
    "addr:full":"4451 Lincoln Hwy York PA 17406",
    "addr:housenumber":"4451",
    "addr:postcode":"17406",
    "addr:street":"Lincoln Hwy",
    "iso:country":"US",
    "sg:address":"4451 Lincoln Hwy",
    "sg:city":"York",
    "sg:classifiers":[
        {
            "category":"Retail",
            "subcategory":"Auto Rental",
            "type":"Services"
        }
    ],
    "sg:phone":"+1 717 757 4345",
    "sg:postcode":"17406",
    "sg:province":"PA",
    "sg:tags":[
        "renting",
        "truck",
        "leasing"
    ],
    "wof:name":"Penske Truck Rental",
    "wof:placetype":"venue"
},
  "geometry": {"coordinates":[-76.61864300000001,40.001556],"type":"Point"}
}