{
  "type": "Feature",
  "properties": {
    "iso:country":"US",
    "sg:address":"658 Pennfield Dr",
    "sg:city":"Hatfield",
    "sg:classifiers":[
        {
            "category":"Retail",
            "subcategory":"Repair Shop",
            "type":"Services"
        }
    ],
    "sg:phone":"+1 215 362 5642",
    "sg:postcode":"19440",
    "sg:province":"PA",
    "sg:tags":[
        "reupholstery",
        "furniture"
    ],
    "wof:name":"Renaissance Upholstery",
    "wof:placetype":"venue"
},
  "geometry": {"coordinates":[-75.306099,40.2673],"type":"Point"}
}