{
  "type": "Feature",
  "properties": {
    "addr:full":"117 S Custer Ave New Holland PA 17557",
    "addr:housenumber":"117",
    "addr:postcode":"17557",
    "addr:street":"S Custer Ave",
    "iso:country":"US",
    "sg:address":"117 S Custer Ave",
    "sg:city":"New Holland",
    "sg:classifiers":[
        {
            "category":"Building & Trades",
            "subcategory":"Construction",
            "type":"Services"
        }
    ],
    "sg:phone":"+1 717 354 4692",
    "sg:postcode":"17557",
    "sg:province":"PA",
    "sg:tags":[
        "television",
        "telephone",
        "cable",
        "contractor"
    ],
    "sg:website":"www.sptnetpower.com",
    "wof:name":"Supply Performance Testers Inc",
    "wof:placetype":"venue"
},
  "geometry": {"coordinates":[-76.090442,40.099468],"type":"Point"}
}