{
  "type": "Feature",
  "properties": {
    "addr:full":"5220A Umbria St Philadelphia PA 19128",
    "addr:housenumber":"5220a",
    "addr:postcode":"19128",
    "addr:street":"Umbria St",
    "iso:country":"US",
    "sg:address":"5220A Umbria St",
    "sg:city":"Philadelphia",
    "sg:classifiers":[
        {
            "category":"Autos & Motor Vehicles",
            "subcategory":"Automobile Sales",
            "type":"Retail Goods"
        },
        {
            "category":"Retail",
            "subcategory":"Auto Rental",
            "type":"Services"
        }
    ],
    "sg:phone":"+1 215 509 7109",
    "sg:postcode":"19128",
    "sg:province":"PA",
    "sg:tags":[
        "car",
        "leasing",
        "truck"
    ],
    "sg:website":"http://www.enterprise.com/car_rental/deeplinkmap.do?gpbr=1755&bid=004&cnty=US&arc=YPTRL01&cm_mmc=Yellowpages.com-_-IYP-_-Tradelisting-_-branch",
    "wof:name":"Enterprise Rent-A-Car",
    "wof:placetype":"venue"
},
  "geometry": {"coordinates":[-75.24078799999999,40.039014],"type":"Point"}
}