{
  "type": "Feature",
  "properties": {
    "iso:country":"US",
    "sg:address":"5000 Hanoverville Rd",
    "sg:city":"Bethlehem",
    "sg:classifiers":[
        {
            "category":"Building & Trades",
            "subcategory":"Construction",
            "type":"Services"
        }
    ],
    "sg:phone":"+1 610 837 9427",
    "sg:postcode":"18017",
    "sg:province":"PA",
    "sg:tags":[
        "general",
        "contractor"
    ],
    "wof:name":"Lehigh Valley Site Contractors",
    "wof:placetype":"venue"
},
  "geometry": {"coordinates":[-75.37932499999999,40.682441],"type":"Point"}
}