{
  "type": "Feature",
  "properties": {
    "iso:country":"US",
    "sg:address":"144 Church St",
    "sg:city":"Indiana",
    "sg:classifiers":[
        {
            "category":"Building & Trades",
            "subcategory":"Construction",
            "type":"Services"
        }
    ],
    "sg:phone":"+1   ",
    "sg:postcode":"15701",
    "sg:province":"PA",
    "sg:tags":[
        "carpentry",
        "contractor"
    ],
    "wof:name":"M & T Contracting",
    "wof:placetype":"venue"
},
  "geometry": {"coordinates":[-79.140523,40.621388],"type":"Point"}
}