{
  "type": "Feature",
  "properties": {
    "addr:full":"35 Swartz Rd Stoneboro PA 16153",
    "addr:housenumber":"35",
    "addr:postcode":"16153",
    "addr:street":"Swartz Rd",
    "iso:country":"US",
    "sg:address":"35 Swartz Rd",
    "sg:city":"Stoneboro",
    "sg:classifiers":[
        {
            "category":"Professional",
            "subcategory":"Art Services",
            "type":"Services"
        }
    ],
    "sg:phone":"+1 724 376 2966",
    "sg:postcode":"16153",
    "sg:province":"PA",
    "sg:tags":[
        "commercial",
        "design"
    ],
    "wof:name":"Cornerstone Graphics Inc",
    "wof:placetype":"venue"
},
  "geometry": {"coordinates":[-80.091775,41.329665],"type":"Point"}
}