{
  "type": "Feature",
  "properties": {
    "iso:country":"US",
    "sg:address":"2316 Sidney St",
    "sg:city":"Pittsburgh",
    "sg:classifiers":[
        {
            "category":"Shopping",
            "subcategory":"Catalog Store",
            "type":"Retail Goods"
        }
    ],
    "sg:phone":"+1   ",
    "sg:postcode":"15203",
    "sg:province":"PA",
    "sg:tags":[
        "mail",
        "house"
    ],
    "wof:name":"Dervin Enterprise",
    "wof:placetype":"venue"
},
  "geometry": {"coordinates":[-79.971239,40.429051],"type":"Point"}
}