{
  "type": "Feature",
  "properties": {
    "iso:country":"US",
    "sg:address":"120 N Washington St",
    "sg:city":"Boyertown",
    "sg:classifiers":[
        {
            "category":"Building & Trades",
            "subcategory":"Construction",
            "type":"Services"
        }
    ],
    "sg:phone":"+1   ",
    "sg:postcode":"19512",
    "sg:province":"PA",
    "sg:tags":[
        "contractor"
    ],
    "wof:name":"Ellis Mike Home Imprv Contr",
    "wof:placetype":"venue"
},
  "geometry": {"coordinates":[-75.63319300000001,40.333403],"type":"Point"}
}