{
  "type": "Feature",
  "properties": {
    "iso:country":"US",
    "sg:address":"4040 Ogden St",
    "sg:city":"Philadelphia",
    "sg:classifiers":[
        {
            "category":"Real Estate",
            "subcategory":"Real Estate Agent",
            "type":"Services"
        }
    ],
    "sg:phone":"+1 215 222 7192",
    "sg:postcode":"19104",
    "sg:province":"PA",
    "sg:tags":[
        "management"
    ],
    "wof:name":"Friends SRO",
    "wof:placetype":"venue"
},
  "geometry": {"coordinates":[-75.204808,39.969272],"type":"Point"}
}