{
  "type": "Feature",
  "properties": {
    "addr:full":"904 Hamilton Mall Allentown PA 18101",
    "addr:housenumber":"904",
    "addr:postcode":"18101",
    "addr:street":"Hamilton Mall",
    "iso:country":"US",
    "sg:address":"904 Hamilton Mall",
    "sg:city":"Allentown",
    "sg:classifiers":[
        {
            "category":"Travel",
            "subcategory":"Hotels & Motels",
            "type":"Entertainment"
        }
    ],
    "sg:phone":"+1   ",
    "sg:postcode":"18101",
    "sg:province":"PA",
    "sg:tags":[
        "operation",
        "eating"
    ],
    "wof:name":"Starwood Hotels & Resorts",
    "wof:placetype":"venue"
},
  "geometry": {"coordinates":[-75.47622699999999,40.600919],"type":"Point"}
}