{
  "type": "Feature",
  "properties": {
    "iso:country":"US",
    "sg:address":"262 Grove City Rd",
    "sg:city":"Slippery Rock",
    "sg:classifiers":[
        {
            "category":"Real Estate",
            "subcategory":"Architect",
            "type":"Services"
        }
    ],
    "sg:phone":"+1 724 794 2380",
    "sg:postcode":"16057",
    "sg:province":"PA",
    "wof:name":"Ligo Architects",
    "wof:placetype":"venue"
},
  "geometry": {"coordinates":[-80.05176400000001,41.075952],"type":"Point"}
}