{
  "type": "Feature",
  "properties": {
    "iso:country":"US",
    "sg:address":"22 W Broad St",
    "sg:city":"Bethlehem",
    "sg:classifiers":[
        {
            "category":"Professional",
            "type":"Services"
        }
    ],
    "sg:phone":"+1 610 861 8657",
    "sg:postcode":"18018",
    "sg:province":"PA",
    "sg:tags":[
        "establishment"
    ],
    "wof:name":"Musikfest",
    "wof:placetype":"venue"
},
  "geometry": {"coordinates":[-75.381694,40.622425],"type":"Point"}
}