{
  "type": "Feature",
  "properties": {
    "iso:country":"US",
    "sg:address":"1380 Jessica Dr",
    "sg:city":"Lebanon",
    "sg:classifiers":[
        {
            "category":"Building & Trades",
            "subcategory":"Cleaning & Sanitation",
            "type":"Services"
        }
    ],
    "sg:phone":"+1   ",
    "sg:postcode":"17046",
    "sg:province":"PA",
    "sg:tags":[
        "maintenance"
    ],
    "wof:name":"Zimmermans Janitorial Service",
    "wof:placetype":"venue"
},
  "geometry": {"coordinates":[-76.439318,40.382115],"type":"Point"}
}