{
  "type": "Feature",
  "properties": {
    "addr:full":"2561 S 61st St Philadelphia PA 19142",
    "addr:housenumber":"2561",
    "addr:postcode":"19142",
    "addr:street":"S 61St St",
    "iso:country":"US",
    "sg:address":"2561 S 61st St",
    "sg:city":"Philadelphia",
    "sg:classifiers":[
        {
            "category":"Shopping",
            "subcategory":"Computers & Home Electronics",
            "type":"Retail Goods"
        }
    ],
    "sg:phone":"+1   ",
    "sg:postcode":"19142",
    "sg:province":"PA",
    "sg:tags":[
        "tape",
        "video",
        "rental"
    ],
    "wof:name":"Metro Video Inc",
    "wof:placetype":"venue"
},
  "geometry": {"coordinates":[-75.224048,39.925654],"type":"Point"}
}