{
  "type": "Feature",
  "properties": {
    "addr:full":"931 Willow St Lebanon PA 17046",
    "addr:housenumber":"931",
    "addr:postcode":"17046",
    "addr:street":"Willow St",
    "iso:country":"US",
    "sg:address":"931 Willow St",
    "sg:city":"Lebanon",
    "sg:classifiers":[
        {
            "category":"Organizations",
            "subcategory":"Religious Organization",
            "type":"Services"
        }
    ],
    "sg:phone":"+1 717 273 6531",
    "sg:postcode":"17046",
    "sg:province":"PA",
    "sg:tags":[
        "church"
    ],
    "wof:name":"St John's United Church-Christ",
    "wof:placetype":"venue"
},
  "geometry": {"coordinates":[-76.427345,40.340476],"type":"Point"}
}