{
  "type": "Feature",
  "properties": {
    "addr:full":"102 Pear St Mohnton PA 19540",
    "addr:housenumber":"102",
    "addr:postcode":"19540",
    "addr:street":"Pear St",
    "iso:country":"US",
    "sg:address":"102 Pear St",
    "sg:city":"Mohnton",
    "sg:classifiers":[
        {
            "category":"Professional",
            "subcategory":"Business Services",
            "type":"Services"
        }
    ],
    "sg:phone":"+1 610 777 1678",
    "sg:postcode":"19540",
    "sg:province":"PA",
    "sg:tags":[
        "plumbing",
        "water",
        "treatment"
    ],
    "wof:name":"Ledwig Associates",
    "wof:placetype":"venue"
},
  "geometry": {"coordinates":[-75.987724,40.28504],"type":"Point"}
}