{
  "type": "Feature",
  "properties": {
    "addr:full":"150 W Fisher Ave Philadelphia PA 19120",
    "addr:housenumber":"150",
    "addr:postcode":"19120",
    "addr:street":"W Fisher Ave",
    "iso:country":"US",
    "sg:address":"150 W Fisher Ave",
    "sg:city":"Philadelphia",
    "sg:classifiers":[
        {
            "category":"Food & Beverages",
            "subcategory":"Groceries & Convenience Stores",
            "type":"Retail Goods"
        }
    ],
    "sg:phone":"+1   ",
    "sg:postcode":"19120",
    "sg:province":"PA",
    "wof:name":"Pats Deli",
    "wof:placetype":"venue"
},
  "geometry": {"coordinates":[-75.12396,40.030813],"type":"Point"}
}