{
  "type": "Feature",
  "properties": {
    "iso:country":"US",
    "sg:address":"5820 6th Ave",
    "sg:city":"Altoona",
    "sg:classifiers":[
        {
            "category":"Restaurant",
            "type":"Food & Drink"
        }
    ],
    "sg:phone":"+1   ",
    "sg:postcode":"16602",
    "sg:province":"PA",
    "sg:tags":[
        "drinking",
        "eating"
    ],
    "wof:name":"T C Zachs",
    "wof:placetype":"venue"
},
  "geometry": {"coordinates":[-78.425398,40.471779],"type":"Point"}
}