{
  "type": "Feature",
  "properties": {
    "iso:country":"US",
    "sg:address":"501 Main St",
    "sg:city":"Clarion",
    "sg:classifiers":[
        {
            "category":"Professional",
            "type":"Services"
        }
    ],
    "sg:phone":"+1   ",
    "sg:postcode":"16214",
    "sg:province":"PA",
    "wof:name":"Alleghny-Cmmnwlth Sttlment Svc",
    "wof:placetype":"venue"
},
  "geometry": {"coordinates":[-79.385628,41.214714],"type":"Point"}
}