{
  "type": "Feature",
  "properties": {
    "addr:full":"3200 Lycoming Creek Rd Williamsport PA 17701",
    "addr:housenumber":"3200",
    "addr:postcode":"17701",
    "addr:street":"Lycoming Creek Rd",
    "iso:country":"US",
    "sg:address":"3200 Lycoming Creek Rd",
    "sg:city":"Williamsport",
    "sg:classifiers":[
        {
            "category":"Place Of Worship",
            "subcategory":"Church",
            "type":"Public Place"
        },
        {
            "category":"Place Of Worship",
            "type":"Public Place"
        }
    ],
    "sg:phone":"+1 570 494 0596",
    "sg:postcode":"17701",
    "sg:province":"PA",
    "sg:tags":[
        "nazarene",
        "churches-church",
        "churches-nazarene"
    ],
    "wof:name":"Calvary Church Of The Nazarene",
    "wof:placetype":"venue"
},
  "geometry": {"coordinates":[-77.055817,41.28875],"type":"Point"}
}