{
  "type": "Feature",
  "properties": {
    "addr:full":"18 Lehigh St Macungie PA 18062",
    "addr:housenumber":"18",
    "addr:postcode":"18062",
    "addr:street":"Lehigh St",
    "iso:country":"US",
    "sg:address":"18 Lehigh St",
    "sg:city":"Macungie",
    "sg:classifiers":[
        {
            "category":"Manufacturing",
            "subcategory":"Musical Instruments",
            "type":"Manufacturing & Wholesale Goods"
        }
    ],
    "sg:phone":"+1 610 966 3561",
    "sg:postcode":"18062",
    "sg:province":"PA",
    "sg:tags":[
        "piano",
        "organ"
    ],
    "wof:name":"Lehigh Organ Co",
    "wof:placetype":"venue"
},
  "geometry": {"coordinates":[-75.55569800000001,40.516821],"type":"Point"}
}