{
  "type": "Feature",
  "properties": {
    "iso:country":"US",
    "sg:address":"1103 Mount Rose Ave",
    "sg:city":"York",
    "sg:classifiers":[
        {
            "category":"Insurance",
            "subcategory":"Insurance Agent",
            "type":"Services"
        }
    ],
    "sg:phone":"+1 717 718 1390",
    "sg:postcode":"17403",
    "sg:province":"PA",
    "sg:tags":[
        "auto"
    ],
    "sg:website":"http://www.chriswilliamsagency.com?utm_source=yp&utm_medium=cpc&utm_campaign=ck_yp",
    "wof:name":"MONROE CHRIS WILLIAMS AGENCY",
    "wof:placetype":"venue"
},
  "geometry": {"coordinates":[-76.702781,39.959808],"type":"Point"}
}