{
  "type": "Feature",
  "properties": {
    "iso:country":"US",
    "sg:address":"2012 Darby Rd",
    "sg:city":"Havertown",
    "sg:classifiers":[
        {
            "category":"Food & Beverages",
            "subcategory":"Liquor & Beverages",
            "type":"Retail Goods"
        }
    ],
    "sg:phone":"+1 610 853 5428",
    "sg:postcode":"19083",
    "sg:province":"PA",
    "wof:name":"Pennsylvania State Liquor Str",
    "wof:placetype":"venue"
},
  "geometry": {"coordinates":[-75.30815,39.98544],"type":"Point"}
}