{
  "type": "Feature",
  "properties": {
    "iso:country":"US",
    "sg:address":"145 N Courtland St",
    "sg:city":"East Stroudsburg",
    "sg:classifiers":[
        {
            "category":"Wholesale",
            "subcategory":"Machinery & Supplies",
            "type":"Manufacturing & Wholesale Goods"
        },
        {
            "category":"Personal",
            "subcategory":"Beauty Salon",
            "type":"Services"
        }
    ],
    "sg:phone":"+1 570 424 6461",
    "sg:postcode":"18301",
    "sg:province":"PA",
    "sg:tags":[
        "equipment",
        "establishment",
        "manicuring"
    ],
    "wof:name":"Jim The Hairdresser Ltd",
    "wof:placetype":"venue"
},
  "geometry": {"coordinates":[-75.183312,41.003153],"type":"Point"}
}