{
  "type": "Feature",
  "properties": {
    "iso:country":"US",
    "sg:address":"55 S Fayette St",
    "sg:city":"York",
    "sg:classifiers":[
        {
            "category":"Autos & Motor Vehicles",
            "subcategory":"Automobile Sales",
            "type":"Retail Goods"
        }
    ],
    "sg:phone":"+1 717 792 3606",
    "sg:postcode":"17404",
    "sg:province":"PA",
    "sg:tags":[
        "truck"
    ],
    "wof:name":"Pennsyvlvania Truck Centers",
    "wof:placetype":"venue"
},
  "geometry": {"coordinates":[-76.77770599999999,39.948589],"type":"Point"}
}