{
  "type": "Feature",
  "properties": {
    "addr:full":"7474 Columbia Blvd Berwick PA 18603",
    "addr:housenumber":"7474",
    "addr:postcode":"18603",
    "addr:street":"Columbia Blvd",
    "iso:country":"US",
    "sg:address":"7474 Columbia Blvd",
    "sg:city":"Berwick",
    "sg:classifiers":[
        {
            "category":"Wholesale",
            "subcategory":"Hardware",
            "type":"Manufacturing & Wholesale Goods"
        },
        {
            "category":"Home & Garden",
            "subcategory":"Garden Supply",
            "type":"Retail Goods"
        },
        {
            "category":"Retail",
            "subcategory":"Repair Shop",
            "type":"Services"
        }
    ],
    "sg:phone":"+1 570 752 7044",
    "sg:postcode":"18603",
    "sg:province":"PA",
    "sg:tags":[
        "renting",
        "lawn",
        "outdoor",
        "power",
        "landscaping",
        "equipment-sales",
        "equipment",
        "saw"
    ],
    "sg:website":"http://www.stihldealer.net/default-dealer-040235.aspx",
    "wof:name":"Jerry's Engine Repair",
    "wof:placetype":"venue"
},
  "geometry": {"coordinates":[-76.29780100000001,41.043899],"type":"Point"}
}