{
  "type": "Feature",
  "properties": {
    "iso:country":"US",
    "sg:address":"2527 East Ave",
    "sg:city":"Erie",
    "sg:classifiers":[
        {
            "category":"Taxi",
            "type":"Transportation"
        }
    ],
    "sg:phone":"+1 814 455 4441",
    "sg:postcode":"16503",
    "sg:province":"PA",
    "sg:tags":[
        "taxicab"
    ],
    "wof:name":"Erie Yellow Cab Co",
    "wof:placetype":"venue"
},
  "geometry": {"coordinates":[-80.051439,42.120368],"type":"Point"}
}