{
  "type": "Feature",
  "properties": {
    "iso:country":"US",
    "sg:address":"1526 Bethlehem Pike",
    "sg:city":"Flourtown",
    "sg:classifiers":[
        {
            "category":"Government",
            "subcategory":"Fire Station",
            "type":"Public Place"
        }
    ],
    "sg:phone":"+1 215 836 4840",
    "sg:postcode":"19031",
    "sg:province":"PA",
    "sg:tags":[
        "department"
    ],
    "wof:name":"Flourtown Fire Company Station 6",
    "wof:placetype":"venue"
},
  "geometry": {"coordinates":[-75.213364,40.10569],"type":"Point"}
}