{
  "type": "Feature",
  "properties": {
    "iso:country":"US",
    "sg:address":"5040 Kutztown Rd",
    "sg:city":"Temple",
    "sg:classifiers":[
        {
            "category":"Building & Trades",
            "subcategory":"Construction",
            "type":"Services"
        },
        {
            "category":"Home & Garden",
            "subcategory":"Carpets & Floor Coverings",
            "type":"Retail Goods"
        }
    ],
    "sg:phone":"+1 610 921 5893",
    "sg:postcode":"19560",
    "sg:province":"PA",
    "sg:tags":[
        "rug",
        "carpentry",
        "dealer",
        "contractor"
    ],
    "wof:name":"Chuck Smith Prof Installations",
    "wof:placetype":"venue"
},
  "geometry": {"coordinates":[-75.920473,40.412271],"type":"Point"}
}