{
  "type": "Feature",
  "properties": {
    "iso:country":"US",
    "sg:address":"1725 Wolf St",
    "sg:city":"Philadelphia",
    "sg:classifiers":[
        {
            "category":"Bars & Pubs",
            "type":"Food & Drink"
        },
        {
            "category":"Restaurant",
            "type":"Food & Drink"
        }
    ],
    "sg:menulink":"http://www.allmenus.com/pa/philadelphia/262745-barrels-fine-food/menu/",
    "sg:phone":"+1 215 389 6010",
    "sg:postcode":"19145",
    "sg:province":"PA",
    "sg:tags":[
        "american",
        "italian"
    ],
    "wof:name":"Barrel's Fine Food",
    "wof:placetype":"venue"
},
  "geometry": {"coordinates":[-75.175984,39.922676],"type":"Point"}
}