{
  "type": "Feature",
  "properties": {
    "addr:full":"1609 State Rte 18 Atlasburg PA 15010",
    "addr:housenumber":"1609",
    "addr:postcode":"15010",
    "addr:street":"State Rte 18",
    "iso:country":"US",
    "sg:address":"1609 State Rte 18",
    "sg:city":"Atlasburg",
    "sg:classifiers":[
        {
            "category":"Local Transit",
            "type":"Transportation"
        }
    ],
    "sg:phone":"+1 724 947 4500",
    "sg:postcode":"15010",
    "sg:province":"PA",
    "sg:tags":[
        "bus",
        "line"
    ],
    "wof:name":"Jake Schneider Bus Contractor",
    "wof:placetype":"venue"
},
  "geometry": {"coordinates":[-80.31943800000001,40.757861],"type":"Point"}
}