{
  "type": "Feature",
  "properties": {
    "iso:country":"US",
    "sg:address":"13589 Baer Rd",
    "sg:city":"Waynesboro",
    "sg:phone":"+1   ",
    "sg:postcode":"17268",
    "sg:province":"PA",
    "sg:tags":[
        "farm",
        "field",
        "corn",
        "soybean",
        "crop"
    ],
    "wof:name":"Petre Aldus",
    "wof:placetype":"venue"
},
  "geometry": {"coordinates":[-77.564345,39.73576],"type":"Point"}
}