{
  "type": "Feature",
  "properties": {
    "addr:full":"1450 Parkway W Harrisburg PA 17112",
    "addr:housenumber":"1450",
    "addr:postcode":"17112",
    "addr:street":"Parkway W",
    "iso:country":"US",
    "sg:address":"1450 Parkway W",
    "sg:city":"Harrisburg",
    "sg:classifiers":[
        {
            "category":"Social Services",
            "subcategory":"Child Care",
            "type":"Services"
        }
    ],
    "sg:phone":"+1 717 652 3360",
    "sg:postcode":"17112",
    "sg:province":"PA",
    "sg:tags":[
        "day"
    ],
    "wof:name":"Kiddie Line Express",
    "wof:placetype":"venue"
},
  "geometry": {"coordinates":[-76.811481,40.341767],"type":"Point"}
}