{
  "type": "Feature",
  "properties": {
    "iso:country":"US",
    "sg:address":"409 Sunny Hill Rd",
    "sg:city":"Broomall",
    "sg:classifiers":[
        {
            "category":"Communications",
            "subcategory":"Film & Video Production",
            "type":"Services"
        }
    ],
    "sg:phone":"+1 610 353 0113",
    "sg:postcode":"19008",
    "sg:province":"PA",
    "sg:tags":[
        "taping"
    ],
    "wof:name":"Christaldi Productions",
    "wof:placetype":"venue"
},
  "geometry": {"coordinates":[-75.385266,39.975911],"type":"Point"}
}