{
  "type": "Feature",
  "properties": {
    "iso:country":"US",
    "sg:address":"703 Hillsboro St",
    "sg:city":"Pittsburgh",
    "sg:classifiers":[
        {
            "category":"Retail",
            "subcategory":"Auto Repair",
            "type":"Services"
        }
    ],
    "sg:phone":"+1 412 331 3773",
    "sg:postcode":"15204",
    "sg:province":"PA",
    "sg:tags":[
        "repairing",
        "automobile"
    ],
    "wof:name":"Hahn's Indoor Garage Sale",
    "wof:placetype":"venue"
},
  "geometry": {"coordinates":[-80.055363,40.452982],"type":"Point"}
}