{
  "type": "Feature",
  "properties": {
    "addr:full":"1008 E Elfinwild Rd Allison Park PA 15101",
    "addr:housenumber":"1008",
    "addr:postcode":"15101",
    "addr:street":"E Elfinwild Rd",
    "iso:country":"US",
    "sg:address":"1008 E Elfinwild Rd",
    "sg:city":"Allison Park",
    "sg:classifiers":[
        {
            "category":"Building & Trades",
            "subcategory":"Construction",
            "type":"Services"
        }
    ],
    "sg:phone":"+1 412 487 2915",
    "sg:postcode":"15101",
    "sg:province":"PA",
    "sg:tags":[
        "contractor"
    ],
    "wof:name":"Wills Masonry",
    "wof:placetype":"venue"
},
  "geometry": {"coordinates":[-79.95868299999999,40.549655],"type":"Point"}
}