{
  "type": "Feature",
  "properties": {
    "iso:country":"US",
    "sg:address":"1722 Lincoln Way",
    "sg:city":"Mc Keesport",
    "sg:classifiers":[
        {
            "category":"Personal",
            "subcategory":"Beauty Salon",
            "type":"Services"
        }
    ],
    "sg:phone":"+1 412 672 1883",
    "sg:postcode":"15131",
    "sg:province":"PA",
    "sg:tags":[
        "shop"
    ],
    "wof:name":"De Blasio's Designs",
    "wof:placetype":"venue"
},
  "geometry": {"coordinates":[-79.81468700000001,40.344257],"type":"Point"}
}