{
  "type": "Feature",
  "properties": {
    "addr:full":"126 E Fairview Ave Connellsville PA 15425",
    "addr:housenumber":"126",
    "addr:postcode":"15425",
    "addr:street":"E Fairview Ave",
    "iso:country":"US",
    "sg:address":"126 E Fairview Ave",
    "sg:city":"Connellsville",
    "sg:classifiers":[
        {
            "category":"Organizations",
            "subcategory":"Religious Organization",
            "type":"Services"
        }
    ],
    "sg:phone":"+1   ",
    "sg:postcode":"15425",
    "sg:province":"PA",
    "wof:name":"Trinity Evang Lutheran Church",
    "wof:placetype":"venue"
},
  "geometry": {"coordinates":[-79.588005,40.016676],"type":"Point"}
}