{
  "type": "Feature",
  "properties": {
    "addr:full":"209 Pitney Rd Lancaster PA 17601",
    "addr:housenumber":"209",
    "addr:postcode":"17601",
    "addr:street":"Pitney Rd",
    "iso:country":"US",
    "sg:address":"209 Pitney Rd",
    "sg:city":"Lancaster",
    "sg:classifiers":[
        {
            "category":"Manufacturing",
            "subcategory":"Tobacco Products",
            "type":"Manufacturing & Wholesale Goods"
        }
    ],
    "sg:phone":"+1   ",
    "sg:postcode":"17601",
    "sg:province":"PA",
    "wof:name":"R J Reynolds Tobacco Company",
    "wof:placetype":"venue"
},
  "geometry": {"coordinates":[-76.262692,40.05171],"type":"Point"}
}