{
  "type": "Feature",
  "properties": {
    "iso:country":"US",
    "sg:address":"3800 Trindle Rd",
    "sg:city":"Mechanicsburg",
    "sg:classifiers":[
        {
            "category":"Restaurant",
            "type":"Food & Drink"
        }
    ],
    "sg:phone":"+1 717 920 1320",
    "sg:postcode":"17050",
    "sg:province":"PA",
    "sg:tags":[
        "pizza"
    ],
    "wof:name":"Two Guys Pizza",
    "wof:placetype":"venue"
},
  "geometry": {"coordinates":[-76.996597,40.244801],"type":"Point"}
}