{
  "type": "Feature",
  "properties": {
    "addr:full":"4271 Forest Glen Dr Allison Park PA 15101",
    "addr:housenumber":"4271",
    "addr:postcode":"15101",
    "addr:street":"Forest Glen Dr",
    "iso:country":"US",
    "sg:address":"4271 Forest Glen Dr",
    "sg:city":"Allison Park",
    "sg:classifiers":[
        {
            "category":"Manufacturing",
            "subcategory":"Printing",
            "type":"Manufacturing & Wholesale Goods"
        }
    ],
    "sg:phone":"+1 412 487 4690",
    "sg:postcode":"15101",
    "sg:province":"PA",
    "sg:tags":[
        "printer",
        "commercial"
    ],
    "wof:name":"Executive Printing Services",
    "wof:placetype":"venue"
},
  "geometry": {"coordinates":[-79.964288,40.575139],"type":"Point"}
}