{
  "type": "Feature",
  "properties": {
    "iso:country":"US",
    "sg:address":"432 N 64th St",
    "sg:city":"Philadelphia",
    "sg:classifiers":[
        {
            "category":"Personal",
            "subcategory":"Beauty Salon",
            "type":"Services"
        }
    ],
    "sg:phone":"+1 215 747 3110",
    "sg:postcode":"19151",
    "sg:province":"PA",
    "wof:name":"Touch Of Elegence",
    "wof:placetype":"venue"
},
  "geometry": {"coordinates":[-75.247354,39.970125],"type":"Point"}
}