{
  "type": "Feature",
  "properties": {
    "addr:full":"330 Hannahstown Rd Cabot PA 16023",
    "addr:housenumber":"330",
    "addr:postcode":"16023",
    "addr:street":"Hannahstown Rd",
    "iso:country":"US",
    "sg:address":"330 Hannahstown Rd",
    "sg:city":"Cabot",
    "sg:classifiers":[
        {
            "category":"Education",
            "subcategory":"School",
            "type":"Public Place"
        }
    ],
    "sg:phone":"+1 724 352 2221",
    "sg:postcode":"16023",
    "sg:province":"PA",
    "sg:website":"www.stlukecabot.org",
    "wof:name":"St Luke's Lutheran School",
    "wof:placetype":"venue"
},
  "geometry": {"coordinates":[-79.80104900000001,40.771865],"type":"Point"}
}