{
  "type": "Feature",
  "properties": {
    "iso:country":"US",
    "sg:address":"16 S 7th St",
    "sg:city":"Akron",
    "sg:classifiers":[
        {
            "category":"Personal",
            "type":"Services"
        },
        {
            "category":"Health Services",
            "subcategory":"Health Practitioner",
            "type":"Services"
        }
    ],
    "sg:phone":"+1 717 859 5577",
    "sg:postcode":"17501",
    "sg:province":"PA",
    "sg:tags":[
        "therapist",
        "massage"
    ],
    "wof:name":"Therapeutic Approach",
    "wof:placetype":"venue"
},
  "geometry": {"coordinates":[-76.205237,40.156623],"type":"Point"}
}