{
  "type": "Feature",
  "properties": {
    "iso:country":"US",
    "sg:address":"4004 Chestnut St",
    "sg:city":"Philadelphia",
    "sg:classifiers":[
        {
            "category":"Restaurant",
            "type":"Food & Drink"
        }
    ],
    "sg:phone":"+1 215 386 1941",
    "sg:postcode":"19104",
    "sg:province":"PA",
    "sg:tags":[
        "indian",
        "buffet"
    ],
    "sg:website":"www.newdelhiweb.com",
    "wof:name":"New Delhi Indian Restaurant",
    "wof:placetype":"venue"
},
  "geometry": {"coordinates":[-75.202614,39.955391],"type":"Point"}
}