{
  "type": "Feature",
  "properties": {
    "iso:country":"US",
    "sg:address":"961 Lower Creek Rd",
    "sg:city":"Milroy",
    "sg:classifiers":[
        {
            "category":"Professional",
            "subcategory":"Computer Services",
            "type":"Services"
        },
        {
            "category":"Internet Cafe",
            "subcategory":"None",
            "type":"Food & Drink"
        }
    ],
    "sg:phone":"+1 717 667 6738",
    "sg:postcode":"17063",
    "sg:province":"PA",
    "sg:tags":[
        "product",
        "software"
    ],
    "wof:name":"Bc Programming",
    "wof:placetype":"venue"
},
  "geometry": {"coordinates":[-77.50905299999999,40.744187],"type":"Point"}
}