{
  "type": "Feature",
  "properties": {
    "addr:full":"120 Kist Hill Rd Kempton PA 19529",
    "addr:housenumber":"120",
    "addr:postcode":"19529",
    "addr:street":"Kist Hill Rd",
    "iso:country":"US",
    "sg:address":"120 Kist Hill Rd",
    "sg:city":"Kempton",
    "sg:classifiers":[
        {
            "category":"Restaurant",
            "type":"Food & Drink"
        }
    ],
    "sg:phone":"+1 610 756 3087",
    "sg:postcode":"19529",
    "sg:province":"PA",
    "wof:name":"Experience On The Wings Of Love",
    "wof:placetype":"venue"
},
  "geometry": {"coordinates":[-75.88899499999999,40.643911],"type":"Point"}
}