{
  "type": "Feature",
  "properties": {
    "addr:full":"501 Williams St Clearfield PA 16830",
    "addr:housenumber":"501",
    "addr:postcode":"16830",
    "addr:street":"Williams St",
    "iso:country":"US",
    "sg:address":"501 Williams St",
    "sg:city":"Clearfield",
    "sg:classifiers":[
        {
            "category":"Autos & Motor Vehicles",
            "subcategory":"Automobile Sales",
            "type":"Retail Goods"
        }
    ],
    "sg:phone":"+1   ",
    "sg:postcode":"16830",
    "sg:province":"PA",
    "sg:tags":[
        "used"
    ],
    "wof:name":"Porter Car Sales",
    "wof:placetype":"venue"
},
  "geometry": {"coordinates":[-78.44175,41.029125],"type":"Point"}
}