{
  "type": "Feature",
  "properties": {
    "iso:country":"US",
    "sg:address":"13469 Joann Dr",
    "sg:city":"Greencastle",
    "sg:classifiers":[
        {
            "category":"Building & Trades",
            "subcategory":"Construction",
            "type":"Services"
        }
    ],
    "sg:phone":"+1 717 762 3854",
    "sg:postcode":"17225",
    "sg:province":"PA",
    "sg:tags":[
        "water",
        "well",
        "drilling"
    ],
    "wof:name":"C A Burcker Well Drilling",
    "wof:placetype":"venue"
},
  "geometry": {"coordinates":[-77.65163800000001,39.753345],"type":"Point"}
}