{
  "type": "Feature",
  "properties": {
    "iso:country":"US",
    "sg:address":"430 Sawmill Run Rd",
    "sg:city":"Butler",
    "sg:classifiers":[
        {
            "category":"Insurance",
            "subcategory":"Insurance Agent",
            "type":"Services"
        }
    ],
    "sg:phone":"+1   ",
    "sg:postcode":"16001",
    "sg:province":"PA",
    "sg:tags":[
        "broker"
    ],
    "wof:name":"Fritz Marilyn Insurance Svcs",
    "wof:placetype":"venue"
},
  "geometry": {"coordinates":[-79.95358,40.842228],"type":"Point"}
}