{
  "type": "Feature",
  "properties": {
    "addr:full":"3555 Valley Dr Pittsburgh PA 15234",
    "addr:housenumber":"3555",
    "addr:postcode":"15234",
    "addr:street":"Valley Dr",
    "iso:country":"US",
    "sg:address":"3555 Valley Dr",
    "sg:city":"Pittsburgh",
    "sg:classifiers":[
        {
            "category":"Personal",
            "type":"Services"
        }
    ],
    "sg:phone":"+1 866 244 8767",
    "sg:postcode":"15234",
    "sg:province":"PA",
    "sg:tags":[
        "mover"
    ],
    "sg:website":"www.twomenandatruckpgh.com",
    "wof:name":"Two Men And A Truck",
    "wof:placetype":"venue"
},
  "geometry": {"coordinates":[-80.0232,40.353536],"type":"Point"}
}