{
  "type": "Feature",
  "properties": {
    "iso:country":"US",
    "sg:address":"2756 S Queen St",
    "sg:city":"Dallastown",
    "sg:classifiers":[
        {
            "category":"Government",
            "subcategory":"Office",
            "type":"Public Place"
        }
    ],
    "sg:phone":"+1   ",
    "sg:postcode":"17313",
    "sg:province":"PA",
    "sg:tags":[
        "executive"
    ],
    "wof:name":"District Court 19 202",
    "wof:placetype":"venue"
},
  "geometry": {"coordinates":[-76.655675,39.90673],"type":"Point"}
}