{
  "type": "Feature",
  "properties": {
    "iso:country":"US",
    "sg:address":"1448 2nd Ave",
    "sg:city":"Conway",
    "sg:classifiers":[
        {
            "category":"Building & Trades",
            "subcategory":"Construction",
            "type":"Services"
        }
    ],
    "sg:phone":"+1 724 869 2905",
    "sg:postcode":"15027",
    "sg:province":"PA",
    "sg:tags":[
        "residential",
        "nonresidential"
    ],
    "wof:name":"Wanchick Construction",
    "wof:placetype":"venue"
},
  "geometry": {"coordinates":[-80.240476,40.66438],"type":"Point"}
}