{
  "type": "Feature",
  "properties": {
    "addr:full":"4150 Birney Ave Moosic PA 18507",
    "addr:housenumber":"4150",
    "addr:postcode":"18507",
    "addr:street":"Birney Ave",
    "iso:country":"US",
    "sg:address":"4150 Birney Ave",
    "sg:city":"Moosic",
    "sg:classifiers":[
        {
            "category":"Autos & Motor Vehicles",
            "subcategory":"Automobile Sales",
            "type":"Retail Goods"
        }
    ],
    "sg:phone":"+1   ",
    "sg:postcode":"18507",
    "sg:province":"PA",
    "wof:name":"Melnick Steve Scrnton Auto Sls",
    "wof:placetype":"venue"
},
  "geometry": {"coordinates":[-75.716605,41.365979],"type":"Point"}
}