{
  "type": "Feature",
  "properties": {
    "iso:country":"US",
    "sg:address":"Cathdrl Mansions",
    "sg:city":"Pittsburgh",
    "sg:classifiers":[
        {
            "category":"Real Estate",
            "subcategory":"Real Estate Operator",
            "type":"Services"
        }
    ],
    "sg:phone":"+1 412 621 8100",
    "sg:postcode":"15233",
    "sg:province":"PA",
    "sg:tags":[
        "apartment"
    ],
    "wof:name":"Empire Corp",
    "wof:placetype":"venue"
},
  "geometry": {"coordinates":[-80.02359800000001,40.452599],"type":"Point"}
}