{
  "type": "Feature",
  "properties": {
    "iso:country":"US",
    "sg:address":"114 E Broad St",
    "sg:city":"Souderton",
    "sg:classifiers":[
        {
            "category":"Professional",
            "subcategory":"Lawyer & Legal Services",
            "type":"Services"
        }
    ],
    "sg:phone":"+1 215 723 4350",
    "sg:postcode":"18964",
    "sg:province":"PA",
    "sg:tags":[
        "attorney"
    ],
    "wof:name":"Bricker Landis Hunsberger LLP",
    "wof:placetype":"venue"
},
  "geometry": {"coordinates":[-75.32030899999999,40.309625],"type":"Point"}
}