{
  "type": "Feature",
  "properties": {
    "iso:country":"US",
    "sg:address":"3929 Old William Penn Hwy",
    "sg:city":"Murrysville",
    "sg:classifiers":[
        {
            "category":"Home & Garden",
            "subcategory":"Home Furnishings",
            "type":"Retail Goods"
        }
    ],
    "sg:phone":"+1   ",
    "sg:postcode":"15668",
    "sg:province":"PA",
    "wof:name":"Burtons Spring Crest Interiors",
    "wof:placetype":"venue"
},
  "geometry": {"coordinates":[-79.69684100000001,40.428257],"type":"Point"}
}