{
  "type": "Feature",
  "properties": {
    "iso:country":"US",
    "sg:address":"737 Wyngold Dr",
    "sg:city":"Pittsburgh",
    "sg:classifiers":[
        {
            "category":"Autos & Motor Vehicles",
            "subcategory":"Automobile Sales",
            "type":"Retail Goods"
        }
    ],
    "sg:phone":"+1   ",
    "sg:postcode":"15237",
    "sg:province":"PA",
    "sg:tags":[
        "car",
        "used",
        "sales"
    ],
    "wof:name":"John L Matalik",
    "wof:placetype":"venue"
},
  "geometry": {"coordinates":[-80.058643,40.570463],"type":"Point"}
}