{
  "type": "Feature",
  "properties": {
    "addr:full":"205 31st St Mckeesport PA 15132",
    "addr:housenumber":"205",
    "addr:postcode":"15132",
    "addr:street":"31St St",
    "iso:country":"US",
    "sg:address":"205 31st St",
    "sg:city":"Mckeesport",
    "sg:classifiers":[
        {
            "category":"Manufacturing",
            "subcategory":"Tools & Machinery",
            "type":"Manufacturing & Wholesale Goods"
        }
    ],
    "sg:phone":"+1 412 672 9210",
    "sg:postcode":"15132",
    "sg:province":"PA",
    "sg:tags":[
        "machine",
        "shop"
    ],
    "wof:name":"Premco Inc",
    "wof:placetype":"venue"
},
  "geometry": {"coordinates":[-79.84455199999999,40.330221],"type":"Point"}
}