{
  "type": "Feature",
  "properties": {
    "addr:full":"211 Mill St Bristol PA 19007",
    "addr:housenumber":"211",
    "addr:postcode":"19007",
    "addr:street":"Mill St",
    "iso:country":"US",
    "sg:address":"211 Mill St",
    "sg:city":"Bristol",
    "sg:classifiers":[
        {
            "category":"Building & Trades",
            "subcategory":"Construction",
            "type":"Services"
        }
    ],
    "sg:phone":"+1 215 781 1822",
    "sg:postcode":"19007",
    "sg:province":"PA",
    "sg:tags":[
        "repair",
        "handyman",
        "maintenance",
        "home"
    ],
    "wof:name":"Psychic Readings",
    "wof:placetype":"venue"
},
  "geometry": {"coordinates":[-74.857274,40.095148],"type":"Point"}
}