{
  "type": "Feature",
  "properties": {
    "iso:country":"US",
    "sg:address":"67 Delaware Ct",
    "sg:city":"Newtown",
    "sg:classifiers":[
        {
            "category":"Professional",
            "subcategory":"Business Services",
            "type":"Services"
        }
    ],
    "sg:phone":"+1 215 860 8110",
    "sg:postcode":"18940",
    "sg:province":"PA",
    "sg:tags":[
        "information",
        "bureau"
    ],
    "wof:name":"Foley, Robert",
    "wof:placetype":"venue"
},
  "geometry": {"coordinates":[-74.953379,40.215993],"type":"Point"}
}