{
  "type": "Feature",
  "properties": {
    "addr:full":"854 Wheatland Cir Bridgeville PA 15017",
    "addr:housenumber":"854",
    "addr:postcode":"15017",
    "addr:street":"Wheatland Cir",
    "iso:country":"US",
    "sg:address":"854 Wheatland Cir",
    "sg:city":"Bridgeville",
    "sg:classifiers":[
        {
            "category":"Arts & Performance",
            "subcategory":"Theater",
            "type":"Entertainment"
        }
    ],
    "sg:phone":"+1 412 221 3573",
    "sg:postcode":"15017",
    "sg:province":"PA",
    "sg:tags":[
        "musician"
    ],
    "wof:name":"Quad One Deuce Production",
    "wof:placetype":"venue"
},
  "geometry": {"coordinates":[-80.13386199999999,40.328291],"type":"Point"}
}