{
  "type": "Feature",
  "properties": {
    "iso:country":"US",
    "sg:address":"500 Lloyd St",
    "sg:city":"Pittsburgh",
    "sg:classifiers":[
        {
            "category":"Real Estate",
            "subcategory":"Real Estate Agent",
            "type":"Services"
        }
    ],
    "sg:phone":"+1   ",
    "sg:postcode":"15208",
    "sg:province":"PA",
    "sg:tags":[
        "personalized"
    ],
    "wof:name":"William Stevens",
    "wof:placetype":"venue"
},
  "geometry": {"coordinates":[-79.907838,40.445792],"type":"Point"}
}