{
  "type": "Feature",
  "properties": {
    "iso:country":"US",
    "sg:address":"24 Henderson St",
    "sg:city":"Lewistown",
    "sg:classifiers":[
        {
            "category":"Wholesale",
            "subcategory":"Scrap",
            "type":"Manufacturing & Wholesale Goods"
        }
    ],
    "sg:phone":"+1 717 242 1682",
    "sg:postcode":"17044",
    "sg:province":"PA",
    "sg:tags":[
        "recycling",
        "center"
    ],
    "wof:name":"Paul's Recycling Yard",
    "wof:placetype":"venue"
},
  "geometry": {"coordinates":[-77.58247,40.600967],"type":"Point"}
}