{
  "type": "Feature",
  "properties": {
    "iso:country":"US",
    "sg:address":"102 W Germantown Pike",
    "sg:city":"Norristown",
    "sg:classifiers":[
        {
            "category":"Professional",
            "subcategory":"Printing & Photocopies",
            "type":"Services"
        },
        {
            "category":"Professional",
            "subcategory":"Business Services",
            "type":"Services"
        }
    ],
    "sg:phone":"+1 610 239 9140",
    "sg:postcode":"19401",
    "sg:province":"PA",
    "sg:tags":[
        "packaging",
        "photocopying"
    ],
    "wof:name":"Mail Ship & Copy",
    "wof:placetype":"venue"
},
  "geometry": {"coordinates":[-75.321444,40.145826],"type":"Point"}
}