{
  "type": "Feature",
  "properties": {
    "addr:full":"3711 Market St Ste 910 Philadelphia PA 19104",
    "addr:housenumber":"3711",
    "addr:postcode":"19104",
    "addr:street":"Market St Ste 910",
    "iso:country":"US",
    "sg:address":"3711 Market St Ste 910",
    "sg:city":"Philadelphia",
    "sg:classifiers":[
        {
            "category":"Home & Garden",
            "subcategory":"Building Materials",
            "type":"Retail Goods"
        }
    ],
    "sg:phone":"+1 877 320 0356",
    "sg:postcode":"19104",
    "sg:province":"PA",
    "sg:tags":[
        "insulation",
        "product",
        "conservation",
        "energy"
    ],
    "wof:name":"Energy Plus",
    "wof:placetype":"venue"
},
  "geometry": {"coordinates":[-75.196298,39.956449],"type":"Point"}
}