{
  "type": "Feature",
  "properties": {
    "iso:country":"US",
    "sg:address":"7221 Haasadahl Rd",
    "sg:city":"Allentown",
    "sg:classifiers":[
        {
            "category":"Building & Trades",
            "subcategory":"Construction",
            "type":"Services"
        }
    ],
    "sg:phone":"+1   ",
    "sg:postcode":"18106",
    "sg:province":"PA",
    "sg:tags":[
        "house"
    ],
    "wof:name":"Jpz",
    "wof:placetype":"venue"
},
  "geometry": {"coordinates":[-75.62897599999999,40.60657],"type":"Point"}
}