{
  "type": "Feature",
  "properties": {
    "iso:country":"US",
    "sg:address":"1020 Evans City Rd",
    "sg:city":"Renfrew",
    "sg:classifiers":[
        {
            "category":"Autos & Motor Vehicles",
            "subcategory":"Automobile Sales",
            "type":"Retail Goods"
        },
        {
            "category":"Retail",
            "subcategory":"Auto Repair",
            "type":"Services"
        }
    ],
    "sg:phone":"+1 724 789 7297",
    "sg:postcode":"16053",
    "sg:province":"PA",
    "sg:tags":[
        "equipment",
        "air conditioning"
    ],
    "wof:name":"Magill Truck & Trailer Repair",
    "wof:placetype":"venue"
},
  "geometry": {"coordinates":[-79.997157,40.840181],"type":"Point"}
}