{
  "type": "Feature",
  "properties": {
    "iso:country":"US",
    "sg:address":"1002 Spruce St ",
    "sg:city":"Latrobe",
    "sg:classifiers":[
        {
            "category":"Restaurant",
            "type":"Food & Drink"
        }
    ],
    "sg:menulink":"http://www.allmenus.com/pa/unity/287682-reds-subs-6-pack--more/menu/",
    "sg:phone":"+1 724 532 3505",
    "sg:postcode":"15650",
    "sg:province":"PA",
    "sg:tags":[
        "sandwich",
        "salad",
        "burger",
        "american",
        "chicken",
        "pizza"
    ],
    "wof:name":"Red's Subs 6 Pack & More ",
    "wof:placetype":"venue"
},
  "geometry": {"coordinates":[-79.361413,40.288679],"type":"Point"}
}