{
  "type": "Feature",
  "properties": {
    "iso:country":"US",
    "sg:address":"320 Dekalb St",
    "sg:city":"Norristown",
    "sg:classifiers":[
        {
            "category":"Travel",
            "subcategory":"Travel Agent",
            "type":"Entertainment"
        }
    ],
    "sg:phone":"+1 610 275 9110",
    "sg:postcode":"19401",
    "sg:province":"PA",
    "sg:tags":[
        "agency"
    ],
    "wof:name":"Gias Agency",
    "wof:placetype":"venue"
},
  "geometry": {"coordinates":[-75.34190599999999,40.114322],"type":"Point"}
}