{
  "type": "Feature",
  "properties": {
    "iso:country":"US",
    "sg:address":"675 Castle Creek Dr",
    "sg:city":"Mars",
    "sg:classifiers":[
        {
            "category":"Food & Beverages",
            "subcategory":"Groceries & Convenience Stores",
            "type":"Retail Goods"
        }
    ],
    "sg:phone":"+1   ",
    "sg:postcode":"16046",
    "sg:province":"PA",
    "wof:name":"Sunoco",
    "wof:placetype":"venue"
},
  "geometry": {"coordinates":[-80.065575,40.684375],"type":"Point"}
}