{
  "type": "Feature",
  "properties": {
    "iso:country":"US",
    "sg:address":"6 Penns Trl",
    "sg:city":"Newtown",
    "sg:classifiers":[
        {
            "category":"Banks & Credit Unions",
            "subcategory":"Bank",
            "type":"Services"
        }
    ],
    "sg:phone":"+1 215 504 7180",
    "sg:postcode":"18940",
    "sg:province":"PA",
    "sg:tags":[
        "loan",
        "mortgage",
        "real estate"
    ],
    "wof:name":"Concorde Acceptance Corp",
    "wof:placetype":"venue"
},
  "geometry": {"coordinates":[-74.909333,40.228099],"type":"Point"}
}