{
  "type": "Feature",
  "properties": {
    "addr:full":"3226 Woodlea Rd Orefield PA 18069",
    "addr:housenumber":"3226",
    "addr:postcode":"18069",
    "addr:street":"Woodlea Rd",
    "iso:country":"US",
    "sg:address":"3226 Woodlea Rd",
    "sg:city":"Orefield",
    "sg:classifiers":[
        {
            "category":"Building & Trades",
            "subcategory":"Construction",
            "type":"Services"
        }
    ],
    "sg:phone":"+1   ",
    "sg:postcode":"18069",
    "sg:province":"PA",
    "sg:tags":[
        "nonresidential"
    ],
    "wof:name":"K&K Contractors Inc",
    "wof:placetype":"venue"
},
  "geometry": {"coordinates":[-75.59269399999999,40.640737],"type":"Point"}
}