{
  "type": "Feature",
  "properties": {
    "addr:full":"195 Swinehart Rd Coatesville PA 19320",
    "addr:housenumber":"195",
    "addr:postcode":"19320",
    "addr:street":"Swinehart Rd",
    "iso:country":"US",
    "sg:address":"195 Swinehart Rd",
    "sg:city":"Coatesville",
    "sg:classifiers":[
        {
            "category":"Building & Trades",
            "subcategory":"Plumbing",
            "type":"Services"
        }
    ],
    "sg:phone":"+1   ",
    "sg:postcode":"19320",
    "sg:province":"PA",
    "sg:tags":[
        "business",
        "contractor"
    ],
    "wof:name":"Beaver Creek Plumbing Inc",
    "wof:placetype":"venue"
},
  "geometry": {"coordinates":[-75.797308,40.036847],"type":"Point"}
}