{
  "type": "Feature",
  "properties": {
    "addr:full":"2420 Durham Rd Bristol PA 19007",
    "addr:housenumber":"2420",
    "addr:postcode":"19007",
    "addr:street":"Durham Rd",
    "iso:country":"US",
    "sg:address":"2420 Durham Rd",
    "sg:city":"Bristol",
    "sg:classifiers":[
        {
            "category":"Retail",
            "subcategory":"Laundry & Dry Cleaning",
            "type":"Services"
        }
    ],
    "sg:phone":"+1 215 269 1945",
    "sg:postcode":"19007",
    "sg:province":"PA",
    "wof:name":"Gemini Cleaners",
    "wof:placetype":"venue"
},
  "geometry": {"coordinates":[-74.88359800000001,40.127701],"type":"Point"}
}