{
  "type": "Feature",
  "properties": {
    "iso:country":"US",
    "sg:address":"898 Rock Rd",
    "sg:city":"Pine Grove",
    "sg:classifiers":[
        {
            "category":"Utilities",
            "subcategory":"Refuse",
            "type":"Services"
        }
    ],
    "sg:phone":"+1 570 345 2076",
    "sg:postcode":"17963",
    "sg:province":"PA",
    "sg:tags":[
        "sanitation"
    ],
    "wof:name":"Cliff's Hauling Svc",
    "wof:placetype":"venue"
},
  "geometry": {"coordinates":[-76.303533,40.54187],"type":"Point"}
}