{
  "type": "Feature",
  "properties": {
    "iso:country":"US",
    "sg:address":"6401 Penn Ave",
    "sg:city":"Pittsburgh",
    "sg:classifiers":[
        {
            "category":"Wholesale",
            "subcategory":"Machinery & Supplies",
            "type":"Manufacturing & Wholesale Goods"
        }
    ],
    "sg:phone":"+1 412 361 3899",
    "sg:postcode":"15206",
    "sg:province":"PA",
    "sg:tags":[
        "equipment",
        "establishment"
    ],
    "wof:name":"Hair Master",
    "wof:placetype":"venue"
},
  "geometry": {"coordinates":[-79.917773,40.457834],"type":"Point"}
}