{
  "type": "Feature",
  "properties": {
    "iso:country":"US",
    "sg:address":"3324 N 21st St",
    "sg:city":"Philadelphia",
    "sg:classifiers":[
        {
            "category":"Food & Beverages",
            "subcategory":"Groceries & Convenience Stores",
            "type":"Retail Goods"
        }
    ],
    "sg:phone":"+1 215 228 5527",
    "sg:postcode":"19140",
    "sg:province":"PA",
    "wof:name":"Mill Way",
    "wof:placetype":"venue"
},
  "geometry": {"coordinates":[-75.16394099999999,40.004655],"type":"Point"}
}