{
  "type": "Feature",
  "properties": {
    "iso:country":"US",
    "sg:address":"911 Tottenham Dr",
    "sg:city":"Coraopolis",
    "sg:classifiers":[
        {
            "category":"Professional",
            "type":"Services"
        }
    ],
    "sg:phone":"+1   ",
    "sg:postcode":"15108",
    "sg:province":"PA",
    "wof:name":"Robert C Tumulty",
    "wof:placetype":"venue"
},
  "geometry": {"coordinates":[-80.206677,40.507861],"type":"Point"}
}