{
  "type": "Feature",
  "properties": {
    "iso:country":"US",
    "sg:address":"95 N Main St",
    "sg:city":"Shavertown",
    "sg:classifiers":[
        {
            "category":"Retail",
            "subcategory":"Auto Repair",
            "type":"Services"
        }
    ],
    "sg:phone":"+1   ",
    "sg:postcode":"18708",
    "sg:province":"PA",
    "sg:tags":[
        "general"
    ],
    "wof:name":"Merls Garage Rearl",
    "wof:placetype":"venue"
},
  "geometry": {"coordinates":[-75.939116,41.318079],"type":"Point"}
}