{
  "type": "Feature",
  "properties": {
    "addr:full":"100 Mellott Dr Warfordsburg PA 17267",
    "addr:housenumber":"100",
    "addr:postcode":"17267",
    "addr:street":"Mellott Dr",
    "iso:country":"US",
    "sg:address":"100 Mellott Dr",
    "sg:city":"Warfordsburg",
    "sg:classifiers":[
        {
            "category":"Professional",
            "subcategory":"Management & Consulting",
            "type":"Services"
        }
    ],
    "sg:phone":"+1 717 294 6868",
    "sg:postcode":"17267",
    "sg:province":"PA",
    "sg:tags":[
        "consultant",
        "nursing"
    ],
    "wof:name":"Vital Staffing",
    "wof:placetype":"venue"
},
  "geometry": {"coordinates":[-78.179986,39.722395],"type":"Point"}
}