{
  "type": "Feature",
  "properties": {
    "addr:full":"1049 5th Ave New Kensington PA 15068",
    "addr:housenumber":"1049",
    "addr:postcode":"15068",
    "addr:street":"5Th Ave",
    "iso:country":"US",
    "sg:address":"1049 5th Ave",
    "sg:city":"New Kensington",
    "sg:classifiers":[
        {
            "category":"Organizations",
            "subcategory":"Community Association",
            "type":"Services"
        }
    ],
    "sg:phone":"+1   ",
    "sg:postcode":"15068",
    "sg:province":"PA",
    "wof:name":"Lodge 53 - New Kensington",
    "wof:placetype":"venue"
},
  "geometry": {"coordinates":[-79.765792,40.56755],"type":"Point"}
}