{
  "type": "Feature",
  "properties": {
    "iso:country":"US",
    "sg:address":"339 Gold Finch Dr",
    "sg:city":"Palmyra",
    "sg:classifiers":[
        {
            "category":"Personal",
            "type":"Services"
        }
    ],
    "sg:phone":"+1 717 832 1125",
    "sg:postcode":"17078",
    "sg:province":"PA",
    "sg:tags":[
        "consultant",
        "wedding"
    ],
    "sg:website":"www.onceuponadream.com",
    "wof:name":"Once Upon A Dream Wedding Inc",
    "wof:placetype":"venue"
},
  "geometry": {"coordinates":[-76.59099500000001,40.279642],"type":"Point"}
}