{
  "type": "Feature",
  "properties": {
    "iso:country":"US",
    "sg:address":"575 Oak Ridge Rd",
    "sg:city":"Hazleton",
    "sg:classifiers":[
        {
            "category":"Wholesale",
            "subcategory":"Non-durable Goods",
            "type":"Manufacturing & Wholesale Goods"
        }
    ],
    "sg:phone":"+1 570 384 0753",
    "sg:postcode":"18202",
    "sg:province":"PA",
    "sg:tags":[
        "pet",
        "supply"
    ],
    "wof:name":"Lazy Pet Products",
    "wof:placetype":"venue"
},
  "geometry": {"coordinates":[-76.048906,40.928119],"type":"Point"}
}