{
  "type": "Feature",
  "properties": {
    "addr:full":"220 Old W Penn Ave Robesonia PA 19565",
    "addr:housenumber":"220",
    "addr:postcode":"19565",
    "addr:street":"Old W Penn Ave",
    "iso:country":"US",
    "sg:address":"220 Old W Penn Ave",
    "sg:city":"Robesonia",
    "sg:classifiers":[
        {
            "category":"Manufacturing",
            "subcategory":"Metals",
            "type":"Manufacturing & Wholesale Goods"
        }
    ],
    "sg:phone":"+1 610 693 5822",
    "sg:postcode":"19565",
    "sg:province":"PA",
    "sg:tags":[
        "steel",
        "prod"
    ],
    "sg:website":"www.reading-alloys.com",
    "wof:name":"Reading Alloys Inc",
    "wof:placetype":"venue"
},
  "geometry": {"coordinates":[-76.118258,40.343455],"type":"Point"}
}