{
  "type": "Feature",
  "properties": {
    "addr:full":"1496 Buck Rd Holland PA 18966",
    "addr:housenumber":"1496",
    "addr:postcode":"18966",
    "addr:street":"Buck Rd",
    "iso:country":"US",
    "sg:address":"1496 Buck Rd",
    "sg:city":"Holland",
    "sg:classifiers":[
        {
            "category":"Health Services",
            "subcategory":"Doctor",
            "type":"Services"
        }
    ],
    "sg:phone":"+1 215 504 8700",
    "sg:postcode":"18966",
    "sg:province":"PA",
    "sg:tags":[
        "physician",
        "medical",
        "surgeon"
    ],
    "wof:name":"Village Shires Family Medicine",
    "wof:placetype":"venue"
},
  "geometry": {"coordinates":[-74.95527300000001,40.204151],"type":"Point"}
}