{
  "type": "Feature",
  "properties": {
    "iso:country":"US",
    "sg:address":"109 Conestoga Blvd",
    "sg:city":"Lancaster",
    "sg:classifiers":[
        {
            "category":"Retail",
            "subcategory":"Repair Shop",
            "type":"Services"
        }
    ],
    "sg:phone":"+1 717 392 7352",
    "sg:postcode":"17602",
    "sg:province":"PA",
    "sg:tags":[
        "taxidermist"
    ],
    "wof:name":"Woody's Taxidermy",
    "wof:placetype":"venue"
},
  "geometry": {"coordinates":[-76.27498799999999,40.032909],"type":"Point"}
}