{
  "type": "Feature",
  "properties": {
    "iso:country":"US",
    "sg:address":"611 Scotrun Ave",
    "sg:city":"Scotrun",
    "sg:classifiers":[
        {
            "category":"Restaurant",
            "type":"Food & Drink"
        }
    ],
    "sg:phone":"+1 570 619 6569",
    "sg:postcode":"18355",
    "sg:province":"PA",
    "sg:tags":[
        "delicatessen"
    ],
    "wof:name":"Anna Polish Deli",
    "wof:placetype":"venue"
},
  "geometry": {"coordinates":[-75.320289,41.066078],"type":"Point"}
}