{
  "type": "Feature",
  "properties": {
    "addr:full":"201 Bear Creek Blvd Wilkes Barre PA 18702",
    "addr:housenumber":"201",
    "addr:postcode":"18702",
    "addr:street":"Bear Creek Blvd",
    "iso:country":"US",
    "sg:address":"201 Bear Creek Blvd",
    "sg:city":"Wilkes Barre",
    "sg:classifiers":[
        {
            "category":"Education",
            "subcategory":"Dance Studio",
            "type":"Public Place"
        }
    ],
    "sg:phone":"+1 570 826 0028",
    "sg:postcode":"18702",
    "sg:province":"PA",
    "sg:tags":[
        "instruction",
        "dancing"
    ],
    "wof:name":"Bravo Dance",
    "wof:placetype":"venue"
},
  "geometry": {"coordinates":[-75.829306,41.245464],"type":"Point"}
}