{
  "type": "Feature",
  "properties": {
    "iso:country":"US",
    "sg:address":"3140 Brodhead Rd",
    "sg:city":"Aliquippa",
    "sg:classifiers":[
        {
            "category":"Health Services",
            "subcategory":"Clinic",
            "type":"Services"
        }
    ],
    "sg:phone":"+1 724 375 1500",
    "sg:postcode":"15001",
    "sg:province":"PA",
    "sg:tags":[
        "holistic",
        "practitioner"
    ],
    "wof:name":"Creative Medicine New Age Emp",
    "wof:placetype":"venue"
},
  "geometry": {"coordinates":[-80.25562499999999,40.577492],"type":"Point"}
}