{
  "type": "Feature",
  "properties": {
    "iso:country":"US",
    "sg:address":"2477 Grant Ave",
    "sg:city":"Philadelphia",
    "sg:classifiers":[
        {
            "category":"Wholesale",
            "subcategory":"Painting Supplies",
            "type":"Manufacturing & Wholesale Goods"
        },
        {
            "category":"Home & Garden",
            "subcategory":"Hardware",
            "type":"Retail Goods"
        },
        {
            "category":"Home & Garden",
            "subcategory":"Building Materials",
            "type":"Retail Goods"
        },
        {
            "category":"Manufacturing",
            "subcategory":"Tools & Machinery",
            "type":"Manufacturing & Wholesale Goods"
        }
    ],
    "sg:phone":"+1 215 776 9006",
    "sg:postcode":"19114",
    "sg:province":"PA",
    "sg:tags":[
        "paint",
        "store",
        "improvement"
    ],
    "sg:website":"http://www.lowes.com",
    "wof:name":"Lowe's",
    "wof:placetype":"venue"
},
  "geometry": {"coordinates":[-75.02594000000001,40.079413],"type":"Point"}
}