{
  "type": "Feature",
  "properties": {
    "iso:country":"US",
    "sg:address":"661 Long Ln",
    "sg:city":"Upper Darby",
    "sg:classifiers":[
        {
            "category":"Retail",
            "subcategory":"Laundry & Dry Cleaning",
            "type":"Services"
        }
    ],
    "sg:phone":"+1 610 623 9394",
    "sg:postcode":"19082",
    "sg:province":"PA",
    "wof:name":"First Long Lane Cleaners",
    "wof:placetype":"venue"
},
  "geometry": {"coordinates":[-75.260803,39.9487],"type":"Point"}
}