{
  "type": "Feature",
  "properties": {
    "iso:country":"US",
    "sg:address":"115 Schoolhouse Rd",
    "sg:city":"Souderton",
    "sg:classifiers":[
        {
            "category":"Retail",
            "subcategory":"Auto Repair",
            "type":"Services"
        }
    ],
    "sg:phone":"+1 215 723 1000",
    "sg:postcode":"18964",
    "sg:province":"PA",
    "sg:tags":[
        "body"
    ],
    "wof:name":"Hayes Barry Auto Body",
    "wof:placetype":"venue"
},
  "geometry": {"coordinates":[-75.343002,40.2757],"type":"Point"}
}