{
  "type": "Feature",
  "properties": {
    "iso:country":"US",
    "sg:address":"3117 Lehigh St",
    "sg:city":"Allentown",
    "sg:classifiers":[
        {
            "category":"Social Services",
            "type":"Services"
        }
    ],
    "sg:phone":"+1   ",
    "sg:postcode":"18103",
    "sg:province":"PA",
    "wof:name":"Adoption Agency",
    "wof:placetype":"venue"
},
  "geometry": {"coordinates":[-75.488106,40.557994],"type":"Point"}
}