{
  "type": "Feature",
  "properties": {
    "iso:country":"US",
    "sg:address":"817 Alpha Rd",
    "sg:city":"Wind Gap",
    "sg:classifiers":[
        {
            "category":"Building & Trades",
            "subcategory":"Electrical",
            "type":"Services"
        }
    ],
    "sg:phone":"+1 610 863 6595",
    "sg:postcode":"18091",
    "sg:province":"PA",
    "sg:tags":[
        "electric",
        "contractor"
    ],
    "wof:name":"Slate Belt Electric Co",
    "wof:placetype":"venue"
},
  "geometry": {"coordinates":[-75.291454,40.856055],"type":"Point"}
}