{
  "type": "Feature",
  "properties": {
    "iso:country":"US",
    "sg:address":"18 E Main St",
    "sg:city":"Lock Haven",
    "sg:classifiers":[
        {
            "category":"Professional",
            "subcategory":"Computer Services",
            "type":"Services"
        }
    ],
    "sg:phone":"+1   ",
    "sg:postcode":"17745",
    "sg:province":"PA",
    "sg:tags":[
        "prepackaged",
        "communications",
        "telephone",
        "software"
    ],
    "wof:name":"Kcnet",
    "wof:placetype":"venue"
},
  "geometry": {"coordinates":[-77.446855,41.137198],"type":"Point"}
}