{
  "type": "Feature",
  "properties": {
    "iso:country":"US",
    "sg:address":"306 Christine Dr",
    "sg:city":"Aliquippa",
    "sg:classifiers":[
        {
            "category":"Building & Trades",
            "subcategory":"Construction",
            "type":"Services"
        }
    ],
    "sg:phone":"+1   ",
    "sg:postcode":"15001",
    "sg:province":"PA",
    "sg:tags":[
        "house"
    ],
    "wof:name":"Dino Dematteis Contractin",
    "wof:placetype":"venue"
},
  "geometry": {"coordinates":[-80.281548,40.615491],"type":"Point"}
}