{
  "type": "Feature",
  "properties": {
    "iso:country":"US",
    "sg:address":"294 Nazareth Pike",
    "sg:city":"Bethlehem",
    "sg:classifiers":[
        {
            "category":"Manufacturing",
            "subcategory":"Tools & Machinery",
            "type":"Manufacturing & Wholesale Goods"
        },
        {
            "category":"Retail",
            "subcategory":"Repair Shop",
            "type":"Services"
        },
        {
            "category":"Building & Trades",
            "subcategory":"Construction",
            "type":"Services"
        },
        {
            "category":"Retail",
            "subcategory":"Auto Repair",
            "type":"Services"
        }
    ],
    "sg:phone":"+1 610 759 6114",
    "sg:postcode":"18020",
    "sg:province":"PA",
    "sg:tags":[
        "machine",
        "automobile",
        "welder",
        "machinery-rebuild"
    ],
    "wof:name":"Flurer Machine & Tool",
    "wof:placetype":"venue"
},
  "geometry": {"coordinates":[-75.34265499999999,40.678026],"type":"Point"}
}