{
  "type": "Feature",
  "properties": {
    "addr:full":"3775 E State St Hermitage PA 16148",
    "addr:housenumber":"3775",
    "addr:postcode":"16148",
    "addr:street":"E State St",
    "iso:country":"US",
    "sg:address":"3775 E State St",
    "sg:city":"Hermitage",
    "sg:classifiers":[
        {
            "category":"Insurance",
            "subcategory":"Insurance Agent",
            "type":"Services"
        }
    ],
    "sg:phone":"+1 724 346 4121",
    "sg:postcode":"16148",
    "sg:province":"PA",
    "sg:website":"www.allenagencyinc.com",
    "wof:name":"Allen Agency Inc-Pennsylvania",
    "wof:placetype":"venue"
},
  "geometry": {"coordinates":[-80.440231,41.234447],"type":"Point"}
}