{
  "type": "Feature",
  "properties": {
    "iso:country":"US",
    "sg:address":"7105 Cedar Park Ave",
    "sg:city":"Philadelphia",
    "sg:classifiers":[
        {
            "category":"Building & Trades",
            "subcategory":"Cleaning & Sanitation",
            "type":"Services"
        }
    ],
    "sg:phone":"+1 215 549 4119",
    "sg:postcode":"19138",
    "sg:province":"PA",
    "sg:tags":[
        "house"
    ],
    "wof:name":"Ronald Wilson Cleaning Team",
    "wof:placetype":"venue"
},
  "geometry": {"coordinates":[-75.154599,40.062996],"type":"Point"}
}