{
  "type": "Feature",
  "properties": {
    "iso:country":"US",
    "sg:address":"737 Hoover Rd",
    "sg:city":"Blue Bell",
    "sg:classifiers":[
        {
            "category":"Real Estate",
            "subcategory":"Real Estate Agent",
            "type":"Services"
        }
    ],
    "sg:phone":"+1   ",
    "sg:postcode":"19422",
    "sg:province":"PA",
    "wof:name":"Blue Bell Management Services",
    "wof:placetype":"venue"
},
  "geometry": {"coordinates":[-75.276296,40.149384],"type":"Point"}
}