{
  "type": "Feature",
  "properties": {
    "iso:country":"US",
    "sg:address":"1421 E Drinker St",
    "sg:city":"Dunmore",
    "sg:classifiers":[
        {
            "category":"Professional",
            "subcategory":"Accounting & Tax Preparation",
            "type":"Services"
        }
    ],
    "sg:phone":"+1 570 346 2057",
    "sg:postcode":"18512",
    "sg:province":"PA",
    "sg:tags":[
        "accountant"
    ],
    "wof:name":"Kelly Barbetti & Co",
    "wof:placetype":"venue"
},
  "geometry": {"coordinates":[-75.600938,41.411696],"type":"Point"}
}