{
  "type": "Feature",
  "properties": {
    "iso:country":"US",
    "sg:address":"3 E North St Ste 300",
    "sg:city":"Bethlehem",
    "sg:classifiers":[
        {
            "category":"Science Facility",
            "type":"Public Place"
        }
    ],
    "sg:phone":"+1 610 954 9230",
    "sg:postcode":"18018",
    "sg:province":"PA",
    "sg:tags":[
        "development",
        "laboratories-research"
    ],
    "wof:name":"Premier Technology",
    "wof:placetype":"venue"
},
  "geometry": {"coordinates":[-75.378319,40.623587],"type":"Point"}
}