{
  "type": "Feature",
  "properties": {
    "iso:country":"US",
    "sg:address":"532 W Tilghman St",
    "sg:city":"Allentown",
    "sg:classifiers":[
        {
            "category":"Shopping",
            "subcategory":"Florist",
            "type":"Retail Goods"
        }
    ],
    "sg:phone":"+1 610 433 0433",
    "sg:postcode":"18102",
    "sg:province":"PA",
    "wof:name":"Bakis C Sons Florists",
    "wof:placetype":"venue"
},
  "geometry": {"coordinates":[-75.47370100000001,40.612701],"type":"Point"}
}