{
  "type": "Feature",
  "properties": {
    "iso:country":"US",
    "sg:address":"127 Stuckey Ln",
    "sg:city":"Reedsville",
    "sg:classifiers":[
        {
            "category":"Building & Trades",
            "subcategory":"Construction",
            "type":"Services"
        }
    ],
    "sg:phone":"+1   ",
    "sg:postcode":"17084",
    "sg:province":"PA",
    "sg:tags":[
        "contractor"
    ],
    "wof:name":"Joe Bonson Construction",
    "wof:placetype":"venue"
},
  "geometry": {"coordinates":[-77.664107,40.677864],"type":"Point"}
}