{
  "type": "Feature",
  "properties": {
    "addr:full":"1380 W Chester Rd West Chester PA 19382",
    "addr:housenumber":"1380",
    "addr:postcode":"19382",
    "addr:street":"W Chester Rd",
    "iso:country":"US",
    "sg:address":"1380 W Chester Rd",
    "sg:city":"West Chester",
    "sg:classifiers":[
        {
            "category":"Manufacturing",
            "subcategory":"Paper Products",
            "type":"Manufacturing & Wholesale Goods"
        }
    ],
    "sg:phone":"+1   ",
    "sg:postcode":"19382",
    "sg:province":"PA",
    "sg:tags":[
        "mill"
    ],
    "wof:name":"Kimberly-Clark",
    "wof:placetype":"venue"
},
  "geometry": {"coordinates":[-75.547369,39.911095],"type":"Point"}
}