{
  "type": "Feature",
  "properties": {
    "iso:country":"US",
    "sg:address":"505 E Gorgas Ln",
    "sg:city":"Philadelphia",
    "sg:classifiers":[
        {
            "category":"Building & Trades",
            "subcategory":"Construction",
            "type":"Services"
        }
    ],
    "sg:phone":"+1 215 242 9009",
    "sg:postcode":"19119",
    "sg:province":"PA",
    "sg:tags":[
        "painter"
    ],
    "wof:name":"Mercer A Redcross III",
    "wof:placetype":"venue"
},
  "geometry": {"coordinates":[-75.17852600000001,40.064016],"type":"Point"}
}