{
  "type": "Feature",
  "properties": {
    "addr:full":"2534 Keeney Dr York PA 17403",
    "addr:housenumber":"2534",
    "addr:postcode":"17403",
    "addr:street":"Keeney Dr",
    "iso:country":"US",
    "sg:address":"2534 Keeney Dr",
    "sg:city":"York",
    "sg:classifiers":[
        {
            "category":"Shopping",
            "subcategory":"Florist",
            "type":"Retail Goods"
        }
    ],
    "sg:phone":"+1   ",
    "sg:postcode":"17403",
    "sg:province":"PA",
    "wof:name":"Anitas Baskets of Flowers",
    "wof:placetype":"venue"
},
  "geometry": {"coordinates":[-76.71948500000001,39.913042],"type":"Point"}
}