{
  "type": "Feature",
  "properties": {
    "addr:full":"3459 Biglerville Rd Biglerville PA 17307",
    "addr:housenumber":"3459",
    "addr:postcode":"17307",
    "addr:street":"Biglerville Rd",
    "iso:country":"US",
    "sg:address":"3459 Biglerville Rd",
    "sg:city":"Biglerville",
    "sg:classifiers":[
        {
            "category":"Banks & Credit Unions",
            "subcategory":"Bank",
            "type":"Services"
        }
    ],
    "sg:phone":"+1 717 677 6172",
    "sg:postcode":"17307",
    "sg:province":"PA",
    "wof:name":"Adams County National Bank",
    "wof:placetype":"venue"
},
  "geometry": {"coordinates":[-77.24826299999999,39.925402],"type":"Point"}
}