{
  "type": "Feature",
  "properties": {
    "iso:country":"US",
    "sg:address":"3098 Carlisle Rd",
    "sg:city":"Dover",
    "sg:classifiers":[
        {
            "category":"Restaurant",
            "type":"Food & Drink"
        }
    ],
    "sg:menulink":"http://www.allmenus.com/pa/dover/71992-pizza-hut/menu/",
    "sg:phone":"+1 717 767 6929",
    "sg:postcode":"17315",
    "sg:province":"PA",
    "sg:tags":[
        "american",
        "pizza"
    ],
    "wof:name":"Pizza Hut",
    "wof:placetype":"venue"
},
  "geometry": {"coordinates":[-76.82109199999999,39.983275],"type":"Point"}
}