{
  "type": "Feature",
  "properties": {
    "addr:full":"722 S Chiques Rd Manheim PA 17545",
    "addr:housenumber":"722",
    "addr:postcode":"17545",
    "addr:street":"S Chiques Rd",
    "iso:country":"US",
    "sg:address":"722 S Chiques Rd",
    "sg:city":"Manheim",
    "sg:classifiers":[
        {
            "category":"Organizations",
            "subcategory":"Community Association",
            "type":"Services"
        }
    ],
    "sg:phone":"+1 717 898 8451",
    "sg:postcode":"17545",
    "sg:province":"PA",
    "sg:tags":[
        "club"
    ],
    "wof:name":"Lancaster Liederkranz",
    "wof:placetype":"venue"
},
  "geometry": {"coordinates":[-76.44382400000001,40.108446],"type":"Point"}
}