{
  "type": "Feature",
  "properties": {
    "iso:country":"US",
    "sg:address":"619 Reed Avenue",
    "sg:city":"Monessen",
    "sg:classifiers":[
        {
            "category":"Food & Beverages",
            "subcategory":"Candy",
            "type":"Retail Goods"
        }
    ],
    "sg:phone":"+1 724 314 3482",
    "sg:postcode":"15062",
    "sg:province":"PA",
    "sg:tags":[
        "dessert"
    ],
    "sg:website":"www.shortbreadcity.com",
    "wof:name":"Shortbread City",
    "wof:placetype":"venue"
},
  "geometry": {"coordinates":[-79.889211,40.159562],"type":"Point"}
}