{
  "type": "Feature",
  "properties": {
    "iso:country":"US",
    "sg:address":"901 Valley Hill Rd",
    "sg:city":"Exton",
    "sg:classifiers":[
        {
            "category":"Wholesale",
            "subcategory":"Motor Vehicles",
            "type":"Manufacturing & Wholesale Goods"
        }
    ],
    "sg:phone":"+1   ",
    "sg:postcode":"19341",
    "sg:province":"PA",
    "sg:tags":[
        "automobile"
    ],
    "wof:name":"Buyfigurecom Inc",
    "wof:placetype":"venue"
},
  "geometry": {"coordinates":[-75.615032,40.050608],"type":"Point"}
}