{
  "type": "Feature",
  "properties": {
    "addr:full":"4711 Derry St Harrisburg PA 17111",
    "addr:housenumber":"4711",
    "addr:postcode":"17111",
    "addr:street":"Derry St",
    "iso:country":"US",
    "sg:address":"4711 Derry St",
    "sg:city":"Harrisburg",
    "sg:classifiers":[
        {
            "category":"Personal",
            "type":"Services"
        }
    ],
    "sg:phone":"+1 717 558 8207",
    "sg:postcode":"17111",
    "sg:province":"PA",
    "sg:tags":[
        "electrolysis"
    ],
    "wof:name":"Ali Baysinger Studio",
    "wof:placetype":"venue"
},
  "geometry": {"coordinates":[-76.80410000000001,40.258396],"type":"Point"}
}