{
  "type": "Feature",
  "properties": {
    "iso:country":"US",
    "sg:address":"124 N 6th St",
    "sg:city":"Perkasie",
    "sg:classifiers":[
        {
            "category":"Home & Garden",
            "subcategory":"Furniture",
            "type":"Retail Goods"
        }
    ],
    "sg:phone":"+1 215 453 8228",
    "sg:postcode":"18944",
    "sg:province":"PA",
    "sg:tags":[
        "builder",
        "custom"
    ],
    "wof:name":"James Van Etten Furniture-Dsgn",
    "wof:placetype":"venue"
},
  "geometry": {"coordinates":[-75.293481,40.374999],"type":"Point"}
}