{
  "type": "Feature",
  "properties": {
    "iso:country":"US",
    "sg:address":"383 Ranch Rd",
    "sg:city":"Pitman",
    "sg:classifiers":[
        {
            "category":"Farming",
            "subcategory":"Dairy Farm",
            "type":"Manufacturing & Wholesale Goods"
        }
    ],
    "sg:phone":"+1   ",
    "sg:postcode":"17964",
    "sg:province":"PA",
    "wof:name":"Larry Hepler",
    "wof:placetype":"venue"
},
  "geometry": {"coordinates":[-76.495204,40.716878],"type":"Point"}
}