{
  "type": "Feature",
  "properties": {
    "iso:country":"US",
    "sg:address":"27 S Mill St",
    "sg:city":"New Salem",
    "sg:classifiers":[
        {
            "category":"Organizations",
            "subcategory":"Religious Organization",
            "type":"Services"
        }
    ],
    "sg:phone":"+1 724 245 2200",
    "sg:postcode":"15468",
    "sg:province":"PA",
    "sg:tags":[
        "church"
    ],
    "wof:name":"New Salem Presbyterian Church",
    "wof:placetype":"venue"
},
  "geometry": {"coordinates":[-79.83768999999999,39.924553],"type":"Point"}
}