{
  "type": "Feature",
  "properties": {
    "iso:country":"US",
    "sg:address":"400 State St",
    "sg:city":"Butler",
    "sg:classifiers":[
        {
            "category":"Home & Garden",
            "subcategory":"Kitchen Supply",
            "type":"Retail Goods"
        }
    ],
    "sg:phone":"+1 724 282 8422",
    "sg:postcode":"16001",
    "sg:province":"PA",
    "sg:tags":[
        "equipment",
        "restaurant"
    ],
    "wof:name":"Mon-D-Aid & Cleanit Company",
    "wof:placetype":"venue"
},
  "geometry": {"coordinates":[-79.902191,40.86422],"type":"Point"}
}