{
  "type": "Feature",
  "properties": {
    "addr:full":"777 N 8th Ave Lebanon PA 17046",
    "addr:housenumber":"777",
    "addr:postcode":"17046",
    "addr:street":"N 8Th Ave",
    "iso:country":"US",
    "sg:address":"777 N 8th Ave",
    "sg:city":"Lebanon",
    "sg:classifiers":[
        {
            "category":"Shopping",
            "subcategory":"Clothing, Apparel, & Fashions",
            "type":"Retail Goods"
        }
    ],
    "sg:phone":"+1 717 272 6466",
    "sg:postcode":"17046",
    "sg:province":"PA",
    "wof:name":"G & G Uniform Shop",
    "wof:placetype":"venue"
},
  "geometry": {"coordinates":[-76.39940900000001,40.353165],"type":"Point"}
}