{
  "type": "Feature",
  "properties": {
    "iso:country":"US",
    "sg:address":"1421 Arch St",
    "sg:city":"Philadelphia",
    "sg:classifiers":[
        {
            "category":"Real Estate",
            "subcategory":"Architect",
            "type":"Services"
        }
    ],
    "sg:phone":"+1 215 496 1352",
    "sg:postcode":"19102",
    "sg:province":"PA",
    "wof:name":"1421 Arch Street Building",
    "wof:placetype":"venue"
},
  "geometry": {"coordinates":[-75.16321499999999,39.954423],"type":"Point"}
}