{
  "type": "Feature",
  "properties": {
    "iso:country":"US",
    "sg:address":"1310 Lackawanna Trl",
    "sg:city":"Clarks Summit",
    "sg:classifiers":[
        {
            "category":"Professional",
            "subcategory":"Accounting & Tax Preparation",
            "type":"Services"
        }
    ],
    "sg:phone":"+1 570 563 1140",
    "sg:postcode":"18411",
    "sg:province":"PA",
    "sg:tags":[
        "accountant"
    ],
    "sg:website":"www.cjspc.com",
    "wof:name":"Cawley Johnson & Sanders PC",
    "wof:placetype":"venue"
},
  "geometry": {"coordinates":[-75.730057,41.522163],"type":"Point"}
}