{
  "type": "Feature",
  "properties": {
    "iso:country":"US",
    "sg:address":"725 S State St",
    "sg:city":"Clarks Summit",
    "sg:classifiers":[
        {
            "category":"Home & Garden",
            "subcategory":"Home Furnishings",
            "type":"Retail Goods"
        }
    ],
    "sg:phone":"+1 570 586 9792",
    "sg:postcode":"18411",
    "sg:province":"PA",
    "wof:name":"Drapery Shop",
    "wof:placetype":"venue"
},
  "geometry": {"coordinates":[-75.69666100000001,41.488971],"type":"Point"}
}