{
  "type": "Feature",
  "properties": {
    "addr:full":"782 Waterdam Rd Canonsburg PA 15317",
    "addr:housenumber":"782",
    "addr:postcode":"15317",
    "addr:street":"Waterdam Rd",
    "iso:country":"US",
    "sg:address":"782 Waterdam Rd",
    "sg:city":"Canonsburg",
    "sg:classifiers":[
        {
            "category":"Professional",
            "subcategory":"Management & Consulting",
            "type":"Services"
        }
    ],
    "sg:phone":"+1   ",
    "sg:postcode":"15317",
    "sg:province":"PA",
    "wof:name":"Equestrian Management Inc",
    "wof:placetype":"venue"
},
  "geometry": {"coordinates":[-80.10056,40.248322],"type":"Point"}
}