{
  "type": "Feature",
  "properties": {
    "iso:country":"US",
    "sg:address":"9710 Wattsburg Rd",
    "sg:city":"Erie",
    "sg:classifiers":[
        {
            "category":"Shopping",
            "subcategory":"Hobbies, Toys, & Games",
            "type":"Retail Goods"
        }
    ],
    "sg:phone":"+1 814 825 6017",
    "sg:postcode":"16509",
    "sg:province":"PA",
    "sg:tags":[
        "craft"
    ],
    "wof:name":"Marci's & Me Too",
    "wof:placetype":"venue"
},
  "geometry": {"coordinates":[-79.942425,42.063714],"type":"Point"}
}