{
  "type": "Feature",
  "properties": {
    "addr:full":"2500 Cumberland St Lebanon PA 17042",
    "addr:housenumber":"2500",
    "addr:postcode":"17042",
    "addr:street":"Cumberland St",
    "iso:country":"US",
    "sg:address":"2500 Cumberland St",
    "sg:city":"Lebanon",
    "sg:classifiers":[
        {
            "category":"Professional",
            "subcategory":"Computer Services",
            "type":"Services"
        }
    ],
    "sg:phone":"+1   ",
    "sg:postcode":"17042",
    "sg:province":"PA",
    "sg:tags":[
        "design",
        "system"
    ],
    "wof:name":"Central P A Computer Solutions",
    "wof:placetype":"venue"
},
  "geometry": {"coordinates":[-76.45595299999999,40.339629],"type":"Point"}
}