{
  "type": "Feature",
  "properties": {
    "iso:country":"US",
    "sg:address":"625 Bethlehem Pike",
    "sg:city":"Glenside",
    "sg:classifiers":[
        {
            "category":"Shopping",
            "subcategory":"Florist",
            "type":"Retail Goods"
        }
    ],
    "sg:phone":"+1 215 836 7330",
    "sg:postcode":"19038",
    "sg:province":"PA",
    "wof:name":"Coupe Flowers Inc",
    "wof:placetype":"venue"
},
  "geometry": {"coordinates":[-75.21438499999999,40.092166],"type":"Point"}
}