{
  "type": "Feature",
  "properties": {
    "addr:full":"6334 Forbes Ave Pittsburgh PA 15217",
    "addr:housenumber":"6334",
    "addr:postcode":"15217",
    "addr:street":"Forbes Ave",
    "iso:country":"US",
    "sg:address":"6334 Forbes Ave",
    "sg:city":"Pittsburgh",
    "sg:classifiers":[
        {
            "category":"Organizations",
            "subcategory":"Non-profit Organization",
            "type":"Services"
        }
    ],
    "sg:phone":"+1   ",
    "sg:postcode":"15217",
    "sg:province":"PA",
    "sg:tags":[
        "social"
    ],
    "wof:name":"Pittsburgh Zionist District",
    "wof:placetype":"venue"
},
  "geometry": {"coordinates":[-79.918235,40.437964],"type":"Point"}
}