{
  "type": "Feature",
  "properties": {
    "addr:full":"136 Grimesville Rd Williamsport PA 17701",
    "addr:housenumber":"136",
    "addr:postcode":"17701",
    "addr:street":"Grimesville Rd",
    "iso:country":"US",
    "sg:address":"136 Grimesville Rd",
    "sg:city":"Williamsport",
    "sg:classifiers":[
        {
            "category":"Social Services",
            "subcategory":"Child Care",
            "type":"Services"
        }
    ],
    "sg:phone":"+1 570 321 7991",
    "sg:postcode":"17701",
    "sg:province":"PA",
    "wof:name":"YMCA Preschool Ctr",
    "wof:placetype":"venue"
},
  "geometry": {"coordinates":[-77.070887,41.252046],"type":"Point"}
}