{
  "type": "Feature",
  "properties": {
    "iso:country":"US",
    "sg:address":"1305 N Providence Rd",
    "sg:city":"Media",
    "sg:classifiers":[
        {
            "category":"Insurance",
            "subcategory":"Insurance Agent",
            "type":"Services"
        }
    ],
    "sg:phone":"+1 610 566 9300",
    "sg:postcode":"19063",
    "sg:province":"PA",
    "wof:name":"E Walter Helm Jr Inc",
    "wof:placetype":"venue"
},
  "geometry": {"coordinates":[-75.39118499999999,39.935271],"type":"Point"}
}