{
  "type": "Feature",
  "properties": {
    "addr:full":"1125 W Chester Pike Havertown PA 19083",
    "addr:housenumber":"1125",
    "addr:postcode":"19083",
    "addr:street":"W Chester Pike",
    "iso:country":"US",
    "sg:address":"1125 W Chester Pike",
    "sg:city":"Havertown",
    "sg:classifiers":[
        {
            "category":"Building & Trades",
            "subcategory":"Pest Control",
            "type":"Services"
        }
    ],
    "sg:phone":"+1 610 789 7378",
    "sg:postcode":"19083",
    "sg:province":"PA",
    "wof:name":"Cunningham Pest Control",
    "wof:placetype":"venue"
},
  "geometry": {"coordinates":[-75.314956,39.97224],"type":"Point"}
}