{
  "type": "Feature",
  "properties": {
    "addr:full":"107 E Market St Clearfield PA 16830",
    "addr:housenumber":"107",
    "addr:postcode":"16830",
    "addr:street":"E Market St",
    "iso:country":"US",
    "sg:address":"107 E Market St",
    "sg:city":"Clearfield",
    "sg:classifiers":[
        {
            "category":"Government",
            "subcategory":"Office",
            "type":"Public Place"
        }
    ],
    "sg:phone":"+1 814 765 1501",
    "sg:postcode":"16830",
    "sg:province":"PA",
    "sg:tags":[
        "village"
    ],
    "wof:name":"Clearfield Sewage Treatment",
    "wof:placetype":"venue"
},
  "geometry": {"coordinates":[-78.43975399999999,41.022006],"type":"Point"}
}