{
  "type": "Feature",
  "properties": {
    "addr:full":"831 Delta Ave Reading PA 19605",
    "addr:housenumber":"831",
    "addr:postcode":"19605",
    "addr:street":"Delta Ave",
    "iso:country":"US",
    "sg:address":"831 Delta Ave",
    "sg:city":"Reading",
    "sg:classifiers":[
        {
            "category":"Arts & Performance",
            "subcategory":"Theater",
            "type":"Entertainment"
        }
    ],
    "sg:phone":"+1   ",
    "sg:postcode":"19605",
    "sg:province":"PA",
    "sg:tags":[
        "group"
    ],
    "wof:name":"Tiggar & Trixann",
    "wof:placetype":"venue"
},
  "geometry": {"coordinates":[-75.922766,40.37008],"type":"Point"}
}