{
  "type": "Feature",
  "properties": {
    "iso:country":"US",
    "sg:address":"6565 Furnace Rd",
    "sg:city":"Waynesboro",
    "sg:classifiers":[
        {
            "category":"Food & Beverages",
            "subcategory":"Meat & Fish",
            "type":"Retail Goods"
        }
    ],
    "sg:phone":"+1 717 749 0098",
    "sg:postcode":"17268",
    "sg:province":"PA",
    "sg:tags":[
        "seafood"
    ],
    "wof:name":"Valley Ag Products",
    "wof:placetype":"venue"
},
  "geometry": {"coordinates":[-77.550416,39.828527],"type":"Point"}
}