{
  "type": "Feature",
  "properties": {
    "addr:full":"2661 Audubon Rd Norristown PA 19403",
    "addr:housenumber":"2661",
    "addr:postcode":"19403",
    "addr:street":"Audubon Rd",
    "iso:country":"US",
    "sg:address":"2661 Audubon Rd",
    "sg:city":"Norristown",
    "sg:classifiers":[
        {
            "category":"Professional",
            "subcategory":"Business Services",
            "type":"Services"
        },
        {
            "category":"Manufacturing",
            "subcategory":"Chemicals & Compounds",
            "type":"Manufacturing & Wholesale Goods"
        }
    ],
    "sg:phone":"+1   ",
    "sg:postcode":"19403",
    "sg:province":"PA",
    "sg:tags":[
        "packaging",
        "trial",
        "clinical",
        "provision",
        "for"
    ],
    "wof:name":"Clinical Trial Services (us)",
    "wof:placetype":"venue"
},
  "geometry": {"coordinates":[-75.42526100000001,40.118777],"type":"Point"}
}