{
  "type": "Feature",
  "properties": {
    "iso:country":"US",
    "sg:address":"332 Willow Hedge Dr",
    "sg:city":"Monroeville",
    "sg:classifiers":[
        {
            "category":"Professional",
            "type":"Services"
        }
    ],
    "sg:phone":"+1   ",
    "sg:postcode":"15146",
    "sg:province":"PA",
    "wof:name":"Craig Codeluppi",
    "wof:placetype":"venue"
},
  "geometry": {"coordinates":[-79.77225900000001,40.453477],"type":"Point"}
}