{
  "type": "Feature",
  "properties": {
    "iso:country":"US",
    "sg:address":"150 Messner Ln",
    "sg:city":"Glenmoore",
    "sg:classifiers":[
        {
            "category":"Building & Trades",
            "subcategory":"Landscaping Services",
            "type":"Services"
        }
    ],
    "sg:phone":"+1 610 942 9799",
    "sg:postcode":"19343",
    "sg:province":"PA",
    "sg:tags":[
        "lawn"
    ],
    "wof:name":"Diamond Black Design Group Inc",
    "wof:placetype":"venue"
},
  "geometry": {"coordinates":[-75.76318999999999,40.068822],"type":"Point"}
}