{
  "type": "Feature",
  "properties": {
    "iso:country":"US",
    "sg:address":"151 N Hanover St",
    "sg:city":"Pottstown",
    "sg:classifiers":[
        {
            "category":"Health Services",
            "subcategory":"Chiropractor",
            "type":"Services"
        }
    ],
    "sg:phone":"+1   ",
    "sg:postcode":"19464",
    "sg:province":"PA",
    "sg:tags":[
        "operator",
        "apartment",
        "dwelling",
        "build"
    ],
    "wof:name":"Jay H Smith DC",
    "wof:placetype":"venue"
},
  "geometry": {"coordinates":[-75.649801,40.248983],"type":"Point"}
}