{
  "type": "Feature",
  "properties": {
    "iso:country":"US",
    "sg:address":"4 Commerce Dr",
    "sg:city":"Plum",
    "sg:classifiers":[
        {
            "category":"Autos & Motor Vehicles",
            "subcategory":"Automobile Sales",
            "type":"Retail Goods"
        },
        {
            "category":"Wholesale",
            "subcategory":"Auto Parts",
            "type":"Manufacturing & Wholesale Goods"
        }
    ],
    "sg:phone":"+1 412 798 1611",
    "sg:postcode":"15239",
    "sg:province":"PA",
    "sg:tags":[
        "car",
        "dealer"
    ],
    "wof:name":"Premier Motor Sales",
    "wof:placetype":"venue"
},
  "geometry": {"coordinates":[-79.772469,40.465681],"type":"Point"}
}