{
  "type": "Feature",
  "properties": {
    "iso:country":"US",
    "sg:address":"20 Hillcrest Ln",
    "sg:city":"Mc Clure",
    "sg:classifiers":[
        {
            "category":"Farming",
            "subcategory":"Livestock Farm",
            "type":"Manufacturing & Wholesale Goods"
        }
    ],
    "sg:phone":"+1   ",
    "sg:postcode":"17841",
    "sg:province":"PA",
    "sg:tags":[
        "beef",
        "feedlot",
        "cattle"
    ],
    "wof:name":"Mark Wright",
    "wof:placetype":"venue"
},
  "geometry": {"coordinates":[-77.35885399999999,40.710304],"type":"Point"}
}