{
  "type": "Feature",
  "properties": {
    "iso:country":"US",
    "sg:address":"1315 S Allen St",
    "sg:city":"State College",
    "sg:classifiers":[
        {
            "category":"Banks & Credit Unions",
            "subcategory":"Investment Brokerage",
            "type":"Services"
        }
    ],
    "sg:phone":"+1 814 235 9676",
    "sg:postcode":"16801",
    "sg:province":"PA",
    "sg:tags":[
        "advisory",
        "financial"
    ],
    "wof:name":"Montauk Financial",
    "wof:placetype":"venue"
},
  "geometry": {"coordinates":[-77.847206,40.783272],"type":"Point"}
}