{
  "type": "Feature",
  "properties": {
    "addr:full":"4002 W Girard Ave Philadelphia PA 19104",
    "addr:housenumber":"4002",
    "addr:postcode":"19104",
    "addr:street":"W Girard Ave",
    "iso:country":"US",
    "sg:address":"4002 W Girard Ave",
    "sg:city":"Philadelphia",
    "sg:classifiers":[
        {
            "category":"Bars & Pubs",
            "type":"Food & Drink"
        }
    ],
    "sg:phone":"+1   ",
    "sg:postcode":"19104",
    "sg:province":"PA",
    "sg:tags":[
        "tavern"
    ],
    "wof:name":"Jakes Lounge Inc",
    "wof:placetype":"venue"
},
  "geometry": {"coordinates":[-75.20639,39.97381],"type":"Point"}
}