{
  "type": "Feature",
  "properties": {
    "addr:full":"814 Main St Avoca PA 18641",
    "addr:housenumber":"814",
    "addr:postcode":"18641",
    "addr:street":"Main St",
    "iso:country":"US",
    "sg:address":"814 Main St",
    "sg:city":"Avoca",
    "sg:classifiers":[
        {
            "category":"Retail",
            "subcategory":"Animal Services",
            "type":"Services"
        }
    ],
    "sg:phone":"+1 570 457 4019",
    "sg:postcode":"18641",
    "sg:province":"PA",
    "sg:tags":[
        "pet",
        "grooming",
        "washing"
    ],
    "wof:name":"Grooming By Eloise",
    "wof:placetype":"venue"
},
  "geometry": {"coordinates":[-75.73951,41.340522],"type":"Point"}
}