{
  "type": "Feature",
  "properties": {
    "iso:country":"US",
    "sg:address":"129 Green Dr",
    "sg:city":"Kersey",
    "sg:classifiers":[
        {
            "category":"Manufacturing",
            "subcategory":"Metals",
            "type":"Manufacturing & Wholesale Goods"
        }
    ],
    "sg:phone":"+1   ",
    "sg:postcode":"15825",
    "sg:province":"PA",
    "sg:tags":[
        "treating",
        "heat"
    ],
    "wof:name":"U S Heat Treaters Inc",
    "wof:placetype":"venue"
},
  "geometry": {"coordinates":[-79.109689,41.169522],"type":"Point"}
}