{
  "type": "Feature",
  "properties": {
    "iso:country":"US",
    "sg:address":"513 E Arch St",
    "sg:city":"St Marys",
    "sg:classifiers":[
        {
            "category":"Social Services",
            "type":"Services"
        }
    ],
    "sg:phone":"+1 814 781 7776",
    "sg:postcode":"15857",
    "sg:province":"PA",
    "sg:tags":[
        "organization",
        "welfare"
    ],
    "wof:name":"Northern Tier Head Start",
    "wof:placetype":"venue"
},
  "geometry": {"coordinates":[-78.556314,41.422006],"type":"Point"}
}