{
  "type": "Feature",
  "properties": {
    "iso:country":"US",
    "sg:address":"864 Maytown Rd",
    "sg:city":"Elizabethtown",
    "sg:classifiers":[
        {
            "category":"Professional",
            "type":"Services"
        }
    ],
    "sg:phone":"+1   ",
    "sg:postcode":"17022",
    "sg:province":"PA",
    "wof:name":"Wendy L Jewell",
    "wof:placetype":"venue"
},
  "geometry": {"coordinates":[-76.59390399999999,40.116026],"type":"Point"}
}