{
  "type": "Feature",
  "properties": {
    "iso:country":"US",
    "sg:address":"2604 S 4th St",
    "sg:city":"Philadelphia",
    "sg:classifiers":[
        {
            "category":"Organizations",
            "subcategory":"Labor Organization",
            "type":"Services"
        }
    ],
    "sg:phone":"+1 215 336 3818",
    "sg:postcode":"19148",
    "sg:province":"PA",
    "wof:name":"United Industrial Workers",
    "wof:placetype":"venue"
},
  "geometry": {"coordinates":[-75.15513300000001,39.914729],"type":"Point"}
}