{
  "type": "Feature",
  "properties": {
    "addr:full":"2244 Perkiomen Ave Reading PA 19606",
    "addr:housenumber":"2244",
    "addr:postcode":"19606",
    "addr:street":"Perkiomen Ave",
    "iso:country":"US",
    "sg:address":"2244 Perkiomen Ave",
    "sg:city":"Reading",
    "sg:classifiers":[
        {
            "category":"Home & Garden",
            "subcategory":"Carpets & Floor Coverings",
            "type":"Retail Goods"
        }
    ],
    "sg:phone":"+1 610 779 2836",
    "sg:postcode":"19606",
    "sg:province":"PA",
    "wof:name":"Bevwood Carpets",
    "wof:placetype":"venue"
},
  "geometry": {"coordinates":[-75.893377,40.327728],"type":"Point"}
}