{
  "type": "Feature",
  "properties": {
    "addr:full":"355 Lackawanna St Reading PA 19601",
    "addr:housenumber":"355",
    "addr:postcode":"19601",
    "addr:street":"Lackawanna St",
    "iso:country":"US",
    "sg:address":"355 Lackawanna St",
    "sg:city":"Reading",
    "sg:classifiers":[
        {
            "category":"Organizations",
            "subcategory":"Religious Organization",
            "type":"Services"
        }
    ],
    "sg:phone":"+1 610 736 0468",
    "sg:postcode":"19601",
    "sg:province":"PA",
    "sg:tags":[
        "clergy"
    ],
    "wof:name":"Angelo Richardson",
    "wof:placetype":"venue"
},
  "geometry": {"coordinates":[-75.95185600000001,40.356403],"type":"Point"}
}