{
  "type": "Feature",
  "properties": {
    "iso:country":"US",
    "sg:address":"430 Regina St",
    "sg:city":"Philadelphia",
    "sg:classifiers":[
        {
            "category":"Professional",
            "type":"Services"
        }
    ],
    "sg:phone":"+1   ",
    "sg:postcode":"19116",
    "sg:province":"PA",
    "wof:name":"Bobkat Inc",
    "wof:placetype":"venue"
},
  "geometry": {"coordinates":[-75.025448,40.120682],"type":"Point"}
}