{
  "type": "Feature",
  "properties": {
    "addr:full":"103 Corporation Dr Aliquippa PA 15001",
    "addr:housenumber":"103",
    "addr:postcode":"15001",
    "addr:street":"Corporation Dr",
    "iso:country":"US",
    "sg:address":"103 Corporation Dr",
    "sg:city":"Aliquippa",
    "sg:classifiers":[
        {
            "category":"Professional",
            "subcategory":"Computer Services",
            "type":"Services"
        }
    ],
    "sg:phone":"+1 724 378 6277",
    "sg:postcode":"15001",
    "sg:province":"PA",
    "sg:tags":[
        "repair"
    ],
    "wof:name":"SMS Systems Maintenance Svc",
    "wof:placetype":"venue"
},
  "geometry": {"coordinates":[-80.270409,40.559147],"type":"Point"}
}