{
  "type": "Feature",
  "properties": {
    "iso:country":"US",
    "sg:address":"870 Croton Rd",
    "sg:city":"Wayne",
    "sg:classifiers":[
        {
            "category":"Organizations",
            "subcategory":"Religious Organization",
            "type":"Services"
        }
    ],
    "sg:phone":"+1 215 635 0509",
    "sg:postcode":"19087",
    "sg:province":"PA",
    "sg:tags":[
        "clergy"
    ],
    "wof:name":"Vincent Saverino",
    "wof:placetype":"venue"
},
  "geometry": {"coordinates":[-75.386633,40.075104],"type":"Point"}
}