{
  "type": "Feature",
  "properties": {
    "iso:country":"US",
    "sg:address":"313 Main St",
    "sg:city":"Hartleton",
    "sg:classifiers":[
        {
            "category":"Food & Beverages",
            "subcategory":"Specialty",
            "type":"Retail Goods"
        }
    ],
    "sg:phone":"+1 570 922 4745",
    "sg:postcode":"17829",
    "sg:province":"PA",
    "wof:name":"Dormans Country Store",
    "wof:placetype":"venue"
},
  "geometry": {"coordinates":[-77.156085,40.90024],"type":"Point"}
}