{
  "type": "Feature",
  "properties": {
    "iso:country":"US",
    "sg:address":"30 Oakland Ave",
    "sg:city":"Uniontown",
    "sg:classifiers":[
        {
            "category":"Professional",
            "subcategory":"Detective & Security Services",
            "type":"Services"
        }
    ],
    "sg:phone":"+1 724 439 4678",
    "sg:postcode":"15401",
    "sg:province":"PA",
    "sg:tags":[
        "investigator"
    ],
    "wof:name":"REDD Investigations",
    "wof:placetype":"venue"
},
  "geometry": {"coordinates":[-79.736402,39.905712],"type":"Point"}
}