{
  "type": "Feature",
  "properties": {
    "iso:country":"US",
    "sg:address":"3897 Wiestertown Rd",
    "sg:city":"Export",
    "sg:classifiers":[
        {
            "category":"Recreation",
            "type":"Entertainment"
        }
    ],
    "sg:phone":"+1 724 325 3910",
    "sg:postcode":"15632",
    "sg:province":"PA",
    "sg:tags":[
        "stable"
    ],
    "wof:name":"Idle Creek Ranch",
    "wof:placetype":"venue"
},
  "geometry": {"coordinates":[-79.62908,40.449477],"type":"Point"}
}