{
  "type": "Feature",
  "properties": {
    "iso:country":"US",
    "sg:address":"10 Willard St",
    "sg:city":"Lehighton",
    "sg:classifiers":[
        {
            "category":"Food & Beverages",
            "subcategory":"Groceries & Convenience Stores",
            "type":"Retail Goods"
        }
    ],
    "sg:phone":"+1 610 377 8080",
    "sg:postcode":"18235",
    "sg:province":"PA",
    "wof:name":"Olde Tyme Corner Store",
    "wof:placetype":"venue"
},
  "geometry": {"coordinates":[-75.72932299999999,40.830091],"type":"Point"}
}