{
  "type": "Feature",
  "properties": {
    "iso:country":"US",
    "sg:address":"4753 E Prospect Rd",
    "sg:city":"York",
    "sg:classifiers":[
        {
            "category":"Building & Trades",
            "subcategory":"Landscaping Services",
            "type":"Services"
        }
    ],
    "sg:phone":"+1   ",
    "sg:postcode":"17406",
    "sg:province":"PA",
    "wof:name":"Chopper Lawn & Landscaping",
    "wof:placetype":"venue"
},
  "geometry": {"coordinates":[-76.56617799999999,39.971979],"type":"Point"}
}