{
  "type": "Feature",
  "properties": {
    "iso:country":"US",
    "sg:address":"3 Honey Stump Cir",
    "sg:city":"Drums",
    "sg:classifiers":[
        {
            "category":"Building & Trades",
            "subcategory":"Construction",
            "type":"Services"
        }
    ],
    "sg:phone":"+1   ",
    "sg:postcode":"18222",
    "sg:province":"PA",
    "sg:tags":[
        "house"
    ],
    "wof:name":"Lawson Enterprises",
    "wof:placetype":"venue"
},
  "geometry": {"coordinates":[-75.931938,41.038797],"type":"Point"}
}