{
  "type": "Feature",
  "properties": {
    "iso:country":"US",
    "sg:address":"4343 Verona Rd",
    "sg:city":"Verona",
    "sg:classifiers":[
        {
            "category":"Personal",
            "subcategory":"Beauty Salon",
            "type":"Services"
        }
    ],
    "sg:phone":"+1 412 731 0441",
    "sg:postcode":"15147",
    "sg:province":"PA",
    "wof:name":"Sudden Change",
    "wof:placetype":"venue"
},
  "geometry": {"coordinates":[-79.85725600000001,40.473222],"type":"Point"}
}