{
  "type": "Feature",
  "properties": {
    "iso:country":"US",
    "sg:address":"318 Foster Hill Rd",
    "sg:city":"Milford",
    "sg:classifiers":[
        {
            "category":"Professional",
            "type":"Services"
        }
    ],
    "sg:phone":"+1 570 409 1140",
    "sg:postcode":"18337",
    "sg:province":"PA",
    "sg:tags":[
        "establishment"
    ],
    "wof:name":"Gait Inc",
    "wof:placetype":"venue"
},
  "geometry": {"coordinates":[-74.809871,41.344209],"type":"Point"}
}