{
  "type": "Feature",
  "properties": {
    "iso:country":"US",
    "sg:address":"32 W Queen St",
    "sg:city":"Chambersburg",
    "sg:classifiers":[
        {
            "category":"Professional",
            "subcategory":"Lawyer & Legal Services",
            "type":"Services"
        }
    ],
    "sg:phone":"+1   ",
    "sg:postcode":"17201",
    "sg:province":"PA",
    "wof:name":"Townsend Law Office",
    "wof:placetype":"venue"
},
  "geometry": {"coordinates":[-77.661872,39.935872],"type":"Point"}
}