{
  "type": "Feature",
  "properties": {
    "iso:country":"US",
    "sg:address":"1528 Walnut St Ste 1501",
    "sg:city":"Philadelphia",
    "sg:classifiers":[
        {
            "category":"Health Services",
            "subcategory":"Doctor",
            "type":"Services"
        }
    ],
    "sg:phone":"+1 215 790 0661",
    "sg:postcode":"19102",
    "sg:province":"PA",
    "wof:name":"Nevyas-Wallace Anita MD",
    "wof:placetype":"venue"
},
  "geometry": {"coordinates":[-75.166861,39.94964],"type":"Point"}
}