{
  "type": "Feature",
  "properties": {
    "iso:country":"US",
    "sg:address":"108 N Beeson Blvd",
    "sg:city":"Uniontown",
    "sg:classifiers":[
        {
            "category":"Building & Trades",
            "subcategory":"Construction",
            "type":"Services"
        }
    ],
    "sg:phone":"+1   ",
    "sg:postcode":"15401",
    "sg:province":"PA",
    "sg:tags":[
        "general",
        "contractor"
    ],
    "wof:name":"P C Yezbak & Son Inc",
    "wof:placetype":"venue"
},
  "geometry": {"coordinates":[-79.72568699999999,39.904047],"type":"Point"}
}