{
  "type": "Feature",
  "properties": {
    "iso:country":"US",
    "sg:address":"2501 Chestnut St",
    "sg:city":"Aliquippa",
    "sg:classifiers":[
        {
            "category":"Health Services",
            "subcategory":"Doctor",
            "type":"Services"
        },
        {
            "category":"Health Services",
            "subcategory":"Dentist",
            "type":"Services"
        }
    ],
    "sg:phone":"+1 724 375 2002",
    "sg:postcode":"15001",
    "sg:province":"PA",
    "sg:tags":[
        "dentists-oral",
        "physician",
        "maxillofacial",
        "surgeons",
        "surgery",
        "oral"
    ],
    "wof:name":"George J Hadeed Dmd",
    "wof:placetype":"venue"
},
  "geometry": {"coordinates":[-80.285599,40.603554],"type":"Point"}
}