{
  "type": "Feature",
  "properties": {
    "iso:country":"US",
    "sg:address":"412 Mount Allen Dr",
    "sg:city":"Mechanicsburg",
    "sg:classifiers":[
        {
            "category":"Shopping",
            "type":"Retail Goods"
        }
    ],
    "sg:phone":"+1 717 790 9617",
    "sg:postcode":"17055",
    "sg:province":"PA",
    "sg:tags":[
        "cosmetic",
        "perfume"
    ],
    "wof:name":"Christi Gates Avon Products",
    "wof:placetype":"venue"
},
  "geometry": {"coordinates":[-76.97416699999999,40.180595],"type":"Point"}
}