{
  "type": "Feature",
  "properties": {
    "iso:country":"US",
    "sg:address":"128 Blackhawk Rd",
    "sg:city":"Beaver Falls",
    "sg:classifiers":[
        {
            "category":"Health Services",
            "subcategory":"Doctor",
            "type":"Services"
        }
    ],
    "sg:phone":"+1 724 843 4280",
    "sg:postcode":"15010",
    "sg:province":"PA",
    "sg:tags":[
        "dentist"
    ],
    "wof:name":"Wichmann & Hamerski PC",
    "wof:placetype":"venue"
},
  "geometry": {"coordinates":[-80.37983800000001,40.772555],"type":"Point"}
}