{
  "type": "Feature",
  "properties": {
    "iso:country":"US",
    "sg:address":"2112 Brady Pl",
    "sg:city":"Bethel Park",
    "sg:classifiers":[
        {
            "category":"Wholesale",
            "subcategory":"Electrical",
            "type":"Manufacturing & Wholesale Goods"
        }
    ],
    "sg:phone":"+1 412 881 9397",
    "sg:postcode":"15102",
    "sg:province":"PA",
    "sg:tags":[
        "telecommunication"
    ],
    "wof:name":"Davis Communications",
    "wof:placetype":"venue"
},
  "geometry": {"coordinates":[-80.031752,40.348954],"type":"Point"}
}