{
  "type": "Feature",
  "properties": {
    "addr:full":"860 Main St Duryea PA 18642",
    "addr:housenumber":"860",
    "addr:postcode":"18642",
    "addr:street":"Main St",
    "iso:country":"US",
    "sg:address":"860 Main St",
    "sg:city":"Duryea",
    "sg:classifiers":[
        {
            "category":"Retail",
            "subcategory":"Auto Repair",
            "type":"Services"
        }
    ],
    "sg:phone":"+1 570 457 7794",
    "sg:postcode":"18642",
    "sg:province":"PA",
    "sg:tags":[
        "repairing",
        "automobile"
    ],
    "wof:name":"Pat Shotwell's Auto Repair",
    "wof:placetype":"venue"
},
  "geometry": {"coordinates":[-75.756209,41.35381],"type":"Point"}
}