{
  "type": "Feature",
  "properties": {
    "iso:country":"US",
    "sg:address":"143 E Broad St",
    "sg:city":"Bethlehem",
    "sg:classifiers":[
        {
            "category":"Health Services",
            "subcategory":"Health Practitioner",
            "type":"Services"
        }
    ],
    "sg:phone":"+1 610 691 1129",
    "sg:postcode":"18018",
    "sg:province":"PA",
    "sg:tags":[
        "psychotherapist"
    ],
    "wof:name":"American Human Svc",
    "wof:placetype":"venue"
},
  "geometry": {"coordinates":[-75.373531,40.622282],"type":"Point"}
}