{
  "type": "Feature",
  "properties": {
    "iso:country":"US",
    "sg:address":"910 E Phil Ellena St",
    "sg:city":"Philadelphia",
    "sg:classifiers":[
        {
            "category":"Building & Trades",
            "subcategory":"Construction",
            "type":"Services"
        }
    ],
    "sg:phone":"+1 215 549 2830",
    "sg:postcode":"19150",
    "sg:province":"PA",
    "sg:tags":[
        "carpentry",
        "contractor"
    ],
    "sg:website":"www.kevindent.com",
    "wof:name":"Environmental Design",
    "wof:placetype":"venue"
},
  "geometry": {"coordinates":[-75.171548,40.065067],"type":"Point"}
}