{
  "type": "Feature",
  "properties": {
    "addr:full":"2375 Garden Way Hermitage PA 16148",
    "addr:housenumber":"2375",
    "addr:postcode":"16148",
    "addr:street":"Garden Way",
    "iso:country":"US",
    "sg:address":"2375 Garden Way",
    "sg:city":"Hermitage",
    "sg:classifiers":[
        {
            "category":"Health Services",
            "subcategory":"Doctor",
            "type":"Services"
        }
    ],
    "sg:phone":"+1 724 983 3888",
    "sg:postcode":"16148",
    "sg:province":"PA",
    "sg:tags":[
        "physician",
        "surgeon"
    ],
    "sg:website":"www.sharonregional.com",
    "wof:name":"Behavioral Health Ctr",
    "wof:placetype":"venue"
},
  "geometry": {"coordinates":[-80.464066,41.237374],"type":"Point"}
}