{
  "type": "Feature",
  "properties": {
    "iso:country":"US",
    "sg:address":"473 Heim Rd",
    "sg:city":"Sunbury",
    "sg:classifiers":[
        {
            "category":"Manufacturing",
            "subcategory":"Food",
            "type":"Manufacturing & Wholesale Goods"
        },
        {
            "category":"Farming",
            "subcategory":"Farm",
            "type":"Manufacturing & Wholesale Goods"
        }
    ],
    "sg:phone":"+1 570 286 0051",
    "sg:postcode":"17801",
    "sg:province":"PA",
    "sg:tags":[
        "corn",
        "product"
    ],
    "wof:name":"Charles Lytle",
    "wof:placetype":"venue"
},
  "geometry": {"coordinates":[-76.72755100000001,40.820148],"type":"Point"}
}