{
  "type": "Feature",
  "properties": {
    "iso:country":"US",
    "sg:address":"52 Railroad St",
    "sg:city":"Valencia",
    "sg:classifiers":[
        {
            "category":"Shopping",
            "subcategory":"Antiques",
            "type":"Retail Goods"
        }
    ],
    "sg:phone":"+1 724 625 2698",
    "sg:postcode":"16059",
    "sg:province":"PA",
    "wof:name":"Professional Furniture Restoration",
    "wof:placetype":"venue"
},
  "geometry": {"coordinates":[-79.987503,40.673599],"type":"Point"}
}