{
  "type": "Feature",
  "properties": {
    "iso:country":"US",
    "sg:address":"2642 Egypt Rd",
    "sg:city":"Norristown",
    "sg:classifiers":[
        {
            "category":"Food & Beverages",
            "subcategory":"Groceries & Convenience Stores",
            "type":"Retail Goods"
        }
    ],
    "sg:phone":"+1   ",
    "sg:postcode":"19403",
    "sg:province":"PA",
    "wof:name":"Hello Deli",
    "wof:placetype":"venue"
},
  "geometry": {"coordinates":[-75.40308,40.13069],"type":"Point"}
}