{
  "type": "Feature",
  "properties": {
    "iso:country":"US",
    "sg:address":"331 School Ln",
    "sg:city":"Mount Joy",
    "sg:classifiers":[
        {
            "category":"Shopping",
            "subcategory":"Crafts & Fabrics",
            "type":"Retail Goods"
        }
    ],
    "sg:phone":"+1   ",
    "sg:postcode":"17552",
    "sg:province":"PA",
    "sg:tags":[
        "sewing"
    ],
    "wof:name":"Stitches & More",
    "wof:placetype":"venue"
},
  "geometry": {"coordinates":[-76.509055,40.104066],"type":"Point"}
}