{
  "type": "Feature",
  "properties": {
    "iso:country":"US",
    "sg:address":"221 Exton Square Mall",
    "sg:city":"Exton",
    "sg:classifiers":[
        {
            "category":"Shopping",
            "subcategory":"Clothing, Apparel, & Fashions",
            "type":"Retail Goods"
        }
    ],
    "sg:phone":"+1   ",
    "sg:postcode":"19341",
    "sg:province":"PA",
    "wof:name":"Just ME Music",
    "wof:placetype":"venue"
},
  "geometry": {"coordinates":[-75.625784,40.032942],"type":"Point"}
}