{
  "type": "Feature",
  "properties": {
    "iso:country":"US",
    "sg:address":"918 N Delaware Ave",
    "sg:city":"Philadelphia",
    "sg:classifiers":[
        {
            "category":"Shopping",
            "subcategory":"Shoes",
            "type":"Retail Goods"
        }
    ],
    "sg:phone":"+1 215 238 9612",
    "sg:postcode":"19123",
    "sg:province":"PA",
    "sg:tags":[
        "store"
    ],
    "wof:name":"Bigston",
    "wof:placetype":"venue"
},
  "geometry": {"coordinates":[-75.135442,39.963988],"type":"Point"}
}