{
  "type": "Feature",
  "properties": {
    "addr:full":"1766 W Market St Pottsville PA 17901",
    "addr:housenumber":"1766",
    "addr:postcode":"17901",
    "addr:street":"W Market St",
    "iso:country":"US",
    "sg:address":"1766 W Market St",
    "sg:city":"Pottsville",
    "sg:classifiers":[
        {
            "category":"Insurance",
            "subcategory":"Insurance Agent",
            "type":"Services"
        }
    ],
    "sg:phone":"+1   ",
    "sg:postcode":"17901",
    "sg:province":"PA",
    "wof:name":"Donald E Davis Agency Inc",
    "wof:placetype":"venue"
},
  "geometry": {"coordinates":[-76.215869,40.677937],"type":"Point"}
}