{
  "type": "Feature",
  "properties": {
    "addr:full":"950 W Fairway Dr Lancaster PA 17603",
    "addr:housenumber":"950",
    "addr:postcode":"17603",
    "addr:street":"W Fairway Dr",
    "iso:country":"US",
    "sg:address":"950 W Fairway Dr",
    "sg:city":"Lancaster",
    "sg:classifiers":[
        {
            "category":"Government",
            "subcategory":"Office",
            "type":"Public Place"
        }
    ],
    "sg:phone":"+1 717 299 5231",
    "sg:postcode":"17603",
    "sg:province":"PA",
    "sg:tags":[
        "supervisor",
        "board"
    ],
    "wof:name":"Manor Township Police Dept",
    "wof:placetype":"venue"
},
  "geometry": {"coordinates":[-76.365064,40.027652],"type":"Point"}
}