{
  "type": "Feature",
  "properties": {
    "iso:country":"US",
    "sg:address":"410 S Cedar Crest Blvd",
    "sg:city":"Allentown",
    "sg:classifiers":[
        {
            "category":"Restaurant",
            "type":"Food & Drink"
        }
    ],
    "sg:menulink":"http://www.allmenus.com/pa/south-whitehall/172871-wendys/menu/",
    "sg:phone":"+1 610 532 3369",
    "sg:postcode":"18103",
    "sg:province":"PA",
    "sg:tags":[
        "burger",
        "american",
        "soup"
    ],
    "wof:name":"Wendy's",
    "wof:placetype":"venue"
},
  "geometry": {"coordinates":[-75.522505,40.583136],"type":"Point"}
}