{
  "type": "Feature",
  "properties": {
    "iso:country":"US",
    "sg:address":"100 E Allen St",
    "sg:city":"Mechanicsburg",
    "sg:classifiers":[
        {
            "category":"Retail",
            "subcategory":"Car Wash",
            "type":"Services"
        }
    ],
    "sg:phone":"+1 717 697 1660",
    "sg:postcode":"17055",
    "sg:province":"PA",
    "sg:tags":[
        "carwash"
    ],
    "wof:name":"Automotive Specialties",
    "wof:placetype":"venue"
},
  "geometry": {"coordinates":[-77.004921,40.21555],"type":"Point"}
}