{
  "type": "Feature",
  "properties": {
    "iso:country":"US",
    "sg:address":"1892 Titan St",
    "sg:city":"Philadelphia",
    "sg:classifiers":[
        {
            "category":"Building & Trades",
            "subcategory":"Locksmith",
            "type":"Services"
        }
    ],
    "sg:phone":"+1 267 719 6077",
    "sg:postcode":"19146",
    "sg:province":"PA",
    "sg:tags":[
        "lock",
        "industrial",
        "locksmiths-commercial"
    ],
    "wof:name":"Total Locksmith",
    "wof:placetype":"venue"
},
  "geometry": {"coordinates":[-75.17533400000001,39.935607],"type":"Point"}
}