{
  "type": "Feature",
  "properties": {
    "iso:country":"US",
    "sg:address":"3913 Carney Ave",
    "sg:city":"Erie",
    "sg:classifiers":[
        {
            "category":"Shopping",
            "type":"Retail Goods"
        }
    ],
    "sg:phone":"+1 814 825 6029",
    "sg:postcode":"16510",
    "sg:province":"PA",
    "sg:tags":[
        "whirlpool",
        "equipment",
        "bath",
        "supply"
    ],
    "sg:website":"www.lcdistributors.com",
    "wof:name":"L C Distributors",
    "wof:placetype":"venue"
},
  "geometry": {"coordinates":[-80.01745,42.117991],"type":"Point"}
}