{
  "type": "Feature",
  "properties": {
    "iso:country":"US",
    "sg:address":"890 W Bridge St",
    "sg:city":"Morrisville",
    "sg:classifiers":[
        {
            "category":"Retail",
            "subcategory":"Animal Services",
            "type":"Services"
        }
    ],
    "sg:phone":"+1 215 428 4701",
    "sg:postcode":"19067",
    "sg:province":"PA",
    "sg:tags":[
        "pet",
        "boarding",
        "sitting"
    ],
    "wof:name":"Four Paws",
    "wof:placetype":"venue"
},
  "geometry": {"coordinates":[-74.787509,40.201554],"type":"Point"}
}