{
  "type": "Feature",
  "properties": {
    "iso:country":"US",
    "sg:address":"21 N Main St",
    "sg:city":"Coopersburg",
    "sg:classifiers":[
        {
            "category":"Arts & Performance",
            "subcategory":"Arts Center",
            "type":"Entertainment"
        }
    ],
    "sg:phone":"+1 610 282 2231",
    "sg:postcode":"18036",
    "sg:province":"PA",
    "sg:tags":[
        "performing"
    ],
    "wof:name":"Medeiros Diane Academy of Dance",
    "wof:placetype":"venue"
},
  "geometry": {"coordinates":[-75.390602,40.5117],"type":"Point"}
}