{
  "type": "Feature",
  "properties": {
    "iso:country":"US",
    "sg:address":"231 S Main St Ste 310",
    "sg:city":"Greensburg",
    "sg:classifiers":[
        {
            "category":"Professional",
            "subcategory":"Lawyer & Legal Services",
            "type":"Services"
        }
    ],
    "sg:phone":"+1 724 834 2002",
    "sg:postcode":"15601",
    "sg:province":"PA",
    "sg:tags":[
        "attorney",
        "practice"
    ],
    "wof:name":"Lawrence R Burns",
    "wof:placetype":"venue"
},
  "geometry": {"coordinates":[-79.543767,40.301072],"type":"Point"}
}