{
  "type": "Feature",
  "properties": {
    "iso:country":"US",
    "sg:address":"401 Moosic Rd",
    "sg:city":"Old Forge",
    "sg:classifiers":[
        {
            "category":"Retail",
            "subcategory":"Laundry & Dry Cleaning",
            "type":"Services"
        }
    ],
    "sg:phone":"+1 570 457 9583",
    "sg:postcode":"18518",
    "sg:province":"PA",
    "sg:tags":[
        "cleaners"
    ],
    "wof:name":"Old Forge Dry Cleaners",
    "wof:placetype":"venue"
},
  "geometry": {"coordinates":[-75.73103399999999,41.367115],"type":"Point"}
}