{
  "type": "Feature",
  "properties": {
    "addr:full":"24 N Juniata St Hollidaysburg PA 16648",
    "addr:housenumber":"24",
    "addr:postcode":"16648",
    "addr:street":"N Juniata St",
    "iso:country":"US",
    "sg:address":"24 N Juniata St",
    "sg:city":"Hollidaysburg",
    "sg:classifiers":[
        {
            "category":"Health Services",
            "subcategory":"Chiropractor",
            "type":"Services"
        }
    ],
    "sg:phone":"+1 814 696 3531",
    "sg:postcode":"16648",
    "sg:province":"PA",
    "wof:name":"Ridenour Chiropractic Office",
    "wof:placetype":"venue"
},
  "geometry": {"coordinates":[-78.409429,40.436341],"type":"Point"}
}