{
  "type": "Feature",
  "properties": {
    "addr:full":"5200 W Baltimore Ave Clifton Heights PA 19018",
    "addr:housenumber":"5200",
    "addr:postcode":"19018",
    "addr:street":"W Baltimore Ave",
    "iso:country":"US",
    "sg:address":"5200 W Baltimore Ave",
    "sg:city":"Clifton Heights",
    "sg:classifiers":[
        {
            "category":"Restaurant",
            "type":"Food & Drink"
        }
    ],
    "sg:menulink":"http://www.allmenus.com/pa/upper-darby/147241-boston-market/menu/",
    "sg:phone":"+1 610 622 7909",
    "sg:postcode":"19018",
    "sg:province":"PA",
    "sg:tags":[
        "barbecue",
        "american",
        "soup"
    ],
    "wof:name":"Boston Market",
    "wof:placetype":"venue"
},
  "geometry": {"coordinates":[-75.30834,39.925394],"type":"Point"}
}