{
  "type": "Feature",
  "properties": {
    "addr:full":"2155 Colebrook Rd Lebanon PA 17042",
    "addr:housenumber":"2155",
    "addr:postcode":"17042",
    "addr:street":"Colebrook Rd",
    "iso:country":"US",
    "sg:address":"2155 Colebrook Rd",
    "sg:city":"Lebanon",
    "sg:phone":"+1   ",
    "sg:postcode":"17042",
    "sg:province":"PA",
    "sg:tags":[
        "farm",
        "corn",
        "soybean"
    ],
    "wof:name":"Henry Martin",
    "wof:placetype":"venue"
},
  "geometry": {"coordinates":[-76.465189,40.294918],"type":"Point"}
}