{
  "type": "Feature",
  "properties": {
    "iso:country":"US",
    "sg:address":"3728 Academy Rd",
    "sg:city":"Philadelphia",
    "sg:classifiers":[
        {
            "category":"Building & Trades",
            "subcategory":"Plumbing",
            "type":"Services"
        }
    ],
    "sg:phone":"+1 215 637 4033",
    "sg:postcode":"19154",
    "sg:province":"PA",
    "wof:name":"O'brien Russell Sewer & Drain Cleaner",
    "wof:placetype":"venue"
},
  "geometry": {"coordinates":[-74.966431,40.092299],"type":"Point"}
}