{
  "type": "Feature",
  "properties": {
    "iso:country":"US",
    "sg:address":"5192 Huntley Rd",
    "sg:city":"West Springfield",
    "sg:classifiers":[
        {
            "category":"Retail",
            "subcategory":"Animal Services",
            "type":"Services"
        }
    ],
    "sg:phone":"+1   ",
    "sg:postcode":"16443",
    "sg:province":"PA",
    "wof:name":"Apple Acre Kennel",
    "wof:placetype":"venue"
},
  "geometry": {"coordinates":[-80.481324,41.944125],"type":"Point"}
}