{
  "type": "Feature",
  "properties": {
    "addr:full":"340 Valley Rd Millersville PA 17551",
    "addr:housenumber":"340",
    "addr:postcode":"17551",
    "addr:street":"Valley Rd",
    "iso:country":"US",
    "sg:address":"340 Valley Rd",
    "sg:city":"Millersville",
    "sg:classifiers":[
        {
            "category":"Organizations",
            "subcategory":"Religious Organization",
            "type":"Services"
        }
    ],
    "sg:phone":"+1 717 872 7005",
    "sg:postcode":"17551",
    "sg:province":"PA",
    "sg:tags":[
        "clergy"
    ],
    "wof:name":"J Val Hastings",
    "wof:placetype":"venue"
},
  "geometry": {"coordinates":[-76.349315,40.010875],"type":"Point"}
}