{
  "type": "Feature",
  "properties": {
    "addr:full":"41 Lincoln St Pittsburgh PA 15223",
    "addr:housenumber":"41",
    "addr:postcode":"15223",
    "addr:street":"Lincoln St",
    "iso:country":"US",
    "sg:address":"41 Lincoln St",
    "sg:city":"Pittsburgh",
    "sg:classifiers":[
        {
            "category":"Organizations",
            "subcategory":"Religious Organization",
            "type":"Services"
        }
    ],
    "sg:phone":"+1 412 921 1125",
    "sg:postcode":"15223",
    "sg:province":"PA",
    "sg:tags":[
        "church"
    ],
    "wof:name":"St Matthew's Lutheran Church",
    "wof:placetype":"venue"
},
  "geometry": {"coordinates":[-79.945127,40.506347],"type":"Point"}
}