{
  "type": "Feature",
  "properties": {
    "iso:country":"US",
    "sg:address":"747 E Wyoming Ave",
    "sg:city":"Philadelphia",
    "sg:classifiers":[
        {
            "category":"Health Services",
            "subcategory":"Hospital",
            "type":"Services"
        }
    ],
    "sg:phone":"+1 215 743 8847",
    "sg:postcode":"19124",
    "sg:province":"PA",
    "sg:tags":[
        "mental"
    ],
    "wof:name":"Kensington Community For Indvl",
    "wof:placetype":"venue"
},
  "geometry": {"coordinates":[-75.108464,40.019638],"type":"Point"}
}