{
  "type": "Feature",
  "properties": {
    "iso:country":"US",
    "sg:address":"302 McKnight Park Dr",
    "sg:city":"Pittsburgh",
    "sg:classifiers":[
        {
            "category":"Professional",
            "subcategory":"Lawyer & Legal Services",
            "type":"Services"
        }
    ],
    "sg:phone":"+1   ",
    "sg:postcode":"15237",
    "sg:province":"PA",
    "wof:name":"Lally & Lally Cpas",
    "wof:placetype":"venue"
},
  "geometry": {"coordinates":[-80.00725799999999,40.53517],"type":"Point"}
}