{
  "type": "Feature",
  "properties": {
    "iso:country":"US",
    "sg:address":"33 S 14th St",
    "sg:city":"Quakertown",
    "sg:classifiers":[
        {
            "category":"Retail",
            "subcategory":"Auto Rental",
            "type":"Services"
        }
    ],
    "sg:phone":"+1 215 536 5120",
    "sg:postcode":"18951",
    "sg:province":"PA",
    "sg:tags":[
        "renting",
        "truck",
        "leasing"
    ],
    "wof:name":"Budget Truck Rental",
    "wof:placetype":"venue"
},
  "geometry": {"coordinates":[-75.35454799999999,40.438978],"type":"Point"}
}