{
  "type": "Feature",
  "properties": {
    "iso:country":"US",
    "sg:address":"945 Latonka Dr",
    "sg:city":"Mercer",
    "sg:classifiers":[
        {
            "category":"Health Services",
            "subcategory":"Clinic",
            "type":"Services"
        }
    ],
    "sg:phone":"+1   ",
    "sg:postcode":"16137",
    "sg:province":"PA",
    "wof:name":"Allegheny Healthcare Mgt",
    "wof:placetype":"venue"
},
  "geometry": {"coordinates":[-80.188974,41.271322],"type":"Point"}
}