{
  "type": "Feature",
  "properties": {
    "addr:full":"8716 Easton Rd Revere PA 18953",
    "addr:housenumber":"8716",
    "addr:postcode":"18953",
    "addr:street":"Easton Rd",
    "iso:country":"US",
    "sg:address":"8716 Easton Rd",
    "sg:city":"Revere",
    "sg:classifiers":[
        {
            "category":"Local Transit",
            "type":"Transportation"
        }
    ],
    "sg:phone":"+1 610 847 8801",
    "sg:postcode":"18953",
    "sg:province":"PA",
    "sg:tags":[
        "ambulance"
    ],
    "wof:name":"Riegelsville-Palisades Med Svc",
    "wof:placetype":"venue"
},
  "geometry": {"coordinates":[-75.167163,40.521627],"type":"Point"}
}