{
  "type": "Feature",
  "properties": {
    "addr:full":"314 Belle Isle Ave Pittsburgh PA 15226",
    "addr:housenumber":"314",
    "addr:postcode":"15226",
    "addr:street":"Belle Isle Ave",
    "iso:country":"US",
    "sg:address":"314 Belle Isle Ave",
    "sg:city":"Pittsburgh",
    "sg:classifiers":[
        {
            "category":"Professional",
            "subcategory":"Business Services",
            "type":"Services"
        }
    ],
    "sg:phone":"+1 412 531 5232",
    "sg:postcode":"15226",
    "sg:province":"PA",
    "sg:tags":[
        "used",
        "merchandise"
    ],
    "wof:name":"D Richards Bookman",
    "wof:placetype":"venue"
},
  "geometry": {"coordinates":[-80.02099,40.399949],"type":"Point"}
}