{
  "type": "Feature",
  "properties": {
    "addr:full":"118 E Market St York PA 17401",
    "addr:housenumber":"118",
    "addr:postcode":"17401",
    "addr:street":"E Market St",
    "iso:country":"US",
    "sg:address":"118 E Market St",
    "sg:city":"York",
    "sg:classifiers":[
        {
            "category":"Banks & Credit Unions",
            "subcategory":"Bank",
            "type":"Services"
        }
    ],
    "sg:phone":"+1 717 846 1970",
    "sg:postcode":"17401",
    "sg:province":"PA",
    "wof:name":"Peoples Bank",
    "wof:placetype":"venue"
},
  "geometry": {"coordinates":[-76.724082,39.963476],"type":"Point"}
}