{
  "type": "Feature",
  "properties": {
    "iso:country":"US",
    "sg:address":"2108 Harrisburg Pike",
    "sg:city":"Lancaster",
    "sg:classifiers":[
        {
            "category":"Health Services",
            "subcategory":"Doctor",
            "type":"Services"
        }
    ],
    "sg:phone":"+1 717 544 3547",
    "sg:postcode":"17601",
    "sg:province":"PA",
    "sg:tags":[
        "physician",
        "surgeon"
    ],
    "wof:name":"Pediatric Neurology Assoc",
    "wof:placetype":"venue"
},
  "geometry": {"coordinates":[-76.357439,40.069355],"type":"Point"}
}