{
  "type": "Feature",
  "properties": {
    "addr:full":"381 Hillside Rd Ridley Park PA 19078",
    "addr:housenumber":"381",
    "addr:postcode":"19078",
    "addr:street":"Hillside Rd;Park",
    "iso:country":"US",
    "sg:address":"381 Hillside Rd",
    "sg:city":"Ridley Park",
    "sg:classifiers":[
        {
            "category":"Organizations",
            "subcategory":"Religious Organization",
            "type":"Services"
        }
    ],
    "sg:phone":"+1 610 521 3539",
    "sg:postcode":"19078",
    "sg:province":"PA",
    "sg:tags":[
        "clergy"
    ],
    "wof:name":"David B Anderson",
    "wof:placetype":"venue"
},
  "geometry": {"coordinates":[-75.33120599999999,39.880045],"type":"Point"}
}