{
  "type": "Feature",
  "properties": {
    "iso:country":"US",
    "sg:address":"6330 Woodlawn Ave",
    "sg:city":"Verona",
    "sg:classifiers":[
        {
            "category":"Professional",
            "subcategory":"Management & Consulting",
            "type":"Services"
        }
    ],
    "sg:phone":"+1   ",
    "sg:postcode":"15147",
    "sg:province":"PA",
    "sg:tags":[
        "business",
        "crop"
    ],
    "wof:name":"Sprout Kingdom",
    "wof:placetype":"venue"
},
  "geometry": {"coordinates":[-79.838928,40.494524],"type":"Point"}
}