{
  "type": "Feature",
  "properties": {
    "iso:country":"US",
    "sg:address":"782 Hazle St",
    "sg:city":"Wilkes Barre",
    "sg:classifiers":[
        {
            "category":"Restaurant",
            "type":"Food & Drink"
        }
    ],
    "sg:phone":"+1   ",
    "sg:postcode":"18706",
    "sg:province":"PA",
    "sg:tags":[
        "eating"
    ],
    "wof:name":"Pizza Bella Inc",
    "wof:placetype":"venue"
},
  "geometry": {"coordinates":[-75.896789,41.218564],"type":"Point"}
}