{
  "type": "Feature",
  "properties": {
    "iso:country":"US",
    "sg:address":"3136 Main St",
    "sg:city":"Springtown",
    "sg:classifiers":[
        {
            "category":"Real Estate",
            "subcategory":"Real Estate Agent",
            "type":"Services"
        }
    ],
    "sg:phone":"+1 610 346 8800",
    "sg:postcode":"18081",
    "sg:province":"PA",
    "sg:website":"www.doreyrealestate.com",
    "wof:name":"Carol C Dorey Real Estate",
    "wof:placetype":"venue"
},
  "geometry": {"coordinates":[-75.28648200000001,40.556772],"type":"Point"}
}