{
  "type": "Feature",
  "properties": {
    "addr:full":"107 6th St Williamsport PA 17701",
    "addr:housenumber":"107",
    "addr:postcode":"17701",
    "addr:street":"6Th St",
    "iso:country":"US",
    "sg:address":"107 6th St",
    "sg:city":"Williamsport",
    "sg:classifiers":[
        {
            "category":"Health Services",
            "subcategory":"Doctor",
            "type":"Services"
        }
    ],
    "sg:phone":"+1   ",
    "sg:postcode":"17701",
    "sg:province":"PA",
    "sg:tags":[
        "medical"
    ],
    "wof:name":"Louis F Campana MD PC",
    "wof:placetype":"venue"
},
  "geometry": {"coordinates":[-77.006629,41.243957],"type":"Point"}
}