{
  "type": "Feature",
  "properties": {
    "iso:country":"US",
    "sg:address":"120 Pike Way",
    "sg:city":"Meadow Lands",
    "sg:classifiers":[
        {
            "category":"Retail",
            "subcategory":"Auto Repair",
            "type":"Services"
        }
    ],
    "sg:phone":"+1 724 229 1110",
    "sg:postcode":"15033",
    "sg:province":"PA",
    "sg:tags":[
        "body",
        "shop"
    ],
    "wof:name":"Meadowlands Collision Center",
    "wof:placetype":"venue"
},
  "geometry": {"coordinates":[-80.21939500000001,40.220898],"type":"Point"}
}