{
  "type": "Feature",
  "properties": {
    "addr:full":"1001 9th Ave Brackenridge PA 15014",
    "addr:housenumber":"1001",
    "addr:postcode":"15014",
    "addr:street":"9Th Ave",
    "iso:country":"US",
    "sg:address":"1001 9th Ave",
    "sg:city":"Brackenridge",
    "sg:classifiers":[
        {
            "category":"Health Services",
            "subcategory":"Doctor",
            "type":"Services"
        }
    ],
    "sg:phone":"+1 724 226 1741",
    "sg:postcode":"15014",
    "sg:province":"PA",
    "sg:tags":[
        "physician",
        "surgeon"
    ],
    "wof:name":"Allegheny Neurosurgery",
    "wof:placetype":"venue"
},
  "geometry": {"coordinates":[-79.74192600000001,40.609548],"type":"Point"}
}