{
  "type": "Feature",
  "properties": {
    "iso:country":"US",
    "sg:address":"500 University Dr",
    "sg:city":"State College",
    "sg:classifiers":[
        {
            "category":"Health Services",
            "subcategory":"Doctor",
            "type":"Services"
        }
    ],
    "sg:phone":"+1 814 235 2480",
    "sg:postcode":"16801",
    "sg:province":"PA",
    "sg:tags":[
        "physician",
        "surgeon"
    ],
    "wof:name":"Penn State University Phys Grp",
    "wof:placetype":"venue"
},
  "geometry": {"coordinates":[-77.85010699999999,40.801162],"type":"Point"}
}