{
  "type": "Feature",
  "properties": {
    "iso:country":"US",
    "sg:address":"1721 Lynrose Cir",
    "sg:city":"Hatfield",
    "sg:classifiers":[
        {
            "category":"Building & Trades",
            "subcategory":"Landscaping Services",
            "type":"Services"
        }
    ],
    "sg:phone":"+1 215 855 6162",
    "sg:postcode":"19440",
    "sg:province":"PA",
    "sg:tags":[
        "lawn",
        "garden",
        "landscape",
        "contractor"
    ],
    "wof:name":"Schroding Lawn and Landscape",
    "wof:placetype":"venue"
},
  "geometry": {"coordinates":[-75.309111,40.283581],"type":"Point"}
}