{
  "type": "Feature",
  "properties": {
    "iso:country":"US",
    "sg:address":"5510 Carlisle Pike",
    "sg:city":"Mechanicsburg",
    "sg:classifiers":[
        {
            "category":"Restaurant",
            "type":"Food & Drink"
        }
    ],
    "sg:phone":"+1 717 791 0300",
    "sg:postcode":"17050",
    "sg:province":"PA",
    "wof:name":"Evergreen Restaurant",
    "wof:placetype":"venue"
},
  "geometry": {"coordinates":[-76.98429899999999,40.240501],"type":"Point"}
}