{
  "type": "Feature",
  "properties": {
    "iso:country":"US",
    "sg:address":"8211 Fayette St",
    "sg:city":"Philadelphia",
    "sg:classifiers":[
        {
            "category":"Manufacturing",
            "subcategory":"Building Materials",
            "type":"Manufacturing & Wholesale Goods"
        }
    ],
    "sg:phone":"+1   ",
    "sg:postcode":"19150",
    "sg:province":"PA",
    "sg:tags":[
        "mfg",
        "wood",
        "kitchen",
        "cabinet"
    ],
    "wof:name":"Cabinetry By E Raphael Inc",
    "wof:placetype":"venue"
},
  "geometry": {"coordinates":[-75.17342499999999,40.076991],"type":"Point"}
}