{
  "type": "Feature",
  "properties": {
    "iso:country":"US",
    "sg:address":"127 McAllister St",
    "sg:city":"State College",
    "sg:classifiers":[
        {
            "category":"Social Services",
            "subcategory":"Child Care",
            "type":"Services"
        }
    ],
    "sg:phone":"+1 814 237 1245",
    "sg:postcode":"16801",
    "sg:province":"PA",
    "sg:tags":[
        "day"
    ],
    "wof:name":"St Paul's Christian Pre School",
    "wof:placetype":"venue"
},
  "geometry": {"coordinates":[-77.858907,40.7961],"type":"Point"}
}