{
  "type": "Feature",
  "properties": {
    "iso:country":"US",
    "sg:address":"6901 Old York Rd",
    "sg:city":"Philadelphia",
    "sg:classifiers":[
        {
            "category":"Health Services",
            "subcategory":"Doctor",
            "type":"Services"
        }
    ],
    "sg:phone":"+1   ",
    "sg:postcode":"19126",
    "sg:province":"PA",
    "sg:tags":[
        "medical"
    ],
    "wof:name":"Arthur Chernoff MD",
    "wof:placetype":"venue"
},
  "geometry": {"coordinates":[-75.13861199999999,40.058737],"type":"Point"}
}