{
  "type": "Feature",
  "properties": {
    "addr:full":"2900 Arcona Rd Mechanicsburg PA 17055",
    "addr:postcode":"2900;17055",
    "addr:street":"Arcona Rd",
    "iso:country":"US",
    "sg:address":"2900 Arcona Rd",
    "sg:city":"Mechanicsburg",
    "sg:classifiers":[
        {
            "category":"Professional",
            "subcategory":"Lawyer & Legal Services",
            "type":"Services"
        }
    ],
    "sg:phone":"+1 717 697 2800",
    "sg:postcode":"17055",
    "sg:province":"PA",
    "wof:name":"Ressler Peter J Attorney",
    "wof:placetype":"venue"
},
  "geometry": {"coordinates":[-76.94380200000001,40.169102],"type":"Point"}
}