{
  "type": "Feature",
  "properties": {
    "iso:country":"US",
    "sg:address":"75 Paul Dr",
    "sg:city":"Washington",
    "sg:classifiers":[
        {
            "category":"Professional",
            "subcategory":"Management & Consulting",
            "type":"Services"
        }
    ],
    "sg:phone":"+1   ",
    "sg:postcode":"15301",
    "sg:province":"PA",
    "wof:name":"M & K Therapy Associates",
    "wof:placetype":"venue"
},
  "geometry": {"coordinates":[-80.22798299999999,40.156906],"type":"Point"}
}