{
  "type": "Feature",
  "properties": {
    "addr:full":"210 N York Rd Hatboro PA 19040",
    "addr:housenumber":"210",
    "addr:postcode":"19040",
    "addr:street":"N York Rd",
    "iso:country":"US",
    "sg:address":"210 N York Rd",
    "sg:city":"Hatboro",
    "sg:classifiers":[
        {
            "category":"Utilities",
            "subcategory":"Telephone",
            "type":"Services"
        }
    ],
    "sg:phone":"+1 215 940 0730",
    "sg:postcode":"19040",
    "sg:province":"PA",
    "sg:tags":[
        "communications"
    ],
    "wof:name":"Wireless Zone",
    "wof:placetype":"venue"
},
  "geometry": {"coordinates":[-75.105093,40.181099],"type":"Point"}
}