{
  "type": "Feature",
  "properties": {
    "addr:full":"3237 Ridge Pike Eagleville PA 19403",
    "addr:housenumber":"3237",
    "addr:postcode":"19403",
    "addr:street":"Ridge Pike",
    "iso:country":"US",
    "sg:address":"3237 Ridge Pike",
    "sg:city":"Eagleville",
    "sg:classifiers":[
        {
            "category":"Wholesale",
            "subcategory":"Construction Materials",
            "type":"Manufacturing & Wholesale Goods"
        }
    ],
    "sg:phone":"+1 610 935 5515",
    "sg:postcode":"19403",
    "sg:province":"PA",
    "sg:tags":[
        "glass"
    ],
    "wof:name":"Mobile Glass",
    "wof:placetype":"venue"
},
  "geometry": {"coordinates":[-75.405888,40.158384],"type":"Point"}
}