{
  "type": "Feature",
  "properties": {
    "iso:country":"US",
    "sg:address":"3093 Washington Pike",
    "sg:city":"Bridgeville",
    "sg:classifiers":[
        {
            "category":"Professional",
            "subcategory":"Accounting & Tax Preparation",
            "type":"Services"
        }
    ],
    "sg:phone":"+1 412 257 2929",
    "sg:postcode":"15017",
    "sg:province":"PA",
    "sg:tags":[
        "accountant"
    ],
    "sg:website":"www.dobisandassociates.com",
    "wof:name":"Dobis & Assocs",
    "wof:placetype":"venue"
},
  "geometry": {"coordinates":[-80.11191599999999,40.349675],"type":"Point"}
}