{
  "type": "Feature",
  "properties": {
    "iso:country":"US",
    "sg:address":"1740 Miller Rd",
    "sg:city":"Dauphin",
    "sg:classifiers":[
        {
            "category":"Professional",
            "type":"Services"
        }
    ],
    "sg:phone":"+1   ",
    "sg:postcode":"17018",
    "sg:province":"PA",
    "wof:name":"Debra A Lark",
    "wof:placetype":"venue"
},
  "geometry": {"coordinates":[-76.96956299999999,40.38982],"type":"Point"}
}