{
  "type": "Feature",
  "properties": {
    "addr:full":"4924 Convent Ln Philadelphia PA 19114",
    "addr:housenumber":"4924",
    "addr:postcode":"19114",
    "addr:street":"Convent Ln",
    "iso:country":"US",
    "sg:address":"4924 Convent Ln",
    "sg:city":"Philadelphia",
    "sg:classifiers":[
        {
            "category":"Home & Garden",
            "subcategory":"Carpets & Floor Coverings",
            "type":"Retail Goods"
        }
    ],
    "sg:phone":"+1 215 824 0865",
    "sg:postcode":"19114",
    "sg:province":"PA",
    "sg:tags":[
        "distributor",
        "rug",
        "manufacturer"
    ],
    "wof:name":"First Class Carpets",
    "wof:placetype":"venue"
},
  "geometry": {"coordinates":[-74.991585,40.052132],"type":"Point"}
}