{
  "type": "Feature",
  "properties": {
    "iso:country":"US",
    "sg:address":"2120 Buchert Rd",
    "sg:city":"Pottstown",
    "sg:classifiers":[
        {
            "category":"Organizations",
            "subcategory":"Religious Organization",
            "type":"Services"
        }
    ],
    "sg:phone":"+1 610 327 8624",
    "sg:postcode":"19464",
    "sg:province":"PA",
    "sg:tags":[
        "clergy"
    ],
    "wof:name":"Leon Lowery",
    "wof:placetype":"venue"
},
  "geometry": {"coordinates":[-75.589005,40.254052],"type":"Point"}
}