{
  "type": "Feature",
  "properties": {
    "iso:country":"US",
    "sg:address":"214 Yochum Run Rd",
    "sg:city":"Galeton",
    "sg:classifiers":[
        {
            "category":"Building & Trades",
            "subcategory":"Construction",
            "type":"Services"
        }
    ],
    "sg:phone":"+1   ",
    "sg:postcode":"16922",
    "sg:province":"PA",
    "sg:tags":[
        "contracting",
        "drywall"
    ],
    "wof:name":"Culp Contracting",
    "wof:placetype":"venue"
},
  "geometry": {"coordinates":[-77.7432,41.625789],"type":"Point"}
}