{
  "type": "Feature",
  "properties": {
    "iso:country":"US",
    "sg:address":"163 Running Horse Ln",
    "sg:city":"Franklin",
    "sg:classifiers":[
        {
            "category":"Farming",
            "subcategory":"Livestock Farm",
            "type":"Manufacturing & Wholesale Goods"
        }
    ],
    "sg:phone":"+1   ",
    "sg:postcode":"16323",
    "sg:province":"PA",
    "sg:tags":[
        "animal",
        "general"
    ],
    "wof:name":"Running Horse Ranch",
    "wof:placetype":"venue"
},
  "geometry": {"coordinates":[-79.85029299999999,41.345371],"type":"Point"}
}