{
  "type": "Feature",
  "properties": {
    "iso:country":"US",
    "sg:address":"105 E Philadelphia Ave",
    "sg:city":"Boyertown",
    "sg:classifiers":[
        {
            "category":"Professional",
            "subcategory":"Lawyer & Legal Services",
            "type":"Services"
        },
        {
            "category":"Real Estate",
            "subcategory":"Real Estate Services",
            "type":"Services"
        }
    ],
    "sg:phone":"+1 610 367 2921",
    "sg:postcode":"19512",
    "sg:province":"PA",
    "sg:tags":[
        "abstract",
        "attorney",
        "title"
    ],
    "wof:name":"Boyertown Abstractr Co",
    "wof:placetype":"venue"
},
  "geometry": {"coordinates":[-75.635631,40.332416],"type":"Point"}
}