{
  "type": "Feature",
  "properties": {
    "addr:full":"15 Kishacoquillas St Belleville PA 17004",
    "addr:housenumber":"15",
    "addr:postcode":"17004",
    "addr:street":"Kishacoquillas St",
    "iso:country":"US",
    "sg:address":"15 Kishacoquillas St",
    "sg:city":"Belleville",
    "sg:classifiers":[
        {
            "category":"Wholesale",
            "subcategory":"Dairy",
            "type":"Manufacturing & Wholesale Goods"
        }
    ],
    "sg:phone":"+1 717 935 2121",
    "sg:postcode":"17004",
    "sg:province":"PA",
    "sg:tags":[
        "product"
    ],
    "wof:name":"Fairmont Products Inc",
    "wof:placetype":"venue"
},
  "geometry": {"coordinates":[-77.72966099999999,40.607524],"type":"Point"}
}