{
  "type": "Feature",
  "properties": {
    "iso:country":"US",
    "sg:address":"130 N 2nd St",
    "sg:city":"Conneaut Lake",
    "sg:classifiers":[
        {
            "category":"Retail",
            "subcategory":"Funeral Services",
            "type":"Services"
        }
    ],
    "sg:phone":"+1 814 382 2895",
    "sg:postcode":"16316",
    "sg:province":"PA",
    "sg:tags":[
        "director"
    ],
    "wof:name":"Dickson Funeral Home",
    "wof:placetype":"venue"
},
  "geometry": {"coordinates":[-80.30276499999999,41.604273],"type":"Point"}
}