{
  "type": "Feature",
  "properties": {
    "iso:country":"US",
    "sg:address":"204 37th St",
    "sg:city":"Pittsburgh",
    "sg:classifiers":[
        {
            "category":"Social Services",
            "type":"Services"
        }
    ],
    "sg:phone":"+1   ",
    "sg:postcode":"15201",
    "sg:province":"PA",
    "sg:tags":[
        "organization",
        "membership"
    ],
    "wof:name":"Catholic Charities Pittsburgh",
    "wof:placetype":"venue"
},
  "geometry": {"coordinates":[-79.96366500000001,40.465279],"type":"Point"}
}