{
  "type": "Feature",
  "properties": {
    "addr:full":"112 W Lancaster Ave Shillington PA 19607",
    "addr:housenumber":"112",
    "addr:postcode":"19607",
    "addr:street":"W Lancaster Ave",
    "iso:country":"US",
    "sg:address":"112 W Lancaster Ave",
    "sg:city":"Shillington",
    "sg:classifiers":[
        {
            "category":"Professional",
            "subcategory":"Accounting & Tax Preparation",
            "type":"Services"
        }
    ],
    "sg:phone":"+1 610 777 4307",
    "sg:postcode":"19607",
    "sg:province":"PA",
    "sg:tags":[
        "accountant"
    ],
    "wof:name":"John Andras & Co",
    "wof:placetype":"venue"
},
  "geometry": {"coordinates":[-75.97005,40.303949],"type":"Point"}
}