{
  "type": "Feature",
  "properties": {
    "iso:country":"US",
    "sg:address":"805 Perry Hwy",
    "sg:city":"Pittsburgh",
    "sg:classifiers":[
        {
            "category":"Professional",
            "subcategory":"Business Services",
            "type":"Services"
        }
    ],
    "sg:phone":"+1 412 366 8536",
    "sg:postcode":"15229",
    "sg:province":"PA",
    "sg:tags":[
        "auction"
    ],
    "wof:name":"Lawrence Sonick",
    "wof:placetype":"venue"
},
  "geometry": {"coordinates":[-80.035075,40.529853],"type":"Point"}
}