{
  "type": "Feature",
  "properties": {
    "addr:full":"185 Franklin Mills Blvd Philadelphia PA 19154",
    "addr:housenumber":"185",
    "addr:postcode":"19154",
    "addr:street":"Franklin Mills Blvd",
    "iso:country":"US",
    "sg:address":"185 Franklin Mills Blvd",
    "sg:city":"Philadelphia",
    "sg:classifiers":[
        {
            "category":"Health Services",
            "subcategory":"Dentist",
            "type":"Services"
        }
    ],
    "sg:phone":"+1 215 637 6900",
    "sg:postcode":"19154",
    "sg:province":"PA",
    "sg:tags":[
        "dental",
        "dentists-pediatric",
        "clinic",
        "orthodontist",
        "dentistry",
        "dentists-orthodontists"
    ],
    "sg:website":"www.brightnow.com",
    "wof:name":"Bright Now! Dental",
    "wof:placetype":"venue"
},
  "geometry": {"coordinates":[-74.96462099999999,40.090876],"type":"Point"}
}