{
  "type": "Feature",
  "properties": {
    "iso:country":"US",
    "sg:address":"255 S Derr Dr",
    "sg:city":"Lewisburg",
    "sg:classifiers":[
        {
            "category":"Organizations",
            "subcategory":"Religious Organization",
            "type":"Services"
        }
    ],
    "sg:phone":"+1 570 524 2061",
    "sg:postcode":"17837",
    "sg:province":"PA",
    "sg:tags":[
        "church"
    ],
    "wof:name":"St Andrews Episcopal Church",
    "wof:placetype":"venue"
},
  "geometry": {"coordinates":[-76.89063899999999,40.955687],"type":"Point"}
}