{
  "type": "Feature",
  "properties": {
    "addr:full":"425 N Center St Corry PA 16407",
    "addr:housenumber":"425",
    "addr:postcode":"16407",
    "addr:street":"N Center St",
    "iso:country":"US",
    "sg:address":"425 N Center St",
    "sg:city":"Corry",
    "sg:classifiers":[
        {
            "category":"Personal",
            "subcategory":"Beauty Salon",
            "type":"Services"
        }
    ],
    "sg:phone":"+1 814 664 9821",
    "sg:postcode":"16407",
    "sg:province":"PA",
    "sg:tags":[
        "hair",
        "shop",
        "stylist"
    ],
    "wof:name":"Cindy's Mane Event",
    "wof:placetype":"venue"
},
  "geometry": {"coordinates":[-79.64139900000001,41.925512],"type":"Point"}
}