{
  "type": "Feature",
  "properties": {
    "iso:country":"US",
    "sg:address":"45 S 9th St",
    "sg:city":"Lebanon",
    "sg:classifiers":[
        {
            "category":"Real Estate",
            "subcategory":"Real Estate Operator",
            "type":"Services"
        }
    ],
    "sg:phone":"+1   ",
    "sg:postcode":"17042",
    "sg:province":"PA",
    "sg:tags":[
        "property",
        "lessor"
    ],
    "wof:name":"Shree Narnaryan Corp",
    "wof:placetype":"venue"
},
  "geometry": {"coordinates":[-76.426205,40.338276],"type":"Point"}
}