{
  "type": "Feature",
  "properties": {
    "addr:full":"4025 Green Pond Rd Bethlehem PA 18020",
    "addr:housenumber":"4025",
    "addr:postcode":"18020",
    "addr:street":"Green Pond Rd",
    "iso:country":"US",
    "sg:address":"4025 Green Pond Rd",
    "sg:city":"Bethlehem",
    "sg:classifiers":[
        {
            "category":"Social Services",
            "subcategory":"Adult Care",
            "type":"Services"
        }
    ],
    "sg:phone":"+1   ",
    "sg:postcode":"18020",
    "sg:province":"PA",
    "sg:tags":[
        "residential"
    ],
    "wof:name":"Genesis Eldrcare Rhblttion Ctr",
    "wof:placetype":"venue"
},
  "geometry": {"coordinates":[-75.32340000000001,40.674909],"type":"Point"}
}