{
  "type": "Feature",
  "properties": {
    "iso:country":"US",
    "sg:address":"10 E 1st Ave",
    "sg:city":"Parkesburg",
    "sg:classifiers":[
        {
            "category":"Food & Beverages",
            "subcategory":"Groceries & Convenience Stores",
            "type":"Retail Goods"
        }
    ],
    "sg:phone":"+1   ",
    "sg:postcode":"19365",
    "sg:province":"PA",
    "sg:tags":[
        "station",
        "gasoline"
    ],
    "wof:name":"Turkey Hill 84",
    "wof:placetype":"venue"
},
  "geometry": {"coordinates":[-75.90987,39.960542],"type":"Point"}
}