{
  "type": "Feature",
  "properties": {
    "iso:country":"US",
    "sg:address":"122 Center St",
    "sg:city":"Danville",
    "sg:classifiers":[
        {
            "category":"Education",
            "subcategory":"Dance Studio",
            "type":"Public Place"
        }
    ],
    "sg:phone":"+1 570 271 1777",
    "sg:postcode":"17821",
    "sg:province":"PA",
    "sg:tags":[
        "instruction",
        "dancing"
    ],
    "wof:name":"Karen Gronsky School Of Dance",
    "wof:placetype":"venue"
},
  "geometry": {"coordinates":[-76.614481,40.965023],"type":"Point"}
}