{
  "type": "Feature",
  "properties": {
    "iso:country":"US",
    "sg:address":"511 E Jamestown Rd",
    "sg:city":"Greenville",
    "sg:classifiers":[
        {
            "category":"Airport",
            "type":"Transportation"
        }
    ],
    "sg:phone":"+1 724 588 1665",
    "sg:postcode":"16125",
    "sg:province":"PA",
    "wof:name":"Elbow Street Aviation Svc",
    "wof:placetype":"venue"
},
  "geometry": {"coordinates":[-80.39912099999999,41.447946],"type":"Point"}
}