{
  "type": "Feature",
  "properties": {
    "addr:full":"3231 Bethlehem Pike Hatfield PA 19440",
    "addr:housenumber":"3231",
    "addr:postcode":"19440",
    "addr:street":"Bethlehem Pike",
    "iso:country":"US",
    "sg:address":"3231 Bethlehem Pike",
    "sg:city":"Hatfield",
    "sg:classifiers":[
        {
            "category":"Building & Trades",
            "subcategory":"Construction",
            "type":"Services"
        }
    ],
    "sg:phone":"+1   ",
    "sg:postcode":"19440",
    "sg:province":"PA",
    "sg:tags":[
        "contractor"
    ],
    "wof:name":"Hazzard Masonry Inc",
    "wof:placetype":"venue"
},
  "geometry": {"coordinates":[-75.296915,40.305977],"type":"Point"}
}