{
  "type": "Feature",
  "properties": {
    "addr:full":"506 Uber Way Grove City PA 16127",
    "addr:housenumber":"506",
    "addr:postcode":"16127",
    "addr:street":"Uber Way",
    "iso:country":"US",
    "sg:address":"506 Uber Way",
    "sg:city":"Grove City",
    "sg:classifiers":[
        {
            "category":"Personal",
            "subcategory":"Beauty Salon",
            "type":"Services"
        }
    ],
    "sg:phone":"+1   ",
    "sg:postcode":"16127",
    "sg:province":"PA",
    "sg:tags":[
        "shop"
    ],
    "wof:name":"Sammy DS",
    "wof:placetype":"venue"
},
  "geometry": {"coordinates":[-80.094289,41.156148],"type":"Point"}
}