{
  "type": "Feature",
  "properties": {
    "addr:full":"883 Plymouth Rd Plymouth Meeting PA 19462",
    "addr:housenumber":"883",
    "addr:postcode":"19462",
    "addr:street":"Plymouth Rd",
    "iso:country":"US",
    "sg:address":"883 Plymouth Rd",
    "sg:city":"Plymouth Meeting",
    "sg:classifiers":[
        {
            "category":"Building & Trades",
            "subcategory":"Plumbing",
            "type":"Services"
        }
    ],
    "sg:phone":"+1 610 272 8714",
    "sg:postcode":"19462",
    "sg:province":"PA",
    "sg:tags":[
        "conditioning",
        "air",
        "system",
        "contractor"
    ],
    "sg:website":"www.jelgeneralcontractorsinc.com",
    "wof:name":"Jel General Contractors Inc",
    "wof:placetype":"venue"
},
  "geometry": {"coordinates":[-75.3086,40.122567],"type":"Point"}
}