{
  "type": "Feature",
  "properties": {
    "iso:country":"US",
    "sg:address":"146 Saxony Dr",
    "sg:city":"Pittsburgh",
    "sg:classifiers":[
        {
            "category":"Shopping",
            "subcategory":"Adult",
            "type":"Retail Goods"
        }
    ],
    "sg:phone":"+1 412 207 2493",
    "sg:postcode":"15241",
    "sg:province":"PA",
    "sg:tags":[
        "entertainment"
    ],
    "sg:website":"www.edescorts.com",
    "wof:name":"Erotic Desires",
    "wof:placetype":"venue"
},
  "geometry": {"coordinates":[-80.077202,40.325802],"type":"Point"}
}