{
  "type": "Feature",
  "properties": {
    "addr:full":"1529 Pine St Philadelphia PA 19102",
    "addr:housenumber":"1529",
    "addr:postcode":"19102",
    "addr:street":"Pine St",
    "iso:country":"US",
    "sg:address":"1529 Pine St",
    "sg:city":"Philadelphia",
    "sg:classifiers":[
        {
            "category":"Education",
            "subcategory":"Music School",
            "type":"Public Place"
        }
    ],
    "sg:phone":"+1 215 545 1100",
    "sg:postcode":"19102",
    "sg:province":"PA",
    "sg:tags":[
        "instrument",
        "teacher",
        "musical"
    ],
    "wof:name":"Oster Fredk Fine Violins",
    "wof:placetype":"venue"
},
  "geometry": {"coordinates":[-75.167801,39.945801],"type":"Point"}
}