{
  "type": "Feature",
  "properties": {
    "iso:country":"US",
    "sg:address":"1 Walsh Rd",
    "sg:city":"Pittsburgh",
    "sg:classifiers":[
        {
            "category":"Retail",
            "subcategory":"Portrait Studio",
            "type":"Services"
        },
        {
            "category":"Shopping",
            "subcategory":"Pharmacy",
            "type":"Retail Goods"
        }
    ],
    "sg:phone":"+1 412 921 5755",
    "sg:postcode":"15205",
    "sg:province":"PA",
    "sg:tags":[
        "photography",
        "drugstore",
        "store"
    ],
    "wof:name":"Eckerd Drugs",
    "wof:placetype":"venue"
},
  "geometry": {"coordinates":[-80.071404,40.4389],"type":"Point"}
}