{
  "type": "Feature",
  "properties": {
    "iso:country":"US",
    "sg:address":"703 Aslan Ct",
    "sg:city":"York",
    "sg:classifiers":[
        {
            "category":"Sports & Exercise",
            "subcategory":"Golf",
            "type":"Entertainment"
        }
    ],
    "sg:phone":"+1   ",
    "sg:postcode":"17404",
    "sg:province":"PA",
    "sg:tags":[
        "course",
        "public"
    ],
    "wof:name":"Caves Valley Golf Course",
    "wof:placetype":"venue"
},
  "geometry": {"coordinates":[-76.76606099999999,39.987448],"type":"Point"}
}