{
  "type": "Feature",
  "properties": {
    "iso:country":"US",
    "sg:address":"903 Rebecca Dr",
    "sg:city":"Phoenixville",
    "sg:classifiers":[
        {
            "category":"Food & Beverages",
            "subcategory":"Groceries & Convenience Stores",
            "type":"Retail Goods"
        }
    ],
    "sg:phone":"+1 484 924 8404",
    "sg:postcode":"19460",
    "sg:province":"PA",
    "wof:name":"Markets Capitol",
    "wof:placetype":"venue"
},
  "geometry": {"coordinates":[-75.55974500000001,40.141994],"type":"Point"}
}