{
  "type": "Feature",
  "properties": {
    "addr:full":"962 Dewees Ln Chester Springs PA 19425",
    "addr:housenumber":"962",
    "addr:postcode":"19425",
    "addr:street":"Dewees Ln",
    "iso:country":"US",
    "sg:address":"962 Dewees Ln",
    "sg:city":"Chester Springs",
    "sg:classifiers":[
        {
            "category":"Wholesale",
            "subcategory":"Dairy",
            "type":"Manufacturing & Wholesale Goods"
        }
    ],
    "sg:phone":"+1 610 827 1141",
    "sg:postcode":"19425",
    "sg:province":"PA",
    "sg:tags":[
        "product"
    ],
    "wof:name":"Largiader International LTD",
    "wof:placetype":"venue"
},
  "geometry": {"coordinates":[-75.650333,40.097533],"type":"Point"}
}