{
  "type": "Feature",
  "properties": {
    "iso:country":"US",
    "sg:address":"58 E High St",
    "sg:city":"New Freedom",
    "sg:classifiers":[
        {
            "category":"Building & Trades",
            "subcategory":"Construction",
            "type":"Services"
        }
    ],
    "sg:phone":"+1 717 235 9910",
    "sg:postcode":"17349",
    "sg:province":"PA",
    "sg:tags":[
        "woodworker"
    ],
    "wof:name":"Country Pine",
    "wof:placetype":"venue"
},
  "geometry": {"coordinates":[-76.70140600000001,39.734351],"type":"Point"}
}