{
  "type": "Feature",
  "properties": {
    "addr:full":"490 1st Ave Royersford PA 19468",
    "addr:housenumber":"490",
    "addr:postcode":"19468",
    "addr:street":"1St Ave",
    "iso:country":"US",
    "sg:address":"490 1st Ave",
    "sg:city":"Royersford",
    "sg:classifiers":[
        {
            "category":"Real Estate",
            "subcategory":"Real Estate Agent",
            "type":"Services"
        }
    ],
    "sg:phone":"+1 610 948 4096",
    "sg:postcode":"19468",
    "sg:province":"PA",
    "sg:tags":[
        "material"
    ],
    "wof:name":"Royersford Industrial Property",
    "wof:placetype":"venue"
},
  "geometry": {"coordinates":[-75.539885,40.176157],"type":"Point"}
}