{
  "type": "Feature",
  "properties": {
    "addr:full":"1054 N Wales Rd North Wales PA 19454",
    "addr:housenumber":"1054",
    "addr:postcode":"19454",
    "addr:street":"N Wales Rd",
    "iso:country":"US",
    "sg:address":"1054 N Wales Rd",
    "sg:city":"North Wales",
    "sg:classifiers":[
        {
            "category":"Building & Trades",
            "subcategory":"Landscaping Services",
            "type":"Services"
        }
    ],
    "sg:phone":"+1 215 653 0707",
    "sg:postcode":"19454",
    "sg:province":"PA",
    "sg:tags":[
        "landscape",
        "contractor"
    ],
    "wof:name":"Cedar Run Landscapes Inc",
    "wof:placetype":"venue"
},
  "geometry": {"coordinates":[-75.242429,40.241592],"type":"Point"}
}