{
  "type": "Feature",
  "properties": {
    "addr:full":"152 Forest Rd Everett PA 15537",
    "addr:housenumber":"152",
    "addr:postcode":"15537",
    "addr:street":"Forest Rd",
    "iso:country":"US",
    "sg:address":"152 Forest Rd",
    "sg:city":"Everett",
    "sg:classifiers":[
        {
            "category":"Health Services",
            "subcategory":"Doctor",
            "type":"Services"
        }
    ],
    "sg:phone":"+1   ",
    "sg:postcode":"15537",
    "sg:province":"PA",
    "sg:tags":[
        "home",
        "medical",
        "care"
    ],
    "wof:name":"Regional",
    "wof:placetype":"venue"
},
  "geometry": {"coordinates":[-78.428713,40.025776],"type":"Point"}
}