{
  "type": "Feature",
  "properties": {
    "iso:country":"US",
    "sg:address":"4 Foxwood Dr",
    "sg:city":"Pittsburgh",
    "sg:classifiers":[
        {
            "category":"Personal",
            "type":"Services"
        }
    ],
    "sg:phone":"+1 412 963 7520",
    "sg:postcode":"15238",
    "sg:province":"PA",
    "sg:tags":[
        "assistant"
    ],
    "wof:name":"Egan Assocs",
    "wof:placetype":"venue"
},
  "geometry": {"coordinates":[-79.87027,40.532014],"type":"Point"}
}