{
  "type": "Feature",
  "properties": {
    "iso:country":"US",
    "sg:address":"220 S Balliet St",
    "sg:city":"Frackville",
    "sg:classifiers":[
        {
            "category":"Personal",
            "subcategory":"Beauty Salon",
            "type":"Services"
        }
    ],
    "sg:phone":"+1 570 874 4437",
    "sg:postcode":"17931",
    "sg:province":"PA",
    "wof:name":"Kutting Edge By Regina",
    "wof:placetype":"venue"
},
  "geometry": {"coordinates":[-76.230968,40.781673],"type":"Point"}
}