{
  "type": "Feature",
  "properties": {
    "addr:full":"259 Exton Square Mall Exton PA 19341",
    "addr:housenumber":"259",
    "addr:postcode":"19341",
    "addr:street":"Exton Square Mall",
    "iso:country":"US",
    "sg:address":"259 Exton Square Mall",
    "sg:city":"Exton",
    "sg:classifiers":[
        {
            "category":"Shopping",
            "subcategory":"Shoes",
            "type":"Retail Goods"
        }
    ],
    "sg:phone":"+1 610 594 0254",
    "sg:postcode":"19341",
    "sg:province":"PA",
    "wof:name":"Journeys",
    "wof:placetype":"venue"
},
  "geometry": {"coordinates":[-75.626029,40.032889],"type":"Point"}
}