{
  "type": "Feature",
  "properties": {
    "iso:country":"US",
    "sg:address":"3221 Macarthur Rd",
    "sg:city":"Whitehall",
    "sg:classifiers":[
        {
            "category":"Government",
            "subcategory":"Office",
            "type":"Public Place"
        }
    ],
    "sg:phone":"+1 610 437 5529",
    "sg:postcode":"18052",
    "sg:province":"PA",
    "sg:tags":[
        "village"
    ],
    "wof:name":"Whitehall Twp Treasurer's Ofc",
    "wof:placetype":"venue"
},
  "geometry": {"coordinates":[-75.50708899999999,40.656856],"type":"Point"}
}