{
  "type": "Feature",
  "properties": {
    "iso:country":"US",
    "sg:address":"295 Lower Morrisville Rd",
    "sg:city":"Levittown",
    "sg:classifiers":[
        {
            "category":"Shopping",
            "subcategory":"Bicycles & Sporting Goods",
            "type":"Retail Goods"
        },
        {
            "category":"Wholesale",
            "subcategory":"Chemicals & Plastics",
            "type":"Manufacturing & Wholesale Goods"
        },
        {
            "category":"Government",
            "subcategory":"Post Office",
            "type":"Public Place"
        }
    ],
    "sg:phone":"+1 215 295 0200",
    "sg:postcode":"19054",
    "sg:province":"PA",
    "sg:tags":[
        "supply",
        "equipment",
        "distributor",
        "manufacturer",
        "supplies-wholesale",
        "pool",
        "swimming"
    ],
    "sg:website":"http://www.garrettliners.com",
    "wof:name":"Garrett Liners, Inc.",
    "wof:placetype":"venue"
},
  "geometry": {"coordinates":[-74.802982,40.192816],"type":"Point"}
}