{
  "type": "Feature",
  "properties": {
    "addr:full":"115 Bowman St Lebanon PA 17046",
    "addr:housenumber":"115",
    "addr:postcode":"17046",
    "addr:street":"Bowman St",
    "iso:country":"US",
    "sg:address":"115 Bowman St",
    "sg:city":"Lebanon",
    "sg:classifiers":[
        {
            "category":"Banks & Credit Unions",
            "subcategory":"Bank",
            "type":"Services"
        }
    ],
    "sg:phone":"+1 717 376 1100",
    "sg:postcode":"17046",
    "sg:province":"PA",
    "wof:name":"Commerce Bank",
    "wof:placetype":"venue"
},
  "geometry": {"coordinates":[-76.395594,40.343613],"type":"Point"}
}