{
  "type": "Feature",
  "properties": {
    "addr:full":"1900 Woodhaven Rd Philadelphia PA 19116",
    "addr:housenumber":"1900",
    "addr:postcode":"19116",
    "addr:street":"Woodhaven Rd",
    "iso:country":"US",
    "sg:address":"1900 Woodhaven Rd",
    "sg:city":"Philadelphia",
    "sg:classifiers":[
        {
            "category":"Personal",
            "type":"Services"
        },
        {
            "category":"Professional",
            "subcategory":"Detective & Security Services",
            "type":"Services"
        },
        {
            "category":"Manufacturing",
            "subcategory":"Electronics",
            "type":"Manufacturing & Wholesale Goods"
        },
        {
            "category":"Shopping",
            "subcategory":"Computers & Home Electronics",
            "type":"Retail Goods"
        },
        {
            "category":"Manufacturing",
            "subcategory":"Building Materials",
            "type":"Manufacturing & Wholesale Goods"
        }
    ],
    "sg:phone":"+1 215 673 8800",
    "sg:postcode":"19116",
    "sg:province":"PA",
    "sg:tags":[
        "control",
        "monitoring",
        "fire",
        "consultant",
        "alarm",
        "system",
        "surveillance",
        "systems-wholesale",
        "equipment",
        "equipment-wholesale",
        "medical",
        "manufacturer"
    ],
    "sg:website":"http://www.fidelityalarm.com",
    "wof:name":"Fidelity Burglar & Fire Alarm",
    "wof:placetype":"venue"
},
  "geometry": {"coordinates":[-75.00250200000001,40.112728],"type":"Point"}
}