{
  "type": "Feature",
  "properties": {
    "iso:country":"US",
    "sg:address":"9088 Main St",
    "sg:city":"Mc Kean",
    "sg:classifiers":[
        {
            "category":"Restaurant",
            "type":"Food & Drink"
        }
    ],
    "sg:phone":"+1 814 476 7800",
    "sg:postcode":"16426",
    "sg:province":"PA",
    "sg:tags":[
        "eating"
    ],
    "wof:name":"Middleboro Pizza Co",
    "wof:placetype":"venue"
},
  "geometry": {"coordinates":[-80.143489,41.994013],"type":"Point"}
}