{
  "type": "Feature",
  "properties": {
    "iso:country":"US",
    "sg:address":"353 Bristol Rd",
    "sg:city":"Chalfont",
    "sg:classifiers":[
        {
            "category":"Building & Trades",
            "subcategory":"Landscaping Services",
            "type":"Services"
        }
    ],
    "sg:phone":"+1   ",
    "sg:postcode":"18914",
    "sg:province":"PA",
    "wof:name":"Greenway Group",
    "wof:placetype":"venue"
},
  "geometry": {"coordinates":[-75.186604,40.284064],"type":"Point"}
}