{
  "type": "Feature",
  "properties": {
    "iso:country":"US",
    "sg:address":"3133 Gaul Street",
    "sg:city":"Philadelphia",
    "sg:classifiers":[
        {
            "category":"Bars & Pubs",
            "subcategory":"Sports Bar",
            "type":"Food & Drink"
        }
    ],
    "sg:phone":"+1 215 423 7878",
    "sg:postcode":"19134",
    "sg:province":"PA",
    "wof:name":"Shenanigans Saloon",
    "wof:placetype":"venue"
},
  "geometry": {"coordinates":[-75.10654100000001,39.986122],"type":"Point"}
}