{
  "type": "Feature",
  "properties": {
    "iso:country":"US",
    "sg:address":"1048 N 27th St",
    "sg:city":"Allentown",
    "sg:classifiers":[
        {
            "category":"Professional",
            "subcategory":"Lawyer & Legal Services",
            "type":"Services"
        }
    ],
    "sg:phone":"+1 610 437 3751",
    "sg:postcode":"18104",
    "sg:province":"PA",
    "wof:name":"Roth Gerald I Atty",
    "wof:placetype":"venue"
},
  "geometry": {"coordinates":[-75.52069899999999,40.606701],"type":"Point"}
}