{
  "type": "Feature",
  "properties": {
    "iso:country":"US",
    "sg:address":"2260 Wells Rd",
    "sg:city":"Pottstown",
    "sg:classifiers":[
        {
            "category":"Retail",
            "subcategory":"Veterinary Services",
            "type":"Services"
        }
    ],
    "sg:phone":"+1 610 469 0102",
    "sg:postcode":"19465",
    "sg:province":"PA",
    "sg:tags":[
        "veterinarian"
    ],
    "wof:name":"John R Dunn Dd",
    "wof:placetype":"venue"
},
  "geometry": {"coordinates":[-75.728801,40.213049],"type":"Point"}
}