{
  "type": "Feature",
  "properties": {
    "iso:country":"US",
    "sg:address":"326 Carter Moir Dr",
    "sg:city":"Lancaster",
    "sg:classifiers":[
        {
            "category":"Manufacturing",
            "subcategory":"Printing",
            "type":"Manufacturing & Wholesale Goods"
        }
    ],
    "sg:phone":"+1 717 569 1477",
    "sg:postcode":"17601",
    "sg:province":"PA",
    "sg:tags":[
        "commercial"
    ],
    "wof:name":"Elegant Affairs",
    "wof:placetype":"venue"
},
  "geometry": {"coordinates":[-76.323153,40.104626],"type":"Point"}
}