{
  "type": "Feature",
  "properties": {
    "iso:country":"US",
    "sg:address":"207 Glenside Ave",
    "sg:city":"Wyncote",
    "sg:classifiers":[
        {
            "category":"Government",
            "subcategory":"Post Office",
            "type":"Public Place"
        }
    ],
    "sg:phone":"+1 215 884 6078",
    "sg:postcode":"19095",
    "sg:province":"PA",
    "sg:tags":[
        "postal",
        "us"
    ],
    "wof:name":"US Post Office",
    "wof:placetype":"venue"
},
  "geometry": {"coordinates":[-75.13676700000001,40.088853],"type":"Point"}
}