{
  "type": "Feature",
  "properties": {
    "iso:country":"US",
    "sg:address":"2551 Industry Ln",
    "sg:city":"Norristown",
    "sg:classifiers":[
        {
            "category":"Professional",
            "subcategory":"Business Services",
            "type":"Services"
        },
        {
            "category":"Manufacturing",
            "subcategory":"Printing",
            "type":"Manufacturing & Wholesale Goods"
        }
    ],
    "sg:phone":"+1 610 337 3136",
    "sg:postcode":"19403",
    "sg:province":"PA",
    "sg:tags":[
        "commercial",
        "broker"
    ],
    "wof:name":"M P S Communication Graphics",
    "wof:placetype":"venue"
},
  "geometry": {"coordinates":[-75.374245,40.153609],"type":"Point"}
}