{
  "type": "Feature",
  "properties": {
    "iso:country":"US",
    "sg:address":"31 W Main St",
    "sg:city":"Galeton",
    "sg:classifiers":[
        {
            "category":"Shopping",
            "subcategory":"Used Merchandise",
            "type":"Retail Goods"
        }
    ],
    "sg:phone":"+1   ",
    "sg:postcode":"16922",
    "sg:province":"PA",
    "wof:name":"Lawsons Used Furniture",
    "wof:placetype":"venue"
},
  "geometry": {"coordinates":[-77.64303099999999,41.735593],"type":"Point"}
}