{
  "type": "Feature",
  "properties": {
    "iso:country":"US",
    "sg:address":"157 S 1st St",
    "sg:city":"Lehighton",
    "sg:classifiers":[
        {
            "category":"Social Services",
            "type":"Services"
        }
    ],
    "sg:phone":"+1 610 379 0261",
    "sg:postcode":"18235",
    "sg:province":"PA",
    "sg:tags":[
        "organization",
        "welfare"
    ],
    "wof:name":"Domestic Violence Svc Ctr",
    "wof:placetype":"venue"
},
  "geometry": {"coordinates":[-75.708434,40.83251],"type":"Point"}
}