{
  "type": "Feature",
  "properties": {
    "iso:country":"US",
    "sg:address":"36 E Center St",
    "sg:city":"Shavertown",
    "sg:classifiers":[
        {
            "category":"Professional",
            "type":"Services"
        }
    ],
    "sg:phone":"+1   ",
    "sg:postcode":"18708",
    "sg:province":"PA",
    "wof:name":"Blue Flame Embroidery",
    "wof:placetype":"venue"
},
  "geometry": {"coordinates":[-75.937927,41.320067],"type":"Point"}
}