{
  "type": "Feature",
  "properties": {
    "iso:country":"US",
    "sg:address":"3 Education Dr",
    "sg:city":"Seneca",
    "sg:classifiers":[
        {
            "category":"Education",
            "subcategory":"School",
            "type":"Public Place"
        }
    ],
    "sg:phone":"+1 814 676 5628",
    "sg:postcode":"16346",
    "sg:province":"PA",
    "sg:tags":[
        "organization",
        "religious",
        "sch"
    ],
    "sg:website":"www.cranberrysd.org",
    "wof:name":"Cranberry Area School District",
    "wof:placetype":"venue"
},
  "geometry": {"coordinates":[-79.708921,41.367138],"type":"Point"}
}