{
  "type": "Feature",
  "properties": {
    "iso:country":"US",
    "sg:address":"11918 Trask Rd",
    "sg:city":"Waterford",
    "sg:classifiers":[
        {
            "category":"Manufacturing",
            "subcategory":"Food",
            "type":"Manufacturing & Wholesale Goods"
        },
        {
            "category":"Farming",
            "subcategory":"Farm",
            "type":"Manufacturing & Wholesale Goods"
        }
    ],
    "sg:phone":"+1 814 796 6356",
    "sg:postcode":"16441",
    "sg:province":"PA",
    "sg:tags":[
        "corn",
        "product"
    ],
    "wof:name":"Albrecht Farms",
    "wof:placetype":"venue"
},
  "geometry": {"coordinates":[-80.018217,41.954039],"type":"Point"}
}