{
  "type": "Feature",
  "properties": {
    "iso:country":"US",
    "sg:address":"215 S Main St",
    "sg:city":"Zelienople",
    "sg:classifiers":[
        {
            "category":"Health Services",
            "subcategory":"Clinic",
            "type":"Services"
        }
    ],
    "sg:phone":"+1 724 452 6691",
    "sg:postcode":"16063",
    "sg:province":"PA",
    "sg:tags":[
        "home"
    ],
    "wof:name":"Home Instead Senior Care",
    "wof:placetype":"venue"
},
  "geometry": {"coordinates":[-80.136815,40.794099],"type":"Point"}
}