{
  "type": "Feature",
  "properties": {
    "addr:full":"157 Schoolhouse Rd Lancaster PA 17603",
    "addr:housenumber":"157",
    "addr:postcode":"17603",
    "addr:street":"Schoolhouse Rd",
    "iso:country":"US",
    "sg:address":"157 Schoolhouse Rd",
    "sg:city":"Lancaster",
    "sg:classifiers":[
        {
            "category":"Personal",
            "subcategory":"Barber",
            "type":"Services"
        }
    ],
    "sg:phone":"+1 717 394 3647",
    "sg:postcode":"17603",
    "sg:province":"PA",
    "wof:name":"De Carlton Barber & Beauty Sln",
    "wof:placetype":"venue"
},
  "geometry": {"coordinates":[-76.338008,40.027521],"type":"Point"}
}