{
  "type": "Feature",
  "properties": {
    "iso:country":"US",
    "sg:address":"3104 Trapper Dr",
    "sg:city":"Library",
    "sg:classifiers":[
        {
            "category":"Manufacturing",
            "subcategory":"Printing",
            "type":"Manufacturing & Wholesale Goods"
        }
    ],
    "sg:phone":"+1   ",
    "sg:postcode":"15129",
    "sg:province":"PA",
    "sg:tags":[
        "newspaper"
    ],
    "wof:name":"Perry Publications Inc",
    "wof:placetype":"venue"
},
  "geometry": {"coordinates":[-79.988709,40.289596],"type":"Point"}
}