{
  "type": "Feature",
  "properties": {
    "iso:country":"US",
    "sg:address":"213 Greenwood Dr",
    "sg:city":"Millerstown",
    "sg:classifiers":[
        {
            "category":"Government",
            "subcategory":"Post Office",
            "type":"Public Place"
        }
    ],
    "sg:phone":"+1   ",
    "sg:postcode":"17062",
    "sg:province":"PA",
    "sg:tags":[
        "postal",
        "us"
    ],
    "wof:name":"US Post Office",
    "wof:placetype":"venue"
},
  "geometry": {"coordinates":[-77.077406,40.596813],"type":"Point"}
}