{
  "type": "Feature",
  "properties": {
    "addr:full":"1409 N Cedar Crest Blvd Allentown PA 18104",
    "addr:housenumber":"1409",
    "addr:postcode":"18104",
    "addr:street":"N Cedar Crest Blvd",
    "iso:country":"US",
    "sg:address":"1409 N Cedar Crest Blvd",
    "sg:city":"Allentown",
    "sg:classifiers":[
        {
            "category":"Retail",
            "subcategory":"Portrait Studio",
            "type":"Services"
        },
        {
            "category":"Professional",
            "subcategory":"Art Services",
            "type":"Services"
        },
        {
            "category":"Professional",
            "subcategory":"Printing & Photocopies",
            "type":"Services"
        }
    ],
    "sg:phone":"+1 610 395 6656",
    "sg:postcode":"18104",
    "sg:province":"PA",
    "sg:tags":[
        "rental",
        "photographers-portrait",
        "photographers-commercial",
        "photographic",
        "darkroom"
    ],
    "sg:website":"http://www.reflectionsfoto.com",
    "wof:name":"Reflections Crative Photography",
    "wof:placetype":"venue"
},
  "geometry": {"coordinates":[-75.53231100000001,40.611151],"type":"Point"}
}