{
  "type": "Feature",
  "properties": {
    "iso:country":"US",
    "sg:address":"49 W Eagle Rd",
    "sg:city":"Havertown",
    "sg:classifiers":[
        {
            "category":"Retail",
            "subcategory":"Repair Shop",
            "type":"Services"
        },
        {
            "category":"Professional",
            "subcategory":"Art Services",
            "type":"Services"
        },
        {
            "category":"Shopping",
            "subcategory":"Antiques",
            "type":"Retail Goods"
        }
    ],
    "sg:phone":"+1 610 449 7963",
    "sg:postcode":"19083",
    "sg:province":"PA",
    "sg:tags":[
        "refinish",
        "restoration",
        "reproduction",
        "furniture"
    ],
    "wof:name":"Ayoub, Naim M & Sons",
    "wof:placetype":"venue"
},
  "geometry": {"coordinates":[-75.312693,39.986857],"type":"Point"}
}