{
  "type": "Feature",
  "properties": {
    "iso:country":"US",
    "sg:address":"608 N Chester Rd",
    "sg:city":"West Chester",
    "sg:classifiers":[
        {
            "category":"Freight",
            "type":"Transportation"
        }
    ],
    "sg:phone":"+1   ",
    "sg:postcode":"19380",
    "sg:province":"PA",
    "sg:tags":[
        "company",
        "trucking"
    ],
    "wof:name":"Lew Amos Trucking",
    "wof:placetype":"venue"
},
  "geometry": {"coordinates":[-75.53932399999999,39.980847],"type":"Point"}
}