{
  "type": "Feature",
  "properties": {
    "addr:full":"745 Rte 30 Imperial PA 15126",
    "addr:housenumber":"745",
    "addr:postcode":"15126",
    "addr:street":"Rte 30",
    "iso:country":"US",
    "sg:address":"745 Rte 30",
    "sg:city":"Imperial",
    "sg:phone":"+1 724 695 7272",
    "sg:postcode":"15126",
    "sg:province":"PA",
    "sg:tags":[
        "oil"
    ],
    "wof:name":"Davis Oil Sales Inc",
    "wof:placetype":"venue"
},
  "geometry": {"coordinates":[-80.269245,40.463769],"type":"Point"}
}