{
  "type": "Feature",
  "properties": {
    "addr:full":"2001 N Front St Harrisburg PA 17102",
    "addr:housenumber":"2001",
    "addr:postcode":"17102",
    "addr:street":"N Front St",
    "iso:country":"US",
    "sg:address":"2001 N Front St",
    "sg:city":"Harrisburg",
    "sg:classifiers":[
        {
            "category":"Retail",
            "subcategory":"Laundry & Dry Cleaning",
            "type":"Services"
        }
    ],
    "sg:phone":"+1 717 232 3700",
    "sg:postcode":"17102",
    "sg:province":"PA",
    "sg:tags":[
        "cleaners",
        "rug",
        "carpet"
    ],
    "wof:name":"One Source",
    "wof:placetype":"venue"
},
  "geometry": {"coordinates":[-76.898932,40.276614],"type":"Point"}
}