{
  "type": "Feature",
  "properties": {
    "iso:country":"US",
    "sg:address":"3440 Maple St",
    "sg:city":"Harrisburg",
    "sg:classifiers":[
        {
            "category":"Government",
            "subcategory":"Fire Station",
            "type":"Public Place"
        }
    ],
    "sg:phone":"+1 717 545 3031",
    "sg:postcode":"17109",
    "sg:province":"PA",
    "sg:tags":[
        "department"
    ],
    "wof:name":"Progress Fire Station",
    "wof:placetype":"venue"
},
  "geometry": {"coordinates":[-76.838449,40.285565],"type":"Point"}
}