{
  "type": "Feature",
  "properties": {
    "iso:country":"US",
    "sg:address":"1016 Lititz Pike",
    "sg:city":"Lititz",
    "sg:classifiers":[
        {
            "category":"Home & Garden",
            "subcategory":"Home Furnishings",
            "type":"Retail Goods"
        }
    ],
    "sg:phone":"+1   ",
    "sg:postcode":"17543",
    "sg:province":"PA",
    "wof:name":"Framery Etc The",
    "wof:placetype":"venue"
},
  "geometry": {"coordinates":[-76.305122,40.127223],"type":"Point"}
}