{
  "type": "Feature",
  "properties": {
    "iso:country":"US",
    "sg:address":"2348 Quarry Rd",
    "sg:city":"Buckingham",
    "sg:classifiers":[
        {
            "category":"Travel",
            "subcategory":"Hotels & Motels",
            "type":"Entertainment"
        },
        {
            "category":"Travel",
            "subcategory":"Bed & Breakfast",
            "type":"Entertainment"
        }
    ],
    "sg:phone":"+1 215 794 3121",
    "sg:postcode":"18912",
    "sg:province":"PA",
    "wof:name":"Mill Creek Farm Bed & Breakfast",
    "wof:placetype":"venue"
},
  "geometry": {"coordinates":[-75.054968,40.32868],"type":"Point"}
}