{
  "type": "Feature",
  "properties": {
    "iso:country":"US",
    "sg:address":"827 E Pleasant St",
    "sg:city":"Glenside",
    "sg:classifiers":[
        {
            "category":"Bars & Pubs",
            "type":"Food & Drink"
        }
    ],
    "sg:phone":"+1 215 233 9953",
    "sg:postcode":"19038",
    "sg:province":"PA",
    "sg:tags":[
        "drinking"
    ],
    "wof:name":"Mc Gurk's",
    "wof:placetype":"venue"
},
  "geometry": {"coordinates":[-75.18835300000001,40.081269],"type":"Point"}
}