{
  "type": "Feature",
  "properties": {
    "addr:full":"1819 John F Kennedy Blvd Philadelphia PA 19103",
    "addr:housenumber":"1819",
    "addr:postcode":"19103",
    "addr:street":"John F Kennedy Blvd",
    "iso:country":"US",
    "sg:address":"1819 John F Kennedy Blvd",
    "sg:city":"Philadelphia",
    "sg:classifiers":[
        {
            "category":"Health Services",
            "subcategory":"Doctor",
            "type":"Services"
        }
    ],
    "sg:phone":"+1 215 563 8333",
    "sg:postcode":"19103",
    "sg:province":"PA",
    "sg:tags":[
        "dermatologist"
    ],
    "wof:name":"Lawrence C Parish",
    "wof:placetype":"venue"
},
  "geometry": {"coordinates":[-75.170097,39.954201],"type":"Point"}
}