{
  "type": "Feature",
  "properties": {
    "iso:country":"US",
    "sg:address":"85 1st Ave",
    "sg:city":"Red Lion",
    "sg:classifiers":[
        {
            "category":"Personal",
            "subcategory":"Beauty Salon",
            "type":"Services"
        }
    ],
    "sg:phone":"+1 717 244 2654",
    "sg:postcode":"17356",
    "sg:province":"PA",
    "wof:name":"Howard's Beauty Salon",
    "wof:placetype":"venue"
},
  "geometry": {"coordinates":[-76.60838200000001,39.901274],"type":"Point"}
}