{
  "type": "Feature",
  "properties": {
    "iso:country":"US",
    "sg:address":"4795 Havana Dr",
    "sg:city":"Pittsburgh",
    "sg:classifiers":[
        {
            "category":"Education",
            "subcategory":"School",
            "type":"Public Place"
        }
    ],
    "sg:phone":"+1 412 795 4430",
    "sg:postcode":"15239",
    "sg:province":"PA",
    "wof:name":"Holiday Park Elementary School",
    "wof:placetype":"venue"
},
  "geometry": {"coordinates":[-79.707545,40.479041],"type":"Point"}
}