{
  "type": "Feature",
  "properties": {
    "iso:country":"US",
    "sg:address":"97 Little Deer Creek Rd",
    "sg:city":"Cheswick",
    "sg:classifiers":[
        {
            "category":"Wholesale",
            "subcategory":"Scrap",
            "type":"Manufacturing & Wholesale Goods"
        }
    ],
    "sg:phone":"+1   ",
    "sg:postcode":"15024",
    "sg:province":"PA",
    "sg:tags":[
        "material"
    ],
    "wof:name":"Micale Wrecking",
    "wof:placetype":"venue"
},
  "geometry": {"coordinates":[-79.82499199999999,40.581877],"type":"Point"}
}