{
  "type": "Feature",
  "properties": {
    "iso:country":"US",
    "sg:address":"2207 Chestnut St",
    "sg:city":"Philadelphia",
    "sg:classifiers":[
        {
            "category":"Professional",
            "subcategory":"Lawyer & Legal Services",
            "type":"Services"
        }
    ],
    "sg:phone":"+1 215 557 6800",
    "sg:postcode":"19103",
    "sg:province":"PA",
    "sg:tags":[
        "attorney",
        "law",
        "disability",
        "security",
        "social"
    ],
    "sg:website":"http://www.connellyfirm.com",
    "wof:name":"The Connelly Firm PC",
    "wof:placetype":"venue"
},
  "geometry": {"coordinates":[-75.177414,39.952557],"type":"Point"}
}