{
  "type": "Feature",
  "properties": {
    "addr:full":"771 W Old Route 422 Butler PA 16001",
    "addr:housenumber":"771",
    "addr:postcode":"16001",
    "addr:street":"W Old Route 422",
    "iso:country":"US",
    "sg:address":"771 W Old Route 422",
    "sg:city":"Butler",
    "sg:classifiers":[
        {
            "category":"Restaurant",
            "type":"Food & Drink"
        }
    ],
    "sg:phone":"+1 724 282 8986",
    "sg:postcode":"16001",
    "sg:province":"PA",
    "sg:tags":[
        "eating"
    ],
    "wof:name":"Patty Kate Caterers",
    "wof:placetype":"venue"
},
  "geometry": {"coordinates":[-79.99420000000001,40.89839],"type":"Point"}
}