{
  "type": "Feature",
  "properties": {
    "iso:country":"US",
    "sg:address":"2732 N 5th St",
    "sg:city":"Philadelphia",
    "sg:classifiers":[
        {
            "category":"Professional",
            "subcategory":"Lawyer & Legal Services",
            "type":"Services"
        }
    ],
    "sg:phone":"+1 215 425 0929",
    "sg:postcode":"19133",
    "sg:province":"PA",
    "sg:tags":[
        "notary"
    ],
    "wof:name":"B & B Services",
    "wof:placetype":"venue"
},
  "geometry": {"coordinates":[-75.14012200000001,39.99262],"type":"Point"}
}