{
  "type": "Feature",
  "properties": {
    "addr:full":"2941 Brownsville Rd Pittsburgh PA 15227",
    "addr:housenumber":"2941",
    "addr:postcode":"15227",
    "addr:street":"Brownsville Rd",
    "iso:country":"US",
    "sg:address":"2941 Brownsville Rd",
    "sg:city":"Pittsburgh",
    "sg:classifiers":[
        {
            "category":"Shopping",
            "subcategory":"Pharmacy",
            "type":"Retail Goods"
        }
    ],
    "sg:phone":"+1 412 884 4400",
    "sg:postcode":"15227",
    "sg:province":"PA",
    "wof:name":"Spartan Pharmacy",
    "wof:placetype":"venue"
},
  "geometry": {"coordinates":[-79.975695,40.380372],"type":"Point"}
}