{
  "type": "Feature",
  "properties": {
    "addr:full":"144 S Market St Elizabethtown PA 17022",
    "addr:housenumber":"144",
    "addr:postcode":"17022",
    "addr:street":"S Market St",
    "iso:country":"US",
    "sg:address":"144 S Market St",
    "sg:city":"Elizabethtown",
    "sg:classifiers":[
        {
            "category":"Organizations",
            "subcategory":"Religious Organization",
            "type":"Services"
        }
    ],
    "sg:phone":"+1 717 367 7060",
    "sg:postcode":"17022",
    "sg:province":"PA",
    "sg:website":"www.etownfirstcog.org",
    "wof:name":"First Church Of God",
    "wof:placetype":"venue"
},
  "geometry": {"coordinates":[-76.604956,40.149672],"type":"Point"}
}