{
  "type": "Feature",
  "properties": {
    "addr:full":"950 Pennsylvania Blvd Feasterville Trevose PA 19053",
    "addr:housenumber":"950",
    "addr:postcode":"19053",
    "addr:street":"Pennsylvania Blvd",
    "iso:country":"US",
    "sg:address":"950 Pennsylvania Blvd",
    "sg:city":"Feasterville Trevose",
    "sg:classifiers":[
        {
            "category":"Professional",
            "subcategory":"Lawyer & Legal Services",
            "type":"Services"
        }
    ],
    "sg:phone":"+1   ",
    "sg:postcode":"19053",
    "sg:province":"PA",
    "wof:name":"Greenfield Murray L & Assoc PC",
    "wof:placetype":"venue"
},
  "geometry": {"coordinates":[-75.01048900000001,40.153673],"type":"Point"}
}