{
  "type": "Feature",
  "properties": {
    "iso:country":"US",
    "sg:address":"134 Broadway",
    "sg:city":"Bangor",
    "sg:classifiers":[
        {
            "category":"Professional",
            "subcategory":"Lawyer & Legal Services",
            "type":"Services"
        }
    ],
    "sg:phone":"+1 610 588 0484",
    "sg:postcode":"18013",
    "sg:province":"PA",
    "sg:tags":[
        "attorney"
    ],
    "wof:name":"Mc Fall Layman & Jordan",
    "wof:placetype":"venue"
},
  "geometry": {"coordinates":[-75.207351,40.865805],"type":"Point"}
}