{
  "type": "Feature",
  "properties": {
    "addr:full":"2672 Coral St Philadelphia PA 19125",
    "addr:housenumber":"2672",
    "addr:postcode":"19125",
    "addr:street":"Coral St",
    "iso:country":"US",
    "sg:address":"2672 Coral St",
    "sg:city":"Philadelphia",
    "sg:classifiers":[
        {
            "category":"Bars & Pubs",
            "type":"Food & Drink"
        },
        {
            "category":"Bars & Pubs",
            "subcategory":"Lounge",
            "type":"Food & Drink"
        }
    ],
    "sg:phone":"+1 215 425 0413",
    "sg:postcode":"19125",
    "sg:province":"PA",
    "sg:tags":[
        "tavern",
        "cocktail"
    ],
    "sg:website":"http://www.shannonspub.com",
    "wof:name":"Shannon's Tavern",
    "wof:placetype":"venue"
},
  "geometry": {"coordinates":[-75.12244200000001,39.986992],"type":"Point"}
}