{
  "type": "Feature",
  "properties": {
    "iso:country":"US",
    "sg:address":"296 Kentucky Ave",
    "sg:city":"Conshohocken",
    "sg:classifiers":[
        {
            "category":"Professional",
            "subcategory":"Art Services",
            "type":"Services"
        }
    ],
    "sg:phone":"+1 610 940 6644",
    "sg:postcode":"19428",
    "sg:province":"PA",
    "sg:tags":[
        "graphic",
        "commercial",
        "designer",
        "artist"
    ],
    "wof:name":"Valentine Design Inc",
    "wof:placetype":"venue"
},
  "geometry": {"coordinates":[-75.327093,40.066108],"type":"Point"}
}