{
  "type": "Feature",
  "properties": {
    "addr:full":"103 Stahl Rd Southampton PA 18966",
    "addr:housenumber":"103",
    "addr:postcode":"18966",
    "addr:street":"Stahl Rd",
    "iso:country":"US",
    "sg:address":"103 Stahl Rd",
    "sg:city":"Southampton",
    "sg:classifiers":[
        {
            "category":"Health Services",
            "subcategory":"Health Practitioner",
            "type":"Services"
        }
    ],
    "sg:phone":"+1 215 322 6781",
    "sg:postcode":"18966",
    "sg:province":"PA",
    "sg:tags":[
        "pathologist",
        "speech"
    ],
    "wof:name":"Ela Britchkow",
    "wof:placetype":"venue"
},
  "geometry": {"coordinates":[-75.05082899999999,40.185659],"type":"Point"}
}