{
  "type": "Feature",
  "properties": {
    "iso:country":"US",
    "sg:address":"718 Lehman St",
    "sg:city":"Lebanon",
    "sg:classifiers":[
        {
            "category":"Autos & Motor Vehicles",
            "subcategory":"Automobile Sales",
            "type":"Retail Goods"
        }
    ],
    "sg:phone":"+1   ",
    "sg:postcode":"17046",
    "sg:province":"PA",
    "sg:tags":[
        "used"
    ],
    "wof:name":"Pitts Auto Sales & Service",
    "wof:placetype":"venue"
},
  "geometry": {"coordinates":[-76.422522,40.345771],"type":"Point"}
}