{
  "type": "Feature",
  "properties": {
    "iso:country":"US",
    "sg:address":"22 S Commerce Way",
    "sg:city":"Bethlehem",
    "sg:classifiers":[
        {
            "category":"Building & Trades",
            "subcategory":"Construction",
            "type":"Services"
        }
    ],
    "sg:phone":"+1 610 332 0550",
    "sg:postcode":"18017",
    "sg:province":"PA",
    "sg:tags":[
        "new",
        "general",
        "commercial",
        "renovation",
        "contractor"
    ],
    "wof:name":"Iron Hill Construction MGM Co",
    "wof:placetype":"venue"
},
  "geometry": {"coordinates":[-75.37403,40.673896],"type":"Point"}
}