{
  "type": "Feature",
  "properties": {
    "iso:country":"US",
    "sg:address":"850 S 58th St",
    "sg:city":"Philadelphia",
    "sg:classifiers":[
        {
            "category":"Personal",
            "subcategory":"Beauty Salon",
            "type":"Services"
        }
    ],
    "sg:phone":"+1 215 748 2620",
    "sg:postcode":"19143",
    "sg:province":"PA",
    "wof:name":"Ida Dunston Beauty Parlor",
    "wof:placetype":"venue"
},
  "geometry": {"coordinates":[-75.239801,39.947552],"type":"Point"}
}