{
  "type": "Feature",
  "properties": {
    "iso:country":"US",
    "sg:address":"6817 Torresdale Ave",
    "sg:city":"Philadelphia",
    "sg:classifiers":[
        {
            "category":"Professional",
            "subcategory":"Management & Consulting",
            "type":"Services"
        }
    ],
    "sg:phone":"+1 215 332 0203",
    "sg:postcode":"19135",
    "sg:province":"PA",
    "sg:tags":[
        "science",
        "consultant",
        "academic"
    ],
    "wof:name":"Burnett Billing & Consulting Services",
    "wof:placetype":"venue"
},
  "geometry": {"coordinates":[-75.044483,40.025326],"type":"Point"}
}