{
  "type": "Feature",
  "properties": {
    "addr:full":"15 Riverside Dr Spring City PA 19475",
    "addr:housenumber":"15",
    "addr:postcode":"19475",
    "addr:street":"Riverside Dr",
    "iso:country":"US",
    "sg:address":"15 Riverside Dr",
    "sg:city":"Spring City",
    "sg:classifiers":[
        {
            "category":"Restaurant",
            "type":"Food & Drink"
        }
    ],
    "sg:phone":"+1 610 948 8202",
    "sg:postcode":"19475",
    "sg:province":"PA",
    "sg:tags":[
        "pizza"
    ],
    "wof:name":"Bb's Grille & Pizza Stop",
    "wof:placetype":"venue"
},
  "geometry": {"coordinates":[-75.546601,40.180355],"type":"Point"}
}