{
  "type": "Feature",
  "properties": {
    "iso:country":"US",
    "sg:address":"521 Market St",
    "sg:city":"Williamsport",
    "sg:classifiers":[
        {
            "category":"Real Estate",
            "subcategory":"Real Estate Operator",
            "type":"Services"
        }
    ],
    "sg:phone":"+1 570 326 1793",
    "sg:postcode":"17701",
    "sg:province":"PA",
    "sg:tags":[
        "apartment"
    ],
    "wof:name":"Teame Associates",
    "wof:placetype":"venue"
},
  "geometry": {"coordinates":[-77.003826,41.244471],"type":"Point"}
}