{
  "type": "Feature",
  "properties": {
    "iso:country":"US",
    "sg:address":"52 E Main St",
    "sg:city":"Palmyra",
    "sg:classifiers":[
        {
            "category":"Health Services",
            "subcategory":"Clinic",
            "type":"Services"
        }
    ],
    "sg:phone":"+1 717 838 6320",
    "sg:postcode":"17078",
    "sg:province":"PA",
    "wof:name":"Angela Reiner",
    "wof:placetype":"venue"
},
  "geometry": {"coordinates":[-76.594998,40.307808],"type":"Point"}
}