{
  "type": "Feature",
  "properties": {
    "iso:country":"US",
    "sg:address":"647 W Brookdale St",
    "sg:city":"Allentown",
    "sg:classifiers":[
        {
            "category":"Building & Trades",
            "subcategory":"Construction",
            "type":"Services"
        }
    ],
    "sg:phone":"+1   ",
    "sg:postcode":"18103",
    "sg:province":"PA",
    "sg:tags":[
        "house"
    ],
    "wof:name":"Quality Construction Co",
    "wof:placetype":"venue"
},
  "geometry": {"coordinates":[-75.46123299999999,40.581756],"type":"Point"}
}