{
  "type": "Feature",
  "properties": {
    "iso:country":"US",
    "sg:address":"111 Bissell Ave",
    "sg:city":"Oil City",
    "sg:classifiers":[
        {
            "category":"Shopping",
            "type":"Retail Goods"
        }
    ],
    "sg:phone":"+1 814 676 5476",
    "sg:postcode":"16301",
    "sg:province":"PA",
    "sg:tags":[
        "hearing",
        "equipment",
        "supply",
        "impaired"
    ],
    "wof:name":"Children's Aid Svc",
    "wof:placetype":"venue"
},
  "geometry": {"coordinates":[-79.701825,41.432431],"type":"Point"}
}