{
  "type": "Feature",
  "properties": {
    "addr:full":"3609 Poinciani Ave Reading PA 19605",
    "addr:housenumber":"3609",
    "addr:postcode":"19605",
    "addr:street":"Poinciani Ave",
    "iso:country":"US",
    "sg:address":"3609 Poinciani Ave",
    "sg:city":"Reading",
    "sg:classifiers":[
        {
            "category":"Organizations",
            "subcategory":"Religious Organization",
            "type":"Services"
        }
    ],
    "sg:phone":"+1 610 921 3771",
    "sg:postcode":"19605",
    "sg:province":"PA",
    "sg:tags":[
        "clergy"
    ],
    "wof:name":"Gerald C Arndt",
    "wof:placetype":"venue"
},
  "geometry": {"coordinates":[-75.945025,40.392181],"type":"Point"}
}