{
  "type": "Feature",
  "properties": {
    "iso:country":"US",
    "sg:address":"204 Merion Rd",
    "sg:city":"Merion Station",
    "sg:classifiers":[
        {
            "category":"Health Services",
            "subcategory":"Dentist",
            "type":"Services"
        }
    ],
    "sg:phone":"+1 610 664 4027",
    "sg:postcode":"19066",
    "sg:province":"PA",
    "wof:name":"Regni Gerald DMD",
    "wof:placetype":"venue"
},
  "geometry": {"coordinates":[-75.250237,39.998168],"type":"Point"}
}