{
  "type": "Feature",
  "properties": {
    "iso:country":"US",
    "sg:address":"407 Mount Nebo Rd",
    "sg:city":"Pittsburgh",
    "sg:classifiers":[
        {
            "category":"Shopping",
            "subcategory":"Clothing, Apparel, & Fashions",
            "type":"Retail Goods"
        },
        {
            "category":"Manufacturing",
            "subcategory":"Textiles",
            "type":"Manufacturing & Wholesale Goods"
        }
    ],
    "sg:phone":"+1 412 847 1444",
    "sg:postcode":"15237",
    "sg:province":"PA",
    "sg:tags":[
        "shirts-custom",
        "printer",
        "made"
    ],
    "sg:website":"http://www.touchofgreytees.com",
    "wof:name":"Touch Of Grey Tees",
    "wof:placetype":"venue"
},
  "geometry": {"coordinates":[-80.07672100000001,40.538447],"type":"Point"}
}