{
  "type": "Feature",
  "properties": {
    "addr:full":"3121 Saltsman Rd Erie PA 16510",
    "addr:housenumber":"3121",
    "addr:postcode":"16510",
    "addr:street":"Saltsman Rd",
    "iso:country":"US",
    "sg:address":"3121 Saltsman Rd",
    "sg:city":"Erie",
    "sg:classifiers":[
        {
            "category":"Shopping",
            "type":"Retail Goods"
        }
    ],
    "sg:phone":"+1 814 835 3033",
    "sg:postcode":"16510",
    "sg:province":"PA",
    "sg:tags":[
        "equipment",
        "telephone",
        "supply"
    ],
    "wof:name":"Martini Telephone Sales & Svc",
    "wof:placetype":"venue"
},
  "geometry": {"coordinates":[-79.98993299999999,42.134118],"type":"Point"}
}