{
  "type": "Feature",
  "properties": {
    "iso:country":"US",
    "sg:address":"500 W Cheltenham Ave",
    "sg:city":"Philadelphia",
    "sg:classifiers":[
        {
            "category":"Professional",
            "type":"Services"
        }
    ],
    "sg:phone":"+1 215 924 0804",
    "sg:postcode":"19126",
    "sg:province":"PA",
    "sg:tags":[
        "establishment"
    ],
    "wof:name":"Ace Network",
    "wof:placetype":"venue"
},
  "geometry": {"coordinates":[-75.128585,40.056757],"type":"Point"}
}