{
  "type": "Feature",
  "properties": {
    "iso:country":"US",
    "sg:address":"972 Liberty Ave",
    "sg:city":"Pittsburgh",
    "sg:classifiers":[
        {
            "category":"Bars & Pubs",
            "type":"Food & Drink"
        }
    ],
    "sg:phone":"+1   ",
    "sg:postcode":"15222",
    "sg:province":"PA",
    "sg:tags":[
        "drinking"
    ],
    "wof:name":"Liberty Tavern",
    "wof:placetype":"venue"
},
  "geometry": {"coordinates":[-79.995654,40.44344],"type":"Point"}
}