{
  "type": "Feature",
  "properties": {
    "iso:country":"US",
    "sg:address":"260 Ohio St",
    "sg:city":"Johnstown",
    "sg:classifiers":[
        {
            "category":"Building & Trades",
            "subcategory":"Landscaping Services",
            "type":"Services"
        }
    ],
    "sg:phone":"+1 814 535 1330",
    "sg:postcode":"15902",
    "sg:province":"PA",
    "sg:tags":[
        "tree"
    ],
    "wof:name":"Village Tree House",
    "wof:placetype":"venue"
},
  "geometry": {"coordinates":[-78.90556100000001,40.29722],"type":"Point"}
}