{
  "type": "Feature",
  "properties": {
    "iso:country":"US",
    "sg:address":"3845 Union Deposit Rd",
    "sg:city":"Harrisburg",
    "sg:classifiers":[
        {
            "category":"Shopping",
            "subcategory":"Clothing, Apparel, & Fashions",
            "type":"Retail Goods"
        }
    ],
    "sg:phone":"+1   ",
    "sg:postcode":"17109",
    "sg:province":"PA",
    "sg:tags":[
        "store"
    ],
    "wof:name":"Haband Co",
    "wof:placetype":"venue"
},
  "geometry": {"coordinates":[-76.825509,40.278254],"type":"Point"}
}