{
  "type": "Feature",
  "properties": {
    "iso:country":"US",
    "sg:address":"12 Park Ave",
    "sg:city":"Swarthmore",
    "sg:classifiers":[
        {
            "category":"Professional",
            "subcategory":"Computer Services",
            "type":"Services"
        }
    ],
    "sg:phone":"+1 610 636 2614",
    "sg:postcode":"19081",
    "sg:province":"PA",
    "sg:tags":[
        "consultant",
        "consulting",
        "designer",
        "system"
    ],
    "sg:website":"http://www.htconsult.net",
    "wof:name":"Ht Consulting Group",
    "wof:placetype":"venue"
},
  "geometry": {"coordinates":[-75.350262,39.902269],"type":"Point"}
}