{
  "type": "Feature",
  "properties": {
    "iso:country":"US",
    "sg:address":"1424 Washington St",
    "sg:city":"Huntingdon",
    "sg:classifiers":[
        {
            "category":"Building & Trades",
            "subcategory":"Construction",
            "type":"Services"
        }
    ],
    "sg:phone":"+1 814 643 0909",
    "sg:postcode":"16652",
    "sg:province":"PA",
    "sg:tags":[
        "concrete",
        "staining",
        "contractor"
    ],
    "wof:name":"Mel's Concrete",
    "wof:placetype":"venue"
},
  "geometry": {"coordinates":[-78.018942,40.494956],"type":"Point"}
}