{
  "type": "Feature",
  "properties": {
    "addr:full":"2000 Wakeling St Philadelphia PA 19124",
    "addr:postcode":"19124",
    "addr:street":"St",
    "iso:country":"US",
    "sg:address":"2000 Wakeling St",
    "sg:city":"Philadelphia",
    "sg:classifiers":[
        {
            "category":"Professional",
            "subcategory":"Management & Consulting",
            "type":"Services"
        }
    ],
    "sg:phone":"+1 215 289 0804",
    "sg:postcode":"19124",
    "sg:province":"PA",
    "sg:tags":[
        "consultant",
        "energy",
        "conservation"
    ],
    "wof:name":"Resources For Human Dev Sbbh",
    "wof:placetype":"venue"
},
  "geometry": {"coordinates":[-75.073295,40.012543],"type":"Point"}
}