{
  "type": "Feature",
  "properties": {
    "addr:full":"733 Pelham Ave Warminster PA 18974",
    "addr:housenumber":"733",
    "addr:postcode":"18974",
    "addr:street":"Pelham Ave",
    "iso:country":"US",
    "sg:address":"733 Pelham Ave",
    "sg:city":"Warminster",
    "sg:classifiers":[
        {
            "category":"Professional",
            "subcategory":"Employment Agencies",
            "type":"Services"
        },
        {
            "category":"Professional",
            "subcategory":"Lawyer & Legal Services",
            "type":"Services"
        }
    ],
    "sg:phone":"+1 215 675 5796",
    "sg:postcode":"18974",
    "sg:province":"PA",
    "sg:tags":[
        "convention",
        "secretarial",
        "reporters-court"
    ],
    "wof:name":"Charles H Johnston",
    "wof:placetype":"venue"
},
  "geometry": {"coordinates":[-75.117439,40.221198],"type":"Point"}
}