{
  "type": "Feature",
  "properties": {
    "iso:country":"US",
    "sg:address":"225 S Henderson Rd",
    "sg:city":"King Of Prussia",
    "sg:classifiers":[
        {
            "category":"Wholesale",
            "subcategory":"Auto Parts",
            "type":"Manufacturing & Wholesale Goods"
        }
    ],
    "sg:phone":"+1   ",
    "sg:postcode":"19406",
    "sg:province":"PA",
    "sg:tags":[
        "automotive"
    ],
    "wof:name":"3d Auto Parts Inc",
    "wof:placetype":"venue"
},
  "geometry": {"coordinates":[-75.36081900000001,40.091738],"type":"Point"}
}