{
  "type": "Feature",
  "properties": {
    "addr:full":"1805 Buchanan Ave Croydon PA 19021",
    "addr:housenumber":"1805",
    "addr:postcode":"19021",
    "addr:street":"Buchanan Ave",
    "iso:country":"US",
    "sg:address":"1805 Buchanan Ave",
    "sg:city":"Croydon",
    "sg:classifiers":[
        {
            "category":"Autos & Motor Vehicles",
            "subcategory":"Auto Supplies",
            "type":"Retail Goods"
        }
    ],
    "sg:phone":"+1 215 781 8124",
    "sg:postcode":"19021",
    "sg:province":"PA",
    "sg:tags":[
        "automobile",
        "stereo",
        "radio",
        "system"
    ],
    "wof:name":"Nu-Sound",
    "wof:placetype":"venue"
},
  "geometry": {"coordinates":[-74.895905,40.096139],"type":"Point"}
}