{
  "type": "Feature",
  "properties": {
    "iso:country":"US",
    "sg:address":"5911 Ditman St",
    "sg:city":"Philadelphia",
    "sg:classifiers":[
        {
            "category":"Home & Garden",
            "subcategory":"Building Materials",
            "type":"Retail Goods"
        }
    ],
    "sg:phone":"+1 215 535 7068",
    "sg:postcode":"19135",
    "sg:province":"PA",
    "sg:tags":[
        "plumbing",
        "fixture",
        "supply"
    ],
    "sg:website":"www.nnsupply.net",
    "wof:name":"N & N Supply Co",
    "wof:placetype":"venue"
},
  "geometry": {"coordinates":[-75.060298,40.018567],"type":"Point"}
}