{
  "type": "Feature",
  "properties": {
    "addr:full":"604 William St Pen Argyl PA 18072",
    "addr:housenumber":"604",
    "addr:postcode":"18072",
    "addr:street":"William St",
    "iso:country":"US",
    "sg:address":"604 William St",
    "sg:city":"Pen Argyl",
    "sg:classifiers":[
        {
            "category":"Freight",
            "type":"Transportation"
        }
    ],
    "sg:phone":"+1   ",
    "sg:postcode":"18072",
    "sg:province":"PA",
    "wof:name":"Crl Transportation Inc",
    "wof:placetype":"venue"
},
  "geometry": {"coordinates":[-75.260767,40.86608],"type":"Point"}
}