{
  "type": "Feature",
  "properties": {
    "iso:country":"US",
    "sg:address":"1737 Lycoming Creek Rd",
    "sg:city":"Williamsport",
    "sg:classifiers":[
        {
            "category":"Autos & Motor Vehicles",
            "subcategory":"Automobile Sales",
            "type":"Retail Goods"
        }
    ],
    "sg:phone":"+1   ",
    "sg:postcode":"17701",
    "sg:province":"PA",
    "wof:name":"Shirns Isuzu",
    "wof:placetype":"venue"
},
  "geometry": {"coordinates":[-77.044208,41.251819],"type":"Point"}
}