{
  "type": "Feature",
  "properties": {
    "iso:country":"US",
    "sg:address":"1705 Valley Rd",
    "sg:city":"Etters",
    "sg:classifiers":[
        {
            "category":"Wholesale",
            "subcategory":"Non-durable Goods",
            "type":"Manufacturing & Wholesale Goods"
        }
    ],
    "sg:phone":"+1 717 938 6669",
    "sg:postcode":"17319",
    "sg:province":"PA",
    "wof:name":"Haring Tree Farm",
    "wof:placetype":"venue"
},
  "geometry": {"coordinates":[-76.76176100000001,40.161909],"type":"Point"}
}