{
  "type": "Feature",
  "properties": {
    "iso:country":"US",
    "sg:address":"301 Fullerton Ave",
    "sg:city":"Whitehall",
    "sg:classifiers":[
        {
            "category":"Shopping",
            "type":"Retail Goods"
        }
    ],
    "sg:phone":"+1 610 433 7012",
    "sg:postcode":"18052",
    "sg:province":"PA",
    "sg:tags":[
        "monument"
    ],
    "wof:name":"Erich Schlosser Memorial",
    "wof:placetype":"venue"
},
  "geometry": {"coordinates":[-75.469048,40.626232],"type":"Point"}
}