{
  "type": "Feature",
  "properties": {
    "addr:full":"211 Shadeland Ave Lansdowne PA 19050",
    "addr:housenumber":"211",
    "addr:postcode":"19050",
    "addr:street":"Shadeland Ave",
    "iso:country":"US",
    "sg:address":"211 Shadeland Ave",
    "sg:city":"Lansdowne",
    "sg:classifiers":[
        {
            "category":"Social Services",
            "subcategory":"Child Care",
            "type":"Services"
        }
    ],
    "sg:phone":"+1 610 623 8383",
    "sg:postcode":"19050",
    "sg:province":"PA",
    "sg:tags":[
        "day"
    ],
    "sg:website":"www.stepbystepkids.com",
    "wof:name":"Step By Step Learning Center",
    "wof:placetype":"venue"
},
  "geometry": {"coordinates":[-75.288342,39.940791],"type":"Point"}
}