{
  "type": "Feature",
  "properties": {
    "addr:full":"10000 Roosevelt Blvd Philadelphia PA 19116",
    "addr:housenumber":"10000",
    "addr:postcode":"19116",
    "addr:street":"Roosevelt Blvd",
    "iso:country":"US",
    "sg:address":"10000 Roosevelt Blvd",
    "sg:city":"Philadelphia",
    "sg:classifiers":[
        {
            "category":"Utilities",
            "subcategory":"Mobile Phone",
            "type":"Services"
        },
        {
            "category":"Shopping",
            "subcategory":"Mobile Phones",
            "type":"Retail Goods"
        }
    ],
    "sg:phone":"+1 215 969 0601",
    "sg:postcode":"19116",
    "sg:province":"PA",
    "sg:tags":[
        "supply",
        "communication",
        "telephone",
        "wireless",
        "equipment",
        "cellular"
    ],
    "wof:name":"Verizon Wireless",
    "wof:placetype":"venue"
},
  "geometry": {"coordinates":[-75.001762,40.104939],"type":"Point"}
}