{
  "type": "Feature",
  "properties": {
    "addr:full":"405 Lebanon Ave Birdsboro PA 19508",
    "addr:housenumber":"405",
    "addr:postcode":"19508",
    "addr:street":"Lebanon Ave",
    "iso:country":"US",
    "sg:address":"405 Lebanon Ave",
    "sg:city":"Birdsboro",
    "sg:classifiers":[
        {
            "category":"Building & Trades",
            "subcategory":"Landscaping Services",
            "type":"Services"
        }
    ],
    "sg:phone":"+1 610 582 5557",
    "sg:postcode":"19508",
    "sg:province":"PA",
    "sg:tags":[
        "landscape",
        "contractor"
    ],
    "wof:name":"C A Landscaping",
    "wof:placetype":"venue"
},
  "geometry": {"coordinates":[-75.81401200000001,40.281447],"type":"Point"}
}