{
  "type": "Feature",
  "properties": {
    "iso:country":"US",
    "sg:address":"524 General Patterson Dr",
    "sg:city":"Glenside",
    "sg:classifiers":[
        {
            "category":"Restaurant",
            "type":"Food & Drink"
        }
    ],
    "sg:phone":"+1   ",
    "sg:postcode":"19038",
    "sg:province":"PA",
    "sg:tags":[
        "eating"
    ],
    "wof:name":"Murray Enterprises",
    "wof:placetype":"venue"
},
  "geometry": {"coordinates":[-75.16484199999999,40.09594],"type":"Point"}
}