{
  "type": "Feature",
  "properties": {
    "addr:full":"15 Laurel Mall Rd Hazleton PA 18201",
    "addr:housenumber":"15",
    "addr:postcode":"18201",
    "addr:street":"Laurel Mall Rd",
    "iso:country":"US",
    "sg:address":"15 Laurel Mall Rd",
    "sg:city":"Hazleton",
    "sg:classifiers":[
        {
            "category":"Shopping",
            "subcategory":"Shoes",
            "type":"Retail Goods"
        }
    ],
    "sg:phone":"+1 570 459 9850",
    "sg:postcode":"18201",
    "sg:province":"PA",
    "wof:name":"Foot Locker",
    "wof:placetype":"venue"
},
  "geometry": {"coordinates":[-76.01933099999999,40.981352],"type":"Point"}
}