{
  "type": "Feature",
  "properties": {
    "iso:country":"US",
    "sg:address":"41 Sterling St",
    "sg:city":"Pittsburgh",
    "sg:classifiers":[
        {
            "category":"Manufacturing",
            "subcategory":"Food",
            "type":"Manufacturing & Wholesale Goods"
        }
    ],
    "sg:phone":"+1 412 431 6668",
    "sg:postcode":"15203",
    "sg:province":"PA",
    "sg:tags":[
        "drink",
        "soft",
        "mfg"
    ],
    "wof:name":"Nowicki Beverage Inc",
    "wof:placetype":"venue"
},
  "geometry": {"coordinates":[-79.973888,40.422862],"type":"Point"}
}