{
  "type": "Feature",
  "properties": {
    "addr:full":"5 Hearthstone Ct Reading PA 19606",
    "addr:housenumber":"5",
    "addr:postcode":"19606",
    "addr:street":"Hearthstone Ct",
    "iso:country":"US",
    "sg:address":"5 Hearthstone Ct",
    "sg:city":"Reading",
    "sg:classifiers":[
        {
            "category":"Health Services",
            "subcategory":"Health Practitioner",
            "type":"Services"
        }
    ],
    "sg:phone":"+1   ",
    "sg:postcode":"19606",
    "sg:province":"PA",
    "wof:name":"HealthSouth",
    "wof:placetype":"venue"
},
  "geometry": {"coordinates":[-75.87388300000001,40.308325],"type":"Point"}
}