{
  "type": "Feature",
  "properties": {
    "iso:country":"US",
    "sg:address":"9000 Perry Hwy",
    "sg:city":"Pittsburgh",
    "sg:classifiers":[
        {
            "category":"Health Services",
            "subcategory":"Dentist",
            "type":"Services"
        }
    ],
    "sg:phone":"+1 412 366 8990",
    "sg:postcode":"15237",
    "sg:province":"PA",
    "wof:name":"Katsur William J DMD",
    "wof:placetype":"venue"
},
  "geometry": {"coordinates":[-80.036976,40.57073],"type":"Point"}
}