{
  "type": "Feature",
  "properties": {
    "iso:country":"US",
    "sg:address":"154 W Gay St",
    "sg:city":"Windsor",
    "sg:classifiers":[
        {
            "category":"Retail",
            "subcategory":"Auto Repair",
            "type":"Services"
        }
    ],
    "sg:phone":"+1 717 244 6533",
    "sg:postcode":"17366",
    "sg:province":"PA",
    "sg:tags":[
        "repairing",
        "automobile"
    ],
    "wof:name":"Whiteley's Auto Svc",
    "wof:placetype":"venue"
},
  "geometry": {"coordinates":[-76.58870400000001,39.914153],"type":"Point"}
}