{
  "type": "Feature",
  "properties": {
    "iso:country":"US",
    "sg:address":"1300 Conshohocken Rd",
    "sg:city":"Conshohocken",
    "sg:classifiers":[
        {
            "category":"Utilities",
            "subcategory":"Fuel Oil & Lpg",
            "type":"Services"
        }
    ],
    "sg:phone":"+1   ",
    "sg:postcode":"19428",
    "sg:province":"PA",
    "wof:name":"Marchese Fuels Inc",
    "wof:placetype":"venue"
},
  "geometry": {"coordinates":[-75.318207,40.102419],"type":"Point"}
}