{
  "type": "Feature",
  "properties": {
    "addr:full":"4002 Main St Homestead PA 15120",
    "addr:housenumber":"4002",
    "addr:postcode":"15120",
    "addr:street":"Main St",
    "iso:country":"US",
    "sg:address":"4002 Main St",
    "sg:city":"Homestead",
    "sg:classifiers":[
        {
            "category":"Retail",
            "subcategory":"Repair Shop",
            "type":"Services"
        }
    ],
    "sg:phone":"+1 412 462 0110",
    "sg:postcode":"15120",
    "sg:province":"PA",
    "sg:tags":[
        "lock",
        "sweeper",
        "locksmith"
    ],
    "wof:name":"Main Street Lock & Key Co",
    "wof:placetype":"venue"
},
  "geometry": {"coordinates":[-79.905171,40.381929],"type":"Point"}
}