{
  "type": "Feature",
  "properties": {
    "addr:full":"2 Village Cir Tunkhannock PA 18612",
    "addr:housenumber":"2",
    "addr:postcode":"18612",
    "addr:street":"Village Cir",
    "iso:country":"US",
    "sg:address":"2 Village Cir",
    "sg:city":"Tunkhannock",
    "sg:classifiers":[
        {
            "category":"Food & Beverages",
            "subcategory":"Liquor & Beverages",
            "type":"Retail Goods"
        }
    ],
    "sg:phone":"+1 570 836 2366",
    "sg:postcode":"18612",
    "sg:province":"PA",
    "wof:name":"Liquor Control Board",
    "wof:placetype":"venue"
},
  "geometry": {"coordinates":[-75.97111599999999,41.335121],"type":"Point"}
}