{
  "type": "Feature",
  "properties": {
    "iso:country":"US",
    "sg:address":"1006 Corn Crib Dr",
    "sg:city":"Huntingdon Valley",
    "sg:classifiers":[
        {
            "category":"Manufacturing",
            "subcategory":"Printing",
            "type":"Manufacturing & Wholesale Goods"
        }
    ],
    "sg:phone":"+1   ",
    "sg:postcode":"19006",
    "sg:province":"PA",
    "sg:tags":[
        "lithographic",
        "commercial"
    ],
    "wof:name":"Strum Screen Printing",
    "wof:placetype":"venue"
},
  "geometry": {"coordinates":[-75.053369,40.146915],"type":"Point"}
}