{
  "type": "Feature",
  "properties": {
    "iso:country":"US",
    "sg:address":"713 W Main St",
    "sg:city":"Grove City",
    "sg:classifiers":[
        {
            "category":"Wholesale",
            "subcategory":"Chemicals & Plastics",
            "type":"Manufacturing & Wholesale Goods"
        }
    ],
    "sg:phone":"+1 724 458 7591",
    "sg:postcode":"16127",
    "sg:province":"PA",
    "wof:name":"Calcium Chloride Sales Inc",
    "wof:placetype":"venue"
},
  "geometry": {"coordinates":[-80.096217,41.162854],"type":"Point"}
}