{
  "type": "Feature",
  "properties": {
    "iso:country":"US",
    "sg:address":"940 Greenfield Ave",
    "sg:city":"Pittsburgh",
    "sg:classifiers":[
        {
            "category":"Shopping",
            "subcategory":"Computers & Home Electronics",
            "type":"Retail Goods"
        }
    ],
    "sg:phone":"+1 412 362 9797",
    "sg:postcode":"15217",
    "sg:province":"PA",
    "sg:tags":[
        "software"
    ],
    "wof:name":"Eureka Software",
    "wof:placetype":"venue"
},
  "geometry": {"coordinates":[-79.932366,40.423766],"type":"Point"}
}