{
  "type": "Feature",
  "properties": {
    "addr:full":"715 Great Springs Rd Bryn Mawr PA 19010",
    "addr:housenumber":"715",
    "addr:postcode":"19010",
    "addr:street":"Great Springs Rd",
    "iso:country":"US",
    "sg:address":"715 Great Springs Rd",
    "sg:city":"Bryn Mawr",
    "sg:classifiers":[
        {
            "category":"Building & Trades",
            "subcategory":"Construction",
            "type":"Services"
        }
    ],
    "sg:phone":"+1 610 526 1996",
    "sg:postcode":"19010",
    "sg:province":"PA",
    "sg:tags":[
        "home",
        "builder"
    ],
    "wof:name":"Bryn Mawr Design Build Inc",
    "wof:placetype":"venue"
},
  "geometry": {"coordinates":[-75.30858499999999,40.042003],"type":"Point"}
}