{
  "type": "Feature",
  "properties": {
    "iso:country":"US",
    "sg:address":"1922 Quarry Rd",
    "sg:city":"Lebanon",
    "sg:classifiers":[
        {
            "category":"Professional",
            "type":"Services"
        }
    ],
    "sg:phone":"+1   ",
    "sg:postcode":"17046",
    "sg:province":"PA",
    "wof:name":"Weaver Darvin",
    "wof:placetype":"venue"
},
  "geometry": {"coordinates":[-76.44725099999999,40.386019],"type":"Point"}
}