{
  "type": "Feature",
  "properties": {
    "iso:country":"US",
    "sg:address":"2 Fuller St",
    "sg:city":"Mt Jewett",
    "sg:classifiers":[
        {
            "category":"Shopping",
            "subcategory":"Computers & Home Electronics",
            "type":"Retail Goods"
        }
    ],
    "sg:phone":"+1 814 778 2291",
    "sg:postcode":"16740",
    "sg:province":"PA",
    "sg:tags":[
        "publishing"
    ],
    "wof:name":"Benson Writing & Editing",
    "wof:placetype":"venue"
},
  "geometry": {"coordinates":[-78.63741899999999,41.727337],"type":"Point"}
}