{
  "type": "Feature",
  "properties": {
    "iso:country":"US",
    "sg:address":"1710 S 10th St",
    "sg:city":"Philadelphia",
    "sg:classifiers":[
        {
            "category":"Food & Beverages",
            "subcategory":"Groceries & Convenience Stores",
            "type":"Retail Goods"
        }
    ],
    "sg:phone":"+1   ",
    "sg:postcode":"19148",
    "sg:province":"PA",
    "wof:name":"Labellas Market",
    "wof:placetype":"venue"
},
  "geometry": {"coordinates":[-75.16179700000001,39.928366],"type":"Point"}
}