{
  "type": "Feature",
  "properties": {
    "iso:country":"US",
    "sg:address":"2200 Macdade Blvd",
    "sg:city":"Holmes",
    "sg:classifiers":[
        {
            "category":"Building & Trades",
            "subcategory":"Pest Control",
            "type":"Services"
        }
    ],
    "sg:phone":"+1   ",
    "sg:postcode":"19043",
    "sg:province":"PA",
    "sg:tags":[
        "carpentry",
        "exterminator",
        "contractor"
    ],
    "wof:name":"Termite Damages Specialist",
    "wof:placetype":"venue"
},
  "geometry": {"coordinates":[-75.309147,39.898066],"type":"Point"}
}