{
  "type": "Feature",
  "properties": {
    "iso:country":"US",
    "sg:address":"230 Lindenwold Ave",
    "sg:city":"Ambler",
    "sg:classifiers":[
        {
            "category":"Retail",
            "subcategory":"Laundry & Dry Cleaning",
            "type":"Services"
        }
    ],
    "sg:phone":"+1 215 646 1598",
    "sg:postcode":"19002",
    "sg:province":"PA",
    "sg:tags":[
        "cleaners"
    ],
    "wof:name":"Lindenwold Tailors & Cleaners",
    "wof:placetype":"venue"
},
  "geometry": {"coordinates":[-75.21723,40.155534],"type":"Point"}
}