{
  "type": "Feature",
  "properties": {
    "iso:country":"US",
    "sg:address":"141 Roads End Ln",
    "sg:city":"Butler",
    "sg:classifiers":[
        {
            "category":"Building & Trades",
            "subcategory":"Electrical",
            "type":"Services"
        }
    ],
    "sg:phone":"+1   ",
    "sg:postcode":"16001",
    "sg:province":"PA",
    "sg:tags":[
        "electrical",
        "contractor"
    ],
    "wof:name":"Do All Electronics",
    "wof:placetype":"venue"
},
  "geometry": {"coordinates":[-79.89505699999999,40.918866],"type":"Point"}
}