{
  "type": "Feature",
  "properties": {
    "addr:full":"201 S Railroad St Palmyra PA 17078",
    "addr:housenumber":"201",
    "addr:postcode":"17078",
    "addr:street":"S Railroad St",
    "iso:country":"US",
    "sg:address":"201 S Railroad St",
    "sg:city":"Palmyra",
    "sg:classifiers":[
        {
            "category":"Professional",
            "subcategory":"Lawyer & Legal Services",
            "type":"Services"
        }
    ],
    "sg:phone":"+1 717 838 1385",
    "sg:postcode":"17078",
    "sg:province":"PA",
    "wof:name":"Farrell Joseph Michael Attorney",
    "wof:placetype":"venue"
},
  "geometry": {"coordinates":[-76.59320099999999,40.306099],"type":"Point"}
}