{
  "type": "Feature",
  "properties": {
    "addr:full":"96 Konhaus Rd Mechanicsburg PA 17050",
    "addr:housenumber":"96",
    "addr:postcode":"17050",
    "addr:street":"Konhaus Rd",
    "iso:country":"US",
    "sg:address":"96 Konhaus Rd",
    "sg:city":"Mechanicsburg",
    "sg:classifiers":[
        {
            "category":"Professional",
            "type":"Services"
        }
    ],
    "sg:phone":"+1 717 691 1193",
    "sg:postcode":"17050",
    "sg:province":"PA",
    "sg:tags":[
        "establishment"
    ],
    "wof:name":"Ro Joo Yong",
    "wof:placetype":"venue"
},
  "geometry": {"coordinates":[-77.040205,40.204279],"type":"Point"}
}