{
  "type": "Feature",
  "properties": {
    "iso:country":"US",
    "sg:address":"2727 Philmont Ave",
    "sg:city":"Huntingdon Vly",
    "sg:classifiers":[
        {
            "category":"Professional",
            "subcategory":"Credit Reporting & Collection",
            "type":"Services"
        }
    ],
    "sg:phone":"+1 215 947 7737",
    "sg:postcode":"19006",
    "sg:province":"PA",
    "sg:tags":[
        "agency"
    ],
    "wof:name":"Accounts Recievable Mgmt Svc",
    "wof:placetype":"venue"
},
  "geometry": {"coordinates":[-75.046221,40.122724],"type":"Point"}
}