{
  "type": "Feature",
  "properties": {
    "addr:full":"155 Little Conestoga Rd Downingtown PA 19335",
    "addr:housenumber":"155",
    "addr:postcode":"19335",
    "addr:street":"Little Conestoga Rd",
    "iso:country":"US",
    "sg:address":"155 Little Conestoga Rd",
    "sg:city":"Downingtown",
    "sg:classifiers":[
        {
            "category":"Insurance",
            "subcategory":"Insurance Agent",
            "type":"Services"
        }
    ],
    "sg:phone":"+1 610 458 1588",
    "sg:postcode":"19335",
    "sg:province":"PA",
    "wof:name":"Stahl & Co",
    "wof:placetype":"venue"
},
  "geometry": {"coordinates":[-75.69027800000001,40.078805],"type":"Point"}
}