{
  "type": "Feature",
  "properties": {
    "iso:country":"US",
    "sg:address":"657 Cheyney Rd",
    "sg:city":"Springfield",
    "sg:classifiers":[
        {
            "category":"Professional",
            "type":"Services"
        },
        {
            "category":"Personal",
            "type":"Services"
        },
        {
            "category":"Shopping",
            "subcategory":"Party Supplies",
            "type":"Retail Goods"
        }
    ],
    "sg:phone":"+1 610 623 6334",
    "sg:postcode":"19064",
    "sg:province":"PA",
    "sg:tags":[
        "food",
        "delivery",
        "wedding",
        "planning",
        "caterer"
    ],
    "sg:website":"http://www.j-mcatering.com",
    "wof:name":"J & M Catering",
    "wof:placetype":"venue"
},
  "geometry": {"coordinates":[-75.358165,39.925997],"type":"Point"}
}