{
  "type": "Feature",
  "properties": {
    "addr:full":"415 Susquehanna Ave Curwensville PA 16833",
    "addr:housenumber":"415",
    "addr:postcode":"16833",
    "addr:street":"Susquehanna Ave",
    "iso:country":"US",
    "sg:address":"415 Susquehanna Ave",
    "sg:city":"Curwensville",
    "sg:classifiers":[
        {
            "category":"Autos & Motor Vehicles",
            "subcategory":"Automobile Sales",
            "type":"Retail Goods"
        }
    ],
    "sg:phone":"+1 814 236 0851",
    "sg:postcode":"16833",
    "sg:province":"PA",
    "sg:tags":[
        "car",
        "dealer"
    ],
    "wof:name":"Bumbarger Auto Repair",
    "wof:placetype":"venue"
},
  "geometry": {"coordinates":[-78.524612,40.968573],"type":"Point"}
}