{
  "type": "Feature",
  "properties": {
    "iso:country":"US",
    "sg:address":"93 Steam Whistle Dr",
    "sg:city":"Warminster",
    "sg:classifiers":[
        {
            "category":"Wholesale",
            "subcategory":"Electrical",
            "type":"Manufacturing & Wholesale Goods"
        }
    ],
    "sg:phone":"+1 215 364 5868",
    "sg:postcode":"18974",
    "sg:province":"PA",
    "sg:tags":[
        "control",
        "security",
        "system"
    ],
    "wof:name":"R 3 Access Inc",
    "wof:placetype":"venue"
},
  "geometry": {"coordinates":[-75.06552000000001,40.228035],"type":"Point"}
}