{
  "type": "Feature",
  "properties": {
    "iso:country":"US",
    "sg:address":"601 Market St",
    "sg:city":"Philadelphia",
    "sg:classifiers":[
        {
            "category":"Government",
            "subcategory":"Police Station",
            "type":"Public Place"
        }
    ],
    "sg:phone":"+1   ",
    "sg:postcode":"19106",
    "sg:province":"PA",
    "sg:tags":[
        "protection"
    ],
    "wof:name":"Eastern District Pennsylvania",
    "wof:placetype":"venue"
},
  "geometry": {"coordinates":[-75.152,39.950936],"type":"Point"}
}