{
  "type": "Feature",
  "properties": {
    "addr:full":"629 4th Ave Ford City PA 16226",
    "addr:housenumber":"629",
    "addr:postcode":"16226",
    "addr:street":"4Th Ave",
    "iso:country":"US",
    "sg:address":"629 4th Ave",
    "sg:city":"Ford City",
    "sg:classifiers":[
        {
            "category":"Professional",
            "subcategory":"Business Services",
            "type":"Services"
        }
    ],
    "sg:phone":"+1   ",
    "sg:postcode":"16226",
    "sg:province":"PA",
    "wof:name":"Adams Notary Service",
    "wof:placetype":"venue"
},
  "geometry": {"coordinates":[-79.53448,40.767152],"type":"Point"}
}