{
  "type": "Feature",
  "properties": {
    "addr:full":"237 Main St Brookville PA 15825",
    "addr:housenumber":"237",
    "addr:postcode":"15825",
    "addr:street":"Main St",
    "iso:country":"US",
    "sg:address":"237 Main St",
    "sg:city":"Brookville",
    "sg:classifiers":[
        {
            "category":"Utilities",
            "subcategory":"Telephone",
            "type":"Services"
        },
        {
            "category":"Retail",
            "subcategory":"Repair Shop",
            "type":"Services"
        },
        {
            "category":"Manufacturing",
            "subcategory":"Electronics",
            "type":"Manufacturing & Wholesale Goods"
        },
        {
            "category":"Shopping",
            "subcategory":"Computers & Home Electronics",
            "type":"Retail Goods"
        }
    ],
    "sg:phone":"+1 814 849 3477",
    "sg:postcode":"15825",
    "sg:province":"PA",
    "sg:tags":[
        "stereo",
        "speakers-rebuild",
        "supply",
        "system",
        "high",
        "equipment",
        "stereophonic",
        "video",
        "equipment-service",
        "equipment-dealers",
        "telecommunications-equipment",
        "fidelity",
        "audio"
    ],
    "wof:name":"Randys Electronics",
    "wof:placetype":"venue"
},
  "geometry": {"coordinates":[-79.08078,41.16058],"type":"Point"}
}