{
  "type": "Feature",
  "properties": {
    "iso:country":"US",
    "sg:address":"601 Chadds Ford Dr",
    "sg:city":"Chadds Ford",
    "sg:classifiers":[
        {
            "category":"Banks & Credit Unions",
            "subcategory":"Investment Brokerage",
            "type":"Services"
        },
        {
            "category":"Banks & Credit Unions",
            "subcategory":"Bank",
            "type":"Services"
        }
    ],
    "sg:phone":"+1 610 388 2501",
    "sg:postcode":"19317",
    "sg:province":"PA",
    "sg:tags":[
        "loan",
        "security",
        "real estate"
    ],
    "wof:name":"Shallcross Mortgage Company",
    "wof:placetype":"venue"
},
  "geometry": {"coordinates":[-75.62514899999999,39.873281],"type":"Point"}
}