{
  "type": "Feature",
  "properties": {
    "iso:country":"US",
    "sg:address":"417 7th St",
    "sg:city":"Beaver Falls",
    "sg:classifiers":[
        {
            "category":"Home & Garden",
            "subcategory":"Household Appliances",
            "type":"Retail Goods"
        }
    ],
    "sg:phone":"+1 724 846 4678",
    "sg:postcode":"15010",
    "sg:province":"PA",
    "wof:name":"George's Used Appliance Ctr",
    "wof:placetype":"venue"
},
  "geometry": {"coordinates":[-80.325794,40.73808],"type":"Point"}
}