{
  "type": "Feature",
  "properties": {
    "addr:full":"5401 Butler St Pittsburgh PA 15201",
    "addr:housenumber":"5401",
    "addr:postcode":"15201",
    "addr:street":"Butler St",
    "iso:country":"US",
    "sg:address":"5401 Butler St",
    "sg:city":"Pittsburgh",
    "sg:classifiers":[
        {
            "category":"Wholesale",
            "subcategory":"Construction Materials",
            "type":"Manufacturing & Wholesale Goods"
        }
    ],
    "sg:phone":"+1 412 782 9800",
    "sg:postcode":"15201",
    "sg:province":"PA",
    "sg:tags":[
        "glass"
    ],
    "wof:name":"Steel City Glass Inc",
    "wof:placetype":"venue"
},
  "geometry": {"coordinates":[-79.94992999999999,40.483582],"type":"Point"}
}