{
  "type": "Feature",
  "properties": {
    "iso:country":"US",
    "sg:address":"695 Smithson Ave",
    "sg:city":"Erie",
    "sg:classifiers":[
        {
            "category":"Organizations",
            "subcategory":"Religious Organization",
            "type":"Services"
        }
    ],
    "sg:phone":"+1 814 899 3000",
    "sg:postcode":"16511",
    "sg:province":"PA",
    "sg:tags":[
        "church"
    ],
    "wof:name":"St Mark Evangelist Roman Cath",
    "wof:placetype":"venue"
},
  "geometry": {"coordinates":[-80.01485099999999,42.154251],"type":"Point"}
}