{
  "type": "Feature",
  "properties": {
    "iso:country":"US",
    "sg:address":"396 Reed Rd",
    "sg:city":"Broomall",
    "sg:classifiers":[
        {
            "category":"Home & Garden",
            "subcategory":"Carpets & Floor Coverings",
            "type":"Retail Goods"
        }
    ],
    "sg:phone":"+1 610 543 1988",
    "sg:postcode":"19008",
    "sg:province":"PA",
    "sg:tags":[
        "dealer",
        "installation",
        "rug",
        "flooring",
        "contractor"
    ],
    "sg:website":"www.eldoradocarpetone.com",
    "wof:name":"Eldorado Carpet One",
    "wof:placetype":"venue"
},
  "geometry": {"coordinates":[-75.342311,39.957249],"type":"Point"}
}