{
  "type": "Feature",
  "properties": {
    "iso:country":"US",
    "sg:address":"150 Lorana Ave",
    "sg:city":"Bradford",
    "sg:classifiers":[
        {
            "category":"Education",
            "subcategory":"School",
            "type":"Public Place"
        }
    ],
    "sg:phone":"+1 814 362 3841",
    "sg:postcode":"16701",
    "sg:province":"PA",
    "wof:name":"Bradford Area School Supt",
    "wof:placetype":"venue"
},
  "geometry": {"coordinates":[-78.619696,41.967156],"type":"Point"}
}