{
  "type": "Feature",
  "properties": {
    "iso:country":"US",
    "sg:address":"2425 Aramingo Ave",
    "sg:city":"Philadelphia",
    "sg:classifiers":[
        {
            "category":"Shopping",
            "type":"Retail Goods"
        }
    ],
    "sg:phone":"+1 215 426 2275",
    "sg:postcode":"19125",
    "sg:province":"PA",
    "sg:tags":[
        "pet",
        "shop",
        "store"
    ],
    "wof:name":"Accent On Animals",
    "wof:placetype":"venue"
},
  "geometry": {"coordinates":[-75.12051099999999,39.975632],"type":"Point"}
}