{
  "type": "Feature",
  "properties": {
    "addr:full":"920 Beaver Rd Ambridge PA 15003",
    "addr:housenumber":"920",
    "addr:postcode":"15003",
    "addr:street":"Beaver Rd",
    "iso:country":"US",
    "sg:address":"920 Beaver Rd",
    "sg:city":"Ambridge",
    "sg:classifiers":[
        {
            "category":"Restaurant",
            "type":"Food & Drink"
        }
    ],
    "sg:phone":"+1   ",
    "sg:postcode":"15003",
    "sg:province":"PA",
    "sg:tags":[
        "eating"
    ],
    "wof:name":"Monaca Pizza",
    "wof:placetype":"venue"
},
  "geometry": {"coordinates":[-80.223433,40.592508],"type":"Point"}
}