{
  "type": "Feature",
  "properties": {
    "addr:full":"1100 Lincoln Way White Oak PA 15131",
    "addr:housenumber":"1100",
    "addr:postcode":"15131",
    "addr:street":"Lincoln Way",
    "iso:country":"US",
    "sg:address":"1100 Lincoln Way",
    "sg:city":"White Oak",
    "sg:classifiers":[
        {
            "category":"Restaurant",
            "type":"Food & Drink"
        }
    ],
    "sg:phone":"+1 412 678 6191",
    "sg:postcode":"15131",
    "sg:province":"PA",
    "sg:tags":[
        "banquet",
        "rooms"
    ],
    "wof:name":"Hospitality Haus",
    "wof:placetype":"venue"
},
  "geometry": {"coordinates":[-79.823764,40.353806],"type":"Point"}
}