{
  "type": "Feature",
  "properties": {
    "iso:country":"US",
    "sg:address":"1001 Baltimore Pike # 301",
    "sg:city":"Springfield",
    "sg:classifiers":[
        {
            "category":"Health Services",
            "subcategory":"Doctor",
            "type":"Services"
        }
    ],
    "sg:phone":"+1 610 394 1234",
    "sg:postcode":"19064",
    "sg:province":"PA",
    "sg:tags":[
        "physician",
        "surgeon"
    ],
    "wof:name":"Mercy Medical",
    "wof:placetype":"venue"
},
  "geometry": {"coordinates":[-75.342438,39.914447],"type":"Point"}
}