{
  "type": "Feature",
  "properties": {
    "addr:full":"1500 Locust St Ste 1413 Philadelphia PA 19102",
    "addr:housenumber":"1500",
    "addr:postcode":"19102",
    "addr:street":"Locust St Ste 1413",
    "iso:country":"US",
    "sg:address":"1500 Locust St Ste 1413",
    "sg:city":"Philadelphia",
    "sg:classifiers":[
        {
            "category":"Health Services",
            "subcategory":"Dentist",
            "type":"Services"
        }
    ],
    "sg:phone":"+1 215 732 4450",
    "sg:postcode":"19102",
    "sg:province":"PA",
    "wof:name":"Locust St Periodontics & Implant Dentistry Llc",
    "wof:placetype":"venue"
},
  "geometry": {"coordinates":[-75.166235,39.948382],"type":"Point"}
}