{
  "type": "Feature",
  "properties": {
    "iso:country":"US",
    "sg:address":"99 S Cameron St",
    "sg:city":"Harrisburg",
    "sg:classifiers":[
        {
            "category":"Professional",
            "subcategory":"Employment Agencies",
            "type":"Services"
        }
    ],
    "sg:phone":"+1 717 257 1360",
    "sg:postcode":"17101",
    "sg:province":"PA",
    "wof:name":"Harrisburg Area Business Development Center",
    "wof:placetype":"venue"
},
  "geometry": {"coordinates":[-76.873901,40.263302],"type":"Point"}
}