{
  "type": "Feature",
  "properties": {
    "iso:country":"US",
    "sg:address":"2321 S 17th St",
    "sg:city":"Philadelphia",
    "sg:classifiers":[
        {
            "category":"Arts & Performance",
            "subcategory":"Music",
            "type":"Entertainment"
        }
    ],
    "sg:phone":"+1 215 462 4330",
    "sg:postcode":"19145",
    "sg:province":"PA",
    "sg:tags":[
        "musician"
    ],
    "wof:name":"Carmen Dee",
    "wof:placetype":"venue"
},
  "geometry": {"coordinates":[-75.175123,39.922264],"type":"Point"}
}