{
  "type": "Feature",
  "properties": {
    "addr:full":"210 E 2nd St Erie PA 16507",
    "addr:housenumber":"210",
    "addr:postcode":"16507",
    "addr:street":"E 2Nd St",
    "iso:country":"US",
    "sg:address":"210 E 2nd St",
    "sg:city":"Erie",
    "sg:classifiers":[
        {
            "category":"Social Services",
            "subcategory":"Adult Care",
            "type":"Services"
        }
    ],
    "sg:phone":"+1 814 454 1252",
    "sg:postcode":"16507",
    "sg:province":"PA",
    "sg:tags":[
        "home",
        "group"
    ],
    "wof:name":"Supportive Living Svc Inc",
    "wof:placetype":"venue"
},
  "geometry": {"coordinates":[-80.081919,42.135569],"type":"Point"}
}