{
  "type": "Feature",
  "properties": {
    "iso:country":"US",
    "sg:address":"438 Leah Dr",
    "sg:city":"Fort Washington",
    "sg:classifiers":[
        {
            "category":"Building & Trades",
            "subcategory":"Electrical",
            "type":"Services"
        }
    ],
    "sg:phone":"+1 215 646 2720",
    "sg:postcode":"19034",
    "sg:province":"PA",
    "sg:tags":[
        "electric",
        "contractor"
    ],
    "wof:name":"Pennington Electrical Svc",
    "wof:placetype":"venue"
},
  "geometry": {"coordinates":[-75.18273000000001,40.132158],"type":"Point"}
}