{
  "type": "Feature",
  "properties": {
    "iso:country":"US",
    "sg:address":"1801 Woodlands Cir",
    "sg:city":"Pittsburgh",
    "sg:classifiers":[
        {
            "category":"Wholesale",
            "subcategory":"Machinery & Supplies",
            "type":"Manufacturing & Wholesale Goods"
        }
    ],
    "sg:phone":"+1   ",
    "sg:postcode":"15241",
    "sg:province":"PA",
    "sg:tags":[
        "industrial"
    ],
    "wof:name":"Sekeras W G & Assoc Inc",
    "wof:placetype":"venue"
},
  "geometry": {"coordinates":[-80.08062,40.343928],"type":"Point"}
}