{
  "type": "Feature",
  "properties": {
    "iso:country":"US",
    "sg:address":"440 Ebenezer Rd",
    "sg:city":"Lebanon",
    "sg:classifiers":[
        {
            "category":"Communications",
            "subcategory":"Radio Station",
            "type":"Services"
        }
    ],
    "sg:phone":"+1 717 272 7651",
    "sg:postcode":"17046",
    "sg:province":"PA",
    "sg:tags":[
        "company",
        "broadcasting"
    ],
    "wof:name":"Lebanon Broadcasting Co",
    "wof:placetype":"venue"
},
  "geometry": {"coordinates":[-76.461764,40.360719],"type":"Point"}
}