{
  "type": "Feature",
  "properties": {
    "iso:country":"US",
    "sg:address":"225 State Rte 30",
    "sg:city":"Latrobe",
    "sg:classifiers":[
        {
            "category":"Restaurant",
            "type":"Food & Drink"
        }
    ],
    "sg:phone":"+1 724 539 7373",
    "sg:postcode":"15650",
    "sg:province":"PA",
    "wof:name":"Pizza Hut",
    "wof:placetype":"venue"
},
  "geometry": {"coordinates":[-79.38483100000001,40.285693],"type":"Point"}
}