{
  "type": "Feature",
  "properties": {
    "addr:full":"1711 Arlington Ave Pittsburgh PA 15210",
    "addr:housenumber":"1711",
    "addr:postcode":"15210",
    "addr:street":"Arlington Ave",
    "iso:country":"US",
    "sg:address":"1711 Arlington Ave",
    "sg:city":"Pittsburgh",
    "sg:classifiers":[
        {
            "category":"Shopping",
            "subcategory":"Catalog Store",
            "type":"Retail Goods"
        }
    ],
    "sg:phone":"+1 412 431 5030",
    "sg:postcode":"15210",
    "sg:province":"PA",
    "sg:tags":[
        "e"
    ],
    "wof:name":"Chess Discounters Inc",
    "wof:placetype":"venue"
},
  "geometry": {"coordinates":[-79.985347,40.41765],"type":"Point"}
}