{
  "type": "Feature",
  "properties": {
    "addr:full":"70 W Afton Ave Morrisville PA 19067",
    "addr:housenumber":"70",
    "addr:postcode":"19067",
    "addr:street":"W Afton Ave",
    "iso:country":"US",
    "sg:address":"70 W Afton Ave",
    "sg:city":"Morrisville",
    "sg:classifiers":[
        {
            "category":"Shopping",
            "subcategory":"Crafts & Fabrics",
            "type":"Retail Goods"
        }
    ],
    "sg:phone":"+1   ",
    "sg:postcode":"19067",
    "sg:province":"PA",
    "sg:tags":[
        "sewing"
    ],
    "wof:name":"Calico Corners",
    "wof:placetype":"venue"
},
  "geometry": {"coordinates":[-74.84147400000001,40.242301],"type":"Point"}
}