{
  "type": "Feature",
  "properties": {
    "iso:country":"US",
    "sg:address":"653 Hidden Pond Ln",
    "sg:city":"Huntingdon Valley",
    "sg:classifiers":[
        {
            "category":"Organizations",
            "subcategory":"Community Association",
            "type":"Services"
        }
    ],
    "sg:phone":"+1   ",
    "sg:postcode":"19006",
    "sg:province":"PA",
    "wof:name":"Pkg Foundation",
    "wof:placetype":"venue"
},
  "geometry": {"coordinates":[-75.078656,40.10813],"type":"Point"}
}