{
  "type": "Feature",
  "properties": {
    "iso:country":"US",
    "sg:address":"2880 Comly Rd",
    "sg:city":"Philadelphia",
    "sg:classifiers":[
        {
            "category":"Wholesale",
            "subcategory":"Machinery & Supplies",
            "type":"Manufacturing & Wholesale Goods"
        }
    ],
    "sg:phone":"+1 215 229 6601",
    "sg:postcode":"19154",
    "sg:province":"PA",
    "sg:tags":[
        "packer",
        "equipment",
        "meat"
    ],
    "wof:name":"U S Food Equipment Co",
    "wof:placetype":"venue"
},
  "geometry": {"coordinates":[-74.997349,40.100767],"type":"Point"}
}