{
  "type": "Feature",
  "properties": {
    "addr:full":"1719 Chestnut St Philadelphia PA 19103",
    "addr:housenumber":"1719",
    "addr:postcode":"19103",
    "addr:street":"Chestnut St",
    "iso:country":"US",
    "sg:address":"1719 Chestnut St",
    "sg:city":"Philadelphia",
    "sg:classifiers":[
        {
            "category":"Real Estate",
            "subcategory":"Real Estate Services",
            "type":"Services"
        },
        {
            "category":"Real Estate",
            "subcategory":"Real Estate Agent",
            "type":"Services"
        }
    ],
    "sg:phone":"+1 215 569 3646",
    "sg:postcode":"19103",
    "sg:province":"PA",
    "sg:tags":[
        "buyer",
        "broker"
    ],
    "wof:name":"Fg Realty",
    "wof:placetype":"venue"
},
  "geometry": {"coordinates":[-75.169061,39.951504],"type":"Point"}
}