{
  "type": "Feature",
  "properties": {
    "iso:country":"US",
    "sg:address":"972 Freeport Rd",
    "sg:city":"Pittsburgh",
    "sg:classifiers":[
        {
            "category":"Shopping",
            "subcategory":"Bicycles & Sporting Goods",
            "type":"Retail Goods"
        }
    ],
    "sg:phone":"+1   ",
    "sg:postcode":"15238",
    "sg:province":"PA",
    "wof:name":"Dunhams 029",
    "wof:placetype":"venue"
},
  "geometry": {"coordinates":[-79.852856,40.515495],"type":"Point"}
}