{
  "type": "Feature",
  "properties": {
    "iso:country":"US",
    "sg:address":"631 N Broad St Exd",
    "sg:city":"Grove City",
    "sg:classifiers":[
        {
            "category":"Health Services",
            "subcategory":"Clinic",
            "type":"Services"
        }
    ],
    "sg:phone":"+1   ",
    "sg:postcode":"16127",
    "sg:province":"PA",
    "wof:name":"Central Blood Bank",
    "wof:placetype":"venue"
},
  "geometry": {"coordinates":[-80.082819,41.170038],"type":"Point"}
}