{
  "type": "Feature",
  "properties": {
    "iso:country":"US",
    "sg:address":"715 E Lancaster Ave",
    "sg:city":"Downingtown",
    "sg:classifiers":[
        {
            "category":"Education",
            "subcategory":"School",
            "type":"Public Place"
        }
    ],
    "sg:phone":"+1 610 873 3820",
    "sg:postcode":"19335",
    "sg:province":"PA",
    "wof:name":"Chester County Alternative",
    "wof:placetype":"venue"
},
  "geometry": {"coordinates":[-75.690434,40.013807],"type":"Point"}
}