{
  "type": "Feature",
  "properties": {
    "addr:full":"163 Washington Ave Vandergrift PA 15690",
    "addr:housenumber":"163",
    "addr:postcode":"15690",
    "addr:street":"Washington Ave",
    "iso:country":"US",
    "sg:address":"163 Washington Ave",
    "sg:city":"Vandergrift",
    "sg:classifiers":[
        {
            "category":"Recreation",
            "subcategory":"Arcade",
            "type":"Entertainment"
        }
    ],
    "sg:phone":"+1   ",
    "sg:postcode":"15690",
    "sg:province":"PA",
    "sg:tags":[
        "amusement"
    ],
    "wof:name":"Tunes -N-Tables Amusement Co",
    "wof:placetype":"venue"
},
  "geometry": {"coordinates":[-79.564718,40.603664],"type":"Point"}
}