{
  "type": "Feature",
  "properties": {
    "iso:country":"US",
    "sg:address":"3001 New Beaver Ave",
    "sg:city":"Pittsburgh",
    "sg:classifiers":[
        {
            "category":"Organizations",
            "subcategory":"Non-profit Organization",
            "type":"Services"
        }
    ],
    "sg:phone":"+1   ",
    "sg:postcode":"15233",
    "sg:province":"PA",
    "sg:tags":[
        "social"
    ],
    "wof:name":"Emsa Correctional Care",
    "wof:placetype":"venue"
},
  "geometry": {"coordinates":[-80.039582,40.470605],"type":"Point"}
}