{
  "type": "Feature",
  "properties": {
    "iso:country":"US",
    "sg:address":"5320 Ellsworth Ave",
    "sg:city":"Pittsburgh",
    "sg:classifiers":[
        {
            "category":"Health Services",
            "subcategory":"Doctor",
            "type":"Services"
        }
    ],
    "sg:phone":"+1   ",
    "sg:postcode":"15232",
    "sg:province":"PA",
    "sg:tags":[
        "medical"
    ],
    "wof:name":"Jerry Gebhard Dr",
    "wof:placetype":"venue"
},
  "geometry": {"coordinates":[-79.936902,40.452594],"type":"Point"}
}