{
  "type": "Feature",
  "properties": {
    "iso:country":"US",
    "sg:address":"834 Cumberland St",
    "sg:city":"Lebanon",
    "sg:classifiers":[
        {
            "category":"Real Estate",
            "subcategory":"Real Estate Agent",
            "type":"Services"
        }
    ],
    "sg:phone":"+1 717 274 5870",
    "sg:postcode":"17042",
    "sg:province":"PA",
    "wof:name":"Rauch Real Estate",
    "wof:placetype":"venue"
},
  "geometry": {"coordinates":[-76.425438,40.339149],"type":"Point"}
}