{
  "type": "Feature",
  "properties": {
    "addr:full":"326 S 10th St Lemoyne PA 17043",
    "addr:housenumber":"326",
    "addr:postcode":"17043",
    "addr:street":"S 10Th St",
    "iso:country":"US",
    "sg:address":"326 S 10th St",
    "sg:city":"Lemoyne",
    "sg:classifiers":[
        {
            "category":"Shopping",
            "subcategory":"Clothing, Apparel, & Fashions",
            "type":"Retail Goods"
        }
    ],
    "sg:phone":"+1 717 737 5282",
    "sg:postcode":"17043",
    "sg:province":"PA",
    "sg:tags":[
        "accessory"
    ],
    "wof:name":"New Englander the",
    "wof:placetype":"venue"
},
  "geometry": {"coordinates":[-76.897598,40.236599],"type":"Point"}
}