{
  "type": "Feature",
  "properties": {
    "iso:country":"US",
    "sg:address":"126 N Wayne Ave",
    "sg:city":"Wayne",
    "sg:classifiers":[
        {
            "category":"Home & Garden",
            "subcategory":"Building Materials",
            "type":"Retail Goods"
        }
    ],
    "sg:phone":"+1 610 688 7070",
    "sg:postcode":"19087",
    "sg:province":"PA",
    "sg:tags":[
        "paint"
    ],
    "wof:name":"Conroy's Paint & Wallpaper",
    "wof:placetype":"venue"
},
  "geometry": {"coordinates":[-75.38792100000001,40.044844],"type":"Point"}
}