{
  "type": "Feature",
  "properties": {
    "iso:country":"US",
    "sg:address":"574 W High St",
    "sg:city":"Phoenixville",
    "sg:classifiers":[
        {
            "category":"Real Estate",
            "subcategory":"Real Estate Agent",
            "type":"Services"
        }
    ],
    "sg:phone":"+1 610 935 5747",
    "sg:postcode":"19460",
    "sg:province":"PA",
    "sg:tags":[
        "management"
    ],
    "wof:name":"Carefree Construction & Prprty",
    "wof:placetype":"venue"
},
  "geometry": {"coordinates":[-75.523039,40.137326],"type":"Point"}
}