{
  "type": "Feature",
  "properties": {
    "iso:country":"US",
    "sg:address":"1998 Smith Ln",
    "sg:city":"Monroeville",
    "sg:classifiers":[
        {
            "category":"Insurance",
            "subcategory":"Insurance Agent",
            "type":"Services"
        }
    ],
    "sg:phone":"+1 412 824 5700",
    "sg:postcode":"15146",
    "sg:province":"PA",
    "wof:name":"C F Buntack Agency",
    "wof:placetype":"venue"
},
  "geometry": {"coordinates":[-79.80816799999999,40.413368],"type":"Point"}
}