{
  "type": "Feature",
  "properties": {
    "iso:country":"US",
    "sg:address":"1343 Route 113",
    "sg:city":"Perkasie",
    "sg:classifiers":[
        {
            "category":"Restaurant",
            "type":"Food & Drink"
        }
    ],
    "sg:phone":"+1 215 256 6277",
    "sg:postcode":"18944",
    "sg:province":"PA",
    "sg:tags":[
        "style",
        "family",
        "pizza"
    ],
    "wof:name":"Pizza Mia Family Restaurant",
    "wof:placetype":"venue"
},
  "geometry": {"coordinates":[-75.242687,40.371374],"type":"Point"}
}