{
  "type": "Feature",
  "properties": {
    "addr:full":"1845 Walnut St Ste 900 Philadelphia PA 19103",
    "addr:housenumber":"1845",
    "addr:postcode":"19103",
    "addr:street":"Walnut St Ste 900",
    "iso:country":"US",
    "sg:address":"1845 Walnut St Ste 900",
    "sg:city":"Philadelphia",
    "sg:classifiers":[
        {
            "category":"Manufacturing",
            "subcategory":"Printing",
            "type":"Manufacturing & Wholesale Goods"
        },
        {
            "category":"Wholesale",
            "subcategory":"Books, Periodicals, & Newspapers",
            "type":"Manufacturing & Wholesale Goods"
        }
    ],
    "sg:phone":"+1 215 567 3200",
    "sg:postcode":"19103",
    "sg:province":"PA",
    "sg:tags":[
        "publisher",
        "magazines-distributors",
        "book"
    ],
    "sg:website":"http://www.familybusinessmagazine.com",
    "wof:name":"Family Business Magazine",
    "wof:placetype":"venue"
},
  "geometry": {"coordinates":[-75.17137099999999,39.95023],"type":"Point"}
}