{
  "type": "Feature",
  "properties": {
    "iso:country":"US",
    "sg:address":"710 Gibraltar Rd",
    "sg:city":"Reading",
    "sg:classifiers":[
        {
            "category":"Shopping",
            "type":"Retail Goods"
        },
        {
            "category":"Retail",
            "subcategory":"Animal Services",
            "type":"Services"
        }
    ],
    "sg:phone":"+1 610 370 2830",
    "sg:postcode":"19606",
    "sg:province":"PA",
    "sg:tags":[
        "pet",
        "grooming",
        "washing",
        "merchandise"
    ],
    "wof:name":"Marie's Pet Grooming Shop",
    "wof:placetype":"venue"
},
  "geometry": {"coordinates":[-75.86487099999999,40.295228],"type":"Point"}
}