{
  "type": "Feature",
  "properties": {
    "addr:full":"1662 S Cameron St Harrisburg PA 17104",
    "addr:housenumber":"1662",
    "addr:postcode":"17104",
    "addr:street":"S Cameron St",
    "iso:country":"US",
    "sg:address":"1662 S Cameron St",
    "sg:city":"Harrisburg",
    "sg:classifiers":[
        {
            "category":"Professional",
            "subcategory":"Engineering",
            "type":"Services"
        }
    ],
    "sg:phone":"+1 717 213 0956",
    "sg:postcode":"17104",
    "sg:province":"PA",
    "sg:tags":[
        "water",
        "treatment",
        "engineer"
    ],
    "wof:name":"Harrisburg Waste Water Trtmnt",
    "wof:placetype":"venue"
},
  "geometry": {"coordinates":[-76.856334,40.241815],"type":"Point"}
}