{
  "type": "Feature",
  "properties": {
    "addr:full":"954 Range End Rd Dillsburg PA 17019",
    "addr:housenumber":"954",
    "addr:postcode":"17019",
    "addr:street":"Range End Rd",
    "iso:country":"US",
    "sg:address":"954 Range End Rd",
    "sg:city":"Dillsburg",
    "sg:classifiers":[
        {
            "category":"Manufacturing",
            "subcategory":"Pottery",
            "type":"Manufacturing & Wholesale Goods"
        }
    ],
    "sg:phone":"+1 717 432 8124",
    "sg:postcode":"17019",
    "sg:province":"PA",
    "sg:tags":[
        "product",
        "mfg"
    ],
    "wof:name":"Fitzgerald Pottery",
    "wof:placetype":"venue"
},
  "geometry": {"coordinates":[-77.05644100000001,40.072656],"type":"Point"}
}