{
  "type": "Feature",
  "properties": {
    "addr:full":"1011 Old Salem Rd Greensburg PA 15601",
    "addr:housenumber":"1011",
    "addr:postcode":"15601",
    "addr:street":"Old Salem Rd",
    "iso:country":"US",
    "sg:address":"1011 Old Salem Rd",
    "sg:city":"Greensburg",
    "sg:classifiers":[
        {
            "category":"Social Services",
            "type":"Services"
        }
    ],
    "sg:phone":"+1 724 837 6198",
    "sg:postcode":"15601",
    "sg:province":"PA",
    "sg:tags":[
        "organization",
        "welfare"
    ],
    "sg:website":"www.bbbswc.org",
    "wof:name":"Big Brothers & Big Sisters",
    "wof:placetype":"venue"
},
  "geometry": {"coordinates":[-79.545935,40.327315],"type":"Point"}
}