{
  "type": "Feature",
  "properties": {
    "iso:country":"US",
    "sg:address":"8301 Roosevelt Blvd",
    "sg:city":"Philadelphia",
    "sg:classifiers":[
        {
            "category":"Social Services",
            "subcategory":"Job Training",
            "type":"Services"
        }
    ],
    "sg:phone":"+1 215 624 8728",
    "sg:postcode":"19152",
    "sg:province":"PA",
    "sg:tags":[
        "rehabilitation"
    ],
    "wof:name":"Rehab Care Contract Therapy",
    "wof:placetype":"venue"
},
  "geometry": {"coordinates":[-75.043505,40.061707],"type":"Point"}
}