{
  "type": "Feature",
  "properties": {
    "addr:full":"1122 Tennis Ave Bensalem PA 19020",
    "addr:housenumber":"1122",
    "addr:postcode":"19020",
    "addr:street":"Tennis Ave",
    "iso:country":"US",
    "sg:address":"1122 Tennis Ave",
    "sg:city":"Bensalem",
    "sg:classifiers":[
        {
            "category":"Building & Trades",
            "subcategory":"Plumbing",
            "type":"Services"
        }
    ],
    "sg:phone":"+1   ",
    "sg:postcode":"19020",
    "sg:province":"PA",
    "sg:tags":[
        "heating"
    ],
    "wof:name":"Litz Mechanical",
    "wof:placetype":"venue"
},
  "geometry": {"coordinates":[-74.975022,40.069428],"type":"Point"}
}