{
  "type": "Feature",
  "properties": {
    "iso:country":"US",
    "sg:address":"6 S Robinson Ave",
    "sg:city":"Pen Argyl",
    "sg:classifiers":[
        {
            "category":"Building & Trades",
            "subcategory":"Construction",
            "type":"Services"
        }
    ],
    "sg:phone":"+1 610 746 2204",
    "sg:postcode":"18072",
    "sg:province":"PA",
    "sg:tags":[
        "paving",
        "contractor"
    ],
    "wof:name":"B H Paving",
    "wof:placetype":"venue"
},
  "geometry": {"coordinates":[-75.25481499999999,40.868474],"type":"Point"}
}