{
  "type": "Feature",
  "properties": {
    "iso:country":"US",
    "sg:address":"5277 Horseshoe Pike",
    "sg:city":"Honey Brook",
    "sg:classifiers":[
        {
            "category":"Real Estate",
            "subcategory":"Developer",
            "type":"Services"
        }
    ],
    "sg:phone":"+1 610 273 3761",
    "sg:postcode":"19344",
    "sg:province":"PA",
    "wof:name":"Frame Group LTD",
    "wof:placetype":"venue"
},
  "geometry": {"coordinates":[-75.929506,40.103265],"type":"Point"}
}