{
  "type": "Feature",
  "properties": {
    "iso:country":"US",
    "sg:address":"2500 Yoder Dr",
    "sg:city":"Erie",
    "sg:classifiers":[
        {
            "category":"Shopping",
            "type":"Retail Goods"
        }
    ],
    "sg:phone":"+1 814 835 7387",
    "sg:postcode":"16506",
    "sg:province":"PA",
    "sg:tags":[
        "pet",
        "shop"
    ],
    "wof:name":"Buzz N' B's Aquarium Pet Shop",
    "wof:placetype":"venue"
},
  "geometry": {"coordinates":[-80.14764700000001,42.085441],"type":"Point"}
}