{
  "type": "Feature",
  "properties": {
    "iso:country":"US",
    "sg:address":"328 N 2nd St",
    "sg:city":"Mc Connellsburg",
    "sg:classifiers":[
        {
            "category":"Health Services",
            "subcategory":"Doctor",
            "type":"Services"
        }
    ],
    "sg:phone":"+1   ",
    "sg:postcode":"17233",
    "sg:province":"PA",
    "sg:tags":[
        "medical"
    ],
    "wof:name":"Gary S Deguzman",
    "wof:placetype":"venue"
},
  "geometry": {"coordinates":[-77.996933,39.936098],"type":"Point"}
}