{
  "type": "Feature",
  "properties": {
    "iso:country":"US",
    "sg:address":"149 Robin St",
    "sg:city":"North Versailles",
    "sg:classifiers":[
        {
            "category":"Shopping",
            "subcategory":"Musical Instruments",
            "type":"Retail Goods"
        }
    ],
    "sg:phone":"+1   ",
    "sg:postcode":"15137",
    "sg:province":"PA",
    "wof:name":"M Humphreys Highland Drum",
    "wof:placetype":"venue"
},
  "geometry": {"coordinates":[-79.815862,40.371551],"type":"Point"}
}