{
  "type": "Feature",
  "properties": {
    "addr:full":"114 Yearsley Mill Rd Media PA 19063",
    "addr:housenumber":"114",
    "addr:postcode":"19063",
    "addr:street":"Yearsley Mill Rd",
    "iso:country":"US",
    "sg:address":"114 Yearsley Mill Rd",
    "sg:city":"Media",
    "sg:classifiers":[
        {
            "category":"Building & Trades",
            "subcategory":"Construction",
            "type":"Services"
        }
    ],
    "sg:phone":"+1   ",
    "sg:postcode":"19063",
    "sg:province":"PA",
    "sg:tags":[
        "concrete",
        "contractor"
    ],
    "wof:name":"D Buoni & Sons Inc",
    "wof:placetype":"venue"
},
  "geometry": {"coordinates":[-75.447464,39.925235],"type":"Point"}
}