{
  "type": "Feature",
  "properties": {
    "iso:country":"US",
    "sg:address":"3939 Derry St",
    "sg:city":"Harrisburg",
    "sg:classifiers":[
        {
            "category":"Retail",
            "subcategory":"Auto Repair",
            "type":"Services"
        }
    ],
    "sg:phone":"+1 717 564 4988",
    "sg:postcode":"17111",
    "sg:province":"PA",
    "sg:tags":[
        "repairing",
        "automobile"
    ],
    "wof:name":"Cigic's Garage",
    "wof:placetype":"venue"
},
  "geometry": {"coordinates":[-76.817036,40.257468],"type":"Point"}
}