{
  "type": "Feature",
  "properties": {
    "iso:country":"US",
    "sg:address":"3009 Appledale Rd",
    "sg:city":"Norristown",
    "sg:classifiers":[
        {
            "category":"Professional",
            "subcategory":"Engineering",
            "type":"Services"
        }
    ],
    "sg:phone":"+1 610 539 1832",
    "sg:postcode":"19403",
    "sg:province":"PA",
    "sg:tags":[
        "engineer"
    ],
    "wof:name":"Audubon Consulting Inc",
    "wof:placetype":"venue"
},
  "geometry": {"coordinates":[-75.411008,40.144745],"type":"Point"}
}