{
  "type": "Feature",
  "properties": {
    "iso:country":"US",
    "sg:address":"39 Rosecroft Run",
    "sg:city":"Hanover",
    "sg:classifiers":[
        {
            "category":"Professional",
            "type":"Services"
        }
    ],
    "sg:phone":"+1   ",
    "sg:postcode":"17331",
    "sg:province":"PA",
    "wof:name":"Lottie A Wilder",
    "wof:placetype":"venue"
},
  "geometry": {"coordinates":[-77.04774999999999,39.79289],"type":"Point"}
}