{
  "type": "Feature",
  "properties": {
    "addr:full":"279 Fisk St Pittsburgh PA 15201",
    "addr:housenumber":"279",
    "addr:postcode":"15201",
    "addr:street":"Fisk St",
    "iso:country":"US",
    "sg:address":"279 Fisk St",
    "sg:city":"Pittsburgh",
    "sg:classifiers":[
        {
            "category":"Education",
            "subcategory":"Library",
            "type":"Public Place"
        }
    ],
    "sg:phone":"+1 412 682 3668",
    "sg:postcode":"15201",
    "sg:province":"PA",
    "wof:name":"Carnegie Library-Lawrenceville",
    "wof:placetype":"venue"
},
  "geometry": {"coordinates":[-79.959047,40.467434],"type":"Point"}
}