{
  "type": "Feature",
  "properties": {
    "addr:full":"1748 N Highland Rd Pittsburgh PA 15241",
    "addr:housenumber":"1748",
    "addr:postcode":"15241",
    "addr:street":"N Highland Rd",
    "iso:country":"US",
    "sg:address":"1748 N Highland Rd",
    "sg:city":"Pittsburgh",
    "sg:classifiers":[
        {
            "category":"Manufacturing",
            "subcategory":"Rubber & Plastics",
            "type":"Manufacturing & Wholesale Goods"
        }
    ],
    "sg:phone":"+1 412 833 9665",
    "sg:postcode":"15241",
    "sg:province":"PA",
    "sg:tags":[
        "product",
        "foam",
        "mfg"
    ],
    "wof:name":"Packaging Store",
    "wof:placetype":"venue"
},
  "geometry": {"coordinates":[-80.05210599999999,40.352334],"type":"Point"}
}