{
  "type": "Feature",
  "properties": {
    "iso:country":"US",
    "sg:address":"218 Murray Rd",
    "sg:city":"Valencia",
    "sg:classifiers":[
        {
            "category":"Building & Trades",
            "subcategory":"Landscaping Services",
            "type":"Services"
        }
    ],
    "sg:phone":"+1 724 898 2084",
    "sg:postcode":"16059",
    "sg:province":"PA",
    "wof:name":"Treez",
    "wof:placetype":"venue"
},
  "geometry": {"coordinates":[-79.90430000000001,40.734706],"type":"Point"}
}