{
  "type": "Feature",
  "properties": {
    "iso:country":"US",
    "sg:address":"10961 Worleytown Rd",
    "sg:city":"Greencastle",
    "sg:classifiers":[
        {
            "category":"Building & Trades",
            "subcategory":"Construction",
            "type":"Services"
        }
    ],
    "sg:phone":"+1 717 597 2390",
    "sg:postcode":"17225",
    "sg:province":"PA",
    "sg:tags":[
        "excavating",
        "contractor"
    ],
    "wof:name":"Reginald R Miller & Sons",
    "wof:placetype":"venue"
},
  "geometry": {"coordinates":[-77.795312,39.776018],"type":"Point"}
}