{
  "type": "Feature",
  "properties": {
    "iso:country":"US",
    "sg:address":"4215 Axe Handle Rd",
    "sg:city":"Quakertown",
    "sg:classifiers":[
        {
            "category":"Building & Trades",
            "subcategory":"Construction",
            "type":"Services"
        }
    ],
    "sg:phone":"+1   ",
    "sg:postcode":"18951",
    "sg:province":"PA",
    "sg:tags":[
        "house"
    ],
    "wof:name":"Mulloy Builder Jim",
    "wof:placetype":"venue"
},
  "geometry": {"coordinates":[-75.29189599999999,40.437441],"type":"Point"}
}