{
  "type": "Feature",
  "properties": {
    "iso:country":"US",
    "sg:address":"1116 Prescott Ave",
    "sg:city":"Scranton",
    "sg:classifiers":[
        {
            "category":"Professional",
            "type":"Services"
        }
    ],
    "sg:phone":"+1   ",
    "sg:postcode":"18510",
    "sg:province":"PA",
    "wof:name":"Ingiamo Salcatore",
    "wof:placetype":"venue"
},
  "geometry": {"coordinates":[-75.639526,41.413008],"type":"Point"}
}