{
  "type": "Feature",
  "properties": {
    "addr:full":"4124 Wood St Erie PA 16509",
    "addr:housenumber":"4124",
    "addr:postcode":"16509",
    "addr:street":"Wood St",
    "iso:country":"US",
    "sg:address":"4124 Wood St",
    "sg:city":"Erie",
    "sg:classifiers":[
        {
            "category":"Wholesale",
            "subcategory":"Scrap",
            "type":"Manufacturing & Wholesale Goods"
        }
    ],
    "sg:phone":"+1 814 456 2698",
    "sg:postcode":"16509",
    "sg:province":"PA",
    "sg:tags":[
        "metal",
        "iron"
    ],
    "wof:name":"Louis Tanner Co",
    "wof:placetype":"venue"
},
  "geometry": {"coordinates":[-80.078435,42.092031],"type":"Point"}
}