{
  "type": "Feature",
  "properties": {
    "iso:country":"US",
    "sg:address":"21 W Chestnut St",
    "sg:city":"Norristown",
    "sg:classifiers":[
        {
            "category":"Building & Trades",
            "subcategory":"Equipment Rental",
            "type":"Services"
        }
    ],
    "sg:phone":"+1   ",
    "sg:postcode":"19401",
    "sg:province":"PA",
    "wof:name":"William Latisha",
    "wof:placetype":"venue"
},
  "geometry": {"coordinates":[-75.343221,40.118684],"type":"Point"}
}