{
  "type": "Feature",
  "properties": {
    "iso:country":"US",
    "sg:address":"7 Reese Ave",
    "sg:city":"Pittsburgh",
    "sg:classifiers":[
        {
            "category":"Manufacturing",
            "subcategory":"Buildings",
            "type":"Manufacturing & Wholesale Goods"
        },
        {
            "category":"Building & Trades",
            "subcategory":"Construction",
            "type":"Services"
        }
    ],
    "sg:phone":"+1 412 784 1577",
    "sg:postcode":"15223",
    "sg:province":"PA",
    "sg:tags":[
        "industrial",
        "altering",
        "wallcoverings-installation",
        "builder",
        "wallpaper",
        "system",
        "specialty",
        "heating",
        "contractor",
        "contractors-commercial",
        "home",
        "remodeling",
        "air conditioning",
        "painting"
    ],
    "wof:name":"Kenst Brothers Inc",
    "wof:placetype":"venue"
},
  "geometry": {"coordinates":[-79.95268,40.509407],"type":"Point"}
}