{
  "type": "Feature",
  "properties": {
    "addr:full":"56 W Linden St Wilkes Barre PA 18702",
    "addr:housenumber":"56",
    "addr:postcode":"18702",
    "addr:street":"W Linden St",
    "iso:country":"US",
    "sg:address":"56 W Linden St",
    "sg:city":"Wilkes Barre",
    "sg:classifiers":[
        {
            "category":"Professional",
            "subcategory":"Management & Consulting",
            "type":"Services"
        }
    ],
    "sg:phone":"+1 570 970 2366",
    "sg:postcode":"18702",
    "sg:province":"PA",
    "sg:tags":[
        "consultant",
        "business"
    ],
    "wof:name":"Renal Consultants",
    "wof:placetype":"venue"
},
  "geometry": {"coordinates":[-75.867183,41.257771],"type":"Point"}
}