{
  "type": "Feature",
  "properties": {
    "iso:country":"US",
    "sg:address":"97 Walnuttown Rd",
    "sg:city":"Fleetwood",
    "sg:classifiers":[
        {
            "category":"Retail",
            "subcategory":"Auto Repair",
            "type":"Services"
        }
    ],
    "sg:phone":"+1 610 944 0898",
    "sg:postcode":"19522",
    "sg:province":"PA",
    "sg:tags":[
        "body",
        "automotive"
    ],
    "wof:name":"B & S Auto Body",
    "wof:placetype":"venue"
},
  "geometry": {"coordinates":[-75.841786,40.446447],"type":"Point"}
}