{
  "type": "Feature",
  "properties": {
    "addr:full":"2 Rutledge St Pittston PA 18640",
    "addr:housenumber":"2",
    "addr:postcode":"18640",
    "addr:street":"Rutledge St",
    "iso:country":"US",
    "sg:address":"2 Rutledge St",
    "sg:city":"Pittston",
    "sg:classifiers":[
        {
            "category":"Banks & Credit Unions",
            "subcategory":"Investment Brokerage",
            "type":"Services"
        }
    ],
    "sg:phone":"+1   ",
    "sg:postcode":"18640",
    "sg:province":"PA",
    "sg:tags":[
        "advisory"
    ],
    "wof:name":"North Gate Financial",
    "wof:placetype":"venue"
},
  "geometry": {"coordinates":[-75.811184,41.299005],"type":"Point"}
}