{
  "type": "Feature",
  "properties": {
    "iso:country":"US",
    "sg:address":"907 Saville Ave",
    "sg:city":"Crum Lynne",
    "sg:classifiers":[
        {
            "category":"Food & Beverages",
            "subcategory":"Groceries & Convenience Stores",
            "type":"Retail Goods"
        }
    ],
    "sg:phone":"+1   ",
    "sg:postcode":"19022",
    "sg:province":"PA",
    "sg:tags":[
        "eating"
    ],
    "wof:name":"Grocery Deli",
    "wof:placetype":"venue"
},
  "geometry": {"coordinates":[-75.343129,39.860591],"type":"Point"}
}