{
  "type": "Feature",
  "properties": {
    "addr:full":"39 Limekiln Pike Glenside PA 19038",
    "addr:housenumber":"39",
    "addr:postcode":"19038",
    "addr:street":"Limekiln Pike",
    "iso:country":"US",
    "sg:address":"39 Limekiln Pike",
    "sg:city":"Glenside",
    "sg:classifiers":[
        {
            "category":"Wholesale",
            "subcategory":"Construction Materials",
            "type":"Manufacturing & Wholesale Goods"
        },
        {
            "category":"Home & Garden",
            "subcategory":"Building Materials",
            "type":"Retail Goods"
        },
        {
            "category":"Building & Trades",
            "subcategory":"Construction",
            "type":"Services"
        }
    ],
    "sg:phone":"+1 215 886 3539",
    "sg:postcode":"19038",
    "sg:province":"PA",
    "sg:tags":[
        "fence-sales",
        "manufacturer",
        "fence-wholesale",
        "fence",
        "contractor"
    ],
    "sg:website":"http://www.everlastingfence.com",
    "wof:name":"Everlasting Fence",
    "wof:placetype":"venue"
},
  "geometry": {"coordinates":[-75.164485,40.106199],"type":"Point"}
}