{
  "type": "Feature",
  "properties": {
    "iso:country":"US",
    "sg:address":"21 N 2nd St",
    "sg:city":"Philadelphia",
    "sg:classifiers":[
        {
            "category":"Personal",
            "subcategory":"Beauty Salon",
            "type":"Services"
        }
    ],
    "sg:phone":"+1 215 923 2272",
    "sg:postcode":"19106",
    "sg:province":"PA",
    "sg:tags":[
        "hair",
        "makeup",
        "artist"
    ],
    "sg:website":"www.lakshmihairstudio.com",
    "wof:name":"Lakshmi Hair Studio",
    "wof:placetype":"venue"
},
  "geometry": {"coordinates":[-75.14356600000001,39.950611],"type":"Point"}
}