{
  "type": "Feature",
  "properties": {
    "iso:country":"US",
    "sg:address":"429 E Mount Pleasant Ave",
    "sg:city":"Philadelphia",
    "sg:classifiers":[
        {
            "category":"Building & Trades",
            "subcategory":"Construction",
            "type":"Services"
        }
    ],
    "sg:phone":"+1 215 753 3181",
    "sg:postcode":"19119",
    "sg:province":"PA",
    "sg:tags":[
        "general",
        "contractor"
    ],
    "wof:name":"Heartwood Building Constr",
    "wof:placetype":"venue"
},
  "geometry": {"coordinates":[-75.18242499999999,40.064534],"type":"Point"}
}