{
  "type": "Feature",
  "properties": {
    "iso:country":"US",
    "sg:address":"2670 N Susquehanna Trl",
    "sg:city":"York",
    "sg:classifiers":[
        {
            "category":"Travel",
            "subcategory":"Hotels & Motels",
            "type":"Entertainment"
        }
    ],
    "sg:phone":"+1 717 764 4327",
    "sg:postcode":"17406",
    "sg:province":"PA",
    "wof:name":"Dixie Motel",
    "wof:placetype":"venue"
},
  "geometry": {"coordinates":[-76.749765,40.003696],"type":"Point"}
}