{
  "type": "Feature",
  "properties": {
    "iso:country":"US",
    "sg:address":"PO Box 221",
    "sg:city":"Valencia",
    "sg:classifiers":[
        {
            "category":"Shopping",
            "subcategory":"Computers & Home Electronics",
            "type":"Retail Goods"
        }
    ],
    "sg:phone":"+1 724 898 3272",
    "sg:postcode":"16059",
    "sg:province":"PA",
    "wof:name":"Satcom",
    "wof:placetype":"venue"
},
  "geometry": {"coordinates":[-79.936203,40.702202],"type":"Point"}
}