{
  "type": "Feature",
  "properties": {
    "addr:full":"189 S Main St Washington PA 15301",
    "addr:housenumber":"189",
    "addr:postcode":"15301",
    "addr:street":"S Main St",
    "iso:country":"US",
    "sg:address":"189 S Main St",
    "sg:city":"Washington",
    "sg:classifiers":[
        {
            "category":"Food & Beverages",
            "subcategory":"Liquor & Beverages",
            "type":"Retail Goods"
        }
    ],
    "sg:phone":"+1 724 223 4385",
    "sg:postcode":"15301",
    "sg:province":"PA",
    "wof:name":"Wine & Spirit Shoppe",
    "wof:placetype":"venue"
},
  "geometry": {"coordinates":[-80.244848,40.168408],"type":"Point"}
}