{
  "type": "Feature",
  "properties": {
    "iso:country":"US",
    "sg:address":"301 Wood St",
    "sg:city":"Bristol",
    "sg:classifiers":[
        {
            "category":"Social Services",
            "subcategory":"Adult Care",
            "type":"Services"
        },
        {
            "category":"Social Services",
            "type":"Services"
        }
    ],
    "sg:phone":"+1 215 788 9238",
    "sg:postcode":"19007",
    "sg:province":"PA",
    "sg:tags":[
        "organization",
        "senior",
        "association",
        "citizen"
    ],
    "wof:name":"Bucks County Assn For Retired",
    "wof:placetype":"venue"
},
  "geometry": {"coordinates":[-74.85500999999999,40.097887],"type":"Point"}
}