{
  "type": "Feature",
  "properties": {
    "addr:full":"5741 E Texas Rd East Texas PA 18046",
    "addr:housenumber":"5741",
    "addr:postcode":"pa 18046",
    "addr:street":"E Texas Rd",
    "iso:country":"US",
    "sg:address":"5741 E Texas Rd",
    "sg:city":"East Texas",
    "sg:classifiers":[
        {
            "category":"Personal",
            "subcategory":"Beauty Salon",
            "type":"Services"
        }
    ],
    "sg:phone":"+1 610 366 9399",
    "sg:postcode":"18046",
    "sg:province":"PA",
    "wof:name":"Hair Etc",
    "wof:placetype":"venue"
},
  "geometry": {"coordinates":[-75.560506,40.548219],"type":"Point"}
}