{
  "type": "Feature",
  "properties": {
    "addr:full":"4309 Ludlow St Philadelphia PA 19104",
    "addr:housenumber":"4309",
    "addr:postcode":"19104",
    "addr:street":"Ludlow St",
    "iso:country":"US",
    "sg:address":"4309 Ludlow St",
    "sg:city":"Philadelphia",
    "sg:classifiers":[
        {
            "category":"Building & Trades",
            "subcategory":"Locksmith",
            "type":"Services"
        }
    ],
    "sg:phone":"+1 267 354 5023",
    "sg:postcode":"19104",
    "sg:province":"PA",
    "sg:tags":[
        "key"
    ],
    "wof:name":"1 24 7 Aalways Locksmith",
    "wof:placetype":"venue"
},
  "geometry": {"coordinates":[-75.20836300000001,39.957289],"type":"Point"}
}