{
  "type": "Feature",
  "properties": {
    "addr:full":"1110 Bethlehem Pike Montgomeryville PA 18936",
    "addr:housenumber":"1110",
    "addr:postcode":"18936",
    "addr:street":"Bethlehem Pike",
    "iso:country":"US",
    "sg:address":"1110 Bethlehem Pike",
    "sg:city":"Montgomeryville",
    "sg:classifiers":[
        {
            "category":"Travel",
            "subcategory":"Hotels & Motels",
            "type":"Entertainment"
        }
    ],
    "sg:phone":"+1 267 468 0111",
    "sg:postcode":"18936",
    "sg:province":"PA",
    "wof:name":"Residence Inn",
    "wof:placetype":"venue"
},
  "geometry": {"coordinates":[-75.225899,40.212101],"type":"Point"}
}