{
  "type": "Feature",
  "properties": {
    "iso:country":"US",
    "sg:address":"322 Cranberry Rd",
    "sg:city":"Hazleton",
    "sg:classifiers":[
        {
            "category":"Autos & Motor Vehicles",
            "subcategory":"Auto Supplies",
            "type":"Retail Goods"
        },
        {
            "category":"Retail",
            "subcategory":"Auto Repair",
            "type":"Services"
        }
    ],
    "sg:phone":"+1 814 678 8328",
    "sg:postcode":"18202",
    "sg:province":"PA",
    "sg:tags":[
        "oil",
        "tire",
        "automobile",
        "accessory",
        "lube",
        "part",
        "supplies-used",
        "brake",
        "rebuilt"
    ],
    "sg:website":"http://www.sears.com/shc/s/v_10153_12605_Automotive?adCell=AH",
    "wof:name":"Sears Auto Center",
    "wof:placetype":"venue"
},
  "geometry": {"coordinates":[-75.99567,40.954228],"type":"Point"}
}