{
  "type": "Feature",
  "properties": {
    "iso:country":"US",
    "sg:address":"3289 Springview Rd",
    "sg:city":"Chambersburg",
    "sg:classifiers":[
        {
            "category":"Professional",
            "type":"Services"
        }
    ],
    "sg:phone":"+1   ",
    "sg:postcode":"17201",
    "sg:province":"PA",
    "wof:name":"Harmons Nursery",
    "wof:placetype":"venue"
},
  "geometry": {"coordinates":[-77.624077,39.888512],"type":"Point"}
}