{
  "type": "Feature",
  "properties": {
    "iso:country":"US",
    "sg:address":"733 Winter Park Dr",
    "sg:city":"Mars",
    "sg:classifiers":[
        {
            "category":"Manufacturing",
            "subcategory":"Rubber & Plastics",
            "type":"Manufacturing & Wholesale Goods"
        }
    ],
    "sg:phone":"+1   ",
    "sg:postcode":"16046",
    "sg:province":"PA",
    "sg:tags":[
        "product",
        "mfg"
    ],
    "wof:name":"Advanced Plastic Systems Inc",
    "wof:placetype":"venue"
},
  "geometry": {"coordinates":[-80.044749,40.685758],"type":"Point"}
}