{
  "type": "Feature",
  "properties": {
    "addr:full":"1228 N 5th St Perkasie PA 18944",
    "addr:housenumber":"1228",
    "addr:postcode":"18944",
    "addr:street":"N 5Th St",
    "iso:country":"US",
    "sg:address":"1228 N 5th St",
    "sg:city":"Perkasie",
    "sg:classifiers":[
        {
            "category":"Education",
            "subcategory":"School",
            "type":"Public Place"
        }
    ],
    "sg:phone":"+1   ",
    "sg:postcode":"18944",
    "sg:province":"PA",
    "wof:name":"Pennrdge Upper Sr Hs Media Ctr",
    "wof:placetype":"venue"
},
  "geometry": {"coordinates":[-75.277497,40.383053],"type":"Point"}
}