{
  "type": "Feature",
  "properties": {
    "iso:country":"US",
    "sg:address":"89 Cross Key Rd",
    "sg:city":"Bernville",
    "sg:classifiers":[
        {
            "category":"Building & Trades",
            "subcategory":"Construction",
            "type":"Services"
        }
    ],
    "sg:phone":"+1 610 488 0239",
    "sg:postcode":"19506",
    "sg:province":"PA",
    "sg:tags":[
        "home",
        "improvement"
    ],
    "wof:name":"Top Quality Remodeling",
    "wof:placetype":"venue"
},
  "geometry": {"coordinates":[-76.169951,40.417436],"type":"Point"}
}