{
  "type": "Feature",
  "properties": {
    "addr:full":"2471 State Rte 737 Kempton PA 19529",
    "addr:housenumber":"2471",
    "addr:postcode":"19529",
    "addr:street":"State Rte 737",
    "iso:country":"US",
    "sg:address":"2471 State Rte 737",
    "sg:city":"Kempton",
    "sg:classifiers":[
        {
            "category":"Manufacturing",
            "subcategory":"Tools & Machinery",
            "type":"Manufacturing & Wholesale Goods"
        }
    ],
    "sg:phone":"+1   ",
    "sg:postcode":"19529",
    "sg:province":"PA",
    "sg:tags":[
        "lighting",
        "fixture",
        "mfg"
    ],
    "wof:name":"David DImperio Inc",
    "wof:placetype":"venue"
},
  "geometry": {"coordinates":[-75.819394,40.619745],"type":"Point"}
}