{
  "type": "Feature",
  "properties": {
    "addr:full":"712 Unity Center Rd Plum PA 15239",
    "addr:housenumber":"712",
    "addr:postcode":"15239",
    "addr:street":"Unity Center Rd",
    "iso:country":"US",
    "sg:address":"712 Unity Center Rd",
    "sg:city":"Plum",
    "sg:classifiers":[
        {
            "category":"Retail",
            "subcategory":"Auto Repair",
            "type":"Services"
        }
    ],
    "sg:phone":"+1 412 798 3600",
    "sg:postcode":"15239",
    "sg:province":"PA",
    "sg:tags":[
        "repairing",
        "automobile"
    ],
    "wof:name":"Plum Automotive Svc Ctr",
    "wof:placetype":"venue"
},
  "geometry": {"coordinates":[-79.76882500000001,40.485229],"type":"Point"}
}