{
  "type": "Feature",
  "properties": {
    "iso:country":"US",
    "sg:address":"256 3rd St",
    "sg:city":"Hanover",
    "sg:classifiers":[
        {
            "category":"Real Estate",
            "subcategory":"Real Estate Agent",
            "type":"Services"
        }
    ],
    "sg:phone":"+1   ",
    "sg:postcode":"17331",
    "sg:province":"PA",
    "wof:name":"Golden Realty Company",
    "wof:placetype":"venue"
},
  "geometry": {"coordinates":[-76.996686,39.804822],"type":"Point"}
}