{
  "type": "Feature",
  "properties": {
    "iso:country":"US",
    "sg:address":"1362 Naamans Creek Rd",
    "sg:city":"Marcus Hook",
    "sg:classifiers":[
        {
            "category":"Shopping",
            "type":"Retail Goods"
        }
    ],
    "sg:phone":"+1 610 485 2668",
    "sg:postcode":"19061",
    "sg:province":"PA",
    "sg:tags":[
        "shop",
        "candle",
        "gift"
    ],
    "wof:name":"Laaken's Candles & Collectible",
    "wof:placetype":"venue"
},
  "geometry": {"coordinates":[-75.498728,39.840042],"type":"Point"}
}