{
  "type": "Feature",
  "properties": {
    "iso:country":"US",
    "sg:address":"485 Fairview Chapel Rd",
    "sg:city":"Birdsboro",
    "sg:classifiers":[
        {
            "category":"Manufacturing",
            "subcategory":"Tools & Machinery",
            "type":"Manufacturing & Wholesale Goods"
        }
    ],
    "sg:phone":"+1 610 404 1940",
    "sg:postcode":"19508",
    "sg:province":"PA",
    "sg:tags":[
        "machine",
        "shop"
    ],
    "wof:name":"H & K Turning",
    "wof:placetype":"venue"
},
  "geometry": {"coordinates":[-75.828553,40.279496],"type":"Point"}
}