{
  "type": "Feature",
  "properties": {
    "iso:country":"US",
    "sg:address":"1 S Penn Sq",
    "sg:city":"Philadelphia",
    "sg:classifiers":[
        {
            "category":"Professional",
            "subcategory":"Lawyer & Legal Services",
            "type":"Services"
        }
    ],
    "sg:phone":"+1 215 575 4400",
    "sg:postcode":"19107",
    "sg:province":"PA",
    "wof:name":"Schipske Timothy Atty",
    "wof:placetype":"venue"
},
  "geometry": {"coordinates":[-75.1632,39.950901],"type":"Point"}
}