{
  "type": "Feature",
  "properties": {
    "iso:country":"US",
    "sg:address":"160 E Street Rd",
    "sg:city":"Feasterville Trevose",
    "sg:classifiers":[
        {
            "category":"Coffee & Tea",
            "type":"Food & Drink"
        }
    ],
    "sg:menulink":"http://www.allmenus.com/pa/lower-southampton/125160-starbucks-coffee/menu/",
    "sg:phone":"+1 215 396 1082",
    "sg:postcode":"19053",
    "sg:province":"PA",
    "sg:tags":[
        "american"
    ],
    "wof:name":"Starbucks Coffee",
    "wof:placetype":"venue"
},
  "geometry": {"coordinates":[-74.998535,40.148477],"type":"Point"}
}