{
  "type": "Feature",
  "properties": {
    "iso:country":"US",
    "sg:address":"4286 Green Garden Rd",
    "sg:city":"Aliquippa",
    "sg:classifiers":[
        {
            "category":"Manufacturing",
            "subcategory":"Tools & Machinery",
            "type":"Manufacturing & Wholesale Goods"
        }
    ],
    "sg:phone":"+1 724 495 2449",
    "sg:postcode":"15001",
    "sg:province":"PA",
    "sg:tags":[
        "machine",
        "shop"
    ],
    "wof:name":"Paff Enterprises Machine",
    "wof:placetype":"venue"
},
  "geometry": {"coordinates":[-80.39002000000001,40.612594],"type":"Point"}
}