{
  "type": "Feature",
  "properties": {
    "iso:country":"US",
    "sg:address":"364 Wilmington Pike",
    "sg:city":"Glen Mills",
    "sg:classifiers":[
        {
            "category":"Shopping",
            "subcategory":"Crafts & Fabrics",
            "type":"Retail Goods"
        }
    ],
    "sg:phone":"+1 610 459 8580",
    "sg:postcode":"19342",
    "sg:province":"PA",
    "sg:tags":[
        "art",
        "supply"
    ],
    "sg:website":"www.strawberrysampler.com",
    "wof:name":"Strawberry Sampler Counted Cross Stitch",
    "wof:placetype":"venue"
},
  "geometry": {"coordinates":[-75.544155,39.863733],"type":"Point"}
}