{
  "type": "Feature",
  "properties": {
    "addr:full":"7727 Ridge Ave Philadelphia PA 19128",
    "addr:housenumber":"7727",
    "addr:postcode":"19128",
    "addr:street":"Ridge Ave",
    "iso:country":"US",
    "sg:address":"7727 Ridge Ave",
    "sg:city":"Philadelphia",
    "sg:classifiers":[
        {
            "category":"Retail",
            "subcategory":"Laundry & Dry Cleaning",
            "type":"Services"
        }
    ],
    "sg:phone":"+1 215 508 1419",
    "sg:postcode":"19128",
    "sg:province":"PA",
    "sg:tags":[
        "drycleaning",
        "plant",
        "cleaners"
    ],
    "wof:name":"Chelten Drive Thru Cleaners",
    "wof:placetype":"venue"
},
  "geometry": {"coordinates":[-75.236214,40.051004],"type":"Point"}
}