{
  "type": "Feature",
  "properties": {
    "iso:country":"US",
    "sg:address":"282 W Main St",
    "sg:city":"Elizabethville",
    "sg:classifiers":[
        {
            "category":"Health Services",
            "subcategory":"Doctor",
            "type":"Services"
        }
    ],
    "sg:phone":"+1 717 362 3371",
    "sg:postcode":"17023",
    "sg:province":"PA",
    "sg:tags":[
        "physician",
        "surgeon"
    ],
    "wof:name":"Kandra Fierer & Kuskin Assoc",
    "wof:placetype":"venue"
},
  "geometry": {"coordinates":[-76.819028,40.547705],"type":"Point"}
}