{
  "type": "Feature",
  "properties": {
    "iso:country":"US",
    "sg:address":"1921 Golden Mile Hwy",
    "sg:city":"Pittsburgh",
    "sg:classifiers":[
        {
            "category":"Retail",
            "subcategory":"Auto Repair",
            "type":"Services"
        }
    ],
    "sg:phone":"+1 412 247 1927",
    "sg:postcode":"15239",
    "sg:province":"PA",
    "sg:tags":[
        "repairing",
        "automobile"
    ],
    "wof:name":"Flynn's Tire & Svc Ctr",
    "wof:placetype":"venue"
},
  "geometry": {"coordinates":[-79.710167,40.456057],"type":"Point"}
}