{
  "type": "Feature",
  "properties": {
    "iso:country":"US",
    "sg:address":"366 Blue Valley Dr",
    "sg:city":"Bangor",
    "sg:classifiers":[
        {
            "category":"Personal",
            "subcategory":"Beauty Salon",
            "type":"Services"
        }
    ],
    "sg:phone":"+1 610 588 2543",
    "sg:postcode":"18013",
    "sg:province":"PA",
    "wof:name":"Patty's Styling Salon",
    "wof:placetype":"venue"
},
  "geometry": {"coordinates":[-75.2315,40.870781],"type":"Point"}
}