{
  "type": "Feature",
  "properties": {
    "iso:country":"US",
    "sg:address":"5111 Willow St",
    "sg:city":"Northampton",
    "sg:classifiers":[
        {
            "category":"Building & Trades",
            "subcategory":"Construction",
            "type":"Services"
        }
    ],
    "sg:phone":"+1   ",
    "sg:postcode":"18052",
    "sg:province":"PA",
    "sg:tags":[
        "hanging",
        "contractor"
    ],
    "wof:name":"Gregorys Gutters & Downspouts",
    "wof:placetype":"venue"
},
  "geometry": {"coordinates":[-75.510307,40.688484],"type":"Point"}
}