{
  "type": "Feature",
  "properties": {
    "iso:country":"US",
    "sg:address":"30 W Commerce St",
    "sg:city":"Shamokin",
    "sg:classifiers":[
        {
            "category":"Shopping",
            "subcategory":"Gifts & Souvenirs",
            "type":"Retail Goods"
        }
    ],
    "sg:phone":"+1 570 644 3932",
    "sg:postcode":"17872",
    "sg:province":"PA",
    "sg:tags":[
        "shop"
    ],
    "wof:name":"Fun Shop Administration",
    "wof:placetype":"venue"
},
  "geometry": {"coordinates":[-76.557743,40.791739],"type":"Point"}
}