{
  "type": "Feature",
  "properties": {
    "iso:country":"US",
    "sg:address":"375 Stayrook Rd",
    "sg:city":"Belleville",
    "sg:classifiers":[
        {
            "category":"Real Estate",
            "subcategory":"Real Estate Operator",
            "type":"Services"
        }
    ],
    "sg:phone":"+1   ",
    "sg:postcode":"17004",
    "sg:province":"PA",
    "sg:tags":[
        "property",
        "lessor"
    ],
    "wof:name":"Robert Stayrook Farm",
    "wof:placetype":"venue"
},
  "geometry": {"coordinates":[-77.72448199999999,40.616651],"type":"Point"}
}