{
  "type": "Feature",
  "properties": {
    "addr:full":"1149 Glasgow St Pottstown PA 19464",
    "addr:housenumber":"1149",
    "addr:postcode":"19464",
    "addr:street":"Glasgow St",
    "iso:country":"US",
    "sg:address":"1149 Glasgow St",
    "sg:city":"Pottstown",
    "sg:classifiers":[
        {
            "category":"Airport",
            "type":"Transportation"
        }
    ],
    "sg:phone":"+1 610 323 0320",
    "sg:postcode":"19464",
    "sg:province":"PA",
    "sg:tags":[
        "aircraft",
        "maintenance"
    ],
    "wof:name":"Witmer's Aircraft Svc",
    "wof:placetype":"venue"
},
  "geometry": {"coordinates":[-75.66503299999999,40.260942],"type":"Point"}
}