{
  "type": "Feature",
  "properties": {
    "iso:country":"US",
    "sg:address":"105 Field Crest Ln",
    "sg:city":"Gordonville",
    "sg:classifiers":[
        {
            "category":"Building & Trades",
            "subcategory":"Construction",
            "type":"Services"
        }
    ],
    "sg:phone":"+1   ",
    "sg:postcode":"17529",
    "sg:province":"PA",
    "sg:tags":[
        "contractor"
    ],
    "wof:name":"R L Petersheim Masonry",
    "wof:placetype":"venue"
},
  "geometry": {"coordinates":[-76.08056000000001,40.032392],"type":"Point"}
}