{
  "type": "Feature",
  "properties": {
    "iso:country":"US",
    "sg:address":"1837 E Lincoln Hwy",
    "sg:city":"Coatesville",
    "sg:classifiers":[
        {
            "category":"Restaurant",
            "type":"Food & Drink"
        }
    ],
    "sg:phone":"+1 610 384 2292",
    "sg:postcode":"19320",
    "sg:province":"PA",
    "sg:tags":[
        "grill",
        "bar",
        "pizza"
    ],
    "wof:name":"Little Anthony's Pizza & Grille",
    "wof:placetype":"venue"
},
  "geometry": {"coordinates":[-75.789293,39.988795],"type":"Point"}
}