{
  "type": "Feature",
  "properties": {
    "addr:full":"303 1/2 W Main St Lansdale PA 19446",
    "addr:housenumber":"303 1 / 2",
    "addr:postcode":"19446",
    "addr:street":"W Main St",
    "iso:country":"US",
    "sg:address":"303 1/2 W Main St",
    "sg:city":"Lansdale",
    "sg:classifiers":[
        {
            "category":"Shopping",
            "subcategory":"Beauty & Cosmetics",
            "type":"Retail Goods"
        },
        {
            "category":"Personal",
            "subcategory":"Skin Care",
            "type":"Services"
        }
    ],
    "sg:phone":"+1 267 879 1554",
    "sg:postcode":"19446",
    "sg:province":"PA",
    "sg:tags":[
        "supply"
    ],
    "sg:website":"greenstreetlux.com",
    "wof:name":"Green Street Luxuries",
    "wof:placetype":"venue"
},
  "geometry": {"coordinates":[-75.28364000000001,40.241897],"type":"Point"}
}