{
  "type": "Feature",
  "properties": {
    "iso:country":"US",
    "sg:address":"1421 W Carson St",
    "sg:city":"Pittsburgh",
    "sg:classifiers":[
        {
            "category":"Wholesale",
            "subcategory":"Chemicals & Plastics",
            "type":"Manufacturing & Wholesale Goods"
        }
    ],
    "sg:phone":"+1   ",
    "sg:postcode":"15204",
    "sg:province":"PA",
    "sg:tags":[
        "industrial",
        "gas"
    ],
    "wof:name":"Lab Source",
    "wof:placetype":"venue"
},
  "geometry": {"coordinates":[-80.02721200000001,40.443466],"type":"Point"}
}