{
  "type": "Feature",
  "properties": {
    "iso:country":"US",
    "sg:address":"6873 Penn Ave",
    "sg:city":"Wernersville",
    "sg:classifiers":[
        {
            "category":"Manufacturing",
            "subcategory":"Toys & Sporting Goods",
            "type":"Manufacturing & Wholesale Goods"
        }
    ],
    "sg:phone":"+1 610 693 9422",
    "sg:postcode":"19565",
    "sg:province":"PA",
    "sg:tags":[
        "store"
    ],
    "wof:name":"Locker Room Inc",
    "wof:placetype":"venue"
},
  "geometry": {"coordinates":[-76.11575499999999,40.342779],"type":"Point"}
}