{
  "type": "Feature",
  "properties": {
    "iso:country":"US",
    "sg:address":"375 Cherryville Rd",
    "sg:city":"Northampton",
    "sg:classifiers":[
        {
            "category":"Real Estate",
            "subcategory":"Real Estate Operator",
            "type":"Services"
        }
    ],
    "sg:phone":"+1   ",
    "sg:postcode":"18067",
    "sg:province":"PA",
    "sg:tags":[
        "vegetable",
        "operation",
        "fruit",
        "market",
        "retail"
    ],
    "wof:name":"Northampton Farmers Market",
    "wof:placetype":"venue"
},
  "geometry": {"coordinates":[-75.52914699999999,40.739187],"type":"Point"}
}