{
  "type": "Feature",
  "properties": {
    "addr:full":"660 Iroquois St Emmaus PA 18049",
    "addr:housenumber":"660",
    "addr:postcode":"18049",
    "addr:street":"Iroquois St",
    "iso:country":"US",
    "sg:address":"660 Iroquois St",
    "sg:city":"Emmaus",
    "sg:classifiers":[
        {
            "category":"Shopping",
            "subcategory":"Gifts & Souvenirs",
            "type":"Retail Goods"
        }
    ],
    "sg:phone":"+1   ",
    "sg:postcode":"18049",
    "sg:province":"PA",
    "wof:name":"Woven Blessings",
    "wof:placetype":"venue"
},
  "geometry": {"coordinates":[-75.50767999999999,40.540028],"type":"Point"}
}