{
  "type": "Feature",
  "properties": {
    "iso:country":"US",
    "sg:address":"103 Kelly Dr",
    "sg:city":"Valencia",
    "sg:classifiers":[
        {
            "category":"Railroad",
            "type":"Transportation"
        }
    ],
    "sg:phone":"+1   ",
    "sg:postcode":"16059",
    "sg:province":"PA",
    "sg:tags":[
        "operator",
        "line"
    ],
    "wof:name":"Norfolk Southern Rlwy Copmany",
    "wof:placetype":"venue"
},
  "geometry": {"coordinates":[-79.91103099999999,40.716298],"type":"Point"}
}