{
  "type": "Feature",
  "properties": {
    "iso:country":"US",
    "sg:address":"429 4th Ave Ste 1600",
    "sg:city":"Pittsburgh",
    "sg:classifiers":[
        {
            "category":"Professional",
            "subcategory":"Lawyer & Legal Services",
            "type":"Services"
        }
    ],
    "sg:phone":"+1 412 434 6211",
    "sg:postcode":"15219",
    "sg:province":"PA",
    "wof:name":"Coster James L Attorney",
    "wof:placetype":"venue"
},
  "geometry": {"coordinates":[-79.998596,40.4384],"type":"Point"}
}