{
  "type": "Feature",
  "properties": {
    "iso:country":"US",
    "sg:address":"18 Briarcliff Rd",
    "sg:city":"Elizabethtown",
    "sg:classifiers":[
        {
            "category":"Personal",
            "subcategory":"Beauty Salon",
            "type":"Services"
        }
    ],
    "sg:phone":"+1 717 367 4366",
    "sg:postcode":"17022",
    "sg:province":"PA",
    "wof:name":"Nancy Russ Styling Salon",
    "wof:placetype":"venue"
},
  "geometry": {"coordinates":[-76.588336,40.141241],"type":"Point"}
}