{
  "type": "Feature",
  "properties": {
    "iso:country":"US",
    "sg:address":"1369 Dilworthtown Xing",
    "sg:city":"West Chester",
    "sg:classifiers":[
        {
            "category":"Restaurant",
            "type":"Food & Drink"
        }
    ],
    "sg:phone":"+1 610 399 8589",
    "sg:postcode":"19382",
    "sg:province":"PA",
    "sg:tags":[
        "sushi",
        "bar",
        "japanese"
    ],
    "wof:name":"Fuji Fusion Steak House Hibachi & Sushi",
    "wof:placetype":"venue"
},
  "geometry": {"coordinates":[-75.544511,39.910749],"type":"Point"}
}