{
  "type": "Feature",
  "properties": {
    "iso:country":"US",
    "sg:address":"225 Clever Rd",
    "sg:city":"Mc Kees Rocks",
    "sg:classifiers":[
        {
            "category":"Restaurant",
            "type":"Food & Drink"
        }
    ],
    "sg:phone":"+1 412 788 1260",
    "sg:postcode":"15136",
    "sg:province":"PA",
    "sg:tags":[
        "eating"
    ],
    "wof:name":"Clever Cone Corner",
    "wof:placetype":"venue"
},
  "geometry": {"coordinates":[-80.126803,40.468699],"type":"Point"}
}