{
  "type": "Feature",
  "properties": {
    "addr:full":"398 S Duke St Millersville PA 17551",
    "addr:housenumber":"398",
    "addr:postcode":"17551",
    "addr:street":"S Duke St",
    "iso:country":"US",
    "sg:address":"398 S Duke St",
    "sg:city":"Millersville",
    "sg:classifiers":[
        {
            "category":"Farming",
            "subcategory":"Dairy Farm",
            "type":"Manufacturing & Wholesale Goods"
        }
    ],
    "sg:phone":"+1   ",
    "sg:postcode":"17551",
    "sg:province":"PA",
    "wof:name":"Ken Shertzer",
    "wof:placetype":"venue"
},
  "geometry": {"coordinates":[-76.360069,39.989819],"type":"Point"}
}