{
  "type": "Feature",
  "properties": {
    "iso:country":"US",
    "sg:address":"355 W Main St",
    "sg:city":"Bath",
    "sg:classifiers":[
        {
            "category":"Health Services",
            "subcategory":"Health Practitioner",
            "type":"Services"
        }
    ],
    "sg:phone":"+1 610 837 9848",
    "sg:postcode":"18014",
    "sg:province":"PA",
    "sg:tags":[
        "therapist",
        "physical"
    ],
    "wof:name":"Hands To Heart",
    "wof:placetype":"venue"
},
  "geometry": {"coordinates":[-75.397948,40.726749],"type":"Point"}
}