{
  "type": "Feature",
  "properties": {
    "iso:country":"US",
    "sg:address":"927 Russell Dr",
    "sg:city":"Lebanon",
    "sg:classifiers":[
        {
            "category":"Health Services",
            "subcategory":"Doctor",
            "type":"Services"
        },
        {
            "category":"Wholesale",
            "subcategory":"Medical Equipment & Supplies",
            "type":"Manufacturing & Wholesale Goods"
        }
    ],
    "sg:phone":"+1 717 274 9775",
    "sg:postcode":"17042",
    "sg:province":"PA",
    "sg:tags":[
        "physician",
        "ear",
        "immunology",
        "reconstructive",
        "allergy",
        "surgeons",
        "cosmetic",
        "hearing",
        "otorhinolaryngology",
        "throat",
        "device",
        "nose",
        "assistive",
        "aid",
        "surgery",
        "plastic"
    ],
    "wof:name":"Melnick, Moffitt & Mesaros ENT Associates",
    "wof:placetype":"venue"
},
  "geometry": {"coordinates":[-76.420284,40.3161],"type":"Point"}
}