{
  "type": "Feature",
  "properties": {
    "addr:full":"493 State Rte 66 Leechburg PA 15656",
    "addr:housenumber":"493",
    "addr:postcode":"15656",
    "addr:street":"State Rte 66",
    "iso:country":"US",
    "sg:address":"493 State Rte 66",
    "sg:city":"Leechburg",
    "sg:classifiers":[
        {
            "category":"Social Services",
            "subcategory":"Child Care",
            "type":"Services"
        }
    ],
    "sg:phone":"+1 724 845 1755",
    "sg:postcode":"15656",
    "sg:province":"PA",
    "wof:name":"ABC Academy",
    "wof:placetype":"venue"
},
  "geometry": {"coordinates":[-79.594841,40.631406],"type":"Point"}
}