{
  "type": "Feature",
  "properties": {
    "addr:full":"425 N Craig St Pittsburgh PA 15213",
    "addr:housenumber":"425",
    "addr:postcode":"15213",
    "addr:street":"N Craig St",
    "iso:country":"US",
    "sg:address":"425 N Craig St",
    "sg:city":"Pittsburgh",
    "sg:classifiers":[
        {
            "category":"Real Estate",
            "subcategory":"Real Estate Agent",
            "type":"Services"
        }
    ],
    "sg:phone":"+1 412 391 1900",
    "sg:postcode":"15213",
    "sg:province":"PA",
    "sg:tags":[
        "consulting",
        "management",
        "leasing",
        "agency"
    ],
    "wof:name":"Arnheim & Neely Inc",
    "wof:placetype":"venue"
},
  "geometry": {"coordinates":[-79.954466,40.455633],"type":"Point"}
}