{
  "type": "Feature",
  "properties": {
    "iso:country":"US",
    "sg:address":"2050 Blue Mountain Pkwy",
    "sg:city":"Harrisburg",
    "sg:classifiers":[
        {
            "category":"Professional",
            "type":"Services"
        }
    ],
    "sg:phone":"+1   ",
    "sg:postcode":"17112",
    "sg:province":"PA",
    "wof:name":"Shawn H Wills Custom",
    "wof:placetype":"venue"
},
  "geometry": {"coordinates":[-76.81794499999999,40.365249],"type":"Point"}
}