{
  "type": "Feature",
  "properties": {
    "iso:country":"US",
    "sg:address":"703 Market St",
    "sg:city":"Kingston",
    "sg:classifiers":[
        {
            "category":"Personal",
            "type":"Services"
        }
    ],
    "sg:phone":"+1 570 331 0531",
    "sg:postcode":"18704",
    "sg:province":"PA",
    "sg:tags":[
        "program",
        "physical",
        "exercise",
        "fitness"
    ],
    "wof:name":"Sheri Pilates Studio",
    "wof:placetype":"venue"
},
  "geometry": {"coordinates":[-75.897954,41.262673],"type":"Point"}
}