{
  "type": "Feature",
  "properties": {
    "iso:country":"US",
    "sg:address":"2056 Springwood Rd",
    "sg:city":"York",
    "sg:classifiers":[
        {
            "category":"Insurance",
            "subcategory":"Insurance Agent",
            "type":"Services"
        }
    ],
    "sg:phone":"+1 717 812 1982",
    "sg:postcode":"17403",
    "sg:province":"PA",
    "wof:name":"Patton Group",
    "wof:placetype":"venue"
},
  "geometry": {"coordinates":[-76.693034,39.939021],"type":"Point"}
}