{
  "type": "Feature",
  "properties": {
    "iso:country":"US",
    "sg:address":"125 W Station Square Dr",
    "sg:city":"Pittsburgh",
    "sg:classifiers":[
        {
            "category":"Wholesale",
            "subcategory":"Office Equipment",
            "type":"Manufacturing & Wholesale Goods"
        },
        {
            "category":"Shopping",
            "subcategory":"Computers & Home Electronics",
            "type":"Retail Goods"
        }
    ],
    "sg:phone":"+1 412 281 6088",
    "sg:postcode":"15219",
    "sg:province":"PA",
    "sg:tags":[
        "typewriter",
        "furniture"
    ],
    "wof:name":"Snyder International",
    "wof:placetype":"venue"
},
  "geometry": {"coordinates":[-80.01339,40.438126],"type":"Point"}
}