{
  "type": "Feature",
  "properties": {
    "iso:country":"US",
    "sg:address":"304 W Pike St",
    "sg:city":"Canonsburg",
    "sg:classifiers":[
        {
            "category":"Retail",
            "subcategory":"Funeral Services",
            "type":"Services"
        }
    ],
    "sg:phone":"+1 724 745 8120",
    "sg:postcode":"15317",
    "sg:province":"PA",
    "sg:tags":[
        "director",
        "cemetery"
    ],
    "sg:website":"www.salandrafuneralserviceinc.com",
    "wof:name":"Salandra Funeral Service Inc",
    "wof:placetype":"venue"
},
  "geometry": {"coordinates":[-80.194298,40.257999],"type":"Point"}
}