{
  "type": "Feature",
  "properties": {
    "iso:country":"US",
    "sg:address":"839 Evans City Rd",
    "sg:city":"Renfrew",
    "sg:classifiers":[
        {
            "category":"Manufacturing",
            "subcategory":"Motor Vehicles & Parts",
            "type":"Manufacturing & Wholesale Goods"
        }
    ],
    "sg:phone":"+1 724 789 9194",
    "sg:postcode":"16053",
    "sg:province":"PA",
    "sg:tags":[
        "body",
        "repair",
        "truck",
        "trailer",
        "mfg"
    ],
    "wof:name":"Viking-Spirit Trailers",
    "wof:placetype":"venue"
},
  "geometry": {"coordinates":[-79.984914,40.850473],"type":"Point"}
}