{
  "type": "Feature",
  "properties": {
    "iso:country":"US",
    "sg:address":"1302 Rte 30",
    "sg:city":"Clinton",
    "sg:classifiers":[
        {
            "category":"Social Services",
            "subcategory":"Adult Care",
            "type":"Services"
        }
    ],
    "sg:phone":"+1   ",
    "sg:postcode":"15026",
    "sg:province":"PA",
    "sg:tags":[
        "handicapped",
        "residential",
        "mentally",
        "for",
        "child"
    ],
    "wof:name":"Allegheny Valley School",
    "wof:placetype":"venue"
},
  "geometry": {"coordinates":[-80.29722,40.491241],"type":"Point"}
}