{
  "type": "Feature",
  "properties": {
    "iso:country":"US",
    "sg:address":"1923 Paint Mills Rd",
    "sg:city":"Shippenville",
    "sg:classifiers":[
        {
            "category":"Retail",
            "subcategory":"Portrait Studio",
            "type":"Services"
        }
    ],
    "sg:phone":"+1 814 782 6339",
    "sg:postcode":"16254",
    "sg:province":"PA",
    "sg:tags":[
        "photographer"
    ],
    "wof:name":"Dimensions Photography",
    "wof:placetype":"venue"
},
  "geometry": {"coordinates":[-79.420728,41.267243],"type":"Point"}
}