{
  "type": "Feature",
  "properties": {
    "iso:country":"US",
    "sg:address":"3140 Ridge Pike",
    "sg:city":"Norristown",
    "sg:classifiers":[
        {
            "category":"Restaurant",
            "type":"Food & Drink"
        }
    ],
    "sg:phone":"+1   ",
    "sg:postcode":"19403",
    "sg:province":"PA",
    "sg:tags":[
        "eating"
    ],
    "wof:name":"Jj Barbeque House",
    "wof:placetype":"venue"
},
  "geometry": {"coordinates":[-75.403812,40.157046],"type":"Point"}
}