{
  "type": "Feature",
  "properties": {
    "addr:full":"1301 12th St Altoona PA 16601",
    "addr:housenumber":"1301",
    "addr:postcode":"16601",
    "addr:street":"12Th St",
    "iso:country":"US",
    "sg:address":"1301 12th St",
    "sg:city":"Altoona",
    "sg:classifiers":[
        {
            "category":"Government",
            "subcategory":"Office",
            "type":"Public Place"
        }
    ],
    "sg:phone":"+1 814 949 2405",
    "sg:postcode":"16601",
    "sg:province":"PA",
    "sg:tags":[
        "city",
        "taxation"
    ],
    "wof:name":"Finance Dept",
    "wof:placetype":"venue"
},
  "geometry": {"coordinates":[-78.402699,40.517748],"type":"Point"}
}