{
  "type": "Feature",
  "properties": {
    "iso:country":"US",
    "sg:address":"37 Vernon Dr",
    "sg:city":"Pittsburgh",
    "sg:classifiers":[
        {
            "category":"Shopping",
            "subcategory":"Computers & Home Electronics",
            "type":"Retail Goods"
        }
    ],
    "sg:phone":"+1   ",
    "sg:postcode":"15228",
    "sg:province":"PA",
    "wof:name":"Whitford Assocs",
    "wof:placetype":"venue"
},
  "geometry": {"coordinates":[-80.053213,40.371331],"type":"Point"}
}