{
  "type": "Feature",
  "properties": {
    "iso:country":"US",
    "sg:address":"18 Bethany Dr",
    "sg:city":"Pittsburgh",
    "sg:classifiers":[
        {
            "category":"Professional",
            "subcategory":"Computer Services",
            "type":"Services"
        },
        {
            "category":"Shopping",
            "subcategory":"Computers & Home Electronics",
            "type":"Retail Goods"
        }
    ],
    "sg:phone":"+1 412 781 9330",
    "sg:postcode":"15215",
    "sg:province":"PA",
    "sg:tags":[
        "prepackaged",
        "custom",
        "programing",
        "software"
    ],
    "sg:website":"www.dotnetusa.com",
    "wof:name":"Dotnet Software",
    "wof:placetype":"venue"
},
  "geometry": {"coordinates":[-79.938947,40.504283],"type":"Point"}
}