{
  "type": "Feature",
  "properties": {
    "addr:full":"4439 Oregon Pike Ephrata PA 17522",
    "addr:housenumber":"4439",
    "addr:postcode":"17522",
    "addr:street":"Oregon Pike",
    "iso:country":"US",
    "sg:address":"4439 Oregon Pike",
    "sg:city":"Ephrata",
    "sg:classifiers":[
        {
            "category":"Autos & Motor Vehicles",
            "subcategory":"Automobile Sales",
            "type":"Retail Goods"
        }
    ],
    "sg:phone":"+1   ",
    "sg:postcode":"17522",
    "sg:province":"PA",
    "sg:tags":[
        "used"
    ],
    "wof:name":"TNT Auto Sales",
    "wof:placetype":"venue"
},
  "geometry": {"coordinates":[-76.210955,40.139707],"type":"Point"}
}