{
  "type": "Feature",
  "properties": {
    "addr:full":"1180 Ben Franklin Hwy E Douglassville PA 19518",
    "addr:housenumber":"1180",
    "addr:postcode":"19518",
    "addr:street":"Ben Franklin Hwy E",
    "iso:country":"US",
    "sg:address":"1180 Ben Franklin Hwy E",
    "sg:city":"Douglassville",
    "sg:classifiers":[
        {
            "category":"Professional",
            "type":"Services"
        }
    ],
    "sg:phone":"+1 610 385 0388",
    "sg:postcode":"19518",
    "sg:province":"PA",
    "wof:name":"Villa At Morlatton",
    "wof:placetype":"venue"
},
  "geometry": {"coordinates":[-75.72877099999999,40.257625],"type":"Point"}
}