{
  "type": "Feature",
  "properties": {
    "iso:country":"US",
    "sg:address":"900 Forty Foot Rd",
    "sg:city":"Hatfield",
    "sg:classifiers":[
        {
            "category":"Social Services",
            "subcategory":"Adult Care",
            "type":"Services"
        }
    ],
    "sg:phone":"+1 267 328 6615",
    "sg:postcode":"19440",
    "sg:province":"PA",
    "sg:tags":[
        "slitting",
        "cutting"
    ],
    "wof:name":"North East Cutting Services",
    "wof:placetype":"venue"
},
  "geometry": {"coordinates":[-75.309319,40.272881],"type":"Point"}
}