{
  "type": "Feature",
  "properties": {
    "iso:country":"US",
    "sg:address":"11 S Belmont St",
    "sg:city":"York",
    "sg:classifiers":[
        {
            "category":"Professional",
            "subcategory":"Detective & Security Services",
            "type":"Services"
        }
    ],
    "sg:phone":"+1 717 846 1981",
    "sg:postcode":"17403",
    "sg:province":"PA",
    "sg:tags":[
        "system"
    ],
    "wof:name":"Berkshire Systems Group Inc",
    "wof:placetype":"venue"
},
  "geometry": {"coordinates":[-76.695143,39.972241],"type":"Point"}
}