{
  "type": "Feature",
  "properties": {
    "addr:full":"2154 E Lake Rd Erie PA 16511",
    "addr:housenumber":"2154",
    "addr:postcode":"16511",
    "addr:street":"E Lake Rd",
    "iso:country":"US",
    "sg:address":"2154 E Lake Rd",
    "sg:city":"Erie",
    "sg:classifiers":[
        {
            "category":"Banks & Credit Unions",
            "subcategory":"Bank",
            "type":"Services"
        }
    ],
    "sg:phone":"+1 814 456 6231",
    "sg:postcode":"16511",
    "sg:province":"PA",
    "sg:website":"www.eriegeempfcu.org",
    "wof:name":"Erie General Electric Fed CU",
    "wof:placetype":"venue"
},
  "geometry": {"coordinates":[-80.03798399999999,42.147312],"type":"Point"}
}