{
  "type": "Feature",
  "properties": {
    "iso:country":"US",
    "sg:address":"15 Alinda Ln",
    "sg:city":"Stroudsburg",
    "sg:classifiers":[
        {
            "category":"Building & Trades",
            "subcategory":"Plumbing",
            "type":"Services"
        }
    ],
    "sg:phone":"+1 570 476 7672",
    "sg:postcode":"18360",
    "sg:province":"PA",
    "sg:tags":[
        "contractor"
    ],
    "wof:name":"John E Snyder Inc",
    "wof:placetype":"venue"
},
  "geometry": {"coordinates":[-75.268407,41.01486],"type":"Point"}
}