{
  "type": "Feature",
  "properties": {
    "addr:full":"439 Franklin Ave Aliquippa PA 15001",
    "addr:housenumber":"439",
    "addr:postcode":"15001",
    "addr:street":"Franklin Ave",
    "iso:country":"US",
    "sg:address":"439 Franklin Ave",
    "sg:city":"Aliquippa",
    "sg:classifiers":[
        {
            "category":"Personal",
            "subcategory":"Beauty Salon",
            "type":"Services"
        }
    ],
    "sg:phone":"+1   ",
    "sg:postcode":"15001",
    "sg:province":"PA",
    "sg:tags":[
        "shop"
    ],
    "wof:name":"Taras Tips & Toes",
    "wof:placetype":"venue"
},
  "geometry": {"coordinates":[-80.24798800000001,40.615779],"type":"Point"}
}