{
  "type": "Feature",
  "properties": {
    "iso:country":"US",
    "sg:address":"1510 Fernwood Rd",
    "sg:city":"Slatington",
    "sg:classifiers":[
        {
            "category":"Building & Trades",
            "subcategory":"Construction",
            "type":"Services"
        }
    ],
    "sg:phone":"+1   ",
    "sg:postcode":"18080",
    "sg:province":"PA",
    "sg:tags":[
        "house"
    ],
    "wof:name":"Homes By Saeger Inc",
    "wof:placetype":"venue"
},
  "geometry": {"coordinates":[-75.617159,40.765733],"type":"Point"}
}