{
  "type": "Feature",
  "properties": {
    "iso:country":"US",
    "sg:address":"2828 Ridge Pike",
    "sg:city":"Norristown",
    "sg:classifiers":[
        {
            "category":"Food & Beverages",
            "subcategory":"Groceries & Convenience Stores",
            "type":"Retail Goods"
        }
    ],
    "sg:phone":"+1   ",
    "sg:postcode":"19403",
    "sg:province":"PA",
    "wof:name":"New Shree Ambe Groceries",
    "wof:placetype":"venue"
},
  "geometry": {"coordinates":[-75.396564,40.148367],"type":"Point"}
}