{
  "type": "Feature",
  "properties": {
    "iso:country":"US",
    "sg:address":"217 South St",
    "sg:city":"Philadelphia",
    "sg:classifiers":[
        {
            "category":"Shopping",
            "type":"Retail Goods"
        }
    ],
    "sg:phone":"+1 215 925 3688",
    "sg:postcode":"19147",
    "sg:province":"PA",
    "sg:tags":[
        "picture",
        "frame",
        "art",
        "gallery",
        "merchandise"
    ],
    "wof:name":"Millennium Art Gallery",
    "wof:placetype":"venue"
},
  "geometry": {"coordinates":[-75.146202,39.9412],"type":"Point"}
}