{
  "type": "Feature",
  "properties": {
    "iso:country":"US",
    "sg:address":"1405 McFarland Rd",
    "sg:city":"Pittsburgh",
    "sg:classifiers":[
        {
            "category":"Banks & Credit Unions",
            "subcategory":"Investment Brokerage",
            "type":"Services"
        }
    ],
    "sg:phone":"+1 412 341 1144",
    "sg:postcode":"15216",
    "sg:province":"PA",
    "sg:tags":[
        "stock",
        "bond"
    ],
    "sg:website":"www.arthurslestrange.com",
    "wof:name":"Arthurs Lestrange",
    "wof:placetype":"venue"
},
  "geometry": {"coordinates":[-80.04159799999999,40.389548],"type":"Point"}
}