{
  "type": "Feature",
  "properties": {
    "iso:country":"US",
    "sg:address":"1424 Banksville Rd # 1",
    "sg:city":"Pittsburgh",
    "sg:classifiers":[
        {
            "category":"Retail",
            "subcategory":"Auto Repair",
            "type":"Services"
        }
    ],
    "sg:phone":"+1 412 563 6000",
    "sg:postcode":"15216",
    "sg:province":"PA",
    "sg:tags":[
        "body",
        "shop"
    ],
    "wof:name":"Arlington Auto Body Service",
    "wof:placetype":"venue"
},
  "geometry": {"coordinates":[-80.030296,40.414501],"type":"Point"}
}