{
  "type": "Feature",
  "properties": {
    "addr:full":"704 Oakland Ave Greensburg PA 15601",
    "addr:housenumber":"704",
    "addr:postcode":"15601",
    "addr:street":"Oakland Ave",
    "iso:country":"US",
    "sg:address":"704 Oakland Ave",
    "sg:city":"Greensburg",
    "sg:classifiers":[
        {
            "category":"Building & Trades",
            "subcategory":"Plumbing",
            "type":"Services"
        }
    ],
    "sg:phone":"+1 724 838 0135",
    "sg:postcode":"15601",
    "sg:province":"PA",
    "sg:tags":[
        "plumber",
        "contractor"
    ],
    "wof:name":"Short's Plumbing",
    "wof:placetype":"venue"
},
  "geometry": {"coordinates":[-79.545687,40.293246],"type":"Point"}
}