{
  "type": "Feature",
  "properties": {
    "iso:country":"US",
    "sg:address":"2615 Dekalb Pike",
    "sg:city":"Norristown",
    "sg:classifiers":[
        {
            "category":"Professional",
            "type":"Services"
        }
    ],
    "sg:phone":"+1   ",
    "sg:postcode":"19401",
    "sg:province":"PA",
    "wof:name":"Jane Mork Gibson",
    "wof:placetype":"venue"
},
  "geometry": {"coordinates":[-75.312707,40.141659],"type":"Point"}
}