{
  "type": "Feature",
  "properties": {
    "iso:country":"US",
    "sg:address":"307 E Church Rd",
    "sg:city":"King Of Prussia",
    "sg:classifiers":[
        {
            "category":"Professional",
            "type":"Services"
        }
    ],
    "sg:phone":"+1   ",
    "sg:postcode":"19406",
    "sg:province":"PA",
    "wof:name":"Rag & Bone Inc",
    "wof:placetype":"venue"
},
  "geometry": {"coordinates":[-75.34565499999999,40.089865],"type":"Point"}
}