{
  "type": "Feature",
  "properties": {
    "iso:country":"US",
    "sg:address":"930 W Airy St",
    "sg:city":"Norristown",
    "sg:classifiers":[
        {
            "category":"Bars & Pubs",
            "type":"Food & Drink"
        }
    ],
    "sg:phone":"+1 610 292 8757",
    "sg:postcode":"19401",
    "sg:province":"PA",
    "sg:tags":[
        "drinking"
    ],
    "wof:name":"Rahill's Tavern",
    "wof:placetype":"venue"
},
  "geometry": {"coordinates":[-75.35531,40.12047],"type":"Point"}
}