{
  "type": "Feature",
  "properties": {
    "iso:country":"US",
    "sg:address":"4424 Spruce St",
    "sg:city":"Hokendauqua",
    "sg:classifiers":[
        {
            "category":"Real Estate",
            "subcategory":"Surveying",
            "type":"Services"
        }
    ],
    "sg:phone":"+1 610 262 2803",
    "sg:postcode":"18052",
    "sg:province":"PA",
    "sg:tags":[
        "surveyor"
    ],
    "wof:name":"Bertoni Land Surveying",
    "wof:placetype":"venue"
},
  "geometry": {"coordinates":[-75.528683,40.687215],"type":"Point"}
}