{
  "type": "Feature",
  "properties": {
    "iso:country":"US",
    "sg:address":"4289 Rte 338",
    "sg:city":"Knox",
    "sg:classifiers":[
        {
            "category":"Manufacturing",
            "subcategory":"Retail Goods",
            "type":"Manufacturing & Wholesale Goods"
        }
    ],
    "sg:phone":"+1 814 797 5031",
    "sg:postcode":"16232",
    "sg:province":"PA",
    "sg:tags":[
        "product",
        "mfg"
    ],
    "wof:name":"Sweetest Moments",
    "wof:placetype":"venue"
},
  "geometry": {"coordinates":[-79.57406899999999,41.189971],"type":"Point"}
}