{
  "type": "Feature",
  "properties": {
    "iso:country":"US",
    "sg:address":"1000 Sandy St",
    "sg:city":"Norristown",
    "sg:classifiers":[
        {
            "category":"Banks & Credit Unions",
            "subcategory":"Bank",
            "type":"Services"
        }
    ],
    "sg:phone":"+1 610 270 8400",
    "sg:postcode":"19401",
    "sg:province":"PA",
    "wof:name":"Fleet Bank",
    "wof:placetype":"venue"
},
  "geometry": {"coordinates":[-75.32247599999999,40.113856],"type":"Point"}
}