{
  "type": "Feature",
  "properties": {
    "iso:country":"US",
    "sg:address":"4648 Umbria St",
    "sg:city":"Philadelphia",
    "sg:classifiers":[
        {
            "category":"Retail",
            "subcategory":"Auto Repair",
            "type":"Services"
        }
    ],
    "sg:phone":"+1 267 335 4337",
    "sg:postcode":"19127",
    "sg:province":"PA",
    "wof:name":"Helix Motor Sports",
    "wof:placetype":"venue"
},
  "geometry": {"coordinates":[-75.230287,40.03057],"type":"Point"}
}