{
  "type": "Feature",
  "properties": {
    "iso:country":"US",
    "sg:address":"117 Penn St",
    "sg:city":"Millheim",
    "sg:classifiers":[
        {
            "category":"Organizations",
            "subcategory":"Religious Organization",
            "type":"Services"
        }
    ],
    "sg:phone":"+1 814 349 5069",
    "sg:postcode":"16854",
    "sg:province":"PA",
    "sg:tags":[
        "church"
    ],
    "wof:name":"Milheim United Methodist Chr",
    "wof:placetype":"venue"
},
  "geometry": {"coordinates":[-77.476327,40.889392],"type":"Point"}
}