{
  "type": "Feature",
  "properties": {
    "addr:full":"6101 Woodland Ave Philadelphia PA 19142",
    "addr:housenumber":"6101",
    "addr:postcode":"19142",
    "addr:street":"Woodland Ave",
    "iso:country":"US",
    "sg:address":"6101 Woodland Ave",
    "sg:city":"Philadelphia",
    "sg:classifiers":[
        {
            "category":"Cinema",
            "subcategory":"Movie Rental",
            "type":"Entertainment"
        }
    ],
    "sg:phone":"+1 215 724 2567",
    "sg:postcode":"19142",
    "sg:province":"PA",
    "sg:tags":[
        "game",
        "video"
    ],
    "wof:name":"Power Gamer",
    "wof:placetype":"venue"
},
  "geometry": {"coordinates":[-75.229202,39.9291],"type":"Point"}
}