{
  "type": "Feature",
  "properties": {
    "addr:full":"5 Kensington Dr Camp Hill PA 17011",
    "addr:housenumber":"5",
    "addr:postcode":"17011",
    "addr:street":"Kensington Dr",
    "iso:country":"US",
    "sg:address":"5 Kensington Dr",
    "sg:city":"Camp Hill",
    "sg:classifiers":[
        {
            "category":"Insurance",
            "subcategory":"Insurance Agent",
            "type":"Services"
        }
    ],
    "sg:phone":"+1 717 737 7225",
    "sg:postcode":"17011",
    "sg:province":"PA",
    "wof:name":"American Health Underwriters",
    "wof:placetype":"venue"
},
  "geometry": {"coordinates":[-76.952252,40.211423],"type":"Point"}
}