{
  "type": "Feature",
  "properties": {
    "iso:country":"US",
    "sg:address":"4136 Winterburn Ave",
    "sg:city":"Pittsburgh",
    "sg:classifiers":[
        {
            "category":"Building & Trades",
            "subcategory":"Landscaping Services",
            "type":"Services"
        }
    ],
    "sg:phone":"+1 412 521 7317",
    "sg:postcode":"15207",
    "sg:province":"PA",
    "sg:tags":[
        "tree"
    ],
    "wof:name":"Ray's Tree Removal",
    "wof:placetype":"venue"
},
  "geometry": {"coordinates":[-79.939882,40.423824],"type":"Point"}
}