{
  "type": "Feature",
  "properties": {
    "iso:country":"US",
    "sg:address":"1039 Park Rd",
    "sg:city":"Leesport",
    "sg:classifiers":[
        {
            "category":"Building & Trades",
            "subcategory":"Landscaping Services",
            "type":"Services"
        }
    ],
    "sg:phone":"+1 610 926 0102",
    "sg:postcode":"19533",
    "sg:province":"PA",
    "sg:tags":[
        "tree"
    ],
    "wof:name":"Bobs Tree Service",
    "wof:placetype":"venue"
},
  "geometry": {"coordinates":[-76.014426,40.431578],"type":"Point"}
}