{
  "type": "Feature",
  "properties": {
    "addr:full":"5462 Spring Rd Shermans Dale PA 17090",
    "addr:housenumber":"5462",
    "addr:postcode":"17090",
    "addr:street":"Spring Rd",
    "iso:country":"US",
    "sg:address":"5462 Spring Rd",
    "sg:city":"Shermans Dale",
    "sg:classifiers":[
        {
            "category":"Autos & Motor Vehicles",
            "subcategory":"Fuel & Gas Station",
            "type":"Retail Goods"
        }
    ],
    "sg:phone":"+1   ",
    "sg:postcode":"17090",
    "sg:province":"PA",
    "sg:tags":[
        "grocery",
        "station",
        "gasoline"
    ],
    "wof:name":"BP",
    "wof:placetype":"venue"
},
  "geometry": {"coordinates":[-77.18086,40.329102],"type":"Point"}
}