{
  "type": "Feature",
  "properties": {
    "addr:full":"538 Prescott Rd Merion Station PA 19066",
    "addr:housenumber":"538",
    "addr:postcode":"19066",
    "addr:street":"Prescott Rd Merion Station",
    "iso:country":"US",
    "sg:address":"538 Prescott Rd",
    "sg:city":"Merion Station",
    "sg:classifiers":[
        {
            "category":"Real Estate",
            "subcategory":"Real Estate Operator",
            "type":"Services"
        }
    ],
    "sg:phone":"+1   ",
    "sg:postcode":"19066",
    "sg:province":"PA",
    "sg:tags":[
        "building",
        "nonresidential"
    ],
    "wof:name":"Prescott Properties Inc",
    "wof:placetype":"venue"
},
  "geometry": {"coordinates":[-75.25115099999999,40.014147],"type":"Point"}
}