{
  "type": "Feature",
  "properties": {
    "addr:full":"400 Technology Dr Canonsburg PA 15317",
    "addr:housenumber":"400",
    "addr:postcode":"15317",
    "addr:street":"Technology Dr",
    "iso:country":"US",
    "sg:address":"400 Technology Dr",
    "sg:city":"Canonsburg",
    "sg:classifiers":[
        {
            "category":"Professional",
            "subcategory":"Management & Consulting",
            "type":"Services"
        }
    ],
    "sg:phone":"+1   ",
    "sg:postcode":"15317",
    "sg:province":"PA",
    "sg:tags":[
        "consultant",
        "business"
    ],
    "wof:name":"Threshold Technologies Inc",
    "wof:placetype":"venue"
},
  "geometry": {"coordinates":[-80.176953,40.287424],"type":"Point"}
}