{
  "type": "Feature",
  "properties": {
    "iso:country":"US",
    "sg:address":"3561 Valley Dr",
    "sg:city":"Pittsburgh",
    "sg:classifiers":[
        {
            "category":"Banks & Credit Unions",
            "subcategory":"Investment Brokerage",
            "type":"Services"
        }
    ],
    "sg:phone":"+1 412 851 1597",
    "sg:postcode":"15234",
    "sg:province":"PA",
    "sg:tags":[
        "consultant",
        "planning",
        "financial"
    ],
    "wof:name":"Tweardy & Assoc",
    "wof:placetype":"venue"
},
  "geometry": {"coordinates":[-80.02484699999999,40.353449],"type":"Point"}
}