{
  "type": "Feature",
  "properties": {
    "iso:country":"US",
    "sg:address":"1117 Broad Ave",
    "sg:city":"Belle Vernon",
    "sg:classifiers":[
        {
            "category":"Shopping",
            "subcategory":"Used Merchandise",
            "type":"Retail Goods"
        }
    ],
    "sg:phone":"+1 724 929 3404",
    "sg:postcode":"15012",
    "sg:province":"PA",
    "sg:tags":[
        "shop",
        "consignment"
    ],
    "wof:name":"2nd Time Around",
    "wof:placetype":"venue"
},
  "geometry": {"coordinates":[-79.85312500000001,40.134195],"type":"Point"}
}