{
  "type": "Feature",
  "properties": {
    "iso:country":"US",
    "sg:address":"2801 N Front St",
    "sg:city":"Harrisburg",
    "sg:classifiers":[
        {
            "category":"Professional",
            "subcategory":"Computer Services",
            "type":"Services"
        }
    ],
    "sg:phone":"+1 717 233 3662",
    "sg:postcode":"17110",
    "sg:province":"PA",
    "sg:tags":[
        "website",
        "design"
    ],
    "wof:name":"Legidyn",
    "wof:placetype":"venue"
},
  "geometry": {"coordinates":[-76.905796,40.291188],"type":"Point"}
}