{
  "type": "Feature",
  "properties": {
    "iso:country":"US",
    "sg:address":"25 Morgantown St",
    "sg:city":"Uniontown",
    "sg:classifiers":[
        {
            "category":"Professional",
            "type":"Services"
        }
    ],
    "sg:phone":"+1 724 438 3940",
    "sg:postcode":"15401",
    "sg:province":"PA",
    "sg:tags":[
        "establishment"
    ],
    "wof:name":"Fayette County Comm Action",
    "wof:placetype":"venue"
},
  "geometry": {"coordinates":[-79.727329,39.9003],"type":"Point"}
}