{
  "type": "Feature",
  "properties": {
    "iso:country":"US",
    "sg:address":"7101 Church Ave",
    "sg:city":"Pittsburgh",
    "sg:classifiers":[
        {
            "category":"Government",
            "subcategory":"Office",
            "type":"Public Place"
        }
    ],
    "sg:phone":"+1   ",
    "sg:postcode":"15202",
    "sg:province":"PA",
    "sg:tags":[
        "executive"
    ],
    "wof:name":"Ben Avon Borough",
    "wof:placetype":"venue"
},
  "geometry": {"coordinates":[-80.083702,40.50859],"type":"Point"}
}