{
  "type": "Feature",
  "properties": {
    "iso:country":"US",
    "sg:address":"21 Keystone St",
    "sg:city":"Littlestown",
    "sg:classifiers":[
        {
            "category":"Wholesale",
            "subcategory":"Auto Parts",
            "type":"Manufacturing & Wholesale Goods"
        }
    ],
    "sg:phone":"+1 717 359 9286",
    "sg:postcode":"17340",
    "sg:province":"PA",
    "sg:tags":[
        "used"
    ],
    "wof:name":"Gartrell Antique Auto Parts",
    "wof:placetype":"venue"
},
  "geometry": {"coordinates":[-77.078171,39.744104],"type":"Point"}
}