{
  "type": "Feature",
  "properties": {
    "iso:country":"US",
    "sg:address":"5903 5th Ave",
    "sg:city":"Pittsburgh",
    "sg:classifiers":[
        {
            "category":"Real Estate",
            "subcategory":"Real Estate Agent",
            "type":"Services"
        }
    ],
    "sg:phone":"+1 412 362 3411",
    "sg:postcode":"15232",
    "sg:province":"PA",
    "wof:name":"Woodland Manor Condominiums",
    "wof:placetype":"venue"
},
  "geometry": {"coordinates":[-79.925563,40.451366],"type":"Point"}
}