{
  "type": "Feature",
  "properties": {
    "addr:full":"28 New Rd Aston PA 19014",
    "addr:housenumber":"28",
    "addr:postcode":"19014",
    "addr:street":"New Rd",
    "iso:country":"US",
    "sg:address":"28 New Rd",
    "sg:city":"Aston",
    "sg:classifiers":[
        {
            "category":"Organizations",
            "subcategory":"Religious Organization",
            "type":"Services"
        }
    ],
    "sg:phone":"+1 610 459 2501",
    "sg:postcode":"19014",
    "sg:province":"PA",
    "sg:tags":[
        "monastery",
        "convent"
    ],
    "wof:name":"Sisters Of St Francis",
    "wof:placetype":"venue"
},
  "geometry": {"coordinates":[-75.451802,39.893069],"type":"Point"}
}