{
  "type": "Feature",
  "properties": {
    "iso:country":"US",
    "sg:address":"115 7th St",
    "sg:city":"Milford",
    "sg:classifiers":[
        {
            "category":"Professional",
            "type":"Services"
        },
        {
            "category":"Shopping",
            "subcategory":"Crafts & Fabrics",
            "type":"Retail Goods"
        }
    ],
    "sg:phone":"+1 570 409 9276",
    "sg:postcode":"18337",
    "sg:province":"PA",
    "sg:tags":[
        "yarn"
    ],
    "wof:name":"Jill Deal Inc",
    "wof:placetype":"venue"
},
  "geometry": {"coordinates":[-74.808925,41.3245],"type":"Point"}
}