{
  "type": "Feature",
  "properties": {
    "addr:full":"340 Chestnut St Mifflinburg PA 17844",
    "addr:housenumber":"340",
    "addr:postcode":"17844",
    "addr:street":"Chestnut St",
    "iso:country":"US",
    "sg:address":"340 Chestnut St",
    "sg:city":"Mifflinburg",
    "sg:classifiers":[
        {
            "category":"Real Estate",
            "subcategory":"Real Estate Agent",
            "type":"Services"
        }
    ],
    "sg:phone":"+1 570 966 7330",
    "sg:postcode":"17844",
    "sg:province":"PA",
    "wof:name":"Villager Realty Inc",
    "wof:placetype":"venue"
},
  "geometry": {"coordinates":[-77.046604,40.91822],"type":"Point"}
}