{
  "type": "Feature",
  "properties": {
    "iso:country":"US",
    "sg:address":"86 E Hanover St",
    "sg:city":"Gettysburg",
    "sg:classifiers":[
        {
            "category":"Utilities",
            "subcategory":"Water",
            "type":"Services"
        }
    ],
    "sg:phone":"+1 717 334 2616",
    "sg:postcode":"17325",
    "sg:province":"PA",
    "sg:tags":[
        "company",
        "sewage"
    ],
    "wof:name":"Bonneauville Water & Sewage",
    "wof:placetype":"venue"
},
  "geometry": {"coordinates":[-77.126937,39.809664],"type":"Point"}
}