{
  "type": "Feature",
  "properties": {
    "addr:full":"1204 Georgetown Cir Carlisle PA 17013",
    "addr:housenumber":"1204",
    "addr:postcode":"17013",
    "addr:street":"Georgetown Cir",
    "iso:country":"US",
    "sg:address":"1204 Georgetown Cir",
    "sg:city":"Carlisle",
    "sg:classifiers":[
        {
            "category":"Professional",
            "subcategory":"Lawyer & Legal Services",
            "type":"Services"
        }
    ],
    "sg:phone":"+1   ",
    "sg:postcode":"17013",
    "sg:province":"PA",
    "wof:name":"Gagliano Health Law",
    "wof:placetype":"venue"
},
  "geometry": {"coordinates":[-77.211895,40.196249],"type":"Point"}
}