{
  "type": "Feature",
  "properties": {
    "addr:full":"5455 Curry Rd Pleasant Hills PA 15236",
    "addr:housenumber":"5455",
    "addr:postcode":"15236",
    "addr:street":"Curry Rd",
    "iso:country":"US",
    "sg:address":"5455 Curry Rd",
    "sg:city":"Pleasant Hills",
    "sg:classifiers":[
        {
            "category":"Bars & Pubs",
            "type":"Food & Drink"
        }
    ],
    "sg:phone":"+1 412 653 7011",
    "sg:postcode":"15236",
    "sg:province":"PA",
    "sg:tags":[
        "drinking"
    ],
    "wof:name":"Bob-Bets Lounge",
    "wof:placetype":"venue"
},
  "geometry": {"coordinates":[-79.990904,40.338713],"type":"Point"}
}