{
  "type": "Feature",
  "properties": {
    "iso:country":"US",
    "sg:address":"550 Fishing Creek Rd",
    "sg:city":"Lewisberry",
    "sg:classifiers":[
        {
            "category":"Manufacturing",
            "subcategory":"Printing",
            "type":"Manufacturing & Wholesale Goods"
        }
    ],
    "sg:phone":"+1 717 938 0595",
    "sg:postcode":"17339",
    "sg:province":"PA",
    "sg:tags":[
        "commercial"
    ],
    "wof:name":"Absolute Graphics",
    "wof:placetype":"venue"
},
  "geometry": {"coordinates":[-76.87463,40.183347],"type":"Point"}
}