{
  "type": "Feature",
  "properties": {
    "iso:country":"US",
    "sg:address":"31 E Orange St",
    "sg:city":"Lancaster",
    "sg:classifiers":[
        {
            "category":"Personal",
            "subcategory":"Beauty Salon",
            "type":"Services"
        }
    ],
    "sg:phone":"+1 717 392 6007",
    "sg:postcode":"17602",
    "sg:province":"PA",
    "sg:tags":[
        "hair",
        "stylist"
    ],
    "wof:name":"D.F.B. Studios",
    "wof:placetype":"venue"
},
  "geometry": {"coordinates":[-76.304863,40.039653],"type":"Point"}
}