{
  "type": "Feature",
  "properties": {
    "addr:full":"226 Erford Rd Camp Hill PA 17011",
    "addr:housenumber":"226",
    "addr:postcode":"17011",
    "addr:street":"Erford Rd",
    "iso:country":"US",
    "sg:address":"226 Erford Rd",
    "sg:city":"Camp Hill",
    "sg:classifiers":[
        {
            "category":"Professional",
            "subcategory":"Computer Services",
            "type":"Services"
        }
    ],
    "sg:phone":"+1 717 975 1926",
    "sg:postcode":"17011",
    "sg:province":"PA",
    "sg:tags":[
        "software"
    ],
    "sg:website":"www.natec.com",
    "wof:name":"Tech Harmony",
    "wof:placetype":"venue"
},
  "geometry": {"coordinates":[-76.922946,40.265854],"type":"Point"}
}