{
  "type": "Feature",
  "properties": {
    "addr:full":"161 Stone Quarry Rd Leola PA 17540",
    "addr:housenumber":"161",
    "addr:postcode":"17540",
    "addr:street":"Stone Quarry Rd",
    "iso:country":"US",
    "sg:address":"161 Stone Quarry Rd",
    "sg:city":"Leola",
    "sg:classifiers":[
        {
            "category":"Communications",
            "subcategory":"Film & Video Production",
            "type":"Services"
        },
        {
            "category":"Professional",
            "type":"Services"
        }
    ],
    "sg:phone":"+1 717 656 7046",
    "sg:postcode":"17540",
    "sg:province":"PA",
    "sg:tags":[
        "establishment",
        "broker"
    ],
    "wof:name":"Benco Polyfilms",
    "wof:placetype":"venue"
},
  "geometry": {"coordinates":[-76.22239999999999,40.120678],"type":"Point"}
}