{
  "type": "Feature",
  "properties": {
    "addr:full":"2813 E Prospect Rd York PA 17402",
    "addr:housenumber":"2813",
    "addr:postcode":"17402",
    "addr:street":"E Prospect Rd",
    "iso:country":"US",
    "sg:address":"2813 E Prospect Rd",
    "sg:city":"York",
    "sg:classifiers":[
        {
            "category":"Wholesale",
            "subcategory":"Medical Equipment & Supplies",
            "type":"Manufacturing & Wholesale Goods"
        }
    ],
    "sg:phone":"+1 717 751 2484",
    "sg:postcode":"17402",
    "sg:province":"PA",
    "sg:tags":[
        "alarm"
    ],
    "wof:name":"Home Choice Preferred Care",
    "wof:placetype":"venue"
},
  "geometry": {"coordinates":[-76.664614,39.958868],"type":"Point"}
}