{
  "type": "Feature",
  "properties": {
    "addr:full":"1 Drake Dr Oil City PA 16301",
    "addr:housenumber":"1",
    "addr:postcode":"16301",
    "addr:street":"Drake Dr",
    "iso:country":"US",
    "sg:address":"1 Drake Dr",
    "sg:city":"Oil City",
    "sg:classifiers":[
        {
            "category":"Professional",
            "subcategory":"Lawyer & Legal Services",
            "type":"Services"
        }
    ],
    "sg:phone":"+1 814 676 3330",
    "sg:postcode":"16301",
    "sg:province":"PA",
    "sg:tags":[
        "attorney"
    ],
    "wof:name":"Michael R Hadley PC",
    "wof:placetype":"venue"
},
  "geometry": {"coordinates":[-79.721991,41.418901],"type":"Point"}
}