{
  "type": "Feature",
  "properties": {
    "addr:full":"230 W 3rd St Williamsport PA 17701",
    "addr:housenumber":"230",
    "addr:postcode":"17701",
    "addr:street":"W 3Rd St",
    "iso:country":"US",
    "sg:address":"230 W 3rd St",
    "sg:city":"Williamsport",
    "sg:classifiers":[
        {
            "category":"Shopping",
            "type":"Retail Goods"
        },
        {
            "category":"Shopping",
            "subcategory":"Clothing, Apparel, & Fashions",
            "type":"Retail Goods"
        }
    ],
    "sg:phone":"+1 570 321 0252",
    "sg:postcode":"17701",
    "sg:province":"PA",
    "sg:tags":[
        "cosmetic",
        "merchandise",
        "perfume"
    ],
    "wof:name":"Virtuous Women Beauty Supplies",
    "wof:placetype":"venue"
},
  "geometry": {"coordinates":[-77.00443,41.23962],"type":"Point"}
}