{
  "type": "Feature",
  "properties": {
    "addr:full":"671 S 1st Ave Coatesville PA 19320",
    "addr:housenumber":"671",
    "addr:postcode":"19320",
    "addr:street":"S 1St Ave",
    "iso:country":"US",
    "sg:address":"671 S 1st Ave",
    "sg:city":"Coatesville",
    "sg:classifiers":[
        {
            "category":"Organizations",
            "subcategory":"Religious Organization",
            "type":"Services"
        }
    ],
    "sg:phone":"+1 610 384 3405",
    "sg:postcode":"19320",
    "sg:province":"PA",
    "sg:tags":[
        "church"
    ],
    "wof:name":"Bethel AME Church",
    "wof:placetype":"venue"
},
  "geometry": {"coordinates":[-75.82001700000001,39.974644],"type":"Point"}
}