{
  "type": "Feature",
  "properties": {
    "addr:full":"751 Waterdam Rd Canonsburg PA 15317",
    "addr:housenumber":"751",
    "addr:postcode":"15317",
    "addr:street":"Waterdam Rd",
    "iso:country":"US",
    "sg:address":"751 Waterdam Rd",
    "sg:city":"Canonsburg",
    "sg:classifiers":[
        {
            "category":"Manufacturing",
            "subcategory":"Signs",
            "type":"Manufacturing & Wholesale Goods"
        }
    ],
    "sg:phone":"+1   ",
    "sg:postcode":"15317",
    "sg:province":"PA",
    "sg:tags":[
        "specialty",
        "mfg"
    ],
    "wof:name":"Page Signs",
    "wof:placetype":"venue"
},
  "geometry": {"coordinates":[-80.104271,40.247884],"type":"Point"}
}