{
  "type": "Feature",
  "properties": {
    "iso:country":"US",
    "sg:address":"2450 Catasauqua Rd",
    "sg:city":"Bethlehem",
    "sg:classifiers":[
        {
            "category":"Retail",
            "subcategory":"Auto Repair",
            "type":"Services"
        }
    ],
    "sg:phone":"+1 610 865 2071",
    "sg:postcode":"18018",
    "sg:province":"PA",
    "sg:tags":[
        "repairing",
        "automobile"
    ],
    "wof:name":"Chet's ABE-Mobil",
    "wof:placetype":"venue"
},
  "geometry": {"coordinates":[-75.42785000000001,40.643198],"type":"Point"}
}