{
  "type": "Feature",
  "properties": {
    "iso:country":"US",
    "sg:address":"168 Lynn Rd",
    "sg:city":"Washington",
    "sg:classifiers":[
        {
            "category":"Building & Trades",
            "subcategory":"Landscaping Services",
            "type":"Services"
        }
    ],
    "sg:phone":"+1   ",
    "sg:postcode":"15301",
    "sg:province":"PA",
    "wof:name":"Kobertz Lawn Garde",
    "wof:placetype":"venue"
},
  "geometry": {"coordinates":[-80.316123,40.226576],"type":"Point"}
}