{
  "type": "Feature",
  "properties": {
    "iso:country":"US",
    "sg:address":"237 Belmont Ave",
    "sg:city":"Ambler",
    "sg:classifiers":[
        {
            "category":"Building & Trades",
            "subcategory":"Electrical",
            "type":"Services"
        }
    ],
    "sg:phone":"+1   ",
    "sg:postcode":"19002",
    "sg:province":"PA",
    "sg:tags":[
        "electrical",
        "contractor"
    ],
    "wof:name":"Connor Electric",
    "wof:placetype":"venue"
},
  "geometry": {"coordinates":[-75.222414,40.158178],"type":"Point"}
}