{
  "type": "Feature",
  "properties": {
    "iso:country":"US",
    "sg:address":"40 E High St",
    "sg:city":"Philadelphia",
    "sg:classifiers":[
        {
            "category":"Education",
            "subcategory":"School",
            "type":"Public Place"
        }
    ],
    "sg:phone":"+1 215 951 4004",
    "sg:postcode":"19144",
    "sg:province":"PA",
    "sg:tags":[
        "high"
    ],
    "wof:name":"Germantown High School",
    "wof:placetype":"venue"
},
  "geometry": {"coordinates":[-75.176286,40.040521],"type":"Point"}
}