{
  "type": "Feature",
  "properties": {
    "iso:country":"US",
    "sg:address":"11683 Althea Dr",
    "sg:city":"Pittsburgh",
    "sg:classifiers":[
        {
            "category":"Autos & Motor Vehicles",
            "subcategory":"Auto Supplies",
            "type":"Retail Goods"
        }
    ],
    "sg:phone":"+1 412 414 7451",
    "sg:postcode":"15235",
    "sg:province":"PA",
    "sg:tags":[
        "wheel"
    ],
    "wof:name":"Suds On Wheels",
    "wof:placetype":"venue"
},
  "geometry": {"coordinates":[-79.82933800000001,40.467981],"type":"Point"}
}