{
  "type": "Feature",
  "properties": {
    "addr:full":"903 8th Ave Beaver Falls PA 15010",
    "addr:housenumber":"903",
    "addr:postcode":"15010",
    "addr:street":"8Th Ave",
    "iso:country":"US",
    "sg:address":"903 8th Ave",
    "sg:city":"Beaver Falls",
    "sg:classifiers":[
        {
            "category":"Organizations",
            "subcategory":"Religious Organization",
            "type":"Services"
        }
    ],
    "sg:phone":"+1 724 843 2899",
    "sg:postcode":"15010",
    "sg:province":"PA",
    "sg:tags":[
        "church"
    ],
    "wof:name":"Beaver Valley Christian Flwshp",
    "wof:placetype":"venue"
},
  "geometry": {"coordinates":[-80.320989,40.751002],"type":"Point"}
}