{
  "type": "Feature",
  "properties": {
    "addr:full":"6809 Greenway Ave Philadelphia PA 19142",
    "addr:housenumber":"6809",
    "addr:postcode":"19142",
    "addr:street":"Greenway Ave",
    "iso:country":"US",
    "sg:address":"6809 Greenway Ave",
    "sg:city":"Philadelphia",
    "sg:classifiers":[
        {
            "category":"Building & Trades",
            "subcategory":"Construction",
            "type":"Services"
        }
    ],
    "sg:phone":"+1   ",
    "sg:postcode":"19142",
    "sg:province":"PA",
    "sg:tags":[
        "construct",
        "contractor"
    ],
    "wof:name":"Ronald G Zawadsky Contracting",
    "wof:placetype":"venue"
},
  "geometry": {"coordinates":[-75.240369,39.9234],"type":"Point"}
}