{
  "type": "Feature",
  "properties": {
    "addr:full":"19 Lynwood Dr Chalfont PA 18914",
    "addr:housenumber":"19",
    "addr:postcode":"18914",
    "addr:street":"Lynwood Dr",
    "iso:country":"US",
    "sg:address":"19 Lynwood Dr",
    "sg:city":"Chalfont",
    "sg:classifiers":[
        {
            "category":"Wholesale",
            "subcategory":"Hardware",
            "type":"Manufacturing & Wholesale Goods"
        }
    ],
    "sg:phone":"+1 215 997 1762",
    "sg:postcode":"18914",
    "sg:province":"PA",
    "sg:tags":[
        "hardware-wholesale",
        "manufacturer"
    ],
    "wof:name":"Guthrie Hill Hardware Company",
    "wof:placetype":"venue"
},
  "geometry": {"coordinates":[-75.219139,40.294048],"type":"Point"}
}