{
  "type": "Feature",
  "properties": {
    "iso:country":"US",
    "sg:address":"410 Glenn Ave",
    "sg:city":"Bloomsburg",
    "sg:classifiers":[
        {
            "category":"Health Services",
            "subcategory":"Podiatrist",
            "type":"Services"
        }
    ],
    "sg:phone":"+1 570 387 2202",
    "sg:postcode":"17815",
    "sg:province":"PA",
    "wof:name":"Karen Campbell DPM",
    "wof:placetype":"venue"
},
  "geometry": {"coordinates":[-76.453947,41.009039],"type":"Point"}
}