{
  "type": "Feature",
  "properties": {
    "iso:country":"US",
    "sg:address":"16 Barr Rd",
    "sg:city":"Berwyn",
    "sg:classifiers":[
        {
            "category":"Professional",
            "subcategory":"Engineering",
            "type":"Services"
        }
    ],
    "sg:phone":"+1 610 353 5595",
    "sg:postcode":"19312",
    "sg:province":"PA",
    "sg:tags":[
        "engineer"
    ],
    "wof:name":"Paul Zamrowski Assoc Inc",
    "wof:placetype":"venue"
},
  "geometry": {"coordinates":[-75.46235,39.997696],"type":"Point"}
}