{
  "type": "Feature",
  "properties": {
    "iso:country":"US",
    "sg:address":"600 Emlen Way",
    "sg:city":"Telford",
    "sg:classifiers":[
        {
            "category":"Manufacturing",
            "subcategory":"Jewelry",
            "type":"Manufacturing & Wholesale Goods"
        }
    ],
    "sg:phone":"+1 215 723 4600",
    "sg:postcode":"18969",
    "sg:province":"PA",
    "sg:tags":[
        "precious",
        "material",
        "metal",
        "mfg"
    ],
    "wof:name":"Keystone Findings Inc",
    "wof:placetype":"venue"
},
  "geometry": {"coordinates":[-75.32438999999999,40.334765],"type":"Point"}
}