{
  "type": "Feature",
  "properties": {
    "iso:country":"US",
    "sg:address":"626 S 4th St",
    "sg:city":"Philadelphia",
    "sg:classifiers":[
        {
            "category":"Personal",
            "subcategory":"Piercing",
            "type":"Services"
        }
    ],
    "sg:phone":"+1 215 923 7335",
    "sg:postcode":"19147",
    "sg:province":"PA",
    "sg:tags":[
        "body"
    ],
    "sg:website":"www.infinitebody.com",
    "wof:name":"Infinite Body Piercing",
    "wof:placetype":"venue"
},
  "geometry": {"coordinates":[-75.1493,39.941399],"type":"Point"}
}