{
  "type": "Feature",
  "properties": {
    "iso:country":"US",
    "sg:address":"94 Barbour St",
    "sg:city":"Bradford",
    "sg:classifiers":[
        {
            "category":"Wholesale",
            "subcategory":"Beer",
            "type":"Manufacturing & Wholesale Goods"
        }
    ],
    "sg:phone":"+1 814 368 4438",
    "sg:postcode":"16701",
    "sg:province":"PA",
    "wof:name":"Gleason Distributing Co",
    "wof:placetype":"venue"
},
  "geometry": {"coordinates":[-78.65498100000001,41.956293],"type":"Point"}
}