{
  "type": "Feature",
  "properties": {
    "addr:full":"3608 W 26th St Erie PA 16506",
    "addr:housenumber":"3608",
    "addr:postcode":"16506",
    "addr:street":"W 26Th St",
    "iso:country":"US",
    "sg:address":"3608 W 26th St",
    "sg:city":"Erie",
    "sg:classifiers":[
        {
            "category":"Government",
            "subcategory":"Office",
            "type":"Public Place"
        }
    ],
    "sg:phone":"+1 814 838 8666",
    "sg:postcode":"16506",
    "sg:province":"PA",
    "sg:tags":[
        "city",
        "taxation"
    ],
    "wof:name":"Millcreek Township Tax Cllctr",
    "wof:placetype":"venue"
},
  "geometry": {"coordinates":[-80.15672499999999,42.081074],"type":"Point"}
}