{
  "type": "Feature",
  "properties": {
    "addr:full":"221 W Lancaster Ave Shillington PA 19607",
    "addr:housenumber":"221",
    "addr:postcode":"19607",
    "addr:street":"W Lancaster Ave",
    "iso:country":"US",
    "sg:address":"221 W Lancaster Ave",
    "sg:city":"Shillington",
    "sg:classifiers":[
        {
            "category":"Personal",
            "subcategory":"Beauty Salon",
            "type":"Services"
        }
    ],
    "sg:phone":"+1 610 777 1481",
    "sg:postcode":"19607",
    "sg:province":"PA",
    "wof:name":"Joanne Tammaro Beauty Salon",
    "wof:placetype":"venue"
},
  "geometry": {"coordinates":[-75.97172399999999,40.304664],"type":"Point"}
}