{
  "type": "Feature",
  "properties": {
    "iso:country":"US",
    "sg:address":"117 S 8th St",
    "sg:city":"Philadelphia",
    "sg:classifiers":[
        {
            "category":"Shopping",
            "subcategory":"Jewelry",
            "type":"Retail Goods"
        }
    ],
    "sg:phone":"+1 215 629 4030",
    "sg:postcode":"19106",
    "sg:province":"PA",
    "sg:tags":[
        "jeweler"
    ],
    "wof:name":"Samuel's Fine Jewelry",
    "wof:placetype":"venue"
},
  "geometry": {"coordinates":[-75.153978,39.948997],"type":"Point"}
}