{
  "type": "Feature",
  "properties": {
    "addr:full":"100 State St Suite 100 Erie PA 16507",
    "addr:housenumber":"100",
    "addr:postcode":"16507",
    "addr:street":"State St Suite 100",
    "iso:country":"US",
    "sg:address":"100 State St Suite 100",
    "sg:city":"Erie",
    "sg:classifiers":[
        {
            "category":"Professional",
            "subcategory":"Management & Consulting",
            "type":"Services"
        },
        {
            "category":"Banks & Credit Unions",
            "subcategory":"Investment Brokerage",
            "type":"Services"
        },
        {
            "category":"Banks & Credit Unions",
            "subcategory":"Bank",
            "type":"Services"
        },
        {
            "category":"Banks & Credit Unions",
            "subcategory":"Financial Services",
            "type":"Services"
        }
    ],
    "sg:phone":"+1 814 453 5021",
    "sg:postcode":"16507",
    "sg:province":"PA",
    "sg:tags":[
        "advisory",
        "financing",
        "planner",
        "consultant",
        "mutual",
        "broker",
        "fund",
        "planning",
        "retirement",
        "security",
        "bond",
        "stock"
    ],
    "sg:website":"http://www.wachoviasec.com",
    "wof:name":"Wells Fargo Advisors",
    "wof:placetype":"venue"
},
  "geometry": {"coordinates":[-80.088509,42.134361],"type":"Point"}
}