{
  "type": "Feature",
  "properties": {
    "iso:country":"US",
    "sg:address":"198 Tiffany Ln",
    "sg:city":"Gettysburg",
    "sg:classifiers":[
        {
            "category":"Building & Trades",
            "subcategory":"Construction",
            "type":"Services"
        }
    ],
    "sg:phone":"+1 717 338 1999",
    "sg:postcode":"17325",
    "sg:province":"PA",
    "sg:tags":[
        "general",
        "contractor"
    ],
    "wof:name":"Kresky & Roth Construction",
    "wof:placetype":"venue"
},
  "geometry": {"coordinates":[-77.26648900000001,39.83229],"type":"Point"}
}