{
  "type": "Feature",
  "properties": {
    "iso:country":"US",
    "sg:address":"1122 Washington Ave",
    "sg:city":"Philadelphia",
    "sg:classifiers":[
        {
            "category":"Travel",
            "subcategory":"Travel Agent",
            "type":"Entertainment"
        }
    ],
    "sg:phone":"+1 215 336 2666",
    "sg:postcode":"19147",
    "sg:province":"PA",
    "sg:tags":[
        "agency",
        "services-commercial"
    ],
    "wof:name":"Que Huong Travel",
    "wof:placetype":"venue"
},
  "geometry": {"coordinates":[-75.16150500000001,39.937202],"type":"Point"}
}