{
  "type": "Feature",
  "properties": {
    "iso:country":"US",
    "sg:address":"1179 York Rd",
    "sg:city":"Warminster",
    "sg:classifiers":[
        {
            "category":"Food & Beverages",
            "subcategory":"Bakery",
            "type":"Retail Goods"
        }
    ],
    "sg:phone":"+1 215 674 1400",
    "sg:postcode":"18974",
    "sg:province":"PA",
    "sg:tags":[
        "eating"
    ],
    "sg:website":"www.bucksbagels.com",
    "wof:name":"Bucks Bagels",
    "wof:placetype":"venue"
},
  "geometry": {"coordinates":[-75.097786,40.22154],"type":"Point"}
}