{
  "type": "Feature",
  "properties": {
    "addr:full":"120 Walnut St Scranton PA 18509",
    "addr:housenumber":"120",
    "addr:postcode":"18509",
    "addr:street":"Walnut St",
    "iso:country":"US",
    "sg:address":"120 Walnut St",
    "sg:city":"Scranton",
    "sg:classifiers":[
        {
            "category":"Shopping",
            "type":"Retail Goods"
        },
        {
            "category":"Wholesale",
            "subcategory":"Chemicals & Plastics",
            "type":"Manufacturing & Wholesale Goods"
        }
    ],
    "sg:phone":"+1 570 343 2272",
    "sg:postcode":"18509",
    "sg:province":"PA",
    "sg:tags":[
        "dry",
        "ice"
    ],
    "wof:name":"Sam Bess Dry Ice Inc",
    "wof:placetype":"venue"
},
  "geometry": {"coordinates":[-75.65534599999999,41.422774],"type":"Point"}
}