{
  "type": "Feature",
  "properties": {
    "iso:country":"US",
    "sg:address":"628 W Broad St",
    "sg:city":"Bethlehem",
    "sg:classifiers":[
        {
            "category":"Professional",
            "subcategory":"Lawyer & Legal Services",
            "type":"Services"
        }
    ],
    "sg:phone":"+1 610 691 6373",
    "sg:postcode":"18018",
    "sg:province":"PA",
    "wof:name":"C R E S Title Insurance Agcy",
    "wof:placetype":"venue"
},
  "geometry": {"coordinates":[-75.3918,40.622601],"type":"Point"}
}