{
  "type": "Feature",
  "properties": {
    "iso:country":"US",
    "sg:address":"1224 Walnut St",
    "sg:city":"Philadelphia",
    "sg:classifiers":[
        {
            "category":"Shopping",
            "subcategory":"Crafts & Fabrics",
            "type":"Retail Goods"
        }
    ],
    "sg:phone":"+1 215 545 4777",
    "sg:postcode":"19107",
    "sg:province":"PA",
    "sg:tags":[
        "shop",
        "reupholstery",
        "furniture"
    ],
    "wof:name":"Stapler Dress'n Drape",
    "wof:placetype":"venue"
},
  "geometry": {"coordinates":[-75.161598,39.9492],"type":"Point"}
}