{
  "type": "Feature",
  "properties": {
    "addr:full":"4 E Shirley St Mt Union PA 17066",
    "addr:housenumber":"4",
    "addr:postcode":"17066",
    "addr:street":"E Shirley St",
    "iso:country":"US",
    "sg:address":"4 E Shirley St",
    "sg:city":"Mt Union",
    "sg:classifiers":[
        {
            "category":"Restaurant",
            "type":"Food & Drink"
        }
    ],
    "sg:phone":"+1 814 542 8000",
    "sg:postcode":"17066",
    "sg:province":"PA",
    "wof:name":"China King",
    "wof:placetype":"venue"
},
  "geometry": {"coordinates":[-77.882912,40.38436],"type":"Point"}
}