{
  "type": "Feature",
  "properties": {
    "iso:country":"US",
    "sg:address":"1840 Montgomery Ave",
    "sg:city":"Villanova",
    "sg:classifiers":[
        {
            "category":"Professional",
            "subcategory":"Business Services",
            "type":"Services"
        }
    ],
    "sg:phone":"+1   ",
    "sg:postcode":"19085",
    "sg:province":"PA",
    "wof:name":"Inspection Association",
    "wof:placetype":"venue"
},
  "geometry": {"coordinates":[-75.33653700000001,40.047671],"type":"Point"}
}