{
  "type": "Feature",
  "properties": {
    "iso:country":"US",
    "sg:address":"1317 Wampum Rd",
    "sg:city":"Wampum",
    "sg:classifiers":[
        {
            "category":"Retail",
            "subcategory":"Auto Repair",
            "type":"Services"
        }
    ],
    "sg:phone":"+1 724 535 4679",
    "sg:postcode":"16117",
    "sg:province":"PA",
    "sg:tags":[
        "repairing",
        "automobile"
    ],
    "wof:name":"Matus Service Station",
    "wof:placetype":"venue"
},
  "geometry": {"coordinates":[-80.314554,40.863891],"type":"Point"}
}