{
  "type": "Feature",
  "properties": {
    "iso:country":"US",
    "sg:address":"345 Oakland Ave",
    "sg:city":"Lansdale",
    "sg:classifiers":[
        {
            "category":"Banks & Credit Unions",
            "subcategory":"Investment Brokerage",
            "type":"Services"
        },
        {
            "category":"Banks & Credit Unions",
            "subcategory":"Financial Services",
            "type":"Services"
        }
    ],
    "sg:phone":"+1 215 361 3523",
    "sg:postcode":"19446",
    "sg:province":"PA",
    "sg:tags":[
        "advisory",
        "planner"
    ],
    "wof:name":"Benner Financial Planning",
    "wof:placetype":"venue"
},
  "geometry": {"coordinates":[-75.273988,40.228349],"type":"Point"}
}