{
  "type": "Feature",
  "properties": {
    "addr:full":"2240 S 12th St Philadelphia PA 19148",
    "addr:housenumber":"2240",
    "addr:postcode":"19148",
    "addr:street":"S 12Th St",
    "iso:country":"US",
    "sg:address":"2240 S 12th St",
    "sg:city":"Philadelphia",
    "sg:classifiers":[
        {
            "category":"Restaurant",
            "type":"Food & Drink"
        }
    ],
    "sg:phone":"+1 215 334 8006",
    "sg:postcode":"19148",
    "sg:province":"PA",
    "sg:tags":[
        "deli"
    ],
    "wof:name":"Johnnie's",
    "wof:placetype":"venue"
},
  "geometry": {"coordinates":[-75.166702,39.921501],"type":"Point"}
}