{
  "type": "Feature",
  "properties": {
    "addr:full":"421 Brossman Rd Ephrata PA 17522",
    "addr:housenumber":"421",
    "addr:postcode":"17522",
    "addr:street":"Brossman Rd",
    "iso:country":"US",
    "sg:address":"421 Brossman Rd",
    "sg:city":"Ephrata",
    "sg:classifiers":[
        {
            "category":"Farming",
            "subcategory":"Livestock Farm",
            "type":"Manufacturing & Wholesale Goods"
        }
    ],
    "sg:phone":"+1   ",
    "sg:postcode":"17522",
    "sg:province":"PA",
    "sg:tags":[
        "beef",
        "feedlot",
        "cattle"
    ],
    "wof:name":"Harvey Zimmerman",
    "wof:placetype":"venue"
},
  "geometry": {"coordinates":[-76.172556,40.156268],"type":"Point"}
}