{
  "type": "Feature",
  "properties": {
    "addr:full":"348 W Orange St Lancaster PA 17603",
    "addr:housenumber":"348",
    "addr:postcode":"17603",
    "addr:street":"W Orange St",
    "iso:country":"US",
    "sg:address":"348 W Orange St",
    "sg:city":"Lancaster",
    "sg:classifiers":[
        {
            "category":"Shopping",
            "subcategory":"Clothing, Apparel, & Fashions",
            "type":"Retail Goods"
        }
    ],
    "sg:phone":"+1 717 397 7664",
    "sg:postcode":"17603",
    "sg:province":"PA",
    "sg:tags":[
        "shop",
        "bridal"
    ],
    "wof:name":"Patricia's Bridal Elegance",
    "wof:placetype":"venue"
},
  "geometry": {"coordinates":[-76.312681,40.038749],"type":"Point"}
}