{
  "type": "Feature",
  "properties": {
    "addr:full":"431 Whitford Hills Rd Exton PA 19341",
    "addr:housenumber":"431",
    "addr:postcode":"19341",
    "addr:street":"Whitford Hills Rd",
    "iso:country":"US",
    "sg:address":"431 Whitford Hills Rd",
    "sg:city":"Exton",
    "sg:classifiers":[
        {
            "category":"Manufacturing",
            "subcategory":"Printing",
            "type":"Manufacturing & Wholesale Goods"
        }
    ],
    "sg:phone":"+1 610 363 6666",
    "sg:postcode":"19341",
    "sg:province":"PA",
    "sg:tags":[
        "printer"
    ],
    "wof:name":"Mac Neill Stephen M Printer",
    "wof:placetype":"venue"
},
  "geometry": {"coordinates":[-75.65448499999999,40.034856],"type":"Point"}
}