{
  "type": "Feature",
  "properties": {
    "iso:country":"US",
    "sg:address":"4820 Londonderry Rd",
    "sg:city":"Harrisburg",
    "sg:classifiers":[
        {
            "category":"Social Services",
            "subcategory":"Child Care",
            "type":"Services"
        }
    ],
    "sg:phone":"+1 717 657 8684",
    "sg:postcode":"17109",
    "sg:province":"PA",
    "wof:name":"Hansel & Gretel Early Learning",
    "wof:placetype":"venue"
},
  "geometry": {"coordinates":[-76.804866,40.284829],"type":"Point"}
}