{
  "type": "Feature",
  "properties": {
    "addr:full":"112 Gardner St Philadelphia PA 19116",
    "addr:housenumber":"112",
    "addr:postcode":"19116",
    "addr:street":"Gardner St",
    "iso:country":"US",
    "sg:address":"112 Gardner St",
    "sg:city":"Philadelphia",
    "sg:classifiers":[
        {
            "category":"Shopping",
            "subcategory":"Computers & Home Electronics",
            "type":"Retail Goods"
        }
    ],
    "sg:phone":"+1 267 207 0449",
    "sg:postcode":"19116",
    "sg:province":"PA",
    "sg:tags":[
        "inventor"
    ],
    "wof:name":"Prestige Real Estate Inventors",
    "wof:placetype":"venue"
},
  "geometry": {"coordinates":[-75.034655,40.120638],"type":"Point"}
}