{
  "type": "Feature",
  "properties": {
    "addr:full":"43 F St Carlisle PA 17013",
    "addr:housenumber":"43",
    "addr:postcode":"17013",
    "addr:street":"F St",
    "iso:country":"US",
    "sg:address":"43 F St",
    "sg:city":"Carlisle",
    "sg:classifiers":[
        {
            "category":"Shopping",
            "subcategory":"Gifts & Souvenirs",
            "type":"Retail Goods"
        }
    ],
    "sg:phone":"+1   ",
    "sg:postcode":"17013",
    "sg:province":"PA",
    "wof:name":"Heavenly Yours Country Gifts",
    "wof:placetype":"venue"
},
  "geometry": {"coordinates":[-77.187054,40.213096],"type":"Point"}
}