{
  "type": "Feature",
  "properties": {
    "addr:full":"300 N Coal St Pottsville PA 17901",
    "addr:housenumber":"300",
    "addr:postcode":"17901",
    "addr:street":"N Coal St",
    "iso:country":"US",
    "sg:address":"300 N Coal St",
    "sg:city":"Pottsville",
    "sg:classifiers":[
        {
            "category":"Restaurant",
            "type":"Food & Drink"
        }
    ],
    "sg:phone":"+1 570 628 4400",
    "sg:postcode":"17901",
    "sg:province":"PA",
    "sg:tags":[
        "eating"
    ],
    "wof:name":"Domino's Pizza",
    "wof:placetype":"venue"
},
  "geometry": {"coordinates":[-76.195168,40.687653],"type":"Point"}
}