{
  "type": "Feature",
  "properties": {
    "iso:country":"US",
    "sg:address":"151 W Marshall St",
    "sg:city":"Norristown",
    "sg:classifiers":[
        {
            "category":"Government",
            "subcategory":"Office",
            "type":"Public Place"
        }
    ],
    "sg:phone":"+1   ",
    "sg:postcode":"19401",
    "sg:province":"PA",
    "sg:tags":[
        "consulting",
        "management"
    ],
    "wof:name":"Housing Finance Agency PA",
    "wof:placetype":"venue"
},
  "geometry": {"coordinates":[-75.345215,40.118375],"type":"Point"}
}