{
  "type": "Feature",
  "properties": {
    "addr:full":"4007 Edgmont Ave Brookhaven PA 19015",
    "addr:housenumber":"4007",
    "addr:postcode":"19015",
    "addr:street":"Edgmont Ave",
    "iso:country":"US",
    "sg:address":"4007 Edgmont Ave",
    "sg:city":"Brookhaven",
    "sg:classifiers":[
        {
            "category":"Manufacturing",
            "subcategory":"Printing",
            "type":"Manufacturing & Wholesale Goods"
        }
    ],
    "sg:phone":"+1   ",
    "sg:postcode":"19015",
    "sg:province":"PA",
    "sg:tags":[
        "lithography",
        "offset"
    ],
    "wof:name":"Multi-Copy Inc",
    "wof:placetype":"venue"
},
  "geometry": {"coordinates":[-75.387463,39.872207],"type":"Point"}
}