{
  "type": "Feature",
  "properties": {
    "iso:country":"US",
    "sg:address":"200 Chestnut St",
    "sg:city":"Downingtown",
    "sg:classifiers":[
        {
            "category":"Personal",
            "subcategory":"Beauty Salon",
            "type":"Services"
        }
    ],
    "sg:phone":"+1   ",
    "sg:postcode":"19335",
    "sg:province":"PA",
    "sg:tags":[
        "shop"
    ],
    "wof:name":"Kcdg Salon",
    "wof:placetype":"venue"
},
  "geometry": {"coordinates":[-75.695206,40.007538],"type":"Point"}
}