{
  "type": "Feature",
  "properties": {
    "iso:country":"US",
    "sg:address":"7601 Grand Ave",
    "sg:city":"Neville Island",
    "sg:classifiers":[
        {
            "category":"Bars & Pubs",
            "type":"Food & Drink"
        }
    ],
    "sg:phone":"+1 412 264 7225",
    "sg:postcode":"15225",
    "sg:province":"PA",
    "sg:tags":[
        "lounge",
        "cocktail"
    ],
    "wof:name":"River Room",
    "wof:placetype":"venue"
},
  "geometry": {"coordinates":[-80.15106400000001,40.516993],"type":"Point"}
}