{
  "type": "Feature",
  "properties": {
    "iso:country":"US",
    "sg:address":"518 Cedar St",
    "sg:city":"Jenkintown",
    "sg:classifiers":[
        {
            "category":"Professional",
            "subcategory":"Engineering",
            "type":"Services"
        }
    ],
    "sg:phone":"+1 215 572 7344",
    "sg:postcode":"19046",
    "sg:province":"PA",
    "sg:tags":[
        "engineer"
    ],
    "wof:name":"Myriad Professional Svc",
    "wof:placetype":"venue"
},
  "geometry": {"coordinates":[-75.12849,40.10051],"type":"Point"}
}