{
  "type": "Feature",
  "properties": {
    "iso:country":"US",
    "sg:address":"15524 Mill St",
    "sg:city":"Saegertown",
    "sg:phone":"+1   ",
    "sg:postcode":"16433",
    "sg:province":"PA",
    "sg:tags":[
        "wheat"
    ],
    "wof:name":"Keith Edwards",
    "wof:placetype":"venue"
},
  "geometry": {"coordinates":[-80.041735,41.68601],"type":"Point"}
}