{
  "type": "Feature",
  "properties": {
    "addr:full":"401 W High St Pottstown PA 19464",
    "addr:housenumber":"401",
    "addr:postcode":"19464",
    "addr:street":"W High St",
    "iso:country":"US",
    "sg:address":"401 W High St",
    "sg:city":"Pottstown",
    "sg:classifiers":[
        {
            "category":"Wholesale",
            "subcategory":"Chemicals & Plastics",
            "type":"Manufacturing & Wholesale Goods"
        }
    ],
    "sg:phone":"+1   ",
    "sg:postcode":"19464",
    "sg:province":"PA",
    "sg:tags":[
        "explosive",
        "mfg"
    ],
    "wof:name":"Explo-Tech",
    "wof:placetype":"venue"
},
  "geometry": {"coordinates":[-75.670962,40.249373],"type":"Point"}
}