{
  "type": "Feature",
  "properties": {
    "addr:full":"332 N Broad St Philadelphia PA 19102",
    "addr:housenumber":"332",
    "addr:postcode":"19102",
    "addr:street":"N Broad St",
    "iso:country":"US",
    "sg:address":"332 N Broad St",
    "sg:city":"Philadelphia",
    "sg:classifiers":[
        {
            "category":"Building & Trades",
            "subcategory":"Construction",
            "type":"Services"
        }
    ],
    "sg:phone":"+1 215 988 9723",
    "sg:postcode":"19102",
    "sg:province":"PA",
    "sg:tags":[
        "pond",
        "supply"
    ],
    "wof:name":"Quality Koi Co",
    "wof:placetype":"venue"
},
  "geometry": {"coordinates":[-75.162176,39.959202],"type":"Point"}
}