{
  "type": "Feature",
  "properties": {
    "iso:country":"US",
    "sg:address":"407 Crossfield Rd",
    "sg:city":"King Of Prussia",
    "sg:classifiers":[
        {
            "category":"Building & Trades",
            "subcategory":"Electrical",
            "type":"Services"
        }
    ],
    "sg:phone":"+1 610 265 3202",
    "sg:postcode":"19406",
    "sg:province":"PA",
    "sg:tags":[
        "electric",
        "contractor"
    ],
    "wof:name":"CBE Construction Inc",
    "wof:placetype":"venue"
},
  "geometry": {"coordinates":[-75.377678,40.097772],"type":"Point"}
}