{
  "type": "Feature",
  "properties": {
    "iso:country":"US",
    "sg:address":"523 Penn St",
    "sg:city":"Reading",
    "sg:classifiers":[
        {
            "category":"Shopping",
            "subcategory":"Jewelry",
            "type":"Retail Goods"
        }
    ],
    "sg:phone":"+1 610 375 1995",
    "sg:postcode":"19601",
    "sg:province":"PA",
    "sg:tags":[
        "jeweler"
    ],
    "wof:name":"Borelli's Jewelry",
    "wof:placetype":"venue"
},
  "geometry": {"coordinates":[-75.927536,40.335383],"type":"Point"}
}