{
  "type": "Feature",
  "properties": {
    "iso:country":"US",
    "sg:address":"2999 Old Rodgers Rd",
    "sg:city":"Bristol",
    "sg:classifiers":[
        {
            "category":"Retail",
            "subcategory":"Auto Repair",
            "type":"Services"
        }
    ],
    "sg:phone":"+1 215 788 6480",
    "sg:postcode":"19007",
    "sg:province":"PA",
    "sg:tags":[
        "body",
        "shop"
    ],
    "wof:name":"Frank Denucci's Auto Body",
    "wof:placetype":"venue"
},
  "geometry": {"coordinates":[-74.878197,40.1222],"type":"Point"}
}