{
  "type": "Feature",
  "properties": {
    "addr:full":"367 Old Bethlehem Rd Quakertown PA 18951",
    "addr:housenumber":"367",
    "addr:postcode":"18951",
    "addr:street":"Old Bethlehem Rd",
    "iso:country":"US",
    "sg:address":"367 Old Bethlehem Rd",
    "sg:city":"Quakertown",
    "sg:classifiers":[
        {
            "category":"Travel",
            "subcategory":"Campground",
            "type":"Entertainment"
        }
    ],
    "sg:phone":"+1 215 536 3357",
    "sg:postcode":"18951",
    "sg:province":"PA",
    "sg:tags":[
        "trailer"
    ],
    "wof:name":"Little Red Barn Camp Grounds",
    "wof:placetype":"venue"
},
  "geometry": {"coordinates":[-75.263876,40.456386],"type":"Point"}
}