{
  "type": "Feature",
  "properties": {
    "addr:full":"5035 Frankford Ave Philadelphia PA 19124",
    "addr:housenumber":"5035",
    "addr:postcode":"19124",
    "addr:street":"Frankford Ave",
    "iso:country":"US",
    "sg:address":"5035 Frankford Ave",
    "sg:city":"Philadelphia",
    "sg:classifiers":[
        {
            "category":"Personal",
            "subcategory":"Beauty Salon",
            "type":"Services"
        }
    ],
    "sg:phone":"+1 215 743 5719",
    "sg:postcode":"19124",
    "sg:province":"PA",
    "sg:tags":[
        "hair"
    ],
    "wof:name":"Hawa Hairbraiding",
    "wof:placetype":"venue"
},
  "geometry": {"coordinates":[-75.079689,40.020802],"type":"Point"}
}