{
  "type": "Feature",
  "properties": {
    "iso:country":"US",
    "sg:address":"801 Sunset Ct",
    "sg:city":"Hawley",
    "sg:classifiers":[
        {
            "category":"Wholesale",
            "subcategory":"Stationery",
            "type":"Manufacturing & Wholesale Goods"
        }
    ],
    "sg:phone":"+1 570 775 7475",
    "sg:postcode":"18428",
    "sg:province":"PA",
    "sg:tags":[
        "packaging",
        "material"
    ],
    "wof:name":"Versiflex Products Inc",
    "wof:placetype":"venue"
},
  "geometry": {"coordinates":[-75.06182099999999,41.337966],"type":"Point"}
}