{
  "type": "Feature",
  "properties": {
    "iso:country":"US",
    "sg:address":"295 Old Mill Rd",
    "sg:city":"Apollo",
    "sg:classifiers":[
        {
            "category":"Real Estate",
            "subcategory":"Real Estate Services",
            "type":"Services"
        },
        {
            "category":"Building & Trades",
            "subcategory":"Cleaning & Sanitation",
            "type":"Services"
        }
    ],
    "sg:phone":"+1 724 727 2833",
    "sg:postcode":"15613",
    "sg:province":"PA",
    "sg:tags":[
        "maintenance",
        "cleaners-interior"
    ],
    "wof:name":"Floyd's Maintenance",
    "wof:placetype":"venue"
},
  "geometry": {"coordinates":[-79.57657399999999,40.56937],"type":"Point"}
}