{
  "type": "Feature",
  "properties": {
    "addr:full":"380 Beaver Ave Aliquippa PA 15001",
    "addr:housenumber":"380",
    "addr:postcode":"15001",
    "addr:street":"Beaver Ave",
    "iso:country":"US",
    "sg:address":"380 Beaver Ave",
    "sg:city":"Aliquippa",
    "sg:classifiers":[
        {
            "category":"Restaurant",
            "type":"Food & Drink"
        }
    ],
    "sg:phone":"+1   ",
    "sg:postcode":"15001",
    "sg:province":"PA",
    "sg:tags":[
        "eating"
    ],
    "wof:name":"Kohr Bros Frozen Custard",
    "wof:placetype":"venue"
},
  "geometry": {"coordinates":[-80.24179599999999,40.637984],"type":"Point"}
}