{
  "type": "Feature",
  "properties": {
    "iso:country":"US",
    "sg:address":"3144 Jefferson Ave",
    "sg:city":"Washington",
    "sg:classifiers":[
        {
            "category":"Building & Trades",
            "subcategory":"Construction",
            "type":"Services"
        }
    ],
    "sg:phone":"+1   ",
    "sg:postcode":"15301",
    "sg:province":"PA",
    "sg:tags":[
        "house"
    ],
    "wof:name":"Tri State Remodeling",
    "wof:placetype":"venue"
},
  "geometry": {"coordinates":[-80.328531,40.2076],"type":"Point"}
}