{
  "type": "Feature",
  "properties": {
    "addr:full":"220 Moore St Philadelphia PA 19148",
    "addr:housenumber":"220",
    "addr:postcode":"19148",
    "addr:street":"Moore St",
    "iso:country":"US",
    "sg:address":"220 Moore St",
    "sg:city":"Philadelphia",
    "sg:classifiers":[
        {
            "category":"Professional",
            "subcategory":"Advertising",
            "type":"Services"
        }
    ],
    "sg:phone":"+1   ",
    "sg:postcode":"19148",
    "sg:province":"PA",
    "sg:tags":[
        "agency",
        "full"
    ],
    "wof:name":"Mecklerstone Inc",
    "wof:placetype":"venue"
},
  "geometry": {"coordinates":[-75.151544,39.925675],"type":"Point"}
}