{
  "type": "Feature",
  "properties": {
    "iso:country":"US",
    "sg:address":"150 Mosside Blvd",
    "sg:city":"North Versailles",
    "sg:classifiers":[
        {
            "category":"Retail",
            "subcategory":"Auto Repair",
            "type":"Services"
        }
    ],
    "sg:phone":"+1 412 823 3288",
    "sg:postcode":"15137",
    "sg:province":"PA",
    "sg:tags":[
        "repairing",
        "automobile"
    ],
    "wof:name":"Chalfant Auto Svc",
    "wof:placetype":"venue"
},
  "geometry": {"coordinates":[-79.776831,40.376402],"type":"Point"}
}