{
  "type": "Feature",
  "properties": {
    "iso:country":"US",
    "sg:address":"119 Sunrise Ln",
    "sg:city":"Pottstown",
    "sg:classifiers":[
        {
            "category":"Building & Trades",
            "subcategory":"Landscaping Services",
            "type":"Services"
        }
    ],
    "sg:phone":"+1   ",
    "sg:postcode":"19464",
    "sg:province":"PA",
    "sg:tags":[
        "landscape"
    ],
    "wof:name":"Natures View Landscape Co",
    "wof:placetype":"venue"
},
  "geometry": {"coordinates":[-75.607697,40.261845],"type":"Point"}
}