{
  "type": "Feature",
  "properties": {
    "addr:full":"25 W Locust St Ephrata PA 17522",
    "addr:housenumber":"25",
    "addr:postcode":"17522",
    "addr:street":"W Locust St",
    "iso:country":"US",
    "sg:address":"25 W Locust St",
    "sg:city":"Ephrata",
    "sg:classifiers":[
        {
            "category":"Health Services",
            "subcategory":"Nursing And Care Facility",
            "type":"Services"
        }
    ],
    "sg:phone":"+1 717 733 2310",
    "sg:postcode":"17522",
    "sg:province":"PA",
    "sg:tags":[
        "personal",
        "home"
    ],
    "wof:name":"Specialized Assisted Living",
    "wof:placetype":"venue"
},
  "geometry": {"coordinates":[-76.175543,40.179892],"type":"Point"}
}