{
  "type": "Feature",
  "properties": {
    "iso:country":"US",
    "sg:address":"4311 Kutztown Rd",
    "sg:city":"Temple",
    "sg:classifiers":[
        {
            "category":"Building & Trades",
            "subcategory":"Construction",
            "type":"Services"
        }
    ],
    "sg:phone":"+1 610 929 4400",
    "sg:postcode":"19560",
    "sg:province":"PA",
    "sg:tags":[
        "asbestos",
        "removal"
    ],
    "wof:name":"Asbestos & Lead Abatement Svc",
    "wof:placetype":"venue"
},
  "geometry": {"coordinates":[-75.91974999999999,40.401837],"type":"Point"}
}