{
  "type": "Feature",
  "properties": {
    "iso:country":"US",
    "sg:address":"7874 Admiral Peary Hwy",
    "sg:city":"Cresson",
    "sg:classifiers":[
        {
            "category":"Restaurant",
            "type":"Food & Drink"
        }
    ],
    "sg:phone":"+1   ",
    "sg:postcode":"16630",
    "sg:province":"PA",
    "sg:tags":[
        "eating"
    ],
    "wof:name":"P JS Tavern",
    "wof:placetype":"venue"
},
  "geometry": {"coordinates":[-78.57742500000001,40.457904],"type":"Point"}
}