{
  "type": "Feature",
  "properties": {
    "iso:country":"US",
    "sg:address":"7780 Saegersville Rd",
    "sg:city":"Slatington",
    "sg:classifiers":[
        {
            "category":"Farming",
            "subcategory":"Farm",
            "type":"Manufacturing & Wholesale Goods"
        }
    ],
    "sg:phone":"+1   ",
    "sg:postcode":"18080",
    "sg:province":"PA",
    "sg:tags":[
        "crop",
        "general"
    ],
    "wof:name":"Kovalchik Farms",
    "wof:placetype":"venue"
},
  "geometry": {"coordinates":[-75.682346,40.722337],"type":"Point"}
}