{
  "type": "Feature",
  "properties": {
    "addr:full":"364 W Trenton Ave Morrisville PA 19067",
    "addr:housenumber":"364",
    "addr:postcode":"19067",
    "addr:street":"W Trenton Ave",
    "iso:country":"US",
    "sg:address":"364 W Trenton Ave",
    "sg:city":"Morrisville",
    "sg:classifiers":[
        {
            "category":"Professional",
            "subcategory":"Printing & Photocopies",
            "type":"Services"
        }
    ],
    "sg:phone":"+1 215 428 4740",
    "sg:postcode":"19067",
    "sg:province":"PA",
    "sg:tags":[
        "duplicating",
        "copying"
    ],
    "sg:website":"http://www.minutemanpress.com",
    "wof:name":"Minuteman Press",
    "wof:placetype":"venue"
},
  "geometry": {"coordinates":[-74.797803,40.209704],"type":"Point"}
}