{
  "type": "Feature",
  "properties": {
    "iso:country":"US",
    "sg:address":"4 Daffodil Pl",
    "sg:city":"Newtown",
    "sg:classifiers":[
        {
            "category":"Food & Beverages",
            "subcategory":"Specialty",
            "type":"Retail Goods"
        }
    ],
    "sg:phone":"+1   ",
    "sg:postcode":"18940",
    "sg:province":"PA",
    "wof:name":"Mindy & Albert Wasilewski",
    "wof:placetype":"venue"
},
  "geometry": {"coordinates":[-74.950963,40.26237],"type":"Point"}
}