{
  "type": "Feature",
  "properties": {
    "iso:country":"US",
    "sg:address":"1605 N Cedar Crest Blvd",
    "sg:city":"Allentown",
    "sg:classifiers":[
        {
            "category":"Professional",
            "type":"Services"
        },
        {
            "category":"Professional",
            "subcategory":"Management & Consulting",
            "type":"Services"
        }
    ],
    "sg:phone":"+1 610 821 8650",
    "sg:postcode":"18104",
    "sg:province":"PA",
    "sg:tags":[
        "establishment",
        "benefit",
        "design",
        "plan",
        "marketing"
    ],
    "wof:name":"Andesa Companies",
    "wof:placetype":"venue"
},
  "geometry": {"coordinates":[-75.533294,40.613757],"type":"Point"}
}