{
  "type": "Feature",
  "properties": {
    "addr:full":"1484 US Hwy 220 Bedford PA 15522",
    "addr:housenumber":"1484",
    "addr:postcode":"15522",
    "addr:street":"Us Hwy 220",
    "iso:country":"US",
    "sg:address":"1484 US Hwy 220",
    "sg:city":"Bedford",
    "sg:classifiers":[
        {
            "category":"Autos & Motor Vehicles",
            "subcategory":"Automobile Sales",
            "type":"Retail Goods"
        }
    ],
    "sg:phone":"+1 814 623 0004",
    "sg:postcode":"15522",
    "sg:province":"PA",
    "sg:tags":[
        "car",
        "dealer"
    ],
    "wof:name":"Fisher's Auto Sales",
    "wof:placetype":"venue"
},
  "geometry": {"coordinates":[-78.69690900000001,39.757205],"type":"Point"}
}