{
  "type": "Feature",
  "properties": {
    "iso:country":"US",
    "sg:address":"724 Cobham Park Rd",
    "sg:city":"Warren",
    "sg:classifiers":[
        {
            "category":"Professional",
            "subcategory":"Computer Services",
            "type":"Services"
        }
    ],
    "sg:phone":"+1   ",
    "sg:postcode":"16365",
    "sg:province":"PA",
    "sg:tags":[
        "programing",
        "custom"
    ],
    "wof:name":"Sdc Associates Inc",
    "wof:placetype":"venue"
},
  "geometry": {"coordinates":[-79.08268700000001,41.860894],"type":"Point"}
}