{
  "type": "Feature",
  "properties": {
    "addr:full":"478 Jeffers St Du Bois PA 15801",
    "addr:housenumber":"478",
    "addr:postcode":"15801",
    "addr:street":"Jeffers St Du Bois",
    "iso:country":"US",
    "sg:address":"478 Jeffers St",
    "sg:city":"Du Bois",
    "sg:classifiers":[
        {
            "category":"Banks & Credit Unions",
            "subcategory":"Financial Services",
            "type":"Services"
        }
    ],
    "sg:phone":"+1 814 375 1372",
    "sg:postcode":"15801",
    "sg:province":"PA",
    "sg:tags":[
        "trust",
        "nonprofit",
        "management"
    ],
    "wof:name":"Headwaters Charitable Trust",
    "wof:placetype":"venue"
},
  "geometry": {"coordinates":[-78.752999,41.121172],"type":"Point"}
}