{
  "type": "Feature",
  "properties": {
    "iso:country":"US",
    "sg:address":"5824 Forbes Ave",
    "sg:city":"Pittsburgh",
    "sg:classifiers":[
        {
            "category":"Restaurant",
            "type":"Food & Drink"
        }
    ],
    "sg:phone":"+1 412 521 5505",
    "sg:postcode":"15217",
    "sg:province":"PA",
    "sg:tags":[
        "grill",
        "bar"
    ],
    "wof:name":"Mediterranean Grill",
    "wof:placetype":"venue"
},
  "geometry": {"coordinates":[-79.922136,40.43809],"type":"Point"}
}