{
  "type": "Feature",
  "properties": {
    "iso:country":"US",
    "sg:address":"118 E Pennsylvania Ave",
    "sg:city":"Mt Union",
    "sg:classifiers":[
        {
            "category":"Manufacturing",
            "subcategory":"Glass & Minerals",
            "type":"Manufacturing & Wholesale Goods"
        }
    ],
    "sg:phone":"+1 814 542 4921",
    "sg:postcode":"17066",
    "sg:province":"PA",
    "sg:tags":[
        "fabricator",
        "fiber"
    ],
    "wof:name":"R W Diven Fiberglass Repair",
    "wof:placetype":"venue"
},
  "geometry": {"coordinates":[-77.87779999999999,40.383893],"type":"Point"}
}