{
  "type": "Feature",
  "properties": {
    "addr:full":"12 S 8th St Stroudsburg PA 18360",
    "addr:housenumber":"12",
    "addr:postcode":"18360",
    "addr:street":"S 8Th St",
    "iso:country":"US",
    "sg:address":"12 S 8th St",
    "sg:city":"Stroudsburg",
    "sg:classifiers":[
        {
            "category":"Travel",
            "subcategory":"Bed & Breakfast",
            "type":"Entertainment"
        }
    ],
    "sg:phone":"+1   ",
    "sg:postcode":"18360",
    "sg:province":"PA",
    "sg:tags":[
        "house"
    ],
    "wof:name":"Carlton House",
    "wof:placetype":"venue"
},
  "geometry": {"coordinates":[-75.195618,40.984194],"type":"Point"}
}