{
  "type": "Feature",
  "properties": {
    "iso:country":"US",
    "sg:address":"6327 Trotter St",
    "sg:city":"Philadelphia",
    "sg:classifiers":[
        {
            "category":"Shopping",
            "type":"Retail Goods"
        }
    ],
    "sg:phone":"+1   ",
    "sg:postcode":"19111",
    "sg:province":"PA",
    "sg:tags":[
        "security",
        "installation",
        "system",
        "sales"
    ],
    "wof:name":"Tcd Security Systems Intl",
    "wof:placetype":"venue"
},
  "geometry": {"coordinates":[-75.083519,40.042368],"type":"Point"}
}