{
  "type": "Feature",
  "properties": {
    "iso:country":"US",
    "sg:address":"2755 Kensington Ave",
    "sg:city":"Philadelphia",
    "sg:classifiers":[
        {
            "category":"Organizations",
            "subcategory":"Religious Organization",
            "type":"Services"
        }
    ],
    "sg:phone":"+1 215 739 3927",
    "sg:postcode":"19134",
    "sg:province":"PA",
    "wof:name":"Rock Ministries Of Phila",
    "wof:placetype":"venue"
},
  "geometry": {"coordinates":[-75.123587,39.99088],"type":"Point"}
}