{
  "type": "Feature",
  "properties": {
    "addr:full":"10090 Old Perry Hwy Wexford PA 15090",
    "addr:housenumber":"10090",
    "addr:postcode":"15090",
    "addr:street":"Old Perry Hwy",
    "iso:country":"US",
    "sg:address":"10090 Old Perry Hwy",
    "sg:city":"Wexford",
    "sg:classifiers":[
        {
            "category":"Organizations",
            "subcategory":"Religious Organization",
            "type":"Services"
        }
    ],
    "sg:phone":"+1   ",
    "sg:postcode":"15090",
    "sg:province":"PA",
    "wof:name":"Diocese of Pittsburgh",
    "wof:placetype":"venue"
},
  "geometry": {"coordinates":[-80.046026,40.597436],"type":"Point"}
}