{
  "type": "Feature",
  "properties": {
    "addr:full":"103 Pine Run Rd Freedom PA 15042",
    "addr:housenumber":"103",
    "addr:postcode":"15042",
    "addr:street":"Pine Run Rd",
    "iso:country":"US",
    "sg:address":"103 Pine Run Rd",
    "sg:city":"Freedom",
    "sg:classifiers":[
        {
            "category":"Building & Trades",
            "subcategory":"Cleaning & Sanitation",
            "type":"Services"
        }
    ],
    "sg:phone":"+1 724 775 1320",
    "sg:postcode":"15042",
    "sg:province":"PA",
    "sg:tags":[
        "janitor",
        "maintenance"
    ],
    "wof:name":"Bluewater Cleaning Service",
    "wof:placetype":"venue"
},
  "geometry": {"coordinates":[-80.236169,40.694912],"type":"Point"}
}