{
  "type": "Feature",
  "properties": {
    "addr:full":"1321 Pine Rd Bryn Mawr PA 19010",
    "addr:housenumber":"1321",
    "addr:postcode":"19010",
    "addr:street":"Pine Rd",
    "iso:country":"US",
    "sg:address":"1321 Pine Rd",
    "sg:city":"Bryn Mawr",
    "sg:classifiers":[
        {
            "category":"Banks & Credit Unions",
            "subcategory":"Financial Services",
            "type":"Services"
        }
    ],
    "sg:phone":"+1   ",
    "sg:postcode":"19010",
    "sg:province":"PA",
    "sg:tags":[
        "trust",
        "management"
    ],
    "wof:name":"McKeel Family Partners LP",
    "wof:placetype":"venue"
},
  "geometry": {"coordinates":[-75.325874,40.037288],"type":"Point"}
}