{
  "type": "Feature",
  "properties": {
    "iso:country":"US",
    "sg:address":"1848 Union Ave",
    "sg:city":"Natrona Heights",
    "sg:classifiers":[
        {
            "category":"Shopping",
            "subcategory":"Books",
            "type":"Retail Goods"
        }
    ],
    "sg:phone":"+1 724 226 3322",
    "sg:postcode":"15065",
    "sg:province":"PA",
    "sg:tags":[
        "dealer"
    ],
    "wof:name":"Family Christian Book Store",
    "wof:placetype":"venue"
},
  "geometry": {"coordinates":[-79.724673,40.621951],"type":"Point"}
}