{
  "type": "Feature",
  "properties": {
    "addr:full":"1333 Pine St Apt 4 Philadelphia PA 19107",
    "addr:housenumber":"1333;4",
    "addr:postcode":"19107",
    "addr:street":"Pine St Apt",
    "iso:country":"US",
    "sg:address":"1333 Pine St Apt 4",
    "sg:city":"Philadelphia",
    "sg:classifiers":[
        {
            "category":"Manufacturing",
            "subcategory":"Buildings",
            "type":"Manufacturing & Wholesale Goods"
        },
        {
            "category":"Building & Trades",
            "subcategory":"Construction",
            "type":"Services"
        }
    ],
    "sg:phone":"+1 215 432 3040",
    "sg:postcode":"19107",
    "sg:province":"PA",
    "sg:tags":[
        "home",
        "builder",
        "contractor"
    ],
    "wof:name":"Far From Home Cafe",
    "wof:placetype":"venue"
},
  "geometry": {"coordinates":[-75.164131,39.945475],"type":"Point"}
}