{
  "type": "Feature",
  "properties": {
    "addr:full":"560 Bair Rd Berwyn PA 19312",
    "addr:housenumber":"560",
    "addr:postcode":"19312",
    "addr:street":"Bair Rd",
    "iso:country":"US",
    "sg:address":"560 Bair Rd",
    "sg:city":"Berwyn",
    "sg:classifiers":[
        {
            "category":"Insurance",
            "subcategory":"Insurance Agent",
            "type":"Services"
        },
        {
            "category":"Insurance",
            "subcategory":"Hazard Insurance",
            "type":"Services"
        }
    ],
    "sg:phone":"+1 610 647 5920",
    "sg:postcode":"19312",
    "sg:province":"PA",
    "sg:tags":[
        "fire",
        "property",
        "casualty"
    ],
    "sg:website":"http://www.ecomponline.com",
    "wof:name":"Aon",
    "wof:placetype":"venue"
},
  "geometry": {"coordinates":[-75.44319400000001,40.057609],"type":"Point"}
}