{
  "type": "Feature",
  "properties": {
    "iso:country":"US",
    "sg:address":"15 W State St",
    "sg:city":"Avondale",
    "sg:classifiers":[
        {
            "category":"Food & Beverages",
            "subcategory":"Bakery",
            "type":"Retail Goods"
        }
    ],
    "sg:phone":"+1 610 268 2123",
    "sg:postcode":"19311",
    "sg:province":"PA",
    "sg:tags":[
        "sandwich"
    ],
    "wof:name":"Earl's Sub Shop",
    "wof:placetype":"venue"
},
  "geometry": {"coordinates":[-75.78360000000001,39.824501],"type":"Point"}
}