{
  "type": "Feature",
  "properties": {
    "iso:country":"US",
    "sg:address":"607 E Church Ln",
    "sg:city":"Philadelphia",
    "sg:classifiers":[
        {
            "category":"Real Estate",
            "subcategory":"Real Estate Agent",
            "type":"Services"
        }
    ],
    "sg:phone":"+1 215 849 5433",
    "sg:postcode":"19144",
    "sg:province":"PA",
    "sg:tags":[
        "management"
    ],
    "wof:name":"Church Lane Apartments",
    "wof:placetype":"venue"
},
  "geometry": {"coordinates":[-75.16180199999999,40.042909],"type":"Point"}
}