{
  "type": "Feature",
  "properties": {
    "addr:full":"100 Vip Dr Wexford PA 15090",
    "addr:housenumber":"100",
    "addr:postcode":"15090",
    "addr:street":"Vip Dr",
    "iso:country":"US",
    "sg:address":"100 Vip Dr",
    "sg:city":"Wexford",
    "sg:classifiers":[
        {
            "category":"Shopping",
            "type":"Retail Goods"
        }
    ],
    "sg:phone":"+1 724 933 5557",
    "sg:postcode":"15090",
    "sg:province":"PA",
    "sg:tags":[
        "product",
        "wire",
        "fabricated",
        "merchandise",
        "mfg"
    ],
    "wof:name":"Frames & More",
    "wof:placetype":"venue"
},
  "geometry": {"coordinates":[-80.093823,40.620214],"type":"Point"}
}