{
  "type": "Feature",
  "properties": {
    "iso:country":"US",
    "sg:address":"431 Mill St",
    "sg:city":"Coraopolis",
    "sg:classifiers":[
        {
            "category":"Restaurant",
            "type":"Food & Drink"
        }
    ],
    "sg:phone":"+1 412 269 1703",
    "sg:postcode":"15108",
    "sg:province":"PA",
    "sg:tags":[
        "shop",
        "coffee",
        "eating"
    ],
    "wof:name":"Poppy's Coffee Corner",
    "wof:placetype":"venue"
},
  "geometry": {"coordinates":[-80.16395900000001,40.517979],"type":"Point"}
}