{
  "type": "Feature",
  "properties": {
    "iso:country":"US",
    "sg:address":"725 Skippack Pike",
    "sg:city":"Blue Bell",
    "sg:classifiers":[
        {
            "category":"Professional",
            "subcategory":"Research",
            "type":"Services"
        }
    ],
    "sg:phone":"+1 215 540 0496",
    "sg:postcode":"19422",
    "sg:province":"PA",
    "wof:name":"Research Pharmaceutical Search",
    "wof:placetype":"venue"
},
  "geometry": {"coordinates":[-75.27096,40.155403],"type":"Point"}
}