{
  "type": "Feature",
  "properties": {
    "iso:country":"US",
    "sg:address":"1100 Muldowney Ave",
    "sg:city":"Pittsburgh",
    "sg:classifiers":[
        {
            "category":"Personal",
            "subcategory":"Beauty Salon",
            "type":"Services"
        }
    ],
    "sg:phone":"+1 412 461 8661",
    "sg:postcode":"15207",
    "sg:province":"PA",
    "sg:tags":[
        "shop"
    ],
    "wof:name":"Vanities Hair Salon",
    "wof:placetype":"venue"
},
  "geometry": {"coordinates":[-79.91557299999999,40.368774],"type":"Point"}
}