{
  "type": "Feature",
  "properties": {
    "addr:full":"10770 Rte 322 Shippenville PA 16254",
    "addr:housenumber":"10770",
    "addr:postcode":"16254",
    "addr:street":"Rte 322 Shippenville",
    "iso:country":"US",
    "sg:address":"10770 Rte 322",
    "sg:city":"Shippenville",
    "sg:classifiers":[
        {
            "category":"Autos & Motor Vehicles",
            "subcategory":"Automobile Sales",
            "type":"Retail Goods"
        }
    ],
    "sg:phone":"+1 814 226 4239",
    "sg:postcode":"16254",
    "sg:province":"PA",
    "sg:tags":[
        "car",
        "dealer"
    ],
    "wof:name":"Auto's 4 Less",
    "wof:placetype":"venue"
},
  "geometry": {"coordinates":[-79.418854,41.237818],"type":"Point"}
}