{
  "type": "Feature",
  "properties": {
    "addr:full":"1250 Bethlehem Pike Unit S Hatfield PA 19440",
    "addr:housenumber":"1250",
    "addr:postcode":"19440",
    "addr:street":"Bethlehem Pike Unit S",
    "iso:country":"US",
    "sg:address":"1250 Bethlehem Pike Unit S",
    "sg:city":"Hatfield",
    "sg:classifiers":[
        {
            "category":"Professional",
            "subcategory":"Lawyer & Legal Services",
            "type":"Services"
        }
    ],
    "sg:phone":"+1 215 997 2212",
    "sg:postcode":"19440",
    "sg:province":"PA",
    "sg:tags":[
        "notary"
    ],
    "sg:website":"www.theupsstore.com",
    "wof:name":"Ups Store the",
    "wof:placetype":"venue"
},
  "geometry": {"coordinates":[-75.26536299999999,40.287236],"type":"Point"}
}