{
  "type": "Feature",
  "properties": {
    "iso:country":"US",
    "sg:address":"153 Campmeeting Rd",
    "sg:city":"Crystal Spring",
    "sg:classifiers":[
        {
            "category":"Retail",
            "subcategory":"Auto Repair",
            "type":"Services"
        }
    ],
    "sg:phone":"+1 814 735 4337",
    "sg:postcode":"15536",
    "sg:province":"PA",
    "sg:tags":[
        "repairing",
        "automobile",
        "general"
    ],
    "wof:name":"Fischer's Garage Inc",
    "wof:placetype":"venue"
},
  "geometry": {"coordinates":[-78.229071,39.947758],"type":"Point"}
}