{
  "type": "Feature",
  "properties": {
    "iso:country":"US",
    "sg:address":"453 Drinker St",
    "sg:city":"Bloomsburg",
    "sg:classifiers":[
        {
            "category":"Real Estate",
            "subcategory":"Real Estate Agent",
            "type":"Services"
        }
    ],
    "sg:phone":"+1   ",
    "sg:postcode":"17815",
    "sg:province":"PA",
    "wof:name":"Yocum & Keyser Property MGT",
    "wof:placetype":"venue"
},
  "geometry": {"coordinates":[-76.46664,41.001425],"type":"Point"}
}