{
  "type": "Feature",
  "properties": {
    "iso:country":"US",
    "sg:address":"2142 Darby Rd",
    "sg:city":"Havertown",
    "sg:classifiers":[
        {
            "category":"Retail",
            "subcategory":"Auto Repair",
            "type":"Services"
        }
    ],
    "sg:phone":"+1 610 853 5400",
    "sg:postcode":"19083",
    "sg:province":"PA",
    "sg:tags":[
        "repairing",
        "automobile"
    ],
    "wof:name":"J & M Inc",
    "wof:placetype":"venue"
},
  "geometry": {"coordinates":[-75.308966,39.986425],"type":"Point"}
}