{
  "type": "Feature",
  "properties": {
    "iso:country":"US",
    "sg:address":"106 W Mahoning St",
    "sg:city":"Punxsutawney",
    "sg:classifiers":[
        {
            "category":"Shopping",
            "subcategory":"Clothing, Apparel, & Fashions",
            "type":"Retail Goods"
        }
    ],
    "sg:phone":"+1   ",
    "sg:postcode":"15767",
    "sg:province":"PA",
    "sg:tags":[
        "sportswear",
        "suit"
    ],
    "wof:name":"Willies Mens and Boys Wear",
    "wof:placetype":"venue"
},
  "geometry": {"coordinates":[-78.971219,40.943571],"type":"Point"}
}