{
  "type": "Feature",
  "properties": {
    "addr:full":"2407 Wylie Ave Pittsburgh PA 15219",
    "addr:housenumber":"2407",
    "addr:postcode":"15219",
    "addr:street":"Wylie Ave",
    "iso:country":"US",
    "sg:address":"2407 Wylie Ave",
    "sg:city":"Pittsburgh",
    "sg:classifiers":[
        {
            "category":"Restaurant",
            "type":"Food & Drink"
        }
    ],
    "sg:phone":"+1 412 682 9627",
    "sg:postcode":"15219",
    "sg:province":"PA",
    "sg:tags":[
        "operation",
        "eating"
    ],
    "wof:name":"Flamingo Hotel",
    "wof:placetype":"venue"
},
  "geometry": {"coordinates":[-79.972734,40.447738],"type":"Point"}
}