{
  "type": "Feature",
  "properties": {
    "iso:country":"US",
    "sg:address":"421 Hidden River Rd",
    "sg:city":"Narberth",
    "sg:classifiers":[
        {
            "category":"Health Services",
            "subcategory":"Doctor",
            "type":"Services"
        }
    ],
    "sg:phone":"+1 610 667 2063",
    "sg:postcode":"19072",
    "sg:province":"PA",
    "sg:tags":[
        "physician",
        "surgeon"
    ],
    "wof:name":"Theodore B Cohen MD",
    "wof:placetype":"venue"
},
  "geometry": {"coordinates":[-75.25050899999999,40.038335],"type":"Point"}
}