{
  "type": "Feature",
  "properties": {
    "iso:country":"US",
    "sg:address":"8600 E Barkhurst Dr",
    "sg:city":"Pittsburgh",
    "sg:classifiers":[
        {
            "category":"Professional",
            "subcategory":"Accounting & Tax Preparation",
            "type":"Services"
        }
    ],
    "sg:phone":"+1 412 630 9123",
    "sg:postcode":"15237",
    "sg:province":"PA",
    "sg:tags":[
        "return",
        "filing"
    ],
    "wof:name":"Barbara Fritsch",
    "wof:placetype":"venue"
},
  "geometry": {"coordinates":[-80.05431299999999,40.563155],"type":"Point"}
}