{
  "type": "Feature",
  "properties": {
    "iso:country":"US",
    "sg:address":"110 Greenwood Dr",
    "sg:city":"New Cumberland",
    "sg:classifiers":[
        {
            "category":"Manufacturing",
            "subcategory":"Lumber",
            "type":"Manufacturing & Wholesale Goods"
        }
    ],
    "sg:phone":"+1 717 938 9136",
    "sg:postcode":"17070",
    "sg:province":"PA",
    "sg:tags":[
        "forester"
    ],
    "wof:name":"Gerber Forestry Svc",
    "wof:placetype":"venue"
},
  "geometry": {"coordinates":[-76.848713,40.185442],"type":"Point"}
}