{
  "type": "Feature",
  "properties": {
    "iso:country":"US",
    "sg:address":"7022 Redcoat Dr",
    "sg:city":"Flourtown",
    "sg:classifiers":[
        {
            "category":"Professional",
            "type":"Services"
        }
    ],
    "sg:phone":"+1   ",
    "sg:postcode":"19031",
    "sg:province":"PA",
    "wof:name":"Angela D Riggs Music Specialis",
    "wof:placetype":"venue"
},
  "geometry": {"coordinates":[-75.209598,40.119868],"type":"Point"}
}