{
  "type": "Feature",
  "properties": {
    "iso:country":"US",
    "sg:address":"508 Methodist Rd",
    "sg:city":"Greenville",
    "sg:classifiers":[
        {
            "category":"Real Estate",
            "subcategory":"Real Estate Operator",
            "type":"Services"
        }
    ],
    "sg:phone":"+1   ",
    "sg:postcode":"16125",
    "sg:province":"PA",
    "sg:tags":[
        "building",
        "apartment"
    ],
    "wof:name":"Greenlees Hlday Mnor Aprtments",
    "wof:placetype":"venue"
},
  "geometry": {"coordinates":[-80.35061,41.393754],"type":"Point"}
}