{
  "type": "Feature",
  "properties": {
    "iso:country":"US",
    "sg:address":"44 Amsler Ave",
    "sg:city":"Shippenville",
    "sg:classifiers":[
        {
            "category":"Home & Garden",
            "subcategory":"Home Furnishings",
            "type":"Retail Goods"
        },
        {
            "category":"Manufacturing",
            "subcategory":"Rubber & Plastics",
            "type":"Manufacturing & Wholesale Goods"
        }
    ],
    "sg:phone":"+1 814 226 5374",
    "sg:postcode":"16254",
    "sg:province":"PA",
    "sg:tags":[
        "bathroom",
        "mfg",
        "fixture",
        "sp",
        "metal",
        "accessory",
        "plumbing",
        "sanitary",
        "ware"
    ],
    "sg:website":"www.clarionbathware.com",
    "wof:name":"Clarion Bathware Inc",
    "wof:placetype":"venue"
},
  "geometry": {"coordinates":[-79.427311,41.239587],"type":"Point"}
}