{
  "type": "Feature",
  "properties": {
    "addr:full":"540 W Penn Ave Reading PA 19608",
    "addr:housenumber":"540",
    "addr:postcode":"19608",
    "addr:street":"W Penn Ave",
    "iso:country":"US",
    "sg:address":"540 W Penn Ave",
    "sg:city":"Reading",
    "sg:classifiers":[
        {
            "category":"Government",
            "subcategory":"Office",
            "type":"Public Place"
        }
    ],
    "sg:phone":"+1   ",
    "sg:postcode":"19608",
    "sg:province":"PA",
    "sg:tags":[
        "municipal"
    ],
    "wof:name":"Sinking Spring Borough of",
    "wof:placetype":"venue"
},
  "geometry": {"coordinates":[-76.02118400000001,40.325262],"type":"Point"}
}