{
  "type": "Feature",
  "properties": {
    "iso:country":"US",
    "sg:address":"5 Grandview Ave Ste 2",
    "sg:city":"Pittsburgh",
    "sg:classifiers":[
        {
            "category":"Organizations",
            "subcategory":"Religious Organization",
            "type":"Services"
        }
    ],
    "sg:phone":"+1 412 488 5090",
    "sg:postcode":"15211",
    "sg:province":"PA",
    "wof:name":"Passionist Overseas Missions",
    "wof:placetype":"venue"
},
  "geometry": {"coordinates":[-80.006119,40.431129],"type":"Point"}
}