{
  "type": "Feature",
  "properties": {
    "iso:country":"US",
    "sg:address":"591 Horsham Rd",
    "sg:city":"Horsham",
    "sg:classifiers":[
        {
            "category":"Retail",
            "subcategory":"Repair Shop",
            "type":"Services"
        }
    ],
    "sg:phone":"+1 215 674 5676",
    "sg:postcode":"19044",
    "sg:province":"PA",
    "sg:tags":[
        "appliance"
    ],
    "wof:name":"Holland Appliance",
    "wof:placetype":"venue"
},
  "geometry": {"coordinates":[-75.14605,40.18838],"type":"Point"}
}