{
  "type": "Feature",
  "properties": {
    "iso:country":"US",
    "sg:address":"312 Saint Joe Rd",
    "sg:city":"Chicora",
    "sg:classifiers":[
        {
            "category":"Professional",
            "subcategory":"Business Services",
            "type":"Services"
        }
    ],
    "sg:phone":"+1 724 283 2275",
    "sg:postcode":"16025",
    "sg:province":"PA",
    "sg:tags":[
        "drafting"
    ],
    "wof:name":"Christopher Skidmore",
    "wof:placetype":"venue"
},
  "geometry": {"coordinates":[-79.78779900000001,40.905514],"type":"Point"}
}