{
  "type": "Feature",
  "properties": {
    "iso:country":"US",
    "sg:address":"415 Lysle Blvd",
    "sg:city":"Mckeesport",
    "sg:classifiers":[
        {
            "category":"Social Services",
            "subcategory":"Child Care",
            "type":"Services"
        }
    ],
    "sg:phone":"+1 412 672 5510",
    "sg:postcode":"15132",
    "sg:province":"PA",
    "wof:name":"Allegheny Childcare Academy",
    "wof:placetype":"venue"
},
  "geometry": {"coordinates":[-79.86258599999999,40.351876],"type":"Point"}
}