{
  "type": "Feature",
  "properties": {
    "iso:country":"US",
    "sg:address":"310 Garden Rd",
    "sg:city":"Oreland",
    "sg:classifiers":[
        {
            "category":"Personal",
            "type":"Services"
        }
    ],
    "sg:phone":"+1   ",
    "sg:postcode":"19075",
    "sg:province":"PA",
    "sg:tags":[
        "reflexology",
        "therapy",
        "massage"
    ],
    "wof:name":"Healthy Horizons",
    "wof:placetype":"venue"
},
  "geometry": {"coordinates":[-75.172816,40.121054],"type":"Point"}
}