{
  "type": "Feature",
  "properties": {
    "iso:country":"US",
    "sg:address":"118 Rutledge Ave",
    "sg:city":"Morton",
    "sg:classifiers":[
        {
            "category":"Building & Trades",
            "subcategory":"Construction",
            "type":"Services"
        }
    ],
    "sg:phone":"+1   ",
    "sg:postcode":"19070",
    "sg:province":"PA",
    "sg:tags":[
        "house"
    ],
    "wof:name":"ONeil Construction",
    "wof:placetype":"venue"
},
  "geometry": {"coordinates":[-75.32822400000001,39.899417],"type":"Point"}
}