{
  "type": "Feature",
  "properties": {
    "iso:country":"US",
    "sg:address":"2341 Schoenersville Rd",
    "sg:city":"Bethlehem",
    "sg:classifiers":[
        {
            "category":"Utilities",
            "subcategory":"Mobile Phone",
            "type":"Services"
        }
    ],
    "sg:phone":"+1 610 882 9225",
    "sg:postcode":"18017",
    "sg:province":"PA",
    "sg:tags":[
        "communication",
        "radiotelephone"
    ],
    "wof:name":"K & B Productions",
    "wof:placetype":"venue"
},
  "geometry": {"coordinates":[-75.404291,40.644028],"type":"Point"}
}