{
  "type": "Feature",
  "properties": {
    "addr:full":"64 Lawrence Ave Southampton PA 18966",
    "addr:housenumber":"64",
    "addr:postcode":"18966",
    "addr:street":"Lawrence Ave",
    "iso:country":"US",
    "sg:address":"64 Lawrence Ave",
    "sg:city":"Southampton",
    "sg:classifiers":[
        {
            "category":"Wholesale",
            "subcategory":"Fruits & Vegetables",
            "type":"Manufacturing & Wholesale Goods"
        }
    ],
    "sg:phone":"+1   ",
    "sg:postcode":"18966",
    "sg:province":"PA",
    "sg:tags":[
        "distributor",
        "fresh",
        "produce"
    ],
    "wof:name":"Cohn Produce Co Inc",
    "wof:placetype":"venue"
},
  "geometry": {"coordinates":[-74.96361899999999,40.193791],"type":"Point"}
}