{
  "type": "Feature",
  "properties": {
    "iso:country":"US",
    "sg:address":"1879 E State St",
    "sg:city":"Hermitage",
    "sg:classifiers":[
        {
            "category":"Professional",
            "subcategory":"Lawyer & Legal Services",
            "type":"Services"
        }
    ],
    "sg:phone":"+1 724 346 2011",
    "sg:postcode":"16148",
    "sg:province":"PA",
    "sg:tags":[
        "attorney"
    ],
    "wof:name":"Robert Vitello",
    "wof:placetype":"venue"
},
  "geometry": {"coordinates":[-80.47405500000001,41.233385],"type":"Point"}
}