{
  "type": "Feature",
  "properties": {
    "iso:country":"US",
    "sg:address":"150 E Butter Rd",
    "sg:city":"York",
    "sg:classifiers":[
        {
            "category":"Building & Trades",
            "subcategory":"Construction",
            "type":"Services"
        }
    ],
    "sg:phone":"+1 717 266 1121",
    "sg:postcode":"17404",
    "sg:province":"PA",
    "sg:tags":[
        "excavation",
        "excavating",
        "work",
        "contractor"
    ],
    "wof:name":"Carl W Fidler Excavating",
    "wof:placetype":"venue"
},
  "geometry": {"coordinates":[-76.781936,40.067246],"type":"Point"}
}