{
  "type": "Feature",
  "properties": {
    "iso:country":"US",
    "sg:address":"821 Enterprise St",
    "sg:city":"Dickson City",
    "sg:classifiers":[
        {
            "category":"Retail",
            "subcategory":"Repair Shop",
            "type":"Services"
        },
        {
            "category":"Wholesale",
            "subcategory":"Electrical",
            "type":"Manufacturing & Wholesale Goods"
        }
    ],
    "sg:phone":"+1 570 383 2649",
    "sg:postcode":"18519",
    "sg:province":"PA",
    "sg:tags":[
        "repeater",
        "communication",
        "tr",
        "system",
        "sales",
        "radio",
        "pager"
    ],
    "wof:name":"Mol Communications & Elect",
    "wof:placetype":"venue"
},
  "geometry": {"coordinates":[-75.6176,41.461593],"type":"Point"}
}