{
  "type": "Feature",
  "properties": {
    "iso:country":"US",
    "sg:address":"724 Market St",
    "sg:city":"Philadelphia",
    "sg:classifiers":[
        {
            "category":"Wholesale",
            "subcategory":"Medical Equipment & Supplies",
            "type":"Manufacturing & Wholesale Goods"
        },
        {
            "category":"Shopping",
            "subcategory":"Pharmacy",
            "type":"Retail Goods"
        },
        {
            "category":"Health Services",
            "subcategory":"Dentist",
            "type":"Services"
        }
    ],
    "sg:phone":"+1 215 923 8281",
    "sg:postcode":"19106",
    "sg:province":"PA",
    "sg:tags":[
        "home",
        "dental",
        "care"
    ],
    "wof:name":"728 Market Street Inc",
    "wof:placetype":"venue"
},
  "geometry": {"coordinates":[-75.152376,39.950991],"type":"Point"}
}