{
  "type": "Feature",
  "properties": {
    "iso:country":"US",
    "sg:address":"51 Berger Rd",
    "sg:city":"Kutztown",
    "sg:classifiers":[
        {
            "category":"Farming",
            "subcategory":"Farm",
            "type":"Manufacturing & Wholesale Goods"
        }
    ],
    "sg:phone":"+1 610 683 6133",
    "sg:postcode":"19530",
    "sg:province":"PA",
    "wof:name":"R E Berger Farms",
    "wof:placetype":"venue"
},
  "geometry": {"coordinates":[-75.77726800000001,40.571724],"type":"Point"}
}