{
  "type": "Feature",
  "properties": {
    "iso:country":"US",
    "sg:address":"230 Executive Dr",
    "sg:city":"Cranberry Twp",
    "sg:classifiers":[
        {
            "category":"Government",
            "subcategory":"Office",
            "type":"Public Place"
        }
    ],
    "sg:phone":"+1 724 772 2333",
    "sg:postcode":"16066",
    "sg:province":"PA",
    "sg:tags":[
        "federal"
    ],
    "wof:name":"US Labor Dept",
    "wof:placetype":"venue"
},
  "geometry": {"coordinates":[-80.107933,40.687103],"type":"Point"}
}