{
  "type": "Feature",
  "properties": {
    "addr:full":"149 E Market St Hellam PA 17406",
    "addr:housenumber":"149",
    "addr:postcode":"17406",
    "addr:street":"E Market St",
    "iso:country":"US",
    "sg:address":"149 E Market St",
    "sg:city":"Hellam",
    "sg:classifiers":[
        {
            "category":"Professional",
            "subcategory":"Lawyer & Legal Services",
            "type":"Services"
        }
    ],
    "sg:phone":"+1 717 854 5800",
    "sg:postcode":"17406",
    "sg:province":"PA",
    "sg:tags":[
        "attorney"
    ],
    "wof:name":"Maria Musti Cook",
    "wof:placetype":"venue"
},
  "geometry": {"coordinates":[-76.60342900000001,40.005353],"type":"Point"}
}