{
  "type": "Feature",
  "properties": {
    "iso:country":"US",
    "sg:address":"708 E Haverford Rd",
    "sg:city":"Bryn Mawr",
    "sg:classifiers":[
        {
            "category":"Professional",
            "subcategory":"Computer Services",
            "type":"Services"
        }
    ],
    "sg:phone":"+1 610 525 6972",
    "sg:postcode":"19010",
    "sg:province":"PA",
    "sg:tags":[
        "repair"
    ],
    "wof:name":"Compuvision International LLC",
    "wof:placetype":"venue"
},
  "geometry": {"coordinates":[-75.315674,40.012102],"type":"Point"}
}