{
  "type": "Feature",
  "properties": {
    "addr:full":"671 State Rte 118 Sweet Valley PA 18656",
    "addr:housenumber":"671",
    "addr:postcode":"18656",
    "addr:street":"State Rte 118",
    "iso:country":"US",
    "sg:address":"671 State Rte 118",
    "sg:city":"Sweet Valley",
    "sg:classifiers":[
        {
            "category":"Government",
            "subcategory":"Fire Station",
            "type":"Public Place"
        }
    ],
    "sg:phone":"+1   ",
    "sg:postcode":"18656",
    "sg:province":"PA",
    "sg:tags":[
        "company",
        "volunteer"
    ],
    "wof:name":"Fairmount Township Volunteer",
    "wof:placetype":"venue"
},
  "geometry": {"coordinates":[-76.242009,41.304282],"type":"Point"}
}