{
  "type": "Feature",
  "properties": {
    "iso:country":"US",
    "sg:address":"73 N Memorial Hwy",
    "sg:city":"Shavertown",
    "sg:classifiers":[
        {
            "category":"Professional",
            "subcategory":"Accounting & Tax Preparation",
            "type":"Services"
        }
    ],
    "sg:phone":"+1   ",
    "sg:postcode":"18708",
    "sg:province":"PA",
    "wof:name":"Joseph R Mazzoni CPA",
    "wof:placetype":"venue"
},
  "geometry": {"coordinates":[-75.935304,41.311582],"type":"Point"}
}