{
  "type": "Feature",
  "properties": {
    "iso:country":"US",
    "sg:address":"4258 Main St",
    "sg:city":"Philadelphia",
    "sg:classifiers":[
        {
            "category":"Real Estate",
            "subcategory":"Real Estate Operator",
            "type":"Services"
        }
    ],
    "sg:phone":"+1 215 482 1401",
    "sg:postcode":"19127",
    "sg:province":"PA",
    "sg:tags":[
        "apartment"
    ],
    "wof:name":"Canal House Apartments the",
    "wof:placetype":"venue"
},
  "geometry": {"coordinates":[-75.22180400000001,40.024583],"type":"Point"}
}