{
  "type": "Feature",
  "properties": {
    "iso:country":"US",
    "sg:address":"222 Red Hill Rd",
    "sg:city":"Newport",
    "sg:classifiers":[
        {
            "category":"Wholesale",
            "subcategory":"Medical Equipment & Supplies",
            "type":"Manufacturing & Wholesale Goods"
        }
    ],
    "sg:phone":"+1 717 567 9374",
    "sg:postcode":"17074",
    "sg:province":"PA",
    "sg:tags":[
        "instrument",
        "surgical"
    ],
    "sg:website":"http://www.ntminc.net",
    "wof:name":"N. T. M., Inc.",
    "wof:placetype":"venue"
},
  "geometry": {"coordinates":[-77.091782,40.501282],"type":"Point"}
}