{
  "type": "Feature",
  "properties": {
    "iso:country":"US",
    "sg:address":"5711 Friendship Ave",
    "sg:city":"Pittsburgh",
    "sg:classifiers":[
        {
            "category":"Professional",
            "subcategory":"Art Services",
            "type":"Services"
        }
    ],
    "sg:phone":"+1 412 661 6150",
    "sg:postcode":"15232",
    "sg:province":"PA",
    "sg:tags":[
        "artist"
    ],
    "wof:name":"John Ritter Illustration",
    "wof:placetype":"venue"
},
  "geometry": {"coordinates":[-79.93204299999999,40.46064],"type":"Point"}
}