{
  "type": "Feature",
  "properties": {
    "iso:country":"US",
    "sg:address":"130 William Cir",
    "sg:city":"Mc Kees Rocks",
    "sg:classifiers":[
        {
            "category":"Professional",
            "subcategory":"Management & Consulting",
            "type":"Services"
        }
    ],
    "sg:phone":"+1 412 771 4757",
    "sg:postcode":"15136",
    "sg:province":"PA",
    "sg:tags":[
        "fire",
        "consultant",
        "protection"
    ],
    "wof:name":"Emergency Specialist Resources",
    "wof:placetype":"venue"
},
  "geometry": {"coordinates":[-80.08685199999999,40.48985],"type":"Point"}
}