{
  "type": "Feature",
  "properties": {
    "addr:full":"3638 E State St Hermitage PA 16148",
    "addr:housenumber":"3638",
    "addr:postcode":"16148",
    "addr:street":"E State St",
    "iso:country":"US",
    "sg:address":"3638 E State St",
    "sg:city":"Hermitage",
    "sg:classifiers":[
        {
            "category":"Real Estate",
            "subcategory":"Real Estate Services",
            "type":"Services"
        }
    ],
    "sg:phone":"+1 724 982 0401",
    "sg:postcode":"16148",
    "sg:province":"PA",
    "sg:tags":[
        "company",
        "title"
    ],
    "wof:name":"Precise Settlement Agency",
    "wof:placetype":"venue"
},
  "geometry": {"coordinates":[-80.442162,41.233953],"type":"Point"}
}