{
  "type": "Feature",
  "properties": {
    "addr:full":"1502 Alter St Philadelphia PA 19146",
    "addr:housenumber":"1502",
    "addr:postcode":"19146",
    "addr:street":"Alter St",
    "iso:country":"US",
    "sg:address":"1502 Alter St",
    "sg:city":"Philadelphia",
    "sg:classifiers":[
        {
            "category":"Retail",
            "subcategory":"Auto Repair",
            "type":"Services"
        }
    ],
    "sg:phone":"+1 215 772 0766",
    "sg:postcode":"19146",
    "sg:province":"PA",
    "wof:name":"Paul's Auto Service",
    "wof:placetype":"venue"
},
  "geometry": {"coordinates":[-75.16889999999999,39.9375],"type":"Point"}
}