{
  "type": "Feature",
  "properties": {
    "iso:country":"US",
    "sg:address":"11 Oak St",
    "sg:city":"Coatesville",
    "sg:classifiers":[
        {
            "category":"Organizations",
            "subcategory":"Religious Organization",
            "type":"Services"
        }
    ],
    "sg:phone":"+1 610 384 0783",
    "sg:postcode":"19320",
    "sg:province":"PA",
    "sg:tags":[
        "church"
    ],
    "wof:name":"St Nicholas Russian Orthodox",
    "wof:placetype":"venue"
},
  "geometry": {"coordinates":[-75.819991,39.978922],"type":"Point"}
}