{
  "type": "Feature",
  "properties": {
    "iso:country":"US",
    "sg:address":"5573 Hamilton Blvd",
    "sg:city":"Allentown",
    "sg:classifiers":[
        {
            "category":"Shopping",
            "type":"Retail Goods"
        },
        {
            "category":"Wholesale",
            "subcategory":"Non-durable Goods",
            "type":"Manufacturing & Wholesale Goods"
        }
    ],
    "sg:phone":"+1 610 395 3995",
    "sg:postcode":"18106",
    "sg:province":"PA",
    "sg:tags":[
        "candle",
        "decor",
        "silk",
        "flower",
        "home"
    ],
    "wof:name":"Early American Candle & Silk",
    "wof:placetype":"venue"
},
  "geometry": {"coordinates":[-75.565496,40.56145],"type":"Point"}
}