{
  "type": "Feature",
  "properties": {
    "iso:country":"US",
    "sg:address":"239 Rte 18",
    "sg:city":"Monaca",
    "sg:classifiers":[
        {
            "category":"Shopping",
            "subcategory":"Clothing, Apparel, & Fashions",
            "type":"Retail Goods"
        }
    ],
    "sg:phone":"+1 724 775 3433",
    "sg:postcode":"15061",
    "sg:province":"PA",
    "wof:name":"Limited",
    "wof:placetype":"venue"
},
  "geometry": {"coordinates":[-80.311948,40.671086],"type":"Point"}
}