{
  "type": "Feature",
  "properties": {
    "iso:country":"US",
    "sg:address":"6801 State Rd",
    "sg:city":"Philadelphia",
    "sg:classifiers":[
        {
            "category":"Retail",
            "subcategory":"Auto Repair",
            "type":"Services"
        }
    ],
    "sg:phone":"+1 215 413 5050",
    "sg:postcode":"19135",
    "sg:province":"PA",
    "sg:tags":[
        "automotive",
        "parts",
        "vehicle",
        "motor",
        "mfg"
    ],
    "wof:name":"Reline Centers Of America",
    "wof:placetype":"venue"
},
  "geometry": {"coordinates":[-75.040194,40.020652],"type":"Point"}
}