{
  "type": "Feature",
  "properties": {
    "addr:full":"15 E Washington St New Castle PA 16101",
    "addr:housenumber":"15",
    "addr:postcode":"16101",
    "addr:street":"E Washington St",
    "iso:country":"US",
    "sg:address":"15 E Washington St",
    "sg:city":"New Castle",
    "sg:classifiers":[
        {
            "category":"Retail",
            "subcategory":"Laundry & Dry Cleaning",
            "type":"Services"
        }
    ],
    "sg:phone":"+1 724 654 5951",
    "sg:postcode":"16101",
    "sg:province":"PA",
    "sg:tags":[
        "cleaners"
    ],
    "wof:name":"Marco's Dry Cleaners",
    "wof:placetype":"venue"
},
  "geometry": {"coordinates":[-80.34717999999999,41.000062],"type":"Point"}
}