{
  "type": "Feature",
  "properties": {
    "addr:full":"4040 City Ave Philadelphia PA 19131",
    "addr:housenumber":"4040",
    "addr:postcode":"19131",
    "addr:street":"City Ave",
    "iso:country":"US",
    "sg:address":"4040 City Ave",
    "sg:city":"Philadelphia",
    "sg:classifiers":[
        {
            "category":"Restaurant",
            "type":"Food & Drink"
        }
    ],
    "sg:phone":"+1 215 878 0452",
    "sg:postcode":"19131",
    "sg:province":"PA",
    "sg:tags":[
        "mexican"
    ],
    "sg:website":"www.chipotle.com",
    "wof:name":"Chipotle Mexican Grill",
    "wof:placetype":"venue"
},
  "geometry": {"coordinates":[-75.21238700000001,40.0075],"type":"Point"}
}