{
  "type": "Feature",
  "properties": {
    "addr:full":"126 Breakneck Ave Connellsville PA 15425",
    "addr:housenumber":"126",
    "addr:postcode":"15425",
    "addr:street":"Breakneck Ave",
    "iso:country":"US",
    "sg:address":"126 Breakneck Ave",
    "sg:city":"Connellsville",
    "sg:classifiers":[
        {
            "category":"Organizations",
            "subcategory":"Religious Organization",
            "type":"Services"
        }
    ],
    "sg:phone":"+1 724 628 3510",
    "sg:postcode":"15425",
    "sg:province":"PA",
    "sg:tags":[
        "church"
    ],
    "sg:website":"www.ccogonline.com",
    "wof:name":"Church Of God",
    "wof:placetype":"venue"
},
  "geometry": {"coordinates":[-79.57752000000001,40.026357],"type":"Point"}
}