{
  "type": "Feature",
  "properties": {
    "addr:full":"757 Milford Rd East Stroudsburg PA 18301",
    "addr:housenumber":"757",
    "addr:postcode":"18301",
    "addr:street":"Milford Rd",
    "iso:country":"US",
    "sg:address":"757 Milford Rd",
    "sg:city":"East Stroudsburg",
    "sg:classifiers":[
        {
            "category":"Shopping",
            "subcategory":"Crafts & Fabrics",
            "type":"Retail Goods"
        }
    ],
    "sg:phone":"+1 570 424 0981",
    "sg:postcode":"18301",
    "sg:province":"PA",
    "sg:tags":[
        "sewing"
    ],
    "wof:name":"American Eagle Fabric Emporium",
    "wof:placetype":"venue"
},
  "geometry": {"coordinates":[-75.17812000000001,41.02034],"type":"Point"}
}