{
  "type": "Feature",
  "properties": {
    "iso:country":"US",
    "sg:address":"601 Walnut St",
    "sg:city":"Philadelphia",
    "sg:classifiers":[
        {
            "category":"Real Estate",
            "subcategory":"Architect",
            "type":"Services"
        }
    ],
    "sg:phone":"+1   ",
    "sg:postcode":"19106",
    "sg:province":"PA",
    "sg:tags":[
        "building",
        "architectural"
    ],
    "wof:name":"R H M Associates",
    "wof:placetype":"venue"
},
  "geometry": {"coordinates":[-75.152671,39.947899],"type":"Point"}
}