{
  "type": "Feature",
  "properties": {
    "addr:full":"130 Main St Slatington PA 18080",
    "addr:housenumber":"130",
    "addr:postcode":"18080",
    "addr:street":"Main St",
    "iso:country":"US",
    "sg:address":"130 Main St",
    "sg:city":"Slatington",
    "sg:classifiers":[
        {
            "category":"Home & Garden",
            "subcategory":"Hardware",
            "type":"Retail Goods"
        }
    ],
    "sg:phone":"+1 610 767 3162",
    "sg:postcode":"18080",
    "sg:province":"PA",
    "wof:name":"Boyer Hardware",
    "wof:placetype":"venue"
},
  "geometry": {"coordinates":[-75.60538099999999,40.752727],"type":"Point"}
}