{
  "type": "Feature",
  "properties": {
    "addr:full":"1116 Manheim Pike Lancaster PA 17601",
    "addr:housenumber":"1116",
    "addr:postcode":"17601",
    "addr:street":"Manheim Pike",
    "iso:country":"US",
    "sg:address":"1116 Manheim Pike",
    "sg:city":"Lancaster",
    "sg:classifiers":[
        {
            "category":"Wholesale",
            "subcategory":"Office Equipment",
            "type":"Manufacturing & Wholesale Goods"
        }
    ],
    "sg:phone":"+1 717 397 4264",
    "sg:postcode":"17601",
    "sg:province":"PA",
    "sg:tags":[
        "machine",
        "duplicating",
        "copying"
    ],
    "wof:name":"ACM Co Inc",
    "wof:placetype":"venue"
},
  "geometry": {"coordinates":[-76.317455,40.058192],"type":"Point"}
}