{
  "type": "Feature",
  "properties": {
    "iso:country":"US",
    "sg:address":"890 Providence Rd",
    "sg:city":"Scranton",
    "sg:classifiers":[
        {
            "category":"Restaurant",
            "type":"Food & Drink"
        }
    ],
    "sg:phone":"+1 570 343 8036",
    "sg:postcode":"18508",
    "sg:province":"PA",
    "sg:tags":[
        "eating",
        "drinking",
        "laundry",
        "power"
    ],
    "wof:name":"Glider Restaurant Inc",
    "wof:placetype":"venue"
},
  "geometry": {"coordinates":[-75.665217,41.420644],"type":"Point"}
}