{
  "type": "Feature",
  "properties": {
    "iso:country":"US",
    "sg:address":"105 S 7th St",
    "sg:city":"Philadelphia",
    "sg:classifiers":[
        {
            "category":"Education",
            "subcategory":"School",
            "type":"Public Place"
        }
    ],
    "sg:phone":"+1 215 238 8000",
    "sg:postcode":"19106",
    "sg:province":"PA",
    "wof:name":"Independence Charter School",
    "wof:placetype":"venue"
},
  "geometry": {"coordinates":[-75.152362,39.94898],"type":"Point"}
}