{
  "type": "Feature",
  "properties": {
    "iso:country":"US",
    "sg:address":"12 Cooper St",
    "sg:city":"Waverly",
    "sg:classifiers":[
        {
            "category":"Social Services",
            "subcategory":"Child Care",
            "type":"Services"
        }
    ],
    "sg:phone":"+1 607 565 7319",
    "sg:postcode":"14892",
    "sg:province":"PA",
    "sg:tags":[
        "day"
    ],
    "wof:name":"Waverly Head Start Center",
    "wof:placetype":"venue"
},
  "geometry": {"coordinates":[-76.533253,42.012172],"type":"Point"}
}