{
  "type": "Feature",
  "properties": {
    "iso:country":"US",
    "sg:address":"716 Ash Ave",
    "sg:city":"Darby",
    "sg:classifiers":[
        {
            "category":"Building & Trades",
            "subcategory":"Electrical",
            "type":"Services"
        }
    ],
    "sg:phone":"+1   ",
    "sg:postcode":"19023",
    "sg:province":"PA",
    "sg:tags":[
        "electrical",
        "contractor"
    ],
    "wof:name":"Richard J Forish Electric",
    "wof:placetype":"venue"
},
  "geometry": {"coordinates":[-75.282568,39.917495],"type":"Point"}
}