{
  "type": "Feature",
  "properties": {
    "addr:full":"339 Butler St Pittsburgh PA 15223",
    "addr:housenumber":"339",
    "addr:postcode":"15223",
    "addr:street":"Butler St",
    "iso:country":"US",
    "sg:address":"339 Butler St",
    "sg:city":"Pittsburgh",
    "sg:classifiers":[
        {
            "category":"Shopping",
            "subcategory":"Books",
            "type":"Retail Goods"
        }
    ],
    "sg:phone":"+1 412 781 3458",
    "sg:postcode":"15223",
    "sg:province":"PA",
    "sg:tags":[
        "dealer"
    ],
    "wof:name":"Block's Book Shop",
    "wof:placetype":"venue"
},
  "geometry": {"coordinates":[-79.944107,40.496461],"type":"Point"}
}