{
  "type": "Feature",
  "properties": {
    "iso:country":"US",
    "sg:address":"5550 State Rte 873",
    "sg:city":"Neffs",
    "sg:classifiers":[
        {
            "category":"Social Services",
            "subcategory":"Child Care",
            "type":"Services"
        }
    ],
    "sg:phone":"+1 610 767 5327",
    "sg:postcode":"18078",
    "sg:province":"PA",
    "sg:tags":[
        "kindergarten",
        "academic",
        "school"
    ],
    "wof:name":"Neffs Union Church Preschool",
    "wof:placetype":"venue"
},
  "geometry": {"coordinates":[-75.60865699999999,40.690844],"type":"Point"}
}