{
  "type": "Feature",
  "properties": {
    "addr:full":"801 S 4th St Hamburg PA 19526",
    "addr:housenumber":"801",
    "addr:postcode":"19526",
    "addr:street":"S 4Th St",
    "iso:country":"US",
    "sg:address":"801 S 4th St",
    "sg:city":"Hamburg",
    "sg:classifiers":[
        {
            "category":"Banks & Credit Unions",
            "subcategory":"Bank",
            "type":"Services"
        }
    ],
    "sg:phone":"+1 610 562 3277",
    "sg:postcode":"19526",
    "sg:province":"PA",
    "wof:name":"Leesport Bank",
    "wof:placetype":"venue"
},
  "geometry": {"coordinates":[-75.97806300000001,40.542878],"type":"Point"}
}