{
  "type": "Feature",
  "properties": {
    "iso:country":"US",
    "sg:address":"135 Large St",
    "sg:city":"Meyersdale",
    "sg:classifiers":[
        {
            "category":"Shopping",
            "subcategory":"Florist",
            "type":"Retail Goods"
        }
    ],
    "sg:phone":"+1   ",
    "sg:postcode":"15552",
    "sg:province":"PA",
    "wof:name":"Meyersdale Cntry Bouquet Florl",
    "wof:placetype":"venue"
},
  "geometry": {"coordinates":[-79.023084,39.812147],"type":"Point"}
}