{
  "type": "Feature",
  "properties": {
    "addr:full":"580 Reed Rd Broomall PA 19008",
    "addr:housenumber":"580",
    "addr:postcode":"19008",
    "addr:street":"Reed Rd",
    "iso:country":"US",
    "sg:address":"580 Reed Rd",
    "sg:city":"Broomall",
    "sg:classifiers":[
        {
            "category":"Social Services",
            "subcategory":"Job Training",
            "type":"Services"
        }
    ],
    "sg:phone":"+1 610 356 6211",
    "sg:postcode":"19008",
    "sg:province":"PA",
    "sg:tags":[
        "rehabilitation"
    ],
    "wof:name":"Nova Care",
    "wof:placetype":"venue"
},
  "geometry": {"coordinates":[-75.354223,39.957797],"type":"Point"}
}