{
  "type": "Feature",
  "properties": {
    "iso:country":"US",
    "sg:address":"1004 66th Ave",
    "sg:city":"Philadelphia",
    "sg:classifiers":[
        {
            "category":"Shopping",
            "subcategory":"Florist",
            "type":"Retail Goods"
        }
    ],
    "sg:phone":"+1 267 297 6448",
    "sg:postcode":"19126",
    "sg:province":"PA",
    "wof:name":"Grace Creations Unlimited",
    "wof:placetype":"venue"
},
  "geometry": {"coordinates":[-75.134389,40.052673],"type":"Point"}
}