{
  "type": "Feature",
  "properties": {
    "iso:country":"US",
    "sg:address":"207 Deibler Rd",
    "sg:city":"Pennsylvania Furnace",
    "sg:classifiers":[
        {
            "category":"Building & Trades",
            "subcategory":"Construction",
            "type":"Services"
        }
    ],
    "sg:phone":"+1   ",
    "sg:postcode":"16865",
    "sg:province":"PA",
    "sg:tags":[
        "contractor"
    ],
    "wof:name":"Installations JRS Quality Tile",
    "wof:placetype":"venue"
},
  "geometry": {"coordinates":[-77.98492899999999,40.707839],"type":"Point"}
}