{
  "type": "Feature",
  "properties": {
    "iso:country":"US",
    "sg:address":"2121 Adams St",
    "sg:city":"Reading",
    "sg:classifiers":[
        {
            "category":"Building & Trades",
            "subcategory":"Construction",
            "type":"Services"
        }
    ],
    "sg:phone":"+1 610 929 1113",
    "sg:postcode":"19605",
    "sg:province":"PA",
    "sg:tags":[
        "installation",
        "petroleum",
        "sta",
        "removal"
    ],
    "wof:name":"B & F Petroleum Installations",
    "wof:placetype":"venue"
},
  "geometry": {"coordinates":[-75.920492,40.367514],"type":"Point"}
}