{
  "type": "Feature",
  "properties": {
    "addr:full":"89 W End Blvd Quakertown PA 18951",
    "addr:housenumber":"89",
    "addr:postcode":"18951",
    "addr:street":"W End Blvd",
    "iso:country":"US",
    "sg:address":"89 W End Blvd",
    "sg:city":"Quakertown",
    "sg:classifiers":[
        {
            "category":"Shopping",
            "subcategory":"Optical Goods",
            "type":"Retail Goods"
        }
    ],
    "sg:phone":"+1 215 536 0620",
    "sg:postcode":"18951",
    "sg:province":"PA",
    "sg:tags":[
        "aids",
        "hearing"
    ],
    "wof:name":"Visionetics",
    "wof:placetype":"venue"
},
  "geometry": {"coordinates":[-75.35131199999999,40.431345],"type":"Point"}
}