{
  "type": "Feature",
  "properties": {
    "iso:country":"US",
    "sg:address":"100 S Conestoga Dr",
    "sg:city":"Shippensburg",
    "sg:classifiers":[
        {
            "category":"Restaurant",
            "type":"Food & Drink"
        }
    ],
    "sg:menulink":"http://www.allmenus.com/pa/shippensburg/133531-subway/menu/",
    "sg:phone":"+1 717 532 4740",
    "sg:postcode":"17257",
    "sg:province":"PA",
    "sg:tags":[
        "american",
        "sandwich"
    ],
    "wof:name":"Subway",
    "wof:placetype":"venue"
},
  "geometry": {"coordinates":[-77.495515,40.060736],"type":"Point"}
}