{
  "type": "Feature",
  "properties": {
    "iso:country":"US",
    "sg:address":"1110 10th Ave",
    "sg:city":"Beaver Falls",
    "sg:classifiers":[
        {
            "category":"Building & Trades",
            "subcategory":"Cleaning & Sanitation",
            "type":"Services"
        }
    ],
    "sg:phone":"+1 724 847 1485",
    "sg:postcode":"15010",
    "sg:province":"PA",
    "sg:tags":[
        "janitor"
    ],
    "wof:name":"Keystone Professional Cleaning",
    "wof:placetype":"venue"
},
  "geometry": {"coordinates":[-80.323396,40.752929],"type":"Point"}
}