{
  "type": "Feature",
  "properties": {
    "addr:full":"205 N Broad St Doylestown PA 18901",
    "addr:housenumber":"205",
    "addr:postcode":"18901",
    "addr:street":"N Broad St",
    "iso:country":"US",
    "sg:address":"205 N Broad St",
    "sg:city":"Doylestown",
    "sg:classifiers":[
        {
            "category":"Manufacturing",
            "subcategory":"Tools & Machinery",
            "type":"Manufacturing & Wholesale Goods"
        }
    ],
    "sg:phone":"+1 215 345 6262",
    "sg:postcode":"18901",
    "sg:province":"PA",
    "sg:tags":[
        "machine",
        "shop",
        "industrial",
        "mfg"
    ],
    "wof:name":"Zenco Machine & Tool Co Inc",
    "wof:placetype":"venue"
},
  "geometry": {"coordinates":[-75.133251,40.314971],"type":"Point"}
}