{
  "type": "Feature",
  "properties": {
    "addr:full":"92 N Lake St North East PA 16428",
    "addr:housenumber":"92",
    "addr:postcode":"16428",
    "addr:street":"N Lake St North",
    "iso:country":"US",
    "sg:address":"92 N Lake St",
    "sg:city":"North East",
    "sg:classifiers":[
        {
            "category":"Retail",
            "subcategory":"Funeral Services",
            "type":"Services"
        }
    ],
    "sg:phone":"+1 814 725 4505",
    "sg:postcode":"16428",
    "sg:province":"PA",
    "sg:tags":[
        "director"
    ],
    "sg:website":"www.bowersfuneralhome.com",
    "wof:name":"W Tad Bowers Funeral Home",
    "wof:placetype":"venue"
},
  "geometry": {"coordinates":[-79.833585,42.219276],"type":"Point"}
}