{
  "type": "Feature",
  "properties": {
    "iso:country":"US",
    "sg:address":"11388 Furnace Rd",
    "sg:city":"Blue Ridge Summit",
    "sg:classifiers":[
        {
            "category":"Building & Trades",
            "subcategory":"Construction",
            "type":"Services"
        }
    ],
    "sg:phone":"+1   ",
    "sg:postcode":"17214",
    "sg:province":"PA",
    "sg:tags":[
        "residential"
    ],
    "wof:name":"Pat Hahn Construction",
    "wof:placetype":"venue"
},
  "geometry": {"coordinates":[-77.46495400000001,39.750564],"type":"Point"}
}