{
  "type": "Feature",
  "properties": {
    "iso:country":"US",
    "sg:address":"2100 Harrisburg Pike",
    "sg:city":"Lancaster",
    "sg:classifiers":[
        {
            "category":"Health Services",
            "subcategory":"Health Practitioner",
            "type":"Services"
        }
    ],
    "sg:phone":"+1 717 544 3103",
    "sg:postcode":"17601",
    "sg:province":"PA",
    "sg:tags":[
        "therapist",
        "physical"
    ],
    "wof:name":"Behavioral Medicane",
    "wof:placetype":"venue"
},
  "geometry": {"coordinates":[-76.35742500000001,40.06944],"type":"Point"}
}