{
  "type": "Feature",
  "properties": {
    "iso:country":"US",
    "sg:address":"797 Patterson School Rd",
    "sg:city":"Grove City",
    "sg:classifiers":[
        {
            "category":"Farming",
            "subcategory":"Dairy Farm",
            "type":"Manufacturing & Wholesale Goods"
        }
    ],
    "sg:phone":"+1   ",
    "sg:postcode":"16127",
    "sg:province":"PA",
    "wof:name":"James Weber",
    "wof:placetype":"venue"
},
  "geometry": {"coordinates":[-80.018764,41.231484],"type":"Point"}
}