{
  "type": "Feature",
  "properties": {
    "addr:full":"2408 Haverford Rd Ardmore PA 19003",
    "addr:housenumber":"2408",
    "addr:postcode":"19003",
    "addr:street":"Haverford Rd",
    "iso:country":"US",
    "sg:address":"2408 Haverford Rd",
    "sg:city":"Ardmore",
    "sg:classifiers":[
        {
            "category":"Food & Beverages",
            "subcategory":"Candy",
            "type":"Retail Goods"
        },
        {
            "category":"Food & Beverages",
            "subcategory":"Specialty",
            "type":"Retail Goods"
        }
    ],
    "sg:phone":"+1 610 642 3066",
    "sg:postcode":"19003",
    "sg:province":"PA",
    "sg:tags":[
        "confectionery",
        "nuts-edible"
    ],
    "wof:name":"The Head Nut",
    "wof:placetype":"venue"
},
  "geometry": {"coordinates":[-75.298366,39.993872],"type":"Point"}
}