{
  "type": "Feature",
  "properties": {
    "iso:country":"US",
    "sg:address":"18 Park Vallei Ln",
    "sg:city":"Brookhaven",
    "sg:classifiers":[
        {
            "category":"Building & Trades",
            "subcategory":"Construction",
            "type":"Services"
        }
    ],
    "sg:phone":"+1   ",
    "sg:postcode":"19015",
    "sg:province":"PA",
    "sg:tags":[
        "house"
    ],
    "wof:name":"Bill Dennon General Contg",
    "wof:placetype":"venue"
},
  "geometry": {"coordinates":[-75.37934300000001,39.870637],"type":"Point"}
}