{
  "type": "Feature",
  "properties": {
    "iso:country":"US",
    "sg:address":"1827 N 54th St",
    "sg:city":"Philadelphia",
    "sg:classifiers":[
        {
            "category":"Organizations",
            "subcategory":"Religious Organization",
            "type":"Services"
        }
    ],
    "sg:phone":"+1 215 877 1555",
    "sg:postcode":"19131",
    "sg:province":"PA",
    "sg:tags":[
        "god",
        "churches-pentecostal",
        "church"
    ],
    "wof:name":"International Church Of God",
    "wof:placetype":"venue"
},
  "geometry": {"coordinates":[-75.23155199999999,39.984913],"type":"Point"}
}