{
  "type": "Feature",
  "properties": {
    "addr:full":"1300 Broad St Montoursville PA 17754",
    "addr:housenumber":"1300",
    "addr:postcode":"17754",
    "addr:street":"Broad St",
    "iso:country":"US",
    "sg:address":"1300 Broad St",
    "sg:city":"Montoursville",
    "sg:classifiers":[
        {
            "category":"Banks & Credit Unions",
            "subcategory":"Bank",
            "type":"Services"
        }
    ],
    "sg:phone":"+1 570 368 7401",
    "sg:postcode":"17754",
    "sg:province":"PA",
    "sg:tags":[
        "federal",
        "federally",
        "chartered"
    ],
    "wof:name":"Lakes To Sea Federal Credit Un",
    "wof:placetype":"venue"
},
  "geometry": {"coordinates":[-76.902131,41.246401],"type":"Point"}
}