{
  "type": "Feature",
  "properties": {
    "iso:country":"US",
    "sg:address":"386 Horton St",
    "sg:city":"Philipsburg",
    "sg:classifiers":[
        {
            "category":"Autos & Motor Vehicles",
            "subcategory":"Fuel & Gas Station",
            "type":"Retail Goods"
        }
    ],
    "sg:phone":"+1   ",
    "sg:postcode":"16866",
    "sg:province":"PA",
    "sg:tags":[
        "station",
        "gasoline"
    ],
    "wof:name":"Price Parkway Service",
    "wof:placetype":"venue"
},
  "geometry": {"coordinates":[-78.242965,40.883142],"type":"Point"}
}