{
  "type": "Feature",
  "properties": {
    "addr:full":"686 Market Sq Meyersdale PA 15552",
    "addr:housenumber":"686",
    "addr:postcode":"15552",
    "addr:street":"Market Sq",
    "iso:country":"US",
    "sg:address":"686 Market Sq",
    "sg:city":"Meyersdale",
    "sg:classifiers":[
        {
            "category":"Food & Beverages",
            "subcategory":"Liquor & Beverages",
            "type":"Retail Goods"
        }
    ],
    "sg:phone":"+1 814 634 8930",
    "sg:postcode":"15552",
    "sg:province":"PA",
    "wof:name":"Liquor Store",
    "wof:placetype":"venue"
},
  "geometry": {"coordinates":[-79.02582700000001,39.813124],"type":"Point"}
}