{
  "type": "Feature",
  "properties": {
    "iso:country":"US",
    "sg:address":"111 Pittsburgh St",
    "sg:city":"Uniontown",
    "sg:classifiers":[
        {
            "category":"Wholesale",
            "subcategory":"Electrical",
            "type":"Manufacturing & Wholesale Goods"
        }
    ],
    "sg:phone":"+1 724 437 1234",
    "sg:postcode":"15401",
    "sg:province":"PA",
    "sg:tags":[
        "electronic"
    ],
    "wof:name":"Security Systems Of America",
    "wof:placetype":"venue"
},
  "geometry": {"coordinates":[-79.727215,39.904681],"type":"Point"}
}