{
  "type": "Feature",
  "properties": {
    "addr:full":"1503 Olive St Coatesville PA 19320",
    "addr:housenumber":"1503",
    "addr:postcode":"19320",
    "addr:street":"Olive St",
    "iso:country":"US",
    "sg:address":"1503 Olive St",
    "sg:city":"Coatesville",
    "sg:classifiers":[
        {
            "category":"Professional",
            "subcategory":"Engineering",
            "type":"Services"
        }
    ],
    "sg:phone":"+1 610 383 3871",
    "sg:postcode":"19320",
    "sg:province":"PA",
    "sg:tags":[
        "legal"
    ],
    "wof:name":"Rooney Associates Inc",
    "wof:placetype":"venue"
},
  "geometry": {"coordinates":[-75.793459,39.986989],"type":"Point"}
}