{
  "type": "Feature",
  "properties": {
    "iso:country":"US",
    "sg:address":"1900 Franklin Mills Cir",
    "sg:city":"Philadelphia",
    "sg:classifiers":[
        {
            "category":"Shopping",
            "subcategory":"Clothing, Apparel, & Fashions",
            "type":"Retail Goods"
        }
    ],
    "sg:phone":"+1   ",
    "sg:postcode":"19154",
    "sg:province":"PA",
    "sg:tags":[
        "retailer"
    ],
    "wof:name":"Petite Sophisticate Annex",
    "wof:placetype":"venue"
},
  "geometry": {"coordinates":[-74.96393399999999,40.081858],"type":"Point"}
}