{
  "type": "Feature",
  "properties": {
    "iso:country":"US",
    "sg:address":"522 N Main St",
    "sg:city":"Topton",
    "sg:classifiers":[
        {
            "category":"Autos & Motor Vehicles",
            "subcategory":"Auto Supplies",
            "type":"Retail Goods"
        }
    ],
    "sg:phone":"+1 610 682 0940",
    "sg:postcode":"19562",
    "sg:province":"PA",
    "sg:tags":[
        "transmission",
        "automobile",
        "accessories-wholesale",
        "parts",
        "manufacturer"
    ],
    "wof:name":"Lehigh Valley Transmission Inc",
    "wof:placetype":"venue"
},
  "geometry": {"coordinates":[-75.703636,40.508943],"type":"Point"}
}