{
  "type": "Feature",
  "properties": {
    "iso:country":"US",
    "sg:address":"2300 Chestnut St",
    "sg:city":"Philadelphia",
    "sg:classifiers":[
        {
            "category":"Wholesale",
            "subcategory":"Furniture",
            "type":"Manufacturing & Wholesale Goods"
        }
    ],
    "sg:phone":"+1 215 988 1788",
    "sg:postcode":"19103",
    "sg:province":"PA",
    "sg:website":"www.knoll.com",
    "wof:name":"Knoll Inc",
    "wof:placetype":"venue"
},
  "geometry": {"coordinates":[-75.179182,39.952757],"type":"Point"}
}