{
  "type": "Feature",
  "properties": {
    "iso:country":"US",
    "sg:address":"19 E Middle St",
    "sg:city":"Gettysburg",
    "sg:classifiers":[
        {
            "category":"Professional",
            "subcategory":"Employment Agencies",
            "type":"Services"
        }
    ],
    "sg:phone":"+1 717 337 0060",
    "sg:postcode":"17325",
    "sg:province":"PA",
    "sg:tags":[
        "opportunity"
    ],
    "wof:name":"Adecco",
    "wof:placetype":"venue"
},
  "geometry": {"coordinates":[-77.23079,39.829675],"type":"Point"}
}