{
  "type": "Feature",
  "properties": {
    "iso:country":"US",
    "sg:address":"618 Jefferson Ave",
    "sg:city":"Morrisville",
    "sg:classifiers":[
        {
            "category":"Wholesale",
            "subcategory":"Medical Equipment & Supplies",
            "type":"Manufacturing & Wholesale Goods"
        }
    ],
    "sg:phone":"+1 215 736 0665",
    "sg:postcode":"19067",
    "sg:province":"PA",
    "sg:tags":[
        "apparatus",
        "x-ray"
    ],
    "wof:name":"Penn Jersey X Ray",
    "wof:placetype":"venue"
},
  "geometry": {"coordinates":[-74.78734900000001,40.213276],"type":"Point"}
}