{
  "type": "Feature",
  "properties": {
    "addr:full":"170 S Independence Mall W L88 Philadelphia PA 19106",
    "addr:housenumber":"170;l88",
    "addr:postcode":"19106",
    "addr:street":"S Independence Mall W",
    "iso:country":"US",
    "sg:address":"170 S Independence Mall W L88",
    "sg:city":"Philadelphia",
    "sg:classifiers":[
        {
            "category":"Professional",
            "subcategory":"Research",
            "type":"Services"
        }
    ],
    "sg:phone":"+1 215 597 3282",
    "sg:postcode":"19106",
    "sg:province":"PA",
    "sg:tags":[
        "economic",
        "analysis"
    ],
    "wof:name":"Economic Analysis & Info",
    "wof:placetype":"venue"
},
  "geometry": {"coordinates":[-75.15096699999999,39.948151],"type":"Point"}
}