{
  "type": "Feature",
  "properties": {
    "iso:country":"US",
    "sg:address":"51 Fawn Ln",
    "sg:city":"Kennett Square",
    "sg:classifiers":[
        {
            "category":"Wholesale",
            "subcategory":"Electrical",
            "type":"Manufacturing & Wholesale Goods"
        }
    ],
    "sg:phone":"+1   ",
    "sg:postcode":"19348",
    "sg:province":"PA",
    "sg:tags":[
        "company",
        "installation",
        "maintenance"
    ],
    "wof:name":"Nova USA Inc",
    "wof:placetype":"venue"
},
  "geometry": {"coordinates":[-75.64307599999999,39.869395],"type":"Point"}
}