{
  "type": "Feature",
  "properties": {
    "iso:country":"US",
    "sg:address":"8460 Edinboro Rd",
    "sg:city":"Mc Kean",
    "sg:classifiers":[
        {
            "category":"Home & Garden",
            "subcategory":"Garden Supply",
            "type":"Retail Goods"
        }
    ],
    "sg:phone":"+1 814 476 7767",
    "sg:postcode":"16426",
    "sg:province":"PA",
    "sg:tags":[
        "tractor"
    ],
    "wof:name":"Pennock's Sales & Svc",
    "wof:placetype":"venue"
},
  "geometry": {"coordinates":[-80.141319,42.00496],"type":"Point"}
}