{
  "type": "Feature",
  "properties": {
    "iso:country":"US",
    "sg:address":"3 Rachael Dr",
    "sg:city":"Pittston",
    "sg:classifiers":[
        {
            "category":"Food Court",
            "type":"Food & Drink"
        }
    ],
    "sg:phone":"+1 570 654 2680",
    "sg:postcode":"18640",
    "sg:province":"PA",
    "sg:tags":[
        "stand",
        "refreshment"
    ],
    "wof:name":"Plaza Beverage Inc",
    "wof:placetype":"venue"
},
  "geometry": {"coordinates":[-75.77003999999999,41.321275],"type":"Point"}
}