{
  "type": "Feature",
  "properties": {
    "addr:full":"125 W 4th St Bethlehem PA 18015",
    "addr:housenumber":"125",
    "addr:postcode":"18015",
    "addr:street":"W 4Th St",
    "iso:country":"US",
    "sg:address":"125 W 4th St",
    "sg:city":"Bethlehem",
    "sg:classifiers":[
        {
            "category":"Shopping",
            "subcategory":"Used Merchandise",
            "type":"Retail Goods"
        }
    ],
    "sg:phone":"+1 610 691 1691",
    "sg:postcode":"18015",
    "sg:province":"PA",
    "sg:tags":[
        "shop",
        "thrift"
    ],
    "wof:name":"Muhlenberg Hospital Thrift Sp",
    "wof:placetype":"venue"
},
  "geometry": {"coordinates":[-75.379947,40.610481],"type":"Point"}
}