{
  "type": "Feature",
  "properties": {
    "iso:country":"US",
    "sg:address":"692 Old Lancaster Pike",
    "sg:city":"Reading",
    "sg:classifiers":[
        {
            "category":"Retail",
            "subcategory":"Auto Repair",
            "type":"Services"
        }
    ],
    "sg:phone":"+1   ",
    "sg:postcode":"19607",
    "sg:province":"PA",
    "sg:tags":[
        "general"
    ],
    "wof:name":"Rinehart Tiny Auto Center",
    "wof:placetype":"venue"
},
  "geometry": {"coordinates":[-75.99654099999999,40.297982],"type":"Point"}
}