{
  "type": "Feature",
  "properties": {
    "addr:full":"1 S Church St Hazleton PA 18201",
    "addr:housenumber":"1",
    "addr:postcode":"18201",
    "addr:street":"S Church St",
    "iso:country":"US",
    "sg:address":"1 S Church St",
    "sg:city":"Hazleton",
    "sg:classifiers":[
        {
            "category":"Professional",
            "subcategory":"Accounting & Tax Preparation",
            "type":"Services"
        }
    ],
    "sg:phone":"+1   ",
    "sg:postcode":"18201",
    "sg:province":"PA",
    "sg:tags":[
        "firm"
    ],
    "wof:name":"Moore Dennis R",
    "wof:placetype":"venue"
},
  "geometry": {"coordinates":[-75.97734800000001,40.95428],"type":"Point"}
}