{
  "type": "Feature",
  "properties": {
    "iso:country":"US",
    "sg:address":"258 Dunksferry Rd",
    "sg:city":"Bensalem",
    "sg:classifiers":[
        {
            "category":"Building & Trades",
            "subcategory":"Plumbing",
            "type":"Services"
        }
    ],
    "sg:phone":"+1 215 638 7700",
    "sg:postcode":"19020",
    "sg:province":"PA",
    "wof:name":"Continental Penpure Atlantic",
    "wof:placetype":"venue"
},
  "geometry": {"coordinates":[-74.922501,40.077],"type":"Point"}
}