{
  "type": "Feature",
  "properties": {
    "iso:country":"US",
    "sg:address":"1630 W Market St",
    "sg:city":"York",
    "sg:classifiers":[
        {
            "category":"Health Services",
            "subcategory":"Chiropractor",
            "type":"Services"
        }
    ],
    "sg:phone":"+1 717 843 2542",
    "sg:postcode":"17404",
    "sg:province":"PA",
    "sg:tags":[
        "physician"
    ],
    "wof:name":"Harcourt Chiropractic Office",
    "wof:placetype":"venue"
},
  "geometry": {"coordinates":[-76.764343,39.953214],"type":"Point"}
}