{
  "type": "Feature",
  "properties": {
    "addr:full":"1719 W Porter St Philadelphia PA 19145",
    "addr:housenumber":"1719",
    "addr:postcode":"19145",
    "addr:street":"W Porter St",
    "iso:country":"US",
    "sg:address":"1719 W Porter St",
    "sg:city":"Philadelphia",
    "sg:classifiers":[
        {
            "category":"Real Estate",
            "subcategory":"Real Estate Agent",
            "type":"Services"
        }
    ],
    "sg:phone":"+1   ",
    "sg:postcode":"19145",
    "sg:province":"PA",
    "wof:name":"Real Estate Development Svc",
    "wof:placetype":"venue"
},
  "geometry": {"coordinates":[-75.176366,39.920108],"type":"Point"}
}