{
  "type": "Feature",
  "properties": {
    "iso:country":"US",
    "sg:address":"5000 W Tilghman St # 240",
    "sg:city":"Allentown",
    "sg:classifiers":[
        {
            "category":"Health Services",
            "subcategory":"Doctor",
            "type":"Services"
        }
    ],
    "sg:phone":"+1 610 395 4044",
    "sg:postcode":"18104",
    "sg:province":"PA",
    "sg:tags":[
        "physician",
        "surgeon",
        "anesthesiology",
        "surgeons"
    ],
    "sg:website":"http://www.lehighanesthesia.com",
    "wof:name":"Lehigh Anesthesia Associates, P.C.",
    "wof:placetype":"venue"
},
  "geometry": {"coordinates":[-75.536064,40.595169],"type":"Point"}
}