{
  "type": "Feature",
  "properties": {
    "iso:country":"US",
    "sg:address":"5 Kearney Dr",
    "sg:city":"North Wales",
    "sg:classifiers":[
        {
            "category":"Building & Trades",
            "subcategory":"Plumbing",
            "type":"Services"
        }
    ],
    "sg:phone":"+1 215 393 5151",
    "sg:postcode":"19454",
    "sg:province":"PA",
    "wof:name":"Desante Plumbing & Heating Inc",
    "wof:placetype":"venue"
},
  "geometry": {"coordinates":[-75.273045,40.222361],"type":"Point"}
}