{
  "type": "Feature",
  "properties": {
    "addr:full":"114 Daughtons Dr Hyndman PA 15545",
    "addr:housenumber":"114",
    "addr:postcode":"15545",
    "addr:street":"Daughtons Dr",
    "iso:country":"US",
    "sg:address":"114 Daughtons Dr",
    "sg:city":"Hyndman",
    "sg:classifiers":[
        {
            "category":"Manufacturing",
            "subcategory":"Signs",
            "type":"Manufacturing & Wholesale Goods"
        }
    ],
    "sg:phone":"+1 814 324 0881",
    "sg:postcode":"15545",
    "sg:province":"PA",
    "sg:tags":[
        "advertising",
        "specialty"
    ],
    "wof:name":"Daughton's Sign Svc",
    "wof:placetype":"venue"
},
  "geometry": {"coordinates":[-78.84923499999999,39.725925],"type":"Point"}
}