{
  "type": "Feature",
  "properties": {
    "iso:country":"US",
    "sg:address":"129 2nd St",
    "sg:city":"Catasauqua",
    "sg:classifiers":[
        {
            "category":"Building & Trades",
            "subcategory":"Construction",
            "type":"Services"
        }
    ],
    "sg:phone":"+1   ",
    "sg:postcode":"18032",
    "sg:province":"PA",
    "sg:tags":[
        "contractor"
    ],
    "wof:name":"McCartney Residential Cnstr",
    "wof:placetype":"venue"
},
  "geometry": {"coordinates":[-75.46962600000001,40.651649],"type":"Point"}
}