{
  "type": "Feature",
  "properties": {
    "addr:full":"522 N 29th St Allentown PA 18104",
    "addr:housenumber":"522",
    "addr:postcode":"18104",
    "addr:street":"N 29Th St",
    "iso:country":"US",
    "sg:address":"522 N 29th St",
    "sg:city":"Allentown",
    "sg:classifiers":[
        {
            "category":"Professional",
            "type":"Services"
        }
    ],
    "sg:phone":"+1   ",
    "sg:postcode":"18104",
    "sg:province":"PA",
    "wof:name":"Heidi W Mayville",
    "wof:placetype":"venue"
},
  "geometry": {"coordinates":[-75.521371,40.597777],"type":"Point"}
}