{
  "type": "Feature",
  "properties": {
    "iso:country":"US",
    "sg:address":"102 Walnut Dr",
    "sg:city":"Baden",
    "sg:classifiers":[
        {
            "category":"Personal",
            "subcategory":"Beauty Salon",
            "type":"Services"
        }
    ],
    "sg:phone":"+1 724 869 2262",
    "sg:postcode":"15005",
    "sg:province":"PA",
    "wof:name":"Aggie Kaunert's KUT & KURL",
    "wof:placetype":"venue"
},
  "geometry": {"coordinates":[-80.17380799999999,40.662817],"type":"Point"}
}