{
  "type": "Feature",
  "properties": {
    "iso:country":"US",
    "sg:address":"509 Taylor St",
    "sg:city":"New Castle",
    "sg:classifiers":[
        {
            "category":"Utilities",
            "subcategory":"Cable",
            "type":"Services"
        },
        {
            "category":"Professional",
            "subcategory":"Computer Services",
            "type":"Services"
        }
    ],
    "sg:phone":"+1 724 654 4511",
    "sg:postcode":"16101",
    "sg:province":"PA",
    "sg:tags":[
        "television",
        "wiring"
    ],
    "wof:name":"Cable Net Systems Inc",
    "wof:placetype":"venue"
},
  "geometry": {"coordinates":[-80.34099500000001,40.99337],"type":"Point"}
}