{
  "type": "Feature",
  "properties": {
    "iso:country":"US",
    "sg:address":"115 Manor Ave",
    "sg:city":"Millersville",
    "sg:classifiers":[
        {
            "category":"Food & Beverages",
            "subcategory":"Groceries & Convenience Stores",
            "type":"Retail Goods"
        }
    ],
    "sg:phone":"+1 717 872 7043",
    "sg:postcode":"17551",
    "sg:province":"PA",
    "wof:name":"Sicoserve",
    "wof:placetype":"venue"
},
  "geometry": {"coordinates":[-76.356345,40.009699],"type":"Point"}
}