{
  "type": "Feature",
  "properties": {
    "iso:country":"US",
    "sg:address":"121 N Washington Ave",
    "sg:city":"Scranton",
    "sg:classifiers":[
        {
            "category":"Food & Beverages",
            "subcategory":"Groceries & Convenience Stores",
            "type":"Retail Goods"
        },
        {
            "category":"Restaurant",
            "type":"Food & Drink"
        }
    ],
    "sg:phone":"+1 570 341 8165",
    "sg:postcode":"18503",
    "sg:province":"PA",
    "sg:tags":[
        "delicatessen"
    ],
    "wof:name":"Deli Licious",
    "wof:placetype":"venue"
},
  "geometry": {"coordinates":[-75.664751,41.407057],"type":"Point"}
}