{
  "type": "Feature",
  "properties": {
    "iso:country":"US",
    "sg:address":"7814 Castor Ave",
    "sg:city":"Philadelphia",
    "sg:classifiers":[
        {
            "category":"Restaurant",
            "type":"Food & Drink"
        }
    ],
    "sg:phone":"+1 215 745 0130",
    "sg:postcode":"19152",
    "sg:province":"PA",
    "wof:name":"Espresso Cafe & Sushi Bar",
    "wof:placetype":"venue"
},
  "geometry": {"coordinates":[-75.059506,40.058262],"type":"Point"}
}