{
  "type": "Feature",
  "properties": {
    "iso:country":"US",
    "sg:address":"549 Mud Rd",
    "sg:city":"Newtown",
    "sg:classifiers":[
        {
            "category":"Health Services",
            "subcategory":"Chiropractor",
            "type":"Services"
        }
    ],
    "sg:phone":"+1   ",
    "sg:postcode":"18940",
    "sg:province":"PA",
    "wof:name":"Hartman Chiropractic Center",
    "wof:placetype":"venue"
},
  "geometry": {"coordinates":[-74.99012500000001,40.261776],"type":"Point"}
}