{
  "type": "Feature",
  "properties": {
    "addr:full":"1832 Harrisburg Ave Mount Joy PA 17552",
    "addr:housenumber":"1832",
    "addr:postcode":"17552",
    "addr:street":"Harrisburg Ave",
    "iso:country":"US",
    "sg:address":"1832 Harrisburg Ave",
    "sg:city":"Mount Joy",
    "sg:classifiers":[
        {
            "category":"Shopping",
            "type":"Retail Goods"
        }
    ],
    "sg:phone":"+1   ",
    "sg:postcode":"17552",
    "sg:province":"PA",
    "sg:tags":[
        "merchandise"
    ],
    "wof:name":"Custom Mat & Frame",
    "wof:placetype":"venue"
},
  "geometry": {"coordinates":[-76.553991,40.124573],"type":"Point"}
}