{
  "type": "Feature",
  "properties": {
    "addr:full":"4499 Huckleberry Hwy Berlin PA 15530",
    "addr:housenumber":"4499",
    "addr:postcode":"15530",
    "addr:street":"Huckleberry Hwy",
    "iso:country":"US",
    "sg:address":"4499 Huckleberry Hwy",
    "sg:city":"Berlin",
    "sg:classifiers":[
        {
            "category":"Farming",
            "subcategory":"Farm",
            "type":"Manufacturing & Wholesale Goods"
        }
    ],
    "sg:phone":"+1   ",
    "sg:postcode":"15530",
    "sg:province":"PA",
    "sg:tags":[
        "crop",
        "general"
    ],
    "wof:name":"T Croner",
    "wof:placetype":"venue"
},
  "geometry": {"coordinates":[-78.93713099999999,39.923035],"type":"Point"}
}