{
  "type": "Feature",
  "properties": {
    "iso:country":"US",
    "sg:address":"2921 New Rodgers Rd",
    "sg:city":"Bristol",
    "sg:classifiers":[
        {
            "category":"Health Services",
            "subcategory":"Medical Lab",
            "type":"Services"
        }
    ],
    "sg:phone":"+1 215 785 5200",
    "sg:postcode":"19007",
    "sg:province":"PA",
    "sg:tags":[
        "laboratory"
    ],
    "wof:name":"Princeton Bio Medical Labs",
    "wof:placetype":"venue"
},
  "geometry": {"coordinates":[-74.881546,40.121127],"type":"Point"}
}