{
  "type": "Feature",
  "properties": {
    "iso:country":"US",
    "sg:address":"241 Ramsey Ave",
    "sg:city":"Bridgeville",
    "sg:classifiers":[
        {
            "category":"Real Estate",
            "subcategory":"Real Estate Agent",
            "type":"Services"
        }
    ],
    "sg:phone":"+1   ",
    "sg:postcode":"15017",
    "sg:province":"PA",
    "wof:name":"Gdmc Inc",
    "wof:placetype":"venue"
},
  "geometry": {"coordinates":[-80.11363900000001,40.360824],"type":"Point"}
}