{
  "type": "Feature",
  "properties": {
    "addr:full":"121 S Center Ave Somerset PA 15501",
    "addr:housenumber":"121",
    "addr:postcode":"15501",
    "addr:street":"S Center Ave",
    "iso:country":"US",
    "sg:address":"121 S Center Ave",
    "sg:city":"Somerset",
    "sg:classifiers":[
        {
            "category":"Banks & Credit Unions",
            "subcategory":"Bank",
            "type":"Services"
        }
    ],
    "sg:phone":"+1 814 445 7941",
    "sg:postcode":"15501",
    "sg:province":"PA",
    "sg:tags":[
        "state"
    ],
    "wof:name":"First National Bank",
    "wof:placetype":"venue"
},
  "geometry": {"coordinates":[-79.07856200000001,40.008249],"type":"Point"}
}