{
  "type": "Feature",
  "properties": {
    "addr:full":"92 Tuscarora St Harrisburg PA 17104",
    "addr:housenumber":"92",
    "addr:postcode":"17104",
    "addr:street":"Tuscarora St",
    "iso:country":"US",
    "sg:address":"92 Tuscarora St",
    "sg:city":"Harrisburg",
    "sg:classifiers":[
        {
            "category":"Health Services",
            "subcategory":"Doctor",
            "type":"Services"
        }
    ],
    "sg:phone":"+1   ",
    "sg:postcode":"17104",
    "sg:province":"PA",
    "sg:tags":[
        "surgery",
        "outpatient",
        "center"
    ],
    "wof:name":"Osci",
    "wof:placetype":"venue"
},
  "geometry": {"coordinates":[-76.87540300000001,40.253254],"type":"Point"}
}