{
  "type": "Feature",
  "properties": {
    "addr:full":"507 Pittsburgh St Mars PA 16046",
    "addr:housenumber":"507",
    "addr:postcode":"16046",
    "addr:street":"Pittsburgh St",
    "iso:country":"US",
    "sg:address":"507 Pittsburgh St",
    "sg:city":"Mars",
    "sg:classifiers":[
        {
            "category":"Professional",
            "subcategory":"Business Services",
            "type":"Services"
        }
    ],
    "sg:phone":"+1 724 625 3544",
    "sg:postcode":"16046",
    "sg:province":"PA",
    "sg:tags":[
        "water",
        "treatment"
    ],
    "wof:name":"Hotsy Equipment Co",
    "wof:placetype":"venue"
},
  "geometry": {"coordinates":[-80.01289300000001,40.695274],"type":"Point"}
}