{
  "type": "Feature",
  "properties": {
    "iso:country":"US",
    "sg:address":"4558 Crackersport Rd",
    "sg:city":"Allentown",
    "sg:classifiers":[
        {
            "category":"Restaurant",
            "type":"Food & Drink"
        }
    ],
    "sg:phone":"+1 610 391 0080",
    "sg:postcode":"18104",
    "sg:province":"PA",
    "sg:tags":[
        "eating"
    ],
    "wof:name":"Chianti Italiano Restaurante",
    "wof:placetype":"venue"
},
  "geometry": {"coordinates":[-75.56199599999999,40.6022],"type":"Point"}
}