{
  "type": "Feature",
  "properties": {
    "addr:full":"3191 Porter Rd Punxsutawney PA 15767",
    "addr:housenumber":"3191",
    "addr:postcode":"15767",
    "addr:street":"Porter Rd",
    "iso:country":"US",
    "sg:address":"3191 Porter Rd",
    "sg:city":"Punxsutawney",
    "sg:classifiers":[
        {
            "category":"Home & Garden",
            "subcategory":"Garden Supply",
            "type":"Retail Goods"
        },
        {
            "category":"Manufacturing",
            "subcategory":"Lumber",
            "type":"Manufacturing & Wholesale Goods"
        }
    ],
    "sg:phone":"+1 814 938 3010",
    "sg:postcode":"15767",
    "sg:province":"PA",
    "sg:tags":[
        "supp",
        "far",
        "nurseryman",
        "tract",
        "operation",
        "timber"
    ],
    "wof:name":"Lettie Enterprises Inc",
    "wof:placetype":"venue"
},
  "geometry": {"coordinates":[-79.16418400000001,40.935408],"type":"Point"}
}