{
  "type": "Feature",
  "properties": {
    "addr:full":"352 Sun Valley Dr Leola PA 17540",
    "addr:housenumber":"352",
    "addr:postcode":"17540",
    "addr:street":"Sun Valley Dr",
    "iso:country":"US",
    "sg:address":"352 Sun Valley Dr",
    "sg:city":"Leola",
    "sg:classifiers":[
        {
            "category":"Professional",
            "type":"Services"
        }
    ],
    "sg:phone":"+1 717 656 0485",
    "sg:postcode":"17540",
    "sg:province":"PA",
    "sg:tags":[
        "establishment"
    ],
    "wof:name":"American Yeast Sales",
    "wof:placetype":"venue"
},
  "geometry": {"coordinates":[-76.218638,40.08853],"type":"Point"}
}