{
  "type": "Feature",
  "properties": {
    "addr:full":"5151 W Stancliff Rd Mc Kean PA 16426",
    "addr:housenumber":"5151",
    "addr:postcode":"16426",
    "addr:street":"W Stancliff Rd",
    "iso:country":"US",
    "sg:address":"5151 W Stancliff Rd",
    "sg:city":"Mc Kean",
    "sg:classifiers":[
        {
            "category":"Travel",
            "subcategory":"Bed & Breakfast",
            "type":"Entertainment"
        }
    ],
    "sg:phone":"+1 814 476 1632",
    "sg:postcode":"16426",
    "sg:province":"PA",
    "sg:tags":[
        "house"
    ],
    "wof:name":"Thunder Valley Stables",
    "wof:placetype":"venue"
},
  "geometry": {"coordinates":[-80.14392100000001,41.9598],"type":"Point"}
}