{
  "type": "Feature",
  "properties": {
    "addr:full":"1270 Wayne Ave Indiana PA 15701",
    "addr:housenumber":"1270",
    "addr:postcode":"15701",
    "addr:street":"Wayne Ave",
    "iso:country":"US",
    "sg:address":"1270 Wayne Ave",
    "sg:city":"Indiana",
    "sg:classifiers":[
        {
            "category":"Autos & Motor Vehicles",
            "subcategory":"Auto Supplies",
            "type":"Retail Goods"
        }
    ],
    "sg:phone":"+1 724 463 9165",
    "sg:postcode":"15701",
    "sg:province":"PA",
    "sg:tags":[
        "automobile",
        "parts"
    ],
    "wof:name":"Indiana Auto Supply",
    "wof:placetype":"venue"
},
  "geometry": {"coordinates":[-79.16349700000001,40.602193],"type":"Point"}
}