{
  "type": "Feature",
  "properties": {
    "addr:full":"30 N Main St Chalfont PA 18914",
    "addr:housenumber":"30",
    "addr:postcode":"18914",
    "addr:street":"N Main St",
    "iso:country":"US",
    "sg:address":"30 N Main St",
    "sg:city":"Chalfont",
    "sg:classifiers":[
        {
            "category":"Shopping",
            "subcategory":"Beauty & Cosmetics",
            "type":"Retail Goods"
        },
        {
            "category":"Personal",
            "subcategory":"Beauty Salon",
            "type":"Services"
        }
    ],
    "sg:phone":"+1 215 996 1800",
    "sg:postcode":"18914",
    "sg:province":"PA",
    "sg:tags":[
        "hair",
        "stylist",
        "supply"
    ],
    "wof:name":"Salon Salvatore Christian",
    "wof:placetype":"venue"
},
  "geometry": {"coordinates":[-75.20819899999999,40.286499],"type":"Point"}
}