{
  "type": "Feature",
  "properties": {
    "addr:full":"1550 S Warfield St Philadelphia PA 19146",
    "addr:housenumber":"1550",
    "addr:postcode":"19146",
    "addr:street":"S Warfield St",
    "iso:country":"US",
    "sg:address":"1550 S Warfield St",
    "sg:city":"Philadelphia",
    "sg:classifiers":[
        {
            "category":"Manufacturing",
            "subcategory":"Tools & Machinery",
            "type":"Manufacturing & Wholesale Goods"
        },
        {
            "category":"Wholesale",
            "subcategory":"Electrical",
            "type":"Manufacturing & Wholesale Goods"
        },
        {
            "category":"Shopping",
            "subcategory":"Computers & Home Electronics",
            "type":"Retail Goods"
        }
    ],
    "sg:phone":"+1 215 336 2211",
    "sg:postcode":"19146",
    "sg:province":"PA",
    "sg:tags":[
        "electric",
        "supply",
        "supplies-wholesale",
        "equipment",
        "consumer",
        "manufacturer"
    ],
    "sg:website":"http://www.graybar.com",
    "wof:name":"Graybar Electric Company, Inc",
    "wof:placetype":"venue"
},
  "geometry": {"coordinates":[-75.200304,39.934721],"type":"Point"}
}