{
  "type": "Feature",
  "properties": {
    "iso:country":"US",
    "sg:address":"202 E 3rd St",
    "sg:city":"Bethlehem",
    "sg:classifiers":[
        {
            "category":"Organizations",
            "subcategory":"Religious Organization",
            "type":"Services"
        }
    ],
    "sg:phone":"+1 610 332 8080",
    "sg:postcode":"18015",
    "sg:province":"PA",
    "wof:name":"New Bethany Ministries",
    "wof:placetype":"venue"
},
  "geometry": {"coordinates":[-75.37458599999999,40.611985],"type":"Point"}
}