{
  "type": "Feature",
  "properties": {
    "addr:full":"53 W Valley Ave Elysburg PA 17824",
    "addr:housenumber":"53",
    "addr:postcode":"17824",
    "addr:street":"W Valley Ave",
    "iso:country":"US",
    "sg:address":"53 W Valley Ave",
    "sg:city":"Elysburg",
    "sg:classifiers":[
        {
            "category":"Home & Garden",
            "subcategory":"Building Materials",
            "type":"Retail Goods"
        }
    ],
    "sg:phone":"+1   ",
    "sg:postcode":"17824",
    "sg:province":"PA",
    "sg:tags":[
        "supply",
        "fa",
        "general",
        "contractor"
    ],
    "wof:name":"Bebenek Kitchens",
    "wof:placetype":"venue"
},
  "geometry": {"coordinates":[-76.558058,40.85711],"type":"Point"}
}