{
  "type": "Feature",
  "properties": {
    "addr:full":"720 Colonial Rd Harrisburg PA 17112",
    "addr:housenumber":"720",
    "addr:postcode":"17112",
    "addr:street":"Colonial Rd",
    "iso:country":"US",
    "sg:address":"720 Colonial Rd",
    "sg:city":"Harrisburg",
    "sg:classifiers":[
        {
            "category":"Restaurant",
            "type":"Food & Drink"
        }
    ],
    "sg:phone":"+1 717 540 5556",
    "sg:postcode":"17112",
    "sg:province":"PA",
    "sg:tags":[
        "pizza"
    ],
    "wof:name":"Brothers Pizza",
    "wof:placetype":"venue"
},
  "geometry": {"coordinates":[-76.82387199999999,40.309282],"type":"Point"}
}