{
  "type": "Feature",
  "properties": {
    "addr:full":"1103 Towncrest Rd Williamsport PA 17701",
    "addr:housenumber":"1103",
    "addr:postcode":"17701",
    "addr:street":"Towncrest Rd",
    "iso:country":"US",
    "sg:address":"1103 Towncrest Rd",
    "sg:city":"Williamsport",
    "sg:classifiers":[
        {
            "category":"Real Estate",
            "subcategory":"Real Estate Operator",
            "type":"Services"
        }
    ],
    "sg:phone":"+1 570 323 0700",
    "sg:postcode":"17701",
    "sg:province":"PA",
    "sg:tags":[
        "apartment"
    ],
    "wof:name":"Woodland Park Apartments",
    "wof:placetype":"venue"
},
  "geometry": {"coordinates":[-77.08446499999999,41.2372],"type":"Point"}
}