{
  "type": "Feature",
  "properties": {
    "iso:country":"US",
    "sg:address":"7150 Windsor Dr",
    "sg:city":"Allentown",
    "sg:classifiers":[
        {
            "category":"Utilities",
            "subcategory":"Telephone",
            "type":"Services"
        }
    ],
    "sg:phone":"+1 610 530 0112",
    "sg:postcode":"18106",
    "sg:province":"PA",
    "sg:tags":[
        "telecommunication"
    ],
    "wof:name":"Choice One Communications",
    "wof:placetype":"venue"
},
  "geometry": {"coordinates":[-75.62204800000001,40.58295],"type":"Point"}
}