{
  "type": "Feature",
  "properties": {
    "addr:full":"608 N 2nd St Harrisburg PA 17101",
    "addr:housenumber":"608",
    "addr:postcode":"17101",
    "addr:street":"N 2Nd St",
    "iso:country":"US",
    "sg:address":"608 N 2nd St",
    "sg:city":"Harrisburg",
    "sg:classifiers":[
        {
            "category":"Personal",
            "subcategory":"Tanning Parlor",
            "type":"Services"
        }
    ],
    "sg:phone":"+1 717 232 4990",
    "sg:postcode":"17101",
    "sg:province":"PA",
    "sg:tags":[
        "salon"
    ],
    "wof:name":"Electric Tan",
    "wof:placetype":"venue"
},
  "geometry": {"coordinates":[-76.887755,40.263495],"type":"Point"}
}