{
  "type": "Feature",
  "properties": {
    "addr:full":"6965 Ogontz Ave Philadelphia PA 19138",
    "addr:housenumber":"6965",
    "addr:postcode":"19138",
    "addr:street":"Ogontz Ave",
    "iso:country":"US",
    "sg:address":"6965 Ogontz Ave",
    "sg:city":"Philadelphia",
    "sg:classifiers":[
        {
            "category":"Social Services",
            "subcategory":"Child Care",
            "type":"Services"
        }
    ],
    "sg:phone":"+1 215 276 2550",
    "sg:postcode":"19138",
    "sg:province":"PA",
    "wof:name":"Mommie Lelene First Step Dycr",
    "wof:placetype":"venue"
},
  "geometry": {"coordinates":[-75.150885,40.060998],"type":"Point"}
}