{
  "type": "Feature",
  "properties": {
    "iso:country":"US",
    "sg:address":"117 Steubenville Pike",
    "sg:city":"Burgettstown",
    "sg:classifiers":[
        {
            "category":"Health Services",
            "subcategory":"Doctor",
            "type":"Services"
        }
    ],
    "sg:phone":"+1   ",
    "sg:postcode":"15021",
    "sg:province":"PA",
    "sg:tags":[
        "medical"
    ],
    "wof:name":"John Cherian",
    "wof:placetype":"venue"
},
  "geometry": {"coordinates":[-80.50448299999999,40.402093],"type":"Point"}
}