{
  "type": "Feature",
  "properties": {
    "iso:country":"US",
    "sg:address":"6 Edgemoor Rd",
    "sg:city":"Cheltenham",
    "sg:classifiers":[
        {
            "category":"Professional",
            "subcategory":"Business Services",
            "type":"Services"
        }
    ],
    "sg:phone":"+1 215 635 5828",
    "sg:postcode":"19012",
    "sg:province":"PA",
    "sg:tags":[
        "holding"
    ],
    "wof:name":"Dunnics Holding",
    "wof:placetype":"venue"
},
  "geometry": {"coordinates":[-75.11035200000001,40.051696],"type":"Point"}
}