{
  "type": "Feature",
  "properties": {
    "iso:country":"US",
    "sg:address":"2044 Grant Ave",
    "sg:city":"Philadelphia",
    "sg:classifiers":[
        {
            "category":"Local Transit",
            "type":"Transportation"
        }
    ],
    "sg:phone":"+1 215 698 9111",
    "sg:postcode":"19115",
    "sg:province":"PA",
    "sg:tags":[
        "ambulance"
    ],
    "wof:name":"Rhawnhurst Bustleton Volunteer",
    "wof:placetype":"venue"
},
  "geometry": {"coordinates":[-75.03292999999999,40.083124],"type":"Point"}
}