{
  "type": "Feature",
  "properties": {
    "iso:country":"US",
    "sg:address":"81 Johanna Dr",
    "sg:city":"Holland",
    "sg:classifiers":[
        {
            "category":"Freight",
            "type":"Transportation"
        }
    ],
    "sg:phone":"+1 215 355 7805",
    "sg:postcode":"18966",
    "sg:province":"PA",
    "sg:tags":[
        "trucking"
    ],
    "wof:name":"K & L Transports",
    "wof:placetype":"venue"
},
  "geometry": {"coordinates":[-74.971659,40.198536],"type":"Point"}
}