{
  "type": "Feature",
  "properties": {
    "addr:full":"285 Rutter Ave Kingston PA 18704",
    "addr:housenumber":"285",
    "addr:postcode":"18704",
    "addr:street":"Rutter Ave",
    "iso:country":"US",
    "sg:address":"285 Rutter Ave",
    "sg:city":"Kingston",
    "sg:classifiers":[
        {
            "category":"Professional",
            "subcategory":"Art Services",
            "type":"Services"
        }
    ],
    "sg:phone":"+1 570 283 2016",
    "sg:postcode":"18704",
    "sg:province":"PA",
    "sg:tags":[
        "graphic",
        "designer"
    ],
    "wof:name":"Mind Composers Inc",
    "wof:placetype":"venue"
},
  "geometry": {"coordinates":[-75.894188,41.262195],"type":"Point"}
}