{
  "type": "Feature",
  "properties": {
    "iso:country":"US",
    "sg:address":"475 Warick Rd",
    "sg:city":"Wynnewood",
    "sg:classifiers":[
        {
            "category":"Professional",
            "type":"Services"
        }
    ],
    "sg:phone":"+1   ",
    "sg:postcode":"19096",
    "sg:province":"PA",
    "wof:name":"Melvin & Eunice A Miller",
    "wof:placetype":"venue"
},
  "geometry": {"coordinates":[-75.278948,39.993533],"type":"Point"}
}