{
  "type": "Feature",
  "properties": {
    "iso:country":"US",
    "sg:address":"8 Hickory St",
    "sg:city":"Kittanning",
    "sg:classifiers":[
        {
            "category":"Government",
            "subcategory":"Office",
            "type":"Public Place"
        }
    ],
    "sg:phone":"+1   ",
    "sg:postcode":"16201",
    "sg:province":"PA",
    "sg:tags":[
        "executive"
    ],
    "wof:name":"Borough of Applewold",
    "wof:placetype":"venue"
},
  "geometry": {"coordinates":[-79.51960800000001,40.806179],"type":"Point"}
}