{
  "type": "Feature",
  "properties": {
    "iso:country":"US",
    "sg:address":"1102 Cardiff Rd",
    "sg:city":"Nanty Glo",
    "sg:classifiers":[
        {
            "category":"Retail",
            "subcategory":"Funeral Services",
            "type":"Services"
        }
    ],
    "sg:phone":"+1 814 749 0821",
    "sg:postcode":"15943",
    "sg:province":"PA",
    "sg:tags":[
        "director"
    ],
    "wof:name":"Bowser-Ondriezek Funeral Home",
    "wof:placetype":"venue"
},
  "geometry": {"coordinates":[-78.832407,40.474092],"type":"Point"}
}