{
  "type": "Feature",
  "properties": {
    "iso:country":"US",
    "sg:address":"306 S Broad St",
    "sg:city":"Lansdale",
    "sg:classifiers":[
        {
            "category":"Retail",
            "subcategory":"Car Wash",
            "type":"Services"
        }
    ],
    "sg:phone":"+1   ",
    "sg:postcode":"19446",
    "sg:province":"PA",
    "sg:tags":[
        "carwash"
    ],
    "wof:name":"Mr As Auto Salon",
    "wof:placetype":"venue"
},
  "geometry": {"coordinates":[-75.28823199999999,40.23709],"type":"Point"}
}