{
  "type": "Feature",
  "properties": {
    "iso:country":"US",
    "sg:address":"162 S Main St",
    "sg:city":"Nazareth",
    "sg:classifiers":[
        {
            "category":"Shopping",
            "subcategory":"Musical Instruments",
            "type":"Retail Goods"
        }
    ],
    "sg:phone":"+1   ",
    "sg:postcode":"18064",
    "sg:province":"PA",
    "sg:tags":[
        "repair",
        "used",
        "rent",
        "new"
    ],
    "wof:name":"Nazareth Music Center Ltd",
    "wof:placetype":"venue"
},
  "geometry": {"coordinates":[-75.311961,40.738482],"type":"Point"}
}