{
  "type": "Feature",
  "properties": {
    "iso:country":"US",
    "sg:address":"756 Timber Trail Ln",
    "sg:city":"Springfield",
    "sg:classifiers":[
        {
            "category":"Building & Trades",
            "subcategory":"Construction",
            "type":"Services"
        }
    ],
    "sg:phone":"+1   ",
    "sg:postcode":"19064",
    "sg:province":"PA",
    "sg:tags":[
        "house"
    ],
    "wof:name":"Mr2 Builder & Remodl",
    "wof:placetype":"venue"
},
  "geometry": {"coordinates":[-75.33308599999999,39.950791],"type":"Point"}
}