{
  "type": "Feature",
  "properties": {
    "iso:country":"US",
    "sg:address":"876 W Lancaster Ave",
    "sg:city":"Bryn Mawr",
    "sg:classifiers":[
        {
            "category":"Home & Garden",
            "subcategory":"Furniture",
            "type":"Retail Goods"
        }
    ],
    "sg:phone":"+1 610 527 6627",
    "sg:postcode":"19010",
    "sg:province":"PA",
    "sg:tags":[
        "furnishing"
    ],
    "wof:name":"Origin & Ash",
    "wof:placetype":"venue"
},
  "geometry": {"coordinates":[-75.320791,40.022609],"type":"Point"}
}