{
  "type": "Feature",
  "properties": {
    "iso:country":"US",
    "sg:address":"51 Small Mountain Rd",
    "sg:city":"Wapwallopen",
    "sg:classifiers":[
        {
            "category":"Transit Center",
            "subcategory":"Freight",
            "type":"Transportation"
        },
        {
            "category":"Freight",
            "type":"Transportation"
        }
    ],
    "sg:phone":"+1 570 868 6936",
    "sg:postcode":"18660",
    "sg:province":"PA",
    "sg:tags":[
        "local",
        "trucking-motor",
        "trucking"
    ],
    "sg:website":"http://www.pennsysupply.com",
    "wof:name":"Pennsy Supply",
    "wof:placetype":"venue"
},
  "geometry": {"coordinates":[-75.964629,41.083791],"type":"Point"}
}