{
  "type": "Feature",
  "properties": {
    "iso:country":"US",
    "sg:address":"3500 Sharon Rd",
    "sg:city":"West Middlesex",
    "sg:classifiers":[
        {
            "category":"Freight",
            "type":"Transportation"
        }
    ],
    "sg:phone":"+1 724 528 3398",
    "sg:postcode":"16159",
    "sg:province":"PA",
    "sg:tags":[
        "trucking"
    ],
    "wof:name":"Arnold Barris Trucking",
    "wof:placetype":"venue"
},
  "geometry": {"coordinates":[-80.455504,41.176722],"type":"Point"}
}