{
  "type": "Feature",
  "properties": {
    "addr:full":"112 Rocky Glen Rd Oxford PA 19363",
    "addr:housenumber":"112",
    "addr:postcode":"19363",
    "addr:street":"Rocky Glen Rd",
    "iso:country":"US",
    "sg:address":"112 Rocky Glen Rd",
    "sg:city":"Oxford",
    "sg:classifiers":[
        {
            "category":"Building & Trades",
            "subcategory":"Construction",
            "type":"Services"
        }
    ],
    "sg:phone":"+1   ",
    "sg:postcode":"19363",
    "sg:province":"PA",
    "sg:tags":[
        "house",
        "carpentry",
        "contractor"
    ],
    "wof:name":"Bill McSorley",
    "wof:placetype":"venue"
},
  "geometry": {"coordinates":[-75.90835300000001,39.737531],"type":"Point"}
}