{
  "type": "Feature",
  "properties": {
    "iso:country":"US",
    "sg:address":"114 Montgomery Ave",
    "sg:city":"Oreland",
    "sg:classifiers":[
        {
            "category":"Real Estate",
            "subcategory":"Real Estate Agent",
            "type":"Services"
        },
        {
            "category":"Professional",
            "subcategory":"Business Services",
            "type":"Services"
        }
    ],
    "sg:phone":"+1 215 886 5950",
    "sg:postcode":"19075",
    "sg:province":"PA",
    "sg:tags":[
        "appraiser"
    ],
    "wof:name":"James P Benencasa Appraisals",
    "wof:placetype":"venue"
},
  "geometry": {"coordinates":[-75.18571,40.116075],"type":"Point"}
}