{
  "type": "Feature",
  "properties": {
    "iso:country":"US",
    "sg:address":"1702 Chichester Ave",
    "sg:city":"Marcus Hook",
    "sg:classifiers":[
        {
            "category":"Personal",
            "subcategory":"Beauty Salon",
            "type":"Services"
        }
    ],
    "sg:phone":"+1   ",
    "sg:postcode":"19061",
    "sg:province":"PA",
    "sg:tags":[
        "shop"
    ],
    "wof:name":"Cianfrinis Cstm Cut Buty Salon",
    "wof:placetype":"venue"
},
  "geometry": {"coordinates":[-75.42925,39.827577],"type":"Point"}
}