{
  "type": "Feature",
  "properties": {
    "iso:country":"US",
    "sg:address":"1309 Highland Ave",
    "sg:city":"Abington",
    "sg:classifiers":[
        {
            "category":"Building & Trades",
            "subcategory":"Construction",
            "type":"Services"
        }
    ],
    "sg:phone":"+1 215 885 4882",
    "sg:postcode":"19001",
    "sg:province":"PA",
    "sg:tags":[
        "general",
        "contractor"
    ],
    "wof:name":"J P Rainey & Co",
    "wof:placetype":"venue"
},
  "geometry": {"coordinates":[-75.119544,40.121504],"type":"Point"}
}