{
  "type": "Feature",
  "properties": {
    "iso:country":"US",
    "sg:address":"4245 Union Deposit Rd",
    "sg:city":"Harrisburg",
    "sg:classifiers":[
        {
            "category":"Banks & Credit Unions",
            "subcategory":"Bank",
            "type":"Services"
        }
    ],
    "sg:phone":"+1 717 652 5713",
    "sg:postcode":"17111",
    "sg:province":"PA",
    "wof:name":"Pnc Bank",
    "wof:placetype":"venue"
},
  "geometry": {"coordinates":[-76.815504,40.27896],"type":"Point"}
}