{
  "type": "Feature",
  "properties": {
    "addr:full":"377 Echo Valley Rd New Galilee PA 16141",
    "addr:housenumber":"377",
    "addr:postcode":"16141",
    "addr:street":"Echo Valley Rd",
    "iso:country":"US",
    "sg:address":"377 Echo Valley Rd",
    "sg:city":"New Galilee",
    "sg:classifiers":[
        {
            "category":"Farming",
            "subcategory":"Livestock Farm",
            "type":"Manufacturing & Wholesale Goods"
        }
    ],
    "sg:phone":"+1   ",
    "sg:postcode":"16141",
    "sg:province":"PA",
    "sg:tags":[
        "feedlot",
        "field",
        "crop",
        "beef",
        "cattle"
    ],
    "wof:name":"Jackie Nelson",
    "wof:placetype":"venue"
},
  "geometry": {"coordinates":[-80.439367,40.850037],"type":"Point"}
}