{
  "type": "Feature",
  "properties": {
    "iso:country":"US",
    "sg:address":"1807 Pine Hollow Rd",
    "sg:city":"Mc Kees Rocks",
    "sg:classifiers":[
        {
            "category":"Personal",
            "subcategory":"Beauty Salon",
            "type":"Services"
        }
    ],
    "sg:phone":"+1   ",
    "sg:postcode":"15136",
    "sg:province":"PA",
    "sg:tags":[
        "shop"
    ],
    "wof:name":"Macys Hair Salon",
    "wof:placetype":"venue"
},
  "geometry": {"coordinates":[-80.10213299999999,40.47713],"type":"Point"}
}