{
  "type": "Feature",
  "properties": {
    "iso:country":"US",
    "sg:address":"340 Regis Ave",
    "sg:city":"Pittsburgh",
    "sg:classifiers":[
        {
            "category":"Recreation",
            "subcategory":"Amusement Park",
            "type":"Entertainment"
        }
    ],
    "sg:phone":"+1   ",
    "sg:postcode":"15236",
    "sg:province":"PA",
    "sg:tags":[
        "park"
    ],
    "wof:name":"Trackers Go Cart Raceway Inc",
    "wof:placetype":"venue"
},
  "geometry": {"coordinates":[-79.955561,40.340522],"type":"Point"}
}