{
  "type": "Feature",
  "properties": {
    "iso:country":"US",
    "sg:address":"959 Bellview St",
    "sg:city":"Creighton",
    "sg:classifiers":[
        {
            "category":"Retail",
            "subcategory":"Auto Repair",
            "type":"Services"
        }
    ],
    "sg:phone":"+1 724 226 3061",
    "sg:postcode":"15030",
    "sg:province":"PA",
    "sg:tags":[
        "wrecker"
    ],
    "wof:name":"Jim Faas Towing",
    "wof:placetype":"venue"
},
  "geometry": {"coordinates":[-79.77836600000001,40.583738],"type":"Point"}
}