{
  "type": "Feature",
  "properties": {
    "addr:full":"103 Smiley Ln Stroudsburg PA 18360",
    "addr:housenumber":"103",
    "addr:postcode":"18360",
    "addr:street":"Smiley Ln",
    "iso:country":"US",
    "sg:address":"103 Smiley Ln",
    "sg:city":"Stroudsburg",
    "sg:classifiers":[
        {
            "category":"Shopping",
            "type":"Retail Goods"
        }
    ],
    "sg:phone":"+1 570 236 9454",
    "sg:postcode":"18360",
    "sg:province":"PA",
    "sg:tags":[
        "merchandise"
    ],
    "wof:name":"Shop To Earn",
    "wof:placetype":"venue"
},
  "geometry": {"coordinates":[-75.316171,40.955509],"type":"Point"}
}