{
  "type": "Feature",
  "properties": {
    "iso:country":"US",
    "sg:address":"2100 Market St",
    "sg:city":"Philadelphia",
    "sg:classifiers":[
        {
            "category":"Restaurant",
            "type":"Food & Drink"
        }
    ],
    "sg:menulink":"http://www.allmenus.com/pa/philadelphia/64640-papa-johns-pizza/menu/",
    "sg:phone":"+1 215 972 0505",
    "sg:postcode":"19103",
    "sg:province":"PA",
    "sg:tags":[
        "american",
        "pizza"
    ],
    "wof:name":"Papa John's Pizza",
    "wof:placetype":"venue"
},
  "geometry": {"coordinates":[-75.175101,39.953822],"type":"Point"}
}