{
  "type": "Feature",
  "properties": {
    "addr:full":"211 South St Waymart PA 18472",
    "addr:housenumber":"211",
    "addr:postcode":"18472",
    "addr:street":"South St",
    "iso:country":"US",
    "sg:address":"211 South St",
    "sg:city":"Waymart",
    "sg:classifiers":[
        {
            "category":"Landmark",
            "subcategory":"Historic",
            "type":"Public Place"
        }
    ],
    "sg:phone":"+1 570 488 6476",
    "sg:postcode":"18472",
    "sg:province":"PA",
    "sg:tags":[
        "historical"
    ],
    "wof:name":"Waymart Area Historical Society",
    "wof:placetype":"venue"
},
  "geometry": {"coordinates":[-75.40728,41.580631],"type":"Point"}
}