{
  "type": "Feature",
  "properties": {
    "iso:country":"US",
    "sg:address":"6401 Vera Cruz Rd S",
    "sg:city":"Zionsville",
    "sg:classifiers":[
        {
            "category":"Organizations",
            "subcategory":"Religious Organization",
            "type":"Services"
        }
    ],
    "sg:phone":"+1   ",
    "sg:postcode":"18092",
    "sg:province":"PA",
    "wof:name":"Bible Fllwship Chrch Zonsville",
    "wof:placetype":"venue"
},
  "geometry": {"coordinates":[-75.497169,40.485199],"type":"Point"}
}