{
  "type": "Feature",
  "properties": {
    "addr:full":"130 Park St Ebensburg PA 15931",
    "addr:housenumber":"130",
    "addr:postcode":"15931",
    "addr:street":"Park St",
    "iso:country":"US",
    "sg:address":"130 Park St",
    "sg:city":"Ebensburg",
    "sg:classifiers":[
        {
            "category":"Banks & Credit Unions",
            "subcategory":"Financial Services",
            "type":"Services"
        }
    ],
    "sg:phone":"+1   ",
    "sg:postcode":"15931",
    "sg:province":"PA",
    "sg:tags":[
        "trust",
        "investment",
        "real estate"
    ],
    "wof:name":"Woo Holding Limited",
    "wof:placetype":"venue"
},
  "geometry": {"coordinates":[-78.733582,40.483882],"type":"Point"}
}