{
  "type": "Feature",
  "properties": {
    "iso:country":"US",
    "sg:address":"1000 W Main St",
    "sg:city":"Lansdale",
    "sg:classifiers":[
        {
            "category":"Education",
            "subcategory":"Preschool",
            "type":"Public Place"
        },
        {
            "category":"Education",
            "subcategory":"School",
            "type":"Public Place"
        }
    ],
    "sg:phone":"+1 215 368 1710",
    "sg:postcode":"19446",
    "sg:province":"PA",
    "sg:tags":[
        "elementary"
    ],
    "sg:website":"www.trinitylansdale.com",
    "wof:name":"Trinity Lutheran Church",
    "wof:placetype":"venue"
},
  "geometry": {"coordinates":[-75.29630299999999,40.249199],"type":"Point"}
}