{
  "type": "Feature",
  "properties": {
    "iso:country":"US",
    "sg:address":"5530 Walnut St",
    "sg:city":"Pittsburgh",
    "sg:classifiers":[
        {
            "category":"Food & Beverages",
            "subcategory":"Specialty",
            "type":"Retail Goods"
        }
    ],
    "sg:phone":"+1 412 621 6512",
    "sg:postcode":"15232",
    "sg:province":"PA",
    "sg:tags":[
        "health",
        "diet"
    ],
    "wof:name":"General Nutrition Ctr",
    "wof:placetype":"venue"
},
  "geometry": {"coordinates":[-79.932159,40.451616],"type":"Point"}
}