{
  "type": "Feature",
  "properties": {
    "iso:country":"US",
    "sg:address":"2370 Ogden Ave",
    "sg:city":"Bensalem",
    "sg:classifiers":[
        {
            "category":"Professional",
            "subcategory":"Detective & Security Services",
            "type":"Services"
        }
    ],
    "sg:phone":"+1 215 639 2521",
    "sg:postcode":"19020",
    "sg:province":"PA",
    "sg:tags":[
        "information",
        "bureau"
    ],
    "wof:name":"Joe Casey Services",
    "wof:placetype":"venue"
},
  "geometry": {"coordinates":[-74.949614,40.081433],"type":"Point"}
}