{
  "type": "Feature",
  "properties": {
    "iso:country":"US",
    "sg:address":"719 W 8th St",
    "sg:city":"Wyoming",
    "sg:classifiers":[
        {
            "category":"Building & Trades",
            "subcategory":"Construction",
            "type":"Services"
        }
    ],
    "sg:phone":"+1   ",
    "sg:postcode":"18644",
    "sg:province":"PA",
    "sg:tags":[
        "roofing",
        "siding",
        "contractor"
    ],
    "wof:name":"Eshelman Archie Jr Cnstr Co",
    "wof:placetype":"venue"
},
  "geometry": {"coordinates":[-75.849924,41.32419],"type":"Point"}
}