{
  "type": "Feature",
  "properties": {
    "iso:country":"US",
    "sg:address":"350 Isle Rd",
    "sg:city":"Butler",
    "sg:classifiers":[
        {
            "category":"Manufacturing",
            "subcategory":"Tools & Machinery",
            "type":"Manufacturing & Wholesale Goods"
        }
    ],
    "sg:phone":"+1 724 865 9746",
    "sg:postcode":"16001",
    "sg:province":"PA",
    "sg:tags":[
        "mfg"
    ],
    "wof:name":"Hemphill Precision",
    "wof:placetype":"venue"
},
  "geometry": {"coordinates":[-80.001482,40.932444],"type":"Point"}
}