{
  "type": "Feature",
  "properties": {
    "iso:country":"US",
    "sg:address":"215 Hillcrest Shopping Center",
    "sg:city":"Lower Burrell",
    "sg:classifiers":[
        {
            "category":"Wholesale",
            "subcategory":"Machinery & Supplies",
            "type":"Manufacturing & Wholesale Goods"
        }
    ],
    "sg:phone":"+1 724 339 4795",
    "sg:postcode":"15068",
    "sg:province":"PA",
    "sg:tags":[
        "shop",
        "equipment",
        "salon",
        "barber",
        "beauty"
    ],
    "wof:name":"Sally Beauty Supply 688",
    "wof:placetype":"venue"
},
  "geometry": {"coordinates":[-79.70886900000001,40.584207],"type":"Point"}
}