{
  "type": "Feature",
  "properties": {
    "iso:country":"US",
    "sg:address":"2201 Spruce St",
    "sg:city":"Philadelphia",
    "sg:classifiers":[
        {
            "category":"Restaurant",
            "type":"Food & Drink"
        }
    ],
    "sg:phone":"+1 215 875 8116",
    "sg:postcode":"19103",
    "sg:province":"PA",
    "sg:tags":[
        "italian"
    ],
    "wof:name":"Melograno",
    "wof:placetype":"venue"
},
  "geometry": {"coordinates":[-75.17785600000001,39.948608],"type":"Point"}
}