{
  "type": "Feature",
  "properties": {
    "iso:country":"US",
    "sg:address":"10 Molleystown Rd",
    "sg:city":"Pine Grove",
    "sg:classifiers":[
        {
            "category":"Restaurant",
            "type":"Food & Drink"
        }
    ],
    "sg:phone":"+1 570 345 2772",
    "sg:postcode":"17963",
    "sg:province":"PA",
    "wof:name":"Dave's Raceway Restaurant",
    "wof:placetype":"venue"
},
  "geometry": {"coordinates":[-76.410394,40.592454],"type":"Point"}
}