{
  "type": "Feature",
  "properties": {
    "addr:full":"604 Sylvania Dr Exton PA 19341",
    "addr:housenumber":"604",
    "addr:postcode":"19341",
    "addr:street":"Sylvania Dr",
    "iso:country":"US",
    "sg:address":"604 Sylvania Dr",
    "sg:city":"Exton",
    "sg:classifiers":[
        {
            "category":"Professional",
            "subcategory":"Management & Consulting",
            "type":"Services"
        }
    ],
    "sg:phone":"+1 610 363 8231",
    "sg:postcode":"19341",
    "sg:province":"PA",
    "sg:tags":[
        "consultant",
        "business"
    ],
    "wof:name":"Ford Business Solutions Inc",
    "wof:placetype":"venue"
},
  "geometry": {"coordinates":[-75.615076,40.0311],"type":"Point"}
}