{
  "type": "Feature",
  "properties": {
    "addr:full":"404 Western Ave Washington PA 15301",
    "addr:housenumber":"404",
    "addr:postcode":"15301",
    "addr:street":"Western Ave",
    "iso:country":"US",
    "sg:address":"404 Western Ave",
    "sg:city":"Washington",
    "sg:classifiers":[
        {
            "category":"Shopping",
            "subcategory":"Used Merchandise",
            "type":"Retail Goods"
        }
    ],
    "sg:phone":"+1 724 222 8276",
    "sg:postcode":"15301",
    "sg:province":"PA",
    "sg:tags":[
        "antique",
        "auctioneer"
    ],
    "wof:name":"Westland Auction",
    "wof:placetype":"venue"
},
  "geometry": {"coordinates":[-80.220156,40.250702],"type":"Point"}
}