{
  "type": "Feature",
  "properties": {
    "addr:full":"2601 N 23rd St Philadelphia PA 19132",
    "addr:housenumber":"2601",
    "addr:postcode":"19132",
    "addr:street":"N 23Rd St",
    "iso:country":"US",
    "sg:address":"2601 N 23rd St",
    "sg:city":"Philadelphia",
    "sg:classifiers":[
        {
            "category":"Food & Beverages",
            "subcategory":"Groceries & Convenience Stores",
            "type":"Retail Goods"
        }
    ],
    "sg:phone":"+1 215 223 0101",
    "sg:postcode":"19132",
    "sg:province":"PA",
    "sg:tags":[
        "grocer"
    ],
    "wof:name":"Franchiany Grocery",
    "wof:placetype":"venue"
},
  "geometry": {"coordinates":[-75.1694,39.994769],"type":"Point"}
}