{
  "type": "Feature",
  "properties": {
    "iso:country":"US",
    "sg:address":"1321 Mahoning Dr E",
    "sg:city":"Lehighton",
    "sg:classifiers":[
        {
            "category":"Professional",
            "type":"Services"
        }
    ],
    "sg:phone":"+1   ",
    "sg:postcode":"18235",
    "sg:province":"PA",
    "wof:name":"Mark Mason",
    "wof:placetype":"venue"
},
  "geometry": {"coordinates":[-75.747091,40.824773],"type":"Point"}
}