{
  "type": "Feature",
  "properties": {
    "iso:country":"US",
    "sg:address":"430 Elizabeth Ave",
    "sg:city":"Reading",
    "sg:classifiers":[
        {
            "category":"Restaurant",
            "type":"Food & Drink"
        }
    ],
    "sg:menulink":"http://www.allmenus.com/pa/muhlenberg/206807-mcdonalds/menu/",
    "sg:phone":"+1 610 921 8681",
    "sg:postcode":"19605",
    "sg:province":"PA",
    "sg:tags":[
        "burger",
        "american"
    ],
    "wof:name":"McDonald's",
    "wof:placetype":"venue"
},
  "geometry": {"coordinates":[-75.926889,40.38506],"type":"Point"}
}