{
  "type": "Feature",
  "properties": {
    "iso:country":"US",
    "sg:address":"1109 W Chester Rd",
    "sg:city":"West Chester",
    "sg:classifiers":[
        {
            "category":"Professional",
            "subcategory":"Management & Consulting",
            "type":"Services"
        }
    ],
    "sg:phone":"+1   ",
    "sg:postcode":"19382",
    "sg:province":"PA",
    "sg:tags":[
        "support",
        "facility"
    ],
    "wof:name":"Ground Water & Envmtl Svc",
    "wof:placetype":"venue"
},
  "geometry": {"coordinates":[-75.546357,39.911133],"type":"Point"}
}