{
  "type": "Feature",
  "properties": {
    "addr:full":"114 Dolores Dr Irwin PA 15642",
    "addr:housenumber":"114",
    "addr:postcode":"15642",
    "addr:street":"Dolores Dr",
    "iso:country":"US",
    "sg:address":"114 Dolores Dr",
    "sg:city":"Irwin",
    "sg:classifiers":[
        {
            "category":"Wholesale",
            "subcategory":"Apparel",
            "type":"Manufacturing & Wholesale Goods"
        }
    ],
    "sg:phone":"+1   ",
    "sg:postcode":"15642",
    "sg:province":"PA",
    "sg:tags":[
        "clothing"
    ],
    "wof:name":"Bold Impressions",
    "wof:placetype":"venue"
},
  "geometry": {"coordinates":[-79.66832700000001,40.373913],"type":"Point"}
}