{
  "type": "Feature",
  "properties": {
    "iso:country":"US",
    "sg:address":"345 N Pike Rd",
    "sg:city":"Sarver",
    "sg:classifiers":[
        {
            "category":"Professional",
            "subcategory":"Accounting & Tax Preparation",
            "type":"Services"
        }
    ],
    "sg:phone":"+1 724 295 3800",
    "sg:postcode":"16055",
    "sg:province":"PA",
    "sg:tags":[
        "accountant"
    ],
    "wof:name":"Paul & Paul PC",
    "wof:placetype":"venue"
},
  "geometry": {"coordinates":[-79.765148,40.742644],"type":"Point"}
}