{
  "type": "Feature",
  "properties": {
    "iso:country":"US",
    "sg:address":"274 Gateshead Dr",
    "sg:city":"Canonsburg",
    "sg:classifiers":[
        {
            "category":"Health Services",
            "subcategory":"Dentist",
            "type":"Services"
        }
    ],
    "sg:phone":"+1 724 941 5751",
    "sg:postcode":"15317",
    "sg:province":"PA",
    "wof:name":"Assid Edwin E DMD",
    "wof:placetype":"venue"
},
  "geometry": {"coordinates":[-80.101303,40.282501],"type":"Point"}
}