{
  "type": "Feature",
  "properties": {
    "iso:country":"US",
    "sg:address":"8313 Stenton Ave",
    "sg:city":"Philadelphia",
    "sg:classifiers":[
        {
            "category":"Retail",
            "subcategory":"Laundry & Dry Cleaning",
            "type":"Services"
        }
    ],
    "sg:phone":"+1 215 247 0668",
    "sg:postcode":"19150",
    "sg:province":"PA",
    "sg:tags":[
        "cleaners"
    ],
    "wof:name":"Clean Cleaners",
    "wof:placetype":"venue"
},
  "geometry": {"coordinates":[-75.182014,40.069104],"type":"Point"}
}