{
  "type": "Feature",
  "properties": {
    "addr:full":"609 Somerset Ave Windber PA 15963",
    "addr:housenumber":"609",
    "addr:postcode":"15963",
    "addr:street":"Somerset Ave",
    "iso:country":"US",
    "sg:address":"609 Somerset Ave",
    "sg:city":"Windber",
    "sg:classifiers":[
        {
            "category":"Health Services",
            "subcategory":"Doctor",
            "type":"Services"
        }
    ],
    "sg:phone":"+1 814 467 6687",
    "sg:postcode":"15963",
    "sg:province":"PA",
    "sg:tags":[
        "physician",
        "surgeon"
    ],
    "wof:name":"Neil Ih Park Inc",
    "wof:placetype":"venue"
},
  "geometry": {"coordinates":[-78.837039,40.241525],"type":"Point"}
}