{
  "type": "Feature",
  "properties": {
    "addr:full":"4670 Horseshoe Pike Honey Brook PA 19344",
    "addr:housenumber":"4670",
    "addr:postcode":"19344",
    "addr:street":"Horseshoe Pike",
    "iso:country":"US",
    "sg:address":"4670 Horseshoe Pike",
    "sg:city":"Honey Brook",
    "sg:phone":"+1 610 273 3240",
    "sg:postcode":"19344",
    "sg:province":"PA",
    "sg:tags":[
        "communications",
        "telegraph"
    ],
    "wof:name":"Eckerd",
    "wof:placetype":"venue"
},
  "geometry": {"coordinates":[-75.91302399999999,40.095653],"type":"Point"}
}