{
  "type": "Feature",
  "properties": {
    "addr:full":"1901 Midland Beaver Rd Industry PA 15052",
    "addr:housenumber":"1901",
    "addr:postcode":"15052",
    "addr:street":"Midland Beaver Rd",
    "iso:country":"US",
    "sg:address":"1901 Midland Beaver Rd",
    "sg:city":"Industry",
    "sg:classifiers":[
        {
            "category":"Restaurant",
            "type":"Food & Drink"
        }
    ],
    "sg:menulink":"http://www.allmenus.com/pa/industry/292512-jrs-pizza/menu/",
    "sg:phone":"+1 724 375 7348",
    "sg:postcode":"15052",
    "sg:province":"PA",
    "sg:tags":[
        "pizza"
    ],
    "wof:name":"JR's Pizza",
    "wof:placetype":"venue"
},
  "geometry": {"coordinates":[-80.400942,40.65128],"type":"Point"}
}