{
  "type": "Feature",
  "properties": {
    "iso:country":"US",
    "sg:address":"5235 Simpson Ferry Rd",
    "sg:city":"Mechanicsburg",
    "sg:classifiers":[
        {
            "category":"Restaurant",
            "type":"Food & Drink"
        }
    ],
    "sg:phone":"+1 717 691 1872",
    "sg:postcode":"17050",
    "sg:province":"PA",
    "sg:website":"www.wendys.com",
    "wof:name":"Wendy's Old Fashioned Hamburgers",
    "wof:placetype":"venue"
},
  "geometry": {"coordinates":[-76.982697,40.217499],"type":"Point"}
}