{
  "type": "Feature",
  "properties": {
    "iso:country":"US",
    "sg:address":"500 Glenn Rd",
    "sg:city":"State College",
    "sg:classifiers":[
        {
            "category":"Professional",
            "type":"Services"
        }
    ],
    "sg:phone":"+1   ",
    "sg:postcode":"16803",
    "sg:province":"PA",
    "wof:name":"Information Resource Corp",
    "wof:placetype":"venue"
},
  "geometry": {"coordinates":[-77.88206099999999,40.795096],"type":"Point"}
}