{
  "type": "Feature",
  "properties": {
    "iso:country":"US",
    "sg:address":"2933 Teesdale St",
    "sg:city":"Philadelphia",
    "sg:classifiers":[
        {
            "category":"Building & Trades",
            "subcategory":"Electrical",
            "type":"Services"
        }
    ],
    "sg:phone":"+1 215 333 4310",
    "sg:postcode":"19152",
    "sg:province":"PA",
    "sg:tags":[
        "electrical",
        "contractor"
    ],
    "wof:name":"Sollmer Electric",
    "wof:placetype":"venue"
},
  "geometry": {"coordinates":[-75.05035100000001,40.043387],"type":"Point"}
}