{
  "type": "Feature",
  "properties": {
    "addr:full":"109 E Main St Dallastown PA 17313",
    "addr:housenumber":"109",
    "addr:postcode":"17313",
    "addr:street":"E Main St",
    "iso:country":"US",
    "sg:address":"109 E Main St",
    "sg:city":"Dallastown",
    "sg:classifiers":[
        {
            "category":"Place Of Worship",
            "subcategory":"Church",
            "type":"Public Place"
        },
        {
            "category":"Place Of Worship",
            "type":"Public Place"
        },
        {
            "category":"Education",
            "subcategory":"Preschool",
            "type":"Public Place"
        }
    ],
    "sg:phone":"+1 717 244 1486",
    "sg:postcode":"17313",
    "sg:province":"PA",
    "sg:tags":[
        "kindergarten",
        "churches-methodist"
    ],
    "wof:name":"Bethlehem United Methodist Church",
    "wof:placetype":"venue"
},
  "geometry": {"coordinates":[-76.641695,39.900512],"type":"Point"}
}