{
  "type": "Feature",
  "properties": {
    "iso:country":"US",
    "sg:address":"1134 Ridge Rd",
    "sg:city":"Pottstown",
    "sg:classifiers":[
        {
            "category":"Wholesale",
            "subcategory":"Electrical",
            "type":"Manufacturing & Wholesale Goods"
        }
    ],
    "sg:phone":"+1 610 469 6082",
    "sg:postcode":"19465",
    "sg:province":"PA",
    "sg:tags":[
        "sound",
        "equipment",
        "system"
    ],
    "wof:name":"Fitch Electronics Inc",
    "wof:placetype":"venue"
},
  "geometry": {"coordinates":[-75.66699300000001,40.174591],"type":"Point"}
}