{
  "type": "Feature",
  "properties": {
    "iso:country":"US",
    "sg:address":"4100 Washington Rd",
    "sg:city":"Canonsburg",
    "sg:classifiers":[
        {
            "category":"Professional",
            "subcategory":"Art Services",
            "type":"Services"
        }
    ],
    "sg:phone":"+1 724 941 5260",
    "sg:postcode":"15317",
    "sg:province":"PA",
    "sg:tags":[
        "commercial",
        "artist"
    ],
    "wof:name":"The Art Department Inc",
    "wof:placetype":"venue"
},
  "geometry": {"coordinates":[-80.129729,40.265335],"type":"Point"}
}