{
  "type": "Feature",
  "properties": {
    "iso:country":"US",
    "sg:address":"3449 N Mascher St",
    "sg:city":"Philadelphia",
    "sg:classifiers":[
        {
            "category":"Education",
            "subcategory":"School",
            "type":"Public Place"
        }
    ],
    "sg:phone":"+1 215 291 4704",
    "sg:postcode":"19140",
    "sg:province":"PA",
    "sg:tags":[
        "high",
        "middle",
        "elementary"
    ],
    "sg:website":"www.phila.k12.pa.us",
    "wof:name":"Philadelphia City School District",
    "wof:placetype":"venue"
},
  "geometry": {"coordinates":[-75.130245,40.002582],"type":"Point"}
}