{
  "type": "Feature",
  "properties": {
    "iso:country":"US",
    "sg:address":"2700 Monroeville Blvd",
    "sg:city":"Monroeville",
    "sg:classifiers":[
        {
            "category":"Social Services",
            "type":"Services"
        }
    ],
    "sg:phone":"+1   ",
    "sg:postcode":"15146",
    "sg:province":"PA",
    "wof:name":"Eastern Rgional Communications",
    "wof:placetype":"venue"
},
  "geometry": {"coordinates":[-79.779983,40.436459],"type":"Point"}
}