{
  "type": "Feature",
  "properties": {
    "iso:country":"US",
    "sg:address":"136 Water Mark Rd",
    "sg:city":"Oxford",
    "sg:phone":"+1   ",
    "sg:postcode":"19363",
    "sg:province":"PA",
    "sg:tags":[
        "wheat",
        "farm",
        "corn",
        "crop",
        "field",
        "soybean"
    ],
    "wof:name":"Watermark Farm",
    "wof:placetype":"venue"
},
  "geometry": {"coordinates":[-75.988435,39.849683],"type":"Point"}
}