{
  "type": "Feature",
  "properties": {
    "iso:country":"US",
    "sg:address":"601 Mayer St",
    "sg:city":"Bridgeville",
    "sg:classifiers":[
        {
            "category":"Wholesale",
            "subcategory":"Machinery & Supplies",
            "type":"Manufacturing & Wholesale Goods"
        },
        {
            "category":"Manufacturing",
            "subcategory":"Tools & Machinery",
            "type":"Manufacturing & Wholesale Goods"
        }
    ],
    "sg:phone":"+1 412 220 9371",
    "sg:postcode":"15017",
    "sg:province":"PA",
    "sg:tags":[
        "measuring",
        "repair",
        "industrial",
        "mfg",
        "equipment",
        "thermocouple"
    ],
    "wof:name":"Pittsburgh Control Systems Inc",
    "wof:placetype":"venue"
},
  "geometry": {"coordinates":[-80.106402,40.365411],"type":"Point"}
}