{
  "type": "Feature",
  "properties": {
    "iso:country":"US",
    "sg:address":"1238 W Market St",
    "sg:city":"Williamstown",
    "sg:classifiers":[
        {
            "category":"Food & Beverages",
            "subcategory":"Groceries & Convenience Stores",
            "type":"Retail Goods"
        }
    ],
    "sg:phone":"+1   ",
    "sg:postcode":"17098",
    "sg:province":"PA",
    "wof:name":"Dayton Market Inc",
    "wof:placetype":"venue"
},
  "geometry": {"coordinates":[-76.646734,40.576892],"type":"Point"}
}