{
  "type": "Feature",
  "properties": {
    "iso:country":"US",
    "sg:address":"210 W Lancaster Ave",
    "sg:city":"Ardmore",
    "sg:classifiers":[
        {
            "category":"Shopping",
            "subcategory":"Hobbies, Toys, & Games",
            "type":"Retail Goods"
        }
    ],
    "sg:phone":"+1   ",
    "sg:postcode":"19003",
    "sg:province":"PA",
    "wof:name":"Ardmore Toy Store",
    "wof:placetype":"venue"
},
  "geometry": {"coordinates":[-75.295779,40.010231],"type":"Point"}
}