{
  "type": "Feature",
  "properties": {
    "iso:country":"US",
    "sg:address":"1121 S 11th St",
    "sg:city":"Philadelphia",
    "sg:classifiers":[
        {
            "category":"Health Services",
            "subcategory":"Clinic",
            "type":"Services"
        },
        {
            "category":"Health Services",
            "subcategory":"Nursing And Care Facility",
            "type":"Services"
        },
        {
            "category":"Health Services",
            "subcategory":"Health Practitioner",
            "type":"Services"
        }
    ],
    "sg:phone":"+1 215 389 1800",
    "sg:postcode":"19147",
    "sg:province":"PA",
    "sg:tags":[
        "home",
        "medical",
        "eldercare-home"
    ],
    "wof:name":"Act Home Health Services, Inc.",
    "wof:placetype":"venue"
},
  "geometry": {"coordinates":[-75.161593,39.936596],"type":"Point"}
}