{
  "type": "Feature",
  "properties": {
    "iso:country":"US",
    "sg:address":"436 Baltimore Ave",
    "sg:city":"Media",
    "sg:classifiers":[
        {
            "category":"Professional",
            "subcategory":"Lawyer & Legal Services",
            "type":"Services"
        }
    ],
    "sg:phone":"+1 610 891 0246",
    "sg:postcode":"19063",
    "sg:province":"PA",
    "sg:tags":[
        "attorney"
    ],
    "sg:website":"www.palumbolawoffice.com",
    "wof:name":"Greg Palumbo & Assoc",
    "wof:placetype":"venue"
},
  "geometry": {"coordinates":[-75.380922,39.915554],"type":"Point"}
}