{
  "type": "Feature",
  "properties": {
    "iso:country":"US",
    "sg:address":"52 Housers Ln",
    "sg:city":"Ringtown",
    "sg:classifiers":[
        {
            "category":"Farming",
            "subcategory":"Livestock Farm",
            "type":"Manufacturing & Wholesale Goods"
        }
    ],
    "sg:phone":"+1   ",
    "sg:postcode":"17967",
    "sg:province":"PA",
    "sg:tags":[
        "beef",
        "corn",
        "cash",
        "field",
        "grain",
        "cattle",
        "cr",
        "feedlot"
    ],
    "wof:name":"Paul Deebel",
    "wof:placetype":"venue"
},
  "geometry": {"coordinates":[-76.20498600000001,40.865948],"type":"Point"}
}