{
  "type": "Feature",
  "properties": {
    "iso:country":"US",
    "sg:address":"128 W Chester Pike",
    "sg:city":"Havertown",
    "sg:classifiers":[
        {
            "category":"Personal",
            "type":"Services"
        }
    ],
    "sg:phone":"+1   ",
    "sg:postcode":"19083",
    "sg:province":"PA",
    "wof:name":"Abats Tag Service",
    "wof:placetype":"venue"
},
  "geometry": {"coordinates":[-75.295863,39.968617],"type":"Point"}
}