{
  "type": "Feature",
  "properties": {
    "iso:country":"US",
    "sg:address":"195 Hykes Mill Rd",
    "sg:city":"York Haven",
    "sg:classifiers":[
        {
            "category":"Autos & Motor Vehicles",
            "subcategory":"Automobile Sales",
            "type":"Retail Goods"
        }
    ],
    "sg:phone":"+1 717 268 8575",
    "sg:postcode":"17370",
    "sg:province":"PA",
    "sg:tags":[
        "car",
        "dealer"
    ],
    "wof:name":"Busser's Auto Sales",
    "wof:placetype":"venue"
},
  "geometry": {"coordinates":[-76.768112,40.100906],"type":"Point"}
}