{
  "type": "Feature",
  "properties": {
    "addr:full":"2243 S 9th St Philadelphia PA 19148",
    "addr:housenumber":"2243",
    "addr:postcode":"19148",
    "addr:street":"S 9Th St",
    "iso:country":"US",
    "sg:address":"2243 S 9th St",
    "sg:city":"Philadelphia",
    "sg:classifiers":[
        {
            "category":"Health Services",
            "subcategory":"Doctor",
            "type":"Services"
        }
    ],
    "sg:phone":"+1   ",
    "sg:postcode":"19148",
    "sg:province":"PA",
    "sg:tags":[
        "medical"
    ],
    "wof:name":"Mary Rubin MD",
    "wof:placetype":"venue"
},
  "geometry": {"coordinates":[-75.161653,39.921376],"type":"Point"}
}