{
  "type": "Feature",
  "properties": {
    "iso:country":"US",
    "sg:address":"1000 Washington Rd",
    "sg:city":"Washington",
    "sg:classifiers":[
        {
            "category":"Farming",
            "subcategory":"Nursery",
            "type":"Manufacturing & Wholesale Goods"
        }
    ],
    "sg:phone":"+1 724 222 0100",
    "sg:postcode":"15301",
    "sg:province":"PA",
    "sg:tags":[
        "ornamental",
        "supply"
    ],
    "wof:name":"Sherwood Nursery & Greenhouse",
    "wof:placetype":"venue"
},
  "geometry": {"coordinates":[-80.207748,40.199368],"type":"Point"}
}