{
  "type": "Feature",
  "properties": {
    "iso:country":"US",
    "sg:address":"1114 Edison St",
    "sg:city":"Allentown",
    "sg:classifiers":[
        {
            "category":"Shopping",
            "subcategory":"Computers & Home Electronics",
            "type":"Retail Goods"
        }
    ],
    "sg:phone":"+1 610 437 1277",
    "sg:postcode":"18101",
    "sg:province":"PA",
    "sg:tags":[
        "equipment",
        "dealer"
    ],
    "wof:name":"Youth Computers",
    "wof:placetype":"venue"
},
  "geometry": {"coordinates":[-75.480862,40.600782],"type":"Point"}
}