{
  "type": "Feature",
  "properties": {
    "iso:country":"US",
    "sg:address":"1045 W Lancaster Ave",
    "sg:city":"Bryn Mawr",
    "sg:classifiers":[
        {
            "category":"Food & Beverages",
            "subcategory":"Groceries & Convenience Stores",
            "type":"Retail Goods"
        }
    ],
    "sg:phone":"+1 610 520 1051",
    "sg:postcode":"19010",
    "sg:province":"PA",
    "sg:tags":[
        "market"
    ],
    "wof:name":"Hua Ling Market",
    "wof:placetype":"venue"
},
  "geometry": {"coordinates":[-75.323947,40.024291],"type":"Point"}
}