{
  "type": "Feature",
  "properties": {
    "iso:country":"US",
    "sg:address":"2548 Freemansburg Ave",
    "sg:city":"Easton",
    "sg:classifiers":[
        {
            "category":"Personal",
            "subcategory":"Beauty Salon",
            "type":"Services"
        }
    ],
    "sg:phone":"+1 610 923 7999",
    "sg:postcode":"18045",
    "sg:province":"PA",
    "sg:tags":[
        "hair",
        "shop",
        "stylist"
    ],
    "wof:name":"Shear Designs Hair Salon",
    "wof:placetype":"venue"
},
  "geometry": {"coordinates":[-75.246747,40.674753],"type":"Point"}
}