{
  "type": "Feature",
  "properties": {
    "addr:full":"1700 Bigler St Philadelphia PA 19145",
    "addr:housenumber":"1700",
    "addr:postcode":"19145",
    "addr:street":"Bigler St",
    "iso:country":"US",
    "sg:address":"1700 Bigler St",
    "sg:city":"Philadelphia",
    "sg:classifiers":[
        {
            "category":"Education",
            "subcategory":"School",
            "type":"Public Place"
        }
    ],
    "sg:phone":"+1 215 952 6218",
    "sg:postcode":"19145",
    "sg:province":"PA",
    "sg:tags":[
        "high",
        "middle",
        "elementary"
    ],
    "sg:website":"www.phila.k12.pa.us",
    "wof:name":"Philadelphia City School District",
    "wof:placetype":"venue"
},
  "geometry": {"coordinates":[-75.17830499999999,39.914934],"type":"Point"}
}