{
  "type": "Feature",
  "properties": {
    "iso:country":"US",
    "sg:address":"301 Center St",
    "sg:city":"Baden",
    "sg:classifiers":[
        {
            "category":"Building & Trades",
            "subcategory":"Plumbing",
            "type":"Services"
        }
    ],
    "sg:phone":"+1 724 242 0113",
    "sg:postcode":"15005",
    "sg:province":"PA",
    "sg:tags":[
        "plumbing",
        "contractor"
    ],
    "wof:name":"Husky Plumbing",
    "wof:placetype":"venue"
},
  "geometry": {"coordinates":[-80.22626,40.628263],"type":"Point"}
}