{
  "type": "Feature",
  "properties": {
    "addr:full":"715 Durham Rd Riegelsville PA 18077",
    "addr:housenumber":"715",
    "addr:postcode":"18077",
    "addr:street":"Durham Rd",
    "iso:country":"US",
    "sg:address":"715 Durham Rd",
    "sg:city":"Riegelsville",
    "sg:classifiers":[
        {
            "category":"Food & Beverages",
            "subcategory":"Groceries & Convenience Stores",
            "type":"Retail Goods"
        }
    ],
    "sg:phone":"+1 610 749 2338",
    "sg:postcode":"18077",
    "sg:province":"PA",
    "sg:tags":[
        "grocer"
    ],
    "wof:name":"Joe's Market",
    "wof:placetype":"venue"
},
  "geometry": {"coordinates":[-75.22859200000001,40.594485],"type":"Point"}
}