{
  "type": "Feature",
  "properties": {
    "iso:country":"US",
    "sg:address":"1422 Holcomb Rd",
    "sg:city":"Huntingdon Vly",
    "sg:classifiers":[
        {
            "category":"Professional",
            "type":"Services"
        }
    ],
    "sg:phone":"+1 215 947 0387",
    "sg:postcode":"19006",
    "sg:province":"PA",
    "sg:tags":[
        "establishment"
    ],
    "wof:name":"Stoddard Thomas G Wi7 5716",
    "wof:placetype":"venue"
},
  "geometry": {"coordinates":[-75.09307200000001,40.125517],"type":"Point"}
}