{
  "type": "Feature",
  "properties": {
    "iso:country":"US",
    "sg:address":"90 Main St",
    "sg:city":"Bellwood",
    "sg:classifiers":[
        {
            "category":"Shopping",
            "subcategory":"Discount & Variety Stores",
            "type":"Retail Goods"
        }
    ],
    "sg:phone":"+1   ",
    "sg:postcode":"16617",
    "sg:province":"PA",
    "wof:name":"Dollar General",
    "wof:placetype":"venue"
},
  "geometry": {"coordinates":[-78.336247,40.595208],"type":"Point"}
}