{
  "type": "Feature",
  "properties": {
    "addr:full":"4879 State Rte 209 Elizabethville PA 17023",
    "addr:housenumber":"4879",
    "addr:postcode":"17023",
    "addr:street":"State Rte 209",
    "iso:country":"US",
    "sg:address":"4879 State Rte 209",
    "sg:city":"Elizabethville",
    "sg:classifiers":[
        {
            "category":"Shopping",
            "subcategory":"Music",
            "type":"Retail Goods"
        }
    ],
    "sg:phone":"+1 717 362 3222",
    "sg:postcode":"17023",
    "sg:province":"PA",
    "sg:tags":[
        "video",
        "disc",
        "tape",
        "cassette"
    ],
    "wof:name":"Mel's Movie Mania",
    "wof:placetype":"venue"
},
  "geometry": {"coordinates":[-76.789691,40.559185],"type":"Point"}
}