{
  "type": "Feature",
  "properties": {
    "iso:country":"US",
    "sg:address":"405 Allentown Dr Unit A",
    "sg:city":"Allentown",
    "sg:classifiers":[
        {
            "category":"Wholesale",
            "subcategory":"Machinery & Supplies",
            "type":"Manufacturing & Wholesale Goods"
        }
    ],
    "sg:phone":"+1 484 223 3265",
    "sg:postcode":"18109",
    "sg:province":"PA",
    "sg:tags":[
        "compressor"
    ],
    "wof:name":"U R I Compressors Inc",
    "wof:placetype":"venue"
},
  "geometry": {"coordinates":[-75.45893,40.626061],"type":"Point"}
}