{
  "type": "Feature",
  "properties": {
    "iso:country":"US",
    "sg:address":"281 Willow Dell Ln",
    "sg:city":"Leola",
    "sg:classifiers":[
        {
            "category":"Communications",
            "subcategory":"Film & Video Production",
            "type":"Services"
        }
    ],
    "sg:phone":"+1   ",
    "sg:postcode":"17540",
    "sg:province":"PA",
    "sg:tags":[
        "motion",
        "p",
        "distribution"
    ],
    "wof:name":"Railroad Video Productions",
    "wof:placetype":"venue"
},
  "geometry": {"coordinates":[-76.157836,40.09521],"type":"Point"}
}