{
  "type": "Feature",
  "properties": {
    "iso:country":"US",
    "sg:address":"12 N Franklin St",
    "sg:city":"Du Bois",
    "sg:classifiers":[
        {
            "category":"Autos & Motor Vehicles",
            "subcategory":"Auto Supplies",
            "type":"Retail Goods"
        }
    ],
    "sg:phone":"+1 814 371 1696",
    "sg:postcode":"15801",
    "sg:province":"PA",
    "sg:tags":[
        "alternator",
        "generator"
    ],
    "wof:name":"Charlie's Alternator & Starter",
    "wof:placetype":"venue"
},
  "geometry": {"coordinates":[-78.765378,41.121496],"type":"Point"}
}