{
  "type": "Feature",
  "properties": {
    "iso:country":"US",
    "sg:address":"132 Swinehart Rd",
    "sg:city":"Coatesville",
    "sg:classifiers":[
        {
            "category":"Autos & Motor Vehicles",
            "subcategory":"Automobile Sales",
            "type":"Retail Goods"
        }
    ],
    "sg:phone":"+1   ",
    "sg:postcode":"19320",
    "sg:province":"PA",
    "wof:name":"Hugh Redditt Company",
    "wof:placetype":"venue"
},
  "geometry": {"coordinates":[-75.79627000000001,40.030492],"type":"Point"}
}