{
  "type": "Feature",
  "properties": {
    "addr:full":"4089 Landisville Rd Doylestown PA 18902",
    "addr:housenumber":"4089",
    "addr:postcode":"18902",
    "addr:street":"Landisville Rd",
    "iso:country":"US",
    "sg:address":"4089 Landisville Rd",
    "sg:city":"Doylestown",
    "sg:classifiers":[
        {
            "category":"Manufacturing",
            "subcategory":"Paper Products",
            "type":"Manufacturing & Wholesale Goods"
        }
    ],
    "sg:phone":"+1 610 329 7177",
    "sg:postcode":"18902",
    "sg:province":"PA",
    "sg:tags":[
        "labels-wholesale",
        "manufacturer"
    ],
    "sg:website":"http://www.lemproductsinc.com",
    "wof:name":"Lem Products, Inc.",
    "wof:placetype":"venue"
},
  "geometry": {"coordinates":[-75.120958,40.340733],"type":"Point"}
}