{
  "type": "Feature",
  "properties": {
    "addr:full":"4517 Butler St Pittsburgh PA 15201",
    "addr:housenumber":"4517",
    "addr:postcode":"15201",
    "addr:street":"Butler St",
    "iso:country":"US",
    "sg:address":"4517 Butler St",
    "sg:city":"Pittsburgh",
    "sg:classifiers":[
        {
            "category":"Bars & Pubs",
            "type":"Food & Drink"
        }
    ],
    "sg:phone":"+1 412 683 3039",
    "sg:postcode":"15201",
    "sg:province":"PA",
    "sg:tags":[
        "drinking"
    ],
    "wof:name":"Salac's Inc",
    "wof:placetype":"venue"
},
  "geometry": {"coordinates":[-79.958932,40.472743],"type":"Point"}
}