{
  "type": "Feature",
  "properties": {
    "addr:full":"331 Folkstone Way York PA 17402",
    "addr:housenumber":"331",
    "addr:postcode":"17402",
    "addr:street":"Folkstone Way",
    "iso:country":"US",
    "sg:address":"331 Folkstone Way",
    "sg:city":"York",
    "sg:classifiers":[
        {
            "category":"Wholesale",
            "subcategory":"Machinery & Supplies",
            "type":"Manufacturing & Wholesale Goods"
        }
    ],
    "sg:phone":"+1   ",
    "sg:postcode":"17402",
    "sg:province":"PA",
    "sg:tags":[
        "equipment",
        "industrial"
    ],
    "wof:name":"Robert Naglieri",
    "wof:placetype":"venue"
},
  "geometry": {"coordinates":[-76.658648,39.97222],"type":"Point"}
}