{
  "type": "Feature",
  "properties": {
    "addr:full":"235 Springville Rd Kinzers PA 17535",
    "addr:housenumber":"235",
    "addr:postcode":"17535",
    "addr:street":"Springville Rd",
    "iso:country":"US",
    "sg:address":"235 Springville Rd",
    "sg:city":"Kinzers",
    "sg:classifiers":[
        {
            "category":"Home & Garden",
            "subcategory":"Home Furnishings",
            "type":"Retail Goods"
        }
    ],
    "sg:phone":"+1   ",
    "sg:postcode":"17535",
    "sg:province":"PA",
    "sg:tags":[
        "miscellaneous",
        "store"
    ],
    "wof:name":"Miriam King",
    "wof:placetype":"venue"
},
  "geometry": {"coordinates":[-76.019577,40.056279],"type":"Point"}
}