{
  "type": "Feature",
  "properties": {
    "iso:country":"US",
    "sg:address":"660 Hollow Rd",
    "sg:city":"Phoenixville",
    "sg:classifiers":[
        {
            "category":"Wholesale",
            "subcategory":"Vending Machines",
            "type":"Manufacturing & Wholesale Goods"
        }
    ],
    "sg:phone":"+1   ",
    "sg:postcode":"19460",
    "sg:province":"PA",
    "sg:tags":[
        "coffee",
        "provides"
    ],
    "wof:name":"Hershey Automatic Coffee Now",
    "wof:placetype":"venue"
},
  "geometry": {"coordinates":[-75.49100900000001,40.136868],"type":"Point"}
}