{
  "type": "Feature",
  "properties": {
    "iso:country":"US",
    "sg:address":"5111 Doyle Rd",
    "sg:city":"Pittsburgh",
    "sg:classifiers":[
        {
            "category":"Shopping",
            "subcategory":"Hobbies, Toys, & Games",
            "type":"Retail Goods"
        },
        {
            "category":"Shopping",
            "subcategory":"Gifts & Souvenirs",
            "type":"Retail Goods"
        }
    ],
    "sg:phone":"+1 412 884 7930",
    "sg:postcode":"15227",
    "sg:province":"PA",
    "sg:tags":[
        "equipment",
        "ceramic",
        "supply"
    ],
    "wof:name":"Ruthie's Ceramics",
    "wof:placetype":"venue"
},
  "geometry": {"coordinates":[-79.964963,40.352355],"type":"Point"}
}