{
  "type": "Feature",
  "properties": {
    "iso:country":"US",
    "sg:address":"822 Franklin Church Rd",
    "sg:city":"Dillsburg",
    "sg:classifiers":[
        {
            "category":"Farming",
            "subcategory":"Dairy Farm",
            "type":"Manufacturing & Wholesale Goods"
        }
    ],
    "sg:phone":"+1   ",
    "sg:postcode":"17019",
    "sg:province":"PA",
    "wof:name":"Gerald Kraybill",
    "wof:placetype":"venue"
},
  "geometry": {"coordinates":[-77.044068,40.029731],"type":"Point"}
}