{
  "type": "Feature",
  "properties": {
    "addr:full":"151 Memorial Hwy Dallas PA 18612",
    "addr:housenumber":"151",
    "addr:postcode":"18612",
    "addr:street":"Memorial Hwy",
    "iso:country":"US",
    "sg:address":"151 Memorial Hwy",
    "sg:city":"Dallas",
    "sg:classifiers":[
        {
            "category":"Autos & Motor Vehicles",
            "subcategory":"Fuel & Gas Station",
            "type":"Retail Goods"
        }
    ],
    "sg:phone":"+1   ",
    "sg:postcode":"18612",
    "sg:province":"PA",
    "sg:tags":[
        "station",
        "gasoline"
    ],
    "wof:name":"Hess",
    "wof:placetype":"venue"
},
  "geometry": {"coordinates":[-75.94677,41.327622],"type":"Point"}
}