{
  "type": "Feature",
  "properties": {
    "iso:country":"US",
    "sg:address":"239 Edgewood Dr Exd",
    "sg:city":"Transfer",
    "sg:classifiers":[
        {
            "category":"Health Services",
            "subcategory":"Doctor",
            "type":"Services"
        }
    ],
    "sg:phone":"+1 724 646 0618",
    "sg:postcode":"16154",
    "sg:province":"PA",
    "sg:tags":[
        "physician",
        "surgeon"
    ],
    "wof:name":"Edgewood Surgical",
    "wof:placetype":"venue"
},
  "geometry": {"coordinates":[-80.416307,41.33017],"type":"Point"}
}