{
  "type": "Feature",
  "properties": {
    "iso:country":"US",
    "sg:address":"8 E Woodland Ave",
    "sg:city":"Springfield",
    "sg:classifiers":[
        {
            "category":"Personal",
            "subcategory":"Beauty Salon",
            "type":"Services"
        }
    ],
    "sg:phone":"+1 610 544 0456",
    "sg:postcode":"19064",
    "sg:province":"PA",
    "sg:tags":[
        "shop"
    ],
    "wof:name":"Scissorhands",
    "wof:placetype":"venue"
},
  "geometry": {"coordinates":[-75.33945900000001,39.924167],"type":"Point"}
}