{
  "type": "Feature",
  "properties": {
    "addr:full":"1570 E Erie Ave Philadelphia PA 19124",
    "addr:housenumber":"1570",
    "addr:postcode":"19124",
    "addr:street":"E Erie Ave",
    "iso:country":"US",
    "sg:address":"1570 E Erie Ave",
    "sg:city":"Philadelphia",
    "sg:phone":"+1 215 831 1660",
    "sg:postcode":"19124",
    "sg:province":"PA",
    "wof:name":"Best Buy In Town Inc.",
    "wof:placetype":"venue"
},
  "geometry": {"coordinates":[-75.097448,40.005826],"type":"Point"}
}