{
  "type": "Feature",
  "properties": {
    "iso:country":"US",
    "sg:address":"16 Meadow Ln",
    "sg:city":"Lancaster",
    "sg:classifiers":[
        {
            "category":"Government",
            "subcategory":"Post Office",
            "type":"Public Place"
        }
    ],
    "sg:phone":"+1 800 275 8777",
    "sg:postcode":"17601",
    "sg:province":"PA",
    "sg:website":"http://www.usps.com",
    "wof:name":"USPS - United States Post Office - Neffsville Branch",
    "wof:placetype":"venue"
},
  "geometry": {"coordinates":[-76.30391899999999,40.093843],"type":"Point"}
}