{
  "type": "Feature",
  "properties": {
    "iso:country":"US",
    "sg:address":"1105 Washington Blvd",
    "sg:city":"Pittsburgh",
    "sg:classifiers":[
        {
            "category":"Building & Trades",
            "subcategory":"Construction",
            "type":"Services"
        }
    ],
    "sg:phone":"+1   ",
    "sg:postcode":"15206",
    "sg:province":"PA",
    "sg:tags":[
        "swimming",
        "pool",
        "contractor"
    ],
    "wof:name":"B & R Pool & Swim Shop",
    "wof:placetype":"venue"
},
  "geometry": {"coordinates":[-79.90702,40.464564],"type":"Point"}
}