{
  "type": "Feature",
  "properties": {
    "iso:country":"US",
    "sg:address":"65 E Main St",
    "sg:city":"Quentin",
    "sg:classifiers":[
        {
            "category":"Professional",
            "subcategory":"Management & Consulting",
            "type":"Services"
        }
    ],
    "sg:phone":"+1 717 270 4500",
    "sg:postcode":"17042",
    "sg:province":"PA",
    "sg:tags":[
        "consultant",
        "business",
        "legal"
    ],
    "wof:name":"The Liberty Consulting Group",
    "wof:placetype":"venue"
},
  "geometry": {"coordinates":[-76.439542,40.279499],"type":"Point"}
}