{
  "type": "Feature",
  "properties": {
    "iso:country":"US",
    "sg:address":"3375 High Point Blvd.",
    "sg:city":"Bethlehem",
    "sg:classifiers":[
        {
            "category":"Travel",
            "subcategory":"Hotels & Motels",
            "type":"Entertainment"
        },
        {
            "category":"Retail",
            "subcategory":"Event Space",
            "type":"Services"
        }
    ],
    "sg:phone":"+1 610 882 2255",
    "sg:postcode":"18017",
    "sg:province":"PA",
    "sg:tags":[
        "venue"
    ],
    "sg:website":"www.holidayinnexpress.com",
    "wof:name":"Holiday Inn Express Hotel & Suites Lehigh Valley Airport",
    "wof:placetype":"venue"
},
  "geometry": {"coordinates":[-75.4164,40.6566],"type":"Point"}
}