{
  "type": "Feature",
  "properties": {
    "addr:full":"2131 Perrysville Ave Pittsburgh PA 15214",
    "addr:housenumber":"2131",
    "addr:postcode":"15214",
    "addr:street":"Perrysville Ave",
    "iso:country":"US",
    "sg:address":"2131 Perrysville Ave",
    "sg:city":"Pittsburgh",
    "sg:classifiers":[
        {
            "category":"Social Services",
            "type":"Services"
        }
    ],
    "sg:phone":"+1 412 321 5338",
    "sg:postcode":"15214",
    "sg:province":"PA",
    "sg:tags":[
        "organization",
        "welfare"
    ],
    "wof:name":"Phase",
    "wof:placetype":"venue"
},
  "geometry": {"coordinates":[-80.01156899999999,40.464796],"type":"Point"}
}