{
  "type": "Feature",
  "properties": {
    "iso:country":"US",
    "sg:address":"276 Murphy Rd",
    "sg:city":"Ebensburg",
    "sg:classifiers":[
        {
            "category":"Building & Trades",
            "subcategory":"Plumbing",
            "type":"Services"
        }
    ],
    "sg:phone":"+1 814 472 5767",
    "sg:postcode":"15931",
    "sg:province":"PA",
    "sg:tags":[
        "heating",
        "contractor"
    ],
    "wof:name":"Mc Kim Heating Air Cond",
    "wof:placetype":"venue"
},
  "geometry": {"coordinates":[-78.687861,40.471579],"type":"Point"}
}