{
  "type": "Feature",
  "properties": {
    "addr:full":"9 Jonathan Morris Cir Media PA 19063",
    "addr:housenumber":"9",
    "addr:postcode":"19063",
    "addr:street":"Jonathan Morris Cir",
    "iso:country":"US",
    "sg:address":"9 Jonathan Morris Cir",
    "sg:city":"Media",
    "sg:classifiers":[
        {
            "category":"Shopping",
            "subcategory":"Pharmacy",
            "type":"Retail Goods"
        }
    ],
    "sg:phone":"+1   ",
    "sg:postcode":"19063",
    "sg:province":"PA",
    "sg:tags":[
        "center",
        "drug"
    ],
    "wof:name":"Brookhaven Drug Center Inc",
    "wof:placetype":"venue"
},
  "geometry": {"coordinates":[-75.388868,39.960643],"type":"Point"}
}