{
  "type": "Feature",
  "properties": {
    "iso:country":"US",
    "sg:address":"255 Park Ave",
    "sg:city":"Mount Joy",
    "sg:classifiers":[
        {
            "category":"Autos & Motor Vehicles",
            "subcategory":"Automobile Sales",
            "type":"Retail Goods"
        }
    ],
    "sg:phone":"+1   ",
    "sg:postcode":"17552",
    "sg:province":"PA",
    "sg:tags":[
        "used"
    ],
    "wof:name":"Mid Atlantic Auto Inc",
    "wof:placetype":"venue"
},
  "geometry": {"coordinates":[-76.49412100000001,40.110877],"type":"Point"}
}