{
  "type": "Feature",
  "properties": {
    "iso:country":"US",
    "sg:address":"8 Village Way",
    "sg:city":"Malvern",
    "sg:classifiers":[
        {
            "category":"Building & Trades",
            "subcategory":"Construction",
            "type":"Services"
        }
    ],
    "sg:phone":"+1   ",
    "sg:postcode":"19355",
    "sg:province":"PA",
    "sg:tags":[
        "contractor"
    ],
    "wof:name":"Lomas Contractors Inc",
    "wof:placetype":"venue"
},
  "geometry": {"coordinates":[-75.529764,40.041282],"type":"Point"}
}