{
  "type": "Feature",
  "properties": {
    "iso:country":"US",
    "sg:address":"310 Limestone Rd",
    "sg:city":"Oxford",
    "sg:classifiers":[
        {
            "category":"Retail",
            "subcategory":"Photofinishing",
            "type":"Services"
        }
    ],
    "sg:phone":"+1   ",
    "sg:postcode":"19363",
    "sg:province":"PA",
    "sg:tags":[
        "laboratory"
    ],
    "wof:name":"Pennsylvnia Dept Trnsprotation",
    "wof:placetype":"venue"
},
  "geometry": {"coordinates":[-75.974153,39.797609],"type":"Point"}
}