{
  "type": "Feature",
  "properties": {
    "addr:full":"3310 Chichester Ave Marcus Hook PA 19061",
    "addr:housenumber":"3310",
    "addr:postcode":"19061",
    "addr:street":"Chichester Ave",
    "iso:country":"US",
    "sg:address":"3310 Chichester Ave",
    "sg:city":"Marcus Hook",
    "sg:classifiers":[
        {
            "category":"Restaurant",
            "type":"Food & Drink"
        }
    ],
    "sg:phone":"+1   ",
    "sg:postcode":"19061",
    "sg:province":"PA",
    "sg:tags":[
        "eating"
    ],
    "wof:name":"Pizza Hut",
    "wof:placetype":"venue"
},
  "geometry": {"coordinates":[-75.442723,39.838944],"type":"Point"}
}