{
  "type": "Feature",
  "properties": {
    "iso:country":"US",
    "sg:address":"206 S 13th St",
    "sg:city":"Philadelphia",
    "sg:classifiers":[
        {
            "category":"Shopping",
            "subcategory":"Music",
            "type":"Retail Goods"
        }
    ],
    "sg:phone":"+1   ",
    "sg:postcode":"19107",
    "sg:province":"PA",
    "wof:name":"Chancellor Records Inc",
    "wof:placetype":"venue"
},
  "geometry": {"coordinates":[-75.16223599999999,39.948504],"type":"Point"}
}