{
  "type": "Feature",
  "properties": {
    "iso:country":"US",
    "sg:address":"1147 S 10th St",
    "sg:city":"Philadelphia",
    "sg:classifiers":[
        {
            "category":"Wholesale",
            "subcategory":"Computers",
            "type":"Manufacturing & Wholesale Goods"
        }
    ],
    "sg:phone":"+1   ",
    "sg:postcode":"19147",
    "sg:province":"PA",
    "wof:name":"Talisma Corp",
    "wof:placetype":"venue"
},
  "geometry": {"coordinates":[-75.160231,39.935104],"type":"Point"}
}