{
  "type": "Feature",
  "properties": {
    "addr:full":"154 Janet St Johnstown PA 15905",
    "addr:housenumber":"154",
    "addr:postcode":"15905",
    "addr:street":"Janet St",
    "iso:country":"US",
    "sg:address":"154 Janet St",
    "sg:city":"Johnstown",
    "sg:classifiers":[
        {
            "category":"Building & Trades",
            "subcategory":"Construction",
            "type":"Services"
        }
    ],
    "sg:phone":"+1   ",
    "sg:postcode":"15905",
    "sg:province":"PA",
    "sg:tags":[
        "excavation",
        "contractor"
    ],
    "wof:name":"Garman Excavating",
    "wof:placetype":"venue"
},
  "geometry": {"coordinates":[-78.921561,40.27354],"type":"Point"}
}