{
  "type": "Feature",
  "properties": {
    "addr:full":"517 New Castle Ave Sharon PA 16146",
    "addr:housenumber":"517",
    "addr:postcode":"16146",
    "addr:street":"New Castle Ave",
    "iso:country":"US",
    "sg:address":"517 New Castle Ave",
    "sg:city":"Sharon",
    "sg:classifiers":[
        {
            "category":"Professional",
            "type":"Services"
        }
    ],
    "sg:phone":"+1   ",
    "sg:postcode":"16146",
    "sg:province":"PA",
    "wof:name":"Ike Jones",
    "wof:placetype":"venue"
},
  "geometry": {"coordinates":[-80.50054799999999,41.225598],"type":"Point"}
}