{
  "type": "Feature",
  "properties": {
    "addr:full":"1055 Baltimore St Hanover PA 17331",
    "addr:housenumber":"1055",
    "addr:postcode":"17331",
    "addr:street":"Baltimore St",
    "iso:country":"US",
    "sg:address":"1055 Baltimore St",
    "sg:city":"Hanover",
    "sg:classifiers":[
        {
            "category":"Banks & Credit Unions",
            "subcategory":"Bank",
            "type":"Services"
        }
    ],
    "sg:phone":"+1   ",
    "sg:postcode":"17331",
    "sg:province":"PA",
    "sg:tags":[
        "state",
        "commercial"
    ],
    "wof:name":"M&T",
    "wof:placetype":"venue"
},
  "geometry": {"coordinates":[-76.96262,39.780045],"type":"Point"}
}