{
  "type": "Feature",
  "properties": {
    "addr:full":"502 Main St Archbald PA 18403",
    "addr:housenumber":"502",
    "addr:postcode":"18403",
    "addr:street":"Main St",
    "iso:country":"US",
    "sg:address":"502 Main St",
    "sg:city":"Archbald",
    "sg:classifiers":[
        {
            "category":"School Buses",
            "type":"Transportation"
        }
    ],
    "sg:phone":"+1   ",
    "sg:postcode":"18403",
    "sg:province":"PA",
    "wof:name":"Stafursky Transportation Inc",
    "wof:placetype":"venue"
},
  "geometry": {"coordinates":[-75.5428,41.495113],"type":"Point"}
}