{
  "type": "Feature",
  "properties": {
    "iso:country":"US",
    "sg:address":"213 Weldy Ave",
    "sg:city":"Oreland",
    "sg:classifiers":[
        {
            "category":"Travel",
            "subcategory":"Travel Agent",
            "type":"Entertainment"
        }
    ],
    "sg:phone":"+1   ",
    "sg:postcode":"19075",
    "sg:province":"PA",
    "sg:tags":[
        "agency"
    ],
    "wof:name":"Horsham Travel Inc",
    "wof:placetype":"venue"
},
  "geometry": {"coordinates":[-75.17948199999999,40.121526],"type":"Point"}
}