{
  "type": "Feature",
  "properties": {
    "iso:country":"US",
    "sg:address":"910 Blair St",
    "sg:city":"Hollidaysburg",
    "sg:classifiers":[
        {
            "category":"Personal",
            "subcategory":"Barber",
            "type":"Services"
        }
    ],
    "sg:phone":"+1 814 696 3388",
    "sg:postcode":"16648",
    "sg:province":"PA",
    "sg:tags":[
        "shop",
        "beauty"
    ],
    "wof:name":"Styles In Motion",
    "wof:placetype":"venue"
},
  "geometry": {"coordinates":[-78.38508,40.429253],"type":"Point"}
}