{
  "type": "Feature",
  "properties": {
    "iso:country":"US",
    "sg:address":"45 E Orange St",
    "sg:city":"Lancaster",
    "sg:classifiers":[
        {
            "category":"Professional",
            "subcategory":"Lawyer & Legal Services",
            "type":"Services"
        }
    ],
    "sg:phone":"+1 717 291 1819",
    "sg:postcode":"17602",
    "sg:province":"PA",
    "sg:tags":[
        "attorney"
    ],
    "wof:name":"Michael J Rostolsky Law Ofc",
    "wof:placetype":"venue"
},
  "geometry": {"coordinates":[-76.30418299999999,40.039798],"type":"Point"}
}