{
  "type": "Feature",
  "properties": {
    "addr:full":"691 Division St Du Bois PA 15801",
    "addr:housenumber":"691",
    "addr:postcode":"15801",
    "addr:street":"Division St Du Bois",
    "iso:country":"US",
    "sg:address":"691 Division St",
    "sg:city":"Du Bois",
    "sg:classifiers":[
        {
            "category":"Wholesale",
            "subcategory":"Office Equipment",
            "type":"Manufacturing & Wholesale Goods"
        }
    ],
    "sg:phone":"+1 814 371 3200",
    "sg:postcode":"15801",
    "sg:province":"PA",
    "sg:tags":[
        "machine",
        "duplicating",
        "copying"
    ],
    "wof:name":"Way Copy Solutions Inc",
    "wof:placetype":"venue"
},
  "geometry": {"coordinates":[-78.74782500000001,41.125505],"type":"Point"}
}