{
  "type": "Feature",
  "properties": {
    "iso:country":"US",
    "sg:address":"9526 State Rte 198",
    "sg:city":"Guys Mills",
    "sg:classifiers":[
        {
            "category":"Manufacturing",
            "subcategory":"Building Materials",
            "type":"Manufacturing & Wholesale Goods"
        }
    ],
    "sg:phone":"+1   ",
    "sg:postcode":"16327",
    "sg:province":"PA",
    "sg:tags":[
        "mill",
        "work",
        "mfg"
    ],
    "wof:name":"Heritage Millwork",
    "wof:placetype":"venue"
},
  "geometry": {"coordinates":[-79.938697,41.595384],"type":"Point"}
}