{
  "type": "Feature",
  "properties": {
    "iso:country":"US",
    "sg:address":"2447 S 6th St",
    "sg:city":"Allentown",
    "sg:classifiers":[
        {
            "category":"Building & Trades",
            "subcategory":"Construction",
            "type":"Services"
        }
    ],
    "sg:phone":"+1 610 797 3654",
    "sg:postcode":"18103",
    "sg:province":"PA",
    "sg:tags":[
        "repairing",
        "lane",
        "refinishing",
        "bowling"
    ],
    "wof:name":"Ronald Kaintz",
    "wof:placetype":"venue"
},
  "geometry": {"coordinates":[-75.457838,40.574073],"type":"Point"}
}