{
  "type": "Feature",
  "properties": {
    "iso:country":"US",
    "sg:address":"429 W Rittenhouse St",
    "sg:city":"Philadelphia",
    "sg:classifiers":[
        {
            "category":"Education",
            "subcategory":"School",
            "type":"Public Place"
        }
    ],
    "sg:phone":"+1 215 844 2200",
    "sg:postcode":"19144",
    "sg:province":"PA",
    "wof:name":"Carson Valley School",
    "wof:placetype":"venue"
},
  "geometry": {"coordinates":[-75.181836,40.032695],"type":"Point"}
}