{
  "type": "Feature",
  "properties": {
    "iso:country":"US",
    "sg:address":"2299 Route 115 # 115",
    "sg:city":"Effort",
    "sg:phone":"+1 570 620 9500",
    "sg:postcode":"18330",
    "sg:province":"PA",
    "sg:website":"http://www.hellersgas.com",
    "wof:name":"Heller's Gas",
    "wof:placetype":"venue"
},
  "geometry": {"coordinates":[-75.453715,40.988781],"type":"Point"}
}