{
  "type": "Feature",
  "properties": {
    "iso:country":"US",
    "sg:address":"1524 W Master St",
    "sg:city":"Philadelphia",
    "sg:classifiers":[
        {
            "category":"Organizations",
            "subcategory":"Religious Organization",
            "type":"Services"
        }
    ],
    "sg:phone":"+1   ",
    "sg:postcode":"19121",
    "sg:province":"PA",
    "wof:name":"Shiloh Apostolic Temple",
    "wof:placetype":"venue"
},
  "geometry": {"coordinates":[-75.161951,39.974811],"type":"Point"}
}