{
  "type": "Feature",
  "properties": {
    "iso:country":"US",
    "sg:address":"2607 Nicholson Rd",
    "sg:city":"Sewickley",
    "sg:classifiers":[
        {
            "category":"Insurance",
            "subcategory":"Insurance Agent",
            "type":"Services"
        }
    ],
    "sg:phone":"+1   ",
    "sg:postcode":"15143",
    "sg:province":"PA",
    "wof:name":"Harte Hawke Zupsic Insurance",
    "wof:placetype":"venue"
},
  "geometry": {"coordinates":[-80.099925,40.611839],"type":"Point"}
}