{
  "type": "Feature",
  "properties": {
    "addr:full":"1249 Pittsburgh Rd Uniontown PA 15401",
    "addr:housenumber":"1249",
    "addr:postcode":"15401",
    "addr:street":"Pittsburgh Rd",
    "iso:country":"US",
    "sg:address":"1249 Pittsburgh Rd",
    "sg:city":"Uniontown",
    "sg:classifiers":[
        {
            "category":"Restaurant",
            "type":"Food & Drink"
        }
    ],
    "sg:phone":"+1 724 438 6550",
    "sg:postcode":"15401",
    "sg:province":"PA",
    "wof:name":"Shining Stone Lounge",
    "wof:placetype":"venue"
},
  "geometry": {"coordinates":[-79.73429899999999,39.948101],"type":"Point"}
}