{
  "type": "Feature",
  "properties": {
    "iso:country":"US",
    "sg:address":"1685 Sumneytown Pike",
    "sg:city":"Kulpsville",
    "sg:classifiers":[
        {
            "category":"Manufacturing",
            "subcategory":"Tools & Machinery",
            "type":"Manufacturing & Wholesale Goods"
        }
    ],
    "sg:phone":"+1   ",
    "sg:postcode":"19438",
    "sg:province":"PA",
    "sg:tags":[
        "compressor",
        "mfg"
    ],
    "wof:name":"Mobil",
    "wof:placetype":"venue"
},
  "geometry": {"coordinates":[-75.43316,40.312203],"type":"Point"}
}