{
  "type": "Feature",
  "properties": {
    "iso:country":"US",
    "sg:address":"440 W Main St",
    "sg:city":"Monongahela",
    "sg:classifiers":[
        {
            "category":"Health Services",
            "subcategory":"Doctor",
            "type":"Services"
        }
    ],
    "sg:phone":"+1 724 258 2711",
    "sg:postcode":"15063",
    "sg:province":"PA",
    "sg:tags":[
        "podiatrist"
    ],
    "wof:name":"Kelly Jon A DPM",
    "wof:placetype":"venue"
},
  "geometry": {"coordinates":[-79.927002,40.203499],"type":"Point"}
}