{
  "type": "Feature",
  "properties": {
    "iso:country":"US",
    "sg:address":"76 Doe Run Rd",
    "sg:city":"Manheim",
    "sg:classifiers":[
        {
            "category":"Health Services",
            "subcategory":"Doctor",
            "type":"Services"
        }
    ],
    "sg:phone":"+1   ",
    "sg:postcode":"17545",
    "sg:province":"PA",
    "sg:tags":[
        "medicine",
        "osteopathic",
        "family"
    ],
    "wof:name":"Lovell Kenneth F Do",
    "wof:placetype":"venue"
},
  "geometry": {"coordinates":[-76.385306,40.169671],"type":"Point"}
}