{
  "type": "Feature",
  "properties": {
    "iso:country":"US",
    "sg:address":"3151 Conway Wallrose Rd",
    "sg:city":"Baden",
    "sg:classifiers":[
        {
            "category":"Education",
            "subcategory":"School",
            "type":"Public Place"
        }
    ],
    "sg:phone":"+1 724 266 1922",
    "sg:postcode":"15005",
    "sg:province":"PA",
    "sg:tags":[
        "high",
        "middle",
        "elementary"
    ],
    "wof:name":"North Hills Christian School",
    "wof:placetype":"venue"
},
  "geometry": {"coordinates":[-80.16480300000001,40.640999],"type":"Point"}
}