{
  "type": "Feature",
  "properties": {
    "iso:country":"US",
    "sg:address":"1016 N Providence Rd",
    "sg:city":"Media",
    "sg:classifiers":[
        {
            "category":"Building & Trades",
            "subcategory":"Plumbing",
            "type":"Services"
        }
    ],
    "sg:phone":"+1 610 565 0633",
    "sg:postcode":"19063",
    "sg:province":"PA",
    "sg:tags":[
        "product",
        "management",
        "energy",
        "system"
    ],
    "wof:name":"Provident Energy Consltng LLC",
    "wof:placetype":"venue"
},
  "geometry": {"coordinates":[-75.388513,39.931554],"type":"Point"}
}