{
  "type": "Feature",
  "properties": {
    "addr:full":"8350 Frankstown Ave Pittsburgh PA 15221",
    "addr:housenumber":"8350",
    "addr:postcode":"15221",
    "addr:street":"Frankstown Ave",
    "iso:country":"US",
    "sg:address":"8350 Frankstown Ave",
    "sg:city":"Pittsburgh",
    "sg:classifiers":[
        {
            "category":"Social Services",
            "type":"Services"
        },
        {
            "category":"Social Services",
            "subcategory":"Child Care",
            "type":"Services"
        }
    ],
    "sg:phone":"+1 412 665 2300",
    "sg:postcode":"15221",
    "sg:province":"PA",
    "sg:tags":[
        "homes-children"
    ],
    "wof:name":"A Second Chance, Inc",
    "wof:placetype":"venue"
},
  "geometry": {"coordinates":[-79.878862,40.456075],"type":"Point"}
}