{
  "type": "Feature",
  "properties": {
    "addr:full":"208 Hadley Rd Greenville PA 16125",
    "addr:housenumber":"208",
    "addr:postcode":"16125",
    "addr:street":"Hadley Rd",
    "iso:country":"US",
    "sg:address":"208 Hadley Rd",
    "sg:city":"Greenville",
    "sg:classifiers":[
        {
            "category":"Insurance",
            "subcategory":"Insurance Agent",
            "type":"Services"
        }
    ],
    "sg:phone":"+1 724 588 2155",
    "sg:postcode":"16125",
    "sg:province":"PA",
    "wof:name":"State Farm Insurance",
    "wof:placetype":"venue"
},
  "geometry": {"coordinates":[-80.346735,41.415179],"type":"Point"}
}