{
  "type": "Feature",
  "properties": {
    "addr:full":"14945 Rte 322 Clarion PA 16214",
    "addr:housenumber":"14945",
    "addr:postcode":"16214",
    "addr:street":"Rte 322",
    "iso:country":"US",
    "sg:address":"14945 Rte 322",
    "sg:city":"Clarion",
    "sg:classifiers":[
        {
            "category":"Home & Garden",
            "subcategory":"Garden Supply",
            "type":"Retail Goods"
        }
    ],
    "sg:phone":"+1   ",
    "sg:postcode":"16214",
    "sg:province":"PA",
    "sg:tags":[
        "hardware"
    ],
    "wof:name":"Keys Equipment",
    "wof:placetype":"venue"
},
  "geometry": {"coordinates":[-79.360381,41.20541],"type":"Point"}
}