{
  "type": "Feature",
  "properties": {
    "iso:country":"US",
    "sg:address":"155 Barnsley Rd",
    "sg:city":"Oxford",
    "sg:classifiers":[
        {
            "category":"Manufacturing",
            "subcategory":"Tools & Machinery",
            "type":"Manufacturing & Wholesale Goods"
        }
    ],
    "sg:phone":"+1   ",
    "sg:postcode":"19363",
    "sg:province":"PA",
    "sg:tags":[
        "converter",
        "mfg",
        "transmission",
        "torque",
        "parts",
        "automatic"
    ],
    "wof:name":"Ger Sales",
    "wof:placetype":"venue"
},
  "geometry": {"coordinates":[-75.98765400000001,39.768978],"type":"Point"}
}