{
  "type": "Feature",
  "properties": {
    "addr:full":"180 E Mountain Rd Hegins PA 17938",
    "addr:housenumber":"180",
    "addr:postcode":"17938",
    "addr:street":"E Mountain Rd",
    "iso:country":"US",
    "sg:address":"180 E Mountain Rd",
    "sg:city":"Hegins",
    "sg:classifiers":[
        {
            "category":"Organizations",
            "subcategory":"Religious Organization",
            "type":"Services"
        }
    ],
    "sg:phone":"+1 570 644 2079",
    "sg:postcode":"17938",
    "sg:province":"PA",
    "sg:tags":[
        "church"
    ],
    "wof:name":"Hegins Valley Mennonite Church",
    "wof:placetype":"venue"
},
  "geometry": {"coordinates":[-76.50367900000001,40.658223],"type":"Point"}
}