{
  "type": "Feature",
  "properties": {
    "iso:country":"US",
    "sg:address":"311 Delaware Ave",
    "sg:city":"Lansdale",
    "sg:classifiers":[
        {
            "category":"Retail",
            "subcategory":"Repair Shop",
            "type":"Services"
        }
    ],
    "sg:phone":"+1 215 362 5749",
    "sg:postcode":"19446",
    "sg:province":"PA",
    "sg:tags":[
        "lock",
        "key",
        "locksmith"
    ],
    "wof:name":"Craig Michael Locksmith",
    "wof:placetype":"venue"
},
  "geometry": {"coordinates":[-75.291702,40.2393],"type":"Point"}
}