{
  "type": "Feature",
  "properties": {
    "addr:full":"125 6th St Monessen PA 15062",
    "addr:housenumber":"125",
    "addr:postcode":"15062",
    "addr:street":"6Th St",
    "iso:country":"US",
    "sg:address":"125 6th St",
    "sg:city":"Monessen",
    "sg:classifiers":[
        {
            "category":"Professional",
            "subcategory":"Lawyer & Legal Services",
            "type":"Services"
        }
    ],
    "sg:phone":"+1 717 541 5451",
    "sg:postcode":"15062",
    "sg:province":"PA",
    "sg:tags":[
        "attorney"
    ],
    "wof:name":"Daniel Myshin",
    "wof:placetype":"venue"
},
  "geometry": {"coordinates":[-79.88767900000001,40.161503],"type":"Point"}
}