{
  "type": "Feature",
  "properties": {
    "iso:country":"US",
    "sg:address":"15002 Endicott St ",
    "sg:city":"Philadelphia",
    "sg:classifiers":[
        {
            "category":"Restaurant",
            "type":"Food & Drink"
        }
    ],
    "sg:menulink":"http://www.allmenus.com/pa/philadelphia/290093-pizza-works/menu/",
    "sg:phone":"+1 215 676 5555",
    "sg:postcode":"19116",
    "sg:province":"PA",
    "sg:tags":[
        "american",
        "pizza"
    ],
    "wof:name":"Pizza Works",
    "wof:placetype":"venue"
},
  "geometry": {"coordinates":[-74.99512799999999,40.12021],"type":"Point"}
}