{
  "type": "Feature",
  "properties": {
    "addr:full":"425 13th St Franklin PA 16323",
    "addr:housenumber":"425",
    "addr:postcode":"16323",
    "addr:street":"13Th St",
    "iso:country":"US",
    "sg:address":"425 13th St",
    "sg:city":"Franklin",
    "sg:classifiers":[
        {
            "category":"Government",
            "subcategory":"Office",
            "type":"Public Place"
        }
    ],
    "sg:phone":"+1   ",
    "sg:postcode":"16323",
    "sg:province":"PA",
    "sg:tags":[
        "legislative",
        "body"
    ],
    "wof:name":"Scott E Represnttive Htchinson",
    "wof:placetype":"venue"
},
  "geometry": {"coordinates":[-79.831429,41.397658],"type":"Point"}
}