{
  "type": "Feature",
  "properties": {
    "iso:country":"US",
    "sg:address":"127 S Main St",
    "sg:city":"Zelienople",
    "sg:classifiers":[
        {
            "category":"Home & Garden",
            "subcategory":"Building Materials",
            "type":"Retail Goods"
        }
    ],
    "sg:phone":"+1   ",
    "sg:postcode":"16063",
    "sg:province":"PA",
    "wof:name":"Youngs Kitchen Center Inc",
    "wof:placetype":"venue"
},
  "geometry": {"coordinates":[-80.13704199999999,40.79537],"type":"Point"}
}