{
  "type": "Feature",
  "properties": {
    "addr:full":"800 Town Center Doylestown PA 18901",
    "addr:housenumber":"800",
    "addr:postcode":"18901",
    "addr:street":"Town",
    "iso:country":"US",
    "sg:address":"800 Town Center",
    "sg:city":"Doylestown",
    "sg:classifiers":[
        {
            "category":"Restaurant",
            "type":"Food & Drink"
        }
    ],
    "sg:phone":"+1   ",
    "sg:postcode":"18901",
    "sg:province":"PA",
    "sg:tags":[
        "eating"
    ],
    "wof:name":"McDonalds",
    "wof:placetype":"venue"
},
  "geometry": {"coordinates":[-75.190254,40.298447],"type":"Point"}
}