{
  "type": "Feature",
  "properties": {
    "iso:country":"US",
    "sg:address":"302 S 4th St",
    "sg:city":"Emmaus",
    "sg:classifiers":[
        {
            "category":"Wholesale",
            "subcategory":"Groceries",
            "type":"Manufacturing & Wholesale Goods"
        }
    ],
    "sg:phone":"+1   ",
    "sg:postcode":"18049",
    "sg:province":"PA",
    "sg:tags":[
        "tea",
        "coffee",
        "spice"
    ],
    "wof:name":"Fasigs Sugar & Spice",
    "wof:placetype":"venue"
},
  "geometry": {"coordinates":[-75.488665,40.53046],"type":"Point"}
}