{
  "type": "Feature",
  "properties": {
    "iso:country":"US",
    "sg:address":"850 N Adams St",
    "sg:city":"Pottstown",
    "sg:classifiers":[
        {
            "category":"Recreation",
            "type":"Entertainment"
        }
    ],
    "sg:phone":"+1 610 323 4520",
    "sg:postcode":"19464",
    "sg:province":"PA",
    "sg:tags":[
        "course",
        "golf"
    ],
    "wof:name":"Brookside Country Club",
    "wof:placetype":"venue"
},
  "geometry": {"coordinates":[-75.629479,40.255073],"type":"Point"}
}