{
  "type": "Feature",
  "properties": {
    "addr:full":"13420 Damar Dr Ste T Philadelphia PA 19116",
    "addr:postcode":"13420;19116",
    "addr:street":"Damar Dr Ste T",
    "iso:country":"US",
    "sg:address":"13420 Damar Dr Ste T",
    "sg:city":"Philadelphia",
    "sg:classifiers":[
        {
            "category":"Home & Garden",
            "subcategory":"Building Materials",
            "type":"Retail Goods"
        },
        {
            "category":"Building & Trades",
            "subcategory":"Construction",
            "type":"Services"
        }
    ],
    "sg:phone":"+1 215 552 9921",
    "sg:postcode":"19116",
    "sg:province":"PA",
    "sg:tags":[
        "fence-sales",
        "fence",
        "contractor"
    ],
    "wof:name":"Apex Services",
    "wof:placetype":"venue"
},
  "geometry": {"coordinates":[-74.99951,40.121142],"type":"Point"}
}