{
  "type": "Feature",
  "properties": {
    "addr:full":"6505 Mars Rd Cranberry Township PA 16066",
    "addr:housenumber":"6505",
    "addr:postcode":"16066",
    "addr:street":"Mars Rd",
    "iso:country":"US",
    "sg:address":"6505 Mars Rd",
    "sg:city":"Cranberry Township",
    "sg:classifiers":[
        {
            "category":"Professional",
            "subcategory":"Engineering",
            "type":"Services"
        }
    ],
    "sg:phone":"+1   ",
    "sg:postcode":"16066",
    "sg:province":"PA",
    "wof:name":"Spectrum Engineers & Assoc",
    "wof:placetype":"venue"
},
  "geometry": {"coordinates":[-80.100482,40.685437],"type":"Point"}
}