{
  "type": "Feature",
  "properties": {
    "iso:country":"US",
    "sg:address":"2425 Wilmington Rd",
    "sg:city":"New Castle",
    "sg:classifiers":[
        {
            "category":"Personal",
            "subcategory":"Beauty Salon",
            "type":"Services"
        }
    ],
    "sg:phone":"+1 724 652 3317",
    "sg:postcode":"16105",
    "sg:province":"PA",
    "wof:name":"Famous Hair",
    "wof:placetype":"venue"
},
  "geometry": {"coordinates":[-80.35411499999999,41.027796],"type":"Point"}
}