{
  "type": "Feature",
  "properties": {
    "iso:country":"US",
    "sg:address":"426 N Broadway St",
    "sg:city":"Scottdale",
    "sg:classifiers":[
        {
            "category":"Local Transit",
            "type":"Transportation"
        }
    ],
    "sg:phone":"+1   ",
    "sg:postcode":"15683",
    "sg:province":"PA",
    "sg:tags":[
        "passenger"
    ],
    "wof:name":"Mutual Aid Ambulance Service",
    "wof:placetype":"venue"
},
  "geometry": {"coordinates":[-79.58540000000001,40.103384],"type":"Point"}
}