{
  "type": "Feature",
  "properties": {
    "iso:country":"US",
    "sg:address":"358 Pierce St",
    "sg:city":"Kingston",
    "sg:classifiers":[
        {
            "category":"Food & Beverages",
            "subcategory":"Groceries & Convenience Stores",
            "type":"Retail Goods"
        }
    ],
    "sg:phone":"+1 570 287 1999",
    "sg:postcode":"18704",
    "sg:province":"PA",
    "wof:name":"Turkey Hill Minit Market",
    "wof:placetype":"venue"
},
  "geometry": {"coordinates":[-75.88681,41.261296],"type":"Point"}
}