{
  "type": "Feature",
  "properties": {
    "addr:full":"1601 John F Kennedy Blvd Philadelphia PA 19103",
    "addr:housenumber":"1601",
    "addr:postcode":"19103",
    "addr:street":"John F Kennedy Blvd",
    "iso:country":"US",
    "sg:address":"1601 John F Kennedy Blvd",
    "sg:city":"Philadelphia",
    "sg:classifiers":[
        {
            "category":"Coffee & Tea",
            "type":"Food & Drink"
        }
    ],
    "sg:phone":"+1 215 567 3410",
    "sg:postcode":"19103",
    "sg:province":"PA",
    "wof:name":"Passero's Gourmet Coffee Co",
    "wof:placetype":"venue"
},
  "geometry": {"coordinates":[-75.173203,39.951302],"type":"Point"}
}