{
  "type": "Feature",
  "properties": {
    "iso:country":"US",
    "sg:address":"170 Commons Dr",
    "sg:city":"Du Bois",
    "sg:classifiers":[
        {
            "category":"Home & Garden",
            "subcategory":"Furniture",
            "type":"Retail Goods"
        }
    ],
    "sg:phone":"+1   ",
    "sg:postcode":"15801",
    "sg:province":"PA",
    "wof:name":"Mattress Emporium",
    "wof:placetype":"venue"
},
  "geometry": {"coordinates":[-78.73291999999999,41.126215],"type":"Point"}
}