{
  "type": "Feature",
  "properties": {
    "iso:country":"US",
    "sg:address":"1400 Church Ln",
    "sg:city":"Easton",
    "sg:classifiers":[
        {
            "category":"Building & Trades",
            "subcategory":"Construction",
            "type":"Services"
        }
    ],
    "sg:phone":"+1 610 258 3159",
    "sg:postcode":"18040",
    "sg:province":"PA",
    "sg:tags":[
        "wallcoverings-installation",
        "wallpaper",
        "painting",
        "contractor"
    ],
    "wof:name":"Scott Mitchell Painting",
    "wof:placetype":"venue"
},
  "geometry": {"coordinates":[-75.243847,40.751505],"type":"Point"}
}