{
  "type": "Feature",
  "properties": {
    "iso:country":"US",
    "sg:address":"225 German St",
    "sg:city":"Dushore",
    "sg:classifiers":[
        {
            "category":"Education",
            "subcategory":"College",
            "type":"Public Place"
        }
    ],
    "sg:phone":"+1 570 928 8941",
    "sg:postcode":"18614",
    "sg:province":"PA",
    "sg:tags":[
        "academic",
        "school"
    ],
    "wof:name":"Penn State University",
    "wof:placetype":"venue"
},
  "geometry": {"coordinates":[-76.401313,41.523335],"type":"Point"}
}