{
  "type": "Feature",
  "properties": {
    "iso:country":"US",
    "sg:address":"280 Osche Rd",
    "sg:city":"Butler",
    "sg:classifiers":[
        {
            "category":"Farming",
            "subcategory":"Nursery",
            "type":"Manufacturing & Wholesale Goods"
        }
    ],
    "sg:phone":"+1 724 287 2908",
    "sg:postcode":"16002",
    "sg:province":"PA",
    "sg:tags":[
        "greenhouse"
    ],
    "wof:name":"Geibel's Greenhouse",
    "wof:placetype":"venue"
},
  "geometry": {"coordinates":[-79.788738,40.827674],"type":"Point"}
}