{
  "type": "Feature",
  "properties": {
    "iso:country":"US",
    "sg:address":"510 Franklin St",
    "sg:city":"Clymer",
    "sg:classifiers":[
        {
            "category":"Retail",
            "subcategory":"Repair Shop",
            "type":"Services"
        }
    ],
    "sg:phone":"+1 724 254 0444",
    "sg:postcode":"15728",
    "sg:province":"PA",
    "sg:tags":[
        "appliance"
    ],
    "wof:name":"Bence's Maytag Home Appliance",
    "wof:placetype":"venue"
},
  "geometry": {"coordinates":[-79.011285,40.668681],"type":"Point"}
}