{
  "type": "Feature",
  "properties": {
    "iso:country":"US",
    "sg:address":"100 Heidelberg Ave",
    "sg:city":"Reading",
    "sg:classifiers":[
        {
            "category":"Shopping",
            "type":"Retail Goods"
        }
    ],
    "sg:phone":"+1 610 779 5617",
    "sg:postcode":"19606",
    "sg:province":"PA",
    "sg:tags":[
        "picture",
        "frame"
    ],
    "wof:name":"Christine Ziegler Studio",
    "wof:placetype":"venue"
},
  "geometry": {"coordinates":[-75.870261,40.345814],"type":"Point"}
}