{
  "type": "Feature",
  "properties": {
    "addr:full":"4614 Baltimore Ave Philadelphia PA 19143",
    "addr:housenumber":"4614",
    "addr:postcode":"19143",
    "addr:street":"Baltimore Ave",
    "iso:country":"US",
    "sg:address":"4614 Baltimore Ave",
    "sg:city":"Philadelphia",
    "sg:classifiers":[
        {
            "category":"Shopping",
            "subcategory":"Computers & Home Electronics",
            "type":"Retail Goods"
        },
        {
            "category":"Professional",
            "subcategory":"Computer Services",
            "type":"Services"
        }
    ],
    "sg:phone":"+1 215 758 6493",
    "sg:postcode":"19143",
    "sg:province":"PA",
    "sg:tags":[
        "repair",
        "recovery",
        "supply",
        "technical",
        "assistance",
        "system",
        "hardware",
        "network",
        "security-systems",
        "design",
        "equipment-service",
        "data",
        "support",
        "software"
    ],
    "wof:name":"The Computer Shoppes",
    "wof:placetype":"venue"
},
  "geometry": {"coordinates":[-75.215728,39.948777],"type":"Point"}
}