{
  "type": "Feature",
  "properties": {
    "iso:country":"US",
    "sg:address":"202 W Butler St",
    "sg:city":"Mount Holly Springs",
    "sg:classifiers":[
        {
            "category":"Organizations",
            "subcategory":"Religious Organization",
            "type":"Services"
        }
    ],
    "sg:phone":"+1   ",
    "sg:postcode":"17065",
    "sg:province":"PA",
    "wof:name":"Mount Holly Sprngs Untd Methds",
    "wof:placetype":"venue"
},
  "geometry": {"coordinates":[-77.19427399999999,40.118069],"type":"Point"}
}