{
  "type": "Feature",
  "properties": {
    "iso:country":"US",
    "sg:address":"121 Dawn Ave",
    "sg:city":"Pittsburgh",
    "sg:classifiers":[
        {
            "category":"Education",
            "subcategory":"School",
            "type":"Public Place"
        },
        {
            "category":"Organizations",
            "subcategory":"Religious Organization",
            "type":"Services"
        }
    ],
    "sg:phone":"+1 412 793 3959",
    "sg:postcode":"15226",
    "sg:province":"PA",
    "sg:tags":[
        "high",
        "middle",
        "elementary"
    ],
    "wof:name":"St Gerard Majella",
    "wof:placetype":"venue"
},
  "geometry": {"coordinates":[-80.011101,40.4133],"type":"Point"}
}