{
  "type": "Feature",
  "properties": {
    "addr:full":"2401 Walnut St Philadelphia PA 19103",
    "addr:housenumber":"2401",
    "addr:postcode":"19103",
    "addr:street":"Walnut St",
    "iso:country":"US",
    "sg:address":"2401 Walnut St",
    "sg:city":"Philadelphia",
    "sg:classifiers":[
        {
            "category":"Travel",
            "subcategory":"Travel Agent",
            "type":"Entertainment"
        }
    ],
    "sg:phone":"+1   ",
    "sg:postcode":"19103",
    "sg:province":"PA",
    "sg:tags":[
        "management"
    ],
    "wof:name":"American Express",
    "wof:placetype":"venue"
},
  "geometry": {"coordinates":[-75.1807,39.95139],"type":"Point"}
}