{
  "type": "Feature",
  "properties": {
    "addr:full":"475 Morgan Ct Scranton PA 18505",
    "addr:housenumber":"475",
    "addr:postcode":"18505",
    "addr:street":"Morgan Ct",
    "iso:country":"US",
    "sg:address":"475 Morgan Ct",
    "sg:city":"Scranton",
    "sg:classifiers":[
        {
            "category":"Health Services",
            "subcategory":"Doctor",
            "type":"Services"
        }
    ],
    "sg:phone":"+1   ",
    "sg:postcode":"18505",
    "sg:province":"PA",
    "sg:tags":[
        "medical"
    ],
    "wof:name":"Stephen A Nezezon MD",
    "wof:placetype":"venue"
},
  "geometry": {"coordinates":[-75.658057,41.396534],"type":"Point"}
}