{
  "type": "Feature",
  "properties": {
    "iso:country":"US",
    "sg:address":"87 Stambaugh Ave",
    "sg:city":"Sharon",
    "sg:classifiers":[
        {
            "category":"Social Services",
            "type":"Services"
        }
    ],
    "sg:phone":"+1 724 981 3670",
    "sg:postcode":"16146",
    "sg:province":"PA",
    "sg:tags":[
        "organization",
        "welfare"
    ],
    "wof:name":"AIDS Svc Program",
    "wof:placetype":"venue"
},
  "geometry": {"coordinates":[-80.493286,41.23158],"type":"Point"}
}