{
  "type": "Feature",
  "properties": {
    "iso:country":"US",
    "sg:address":"3092 Plum Hollow Rd",
    "sg:city":"Fort Littleton",
    "sg:classifiers":[
        {
            "category":"Building & Trades",
            "subcategory":"Landscaping Services",
            "type":"Services"
        }
    ],
    "sg:phone":"+1   ",
    "sg:postcode":"17223",
    "sg:province":"PA",
    "sg:tags":[
        "landscape"
    ],
    "wof:name":"Derrick S Winegardner",
    "wof:placetype":"venue"
},
  "geometry": {"coordinates":[-77.963199,40.061457],"type":"Point"}
}