{
  "type": "Feature",
  "properties": {
    "iso:country":"US",
    "sg:address":"212 Walnut St",
    "sg:city":"Philadelphia",
    "sg:classifiers":[
        {
            "category":"Sports & Exercise",
            "subcategory":"Gym",
            "type":"Entertainment"
        }
    ],
    "sg:phone":"+1 215 627 0900",
    "sg:postcode":"19106",
    "sg:province":"PA",
    "sg:tags":[
        "gymnasium"
    ],
    "sg:website":"http://www.poselmanagement.com",
    "wof:name":"Sid Ray",
    "wof:placetype":"venue"
},
  "geometry": {"coordinates":[-75.145031,39.946941],"type":"Point"}
}