{
  "type": "Feature",
  "properties": {
    "iso:country":"US",
    "sg:address":"363 Vanadium Rd",
    "sg:city":"Pittsburgh",
    "sg:classifiers":[
        {
            "category":"Health Services",
            "subcategory":"Doctor",
            "type":"Services"
        }
    ],
    "sg:phone":"+1 412 429 0880",
    "sg:postcode":"15243",
    "sg:province":"PA",
    "wof:name":"Beachler John S MD",
    "wof:placetype":"venue"
},
  "geometry": {"coordinates":[-80.085503,40.369301],"type":"Point"}
}