{
  "type": "Feature",
  "properties": {
    "iso:country":"US",
    "sg:address":"6400 N Radcliffe St",
    "sg:city":"Bristol",
    "sg:classifiers":[
        {
            "category":"Banks & Credit Unions",
            "subcategory":"Investment Brokerage",
            "type":"Services"
        }
    ],
    "sg:phone":"+1 215 781 0980",
    "sg:postcode":"19007",
    "sg:province":"PA",
    "sg:tags":[
        "advisory",
        "financial"
    ],
    "wof:name":"Volunteer's Financial Svc",
    "wof:placetype":"venue"
},
  "geometry": {"coordinates":[-74.835684,40.112845],"type":"Point"}
}