{
  "type": "Feature",
  "properties": {
    "iso:country":"US",
    "sg:address":"102 Essex Ct",
    "sg:city":"Lansdale",
    "sg:classifiers":[
        {
            "category":"Building & Trades",
            "subcategory":"Cleaning & Sanitation",
            "type":"Services"
        }
    ],
    "sg:phone":"+1 215 368 3650",
    "sg:postcode":"19446",
    "sg:province":"PA",
    "sg:tags":[
        "window"
    ],
    "wof:name":"Abracadabra",
    "wof:placetype":"venue"
},
  "geometry": {"coordinates":[-75.220812,40.258201],"type":"Point"}
}