{
  "type": "Feature",
  "properties": {
    "addr:full":"1107 Island Ave Mc Kees Rocks PA 15136",
    "addr:housenumber":"1107",
    "addr:postcode":"15136",
    "addr:street":"Island Ave Mc Kees Rocks",
    "iso:country":"US",
    "sg:address":"1107 Island Ave",
    "sg:city":"Mc Kees Rocks",
    "sg:classifiers":[
        {
            "category":"Bars & Pubs",
            "subcategory":"Nightclub",
            "type":"Food & Drink"
        }
    ],
    "sg:phone":"+1 412 331 4068",
    "sg:postcode":"15136",
    "sg:province":"PA",
    "sg:tags":[
        "nightlife"
    ],
    "wof:name":"Silky's",
    "wof:placetype":"venue"
},
  "geometry": {"coordinates":[-80.06619999999999,40.4772],"type":"Point"}
}