{
  "type": "Feature",
  "properties": {
    "iso:country":"US",
    "sg:address":"106 E Main St",
    "sg:city":"Bloomsburg",
    "sg:classifiers":[
        {
            "category":"Shopping",
            "subcategory":"Music",
            "type":"Retail Goods"
        }
    ],
    "sg:phone":"+1 570 784 7134",
    "sg:postcode":"17815",
    "sg:province":"PA",
    "sg:tags":[
        "compact",
        "record",
        "disc",
        "tape"
    ],
    "wof:name":"Mugsy's Discount Records",
    "wof:placetype":"venue"
},
  "geometry": {"coordinates":[-76.45423700000001,41.004089],"type":"Point"}
}