{
  "type": "Feature",
  "properties": {
    "iso:country":"US",
    "sg:address":"4719 Buffalo Rd",
    "sg:city":"Erie",
    "sg:classifiers":[
        {
            "category":"Education",
            "subcategory":"School",
            "type":"Public Place"
        }
    ],
    "sg:phone":"+1 814 899 3711",
    "sg:postcode":"16510",
    "sg:province":"PA",
    "wof:name":"Harborcreek Baptist Church",
    "wof:placetype":"venue"
},
  "geometry": {"coordinates":[-79.996472,42.148934],"type":"Point"}
}