{
  "type": "Feature",
  "properties": {
    "iso:country":"US",
    "sg:address":"602 Main St Exn",
    "sg:city":"Port Matilda",
    "sg:classifiers":[
        {
            "category":"Building & Trades",
            "subcategory":"Construction",
            "type":"Services"
        }
    ],
    "sg:phone":"+1   ",
    "sg:postcode":"16870",
    "sg:province":"PA",
    "sg:tags":[
        "contractor"
    ],
    "wof:name":"Mickle Roofing",
    "wof:placetype":"venue"
},
  "geometry": {"coordinates":[-78.048596,40.797062],"type":"Point"}
}