{
  "type": "Feature",
  "properties": {
    "iso:country":"US",
    "sg:address":"2611 Hampden Blvd",
    "sg:city":"Reading",
    "sg:classifiers":[
        {
            "category":"Health Services",
            "subcategory":"Chiropractor",
            "type":"Services"
        }
    ],
    "sg:phone":"+1   ",
    "sg:postcode":"19604",
    "sg:province":"PA",
    "wof:name":"Berks Cnty Chiropractic Spec",
    "wof:placetype":"venue"
},
  "geometry": {"coordinates":[-75.89719700000001,40.374274],"type":"Point"}
}