{
  "type": "Feature",
  "properties": {
    "addr:full":"10 Langley Dr Bradford PA 16701",
    "addr:housenumber":"10",
    "addr:postcode":"16701",
    "addr:street":"Langley Dr",
    "iso:country":"US",
    "sg:address":"10 Langley Dr",
    "sg:city":"Bradford",
    "sg:classifiers":[
        {
            "category":"Wholesale",
            "subcategory":"Furniture",
            "type":"Manufacturing & Wholesale Goods"
        }
    ],
    "sg:phone":"+1   ",
    "sg:postcode":"16701",
    "sg:province":"PA",
    "sg:tags":[
        "household"
    ],
    "wof:name":"Highland Furniture",
    "wof:placetype":"venue"
},
  "geometry": {"coordinates":[-78.612742,41.900167],"type":"Point"}
}