{
  "type": "Feature",
  "properties": {
    "addr:full":"361 Park Ave New Cumberland PA 17070",
    "addr:housenumber":"361",
    "addr:postcode":"17070",
    "addr:street":"Park Ave",
    "iso:country":"US",
    "sg:address":"361 Park Ave",
    "sg:city":"New Cumberland",
    "sg:classifiers":[
        {
            "category":"Insurance",
            "subcategory":"Insurance Agent",
            "type":"Services"
        }
    ],
    "sg:phone":"+1   ",
    "sg:postcode":"17070",
    "sg:province":"PA",
    "wof:name":"Wts Claim Service Inc",
    "wof:placetype":"venue"
},
  "geometry": {"coordinates":[-76.875846,40.231237],"type":"Point"}
}