{
  "type": "Feature",
  "properties": {
    "iso:country":"US",
    "sg:address":"2124 Marietta Ave",
    "sg:city":"Lancaster",
    "sg:classifiers":[
        {
            "category":"Social Services",
            "type":"Services"
        }
    ],
    "sg:phone":"+1 717 431 1314",
    "sg:postcode":"17603",
    "sg:province":"PA",
    "sg:tags":[
        "counseling"
    ],
    "wof:name":"Michelle Sheaffer Pro Cnslng",
    "wof:placetype":"venue"
},
  "geometry": {"coordinates":[-76.35682,40.051786],"type":"Point"}
}