{
  "type": "Feature",
  "properties": {
    "addr:full":"35 E Main St Waynesboro PA 17268",
    "addr:housenumber":"35",
    "addr:postcode":"17268",
    "addr:street":"E Main St",
    "iso:country":"US",
    "sg:address":"35 E Main St",
    "sg:city":"Waynesboro",
    "sg:classifiers":[
        {
            "category":"Banks & Credit Unions",
            "subcategory":"Investment Brokerage",
            "type":"Services"
        }
    ],
    "sg:phone":"+1 717 762 0911",
    "sg:postcode":"17268",
    "sg:province":"PA",
    "sg:tags":[
        "stock",
        "bond"
    ],
    "wof:name":"Edward Jones Co",
    "wof:placetype":"venue"
},
  "geometry": {"coordinates":[-77.577355,39.75558],"type":"Point"}
}