{
  "type": "Feature",
  "properties": {
    "iso:country":"US",
    "sg:address":"1206 Ag Center Dr",
    "sg:city":"Pottsville",
    "sg:classifiers":[
        {
            "category":"Government",
            "subcategory":"Office",
            "type":"Public Place"
        }
    ],
    "sg:phone":"+1   ",
    "sg:postcode":"17901",
    "sg:province":"PA",
    "sg:tags":[
        "conservation"
    ],
    "wof:name":"Schuylkill Conservation Dst",
    "wof:placetype":"venue"
},
  "geometry": {"coordinates":[-76.233947,40.671458],"type":"Point"}
}