{
  "type": "Feature",
  "properties": {
    "iso:country":"US",
    "sg:address":"604 Riverstix Ln",
    "sg:city":"Mechanicsburg",
    "sg:classifiers":[
        {
            "category":"Retail",
            "subcategory":"Repair Shop",
            "type":"Services"
        }
    ],
    "sg:phone":"+1 717 766 8317",
    "sg:postcode":"17050",
    "sg:province":"PA",
    "sg:tags":[
        "energy",
        "system",
        "solar"
    ],
    "wof:name":"R Harris Svc",
    "wof:placetype":"venue"
},
  "geometry": {"coordinates":[-76.948449,40.263187],"type":"Point"}
}