{
  "type": "Feature",
  "properties": {
    "iso:country":"US",
    "sg:address":"1405 New Rodgers Rd",
    "sg:city":"Bristol",
    "sg:classifiers":[
        {
            "category":"Real Estate",
            "subcategory":"Real Estate Operator",
            "type":"Services"
        }
    ],
    "sg:phone":"+1   ",
    "sg:postcode":"19007",
    "sg:province":"PA",
    "sg:tags":[
        "owns",
        "apartment",
        "an",
        "complex",
        "operates"
    ],
    "wof:name":"Bristol Gardens Inc",
    "wof:placetype":"venue"
},
  "geometry": {"coordinates":[-74.879648,40.112424],"type":"Point"}
}