{
  "type": "Feature",
  "properties": {
    "iso:country":"US",
    "sg:address":"1733 E Harrisburg Pike",
    "sg:city":"Middletown",
    "sg:classifiers":[
        {
            "category":"Shopping",
            "subcategory":"Bicycles & Sporting Goods",
            "type":"Retail Goods"
        }
    ],
    "sg:phone":"+1   ",
    "sg:postcode":"17057",
    "sg:province":"PA",
    "wof:name":"Thunder & Lightning Sport",
    "wof:placetype":"venue"
},
  "geometry": {"coordinates":[-76.70102199999999,40.197211],"type":"Point"}
}