{
  "type": "Feature",
  "properties": {
    "iso:country":"US",
    "sg:address":"1321 McLaughlin Run Rd",
    "sg:city":"Pittsburgh",
    "sg:classifiers":[
        {
            "category":"Building & Trades",
            "subcategory":"Construction",
            "type":"Services"
        }
    ],
    "sg:phone":"+1   ",
    "sg:postcode":"15241",
    "sg:province":"PA",
    "sg:tags":[
        "house"
    ],
    "wof:name":"Affordable Improvements",
    "wof:placetype":"venue"
},
  "geometry": {"coordinates":[-80.096411,40.356358],"type":"Point"}
}