{
  "type": "Feature",
  "properties": {
    "addr:full":"249 N Keswick Ave Glenside PA 19038",
    "addr:housenumber":"249",
    "addr:postcode":"19038",
    "addr:street":"N Keswick Ave",
    "iso:country":"US",
    "sg:address":"249 N Keswick Ave",
    "sg:city":"Glenside",
    "sg:classifiers":[
        {
            "category":"Travel",
            "subcategory":"Travel Agent",
            "type":"Entertainment"
        }
    ],
    "sg:phone":"+1 215 886 4884",
    "sg:postcode":"19038",
    "sg:province":"PA",
    "sg:tags":[
        "agency"
    ],
    "wof:name":"Away We Go Travel Inc",
    "wof:placetype":"venue"
},
  "geometry": {"coordinates":[-75.147094,40.10437],"type":"Point"}
}