{
  "type": "Feature",
  "properties": {
    "addr:full":"3111 N Wales Rd Norristown PA 19403",
    "addr:housenumber":"3111",
    "addr:postcode":"19403",
    "addr:street":"N Wales Rd",
    "iso:country":"US",
    "sg:address":"3111 N Wales Rd",
    "sg:city":"Norristown",
    "sg:classifiers":[
        {
            "category":"Building & Trades",
            "subcategory":"Construction",
            "type":"Services"
        }
    ],
    "sg:phone":"+1   ",
    "sg:postcode":"19403",
    "sg:province":"PA",
    "sg:tags":[
        "hanging",
        "contractor"
    ],
    "wof:name":"John G Cinaglia Pntg",
    "wof:placetype":"venue"
},
  "geometry": {"coordinates":[-75.33112800000001,40.15559],"type":"Point"}
}