{
  "type": "Feature",
  "properties": {
    "addr:full":"2423 Dorchester St W Furlong PA 18925",
    "addr:housenumber":"2423",
    "addr:postcode":"18925",
    "addr:street":"Dorchester St W",
    "iso:country":"US",
    "sg:address":"2423 Dorchester St W",
    "sg:city":"Furlong",
    "sg:classifiers":[
        {
            "category":"Wholesale",
            "subcategory":"Apparel",
            "type":"Manufacturing & Wholesale Goods"
        }
    ],
    "sg:phone":"+1 215 429 7746",
    "sg:postcode":"18925",
    "sg:province":"PA",
    "sg:tags":[
        "shoes-wholesale",
        "manufacturer"
    ],
    "wof:name":"Jane & Justine",
    "wof:placetype":"venue"
},
  "geometry": {"coordinates":[-75.09065,40.286173],"type":"Point"}
}