{
  "type": "Feature",
  "properties": {
    "addr:full":"241 W Grant St New Castle PA 16101",
    "addr:housenumber":"241",
    "addr:postcode":"16101",
    "addr:street":"W Grant St",
    "iso:country":"US",
    "sg:address":"241 W Grant St",
    "sg:city":"New Castle",
    "sg:classifiers":[
        {
            "category":"Manufacturing",
            "subcategory":"Printing",
            "type":"Manufacturing & Wholesale Goods"
        }
    ],
    "sg:phone":"+1 724 658 2005",
    "sg:postcode":"16101",
    "sg:province":"PA",
    "sg:tags":[
        "commercial"
    ],
    "wof:name":"Big Kahuna Screen Printing",
    "wof:placetype":"venue"
},
  "geometry": {"coordinates":[-80.349199,41.003346],"type":"Point"}
}