{
  "type": "Feature",
  "properties": {
    "addr:full":"496 W Chester Rd West Chester PA 19382",
    "addr:housenumber":"496",
    "addr:postcode":"19382",
    "addr:street":"W Chester Rd",
    "iso:country":"US",
    "sg:address":"496 W Chester Rd",
    "sg:city":"West Chester",
    "sg:classifiers":[
        {
            "category":"Building & Trades",
            "subcategory":"Plumbing",
            "type":"Services"
        }
    ],
    "sg:phone":"+1 610 793 0700",
    "sg:postcode":"19382",
    "sg:province":"PA",
    "sg:tags":[
        "plumbing",
        "contractor"
    ],
    "wof:name":"Rodney G Wynn",
    "wof:placetype":"venue"
},
  "geometry": {"coordinates":[-75.545187,39.910787],"type":"Point"}
}