{
  "type": "Feature",
  "properties": {
    "addr:full":"453 Eisenhower Dr Hanover PA 17331",
    "addr:housenumber":"453",
    "addr:postcode":"17331",
    "addr:street":"Eisenhower Dr",
    "iso:country":"US",
    "sg:address":"453 Eisenhower Dr",
    "sg:city":"Hanover",
    "sg:classifiers":[
        {
            "category":"Banks & Credit Unions",
            "subcategory":"Bank",
            "type":"Services"
        }
    ],
    "sg:phone":"+1 717 637 2201",
    "sg:postcode":"17331",
    "sg:province":"PA",
    "sg:tags":[
        "state",
        "commercial"
    ],
    "sg:website":"www.bankofhanover.com",
    "wof:name":"Bank Of Hanover & Trust Co",
    "wof:placetype":"venue"
},
  "geometry": {"coordinates":[-76.97402700000001,39.825376],"type":"Point"}
}