{
  "type": "Feature",
  "properties": {
    "addr:full":"109 Horseshoe Dr Hollidaysburg PA 16648",
    "addr:housenumber":"109",
    "addr:postcode":"16648",
    "addr:street":"Horseshoe Dr",
    "iso:country":"US",
    "sg:address":"109 Horseshoe Dr",
    "sg:city":"Hollidaysburg",
    "sg:classifiers":[
        {
            "category":"Professional",
            "subcategory":"Business Services",
            "type":"Services"
        }
    ],
    "sg:phone":"+1 814 695 9091",
    "sg:postcode":"16648",
    "sg:province":"PA",
    "sg:tags":[
        "auctioneer"
    ],
    "wof:name":"Panasiti & Assoc Auctioneering",
    "wof:placetype":"venue"
},
  "geometry": {"coordinates":[-78.354928,40.456553],"type":"Point"}
}