{
  "type": "Feature",
  "properties": {
    "iso:country":"US",
    "sg:address":"1602 Majestic Dr",
    "sg:city":"Chambersburg",
    "sg:classifiers":[
        {
            "category":"Wholesale",
            "subcategory":"Metals & Minerals",
            "type":"Manufacturing & Wholesale Goods"
        }
    ],
    "sg:phone":"+1 717 263 4670",
    "sg:postcode":"17202",
    "sg:province":"PA",
    "sg:tags":[
        "aluminum"
    ],
    "wof:name":"M E Landis Aluminum Products",
    "wof:placetype":"venue"
},
  "geometry": {"coordinates":[-80.243394,40.099516],"type":"Point"}
}