{
  "type": "Feature",
  "properties": {
    "iso:country":"US",
    "sg:address":"328 E Broad St",
    "sg:city":"Bethlehem",
    "sg:classifiers":[
        {
            "category":"Building & Trades",
            "subcategory":"Plumbing",
            "type":"Services"
        }
    ],
    "sg:phone":"+1 610 868 4995",
    "sg:postcode":"18018",
    "sg:province":"PA",
    "sg:tags":[
        "contractor"
    ],
    "wof:name":"Wayne Plumbing & Heating",
    "wof:placetype":"venue"
},
  "geometry": {"coordinates":[-75.368959,40.622059],"type":"Point"}
}