{
  "type": "Feature",
  "properties": {
    "iso:country":"US",
    "sg:address":"6100 W Jefferson St",
    "sg:city":"Philadelphia",
    "sg:classifiers":[
        {
            "category":"Banks & Credit Unions",
            "subcategory":"Investment Brokerage",
            "type":"Services"
        }
    ],
    "sg:phone":"+1 215 877 2171",
    "sg:postcode":"19151",
    "sg:province":"PA",
    "sg:tags":[
        "consultant",
        "planning",
        "financial"
    ],
    "wof:name":"Black River Group",
    "wof:placetype":"venue"
},
  "geometry": {"coordinates":[-75.243245,39.978609],"type":"Point"}
}