{
  "type": "Feature",
  "properties": {
    "iso:country":"US",
    "sg:address":"326 E 2nd Ave",
    "sg:city":"Tarentum",
    "sg:classifiers":[
        {
            "category":"Retail",
            "subcategory":"Auto Repair",
            "type":"Services"
        }
    ],
    "sg:phone":"+1 724 224 7527",
    "sg:postcode":"15084",
    "sg:province":"PA",
    "sg:tags":[
        "repairing",
        "automobile"
    ],
    "wof:name":"B C Specialties",
    "wof:placetype":"venue"
},
  "geometry": {"coordinates":[-79.75244600000001,40.600671],"type":"Point"}
}