{
  "type": "Feature",
  "properties": {
    "addr:full":"26 Hummel Ave Camp Hill PA 17011",
    "addr:housenumber":"26",
    "addr:postcode":"17011",
    "addr:street":"Hummel Ave",
    "iso:country":"US",
    "sg:address":"26 Hummel Ave",
    "sg:city":"Camp Hill",
    "sg:classifiers":[
        {
            "category":"Health Services",
            "subcategory":"Clinic",
            "type":"Services"
        }
    ],
    "sg:phone":"+1 717 975 8910",
    "sg:postcode":"17011",
    "sg:province":"PA",
    "sg:tags":[
        "equipment",
        "therapy",
        "oxygen"
    ],
    "wof:name":"Wasserott's",
    "wof:placetype":"venue"
},
  "geometry": {"coordinates":[-76.908708,40.236618],"type":"Point"}
}