{
  "type": "Feature",
  "properties": {
    "addr:full":"2200 Market St Camp Hill PA 17011",
    "addr:housenumber":"2200",
    "addr:postcode":"17011",
    "addr:street":"Market St",
    "iso:country":"US",
    "sg:address":"2200 Market St",
    "sg:city":"Camp Hill",
    "sg:classifiers":[
        {
            "category":"Wholesale",
            "subcategory":"Groceries",
            "type":"Manufacturing & Wholesale Goods"
        }
    ],
    "sg:phone":"+1   ",
    "sg:postcode":"17011",
    "sg:province":"PA",
    "sg:tags":[
        "general"
    ],
    "wof:name":"Roger J Wood Company",
    "wof:placetype":"venue"
},
  "geometry": {"coordinates":[-76.92341999999999,40.240328],"type":"Point"}
}