{
  "type": "Feature",
  "properties": {
    "iso:country":"US",
    "sg:address":"12273 Townsend Rd",
    "sg:city":"Philadelphia",
    "sg:classifiers":[
        {
            "category":"Organizations",
            "subcategory":"Labor Organization",
            "type":"Services"
        }
    ],
    "sg:phone":"+1 215 676 2555",
    "sg:postcode":"19154",
    "sg:province":"PA",
    "wof:name":"Elevator Constructors",
    "wof:placetype":"venue"
},
  "geometry": {"coordinates":[-74.9867,40.101063],"type":"Point"}
}