{
  "type": "Feature",
  "properties": {
    "iso:country":"US",
    "sg:address":"174 Church Rd",
    "sg:city":"Schellsburg",
    "sg:classifiers":[
        {
            "category":"Organizations",
            "subcategory":"Religious Organization",
            "type":"Services"
        }
    ],
    "sg:phone":"+1 814 733 4763",
    "sg:postcode":"15559",
    "sg:province":"PA",
    "sg:tags":[
        "church"
    ],
    "wof:name":"Point United Methodist Church",
    "wof:placetype":"venue"
},
  "geometry": {"coordinates":[-78.602799,40.079124],"type":"Point"}
}