{
  "type": "Feature",
  "properties": {
    "iso:country":"US",
    "sg:address":"105 N 7th St",
    "sg:city":"Allentown",
    "sg:classifiers":[
        {
            "category":"Restaurant",
            "type":"Food & Drink"
        }
    ],
    "sg:phone":"+1 484 664 7259",
    "sg:postcode":"18101",
    "sg:province":"PA",
    "sg:tags":[
        "eating"
    ],
    "wof:name":"Solido Deli",
    "wof:placetype":"venue"
},
  "geometry": {"coordinates":[-75.472945,40.605011],"type":"Point"}
}