{
  "type": "Feature",
  "properties": {
    "iso:country":"US",
    "sg:address":"139 E Meadow St",
    "sg:city":"Shavertown",
    "sg:classifiers":[
        {
            "category":"Manufacturing",
            "subcategory":"Electronics",
            "type":"Manufacturing & Wholesale Goods"
        },
        {
            "category":"Utilities",
            "subcategory":"Telephone",
            "type":"Services"
        },
        {
            "category":"Shopping",
            "subcategory":"Computers & Home Electronics",
            "type":"Retail Goods"
        },
        {
            "category":"Communications",
            "type":"Services"
        }
    ],
    "sg:phone":"+1 570 696 4809",
    "sg:postcode":"18708",
    "sg:province":"PA",
    "sg:tags":[
        "sound",
        "television",
        "electronic",
        "system",
        "equipment",
        "radio",
        "consumer",
        "supplies-wholesale",
        "store",
        "manufacturer"
    ],
    "wof:name":"Telecom Reps",
    "wof:placetype":"venue"
},
  "geometry": {"coordinates":[-75.96856200000001,41.283106],"type":"Point"}
}