{
  "type": "Feature",
  "properties": {
    "iso:country":"US",
    "sg:address":"638 Wyoming Ave",
    "sg:city":"Wyoming",
    "sg:classifiers":[
        {
            "category":"Health Services",
            "subcategory":"Doctor",
            "type":"Services"
        }
    ],
    "sg:phone":"+1   ",
    "sg:postcode":"18644",
    "sg:province":"PA",
    "sg:tags":[
        "medical"
    ],
    "wof:name":"Scrobola Charles C MD",
    "wof:placetype":"venue"
},
  "geometry": {"coordinates":[-75.841612,41.308395],"type":"Point"}
}