{
  "type": "Feature",
  "properties": {
    "iso:country":"US",
    "sg:address":"893 Strickler Rd",
    "sg:city":"Mount Joy",
    "sg:classifiers":[
        {
            "category":"Shopping",
            "subcategory":"Used Merchandise",
            "type":"Retail Goods"
        }
    ],
    "sg:phone":"+1   ",
    "sg:postcode":"17552",
    "sg:province":"PA",
    "wof:name":"Anthony Ritrobato",
    "wof:placetype":"venue"
},
  "geometry": {"coordinates":[-76.462782,40.11658],"type":"Point"}
}