{
  "type": "Feature",
  "properties": {
    "iso:country":"US",
    "sg:address":"5256 State Route 30 ",
    "sg:city":"Greensburg",
    "sg:classifiers":[
        {
            "category":"Restaurant",
            "type":"Food & Drink"
        }
    ],
    "sg:menulink":"http://www.allmenus.com/pa/hempfield/287701-charleys-grilled-subs/menu/",
    "sg:phone":"+1 724 600 0995",
    "sg:postcode":"15601",
    "sg:province":"PA",
    "sg:tags":[
        "barbecue",
        "chicken",
        "american"
    ],
    "wof:name":"Charley's Grilled Subs",
    "wof:placetype":"venue"
},
  "geometry": {"coordinates":[-79.507789,40.302975],"type":"Point"}
}