{
  "type": "Feature",
  "properties": {
    "iso:country":"US",
    "sg:address":"325 Chestnut St",
    "sg:city":"Philadelphia",
    "sg:classifiers":[
        {
            "category":"Professional",
            "subcategory":"Advertising",
            "type":"Services"
        }
    ],
    "sg:phone":"+1 215 413 2686",
    "sg:postcode":"19106",
    "sg:province":"PA",
    "sg:tags":[
        "counselor"
    ],
    "sg:website":"www.kanterinternational.com",
    "wof:name":"Kanter International",
    "wof:placetype":"venue"
},
  "geometry": {"coordinates":[-75.147273,39.948863],"type":"Point"}
}