{
  "type": "Feature",
  "properties": {
    "iso:country":"US",
    "sg:address":"226 Oxford Cir",
    "sg:city":"Norristown",
    "sg:classifiers":[
        {
            "category":"Professional",
            "subcategory":"Management & Consulting",
            "type":"Services"
        },
        {
            "category":"Professional",
            "subcategory":"Advertising",
            "type":"Services"
        }
    ],
    "sg:phone":"+1 484 429 3815",
    "sg:postcode":"19403",
    "sg:province":"PA",
    "sg:tags":[
        "marketing",
        "program",
        "consultant"
    ],
    "sg:website":"http://www.lbmarketingonline.com",
    "wof:name":"L B Marketing",
    "wof:placetype":"venue"
},
  "geometry": {"coordinates":[-75.366043,40.131859],"type":"Point"}
}