{
  "type": "Feature",
  "properties": {
    "addr:full":"892 Blakeslee Boulevard Dr E Lehighton PA 18235",
    "addr:housenumber":"892",
    "addr:postcode":"18235",
    "addr:street":"Blakeslee Boulevard Dr E",
    "iso:country":"US",
    "sg:address":"892 Blakeslee Boulevard Dr E",
    "sg:city":"Lehighton",
    "sg:classifiers":[
        {
            "category":"Professional",
            "subcategory":"Engineering",
            "type":"Services"
        }
    ],
    "sg:phone":"+1   ",
    "sg:postcode":"18235",
    "sg:province":"PA",
    "sg:tags":[
        "repair",
        "consulting",
        "mfg",
        "equipment",
        "compounding",
        "engineer"
    ],
    "wof:name":"Technical Process & Engrg",
    "wof:placetype":"venue"
},
  "geometry": {"coordinates":[-75.72675700000001,40.818715],"type":"Point"}
}