{
  "type": "Feature",
  "properties": {
    "iso:country":"US",
    "sg:address":"62 E Clymer Ave",
    "sg:city":"Sellersville",
    "sg:classifiers":[
        {
            "category":"Professional",
            "subcategory":"Business Services",
            "type":"Services"
        }
    ],
    "sg:phone":"+1 215 453 7328",
    "sg:postcode":"18960",
    "sg:province":"PA",
    "sg:tags":[
        "embroidery"
    ],
    "wof:name":"Sellersville Custom Embroidery",
    "wof:placetype":"venue"
},
  "geometry": {"coordinates":[-75.304194,40.354267],"type":"Point"}
}