{
  "type": "Feature",
  "properties": {
    "addr:full":"2521 Stillhouse Hollow Rd Shippensburg PA 17257",
    "addr:housenumber":"2521",
    "addr:postcode":"17257",
    "addr:street":"Stillhouse Hollow Rd",
    "iso:country":"US",
    "sg:address":"2521 Stillhouse Hollow Rd",
    "sg:city":"Shippensburg",
    "sg:classifiers":[
        {
            "category":"Organizations",
            "subcategory":"Membership Organization",
            "type":"Services"
        }
    ],
    "sg:phone":"+1 717 532 7489",
    "sg:postcode":"17257",
    "sg:province":"PA",
    "sg:tags":[
        "society",
        "humane"
    ],
    "wof:name":"Nusiance Wildlife Control",
    "wof:placetype":"venue"
},
  "geometry": {"coordinates":[-77.51430999999999,39.969627],"type":"Point"}
}