{
  "type": "Feature",
  "properties": {
    "iso:country":"US",
    "sg:address":"1848 Charter Ln",
    "sg:city":"Lancaster",
    "sg:classifiers":[
        {
            "category":"Travel",
            "subcategory":"Travel Agent",
            "type":"Entertainment"
        }
    ],
    "sg:phone":"+1 717 299 2521",
    "sg:postcode":"17601",
    "sg:province":"PA",
    "sg:tags":[
        "agency",
        "bureau"
    ],
    "wof:name":"Travel Time Travel Agency Inc",
    "wof:placetype":"venue"
},
  "geometry": {"coordinates":[-76.249926,40.052205],"type":"Point"}
}