{
  "type": "Feature",
  "properties": {
    "iso:country":"US",
    "sg:address":"20 Lenox Ct",
    "sg:city":"Mechanicsburg",
    "sg:classifiers":[
        {
            "category":"Building & Trades",
            "subcategory":"Cleaning & Sanitation",
            "type":"Services"
        }
    ],
    "sg:phone":"+1 717 697 8311",
    "sg:postcode":"17050",
    "sg:province":"PA",
    "sg:tags":[
        "window"
    ],
    "wof:name":"Central Penn Window Cleaning",
    "wof:placetype":"venue"
},
  "geometry": {"coordinates":[-77.071906,40.239507],"type":"Point"}
}