{
  "type": "Feature",
  "properties": {
    "iso:country":"US",
    "sg:address":"5121 Butler St",
    "sg:city":"Pittsburgh",
    "sg:classifiers":[
        {
            "category":"Restaurant",
            "type":"Food & Drink"
        }
    ],
    "sg:menulink":"http://www.allmenus.com/pa/pittsburgh/286566-remedy/menu/",
    "sg:phone":"+1 412 781 6771",
    "sg:postcode":"15201",
    "sg:province":"PA",
    "sg:tags":[
        "american"
    ],
    "wof:name":"Remedy",
    "wof:placetype":"venue"
},
  "geometry": {"coordinates":[-79.955117,40.479626],"type":"Point"}
}