{
  "type": "Feature",
  "properties": {
    "addr:full":"5104 Germantown Ave Philadelphia PA 19144",
    "addr:housenumber":"5104",
    "addr:postcode":"19144",
    "addr:street":"Germantown Ave",
    "iso:country":"US",
    "sg:address":"5104 Germantown Ave",
    "sg:city":"Philadelphia",
    "sg:classifiers":[
        {
            "category":"Personal",
            "subcategory":"Beauty Salon",
            "type":"Services"
        }
    ],
    "sg:phone":"+1   ",
    "sg:postcode":"19144",
    "sg:province":"PA",
    "sg:tags":[
        "shop"
    ],
    "wof:name":"Cuts By US",
    "wof:placetype":"venue"
},
  "geometry": {"coordinates":[-75.166004,40.030421],"type":"Point"}
}