{
  "type": "Feature",
  "properties": {
    "iso:country":"US",
    "sg:address":"4041 Sherry Hill Rd",
    "sg:city":"Hellertown",
    "sg:classifiers":[
        {
            "category":"Building & Trades",
            "subcategory":"Construction",
            "type":"Services"
        }
    ],
    "sg:phone":"+1   ",
    "sg:postcode":"18055",
    "sg:province":"PA",
    "sg:tags":[
        "hanging",
        "contractor"
    ],
    "wof:name":"Bobs Maintenance Contractor",
    "wof:placetype":"venue"
},
  "geometry": {"coordinates":[-75.30088000000001,40.614509],"type":"Point"}
}