{
  "type": "Feature",
  "properties": {
    "iso:country":"US",
    "sg:address":"571 Mayer St",
    "sg:city":"Bridgeville",
    "sg:classifiers":[
        {
            "category":"Retail",
            "subcategory":"Auto Repair",
            "type":"Services"
        }
    ],
    "sg:phone":"+1 412 221 3818",
    "sg:postcode":"15017",
    "sg:province":"PA",
    "sg:tags":[
        "body",
        "automobile",
        "dent",
        "removal",
        "painting",
        "repairing"
    ],
    "wof:name":"Clark Auto Repair",
    "wof:placetype":"venue"
},
  "geometry": {"coordinates":[-80.105933,40.365177],"type":"Point"}
}