{
  "type": "Feature",
  "properties": {
    "iso:country":"US",
    "sg:address":"2716 Jenkintown Rd",
    "sg:city":"Glenside",
    "sg:classifiers":[
        {
            "category":"Organizations",
            "subcategory":"Religious Organization",
            "type":"Services"
        }
    ],
    "sg:phone":"+1 215 886 1527",
    "sg:postcode":"19038",
    "sg:province":"PA",
    "sg:tags":[
        "church"
    ],
    "wof:name":"Phila Korean Bible Church",
    "wof:placetype":"venue"
},
  "geometry": {"coordinates":[-75.15670299999999,40.115828],"type":"Point"}
}