{
  "type": "Feature",
  "properties": {
    "iso:country":"US",
    "sg:address":"55 Salem Ave",
    "sg:city":"Carbondale",
    "sg:classifiers":[
        {
            "category":"Manufacturing",
            "subcategory":"Food",
            "type":"Manufacturing & Wholesale Goods"
        },
        {
            "category":"Food & Beverages",
            "subcategory":"Bakery",
            "type":"Retail Goods"
        }
    ],
    "sg:phone":"+1 570 282 4710",
    "sg:postcode":"18407",
    "sg:province":"PA",
    "sg:tags":[
        "baker",
        "product",
        "mfg"
    ],
    "wof:name":"Barbour's Bakery",
    "wof:placetype":"venue"
},
  "geometry": {"coordinates":[-75.500879,41.573133],"type":"Point"}
}