{
  "type": "Feature",
  "properties": {
    "addr:full":"200 Lora Dr Irwin PA 15642",
    "addr:housenumber":"200",
    "addr:postcode":"15642",
    "addr:street":"Lora Dr",
    "iso:country":"US",
    "sg:address":"200 Lora Dr",
    "sg:city":"Irwin",
    "sg:classifiers":[
        {
            "category":"Shopping",
            "subcategory":"Bicycles & Sporting Goods",
            "type":"Retail Goods"
        }
    ],
    "sg:phone":"+1   ",
    "sg:postcode":"15642",
    "sg:province":"PA",
    "wof:name":"Jobar",
    "wof:placetype":"venue"
},
  "geometry": {"coordinates":[-79.674503,40.343688],"type":"Point"}
}