{
  "type": "Feature",
  "properties": {
    "addr:full":"3396 Mountain Rd Hamburg PA 19526",
    "addr:housenumber":"3396",
    "addr:postcode":"19526",
    "addr:street":"Mountain Rd",
    "iso:country":"US",
    "sg:address":"3396 Mountain Rd",
    "sg:city":"Hamburg",
    "sg:classifiers":[
        {
            "category":"Wholesale",
            "subcategory":"Non-durable Goods",
            "type":"Manufacturing & Wholesale Goods"
        }
    ],
    "sg:phone":"+1   ",
    "sg:postcode":"19526",
    "sg:province":"PA",
    "sg:tags":[
        "store",
        "variety"
    ],
    "wof:name":"Blue Mountain Storage",
    "wof:placetype":"venue"
},
  "geometry": {"coordinates":[-76.093316,40.528745],"type":"Point"}
}