{
  "type": "Feature",
  "properties": {
    "iso:country":"US",
    "sg:address":"3061 Industry Dr",
    "sg:city":"Lancaster",
    "sg:classifiers":[
        {
            "category":"Manufacturing",
            "subcategory":"Tools & Machinery",
            "type":"Manufacturing & Wholesale Goods"
        }
    ],
    "sg:phone":"+1   ",
    "sg:postcode":"17603",
    "sg:province":"PA",
    "sg:tags":[
        "instrumentation",
        "product",
        "flight",
        "mfg"
    ],
    "wof:name":"Herley Industries",
    "wof:placetype":"venue"
},
  "geometry": {"coordinates":[-76.390688,40.043806],"type":"Point"}
}