{
  "type": "Feature",
  "properties": {
    "addr:full":"102 N Pike Rd Sarver PA 16055",
    "addr:housenumber":"102",
    "addr:postcode":"16055",
    "addr:street":"N Pike Rd",
    "iso:country":"US",
    "sg:address":"102 N Pike Rd",
    "sg:city":"Sarver",
    "sg:classifiers":[
        {
            "category":"Health Services",
            "subcategory":"Doctor",
            "type":"Services"
        }
    ],
    "sg:phone":"+1 724 353 1521",
    "sg:postcode":"16055",
    "sg:province":"PA",
    "sg:tags":[
        "dentist"
    ],
    "wof:name":"Adam Associates",
    "wof:placetype":"venue"
},
  "geometry": {"coordinates":[-79.756371,40.722419],"type":"Point"}
}