{
  "type": "Feature",
  "properties": {
    "addr:full":"101 N Narberth Ave Narberth PA 19072",
    "addr:housenumber":"101",
    "addr:postcode":"19072",
    "addr:street":"N Narberth Ave",
    "iso:country":"US",
    "sg:address":"101 N Narberth Ave",
    "sg:city":"Narberth",
    "sg:classifiers":[
        {
            "category":"Bars & Pubs",
            "type":"Food & Drink"
        }
    ],
    "sg:phone":"+1   ",
    "sg:postcode":"19072",
    "sg:province":"PA",
    "sg:tags":[
        "drinking"
    ],
    "wof:name":"Tap Room USA",
    "wof:placetype":"venue"
},
  "geometry": {"coordinates":[-75.26024700000001,40.006081],"type":"Point"}
}