{
  "type": "Feature",
  "properties": {
    "iso:country":"US",
    "sg:address":"1478 Old State Rd",
    "sg:city":"Waterford",
    "sg:classifiers":[
        {
            "category":"Professional",
            "subcategory":"Research",
            "type":"Services"
        }
    ],
    "sg:phone":"+1 814 796 2046",
    "sg:postcode":"16441",
    "sg:province":"PA",
    "sg:tags":[
        "development",
        "electronic"
    ],
    "wof:name":"Poly Tronics",
    "wof:placetype":"venue"
},
  "geometry": {"coordinates":[-80.032276,41.930724],"type":"Point"}
}