{
  "type": "Feature",
  "properties": {
    "addr:full":"1135 Edgar St York PA 17403",
    "addr:housenumber":"1135",
    "addr:postcode":"17403",
    "addr:street":"Edgar St",
    "iso:country":"US",
    "sg:address":"1135 Edgar St",
    "sg:city":"York",
    "sg:classifiers":[
        {
            "category":"Professional",
            "type":"Services"
        }
    ],
    "sg:phone":"+1   ",
    "sg:postcode":"17403",
    "sg:province":"PA",
    "wof:name":"Bald Smile Inc",
    "wof:placetype":"venue"
},
  "geometry": {"coordinates":[-76.709588,39.95013],"type":"Point"}
}