{
  "type": "Feature",
  "properties": {
    "iso:country":"US",
    "sg:address":"4215 Hamilton Rd",
    "sg:city":"Pittsburgh",
    "sg:classifiers":[
        {
            "category":"Retail",
            "subcategory":"Auto Repair",
            "type":"Services"
        }
    ],
    "sg:phone":"+1   ",
    "sg:postcode":"15236",
    "sg:province":"PA",
    "sg:tags":[
        "body"
    ],
    "wof:name":"L A Collision Parts",
    "wof:placetype":"venue"
},
  "geometry": {"coordinates":[-80.01611,40.357585],"type":"Point"}
}