{
  "type": "Feature",
  "properties": {
    "iso:country":"US",
    "sg:address":"1535 Cherry St",
    "sg:city":"Philadelphia",
    "sg:classifiers":[
        {
            "category":"Retail",
            "subcategory":"Laundry & Dry Cleaning",
            "type":"Services"
        }
    ],
    "sg:phone":"+1 215 665 1110",
    "sg:postcode":"19102",
    "sg:province":"PA",
    "sg:tags":[
        "cleaners"
    ],
    "wof:name":"Maggie's Cleaners",
    "wof:placetype":"venue"
},
  "geometry": {"coordinates":[-75.166147,39.955805],"type":"Point"}
}