{
  "type": "Feature",
  "properties": {
    "iso:country":"US",
    "sg:address":"14 Sonny Dr",
    "sg:city":"Old Forge",
    "sg:classifiers":[
        {
            "category":"Building & Trades",
            "subcategory":"Electrical",
            "type":"Services"
        }
    ],
    "sg:phone":"+1 570 457 9481",
    "sg:postcode":"18518",
    "sg:province":"PA",
    "sg:tags":[
        "electrical",
        "contractor"
    ],
    "wof:name":"Northeastern Electric Co",
    "wof:placetype":"venue"
},
  "geometry": {"coordinates":[-75.750637,41.384096],"type":"Point"}
}