{
  "type": "Feature",
  "properties": {
    "addr:full":"1252 Liberty St Franklin PA 16323",
    "addr:housenumber":"1252",
    "addr:postcode":"16323",
    "addr:street":"Liberty St",
    "iso:country":"US",
    "sg:address":"1252 Liberty St",
    "sg:city":"Franklin",
    "sg:classifiers":[
        {
            "category":"Health Services",
            "subcategory":"Health Practitioner",
            "type":"Services"
        }
    ],
    "sg:phone":"+1   ",
    "sg:postcode":"16323",
    "sg:province":"PA",
    "wof:name":"Dawn Haggart MA",
    "wof:placetype":"venue"
},
  "geometry": {"coordinates":[-79.829126,41.397625],"type":"Point"}
}