{
  "type": "Feature",
  "properties": {
    "iso:country":"US",
    "sg:address":"730 Main St",
    "sg:city":"Forest City",
    "sg:classifiers":[
        {
            "category":"Bars & Pubs",
            "type":"Food & Drink"
        }
    ],
    "sg:phone":"+1 570 785 3489",
    "sg:postcode":"18421",
    "sg:province":"PA",
    "sg:tags":[
        "drinking"
    ],
    "wof:name":"Fitz's Place",
    "wof:placetype":"venue"
},
  "geometry": {"coordinates":[-75.466002,41.652225],"type":"Point"}
}