{
  "type": "Feature",
  "properties": {
    "iso:country":"US",
    "sg:address":"440 Center St",
    "sg:city":"Clarksville",
    "sg:classifiers":[
        {
            "category":"Professional",
            "subcategory":"Art Services",
            "type":"Services"
        },
        {
            "category":"Manufacturing",
            "subcategory":"Printing",
            "type":"Manufacturing & Wholesale Goods"
        }
    ],
    "sg:phone":"+1 724 377 0161",
    "sg:postcode":"15322",
    "sg:province":"PA",
    "sg:tags":[
        "commercial",
        "screen",
        "design"
    ],
    "sg:website":"www.hoylesgraphix.com",
    "wof:name":"Hoyle's Graphic Xpressions",
    "wof:placetype":"venue"
},
  "geometry": {"coordinates":[-80.044777,39.973735],"type":"Point"}
}