{
  "type": "Feature",
  "properties": {
    "addr:full":"211 N Whitfield St Pittsburgh PA 15206",
    "addr:housenumber":"211",
    "addr:postcode":"15206",
    "addr:street":"N Whitfield St",
    "iso:country":"US",
    "sg:address":"211 N Whitfield St",
    "sg:city":"Pittsburgh",
    "sg:classifiers":[
        {
            "category":"Health Services",
            "subcategory":"Doctor",
            "type":"Services"
        }
    ],
    "sg:phone":"+1 412 361 3132",
    "sg:postcode":"15206",
    "sg:province":"PA",
    "sg:tags":[
        "physician",
        "surgeon"
    ],
    "wof:name":"Kisner & Turner",
    "wof:placetype":"venue"
},
  "geometry": {"coordinates":[-79.925146,40.462856],"type":"Point"}
}