{
  "type": "Feature",
  "properties": {
    "addr:full":"9 S 69th St Upper Darby PA 19082",
    "addr:housenumber":"9",
    "addr:postcode":"19082",
    "addr:street":"S 69Th St",
    "iso:country":"US",
    "sg:address":"9 S 69th St",
    "sg:city":"Upper Darby",
    "sg:classifiers":[
        {
            "category":"Shopping",
            "subcategory":"Clothing, Apparel, & Fashions",
            "type":"Retail Goods"
        }
    ],
    "sg:phone":"+1   ",
    "sg:postcode":"19082",
    "sg:province":"PA",
    "wof:name":"Simply Fashions",
    "wof:placetype":"venue"
},
  "geometry": {"coordinates":[-75.25884600000001,39.961618],"type":"Point"}
}