{
  "type": "Feature",
  "properties": {
    "addr:full":"20455 Route 19 Cranberry Twp PA 16066",
    "addr:housenumber":"20455",
    "addr:postcode":"16066",
    "addr:street":"Route 19",
    "iso:country":"US",
    "sg:address":"20455 Route 19",
    "sg:city":"Cranberry Twp",
    "sg:classifiers":[
        {
            "category":"Banks & Credit Unions",
            "subcategory":"Financial Services",
            "type":"Services"
        }
    ],
    "sg:phone":"+1 724 742 8688",
    "sg:postcode":"16066",
    "sg:province":"PA",
    "sg:tags":[
        "broker",
        "mortgage"
    ],
    "wof:name":"Midlantic Mortgage Co",
    "wof:placetype":"venue"
},
  "geometry": {"coordinates":[-80.10459899999999,40.701599],"type":"Point"}
}