{
  "type": "Feature",
  "properties": {
    "iso:country":"US",
    "sg:address":"81 Sharon Dr",
    "sg:city":"Richboro",
    "sg:classifiers":[
        {
            "category":"Ferry",
            "type":"Transportation"
        }
    ],
    "sg:phone":"+1 215 322 0515",
    "sg:postcode":"18954",
    "sg:province":"PA",
    "sg:tags":[
        "passenger",
        "deep",
        "sea"
    ],
    "wof:name":"Cruise Events",
    "wof:placetype":"venue"
},
  "geometry": {"coordinates":[-75.029724,40.216661],"type":"Point"}
}