{
  "type": "Feature",
  "properties": {
    "iso:country":"US",
    "sg:address":"409 Moonhill Dr",
    "sg:city":"Schuylkill Haven",
    "sg:classifiers":[
        {
            "category":"Manufacturing",
            "subcategory":"Printing",
            "type":"Manufacturing & Wholesale Goods"
        }
    ],
    "sg:phone":"+1 570 739 4700",
    "sg:postcode":"17972",
    "sg:province":"PA",
    "sg:tags":[
        "periodical"
    ],
    "wof:name":"Gurugraphix Inc",
    "wof:placetype":"venue"
},
  "geometry": {"coordinates":[-76.209346,40.604976],"type":"Point"}
}