{
  "type": "Feature",
  "properties": {
    "iso:country":"US",
    "sg:address":"Mclaughlin Run Rd",
    "sg:city":"Bridgeville",
    "sg:classifiers":[
        {
            "category":"Deli",
            "type":"Food & Drink"
        }
    ],
    "sg:menulink":"http://www.allmenus.com/pa/bridgeville/27929-pjs-deli/menu/",
    "sg:phone":"+1 412 257 4944",
    "sg:postcode":"15017",
    "sg:province":"PA",
    "sg:tags":[
        "american"
    ],
    "wof:name":"PJ's Deli",
    "wof:placetype":"venue"
},
  "geometry": {"coordinates":[-80.10044000000001,40.35383],"type":"Point"}
}