{
  "type": "Feature",
  "properties": {
    "iso:country":"US",
    "sg:address":"15 Industrial Pkwy",
    "sg:city":"Mifflinburg",
    "sg:classifiers":[
        {
            "category":"Manufacturing",
            "subcategory":"Buildings",
            "type":"Manufacturing & Wholesale Goods"
        }
    ],
    "sg:phone":"+1 570 966 1053",
    "sg:postcode":"17844",
    "sg:province":"PA",
    "sg:tags":[
        "mobile",
        "home"
    ],
    "sg:website":"www.ritz-craft.com",
    "wof:name":"Ritz-Craft Corp Of Penna Inc",
    "wof:placetype":"venue"
},
  "geometry": {"coordinates":[-77.058836,40.915233],"type":"Point"}
}