{
  "type": "Feature",
  "properties": {
    "iso:country":"US",
    "sg:address":"131 Verlinden Dr",
    "sg:city":"Monroeville",
    "sg:classifiers":[
        {
            "category":"Wholesale",
            "subcategory":"Electrical",
            "type":"Manufacturing & Wholesale Goods"
        }
    ],
    "sg:phone":"+1   ",
    "sg:postcode":"15146",
    "sg:province":"PA",
    "sg:tags":[
        "equipment",
        "establishment"
    ],
    "wof:name":"Apex Products Co Inc",
    "wof:placetype":"venue"
},
  "geometry": {"coordinates":[-79.709976,40.446344],"type":"Point"}
}