{
  "type": "Feature",
  "properties": {
    "iso:country":"US",
    "sg:address":"23 E Eagle Rd",
    "sg:city":"Havertown",
    "sg:classifiers":[
        {
            "category":"Shopping",
            "subcategory":"Jewelry",
            "type":"Retail Goods"
        }
    ],
    "sg:phone":"+1 610 446 0767",
    "sg:postcode":"19083",
    "sg:province":"PA",
    "sg:tags":[
        "jeweler"
    ],
    "wof:name":"Vinci Brothers",
    "wof:placetype":"venue"
},
  "geometry": {"coordinates":[-75.30990199999999,39.988544],"type":"Point"}
}