{
  "type": "Feature",
  "properties": {
    "iso:country":"US",
    "sg:address":"723 Ekastown Rd",
    "sg:city":"Sarver",
    "sg:classifiers":[
        {
            "category":"Professional",
            "subcategory":"Engineering",
            "type":"Services"
        }
    ],
    "sg:phone":"+1   ",
    "sg:postcode":"16055",
    "sg:province":"PA",
    "wof:name":"John M Saban",
    "wof:placetype":"venue"
},
  "geometry": {"coordinates":[-79.778316,40.714067],"type":"Point"}
}