{
  "type": "Feature",
  "properties": {
    "addr:full":"102 Ohare Rd Canonsburg PA 15317",
    "addr:housenumber":"102",
    "addr:postcode":"15317",
    "addr:street":"Ohare Rd",
    "iso:country":"US",
    "sg:address":"102 Ohare Rd",
    "sg:city":"Canonsburg",
    "sg:classifiers":[
        {
            "category":"Marine",
            "type":"Transportation"
        }
    ],
    "sg:phone":"+1   ",
    "sg:postcode":"15317",
    "sg:province":"PA",
    "sg:tags":[
        "water",
        "transport"
    ],
    "wof:name":"K & S Water Service",
    "wof:placetype":"venue"
},
  "geometry": {"coordinates":[-80.207168,40.289992],"type":"Point"}
}