{
  "type": "Feature",
  "properties": {
    "iso:country":"US",
    "sg:address":"5 Windsor Ave",
    "sg:city":"Upper Darby",
    "sg:classifiers":[
        {
            "category":"Health Services",
            "subcategory":"Nursing And Care Facility",
            "type":"Services"
        }
    ],
    "sg:phone":"+1 610 853 6798",
    "sg:postcode":"19082",
    "sg:province":"PA",
    "sg:tags":[
        "skilled"
    ],
    "sg:website":"www.chchomecare.com",
    "wof:name":"Continuous Home Care Inc",
    "wof:placetype":"venue"
},
  "geometry": {"coordinates":[-75.283028,39.964423],"type":"Point"}
}