{
  "type": "Feature",
  "properties": {
    "iso:country":"US",
    "sg:address":"97 N 2nd St",
    "sg:city":"Indiana",
    "sg:classifiers":[
        {
            "category":"Retail",
            "subcategory":"Auto Repair",
            "type":"Services"
        }
    ],
    "sg:phone":"+1   ",
    "sg:postcode":"15701",
    "sg:province":"PA",
    "sg:tags":[
        "body"
    ],
    "wof:name":"Colonial Motor Mart Body Shop",
    "wof:placetype":"venue"
},
  "geometry": {"coordinates":[-79.14062699999999,40.623731],"type":"Point"}
}