{
  "type": "Feature",
  "properties": {
    "addr:full":"119 Sinking Creek Rd Spring Mills PA 16875",
    "addr:housenumber":"119",
    "addr:postcode":"16875",
    "addr:street":"Sinking Creek Rd",
    "iso:country":"US",
    "sg:address":"119 Sinking Creek Rd",
    "sg:city":"Spring Mills",
    "sg:classifiers":[
        {
            "category":"Professional",
            "subcategory":"Management & Consulting",
            "type":"Services"
        }
    ],
    "sg:phone":"+1 814 364 2399",
    "sg:postcode":"16875",
    "sg:province":"PA",
    "sg:tags":[
        "consultant",
        "educational"
    ],
    "wof:name":"Adventure Based Consulting",
    "wof:placetype":"venue"
},
  "geometry": {"coordinates":[-77.64587299999999,40.820799],"type":"Point"}
}