{
  "type": "Feature",
  "properties": {
    "iso:country":"US",
    "sg:address":"800 N 4th Ave",
    "sg:city":"Altoona",
    "sg:classifiers":[
        {
            "category":"Restaurant",
            "type":"Food & Drink"
        }
    ],
    "sg:phone":"+1 814 942 2828",
    "sg:postcode":"16601",
    "sg:province":"PA",
    "sg:tags":[
        "pizza"
    ],
    "wof:name":"Pal-Mino's Pizza",
    "wof:placetype":"venue"
},
  "geometry": {"coordinates":[-78.379785,40.540276],"type":"Point"}
}