{
  "type": "Feature",
  "properties": {
    "iso:country":"US",
    "sg:address":"3549 Menoher Blvd",
    "sg:city":"Johnstown",
    "sg:classifiers":[
        {
            "category":"Professional",
            "subcategory":"Management & Consulting",
            "type":"Services"
        }
    ],
    "sg:phone":"+1 814 255 6099",
    "sg:postcode":"15905",
    "sg:province":"PA",
    "sg:tags":[
        "food",
        "consultant",
        "facility"
    ],
    "wof:name":"Subway Development Enterprises, Inc",
    "wof:placetype":"venue"
},
  "geometry": {"coordinates":[-79.013549,40.299809],"type":"Point"}
}