{
  "type": "Feature",
  "properties": {
    "iso:country":"US",
    "sg:address":"585 W Pike St",
    "sg:city":"Canonsburg",
    "sg:classifiers":[
        {
            "category":"Restaurant",
            "type":"Food & Drink"
        }
    ],
    "sg:phone":"+1   ",
    "sg:postcode":"15317",
    "sg:province":"PA",
    "sg:tags":[
        "eating"
    ],
    "wof:name":"Gabbys Pizza & Beer",
    "wof:placetype":"venue"
},
  "geometry": {"coordinates":[-80.206069,40.255356],"type":"Point"}
}