{
  "type": "Feature",
  "properties": {
    "addr:full":"4715 Mercer St Philadelphia PA 19137",
    "addr:housenumber":"4715",
    "addr:postcode":"19137",
    "addr:street":"Mercer St",
    "iso:country":"US",
    "sg:address":"4715 Mercer St",
    "sg:city":"Philadelphia",
    "sg:classifiers":[
        {
            "category":"Organizations",
            "subcategory":"Community Association",
            "type":"Services"
        }
    ],
    "sg:phone":"+1   ",
    "sg:postcode":"19137",
    "sg:province":"PA",
    "wof:name":"Philadelphia Vietnam Veterans",
    "wof:placetype":"venue"
},
  "geometry": {"coordinates":[-75.068089,40.003813],"type":"Point"}
}