{
  "type": "Feature",
  "properties": {
    "iso:country":"US",
    "sg:address":"598 Church Rd",
    "sg:city":"Northampton",
    "sg:classifiers":[
        {
            "category":"Personal",
            "subcategory":"Hair Removal",
            "type":"Services"
        }
    ],
    "sg:phone":"+1 610 261 2690",
    "sg:postcode":"18067",
    "sg:province":"PA",
    "sg:website":"www.baresensationelectrolysis.com",
    "wof:name":"Bare Sensation Electrolysis",
    "wof:placetype":"venue"
},
  "geometry": {"coordinates":[-75.501434,40.732294],"type":"Point"}
}