{
  "type": "Feature",
  "properties": {
    "addr:full":"2 Old Mill Rd Dillsburg PA 17019",
    "addr:housenumber":"2",
    "addr:postcode":"17019",
    "addr:street":"Old Mill Rd",
    "iso:country":"US",
    "sg:address":"2 Old Mill Rd",
    "sg:city":"Dillsburg",
    "sg:classifiers":[
        {
            "category":"Fast Food",
            "type":"Food & Drink"
        },
        {
            "category":"Restaurant",
            "type":"Food & Drink"
        }
    ],
    "sg:phone":"+1 717 432 8933",
    "sg:postcode":"17019",
    "sg:province":"PA",
    "sg:tags":[
        "american",
        "hot",
        "hamburger",
        "dog"
    ],
    "sg:website":"http://www.wendys.com",
    "wof:name":"Wendy's",
    "wof:placetype":"venue"
},
  "geometry": {"coordinates":[-77.03949,40.116669],"type":"Point"}
}