{
  "type": "Feature",
  "properties": {
    "addr:full":"83 Maffett St Wilkes Barre PA 18702",
    "addr:housenumber":"83",
    "addr:postcode":"18702",
    "addr:street":"Maffett St",
    "iso:country":"US",
    "sg:address":"83 Maffett St",
    "sg:city":"Wilkes Barre",
    "sg:classifiers":[
        {
            "category":"Building & Trades",
            "subcategory":"Construction",
            "type":"Services"
        }
    ],
    "sg:phone":"+1   ",
    "sg:postcode":"18702",
    "sg:province":"PA",
    "sg:tags":[
        "house"
    ],
    "wof:name":"Ciavarella Construction",
    "wof:placetype":"venue"
},
  "geometry": {"coordinates":[-75.907601,41.245533],"type":"Point"}
}