{
  "type": "Feature",
  "properties": {
    "iso:country":"US",
    "sg:address":"232 Horner St",
    "sg:city":"Johnstown",
    "sg:classifiers":[
        {
            "category":"Autos & Motor Vehicles",
            "subcategory":"Automobile Sales",
            "type":"Retail Goods"
        }
    ],
    "sg:phone":"+1 814 535 3521",
    "sg:postcode":"15902",
    "sg:province":"PA",
    "sg:tags":[
        "car",
        "dealer"
    ],
    "sg:website":"www.team.com",
    "wof:name":"Team Cheverolet",
    "wof:placetype":"venue"
},
  "geometry": {"coordinates":[-78.912408,40.31571],"type":"Point"}
}