{
  "type": "Feature",
  "properties": {
    "iso:country":"US",
    "sg:address":"8701 W Chester Pike",
    "sg:city":"Upper Darby",
    "sg:classifiers":[
        {
            "category":"Professional",
            "subcategory":"Accounting & Tax Preparation",
            "type":"Services"
        }
    ],
    "sg:phone":"+1 610 734 0610",
    "sg:postcode":"19082",
    "sg:province":"PA",
    "sg:tags":[
        "billing"
    ],
    "wof:name":"Consolidated Billing Svc",
    "wof:placetype":"venue"
},
  "geometry": {"coordinates":[-75.286608,39.966948],"type":"Point"}
}