{
  "type": "Feature",
  "properties": {
    "addr:full":"1201 Grampian Blvd Williamsport PA 17701",
    "addr:housenumber":"1201",
    "addr:postcode":"17701",
    "addr:street":"Grampian Blvd",
    "iso:country":"US",
    "sg:address":"1201 Grampian Blvd",
    "sg:city":"Williamsport",
    "sg:classifiers":[
        {
            "category":"Health Services",
            "subcategory":"Doctor",
            "type":"Services"
        }
    ],
    "sg:phone":"+1   ",
    "sg:postcode":"17701",
    "sg:province":"PA",
    "sg:tags":[
        "medical"
    ],
    "wof:name":"Alexander R Nesbitt MD",
    "wof:placetype":"venue"
},
  "geometry": {"coordinates":[-76.985736,41.260754],"type":"Point"}
}