{
  "type": "Feature",
  "properties": {
    "addr:full":"844 4th Ave Coraopolis PA 15108",
    "addr:housenumber":"844",
    "addr:postcode":"15108",
    "addr:street":"4Th Ave",
    "iso:country":"US",
    "sg:address":"844 4th Ave",
    "sg:city":"Coraopolis",
    "sg:classifiers":[
        {
            "category":"Real Estate",
            "subcategory":"Real Estate Agent",
            "type":"Services"
        }
    ],
    "sg:phone":"+1   ",
    "sg:postcode":"15108",
    "sg:province":"PA",
    "wof:name":"Basic Affordable Housing",
    "wof:placetype":"venue"
},
  "geometry": {"coordinates":[-80.169825,40.520692],"type":"Point"}
}