{
  "type": "Feature",
  "properties": {
    "iso:country":"US",
    "sg:address":"505 Beacon Hill Ln",
    "sg:city":"Plymouth Meeting",
    "sg:classifiers":[
        {
            "category":"Recreation",
            "type":"Entertainment"
        }
    ],
    "sg:phone":"+1   ",
    "sg:postcode":"19462",
    "sg:province":"PA",
    "wof:name":"Academy of Self Defense I",
    "wof:placetype":"venue"
},
  "geometry": {"coordinates":[-75.287643,40.133023],"type":"Point"}
}