{
  "type": "Feature",
  "properties": {
    "addr:full":"820 Turnpike Ave Clearfield PA 16830",
    "addr:housenumber":"820",
    "addr:postcode":"16830",
    "addr:street":"Turnpike Ave",
    "iso:country":"US",
    "sg:address":"820 Turnpike Ave",
    "sg:city":"Clearfield",
    "sg:classifiers":[
        {
            "category":"Health Services",
            "subcategory":"Doctor",
            "type":"Services"
        }
    ],
    "sg:phone":"+1   ",
    "sg:postcode":"16830",
    "sg:province":"PA",
    "sg:tags":[
        "medical"
    ],
    "wof:name":"Bruno J Romeo MD",
    "wof:placetype":"venue"
},
  "geometry": {"coordinates":[-78.450039,41.032942],"type":"Point"}
}