{
  "type": "Feature",
  "properties": {
    "iso:country":"US",
    "sg:address":"403 E Ohio St",
    "sg:city":"Pittsburgh",
    "sg:classifiers":[
        {
            "category":"Restaurant",
            "type":"Food & Drink"
        }
    ],
    "sg:phone":"+1 412 224 2273",
    "sg:postcode":"15212",
    "sg:province":"PA",
    "sg:website":"parkhousepgh.com/",
    "wof:name":"Park House",
    "wof:placetype":"venue"
},
  "geometry": {"coordinates":[-80.001402,40.45314],"type":"Point"}
}