{
  "type": "Feature",
  "properties": {
    "iso:country":"US",
    "sg:address":"2259 Pinehurst Rd",
    "sg:city":"Bethlehem",
    "sg:classifiers":[
        {
            "category":"Building & Trades",
            "subcategory":"Construction",
            "type":"Services"
        }
    ],
    "sg:phone":"+1 610 868 4175",
    "sg:postcode":"18018",
    "sg:province":"PA",
    "sg:tags":[
        "house"
    ],
    "wof:name":"Haas Contracting",
    "wof:placetype":"venue"
},
  "geometry": {"coordinates":[-75.42282899999999,40.635629],"type":"Point"}
}