{
  "type": "Feature",
  "properties": {
    "iso:country":"US",
    "sg:address":"7902 Cedarbrook Ave",
    "sg:city":"Philadelphia",
    "sg:classifiers":[
        {
            "category":"Professional",
            "type":"Services"
        }
    ],
    "sg:phone":"+1   ",
    "sg:postcode":"19150",
    "sg:province":"PA",
    "wof:name":"Cedarbrook Home Remdeling",
    "wof:placetype":"venue"
},
  "geometry": {"coordinates":[-75.16290600000001,40.075659],"type":"Point"}
}