{
  "type": "Feature",
  "properties": {
    "iso:country":"US",
    "sg:address":"451 N 3rd St",
    "sg:city":"Wrightsville",
    "sg:classifiers":[
        {
            "category":"Shopping",
            "type":"Retail Goods"
        }
    ],
    "sg:phone":"+1   ",
    "sg:postcode":"17368",
    "sg:province":"PA",
    "sg:tags":[
        "merchandise"
    ],
    "wof:name":"George M Scantling",
    "wof:placetype":"venue"
},
  "geometry": {"coordinates":[-76.533293,40.029035],"type":"Point"}
}