{
  "type": "Feature",
  "properties": {
    "iso:country":"US",
    "sg:address":"414 Allegheny River Blvd",
    "sg:city":"Oakmont",
    "sg:classifiers":[
        {
            "category":"Health Services",
            "subcategory":"Health Practitioner",
            "type":"Services"
        }
    ],
    "sg:phone":"+1 412 828 0765",
    "sg:postcode":"15139",
    "sg:province":"PA",
    "sg:tags":[
        "psychologist"
    ],
    "wof:name":"Pete De Louis",
    "wof:placetype":"venue"
},
  "geometry": {"coordinates":[-79.84272,40.517347],"type":"Point"}
}