{
  "type": "Feature",
  "properties": {
    "iso:country":"US",
    "sg:address":"207 Mc Ewen Rd",
    "sg:city":"Mercer",
    "sg:classifiers":[
        {
            "category":"Social Services",
            "subcategory":"Child Care",
            "type":"Services"
        }
    ],
    "sg:phone":"+1 724 475 4754",
    "sg:postcode":"16137",
    "sg:province":"PA",
    "wof:name":"Hazelet Group Day Care Home",
    "wof:placetype":"venue"
},
  "geometry": {"coordinates":[-80.210663,41.275053],"type":"Point"}
}