{
  "type": "Feature",
  "properties": {
    "iso:country":"US",
    "sg:address":"600 Highland St",
    "sg:city":"Harrisburg",
    "sg:classifiers":[
        {
            "category":"Organizations",
            "subcategory":"Religious Organization",
            "type":"Services"
        }
    ],
    "sg:phone":"+1 717 939 7576",
    "sg:postcode":"17113",
    "sg:province":"PA",
    "sg:tags":[
        "place",
        "worship",
        "church"
    ],
    "wof:name":"Enhaut Bible Church",
    "wof:placetype":"venue"
},
  "geometry": {"coordinates":[-76.824799,40.2341],"type":"Point"}
}