{
  "type": "Feature",
  "properties": {
    "iso:country":"US",
    "sg:address":"251 Clare Dr",
    "sg:city":"Canonsburg",
    "sg:classifiers":[
        {
            "category":"Building & Trades",
            "subcategory":"Plumbing",
            "type":"Services"
        }
    ],
    "sg:phone":"+1 724 745 0484",
    "sg:postcode":"15317",
    "sg:province":"PA",
    "sg:tags":[
        "conditioning",
        "air",
        "system",
        "contractor"
    ],
    "wof:name":"R C Heating & Cooling",
    "wof:placetype":"venue"
},
  "geometry": {"coordinates":[-80.167942,40.257667],"type":"Point"}
}