{
  "type": "Feature",
  "properties": {
    "addr:full":"3715 Falkstone Dr Mechanicsburg PA 17050",
    "addr:housenumber":"3715",
    "addr:postcode":"17050",
    "addr:street":"Falkstone Dr",
    "iso:country":"US",
    "sg:address":"3715 Falkstone Dr",
    "sg:city":"Mechanicsburg",
    "sg:classifiers":[
        {
            "category":"Banks & Credit Unions",
            "subcategory":"Financial Services",
            "type":"Services"
        }
    ],
    "sg:phone":"+1 717 732 9440",
    "sg:postcode":"17050",
    "sg:province":"PA",
    "sg:tags":[
        "broker",
        "mortgage"
    ],
    "wof:name":"Haven Mortgage Services",
    "wof:placetype":"venue"
},
  "geometry": {"coordinates":[-76.95970199999999,40.275002],"type":"Point"}
}