{
  "type": "Feature",
  "properties": {
    "iso:country":"US",
    "sg:address":"129 Kensington Ln",
    "sg:city":"Oxford",
    "sg:classifiers":[
        {
            "category":"Health Services",
            "subcategory":"Doctor",
            "type":"Services"
        }
    ],
    "sg:phone":"+1 610 998 2553",
    "sg:postcode":"19363",
    "sg:province":"PA",
    "sg:tags":[
        "physician",
        "surgeon"
    ],
    "wof:name":"Charles E Alexander MD",
    "wof:placetype":"venue"
},
  "geometry": {"coordinates":[-75.987492,39.786769],"type":"Point"}
}