{
  "type": "Feature",
  "properties": {
    "addr:full":"929 S Hall St Allentown PA 18103",
    "addr:housenumber":"929",
    "addr:postcode":"18103",
    "addr:street":"S Hall St",
    "iso:country":"US",
    "sg:address":"929 S Hall St",
    "sg:city":"Allentown",
    "sg:classifiers":[
        {
            "category":"Autos & Motor Vehicles",
            "subcategory":"Boat Sales",
            "type":"Retail Goods"
        }
    ],
    "sg:phone":"+1 610 435 8517",
    "sg:postcode":"18103",
    "sg:province":"PA",
    "sg:tags":[
        "top",
        "upholstery",
        "cover"
    ],
    "wof:name":"Allen Canvas Co",
    "wof:placetype":"venue"
},
  "geometry": {"coordinates":[-75.467249,40.590963],"type":"Point"}
}