{
  "type": "Feature",
  "properties": {
    "iso:country":"US",
    "sg:address":"207 Mount Joy Rd",
    "sg:city":"Clearfield",
    "sg:classifiers":[
        {
            "category":"Autos & Motor Vehicles",
            "subcategory":"Automobile Sales",
            "type":"Retail Goods"
        }
    ],
    "sg:phone":"+1   ",
    "sg:postcode":"16830",
    "sg:province":"PA",
    "sg:tags":[
        "used"
    ],
    "wof:name":"American Classics",
    "wof:placetype":"venue"
},
  "geometry": {"coordinates":[-78.438861,41.032328],"type":"Point"}
}