{
  "type": "Feature",
  "properties": {
    "addr:full":"255 S Mennonite Rd Collegeville PA 19426",
    "addr:housenumber":"255",
    "addr:postcode":"19426",
    "addr:street":"Mennonite Rd",
    "iso:country":"US",
    "sg:address":"255 S Mennonite Rd",
    "sg:city":"Collegeville",
    "sg:classifiers":[
        {
            "category":"Building & Trades",
            "subcategory":"Plumbing",
            "type":"Services"
        }
    ],
    "sg:phone":"+1 610 489 7516",
    "sg:postcode":"19426",
    "sg:province":"PA",
    "sg:tags":[
        "plumbing",
        "contractor"
    ],
    "wof:name":"K and E Mechanical Contracting",
    "wof:placetype":"venue"
},
  "geometry": {"coordinates":[-75.479902,40.171555],"type":"Point"}
}