{
  "type": "Feature",
  "properties": {
    "iso:country":"US",
    "sg:address":"518 W Grant St",
    "sg:city":"Lancaster",
    "sg:classifiers":[
        {
            "category":"Building & Trades",
            "subcategory":"Electrical",
            "type":"Services"
        }
    ],
    "sg:phone":"+1 717 207 0307",
    "sg:postcode":"17603",
    "sg:province":"PA",
    "sg:tags":[
        "electric",
        "contractor"
    ],
    "wof:name":"Red Rose Construction",
    "wof:placetype":"venue"
},
  "geometry": {"coordinates":[-76.315979,40.037602],"type":"Point"}
}