{
  "type": "Feature",
  "properties": {
    "addr:full":"479 Slocum Ave Exeter PA 18643",
    "addr:housenumber":"479",
    "addr:postcode":"18643",
    "addr:street":"Slocum Ave",
    "iso:country":"US",
    "sg:address":"479 Slocum Ave",
    "sg:city":"Exeter",
    "sg:classifiers":[
        {
            "category":"Personal",
            "subcategory":"Beauty Salon",
            "type":"Services"
        }
    ],
    "sg:phone":"+1 570 693 1109",
    "sg:postcode":"18643",
    "sg:province":"PA",
    "sg:tags":[
        "manicuring"
    ],
    "wof:name":"Garden Of Eden Nail Salon",
    "wof:placetype":"venue"
},
  "geometry": {"coordinates":[-75.82468299999999,41.334337],"type":"Point"}
}