{
  "type": "Feature",
  "properties": {
    "iso:country":"US",
    "sg:address":"10 Fruit Ave",
    "sg:city":"Farrell",
    "sg:classifiers":[
        {
            "category":"Education",
            "subcategory":"Vocational School",
            "type":"Public Place"
        }
    ],
    "sg:phone":"+1 724 347 9850",
    "sg:postcode":"16121",
    "sg:province":"PA",
    "sg:tags":[
        "technical",
        "trade"
    ],
    "wof:name":"CNC Tek",
    "wof:placetype":"venue"
},
  "geometry": {"coordinates":[-80.50030599999999,41.203796],"type":"Point"}
}