{
  "type": "Feature",
  "properties": {
    "iso:country":"US",
    "sg:address":"1914 Mosteller Rd",
    "sg:city":"Montoursville",
    "sg:classifiers":[
        {
            "category":"Building & Trades",
            "subcategory":"Construction",
            "type":"Services"
        }
    ],
    "sg:phone":"+1 570 435 0332",
    "sg:postcode":"17754",
    "sg:province":"PA",
    "sg:tags":[
        "excavation",
        "contractor"
    ],
    "wof:name":"Woodhead Inc",
    "wof:placetype":"venue"
},
  "geometry": {"coordinates":[-76.93333199999999,41.322299],"type":"Point"}
}