{
  "type": "Feature",
  "properties": {
    "addr:full":"107 W Nittany Ave State College PA 16801",
    "addr:housenumber":"107",
    "addr:postcode":"16801",
    "addr:street":"W Nittany Ave",
    "iso:country":"US",
    "sg:address":"107 W Nittany Ave",
    "sg:city":"State College",
    "sg:classifiers":[
        {
            "category":"Retail",
            "subcategory":"Self-service Laundry",
            "type":"Services"
        }
    ],
    "sg:phone":"+1 814 237 9390",
    "sg:postcode":"16801",
    "sg:province":"PA",
    "wof:name":"Laundromat One Eleven",
    "wof:placetype":"venue"
},
  "geometry": {"coordinates":[-77.857704,40.791472],"type":"Point"}
}