{
  "type": "Feature",
  "properties": {
    "iso:country":"US",
    "sg:address":"1608 Walnut St",
    "sg:city":"Philadelphia",
    "sg:classifiers":[
        {
            "category":"Professional",
            "type":"Services"
        }
    ],
    "sg:phone":"+1 215 546 4950",
    "sg:postcode":"19103",
    "sg:province":"PA",
    "sg:tags":[
        "establishment"
    ],
    "wof:name":"LECG LLC",
    "wof:placetype":"venue"
},
  "geometry": {"coordinates":[-75.169015,39.949853],"type":"Point"}
}