{
  "type": "Feature",
  "properties": {
    "iso:country":"US",
    "sg:address":"15 N Washington St",
    "sg:city":"Wilkes Barre",
    "sg:classifiers":[
        {
            "category":"Government",
            "subcategory":"Police Station",
            "type":"Public Place"
        }
    ],
    "sg:phone":"+1 570 826 8109",
    "sg:postcode":"18701",
    "sg:province":"PA",
    "sg:tags":[
        "department"
    ],
    "wof:name":"Wilkes Barre Police-Traffic",
    "wof:placetype":"venue"
},
  "geometry": {"coordinates":[-75.880062,41.244952],"type":"Point"}
}