{
  "type": "Feature",
  "properties": {
    "addr:full":"2279 Main St Homestead PA 15120",
    "addr:housenumber":"2279",
    "addr:postcode":"15120",
    "addr:street":"Main St",
    "iso:country":"US",
    "sg:address":"2279 Main St",
    "sg:city":"Homestead",
    "sg:classifiers":[
        {
            "category":"Health Services",
            "subcategory":"Health Practitioner",
            "type":"Services"
        }
    ],
    "sg:phone":"+1   ",
    "sg:postcode":"15120",
    "sg:province":"PA",
    "wof:name":"Intergrtive Rhbilitation Assoc",
    "wof:placetype":"venue"
},
  "geometry": {"coordinates":[-79.900609,40.396914],"type":"Point"}
}