{
  "type": "Feature",
  "properties": {
    "addr:full":"7420 Haverford Ave Philadelphia PA 19151",
    "addr:housenumber":"7420",
    "addr:postcode":"19151",
    "addr:street":"Haverford Ave",
    "iso:country":"US",
    "sg:address":"7420 Haverford Ave",
    "sg:city":"Philadelphia",
    "sg:classifiers":[
        {
            "category":"Personal",
            "subcategory":"Beauty Salon",
            "type":"Services"
        }
    ],
    "sg:phone":"+1 215 477 7699",
    "sg:postcode":"19151",
    "sg:province":"PA",
    "wof:name":"Sheer Joy",
    "wof:placetype":"venue"
},
  "geometry": {"coordinates":[-75.264464,39.976512],"type":"Point"}
}