{
  "type": "Feature",
  "properties": {
    "iso:country":"US",
    "sg:address":"29 Main St",
    "sg:city":"Ripley",
    "sg:classifiers":[
        {
            "category":"Farming",
            "subcategory":"Vineyard",
            "type":"Manufacturing & Wholesale Goods"
        }
    ],
    "sg:phone":"+1 716 736 3782",
    "sg:postcode":"14775",
    "sg:province":"NY",
    "sg:tags":[
        "grape"
    ],
    "wof:name":"Robert Youngs",
    "wof:placetype":"venue"
},
  "geometry": {"coordinates":[-79.703953,42.269726],"type":"Point"}
}