{
  "type": "Feature",
  "properties": {
    "iso:country":"US",
    "sg:address":"330 Phillips St",
    "sg:city":"Wilkes Barre",
    "sg:classifiers":[
        {
            "category":"Personal",
            "subcategory":"Beauty Salon",
            "type":"Services"
        }
    ],
    "sg:phone":"+1   ",
    "sg:postcode":"18706",
    "sg:province":"PA",
    "sg:tags":[
        "shop"
    ],
    "wof:name":"Marias Magic Moments",
    "wof:placetype":"venue"
},
  "geometry": {"coordinates":[-75.933513,41.232409],"type":"Point"}
}