{
  "type": "Feature",
  "properties": {
    "iso:country":"US",
    "sg:address":"244 W Franklin St",
    "sg:city":"Morrisville",
    "sg:classifiers":[
        {
            "category":"Building & Trades",
            "subcategory":"Construction",
            "type":"Services"
        }
    ],
    "sg:phone":"+1   ",
    "sg:postcode":"19067",
    "sg:province":"PA",
    "sg:tags":[
        "house"
    ],
    "wof:name":"Kmj Contractors",
    "wof:placetype":"venue"
},
  "geometry": {"coordinates":[-74.78322900000001,40.211385],"type":"Point"}
}