{
  "type": "Feature",
  "properties": {
    "iso:country":"US",
    "sg:address":"173 Main St",
    "sg:city":"Emmaus",
    "sg:classifiers":[
        {
            "category":"Shopping",
            "subcategory":"Gifts & Souvenirs",
            "type":"Retail Goods"
        }
    ],
    "sg:phone":"+1 610 966 5116",
    "sg:postcode":"18049",
    "sg:province":"PA",
    "wof:name":"Patches",
    "wof:placetype":"venue"
},
  "geometry": {"coordinates":[-75.488933,40.537345],"type":"Point"}
}