{
  "type": "Feature",
  "properties": {
    "iso:country":"US",
    "sg:address":"1238 Mount Joy Rd",
    "sg:city":"Manheim",
    "sg:classifiers":[
        {
            "category":"Building & Trades",
            "subcategory":"Construction",
            "type":"Services"
        }
    ],
    "sg:phone":"+1 717 665 2418",
    "sg:postcode":"17545",
    "sg:province":"PA",
    "sg:tags":[
        "home",
        "remodeling",
        "new",
        "contractor"
    ],
    "wof:name":"Martin Melvin J Contractor",
    "wof:placetype":"venue"
},
  "geometry": {"coordinates":[-76.424015,40.141494],"type":"Point"}
}