{
  "type": "Feature",
  "properties": {
    "iso:country":"US",
    "sg:address":"204 Chambersburg St",
    "sg:city":"Gettysburg",
    "sg:classifiers":[
        {
            "category":"Real Estate",
            "subcategory":"Real Estate Services",
            "type":"Services"
        },
        {
            "category":"Real Estate",
            "subcategory":"Real Estate Agent",
            "type":"Services"
        }
    ],
    "sg:phone":"+1 717 334 9132",
    "sg:postcode":"17325",
    "sg:province":"PA",
    "sg:tags":[
        "management"
    ],
    "wof:name":"Keller Williams Keystone Realty",
    "wof:placetype":"venue"
},
  "geometry": {"coordinates":[-77.23499200000001,39.830891],"type":"Point"}
}