{
  "type": "Feature",
  "properties": {
    "addr:full":"235 Fairview Ave Souderton PA 18964",
    "addr:housenumber":"235",
    "addr:postcode":"18964",
    "addr:street":"Fairview Ave",
    "iso:country":"US",
    "sg:address":"235 Fairview Ave",
    "sg:city":"Souderton",
    "sg:classifiers":[
        {
            "category":"Retail",
            "subcategory":"Repair Shop",
            "type":"Services"
        }
    ],
    "sg:phone":"+1   ",
    "sg:postcode":"18964",
    "sg:province":"PA",
    "wof:name":"J & B Pallet Inc",
    "wof:placetype":"venue"
},
  "geometry": {"coordinates":[-75.322091,40.315683],"type":"Point"}
}