{
  "type": "Feature",
  "properties": {
    "iso:country":"US",
    "sg:address":"290 N Riverside Dr",
    "sg:city":"Easton",
    "sg:classifiers":[
        {
            "category":"Retail",
            "subcategory":"Auto Repair",
            "type":"Services"
        }
    ],
    "sg:phone":"+1 610 252 6653",
    "sg:postcode":"18042",
    "sg:province":"PA",
    "sg:tags":[
        "repairing",
        "transmission",
        "general",
        "automobile"
    ],
    "wof:name":"T & H Automotive Inc",
    "wof:placetype":"venue"
},
  "geometry": {"coordinates":[-75.205603,40.696064],"type":"Point"}
}