{
  "type": "Feature",
  "properties": {
    "addr:full":"1501 Easton Rd Roslyn PA 19001",
    "addr:housenumber":"1501",
    "addr:postcode":"19001",
    "addr:street":"Easton Rd",
    "iso:country":"US",
    "sg:address":"1501 Easton Rd",
    "sg:city":"Roslyn",
    "sg:classifiers":[
        {
            "category":"Retail",
            "subcategory":"Auto Repair",
            "type":"Services"
        }
    ],
    "sg:phone":"+1 215 657 2249",
    "sg:postcode":"19001",
    "sg:province":"PA",
    "sg:tags":[
        "automobile",
        "rustproofing",
        "undercoating"
    ],
    "wof:name":"Xtreme Auto Interiors",
    "wof:placetype":"venue"
},
  "geometry": {"coordinates":[-75.127409,40.130759],"type":"Point"}
}