{
  "type": "Feature",
  "properties": {
    "iso:country":"US",
    "sg:address":"3801 Filbert St",
    "sg:city":"Philadelphia",
    "sg:classifiers":[
        {
            "category":"Health Services",
            "subcategory":"Doctor",
            "type":"Services"
        }
    ],
    "sg:phone":"+1   ",
    "sg:postcode":"19104",
    "sg:province":"PA",
    "sg:tags":[
        "medical"
    ],
    "wof:name":"Edward G Reis MD",
    "wof:placetype":"venue"
},
  "geometry": {"coordinates":[-75.198712,39.957512],"type":"Point"}
}