{
  "type": "Feature",
  "properties": {
    "addr:full":"141 Rte 908 Exd Tarentum PA 15084",
    "addr:housenumber":"141",
    "addr:postcode":"15084",
    "addr:street":"Rte 908 Exd",
    "iso:country":"US",
    "sg:address":"141 Rte 908 Exd",
    "sg:city":"Tarentum",
    "sg:classifiers":[
        {
            "category":"Retail",
            "subcategory":"Auto Repair",
            "type":"Services"
        }
    ],
    "sg:phone":"+1   ",
    "sg:postcode":"15084",
    "sg:province":"PA",
    "sg:tags":[
        "transmission"
    ],
    "wof:name":"AAMCO Transmissions",
    "wof:placetype":"venue"
},
  "geometry": {"coordinates":[-79.80227600000001,40.643909],"type":"Point"}
}