{
  "type": "Feature",
  "properties": {
    "iso:country":"US",
    "sg:address":"2516 Mercer West Middlesex Rd",
    "sg:city":"West Middlesex",
    "sg:classifiers":[
        {
            "category":"Insurance",
            "subcategory":"Insurance Agent",
            "type":"Services"
        }
    ],
    "sg:phone":"+1   ",
    "sg:postcode":"16159",
    "sg:province":"PA",
    "wof:name":"Advanced Insur Clims Rstration",
    "wof:placetype":"venue"
},
  "geometry": {"coordinates":[-80.406014,41.18776],"type":"Point"}
}