{
  "type": "Feature",
  "properties": {
    "iso:country":"US",
    "sg:address":"375 S Belmont St",
    "sg:city":"York",
    "sg:classifiers":[
        {
            "category":"Food & Beverages",
            "subcategory":"Bakery",
            "type":"Retail Goods"
        }
    ],
    "sg:phone":"+1 717 848 6630",
    "sg:postcode":"17403",
    "sg:province":"PA",
    "sg:tags":[
        "baker"
    ],
    "wof:name":"Stauffer's Cookie Outlet",
    "wof:placetype":"venue"
},
  "geometry": {"coordinates":[-76.69395900000001,39.968165],"type":"Point"}
}