{
  "type": "Feature",
  "properties": {
    "iso:country":"US",
    "sg:address":"1402 W Broad St",
    "sg:city":"Quakertown",
    "sg:classifiers":[
        {
            "category":"Health Services",
            "subcategory":"Doctor",
            "type":"Services"
        }
    ],
    "sg:phone":"+1 215 536 8133",
    "sg:postcode":"18951",
    "sg:province":"PA",
    "sg:tags":[
        "dentist"
    ],
    "wof:name":"Mark P Elstein DDS",
    "wof:placetype":"venue"
},
  "geometry": {"coordinates":[-75.35504899999999,40.443297],"type":"Point"}
}