{
  "type": "Feature",
  "properties": {
    "iso:country":"US",
    "sg:address":"1511 Kutchs Dr",
    "sg:city":"Somerset",
    "sg:classifiers":[
        {
            "category":"Shopping",
            "subcategory":"Gifts & Souvenirs",
            "type":"Retail Goods"
        }
    ],
    "sg:phone":"+1   ",
    "sg:postcode":"15501",
    "sg:province":"PA",
    "wof:name":"Crafty Gifts",
    "wof:placetype":"venue"
},
  "geometry": {"coordinates":[-79.089241,39.990207],"type":"Point"}
}