{
  "type": "Feature",
  "properties": {
    "addr:full":"2738 E Allegheny Ave Philadelphia PA 19134",
    "addr:housenumber":"2738",
    "addr:postcode":"19134",
    "addr:street":"E Allegheny Ave",
    "iso:country":"US",
    "sg:address":"2738 E Allegheny Ave",
    "sg:city":"Philadelphia",
    "sg:classifiers":[
        {
            "category":"Banks & Credit Unions",
            "subcategory":"Bank",
            "type":"Services"
        }
    ],
    "sg:phone":"+1 215 634 8816",
    "sg:postcode":"19134",
    "sg:province":"PA",
    "sg:tags":[
        "cashing",
        "photocopying",
        "exporter",
        "export",
        "check"
    ],
    "wof:name":"Kris Express Check Cashing",
    "wof:placetype":"venue"
},
  "geometry": {"coordinates":[-75.10151500000001,39.982952],"type":"Point"}
}