{
  "type": "Feature",
  "properties": {
    "iso:country":"US",
    "sg:address":"1500 Washington Rd",
    "sg:city":"Pittsburgh",
    "sg:classifiers":[
        {
            "category":"Restaurant",
            "type":"Food & Drink"
        }
    ],
    "sg:menulink":"http://www.allmenus.com/pa/mount-lebanon/27185-mark-pis-china-gate/menu/",
    "sg:phone":"+1 412 341 8890",
    "sg:postcode":"15228",
    "sg:province":"PA",
    "sg:tags":[
        "asian",
        "chinese"
    ],
    "wof:name":"Mark Pi's China Gate",
    "wof:placetype":"venue"
},
  "geometry": {"coordinates":[-80.050381,40.355923],"type":"Point"}
}