{
  "type": "Feature",
  "properties": {
    "iso:country":"US",
    "sg:address":"4617 Milnor St",
    "sg:city":"Philadelphia",
    "sg:classifiers":[
        {
            "category":"Manufacturing",
            "subcategory":"Tools & Machinery",
            "type":"Manufacturing & Wholesale Goods"
        }
    ],
    "sg:phone":"+1 215 289 3450",
    "sg:postcode":"19137",
    "sg:province":"PA",
    "sg:tags":[
        "machine",
        "shop"
    ],
    "sg:website":"www.labbmachine.com",
    "wof:name":"Wm J Labb Sons",
    "wof:placetype":"venue"
},
  "geometry": {"coordinates":[-75.07652,40.005455],"type":"Point"}
}