{
  "type": "Feature",
  "properties": {
    "iso:country":"US",
    "sg:address":"215 N 9th St",
    "sg:city":"Allentown",
    "sg:classifiers":[
        {
            "category":"Professional",
            "subcategory":"Lawyer & Legal Services",
            "type":"Services"
        }
    ],
    "sg:phone":"+1 610 435 3530",
    "sg:postcode":"18102",
    "sg:province":"PA",
    "wof:name":"Karess Martin J Atty",
    "wof:placetype":"venue"
},
  "geometry": {"coordinates":[-75.477097,40.604301],"type":"Point"}
}