{
  "type": "Feature",
  "properties": {
    "iso:country":"US",
    "sg:address":"13 W Trenton Ave",
    "sg:city":"Morrisville",
    "sg:classifiers":[
        {
            "category":"Shopping",
            "subcategory":"Pharmacy",
            "type":"Retail Goods"
        }
    ],
    "sg:phone":"+1   ",
    "sg:postcode":"19067",
    "sg:province":"PA",
    "sg:tags":[
        "drug",
        "store"
    ],
    "wof:name":"Rite Aid",
    "wof:placetype":"venue"
},
  "geometry": {"coordinates":[-74.786698,40.214726],"type":"Point"}
}