{
  "type": "Feature",
  "properties": {
    "addr:full":"254 Tucquan Glen Rd Holtwood PA 17532",
    "addr:housenumber":"254",
    "addr:postcode":"17532",
    "addr:street":"Tucquan Glen Rd",
    "iso:country":"US",
    "sg:address":"254 Tucquan Glen Rd",
    "sg:city":"Holtwood",
    "sg:classifiers":[
        {
            "category":"Manufacturing",
            "subcategory":"Buildings",
            "type":"Manufacturing & Wholesale Goods"
        },
        {
            "category":"Building & Trades",
            "subcategory":"Construction",
            "type":"Services"
        }
    ],
    "sg:phone":"+1 717 284 2254",
    "sg:postcode":"17532",
    "sg:province":"PA",
    "sg:tags":[
        "home",
        "builder",
        "contractor"
    ],
    "wof:name":"William S Royer",
    "wof:placetype":"venue"
},
  "geometry": {"coordinates":[-76.30331,39.874782],"type":"Point"}
}