{
  "type": "Feature",
  "properties": {
    "iso:country":"US",
    "sg:address":"1992 York Rd",
    "sg:city":"Warminster",
    "sg:phone":"+1 215 491 2001",
    "sg:postcode":"18974",
    "sg:province":"PA",
    "wof:name":"Luigi's Restaurant",
    "wof:placetype":"venue"
},
  "geometry": {"coordinates":[-75.09272799999999,40.228378],"type":"Point"}
}