{
  "type": "Feature",
  "properties": {
    "addr:full":"1016 Park Ave Meadville PA 16335",
    "addr:housenumber":"1016",
    "addr:postcode":"16335",
    "addr:street":"Park Ave",
    "iso:country":"US",
    "sg:address":"1016 Park Ave",
    "sg:city":"Meadville",
    "sg:classifiers":[
        {
            "category":"Retail",
            "subcategory":"Auto Repair",
            "type":"Services"
        }
    ],
    "sg:phone":"+1 814 724 5937",
    "sg:postcode":"16335",
    "sg:province":"PA",
    "sg:tags":[
        "body",
        "automobile",
        "painting"
    ],
    "wof:name":"Body Shop",
    "wof:placetype":"venue"
},
  "geometry": {"coordinates":[-80.153673,41.635672],"type":"Point"}
}