{
  "type": "Feature",
  "properties": {
    "iso:country":"US",
    "sg:address":"611 Blanchard St",
    "sg:city":"Bellefonte",
    "sg:classifiers":[
        {
            "category":"Manufacturing",
            "subcategory":"Glass & Minerals",
            "type":"Manufacturing & Wholesale Goods"
        }
    ],
    "sg:phone":"+1   ",
    "sg:postcode":"16823",
    "sg:province":"PA",
    "sg:tags":[
        "installs",
        "burial",
        "mfg",
        "cement",
        "vault"
    ],
    "wof:name":"Haines Vaults",
    "wof:placetype":"venue"
},
  "geometry": {"coordinates":[-77.766127,40.906894],"type":"Point"}
}