{
  "type": "Feature",
  "properties": {
    "iso:country":"US",
    "sg:address":"715 S Park St",
    "sg:city":"Red Lion",
    "sg:classifiers":[
        {
            "category":"Farming",
            "subcategory":"Livestock Farm",
            "type":"Manufacturing & Wholesale Goods"
        }
    ],
    "sg:phone":"+1   ",
    "sg:postcode":"17356",
    "sg:province":"PA",
    "sg:tags":[
        "animal",
        "general"
    ],
    "wof:name":"Dale Grim",
    "wof:placetype":"venue"
},
  "geometry": {"coordinates":[-76.620937,39.872554],"type":"Point"}
}