{
  "type": "Feature",
  "properties": {
    "iso:country":"US",
    "sg:address":"1901 Kutztown Rd",
    "sg:city":"Reading",
    "sg:classifiers":[
        {
            "category":"Autos & Motor Vehicles",
            "subcategory":"Auto Supplies",
            "type":"Retail Goods"
        },
        {
            "category":"Retail",
            "subcategory":"Auto Repair",
            "type":"Services"
        }
    ],
    "sg:phone":"+1 610 929 4723",
    "sg:postcode":"19604",
    "sg:province":"PA",
    "sg:tags":[
        "alignment-frame",
        "brake",
        "absorber",
        "automobile",
        "system",
        "lube",
        "equipment-service",
        "wheel",
        "exhaust",
        "oil",
        "accessory",
        "servicing-automotive",
        "part",
        "balancing",
        "axle",
        "wheels-aligning",
        "muffler",
        "strut",
        "air conditioning",
        "transmission",
        "shock"
    ],
    "sg:website":"http://1901kutztownroad.midasphiladelphia.com/store.aspx?shopNum=4411&language=en-US",
    "wof:name":"Midas Auto Service Experts",
    "wof:placetype":"venue"
},
  "geometry": {"coordinates":[-75.91899600000001,40.364233],"type":"Point"}
}