{
  "type": "Feature",
  "properties": {
    "iso:country":"US",
    "sg:address":"3261 Frankford Ave",
    "sg:city":"Philadelphia",
    "sg:classifiers":[
        {
            "category":"Retail",
            "subcategory":"Auto Repair",
            "type":"Services"
        }
    ],
    "sg:phone":"+1 215 426 2589",
    "sg:postcode":"19134",
    "sg:province":"PA",
    "wof:name":"Cruz Auto Repair",
    "wof:placetype":"venue"
},
  "geometry": {"coordinates":[-75.108358,39.993742],"type":"Point"}
}