{
  "type": "Feature",
  "properties": {
    "iso:country":"US",
    "sg:address":"1 Lutes Ave",
    "sg:city":"Mansfield",
    "sg:classifiers":[
        {
            "category":"Wholesale",
            "subcategory":"Construction Materials",
            "type":"Manufacturing & Wholesale Goods"
        },
        {
            "category":"Home & Garden",
            "subcategory":"Building Materials",
            "type":"Retail Goods"
        }
    ],
    "sg:phone":"+1 570 662 3868",
    "sg:postcode":"16933",
    "sg:province":"PA",
    "sg:tags":[
        "pallet",
        "skid",
        "lumber-used"
    ],
    "wof:name":"House Wood Products Co",
    "wof:placetype":"venue"
},
  "geometry": {"coordinates":[-77.071854,41.7925],"type":"Point"}
}