{
  "type": "Feature",
  "properties": {
    "iso:country":"US",
    "sg:address":"2809 Leechburg Rd",
    "sg:city":"Lower Burrell",
    "sg:classifiers":[
        {
            "category":"Restaurant",
            "type":"Food & Drink"
        }
    ],
    "sg:phone":"+1 724 339 0505",
    "sg:postcode":"15068",
    "sg:province":"PA",
    "sg:tags":[
        "drinking",
        "eating"
    ],
    "wof:name":"Lamp Post",
    "wof:placetype":"venue"
},
  "geometry": {"coordinates":[-79.73120900000001,40.59177],"type":"Point"}
}