{
  "type": "Feature",
  "properties": {
    "iso:country":"US",
    "sg:address":"102 Wyndham Cir",
    "sg:city":"Boalsburg",
    "sg:classifiers":[
        {
            "category":"Bars & Pubs",
            "type":"Food & Drink"
        }
    ],
    "sg:phone":"+1   ",
    "sg:postcode":"16827",
    "sg:province":"PA",
    "sg:tags":[
        "drinking"
    ],
    "wof:name":"Brewery Inc",
    "wof:placetype":"venue"
},
  "geometry": {"coordinates":[-77.764655,40.784711],"type":"Point"}
}