{
  "type": "Feature",
  "properties": {
    "iso:country":"US",
    "sg:address":"110 Old York Rd",
    "sg:city":"New Cumberland",
    "sg:classifiers":[
        {
            "category":"Shopping",
            "subcategory":"Tobacco",
            "type":"Retail Goods"
        }
    ],
    "sg:phone":"+1 717 920 9990",
    "sg:postcode":"17070",
    "sg:province":"PA",
    "sg:tags":[
        "shop"
    ],
    "wof:name":"Smoker's Express",
    "wof:placetype":"venue"
},
  "geometry": {"coordinates":[-76.86019899999999,40.223499],"type":"Point"}
}