{
  "type": "Feature",
  "properties": {
    "iso:country":"US",
    "sg:address":"20 N Michael St",
    "sg:city":"St Marys",
    "sg:classifiers":[
        {
            "category":"Shopping",
            "type":"Retail Goods"
        }
    ],
    "sg:phone":"+1 814 834 7721",
    "sg:postcode":"15857",
    "sg:province":"PA",
    "sg:tags":[
        "hearing",
        "equipment",
        "supply",
        "impaired"
    ],
    "wof:name":"Richard W Foust Audiological",
    "wof:placetype":"venue"
},
  "geometry": {"coordinates":[-78.56184,41.428862],"type":"Point"}
}