{
  "type": "Feature",
  "properties": {
    "addr:full":"7750 Airport Rd Bath PA 18014",
    "addr:housenumber":"7750",
    "addr:postcode":"18014",
    "addr:street":"Airport Rd",
    "iso:country":"US",
    "sg:address":"7750 Airport Rd",
    "sg:city":"Bath",
    "sg:classifiers":[
        {
            "category":"Building & Trades",
            "subcategory":"Construction",
            "type":"Services"
        }
    ],
    "sg:phone":"+1 610 837 6468",
    "sg:postcode":"18014",
    "sg:province":"PA",
    "sg:tags":[
        "contractor"
    ],
    "wof:name":"Ideal Glass",
    "wof:placetype":"venue"
},
  "geometry": {"coordinates":[-75.418724,40.709335],"type":"Point"}
}