{
  "type": "Feature",
  "properties": {
    "iso:country":"US",
    "sg:address":"4219 Oregon Pike",
    "sg:city":"Ephrata",
    "sg:classifiers":[
        {
            "category":"Personal",
            "subcategory":"Beauty Salon",
            "type":"Services"
        }
    ],
    "sg:phone":"+1 717 859 3442",
    "sg:postcode":"17522",
    "sg:province":"PA",
    "wof:name":"Prime Time Salon Inc",
    "wof:placetype":"venue"
},
  "geometry": {"coordinates":[-76.21648999999999,40.131523],"type":"Point"}
}