{
  "type": "Feature",
  "properties": {
    "addr:full":"5274 Old Route 22 Hamburg PA 19526",
    "addr:housenumber":"5274",
    "addr:postcode":"19526",
    "addr:street":"Old Route 22",
    "iso:country":"US",
    "sg:address":"5274 Old Route 22",
    "sg:city":"Hamburg",
    "sg:classifiers":[
        {
            "category":"Farming",
            "subcategory":"Farm",
            "type":"Manufacturing & Wholesale Goods"
        }
    ],
    "sg:phone":"+1 610 781 3756",
    "sg:postcode":"19526",
    "sg:province":"PA",
    "wof:name":"Kratz Brothers Farm",
    "wof:placetype":"venue"
},
  "geometry": {"coordinates":[-76.083364,40.512799],"type":"Point"}
}