{
  "type": "Feature",
  "properties": {
    "iso:country":"US",
    "sg:address":"500 Stevenson Blvd",
    "sg:city":"New Kensington",
    "sg:classifiers":[
        {
            "category":"Autos & Motor Vehicles",
            "subcategory":"Automobile Sales",
            "type":"Retail Goods"
        }
    ],
    "sg:phone":"+1   ",
    "sg:postcode":"15068",
    "sg:province":"PA",
    "sg:tags":[
        "sell",
        "new",
        "used",
        "truck",
        "car"
    ],
    "wof:name":"Avis Truck & Car Rental",
    "wof:placetype":"venue"
},
  "geometry": {"coordinates":[-79.759006,40.559965],"type":"Point"}
}