{
  "type": "Feature",
  "properties": {
    "addr:full":"610 Hanover St Northumberland PA 17857",
    "addr:housenumber":"610",
    "addr:postcode":"17857",
    "addr:street":"Hanover St",
    "iso:country":"US",
    "sg:address":"610 Hanover St",
    "sg:city":"Northumberland",
    "sg:classifiers":[
        {
            "category":"Building & Trades",
            "subcategory":"Construction",
            "type":"Services"
        }
    ],
    "sg:phone":"+1   ",
    "sg:postcode":"17857",
    "sg:province":"PA",
    "sg:tags":[
        "house"
    ],
    "wof:name":"R F Middlesworth Construction",
    "wof:placetype":"venue"
},
  "geometry": {"coordinates":[-76.80056399999999,40.897251],"type":"Point"}
}