{
  "type": "Feature",
  "properties": {
    "iso:country":"US",
    "sg:address":"334 Airport Rd",
    "sg:city":"Butler",
    "sg:classifiers":[
        {
            "category":"Education",
            "subcategory":"Preschool",
            "type":"Public Place"
        },
        {
            "category":"Education",
            "subcategory":"School",
            "type":"Public Place"
        }
    ],
    "sg:phone":"+1 724 586 2015",
    "sg:postcode":"16002",
    "sg:province":"PA",
    "sg:tags":[
        "elementary"
    ],
    "wof:name":"Nixon Pre-School",
    "wof:placetype":"venue"
},
  "geometry": {"coordinates":[-79.94319900000001,40.779999],"type":"Point"}
}