{
  "type": "Feature",
  "properties": {
    "iso:country":"US",
    "sg:address":"726 Washington Blvd",
    "sg:city":"Williamsport",
    "sg:classifiers":[
        {
            "category":"Travel",
            "subcategory":"Hotels & Motels",
            "type":"Entertainment"
        }
    ],
    "sg:phone":"+1 570 322 7623",
    "sg:postcode":"17701",
    "sg:province":"PA",
    "sg:tags":[
        "operation"
    ],
    "sg:website":"www.jeffersonsquare.com",
    "wof:name":"Jefferson Square",
    "wof:placetype":"venue"
},
  "geometry": {"coordinates":[-76.990387,41.24757],"type":"Point"}
}