{
  "type": "Feature",
  "properties": {
    "iso:country":"US",
    "sg:address":"180 Greenfield Rd",
    "sg:city":"Lancaster",
    "sg:classifiers":[
        {
            "category":"Food & Beverages",
            "subcategory":"Bakery",
            "type":"Retail Goods"
        }
    ],
    "sg:phone":"+1   ",
    "sg:postcode":"17601",
    "sg:province":"PA",
    "wof:name":"Anderson Pretzel Bakery",
    "wof:placetype":"venue"
},
  "geometry": {"coordinates":[-76.255295,40.046657],"type":"Point"}
}