{
  "type": "Feature",
  "properties": {
    "iso:country":"US",
    "sg:address":"3302 Tuxedo St",
    "sg:city":"Pittsburgh",
    "sg:classifiers":[
        {
            "category":"Building & Trades",
            "subcategory":"Construction",
            "type":"Services"
        }
    ],
    "sg:phone":"+1   ",
    "sg:postcode":"15204",
    "sg:province":"PA",
    "sg:tags":[
        "garage",
        "door",
        "installation"
    ],
    "wof:name":"Schafer Electronics",
    "wof:placetype":"venue"
},
  "geometry": {"coordinates":[-80.068157,40.45461],"type":"Point"}
}