{
  "type": "Feature",
  "properties": {
    "addr:full":"2600 W Lehigh Ave Philadelphia PA 19132",
    "addr:housenumber":"2600",
    "addr:postcode":"19132",
    "addr:street":"W Lehigh Ave",
    "iso:country":"US",
    "sg:address":"2600 W Lehigh Ave",
    "sg:city":"Philadelphia",
    "sg:classifiers":[
        {
            "category":"Banks & Credit Unions",
            "subcategory":"Bank",
            "type":"Services"
        }
    ],
    "sg:phone":"+1 215 228 9233",
    "sg:postcode":"19132",
    "sg:province":"PA",
    "sg:tags":[
        "cashing",
        "check"
    ],
    "wof:name":"Fast Cash Atm",
    "wof:placetype":"venue"
},
  "geometry": {"coordinates":[-75.175539,39.996638],"type":"Point"}
}