{
  "type": "Feature",
  "properties": {
    "iso:country":"US",
    "sg:address":"89 Cedar Manor",
    "sg:city":"Elizabethtown",
    "sg:classifiers":[
        {
            "category":"Professional",
            "subcategory":"Business Services",
            "type":"Services"
        }
    ],
    "sg:phone":"+1 717 367 1727",
    "sg:postcode":"17022",
    "sg:province":"PA",
    "sg:tags":[
        "notary"
    ],
    "wof:name":"E & St Tag & Notary",
    "wof:placetype":"venue"
},
  "geometry": {"coordinates":[-76.650971,40.172923],"type":"Point"}
}