{
  "type": "Feature",
  "properties": {
    "addr:full":"1940 Swamp Rd Quakertown PA 18951",
    "addr:housenumber":"1940",
    "addr:postcode":"18951",
    "addr:street":"Swamp Rd",
    "iso:country":"US",
    "sg:address":"1940 Swamp Rd",
    "sg:city":"Quakertown",
    "sg:classifiers":[
        {
            "category":"Shopping",
            "subcategory":"Stationery & Office Supplies",
            "type":"Retail Goods"
        }
    ],
    "sg:phone":"+1 215 529 2951",
    "sg:postcode":"18951",
    "sg:province":"PA",
    "wof:name":"Safeguard Business Systems",
    "wof:placetype":"venue"
},
  "geometry": {"coordinates":[-75.41146500000001,40.457409],"type":"Point"}
}