{
  "type": "Feature",
  "properties": {
    "iso:country":"US",
    "sg:address":"2902 New Rodgers Rd",
    "sg:city":"Bristol",
    "sg:classifiers":[
        {
            "category":"Professional",
            "subcategory":"Business Services",
            "type":"Services"
        }
    ],
    "sg:phone":"+1 215 788 8881",
    "sg:postcode":"19007",
    "sg:province":"PA",
    "sg:tags":[
        "water",
        "treatment"
    ],
    "wof:name":"Professional Water Services",
    "wof:placetype":"venue"
},
  "geometry": {"coordinates":[-74.881404,40.121256],"type":"Point"}
}