{
  "type": "Feature",
  "properties": {
    "iso:country":"US",
    "sg:address":"549 Monument Ave",
    "sg:city":"Wyoming",
    "sg:classifiers":[
        {
            "category":"Personal",
            "subcategory":"Beauty Salon",
            "type":"Services"
        }
    ],
    "sg:phone":"+1   ",
    "sg:postcode":"18644",
    "sg:province":"PA",
    "sg:tags":[
        "shop"
    ],
    "wof:name":"Brendas Beauty World",
    "wof:placetype":"venue"
},
  "geometry": {"coordinates":[-75.841379,41.306961],"type":"Point"}
}