{
  "type": "Feature",
  "properties": {
    "iso:country":"US",
    "sg:address":"631 Manchester Rd",
    "sg:city":"Norristown",
    "sg:classifiers":[
        {
            "category":"Manufacturing",
            "subcategory":"Tools & Machinery",
            "type":"Manufacturing & Wholesale Goods"
        }
    ],
    "sg:phone":"+1   ",
    "sg:postcode":"19403",
    "sg:province":"PA",
    "sg:tags":[
        "equipment",
        "mfg"
    ],
    "wof:name":"Zz Enterprises Inc",
    "wof:placetype":"venue"
},
  "geometry": {"coordinates":[-75.33789899999999,40.161204],"type":"Point"}
}