{
  "type": "Feature",
  "properties": {
    "addr:full":"256 Gedding St Pittston PA 18641",
    "addr:housenumber":"256",
    "addr:postcode":"18641",
    "addr:street":"Gedding St",
    "iso:country":"US",
    "sg:address":"256 Gedding St",
    "sg:city":"Pittston",
    "sg:classifiers":[
        {
            "category":"Shopping",
            "subcategory":"Gifts & Souvenirs",
            "type":"Retail Goods"
        }
    ],
    "sg:phone":"+1   ",
    "sg:postcode":"18641",
    "sg:province":"PA",
    "wof:name":"Little Richies Angel Shop",
    "wof:placetype":"venue"
},
  "geometry": {"coordinates":[-75.751087,41.336369],"type":"Point"}
}