{
  "type": "Feature",
  "properties": {
    "addr:full":"5601 Grand Ave Pittsburgh PA 15225",
    "addr:housenumber":"5601",
    "addr:postcode":"15225",
    "addr:street":"Grand Ave",
    "iso:country":"US",
    "sg:address":"5601 Grand Ave",
    "sg:city":"Pittsburgh",
    "sg:classifiers":[
        {
            "category":"Building & Trades",
            "subcategory":"Equipment Rental",
            "type":"Services"
        }
    ],
    "sg:phone":"+1   ",
    "sg:postcode":"15225",
    "sg:province":"PA",
    "sg:tags":[
        "wholesale",
        "construction",
        "supply"
    ],
    "wof:name":"Construction Rental & Sup Inc",
    "wof:placetype":"venue"
},
  "geometry": {"coordinates":[-80.13585500000001,40.513113],"type":"Point"}
}