{
  "type": "Feature",
  "properties": {
    "iso:country":"US",
    "sg:address":"6482 Sherwood Rd",
    "sg:city":"Philadelphia",
    "sg:classifiers":[
        {
            "category":"Professional",
            "subcategory":"Lawyer & Legal Services",
            "type":"Services"
        }
    ],
    "sg:phone":"+1 215 477 6790",
    "sg:postcode":"19151",
    "sg:province":"PA",
    "sg:tags":[
        "information",
        "attorney",
        "referral"
    ],
    "wof:name":"Law Office Anthony W Novasitis",
    "wof:placetype":"venue"
},
  "geometry": {"coordinates":[-75.25654400000001,39.984053],"type":"Point"}
}