{
  "type": "Feature",
  "properties": {
    "iso:country":"US",
    "sg:address":"562 Mountain Rd",
    "sg:city":"Boyertown",
    "sg:classifiers":[
        {
            "category":"Professional",
            "subcategory":"Computer Services",
            "type":"Services"
        }
    ],
    "sg:phone":"+1 610 369 0022",
    "sg:postcode":"19512",
    "sg:province":"PA",
    "sg:tags":[
        "consultant",
        "designer"
    ],
    "wof:name":"Jurgensen Associates",
    "wof:placetype":"venue"
},
  "geometry": {"coordinates":[-75.677406,40.35252],"type":"Point"}
}