{
  "type": "Feature",
  "properties": {
    "iso:country":"US",
    "sg:address":"450 N Wales Rd",
    "sg:city":"Lansdale",
    "sg:classifiers":[
        {
            "category":"Wholesale",
            "subcategory":"Farm Supplies",
            "type":"Manufacturing & Wholesale Goods"
        }
    ],
    "sg:phone":"+1   ",
    "sg:postcode":"19446",
    "sg:province":"PA",
    "wof:name":"Greger David P Tpsl Splr",
    "wof:placetype":"venue"
},
  "geometry": {"coordinates":[-75.283361,40.20491],"type":"Point"}
}