{
  "type": "Feature",
  "properties": {
    "iso:country":"US",
    "sg:address":"711 Bethlehem Pike",
    "sg:city":"Glenside",
    "sg:classifiers":[
        {
            "category":"Insurance",
            "subcategory":"Insurance Agent",
            "type":"Services"
        }
    ],
    "sg:phone":"+1 215 233 2000",
    "sg:postcode":"19038",
    "sg:province":"PA",
    "wof:name":"Costello Brothers & Brady Inc",
    "wof:placetype":"venue"
},
  "geometry": {"coordinates":[-75.21422200000001,40.092616],"type":"Point"}
}