{
  "type": "Feature",
  "properties": {
    "addr:full":"1659 Old Philadelphia Pike Lancaster PA 17602",
    "addr:housenumber":"1659",
    "addr:postcode":"17602",
    "addr:street":"Old Philadelphia Pike",
    "iso:country":"US",
    "sg:address":"1659 Old Philadelphia Pike",
    "sg:city":"Lancaster",
    "sg:classifiers":[
        {
            "category":"Recreation",
            "type":"Entertainment"
        }
    ],
    "sg:phone":"+1 717 392 7100",
    "sg:postcode":"17602",
    "sg:province":"PA",
    "sg:tags":[
        "martial",
        "arts",
        "instruction"
    ],
    "wof:name":"Kim Studios Of Karate",
    "wof:placetype":"venue"
},
  "geometry": {"coordinates":[-76.26943799999999,40.038339],"type":"Point"}
}