{
  "type": "Feature",
  "properties": {
    "addr:full":"550 Baltimore Pike Avondale PA 19311",
    "addr:housenumber":"550",
    "addr:postcode":"19311",
    "addr:street":"Baltimore Pike",
    "iso:country":"US",
    "sg:address":"550 Baltimore Pike",
    "sg:city":"Avondale",
    "sg:classifiers":[
        {
            "category":"Shopping",
            "type":"Retail Goods"
        }
    ],
    "sg:phone":"+1 610 925 3922",
    "sg:postcode":"19311",
    "sg:province":"PA",
    "sg:tags":[
        "wedding",
        "supply"
    ],
    "wof:name":"International Tours & Cruises",
    "wof:placetype":"venue"
},
  "geometry": {"coordinates":[-75.792461,39.833774],"type":"Point"}
}