{
  "type": "Feature",
  "properties": {
    "addr:full":"2608 Cottman Ave Philadelphia PA 19149",
    "addr:housenumber":"2608",
    "addr:postcode":"19149",
    "addr:street":"Cottman Ave",
    "iso:country":"US",
    "sg:address":"2608 Cottman Ave",
    "sg:city":"Philadelphia",
    "sg:classifiers":[
        {
            "category":"Home & Garden",
            "subcategory":"Furniture",
            "type":"Retail Goods"
        }
    ],
    "sg:phone":"+1 215 335 2800",
    "sg:postcode":"19149",
    "sg:province":"PA",
    "sg:tags":[
        "mattress"
    ],
    "wof:name":"Rockaway Bedding Inc",
    "wof:placetype":"venue"
},
  "geometry": {"coordinates":[-75.05464499999999,40.044644],"type":"Point"}
}