{
  "type": "Feature",
  "properties": {
    "iso:country":"US",
    "sg:address":"1300 W Chester Rd",
    "sg:city":"West Chester",
    "sg:classifiers":[
        {
            "category":"Health Services",
            "subcategory":"Doctor",
            "type":"Services"
        }
    ],
    "sg:phone":"+1   ",
    "sg:postcode":"19382",
    "sg:province":"PA",
    "sg:tags":[
        "medical"
    ],
    "wof:name":"Mia D Finlelston MD",
    "wof:placetype":"venue"
},
  "geometry": {"coordinates":[-75.547214,39.911062],"type":"Point"}
}