{
  "type": "Feature",
  "properties": {
    "iso:country":"US",
    "sg:address":"310 Alumni Ave",
    "sg:city":"Harleysville",
    "sg:classifiers":[
        {
            "category":"Government",
            "subcategory":"Office",
            "type":"Public Place"
        }
    ],
    "sg:phone":"+1 215 256 8331",
    "sg:postcode":"19438",
    "sg:province":"PA",
    "sg:tags":[
        "village"
    ],
    "wof:name":"Township Garage",
    "wof:placetype":"venue"
},
  "geometry": {"coordinates":[-75.386543,40.278562],"type":"Point"}
}