{
  "type": "Feature",
  "properties": {
    "addr:full":"1105 Meetinghouse Rd Boothwyn PA 19061",
    "addr:housenumber":"1105",
    "addr:postcode":"19061",
    "addr:street":"Meetinghouse Rd",
    "iso:country":"US",
    "sg:address":"1105 Meetinghouse Rd",
    "sg:city":"Boothwyn",
    "sg:classifiers":[
        {
            "category":"Autos & Motor Vehicles",
            "subcategory":"Auto Supplies",
            "type":"Retail Goods"
        }
    ],
    "sg:phone":"+1 610 534 0668",
    "sg:postcode":"19061",
    "sg:province":"PA",
    "sg:tags":[
        "automobile",
        "stereo",
        "radio"
    ],
    "wof:name":"Sound Waves Car Audio & Alarm",
    "wof:placetype":"venue"
},
  "geometry": {"coordinates":[-75.43825099999999,39.831209],"type":"Point"}
}