{
  "type": "Feature",
  "properties": {
    "iso:country":"US",
    "sg:address":"10103 Northeast Ave # 17",
    "sg:city":"Philadelphia",
    "sg:classifiers":[
        {
            "category":"Shopping",
            "subcategory":"Clothing, Apparel, & Fashions",
            "type":"Retail Goods"
        }
    ],
    "sg:phone":"+1 215 289 0100",
    "sg:postcode":"19116",
    "sg:province":"PA",
    "sg:tags":[
        "uniforms-accessories",
        "uniform"
    ],
    "wof:name":"Uniform Plus",
    "wof:placetype":"venue"
},
  "geometry": {"coordinates":[-75.024331,40.104281],"type":"Point"}
}