{
  "type": "Feature",
  "properties": {
    "iso:country":"US",
    "sg:address":"3366 Grant Ave",
    "sg:city":"Philadelphia",
    "sg:classifiers":[
        {
            "category":"Autos & Motor Vehicles",
            "subcategory":"Auto Supplies",
            "type":"Retail Goods"
        }
    ],
    "sg:phone":"+1   ",
    "sg:postcode":"19114",
    "sg:province":"PA",
    "sg:tags":[
        "repair",
        "general"
    ],
    "wof:name":"R & S Parts and Service Inc",
    "wof:placetype":"venue"
},
  "geometry": {"coordinates":[-75.00406,40.067448],"type":"Point"}
}