{
  "type": "Feature",
  "properties": {
    "addr:full":"1500 Spring Garden St Philadelphia PA 19130",
    "addr:housenumber":"1500",
    "addr:postcode":"19130",
    "addr:street":"Spring Garden St",
    "iso:country":"US",
    "sg:address":"1500 Spring Garden St",
    "sg:city":"Philadelphia",
    "sg:classifiers":[
        {
            "category":"Building & Trades",
            "subcategory":"Construction",
            "type":"Services"
        }
    ],
    "sg:phone":"+1 215 557 9499",
    "sg:postcode":"19130",
    "sg:province":"PA",
    "sg:tags":[
        "contractor"
    ],
    "wof:name":"Fifteen Hundred Networks Assoc",
    "wof:placetype":"venue"
},
  "geometry": {"coordinates":[-75.163498,39.9627],"type":"Point"}
}