{
  "type": "Feature",
  "properties": {
    "iso:country":"US",
    "sg:address":"2380 Lincoln Blvd",
    "sg:city":"Elizabeth",
    "sg:classifiers":[
        {
            "category":"Retail",
            "subcategory":"Auto Repair",
            "type":"Services"
        }
    ],
    "sg:phone":"+1 412 678 1641",
    "sg:postcode":"15037",
    "sg:province":"PA",
    "sg:tags":[
        "truck"
    ],
    "wof:name":"Dan's Truck Svc",
    "wof:placetype":"venue"
},
  "geometry": {"coordinates":[-79.86546300000001,40.298362],"type":"Point"}
}