{
  "type": "Feature",
  "properties": {
    "iso:country":"US",
    "sg:address":"200 1st Ave Ste 300",
    "sg:city":"Pittsburgh",
    "sg:classifiers":[
        {
            "category":"Professional",
            "subcategory":"Lawyer & Legal Services",
            "type":"Services"
        }
    ],
    "sg:phone":"+1 412 261 2393",
    "sg:postcode":"15222",
    "sg:province":"PA",
    "sg:website":"www.dscslaw.com",
    "wof:name":"Del Sole Cavanaugh Stroyd Llc",
    "wof:placetype":"venue"
},
  "geometry": {"coordinates":[-80.004103,40.438432],"type":"Point"}
}