{
  "type": "Feature",
  "properties": {
    "iso:country":"US",
    "sg:address":"875 Chippewa Rd",
    "sg:city":"Muncy",
    "sg:classifiers":[
        {
            "category":"Building & Trades",
            "subcategory":"Landscaping Services",
            "type":"Services"
        }
    ],
    "sg:phone":"+1 570 435 0346",
    "sg:postcode":"17756",
    "sg:province":"PA",
    "sg:tags":[
        "landscape",
        "contractor"
    ],
    "wof:name":"Keystone Natural Turf",
    "wof:placetype":"venue"
},
  "geometry": {"coordinates":[-76.767281,41.225498],"type":"Point"}
}