{
  "type": "Feature",
  "properties": {
    "iso:country":"US",
    "sg:address":"730 N Franklin St",
    "sg:city":"York",
    "sg:classifiers":[
        {
            "category":"Wholesale",
            "subcategory":"Machinery & Supplies",
            "type":"Manufacturing & Wholesale Goods"
        }
    ],
    "sg:phone":"+1   ",
    "sg:postcode":"17403",
    "sg:province":"PA",
    "sg:tags":[
        "industrial"
    ],
    "wof:name":"IV R I",
    "wof:placetype":"venue"
},
  "geometry": {"coordinates":[-76.715429,39.977234],"type":"Point"}
}