{
  "type": "Feature",
  "properties": {
    "iso:country":"US",
    "sg:address":"124 E Washington St",
    "sg:city":"New Castle",
    "sg:classifiers":[
        {
            "category":"Shopping",
            "subcategory":"Jewelry",
            "type":"Retail Goods"
        }
    ],
    "sg:phone":"+1 724 652 5525",
    "sg:postcode":"16101",
    "sg:province":"PA",
    "sg:tags":[
        "jeweler"
    ],
    "wof:name":"King's Jewelry",
    "wof:placetype":"venue"
},
  "geometry": {"coordinates":[-80.344408,40.99992],"type":"Point"}
}