{
  "type": "Feature",
  "properties": {
    "iso:country":"US",
    "sg:address":"18 Treaty Dr",
    "sg:city":"Chesterbrook",
    "sg:classifiers":[
        {
            "category":"Education",
            "subcategory":"Library",
            "type":"Public Place"
        }
    ],
    "sg:phone":"+1 610 644 5290",
    "sg:postcode":"19087",
    "sg:province":"PA",
    "sg:tags":[
        "professional",
        "educational"
    ],
    "wof:name":"American Soc For Microbiology",
    "wof:placetype":"venue"
},
  "geometry": {"coordinates":[-75.455423,40.07924],"type":"Point"}
}