{
  "type": "Feature",
  "properties": {
    "iso:country":"US",
    "sg:address":"140 Quaker Ln",
    "sg:city":"Malvern",
    "sg:classifiers":[
        {
            "category":"Professional",
            "subcategory":"Computer Services",
            "type":"Services"
        }
    ],
    "sg:phone":"+1   ",
    "sg:postcode":"19355",
    "sg:province":"PA",
    "sg:tags":[
        "cabling",
        "local",
        "network",
        "area"
    ],
    "wof:name":"Summit Data Network Services",
    "wof:placetype":"venue"
},
  "geometry": {"coordinates":[-75.520129,40.037328],"type":"Point"}
}