{
  "type": "Feature",
  "properties": {
    "addr:full":"421 19th Ave Scranton PA 18504",
    "addr:housenumber":"421",
    "addr:postcode":"18504",
    "addr:street":"19Th Ave",
    "iso:country":"US",
    "sg:address":"421 19th Ave",
    "sg:city":"Scranton",
    "sg:classifiers":[
        {
            "category":"Health Services",
            "subcategory":"Clinic",
            "type":"Services"
        }
    ],
    "sg:phone":"+1 570 947 8103",
    "sg:postcode":"18504",
    "sg:province":"PA",
    "sg:tags":[
        "information",
        "alcoholism",
        "treatment"
    ],
    "wof:name":"Therapy Unlimited",
    "wof:placetype":"venue"
},
  "geometry": {"coordinates":[-75.694682,41.412589],"type":"Point"}
}