{
  "type": "Feature",
  "properties": {
    "addr:full":"3380 Washington Rd Canonsburg PA 15317",
    "addr:housenumber":"3380",
    "addr:postcode":"15317",
    "addr:street":"Washington Rd",
    "iso:country":"US",
    "sg:address":"3380 Washington Rd",
    "sg:city":"Canonsburg",
    "sg:classifiers":[
        {
            "category":"Shopping",
            "subcategory":"Gifts & Souvenirs",
            "type":"Retail Goods"
        }
    ],
    "sg:phone":"+1   ",
    "sg:postcode":"15317",
    "sg:province":"PA",
    "wof:name":"All Occasions Party Rental",
    "wof:placetype":"venue"
},
  "geometry": {"coordinates":[-80.116575,40.287454],"type":"Point"}
}