{
  "type": "Feature",
  "properties": {
    "iso:country":"US",
    "sg:address":"5358 York Road",
    "sg:city":"Holicong",
    "sg:classifiers":[
        {
            "category":"Travel",
            "subcategory":"Hotels & Motels",
            "type":"Entertainment"
        },
        {
            "category":"Travel",
            "subcategory":"Bed & Breakfast",
            "type":"Entertainment"
        }
    ],
    "sg:phone":"+1 215 794 5373",
    "sg:postcode":"18928",
    "sg:province":"PA",
    "sg:website":"www.ashmillfarm.com",
    "wof:name":"Ash Mill Farm",
    "wof:placetype":"venue"
},
  "geometry": {"coordinates":[-75.046459,40.340228],"type":"Point"}
}