{
  "type": "Feature",
  "properties": {
    "iso:country":"US",
    "sg:address":"342 North St",
    "sg:city":"Meadville",
    "sg:classifiers":[
        {
            "category":"Shopping",
            "subcategory":"Gifts & Souvenirs",
            "type":"Retail Goods"
        }
    ],
    "sg:phone":"+1 814 337 2874",
    "sg:postcode":"16335",
    "sg:province":"PA",
    "sg:tags":[
        "collectible"
    ],
    "wof:name":"Round Again Records",
    "wof:placetype":"venue"
},
  "geometry": {"coordinates":[-80.148911,41.640494],"type":"Point"}
}