{
  "type": "Feature",
  "properties": {
    "iso:country":"US",
    "sg:address":"7007 York Rd",
    "sg:city":"Abbottstown",
    "sg:classifiers":[
        {
            "category":"Health Services",
            "subcategory":"Nursing And Care Facility",
            "type":"Services"
        }
    ],
    "sg:phone":"+1 717 624 1555",
    "sg:postcode":"17301",
    "sg:province":"PA",
    "sg:tags":[
        "home",
        "institution"
    ],
    "wof:name":"Skills Of Central Pa",
    "wof:placetype":"venue"
},
  "geometry": {"coordinates":[-76.99974400000001,39.881406],"type":"Point"}
}