{
  "type": "Feature",
  "properties": {
    "iso:country":"US",
    "sg:address":"1104 Sitka Dr",
    "sg:city":"Imperial",
    "sg:classifiers":[
        {
            "category":"Building & Trades",
            "subcategory":"Construction",
            "type":"Services"
        }
    ],
    "sg:phone":"+1   ",
    "sg:postcode":"15126",
    "sg:province":"PA",
    "sg:tags":[
        "house"
    ],
    "wof:name":"Sherlock Homes Residential Bu",
    "wof:placetype":"venue"
},
  "geometry": {"coordinates":[-80.242188,40.458944],"type":"Point"}
}