{
  "type": "Feature",
  "properties": {
    "addr:full":"729 E Lake Rd Transfer PA 16154",
    "addr:housenumber":"729",
    "addr:postcode":"16154",
    "addr:street":"E Lake Rd",
    "iso:country":"US",
    "sg:address":"729 E Lake Rd",
    "sg:city":"Transfer",
    "sg:classifiers":[
        {
            "category":"Organizations",
            "subcategory":"Non-profit Organization",
            "type":"Services"
        }
    ],
    "sg:phone":"+1   ",
    "sg:postcode":"16154",
    "sg:province":"PA",
    "sg:tags":[
        "social"
    ],
    "wof:name":"United Ostomy Association",
    "wof:placetype":"venue"
},
  "geometry": {"coordinates":[-80.415314,41.300017],"type":"Point"}
}