{
  "type": "Feature",
  "properties": {
    "addr:full":"486 Nutt Rd Phoenixville PA 19460",
    "addr:housenumber":"486",
    "addr:postcode":"19460",
    "addr:street":"Nutt Rd",
    "iso:country":"US",
    "sg:address":"486 Nutt Rd",
    "sg:city":"Phoenixville",
    "sg:classifiers":[
        {
            "category":"Autos & Motor Vehicles",
            "subcategory":"Auto Supplies",
            "type":"Retail Goods"
        },
        {
            "category":"Wholesale",
            "subcategory":"Electrical",
            "type":"Manufacturing & Wholesale Goods"
        }
    ],
    "sg:phone":"+1 610 933 4102",
    "sg:postcode":"19460",
    "sg:province":"PA",
    "sg:tags":[
        "battery",
        "automobile",
        "part",
        "accessory"
    ],
    "sg:website":"http://www.napaonline.com",
    "wof:name":"Napa Auto Parts",
    "wof:placetype":"venue"
},
  "geometry": {"coordinates":[-75.52637900000001,40.128547],"type":"Point"}
}