{
  "type": "Feature",
  "properties": {
    "iso:country":"US",
    "sg:address":"735 High Blvd",
    "sg:city":"Shillington",
    "sg:classifiers":[
        {
            "category":"Organizations",
            "subcategory":"Religious Organization",
            "type":"Services"
        }
    ],
    "sg:phone":"+1 610 796 2721",
    "sg:postcode":"19607",
    "sg:province":"PA",
    "sg:tags":[
        "church"
    ],
    "wof:name":"Local Christian Assembly",
    "wof:placetype":"venue"
},
  "geometry": {"coordinates":[-75.940668,40.300638],"type":"Point"}
}