{
  "type": "Feature",
  "properties": {
    "addr:full":"989 Keller Rd York PA 17406",
    "addr:housenumber":"989",
    "addr:postcode":"17406",
    "addr:street":"Keller Rd",
    "iso:country":"US",
    "sg:address":"989 Keller Rd",
    "sg:city":"York",
    "sg:classifiers":[
        {
            "category":"Personal",
            "subcategory":"Beauty Salon",
            "type":"Services"
        }
    ],
    "sg:phone":"+1 717 252 4782",
    "sg:postcode":"17406",
    "sg:province":"PA",
    "wof:name":"Pat Barnett's Beauty Shop",
    "wof:placetype":"venue"
},
  "geometry": {"coordinates":[-76.55021000000001,39.982148],"type":"Point"}
}