{
  "type": "Feature",
  "properties": {
    "iso:country":"US",
    "sg:address":"5731 Malvern Ave",
    "sg:city":"Philadelphia",
    "sg:classifiers":[
        {
            "category":"Food & Beverages",
            "subcategory":"Groceries & Convenience Stores",
            "type":"Retail Goods"
        }
    ],
    "sg:phone":"+1 215 877 8004",
    "sg:postcode":"19131",
    "sg:province":"PA",
    "sg:tags":[
        "grocer"
    ],
    "wof:name":"Francis Food Market",
    "wof:placetype":"venue"
},
  "geometry": {"coordinates":[-75.23840300000001,39.987499],"type":"Point"}
}