{
  "type": "Feature",
  "properties": {
    "iso:country":"US",
    "sg:address":"543 3rd St",
    "sg:city":"Beaver",
    "sg:classifiers":[
        {
            "category":"Home & Garden",
            "subcategory":"Furniture",
            "type":"Retail Goods"
        }
    ],
    "sg:phone":"+1 724 775 5080",
    "sg:postcode":"15009",
    "sg:province":"PA",
    "sg:tags":[
        "store"
    ],
    "wof:name":"The Amish Woodshed",
    "wof:placetype":"venue"
},
  "geometry": {"coordinates":[-80.30370499999999,40.695685],"type":"Point"}
}