{
  "type": "Feature",
  "properties": {
    "iso:country":"US",
    "sg:address":"4629 E Thompson St",
    "sg:city":"Philadelphia",
    "sg:classifiers":[
        {
            "category":"Education",
            "subcategory":"School",
            "type":"Public Place"
        }
    ],
    "sg:phone":"+1   ",
    "sg:postcode":"19137",
    "sg:province":"PA",
    "wof:name":"All Saints School",
    "wof:placetype":"venue"
},
  "geometry": {"coordinates":[-75.06910499999999,40.002445],"type":"Point"}
}