{
  "type": "Feature",
  "properties": {
    "iso:country":"US",
    "sg:address":"2268 Kennedy St",
    "sg:city":"Philadelphia",
    "sg:classifiers":[
        {
            "category":"Restaurant",
            "type":"Food & Drink"
        }
    ],
    "sg:phone":"+1   ",
    "sg:postcode":"19137",
    "sg:province":"PA",
    "sg:tags":[
        "drinking",
        "eating"
    ],
    "wof:name":"Cannonball Tavern Inc",
    "wof:placetype":"venue"
},
  "geometry": {"coordinates":[-75.06670200000001,40.010149],"type":"Point"}
}