{
  "type": "Feature",
  "properties": {
    "addr:full":"117 N Monroe St Media PA 19063",
    "addr:housenumber":"117",
    "addr:postcode":"19063",
    "addr:street":"N Monroe St",
    "iso:country":"US",
    "sg:address":"117 N Monroe St",
    "sg:city":"Media",
    "sg:classifiers":[
        {
            "category":"Professional",
            "subcategory":"Lawyer & Legal Services",
            "type":"Services"
        }
    ],
    "sg:phone":"+1   ",
    "sg:postcode":"19063",
    "sg:province":"PA",
    "wof:name":"Emerson S Jonathan",
    "wof:placetype":"venue"
},
  "geometry": {"coordinates":[-75.387163,39.919335],"type":"Point"}
}