{
  "type": "Feature",
  "properties": {
    "iso:country":"US",
    "sg:address":"2902 Kensington Ave",
    "sg:city":"Philadelphia",
    "sg:classifiers":[
        {
            "category":"Autos & Motor Vehicles",
            "subcategory":"Automobile Sales",
            "type":"Retail Goods"
        }
    ],
    "sg:phone":"+1   ",
    "sg:postcode":"19134",
    "sg:province":"PA",
    "sg:tags":[
        "used"
    ],
    "wof:name":"Mikes Auto Sales Inc",
    "wof:placetype":"venue"
},
  "geometry": {"coordinates":[-75.119771,39.993054],"type":"Point"}
}