{
  "type": "Feature",
  "properties": {
    "iso:country":"US",
    "sg:address":"14657 Mercersburg Rd",
    "sg:city":"Greencastle",
    "sg:classifiers":[
        {
            "category":"Building & Trades",
            "subcategory":"Construction",
            "type":"Services"
        }
    ],
    "sg:phone":"+1   ",
    "sg:postcode":"17225",
    "sg:province":"PA",
    "sg:tags":[
        "residential",
        "roofing",
        "contractor"
    ],
    "wof:name":"McCardell Roofing Contractor",
    "wof:placetype":"venue"
},
  "geometry": {"coordinates":[-77.810182,39.725624],"type":"Point"}
}