{
  "type": "Feature",
  "properties": {
    "iso:country":"US",
    "sg:address":"460 Colebrookdale Rd",
    "sg:city":"Boyertown",
    "sg:classifiers":[
        {
            "category":"Professional",
            "subcategory":"Accounting & Tax Preparation",
            "type":"Services"
        }
    ],
    "sg:phone":"+1 610 987 8063",
    "sg:postcode":"19512",
    "sg:province":"PA",
    "sg:tags":[
        "billing"
    ],
    "wof:name":"Main Street Billing",
    "wof:placetype":"venue"
},
  "geometry": {"coordinates":[-75.65742899999999,40.29514],"type":"Point"}
}