{
  "type": "Feature",
  "properties": {
    "addr:full":"1053 Philadelphia St Indiana PA 15701",
    "addr:housenumber":"1053",
    "addr:postcode":"15701",
    "addr:street":"Philadelphia St",
    "iso:country":"US",
    "sg:address":"1053 Philadelphia St",
    "sg:city":"Indiana",
    "sg:classifiers":[
        {
            "category":"Personal",
            "subcategory":"Beauty Salon",
            "type":"Services"
        }
    ],
    "sg:phone":"+1 724 349 8304",
    "sg:postcode":"15701",
    "sg:province":"PA",
    "wof:name":"Executive Suite",
    "wof:placetype":"venue"
},
  "geometry": {"coordinates":[-79.160653,40.62316],"type":"Point"}
}