{
  "type": "Feature",
  "properties": {
    "iso:country":"US",
    "sg:address":"422 E Locust Ave",
    "sg:city":"Philadelphia",
    "sg:classifiers":[
        {
            "category":"Arena",
            "subcategory":"Sports Club",
            "type":"Entertainment"
        },
        {
            "category":"Sports & Exercise",
            "subcategory":"Sports Center",
            "type":"Entertainment"
        },
        {
            "category":"Sports & Exercise",
            "subcategory":"Tennis Court",
            "type":"Entertainment"
        }
    ],
    "sg:phone":"+1 215 844 9941",
    "sg:postcode":"19144",
    "sg:province":"PA",
    "sg:tags":[
        "courts-private"
    ],
    "wof:name":"Philadelphia Tennis Club Inc",
    "wof:placetype":"venue"
},
  "geometry": {"coordinates":[-75.16849000000001,40.038628],"type":"Point"}
}