{
  "type": "Feature",
  "properties": {
    "iso:country":"US",
    "sg:address":"34 Wabash St",
    "sg:city":"Pittsburgh",
    "sg:classifiers":[
        {
            "category":"Shopping",
            "subcategory":"Florist",
            "type":"Retail Goods"
        }
    ],
    "sg:phone":"+1 412 921 5053",
    "sg:postcode":"15220",
    "sg:province":"PA",
    "wof:name":"Muetzel Florist & Gift Shoppe",
    "wof:placetype":"venue"
},
  "geometry": {"coordinates":[-80.034695,40.440438],"type":"Point"}
}