{
  "type": "Feature",
  "properties": {
    "addr:full":"219 E Cambria St Philadelphia PA 19134",
    "addr:housenumber":"219",
    "addr:postcode":"19134",
    "addr:street":"E Cambria St",
    "iso:country":"US",
    "sg:address":"219 E Cambria St",
    "sg:city":"Philadelphia",
    "sg:classifiers":[
        {
            "category":"Shopping",
            "subcategory":"Discount & Variety Stores",
            "type":"Retail Goods"
        }
    ],
    "sg:phone":"+1 215 634 5339",
    "sg:postcode":"19134",
    "sg:province":"PA",
    "wof:name":"Schmidt's Variety Store",
    "wof:placetype":"venue"
},
  "geometry": {"coordinates":[-75.128292,39.993739],"type":"Point"}
}