{
  "type": "Feature",
  "properties": {
    "iso:country":"US",
    "sg:address":"222 Farmall Rd",
    "sg:city":"Grantville",
    "sg:classifiers":[
        {
            "category":"Building & Trades",
            "subcategory":"Plumbing",
            "type":"Services"
        }
    ],
    "sg:phone":"+1 717 469 9332",
    "sg:postcode":"17028",
    "sg:province":"PA",
    "sg:tags":[
        "plumbing",
        "contractor"
    ],
    "wof:name":"Advanced Plumbing Svc",
    "wof:placetype":"venue"
},
  "geometry": {"coordinates":[-76.667023,40.403725],"type":"Point"}
}