{
  "type": "Feature",
  "properties": {
    "addr:full":"2109 Conestoga Rd Malvern PA 19355",
    "addr:housenumber":"2109",
    "addr:postcode":"19355",
    "addr:street":"Conestoga Rd",
    "iso:country":"US",
    "sg:address":"2109 Conestoga Rd",
    "sg:city":"Malvern",
    "sg:classifiers":[
        {
            "category":"Organizations",
            "subcategory":"Religious Organization",
            "type":"Services"
        }
    ],
    "sg:phone":"+1 610 827 9101",
    "sg:postcode":"19355",
    "sg:province":"PA",
    "sg:website":"www.bactonhillbiblechurch.org",
    "wof:name":"Bacton Hill Bible Church",
    "wof:placetype":"venue"
},
  "geometry": {"coordinates":[-75.60597799999999,40.059652],"type":"Point"}
}