{
  "type": "Feature",
  "properties": {
    "addr:full":"2470 Bedford St Johnstown PA 15904",
    "addr:housenumber":"2470",
    "addr:postcode":"15904",
    "addr:street":"Bedford St",
    "iso:country":"US",
    "sg:address":"2470 Bedford St",
    "sg:city":"Johnstown",
    "sg:classifiers":[
        {
            "category":"Shopping",
            "subcategory":"Pharmacy",
            "type":"Retail Goods"
        }
    ],
    "sg:phone":"+1   ",
    "sg:postcode":"15904",
    "sg:province":"PA",
    "sg:tags":[
        "photofinishing",
        "drug",
        "laboratory"
    ],
    "wof:name":"Rite Aid",
    "wof:placetype":"venue"
},
  "geometry": {"coordinates":[-78.869777,40.294816],"type":"Point"}
}