{
  "type": "Feature",
  "properties": {
    "iso:country":"US",
    "sg:address":"220 Mapleflower Rd",
    "sg:city":"Glenmoore",
    "sg:classifiers":[
        {
            "category":"Building & Trades",
            "subcategory":"Construction",
            "type":"Services"
        }
    ],
    "sg:phone":"+1 610 942 2417",
    "sg:postcode":"19343",
    "sg:province":"PA",
    "sg:tags":[
        "altering",
        "remodeling",
        "contractor"
    ],
    "wof:name":"Anthony E Landers Jr",
    "wof:placetype":"venue"
},
  "geometry": {"coordinates":[-75.774061,40.115781],"type":"Point"}
}