{
  "type": "Feature",
  "properties": {
    "iso:country":"US",
    "sg:address":"1469 Gruversville Rd",
    "sg:city":"Coopersburg",
    "sg:classifiers":[
        {
            "category":"Health Services",
            "subcategory":"Health Practitioner",
            "type":"Services"
        }
    ],
    "sg:phone":"+1 610 346 6354",
    "sg:postcode":"18036",
    "sg:province":"PA",
    "wof:name":"Lehigh Valley Muscle Therapy",
    "wof:placetype":"venue"
},
  "geometry": {"coordinates":[-75.321012,40.499898],"type":"Point"}
}