{
  "type": "Feature",
  "properties": {
    "iso:country":"US",
    "sg:address":"504 State Rd",
    "sg:city":"Croydon",
    "sg:classifiers":[
        {
            "category":"Banks & Credit Unions",
            "subcategory":"Bank",
            "type":"Services"
        }
    ],
    "sg:phone":"+1 215 781 6455",
    "sg:postcode":"19021",
    "sg:province":"PA",
    "sg:tags":[
        "cashing",
        "check"
    ],
    "wof:name":"United Check Cashing Co",
    "wof:placetype":"venue"
},
  "geometry": {"coordinates":[-74.905995,40.08642],"type":"Point"}
}