{
  "type": "Feature",
  "properties": {
    "iso:country":"US",
    "sg:address":"1630 Hoffnagle St",
    "sg:city":"Philadelphia",
    "sg:classifiers":[
        {
            "category":"Education",
            "subcategory":"School",
            "type":"Public Place"
        }
    ],
    "sg:phone":"+1 215 725 3800",
    "sg:postcode":"19152",
    "sg:province":"PA",
    "wof:name":"Stern Hebrew High School",
    "wof:placetype":"venue"
},
  "geometry": {"coordinates":[-75.058485,40.068777],"type":"Point"}
}