{
  "type": "Feature",
  "properties": {
    "addr:full":"110 E Allison St Centre Hall PA 16828",
    "addr:housenumber":"110",
    "addr:postcode":"16828",
    "addr:street":"E Allison St",
    "iso:country":"US",
    "sg:address":"110 E Allison St",
    "sg:city":"Centre Hall",
    "sg:classifiers":[
        {
            "category":"Manufacturing",
            "subcategory":"Pet Food",
            "type":"Manufacturing & Wholesale Goods"
        }
    ],
    "sg:phone":"+1 814 364 1393",
    "sg:postcode":"16828",
    "sg:province":"PA",
    "sg:tags":[
        "feed"
    ],
    "wof:name":"Centre Hall Farm Store",
    "wof:placetype":"venue"
},
  "geometry": {"coordinates":[-77.67721299999999,40.841714],"type":"Point"}
}