{
  "type": "Feature",
  "properties": {
    "iso:country":"US",
    "sg:address":"7941 Redtop Rd",
    "sg:city":"Hummelstown",
    "sg:classifiers":[
        {
            "category":"Professional",
            "subcategory":"Detective & Security Services",
            "type":"Services"
        }
    ],
    "sg:phone":"+1 717 566 1300",
    "sg:postcode":"17036",
    "sg:province":"PA",
    "sg:tags":[
        "car",
        "armored",
        "private",
        "investigator"
    ],
    "wof:name":"Pa Special Task Force, Inc",
    "wof:placetype":"venue"
},
  "geometry": {"coordinates":[-76.70315600000001,40.318432],"type":"Point"}
}