{
  "type": "Feature",
  "properties": {
    "iso:country":"US",
    "sg:address":"3629 Oak St",
    "sg:city":"Schnecksville",
    "sg:classifiers":[
        {
            "category":"Health Services",
            "subcategory":"Health Practitioner",
            "type":"Services"
        }
    ],
    "sg:phone":"+1   ",
    "sg:postcode":"18078",
    "sg:province":"PA",
    "wof:name":"Elizabeth Hummber",
    "wof:placetype":"venue"
},
  "geometry": {"coordinates":[-75.580581,40.667682],"type":"Point"}
}