{
  "type": "Feature",
  "properties": {
    "iso:country":"US",
    "sg:address":"830 Tryens Rd",
    "sg:city":"Aston",
    "sg:classifiers":[
        {
            "category":"Wholesale",
            "subcategory":"Machinery & Supplies",
            "type":"Manufacturing & Wholesale Goods"
        }
    ],
    "sg:phone":"+1   ",
    "sg:postcode":"19014",
    "sg:province":"PA",
    "sg:tags":[
        "repair",
        "industrial",
        "se",
        "mfg"
    ],
    "wof:name":"Smith-Koch Co",
    "wof:placetype":"venue"
},
  "geometry": {"coordinates":[-75.445397,39.86937],"type":"Point"}
}