{
  "type": "Feature",
  "properties": {
    "iso:country":"US",
    "sg:address":"141 N Kennedy Dr",
    "sg:city":"Mcadoo",
    "sg:classifiers":[
        {
            "category":"Personal",
            "subcategory":"Beauty Salon",
            "type":"Services"
        }
    ],
    "sg:phone":"+1 570 929 2505",
    "sg:postcode":"18237",
    "sg:province":"PA",
    "wof:name":"Denise's Hair Quarters",
    "wof:placetype":"venue"
},
  "geometry": {"coordinates":[-75.993118,40.904606],"type":"Point"}
}