{
  "type": "Feature",
  "properties": {
    "addr:full":"4715 N Front St Philadelphia PA 19120",
    "addr:housenumber":"4715",
    "addr:postcode":"19120",
    "addr:street":"N Front St",
    "iso:country":"US",
    "sg:address":"4715 N Front St",
    "sg:city":"Philadelphia",
    "sg:classifiers":[
        {
            "category":"Restaurant",
            "type":"Food & Drink"
        }
    ],
    "sg:phone":"+1 267 385 5690",
    "sg:postcode":"19120",
    "sg:province":"PA",
    "sg:tags":[
        "mexican"
    ],
    "wof:name":"Rancho Alegre Mexican Restaurant",
    "wof:placetype":"venue"
},
  "geometry": {"coordinates":[-75.12405699999999,40.022024],"type":"Point"}
}