{
  "type": "Feature",
  "properties": {
    "iso:country":"US",
    "sg:address":"5159 Morningrise Dr",
    "sg:city":"Pittsburgh",
    "sg:classifiers":[
        {
            "category":"Building & Trades",
            "subcategory":"Construction",
            "type":"Services"
        }
    ],
    "sg:phone":"+1   ",
    "sg:postcode":"15236",
    "sg:province":"PA",
    "sg:tags":[
        "house"
    ],
    "wof:name":"J A Kartman Master Builder",
    "wof:placetype":"venue"
},
  "geometry": {"coordinates":[-80.00499000000001,40.361241],"type":"Point"}
}