{
  "type": "Feature",
  "properties": {
    "iso:country":"US",
    "sg:address":"7725 Ridge Ave",
    "sg:city":"Philadelphia",
    "sg:classifiers":[
        {
            "category":"Wholesale",
            "subcategory":"Sporting Goods",
            "type":"Manufacturing & Wholesale Goods"
        }
    ],
    "sg:phone":"+1 215 483 5000",
    "sg:postcode":"19128",
    "sg:province":"PA",
    "sg:tags":[
        "course",
        "golf",
        "equipment"
    ],
    "wof:name":"Farm & Golf Course Supply Co",
    "wof:placetype":"venue"
},
  "geometry": {"coordinates":[-75.236223,40.051035],"type":"Point"}
}