{
  "type": "Feature",
  "properties": {
    "addr:full":"173 Glendale Rd Beaver Falls PA 15010",
    "addr:housenumber":"173",
    "addr:postcode":"15010",
    "addr:street":"Glendale Rd",
    "iso:country":"US",
    "sg:address":"173 Glendale Rd",
    "sg:city":"Beaver Falls",
    "sg:classifiers":[
        {
            "category":"Recreation",
            "type":"Entertainment"
        }
    ],
    "sg:phone":"+1 724 843 6582",
    "sg:postcode":"15010",
    "sg:province":"PA",
    "sg:tags":[
        "stable"
    ],
    "wof:name":"Skyline Stables",
    "wof:placetype":"venue"
},
  "geometry": {"coordinates":[-80.271981,40.773791],"type":"Point"}
}