{
  "type": "Feature",
  "properties": {
    "addr:full":"7716 Castor Ave Philadelphia PA 19152",
    "addr:housenumber":"7716",
    "addr:postcode":"19152",
    "addr:street":"Castor Ave",
    "iso:country":"US",
    "sg:address":"7716 Castor Ave",
    "sg:city":"Philadelphia",
    "sg:classifiers":[
        {
            "category":"Professional",
            "subcategory":"Lawyer & Legal Services",
            "type":"Services"
        }
    ],
    "sg:phone":"+1 215 722 5850",
    "sg:postcode":"19152",
    "sg:province":"PA",
    "sg:tags":[
        "plan"
    ],
    "wof:name":"Howard M Goldsmith Pc",
    "wof:placetype":"venue"
},
  "geometry": {"coordinates":[-75.06017300000001,40.057565],"type":"Point"}
}