{
  "type": "Feature",
  "properties": {
    "iso:country":"US",
    "sg:address":"129 S Mckean St",
    "sg:city":"Butler",
    "sg:classifiers":[
        {
            "category":"Professional",
            "subcategory":"Lawyer & Legal Services",
            "type":"Services"
        }
    ],
    "sg:phone":"+1 724 283 6445",
    "sg:postcode":"16001",
    "sg:province":"PA",
    "sg:tags":[
        "attorney",
        "estate",
        "wills",
        "practice",
        "planning",
        "plan",
        "trust"
    ],
    "wof:name":"John Davey Esq",
    "wof:placetype":"venue"
},
  "geometry": {"coordinates":[-79.893648,40.860326],"type":"Point"}
}