{
  "type": "Feature",
  "properties": {
    "iso:country":"US",
    "sg:address":"112 Long Rd",
    "sg:city":"King Of Prussia",
    "sg:classifiers":[
        {
            "category":"Professional",
            "subcategory":"Lawyer & Legal Services",
            "type":"Services"
        }
    ],
    "sg:phone":"+1 610 337 3880",
    "sg:postcode":"19406",
    "sg:province":"PA",
    "sg:tags":[
        "attorney"
    ],
    "wof:name":"Professional Information Corp",
    "wof:placetype":"venue"
},
  "geometry": {"coordinates":[-75.383178,40.086621],"type":"Point"}
}