{
  "type": "Feature",
  "properties": {
    "addr:full":"807 Northwinds Dr Bryn Mawr PA 19010",
    "addr:housenumber":"807",
    "addr:postcode":"19010",
    "addr:street":"Northwinds Dr",
    "iso:country":"US",
    "sg:address":"807 Northwinds Dr",
    "sg:city":"Bryn Mawr",
    "sg:classifiers":[
        {
            "category":"Banks & Credit Unions",
            "subcategory":"Financial Services",
            "type":"Services"
        }
    ],
    "sg:phone":"+1   ",
    "sg:postcode":"19010",
    "sg:province":"PA",
    "sg:tags":[
        "investment",
        "private"
    ],
    "wof:name":"Pb Investments Inc",
    "wof:placetype":"venue"
},
  "geometry": {"coordinates":[-75.34614000000001,40.007815],"type":"Point"}
}