{
  "type": "Feature",
  "properties": {
    "iso:country":"US",
    "sg:address":"10 N College St",
    "sg:city":"Washington",
    "sg:classifiers":[
        {
            "category":"Building & Trades",
            "subcategory":"Construction",
            "type":"Services"
        }
    ],
    "sg:phone":"+1   ",
    "sg:postcode":"15301",
    "sg:province":"PA",
    "sg:tags":[
        "house"
    ],
    "wof:name":"Mascaro Construction Co",
    "wof:placetype":"venue"
},
  "geometry": {"coordinates":[-80.24289899999999,40.171558],"type":"Point"}
}