{
  "type": "Feature",
  "properties": {
    "iso:country":"US",
    "sg:address":"898 Plaza Blvd",
    "sg:city":"Lancaster",
    "sg:classifiers":[
        {
            "category":"Personal",
            "type":"Services"
        }
    ],
    "sg:phone":"+1   ",
    "sg:postcode":"17601",
    "sg:province":"PA",
    "wof:name":"Capitol Rent-A-Tux",
    "wof:placetype":"venue"
},
  "geometry": {"coordinates":[-76.34101800000001,40.070969],"type":"Point"}
}