{
  "type": "Feature",
  "properties": {
    "iso:country":"US",
    "sg:address":"6650 Mountain Rd",
    "sg:city":"Macungie",
    "sg:classifiers":[
        {
            "category":"Shopping",
            "subcategory":"Gifts & Souvenirs",
            "type":"Retail Goods"
        }
    ],
    "sg:phone":"+1 610 965 5511",
    "sg:postcode":"18062",
    "sg:province":"PA",
    "sg:tags":[
        "shop"
    ],
    "wof:name":"Wreaths & Roses",
    "wof:placetype":"venue"
},
  "geometry": {"coordinates":[-75.56292000000001,40.505141],"type":"Point"}
}