{
  "type": "Feature",
  "properties": {
    "iso:country":"US",
    "sg:address":"42 N 8th St",
    "sg:city":"Allentown",
    "sg:classifiers":[
        {
            "category":"Personal",
            "subcategory":"Beauty Salon",
            "type":"Services"
        }
    ],
    "sg:phone":"+1 484 274 6101",
    "sg:postcode":"18101",
    "sg:province":"PA",
    "sg:tags":[
        "hair"
    ],
    "wof:name":"Chris Beauty Salon",
    "wof:placetype":"venue"
},
  "geometry": {"coordinates":[-75.47415599999999,40.602561],"type":"Point"}
}