{
  "type": "Feature",
  "properties": {
    "addr:full":"3636 Blvd of the Allies Pittsburgh PA 15213",
    "addr:housenumber":"3636",
    "addr:postcode":"15213",
    "addr:street":"Blvd Of The Allies",
    "iso:country":"US",
    "sg:address":"3636 Blvd of the Allies",
    "sg:city":"Pittsburgh",
    "sg:classifiers":[
        {
            "category":"Professional",
            "subcategory":"Research",
            "type":"Services"
        }
    ],
    "sg:phone":"+1   ",
    "sg:postcode":"15213",
    "sg:province":"PA",
    "sg:tags":[
        "development",
        "polymer",
        "make",
        "enzyme",
        "to"
    ],
    "wof:name":"Agentase LLC",
    "wof:placetype":"venue"
},
  "geometry": {"coordinates":[-79.95366799999999,40.434377],"type":"Point"}
}