{
  "type": "Feature",
  "properties": {
    "iso:country":"US",
    "sg:address":"1050 Park Manor Blvd",
    "sg:city":"Pittsburgh",
    "sg:classifiers":[
        {
            "category":"Professional",
            "subcategory":"Management & Consulting",
            "type":"Services"
        }
    ],
    "sg:phone":"+1 412 787 1355",
    "sg:postcode":"15205",
    "sg:province":"PA",
    "sg:tags":[
        "construction"
    ],
    "wof:name":"Commercial Construction Mgmt",
    "wof:placetype":"venue"
},
  "geometry": {"coordinates":[-80.163071,40.449984],"type":"Point"}
}