{
  "type": "Feature",
  "properties": {
    "iso:country":"US",
    "sg:address":"608 W King St",
    "sg:city":"Shippensburg",
    "sg:classifiers":[
        {
            "category":"Autos & Motor Vehicles",
            "subcategory":"Automobile Sales",
            "type":"Retail Goods"
        }
    ],
    "sg:phone":"+1 717 532 4136",
    "sg:postcode":"17257",
    "sg:province":"PA",
    "sg:tags":[
        "new",
        "pickup",
        "used",
        "truck"
    ],
    "sg:website":"www.nauglemotors.com",
    "wof:name":"Naugle Motors Inc",
    "wof:placetype":"venue"
},
  "geometry": {"coordinates":[-77.528476,40.046742],"type":"Point"}
}