{
  "type": "Feature",
  "properties": {
    "addr:full":"1018 W 8th Ave King Of Prussia PA 19406",
    "addr:housenumber":"1018",
    "addr:postcode":"19406",
    "addr:street":"W 8Th Ave",
    "iso:country":"US",
    "sg:address":"1018 W 8th Ave",
    "sg:city":"King Of Prussia",
    "sg:classifiers":[
        {
            "category":"Retail",
            "subcategory":"Repair Shop",
            "type":"Services"
        }
    ],
    "sg:phone":"+1   ",
    "sg:postcode":"19406",
    "sg:province":"PA",
    "sg:tags":[
        "communication",
        "mfg"
    ],
    "wof:name":"G E Mobile Communications",
    "wof:placetype":"venue"
},
  "geometry": {"coordinates":[-75.415308,40.098774],"type":"Point"}
}