{
  "type": "Feature",
  "properties": {
    "iso:country":"US",
    "sg:address":"3423 Frankford Ave",
    "sg:city":"Philadelphia",
    "sg:classifiers":[
        {
            "category":"Home & Garden",
            "subcategory":"Hardware",
            "type":"Retail Goods"
        }
    ],
    "sg:phone":"+1 215 288 3192",
    "sg:postcode":"19134",
    "sg:province":"PA",
    "wof:name":"B Tannenbaum Hardware",
    "wof:placetype":"venue"
},
  "geometry": {"coordinates":[-75.10447000000001,39.995912],"type":"Point"}
}