{
  "type": "Feature",
  "properties": {
    "addr:full":"22 Penns Ct Aston PA 19014",
    "addr:housenumber":"22",
    "addr:postcode":"19014",
    "addr:street":"Penns Ct Aston",
    "iso:country":"US",
    "sg:address":"22 Penns Ct",
    "sg:city":"Aston",
    "sg:classifiers":[
        {
            "category":"Professional",
            "type":"Services"
        }
    ],
    "sg:phone":"+1   ",
    "sg:postcode":"19014",
    "sg:province":"PA",
    "wof:name":"Aquajox",
    "wof:placetype":"venue"
},
  "geometry": {"coordinates":[-75.448628,39.872865],"type":"Point"}
}