{
  "type": "Feature",
  "properties": {
    "addr:full":"2230 S Broad St 2nd Floor Philadelphia PA 19145",
    "addr:housenumber":"2230;2nd floor",
    "addr:postcode":"19145",
    "addr:street":"S Broad St",
    "iso:country":"US",
    "sg:address":"2230 S Broad St 2nd Floor",
    "sg:city":"Philadelphia",
    "sg:classifiers":[
        {
            "category":"Health Services",
            "subcategory":"Clinic",
            "type":"Services"
        }
    ],
    "sg:phone":"+1 215 551 6080",
    "sg:postcode":"19145",
    "sg:province":"PA",
    "sg:tags":[
        "medical"
    ],
    "sg:website":"mbidv.com",
    "wof:name":"Medical Billing Inc of Delaware Valley",
    "wof:placetype":"venue"
},
  "geometry": {"coordinates":[-75.170395,39.92253],"type":"Point"}
}