{
  "type": "Feature",
  "properties": {
    "addr:full":"876 Blakeslee Boulevard Dr E Lehighton PA 18235",
    "addr:housenumber":"876",
    "addr:postcode":"18235",
    "addr:street":"Blakeslee Boulevard Dr E",
    "iso:country":"US",
    "sg:address":"876 Blakeslee Boulevard Dr E",
    "sg:city":"Lehighton",
    "sg:classifiers":[
        {
            "category":"Food & Beverages",
            "subcategory":"Groceries & Convenience Stores",
            "type":"Retail Goods"
        }
    ],
    "sg:phone":"+1 610 000 1111",
    "sg:postcode":"18235",
    "sg:province":"PA",
    "sg:tags":[
        "grocer"
    ],
    "wof:name":"Aldi",
    "wof:placetype":"venue"
},
  "geometry": {"coordinates":[-75.726586,40.81882],"type":"Point"}
}