{
  "type": "Feature",
  "properties": {
    "iso:country":"US",
    "sg:address":"700 Croton Rd",
    "sg:city":"Wayne",
    "sg:classifiers":[
        {
            "category":"Sports & Exercise",
            "subcategory":"Golf",
            "type":"Entertainment"
        }
    ],
    "sg:phone":"+1 610 687 2340",
    "sg:postcode":"19087",
    "sg:province":"PA",
    "sg:tags":[
        "course"
    ],
    "wof:name":"Golf Association of Philadelphia",
    "wof:placetype":"venue"
},
  "geometry": {"coordinates":[-75.37779999999999,40.078892],"type":"Point"}
}