{
  "type": "Feature",
  "properties": {
    "iso:country":"US",
    "sg:address":"1598 Virginia Ave",
    "sg:city":"Monaca",
    "sg:classifiers":[
        {
            "category":"Social Services",
            "subcategory":"Adult Care",
            "type":"Services"
        }
    ],
    "sg:phone":"+1 724 775 0209",
    "sg:postcode":"15061",
    "sg:province":"PA",
    "sg:tags":[
        "foster"
    ],
    "wof:name":"Children's Institute",
    "wof:placetype":"venue"
},
  "geometry": {"coordinates":[-80.27339499999999,40.689158],"type":"Point"}
}