{
  "type": "Feature",
  "properties": {
    "addr:full":"6 N Main St Pittston PA 18640",
    "addr:housenumber":"6",
    "addr:postcode":"18640",
    "addr:street":"N Main St",
    "iso:country":"US",
    "sg:address":"6 N Main St",
    "sg:city":"Pittston",
    "sg:classifiers":[
        {
            "category":"Health Services",
            "subcategory":"Optometrist",
            "type":"Services"
        }
    ],
    "sg:phone":"+1   ",
    "sg:postcode":"18640",
    "sg:province":"PA",
    "wof:name":"Bozzuto James P",
    "wof:placetype":"venue"
},
  "geometry": {"coordinates":[-75.790138,41.323353],"type":"Point"}
}