{
  "type": "Feature",
  "properties": {
    "iso:country":"US",
    "sg:address":"1045 Bristol Rd",
    "sg:city":"Morrisville",
    "sg:classifiers":[
        {
            "category":"Building & Trades",
            "subcategory":"Plumbing",
            "type":"Services"
        }
    ],
    "sg:phone":"+1 215 337 9003",
    "sg:postcode":"19067",
    "sg:province":"PA",
    "sg:tags":[
        "plumbing",
        "contractor"
    ],
    "wof:name":"Drainrooter",
    "wof:placetype":"venue"
},
  "geometry": {"coordinates":[-74.78849200000001,40.179661],"type":"Point"}
}