{
  "type": "Feature",
  "properties": {
    "iso:country":"US",
    "sg:address":"601 New Britain Rd",
    "sg:city":"Doylestown",
    "sg:classifiers":[
        {
            "category":"Social Services",
            "subcategory":"Child Care",
            "type":"Services"
        },
        {
            "category":"Education",
            "subcategory":"Preschool",
            "type":"Public Place"
        },
        {
            "category":"Education",
            "subcategory":"School",
            "type":"Public Place"
        }
    ],
    "sg:phone":"+1 215 345 5877",
    "sg:postcode":"18901",
    "sg:province":"PA",
    "sg:tags":[
        "elementary",
        "day"
    ],
    "wof:name":"Children House Tabor",
    "wof:placetype":"venue"
},
  "geometry": {"coordinates":[-75.132896,40.291],"type":"Point"}
}