{
  "type": "Feature",
  "properties": {
    "iso:country":"US",
    "sg:address":"739 N 9th St",
    "sg:city":"Reading",
    "sg:classifiers":[
        {
            "category":"Food & Beverages",
            "subcategory":"Groceries & Convenience Stores",
            "type":"Retail Goods"
        }
    ],
    "sg:phone":"+1 610 375 0972",
    "sg:postcode":"19604",
    "sg:province":"PA",
    "sg:tags":[
        "grocer"
    ],
    "wof:name":"International Deli Grocery",
    "wof:placetype":"venue"
},
  "geometry": {"coordinates":[-75.91967099999999,40.34677],"type":"Point"}
}