{
  "type": "Feature",
  "properties": {
    "addr:full":"173 Dusty Trail Ln Berlin PA 15530",
    "addr:housenumber":"173",
    "addr:postcode":"15530",
    "addr:street":"Dusty Trail Ln",
    "iso:country":"US",
    "sg:address":"173 Dusty Trail Ln",
    "sg:city":"Berlin",
    "sg:classifiers":[
        {
            "category":"Building & Trades",
            "subcategory":"Electrical",
            "type":"Services"
        }
    ],
    "sg:phone":"+1 814 445 2046",
    "sg:postcode":"15530",
    "sg:province":"PA",
    "sg:tags":[
        "electric",
        "contractor"
    ],
    "wof:name":"Lewis Electric",
    "wof:placetype":"venue"
},
  "geometry": {"coordinates":[-79.039796,39.953185],"type":"Point"}
}