{
  "type": "Feature",
  "properties": {
    "iso:country":"US",
    "sg:address":"764 Allenview Dr",
    "sg:city":"Mechanicsburg",
    "sg:classifiers":[
        {
            "category":"Building & Trades",
            "subcategory":"Construction",
            "type":"Services"
        }
    ],
    "sg:phone":"+1 717 795 0704",
    "sg:postcode":"17055",
    "sg:province":"PA",
    "sg:tags":[
        "wallcoverings-installation",
        "wallpaper",
        "painting",
        "contractor"
    ],
    "wof:name":"Straight Edge Painting",
    "wof:placetype":"venue"
},
  "geometry": {"coordinates":[-76.965712,40.180962],"type":"Point"}
}