{
  "type": "Feature",
  "properties": {
    "iso:country":"US",
    "sg:address":"1770 Pine Hollow Rd",
    "sg:city":"Mc Kees Rocks",
    "sg:classifiers":[
        {
            "category":"Home & Garden",
            "subcategory":"Carpets & Floor Coverings",
            "type":"Retail Goods"
        }
    ],
    "sg:phone":"+1 412 331 2440",
    "sg:postcode":"15136",
    "sg:province":"PA",
    "wof:name":"R Uram Flooring Co",
    "wof:placetype":"venue"
},
  "geometry": {"coordinates":[-80.101135,40.476461],"type":"Point"}
}