{
  "type": "Feature",
  "properties": {
    "iso:country":"US",
    "sg:address":"239 Northern Blvd",
    "sg:city":"Chinchilla",
    "sg:classifiers":[
        {
            "category":"Banks & Credit Unions",
            "subcategory":"Bank",
            "type":"Services"
        }
    ],
    "sg:phone":"+1   ",
    "sg:postcode":"18410",
    "sg:province":"PA",
    "sg:tags":[
        "personal",
        "institution"
    ],
    "wof:name":"Associates Consumer Disc Co",
    "wof:placetype":"venue"
},
  "geometry": {"coordinates":[-75.66814599999999,41.465889],"type":"Point"}
}