{
  "type": "Feature",
  "properties": {
    "iso:country":"US",
    "sg:address":"701 N Homewood Ave",
    "sg:city":"Pittsburgh",
    "sg:classifiers":[
        {
            "category":"Education",
            "subcategory":"Junior College",
            "type":"Public Place"
        }
    ],
    "sg:phone":"+1   ",
    "sg:postcode":"15208",
    "sg:province":"PA",
    "wof:name":"Community Cllege Allgheny Cnty",
    "wof:placetype":"venue"
},
  "geometry": {"coordinates":[-79.89684,40.455999],"type":"Point"}
}