{
  "type": "Feature",
  "properties": {
    "iso:country":"US",
    "sg:address":"841 Sharon New Castle Rd",
    "sg:city":"Farrell",
    "sg:classifiers":[
        {
            "category":"Restaurant",
            "type":"Food & Drink"
        }
    ],
    "sg:phone":"+1 724 346 1933",
    "sg:postcode":"16121",
    "sg:province":"PA",
    "sg:tags":[
        "style",
        "family",
        "lunch",
        "american",
        "brunch",
        "breakfast"
    ],
    "sg:website":"http://www.wafflehouse.com",
    "wof:name":"Waffle House",
    "wof:placetype":"venue"
},
  "geometry": {"coordinates":[-80.48112,41.213133],"type":"Point"}
}