{
  "type": "Feature",
  "properties": {
    "addr:full":"5100 Walnut St Mc Keesport PA 15132",
    "addr:housenumber":"5100",
    "addr:postcode":"15132",
    "addr:street":"Walnut St",
    "iso:country":"US",
    "sg:address":"5100 Walnut St",
    "sg:city":"Mc Keesport",
    "sg:classifiers":[
        {
            "category":"Government",
            "subcategory":"Office",
            "type":"Public Place"
        }
    ],
    "sg:phone":"+1   ",
    "sg:postcode":"15132",
    "sg:province":"PA",
    "sg:tags":[
        "city"
    ],
    "wof:name":"Versailles Borough",
    "wof:placetype":"venue"
},
  "geometry": {"coordinates":[-79.830376,40.315015],"type":"Point"}
}