{
  "type": "Feature",
  "properties": {
    "addr:full":"138 W Chelten Ave Philadelphia PA 19144",
    "addr:housenumber":"138",
    "addr:postcode":"19144",
    "addr:street":"W Chelten Ave",
    "iso:country":"US",
    "sg:address":"138 W Chelten Ave",
    "sg:city":"Philadelphia",
    "sg:classifiers":[
        {
            "category":"Government",
            "subcategory":"Office",
            "type":"Public Place"
        }
    ],
    "sg:phone":"+1 215 685 0782",
    "sg:postcode":"19144",
    "sg:province":"PA",
    "sg:tags":[
        "village"
    ],
    "wof:name":"Philadelphia Area Office B",
    "wof:placetype":"venue"
},
  "geometry": {"coordinates":[-75.17868199999999,40.031885],"type":"Point"}
}