{
  "type": "Feature",
  "properties": {
    "iso:country":"US",
    "sg:address":"166 Dreher Rd",
    "sg:city":"Butler",
    "sg:classifiers":[
        {
            "category":"Retail",
            "subcategory":"Auto Repair",
            "type":"Services"
        }
    ],
    "sg:phone":"+1 724 352 9559",
    "sg:postcode":"16002",
    "sg:province":"PA",
    "sg:tags":[
        "body",
        "automobile",
        "painting"
    ],
    "wof:name":"Automotive Concepts",
    "wof:placetype":"venue"
},
  "geometry": {"coordinates":[-79.80961000000001,40.800225],"type":"Point"}
}