{
  "type": "Feature",
  "properties": {
    "addr:full":"111 W 3rd St Hershey PA 17033",
    "addr:housenumber":"111",
    "addr:postcode":"17033",
    "addr:street":"W 3Rd St",
    "iso:country":"US",
    "sg:address":"111 W 3rd St",
    "sg:city":"Hershey",
    "sg:classifiers":[
        {
            "category":"Government",
            "subcategory":"Office",
            "type":"Public Place"
        }
    ],
    "sg:phone":"+1 717 566 0224",
    "sg:postcode":"17033",
    "sg:province":"PA",
    "sg:tags":[
        "village"
    ],
    "wof:name":"South Hanover Twp Office",
    "wof:placetype":"venue"
},
  "geometry": {"coordinates":[-76.684999,40.290514],"type":"Point"}
}