{
  "type": "Feature",
  "properties": {
    "iso:country":"US",
    "sg:address":"4171 Horseshoe Pike",
    "sg:city":"Honey Brook",
    "sg:classifiers":[
        {
            "category":"Autos & Motor Vehicles",
            "subcategory":"Automobile Sales",
            "type":"Retail Goods"
        }
    ],
    "sg:phone":"+1 610 273 9200",
    "sg:postcode":"19344",
    "sg:province":"PA",
    "sg:tags":[
        "sport",
        "trailer",
        "utility"
    ],
    "wof:name":"Yarnall Equipment Co Inc",
    "wof:placetype":"venue"
},
  "geometry": {"coordinates":[-75.907794,40.092361],"type":"Point"}
}