{
  "type": "Feature",
  "properties": {
    "iso:country":"US",
    "sg:address":"3522 Rhoads Ave",
    "sg:city":"Newtown Square",
    "sg:classifiers":[
        {
            "category":"Building & Trades",
            "subcategory":"Construction",
            "type":"Services"
        }
    ],
    "sg:phone":"+1 610 356 0152",
    "sg:postcode":"19073",
    "sg:province":"PA",
    "sg:tags":[
        "general",
        "contractor"
    ],
    "wof:name":"Niemeyer Irvin H & Son Builder",
    "wof:placetype":"venue"
},
  "geometry": {"coordinates":[-75.395749,39.987278],"type":"Point"}
}