{
  "type": "Feature",
  "properties": {
    "addr:full":"204 W Main St Bath PA 18014",
    "addr:housenumber":"204",
    "addr:postcode":"18014",
    "addr:street":"W Main St",
    "iso:country":"US",
    "sg:address":"204 W Main St",
    "sg:city":"Bath",
    "sg:classifiers":[
        {
            "category":"Bars & Pubs",
            "type":"Food & Drink"
        }
    ],
    "sg:phone":"+1 610 837 3831",
    "sg:postcode":"18014",
    "sg:province":"PA",
    "wof:name":"WSM Inc",
    "wof:placetype":"venue"
},
  "geometry": {"coordinates":[-75.394327,40.725847],"type":"Point"}
}