{
  "type": "Feature",
  "properties": {
    "addr:full":"629 Maple Ave Aldan PA 19018",
    "addr:housenumber":"629",
    "addr:postcode":"19018",
    "addr:street":"Maple Ave",
    "iso:country":"US",
    "sg:address":"629 Maple Ave",
    "sg:city":"Aldan",
    "sg:classifiers":[
        {
            "category":"Banks & Credit Unions",
            "subcategory":"Bank",
            "type":"Services"
        }
    ],
    "sg:phone":"+1 610 622 8228",
    "sg:postcode":"19018",
    "sg:province":"PA",
    "sg:tags":[
        "loan",
        "mortgage",
        "real estate"
    ],
    "wof:name":"A Plus Mortgage Solutions",
    "wof:placetype":"venue"
},
  "geometry": {"coordinates":[-75.29545,39.917935],"type":"Point"}
}