{
  "type": "Feature",
  "properties": {
    "addr:full":"2829 N Lambert St Philadelphia PA 19132",
    "addr:housenumber":"2829",
    "addr:postcode":"19132",
    "addr:street":"N Lambert St",
    "iso:country":"US",
    "sg:address":"2829 N Lambert St",
    "sg:city":"Philadelphia",
    "sg:classifiers":[
        {
            "category":"Building & Trades",
            "subcategory":"Construction",
            "type":"Services"
        }
    ],
    "sg:phone":"+1 215 226 4000",
    "sg:postcode":"19132",
    "sg:province":"PA",
    "sg:tags":[
        "home",
        "builder"
    ],
    "wof:name":"Home Buyer Educational",
    "wof:placetype":"venue"
},
  "geometry": {"coordinates":[-75.16465100000001,39.997968],"type":"Point"}
}