{
  "type": "Feature",
  "properties": {
    "addr:full":"505 N 6th St Indiana PA 15701",
    "addr:housenumber":"505",
    "addr:postcode":"15701",
    "addr:street":"N 6Th St",
    "iso:country":"US",
    "sg:address":"505 N 6th St",
    "sg:city":"Indiana",
    "sg:classifiers":[
        {
            "category":"Professional",
            "subcategory":"Management & Consulting",
            "type":"Services"
        }
    ],
    "sg:phone":"+1 724 541 4439",
    "sg:postcode":"15701",
    "sg:province":"PA",
    "sg:tags":[
        "consultant",
        "safety"
    ],
    "wof:name":"Rhodes & Assoc Inc",
    "wof:placetype":"venue"
},
  "geometry": {"coordinates":[-79.151308,40.630385],"type":"Point"}
}