{
  "type": "Feature",
  "properties": {
    "iso:country":"US",
    "sg:address":"215 Messenger St",
    "sg:city":"Johnstown",
    "sg:classifiers":[
        {
            "category":"Retail",
            "subcategory":"Veterinary Services",
            "type":"Services"
        }
    ],
    "sg:phone":"+1 814 536 5105",
    "sg:postcode":"15902",
    "sg:province":"PA",
    "wof:name":"Johnstown Veterinary Assoc",
    "wof:placetype":"venue"
},
  "geometry": {"coordinates":[-78.91130200000001,40.309355],"type":"Point"}
}