{
  "type": "Feature",
  "properties": {
    "iso:country":"US",
    "sg:address":"10 N Railroad St",
    "sg:city":"Hanover",
    "sg:classifiers":[
        {
            "category":"Shopping",
            "type":"Retail Goods"
        }
    ],
    "sg:phone":"+1   ",
    "sg:postcode":"17331",
    "sg:province":"PA",
    "sg:tags":[
        "merchandise"
    ],
    "wof:name":"Frame Shop At Shirks",
    "wof:placetype":"venue"
},
  "geometry": {"coordinates":[-76.983086,39.801408],"type":"Point"}
}