{
  "type": "Feature",
  "properties": {
    "iso:country":"US",
    "sg:address":"1287 County Welfare Rd",
    "sg:city":"Leesport",
    "sg:phone":"+1 610 373 2883",
    "sg:postcode":"19533",
    "sg:province":"PA",
    "sg:tags":[
        "communications",
        "telegraph"
    ],
    "wof:name":"Inmate Telephone Inc",
    "wof:placetype":"venue"
},
  "geometry": {"coordinates":[-76.022662,40.380766],"type":"Point"}
}