{
  "type": "Feature",
  "properties": {
    "iso:country":"US",
    "sg:address":"10 E School House Ln",
    "sg:city":"Philadelphia",
    "sg:classifiers":[
        {
            "category":"Health Services",
            "subcategory":"Doctor",
            "type":"Services"
        }
    ],
    "sg:phone":"+1   ",
    "sg:postcode":"19144",
    "sg:province":"PA",
    "wof:name":"Moody Ernest W Jr DDS",
    "wof:placetype":"venue"
},
  "geometry": {"coordinates":[-75.171926,40.035069],"type":"Point"}
}