{
  "type": "Feature",
  "properties": {
    "iso:country":"US",
    "sg:address":"119 Meadow Dr",
    "sg:city":"Milford",
    "sg:classifiers":[
        {
            "category":"Professional",
            "subcategory":"Accounting & Tax Preparation",
            "type":"Services"
        }
    ],
    "sg:phone":"+1 570 296 8514",
    "sg:postcode":"18337",
    "sg:province":"PA",
    "sg:tags":[
        "accountant"
    ],
    "wof:name":"Berard & Donahue",
    "wof:placetype":"venue"
},
  "geometry": {"coordinates":[-74.778915,41.337794],"type":"Point"}
}