{
  "type": "Feature",
  "properties": {
    "addr:full":"3605 Germantown Ave Philadelphia PA 19140",
    "addr:housenumber":"3605",
    "addr:postcode":"19140",
    "addr:street":"Germantown Ave",
    "iso:country":"US",
    "sg:address":"3605 Germantown Ave",
    "sg:city":"Philadelphia",
    "sg:classifiers":[
        {
            "category":"Sports & Exercise",
            "subcategory":"Bicycle Rental",
            "type":"Entertainment"
        }
    ],
    "sg:phone":"+1 215 226 4222",
    "sg:postcode":"19140",
    "sg:province":"PA",
    "sg:tags":[
        "wear"
    ],
    "wof:name":"Extreme 1",
    "wof:placetype":"venue"
},
  "geometry": {"coordinates":[-75.150143,40.007667],"type":"Point"}
}