{
  "type": "Feature",
  "properties": {
    "iso:country":"US",
    "sg:address":"538 Lyman Ave",
    "sg:city":"Womelsdorf",
    "sg:classifiers":[
        {
            "category":"Personal",
            "type":"Services"
        }
    ],
    "sg:phone":"+1   ",
    "sg:postcode":"19567",
    "sg:province":"PA",
    "wof:name":"Vivian P Gerhart",
    "wof:placetype":"venue"
},
  "geometry": {"coordinates":[-76.19332799999999,40.367971],"type":"Point"}
}