{
  "type": "Feature",
  "properties": {
    "iso:country":"US",
    "sg:address":"3122 Kensington Ave",
    "sg:city":"Philadelphia",
    "sg:classifiers":[
        {
            "category":"Shopping",
            "subcategory":"Shoes",
            "type":"Retail Goods"
        }
    ],
    "sg:phone":"+1 215 634 1451",
    "sg:postcode":"19134",
    "sg:province":"PA",
    "wof:name":"Economy Shoe Shop Inc",
    "wof:placetype":"venue"
},
  "geometry": {"coordinates":[-75.11577699999999,39.995166],"type":"Point"}
}