{
  "type": "Feature",
  "properties": {
    "iso:country":"US",
    "sg:address":"4185 Washington Rd",
    "sg:city":"Canonsburg",
    "sg:classifiers":[
        {
            "category":"Shopping",
            "subcategory":"Pharmacy",
            "type":"Retail Goods"
        }
    ],
    "sg:phone":"+1 724 942 9111",
    "sg:postcode":"15317",
    "sg:province":"PA",
    "sg:tags":[
        "drugstore"
    ],
    "wof:name":"Rite Aid Pharmacies",
    "wof:placetype":"venue"
},
  "geometry": {"coordinates":[-80.13301300000001,40.262762],"type":"Point"}
}