{
  "type": "Feature",
  "properties": {
    "addr:full":"316 N Temple Blvd Temple PA 19560",
    "addr:housenumber":"316",
    "addr:postcode":"19560",
    "addr:street":"N Temple Blvd",
    "iso:country":"US",
    "sg:address":"316 N Temple Blvd",
    "sg:city":"Temple",
    "sg:classifiers":[
        {
            "category":"Wholesale",
            "subcategory":"Computers",
            "type":"Manufacturing & Wholesale Goods"
        }
    ],
    "sg:phone":"+1 610 929 9670",
    "sg:postcode":"19560",
    "sg:province":"PA",
    "sg:tags":[
        "equipment"
    ],
    "wof:name":"Software Professional Group In",
    "wof:placetype":"venue"
},
  "geometry": {"coordinates":[-75.92736600000001,40.39872],"type":"Point"}
}