{
  "type": "Feature",
  "properties": {
    "iso:country":"US",
    "sg:address":"10 N Third St",
    "sg:city":"Emmaus",
    "sg:classifiers":[
        {
            "category":"Sports & Exercise",
            "subcategory":"Playing Field",
            "type":"Entertainment"
        }
    ],
    "sg:postcode":"18099",
    "sg:province":"PA",
    "sg:tags":[
        "instruction",
        "fitness"
    ],
    "wof:name":"Round 1 Martial Arts & Boxing Academy",
    "wof:placetype":"venue"
},
  "geometry": {"coordinates":[-75.49063099999999,40.536087],"type":"Point"}
}