{
  "type": "Feature",
  "properties": {
    "iso:country":"US",
    "sg:address":"649 Cedar Dr",
    "sg:city":"Imperial",
    "sg:classifiers":[
        {
            "category":"Health Services",
            "subcategory":"Doctor",
            "type":"Services"
        }
    ],
    "sg:phone":"+1   ",
    "sg:postcode":"15126",
    "sg:province":"PA",
    "sg:tags":[
        "medical"
    ],
    "wof:name":"M Ujevich MD",
    "wof:placetype":"venue"
},
  "geometry": {"coordinates":[-80.24924799999999,40.461373],"type":"Point"}
}