{
  "type": "Feature",
  "properties": {
    "iso:country":"US",
    "sg:address":"135 Sherman Ave",
    "sg:city":"Vandergrift",
    "sg:classifiers":[
        {
            "category":"Building & Trades",
            "subcategory":"Landscaping Services",
            "type":"Services"
        }
    ],
    "sg:phone":"+1   ",
    "sg:postcode":"15690",
    "sg:province":"PA",
    "sg:tags":[
        "landscape"
    ],
    "wof:name":"JD Landscaping Service",
    "wof:placetype":"venue"
},
  "geometry": {"coordinates":[-79.562021,40.605422],"type":"Point"}
}