{
  "type": "Feature",
  "properties": {
    "addr:full":"303 Pennsylvania Ave E Warren PA 16365",
    "addr:housenumber":"303",
    "addr:postcode":"16365",
    "addr:street":"Pennsylvania Ave E",
    "iso:country":"US",
    "sg:address":"303 Pennsylvania Ave E",
    "sg:city":"Warren",
    "sg:classifiers":[
        {
            "category":"Cinema",
            "subcategory":"Movie Rental",
            "type":"Entertainment"
        }
    ],
    "sg:phone":"+1   ",
    "sg:postcode":"16365",
    "sg:province":"PA",
    "sg:tags":[
        "video",
        "tape"
    ],
    "wof:name":"T Js Video",
    "wof:placetype":"venue"
},
  "geometry": {"coordinates":[-79.137176,41.842577],"type":"Point"}
}