{
  "type": "Feature",
  "properties": {
    "iso:country":"US",
    "sg:address":"6645 N 16th St",
    "sg:city":"Philadelphia",
    "sg:classifiers":[
        {
            "category":"Food & Beverages",
            "subcategory":"Groceries & Convenience Stores",
            "type":"Retail Goods"
        }
    ],
    "sg:phone":"+1 215 424 2262",
    "sg:postcode":"19126",
    "sg:province":"PA",
    "wof:name":"Bamford Market",
    "wof:placetype":"venue"
},
  "geometry": {"coordinates":[-75.144649,40.054072],"type":"Point"}
}