{
  "type": "Feature",
  "properties": {
    "addr:full":"689 W Germantown Pike Norristown PA 19403",
    "addr:housenumber":"689",
    "addr:postcode":"19403",
    "addr:street":"W Germantown Pike",
    "iso:country":"US",
    "sg:address":"689 W Germantown Pike",
    "sg:city":"Norristown",
    "sg:classifiers":[
        {
            "category":"Restaurant",
            "type":"Food & Drink"
        }
    ],
    "sg:menulink":"http://www.allmenus.com/pa/east-norriton/206697-mcdonalds/menu/",
    "sg:phone":"+1 610 630 2220",
    "sg:postcode":"19403",
    "sg:province":"PA",
    "sg:tags":[
        "burger",
        "american"
    ],
    "wof:name":"McDonald's",
    "wof:placetype":"venue"
},
  "geometry": {"coordinates":[-75.348398,40.152196],"type":"Point"}
}