{
  "type": "Feature",
  "properties": {
    "iso:country":"US",
    "sg:address":"125 Lindley Ln",
    "sg:city":"Pittsburgh",
    "sg:classifiers":[
        {
            "category":"Retail",
            "subcategory":"Repair Shop",
            "type":"Services"
        }
    ],
    "sg:phone":"+1 412 367 3155",
    "sg:postcode":"15237",
    "sg:province":"PA",
    "sg:tags":[
        "repairing",
        "piano",
        "refinishing"
    ],
    "wof:name":"A-1 Piano Svc",
    "wof:placetype":"venue"
},
  "geometry": {"coordinates":[-80.04081100000001,40.539984],"type":"Point"}
}