{
  "type": "Feature",
  "properties": {
    "iso:country":"US",
    "sg:address":"720 River Rd",
    "sg:city":"Dauphin",
    "sg:classifiers":[
        {
            "category":"Building & Trades",
            "subcategory":"Construction",
            "type":"Services"
        }
    ],
    "sg:phone":"+1   ",
    "sg:postcode":"17018",
    "sg:province":"PA",
    "sg:tags":[
        "contractor"
    ],
    "wof:name":"American Home Service",
    "wof:placetype":"venue"
},
  "geometry": {"coordinates":[-76.940228,40.367235],"type":"Point"}
}