{
  "type": "Feature",
  "properties": {
    "addr:full":"2705 Willow St Coplay PA 18037",
    "addr:housenumber":"2705",
    "addr:postcode":"18037",
    "addr:street":"Willow St",
    "iso:country":"US",
    "sg:address":"2705 Willow St",
    "sg:city":"Coplay",
    "sg:classifiers":[
        {
            "category":"Real Estate",
            "subcategory":"Surveying",
            "type":"Services"
        }
    ],
    "sg:phone":"+1   ",
    "sg:postcode":"18037",
    "sg:province":"PA",
    "wof:name":"Prof Hoppes Engrg & Serveying",
    "wof:placetype":"venue"
},
  "geometry": {"coordinates":[-75.544302,40.655323],"type":"Point"}
}