{
  "type": "Feature",
  "properties": {
    "iso:country":"US",
    "sg:address":"236 Lake Rd",
    "sg:city":"Somerset",
    "sg:classifiers":[
        {
            "category":"Government",
            "subcategory":"Office",
            "type":"Public Place"
        }
    ],
    "sg:phone":"+1 814 445 8974",
    "sg:postcode":"15501",
    "sg:province":"PA",
    "wof:name":"Fish & Boat Commission",
    "wof:placetype":"venue"
},
  "geometry": {"coordinates":[-79.07016299999999,40.022201],"type":"Point"}
}