{
  "type": "Feature",
  "properties": {
    "iso:country":"US",
    "sg:address":"103 Bridge St",
    "sg:city":"Ridgway",
    "sg:classifiers":[
        {
            "category":"Manufacturing",
            "subcategory":"Electronics",
            "type":"Manufacturing & Wholesale Goods"
        }
    ],
    "sg:phone":"+1 814 834 2817",
    "sg:postcode":"15845",
    "sg:province":"PA",
    "sg:tags":[
        "equipment",
        "electronic",
        "supply"
    ],
    "wof:name":"CMFJLP",
    "wof:placetype":"venue"
},
  "geometry": {"coordinates":[-78.674927,41.488474],"type":"Point"}
}