{
  "type": "Feature",
  "properties": {
    "addr:full":"5072 Jonestown Rd Harrisburg PA 17112",
    "addr:housenumber":"5072",
    "addr:postcode":"17112",
    "addr:street":"Jonestown Rd",
    "iso:country":"US",
    "sg:address":"5072 Jonestown Rd",
    "sg:city":"Harrisburg",
    "sg:classifiers":[
        {
            "category":"Professional",
            "subcategory":"Accounting & Tax Preparation",
            "type":"Services"
        }
    ],
    "sg:phone":"+1   ",
    "sg:postcode":"17112",
    "sg:province":"PA",
    "sg:tags":[
        "return"
    ],
    "wof:name":"H & R Block",
    "wof:placetype":"venue"
},
  "geometry": {"coordinates":[-76.80157,40.311375],"type":"Point"}
}