{
  "type": "Feature",
  "properties": {
    "iso:country":"US",
    "sg:address":"5072 Jonestown Rd",
    "sg:city":"Harrisburg",
    "sg:classifiers":[
        {
            "category":"Professional",
            "subcategory":"Accounting & Tax Preparation",
            "type":"Services"
        }
    ],
    "sg:phone":"+1   ",
    "sg:postcode":"17112",
    "sg:province":"PA",
    "sg:tags":[
        "return"
    ],
    "wof:name":"H & R Block",
    "wof:placetype":"venue"
},
  "geometry": {"coordinates":[-76.80157,40.311375],"type":"Point"}
}